{
  "type": "Feature",
  "properties": {
    "iso:country":"NL",
    "sg:address":"Schoolstr 31",
    "sg:city":"Tegelen",
    "sg:orig_category":"Onderhoudswerken",
    "sg:phone":"+31 6 22472155",
    "sg:postcode":"5931 PA",
    "sg:province":"Limburg",
    "wof:name":"Gerritsen",
    "wof:placetype":"venue"
},
  "geometry": {"coordinates":[6.13718,51.341282],"type":"Point"}
}