{
  "type": "Feature",
  "properties": {
    "addr:full":"Dolderstraat 58 Wageningen Gelderland 6706 JG",
    "addr:housenumber":"58",
    "addr:postcode":"6706 jg",
    "addr:street":"Dolderstraat;Gelderland",
    "iso:country":"NL",
    "sg:address":"Dolderstraat 58",
    "sg:city":"Wageningen",
    "sg:classifiers":[
        {
            "category":"Education",
            "subcategory":"Preschool",
            "type":"Public Place"
        }
    ],
    "sg:phone":"+31 317 412 024",
    "sg:postcode":"6706 JG",
    "sg:province":"Gelderland",
    "sg:tags":[
        "kleuteronderwijs",
        "basis-"
    ],
    "wof:name":"Jenaplanschool Sint Jozef",
    "wof:placetype":"venue"
},
  "geometry": {"coordinates":[5.676902,51.976982],"type":"Point"}
}