{
  "type": "Feature",
  "properties": {
    "addr:full":"Hoofdstraat 4 S Gravenmoer Noord-Brabant 5109 AC",
    "addr:housenumber":"4",
    "addr:postcode":"5109 ac",
    "addr:street":"Hoofdstraat;S Gravenmoer",
    "iso:country":"NL",
    "sg:address":"Hoofdstraat 4",
    "sg:city":"S Gravenmoer",
    "sg:orig_category":"Overheidsdiensten",
    "sg:phone":"+31 162 318 861",
    "sg:postcode":"5109 AC",
    "sg:province":"Noord-Brabant",
    "wof:name":"De Geubel",
    "wof:placetype":"venue"
},
  "geometry": {"coordinates":[4.9404840469,51.6574554443],"type":"Point"}
}