{
  "type": "Feature",
  "properties": {
    "addr:full":"Wegterswg 38 Hengelo Overijssel 7556 BR",
    "addr:housenumber":"38",
    "addr:postcode":"7556 br",
    "addr:street":"Wegterswg",
    "iso:country":"NL",
    "sg:address":"Wegterswg 38",
    "sg:city":"Hengelo",
    "sg:orig_category":"Elektrotechnische Apparatuur - Fabrieken En Groothandel",
    "sg:phone":"+31 74 291 9441",
    "sg:postcode":"7556 BR",
    "sg:province":"Overijssel",
    "wof:name":"Solenoid Benelux Bv",
    "wof:placetype":"venue"
},
  "geometry": {"coordinates":[6.771743,52.281818],"type":"Point"}
}