{
  "type": "Feature",
  "properties": {
    "addr:full":"Rijpershoek 4 Reusel North Brabant 5541 VX",
    "addr:housenumber":"4",
    "addr:postcode":"5541 vx",
    "addr:street":"Rijpershoek",
    "iso:country":"NL",
    "sg:address":"Rijpershoek 4",
    "sg:city":"Reusel",
    "sg:orig_category":"Huishoudapparatuur, Televisies And Radio'S",
    "sg:phone":"+31 6 26168521",
    "sg:postcode":"5541 VX",
    "sg:province":"North Brabant",
    "wof:name":"Mi Amigo Electronics",
    "wof:placetype":"venue"
},
  "geometry": {"coordinates":[5.163661,51.366772],"type":"Point"}
}