{
  "type": "Feature",
  "properties": {
    "addr:full":"Spechtweg 8 Hengelo Ov NL.08 7557 PK",
    "addr:housenumber":"8",
    "addr:postcode":"7557 pk",
    "addr:street":"Spechtweg;Ov",
    "iso:country":"NL",
    "sg:address":"Spechtweg 8",
    "sg:city":"Hengelo Ov",
    "sg:orig_category":"Zalenexploitatie",
    "sg:phone":"+31 74 243 4823",
    "sg:postcode":"7557 PK",
    "sg:province":"NL.08",
    "wof:name":"Galerie Jan Wessels",
    "wof:placetype":"venue"
},
  "geometry": {"coordinates":[6.801337,52.267853],"type":"Point"}
}