{
  "type": "Feature",
  "properties": {
    "addr:full":"Hoofdwg 131 Westerh Vriezenv W Lower Austria 7676 AD",
    "addr:housenumber":"131",
    "addr:postcode":"7676 ad",
    "addr:street":"Westerh;W",
    "iso:country":"NL",
    "sg:address":"Hoofdwg 131",
    "sg:city":"Westerh Vriezenv W",
    "sg:orig_category":"Bloemen En Planten",
    "sg:phone":"+31 546 659 203",
    "sg:postcode":"7676 AD",
    "sg:province":"Lower Austria",
    "wof:name":"Lelie, De",
    "wof:placetype":"venue"
},
  "geometry": {"coordinates":[16.00322,47.58403],"type":"Point"}
}