{
  "type": "Feature",
  "properties": {
    "addr:full":"Vleesstr 15A Tiel Gelderland 4001 BB",
    "addr:housenumber":"15a",
    "addr:postcode":"4001 bb",
    "addr:street":"Vleesstr;Gelderland",
    "iso:country":"NL",
    "sg:address":"Vleesstr 15A",
    "sg:city":"Tiel",
    "sg:orig_category":"Pruiken",
    "sg:phone":"+31 344 613 104",
    "sg:postcode":"4001 BB",
    "sg:province":"Gelderland",
    "wof:name":"Sierdsema, J",
    "wof:placetype":"venue"
},
  "geometry": {"coordinates":[5.436422,51.887383],"type":"Point"}
}