{
  "type": "Feature",
  "properties": {
    "iso:country":"NL",
    "sg:address":"Kerklaan 28",
    "sg:city":"De Kwakel",
    "sg:orig_category":"Banken And Kredietinstellingen",
    "sg:phone":"+31 297 513 737",
    "sg:postcode":"1424 BK",
    "sg:province":"Noord-Holland",
    "wof:name":"Rabobank",
    "wof:placetype":"venue"
},
  "geometry": {"coordinates":[4.793271,52.238289],"type":"Point"}
}