{
  "type": "Feature",
  "properties": {
    "addr:full":"Brakenstr 4A Valkenswaard North Brabant 5555 CL",
    "addr:housenumber":"4a",
    "addr:postcode":"5555",
    "addr:street":"Brakenstr",
    "iso:country":"NL",
    "sg:address":"Brakenstr 4A",
    "sg:city":"Valkenswaard",
    "sg:orig_category":"Fietsen En Bromfietsen",
    "sg:phone":"+31 40 201 5006",
    "sg:postcode":"5555 CL",
    "sg:province":"North Brabant",
    "sg:website":"http://www.valkenswaard-plaza.nl",
    "wof:name":"Scooter Centr Valkenswaard",
    "wof:placetype":"venue"
},
  "geometry": {"coordinates":[5.465231,51.352482],"type":"Point"}
}