{
  "type": "Feature",
  "properties": {
    "addr:full":"Goudsesngl 80 Rotterdam Zuid-Holland 3011 KD",
    "addr:housenumber":"80",
    "addr:postcode":"3011 kd",
    "addr:street":"Goudsesngl",
    "iso:country":"NL",
    "sg:address":"Goudsesngl 80",
    "sg:city":"Rotterdam",
    "sg:orig_category":"Adviesbureaus Personeel",
    "sg:phone":"+31 10 280 0231",
    "sg:postcode":"3011 KD",
    "sg:province":"Zuid-Holland",
    "sg:website":"http://www.passievoorpersoneel.nl",
    "wof:name":"Passie Voor Personeel Bv",
    "wof:placetype":"venue"
},
  "geometry": {"coordinates":[4.49426,51.9221],"type":"Point"}
}