{
  "type": "Feature",
  "properties": {
    "addr:full":"Vermeerstraat 8 Nijmegen Gelderland 6521 LW",
    "addr:housenumber":"8",
    "addr:postcode":"6521 lw",
    "addr:street":"Vermeerstraat;Gelderland",
    "iso:country":"NL",
    "sg:address":"Vermeerstraat 8",
    "sg:city":"Nijmegen",
    "sg:orig_category":"Public Relationbureaus",
    "sg:phone":"+31 24 360 9507",
    "sg:postcode":"6521 LW",
    "sg:province":"Gelderland",
    "wof:name":"Advies En Communicatiebureau Spirit Plus",
    "wof:placetype":"venue"
},
  "geometry": {"coordinates":[5.877154,51.839085],"type":"Point"}
}