{
  "type": "Feature",
  "properties": {
    "addr:full":"Speenkruid 24 Doorn Utrecht 3941 TE",
    "addr:housenumber":"24",
    "addr:postcode":"3941 te",
    "addr:street":"Speenkruid",
    "iso:country":"NL",
    "sg:address":"Speenkruid 24",
    "sg:city":"Doorn",
    "sg:orig_category":"Adviesbureaus Bedrijfsorganisatie",
    "sg:phone":"+31 343 413 922",
    "sg:postcode":"3941 TE",
    "sg:province":"Utrecht",
    "wof:name":"Change Management Consulting Bv",
    "wof:placetype":"venue"
},
  "geometry": {"coordinates":[5.346785,52.026585],"type":"Point"}
}