{
  "type": "Feature",
  "properties": {
    "iso:country":"NL",
    "sg:address":"Speenkruid 24",
    "sg:city":"Doorn",
    "sg:orig_category":"Adviesbureaus Bedrijfsorganisatie",
    "sg:phone":"+31 343 413 922",
    "sg:postcode":"3941 TE",
    "sg:province":"Utrecht",
    "wof:name":"Change Management Consulting Bv",
    "wof:placetype":"venue"
},
  "geometry": {"coordinates":[5.346785,52.026585],"type":"Point"}
}