{
  "type": "Feature",
  "properties": {
    "addr:full":"Hekelstraat 11 'S Gravendeel Zuid-Holland 3295 TD",
    "addr:housenumber":"11",
    "addr:postcode":"3295 td",
    "addr:street":"Hekelstraat;' S",
    "iso:country":"NL",
    "sg:address":"Hekelstraat 11",
    "sg:city":"'S Gravendeel",
    "sg:orig_category":"Goederenvervoer Over De Weg",
    "sg:phone":"+31 78 673 4868",
    "sg:postcode":"3295 TD",
    "sg:province":"Zuid-Holland",
    "wof:name":"A Baars",
    "wof:placetype":"venue"
},
  "geometry": {"coordinates":[4.608148,51.774937],"type":"Point"}
}