{
  "type": "Feature",
  "properties": {
    "addr:full":"Industriestraat 42 Delft South Holland 2624 BB",
    "addr:housenumber":"42",
    "addr:postcode":"2624 bb",
    "addr:street":"Industriestraat",
    "iso:country":"NL",
    "sg:address":"Industriestraat 42",
    "sg:city":"Delft",
    "sg:orig_category":"Elektriciens",
    "sg:phone":"+31 15 285 5888",
    "sg:postcode":"2624 BB",
    "sg:province":"South Holland",
    "wof:name":"Bv Technisch Installatiebureau Reno",
    "wof:placetype":"venue"
},
  "geometry": {"coordinates":[4.356032,52.001225],"type":"Point"}
}