{
  "type": "Feature",
  "properties": {
    "iso:country":"NL",
    "sg:address":"Jol 3772",
    "sg:city":"Lelystad",
    "sg:classifiers":[
        {
            "category":"Education",
            "subcategory":"Preschool",
            "type":"Public Place"
        }
    ],
    "sg:phone":"+31 320 233 321",
    "sg:postcode":"8243 HS",
    "sg:province":"Flevoland",
    "sg:tags":[
        "kleuteronderwijs",
        "basis-"
    ],
    "wof:name":"Peuterspeelzaal Pinokkio",
    "wof:placetype":"venue"
},
  "geometry": {"coordinates":[5.448248,52.509331],"type":"Point"}
}