{
  "type": "Feature",
  "properties": {
    "addr:full":"Van Ewijcksvaart 24 Anna Paulowna Noord-Holland 1761 JS",
    "addr:housenumber":"24",
    "addr:postcode":"1761 js",
    "addr:street":"Van Ewijcksvaart",
    "iso:country":"NL",
    "sg:address":"Van Ewijcksvaart 24",
    "sg:city":"Anna Paulowna",
    "sg:orig_category":"Kampeerterreinen",
    "sg:phone":"+31 223 531 380",
    "sg:postcode":"1761 JS",
    "sg:province":"Noord-Holland",
    "wof:name":"Fa A. Vergouwe & Zn",
    "wof:placetype":"venue"
},
  "geometry": {"coordinates":[4.8508467674,52.8684501648],"type":"Point"}
}