{
  "type": "Feature",
  "properties": {
    "addr:full":"Zuidmede 9 Middelburg Zeeland 4337 AJ",
    "addr:housenumber":"9",
    "addr:postcode":"4337 aj",
    "addr:street":"Zuidmede",
    "iso:country":"NL",
    "sg:address":"Zuidmede 9",
    "sg:city":"Middelburg",
    "sg:orig_category":"Materiaalonderzoek",
    "sg:phone":"+31 118 613 849",
    "sg:postcode":"4337 AJ",
    "sg:province":"Zeeland",
    "wof:name":"Helmich, E M O",
    "wof:placetype":"venue"
},
  "geometry": {"coordinates":[3.625864,51.48568],"type":"Point"}
}