{
  "type": "Feature",
  "properties": {
    "addr:full":"Maywg 14 S Hertogenbosch Noord-Brabant 5211 AA",
    "addr:housenumber":"14",
    "addr:postcode":"5211 aa",
    "addr:street":"Maywg;S",
    "iso:country":"NL",
    "sg:address":"Maywg 14",
    "sg:city":"S Hertogenbosch",
    "sg:orig_category":"Advocaten En Advocatenkantoren",
    "sg:phone":"+31 73 613 9030",
    "sg:postcode":"5211 AA",
    "sg:province":"Noord-Brabant",
    "wof:name":"Vroom, De",
    "wof:placetype":"venue"
},
  "geometry": {"coordinates":[5.28401,51.680283],"type":"Point"}
}