{
  "type": "Feature",
  "properties": {
    "addr:full":"Stocreve 40 Goor Overijssel 7471 TM",
    "addr:housenumber":"40",
    "addr:postcode":"7471 tm",
    "addr:street":"Stocreve",
    "iso:country":"NL",
    "sg:address":"Stocreve 40",
    "sg:city":"Goor",
    "sg:orig_category":"Adviesbureaus Bedrijfsorganisatie",
    "sg:phone":"+31 547 260 600",
    "sg:postcode":"7471 TM",
    "sg:province":"Overijssel",
    "sg:website":"http://www.matrix-im.nl",
    "wof:name":"Matrix",
    "wof:placetype":"venue"
},
  "geometry": {"coordinates":[6.597405,52.242474],"type":"Point"}
}