{
  "type": "Feature",
  "properties": {
    "iso:country":"NL",
    "sg:address":"Pagelaan 4",
    "sg:city":"Eindhoven",
    "sg:orig_category":"Bloemen And Planten",
    "sg:phone":"+31 40 281 1853",
    "sg:postcode":"5641 CC",
    "sg:province":"Noord-Brabant",
    "wof:name":"Bloemenkas Gulberg Bv",
    "wof:placetype":"venue"
},
  "geometry": {"coordinates":[5.515194,51.450382],"type":"Point"}
}