{
  "type": "Feature",
  "properties": {
    "addr:full":"Pagelaan 4 Eindhoven Noord-Brabant 5641 CC",
    "addr:housenumber":"4",
    "addr:postcode":"5641 cc",
    "addr:street":"Pagelaan",
    "iso:country":"NL",
    "sg:address":"Pagelaan 4",
    "sg:city":"Eindhoven",
    "sg:orig_category":"Bloemen And Planten",
    "sg:phone":"+31 40 281 1853",
    "sg:postcode":"5641 CC",
    "sg:province":"Noord-Brabant",
    "wof:name":"Bloemenkas Gulberg Bv",
    "wof:placetype":"venue"
},
  "geometry": {"coordinates":[5.515194,51.450382],"type":"Point"}
}