{
  "type": "Feature",
  "properties": {
    "addr:full":"Otterlosewg 12 Wekerom Gelderland 6733 AM",
    "addr:housenumber":"12",
    "addr:postcode":"6733",
    "addr:street":"Otterlosewg;Gelderland",
    "iso:country":"NL",
    "sg:address":"Otterlosewg 12",
    "sg:city":"Wekerom",
    "sg:orig_category":"Fietsen En Bromfietsen",
    "sg:phone":"+31 318 463 132",
    "sg:postcode":"6733 AM",
    "sg:province":"Gelderland",
    "wof:name":"Zande Vof, H Van Der",
    "wof:placetype":"venue"
},
  "geometry": {"coordinates":[5.720724,52.112858],"type":"Point"}
}