{
  "type": "Feature",
  "properties": {
    "addr:full":"Venestr 4 S Gravenhage Zuid-Holland 2511 AS",
    "addr:housenumber":"4;gravenhage",
    "addr:postcode":"2511 as",
    "addr:street":"Venestr;S",
    "iso:country":"NL",
    "sg:address":"Venestr 4",
    "sg:city":"S Gravenhage",
    "sg:orig_category":"Warenhuizen",
    "sg:phone":"+31 70 364 2127",
    "sg:postcode":"2511 AS",
    "sg:province":"Zuid-Holland",
    "wof:name":"Xenos Bv",
    "wof:placetype":"venue"
},
  "geometry": {"coordinates":[4.3162698746,52.0789604187],"type":"Point"}
}