{
  "type": "Feature",
  "properties": {
    "iso:country":"NL",
    "sg:address":"Koningsakkers 45",
    "sg:city":"Siddeburen",
    "sg:orig_category":"Journalisten Freelance",
    "sg:phone":"+31 598 430 586",
    "sg:postcode":"9628 EG",
    "sg:province":"Groningen",
    "wof:name":"Bolland, H J",
    "wof:placetype":"venue"
},
  "geometry": {"coordinates":[6.872819,53.248051],"type":"Point"}
}