{
  "type": "Feature",
  "properties": {
    "addr:full":"Molendijk 38 Sliedrecht Zuid-Holland 3361 EN",
    "addr:housenumber":"38",
    "addr:postcode":"3361 en",
    "addr:street":"Molendijk",
    "iso:country":"NL",
    "sg:address":"Molendijk 38",
    "sg:city":"Sliedrecht",
    "sg:orig_category":"Schilderwerk",
    "sg:phone":"+31 6 22018420",
    "sg:postcode":"3361 EN",
    "sg:province":"Zuid-Holland",
    "wof:name":"Multi Color",
    "wof:placetype":"venue"
},
  "geometry": {"coordinates":[4.763607,51.824875],"type":"Point"}
}