{
  "type": "Feature",
  "properties": {
    "iso:country":"NL",
    "sg:address":"Frans Roesstraat 14",
    "sg:city":"Gaanderen",
    "sg:orig_category":"Makelaars In Onroerend Goed",
    "sg:phone":"+31 315 340 544",
    "sg:postcode":"7011 HB",
    "sg:province":"Gelderland",
    "wof:name":"Van Bijsterveld Bv",
    "wof:placetype":"venue"
},
  "geometry": {"coordinates":[6.348112,51.936661],"type":"Point"}
}