{
  "type": "Feature",
  "properties": {
    "addr:full":"Bisonspoor 1055 Maarssen Noord-Holland 3605 KG",
    "addr:housenumber":"1055",
    "addr:postcode":"3605 kg",
    "addr:street":"Bisonspoor",
    "iso:country":"NL",
    "sg:address":"Bisonspoor 1055",
    "sg:city":"Maarssen",
    "sg:orig_category":"Schoenen",
    "sg:phone":"+31 346 579 918",
    "sg:postcode":"3605 KG",
    "sg:province":"Noord-Holland",
    "wof:name":"Nelson Schoenen Bv",
    "wof:placetype":"venue"
},
  "geometry": {"coordinates":[5.030435,52.135517],"type":"Point"}
}