{
  "type": "Feature",
  "properties": {
    "addr:full":"Voorstr 146 Egmond Aan Zee Noord-Holland 1931 AP",
    "addr:housenumber":"146",
    "addr:postcode":"1931 ap",
    "iso:country":"NL",
    "sg:address":"Voorstr 146",
    "sg:city":"Egmond Aan Zee",
    "sg:orig_category":"Onderhoudswerken",
    "sg:phone":"+31 72 506 1926",
    "sg:postcode":"1931 AP",
    "sg:province":"Noord-Holland",
    "wof:name":"Leeuwenkamp",
    "wof:placetype":"venue"
},
  "geometry": {"coordinates":[4.6224808693,52.617855072],"type":"Point"}
}