{
  "type": "Feature",
  "properties": {
    "addr:full":"Hoofdstr 21 T Zandt Gn Groningen 9915 PA",
    "addr:housenumber":"21 t",
    "addr:postcode":"gn;9915",
    "addr:street":"Hoofdstr",
    "iso:country":"NL",
    "sg:address":"Hoofdstr 21",
    "sg:city":"T Zandt Gn",
    "sg:orig_category":"Banken",
    "sg:phone":"+31 595 437 935",
    "sg:postcode":"9915 PA",
    "sg:province":"Groningen",
    "wof:name":"Rabobank",
    "wof:placetype":"venue"
},
  "geometry": {"coordinates":[6.775411,53.363605],"type":"Point"}
}