{
  "type": "Feature",
  "properties": {
    "iso:country":"NL",
    "sg:address":"Dennestr 2",
    "sg:city":"Heerlen",
    "sg:orig_category":"Verenigingsgebouwen",
    "sg:phone":"+31 45 522 9203",
    "sg:postcode":"6413 PV",
    "sg:province":"Limburg",
    "wof:name":"Volkshuis, 'T",
    "wof:placetype":"venue"
},
  "geometry": {"coordinates":[5.943024,50.926441],"type":"Point"}
}