{
  "type": "Feature",
  "properties": {
    "addr:full":"Dennestr 2 Heerlen Limburg 6413 PV",
    "addr:housenumber":"2",
    "addr:postcode":"6413 pv",
    "addr:street":"Dennestr",
    "iso:country":"NL",
    "sg:address":"Dennestr 2",
    "sg:city":"Heerlen",
    "sg:orig_category":"Verenigingsgebouwen",
    "sg:phone":"+31 45 522 9203",
    "sg:postcode":"6413 PV",
    "sg:province":"Limburg",
    "wof:name":"Volkshuis, 'T",
    "wof:placetype":"venue"
},
  "geometry": {"coordinates":[5.943024,50.926441],"type":"Point"}
}