{
  "type": "Feature",
  "properties": {
    "iso:country":"NL",
    "sg:address":"Burg Hellenberg Hubarln 20",
    "sg:city":"Hilversum",
    "sg:orig_category":"Film-, Tv- And Videoproductie",
    "sg:phone":"+31 6 53169800",
    "sg:postcode":"1217 LL",
    "sg:province":"Noord-Holland",
    "wof:name":"De Wakkere Knapen",
    "wof:placetype":"venue"
},
  "geometry": {"coordinates":[5.17355,52.228985],"type":"Point"}
}