{
  "type": "Feature",
  "properties": {
    "addr:full":"Burg Vd Mortelpln 60 Tilburg Noord-Brabant 5037 PK",
    "addr:housenumber":"60",
    "addr:postcode":"5037 pk",
    "addr:street":"Burg",
    "iso:country":"NL",
    "sg:address":"Burg Vd Mortelpln 60",
    "sg:city":"Tilburg",
    "sg:classifiers":[
        {
            "category":"Food & Beverages",
            "subcategory":"Fruits & Vegetables",
            "type":"Retail Goods"
        }
    ],
    "sg:phone":"+31 13 468 2144",
    "sg:postcode":"5037 PK",
    "sg:province":"Noord-Brabant",
    "sg:tags":[
        "groenten"
    ],
    "wof:name":"Van Der Linden Vof",
    "wof:placetype":"venue"
},
  "geometry": {"coordinates":[5.05618,51.551212],"type":"Point"}
}