{
  "type": "Feature",
  "properties": {
    "addr:full":"Prinsengr 2 Sneek Provincie Friesland 8607 AD",
    "addr:housenumber":"2",
    "addr:postcode":"8607 ad",
    "addr:street":"Prinsengr;Provincie Friesland",
    "iso:country":"NL",
    "sg:address":"Prinsengr 2",
    "sg:city":"Sneek",
    "sg:orig_category":"Kunststoffen - Fabrieken En Groothandel",
    "sg:phone":"+31 515 423 881",
    "sg:postcode":"8607 AD",
    "sg:province":"Provincie Friesland",
    "wof:name":"Mitsui Petrochemicals Netherlands Bv",
    "wof:placetype":"venue"
},
  "geometry": {"coordinates":[5.659979,53.028027],"type":"Point"}
}