{
  "type": "Feature",
  "properties": {
    "iso:country":"NL",
    "sg:address":"Prinsengr 2",
    "sg:city":"Sneek",
    "sg:orig_category":"Kunststoffen - Fabrieken En Groothandel",
    "sg:phone":"+31 515 423 881",
    "sg:postcode":"8607 AD",
    "sg:province":"Provincie Friesland",
    "wof:name":"Mitsui Petrochemicals Netherlands Bv",
    "wof:placetype":"venue"
},
  "geometry": {"coordinates":[5.659979,53.028027],"type":"Point"}
}