{
  "type": "Feature",
  "properties": {
    "addr:full":"Winkelcentrum 4 Etten-Leur Noord-Brabant 4873 AA",
    "addr:housenumber":"4",
    "addr:postcode":"4873 aa",
    "addr:street":"Winkelcentrum",
    "iso:country":"NL",
    "sg:address":"Winkelcentrum 4",
    "sg:city":"Etten-Leur",
    "sg:orig_category":"Verlichting And Huishoudartikelen",
    "sg:phone":"+31 76 504 0527",
    "sg:postcode":"4873 AA",
    "sg:province":"Noord-Brabant",
    "wof:name":"Giraffe Bv",
    "wof:placetype":"venue"
},
  "geometry": {"coordinates":[4.635478,51.568321],"type":"Point"}
}