{
  "type": "Feature",
  "properties": {
    "addr:full":"Visserslaan 55 Arnhem Gelderland 6833 EL",
    "addr:housenumber":"55",
    "addr:postcode":"6833 el",
    "addr:street":"Visserslaan",
    "iso:country":"NL",
    "sg:address":"Visserslaan 55",
    "sg:city":"Arnhem",
    "sg:orig_category":"Verzekeringen",
    "sg:phone":"+31 26 321 2375",
    "sg:postcode":"6833 EL",
    "sg:province":"Gelderland",
    "wof:name":"Assurantiebedrijf N. Koolwijk",
    "wof:placetype":"venue"
},
  "geometry": {"coordinates":[5.916996,51.966434],"type":"Point"}
}