{
  "type": "Feature",
  "properties": {
    "addr:full":"Romeinstr 41 Enkhuizen Noord-Holland 1601 AZ",
    "addr:housenumber":"41",
    "addr:postcode":"1601 az",
    "addr:street":"Romeinstr",
    "iso:country":"NL",
    "sg:address":"Romeinstr 41",
    "sg:city":"Enkhuizen",
    "sg:orig_category":"Kappers",
    "sg:phone":"+31 228 318 587",
    "sg:postcode":"1601 AZ",
    "sg:province":"Noord-Holland",
    "wof:name":"Jutha",
    "wof:placetype":"venue"
},
  "geometry": {"coordinates":[5.2799429893,52.7028770447],"type":"Point"}
}