{
  "type": "Feature",
  "properties": {
    "addr:full":"Dantelaan 103 Utrecht Utrecht 3533 VC",
    "addr:housenumber":"103",
    "addr:postcode":"3533 vc",
    "addr:street":"Dantelaan",
    "iso:country":"NL",
    "sg:address":"Dantelaan 103",
    "sg:city":"Utrecht",
    "sg:orig_category":"Verzekeringen",
    "sg:phone":"+31 30 293 1012",
    "sg:postcode":"3533 VC",
    "sg:province":"Utrecht",
    "wof:name":"Expertiseknt Voor Uitvaartond. Hoogstaet",
    "wof:placetype":"venue"
},
  "geometry": {"coordinates":[5.083749,52.088253],"type":"Point"}
}