{
  "type": "Feature",
  "properties": {
    "addr:full":"Dr Ramaerln 102 Sam-Sam Den Dolder Utrecht 3734 EB",
    "addr:housenumber":"102",
    "addr:postcode":"3734 eb",
    "addr:street":"Sam-Sam Den",
    "iso:country":"NL",
    "sg:address":"Dr Ramaerln 102 Sam-Sam",
    "sg:city":"Den Dolder",
    "sg:orig_category":"Kinderopvang",
    "sg:phone":"+31 30 225 0776",
    "sg:postcode":"3734 EB",
    "sg:province":"Utrecht",
    "wof:name":"Kinderopvang Zeist, Sticht",
    "wof:placetype":"venue"
},
  "geometry": {"coordinates":[5.241445,52.139938],"type":"Point"}
}