{
  "type": "Feature",
  "properties": {
    "iso:country":"NL",
    "sg:address":"Bedrijvenweg 22",
    "sg:city":"Sint Michielsgestel",
    "sg:orig_category":"Loodgieterswerk, Verwarming And Sanitaire Installaties",
    "sg:phone":"+31 73 551 5371",
    "sg:postcode":"5272 PB",
    "sg:province":"Noord-Brabant",
    "wof:name":"Van Hout Installatietechniek Bv",
    "wof:placetype":"venue"
},
  "geometry": {"coordinates":[5.363253,51.647972],"type":"Point"}
}