{
  "type": "Feature",
  "properties": {
    "addr:full":"Langestraat 266 Klazienaveen Drenthe 7891 GR",
    "addr:housenumber":"266",
    "addr:postcode":"7891",
    "addr:street":"Langestraat",
    "iso:country":"NL",
    "sg:address":"Langestraat 266",
    "sg:city":"Klazienaveen",
    "sg:orig_category":"Verlichting And Huishoudartikelen",
    "sg:phone":"+31 591 314 404",
    "sg:postcode":"7891 GR",
    "sg:province":"Drenthe",
    "wof:name":"Gordijnencentrum Wendy",
    "wof:placetype":"venue"
},
  "geometry": {"coordinates":[6.999542,52.724361],"type":"Point"}
}