{
  "type": "Feature",
  "properties": {
    "addr:full":"Ln V Meerdervoort 311 S Gravenhage Zuid-Holland 2563 AN",
    "addr:housenumber":"311;gravenhage",
    "addr:postcode":"2563 an",
    "addr:street":"Ln;Meerdervoort;S",
    "iso:country":"NL",
    "sg:address":"Ln V Meerdervoort 311",
    "sg:city":"S Gravenhage",
    "sg:orig_category":"Hoortoestellen",
    "sg:phone":"+31 70 363 0879",
    "sg:postcode":"2563 AN",
    "sg:province":"Zuid-Holland",
    "sg:website":"http://www.schoonenberg.nl",
    "wof:name":"Schoonenberg Hoorcomfort",
    "wof:placetype":"venue"
},
  "geometry": {"coordinates":[4.270956,52.072578],"type":"Point"}
}