{
  "type": "Feature",
  "properties": {
    "addr:full":"A Luthulistr 4 Heerlen Limburg 6418 PN",
    "addr:housenumber":"4",
    "addr:postcode":"6418 pn",
    "iso:country":"NL",
    "sg:address":"A Luthulistr 4",
    "sg:city":"Heerlen",
    "sg:orig_category":"Administratie- En Boekhoudkantoren",
    "sg:phone":"+31 45 566 0088",
    "sg:postcode":"6418 PN",
    "sg:province":"Limburg",
    "wof:name":"Oostwegel",
    "wof:placetype":"venue"
},
  "geometry": {"coordinates":[5.994032,50.868717],"type":"Point"}
}