{
  "type": "Feature",
  "properties": {
    "addr:full":"Grotestraat 281 Waalwijk Noord-Brabant 5141 JT",
    "addr:housenumber":"281",
    "addr:postcode":"5141 jt",
    "addr:street":"Grotestraat",
    "iso:country":"NL",
    "sg:address":"Grotestraat 281",
    "sg:city":"Waalwijk",
    "sg:classifiers":[
        {
            "category":"Shopping",
            "subcategory":"Gifts & Souvenirs",
            "type":"Retail Goods"
        }
    ],
    "sg:phone":"+31 416 330 221",
    "sg:postcode":"5141 JT",
    "sg:province":"Noord-Brabant",
    "sg:tags":[
        "geschenken"
    ],
    "wof:name":"Kadoshop Ceciel",
    "wof:placetype":"venue"
},
  "geometry": {"coordinates":[5.068124,51.690758],"type":"Point"}
}