{
  "type": "Feature",
  "properties": {
    "addr:full":"Weteringsngl 4 Krimpen Ad Yssel Zuid-Holland 2921 BB",
    "addr:housenumber":"4",
    "addr:postcode":"2921 bb",
    "addr:street":"Weteringsngl",
    "iso:country":"NL",
    "sg:address":"Weteringsngl 4",
    "sg:city":"Krimpen Ad Yssel",
    "sg:orig_category":"Cafetaria'S",
    "sg:phone":"+31 180 513 466",
    "sg:postcode":"2921 BB",
    "sg:province":"Zuid-Holland",
    "wof:name":"Graafland, A",
    "wof:placetype":"venue"
},
  "geometry": {"coordinates":[4.5731,51.909908],"type":"Point"}
}