{
  "type": "Feature",
  "properties": {
    "iso:country":"NL",
    "sg:address":"Bedryvenpk Twente 1",
    "sg:city":"Almelo",
    "sg:orig_category":"Elektronica - Ontwikkeling En Groothandel",
    "sg:phone":"+31 546 576 465",
    "sg:postcode":"7602 KA",
    "sg:province":"NL.08",
    "wof:name":"Semecs",
    "wof:placetype":"venue"
},
  "geometry": {"coordinates":[6.609531,52.382824],"type":"Point"}
}