{
  "type": "Feature",
  "properties": {
    "iso:country":"NL",
    "sg:address":"Hofdyck 66",
    "sg:city":"Oegstgeest",
    "sg:orig_category":"Vertaalbureaus",
    "sg:phone":"+31 71 572 6464",
    "sg:postcode":"2341 NE",
    "sg:province":"Zuid-Holland",
    "wof:name":"Gibbs, A C",
    "wof:placetype":"venue"
},
  "geometry": {"coordinates":[4.477153,52.182087],"type":"Point"}
}