{
  "type": "Feature",
  "properties": {
    "addr:full":"Dorpsdijk 108 Rhoon South Holland 3161 CD",
    "addr:housenumber":"108",
    "addr:postcode":"3161 cd",
    "addr:street":"Dorpsdijk",
    "iso:country":"NL",
    "sg:address":"Dorpsdijk 108",
    "sg:city":"Rhoon",
    "sg:orig_category":"Verlichting And Huishoudartikelen",
    "sg:phone":"+31 10 501 5731",
    "sg:postcode":"3161 CD",
    "sg:province":"South Holland",
    "wof:name":"Familux",
    "wof:placetype":"venue"
},
  "geometry": {"coordinates":[4.419432,51.856388],"type":"Point"}
}