{
  "type": "Feature",
  "properties": {
    "addr:full":"Rembrandtln 14 Voorhout South Holland 2215 CK",
    "addr:housenumber":"14",
    "addr:postcode":"2215 ck",
    "addr:street":"Rembrandtln",
    "iso:country":"NL",
    "sg:address":"Rembrandtln 14",
    "sg:city":"Voorhout",
    "sg:orig_category":"Scholen Voor Basisonderwijs",
    "sg:phone":"+31 252 224 427",
    "sg:postcode":"2215 CK",
    "sg:province":"South Holland",
    "wof:name":"Andreas Rk",
    "wof:placetype":"venue"
},
  "geometry": {"coordinates":[4.478922,52.22332],"type":"Point"}
}