{
  "type": "Feature",
  "properties": {
    "iso:country":"NL",
    "sg:address":"Hoofdstr 4",
    "sg:city":"Hoogezand",
    "sg:orig_category":"Verenigingen En Stichtingen",
    "sg:phone":"+31 598 394 892",
    "sg:postcode":"9601 EH",
    "sg:province":"Groningen",
    "wof:name":"Bijz Begraafpl, Sticht",
    "wof:placetype":"venue"
},
  "geometry": {"coordinates":[6.756412,53.163502],"type":"Point"}
}