{
  "type": "Feature",
  "properties": {
    "iso:country":"NL",
    "sg:address":"Nijverheidsweg-Noord 73",
    "sg:city":"Amersfoort",
    "sg:classifiers":[
        {
            "category":"Retail",
            "subcategory":"Storage",
            "type":"Services"
        }
    ],
    "sg:phone":"+31 33 422 1050",
    "sg:postcode":"3812 PK",
    "sg:province":"Utrecht",
    "sg:tags":[
        "opslag",
        "bewaring"
    ],
    "wof:name":"Centropa Logistics Bv",
    "wof:placetype":"venue"
},
  "geometry": {"coordinates":[5.3782920837,52.1593017578],"type":"Point"}
}