{
  "type": "Feature",
  "properties": {
    "addr:full":"Prinses Christinalaan 118 Uithoorn Noord-Holland 1421 BN",
    "addr:housenumber":"118",
    "addr:postcode":"1421 bn",
    "addr:street":"Prinses Christinalaan",
    "iso:country":"NL",
    "sg:address":"Prinses Christinalaan 118",
    "sg:city":"Uithoorn",
    "sg:orig_category":"Fotostudio'S And Fotografen",
    "sg:phone":"+31 297 561 532",
    "sg:postcode":"1421 BN",
    "sg:province":"Noord-Holland",
    "wof:name":"G. De Vries",
    "wof:placetype":"venue"
},
  "geometry": {"coordinates":[4.823913,52.238098],"type":"Point"}
}