{
  "type": "Feature",
  "properties": {
    "iso:country":"NL",
    "sg:address":"Heezerwg 286",
    "sg:city":"Eindhoven",
    "sg:orig_category":"Dumpgoederen",
    "sg:phone":"+31 40 211 8206",
    "sg:postcode":"5643 KL",
    "sg:province":"Noord-Brabant",
    "wof:name":"Foerier, De",
    "wof:placetype":"venue"
},
  "geometry": {"coordinates":[5.498526,51.423496],"type":"Point"}
}