{
  "type": "Feature",
  "properties": {
    "addr:full":"Westerstraat 24 Rotterdam Zuid-Holland 3016 DH",
    "addr:housenumber":"24",
    "addr:postcode":"3016 dh",
    "addr:street":"Westerstraat",
    "iso:country":"NL",
    "sg:address":"Westerstraat 24",
    "sg:city":"Rotterdam",
    "sg:orig_category":"Drukkerijen And Copyshops",
    "sg:phone":"+31 10 414 0496",
    "sg:postcode":"3016 DH",
    "sg:province":"Zuid-Holland",
    "wof:name":"Vof Drukkerij Van Hooff De Waard",
    "wof:placetype":"venue"
},
  "geometry": {"coordinates":[4.481255,51.908978],"type":"Point"}
}