{
  "type": "Feature",
  "properties": {
    "addr:full":"Kostverlorenstr 95 Zandvoort Noord-Holland 2042 PD",
    "addr:housenumber":"95",
    "addr:postcode":"2042 pd",
    "addr:street":"Kostverlorenstr",
    "iso:country":"NL",
    "sg:address":"Kostverlorenstr 95",
    "sg:city":"Zandvoort",
    "sg:orig_category":"Kinderhuizen",
    "sg:phone":"+31 23 571 2095",
    "sg:postcode":"2042 PD",
    "sg:province":"Noord-Holland",
    "wof:name":"Rkz",
    "wof:placetype":"venue"
},
  "geometry": {"coordinates":[4.541322,52.372711],"type":"Point"}
}