{
  "type": "Feature",
  "properties": {
    "addr:full":"Burg Stramanwg 107Ab Amsterdam Zuidoost North Holland 1101 AA",
    "addr:housenumber":"107ab",
    "addr:postcode":"1101 aa",
    "addr:street":"Burg Stramanwg",
    "iso:country":"NL",
    "sg:address":"Burg Stramanwg 107Ab",
    "sg:city":"Amsterdam Zuidoost",
    "sg:orig_category":"Product-Promotie",
    "sg:phone":"+31 20 312 1111",
    "sg:postcode":"1101 AA",
    "sg:province":"North Holland",
    "wof:name":"Action Team",
    "wof:placetype":"venue"
},
  "geometry": {"coordinates":[4.936948,52.31245],"type":"Point"}
}