{
  "type": "Feature",
  "properties": {
    "addr:full":"De Vier Akkers 23 Hoogland Utrecht 3828 SC",
    "addr:housenumber":"23",
    "addr:postcode":"3828",
    "addr:street":"De Vier Akkers",
    "iso:country":"NL",
    "sg:address":"De Vier Akkers 23",
    "sg:city":"Hoogland",
    "sg:orig_category":"Verzekeringen",
    "sg:phone":"+31 33 480 1478",
    "sg:postcode":"3828 SC",
    "sg:province":"Utrecht",
    "wof:name":"Dekker Assurantien",
    "wof:placetype":"venue"
},
  "geometry": {"coordinates":[5.374405,52.178391],"type":"Point"}
}