{
  "type": "Feature",
  "properties": {
    "addr:full":"Kanaalstraat 12 Heerde Gelderland 8181 HW",
    "addr:housenumber":"12",
    "addr:postcode":"8181 hw",
    "addr:street":"Kanaalstraat;Gelderland",
    "iso:country":"NL",
    "sg:address":"Kanaalstraat 12",
    "sg:city":"Heerde",
    "sg:orig_category":"Meubelreparatie And -Restauratie",
    "sg:phone":"+31 578 691 462",
    "sg:postcode":"8181 HW",
    "sg:province":"Gelderland",
    "wof:name":"Timmerbed.Meubelmak. 'T Doelbeek H.V.D.",
    "wof:placetype":"venue"
},
  "geometry": {"coordinates":[6.043521,52.38567],"type":"Point"}
}