{
  "type": "Feature",
  "properties": {
    "iso:country":"NL",
    "sg:address":"Graafdijk Oost 11",
    "sg:city":"Molenaarsgraaf",
    "sg:orig_category":"Notarissen",
    "sg:phone":"+31 184 641 600",
    "sg:postcode":"2973 XA",
    "sg:province":"Zuid-Holland",
    "wof:name":"Mr. Van Leussen & Mr. Van Den Broek Notarissen",
    "wof:placetype":"venue"
},
  "geometry": {"coordinates":[4.842021,51.881588],"type":"Point"}
}