{
  "type": "Feature",
  "properties": {
    "iso:country":"NL",
    "sg:address":"Havenwg 30",
    "sg:city":"Waalwyk",
    "sg:orig_category":"Keukenspeciaalzaken",
    "sg:phone":"+31 416 569 310",
    "sg:postcode":"5145 NJ",
    "sg:province":"Noord-Brabant",
    "wof:name":"Mandemakers",
    "wof:placetype":"venue"
},
  "geometry": {"coordinates":[5.041843,51.693581],"type":"Point"}
}