{
  "type": "Feature",
  "properties": {
    "addr:full":"Industriestraat 4 Spijkenisse South Holland 3201 VD",
    "addr:housenumber":"4",
    "addr:postcode":"3201 vd",
    "addr:street":"Industriestraat",
    "iso:country":"NL",
    "sg:address":"Industriestraat 4",
    "sg:city":"Spijkenisse",
    "sg:orig_category":"Autokeuringen",
    "sg:phone":"+31 181 618 183",
    "sg:postcode":"3201 VD",
    "sg:province":"South Holland",
    "wof:name":"Garage Wildenbos",
    "wof:placetype":"venue"
},
  "geometry": {"coordinates":[4.326975,51.845531],"type":"Point"}
}