{
  "type": "Feature",
  "properties": {
    "addr:full":"Oost Ravenwg 8 Epe Gelderland 8162 PJ",
    "addr:housenumber":"8",
    "addr:postcode":"8162 pj",
    "addr:street":"Ravenwg;Gelderland",
    "iso:country":"NL",
    "sg:address":"Oost Ravenwg 8",
    "sg:city":"Epe",
    "sg:classifiers":[
        {
            "category":"Travel",
            "subcategory":"Hotels & Motels",
            "type":"Entertainment"
        }
    ],
    "sg:phone":"+31 578 612 991",
    "sg:postcode":"8162 PJ",
    "sg:province":"Gelderland",
    "sg:website":"http://www.geo.nl/witteberken/",
    "wof:name":"Witte Berken, Hotel Rest De",
    "wof:placetype":"venue"
},
  "geometry": {"coordinates":[5.938077,52.345558],"type":"Point"}
}