{
  "type": "Feature",
  "properties": {
    "addr:full":"Lirewg 100 Nieuw Vennep Noord-Holland 2153 PH",
    "addr:housenumber":"100",
    "addr:postcode":"2153",
    "addr:street":"Nieuw Vennep",
    "iso:country":"NL",
    "sg:address":"Lirewg 100",
    "sg:city":"Nieuw Vennep",
    "sg:orig_category":"Kantoorbenodigdheden - Fabrieken En Groothandel",
    "sg:phone":"+31 252 629 050",
    "sg:postcode":"2153 PH",
    "sg:province":"Noord-Holland",
    "sg:website":"http://www.supply-center.nl",
    "wof:name":"Supply Center",
    "wof:placetype":"venue"
},
  "geometry": {"coordinates":[4.6308197975,52.2543792725],"type":"Point"}
}