{
  "type": "Feature",
  "properties": {
    "addr:full":"Hooftstr 116A Alphen Aan Den Ryn Zuid-Holland 2406 GM",
    "addr:housenumber":"116a",
    "addr:postcode":"2406 gm",
    "addr:street":"Aan Den Ryn",
    "iso:country":"NL",
    "sg:address":"Hooftstr 116A",
    "sg:city":"Alphen Aan Den Ryn",
    "sg:orig_category":"Schilders",
    "sg:phone":"+31 6 55101095",
    "sg:postcode":"2406 GM",
    "sg:province":"Zuid-Holland",
    "wof:name":"Verzaal & Broer",
    "wof:placetype":"venue"
},
  "geometry": {"coordinates":[4.663693,52.133392],"type":"Point"}
}