{
  "type": "Feature",
  "properties": {
    "addr:full":"Cattepoelseweg 250 Arnhem Gelderland 6815 CJ",
    "addr:housenumber":"250",
    "addr:postcode":"6815 cj",
    "addr:street":"Cattepoelseweg",
    "iso:country":"NL",
    "sg:address":"Cattepoelseweg 250",
    "sg:city":"Arnhem",
    "sg:orig_category":"Wapens And Munitie",
    "sg:phone":"+31 26 443 3752",
    "sg:postcode":"6815 CJ",
    "sg:province":"Gelderland",
    "wof:name":"Technisch Bureau H.A. Muller-Armamar",
    "wof:placetype":"venue"
},
  "geometry": {"coordinates":[5.9109659195,52.0035896301],"type":"Point"}
}