{
  "type": "Feature",
  "properties": {
    "addr:full":"Voorstraat 9 Klaaswaal Zuid-Holland 3286 AX",
    "addr:housenumber":"9",
    "addr:postcode":"3286 ax",
    "addr:street":"Voorstraat",
    "iso:country":"NL",
    "sg:address":"Voorstraat 9",
    "sg:city":"Klaaswaal",
    "sg:orig_category":"Verlichting And Huishoudartikelen",
    "sg:phone":"+31 186 579 909",
    "sg:postcode":"3286 AX",
    "sg:province":"Zuid-Holland",
    "wof:name":"D. Van Garderen En Zn",
    "wof:placetype":"venue"
},
  "geometry": {"coordinates":[4.44581,51.768478],"type":"Point"}
}