{
  "type": "Feature",
  "properties": {
    "addr:full":"Jacob Van Lennepkade 120 Amsterdam Noord-Holland 1053 MS",
    "addr:housenumber":"120",
    "addr:postcode":"1053 ms",
    "addr:street":"Jacob Van Lennepkade",
    "iso:country":"NL",
    "sg:address":"Jacob Van Lennepkade 120",
    "sg:city":"Amsterdam",
    "sg:orig_category":"Vertaal- And Tolkenbureaus",
    "sg:phone":"+31 20 683 7297",
    "sg:postcode":"1053 MS",
    "sg:province":"Noord-Holland",
    "wof:name":"Drs Winnie Franssen-Andersen",
    "wof:placetype":"venue"
},
  "geometry": {"coordinates":[4.869611,52.364841],"type":"Point"}
}