{
  "type": "Feature",
  "properties": {
    "addr:full":"Straatweg 50 Rotterdam Zuid-Holland 3051 BH",
    "addr:housenumber":"50",
    "addr:postcode":"3051 bh",
    "addr:street":"Straatweg",
    "iso:country":"NL",
    "sg:address":"Straatweg 50",
    "sg:city":"Rotterdam",
    "sg:orig_category":"Wasserettes And Stomerijen",
    "sg:phone":"+31 10 418 5089",
    "sg:postcode":"3051 BH",
    "sg:province":"Zuid-Holland",
    "wof:name":"W.H. Suyker Vof",
    "wof:placetype":"venue"
},
  "geometry": {"coordinates":[4.4827189445,51.944442749],"type":"Point"}
}