{
  "type": "Feature",
  "properties": {
    "addr:full":"Druivenstraat 55 Amsterdam Noord-Holland 1033 JS",
    "addr:housenumber":"55",
    "addr:postcode":"1033 js",
    "addr:street":"Druivenstraat",
    "iso:country":"NL",
    "sg:address":"Druivenstraat 55",
    "sg:city":"Amsterdam",
    "sg:orig_category":"Reisbureaus",
    "sg:phone":"+31 20 631 4753",
    "sg:postcode":"1033 JS",
    "sg:province":"Noord-Holland",
    "wof:name":"Otter Travel Service",
    "wof:placetype":"venue"
},
  "geometry": {"coordinates":[4.903051,52.411171],"type":"Point"}
}