{
  "type": "Feature",
  "properties": {
    "addr:full":"Hoogstr 4 Alkmaar North Holland 1811 KV",
    "addr:housenumber":"4",
    "addr:postcode":"1811 kv",
    "addr:street":"Hoogstr",
    "iso:country":"NL",
    "sg:address":"Hoogstr 4",
    "sg:city":"Alkmaar",
    "sg:orig_category":"Bloemen En Planten",
    "sg:phone":"+31 72 511 6022",
    "sg:postcode":"1811 KV",
    "sg:province":"North Holland",
    "wof:name":"Bloemgoed Alkmaar",
    "wof:placetype":"venue"
},
  "geometry": {"coordinates":[4.746258,52.634361],"type":"Point"}
}