{
  "type": "Feature",
  "properties": {
    "addr:full":"Olmenlaan 91 Bussum Noord-Holland 1404 DE",
    "addr:housenumber":"91",
    "addr:postcode":"1404 de",
    "addr:street":"Olmenlaan",
    "iso:country":"NL",
    "sg:address":"Olmenlaan 91",
    "sg:city":"Bussum",
    "sg:orig_category":"Artiesten",
    "sg:phone":"+31 35 693 8462",
    "sg:postcode":"1404 DE",
    "sg:province":"Noord-Holland",
    "wof:name":"N Van Sluis",
    "wof:placetype":"venue"
},
  "geometry": {"coordinates":[5.160595,52.276394],"type":"Point"}
}