{
  "type": "Feature",
  "properties": {
    "iso:country":"NL",
    "sg:address":"Oldenzaalsestraat 197",
    "sg:city":"Hengelo Ov",
    "sg:orig_category":"Kinderopvang Behalve Thuis",
    "sg:phone":"+31 74 243 5324",
    "sg:postcode":"7557 GK",
    "sg:province":"Overijssel",
    "wof:name":"De Zeven Bergen Kinderdagverblijf",
    "wof:placetype":"venue"
},
  "geometry": {"coordinates":[6.804661,52.270309],"type":"Point"}
}