{
  "type": "Feature",
  "properties": {
    "addr:full":"Z Rondwg 225 Waddinxveen Zuid-Holland 2742 HZ",
    "addr:housenumber":"225",
    "addr:postcode":"waddinxveen;2742 hz",
    "iso:country":"NL",
    "sg:address":"Z Rondwg 225",
    "sg:city":"Waddinxveen",
    "sg:orig_category":"Hulpverlening Sociaal",
    "sg:phone":"+31 182 641 600",
    "sg:postcode":"2742 HZ",
    "sg:province":"Zuid-Holland",
    "wof:name":"Azc Waddinxveen",
    "wof:placetype":"venue"
},
  "geometry": {"coordinates":[4.65507,52.044601],"type":"Point"}
}