{
  "type": "Feature",
  "properties": {
    "iso:country":"NL",
    "sg:address":"Mijnsherenweg 4",
    "sg:city":"Lambertschaag",
    "sg:orig_category":"Fotostudio'S And Fotografen",
    "sg:phone":"+31 229 582 504",
    "sg:postcode":"1658 CA",
    "sg:province":"Noord-Holland",
    "wof:name":"Fotostudio Jaap Woets",
    "wof:placetype":"venue"
},
  "geometry": {"coordinates":[5.027218,52.745289],"type":"Point"}
}