{
  "type": "Feature",
  "properties": {
    "iso:country":"NL",
    "sg:address":"Ln V Het Kinholt 645",
    "sg:city":"Emmen",
    "sg:orig_category":"Beeldende Kunstenaars",
    "sg:phone":"+31 591 627 007",
    "sg:postcode":"7823 GR",
    "sg:province":"Provincie Drenthe",
    "wof:name":"Kind, Willem",
    "wof:placetype":"venue"
},
  "geometry": {"coordinates":[6.94262,52.787819],"type":"Point"}
}