{
  "type": "Feature",
  "properties": {
    "addr:full":"Princedwarsstraat 1 Katwijk Zh Zuid-Holland 2225 GD",
    "addr:housenumber":"1",
    "addr:postcode":"2225 gd",
    "addr:street":"Princedwarsstraat",
    "iso:country":"NL",
    "sg:address":"Princedwarsstraat 1",
    "sg:city":"Katwijk Zh",
    "sg:orig_category":"Schoenen",
    "sg:phone":"+31 71 407 2148",
    "sg:postcode":"2225 GD",
    "sg:province":"Zuid-Holland",
    "wof:name":"Massa Schoen & Mode Bv",
    "wof:placetype":"venue"
},
  "geometry": {"coordinates":[4.394563,52.204002],"type":"Point"}
}