{
  "type": "Feature",
  "properties": {
    "addr:full":"Coolsingel 65 Rotterdam Zuid-Holland 3012 AC",
    "addr:housenumber":"65",
    "addr:postcode":"3012 ac",
    "addr:street":"Coolsingel",
    "iso:country":"NL",
    "sg:address":"Coolsingel 65",
    "sg:city":"Rotterdam",
    "sg:orig_category":"Verzekeringen",
    "sg:phone":"+31 10 282 8900",
    "sg:postcode":"3012 AC",
    "sg:province":"Zuid-Holland",
    "wof:name":"Fortis Bank",
    "wof:placetype":"venue"
},
  "geometry": {"coordinates":[4.478551,51.922455],"type":"Point"}
}