{
  "type": "Feature",
  "properties": {
    "addr:full":"Nw Tuinen 24 De Lier South Holland 2678 AJ",
    "addr:housenumber":"24",
    "addr:postcode":"2678 aj",
    "addr:street":"Tuinen",
    "iso:country":"NL",
    "sg:address":"Nw Tuinen 24",
    "sg:city":"De Lier",
    "sg:orig_category":"Kassenonderhoud",
    "sg:phone":"+31 174 514 691",
    "sg:postcode":"2678 AJ",
    "sg:province":"South Holland",
    "wof:name":"Gri",
    "wof:placetype":"venue"
},
  "geometry": {"coordinates":[4.233493,51.975552],"type":"Point"}
}