{
  "type": "Feature",
  "properties": {
    "iso:country":"NL",
    "sg:address":"Robijnstraat 6",
    "sg:city":"Breda",
    "sg:orig_category":"Film-, Tv- And Videoproductie",
    "sg:phone":"+31 76 530 9862",
    "sg:postcode":"4817 JG",
    "sg:province":"North Brabant",
    "wof:name":"M. Schellekens",
    "wof:placetype":"venue"
},
  "geometry": {"coordinates":[4.79815,51.590195],"type":"Point"}
}