{
  "type": "Feature",
  "properties": {
    "addr:full":"Schippersvaartweg 22 Noordwijkerhout Zuid-Holland 2211 TL",
    "addr:housenumber":"22",
    "addr:postcode":"2211 tl",
    "addr:street":"Schippersvaartweg",
    "iso:country":"NL",
    "sg:address":"Schippersvaartweg 22",
    "sg:city":"Noordwijkerhout",
    "sg:orig_category":"Bloemen And Planten Gh",
    "sg:phone":"+31 252 371 620",
    "sg:postcode":"2211 TL",
    "sg:province":"Zuid-Holland",
    "wof:name":"H.C.J. Granneman Bv",
    "wof:placetype":"venue"
},
  "geometry": {"coordinates":[4.505142,52.258671],"type":"Point"}
}