{
  "type": "Feature",
  "properties": {
    "addr:full":"Westhavendk 100 Steenbergen Nb Noord-Brabant 4651 VZ",
    "addr:housenumber":"100",
    "addr:postcode":"4651 vz",
    "iso:country":"NL",
    "sg:address":"Westhavendk 100",
    "sg:city":"Steenbergen Nb",
    "sg:orig_category":"Administratie- En Boekhoudkantoren",
    "sg:phone":"+31 167 561 916",
    "sg:postcode":"4651 VZ",
    "sg:province":"Noord-Brabant",
    "wof:name":"Blommers",
    "wof:placetype":"venue"
},
  "geometry": {"coordinates":[4.31044,51.591209],"type":"Point"}
}