{
  "type": "Feature",
  "properties": {
    "addr:full":"Sarphatistr 27 Amsterdam North Holland 1018 EV",
    "addr:housenumber":"27",
    "addr:postcode":"1018 ev",
    "addr:street":"Sarphatistr",
    "iso:country":"NL",
    "sg:address":"Sarphatistr 27",
    "sg:city":"Amsterdam",
    "sg:orig_category":"Psychologen",
    "sg:phone":"+31 20 625 0899",
    "sg:postcode":"1018 EV",
    "sg:province":"North Holland",
    "wof:name":"Jong, Drs P M De",
    "wof:placetype":"venue"
},
  "geometry": {"coordinates":[4.90526,52.360695],"type":"Point"}
}