{
  "type": "Feature",
  "properties": {
    "addr:full":"Markt 34 Geertruidenberg Noord-Brabant 4931 BT",
    "addr:housenumber":"34",
    "addr:postcode":"4931 bt",
    "addr:street":"Markt",
    "iso:country":"NL",
    "sg:address":"Markt 34",
    "sg:city":"Geertruidenberg",
    "sg:orig_category":"Scholen Voor Basisonderwijs",
    "sg:phone":"+31 162 510 262",
    "sg:postcode":"4931 BT",
    "sg:province":"Noord-Brabant",
    "wof:name":"Elisabeth, Sticht",
    "wof:placetype":"venue"
},
  "geometry": {"coordinates":[4.86043,51.700573],"type":"Point"}
}