{
  "type": "Feature",
  "properties": {
    "iso:country":"NL",
    "sg:address":"Kerkstraat 50",
    "sg:city":"Veendam",
    "sg:classifiers":[
        {
            "category":"Fast Food",
            "type":"Food & Drink"
        }
    ],
    "sg:phone":"+31 598 632 150",
    "sg:postcode":"9641 AT",
    "sg:province":"Groningen",
    "sg:tags":[
        "afhaal",
        "restaurant"
    ],
    "wof:name":"Pizzeria Ristorante Romantica",
    "wof:placetype":"venue"
},
  "geometry": {"coordinates":[6.876551,53.106075],"type":"Point"}
}