{
  "type": "Feature",
  "properties": {
    "iso:country":"NL",
    "sg:address":"Hertenrade 462",
    "sg:city":"'S Gravenhage",
    "sg:orig_category":"Wasserettes And Stomerijen",
    "sg:phone":"+31 70 367 3863",
    "sg:postcode":"2544 HT",
    "sg:province":"Zuid-Holland",
    "wof:name":"Stomerij Wasserij Betere Boek",
    "wof:placetype":"venue"
},
  "geometry": {"coordinates":[4.2632470131,52.046245575],"type":"Point"}
}