{
  "type": "Feature",
  "properties": {
    "addr:full":"Brugstr 53 Middenmeer Noord-Holland 1775 BD",
    "addr:housenumber":"53",
    "addr:postcode":"1775 bd",
    "addr:street":"Brugstr",
    "iso:country":"NL",
    "sg:address":"Brugstr 53",
    "sg:city":"Middenmeer",
    "sg:orig_category":"Makelaars En Adviseurs Onroerende Goederen",
    "sg:phone":"+31 227 501 111",
    "sg:postcode":"1775 BD",
    "sg:province":"Noord-Holland",
    "sg:website":"http://www.vsomakelaars.nl",
    "wof:name":"Vso",
    "wof:placetype":"venue"
},
  "geometry": {"coordinates":[4.996853,52.808773],"type":"Point"}
}