{
  "type": "Feature",
  "properties": {
    "addr:full":"Nieuwstraat 11 Middelharnis Zuid-Holland 3241 CL",
    "addr:housenumber":"11",
    "addr:postcode":"3241",
    "addr:street":"Nieuwstraat",
    "iso:country":"NL",
    "sg:address":"Nieuwstraat 11",
    "sg:city":"Middelharnis",
    "sg:classifiers":[
        {
            "category":"Fast Food",
            "type":"Food & Drink"
        }
    ],
    "sg:phone":"+31 187 486 900",
    "sg:postcode":"3241 CL",
    "sg:province":"Zuid-Holland",
    "sg:tags":[
        "afhaal",
        "restaurant"
    ],
    "wof:name":"Fook Lam",
    "wof:placetype":"venue"
},
  "geometry": {"coordinates":[4.164971,51.759598],"type":"Point"}
}