{
  "type": "Feature",
  "properties": {
    "addr:full":"Van Weerden Poelmansstraat 9 Heerlen Limburg 6417 EJ",
    "addr:housenumber":"9",
    "addr:postcode":"6417 ej",
    "addr:street":"Van Weerden Poelmansstraat",
    "iso:country":"NL",
    "sg:address":"Van Weerden Poelmansstraat 9",
    "sg:city":"Heerlen",
    "sg:orig_category":"Bedrijfsinventaris Gh",
    "sg:phone":"+31 45560011",
    "sg:postcode":"6417 EJ",
    "sg:province":"Limburg",
    "wof:name":"Kapsalon Gm",
    "wof:placetype":"venue"
},
  "geometry": {"coordinates":[5.982815,50.876225],"type":"Point"}
}