{
  "type": "Feature",
  "properties": {
    "addr:full":"Boompjes 425 Rotterdam Zuid-Holland 3011 XZ",
    "addr:housenumber":"425",
    "addr:postcode":"3011 xz",
    "addr:street":"Boompjes",
    "iso:country":"NL",
    "sg:address":"Boompjes 425",
    "sg:city":"Rotterdam",
    "sg:orig_category":"Afslankinstituten",
    "sg:phone":"+31 10 213 0341",
    "sg:postcode":"3011 XZ",
    "sg:province":"Zuid-Holland",
    "wof:name":"Herbajetics",
    "wof:placetype":"venue"
},
  "geometry": {"coordinates":[4.486135,51.913918],"type":"Point"}
}