{
  "type": "Feature",
  "properties": {
    "addr:full":"Bergerstraat 34 Maastricht Limburg 6226 BD",
    "addr:housenumber":"34",
    "addr:postcode":"6226 bd",
    "addr:street":"Bergerstraat",
    "iso:country":"NL",
    "sg:address":"Bergerstraat 34",
    "sg:city":"Maastricht",
    "sg:orig_category":"Diverse Grafische Activiteiten",
    "sg:phone":"+31 43 362 5889",
    "sg:postcode":"6226 BD",
    "sg:province":"Limburg",
    "wof:name":"Boekbinderij Lipsch",
    "wof:placetype":"venue"
},
  "geometry": {"coordinates":[5.727767,50.850712],"type":"Point"}
}