{
  "type": "Feature",
  "properties": {
    "addr:full":"Molenstr 5 Enschede Overijssel 7514 DJ",
    "addr:housenumber":"5",
    "addr:postcode":"7514 dj",
    "addr:street":"Molenstr",
    "iso:country":"NL",
    "sg:address":"Molenstr 5",
    "sg:city":"Enschede",
    "sg:orig_category":"Bloemen En Planten",
    "sg:phone":"+31 53 434 4141",
    "sg:postcode":"7514 DJ",
    "sg:province":"Overijssel",
    "wof:name":"Eeuwige Lente, De",
    "wof:placetype":"venue"
},
  "geometry": {"coordinates":[6.893612,52.223331],"type":"Point"}
}