{
  "type": "Feature",
  "properties": {
    "addr:full":"Ptr Pottgensstr 17 Kerkrade Limburg 6463 DN",
    "addr:housenumber":"17",
    "addr:postcode":"6463 dn",
    "iso:country":"NL",
    "sg:address":"Ptr Pottgensstr 17",
    "sg:city":"Kerkrade",
    "sg:orig_category":"Bedrijfsopleidingen",
    "sg:phone":"+31 45 535 4652",
    "sg:postcode":"6463 DN",
    "sg:province":"Limburg",
    "wof:name":"Medidact",
    "wof:placetype":"venue"
},
  "geometry": {"coordinates":[6.059685,50.863773],"type":"Point"}
}