{
  "type": "Feature",
  "properties": {
    "iso:country":"NL",
    "sg:address":"Herengr 100",
    "sg:city":"Amsterdam",
    "sg:orig_category":"Fietsen En Bromfietsen",
    "sg:phone":"+31 20 624 9198",
    "sg:postcode":"1015 BS",
    "sg:province":"Noord-Holland",
    "wof:name":"Staller Studio Nederland",
    "wof:placetype":"venue"
},
  "geometry": {"coordinates":[4.88881,52.376331],"type":"Point"}
}