{
  "type": "Feature",
  "properties": {
    "iso:country":"NL",
    "sg:address":"Bezuidenhoutseweg 195",
    "sg:city":"'S Gravenhage",
    "sg:orig_category":"Hypotheken And Hypotheekbanken",
    "sg:phone":"+31 70 347 7509",
    "sg:postcode":"2594 AJ",
    "sg:province":"Zuid-Holland",
    "wof:name":"Goldbach Assurantien",
    "wof:placetype":"venue"
},
  "geometry": {"coordinates":[4.334649,52.087543],"type":"Point"}
}