{
  "type": "Feature",
  "properties": {
    "addr:full":"Herenstr 5 Slagharen Overijssel 7776 AG",
    "addr:housenumber":"5",
    "addr:postcode":"7776",
    "addr:street":"Herenstr",
    "iso:country":"NL",
    "sg:address":"Herenstr 5",
    "sg:city":"Slagharen",
    "sg:orig_category":"Gordijnenateliers",
    "sg:phone":"+31 523 682 064",
    "sg:postcode":"7776 AG",
    "sg:province":"Overijssel",
    "wof:name":"Hudepohl",
    "wof:placetype":"venue"
},
  "geometry": {"coordinates":[6.5573368073,52.6256599426],"type":"Point"}
}