{
  "type": "Feature",
  "properties": {
    "addr:full":"De Mossel 15 Noord-Scharwoude Noord-Holland 1723 HZ",
    "addr:housenumber":"15",
    "addr:postcode":"1723 hz",
    "addr:street":"De Mossel",
    "iso:country":"NL",
    "sg:address":"De Mossel 15",
    "sg:city":"Noord-Scharwoude",
    "sg:orig_category":"Boekenuitgeverijen",
    "sg:phone":"+31 226 316 264",
    "sg:postcode":"1723 HZ",
    "sg:province":"Noord-Holland",
    "wof:name":"Elma Edities Bv",
    "wof:placetype":"venue"
},
  "geometry": {"coordinates":[4.804256,52.704224],"type":"Point"}
}