{
  "type": "Feature",
  "properties": {
    "iso:country":"NL",
    "sg:address":"Grietmansrecht 30",
    "sg:city":"Drachten",
    "sg:orig_category":"Verzekeringen",
    "sg:phone":"+31 512 512 506",
    "sg:postcode":"9201 TZ",
    "sg:province":"Friesland",
    "wof:name":"J Postma",
    "wof:placetype":"venue"
},
  "geometry": {"coordinates":[6.09858,53.113712],"type":"Point"}
}