{
  "type": "Feature",
  "properties": {
    "addr:full":"Grotestraat 16 Beers Nb Noord-Brabant 5437 AS",
    "addr:housenumber":"16",
    "addr:postcode":"5437 as",
    "addr:street":"Grotestraat",
    "iso:country":"NL",
    "sg:address":"Grotestraat 16",
    "sg:city":"Beers Nb",
    "sg:orig_category":"Bibliotheken And Openbare Archieven",
    "sg:phone":"+31 485 318 280",
    "sg:postcode":"5437 AS",
    "sg:province":"Noord-Brabant",
    "wof:name":"Openbare Bibliotheek",
    "wof:placetype":"venue"
},
  "geometry": {"coordinates":[5.827763,51.725075],"type":"Point"}
}