{
  "type": "Feature",
  "properties": {
    "addr:full":"Talingwg 72A Apeldoorn Gelderland 7331 GP",
    "addr:housenumber":"72a",
    "addr:postcode":"7331 gp",
    "addr:street":"Talingwg;Gelderland",
    "iso:country":"NL",
    "sg:address":"Talingwg 72A",
    "sg:city":"Apeldoorn",
    "sg:orig_category":"Warenhuizen",
    "sg:phone":"+31 55 540 1825",
    "sg:postcode":"7331 GP",
    "sg:province":"Gelderland",
    "wof:name":"Huma",
    "wof:placetype":"venue"
},
  "geometry": {"coordinates":[5.9663357735,52.2000350952],"type":"Point"}
}