{
  "type": "Feature",
  "properties": {
    "addr:full":"Grotestr 39 Tubbergen NL.08 7651 CG",
    "addr:housenumber":"39;nl.08",
    "addr:postcode":"7651 cg",
    "addr:street":"Grotestr",
    "iso:country":"NL",
    "sg:address":"Grotestr 39",
    "sg:city":"Tubbergen",
    "sg:classifiers":[
        {
            "category":"Food & Beverages",
            "subcategory":"Bakery",
            "type":"Retail Goods"
        }
    ],
    "sg:phone":"+31 546 621 421",
    "sg:postcode":"7651 CG",
    "sg:province":"NL.08",
    "sg:tags":[
        "brood",
        "en",
        "banket"
    ],
    "wof:name":"Jos",
    "wof:placetype":"venue"
},
  "geometry": {"coordinates":[6.781609,52.406445],"type":"Point"}
}