{
  "type": "Feature",
  "properties": {
    "addr:full":"Hoolwg 1 Maurik Gelderland 4021 CN",
    "addr:housenumber":"1",
    "addr:postcode":"4021 cn",
    "addr:street":"Hoolwg;Gelderland",
    "iso:country":"NL",
    "sg:address":"Hoolwg 1",
    "sg:city":"Maurik",
    "sg:classifiers":[
        {
            "category":"Sports & Exercise",
            "subcategory":"Stables",
            "type":"Entertainment"
        }
    ],
    "sg:phone":"+31 344 692 281",
    "sg:postcode":"4021 CN",
    "sg:province":"Gelderland",
    "sg:tags":[
        "maneges"
    ],
    "wof:name":"Elzenhof",
    "wof:placetype":"venue"
},
  "geometry": {"coordinates":[5.40416,51.9561],"type":"Point"}
}