{
  "type": "Feature",
  "properties": {
    "iso:country":"NL",
    "sg:address":"Grt Vaartln 24",
    "sg:city":"Veendam",
    "sg:orig_category":"Administratie- En Boekhoudkantoren",
    "sg:phone":"+31 598 613 266",
    "sg:postcode":"9642 PD",
    "sg:province":"Groningen",
    "wof:name":"Koning, H",
    "wof:placetype":"venue"
},
  "geometry": {"coordinates":[6.856532,53.10635],"type":"Point"}
}