{
  "type": "Feature",
  "properties": {
    "iso:country":"NL",
    "sg:address":"Lange Bisschopstraat 41",
    "sg:city":"Deventer",
    "sg:orig_category":"Boekenuitgeverijen",
    "sg:phone":"+31 570 612 025",
    "sg:postcode":"7411 KH",
    "sg:province":"NL.08",
    "wof:name":"Boekhandel Praamstra Bv",
    "wof:placetype":"venue"
},
  "geometry": {"coordinates":[6.15735,52.25351],"type":"Point"}
}