{
  "type": "Feature",
  "properties": {
    "addr:full":"Emmastr 30 Asten Noord-Brabant 5721 HB",
    "addr:housenumber":"30",
    "addr:postcode":"5721 hb",
    "addr:street":"Emmastr",
    "iso:country":"NL",
    "sg:address":"Emmastr 30",
    "sg:city":"Asten",
    "sg:orig_category":"Kappers",
    "sg:phone":"+31 493 692 215",
    "sg:postcode":"5721 HB",
    "sg:province":"Noord-Brabant",
    "wof:name":"Jama?",
    "wof:placetype":"venue"
},
  "geometry": {"coordinates":[5.7483420372,51.4031524658],"type":"Point"}
}