{
  "type": "Feature",
  "properties": {
    "iso:country":"NL",
    "sg:address":"Moleneind 7",
    "sg:city":"Kortenhoef",
    "sg:orig_category":"Pleziervaartuigen And Reparatie",
    "sg:phone":"+31 35 656 1394",
    "sg:postcode":"1241 NE",
    "sg:province":"Noord-Holland",
    "wof:name":"Jachtwerf Gebroeders De Kloet",
    "wof:placetype":"venue"
},
  "geometry": {"coordinates":[5.082203,52.224724],"type":"Point"}
}