{
  "type": "Feature",
  "properties": {
    "iso:country":"NL",
    "sg:address":"Postbus 78",
    "sg:city":"Koudekerk Ad Ryn",
    "sg:orig_category":"Verzekeringen - Verzekeringskantoren",
    "sg:phone":"+31 172 472 917",
    "sg:postcode":"2396 ZH",
    "sg:province":"Zuid-Holland",
    "wof:name":"Colijn",
    "wof:placetype":"venue"
},
  "geometry": {"coordinates":[4.603195,52.133533],"type":"Point"}
}