{
  "type": "Feature",
  "properties": {
    "iso:country":"NL",
    "sg:address":"Lavendelstraat 8",
    "sg:city":"Beuningen Gld",
    "sg:orig_category":"Gespecialiseerde Bouw",
    "sg:phone":"+31 24 677 0036",
    "sg:postcode":"6641 BX",
    "sg:province":"Gelderland",
    "wof:name":"Abb",
    "wof:placetype":"venue"
},
  "geometry": {"coordinates":[5.778762,51.860252],"type":"Point"}
}