{
  "type": "Feature",
  "properties": {
    "iso:country":"NL",
    "sg:address":"Bredenoord 32",
    "sg:city":"Rotterdam",
    "sg:orig_category":"Keramische Producten Fab",
    "sg:phone":"+31 10 483 5653",
    "sg:postcode":"3079 JE",
    "sg:province":"Zuid-Holland",
    "wof:name":"Pigeltje",
    "wof:placetype":"venue"
},
  "geometry": {"coordinates":[4.552452,51.881985],"type":"Point"}
}