{
  "type": "Feature",
  "properties": {
    "iso:country":"NL",
    "sg:address":"Stationswg 197",
    "sg:city":"Drachten",
    "sg:orig_category":"Wasmachines En Wasdrogers - Onderhoud En Reparatie",
    "sg:phone":"+31 512 522 154",
    "sg:postcode":"9201 GM",
    "sg:province":"Friesland",
    "wof:name":"Lindeboom",
    "wof:placetype":"venue"
},
  "geometry": {"coordinates":[6.0961198807,53.1167831421],"type":"Point"}
}