{
  "type": "Feature",
  "properties": {
    "addr:full":"Vogelenzangsewg 83 Vogelenzang North Holland 2114 CC",
    "addr:housenumber":"83",
    "addr:postcode":"2114 cc",
    "addr:street":"Vogelenzangsewg",
    "iso:country":"NL",
    "sg:address":"Vogelenzangsewg 83",
    "sg:city":"Vogelenzang",
    "sg:orig_category":"Horloges En Klokken",
    "sg:phone":"+31 23 584 8888",
    "sg:postcode":"2114 CC",
    "sg:province":"North Holland",
    "sg:website":"http://www.klokkenspeciaalzaak.nl",
    "wof:name":"Klaren Klokkenspeciaalzaak",
    "wof:placetype":"venue"
},
  "geometry": {"coordinates":[4.578044,52.323059],"type":"Point"}
}