{
  "type": "Feature",
  "properties": {
    "addr:full":"Weesperzijde 42 Amsterdam Noord-Holland 1091 EE",
    "addr:housenumber":"42",
    "addr:postcode":"1091 ee",
    "addr:street":"Weesperzijde",
    "iso:country":"NL",
    "sg:address":"Weesperzijde 42",
    "sg:city":"Amsterdam",
    "sg:classifiers":[
        {
            "category":"Fast Food",
            "type":"Food & Drink"
        }
    ],
    "sg:phone":"+31 20 693 3766",
    "sg:postcode":"1091 EE",
    "sg:province":"Noord-Holland",
    "sg:tags":[
        "afhaal",
        "restaurant"
    ],
    "wof:name":"Automatiek Jado",
    "wof:placetype":"venue"
},
  "geometry": {"coordinates":[4.907382,52.355804],"type":"Point"}
}