{
  "type": "Feature",
  "properties": {
    "iso:country":"NL",
    "sg:address":"Zuidwalwg 22",
    "sg:city":"Harlingen",
    "sg:orig_category":"Houtgroothandel",
    "sg:phone":"+31 517 413 741",
    "sg:postcode":"8861 NV",
    "sg:province":"Friesland",
    "wof:name":"Meinesz Bv",
    "wof:placetype":"venue"
},
  "geometry": {"coordinates":[5.425059,53.181915],"type":"Point"}
}