{
  "type": "Feature",
  "properties": {
    "addr:full":"Zuidwalwg 22 Harlingen Friesland 8861 NV",
    "addr:housenumber":"22",
    "addr:postcode":"8861 nv",
    "addr:street":"Zuidwalwg",
    "iso:country":"NL",
    "sg:address":"Zuidwalwg 22",
    "sg:city":"Harlingen",
    "sg:orig_category":"Houtgroothandel",
    "sg:phone":"+31 517 413 741",
    "sg:postcode":"8861 NV",
    "sg:province":"Friesland",
    "wof:name":"Meinesz Bv",
    "wof:placetype":"venue"
},
  "geometry": {"coordinates":[5.425059,53.181915],"type":"Point"}
}