{
  "type": "Feature",
  "properties": {
    "addr:full":"Gastelsewg 49 Roosendaal North Brabant 4702 SZ",
    "addr:housenumber":"49",
    "addr:postcode":"4702 sz",
    "addr:street":"Gastelsewg",
    "iso:country":"NL",
    "sg:address":"Gastelsewg 49",
    "sg:city":"Roosendaal",
    "sg:orig_category":"Meubelstoffering",
    "sg:phone":"+31 165 541 285",
    "sg:postcode":"4702 SZ",
    "sg:province":"North Brabant",
    "wof:name":"Loon, Van",
    "wof:placetype":"venue"
},
  "geometry": {"coordinates":[4.474056,51.543816],"type":"Point"}
}