{
  "type": "Feature",
  "properties": {
    "iso:country":"NL",
    "sg:address":"Lijsterbesstraat 10",
    "sg:city":"Den Helder",
    "sg:orig_category":"Overheidsdiensten",
    "sg:phone":"+31 223 624 454",
    "sg:postcode":"1783 HT",
    "sg:province":"Noord-Holland",
    "wof:name":"West-End",
    "wof:placetype":"venue"
},
  "geometry": {"coordinates":[4.7341032028,52.9417266846],"type":"Point"}
}