{
  "type": "Feature",
  "properties": {
    "addr:full":"Nucleonenweg 5 Utrecht Utrecht 3542 CD",
    "addr:housenumber":"5",
    "addr:postcode":"3542 cd",
    "addr:street":"Nucleonenweg",
    "iso:country":"NL",
    "sg:address":"Nucleonenweg 5",
    "sg:city":"Utrecht",
    "sg:classifiers":[
        {
            "category":"Retail",
            "subcategory":"Storage",
            "type":"Services"
        }
    ],
    "sg:phone":"+31 30 241 0211",
    "sg:postcode":"3542 CD",
    "sg:province":"Utrecht",
    "sg:tags":[
        "opslag",
        "bewaring"
    ],
    "sg:website":"http://www.devonselfstorage.com",
    "wof:name":"Devon Storage Utrecht",
    "wof:placetype":"venue"
},
  "geometry": {"coordinates":[5.0607790947,52.1077575684],"type":"Point"}
}