{
  "type": "Feature",
  "properties": {
    "addr:full":"Bakenbergsewg 210 Arnhem Gelderland 6814 MS",
    "addr:housenumber":"210",
    "addr:postcode":"6814 ms",
    "iso:country":"NL",
    "sg:address":"Bakenbergsewg 210",
    "sg:city":"Arnhem",
    "sg:orig_category":"Adviesbureaus Bedrijfsorganisatie",
    "sg:phone":"+31 26 442 1001",
    "sg:postcode":"6814 MS",
    "sg:province":"Gelderland",
    "wof:name":"Mare Bv",
    "wof:placetype":"venue"
},
  "geometry": {"coordinates":[5.882966,51.998203],"type":"Point"}
}