{
  "type": "Feature",
  "properties": {
    "addr:full":"Dorpsstr 12 De Bilt Utrecht 3732 HJ",
    "addr:housenumber":"12",
    "addr:postcode":"3732 hj",
    "addr:street":"Dorpsstr",
    "iso:country":"NL",
    "sg:address":"Dorpsstr 12",
    "sg:city":"De Bilt",
    "sg:orig_category":"Werving En Selectie",
    "sg:phone":"+31 30 220 9209",
    "sg:postcode":"3732 HJ",
    "sg:province":"Utrecht",
    "sg:website":"http://www.deloitte.nl/humancapitalgroup",
    "wof:name":"Human Capital Group",
    "wof:placetype":"venue"
},
  "geometry": {"coordinates":[5.1855487823,52.1044273376],"type":"Point"}
}