{
  "type": "Feature",
  "properties": {
    "addr:full":"Smitshoek 49 Barendrecht South Holland 2993 BG",
    "addr:housenumber":"49",
    "addr:postcode":"2993",
    "addr:street":"Smitshoek",
    "iso:country":"NL",
    "sg:address":"Smitshoek 49",
    "sg:city":"Barendrecht",
    "sg:orig_category":"Koeltechniek",
    "sg:phone":"+31 180 618 378",
    "sg:postcode":"2993 BG",
    "sg:province":"South Holland",
    "sg:website":"http://www.bako.nl",
    "wof:name":"Bako Koeltechniek",
    "wof:placetype":"venue"
},
  "geometry": {"coordinates":[4.480547,51.861916],"type":"Point"}
}