{
  "type": "Feature",
  "properties": {
    "addr:full":"A Schweitzersngl 347 Amersfoort Utrecht 3822 BV",
    "addr:housenumber":"347",
    "addr:postcode":"3822 bv",
    "iso:country":"NL",
    "sg:address":"A Schweitzersngl 347",
    "sg:city":"Amersfoort",
    "sg:orig_category":"Verzekeringen - Verzekeringskantoren",
    "sg:phone":"+31 33 455 6363",
    "sg:postcode":"3822 BV",
    "sg:province":"Utrecht",
    "wof:name":"Kelderman",
    "wof:placetype":"venue"
},
  "geometry": {"coordinates":[5.406484,52.184551],"type":"Point"}
}