{
  "type": "Feature",
  "properties": {
    "addr:full":"Maast Smedenstr 5 Maastricht Limburg 6211 GK",
    "addr:housenumber":"5",
    "addr:postcode":"6211 gk",
    "addr:street":"Smedenstr",
    "iso:country":"NL",
    "sg:address":"Maast Smedenstr 5",
    "sg:city":"Maastricht",
    "sg:orig_category":"Herenkleding",
    "sg:phone":"+31 43 327 0831",
    "sg:postcode":"6211 GK",
    "sg:province":"Limburg",
    "wof:name":"Grimaldi",
    "wof:placetype":"venue"
},
  "geometry": {"coordinates":[5.693806,50.848824],"type":"Point"}
}