{
  "type": "Feature",
  "properties": {
    "iso:country":"NL",
    "sg:address":"Sportlaan 10",
    "sg:city":"Venray",
    "sg:orig_category":"Meubelzaken, Woning- And Keukeninrichting",
    "sg:phone":"+31 478 581 101",
    "sg:postcode":"5801 AH",
    "sg:province":"Limburg",
    "wof:name":"G.J.V. Stoks",
    "wof:placetype":"venue"
},
  "geometry": {"coordinates":[5.973691,51.515625],"type":"Point"}
}