{
  "type": "Feature",
  "properties": {
    "addr:full":"Keizersgr 478 Amsterdam North Holland 1017 EG",
    "addr:housenumber":"478",
    "addr:postcode":"1017 eg",
    "iso:country":"NL",
    "sg:address":"Keizersgr 478",
    "sg:city":"Amsterdam",
    "sg:orig_category":"Luchtvaart- Maatschappijen",
    "sg:phone":"+31 20 626 1766",
    "sg:postcode":"1017 EG",
    "sg:province":"North Holland",
    "wof:name":"Biman Bangladesh Airlines",
    "wof:placetype":"venue"
},
  "geometry": {"coordinates":[4.885075,52.366302],"type":"Point"}
}