{
  "type": "Feature",
  "properties": {
    "addr:full":"Dierenriemstraat 242 Groningen Groningen 9742 AN",
    "addr:housenumber":"242",
    "addr:postcode":"9742 an",
    "addr:street":"Dierenriemstraat",
    "iso:country":"NL",
    "sg:address":"Dierenriemstraat 242",
    "sg:city":"Groningen",
    "sg:classifiers":[
        {
            "category":"Communications",
            "subcategory":"Television Station",
            "type":"Services"
        }
    ],
    "sg:phone":"+31 50 571 8276",
    "sg:postcode":"9742 AN",
    "sg:province":"Groningen",
    "sg:tags":[
        "video",
        "audio",
        "verhuur"
    ],
    "wof:name":"Videoland Paddepoel",
    "wof:placetype":"venue"
},
  "geometry": {"coordinates":[6.545097,53.230484],"type":"Point"}
}