{
  "type": "Feature",
  "properties": {
    "addr:full":"Singelstr 22 Leeuwarden Friesland 8917 BK",
    "addr:housenumber":"22",
    "addr:postcode":"8917 bk",
    "addr:street":"Singelstr",
    "iso:country":"NL",
    "sg:address":"Singelstr 22",
    "sg:city":"Leeuwarden",
    "sg:orig_category":"Peuterspeelzalen",
    "sg:phone":"+31 58 213 3067",
    "sg:postcode":"8917 BK",
    "sg:province":"Friesland",
    "wof:name":"Rengerspark",
    "wof:placetype":"venue"
},
  "geometry": {"coordinates":[5.793521,53.206982],"type":"Point"}
}