{
  "type": "Feature",
  "properties": {
    "addr:full":"Loopkantstr 1E Uden North Brabant 5405 NB",
    "addr:housenumber":"1e",
    "addr:postcode":"5405 nb",
    "addr:street":"Loopkantstr",
    "iso:country":"NL",
    "sg:address":"Loopkantstr 1E",
    "sg:city":"Uden",
    "sg:orig_category":"Verzekeringen - Verzekeringskantoren",
    "sg:phone":"+31 413 339 944",
    "sg:postcode":"5405 NB",
    "sg:province":"North Brabant",
    "wof:name":"Guijt",
    "wof:placetype":"venue"
},
  "geometry": {"coordinates":[5.628518,51.655361],"type":"Point"}
}