{
  "type": "Feature",
  "properties": {
    "addr:full":"Boerendanssteeg 25 Holten Overijssel 7451 LP",
    "addr:housenumber":"25",
    "addr:postcode":"7451 lp",
    "addr:street":"Boerendanssteeg",
    "iso:country":"NL",
    "sg:address":"Boerendanssteeg 25",
    "sg:city":"Holten",
    "sg:orig_category":"Houtverwerking",
    "sg:phone":"+31 548 361 404",
    "sg:postcode":"7451 LP",
    "sg:province":"Overijssel",
    "wof:name":"J. Koopman",
    "wof:placetype":"venue"
},
  "geometry": {"coordinates":[6.347167,52.279827],"type":"Point"}
}