{
  "type": "Feature",
  "properties": {
    "addr:full":"Dobbeweg 9 Voorschoten South Holland 2254 AG",
    "addr:housenumber":"9",
    "addr:postcode":"2254",
    "addr:street":"Dobbeweg",
    "iso:country":"NL",
    "sg:address":"Dobbeweg 9",
    "sg:city":"Voorschoten",
    "sg:orig_category":"Verhuur Bouwmachines",
    "sg:phone":"+31 71 561 9141",
    "sg:postcode":"2254 AG",
    "sg:province":"South Holland",
    "wof:name":"De Groot Kraanverhuur En Transport Bv",
    "wof:placetype":"venue"
},
  "geometry": {"coordinates":[4.433069,52.129757],"type":"Point"}
}