{
  "type": "Feature",
  "properties": {
    "addr:full":"Julianalaan 38 Bilthoven Utrecht 3722 GR",
    "addr:housenumber":"38",
    "addr:postcode":"3722",
    "addr:street":"Julianalaan",
    "iso:country":"NL",
    "sg:address":"Julianalaan 38",
    "sg:city":"Bilthoven",
    "sg:orig_category":"Opticiens",
    "sg:phone":"+31 30 228 3014",
    "sg:postcode":"3722 GR",
    "sg:province":"Utrecht",
    "wof:name":"Meijer Optiek Bilthoven Bv",
    "wof:placetype":"venue"
},
  "geometry": {"coordinates":[5.2088899612,52.1293792725],"type":"Point"}
}