{
  "type": "Feature",
  "properties": {
    "iso:country":"NL",
    "sg:address":"Kievit 20",
    "sg:city":"Zoeterwoude",
    "sg:classifiers":[
        {
            "category":"Shopping",
            "subcategory":"Gifts & Souvenirs",
            "type":"Retail Goods"
        }
    ],
    "sg:phone":"+31 71 580 3328",
    "sg:postcode":"2381 KC",
    "sg:province":"Zuid-Holland",
    "sg:tags":[
        "geschenken"
    ],
    "wof:name":"Shady Tree",
    "wof:placetype":"venue"
},
  "geometry": {"coordinates":[4.492989,52.121941],"type":"Point"}
}