{
  "type": "Feature",
  "properties": {
    "iso:country":"NL",
    "sg:address":"De Wygeast 32",
    "sg:city":"Oudwoude",
    "sg:orig_category":"Loodgieterswerk, Verwarming And Sanitaire Installaties",
    "sg:phone":"+31 511 452 940",
    "sg:postcode":"9294 KR",
    "sg:province":"Friesland",
    "wof:name":"Hoekstra'S Klussenbedrijf",
    "wof:placetype":"venue"
},
  "geometry": {"coordinates":[6.117829,53.286358],"type":"Point"}
}