{
  "type": "Feature",
  "properties": {
    "addr:full":"Mecklenburgln 5 Doorwerth Gelderland 6865 HC",
    "addr:housenumber":"5",
    "addr:postcode":"6865 hc",
    "addr:street":"Mecklenburgln;Gelderland",
    "iso:country":"NL",
    "sg:address":"Mecklenburgln 5",
    "sg:city":"Doorwerth",
    "sg:orig_category":"Fotoreportages",
    "sg:phone":"+31 26 333 7317",
    "sg:postcode":"6865 HC",
    "sg:province":"Gelderland",
    "sg:website":"http://www.lieskemeimafotografie.nl",
    "wof:name":"Meima, Lieske",
    "wof:placetype":"venue"
},
  "geometry": {"coordinates":[5.803009,51.980095],"type":"Point"}
}