{
  "type": "Feature",
  "properties": {
    "addr:full":"Noordkant 29 St Anthonis North Brabant 5845 EX",
    "addr:housenumber":"29",
    "addr:postcode":"5845 ex",
    "addr:street":"Noordkant;St Anthonis",
    "iso:country":"NL",
    "sg:address":"Noordkant 29",
    "sg:city":"St Anthonis",
    "sg:orig_category":"Dierenvoeder - Fabrieken",
    "sg:phone":"+31 485 385 655",
    "sg:postcode":"5845 EX",
    "sg:province":"North Brabant",
    "wof:name":"Nutri - Use Bv",
    "wof:placetype":"venue"
},
  "geometry": {"coordinates":[5.894175,51.639828],"type":"Point"}
}