{
  "type": "Feature",
  "properties": {
    "iso:country":"NL",
    "sg:address":"Horst 2950",
    "sg:city":"Lelystad",
    "sg:orig_category":"Postorderbedrijven",
    "sg:phone":"+31 320 258 826",
    "sg:postcode":"8225 MV",
    "sg:province":"Flevoland",
    "sg:website":"http://www.condoombox.nl",
    "wof:name":"Condoombox Nederland",
    "wof:placetype":"venue"
},
  "geometry": {"coordinates":[5.494801,52.504055],"type":"Point"}
}