{
  "type": "Feature",
  "properties": {
    "addr:full":"Stuwwal 20 Kraggenburg NL. 8317 BE",
    "addr:housenumber":"20",
    "addr:postcode":"8317",
    "addr:street":"Stuwwal;Nl.",
    "iso:country":"NL",
    "sg:address":"Stuwwal 20",
    "sg:city":"Kraggenburg",
    "sg:classifiers":[
        {
            "category":"Personal",
            "subcategory":"Nail Salon",
            "type":"Services"
        }
    ],
    "sg:phone":"+31 527 252 447",
    "sg:postcode":"8317 BE",
    "sg:province":"NL.",
    "sg:tags":[
        "pedicure"
    ],
    "wof:name":"Bosch-Hoek, A M S Van Den",
    "wof:placetype":"venue"
},
  "geometry": {"coordinates":[5.906193,52.663101],"type":"Point"}
}