{
  "type": "Feature",
  "properties": {
    "addr:full":"De Eenhoorn 150 Oosterblokker Noord-Holland 1696 CN",
    "addr:housenumber":"150",
    "addr:postcode":"1696 cn",
    "addr:street":"De Eenhoorn",
    "iso:country":"NL",
    "sg:address":"De Eenhoorn 150",
    "sg:city":"Oosterblokker",
    "sg:orig_category":"Schilders",
    "sg:phone":"+31 229 263 980",
    "sg:postcode":"1696 CN",
    "sg:province":"Noord-Holland",
    "wof:name":"Beek, Richard",
    "wof:placetype":"venue"
},
  "geometry": {"coordinates":[5.119269,52.670033],"type":"Point"}
}