{
  "type": "Feature",
  "properties": {
    "iso:country":"NL",
    "sg:address":"Thyssestr 487",
    "sg:city":"S Gravenhage",
    "sg:classifiers":[
        {
            "category":"Personal",
            "subcategory":"Nail Salon",
            "type":"Services"
        }
    ],
    "sg:phone":"+31 70 336 8081",
    "sg:postcode":"2521 ZK",
    "sg:province":"South Holland",
    "sg:tags":[
        "pedicure"
    ],
    "wof:name":"Rozema",
    "wof:placetype":"venue"
},
  "geometry": {"coordinates":[4.32071,52.062988],"type":"Point"}
}