{
  "type": "Feature",
  "properties": {
    "iso:country":"NL",
    "sg:address":"Eglantierbaan 43",
    "sg:city":"Capelle A/D Ijssel",
    "sg:orig_category":"Elektronische Bedrijfsinstallaties",
    "sg:phone":"+31 10 458 9188",
    "sg:postcode":"2908 LV",
    "sg:province":"South Holland",
    "wof:name":"Thorn Security Nederland Bv",
    "wof:placetype":"venue"
},
  "geometry": {"coordinates":[4.575182,51.957745],"type":"Point"}
}