{
  "type": "Feature",
  "properties": {
    "addr:full":"Galgeriet 12 Monnickendam Noord-Holland 1141 GM",
    "addr:housenumber":"12",
    "addr:postcode":"1141 gm",
    "addr:street":"Galgeriet",
    "iso:country":"NL",
    "sg:address":"Galgeriet 12",
    "sg:city":"Monnickendam",
    "sg:orig_category":"Huishoudapparatuur, Televisies And Radio'S",
    "sg:phone":"+31 299 657 770",
    "sg:postcode":"1141 GM",
    "sg:province":"Noord-Holland",
    "wof:name":"Ronday Bv",
    "wof:placetype":"venue"
},
  "geometry": {"coordinates":[5.040305,52.457527],"type":"Point"}
}