{
  "type": "Feature",
  "properties": {
    "addr:full":"Korvelsewg 219 Tilburg Noord-Brabant 5025 JG",
    "addr:housenumber":"219",
    "addr:postcode":"5025 jg",
    "addr:street":"Tilburg",
    "iso:country":"NL",
    "sg:address":"Korvelsewg 219",
    "sg:city":"Tilburg",
    "sg:orig_category":"Videotheken",
    "sg:phone":"+31 13 535 7181",
    "sg:postcode":"5025 JG",
    "sg:province":"Noord-Brabant",
    "wof:name":"Jumbo",
    "wof:placetype":"venue"
},
  "geometry": {"coordinates":[5.071041,51.550552],"type":"Point"}
}