{
  "type": "Feature",
  "properties": {
    "addr:full":"Wieldk 1 Heenvliet Zuid-Holland 3218 LL",
    "addr:housenumber":"1",
    "addr:postcode":"3218 ll",
    "addr:street":"Wieldk",
    "iso:country":"NL",
    "sg:address":"Wieldk 1",
    "sg:city":"Heenvliet",
    "sg:orig_category":"Jachthavens - Jachtwerven",
    "sg:phone":"+31 181 664 184",
    "sg:postcode":"3218 LL",
    "sg:province":"Zuid-Holland",
    "wof:name":"Kleine Bernisse, De",
    "wof:placetype":"venue"
},
  "geometry": {"coordinates":[4.24787,51.867279],"type":"Point"}
}