{
  "type": "Feature",
  "properties": {
    "iso:country":"NL",
    "sg:address":"Veilingwg 11",
    "sg:city":"Gronsveld",
    "sg:orig_category":"Bouwmaterialen",
    "sg:phone":"+31 43 408 3333",
    "sg:postcode":"6247 EP",
    "sg:province":"Limburg",
    "wof:name":"Brentjens Handelsonderneming",
    "wof:placetype":"venue"
},
  "geometry": {"coordinates":[5.732333,50.799728],"type":"Point"}
}