{
  "type": "Feature",
  "properties": {
    "iso:country":"NL",
    "sg:address":"Schinkelstr 22",
    "sg:city":"Hoofddorp",
    "sg:orig_category":"Koeriersdiensten",
    "sg:phone":"+31 23 564 2090",
    "sg:postcode":"2131 DK",
    "sg:province":"North Holland",
    "wof:name":"Aardema",
    "wof:placetype":"venue"
},
  "geometry": {"coordinates":[4.685413,52.313438],"type":"Point"}
}