{
  "type": "Feature",
  "properties": {
    "addr:full":"Paleisstraat 137 Amsterdam Noord-Holland 1012 ZL",
    "addr:housenumber":"137",
    "addr:postcode":"1012 zl",
    "addr:street":"Paleisstraat",
    "iso:country":"NL",
    "sg:address":"Paleisstraat 137",
    "sg:city":"Amsterdam",
    "sg:orig_category":"Overheidsdiensten",
    "sg:phone":"+31 20 626 0076",
    "sg:postcode":"1012 ZL",
    "sg:province":"Noord-Holland",
    "wof:name":"Cooperatieve Vereniging De Spruitjes Ua",
    "wof:placetype":"venue"
},
  "geometry": {"coordinates":[4.8897461891,52.3722343445],"type":"Point"}
}