{
  "type": "Feature",
  "properties": {
    "iso:country":"NL",
    "sg:address":"Waagwg 10",
    "sg:city":"Holten",
    "sg:orig_category":"Meubelen - Fabrieken En Groothandel",
    "sg:phone":"+31 548 363 100",
    "sg:postcode":"7451 AZ",
    "sg:province":"Overijssel",
    "wof:name":"Banz Bord Bv",
    "wof:placetype":"venue"
},
  "geometry": {"coordinates":[6.42725,52.284645],"type":"Point"}
}