{
  "type": "Feature",
  "properties": {
    "addr:full":"Flemingln 16 Ryswyk Zh South Holland 2289 CP",
    "addr:housenumber":"16;zh",
    "addr:postcode":"2289 cp",
    "addr:street":"Flemingln",
    "iso:country":"NL",
    "sg:address":"Flemingln 16",
    "sg:city":"Ryswyk Zh",
    "sg:orig_category":"Verenigingen En Stichtingen",
    "sg:phone":"+31 70 319 2583",
    "sg:postcode":"2289 CP",
    "sg:province":"South Holland",
    "wof:name":"Vakantiefonds Metaalnijverheid",
    "wof:placetype":"venue"
},
  "geometry": {"coordinates":[4.32436,52.037251],"type":"Point"}
}