{
  "type": "Feature",
  "properties": {
    "addr:full":"Lemmenhoek 21 Ospel Limburg 6035 AJ",
    "addr:housenumber":"21",
    "addr:postcode":"6035 aj",
    "addr:street":"Lemmenhoek",
    "iso:country":"NL",
    "sg:address":"Lemmenhoek 21",
    "sg:city":"Ospel",
    "sg:orig_category":"Autorijscholen",
    "sg:phone":"+31 495 631 277",
    "sg:postcode":"6035 AJ",
    "sg:province":"Limburg",
    "wof:name":"Bussel, H Van",
    "wof:placetype":"venue"
},
  "geometry": {"coordinates":[-86.165451,34.620892],"type":"Point"}
}