{
  "type": "Feature",
  "properties": {
    "addr:full":"Z Midslandwg 3 Terschelling Midld Friesland 8891 GH",
    "addr:housenumber":"3;midld",
    "addr:postcode":"8891 gh",
    "addr:street":"Terschelling",
    "iso:country":"NL",
    "sg:address":"Z Midslandwg 3",
    "sg:city":"Terschelling Midld",
    "sg:orig_category":"Bloemen En Planten - Decoratie",
    "sg:phone":"+31 562 449 505",
    "sg:postcode":"8891 GH",
    "sg:province":"Friesland",
    "wof:name":"Buitenleven",
    "wof:placetype":"venue"
},
  "geometry": {"coordinates":[5.28566,53.382023],"type":"Point"}
}