{
  "type": "Feature",
  "properties": {
    "addr:full":"Trompet 18 De Lier South Holland 2678 HE",
    "addr:housenumber":"18",
    "addr:postcode":"2678 he",
    "addr:street":"Trompet",
    "iso:country":"NL",
    "sg:address":"Trompet 18",
    "sg:city":"De Lier",
    "sg:orig_category":"Architecten",
    "sg:phone":"+31 174 517 158",
    "sg:postcode":"2678 HE",
    "sg:province":"South Holland",
    "wof:name":"J.M.D. Zwinkels Architekt Bna",
    "wof:placetype":"venue"
},
  "geometry": {"coordinates":[4.239748,51.974239],"type":"Point"}
}