{
  "type": "Feature",
  "properties": {
    "iso:country":"NL",
    "sg:address":"Demkaweg 19",
    "sg:city":"Utrecht",
    "sg:orig_category":"Werving And Selectie Van Tijdelijk Personeel And Uitzendkantoren",
    "sg:phone":"+31 30 242 8340",
    "sg:postcode":"3555 HW",
    "sg:province":"Utrecht",
    "wof:name":"Swa Uitzendorganisatie Bv",
    "wof:placetype":"venue"
},
  "geometry": {"coordinates":[5.0797362328,52.1107711792],"type":"Point"}
}