{
  "type": "Feature",
  "properties": {
    "addr:full":"Groenendaal 39 Rotterdam South Holland 3011 SM",
    "addr:housenumber":"39",
    "addr:postcode":"3011 sm",
    "addr:street":"Groenendaal",
    "iso:country":"NL",
    "sg:address":"Groenendaal 39",
    "sg:city":"Rotterdam",
    "sg:classifiers":[
        {
            "category":"Retail",
            "subcategory":"Photofinishing",
            "type":"Services"
        }
    ],
    "sg:phone":"+31 10 214 1314",
    "sg:postcode":"3011 SM",
    "sg:province":"South Holland",
    "sg:tags":[
        "foto",
        "film"
    ],
    "wof:name":"Photex Bv",
    "wof:placetype":"venue"
},
  "geometry": {"coordinates":[4.494636,51.922379],"type":"Point"}
}