{
  "type": "Feature",
  "properties": {
    "addr:full":"Meidoornln 38 Veenhuizen Provincie Drenthe 9341 AP",
    "addr:housenumber":"38",
    "addr:postcode":"9341 ap",
    "addr:street":"Meidoornln;Provincie Drenthe",
    "iso:country":"NL",
    "sg:address":"Meidoornln 38",
    "sg:city":"Veenhuizen",
    "sg:orig_category":"Voetbalverenigingen",
    "sg:phone":"+31 592 397 863",
    "sg:postcode":"9341 AP",
    "sg:province":"Provincie Drenthe",
    "wof:name":"Esserheem",
    "wof:placetype":"venue"
},
  "geometry": {"coordinates":[6.393605,53.040237],"type":"Point"}
}