{
  "type": "Feature",
  "properties": {
    "addr:full":"Lg Bothofstr 159 Enschede NL.08 7533 AS",
    "addr:housenumber":"159",
    "addr:postcode":"7533 as",
    "addr:street":"Lg",
    "iso:country":"NL",
    "sg:address":"Lg Bothofstr 159",
    "sg:city":"Enschede",
    "sg:orig_category":"Schoenen",
    "sg:phone":"+31 53 430 6114",
    "sg:postcode":"7533 AS",
    "sg:province":"NL.08",
    "sg:website":"http://www.scapino.nl",
    "wof:name":"Scapino",
    "wof:placetype":"venue"
},
  "geometry": {"coordinates":[6.910903,52.223495],"type":"Point"}
}