{
  "type": "Feature",
  "properties": {
    "iso:country":"NL",
    "sg:address":"Linnaeusstr 48",
    "sg:city":"Amsterdam",
    "sg:orig_category":"Bloemen En Planten",
    "sg:phone":"+31 20 693 2129",
    "sg:postcode":"1092 CM",
    "sg:province":"North Holland",
    "wof:name":"Mulders, N G M",
    "wof:placetype":"venue"
},
  "geometry": {"coordinates":[4.926686,52.357449],"type":"Point"}
}