{
  "type": "Feature",
  "properties": {
    "iso:country":"NL",
    "sg:address":"Maliesingel 23",
    "sg:city":"Utrecht",
    "sg:orig_category":"Bedrijfs- And Managementsconsultants",
    "sg:phone":"+31 30 231 3308",
    "sg:postcode":"3581 BG",
    "sg:province":"Utrecht",
    "wof:name":"Van Doorn & Partners Organisatie Adviseurs Bv",
    "wof:placetype":"venue"
},
  "geometry": {"coordinates":[5.129177,52.090031],"type":"Point"}
}