{
  "type": "Feature",
  "properties": {
    "addr:full":"Nedercamp 36 Houten Utrecht 3992 RP",
    "addr:housenumber":"36",
    "addr:postcode":"3992 rp",
    "addr:street":"Nedercamp",
    "iso:country":"NL",
    "sg:address":"Nedercamp 36",
    "sg:city":"Houten",
    "sg:orig_category":"Adviesbureaus Bedrijfsorganisatie",
    "sg:phone":"+31 30 638 1613",
    "sg:postcode":"3992 RP",
    "sg:province":"Utrecht",
    "wof:name":"Dav-It Bv",
    "wof:placetype":"venue"
},
  "geometry": {"coordinates":[5.149568,52.033516],"type":"Point"}
}