{
  "type": "Feature",
  "properties": {
    "addr:full":"Westeinde 14 S Gravenhage Zuid-Holland 2512 HD",
    "addr:housenumber":"14;gravenhage",
    "addr:postcode":"2512 hd",
    "addr:street":"Westeinde;S",
    "iso:country":"NL",
    "sg:address":"Westeinde 14",
    "sg:city":"S Gravenhage",
    "sg:orig_category":"Verenigingen En Stichtingen",
    "sg:phone":"+31 70 345 4695",
    "sg:postcode":"2512 HD",
    "sg:province":"Zuid-Holland",
    "wof:name":"Bewaakt & Bewoond, Sticht",
    "wof:placetype":"venue"
},
  "geometry": {"coordinates":[4.30618,52.073212],"type":"Point"}
}