{
  "type": "Feature",
  "properties": {
    "addr:full":"De Paal 1-6 Almere Flevoland 1351 JA",
    "addr:housenumber":"1-6",
    "addr:postcode":"1351 ja",
    "addr:street":"De Paal;Flevoland",
    "iso:country":"NL",
    "sg:address":"De Paal 1-6",
    "sg:city":"Almere",
    "sg:classifiers":[
        {
            "category":"Professional",
            "subcategory":"Accounting & Tax Preparation",
            "type":"Services"
        }
    ],
    "sg:phone":"+31 36 538 6849",
    "sg:postcode":"1351 JA",
    "sg:province":"Flevoland",
    "sg:tags":[
        "accountant"
    ],
    "wof:name":"Accountantskantoor Heemskerk En Snels",
    "wof:placetype":"venue"
},
  "geometry": {"coordinates":[5.219284,52.347095],"type":"Point"}
}