{
  "type": "Feature",
  "properties": {
    "addr:full":"Hennebergweg 1 Simpelveld Limburg 6369 BL",
    "addr:housenumber":"1",
    "addr:postcode":"6369 bl",
    "addr:street":"Hennebergweg",
    "iso:country":"NL",
    "sg:address":"Hennebergweg 1",
    "sg:city":"Simpelveld",
    "sg:classifiers":[
        {
            "category":"Travel",
            "subcategory":"Hotels & Motels",
            "type":"Entertainment"
        }
    ],
    "sg:phone":"+31 45 544 5051",
    "sg:postcode":"6369 BL",
    "sg:province":"Limburg",
    "wof:name":"De Witte Keizerin",
    "wof:placetype":"venue"
},
  "geometry": {"coordinates":[5.9731,50.834724],"type":"Point"}
}