{
  "type": "Feature",
  "properties": {
    "addr:full":"Jonkheer Geverslaan 7 Heemskerk Noord-Holland 1964 KG",
    "addr:housenumber":"7",
    "addr:postcode":"1964 kg",
    "addr:street":"Jonkheer Geverslaan",
    "iso:country":"NL",
    "sg:address":"Jonkheer Geverslaan 7",
    "sg:city":"Heemskerk",
    "sg:orig_category":"Bloemen And Planten Gh",
    "sg:phone":"+31 251 237 801",
    "sg:postcode":"1964 KG",
    "sg:province":"Noord-Holland",
    "wof:name":"Berghuis Bloemen Import-Export",
    "wof:placetype":"venue"
},
  "geometry": {"coordinates":[4.664999,52.513702],"type":"Point"}
}