{
  "type": "Feature",
  "properties": {
    "addr:full":"Roebol 43 Genemuiden Overijssel 8281 LL",
    "addr:housenumber":"43",
    "addr:postcode":"8281 ll",
    "addr:street":"Roebol",
    "iso:country":"NL",
    "sg:address":"Roebol 43",
    "sg:city":"Genemuiden",
    "sg:orig_category":"Administratie- En Boekhoudkantoren",
    "sg:phone":"+31 38 385 6041",
    "sg:postcode":"8281 LL",
    "sg:province":"Overijssel",
    "wof:name":"Beens-Van Der Vegte",
    "wof:placetype":"venue"
},
  "geometry": {"coordinates":[6.034791,52.629299],"type":"Point"}
}