{
  "type": "Feature",
  "properties": {
    "addr:full":"Telefoonstr 40 Tilburg Noord-Brabant 5038 DM",
    "addr:housenumber":"40",
    "addr:postcode":"5038 dm",
    "addr:street":"Telefoonstr",
    "iso:country":"NL",
    "sg:address":"Telefoonstr 40",
    "sg:city":"Tilburg",
    "sg:orig_category":"Babyartikelen",
    "sg:phone":"+31 13 580 1068",
    "sg:postcode":"5038 DM",
    "sg:province":"Noord-Brabant",
    "wof:name":"Pr?natal",
    "wof:placetype":"venue"
},
  "geometry": {"coordinates":[5.085153,51.556133],"type":"Point"}
}