{
  "type": "Feature",
  "properties": {
    "addr:full":"Kerkstr 2 Huizen North Holland 1271 RL",
    "addr:housenumber":"2",
    "addr:postcode":"1271 rl",
    "addr:street":"Kerkstr",
    "iso:country":"NL",
    "sg:address":"Kerkstr 2",
    "sg:city":"Huizen",
    "sg:orig_category":"Postkantoren",
    "sg:phone":"+31 35 525 5875",
    "sg:postcode":"1271 RL",
    "sg:province":"North Holland",
    "sg:website":"http://www.postkantoor.nl",
    "wof:name":"Postkantoor",
    "wof:placetype":"venue"
},
  "geometry": {"coordinates":[5.232356,52.297264],"type":"Point"}
}