{
  "type": "Feature",
  "properties": {
    "addr:full":"Prelaatweg 4 Westkapelle Zeeland 4361 SC",
    "addr:housenumber":"4",
    "addr:postcode":"4361",
    "addr:street":"Prelaatweg",
    "iso:country":"NL",
    "sg:address":"Prelaatweg 4",
    "sg:city":"Westkapelle",
    "sg:classifiers":[
        {
            "category":"Travel",
            "subcategory":"Hotels & Motels",
            "type":"Entertainment"
        }
    ],
    "sg:phone":"+31 118 571 851",
    "sg:postcode":"4361 SC",
    "sg:province":"Zeeland",
    "wof:name":"Villa Eb En Vloed",
    "wof:placetype":"venue"
},
  "geometry": {"coordinates":[3.450705,51.528606],"type":"Point"}
}