{
  "type": "Feature",
  "properties": {
    "addr:full":"L Bisschopstr 64 Deventer Overijssel 7411 KN",
    "addr:housenumber":"64",
    "addr:postcode":"7411 kn",
    "iso:country":"NL",
    "sg:address":"L Bisschopstr 64",
    "sg:city":"Deventer",
    "sg:orig_category":"Juweliers",
    "sg:phone":"+31 570 645 366",
    "sg:postcode":"7411 KN",
    "sg:province":"Overijssel",
    "wof:name":"Zeeland, Paul Van",
    "wof:placetype":"venue"
},
  "geometry": {"coordinates":[6.158219,52.253708],"type":"Point"}
}