{
  "type": "Feature",
  "properties": {
    "addr:full":"Swammerdamwg 9 Ysselstein Ut Utrecht 3401 MP",
    "addr:housenumber":"9",
    "addr:postcode":"3401 mp",
    "addr:street":"Swammerdamwg",
    "iso:country":"NL",
    "sg:address":"Swammerdamwg 9",
    "sg:city":"Ysselstein Ut",
    "sg:orig_category":"Centrale Verwarming - Installatie En Onderhoud",
    "sg:phone":"+31 30 686 9030",
    "sg:postcode":"3401 MP",
    "sg:province":"Utrecht",
    "sg:website":"http://www.4some.nl",
    "wof:name":"4Sometechnisch Beh Bv",
    "wof:placetype":"venue"
},
  "geometry": {"coordinates":[5.052587,52.016842],"type":"Point"}
}