{
  "type": "Feature",
  "properties": {
    "addr:full":"Ockeghemstraat 26 Eindhoven Noord-Brabant 5654 BZ",
    "addr:housenumber":"26",
    "addr:postcode":"5654 bz",
    "addr:street":"Ockeghemstraat",
    "iso:country":"NL",
    "sg:address":"Ockeghemstraat 26",
    "sg:city":"Eindhoven",
    "sg:orig_category":"Boekhouders",
    "sg:phone":"+31 40 255 5344",
    "sg:postcode":"5654 BZ",
    "sg:province":"Noord-Brabant",
    "wof:name":"Alexandra Nagel",
    "wof:placetype":"venue"
},
  "geometry": {"coordinates":[5.463218,51.418583],"type":"Point"}
}