{
  "type": "Feature",
  "properties": {
    "iso:country":"NL",
    "sg:address":"Amperestr 24",
    "sg:city":"Ede Gld",
    "sg:classifiers":[
        {
            "category":"Manufacturing",
            "subcategory":"Metals",
            "type":"Manufacturing & Wholesale Goods"
        }
    ],
    "sg:phone":"+31 318 692 774",
    "sg:postcode":"6716 BN",
    "sg:province":"Gelderland",
    "sg:tags":[
        "aluminium"
    ],
    "wof:name":"Rs Aluminium",
    "wof:placetype":"venue"
},
  "geometry": {"coordinates":[5.617734,52.026299],"type":"Point"}
}