{
  "type": "Feature",
  "properties": {
    "addr:full":"Postbus 2474 S Hertogenbosch 5202 CL",
    "addr:housenumber":"2474",
    "addr:postcode":"5202",
    "addr:street":"Postbus;S Hertogenbosch",
    "iso:country":"NL",
    "sg:address":"Postbus 2474",
    "sg:city":"S Hertogenbosch",
    "sg:orig_category":"Magazijninrichtingen",
    "sg:phone":"+31 73 642 4149",
    "sg:postcode":"5202 CL",
    "wof:name":"Ger Verhallen Bv",
    "wof:placetype":"venue"
},
  "geometry": {"coordinates":[5.30421,51.68922],"type":"Point"}
}