{
  "type": "Feature",
  "properties": {
    "addr:full":"Verdistr 40 Hengelo Ov Overijssel 7557 SE",
    "addr:housenumber":"40",
    "addr:postcode":"7557 se",
    "addr:street":"Verdistr;Ov",
    "iso:country":"NL",
    "sg:address":"Verdistr 40",
    "sg:city":"Hengelo Ov",
    "sg:orig_category":"Bestratingen",
    "sg:phone":"+31 74 250 3824",
    "sg:postcode":"7557 SE",
    "sg:province":"Overijssel",
    "wof:name":"Nijhof, Michel",
    "wof:placetype":"venue"
},
  "geometry": {"coordinates":[6.813091,52.269119],"type":"Point"}
}