{
  "type": "Feature",
  "properties": {
    "addr:full":"Weegbree 31 Raamsdonksveer North Brabant 4941 VT",
    "addr:housenumber":"31",
    "addr:postcode":"4941",
    "addr:street":"Weegbree",
    "iso:country":"NL",
    "sg:address":"Weegbree 31",
    "sg:city":"Raamsdonksveer",
    "sg:orig_category":"Folies",
    "sg:phone":"+31 162 521 365",
    "sg:postcode":"4941 VT",
    "sg:province":"North Brabant",
    "wof:name":"Mecari Bv",
    "wof:placetype":"venue"
},
  "geometry": {"coordinates":[4.8875,51.708519],"type":"Point"}
}