{
  "type": "Feature",
  "properties": {
    "addr:full":"Weilenseind 18 Gilze North Brabant 5126 PM",
    "addr:housenumber":"18",
    "addr:postcode":"5126 pm",
    "addr:street":"Weilenseind",
    "iso:country":"NL",
    "sg:address":"Weilenseind 18",
    "sg:city":"Gilze",
    "sg:orig_category":"Metaalbewerking",
    "sg:phone":"+31 161 455 596",
    "sg:postcode":"5126 PM",
    "sg:province":"North Brabant",
    "wof:name":"Appels",
    "wof:placetype":"venue"
},
  "geometry": {"coordinates":[4.948929,51.533516],"type":"Point"}
}