{
  "type": "Feature",
  "properties": {
    "iso:country":"NL",
    "sg:address":"Huissensestr 163-1",
    "sg:city":"Arnhem",
    "sg:orig_category":"Artsen - Huisartsen",
    "sg:phone":"+31 26 321 0226",
    "sg:postcode":"6833 HV",
    "sg:province":"Gelderland",
    "wof:name":"Doran, R F",
    "wof:placetype":"venue"
},
  "geometry": {"coordinates":[5.916396,51.96468],"type":"Point"}
}