{
  "type": "Feature",
  "properties": {
    "addr:full":"Stuiverstraat 1 Eindhoven North Brabant 5611 TA",
    "addr:housenumber":"1",
    "addr:postcode":"5611 ta",
    "addr:street":"Stuiverstraat",
    "iso:country":"NL",
    "sg:address":"Stuiverstraat 1",
    "sg:city":"Eindhoven",
    "sg:classifiers":[
        {
            "category":"Professional",
            "subcategory":"Accounting & Tax Preparation",
            "type":"Services"
        }
    ],
    "sg:phone":"+31 40 293 0652",
    "sg:postcode":"5611 TA",
    "sg:province":"North Brabant",
    "sg:tags":[
        "accountant"
    ],
    "wof:name":"Acc Computers",
    "wof:placetype":"venue"
},
  "geometry": {"coordinates":[5.491219,51.435535],"type":"Point"}
}