{
  "type": "Feature",
  "properties": {
    "addr:full":"B Wolffstr 182 S Gravenhage Zuid-Holland 2533 HV",
    "addr:housenumber":"182;gravenhage",
    "addr:postcode":"2533 hv",
    "addr:street":"S",
    "iso:country":"NL",
    "sg:address":"B Wolffstr 182",
    "sg:city":"S Gravenhage",
    "sg:orig_category":"Opticiens",
    "sg:phone":"+31 70 380 0422",
    "sg:postcode":"2533 HV",
    "sg:province":"Zuid-Holland",
    "wof:name":"Opticus",
    "wof:placetype":"venue"
},
  "geometry": {"coordinates":[4.2858099937,52.05286026],"type":"Point"}
}