{
  "type": "Feature",
  "properties": {
    "addr:full":"Houtwal 27 Oosterwolde Fr Friesland 8431 EX",
    "addr:housenumber":"27",
    "addr:postcode":"8431 ex",
    "addr:street":"Houtwal",
    "iso:country":"NL",
    "sg:address":"Houtwal 27",
    "sg:city":"Oosterwolde Fr",
    "sg:classifiers":[
        {
            "category":"Retail",
            "subcategory":"Storage",
            "type":"Services"
        }
    ],
    "sg:phone":"+31 516 513 061",
    "sg:postcode":"8431 EX",
    "sg:province":"Friesland",
    "sg:tags":[
        "op-",
        "en",
        "overslagbedrijven"
    ],
    "wof:name":"Buisman'S Veem- En Opslagbedrijf Bv",
    "wof:placetype":"venue"
},
  "geometry": {"coordinates":[6.301879,52.986897],"type":"Point"}
}