{
  "type": "Feature",
  "properties": {
    "addr:full":"Het Tasveld 1 Hendrik Ido Ambacht South Holland 3342 GT",
    "addr:housenumber":"1",
    "addr:postcode":"3342 gt",
    "addr:street":"Het Tasveld",
    "iso:country":"NL",
    "sg:address":"Het Tasveld 1",
    "sg:city":"Hendrik Ido Ambacht",
    "sg:orig_category":"Verzekeringen",
    "sg:phone":"+31 78 681 8566",
    "sg:postcode":"3342 GT",
    "sg:province":"South Holland",
    "wof:name":"Oosthoek Bedrijfsassurantien",
    "wof:placetype":"venue"
},
  "geometry": {"coordinates":[4.621364,51.837559],"type":"Point"}
}