{
  "type": "Feature",
  "properties": {
    "addr:full":"Julianastraat 87 Dedemsvaart NL.08 7701 GK",
    "addr:housenumber":"87;nl.08",
    "addr:postcode":"7701 gk",
    "addr:street":"Julianastraat",
    "iso:country":"NL",
    "sg:address":"Julianastraat 87",
    "sg:city":"Dedemsvaart",
    "sg:orig_category":"Opticiens",
    "sg:phone":"+31 523 612 702",
    "sg:postcode":"7701 GK",
    "sg:province":"NL.08",
    "wof:name":"L. Meilink Special Optiek",
    "wof:placetype":"venue"
},
  "geometry": {"coordinates":[6.4578180313,52.6042671204],"type":"Point"}
}