{
  "type": "Feature",
  "properties": {
    "addr:full":"Kanaalweg 15 Utrecht Utrecht 3526 KL",
    "addr:housenumber":"15",
    "addr:postcode":"3526 kl",
    "addr:street":"Kanaalweg",
    "iso:country":"NL",
    "sg:address":"Kanaalweg 15",
    "sg:city":"Utrecht",
    "sg:orig_category":"Goederenvervoer Over De Weg",
    "sg:phone":"+31 30 296 9111",
    "sg:postcode":"3526 KL",
    "sg:province":"Utrecht",
    "wof:name":"Tnt Nederland Bv",
    "wof:placetype":"venue"
},
  "geometry": {"coordinates":[5.109022,52.068665],"type":"Point"}
}