{
  "type": "Feature",
  "properties": {
    "addr:full":"Maasdijk 191 Wijk En Aalburg Noord-Brabant 4261 AJ",
    "addr:housenumber":"191",
    "addr:postcode":"4261 aj",
    "addr:street":"Maasdijk",
    "iso:country":"NL",
    "sg:address":"Maasdijk 191",
    "sg:city":"Wijk En Aalburg",
    "sg:orig_category":"Bloemen And Planten",
    "sg:phone":"+31 416 693 407",
    "sg:postcode":"4261 AJ",
    "sg:province":"Noord-Brabant",
    "wof:name":"Gebroeders Bouman Vof",
    "wof:placetype":"venue"
},
  "geometry": {"coordinates":[5.124726,51.76865],"type":"Point"}
}