{
  "type": "Feature",
  "properties": {
    "addr:full":"Markt 4 Hasselt Overijssel 8061 GG",
    "addr:housenumber":"4",
    "addr:postcode":"8061 gg",
    "addr:street":"Markt",
    "iso:country":"NL",
    "sg:address":"Markt 4",
    "sg:city":"Hasselt",
    "sg:orig_category":"Boekenuitgeverijen",
    "sg:phone":"+31 38 477 1372",
    "sg:postcode":"8061 GG",
    "sg:province":"Overijssel",
    "wof:name":"Boek- En Kantoorboekhandel De Haan",
    "wof:placetype":"venue"
},
  "geometry": {"coordinates":[6.089815,52.590878],"type":"Point"}
}