{
  "type": "Feature",
  "properties": {
    "addr:full":"Koningin Julianastraat 3 Mook Limburg 6585 XP",
    "addr:housenumber":"3",
    "addr:postcode":"6585 xp",
    "addr:street":"Koningin Julianastraat",
    "iso:country":"NL",
    "sg:address":"Koningin Julianastraat 3",
    "sg:city":"Mook",
    "sg:orig_category":"Kinderopvang Behalve Thuis",
    "sg:phone":"+31 24 696 1226",
    "sg:postcode":"6585 XP",
    "sg:province":"Limburg",
    "wof:name":"Kinderdagverblijf Bambi",
    "wof:placetype":"venue"
},
  "geometry": {"coordinates":[5.883661,51.751392],"type":"Point"}
}