{
  "type": "Feature",
  "properties": {
    "addr:full":"Ruurloseweg 49 Barchem Gelderland 7244 PC",
    "addr:housenumber":"49",
    "addr:postcode":"7244 pc",
    "addr:street":"Ruurloseweg;Gelderland",
    "iso:country":"NL",
    "sg:address":"Ruurloseweg 49",
    "sg:city":"Barchem",
    "sg:orig_category":"Kappers",
    "sg:phone":"+31 573 441 994",
    "sg:postcode":"7244 PC",
    "sg:province":"Gelderland",
    "wof:name":"Kapsalon Gerry Leussink",
    "wof:placetype":"venue"
},
  "geometry": {"coordinates":[6.4442977905,52.1193161011],"type":"Point"}
}