{
  "type": "Feature",
  "properties": {
    "iso:country":"NL",
    "sg:address":"Spaarpot Oost 18",
    "sg:city":"Geldrop",
    "sg:orig_category":"Koeltechniek",
    "sg:phone":"+31 40 280 1739",
    "sg:postcode":"5667 KT",
    "sg:province":"Noord-Brabant",
    "sg:website":"http://www.transportkoeling.info",
    "wof:name":"Batro Vof",
    "wof:placetype":"venue"
},
  "geometry": {"coordinates":[5.567535,51.439484],"type":"Point"}
}