{
  "type": "Feature",
  "properties": {
    "addr:full":"Spaarpot Oost 18 Geldrop Noord-Brabant 5667 KT",
    "addr:housenumber":"18",
    "addr:postcode":"5667 kt",
    "addr:street":"Spaarpot Oost",
    "iso:country":"NL",
    "sg:address":"Spaarpot Oost 18",
    "sg:city":"Geldrop",
    "sg:orig_category":"Koeltechniek",
    "sg:phone":"+31 40 280 1739",
    "sg:postcode":"5667 KT",
    "sg:province":"Noord-Brabant",
    "sg:website":"http://www.transportkoeling.info",
    "wof:name":"Batro Vof",
    "wof:placetype":"venue"
},
  "geometry": {"coordinates":[5.567535,51.439484],"type":"Point"}
}