{
  "type": "Feature",
  "properties": {
    "addr:full":"Postbus 128 Hendrik Ido Ambacht South Holland 3340 AC",
    "addr:housenumber":"128",
    "addr:postcode":"3340 ac",
    "addr:street":"Postbus",
    "iso:country":"NL",
    "sg:address":"Postbus 128",
    "sg:city":"Hendrik Ido Ambacht",
    "sg:orig_category":"Scholen Voor Basisonderwijs",
    "sg:phone":"+31 78 681 4135",
    "sg:postcode":"3340 AC",
    "sg:province":"South Holland",
    "wof:name":"John F Kennedy Kath",
    "wof:placetype":"venue"
},
  "geometry": {"coordinates":[4.630965,51.846111],"type":"Point"}
}