{
  "type": "Feature",
  "properties": {
    "addr:full":"Hem 20 Zierikzee Zeeland 4301 HR",
    "addr:housenumber":"20",
    "addr:postcode":"4301 hr",
    "addr:street":"Hem",
    "iso:country":"NL",
    "sg:address":"Hem 20",
    "sg:city":"Zierikzee",
    "sg:orig_category":"Woninginrichting",
    "sg:phone":"+31 6 24675907",
    "sg:postcode":"4301 HR",
    "sg:province":"Zeeland",
    "wof:name":"Woondiscount Zierikzee",
    "wof:placetype":"venue"
},
  "geometry": {"coordinates":[3.9196650982,51.6519927979],"type":"Point"}
}