{
  "type": "Feature",
  "properties": {
    "addr:full":"Scheerdersdonk 726 Apeldoorn Gelderland 7326 CC",
    "addr:housenumber":"726",
    "addr:postcode":"7326 cc",
    "addr:street":"Scheerdersdonk;Gelderland",
    "iso:country":"NL",
    "sg:address":"Scheerdersdonk 726",
    "sg:city":"Apeldoorn",
    "sg:orig_category":"Adviesbureaus Bedrijfsorganisatie",
    "sg:phone":"+31 55 543 0168",
    "sg:postcode":"7326 CC",
    "sg:province":"Gelderland",
    "wof:name":"Nijhuis",
    "wof:placetype":"venue"
},
  "geometry": {"coordinates":[6.010447,52.200859],"type":"Point"}
}