{
  "type": "Feature",
  "properties": {
    "addr:full":"Tuinstr 19 Boekel Noord-Brabant 5427 PR",
    "addr:housenumber":"19",
    "addr:postcode":"5427 pr",
    "addr:street":"Tuinstr",
    "iso:country":"NL",
    "sg:address":"Tuinstr 19",
    "sg:city":"Boekel",
    "sg:orig_category":"Metaalbewerking",
    "sg:phone":"+31 492 322 525",
    "sg:postcode":"5427 PR",
    "sg:province":"Noord-Brabant",
    "sg:website":"http://www.vanhaandelmetaal.nl",
    "wof:name":"Haandel Metaal Bv, Van",
    "wof:placetype":"venue"
},
  "geometry": {"coordinates":[5.66649,51.605831],"type":"Point"}
}