{
  "type": "Feature",
  "properties": {
    "addr:full":"Boulevard Barnaart 57 Zandvoort Noord-Holland 2041 JA",
    "addr:housenumber":"57",
    "addr:postcode":"2041 ja",
    "addr:street":"Boulevard Barnaart",
    "iso:country":"NL",
    "sg:address":"Boulevard Barnaart 57",
    "sg:city":"Zandvoort",
    "sg:classifiers":[
        {
            "category":"Fast Food",
            "type":"Food & Drink"
        }
    ],
    "sg:phone":"+31 23 571 9407",
    "sg:postcode":"2041 JA",
    "sg:province":"Noord-Holland",
    "sg:tags":[
        "afhaal",
        "restaurant"
    ],
    "wof:name":"Noorderbad Snacks",
    "wof:placetype":"venue"
},
  "geometry": {"coordinates":[4.53042,52.380871],"type":"Point"}
}