{
  "type": "Feature",
  "properties": {
    "addr:full":"Wittebrem 7 Rotterdam South Holland 3068 TL",
    "addr:housenumber":"7",
    "addr:postcode":"3068 tl",
    "addr:street":"Wittebrem",
    "iso:country":"NL",
    "sg:address":"Wittebrem 7",
    "sg:city":"Rotterdam",
    "sg:orig_category":"Adviesbureaus Bedrijfsorganisatie",
    "sg:phone":"+31 10 456 0419",
    "sg:postcode":"3068 TL",
    "sg:province":"South Holland",
    "wof:name":"Vermeulen",
    "wof:placetype":"venue"
},
  "geometry": {"coordinates":[4.556472,51.961494],"type":"Point"}
}