{
  "type": "Feature",
  "properties": {
    "addr:full":"Hogedijken 29 Dokkum Friesland 9101 WV",
    "addr:housenumber":"29",
    "addr:postcode":"9101 wv",
    "addr:street":"Hogedijken",
    "iso:country":"NL",
    "sg:address":"Hogedijken 29",
    "sg:city":"Dokkum",
    "sg:orig_category":"Bloemen And Planten",
    "sg:phone":"+31 519 294 474",
    "sg:postcode":"9101 WV",
    "sg:province":"Friesland",
    "wof:name":"Bloemisterij Hanemaayer - Drogt",
    "wof:placetype":"venue"
},
  "geometry": {"coordinates":[6.008053,53.324589],"type":"Point"}
}