{
  "type": "Feature",
  "properties": {
    "addr:full":"Ekelshoek 11 Blaricum Noord-Holland 1261 TT",
    "addr:housenumber":"11",
    "addr:postcode":"1261 tt",
    "addr:street":"Ekelshoek",
    "iso:country":"NL",
    "sg:address":"Ekelshoek 11",
    "sg:city":"Blaricum",
    "sg:orig_category":"Loodgieterswerk, Verwarming And Sanitaire Installaties",
    "sg:phone":"+31 35 531 0467",
    "sg:postcode":"1261 TT",
    "sg:province":"Noord-Holland",
    "wof:name":"Van Loo Onderhoudsbedrijf",
    "wof:placetype":"venue"
},
  "geometry": {"coordinates":[5.253701,52.274094],"type":"Point"}
}