{
  "type": "Feature",
  "properties": {
    "iso:country":"NL",
    "sg:address":"Nieuwe Vaart 9",
    "sg:city":"'S Gravenzande",
    "sg:orig_category":"Bloemen And Planten",
    "sg:phone":"+31 174 440 466",
    "sg:postcode":"2691 MA",
    "sg:province":"Zuid-Holland",
    "wof:name":"Firma H. Van Der Sar En Zn",
    "wof:placetype":"venue"
},
  "geometry": {"coordinates":[4.180059,52.000584],"type":"Point"}
}