{
  "type": "Feature",
  "properties": {
    "addr:full":"Flora 201 Deventer Overijssel 7422 LP",
    "addr:housenumber":"201",
    "addr:postcode":"7422 lp",
    "addr:street":"Flora",
    "iso:country":"NL",
    "sg:address":"Flora 201",
    "sg:city":"Deventer",
    "sg:orig_category":"Natuurvoeding En Reformartikelen",
    "sg:phone":"+31 570 651 760",
    "sg:postcode":"7422 LP",
    "sg:province":"Overijssel",
    "wof:name":"Natuurwinkel, De",
    "wof:placetype":"venue"
},
  "geometry": {"coordinates":[6.214815,52.248203],"type":"Point"}
}