{
  "type": "Feature",
  "properties": {
    "addr:full":"Veendijk 22 Loosdrecht Noord-Holland 1231 PD",
    "addr:housenumber":"22",
    "addr:postcode":"1231 pd",
    "addr:street":"Veendijk",
    "iso:country":"NL",
    "sg:address":"Veendijk 22",
    "sg:city":"Loosdrecht",
    "sg:orig_category":"Diverse Bedrijfsinstallaties Gh",
    "sg:phone":"+31 35 582 7195",
    "sg:postcode":"1231 PD",
    "sg:province":"Noord-Holland",
    "wof:name":"Technoservice Holland",
    "wof:placetype":"venue"
},
  "geometry": {"coordinates":[5.061539,52.199291],"type":"Point"}
}