{
  "type": "Feature",
  "properties": {
    "addr:full":"Kamelenspoor 186 Maarssen Utrecht 3605 EK",
    "addr:housenumber":"186",
    "addr:postcode":"3605 ek",
    "addr:street":"Kamelenspoor",
    "iso:country":"NL",
    "sg:address":"Kamelenspoor 186",
    "sg:city":"Maarssen",
    "sg:orig_category":"Goederenvervoer Over De Weg",
    "sg:phone":"+31 346 578 738",
    "sg:postcode":"3605 EK",
    "sg:province":"Utrecht",
    "wof:name":"H.W. Leen Internationaal Transportbedrij",
    "wof:placetype":"venue"
},
  "geometry": {"coordinates":[5.025903,52.137276],"type":"Point"}
}