{
  "type": "Feature",
  "properties": {
    "addr:full":"Hofkamp 48 Wommels Friesland 8731 BW",
    "addr:housenumber":"48",
    "addr:postcode":"8731 bw",
    "addr:street":"Hofkamp",
    "iso:country":"NL",
    "sg:address":"Hofkamp 48",
    "sg:city":"Wommels",
    "sg:orig_category":"Goederenvervoer Over De Weg",
    "sg:phone":"+31 515 331 414",
    "sg:postcode":"8731 BW",
    "sg:province":"Friesland",
    "wof:name":"Wal Handel En Transport",
    "wof:placetype":"venue"
},
  "geometry": {"coordinates":[5.585832,53.105598],"type":"Point"}
}