{
  "type": "Feature",
  "properties": {
    "addr:full":"Utrechtsestraat 49 Amersfoort Utrecht 3811 LA",
    "addr:housenumber":"49",
    "addr:postcode":"3811 la",
    "addr:street":"Utrechtsestraat",
    "iso:country":"NL",
    "sg:address":"Utrechtsestraat 49",
    "sg:city":"Amersfoort",
    "sg:orig_category":"Kantoorapparatuur Gh",
    "sg:phone":"+31 33 465 6460",
    "sg:postcode":"3811 LA",
    "sg:province":"Utrecht",
    "wof:name":"The Phone House",
    "wof:placetype":"venue"
},
  "geometry": {"coordinates":[5.3847751617,52.1540184021],"type":"Point"}
}