{
  "type": "Feature",
  "properties": {
    "addr:full":"Rusthoflaan 29 Rotterdam Zuid-Holland 3034 XG",
    "addr:housenumber":"29",
    "addr:postcode":"3034 xg",
    "addr:street":"Rusthoflaan",
    "iso:country":"NL",
    "sg:address":"Rusthoflaan 29",
    "sg:city":"Rotterdam",
    "sg:orig_category":"Film-, Tv- And Videoproductie",
    "sg:phone":"+31 10 413 4919",
    "sg:postcode":"3034 XG",
    "sg:province":"Zuid-Holland",
    "wof:name":"Third Eye",
    "wof:placetype":"venue"
},
  "geometry": {"coordinates":[4.494372,51.936085],"type":"Point"}
}