{
  "type": "Feature",
  "properties": {
    "addr:full":"Buikslotermeerplein 432 Amsterdam North Holland 1025 WP",
    "addr:housenumber":"432",
    "addr:postcode":"1025 wp",
    "addr:street":"Buikslotermeerplein",
    "iso:country":"NL",
    "sg:address":"Buikslotermeerplein 432",
    "sg:city":"Amsterdam",
    "sg:orig_category":"Werving And Selectie Van Tijdelijk Personeel And Uitzendkantoren",
    "sg:phone":"+31 20 636 6504",
    "sg:postcode":"1025 WP",
    "sg:province":"North Holland",
    "wof:name":"Manpower Uitzendorganisatie",
    "wof:placetype":"venue"
},
  "geometry": {"coordinates":[4.9413609505,52.3976097107],"type":"Point"}
}