{
  "type": "Feature",
  "properties": {
    "addr:full":"Vondelpark 6 Amsterdam Noord-Holland 1071 AA",
    "addr:housenumber":"6",
    "addr:postcode":"1071 aa",
    "addr:street":"Vondelpark",
    "iso:country":"NL",
    "sg:address":"Vondelpark 6",
    "sg:city":"Amsterdam",
    "sg:orig_category":"Kinderopvang Behalve Thuis",
    "sg:phone":"+31 20 612 9035",
    "sg:postcode":"1071 AA",
    "sg:province":"Noord-Holland",
    "wof:name":"Dromelot Kinderdagverblijf",
    "wof:placetype":"venue"
},
  "geometry": {"coordinates":[4.872188,52.359375],"type":"Point"}
}