{
  "type": "Feature",
  "properties": {
    "addr:full":"Luuschwg 15 Venlo Limburg 5926 PV",
    "addr:housenumber":"15",
    "addr:postcode":"5926 pv",
    "addr:street":"Luuschwg",
    "iso:country":"NL",
    "sg:address":"Luuschwg 15",
    "sg:city":"Venlo",
    "sg:orig_category":"Grondwerken",
    "sg:phone":"+31 77 382 1689",
    "sg:postcode":"5926 PV",
    "sg:province":"Limburg",
    "wof:name":"Huys & Zn, J",
    "wof:placetype":"venue"
},
  "geometry": {"coordinates":[6.128717,51.360588],"type":"Point"}
}