{
  "type": "Feature",
  "properties": {
    "iso:country":"NL",
    "sg:address":"Pastoor Van Hooijdonkln 2-4",
    "sg:city":"Lage Zwaluwe",
    "sg:orig_category":"Kinderopvang Behalve Thuis",
    "sg:phone":"+31 168 484 559",
    "sg:postcode":"4926 CH",
    "sg:province":"North Brabant",
    "wof:name":"Kinderdagverblijf Speelhoekje",
    "wof:placetype":"venue"
},
  "geometry": {"coordinates":[4.705777,51.70607],"type":"Point"}
}