{
  "type": "Feature",
  "properties": {
    "addr:full":"Bruggendijk 5 Zuidzande Zeeland 4505 PP",
    "addr:housenumber":"5",
    "addr:postcode":"4505 pp",
    "addr:street":"Bruggendijk",
    "iso:country":"NL",
    "sg:address":"Bruggendijk 5",
    "sg:city":"Zuidzande",
    "sg:orig_category":"Goederenvervoer Over De Weg",
    "sg:phone":"+31 117 452 862",
    "sg:postcode":"4505 PP",
    "sg:province":"Zeeland",
    "wof:name":"Transportbedrijf Fieret Vof",
    "wof:placetype":"venue"
},
  "geometry": {"coordinates":[3.46252,51.337746],"type":"Point"}
}