{
  "type": "Feature",
  "properties": {
    "addr:full":"F Hendrikstr 137 Amsterdam North Holland 1052 HR",
    "addr:housenumber":"137",
    "addr:postcode":"1052 hr",
    "iso:country":"NL",
    "sg:address":"F Hendrikstr 137",
    "sg:city":"Amsterdam",
    "sg:orig_category":"Verzekeringen - Verzekeringskantoren",
    "sg:phone":"+31 20 486 9082",
    "sg:postcode":"1052 HR",
    "sg:province":"North Holland",
    "wof:name":"Denco-Advies",
    "wof:placetype":"venue"
},
  "geometry": {"coordinates":[4.872283,52.373554],"type":"Point"}
}