{
  "type": "Feature",
  "properties": {
    "addr:full":"Wernerln 12 Hilversum Noord-Holland 1213 AT",
    "addr:housenumber":"12",
    "addr:postcode":"1213",
    "addr:street":"Wernerln",
    "iso:country":"NL",
    "sg:address":"Wernerln 12",
    "sg:city":"Hilversum",
    "sg:orig_category":"Adviesbureaus Bedrijfsorganisatie",
    "sg:phone":"+31 35 621 4518",
    "sg:postcode":"1213 AT",
    "sg:province":"Noord-Holland",
    "wof:name":"Igop",
    "wof:placetype":"venue"
},
  "geometry": {"coordinates":[5.1695,52.228565],"type":"Point"}
}