{
  "type": "Feature",
  "properties": {
    "addr:full":"Jousterweg 22 Heerenveen Friesland 8447 RH",
    "addr:housenumber":"22",
    "addr:postcode":"8447 rh",
    "addr:street":"Jousterweg",
    "iso:country":"NL",
    "sg:address":"Jousterweg 22",
    "sg:city":"Heerenveen",
    "sg:orig_category":"Diverse Grafische Activiteiten",
    "sg:phone":"+31 513 624 333",
    "sg:postcode":"8447 RH",
    "sg:province":"Friesland",
    "wof:name":"Woudengroep Grafisch Centrum",
    "wof:placetype":"venue"
},
  "geometry": {"coordinates":[5.904498,52.964527],"type":"Point"}
}