{
  "type": "Feature",
  "properties": {
    "iso:country":"NL",
    "sg:address":"Molenlei 1J",
    "sg:city":"Akersloot",
    "sg:orig_category":"Bedrijfsopleidingen",
    "sg:phone":"+31 72 532 0830",
    "sg:postcode":"1921 CX",
    "sg:province":"Noord-Holland",
    "sg:website":"http://www.rodema.nl",
    "wof:name":"Rodema Engineering",
    "wof:placetype":"venue"
},
  "geometry": {"coordinates":[4.754985,52.590145],"type":"Point"}
}