{
  "type": "Feature",
  "properties": {
    "iso:country":"NL",
    "sg:address":"F Nightingalestr 29",
    "sg:city":"Brunssum",
    "sg:orig_category":"Autorijscholen",
    "sg:phone":"+31 45 527 3831",
    "sg:postcode":"6441 HS",
    "sg:province":"Limburg",
    "wof:name":"Voncken, Peter",
    "wof:placetype":"venue"
},
  "geometry": {"coordinates":[5.958522,50.949017],"type":"Point"}
}