{
  "type": "Feature",
  "properties": {
    "addr:full":"Jan Steenstraat 48 Waalwijk Noord-Brabant 5143 GS",
    "addr:housenumber":"48",
    "addr:postcode":"5143 gs",
    "addr:street":"Jan Steenstraat",
    "iso:country":"NL",
    "sg:address":"Jan Steenstraat 48",
    "sg:city":"Waalwijk",
    "sg:orig_category":"Paramedische Behandelingen",
    "sg:phone":"+31 416 650 633",
    "sg:postcode":"5143 GS",
    "sg:province":"Noord-Brabant",
    "wof:name":"J C M Smulders",
    "wof:placetype":"venue"
},
  "geometry": {"coordinates":[5.082842,51.677929],"type":"Point"}
}