{
  "type": "Feature",
  "properties": {
    "addr:full":"Kerkstraat 16 Leerdam Zuid-Holland 4141 AW",
    "addr:housenumber":"16",
    "addr:postcode":"4141 aw",
    "addr:street":"Kerkstraat",
    "iso:country":"NL",
    "sg:address":"Kerkstraat 16",
    "sg:city":"Leerdam",
    "sg:orig_category":"Schoenen",
    "sg:phone":"+31 345 611 106",
    "sg:postcode":"4141 AW",
    "sg:province":"Zuid-Holland",
    "wof:name":"Schoenenreus",
    "wof:placetype":"venue"
},
  "geometry": {"coordinates":[5.094317,51.891266],"type":"Point"}
}