{
  "type": "Feature",
  "properties": {
    "addr:full":"W V Pontln 80 Zaltbommel Gelderland 5302 XC",
    "addr:housenumber":"80",
    "addr:postcode":"5302 xc",
    "addr:street":"W V Pontln;Gelderland",
    "iso:country":"NL",
    "sg:address":"W V Pontln 80",
    "sg:city":"Zaltbommel",
    "sg:orig_category":"Boeken En Tijdschriften",
    "sg:phone":"+31 418 680 979",
    "sg:postcode":"5302 XC",
    "sg:province":"Gelderland",
    "wof:name":"Deur Der Hoop",
    "wof:placetype":"venue"
},
  "geometry": {"coordinates":[5.24998,51.799179],"type":"Point"}
}