{
  "type": "Feature",
  "properties": {
    "iso:country":"NL",
    "sg:address":"Wiltonstr 23",
    "sg:city":"Zoetermeer",
    "sg:orig_category":"Metaaldraaierijen",
    "sg:phone":"+31 79 331 5302",
    "sg:postcode":"2722 NG",
    "sg:province":"Zuid-Holland",
    "wof:name":"Winters Arnhem Bv",
    "wof:placetype":"venue"
},
  "geometry": {"coordinates":[4.513876,52.050377],"type":"Point"}
}