{
  "type": "Feature",
  "properties": {
    "addr:full":"Ambachtstr 3 Naaldwyk Zuid-Holland 2671 CN",
    "addr:housenumber":"3",
    "addr:postcode":"2671 cn",
    "addr:street":"Ambachtstr",
    "iso:country":"NL",
    "sg:address":"Ambachtstr 3",
    "sg:city":"Naaldwyk",
    "sg:classifiers":[
        {
            "category":"Professional",
            "type":"Services"
        }
    ],
    "sg:phone":"+31 174 624 057",
    "sg:postcode":"2671 CN",
    "sg:province":"Zuid-Holland",
    "sg:tags":[
        "leasing"
    ],
    "sg:website":"http://www.vemo-leasing.nl",
    "wof:name":"Vemo Bv",
    "wof:placetype":"venue"
},
  "geometry": {"coordinates":[4.211865,51.998875],"type":"Point"}
}