{
  "type": "Feature",
  "properties": {
    "addr:full":"Wildenborch 5 Diemen Noord-Holland 1112 XB",
    "addr:housenumber":"5",
    "addr:postcode":"1112 xb",
    "addr:street":"Wildenborch",
    "iso:country":"NL",
    "sg:address":"Wildenborch 5",
    "sg:city":"Diemen",
    "sg:orig_category":"Boekenuitgeverijen",
    "sg:phone":"+31 20 416 7992",
    "sg:postcode":"1112 XB",
    "sg:province":"Noord-Holland",
    "wof:name":"Uitgeverij Equipe",
    "wof:placetype":"venue"
},
  "geometry": {"coordinates":[4.962448,52.32827],"type":"Point"}
}