{
  "type": "Feature",
  "properties": {
    "iso:country":"NL",
    "sg:address":"Zeggegors 42",
    "sg:city":"Mijnsheerenland",
    "sg:orig_category":"Binnenhuisarchitecten",
    "sg:phone":"+31 186 602 253",
    "sg:postcode":"3271 XL",
    "sg:province":"Zuid-Holland",
    "wof:name":"T. Alberts",
    "wof:placetype":"venue"
},
  "geometry": {"coordinates":[4.478468,51.796268],"type":"Point"}
}