{
  "type": "Feature",
  "properties": {
    "addr:full":"Neude 31 Utrecht-Centrum Utrecht 3512 AG",
    "addr:housenumber":"31",
    "addr:postcode":"3512",
    "addr:street":"Neude",
    "iso:country":"NL",
    "sg:address":"Neude 31",
    "sg:city":"Utrecht-Centrum",
    "sg:orig_category":"Werving And Selectie Van Tijdelijk Personeel And Uitzendkantoren",
    "sg:phone":"+31 30 231 0942",
    "sg:postcode":"3512 AG",
    "sg:province":"Utrecht",
    "wof:name":"Vedior",
    "wof:placetype":"venue"
},
  "geometry": {"coordinates":[5.1187529564,52.0927505493],"type":"Point"}
}