{
  "type": "Feature",
  "properties": {
    "addr:full":"Ridderln 85 S Gravenhage South Holland 2596 PH",
    "addr:housenumber":"85",
    "addr:postcode":"2596",
    "addr:street":"Ridderln;S Gravenhage",
    "iso:country":"NL",
    "sg:address":"Ridderln 85",
    "sg:city":"S Gravenhage",
    "sg:orig_category":"Vertalers",
    "sg:phone":"+31 70 326 4809",
    "sg:postcode":"2596 PH",
    "sg:province":"South Holland",
    "wof:name":"Snel, M S",
    "wof:placetype":"venue"
},
  "geometry": {"coordinates":[4.31846,52.093311],"type":"Point"}
}