{
  "type": "Feature",
  "properties": {
    "addr:full":"Groot Mijdrechtstraat 65A Mijdrecht Utrecht 3641 RV",
    "addr:housenumber":"65a",
    "addr:postcode":"3641 rv",
    "addr:street":"Groot Mijdrechtstraat",
    "iso:country":"NL",
    "sg:address":"Groot Mijdrechtstraat 65A",
    "sg:city":"Mijdrecht",
    "sg:orig_category":"Kantoor- En Secretariaatsservice",
    "sg:phone":"+31 297 288 019",
    "sg:postcode":"3641 RV",
    "sg:province":"Utrecht",
    "wof:name":"Project, Het",
    "wof:placetype":"venue"
},
  "geometry": {"coordinates":[4.8736948967,52.2118377686],"type":"Point"}
}