{
  "type": "Feature",
  "properties": {
    "addr:full":"Aristotelesln 95 Huizen Noord-Holland 1277 AP",
    "addr:housenumber":"95",
    "addr:postcode":"1277 ap",
    "addr:street":"Aristotelesln",
    "iso:country":"NL",
    "sg:address":"Aristotelesln 95",
    "sg:city":"Huizen",
    "sg:orig_category":"Adviesbureaus Bouwkunde",
    "sg:phone":"+31 35 526 8772",
    "sg:postcode":"1277 AP",
    "sg:province":"Noord-Holland",
    "wof:name":"Visser Huizen Bv",
    "wof:placetype":"venue"
},
  "geometry": {"coordinates":[5.2774457932,52.2963256836],"type":"Point"}
}