{
  "type": "Feature",
  "properties": {
    "iso:country":"NL",
    "sg:address":"Rijksstraatweg 246",
    "sg:city":"Haarlem",
    "sg:orig_category":"Opticiens",
    "sg:phone":"+31 23 537 9428",
    "sg:postcode":"2022 DJ",
    "sg:province":"Noord-Holland",
    "wof:name":"Federmann",
    "wof:placetype":"venue"
},
  "geometry": {"coordinates":[4.650633812,52.4086990356],"type":"Point"}
}