{
  "type": "Feature",
  "properties": {
    "iso:country":"NL",
    "sg:address":"P Calandln 778",
    "sg:city":"Amsterdam",
    "sg:orig_category":"Kappers",
    "sg:phone":"+31 20 667 3854",
    "sg:postcode":"1060 TZ",
    "sg:province":"Noord-Holland",
    "wof:name":"Loes De Kort",
    "wof:placetype":"venue"
},
  "geometry": {"coordinates":[4.786822,52.349743],"type":"Point"}
}