{
  "type": "Feature",
  "properties": {
    "addr:full":"Floraln 49 Wervershoof Noord-Holland 1693 GJ",
    "addr:housenumber":"49",
    "addr:postcode":"1693 gj",
    "addr:street":"Floraln",
    "iso:country":"NL",
    "sg:address":"Floraln 49",
    "sg:city":"Wervershoof",
    "sg:orig_category":"Administratie- En Boekhoudkantoren",
    "sg:phone":"+31 228 582 060",
    "sg:postcode":"1693 GJ",
    "sg:province":"Noord-Holland",
    "wof:name":"Ankersmit, M",
    "wof:placetype":"venue"
},
  "geometry": {"coordinates":[5.14762,52.730137],"type":"Point"}
}