{
  "type": "Feature",
  "properties": {
    "iso:country":"NL",
    "sg:address":"Hoofdstr O 4",
    "sg:city":"Noordwolde Fr",
    "sg:orig_category":"Makelaars En Adviseurs Onroerende Goederen",
    "sg:phone":"+31 561 438 687",
    "sg:postcode":"8391 AV",
    "sg:province":"Friesland",
    "sg:website":"http://www.woudenhof.nl",
    "wof:name":"Woudenhof Bv, De",
    "wof:placetype":"venue"
},
  "geometry": {"coordinates":[6.14197,52.891758],"type":"Point"}
}