{
  "type": "Feature",
  "properties": {
    "addr:full":"Vlaardingerstr 24 Schiedam Zuid-Holland 3111 BP",
    "addr:housenumber":"24",
    "addr:postcode":"3111 bp",
    "addr:street":"Vlaardingerstr",
    "iso:country":"NL",
    "sg:address":"Vlaardingerstr 24",
    "sg:city":"Schiedam",
    "sg:orig_category":"Verzekeringen - Verzekeringskantoren",
    "sg:phone":"+31 10 426 2266",
    "sg:postcode":"3111 BP",
    "sg:province":"Zuid-Holland",
    "wof:name":"Assurantieland",
    "wof:placetype":"venue"
},
  "geometry": {"coordinates":[4.393007,51.917664],"type":"Point"}
}