{
  "type": "Feature",
  "properties": {
    "addr:full":"Slinge 447 Rotterdam Zuid-Holland 3085 ES",
    "addr:housenumber":"447",
    "addr:postcode":"3085 es",
    "addr:street":"Slinge",
    "iso:country":"NL",
    "sg:address":"Slinge 447",
    "sg:city":"Rotterdam",
    "sg:orig_category":"Discountwinkels",
    "sg:phone":"+31 10 293 7795",
    "sg:postcode":"3085 ES",
    "sg:province":"Zuid-Holland",
    "wof:name":"Zeeman Textielsupers",
    "wof:placetype":"venue"
},
  "geometry": {"coordinates":[4.486165,51.873688],"type":"Point"}
}