{
  "type": "Feature",
  "properties": {
    "addr:full":"Smeenkln 1 Amstelveen Noord-Holland 1182 GC",
    "addr:housenumber":"1",
    "addr:postcode":"1182 gc",
    "addr:street":"Smeenkln",
    "iso:country":"NL",
    "sg:address":"Smeenkln 1",
    "sg:city":"Amstelveen",
    "sg:orig_category":"Verenigingen En Stichtingen",
    "sg:phone":"+31 20 645 8141",
    "sg:postcode":"1182 GC",
    "sg:province":"Noord-Holland",
    "wof:name":"Pluspunt",
    "wof:placetype":"venue"
},
  "geometry": {"coordinates":[4.845061,52.308186],"type":"Point"}
}