{
  "type": "Feature",
  "properties": {
    "addr:full":"Herculesstraat 33 Emmeloord NL. 8303 AW",
    "addr:housenumber":"33",
    "addr:postcode":"8303 aw",
    "addr:street":"Herculesstraat;Nl.",
    "iso:country":"NL",
    "sg:address":"Herculesstraat 33",
    "sg:city":"Emmeloord",
    "sg:orig_category":"Koeriersdiensten",
    "sg:phone":"+31 527 698 393",
    "sg:postcode":"8303 AW",
    "sg:province":"NL.",
    "wof:name":"N.G. Van Der Plaat-Van Santen",
    "wof:placetype":"venue"
},
  "geometry": {"coordinates":[5.735179,52.703316],"type":"Point"}
}