{
  "type": "Feature",
  "properties": {
    "addr:full":"Koningshoek 92417 Maassluis Friesland 3144 BA",
    "addr:housenumber":"92417",
    "addr:postcode":"3144 ba",
    "addr:street":"Koningshoek",
    "iso:country":"NL",
    "sg:address":"Koningshoek 92417",
    "sg:city":"Maassluis",
    "sg:orig_category":"Babyartikelen",
    "sg:phone":"+31 10 592 8363",
    "sg:postcode":"3144 BA",
    "sg:province":"Friesland",
    "wof:name":"Duimeland Bebel",
    "wof:placetype":"venue"
},
  "geometry": {"coordinates":[4.239919,51.927914],"type":"Point"}
}