{
  "type": "Feature",
  "properties": {
    "addr:full":"Hoefkade 35 'S Gravenhage South Holland 2526 BN",
    "addr:housenumber":"35",
    "addr:postcode":"2526 bn",
    "addr:street":"Hoefkade;' S Gravenhage",
    "iso:country":"NL",
    "sg:address":"Hoefkade 35",
    "sg:city":"'S Gravenhage",
    "sg:classifiers":[
        {
            "category":"Food & Beverages",
            "subcategory":"Fruits & Vegetables",
            "type":"Retail Goods"
        }
    ],
    "sg:phone":"+31 70 388 3809",
    "sg:postcode":"2526 BN",
    "sg:province":"South Holland",
    "sg:tags":[
        "groenten"
    ],
    "wof:name":"Groentezaak Sevim",
    "wof:placetype":"venue"
},
  "geometry": {"coordinates":[4.30555,52.0681],"type":"Point"}
}