{
  "type": "Feature",
  "properties": {
    "addr:full":"Hermitage 42 Capelle A/D Ijssel Zuid-Holland 2907 NB",
    "addr:housenumber":"42;a / d",
    "addr:postcode":"2907 nb",
    "addr:street":"Hermitage",
    "iso:country":"NL",
    "sg:address":"Hermitage 42",
    "sg:city":"Capelle A/D Ijssel",
    "sg:classifiers":[
        {
            "category":"Education",
            "subcategory":"Preschool",
            "type":"Public Place"
        }
    ],
    "sg:phone":"+31 10 458 3031",
    "sg:postcode":"2907 NB",
    "sg:province":"Zuid-Holland",
    "sg:tags":[
        "kleuteronderwijs",
        "basis-"
    ],
    "wof:name":"Openbare Basisschool De Piramide",
    "wof:placetype":"venue"
},
  "geometry": {"coordinates":[4.591899,51.951111],"type":"Point"}
}