{
  "type": "Feature",
  "properties": {
    "addr:full":"Poelvoordestr 1 S Gravenpolder Zeeland 4431 BP",
    "addr:housenumber":"1",
    "addr:postcode":"4431 bp",
    "addr:street":"Poelvoordestr;S Gravenpolder Zeeland",
    "iso:country":"NL",
    "sg:address":"Poelvoordestr 1",
    "sg:city":"S Gravenpolder",
    "sg:orig_category":"Verenigingen En Stichtingen",
    "sg:phone":"+31 113 316 305",
    "sg:postcode":"4431 BP",
    "sg:province":"Zeeland",
    "wof:name":"Vluchtelingen & Nieuwkomers Borsele, Stichting Voor",
    "wof:placetype":"venue"
},
  "geometry": {"coordinates":[3.898686,51.459209],"type":"Point"}
}