{
  "type": "Feature",
  "properties": {
    "iso:country":"NL",
    "sg:address":"Graftermeerstr 61",
    "sg:city":"Hoofddorp",
    "sg:orig_category":"Schoenen",
    "sg:phone":"+31 23 562 9282",
    "sg:postcode":"2131 AB",
    "sg:province":"North Holland",
    "wof:name":"Leemans Bv",
    "wof:placetype":"venue"
},
  "geometry": {"coordinates":[4.69191,52.313858],"type":"Point"}
}