{
  "type": "Feature",
  "properties": {
    "addr:full":"Kwartelenmarkt 4 Venlo Limburg 5911 HZ",
    "addr:housenumber":"4",
    "addr:postcode":"5911 hz",
    "addr:street":"Kwartelenmarkt",
    "iso:country":"NL",
    "sg:address":"Kwartelenmarkt 4",
    "sg:city":"Venlo",
    "sg:orig_category":"Herenmodezaken",
    "sg:phone":"+31 77 351 2786",
    "sg:postcode":"5911 HZ",
    "sg:province":"Limburg",
    "wof:name":"H.M.C. Cremers V/H J. Van Can",
    "wof:placetype":"venue"
},
  "geometry": {"coordinates":[6.165217,51.368538],"type":"Point"}
}