{
  "type": "Feature",
  "properties": {
    "addr:full":"Leenderweg 66 Eindhoven Noord-Brabant 5615 AB",
    "addr:housenumber":"66",
    "addr:postcode":"5615 ab",
    "addr:street":"Leenderweg",
    "iso:country":"NL",
    "sg:address":"Leenderweg 66",
    "sg:city":"Eindhoven",
    "sg:orig_category":"Meubelzaken, Woning- And Keukeninrichting",
    "sg:phone":"+31 40 212 4365",
    "sg:postcode":"5615 AB",
    "sg:province":"Noord-Brabant",
    "wof:name":"Colonial Design",
    "wof:placetype":"venue"
},
  "geometry": {"coordinates":[5.489023,51.426212],"type":"Point"}
}