{
  "type": "Feature",
  "properties": {
    "addr:full":"Petronella Moensweg 12 Leiden Zuid-Holland 2331 DX",
    "addr:housenumber":"12",
    "addr:postcode":"2331 dx",
    "addr:street":"Petronella Moensweg",
    "iso:country":"NL",
    "sg:address":"Petronella Moensweg 12",
    "sg:city":"Leiden",
    "sg:orig_category":"Gespecialiseerde Bouw",
    "sg:phone":"+31 71 531 5086",
    "sg:postcode":"2331 DX",
    "sg:province":"Zuid-Holland",
    "wof:name":"B Pijnakker",
    "wof:placetype":"venue"
},
  "geometry": {"coordinates":[4.449957,52.154156],"type":"Point"}
}