{
  "type": "Feature",
  "properties": {
    "addr:full":"O L Vrouwestr 147 Zegge North Brabant 4735 AC",
    "addr:housenumber":"147",
    "addr:postcode":"4735 ac",
    "addr:street":"O;Zegge",
    "iso:country":"NL",
    "sg:address":"O L Vrouwestr 147",
    "sg:city":"Zegge",
    "sg:orig_category":"Autoschade- Herstelbedrijven",
    "sg:phone":"+31 165 542 609",
    "sg:postcode":"4735 AC",
    "sg:province":"North Brabant",
    "wof:name":"Leja",
    "wof:placetype":"venue"
},
  "geometry": {"coordinates":[4.516285,51.559078],"type":"Point"}
}