{
  "type": "Feature",
  "properties": {
    "iso:country":"NL",
    "sg:address":"A Blamanstr 2",
    "sg:city":"Hoofddorp",
    "sg:orig_category":"Peuterspeelzalen",
    "sg:phone":"+31 23 565 1958",
    "sg:postcode":"2135 PT",
    "sg:province":"Noord-Holland",
    "wof:name":"Pippeloentje",
    "wof:placetype":"venue"
},
  "geometry": {"coordinates":[4.665461,52.296818],"type":"Point"}
}