{
  "type": "Feature",
  "properties": {
    "addr:full":"Haagwg 392 Breda Noord-Brabant 4813 XG",
    "addr:housenumber":"392",
    "addr:postcode":"4813 xg",
    "iso:country":"NL",
    "sg:address":"Haagwg 392",
    "sg:city":"Breda",
    "sg:orig_category":"Onroerende Goederen",
    "sg:phone":"+31 76 521 7010",
    "sg:postcode":"4813 XG",
    "sg:province":"Noord-Brabant",
    "wof:name":"Franken Bv, Mariska",
    "wof:placetype":"venue"
},
  "geometry": {"coordinates":[4.744286,51.578663],"type":"Point"}
}