{
  "type": "Feature",
  "properties": {
    "addr:full":"Rembrandtstr 19 Reeuwyk South Holland 2811 XA",
    "addr:housenumber":"19",
    "addr:postcode":"2811 xa",
    "addr:street":"Rembrandtstr",
    "iso:country":"NL",
    "sg:address":"Rembrandtstr 19",
    "sg:city":"Reeuwyk",
    "sg:orig_category":"Afslankinstituten",
    "sg:phone":"+31 182 399 450",
    "sg:postcode":"2811 XA",
    "sg:province":"South Holland",
    "sg:website":"http://www.herbalife.demon.nl",
    "wof:name":"Broekman Vof",
    "wof:placetype":"venue"
},
  "geometry": {"coordinates":[4.716525,52.044102],"type":"Point"}
}