{
  "type": "Feature",
  "properties": {
    "iso:country":"NL",
    "sg:address":"Woutery 47",
    "sg:city":"Koewacht",
    "sg:orig_category":"Bierleidingreiniging",
    "sg:phone":"+31 114 361 754",
    "sg:postcode":"4576 AD",
    "sg:province":"Zeeland",
    "wof:name":"Hartog, Den",
    "wof:placetype":"venue"
},
  "geometry": {"coordinates":[3.968219,51.228291],"type":"Point"}
}