{
  "type": "Feature",
  "properties": {
    "addr:full":"Kerkweg 10 Heenvliet Zuid-Holland 3218 AH",
    "addr:housenumber":"10",
    "addr:postcode":"3218 ah",
    "addr:street":"Kerkweg",
    "iso:country":"NL",
    "sg:address":"Kerkweg 10",
    "sg:city":"Heenvliet",
    "sg:orig_category":"Fitnesscentra",
    "sg:phone":"+31 181 662 528",
    "sg:postcode":"3218 AH",
    "sg:province":"Zuid-Holland",
    "wof:name":"Kam-Lung",
    "wof:placetype":"venue"
},
  "geometry": {"coordinates":[4.244852,51.866825],"type":"Point"}
}