{
  "type": "Feature",
  "properties": {
    "addr:full":"Commanderij 61 Sneek Friesland 8604 AN",
    "addr:housenumber":"61",
    "addr:postcode":"8604 an",
    "addr:street":"Commanderij",
    "iso:country":"NL",
    "sg:address":"Commanderij 61",
    "sg:city":"Sneek",
    "sg:orig_category":"Meubelreparatie And -Restauratie",
    "sg:phone":"+31 515 417 791",
    "sg:postcode":"8604 AN",
    "sg:province":"Friesland",
    "wof:name":"A.J. Hogenes",
    "wof:placetype":"venue"
},
  "geometry": {"coordinates":[5.676605,53.041695],"type":"Point"}
}