{
  "type": "Feature",
  "properties": {
    "addr:full":"Leyparkwg 55 Tilburg North Brabant 5022 AB",
    "addr:housenumber":"55",
    "addr:postcode":"5022 ab",
    "addr:street":"Leyparkwg",
    "iso:country":"NL",
    "sg:address":"Leyparkwg 55",
    "sg:city":"Tilburg",
    "sg:orig_category":"Administratie- En Boekhoudkantoren",
    "sg:phone":"+31 13 580 0378",
    "sg:postcode":"5022 AB",
    "sg:province":"North Brabant",
    "wof:name":"Averta",
    "wof:placetype":"venue"
},
  "geometry": {"coordinates":[5.09431,51.541271],"type":"Point"}
}