{
  "type": "Feature",
  "properties": {
    "addr:full":"M Veningastr 89 Hoogezand Groningen 9601 KD",
    "addr:housenumber":"89",
    "addr:postcode":"9601 kd",
    "iso:country":"NL",
    "sg:address":"M Veningastr 89",
    "sg:city":"Hoogezand",
    "sg:orig_category":"Kappers",
    "sg:phone":"+31 598 393 584",
    "sg:postcode":"9601 KD",
    "sg:province":"Groningen",
    "wof:name":"Rijkens",
    "wof:placetype":"venue"
},
  "geometry": {"coordinates":[6.749707,53.163601],"type":"Point"}
}