{
  "type": "Feature",
  "properties": {
    "addr:full":"Vulcanuswg 267 Delft Zuid-Holland 2624 AV",
    "addr:housenumber":"267",
    "addr:postcode":"delft;2624 av",
    "iso:country":"NL",
    "sg:address":"Vulcanuswg 267",
    "sg:city":"Delft",
    "sg:orig_category":"Kinderopvang",
    "sg:phone":"+31 15 256 9994",
    "sg:postcode":"2624 AV",
    "sg:province":"Zuid-Holland",
    "wof:name":"Knotz",
    "wof:placetype":"venue"
},
  "geometry": {"coordinates":[4.360835,51.995819],"type":"Point"}
}