{
  "type": "Feature",
  "properties": {
    "iso:country":"NL",
    "sg:address":"Bosschewg 51",
    "sg:city":"Boxtel",
    "sg:orig_category":"Kaarsen - Fabrieken En Groothandel",
    "sg:phone":"+31 411 611 933",
    "sg:postcode":"5281 AH",
    "sg:province":"Noord-Brabant",
    "wof:name":"Aarle Bv, Jan Van",
    "wof:placetype":"venue"
},
  "geometry": {"coordinates":[5.3241128922,51.5953674316],"type":"Point"}
}