{
  "type": "Feature",
  "properties": {
    "addr:full":"Kotterstraat 47 Tilburg North Brabant 5017 CZ",
    "addr:housenumber":"47",
    "addr:postcode":"5017",
    "addr:street":"Kotterstraat",
    "iso:country":"NL",
    "sg:address":"Kotterstraat 47",
    "sg:city":"Tilburg",
    "sg:orig_category":"Binnenhuisarchitecten",
    "sg:phone":"+31 13 544 5891",
    "sg:postcode":"5017 CZ",
    "sg:province":"North Brabant",
    "wof:name":"S.W. Van Bussel",
    "wof:placetype":"venue"
},
  "geometry": {"coordinates":[5.094722,51.554447],"type":"Point"}
}