{
  "type": "Feature",
  "properties": {
    "addr:full":"Koningin Emmaweg 1 Slootdorp North Holland 1774 BE",
    "addr:housenumber":"1",
    "addr:postcode":"1774",
    "addr:street":"Koningin Emmaweg",
    "iso:country":"NL",
    "sg:address":"Koningin Emmaweg 1",
    "sg:city":"Slootdorp",
    "sg:orig_category":"Meubelzaken, Woning- And Keukeninrichting",
    "sg:phone":"+31 227 581 201",
    "sg:postcode":"1774 BE",
    "sg:province":"North Holland",
    "wof:name":"Van Der Kooi'S Woninginrichting En Textiel",
    "wof:placetype":"venue"
},
  "geometry": {"coordinates":[4.968019,52.845539],"type":"Point"}
}