{
  "type": "Feature",
  "properties": {
    "addr:full":"Tiendwg 14 Naaldwyk Zuid-Holland 2671 SB",
    "addr:housenumber":"14",
    "addr:postcode":"2671 sb",
    "addr:street":"Tiendwg",
    "iso:country":"NL",
    "sg:address":"Tiendwg 14",
    "sg:city":"Naaldwyk",
    "sg:orig_category":"Verzekeringen - Verzekeringskantoren",
    "sg:phone":"+31 174 624 298",
    "sg:postcode":"2671 SB",
    "sg:province":"Zuid-Holland",
    "wof:name":"Attentiv-P Berghegen Bv",
    "wof:placetype":"venue"
},
  "geometry": {"coordinates":[4.220518,51.99115],"type":"Point"}
}