{
  "type": "Feature",
  "properties": {
    "iso:country":"NL",
    "sg:address":"Kraayenberg 9148",
    "sg:city":"Wijchen",
    "sg:orig_category":"Verzekeringen",
    "sg:phone":"+31 24 645 5544",
    "sg:postcode":"6601 PN",
    "sg:province":"Friesland",
    "wof:name":"Veka Verzekeringen",
    "wof:placetype":"venue"
},
  "geometry": {"coordinates":[5.73085,51.808395],"type":"Point"}
}