{
  "type": "Feature",
  "properties": {
    "iso:country":"NL",
    "sg:address":"Bilderbeekstr 29",
    "sg:city":"Boxmeer",
    "sg:orig_category":"Pensioenen",
    "sg:phone":"+31 485 572 129",
    "sg:postcode":"5831 CW",
    "sg:province":"North Brabant",
    "sg:website":"http://www.lambertblonk.nl",
    "wof:name":"Blonk, Lambert",
    "wof:placetype":"venue"
},
  "geometry": {"coordinates":[5.943088,51.645412],"type":"Point"}
}