{
  "type": "Feature",
  "properties": {
    "addr:full":"Burg Panisstr 15 Haaren Noord-Brabant 5076 GC",
    "addr:housenumber":"15 haaren",
    "addr:postcode":"5076 gc",
    "addr:street":"Burg",
    "iso:country":"NL",
    "sg:address":"Burg Panisstr 15",
    "sg:city":"Haaren",
    "sg:orig_category":"Organisatiebureaus",
    "sg:phone":"+31 411 623 700",
    "sg:postcode":"5076 GC",
    "sg:province":"Noord-Brabant",
    "wof:name":"Verheij Bv",
    "wof:placetype":"venue"
},
  "geometry": {"coordinates":[-95.9960784912,34.5803718567],"type":"Point"}
}