{
  "type": "Feature",
  "properties": {
    "addr:full":"Stationspln 3B Rosmalen Noord-Brabant 5241 GN",
    "addr:housenumber":"3b",
    "addr:postcode":"5241 gn",
    "addr:street":"Stationspln",
    "iso:country":"NL",
    "sg:address":"Stationspln 3B",
    "sg:city":"Rosmalen",
    "sg:orig_category":"Verzekeringen - Verzekeringskantoren",
    "sg:phone":"+31 73 521 4576",
    "sg:postcode":"5241 GN",
    "sg:province":"Noord-Brabant",
    "wof:name":"Guijt",
    "wof:placetype":"venue"
},
  "geometry": {"coordinates":[5.368799,51.715931],"type":"Point"}
}