{
  "type": "Feature",
  "properties": {
    "addr:full":"Dorpstr 142 Heythuysen Limburg 6093 ED",
    "addr:housenumber":"142",
    "addr:postcode":"6093 ed",
    "iso:country":"NL",
    "sg:address":"Dorpstr 142",
    "sg:city":"Heythuysen",
    "sg:orig_category":"Fietsen En Bromfietsen",
    "sg:phone":"+31 475 491 217",
    "sg:postcode":"6093 ED",
    "sg:province":"Limburg",
    "wof:name":"Versteegen En Zn, Fa F H",
    "wof:placetype":"venue"
},
  "geometry": {"coordinates":[5.902023,51.249859],"type":"Point"}
}