{
  "type": "Feature",
  "properties": {
    "addr:full":"Sonderenstraat 22 Haaksbergen Overijssel 7481 HC",
    "addr:housenumber":"22",
    "addr:postcode":"7481 hc",
    "addr:street":"Sonderenstraat",
    "iso:country":"NL",
    "sg:address":"Sonderenstraat 22",
    "sg:city":"Haaksbergen",
    "sg:classifiers":[
        {
            "category":"Bakery",
            "type":"Food & Drink"
        }
    ],
    "sg:phone":"+31 53 572 1382",
    "sg:postcode":"7481 HC",
    "sg:province":"Overijssel",
    "sg:tags":[
        "brood",
        "banket"
    ],
    "wof:name":"J.B.H. Velthof",
    "wof:placetype":"venue"
},
  "geometry": {"coordinates":[6.736457,52.150974],"type":"Point"}
}