{
  "type": "Feature",
  "properties": {
    "iso:country":"NL",
    "sg:address":"Engelsewg 202",
    "sg:city":"Helmond",
    "sg:orig_category":"Keukens",
    "sg:phone":"+31 492 545 535",
    "sg:postcode":"5705 AJ",
    "sg:province":"Noord-Brabant",
    "sg:website":"http://www.grando.nl",
    "wof:name":"Grando",
    "wof:placetype":"venue"
},
  "geometry": {"coordinates":[5.675228,51.473209],"type":"Point"}
}