{
  "type": "Feature",
  "properties": {
    "addr:full":"Gastelsewg 46 Roosendaal Noord-Brabant 4702 TB",
    "addr:housenumber":"46",
    "addr:postcode":"4702 tb",
    "addr:street":"Gastelsewg",
    "iso:country":"NL",
    "sg:address":"Gastelsewg 46",
    "sg:city":"Roosendaal",
    "sg:orig_category":"Plastificeren",
    "sg:phone":"+31 6 20608692",
    "sg:postcode":"4702 TB",
    "sg:province":"Noord-Brabant",
    "wof:name":"Lamination Services Roosendaal",
    "wof:placetype":"venue"
},
  "geometry": {"coordinates":[4.474308,51.543579],"type":"Point"}
}