{
  "type": "Feature",
  "properties": {
    "iso:country":"NL",
    "sg:address":"V Schaffel Plnts 4",
    "sg:city":"Amsterdam",
    "sg:classifiers":[
        {
            "category":"Wholesale",
            "subcategory":"Meat",
            "type":"Manufacturing & Wholesale Goods"
        }
    ],
    "sg:phone":"+31 20 681 1605",
    "sg:postcode":"1061 DN",
    "sg:province":"North Holland",
    "sg:tags":[
        "bode-",
        "en",
        "lijndiensten"
    ],
    "wof:name":"Ouderenvervoer A'Dam Oud West, Sticht",
    "wof:placetype":"venue"
},
  "geometry": {"coordinates":[4.83934,52.374611],"type":"Point"}
}