{
  "type": "Feature",
  "properties": {
    "addr:full":"Sportlaan 5 Otterlo Gelderland 6731 BD",
    "addr:housenumber":"5",
    "addr:postcode":"6731 bd",
    "addr:street":"Sportlaan;Gelderland",
    "iso:country":"NL",
    "sg:address":"Sportlaan 5",
    "sg:city":"Otterlo",
    "sg:classifiers":[
        {
            "category":"Education",
            "subcategory":"Preschool",
            "type":"Public Place"
        }
    ],
    "sg:phone":"+31 318 592 246",
    "sg:postcode":"6731 BD",
    "sg:province":"Gelderland",
    "sg:tags":[
        "kleuteronderwijs",
        "basis-"
    ],
    "wof:name":"De Heidehummel",
    "wof:placetype":"venue"
},
  "geometry": {"coordinates":[5.774229,52.101006],"type":"Point"}
}