{
  "type": "Feature",
  "properties": {
    "addr:full":"Veestraat 34 Helmond Noord-Brabant 5701 RD",
    "addr:housenumber":"34",
    "addr:postcode":"5701 rd",
    "addr:street":"Veestraat",
    "iso:country":"NL",
    "sg:address":"Veestraat 34",
    "sg:city":"Helmond",
    "sg:orig_category":"Verlichting And Huishoudartikelen",
    "sg:phone":"+31 492 599 056",
    "sg:postcode":"5701 RD",
    "sg:province":"Noord-Brabant",
    "wof:name":"Xenos Bv",
    "wof:placetype":"venue"
},
  "geometry": {"coordinates":[5.652746,51.479118],"type":"Point"}
}