{
  "type": "Feature",
  "properties": {
    "iso:country":"NL",
    "sg:address":"Goereesestraat 10",
    "sg:city":"Rotterdam",
    "sg:classifiers":[
        {
            "category":"Professional",
            "subcategory":"Accounting & Tax Preparation",
            "type":"Services"
        }
    ],
    "sg:phone":"+31 10 210 1436",
    "sg:postcode":"3083 DJ",
    "sg:province":"Zuid-Holland",
    "sg:tags":[
        "accountant"
    ],
    "wof:name":"Administratiekantoor H Houwers",
    "wof:placetype":"venue"
},
  "geometry": {"coordinates":[4.487399,51.888939],"type":"Point"}
}