{
  "type": "Feature",
  "properties": {
    "addr:full":"Industriewg 2 Bladel North Brabant 5531 AD",
    "addr:housenumber":"2",
    "addr:postcode":"5531 ad",
    "addr:street":"Industriewg",
    "iso:country":"NL",
    "sg:address":"Industriewg 2",
    "sg:city":"Bladel",
    "sg:orig_category":"Metaalbewerking",
    "sg:phone":"+31 497 385 898",
    "sg:postcode":"5531 AD",
    "sg:province":"North Brabant",
    "wof:name":"Fransen Bv",
    "wof:placetype":"venue"
},
  "geometry": {"coordinates":[5.20277,51.361622],"type":"Point"}
}