{
  "type": "Feature",
  "properties": {
    "addr:full":"Dreef 7 Hengelo Gld Gelderland 7255 WV",
    "addr:housenumber":"7",
    "addr:postcode":"7255 wv",
    "addr:street":"Dreef",
    "iso:country":"NL",
    "sg:address":"Dreef 7",
    "sg:city":"Hengelo Gld",
    "sg:orig_category":"Autolakken",
    "sg:phone":"+31 575 463 251",
    "sg:postcode":"7255 WV",
    "sg:province":"Gelderland",
    "sg:website":"http://www.dbflex.nl",
    "wof:name":"Dbflex",
    "wof:placetype":"venue"
},
  "geometry": {"coordinates":[6.310447,52.05249],"type":"Point"}
}