{
  "type": "Feature",
  "properties": {
    "iso:country":"NL",
    "sg:address":"Wolvenstr 5",
    "sg:city":"Amsterdam",
    "sg:orig_category":"Kappers",
    "sg:phone":"+31 20 427 1651",
    "sg:postcode":"1016 EM",
    "sg:province":"Noord-Holland",
    "wof:name":"Souk, Le",
    "wof:placetype":"venue"
},
  "geometry": {"coordinates":[4.886226,52.370171],"type":"Point"}
}