{
  "type": "Feature",
  "properties": {
    "addr:full":"Ged Veert 203 St Pancras Noord-Holland 1834 DC",
    "addr:housenumber":"203",
    "addr:postcode":"1834",
    "addr:street":"Ged Veert",
    "iso:country":"NL",
    "sg:address":"Ged Veert 203",
    "sg:city":"St Pancras",
    "sg:orig_category":"Leesportefeuilles",
    "sg:phone":"+31 72 564 2910",
    "sg:postcode":"1834 DC",
    "sg:province":"Noord-Holland",
    "wof:name":"Leeskring, De",
    "wof:placetype":"venue"
},
  "geometry": {"coordinates":[4.777001,52.65387],"type":"Point"}
}