{
  "type": "Feature",
  "properties": {
    "addr:full":"Ceintuurbaan 77 Amsterdam North Holland 1072 EW",
    "addr:housenumber":"77",
    "addr:postcode":"1072 ew",
    "addr:street":"Ceintuurbaan",
    "iso:country":"NL",
    "sg:address":"Ceintuurbaan 77",
    "sg:city":"Amsterdam",
    "sg:orig_category":"Huishoudapparatuur, Televisies And Radio'S",
    "sg:phone":"+31 20 671 6251",
    "sg:postcode":"1072 EW",
    "sg:province":"North Holland",
    "wof:name":"Modern Electronics",
    "wof:placetype":"venue"
},
  "geometry": {"coordinates":[4.890303,52.352829],"type":"Point"}
}