{
  "type": "Feature",
  "properties": {
    "iso:country":"NL",
    "sg:address":"Mezenbergerweg 5",
    "sg:city":"Doornspijk",
    "sg:orig_category":"Verhuur Diversen",
    "sg:phone":"+31 525 661 368",
    "sg:postcode":"8085 ST",
    "sg:province":"Gelderland",
    "wof:name":"Handelsonderneming Zegers",
    "wof:placetype":"venue"
},
  "geometry": {"coordinates":[5.796991,52.405178],"type":"Point"}
}