{
  "type": "Feature",
  "properties": {
    "addr:full":"Amsteldijk Noord 42 Amstelveen North Holland 1184 TD",
    "addr:housenumber":"42",
    "addr:postcode":"1184 td",
    "addr:street":"Amsteldijk Noord",
    "iso:country":"NL",
    "sg:address":"Amsteldijk Noord 42",
    "sg:city":"Amstelveen",
    "sg:orig_category":"Organisaties And Verenigingen",
    "sg:phone":"+31 20 496 9333",
    "sg:postcode":"1184 TD",
    "sg:province":"North Holland",
    "wof:name":"Stichting Koninklijk Nederlands Geleidehonden Fond",
    "wof:placetype":"venue"
},
  "geometry": {"coordinates":[4.9029669762,52.3036231995],"type":"Point"}
}