{
  "type": "Feature",
  "properties": {
    "addr:full":"Zr Hennekepln 47 Rotterdam Zuid-Holland 3033 BW",
    "addr:housenumber":"47",
    "addr:postcode":"3033 bw",
    "iso:country":"NL",
    "sg:address":"Zr Hennekepln 47",
    "sg:city":"Rotterdam",
    "sg:orig_category":"Architecten En Architectenbureaus",
    "sg:phone":"+31 10 243 0144",
    "sg:postcode":"3033 BW",
    "sg:province":"Zuid-Holland",
    "wof:name":"Schut & Kolova",
    "wof:placetype":"venue"
},
  "geometry": {"coordinates":[4.474658,51.92675],"type":"Point"}
}