{
  "type": "Feature",
  "properties": {
    "addr:full":"Blekerstr 30 Almere Flevoland 1315 AJ",
    "addr:housenumber":"30",
    "addr:postcode":"1315 aj",
    "addr:street":"Blekerstr;Flevoland",
    "iso:country":"NL",
    "sg:address":"Blekerstr 30",
    "sg:city":"Almere",
    "sg:orig_category":"Biljartzalen",
    "sg:phone":"+31 36 534 4084",
    "sg:postcode":"1315 AJ",
    "sg:province":"Flevoland",
    "wof:name":"Almere Stad",
    "wof:placetype":"venue"
},
  "geometry": {"coordinates":[5.215294,52.368912],"type":"Point"}
}