{
  "type": "Feature",
  "properties": {
    "addr:full":"Polanenhof 7 Ryen North Brabant 5121 BL",
    "addr:housenumber":"7",
    "addr:postcode":"5121 bl",
    "addr:street":"Polanenhof",
    "iso:country":"NL",
    "sg:address":"Polanenhof 7",
    "sg:city":"Ryen",
    "sg:orig_category":"Schoonheidsinstituten",
    "sg:phone":"+31 161 223 895",
    "sg:postcode":"5121 BL",
    "sg:province":"North Brabant",
    "wof:name":"Faes-Hermes",
    "wof:placetype":"venue"
},
  "geometry": {"coordinates":[4.9197,51.588017],"type":"Point"}
}