{
  "type": "Feature",
  "properties": {
    "addr:full":"Burg De Bruineln 27 Zwyndrecht Zuid-Holland 3331 AC",
    "addr:housenumber":"27",
    "addr:postcode":"3331 ac",
    "iso:country":"NL",
    "sg:address":"Burg De Bruineln 27",
    "sg:city":"Zwyndrecht",
    "sg:orig_category":"Kappers",
    "sg:phone":"+31 78 619 5548",
    "sg:postcode":"3331 AC",
    "sg:province":"Zuid-Holland",
    "sg:website":"http://www.janbakelaar.nl",
    "wof:name":"Bakelaar, Kapsalon & Nagelstudio Jan",
    "wof:placetype":"venue"
},
  "geometry": {"coordinates":[4.6407299042,51.8207015991],"type":"Point"}
}