{
  "type": "Feature",
  "properties": {
    "addr:full":"Hoofdwg 28 Eelde Provincie Drenthe 9761 EH",
    "addr:housenumber":"28",
    "addr:postcode":"9761 eh",
    "addr:street":"Hoofdwg;Provincie Drenthe",
    "iso:country":"NL",
    "sg:address":"Hoofdwg 28",
    "sg:city":"Eelde",
    "sg:orig_category":"Bloemen En Planten",
    "sg:phone":"+31 50 309 4914",
    "sg:postcode":"9761 EH",
    "sg:province":"Provincie Drenthe",
    "wof:name":"Tip, De",
    "wof:placetype":"venue"
},
  "geometry": {"coordinates":[6.566252,53.128387],"type":"Point"}
}