{
  "type": "Feature",
  "properties": {
    "addr:full":"Brugstr 2A Roermond Limburg 6041 ER",
    "addr:housenumber":"2a",
    "addr:postcode":"6041 er",
    "addr:street":"Brugstr",
    "iso:country":"NL",
    "sg:address":"Brugstr 2A",
    "sg:city":"Roermond",
    "sg:orig_category":"Schoenen",
    "sg:phone":"+31 475 334 834",
    "sg:postcode":"6041 ER",
    "sg:province":"Limburg",
    "wof:name":"Handmates",
    "wof:placetype":"venue"
},
  "geometry": {"coordinates":[5.985158,51.194637],"type":"Point"}
}