{
  "type": "Feature",
  "properties": {
    "addr:full":"Waardjeswg 71 Heusden Gem Asten North Brabant 5725 TB",
    "addr:housenumber":"71",
    "addr:postcode":"5725 tb",
    "addr:street":"Waardjeswg",
    "iso:country":"NL",
    "sg:address":"Waardjeswg 71",
    "sg:city":"Heusden Gem Asten",
    "sg:orig_category":"Administratie- En Boekhoudkantoren",
    "sg:phone":"+31 493 670 111",
    "sg:postcode":"5725 TB",
    "sg:province":"North Brabant",
    "wof:name":"Awa",
    "wof:placetype":"venue"
},
  "geometry": {"coordinates":[5.74556,51.384411],"type":"Point"}
}