{
  "type": "Feature",
  "properties": {
    "addr:full":"Dorpsstraat 57 Elst Gld Gelderland 6661 EG",
    "addr:housenumber":"57",
    "addr:postcode":"6661 eg",
    "addr:street":"Dorpsstraat;Gld Gelderland",
    "iso:country":"NL",
    "sg:address":"Dorpsstraat 57",
    "sg:city":"Elst Gld",
    "sg:orig_category":"Werving And Selectie Van Tijdelijk Personeel And Uitzendkantoren",
    "sg:phone":"+31 481 350 170",
    "sg:postcode":"6661 EG",
    "sg:province":"Gelderland",
    "wof:name":"Adecco",
    "wof:placetype":"venue"
},
  "geometry": {"coordinates":[5.846323967,51.9185638428],"type":"Point"}
}