{
  "type": "Feature",
  "properties": {
    "iso:country":"NL",
    "sg:address":"Basicwg 7",
    "sg:city":"Amersfoort",
    "sg:orig_category":"Onroerende Goederen",
    "sg:phone":"+31 33 456 2363",
    "sg:postcode":"3821 BR",
    "sg:province":"Utrecht",
    "wof:name":"Schipper Bosch",
    "wof:placetype":"venue"
},
  "geometry": {"coordinates":[5.421731,52.176495],"type":"Point"}
}