{
  "type": "Feature",
  "properties": {
    "addr:full":"Rokin 150Bg Amsterdam Noord-Holland 1012 LE",
    "addr:housenumber":"150bg",
    "addr:postcode":"1012 le",
    "addr:street":"Rokin",
    "iso:country":"NL",
    "sg:address":"Rokin 150Bg",
    "sg:city":"Amsterdam",
    "sg:classifiers":[
        {
            "category":"Shopping",
            "subcategory":"Gifts & Souvenirs",
            "type":"Retail Goods"
        }
    ],
    "sg:phone":"+31 20 623 7095",
    "sg:postcode":"1012 LE",
    "sg:province":"Noord-Holland",
    "sg:tags":[
        "geschenken"
    ],
    "wof:name":"Holland Souvenirs Shopping",
    "wof:placetype":"venue"
},
  "geometry": {"coordinates":[4.892677,52.367924],"type":"Point"}
}