{
  "type": "Feature",
  "properties": {
    "iso:country":"NL",
    "sg:address":"Waterigewg 36",
    "sg:city":"Zeist",
    "sg:orig_category":"Adviesbureaus Bedrijfsorganisatie",
    "sg:phone":"+31 30 691 8601",
    "sg:postcode":"3703 CP",
    "sg:province":"Utrecht",
    "wof:name":"Re-Part Bv",
    "wof:placetype":"venue"
},
  "geometry": {"coordinates":[5.231619,52.079563],"type":"Point"}
}