{
  "type": "Feature",
  "properties": {
    "addr:full":"Lieshoutseweg 7 Aarle Rixtel Noord-Brabant 5735 BA",
    "addr:housenumber":"7",
    "addr:postcode":"5735 ba",
    "addr:street":"Lieshoutseweg",
    "iso:country":"NL",
    "sg:address":"Lieshoutseweg 7",
    "sg:city":"Aarle Rixtel",
    "sg:orig_category":"Zuivelproducten",
    "sg:phone":"+31 492 381 935",
    "sg:postcode":"5735 BA",
    "sg:province":"Noord-Brabant",
    "wof:name":"Zuivelhandel Thijs Van Rosmalen",
    "wof:placetype":"venue"
},
  "geometry": {"coordinates":[5.634529,51.508919],"type":"Point"}
}