{
  "type": "Feature",
  "properties": {
    "addr:full":"Kast Schaloenstr 37 Maastricht Limburg 6222 TN",
    "addr:housenumber":"37",
    "addr:postcode":"6222",
    "iso:country":"NL",
    "sg:address":"Kast Schaloenstr 37",
    "sg:city":"Maastricht",
    "sg:orig_category":"Woninginrichting",
    "sg:phone":"+31 6 11308252",
    "sg:postcode":"6222 TN",
    "sg:province":"Limburg",
    "wof:name":"Schepers, Ruud",
    "wof:placetype":"venue"
},
  "geometry": {"coordinates":[5.7161488533,50.8640441895],"type":"Point"}
}