{
  "type": "Feature",
  "properties": {
    "addr:full":"Hg Zyde 62 Bavel North Brabant 4854 AJ",
    "addr:housenumber":"62",
    "addr:postcode":"4854 aj",
    "iso:country":"NL",
    "sg:address":"Hg Zyde 62",
    "sg:city":"Bavel",
    "sg:classifiers":[
        {
            "category":"Food & Beverages",
            "subcategory":"Fruits & Vegetables",
            "type":"Retail Goods"
        }
    ],
    "sg:phone":"+31 161 433 612",
    "sg:postcode":"4854 AJ",
    "sg:province":"North Brabant",
    "sg:tags":[
        "en",
        "groenten"
    ],
    "wof:name":"Beekers Vof, J F",
    "wof:placetype":"venue"
},
  "geometry": {"coordinates":[4.829695,51.565334],"type":"Point"}
}