{
  "type": "Feature",
  "properties": {
    "addr:full":"Emmastr 44 Poortugaal Zuid-Holland 3171 AH",
    "addr:housenumber":"44",
    "addr:postcode":"3171 ah",
    "addr:street":"Emmastr",
    "iso:country":"NL",
    "sg:address":"Emmastr 44",
    "sg:city":"Poortugaal",
    "sg:orig_category":"Kinderopvang",
    "sg:phone":"+31 10 501 0444",
    "sg:postcode":"3171 AH",
    "sg:province":"Zuid-Holland",
    "wof:name":"Bon Bon, Sticht",
    "wof:placetype":"venue"
},
  "geometry": {"coordinates":[4.393017,51.856911],"type":"Point"}
}