{
  "type": "Feature",
  "properties": {
    "iso:country":"NL",
    "sg:address":"Uitvaltij 2",
    "sg:city":"Noordwijk Zh",
    "sg:classifiers":[
        {
            "category":"Education",
            "subcategory":"Preschool",
            "type":"Public Place"
        }
    ],
    "sg:phone":"+31 71 361 5646",
    "sg:postcode":"2201 WL",
    "sg:province":"South Holland",
    "sg:tags":[
        "kleuteronderwijs",
        "basis-"
    ],
    "wof:name":"De Jutter Openbare Basisschool",
    "wof:placetype":"venue"
},
  "geometry": {"coordinates":[4.437227,52.228298],"type":"Point"}
}