{
  "type": "Feature",
  "properties": {
    "iso:country":"NL",
    "sg:address":"Postbus 30210",
    "sg:city":"Almere",
    "sg:orig_category":"Webdesign Bureaus",
    "sg:phone":"+31 36 844 2723",
    "sg:postcode":"1303 AE",
    "sg:province":"NL.",
    "sg:website":"http://www.bouwie.nl",
    "wof:name":"Bouwie Media Creations",
    "wof:placetype":"venue"
},
  "geometry": {"coordinates":[5.2180199623,52.3722114563],"type":"Point"}
}