{
  "type": "Feature",
  "properties": {
    "addr:full":"Doorzwin 4214 Den Helder North Holland 1788 NS",
    "addr:housenumber":"4214",
    "addr:postcode":"1788 ns",
    "addr:street":"Doorzwin",
    "iso:country":"NL",
    "sg:address":"Doorzwin 4214",
    "sg:city":"Den Helder",
    "sg:orig_category":"Organisatiebureaus",
    "sg:phone":"+31 223 690 533",
    "sg:postcode":"1788 NS",
    "sg:province":"North Holland",
    "wof:name":"Quick Quality",
    "wof:placetype":"venue"
},
  "geometry": {"coordinates":[4.7474431992,52.8874549866],"type":"Point"}
}