{
  "type": "Feature",
  "properties": {
    "addr:full":"Zilverstr 22 S Gravenhage Zuid-Holland 2544 ER",
    "addr:housenumber":"22;gravenhage",
    "addr:postcode":"2544 er",
    "addr:street":"Zilverstr;S",
    "iso:country":"NL",
    "sg:address":"Zilverstr 22",
    "sg:city":"S Gravenhage",
    "sg:orig_category":"Metaaldraaierijen",
    "sg:phone":"+31 70 329 5877",
    "sg:postcode":"2544 ER",
    "sg:province":"Zuid-Holland",
    "sg:website":"http://www.supplierexpert.nl",
    "wof:name":"Supplierexpert Bv",
    "wof:placetype":"venue"
},
  "geometry": {"coordinates":[4.25157,52.039551],"type":"Point"}
}