{
  "type": "Feature",
  "properties": {
    "addr:full":"Maassluiseweg 1 Maasland Zuid-Holland 3155 EJ",
    "addr:housenumber":"1",
    "addr:postcode":"3155 ej",
    "addr:street":"Maassluiseweg",
    "iso:country":"NL",
    "sg:address":"Maassluiseweg 1",
    "sg:city":"Maasland",
    "sg:orig_category":"Metaalafval, Schrootrecycling And Sloperijen",
    "sg:phone":"+31 10 592 1555",
    "sg:postcode":"3155 EJ",
    "sg:province":"Zuid-Holland",
    "wof:name":"Autosloperij Bandenservice N Boekestijn",
    "wof:placetype":"venue"
},
  "geometry": {"coordinates":[4.269589,51.927193],"type":"Point"}
}