{
  "type": "Feature",
  "properties": {
    "addr:full":"A Hofmanwg 5A Haarlem Noord-Holland 2031 BH",
    "addr:housenumber":"5a",
    "addr:postcode":"2031 bh",
    "iso:country":"NL",
    "sg:address":"A Hofmanwg 5A",
    "sg:city":"Haarlem",
    "sg:orig_category":"Product-Promotie",
    "sg:phone":"+31 23 750 5125",
    "sg:postcode":"2031 BH",
    "sg:province":"Noord-Holland",
    "wof:name":"2Promote",
    "wof:placetype":"venue"
},
  "geometry": {"coordinates":[4.666949,52.392616],"type":"Point"}
}