{
  "type": "Feature",
  "properties": {
    "addr:full":"J Cremerstr 1 Tiel Gelderland 4001 XM",
    "addr:housenumber":"1",
    "addr:postcode":"4001 xm",
    "addr:street":"Gelderland",
    "iso:country":"NL",
    "sg:address":"J Cremerstr 1",
    "sg:city":"Tiel",
    "sg:orig_category":"Scholen Voor Algemeen Voortgezet Onderwijs",
    "sg:phone":"+31 344 619 125",
    "sg:postcode":"4001 XM",
    "sg:province":"Gelderland",
    "wof:name":"Roc Educatiefcentr Tiel",
    "wof:placetype":"venue"
},
  "geometry": {"coordinates":[5.428471,51.89043],"type":"Point"}
}