{
  "type": "Feature",
  "properties": {
    "iso:country":"NL",
    "sg:address":"Klaverbeemd 40",
    "sg:city":"Terheyden",
    "sg:orig_category":"Administratie- En Boekhoudkantoren",
    "sg:phone":"+31 76 593 8206",
    "sg:postcode":"4844 RK",
    "sg:province":"Noord-Brabant",
    "wof:name":"Gemar Ned",
    "wof:placetype":"venue"
},
  "geometry": {"coordinates":[4.756204,51.644821],"type":"Point"}
}