{
  "type": "Feature",
  "properties": {
    "addr:full":"Spoorstraat 24 Dorst North Brabant 4849 AT",
    "addr:housenumber":"24",
    "addr:postcode":"4849",
    "addr:street":"Spoorstraat",
    "iso:country":"NL",
    "sg:address":"Spoorstraat 24",
    "sg:city":"Dorst",
    "sg:orig_category":"Kappers",
    "sg:phone":"+31 161 412 037",
    "sg:postcode":"4849 AT",
    "sg:province":"North Brabant",
    "wof:name":"Elly'S Hair Line",
    "wof:placetype":"venue"
},
  "geometry": {"coordinates":[4.8608360291,51.5931816101],"type":"Point"}
}