{
  "type": "Feature",
  "properties": {
    "addr:full":"Texelweg 152 Amsterdam Noord-Holland 1025 MB",
    "addr:housenumber":"152",
    "addr:postcode":"1025 mb",
    "addr:street":"Texelweg",
    "iso:country":"NL",
    "sg:address":"Texelweg 152",
    "sg:city":"Amsterdam",
    "sg:orig_category":"Diverse Consumentenartikelen Gh",
    "sg:phone":"+31 20 636 2692",
    "sg:postcode":"1025 MB",
    "sg:province":"Noord-Holland",
    "wof:name":"Badr-El Din Import-Export-Trading",
    "wof:placetype":"venue"
},
  "geometry": {"coordinates":[4.925501,52.394665],"type":"Point"}
}