{
  "type": "Feature",
  "properties": {
    "addr:full":"Ringoven 37 Arnhem Gelderland 6826 TP",
    "addr:housenumber":"37",
    "addr:postcode":"6826 tp",
    "addr:street":"Ringoven",
    "iso:country":"NL",
    "sg:address":"Ringoven 37",
    "sg:city":"Arnhem",
    "sg:orig_category":"Elektrotechnische Installatiebureaus",
    "sg:phone":"+31 26 369 2911",
    "sg:postcode":"6826 TP",
    "sg:province":"Gelderland",
    "wof:name":"Gti Bv",
    "wof:placetype":"venue"
},
  "geometry": {"coordinates":[5.957391,51.974468],"type":"Point"}
}