{
  "type": "Feature",
  "properties": {
    "iso:country":"NL",
    "sg:address":"K Boschstr 8",
    "sg:city":"Breda",
    "sg:orig_category":"Verenigingen En Stichtingen",
    "sg:phone":"+31 76 514 7821",
    "sg:postcode":"4811 ES",
    "sg:province":"Noord-Brabant",
    "wof:name":"Islamitische Sticht Yeni Breda",
    "wof:placetype":"venue"
},
  "geometry": {"coordinates":[4.784154,51.591541],"type":"Point"}
}