{
  "type": "Feature",
  "properties": {
    "addr:full":"Stationswg 51 Marienberg NL.08 7692 AB",
    "addr:housenumber":"51;nl.08",
    "addr:postcode":"7692 ab",
    "addr:street":"Stationswg",
    "iso:country":"NL",
    "sg:address":"Stationswg 51",
    "sg:city":"Marienberg",
    "sg:orig_category":"Zonnebank- En Solariumcentra",
    "sg:phone":"+31 523 251 166",
    "sg:postcode":"7692 AB",
    "sg:province":"NL.08",
    "wof:name":"Judith",
    "wof:placetype":"venue"
},
  "geometry": {"coordinates":[6.578231,52.512981],"type":"Point"}
}