{
  "type": "Feature",
  "properties": {
    "addr:full":"Ijmuiderstraatweg 144 Ijmuiden Noord-Holland 1972 LH",
    "addr:housenumber":"144",
    "addr:postcode":"1972 lh",
    "addr:street":"Ijmuiderstraatweg",
    "iso:country":"NL",
    "sg:address":"Ijmuiderstraatweg 144",
    "sg:city":"Ijmuiden",
    "sg:orig_category":"Film-, Tv- And Videoproductie",
    "sg:phone":"+31 255 523 306",
    "sg:postcode":"1972 LH",
    "sg:province":"Noord-Holland",
    "wof:name":"Erwin Aubroeck",
    "wof:placetype":"venue"
},
  "geometry": {"coordinates":[4.612649,52.462868],"type":"Point"}
}