{
  "type": "Feature",
  "properties": {
    "iso:country":"NL",
    "sg:address":"Lavendelpln 6",
    "sg:city":"Barneveld",
    "sg:orig_category":"Adviesbureaus Personeel",
    "sg:phone":"+31 342 406 220",
    "sg:postcode":"3773 CM",
    "sg:province":"Gelderland",
    "sg:website":"http://www.care-group.nl",
    "wof:name":"Care Intermediair Bv",
    "wof:placetype":"venue"
},
  "geometry": {"coordinates":[5.604392,52.13475],"type":"Point"}
}