{
  "type": "Feature",
  "properties": {
    "addr:full":"Rynstr 14 Tolkamer Gelderland 6916 BD",
    "addr:housenumber":"14",
    "addr:postcode":"6916 bd",
    "addr:street":"Rynstr;Gelderland",
    "iso:country":"NL",
    "sg:address":"Rynstr 14",
    "sg:city":"Tolkamer",
    "sg:orig_category":"Cafetaria'S",
    "sg:phone":"+31 316 543 886",
    "sg:postcode":"6916 BD",
    "sg:province":"Gelderland",
    "wof:name":"Luifeltje, 'T",
    "wof:placetype":"venue"
},
  "geometry": {"coordinates":[6.10671,51.853165],"type":"Point"}
}