{
  "type": "Feature",
  "properties": {
    "addr:full":"Wolveschansdreef 25 Leek Groningen 9351 SE",
    "addr:housenumber":"25",
    "addr:postcode":"9351 se",
    "addr:street":"Wolveschansdreef",
    "iso:country":"NL",
    "sg:address":"Wolveschansdreef 25",
    "sg:city":"Leek",
    "sg:orig_category":"Diverse Grafische Activiteiten",
    "sg:phone":"+31 594 518 678",
    "sg:postcode":"9351 SE",
    "sg:province":"Groningen",
    "wof:name":"Franken Vormgeving B N O",
    "wof:placetype":"venue"
},
  "geometry": {"coordinates":[6.373458,53.154942],"type":"Point"}
}