{
  "type": "Feature",
  "properties": {
    "addr:full":"Putkop 3 Harmelen Utrecht 3481 LK",
    "addr:housenumber":"3",
    "addr:postcode":"3481 lk",
    "addr:street":"Putkop",
    "iso:country":"NL",
    "sg:address":"Putkop 3",
    "sg:city":"Harmelen",
    "sg:orig_category":"Administratie- En Boekhoudkantoren",
    "sg:phone":"+31 348 444 046",
    "sg:postcode":"3481 LK",
    "sg:province":"Utrecht",
    "wof:name":"Onnies",
    "wof:placetype":"venue"
},
  "geometry": {"coordinates":[4.941768,52.100754],"type":"Point"}
}