{
  "type": "Feature",
  "properties": {
    "addr:full":"James Wattstraat 5 Cromstrijen Zuid-Holland 3281 NK",
    "addr:housenumber":"5",
    "addr:postcode":"3281 nk",
    "addr:street":"James Wattstraat",
    "iso:country":"NL",
    "sg:address":"James Wattstraat 5",
    "sg:city":"Cromstrijen",
    "sg:orig_category":"Binnenhuisarchitecten",
    "sg:phone":"+31 186 681 781",
    "sg:postcode":"3281 NK",
    "sg:province":"Zuid-Holland",
    "wof:name":"Warmtecentre",
    "wof:placetype":"venue"
},
  "geometry": {"coordinates":[4.451637,51.744965],"type":"Point"}
}