{
  "type": "Feature",
  "properties": {
    "addr:full":"Merwedestraat 1 Purmerend Noord-Holland 1442 SK",
    "addr:housenumber":"1",
    "addr:street":"Merwedestraat;1442",
    "iso:country":"NL",
    "sg:address":"Merwedestraat 1",
    "sg:city":"Purmerend",
    "sg:orig_category":"Naai- And Breimachines",
    "sg:phone":"+31 299 427 258",
    "sg:postcode":"1442 SK",
    "sg:province":"Noord-Holland",
    "wof:name":"Handelsonderneming Ruygal",
    "wof:placetype":"venue"
},
  "geometry": {"coordinates":[4.963376,52.515408],"type":"Point"}
}