{
  "type": "Feature",
  "properties": {
    "iso:country":"NL",
    "sg:address":"Meerssenhoven 200A",
    "sg:city":"Maastricht",
    "sg:orig_category":"Beeldende Kunstenaars",
    "sg:phone":"+31 43 364 7897",
    "sg:postcode":"6222 PD",
    "sg:province":"Limburg",
    "wof:name":"Engelen, A",
    "wof:placetype":"venue"
},
  "geometry": {"coordinates":[5.719411,50.890232],"type":"Point"}
}