{
  "type": "Feature",
  "properties": {
    "addr:full":"Dordognelaan 66 Eindhoven North Brabant 5627 HG",
    "addr:housenumber":"66",
    "addr:postcode":"5627 hg",
    "addr:street":"Dordognelaan",
    "iso:country":"NL",
    "sg:address":"Dordognelaan 66",
    "sg:city":"Eindhoven",
    "sg:orig_category":"Autokeuringen",
    "sg:phone":"+31 40 292 6029",
    "sg:postcode":"5627 HG",
    "sg:province":"North Brabant",
    "wof:name":"Usa Select",
    "wof:placetype":"venue"
},
  "geometry": {"coordinates":[5.455049,51.479412],"type":"Point"}
}