{
  "type": "Feature",
  "properties": {
    "addr:full":"Hellingpaed 8 Gaastmeer Provincie Friesland 8611 JR",
    "addr:housenumber":"8;8611",
    "addr:street":"Hellingpaed;Provincie Friesland",
    "iso:country":"NL",
    "sg:address":"Hellingpaed 8",
    "sg:city":"Gaastmeer",
    "sg:orig_category":"Pleziervaartuigen And Reparatie",
    "sg:phone":"+31 515 469 606",
    "sg:postcode":"8611 JR",
    "sg:province":"Provincie Friesland",
    "wof:name":"Jachtwerf Wildschut",
    "wof:placetype":"venue"
},
  "geometry": {"coordinates":[5.542219,52.964249],"type":"Point"}
}