{
  "type": "Feature",
  "properties": {
    "iso:country":"NL",
    "sg:address":"K R Poststr 8",
    "sg:city":"Heerenveen",
    "sg:orig_category":"Adviesbureaus Bouwkunde",
    "sg:phone":"+31 513 650 908",
    "sg:postcode":"8441 EP",
    "sg:province":"Friesland",
    "wof:name":"Bap Heerenveen",
    "wof:placetype":"venue"
},
  "geometry": {"coordinates":[5.920984,52.961861],"type":"Point"}
}