{
  "type": "Feature",
  "properties": {
    "addr:full":"William Pontstraat 80 1135 Zj North Holland EDAM ",
    "addr:housenumber":"80",
    "addr:postcode":"1135 zj",
    "addr:street":"William Pontstraat",
    "iso:country":"NL",
    "sg:address":"William Pontstraat 80",
    "sg:city":"1135 Zj",
    "sg:classifiers":[
        {
            "category":"Banks & Credit Unions",
            "subcategory":"Bank",
            "type":"Services"
        }
    ],
    "sg:phone":"+31 299 362 211",
    "sg:postcode":"EDAM ",
    "sg:province":"North Holland",
    "wof:name":"Ing Bank Nv",
    "wof:placetype":"venue"
},
  "geometry": {"coordinates":[5.052467,52.507828],"type":"Point"}
}