{
  "type": "Feature",
  "properties": {
    "addr:full":"Willemstr 37 Bodegraven South Holland 2411 CP",
    "addr:housenumber":"37",
    "addr:postcode":"2411 cp",
    "addr:street":"Willemstr",
    "iso:country":"NL",
    "sg:address":"Willemstr 37",
    "sg:city":"Bodegraven",
    "sg:orig_category":"Woningstoffeerders",
    "sg:phone":"+31 172 617 265",
    "sg:postcode":"2411 CP",
    "sg:province":"South Holland",
    "wof:name":"Meer, D J Van Der",
    "wof:placetype":"venue"
},
  "geometry": {"coordinates":[4.7475471497,52.0855522156],"type":"Point"}
}