{
  "type": "Feature",
  "properties": {
    "addr:full":"Voorstraat 49 Spijkenisse Zuid-Holland 3201 BA",
    "addr:housenumber":"49",
    "addr:postcode":"3201 ba",
    "addr:street":"Voorstraat",
    "iso:country":"NL",
    "sg:address":"Voorstraat 49",
    "sg:city":"Spijkenisse",
    "sg:orig_category":"Hypotheken And Hypotheekbanken",
    "sg:phone":"+31 181 690 444",
    "sg:postcode":"3201 BA",
    "sg:province":"Zuid-Holland",
    "wof:name":"De Hypotheekshop",
    "wof:placetype":"venue"
},
  "geometry": {"coordinates":[4.325045,51.849525],"type":"Point"}
}