{
  "type": "Feature",
  "properties": {
    "addr:full":"Rembrandthof 42 Amstelveen North Holland 1181 ZL",
    "addr:housenumber":"42",
    "addr:postcode":"1181 zl",
    "addr:street":"Rembrandthof",
    "iso:country":"NL",
    "sg:address":"Rembrandthof 42",
    "sg:city":"Amstelveen",
    "sg:orig_category":"Modelbouw",
    "sg:phone":"+31 20 347 3344",
    "sg:postcode":"1181 ZL",
    "sg:province":"North Holland",
    "sg:website":"http://www.degroottoyspecialstore.nl",
    "wof:name":"Groot Toyspecial Store, De",
    "wof:placetype":"venue"
},
  "geometry": {"coordinates":[4.86011,52.303333],"type":"Point"}
}