{
  "type": "Feature",
  "properties": {
    "addr:full":"Boezemlaan 17 Boskoop Zuid-Holland 2771 VN",
    "addr:housenumber":"17",
    "addr:postcode":"2771 vn",
    "addr:street":"Boezemlaan",
    "iso:country":"NL",
    "sg:address":"Boezemlaan 17",
    "sg:city":"Boskoop",
    "sg:orig_category":"Boomkwekerijen",
    "sg:phone":"+31 172 212 937",
    "sg:postcode":"2771 VN",
    "sg:province":"Zuid-Holland",
    "wof:name":"Westdijk'S Boomkwekerijen",
    "wof:placetype":"venue"
},
  "geometry": {"coordinates":[4.647155,52.072815],"type":"Point"}
}