{
  "type": "Feature",
  "properties": {
    "addr:full":"Raadhuisstraat 16 Geleen Limburg 6161 GD",
    "addr:housenumber":"16",
    "addr:postcode":"6161 gd",
    "addr:street":"Raadhuisstraat",
    "iso:country":"NL",
    "sg:address":"Raadhuisstraat 16",
    "sg:city":"Geleen",
    "sg:orig_category":"Kappers",
    "sg:phone":"+31 46 475 3313",
    "sg:postcode":"6161 GD",
    "sg:province":"Limburg",
    "wof:name":"Mudo Hikmet Kuskal",
    "wof:placetype":"venue"
},
  "geometry": {"coordinates":[5.828473,50.968555],"type":"Point"}
}