{
  "type": "Feature",
  "properties": {
    "iso:country":"NL",
    "sg:address":"Graaf Van Rechterenweg 12",
    "sg:city":"Oosterbeek",
    "sg:classifiers":[
        {
            "category":"Travel",
            "subcategory":"Hotels & Motels",
            "type":"Entertainment"
        }
    ],
    "sg:phone":"+31 26 333 3169",
    "sg:postcode":"6861 BR",
    "sg:province":"Gelderland",
    "sg:website":"http://www.dreyeroord.nl",
    "wof:name":"Hotel Dreyeroord",
    "wof:placetype":"venue"
},
  "geometry": {"coordinates":[5.838662,51.99403],"type":"Point"}
}