{
  "type": "Feature",
  "properties": {
    "addr:full":"Weerestein 37 Gouda Zuid-Holland 2804 GG",
    "addr:housenumber":"37",
    "addr:postcode":"2804 gg",
    "addr:street":"Weerestein",
    "iso:country":"NL",
    "sg:address":"Weerestein 37",
    "sg:city":"Gouda",
    "sg:classifiers":[
        {
            "category":"Education",
            "subcategory":"Preschool",
            "type":"Public Place"
        }
    ],
    "sg:phone":"+31 182 534 118",
    "sg:postcode":"2804 GG",
    "sg:province":"Zuid-Holland",
    "sg:tags":[
        "kleuteronderwijs",
        "basis-"
    ],
    "wof:name":"Plaswijckschool",
    "wof:placetype":"venue"
},
  "geometry": {"coordinates":[4.711533,52.030285],"type":"Point"}
}