{
  "type": "Feature",
  "properties": {
    "addr:full":"Stadhoudersln 114 Utrecht Utrecht 3583 JP",
    "addr:housenumber":"114",
    "addr:postcode":"3583 jp",
    "iso:country":"NL",
    "sg:address":"Stadhoudersln 114",
    "sg:city":"Utrecht",
    "sg:orig_category":"Psychotherapeuten",
    "sg:phone":"+31 30 254 0940",
    "sg:postcode":"3583 JP",
    "sg:province":"Utrecht",
    "sg:website":"http://www.mensontwikkeling.com",
    "wof:name":"Centrum Voor Mensontwikkeling",
    "wof:placetype":"venue"
},
  "geometry": {"coordinates":[5.14371,52.086601],"type":"Point"}
}