{
  "type": "Feature",
  "properties": {
    "addr:full":"Beekln 1 Wouw Noord-Brabant 4724 BM",
    "addr:housenumber":"1",
    "addr:postcode":"4724 bm",
    "addr:street":"Beekln",
    "iso:country":"NL",
    "sg:address":"Beekln 1",
    "sg:city":"Wouw",
    "sg:orig_category":"Homeopathie",
    "sg:phone":"+31 165 302 906",
    "sg:postcode":"4724 BM",
    "sg:province":"Noord-Brabant",
    "wof:name":"Bosch-Van Tiggelen, A Van Den",
    "wof:placetype":"venue"
},
  "geometry": {"coordinates":[4.387532,51.523155],"type":"Point"}
}