{
  "type": "Feature",
  "properties": {
    "addr:full":"Lagedijk 7 Helmond North Brabant 5705 BX",
    "addr:housenumber":"7",
    "addr:postcode":"5705 bx",
    "addr:street":"Lagedijk",
    "iso:country":"NL",
    "sg:address":"Lagedijk 7",
    "sg:city":"Helmond",
    "sg:orig_category":"Autokeuringen",
    "sg:phone":"+31 6 53739741",
    "sg:postcode":"5705 BX",
    "sg:province":"North Brabant",
    "wof:name":"Autopoetssalon Stassen",
    "wof:placetype":"venue"
},
  "geometry": {"coordinates":[5.658284,51.482239],"type":"Point"}
}