{
  "type": "Feature",
  "properties": {
    "iso:country":"NL",
    "sg:address":"Pyreneeen 45",
    "sg:city":"Utrecht",
    "sg:orig_category":"Werving And Selectie Van Tijdelijk Personeel And Uitzendkantoren",
    "sg:phone":"+31 30 280 4301",
    "sg:postcode":"3524 VM",
    "sg:province":"Utrecht",
    "wof:name":"Jobstore",
    "wof:placetype":"venue"
},
  "geometry": {"coordinates":[5.1341700554,52.0622138977],"type":"Point"}
}