{
  "type": "Feature",
  "properties": {
    "addr:full":"Weltertuynstr 72A Heerlen Limburg 6419 CV",
    "addr:housenumber":"72a",
    "addr:postcode":"6419 cv",
    "addr:street":"Weltertuynstr",
    "iso:country":"NL",
    "sg:address":"Weltertuynstr 72A",
    "sg:city":"Heerlen",
    "sg:classifiers":[
        {
            "category":"Food & Beverages",
            "subcategory":"Bakery",
            "type":"Retail Goods"
        }
    ],
    "sg:phone":"+31 45 571 5504",
    "sg:postcode":"6419 CV",
    "sg:province":"Limburg",
    "sg:tags":[
        "brood",
        "en",
        "banket"
    ],
    "wof:name":"Voncken",
    "wof:placetype":"venue"
},
  "geometry": {"coordinates":[5.9661,50.875561],"type":"Point"}
}