{
  "type": "Feature",
  "properties": {
    "addr:full":"Driessenstr 5 Landgraaf Limburg 6374 AS",
    "addr:housenumber":"5",
    "addr:postcode":"6374 as",
    "addr:street":"Driessenstr",
    "iso:country":"NL",
    "sg:address":"Driessenstr 5",
    "sg:city":"Landgraaf",
    "sg:orig_category":"Vertalers",
    "sg:phone":"+31 45 569 0710",
    "sg:postcode":"6374 AS",
    "sg:province":"Limburg",
    "wof:name":"Jonge, W A De",
    "wof:placetype":"venue"
},
  "geometry": {"coordinates":[6.041505,50.921436],"type":"Point"}
}