{
  "type": "Feature",
  "properties": {
    "addr:full":"Hotel De Wereldstraat 8 Almere Flevoland 1318 AR",
    "addr:housenumber":"8",
    "addr:postcode":"1318",
    "addr:street":"De Wereldstraat;Flevoland",
    "iso:country":"NL",
    "sg:address":"Hotel De Wereldstraat 8",
    "sg:city":"Almere",
    "sg:orig_category":"Boekhouders",
    "sg:phone":"+31 36 537 7474",
    "sg:postcode":"1318 AR",
    "sg:province":"Flevoland",
    "wof:name":"Abc",
    "wof:placetype":"venue"
},
  "geometry": {"coordinates":[-58.376019,-34.601131],"type":"Point"}
}