{
  "type": "Feature",
  "properties": {
    "iso:country":"NL",
    "sg:address":"Kon Emmastr 7",
    "sg:city":"Randwyk",
    "sg:orig_category":"Exploitatie- Maatschappijen",
    "sg:phone":"+31 6 51381509",
    "sg:postcode":"6668 AM",
    "sg:province":"Gelderland",
    "wof:name":"Meijde Vof, Van Der",
    "wof:placetype":"venue"
},
  "geometry": {"coordinates":[5.712825,51.944649],"type":"Point"}
}