{
  "type": "Feature",
  "properties": {
    "addr:full":"Mauritsstraat 81 Utrecht Utrecht 3583 HK",
    "addr:housenumber":"81",
    "addr:postcode":"3583 hk",
    "addr:street":"Mauritsstraat",
    "iso:country":"NL",
    "sg:address":"Mauritsstraat 81",
    "sg:city":"Utrecht",
    "sg:orig_category":"Artsen And Specialisten",
    "sg:phone":"+31 30 251 4308",
    "sg:postcode":"3583 HK",
    "sg:province":"Utrecht",
    "wof:name":"Drs. M. Smit",
    "wof:placetype":"venue"
},
  "geometry": {"coordinates":[5.143119,52.088573],"type":"Point"}
}