{
  "type": "Feature",
  "properties": {
    "iso:country":"NL",
    "sg:address":"Danzigweg 7",
    "sg:city":"Deventer",
    "sg:orig_category":"Metaalafval, Schrootrecycling And Sloperijen",
    "sg:phone":"+31 570 635 741",
    "sg:postcode":"7418 EN",
    "sg:province":"Overijssel",
    "wof:name":"Autosloperij A Van Lies",
    "wof:placetype":"venue"
},
  "geometry": {"coordinates":[6.201491,52.244915],"type":"Point"}
}