{
  "type": "Feature",
  "properties": {
    "iso:country":"NL",
    "sg:address":"Schepenlaan 7",
    "sg:city":"Zaandam",
    "sg:orig_category":"Paramedische Behandelingen",
    "sg:phone":"+31 75 616 9823",
    "sg:postcode":"1503 HJ",
    "sg:province":"Noord-Holland",
    "wof:name":"Drs. J.A.W.M. Zunnebeld",
    "wof:placetype":"venue"
},
  "geometry": {"coordinates":[4.83383,52.449268],"type":"Point"}
}