{
  "type": "Feature",
  "properties": {
    "addr:full":"Grotestr 23 Almelo Overijssel 7607 CB",
    "addr:housenumber":"23",
    "addr:postcode":"7607 cb",
    "addr:street":"Grotestr",
    "iso:country":"NL",
    "sg:address":"Grotestr 23",
    "sg:city":"Almelo",
    "sg:orig_category":"Juweliers",
    "sg:phone":"+31 546 812 005",
    "sg:postcode":"7607 CB",
    "sg:province":"Overijssel",
    "wof:name":"Berendsen",
    "wof:placetype":"venue"
},
  "geometry": {"coordinates":[6.664832,52.358555],"type":"Point"}
}