{
  "type": "Feature",
  "properties": {
    "addr:full":"Moesdaal 80 Maastricht Limburg 6228 HV",
    "addr:housenumber":"80",
    "addr:postcode":"6228 hv",
    "addr:street":"Moesdaal",
    "iso:country":"NL",
    "sg:address":"Moesdaal 80",
    "sg:city":"Maastricht",
    "sg:orig_category":"Autorijscholen",
    "sg:phone":"+31 43 361 0728",
    "sg:postcode":"6228 HV",
    "sg:province":"Limburg",
    "wof:name":"Pieters, Tonny",
    "wof:placetype":"venue"
},
  "geometry": {"coordinates":[5.720193,50.82523],"type":"Point"}
}