{
  "type": "Feature",
  "properties": {
    "iso:country":"NL",
    "sg:address":"Tuurkesweg 5",
    "sg:city":"Weert",
    "sg:orig_category":"Beautyfarms And Sauna'S",
    "sg:phone":"+31 495 566 088",
    "sg:postcode":"6006 SG",
    "sg:province":"Limburg",
    "wof:name":"L'Institut Nouveau Cosmetique",
    "wof:placetype":"venue"
},
  "geometry": {"coordinates":[5.717566,51.210873],"type":"Point"}
}