{
  "type": "Feature",
  "properties": {
    "addr:full":"Laan Van Biel 12 Almelo NL.08 7607 PP",
    "addr:housenumber":"12;nl.08",
    "addr:postcode":"7607 pp",
    "addr:street":"Laan Van Biel",
    "iso:country":"NL",
    "sg:address":"Laan Van Biel 12",
    "sg:city":"Almelo",
    "sg:classifiers":[
        {
            "category":"Fast Food",
            "type":"Food & Drink"
        }
    ],
    "sg:phone":"+31 546 814 663",
    "sg:postcode":"7607 PP",
    "sg:province":"NL.08",
    "sg:tags":[
        "afhaal",
        "restaurant"
    ],
    "wof:name":"F.A.G. Stokkelaar",
    "wof:placetype":"venue"
},
  "geometry": {"coordinates":[6.682545,52.352619],"type":"Point"}
}