{
  "type": "Feature",
  "properties": {
    "addr:full":"Lange Dreef 25 Vianen Zh Utrecht 4131 NH",
    "addr:housenumber":"25",
    "addr:postcode":"zh;4131 nh",
    "addr:street":"Lange Dreef",
    "iso:country":"NL",
    "sg:address":"Lange Dreef 25",
    "sg:city":"Vianen Zh",
    "sg:orig_category":"Kantoor- And Schoolbenodigdheden Gh",
    "sg:phone":"+31 347 372 525",
    "sg:postcode":"4131 NH",
    "sg:province":"Utrecht",
    "wof:name":"Paper Disposables Vianen Bv",
    "wof:placetype":"venue"
},
  "geometry": {"coordinates":[5.1043100357,51.9854202271],"type":"Point"}
}