{
  "type": "Feature",
  "properties": {
    "iso:country":"NL",
    "sg:address":"Gemaalweg 7",
    "sg:city":"'S Hertogenbosch",
    "sg:orig_category":"Huishoudapparatuur, Televisies And Radio'S",
    "sg:phone":"+31 73 633 0157",
    "sg:postcode":"5221 CH",
    "sg:province":"Noord-Brabant",
    "wof:name":"Audiovisual Products Services A.P.S.",
    "wof:placetype":"venue"
},
  "geometry": {"coordinates":[5.275857,51.719177],"type":"Point"}
}