{
  "type": "Feature",
  "properties": {
    "iso:country":"NL",
    "sg:address":"Hogeveld 8",
    "sg:city":"Bergharen",
    "sg:orig_category":"Meubelen - Fabrieken En Groothandel",
    "sg:phone":"+31 487 531 288",
    "sg:postcode":"6617 KR",
    "sg:province":"Gelderland",
    "wof:name":"Rossum Bv, Van",
    "wof:placetype":"venue"
},
  "geometry": {"coordinates":[5.65512,51.852783],"type":"Point"}
}