{
  "type": "Feature",
  "properties": {
    "addr:full":"Gentenerf 11 Ermelo Gelderland 3852 LW",
    "addr:housenumber":"11",
    "addr:postcode":"3852 lw",
    "addr:street":"Gentenerf;Gelderland",
    "iso:country":"NL",
    "sg:address":"Gentenerf 11",
    "sg:city":"Ermelo",
    "sg:orig_category":"Algemene Werktuigbouw",
    "sg:phone":"+31 341 431 789",
    "sg:postcode":"3852 LW",
    "sg:province":"Gelderland",
    "wof:name":"M.C. Lansink Montage",
    "wof:placetype":"venue"
},
  "geometry": {"coordinates":[5.623496,52.323483],"type":"Point"}
}