{
  "type": "Feature",
  "properties": {
    "addr:full":"Dordsedwstr 9 Emmen Provincie Drenthe 7811 KB",
    "addr:housenumber":"9",
    "addr:postcode":"7811 kb",
    "addr:street":"Dordsedwstr;Provincie Drenthe",
    "iso:country":"NL",
    "sg:address":"Dordsedwstr 9",
    "sg:city":"Emmen",
    "sg:orig_category":"Fietsen En Bromfietsen",
    "sg:phone":"+31 591 614 899",
    "sg:postcode":"7811 KB",
    "sg:province":"Provincie Drenthe",
    "wof:name":"Motorino Mario",
    "wof:placetype":"venue"
},
  "geometry": {"coordinates":[6.897321,52.777546],"type":"Point"}
}