{
  "type": "Feature",
  "properties": {
    "addr:full":"Driehoefyzersstr 6 Zevenbergs Hoek Noord-Brabant 4765 BG",
    "addr:housenumber":"6",
    "addr:postcode":"4765",
    "addr:street":"Driehoefyzersstr",
    "iso:country":"NL",
    "sg:address":"Driehoefyzersstr 6",
    "sg:city":"Zevenbergs Hoek",
    "sg:orig_category":"Grafische Bedrijven",
    "sg:phone":"+31 168 452 026",
    "sg:postcode":"4765 BG",
    "sg:province":"Noord-Brabant",
    "wof:name":"Riche",
    "wof:placetype":"venue"
},
  "geometry": {"coordinates":[24.5637,41.551899],"type":"Point"}
}