{
  "type": "Feature",
  "properties": {
    "addr:full":"Marktplein 7 Geldermalsen Gelderland 4191 AC",
    "addr:housenumber":"7",
    "addr:postcode":"4191 ac",
    "addr:street":"Marktplein;Gelderland",
    "iso:country":"NL",
    "sg:address":"Marktplein 7",
    "sg:city":"Geldermalsen",
    "sg:classifiers":[
        {
            "category":"Bakery",
            "type":"Food & Drink"
        }
    ],
    "sg:phone":"+31 345 575 800",
    "sg:postcode":"4191 AC",
    "sg:province":"Gelderland",
    "sg:tags":[
        "brood",
        "banket"
    ],
    "wof:name":"Drop-Inn",
    "wof:placetype":"venue"
},
  "geometry": {"coordinates":[5.288647,51.883358],"type":"Point"}
}