{
  "type": "Feature",
  "properties": {
    "addr:full":"Loswal 6 Drachten Friesland 9206 AH",
    "addr:housenumber":"6",
    "addr:postcode":"9206 ah",
    "addr:street":"Loswal",
    "iso:country":"NL",
    "sg:address":"Loswal 6",
    "sg:city":"Drachten",
    "sg:orig_category":"Verhuisdiensten",
    "sg:phone":"+31 512 515 000",
    "sg:postcode":"9206 AH",
    "sg:province":"Friesland",
    "wof:name":"Verhuisbedrijf Prinsen",
    "wof:placetype":"venue"
},
  "geometry": {"coordinates":[6.077408,53.109787],"type":"Point"}
}