{
  "type": "Feature",
  "properties": {
    "addr:full":"Boerenkampln 183 Someren North Brabant 5712 AD",
    "addr:housenumber":"183",
    "addr:postcode":"5712 ad",
    "iso:country":"NL",
    "sg:address":"Boerenkampln 183",
    "sg:city":"Someren",
    "sg:orig_category":"Parketvloeren",
    "sg:phone":"+31 493 491 080",
    "sg:postcode":"5712 AD",
    "sg:province":"North Brabant",
    "sg:website":"http://www.musanparket.nl",
    "wof:name":"Musan Parket",
    "wof:placetype":"venue"
},
  "geometry": {"coordinates":[5.735223,51.358841],"type":"Point"}
}