{
  "type": "Feature",
  "properties": {
    "addr:full":"Kennedylaan 6 Brunssum Limburg 6441 JD",
    "addr:housenumber":"6",
    "addr:postcode":"6441 jd",
    "addr:street":"Kennedylaan",
    "iso:country":"NL",
    "sg:address":"Kennedylaan 6",
    "sg:city":"Brunssum",
    "sg:orig_category":"Public Relationbureaus",
    "sg:phone":"+31 45 525 2591",
    "sg:postcode":"6441 JD",
    "sg:province":"Limburg",
    "wof:name":"Rs & P",
    "wof:placetype":"venue"
},
  "geometry": {"coordinates":[5.966213,50.951977],"type":"Point"}
}