{
  "type": "Feature",
  "properties": {
    "addr:full":"Kerkenveld 10 Epe Gelderland 8162 JV",
    "addr:housenumber":"10",
    "addr:postcode":"8162 jv",
    "addr:street":"Kerkenveld;Gelderland",
    "iso:country":"NL",
    "sg:address":"Kerkenveld 10",
    "sg:city":"Epe",
    "sg:orig_category":"Kinderopvang Behalve Thuis",
    "sg:phone":"+31 578 615 825",
    "sg:postcode":"8162 JV",
    "sg:province":"Gelderland",
    "wof:name":"Kierewam Kindercentrum",
    "wof:placetype":"venue"
},
  "geometry": {"coordinates":[5.970733,52.346661],"type":"Point"}
}