{
  "type": "Feature",
  "properties": {
    "iso:country":"NL",
    "sg:address":"Vlierberg 12",
    "sg:city":"Eemnes",
    "sg:orig_category":"Film-, Tv- And Videoproductie",
    "sg:phone":"+31 35 533 5720",
    "sg:postcode":"3755 BS",
    "sg:province":"Utrecht",
    "wof:name":"Ftv Productions B.V.",
    "wof:placetype":"venue"
},
  "geometry": {"coordinates":[5.249126,52.246906],"type":"Point"}
}