{
  "type": "Feature",
  "properties": {
    "iso:country":"NL",
    "sg:address":"Bergerdensestr 3A",
    "sg:city":"Huissen",
    "sg:orig_category":"Pijpleidingen - Apparatuur En Benodigdheden",
    "sg:phone":"+31 26 388 6395",
    "sg:postcode":"6851 EN",
    "sg:province":"Gelderland",
    "wof:name":"Valk Ips",
    "wof:placetype":"venue"
},
  "geometry": {"coordinates":[5.907809,51.93037],"type":"Point"}
}