{
  "type": "Feature",
  "properties": {
    "iso:country":"NL",
    "sg:address":"Krommeniedk 51",
    "sg:city":"Krommenie",
    "sg:orig_category":"Onderhoudswerken",
    "sg:phone":"+31 75 622 6289",
    "sg:postcode":"1562 GJ",
    "sg:province":"North Holland",
    "wof:name":"Engel Bv",
    "wof:placetype":"venue"
},
  "geometry": {"coordinates":[4.764341,52.515553],"type":"Point"}
}