{
  "type": "Feature",
  "properties": {
    "addr:full":"De Meelzak 12 De Ryp North Holland 1483 AV",
    "addr:housenumber":"12;1483",
    "addr:postcode":"av",
    "addr:street":"De Meelzak;De Ryp North",
    "iso:country":"NL",
    "sg:address":"De Meelzak 12",
    "sg:city":"De Ryp",
    "sg:orig_category":"Jachthavens - Jachtwerven",
    "sg:phone":"+31 299 674 085",
    "sg:postcode":"1483 AV",
    "sg:province":"North Holland",
    "wof:name":"Passantenhaven, Sticht",
    "wof:placetype":"venue"
},
  "geometry": {"coordinates":[4.846465,52.560177],"type":"Point"}
}