{
  "type": "Feature",
  "properties": {
    "addr:full":"Postbus 1 Slochteren Groningen 9620 AA",
    "addr:housenumber":"1",
    "addr:postcode":"9620 aa",
    "addr:street":"Postbus",
    "iso:country":"NL",
    "sg:address":"Postbus 1",
    "sg:city":"Slochteren",
    "sg:orig_category":"Boeken En Tijdschriften",
    "sg:phone":"+31 598 423 559",
    "sg:postcode":"9620 AA",
    "sg:province":"Groningen",
    "sg:website":"http://www.waddenkiosk.com",
    "wof:name":"Waddenkiosk.Nl",
    "wof:placetype":"venue"
},
  "geometry": {"coordinates":[6.80568,53.219734],"type":"Point"}
}