{
  "type": "Feature",
  "properties": {
    "addr:full":"Henri Hermansstraat 29 Nuth Limburg 6361 BS",
    "addr:housenumber":"29",
    "addr:postcode":"6361 bs",
    "addr:street":"Henri Hermansstraat",
    "iso:country":"NL",
    "sg:address":"Henri Hermansstraat 29",
    "sg:city":"Nuth",
    "sg:orig_category":"Kappers",
    "sg:phone":"+31 45 524 1865",
    "sg:postcode":"6361 BS",
    "sg:province":"Limburg",
    "wof:name":"Hairstyling Ger Weustenraad",
    "wof:placetype":"venue"
},
  "geometry": {"coordinates":[5.8879981041,50.9189376831],"type":"Point"}
}