{
  "type": "Feature",
  "properties": {
    "iso:country":"NL",
    "sg:address":"Zuivelstr 27",
    "sg:city":"Bergen Op Zoom",
    "sg:classifiers":[
        {
            "category":"Shopping",
            "subcategory":"Adult",
            "type":"Retail Goods"
        }
    ],
    "sg:phone":"+31 164 240 808",
    "sg:postcode":"4611 PE",
    "sg:province":"Noord-Brabant",
    "sg:tags":[
        "lingerie",
        "en",
        "tricotage"
    ],
    "wof:name":"Dekkers",
    "wof:placetype":"venue"
},
  "geometry": {"coordinates":[4.288727,51.495132],"type":"Point"}
}