{
  "type": "Feature",
  "properties": {
    "addr:full":"Herenstr 83 Bussum Noord-Holland 1406 PB",
    "addr:housenumber":"83",
    "addr:postcode":"1406 pb",
    "addr:street":"Herenstr",
    "iso:country":"NL",
    "sg:address":"Herenstr 83",
    "sg:city":"Bussum",
    "sg:orig_category":"Verenigingen En Stichtingen",
    "sg:phone":"+31 35 691 6941",
    "sg:postcode":"1406 PB",
    "sg:province":"Noord-Holland",
    "wof:name":"Unicef",
    "wof:placetype":"venue"
},
  "geometry": {"coordinates":[5.157358,52.272915],"type":"Point"}
}