{
  "type": "Feature",
  "properties": {
    "iso:country":"NL",
    "sg:address":"Hoofdstr 122",
    "sg:city":"Landgraaf",
    "sg:orig_category":"Broodjeszaken",
    "sg:phone":"+31 45 531 2673",
    "sg:postcode":"6372 EN",
    "sg:province":"Limburg",
    "wof:name":"Pain Chevy",
    "wof:placetype":"venue"
},
  "geometry": {"coordinates":[6.015308,50.89267],"type":"Point"}
}