{
  "type": "Feature",
  "properties": {
    "addr:full":"Vlietlaan 44 Bussum Noord-Holland 1404 CC",
    "addr:housenumber":"44",
    "addr:postcode":"1404 cc",
    "addr:street":"Vlietlaan",
    "iso:country":"NL",
    "sg:address":"Vlietlaan 44",
    "sg:city":"Bussum",
    "sg:classifiers":[
        {
            "category":"Retail",
            "subcategory":"Photofinishing",
            "type":"Services"
        }
    ],
    "sg:phone":"+31 35 691 6825",
    "sg:postcode":"1404 CC",
    "sg:province":"Noord-Holland",
    "sg:tags":[
        "foto",
        "film"
    ],
    "wof:name":"Foto Cine Tadema Wieland",
    "wof:placetype":"venue"
},
  "geometry": {"coordinates":[5.159041,52.277233],"type":"Point"}
}