{
  "type": "Feature",
  "properties": {
    "iso:country":"NL",
    "sg:address":"Stationsstr 2-4",
    "sg:city":"Volendam",
    "sg:orig_category":"Homeopathie",
    "sg:phone":"+31 299 320 677",
    "sg:postcode":"1131 ZP",
    "sg:province":"Noord-Holland",
    "wof:name":"Homeoplexan Vof",
    "wof:placetype":"venue"
},
  "geometry": {"coordinates":[5.073996,52.494225],"type":"Point"}
}