{
  "type": "Feature",
  "properties": {
    "iso:country":"NL",
    "sg:address":"Hossenbosdk 6",
    "sg:city":"Vierpolders",
    "sg:orig_category":"Fietsen En Bromfietsen Verhuur",
    "sg:phone":"+31 181 415 204",
    "sg:postcode":"3237 KD",
    "sg:province":"South Holland",
    "sg:website":"http://www.ligfietscentrumbrielle.nl",
    "wof:name":"Ligfietscentrum Brielle",
    "wof:placetype":"venue"
},
  "geometry": {"coordinates":[4.170921,51.894318],"type":"Point"}
}