{
  "type": "Feature",
  "properties": {
    "iso:country":"NL",
    "sg:address":"Westerhovensewg 18",
    "sg:city":"Valkenswaard",
    "sg:orig_category":"Kousen En Sokken",
    "sg:phone":"+31 40 204 2064",
    "sg:postcode":"5551 AD",
    "sg:province":"Noord-Brabant",
    "wof:name":"Jong-Degen, De",
    "wof:placetype":"venue"
},
  "geometry": {"coordinates":[5.428007,51.346588],"type":"Point"}
}