{
  "type": "Feature",
  "properties": {
    "iso:country":"NL",
    "sg:address":"Weipoortsewg 46",
    "sg:city":"Zoeterwoude",
    "sg:orig_category":"Onderhoudswerken",
    "sg:phone":"+31 71 580 1721",
    "sg:postcode":"2381 NE",
    "sg:province":"South Holland",
    "wof:name":"Ttm",
    "wof:placetype":"venue"
},
  "geometry": {"coordinates":[4.526314,52.120781],"type":"Point"}
}