{
  "type": "Feature",
  "properties": {
    "addr:full":"Vredenhofpad 10 Amsterdam Noord-Holland 1051 LK",
    "addr:housenumber":"10",
    "addr:postcode":"1051 lk",
    "addr:street":"Vredenhofpad",
    "iso:country":"NL",
    "sg:address":"Vredenhofpad 10",
    "sg:city":"Amsterdam",
    "sg:orig_category":"Psychotherapeuten",
    "sg:phone":"+31 20 681 3357",
    "sg:postcode":"1051 LK",
    "sg:province":"Noord-Holland",
    "wof:name":"Calkhoven, M J",
    "wof:placetype":"venue"
},
  "geometry": {"coordinates":[4.86154,52.383205],"type":"Point"}
}