{
  "type": "Feature",
  "properties": {
    "addr:full":"1E Helmersstr 55H Amsterdam Noord-Holland 1054 DB",
    "addr:housenumber":"55h",
    "addr:postcode":"1054 db",
    "addr:street":"1E Helmersstr",
    "iso:country":"NL",
    "sg:address":"1E Helmersstr 55H",
    "sg:city":"Amsterdam",
    "sg:orig_category":"Wijnkoperijen En -Groothandel",
    "sg:phone":"+31 20 612 5123",
    "sg:postcode":"1054 DB",
    "sg:province":"Noord-Holland",
    "wof:name":"Ruiter, Th De",
    "wof:placetype":"venue"
},
  "geometry": {"coordinates":[4.8753471375,52.3633842468],"type":"Point"}
}