{
  "type": "Feature",
  "properties": {
    "addr:full":"Industrieweg 1 Hapert North Brabant 5527 AJ",
    "addr:housenumber":"1",
    "addr:postcode":"5527 aj",
    "addr:street":"Industrieweg",
    "iso:country":"NL",
    "sg:address":"Industrieweg 1",
    "sg:city":"Hapert",
    "sg:orig_category":"Elektrische Apparatuur Gh",
    "sg:phone":"+31 497 381 644",
    "sg:postcode":"5527 AJ",
    "sg:province":"North Brabant",
    "wof:name":"Matrex Spuitgietmatrijzen Bv",
    "wof:placetype":"venue"
},
  "geometry": {"coordinates":[5.264508,51.372059],"type":"Point"}
}