{
  "type": "Feature",
  "properties": {
    "addr:full":"Schoolstraat 20A Amsterdam Noord-Holland 1054 KD",
    "addr:housenumber":"20a",
    "addr:postcode":"1054 kd",
    "addr:street":"Schoolstraat",
    "iso:country":"NL",
    "sg:address":"Schoolstraat 20A",
    "sg:city":"Amsterdam",
    "sg:orig_category":"Adviesbureaus Bedrijfsorganisatie",
    "sg:phone":"+31 20 489 4774",
    "sg:postcode":"1054 KD",
    "sg:province":"Noord-Holland",
    "sg:website":"http://www.ofa-dagindeling.nl",
    "wof:name":"Dagindeling, Adviesburea Voor",
    "wof:placetype":"venue"
},
  "geometry": {"coordinates":[4.86153,52.358704],"type":"Point"}
}