{
  "type": "Feature",
  "properties": {
    "addr:full":"Voorweg 40 Zoetermeer Zuid-Holland 2713 RX",
    "addr:housenumber":"40",
    "addr:postcode":"2713 rx",
    "addr:street":"Voorweg",
    "iso:country":"NL",
    "sg:address":"Voorweg 40",
    "sg:city":"Zoetermeer",
    "sg:orig_category":"Boekhouders",
    "sg:phone":"+31 79 323 0186",
    "sg:postcode":"2713 RX",
    "sg:province":"Zuid-Holland",
    "wof:name":"C.C.J. Dijkhuizen",
    "wof:placetype":"venue"
},
  "geometry": {"coordinates":[4.484486,52.059582],"type":"Point"}
}