{
  "type": "Feature",
  "properties": {
    "addr:full":"Veilingwg 11 St Annaland Zeeland 4697 RB",
    "addr:housenumber":"11",
    "addr:postcode":"4697 rb",
    "addr:street":"Veilingwg",
    "iso:country":"NL",
    "sg:address":"Veilingwg 11",
    "sg:city":"St Annaland",
    "sg:orig_category":"Kunststoffen - Fabrieken En Groothandel",
    "sg:phone":"+31 166 657 106",
    "sg:postcode":"4697 RB",
    "sg:province":"Zeeland",
    "wof:name":"Kurepro Vof",
    "wof:placetype":"venue"
},
  "geometry": {"coordinates":[4.108465,51.596088],"type":"Point"}
}