{
  "type": "Feature",
  "properties": {
    "addr:full":"Spuistr 145 Ridderkerk Zuid-Holland 2987 TJ",
    "addr:housenumber":"145",
    "addr:postcode":"2987 tj",
    "iso:country":"NL",
    "sg:address":"Spuistr 145",
    "sg:city":"Ridderkerk",
    "sg:orig_category":"Organisatiebureaus",
    "sg:phone":"+31 180 462 848",
    "sg:postcode":"2987 TJ",
    "sg:province":"Zuid-Holland",
    "wof:name":"Montfoort, Jacques",
    "wof:placetype":"venue"
},
  "geometry": {"coordinates":[4.5845189095,51.8905220032],"type":"Point"}
}