{
  "type": "Feature",
  "properties": {
    "addr:full":"De Clomp 3122 Zeist Utrecht 3704 KA",
    "addr:housenumber":"3122",
    "addr:postcode":"3704 ka",
    "addr:street":"De Clomp",
    "iso:country":"NL",
    "sg:address":"De Clomp 3122",
    "sg:city":"Zeist",
    "sg:classifiers":[
        {
            "category":"Food & Beverages",
            "subcategory":"Fruits & Vegetables",
            "type":"Retail Goods"
        }
    ],
    "sg:phone":"+31 30 695 5182",
    "sg:postcode":"3704 KA",
    "sg:province":"Utrecht",
    "sg:tags":[
        "en",
        "groenten"
    ],
    "wof:name":"Dalhuizen, R",
    "wof:placetype":"venue"
},
  "geometry": {"coordinates":[5.218903,52.082794],"type":"Point"}
}