{
  "type": "Feature",
  "properties": {
    "addr:full":"Sandelingpln 15A Rotterdam Zuid-Holland 3073 AL",
    "addr:housenumber":"15a",
    "addr:postcode":"3073 al",
    "addr:street":"Sandelingpln",
    "iso:country":"NL",
    "sg:address":"Sandelingpln 15A",
    "sg:city":"Rotterdam",
    "sg:orig_category":"Verzekeringen - Verzekeringskantoren",
    "sg:phone":"+31 10 485 3409",
    "sg:postcode":"3073 AL",
    "sg:province":"Zuid-Holland",
    "wof:name":"Euro Spaarcentrale",
    "wof:placetype":"venue"
},
  "geometry": {"coordinates":[4.502877,51.892345],"type":"Point"}
}