{
  "type": "Feature",
  "properties": {
    "addr:full":"Houtwijk 27 Dronten Flevoland 8251 GD",
    "addr:housenumber":"27",
    "addr:postcode":"8251 gd",
    "addr:street":"Houtwijk;Flevoland",
    "iso:country":"NL",
    "sg:address":"Houtwijk 27",
    "sg:city":"Dronten",
    "sg:orig_category":"Meubelzaken, Woning- And Keukeninrichting",
    "sg:phone":"+31 321 318 737",
    "sg:postcode":"8251 GD",
    "sg:province":"Flevoland",
    "wof:name":"Sjors Meubel Bv",
    "wof:placetype":"venue"
},
  "geometry": {"coordinates":[5.72987,52.520309],"type":"Point"}
}