{
  "type": "Feature",
  "properties": {
    "addr:full":"Markt 2B-2C Budel North Brabant 6021 CD",
    "addr:housenumber":"2b-2c",
    "addr:postcode":"6021 cd",
    "addr:street":"Markt",
    "iso:country":"NL",
    "sg:address":"Markt 2B-2C",
    "sg:city":"Budel",
    "sg:orig_category":"Adviesbureaus Bouwkunde",
    "sg:phone":"+31 495 430 080",
    "sg:postcode":"6021 CD",
    "sg:province":"North Brabant",
    "wof:name":"Gogh, Bouwtechniek Van",
    "wof:placetype":"venue"
},
  "geometry": {"coordinates":[5.574706,51.274258],"type":"Point"}
}