{
  "type": "Feature",
  "properties": {
    "addr:full":"Metaalweg 11 Hapert Noord-Brabant 5527 AE",
    "addr:housenumber":"11",
    "addr:postcode":"5527 ae",
    "addr:street":"Metaalweg",
    "iso:country":"NL",
    "sg:address":"Metaalweg 11",
    "sg:city":"Hapert",
    "sg:orig_category":"Metaalafval, Schrootrecycling And Sloperijen",
    "sg:phone":"+31 497 386 033",
    "sg:postcode":"5527 AE",
    "sg:province":"Noord-Brabant",
    "wof:name":"Autorecycling Hapert Bv",
    "wof:placetype":"venue"
},
  "geometry": {"coordinates":[5.273336,51.371101],"type":"Point"}
}