{
  "type": "Feature",
  "properties": {
    "iso:country":"NL",
    "sg:address":"J Breukersstr 15-17",
    "sg:city":"Roermond",
    "sg:orig_category":"Verhuur",
    "sg:phone":"+31 475 331 500",
    "sg:postcode":"6041 BP",
    "sg:province":"Limburg",
    "wof:name":"Multihuur",
    "wof:placetype":"venue"
},
  "geometry": {"coordinates":[6.002024,51.208519],"type":"Point"}
}