{
  "type": "Feature",
  "properties": {
    "addr:full":"Prinses Beatrixlaan 1 Ouderkerk A/D Amstel Noord-Holland 1191 CC",
    "addr:housenumber":"1;a / d",
    "addr:postcode":"1191 cc",
    "addr:street":"Prinses Beatrixlaan",
    "iso:country":"NL",
    "sg:address":"Prinses Beatrixlaan 1",
    "sg:city":"Ouderkerk A/D Amstel",
    "sg:classifiers":[
        {
            "category":"Fast Food",
            "type":"Food & Drink"
        }
    ],
    "sg:phone":"+31 20 496 3938",
    "sg:postcode":"1191 CC",
    "sg:province":"Noord-Holland",
    "sg:tags":[
        "afhaal",
        "restaurant"
    ],
    "wof:name":"Snackkar 'T Stokpaardje",
    "wof:placetype":"venue"
},
  "geometry": {"coordinates":[4.906174,52.296947],"type":"Point"}
}