{
  "type": "Feature",
  "properties": {
    "addr:full":"Middel Broekwg 33 Honselersdyk Zuid-Holland 2675 KC",
    "addr:housenumber":"33",
    "addr:postcode":"2675 kc",
    "iso:country":"NL",
    "sg:address":"Middel Broekwg 33",
    "sg:city":"Honselersdyk",
    "sg:orig_category":"Bloemen En Planten - Groothandel",
    "sg:phone":"+31 174 633 363",
    "sg:postcode":"2675 KC",
    "sg:province":"Zuid-Holland",
    "wof:name":"Pyramide",
    "wof:placetype":"venue"
},
  "geometry": {"coordinates":[4.231427,51.999081],"type":"Point"}
}