{
  "type": "Feature",
  "properties": {
    "iso:country":"NL",
    "sg:address":"Steenbokstraat 48",
    "sg:city":"Hoorn Nh",
    "sg:orig_category":"Binnenhuisarchitecten",
    "sg:phone":"+31 229 235 087",
    "sg:postcode":"1622 BP",
    "sg:province":"Noord-Holland",
    "wof:name":"D.M. Koopman",
    "wof:placetype":"venue"
},
  "geometry": {"coordinates":[5.040537,52.642479],"type":"Point"}
}