{
  "type": "Feature",
  "properties": {
    "addr:full":"Steenbokstraat 48 Hoorn Nh Noord-Holland 1622 BP",
    "addr:housenumber":"48",
    "addr:postcode":"1622 bp",
    "addr:street":"Steenbokstraat",
    "iso:country":"NL",
    "sg:address":"Steenbokstraat 48",
    "sg:city":"Hoorn Nh",
    "sg:orig_category":"Binnenhuisarchitecten",
    "sg:phone":"+31 229 235 087",
    "sg:postcode":"1622 BP",
    "sg:province":"Noord-Holland",
    "wof:name":"D.M. Koopman",
    "wof:placetype":"venue"
},
  "geometry": {"coordinates":[5.040537,52.642479],"type":"Point"}
}