{
  "type": "Feature",
  "properties": {
    "addr:full":"Hoofdwg 128 Westerlee Gn Groningen 9678 PR",
    "addr:housenumber":"128",
    "addr:postcode":"gn;9678 pr",
    "iso:country":"NL",
    "sg:address":"Hoofdwg 128",
    "sg:city":"Westerlee Gn",
    "sg:orig_category":"Verenigingsgebouwen",
    "sg:phone":"+31 597 422 159",
    "sg:postcode":"9678 PR",
    "sg:province":"Groningen",
    "wof:name":"Antenne Verenigingscentrum",
    "wof:placetype":"venue"
},
  "geometry": {"coordinates":[6.987882,53.145535],"type":"Point"}
}