{
  "type": "Feature",
  "properties": {
    "addr:full":"Havendk 1 Bij Yerseke Zeeland 4401 NS",
    "addr:housenumber":"1",
    "addr:postcode":"4401 ns",
    "addr:street":"Havendk;Bij Yerseke",
    "iso:country":"NL",
    "sg:address":"Havendk 1 Bij",
    "sg:city":"Yerseke",
    "sg:orig_category":"Mosselen En Oesters",
    "sg:phone":"+31 113 573 333",
    "sg:postcode":"4401 NS",
    "sg:province":"Zeeland",
    "wof:name":"Murre, Gebr",
    "wof:placetype":"venue"
},
  "geometry": {"coordinates":[4.046035,51.491943],"type":"Point"}
}