{
  "type": "Feature",
  "properties": {
    "iso:country":"NL",
    "sg:address":"L Dam 2",
    "sg:city":"Urk",
    "sg:orig_category":"Verenigingsgebouwen",
    "sg:phone":"+31 527 682 400",
    "sg:postcode":"8321 XV",
    "sg:province":"NL.",
    "wof:name":"Ark, De",
    "wof:placetype":"venue"
},
  "geometry": {"coordinates":[5.602367,52.662838],"type":"Point"}
}