{
  "type": "Feature",
  "properties": {
    "addr:full":"Kortegracht 24 Amersfoort Utrecht 3811 KH",
    "addr:housenumber":"24",
    "addr:postcode":"3811 kh",
    "addr:street":"Kortegracht",
    "iso:country":"NL",
    "sg:address":"Kortegracht 24",
    "sg:city":"Amersfoort",
    "sg:orig_category":"Overheidsdiensten",
    "sg:phone":"+31 33 463 2931",
    "sg:postcode":"3811 KH",
    "sg:province":"Utrecht",
    "wof:name":"De Lanteern Buurthuis",
    "wof:placetype":"venue"
},
  "geometry": {"coordinates":[5.3860850334,52.1523246765],"type":"Point"}
}