{
  "type": "Feature",
  "properties": {
    "addr:full":"Slotmakersstraat 3 Makkum Fr Friesland 8754 EL",
    "addr:housenumber":"3",
    "addr:postcode":"8754 el",
    "addr:street":"Slotmakersstraat",
    "iso:country":"NL",
    "sg:address":"Slotmakersstraat 3",
    "sg:city":"Makkum Fr",
    "sg:orig_category":"Webdesign Bureaus",
    "sg:phone":"+31 515 231 412",
    "sg:postcode":"8754 EL",
    "sg:province":"Friesland",
    "sg:website":"http://www.flight23.com",
    "wof:name":"Flight 23",
    "wof:placetype":"venue"
},
  "geometry": {"coordinates":[5.4024319649,53.0561981201],"type":"Point"}
}