{
  "type": "Feature",
  "properties": {
    "addr:full":"Boterbloem 33 Beilen Drenthe 9411 CG",
    "addr:housenumber":"33",
    "addr:postcode":"9411 cg",
    "addr:street":"Boterbloem",
    "iso:country":"NL",
    "sg:address":"Boterbloem 33",
    "sg:city":"Beilen",
    "sg:orig_category":"Elektrotechnische Apparatuur - Fabrieken En Groothandel",
    "sg:phone":"+31 593 540 166",
    "sg:postcode":"9411 CG",
    "sg:province":"Drenthe",
    "wof:name":"Genetic Network Trading Systems",
    "wof:placetype":"venue"
},
  "geometry": {"coordinates":[6.505452,52.854691],"type":"Point"}
}