{
  "type": "Feature",
  "properties": {
    "addr:full":"Haskerlandstraat 12 Tilburg North Brabant 5045 HC",
    "addr:housenumber":"12",
    "addr:postcode":"5045 hc",
    "addr:street":"Haskerlandstraat",
    "iso:country":"NL",
    "sg:address":"Haskerlandstraat 12",
    "sg:city":"Tilburg",
    "sg:orig_category":"Muziekinstrumenten",
    "sg:phone":"+31 13 570 4322",
    "sg:postcode":"5045 HC",
    "sg:province":"North Brabant",
    "wof:name":"H. Van Der Burgt",
    "wof:placetype":"venue"
},
  "geometry": {"coordinates":[4.998957,51.582359],"type":"Point"}
}