{
  "type": "Feature",
  "properties": {
    "addr:full":"Lange Reke 5A Renesse Zeeland 4325 AA",
    "addr:housenumber":"5a",
    "addr:postcode":"4325 aa",
    "addr:street":"Lange Reke",
    "iso:country":"NL",
    "sg:address":"Lange Reke 5A",
    "sg:city":"Renesse",
    "sg:orig_category":"Kappers",
    "sg:phone":"+31 111 463 434",
    "sg:postcode":"4325 AA",
    "sg:province":"Zeeland",
    "wof:name":"Martin Hair",
    "wof:placetype":"venue"
},
  "geometry": {"coordinates":[3.773377,51.73246],"type":"Point"}
}