{
  "type": "Feature",
  "properties": {
    "addr:full":"Het Anker 1 Raamsdonksveer North Brabant 4941 RG",
    "addr:housenumber":"1",
    "addr:postcode":"4941 rg",
    "addr:street":"Het Anker",
    "iso:country":"NL",
    "sg:address":"Het Anker 1",
    "sg:city":"Raamsdonksveer",
    "sg:orig_category":"Juweliers",
    "sg:phone":"+31 162 512 351",
    "sg:postcode":"4941 RG",
    "sg:province":"North Brabant",
    "wof:name":"Kanters, Nel",
    "wof:placetype":"venue"
},
  "geometry": {"coordinates":[4.873573,51.695831],"type":"Point"}
}