{
  "type": "Feature",
  "properties": {
    "addr:full":"Voldersgracht 33 Delft South Holland 2611 EV",
    "addr:housenumber":"33",
    "addr:postcode":"2611 ev",
    "addr:street":"Voldersgracht",
    "iso:country":"NL",
    "sg:address":"Voldersgracht 33",
    "sg:city":"Delft",
    "sg:orig_category":"Veilingen",
    "sg:phone":"+31 15 214 6585",
    "sg:postcode":"2611 EV",
    "sg:province":"South Holland",
    "wof:name":"Top Galery",
    "wof:placetype":"venue"
},
  "geometry": {"coordinates":[4.36019,52.012764],"type":"Point"}
}