{
  "type": "Feature",
  "properties": {
    "addr:full":"Hoofdstr 35 Hoensbroek Limburg 6431 LB",
    "addr:housenumber":"35",
    "addr:postcode":"6431 lb",
    "addr:street":"Hoofdstr",
    "iso:country":"NL",
    "sg:address":"Hoofdstr 35",
    "sg:city":"Hoensbroek",
    "sg:orig_category":"Kappers",
    "sg:phone":"+31 45 521 3795",
    "sg:postcode":"6431 LB",
    "sg:province":"Limburg",
    "wof:name":"Hunnekens, R",
    "wof:placetype":"venue"
},
  "geometry": {"coordinates":[5.9252028465,50.9241676331],"type":"Point"}
}