{
  "type": "Feature",
  "properties": {
    "addr:full":"Dorpsstraat 2 Bemmel Gelderland 6681 BN",
    "addr:housenumber":"2",
    "addr:postcode":"6681 bn",
    "addr:street":"Dorpsstraat;Gelderland",
    "iso:country":"NL",
    "sg:address":"Dorpsstraat 2",
    "sg:city":"Bemmel",
    "sg:orig_category":"Banken And Kredietinstellingen",
    "sg:phone":"+31 481 465 207",
    "sg:postcode":"6681 BN",
    "sg:province":"Gelderland",
    "wof:name":"Ing Bank",
    "wof:placetype":"venue"
},
  "geometry": {"coordinates":[5.902298,51.89468],"type":"Point"}
}