{
  "type": "Feature",
  "properties": {
    "iso:country":"NL",
    "sg:address":"Kersstraat 7",
    "sg:city":"Terneuzen",
    "sg:orig_category":"Verlichting And Huishoudartikelen",
    "sg:phone":"+31 115 648 573",
    "sg:postcode":"4531 EV",
    "sg:province":"Zeeland",
    "wof:name":"Xenos",
    "wof:placetype":"venue"
},
  "geometry": {"coordinates":[3.827913,51.336308],"type":"Point"}
}