{
  "type": "Feature",
  "properties": {
    "addr:full":"Rijksstraatweg 79 Sleeuwijk Noord-Brabant 4254 XB",
    "addr:housenumber":"79",
    "addr:postcode":"4254 xb",
    "addr:street":"Rijksstraatweg",
    "iso:country":"NL",
    "sg:address":"Rijksstraatweg 79",
    "sg:city":"Sleeuwijk",
    "sg:orig_category":"Autokeuringen",
    "sg:phone":"+31 183 301 439",
    "sg:postcode":"4254 XB",
    "sg:province":"Noord-Brabant",
    "wof:name":"Verhoeven Auto'S Sleeuwijk Bv",
    "wof:placetype":"venue"
},
  "geometry": {"coordinates":[4.951587,51.810383],"type":"Point"}
}