{
  "type": "Feature",
  "properties": {
    "iso:country":"NL",
    "sg:address":"Statenwg 131",
    "sg:city":"Venhorst",
    "sg:orig_category":"Heftrucks",
    "sg:phone":"+31 492 359 002",
    "sg:postcode":"5428 NL",
    "sg:province":"Noord-Brabant",
    "wof:name":"Kooi",
    "wof:placetype":"venue"
},
  "geometry": {"coordinates":[5.74823,51.610619],"type":"Point"}
}