{
  "type": "Feature",
  "properties": {
    "addr:full":"Statenwg 131 Venhorst Noord-Brabant 5428 NL",
    "addr:housenumber":"131",
    "addr:postcode":"5428 nl",
    "iso:country":"NL",
    "sg:address":"Statenwg 131",
    "sg:city":"Venhorst",
    "sg:orig_category":"Heftrucks",
    "sg:phone":"+31 492 359 002",
    "sg:postcode":"5428 NL",
    "sg:province":"Noord-Brabant",
    "wof:name":"Kooi",
    "wof:placetype":"venue"
},
  "geometry": {"coordinates":[5.74823,51.610619],"type":"Point"}
}