{
  "type": "Feature",
  "properties": {
    "addr:full":"Dalwg 21 Zeist Utrecht 3707 BG",
    "addr:housenumber":"21",
    "addr:postcode":"3707",
    "addr:street":"Dalwg",
    "iso:country":"NL",
    "sg:address":"Dalwg 21",
    "sg:city":"Zeist",
    "sg:orig_category":"Agenturen En Commissiehandel",
    "sg:phone":"+31 30 691 1617",
    "sg:postcode":"3707 BG",
    "sg:province":"Utrecht",
    "sg:website":"http://www.arteza.nl",
    "wof:name":"Arteza",
    "wof:placetype":"venue"
},
  "geometry": {"coordinates":[5.248316,52.093987],"type":"Point"}
}