{
  "type": "Feature",
  "properties": {
    "addr:full":"Jan Vosstraat 60 'S Gravenhage Zuid-Holland 2533 TX",
    "addr:housenumber":"60",
    "addr:postcode":"2533 tx",
    "addr:street":"Jan Vosstraat;' S",
    "iso:country":"NL",
    "sg:address":"Jan Vosstraat 60",
    "sg:city":"'S Gravenhage",
    "sg:orig_category":"Werving And Selectie Van Tijdelijk Personeel And Uitzendkantoren",
    "sg:phone":"+31 70 389 2186",
    "sg:postcode":"2533 TX",
    "sg:province":"Zuid-Holland",
    "wof:name":"Orgineel",
    "wof:placetype":"venue"
},
  "geometry": {"coordinates":[4.296148777,52.0507278442],"type":"Point"}
}