{
  "type": "Feature",
  "properties": {
    "addr:full":"Lierweg 48G De Lier South Holland 2678 CX",
    "addr:housenumber":"48g",
    "addr:postcode":"2678 cx",
    "addr:street":"Lierweg",
    "iso:country":"NL",
    "sg:address":"Lierweg 48G",
    "sg:city":"De Lier",
    "sg:orig_category":"Pompen And Compressoren Fab",
    "sg:phone":"+31 174 517 435",
    "sg:postcode":"2678 CX",
    "sg:province":"South Holland",
    "wof:name":"Laadklepservice Westland",
    "wof:placetype":"venue"
},
  "geometry": {"coordinates":[4.261776,51.977104],"type":"Point"}
}