{
  "type": "Feature",
  "properties": {
    "addr:full":"Fornebubaan 21 Rotterdam South Holland 3045 AV",
    "addr:housenumber":"21",
    "addr:postcode":"3045 av",
    "addr:street":"Fornebubaan",
    "iso:country":"NL",
    "sg:address":"Fornebubaan 21",
    "sg:city":"Rotterdam",
    "sg:orig_category":"Koeriersdiensten",
    "sg:phone":"+31 10 262 2666",
    "sg:postcode":"3045 AV",
    "sg:province":"South Holland",
    "wof:name":"Rapid Air Bv",
    "wof:placetype":"venue"
},
  "geometry": {"coordinates":[4.44001,51.949421],"type":"Point"}
}