{
  "type": "Feature",
  "properties": {
    "addr:full":"Westerkd 13 Groningen Groningen 9718 AR",
    "addr:housenumber":"13",
    "addr:postcode":"9718",
    "addr:street":"Westerkd",
    "iso:country":"NL",
    "sg:address":"Westerkd 13",
    "sg:city":"Groningen",
    "sg:orig_category":"Zonnebank- En Solariumcentra",
    "sg:phone":"+31 50 318 3550",
    "sg:postcode":"9718 AR",
    "sg:province":"Groningen",
    "sg:website":"http://www.sundays.nl",
    "wof:name":"Sunday'S",
    "wof:placetype":"venue"
},
  "geometry": {"coordinates":[6.574715,53.217144],"type":"Point"}
}