{
  "type": "Feature",
  "properties": {
    "addr:full":"Goudsbloemln 113 S Gravenhage South Holland 2565 CR",
    "addr:housenumber":"113",
    "addr:postcode":"2565 cr",
    "addr:street":"S Gravenhage",
    "iso:country":"NL",
    "sg:address":"Goudsbloemln 113",
    "sg:city":"S Gravenhage",
    "sg:orig_category":"Postkantoren",
    "sg:phone":"+31 70 360 6547",
    "sg:postcode":"2565 CR",
    "sg:province":"South Holland",
    "sg:website":"http://www.postkantoor.nl",
    "wof:name":"Postkantoor",
    "wof:placetype":"venue"
},
  "geometry": {"coordinates":[4.26129,52.076382],"type":"Point"}
}