{
  "type": "Feature",
  "properties": {
    "iso:country":"NL",
    "sg:address":"F C Kuyperstraat 3",
    "sg:city":"Soest",
    "sg:orig_category":"Bedrijfscatering",
    "sg:phone":"+31 35 602 4664",
    "sg:postcode":"3761 EG",
    "sg:province":"Utrecht",
    "wof:name":"Le Saladier",
    "wof:placetype":"venue"
},
  "geometry": {"coordinates":[5.297708,52.185932],"type":"Point"}
}