{
  "type": "Feature",
  "properties": {
    "addr:full":"Borghoutspk 58 Veldhoven Noord-Brabant 5502 JZ",
    "addr:housenumber":"58",
    "addr:postcode":"5502 jz",
    "addr:street":"Borghoutspk",
    "iso:country":"NL",
    "sg:address":"Borghoutspk 58",
    "sg:city":"Veldhoven",
    "sg:orig_category":"Accountants - Administratie- Consulenten En -Kantoren",
    "sg:phone":"+31 40 213 3004",
    "sg:postcode":"5502 JZ",
    "sg:province":"Noord-Brabant",
    "wof:name":"H & S",
    "wof:placetype":"venue"
},
  "geometry": {"coordinates":[5.42641,51.42971],"type":"Point"}
}