{
  "type": "Feature",
  "properties": {
    "addr:full":"Bloemkeshof 116 Zaltbommel Gelderland 5301 WT",
    "addr:housenumber":"116",
    "addr:postcode":"5301 wt",
    "addr:street":"Bloemkeshof;Gelderland",
    "iso:country":"NL",
    "sg:address":"Bloemkeshof 116",
    "sg:city":"Zaltbommel",
    "sg:orig_category":"Kinderkleding",
    "sg:phone":"+31 418 513 841",
    "sg:postcode":"5301 WT",
    "sg:province":"Gelderland",
    "wof:name":"B'Wiched",
    "wof:placetype":"venue"
},
  "geometry": {"coordinates":[5.235266,51.807693],"type":"Point"}
}