{
  "type": "Feature",
  "properties": {
    "addr:full":"Eekwal 4 Zwolle Overijssel 8011 LD",
    "addr:housenumber":"4",
    "addr:postcode":"8011 ld",
    "addr:street":"Eekwal",
    "iso:country":"NL",
    "sg:address":"Eekwal 4",
    "sg:city":"Zwolle",
    "sg:orig_category":"Advocaten And Juridische Adviseurs",
    "sg:phone":"+31 38 421 5221",
    "sg:postcode":"8011 LD",
    "sg:province":"Overijssel",
    "wof:name":"Stein Advocaten Zwolle",
    "wof:placetype":"venue"
},
  "geometry": {"coordinates":[6.089703,52.510746],"type":"Point"}
}