{
  "type": "Feature",
  "properties": {
    "iso:country":"NL",
    "sg:address":"Dorpsstr 43",
    "sg:city":"Putten",
    "sg:orig_category":"Postkantoren",
    "sg:phone":"+31 341 360 506",
    "sg:postcode":"3881 BA",
    "sg:province":"Gelderland",
    "sg:website":"http://www.postkantoor.nl",
    "wof:name":"Postkantoor",
    "wof:placetype":"venue"
},
  "geometry": {"coordinates":[5.604758,52.260315],"type":"Point"}
}