{
  "type": "Feature",
  "properties": {
    "addr:full":"Patronaatstraat 94 Kerkrade Limburg 6466 HR",
    "addr:housenumber":"94",
    "addr:postcode":"6466 hr",
    "addr:street":"Patronaatstraat",
    "iso:country":"NL",
    "sg:address":"Patronaatstraat 94",
    "sg:city":"Kerkrade",
    "sg:orig_category":"Fotostudio'S And Fotografen",
    "sg:phone":"+31 45 541 5190",
    "sg:postcode":"6466 HR",
    "sg:province":"Limburg",
    "wof:name":"N. Johnen Fotografie-Grafische Vormgevin",
    "wof:placetype":"venue"
},
  "geometry": {"coordinates":[6.024948,50.856369],"type":"Point"}
}