{
  "type": "Feature",
  "properties": {
    "iso:country":"NL",
    "sg:address":"Wijheseweg 10",
    "sg:city":"Raalte",
    "sg:orig_category":"Bloemen And Planten",
    "sg:phone":"+31 572 355 811",
    "sg:postcode":"8101 MB",
    "sg:province":"NL.08",
    "wof:name":"Kwekerij W Binnenpoorte",
    "wof:placetype":"venue"
},
  "geometry": {"coordinates":[6.237949,52.385201],"type":"Point"}
}