{
  "type": "Feature",
  "properties": {
    "addr:full":"Wijheseweg 10 Raalte NL.08 8101 MB",
    "addr:housenumber":"10;nl.08",
    "addr:postcode":"8101 mb",
    "addr:street":"Wijheseweg",
    "iso:country":"NL",
    "sg:address":"Wijheseweg 10",
    "sg:city":"Raalte",
    "sg:orig_category":"Bloemen And Planten",
    "sg:phone":"+31 572 355 811",
    "sg:postcode":"8101 MB",
    "sg:province":"NL.08",
    "wof:name":"Kwekerij W Binnenpoorte",
    "wof:placetype":"venue"
},
  "geometry": {"coordinates":[6.237949,52.385201],"type":"Point"}
}