{
  "type": "Feature",
  "properties": {
    "addr:full":"Professor G Molierestr 44 Wieringerwerf Noord-Holland 1771 AG",
    "addr:housenumber":"44",
    "addr:postcode":"1771",
    "addr:street":"Professor G Molierestr",
    "iso:country":"NL",
    "sg:address":"Professor G Molierestr 44",
    "sg:city":"Wieringerwerf",
    "sg:orig_category":"Paramedische Behandelingen",
    "sg:phone":"+31 227 601 470",
    "sg:postcode":"1771 AG",
    "sg:province":"Noord-Holland",
    "wof:name":"Kruiswerk Kop Van Noord-Holland",
    "wof:placetype":"venue"
},
  "geometry": {"coordinates":[5.022714,52.850872],"type":"Point"}
}