{
  "type": "Feature",
  "properties": {
    "iso:country":"NL",
    "sg:address":"L Herenvest 82-84",
    "sg:city":"Haarlem",
    "sg:orig_category":"Onderhoudswerken",
    "sg:phone":"+31 23 535 4304",
    "sg:postcode":"2011 BV",
    "sg:province":"North Holland",
    "wof:name":"Koene",
    "wof:placetype":"venue"
},
  "geometry": {"coordinates":[4.643515,52.378403],"type":"Point"}
}