{
  "type": "Feature",
  "properties": {
    "iso:country":"NL",
    "sg:address":"Escamplaan 870",
    "sg:city":"'S Gravenhage",
    "sg:orig_category":"Bloemen And Planten",
    "sg:phone":"+31 70 366 9392",
    "sg:postcode":"2547 EX",
    "sg:province":"Zuid-Holland",
    "wof:name":"Bloemen En Planten Kas In",
    "wof:placetype":"venue"
},
  "geometry": {"coordinates":[4.263753,52.058048],"type":"Point"}
}