{
  "type": "Feature",
  "properties": {
    "iso:country":"NL",
    "sg:address":"L Achterwg 28",
    "sg:city":"S Heer Arendskerke",
    "sg:orig_category":"Keukens",
    "sg:phone":"+31 6 21535839",
    "sg:postcode":"4458 AC",
    "sg:province":"Zeeland",
    "wof:name":"Tolhoek",
    "wof:placetype":"venue"
},
  "geometry": {"coordinates":[3.821584,51.491302],"type":"Point"}
}