{
  "type": "Feature",
  "properties": {
    "addr:full":"Nieuwezyds Kolk 25 Amsterdam North Holland 1012 PV",
    "addr:housenumber":"25",
    "addr:postcode":"1012 pv",
    "addr:street":"Kolk",
    "iso:country":"NL",
    "sg:address":"Nieuwezyds Kolk 25",
    "sg:city":"Amsterdam",
    "sg:orig_category":"Werving En Selectie",
    "sg:phone":"+31 20 421 1577",
    "sg:postcode":"1012 PV",
    "sg:province":"North Holland",
    "wof:name":"Htnk",
    "wof:placetype":"venue"
},
  "geometry": {"coordinates":[4.8942217827,52.3761138916],"type":"Point"}
}