{
  "type": "Feature",
  "properties": {
    "addr:full":"Kapellebosln 2A Noordwyk Zh Zuid-Holland 2204 AK",
    "addr:housenumber":"2a",
    "addr:postcode":"2204 ak",
    "addr:street":"Kapellebosln",
    "iso:country":"NL",
    "sg:address":"Kapellebosln 2A",
    "sg:city":"Noordwyk Zh",
    "sg:orig_category":"Adviesbureaus Bedrijfsorganisatie",
    "sg:phone":"+31 252 374 974",
    "sg:postcode":"2204 AK",
    "sg:province":"Zuid-Holland",
    "wof:name":"Quirine Bv",
    "wof:placetype":"venue"
},
  "geometry": {"coordinates":[4.486295,52.284084],"type":"Point"}
}