{
  "type": "Feature",
  "properties": {
    "addr:full":"Dorpsstraat 77 Bleiswijk Zuid-Holland 2665 BH",
    "addr:housenumber":"77",
    "addr:postcode":"2665 bh",
    "addr:street":"Dorpsstraat",
    "iso:country":"NL",
    "sg:address":"Dorpsstraat 77",
    "sg:city":"Bleiswijk",
    "sg:orig_category":"Vaste And Vloeibare Brandstoffen",
    "sg:phone":"+31 10 521 2552",
    "sg:postcode":"2665 BH",
    "sg:province":"Zuid-Holland",
    "wof:name":"Firma J.H. Dammes",
    "wof:placetype":"venue"
},
  "geometry": {"coordinates":[4.530812,52.011387],"type":"Point"}
}