{
  "type": "Feature",
  "properties": {
    "addr:full":"Postbus 78 Wageningen Gelderland 6700 AB",
    "addr:housenumber":"78",
    "addr:postcode":"6700 ab",
    "addr:street":"Postbus;Gelderland",
    "iso:country":"NL",
    "sg:address":"Postbus 78",
    "sg:city":"Wageningen",
    "sg:orig_category":"Onderwijsmateriaal",
    "sg:phone":"+31 317 472 711",
    "sg:postcode":"6700 AB",
    "sg:province":"Gelderland",
    "sg:website":"http://www.stoas.nl",
    "wof:name":"Stoas",
    "wof:placetype":"venue"
},
  "geometry": {"coordinates":[5.660976,51.964355],"type":"Point"}
}