{
  "type": "Feature",
  "properties": {
    "addr:full":"Berg 47 Nuenen Noord-Brabant 5671 CB",
    "addr:housenumber":"47",
    "addr:postcode":"5671 cb",
    "addr:street":"Berg",
    "iso:country":"NL",
    "sg:address":"Berg 47",
    "sg:city":"Nuenen",
    "sg:orig_category":"Werving And Selectie Van Tijdelijk Personeel And Uitzendkantoren",
    "sg:phone":"+31 40 283 6990",
    "sg:postcode":"5671 CB",
    "sg:province":"Noord-Brabant",
    "wof:name":"Aps Uitzendbureau",
    "wof:placetype":"venue"
},
  "geometry": {"coordinates":[5.5505518913,51.4781455994],"type":"Point"}
}