{
  "type": "Feature",
  "properties": {
    "addr:full":"Haaksbergerstr 906 Enschede NL.08 7545 PG",
    "addr:housenumber":"906",
    "addr:postcode":"7545",
    "addr:street":"Pg",
    "iso:country":"NL",
    "sg:address":"Haaksbergerstr 906",
    "sg:city":"Enschede",
    "sg:orig_category":"Dierenziektekosten- Verzekeringen",
    "sg:phone":"+31 800 029959",
    "sg:postcode":"7545 PG",
    "sg:province":"NL.08",
    "wof:name":"Nhz, Dierenkostenverz",
    "wof:placetype":"venue"
},
  "geometry": {"coordinates":[6.84747,52.20583],"type":"Point"}
}