{
  "type": "Feature",
  "properties": {
    "addr:full":"1E Wormenseweg 95 Apeldoorn Gelderland 7331 DC",
    "addr:housenumber":"95",
    "addr:postcode":"7331",
    "addr:street":"1E Wormenseweg;Gelderland",
    "iso:country":"NL",
    "sg:address":"1E Wormenseweg 95",
    "sg:city":"Apeldoorn",
    "sg:orig_category":"Diverse Consumentenartikelen Gh",
    "sg:phone":"+31 55 542 0015",
    "sg:postcode":"7331 DC",
    "sg:province":"Gelderland",
    "wof:name":"Handelsonderneming Evers",
    "wof:placetype":"venue"
},
  "geometry": {"coordinates":[5.96948,52.204227],"type":"Point"}
}