{
  "type": "Feature",
  "properties": {
    "addr:full":"Plantenstraat 8 Doetinchem Gelderland 7001 EZ",
    "addr:housenumber":"8",
    "addr:postcode":"7001 ez",
    "addr:street":"Plantenstraat;Gelderland",
    "iso:country":"NL",
    "sg:address":"Plantenstraat 8",
    "sg:city":"Doetinchem",
    "sg:classifiers":[
        {
            "category":"Professional",
            "subcategory":"Accounting & Tax Preparation",
            "type":"Services"
        }
    ],
    "sg:phone":"+31 314 332 241",
    "sg:postcode":"7001 EZ",
    "sg:province":"Gelderland",
    "sg:tags":[
        "accountant"
    ],
    "wof:name":"Accountants- En Belasting- Adviesbureau Dales Bv",
    "wof:placetype":"venue"
},
  "geometry": {"coordinates":[6.293428,51.962524],"type":"Point"}
}