{
  "type": "Feature",
  "properties": {
    "addr:full":"Bleihof 71 Voorhout Zuid-Holland 2215 XT",
    "addr:housenumber":"71",
    "addr:postcode":"2215 xt",
    "addr:street":"Bleihof",
    "iso:country":"NL",
    "sg:address":"Bleihof 71",
    "sg:city":"Voorhout",
    "sg:orig_category":"Verzekeringen - Verzekeringskantoren",
    "sg:phone":"+31 252 226 322",
    "sg:postcode":"2215 XT",
    "sg:province":"Zuid-Holland",
    "wof:name":"Nationaal Spaarfonds",
    "wof:placetype":"venue"
},
  "geometry": {"coordinates":[4.497175,52.227047],"type":"Point"}
}