{
  "type": "Feature",
  "properties": {
    "addr:full":"Russischestraat 29 Rotterdam South Holland 3028 BD",
    "addr:housenumber":"29",
    "addr:postcode":"3028 bd",
    "addr:street":"Russischestraat",
    "iso:country":"NL",
    "sg:address":"Russischestraat 29",
    "sg:city":"Rotterdam",
    "sg:orig_category":"Kinderopvang Behalve Thuis",
    "sg:phone":"+31 10 437 6474",
    "sg:postcode":"3028 BD",
    "sg:province":"South Holland",
    "wof:name":"Katinka",
    "wof:placetype":"venue"
},
  "geometry": {"coordinates":[4.419989,51.914894],"type":"Point"}
}