{
  "type": "Feature",
  "properties": {
    "addr:full":"Leestraat 7 Baarn Utrecht 3743 EH",
    "addr:housenumber":"7",
    "addr:postcode":"3743 eh",
    "addr:street":"Leestraat",
    "iso:country":"NL",
    "sg:address":"Leestraat 7",
    "sg:city":"Baarn",
    "sg:orig_category":"Diverse Bedrijfsinstallaties Gh",
    "sg:phone":"+31 35 543 2570",
    "sg:postcode":"3743 EH",
    "sg:province":"Utrecht",
    "wof:name":"Reba",
    "wof:placetype":"venue"
},
  "geometry": {"coordinates":[5.289392,52.210258],"type":"Point"}
}