{
  "type": "Feature",
  "properties": {
    "addr:full":"Minkeloos 10A Noordeloos Zuid-Holland 4225 SP",
    "addr:housenumber":"10a",
    "addr:postcode":"4225 sp",
    "addr:street":"Minkeloos",
    "iso:country":"NL",
    "sg:address":"Minkeloos 10A",
    "sg:city":"Noordeloos",
    "sg:orig_category":"Loonbedrijven",
    "sg:phone":"+31 183 582 207",
    "sg:postcode":"4225 SP",
    "sg:province":"Zuid-Holland",
    "wof:name":"Habo, Loon-Grondverzetbedrijf",
    "wof:placetype":"venue"
},
  "geometry": {"coordinates":[4.97143,51.893368],"type":"Point"}
}