{
  "type": "Feature",
  "properties": {
    "addr:full":"V Broeckhovenln 4X S Hertogenbosch Noord-Brabant 5213 HX",
    "addr:housenumber":"4x",
    "addr:postcode":"5213 hx",
    "addr:street":"Broeckhovenln;S Hertogenbosch",
    "iso:country":"NL",
    "sg:address":"V Broeckhovenln 4X",
    "sg:city":"S Hertogenbosch",
    "sg:orig_category":"Administratie- En Boekhoudkantoren",
    "sg:phone":"+31 73 690 0320",
    "sg:postcode":"5213 HX",
    "sg:province":"Noord-Brabant",
    "wof:name":"Bontekoe",
    "wof:placetype":"venue"
},
  "geometry": {"coordinates":[5.331093,51.696232],"type":"Point"}
}