{
  "type": "Feature",
  "properties": {
    "addr:full":"A M De Jongln 9 Blaricum Noord-Holland 1261 DB",
    "addr:housenumber":"9",
    "addr:postcode":"1261 db",
    "addr:street":"A M De Jongln",
    "iso:country":"NL",
    "sg:address":"A M De Jongln 9",
    "sg:city":"Blaricum",
    "sg:orig_category":"Vertalers",
    "sg:phone":"+31 35 531 3714",
    "sg:postcode":"1261 DB",
    "sg:province":"Noord-Holland",
    "wof:name":"Leusden, Van",
    "wof:placetype":"venue"
},
  "geometry": {"coordinates":[5.243439,52.273277],"type":"Point"}
}