{
  "type": "Feature",
  "properties": {
    "addr:full":"Jeroen Boschstraat 2 Bergen Lb Limburg 5854 CZ",
    "addr:housenumber":"2",
    "addr:postcode":"lb;5854",
    "addr:street":"Jeroen Boschstraat",
    "iso:country":"NL",
    "sg:address":"Jeroen Boschstraat 2",
    "sg:city":"Bergen Lb",
    "sg:orig_category":"Banken And Kredietinstellingen",
    "sg:phone":"+31 485 348 888",
    "sg:postcode":"5854 CZ",
    "sg:province":"Limburg",
    "wof:name":"Rabobank",
    "wof:placetype":"venue"
},
  "geometry": {"coordinates":[-93.129936,36.705662],"type":"Point"}
}