{
  "type": "Feature",
  "properties": {
    "addr:full":"Kinderbalk 30 Hoorn Nh Noord-Holland 1628 MD",
    "addr:housenumber":"30",
    "addr:postcode":"1628",
    "addr:street":"Kinderbalk",
    "iso:country":"NL",
    "sg:address":"Kinderbalk 30",
    "sg:city":"Hoorn Nh",
    "sg:orig_category":"Fruit And Groenten Gh",
    "sg:phone":"+31 229 274 785",
    "sg:postcode":"1628 MD",
    "sg:province":"Noord-Holland",
    "wof:name":"Lewan Vof",
    "wof:placetype":"venue"
},
  "geometry": {"coordinates":[5.092767,52.654045],"type":"Point"}
}