{
  "type": "Feature",
  "properties": {
    "addr:full":"Klokstg 11 Leiden Zuid-Holland 2311 SK",
    "addr:housenumber":"11",
    "addr:street":"Klokstg;2311",
    "iso:country":"NL",
    "sg:address":"Klokstg 11",
    "sg:city":"Leiden",
    "sg:orig_category":"Antiquiteiten",
    "sg:phone":"+31 71 512 0225",
    "sg:postcode":"2311 SK",
    "sg:province":"Zuid-Holland",
    "wof:name":"Malo",
    "wof:placetype":"venue"
},
  "geometry": {"coordinates":[4.487093,52.157112],"type":"Point"}
}