{
  "type": "Feature",
  "properties": {
    "addr:full":"Lingedk 141 Geldermalsen Gelderland 4191 VD",
    "addr:housenumber":"141",
    "addr:postcode":"4191 vd",
    "addr:street":"Gelderland",
    "iso:country":"NL",
    "sg:address":"Lingedk 141",
    "sg:city":"Geldermalsen",
    "sg:orig_category":"Bestratingen",
    "sg:phone":"+31 345 571 823",
    "sg:postcode":"4191 VD",
    "sg:province":"Gelderland",
    "wof:name":"Lith, J Van",
    "wof:placetype":"venue"
},
  "geometry": {"coordinates":[5.316169,51.88538],"type":"Point"}
}