{
  "type": "Feature",
  "properties": {
    "addr:full":"Schutstr 16 Kloosterhaar Overijssel 7694 AZ",
    "addr:housenumber":"16",
    "addr:postcode":"7694 az",
    "addr:street":"Schutstr",
    "iso:country":"NL",
    "sg:address":"Schutstr 16",
    "sg:city":"Kloosterhaar",
    "sg:orig_category":"Hek- En Rasterwerken",
    "sg:phone":"+31 523 242 376",
    "sg:postcode":"7694 AZ",
    "sg:province":"Overijssel",
    "wof:name":"Zondag, K",
    "wof:placetype":"venue"
},
  "geometry": {"coordinates":[6.674845,52.499714],"type":"Point"}
}