{
  "type": "Feature",
  "properties": {
    "addr:full":"Benedenrywg 67 Ridderkerk Zuid-Holland 2983 GA",
    "addr:housenumber":"67",
    "addr:postcode":"2983 ga",
    "addr:street":"Benedenrywg",
    "iso:country":"NL",
    "sg:address":"Benedenrywg 67",
    "sg:city":"Ridderkerk",
    "sg:orig_category":"Projectontwikkeling",
    "sg:phone":"+31 180 415 500",
    "sg:postcode":"2983 GA",
    "sg:province":"Zuid-Holland",
    "wof:name":"Bouhuys Bv",
    "wof:placetype":"venue"
},
  "geometry": {"coordinates":[4.602569,51.876022],"type":"Point"}
}