{
  "type": "Feature",
  "properties": {
    "addr:full":"Overschies Kleiwg 581 Rotterdam Zuid-Holland 3045 LJ",
    "addr:housenumber":"581",
    "addr:postcode":"3045 lj",
    "iso:country":"NL",
    "sg:address":"Overschies Kleiwg 581",
    "sg:city":"Rotterdam",
    "sg:orig_category":"Autoschade- Herstelbedrijven",
    "sg:phone":"+31 10 265 2211",
    "sg:postcode":"3045 LJ",
    "sg:province":"Zuid-Holland",
    "wof:name":"Eichelsheim",
    "wof:placetype":"venue"
},
  "geometry": {"coordinates":[4.456208,51.94022],"type":"Point"}
}