{
  "type": "Feature",
  "properties": {
    "addr:full":"F V Borselenln 15 Voorhout South Holland 2215 RM",
    "addr:housenumber":"15",
    "addr:postcode":"2215 rm",
    "addr:street":"Borselenln",
    "iso:country":"NL",
    "sg:address":"F V Borselenln 15",
    "sg:city":"Voorhout",
    "sg:orig_category":"Bloembollen - Groothandel",
    "sg:phone":"+31 252 240 280",
    "sg:postcode":"2215 RM",
    "sg:province":"South Holland",
    "wof:name":"Koning Holl Bv",
    "wof:placetype":"venue"
},
  "geometry": {"coordinates":[4.48252,52.221874],"type":"Point"}
}