{
  "type": "Feature",
  "properties": {
    "addr:full":"Brabis 19 Eindhoven Noord-Brabant 5641 JT",
    "addr:housenumber":"19",
    "addr:postcode":"5641 jt",
    "addr:street":"Brabis",
    "iso:country":"NL",
    "sg:address":"Brabis 19",
    "sg:city":"Eindhoven",
    "sg:orig_category":"Artiestenbureaus",
    "sg:phone":"+31 40 281 6413",
    "sg:postcode":"5641 JT",
    "sg:province":"Noord-Brabant",
    "wof:name":"City Band",
    "wof:placetype":"venue"
},
  "geometry": {"coordinates":[5.52428,51.450779],"type":"Point"}
}