{
  "type": "Feature",
  "properties": {
    "addr:full":"Brouwersgr 276 Amsterdam Noord-Holland 1013 HG",
    "addr:housenumber":"276",
    "addr:postcode":"1013 hg",
    "iso:country":"NL",
    "sg:address":"Brouwersgr 276",
    "sg:city":"Amsterdam",
    "sg:orig_category":"Verenigingen En Stichtingen",
    "sg:phone":"+31 20 523 1523",
    "sg:postcode":"1013 HG",
    "sg:province":"Noord-Holland",
    "wof:name":"Fonds Voor Beeldende Kunsten Vormgeving En Bouwkunst, Sticht",
    "wof:placetype":"venue"
},
  "geometry": {"coordinates":[4.884548,52.383106],"type":"Point"}
}