{
  "type": "Feature",
  "properties": {
    "addr:full":"Grotestr 20 Venray Limburg 5801 BG",
    "addr:housenumber":"20",
    "addr:postcode":"5801",
    "addr:street":"Grotestr",
    "iso:country":"NL",
    "sg:address":"Grotestr 20",
    "sg:city":"Venray",
    "sg:orig_category":"Zoetwaren - Winkels",
    "sg:phone":"+31 478 511 328",
    "sg:postcode":"5801 BG",
    "sg:province":"Limburg",
    "wof:name":"Jamin",
    "wof:placetype":"venue"
},
  "geometry": {"coordinates":[5.975534,51.52623],"type":"Point"}
}