{
  "type": "Feature",
  "properties": {
    "addr:full":"Merwedepln 63Hg Amsterdam North Holland 1078 ND",
    "addr:postcode":"1078 nd",
    "iso:country":"NL",
    "sg:address":"Merwedepln 63Hg",
    "sg:city":"Amsterdam",
    "sg:orig_category":"Video - Faciliteiten En Producties",
    "sg:phone":"+31 20 671 8140",
    "sg:postcode":"1078 ND",
    "sg:province":"North Holland",
    "wof:name":"Lemaire, Rob",
    "wof:placetype":"venue"
},
  "geometry": {"coordinates":[4.89985,52.345509],"type":"Point"}
}