{
  "type": "Feature",
  "properties": {
    "addr:full":"Schadewijkpad 2 Twello Gelderland 7391 TJ",
    "addr:housenumber":"2",
    "addr:postcode":"7391 tj",
    "addr:street":"Schadewijkpad;Gelderland",
    "iso:country":"NL",
    "sg:address":"Schadewijkpad 2",
    "sg:city":"Twello",
    "sg:orig_category":"Kappers",
    "sg:phone":"+31 571 275 077",
    "sg:postcode":"7391 TJ",
    "sg:province":"Gelderland",
    "wof:name":"Haarmode V.D. Linde",
    "wof:placetype":"venue"
},
  "geometry": {"coordinates":[6.1112070084,52.231628418],"type":"Point"}
}