{
  "type": "Feature",
  "properties": {
    "addr:full":"Vlasakker 25 Zevenhoven Zuid-Holland 2435 WV",
    "addr:housenumber":"25",
    "addr:postcode":"2435 wv",
    "addr:street":"Vlasakker",
    "iso:country":"NL",
    "sg:address":"Vlasakker 25",
    "sg:city":"Zevenhoven",
    "sg:orig_category":"Adviesbureaus",
    "sg:phone":"+31 172 538 156",
    "sg:postcode":"2435 WV",
    "sg:province":"Zuid-Holland",
    "wof:name":"Ravco Vof",
    "wof:placetype":"venue"
},
  "geometry": {"coordinates":[4.776937,52.182346],"type":"Point"}
}