{
  "type": "Feature",
  "properties": {
    "iso:country":"NL",
    "sg:address":"Nieuwediep 7",
    "sg:city":"Nieuwediep",
    "sg:orig_category":"Meubelmakerijen",
    "sg:phone":"+31 598 467 886",
    "sg:postcode":"9512 SC",
    "sg:province":"Drenthe",
    "sg:website":"http://www.kaywanna.nl.hetnet",
    "wof:name":"Pb Exclusieve",
    "wof:placetype":"venue"
},
  "geometry": {"coordinates":[6.847663,53.048794],"type":"Point"}
}