{
  "type": "Feature",
  "properties": {
    "addr:full":"Kl Oever 2 Meppel Provincie Drenthe 7941 BK",
    "addr:housenumber":"2",
    "addr:postcode":"7941 bk",
    "addr:street":"Kl Oever;Provincie Drenthe",
    "iso:country":"NL",
    "sg:address":"Kl Oever 2",
    "sg:city":"Meppel",
    "sg:orig_category":"Vakorganisaties",
    "sg:phone":"+31 522 252 878",
    "sg:postcode":"7941 BK",
    "sg:province":"Provincie Drenthe",
    "wof:name":"Abvakabo Fnv",
    "wof:placetype":"venue"
},
  "geometry": {"coordinates":[6.188257,52.697243],"type":"Point"}
}