{
  "type": "Feature",
  "properties": {
    "addr:full":"Munsterstraat 9 Deventer NL.08 7418 EV",
    "addr:housenumber":"9;nl.08",
    "addr:postcode":"7418 ev",
    "addr:street":"Munsterstraat",
    "iso:country":"NL",
    "sg:address":"Munsterstraat 9",
    "sg:city":"Deventer",
    "sg:orig_category":"Makelaars In Onroerend Goed",
    "sg:phone":"+31 570 662 929",
    "sg:postcode":"7418 EV",
    "sg:province":"NL.08",
    "wof:name":"Homburg Exploitatie Mij Bv",
    "wof:placetype":"venue"
},
  "geometry": {"coordinates":[6.185918,52.238407],"type":"Point"}
}