{
  "type": "Feature",
  "properties": {
    "addr:full":"Hertogin Johannasingel 38 Oss Virginia 5345 AJ",
    "addr:housenumber":"38",
    "addr:postcode":"5345 aj",
    "addr:street":"Hertogin Johannasingel",
    "iso:country":"NL",
    "sg:address":"Hertogin Johannasingel 38",
    "sg:city":"Oss",
    "sg:orig_category":"Verzekeringen - Verzekeringskantoren",
    "sg:phone":"+31 412 631 999",
    "sg:postcode":"5345 AJ",
    "sg:province":"Virginia",
    "wof:name":"Cheizoo Zekerheid",
    "wof:placetype":"venue"
},
  "geometry": {"coordinates":[-77.235214,38.312599],"type":"Point"}
}