{
  "type": "Feature",
  "properties": {
    "iso:country":"NL",
    "sg:address":"Hertogin Johannasingel 38",
    "sg:city":"Oss",
    "sg:orig_category":"Verzekeringen - Verzekeringskantoren",
    "sg:phone":"+31 412 631 999",
    "sg:postcode":"5345 AJ",
    "sg:province":"Virginia",
    "wof:name":"Cheizoo Zekerheid",
    "wof:placetype":"venue"
},
  "geometry": {"coordinates":[-77.235214,38.312599],"type":"Point"}
}