{
  "type": "Feature",
  "properties": {
    "iso:country":"NL",
    "sg:address":"Rumpenerstraat 55",
    "sg:city":"Brunssum",
    "sg:orig_category":"Kappers",
    "sg:phone":"+31 45 564 0401",
    "sg:postcode":"6443 CC",
    "sg:province":"Limburg",
    "wof:name":"Kapsalon Avalon",
    "wof:placetype":"venue"
},
  "geometry": {"coordinates":[5.9693827629,50.9406852722],"type":"Point"}
}