{
  "type": "Feature",
  "properties": {
    "iso:country":"NL",
    "sg:address":"H Westerstr 60",
    "sg:city":"Oude Pekela",
    "sg:orig_category":"Machineonderhoud En -Reparatie",
    "sg:phone":"+31 597 675 060",
    "sg:postcode":"9665 AN",
    "sg:province":"Groningen",
    "sg:website":"http://www.deltaservices.nl",
    "wof:name":"Delta Bv",
    "wof:placetype":"venue"
},
  "geometry": {"coordinates":[7.016394,53.105057],"type":"Point"}
}