{
  "type": "Feature",
  "properties": {
    "addr:full":"Ln V Ouderzorg 80 Leiderdorp Zuid-Holland 2352 HX",
    "addr:housenumber":"80",
    "addr:postcode":"2352 hx",
    "addr:street":"Ln;Ouderzorg",
    "iso:country":"NL",
    "sg:address":"Ln V Ouderzorg 80",
    "sg:city":"Leiderdorp",
    "sg:orig_category":"Adviesbureaus Bedrijfsorganisatie",
    "sg:phone":"+31 71 541 6363",
    "sg:postcode":"2352 HX",
    "sg:province":"Zuid-Holland",
    "wof:name":"Ghc International",
    "wof:placetype":"venue"
},
  "geometry": {"coordinates":[4.534218,52.156174],"type":"Point"}
}