{
  "type": "Feature",
  "properties": {
    "addr:full":"Krommenieerweg 93 Wormerveer North Holland 1521 HD",
    "addr:housenumber":"93",
    "addr:postcode":"1521 hd",
    "addr:street":"Krommenieerweg",
    "iso:country":"NL",
    "sg:address":"Krommenieerweg 93",
    "sg:city":"Wormerveer",
    "sg:orig_category":"Antiekzaken",
    "sg:phone":"+31 75 628 7287",
    "sg:postcode":"1521 HD",
    "sg:province":"North Holland",
    "wof:name":"Roel Antiek Wormerveer",
    "wof:placetype":"venue"
},
  "geometry": {"coordinates":[4.783151,52.495445],"type":"Point"}
}