{
  "type": "Feature",
  "properties": {
    "addr:full":"Perebomenweg 9 Elim Drenthe 7916 PE",
    "addr:housenumber":"9",
    "addr:postcode":"7916 pe",
    "addr:street":"Perebomenweg",
    "iso:country":"NL",
    "sg:address":"Perebomenweg 9",
    "sg:city":"Elim",
    "sg:orig_category":"Fietshandelaren",
    "sg:phone":"+31 528 351 283",
    "sg:postcode":"7916 PE",
    "sg:province":"Drenthe",
    "wof:name":"Firma De Jonge",
    "wof:placetype":"venue"
},
  "geometry": {"coordinates":[6.581728,52.682541],"type":"Point"}
}