{
  "type": "Feature",
  "properties": {
    "addr:full":"Korte Hengelosestraat 18 Enschede Overijssel 7511 JB",
    "addr:housenumber":"18",
    "addr:postcode":"7511 jb",
    "addr:street":"Korte Hengelosestraat",
    "iso:country":"NL",
    "sg:address":"Korte Hengelosestraat 18",
    "sg:city":"Enschede",
    "sg:orig_category":"Kappers",
    "sg:phone":"+31 53 434 3200",
    "sg:postcode":"7511 JB",
    "sg:province":"Overijssel",
    "wof:name":"Salon Jacques",
    "wof:placetype":"venue"
},
  "geometry": {"coordinates":[6.893158,52.222019],"type":"Point"}
}