{
  "type": "Feature",
  "properties": {
    "addr:full":"Erve Teeselink 7 Holten NL.08 7451 WE",
    "addr:housenumber":"7;nl.08",
    "addr:postcode":"7451 we",
    "addr:street":"Erve Teeselink",
    "iso:country":"NL",
    "sg:address":"Erve Teeselink 7",
    "sg:city":"Holten",
    "sg:orig_category":"Modevakscholen",
    "sg:phone":"+31 548 362 287",
    "sg:postcode":"7451 WE",
    "sg:province":"NL.08",
    "wof:name":"Modevakschool Holten",
    "wof:placetype":"venue"
},
  "geometry": {"coordinates":[6.420288,52.27544],"type":"Point"}
}