{
  "type": "Feature",
  "properties": {
    "addr:full":"Schuijtstraat 4 'S Gravenhage Zuid-Holland 2517 XE",
    "addr:housenumber":"4 '",
    "addr:postcode":"2517 xe",
    "addr:street":"Schuijtstraat",
    "iso:country":"NL",
    "sg:address":"Schuijtstraat 4",
    "sg:city":"'S Gravenhage",
    "sg:orig_category":"Bedrijfs- And Managementsconsultants",
    "sg:phone":"+31 70 346 4078",
    "sg:postcode":"2517 XE",
    "sg:province":"Zuid-Holland",
    "wof:name":"Deltatee Bv",
    "wof:placetype":"venue"
},
  "geometry": {"coordinates":[4.28819,52.083614],"type":"Point"}
}