{
  "type": "Feature",
  "properties": {
    "iso:country":"NL",
    "sg:address":"F Hendrikln 244",
    "sg:city":"S Gravenhage",
    "sg:orig_category":"Kappers",
    "sg:phone":"+31 70 355 1932",
    "sg:postcode":"2582 BM",
    "sg:province":"South Holland",
    "wof:name":"Huisman, Kapsalon",
    "wof:placetype":"venue"
},
  "geometry": {"coordinates":[4.2785201073,52.0924110413],"type":"Point"}
}