{
  "type": "Feature",
  "properties": {
    "addr:full":"Schaapsdrift 255 Zevenaar Gelderland 6902 AH",
    "addr:housenumber":"255",
    "addr:postcode":"6902 ah",
    "addr:street":"Schaapsdrift",
    "iso:country":"NL",
    "sg:address":"Schaapsdrift 255",
    "sg:city":"Zevenaar",
    "sg:orig_category":"Vertaal- And Tolkenbureaus",
    "sg:phone":"+31 316 527 316",
    "sg:postcode":"6902 AH",
    "sg:province":"Gelderland",
    "wof:name":"Landman Language Services",
    "wof:placetype":"venue"
},
  "geometry": {"coordinates":[6.088993,51.932892],"type":"Point"}
}