{
  "type": "Feature",
  "properties": {
    "addr:full":"Rijksstraatweg 40F Dordrecht Zuid-Holland 3316 EH",
    "addr:housenumber":"40f",
    "addr:postcode":"3316 eh",
    "addr:street":"Rijksstraatweg",
    "iso:country":"NL",
    "sg:address":"Rijksstraatweg 40F",
    "sg:city":"Dordrecht",
    "sg:orig_category":"Metaalbekleding And -Behandeling",
    "sg:phone":"+31 78 617 2469",
    "sg:postcode":"3316 EH",
    "sg:province":"Zuid-Holland",
    "wof:name":"Busink Auto Las-En Reparatiebedryf",
    "wof:placetype":"venue"
},
  "geometry": {"coordinates":[4.644124,51.774151],"type":"Point"}
}