{
  "type": "Feature",
  "properties": {
    "addr:full":"Winkelc Woensel 9 Eindhoven Noord-Brabant 5625 AA",
    "addr:housenumber":"9",
    "addr:postcode":"5625 aa",
    "addr:street":"Winkelc Woensel",
    "iso:country":"NL",
    "sg:address":"Winkelc Woensel 9",
    "sg:city":"Eindhoven",
    "sg:orig_category":"Verhuur",
    "sg:phone":"+31 40 292 6686",
    "sg:postcode":"5625 AA",
    "sg:province":"Noord-Brabant",
    "wof:name":"Skala Bv",
    "wof:placetype":"venue"
},
  "geometry": {"coordinates":[5.476738,51.467838],"type":"Point"}
}