{
  "type": "Feature",
  "properties": {
    "addr:full":"Surinameplein 118 Amsterdam Noord-Holland 1058 GV",
    "addr:housenumber":"118",
    "addr:postcode":"1058 gv",
    "addr:street":"Surinameplein",
    "iso:country":"NL",
    "sg:address":"Surinameplein 118",
    "sg:city":"Amsterdam",
    "sg:orig_category":"Politie",
    "sg:phone":"+31 900 8844",
    "sg:postcode":"1058 GV",
    "sg:province":"Noord-Holland",
    "wof:name":"Politie Amsterdam-Amstelland Wijkbureau",
    "wof:placetype":"venue"
},
  "geometry": {"coordinates":[4.849866,52.358639],"type":"Point"}
}