{
  "type": "Feature",
  "properties": {
    "addr:full":"Ambachtswg 5 Katwyk Zh Zuid-Holland 2222 AH",
    "addr:housenumber":"5",
    "addr:postcode":"2222 ah",
    "addr:street":"Ambachtswg",
    "iso:country":"NL",
    "sg:address":"Ambachtswg 5",
    "sg:city":"Katwyk Zh",
    "sg:orig_category":"Keukens",
    "sg:phone":"+31 71 403 1098",
    "sg:postcode":"2222 AH",
    "sg:province":"Zuid-Holland",
    "wof:name":"Verschoor & Jansen Keukenstudio",
    "wof:placetype":"venue"
},
  "geometry": {"coordinates":[4.433127,52.203102],"type":"Point"}
}