{
  "type": "Feature",
  "properties": {
    "addr:full":"Raadhuisstraat 16 Heemstede Noord-Holland 2101 HG",
    "addr:housenumber":"16",
    "addr:postcode":"2101 hg",
    "addr:street":"Raadhuisstraat",
    "iso:country":"NL",
    "sg:address":"Raadhuisstraat 16",
    "sg:city":"Heemstede",
    "sg:orig_category":"Kappers",
    "sg:phone":"+31 23 547 1171",
    "sg:postcode":"2101 HG",
    "sg:province":"Noord-Holland",
    "wof:name":"John Heeren Kapper",
    "wof:placetype":"venue"
},
  "geometry": {"coordinates":[4.6205258369,52.3474731445],"type":"Point"}
}