{
  "type": "Feature",
  "properties": {
    "addr:full":"V Loostr 17 S Gravenhage South Holland 2582 VZ",
    "addr:housenumber":"17",
    "addr:postcode":"2582 vz",
    "addr:street":"S Gravenhage",
    "iso:country":"NL",
    "sg:address":"V Loostr 17",
    "sg:city":"S Gravenhage",
    "sg:orig_category":"Fotografie Reclame En Mode",
    "sg:phone":"+31 70 302 0516",
    "sg:postcode":"2582 VZ",
    "sg:province":"South Holland",
    "sg:website":"http://www.waalewijn.nl",
    "wof:name":"Waalewijn, Hessel",
    "wof:placetype":"venue"
},
  "geometry": {"coordinates":[4.27852,52.092411],"type":"Point"}
}