{
  "type": "Feature",
  "properties": {
    "iso:country":"NL",
    "sg:address":"Postbus 174",
    "sg:city":"Goirle",
    "sg:orig_category":"Organisatiebureaus",
    "sg:phone":"+31 13 590 1955",
    "sg:postcode":"5050 AD",
    "sg:province":"Noord-Brabant",
    "sg:website":"http://www.coact.nl",
    "wof:name":"Coact Consult",
    "wof:placetype":"venue"
},
  "geometry": {"coordinates":[5.0678877831,51.5186233521],"type":"Point"}
}