{
  "type": "Feature",
  "properties": {
    "iso:country":"NL",
    "sg:address":"Fransenstr 20",
    "sg:city":"Vlaardingen",
    "sg:orig_category":"Kinderkleding",
    "sg:phone":"+31 10 435 4660",
    "sg:postcode":"3131 CC",
    "sg:province":"Zuid-Holland",
    "wof:name":"Poco Loco",
    "wof:placetype":"venue"
},
  "geometry": {"coordinates":[4.34062,51.909397],"type":"Point"}
}