{
  "type": "Feature",
  "properties": {
    "addr:full":"Edisonstr 35 Huizen Noord-Holland 1276 GB",
    "addr:housenumber":"35",
    "addr:postcode":"1276 gb",
    "addr:street":"Edisonstr",
    "iso:country":"NL",
    "sg:address":"Edisonstr 35",
    "sg:city":"Huizen",
    "sg:orig_category":"Loodgieters",
    "sg:phone":"+31 35 526 3356",
    "sg:postcode":"1276 GB",
    "sg:province":"Noord-Holland",
    "wof:name":"Schaap",
    "wof:placetype":"venue"
},
  "geometry": {"coordinates":[5.247585,52.28849],"type":"Point"}
}