{
  "type": "Feature",
  "properties": {
    "addr:full":"Langenkamp 2 Losser Overijssel 7581 JE",
    "addr:housenumber":"2",
    "addr:postcode":"7581 je",
    "addr:street":"Langenkamp",
    "iso:country":"NL",
    "sg:address":"Langenkamp 2",
    "sg:city":"Losser",
    "sg:orig_category":"Woninginrichting",
    "sg:phone":"+31 53 536 2173",
    "sg:postcode":"7581 JE",
    "sg:province":"Overijssel",
    "wof:name":"Decorette",
    "wof:placetype":"venue"
},
  "geometry": {"coordinates":[7.0078549385,52.2609634399],"type":"Point"}
}