{
  "type": "Feature",
  "properties": {
    "addr:full":"De Kreken 25 Alblasserdam Zuid-Holland 2953 WG",
    "addr:housenumber":"25",
    "addr:postcode":"2953 wg",
    "addr:street":"De Kreken",
    "iso:country":"NL",
    "sg:address":"De Kreken 25",
    "sg:city":"Alblasserdam",
    "sg:orig_category":"Acupunctuur",
    "sg:phone":"+31 78 691 2258",
    "sg:postcode":"2953 WG",
    "sg:province":"Zuid-Holland",
    "wof:name":"Apfl",
    "wof:placetype":"venue"
},
  "geometry": {"coordinates":[4.648016,51.871799],"type":"Point"}
}