{
  "type": "Feature",
  "properties": {
    "addr:full":"Lindenlaan 77A Huizen Noord-Holland 1271 AW",
    "addr:housenumber":"77a",
    "addr:postcode":"1271 aw",
    "addr:street":"Lindenlaan",
    "iso:country":"NL",
    "sg:address":"Lindenlaan 77A",
    "sg:city":"Huizen",
    "sg:orig_category":"Meubelzaken, Woning- And Keukeninrichting",
    "sg:phone":"+31 35 524 1029",
    "sg:postcode":"1271 AW",
    "sg:province":"Noord-Holland",
    "wof:name":"Noekies",
    "wof:placetype":"venue"
},
  "geometry": {"coordinates":[5.237779,52.294533],"type":"Point"}
}