{
  "type": "Feature",
  "properties": {
    "addr:full":"Stationsstraat 17 Heerde Gelderland 8181 CW",
    "addr:housenumber":"17",
    "addr:postcode":"8181 cw",
    "addr:street":"Stationsstraat;Gelderland",
    "iso:country":"NL",
    "sg:address":"Stationsstraat 17",
    "sg:city":"Heerde",
    "sg:orig_category":"Kappers",
    "sg:phone":"+31 578 691 857",
    "sg:postcode":"8181 CW",
    "sg:province":"Gelderland",
    "wof:name":"Coiffures Van De Put",
    "wof:placetype":"venue"
},
  "geometry": {"coordinates":[6.0389208794,52.3890724182],"type":"Point"}
}