{
  "type": "Feature",
  "properties": {
    "addr:full":"Hoyserstr 19 Someren North Brabant 5711 PV",
    "addr:housenumber":"19",
    "addr:postcode":"5711 pv",
    "addr:street":"Hoyserstr",
    "iso:country":"NL",
    "sg:address":"Hoyserstr 19",
    "sg:city":"Someren",
    "sg:orig_category":"Zonweringen",
    "sg:phone":"+31 6 51151139",
    "sg:postcode":"5711 PV",
    "sg:province":"North Brabant",
    "wof:name":"Borgers",
    "wof:placetype":"venue"
},
  "geometry": {"coordinates":[5.711272,51.384651],"type":"Point"}
}