{
  "type": "Feature",
  "properties": {
    "iso:country":"NL",
    "sg:address":"Vechtstr 31",
    "sg:city":"Zwolle",
    "sg:orig_category":"Sanitaire Artikelen",
    "sg:phone":"+31 38 453 3835",
    "sg:postcode":"8021 AS",
    "sg:province":"Overijssel",
    "wof:name":"Sleurink Sanidr?Me",
    "wof:placetype":"venue"
},
  "geometry": {"coordinates":[6.105684,52.51582],"type":"Point"}
}