{
  "type": "Feature",
  "properties": {
    "addr:full":"De Tollande 21 Hoogeloon North Brabant 5528 BR",
    "addr:housenumber":"21",
    "addr:postcode":"5528 br",
    "addr:street":"De Tollande",
    "iso:country":"NL",
    "sg:address":"De Tollande 21",
    "sg:city":"Hoogeloon",
    "sg:orig_category":"Loodgieters",
    "sg:phone":"+31 497 681 863",
    "sg:postcode":"5528 BR",
    "sg:province":"North Brabant",
    "wof:name":"Brouwer Van De Put, De",
    "wof:placetype":"venue"
},
  "geometry": {"coordinates":[5.270579,51.399994],"type":"Point"}
}