{
  "type": "Feature",
  "properties": {
    "addr:full":"Burg Smeeleln 40 Waalwijk Noord-Brabant 5144 AS",
    "addr:housenumber":"40",
    "addr:postcode":"5144 as",
    "addr:street":"Burg",
    "iso:country":"NL",
    "sg:address":"Burg Smeeleln 40",
    "sg:city":"Waalwijk",
    "sg:orig_category":"Verenigingen En Stichtingen",
    "sg:phone":"+31 416 332 226",
    "sg:postcode":"5144 AS",
    "sg:province":"Noord-Brabant",
    "wof:name":"Astmapati\u00ebntenver Vbba",
    "wof:placetype":"venue"
},
  "geometry": {"coordinates":[5.062876,51.689789],"type":"Point"}
}