{
  "type": "Feature",
  "properties": {
    "addr:full":"Nieuwegr 32 Utrecht Utrecht 3512 LS",
    "addr:housenumber":"32",
    "addr:postcode":"3512 ls",
    "addr:street":"Nieuwegr",
    "iso:country":"NL",
    "sg:address":"Nieuwegr 32",
    "sg:city":"Utrecht",
    "sg:orig_category":"Journalisten Freelance",
    "sg:phone":"+31 30 233 3330",
    "sg:postcode":"3512 LS",
    "sg:province":"Utrecht",
    "wof:name":"Groenvoer",
    "wof:placetype":"venue"
},
  "geometry": {"coordinates":[5.12493,52.088715],"type":"Point"}
}