{
  "type": "Feature",
  "properties": {
    "addr:full":"Stadhouderskd 89 Amsterdam Noord-Holland 1073 AV",
    "addr:housenumber":"89",
    "addr:postcode":"1073 av",
    "addr:street":"Stadhouderskd",
    "iso:country":"NL",
    "sg:address":"Stadhouderskd 89",
    "sg:city":"Amsterdam",
    "sg:orig_category":"Verenigingen En Stichtingen",
    "sg:phone":"+31 20 305 7005",
    "sg:postcode":"1073 AV",
    "sg:province":"Noord-Holland",
    "sg:website":"http://www.swda.org",
    "wof:name":"Doven Amsterdam Swda, St Welzijn",
    "wof:placetype":"venue"
},
  "geometry": {"coordinates":[4.8984,52.353001],"type":"Point"}
}