{
  "type": "Feature",
  "properties": {
    "addr:full":"Diamantpln 7 Leiden South Holland 2332 HR",
    "addr:housenumber":"7",
    "addr:postcode":"2332 hr",
    "addr:street":"Diamantpln",
    "iso:country":"NL",
    "sg:address":"Diamantpln 7",
    "sg:city":"Leiden",
    "sg:orig_category":"Kappers",
    "sg:phone":"+31 71 576 4715",
    "sg:postcode":"2332 HR",
    "sg:province":"South Holland",
    "wof:name":"Haarshop, De",
    "wof:placetype":"venue"
},
  "geometry": {"coordinates":[4.464589119,52.1567649841],"type":"Point"}
}