{
  "type": "Feature",
  "properties": {
    "addr:full":"Flemingstr 15 Heerhugowaard Noord-Holland 1704 SL",
    "addr:housenumber":"15",
    "addr:postcode":"1704 sl",
    "addr:street":"Flemingstr",
    "iso:country":"NL",
    "sg:address":"Flemingstr 15",
    "sg:city":"Heerhugowaard",
    "sg:classifiers":[
        {
            "category":"Retail",
            "subcategory":"Auto Repair",
            "type":"Services"
        }
    ],
    "sg:phone":"+31 72 571 0887",
    "sg:postcode":"1704 SL",
    "sg:province":"Noord-Holland",
    "sg:tags":[
        "garage"
    ],
    "wof:name":"Nic Smit Garage, Usa Cars",
    "wof:placetype":"venue"
},
  "geometry": {"coordinates":[4.831598,52.695564],"type":"Point"}
}