{
  "type": "Feature",
  "properties": {
    "iso:country":"NL",
    "sg:address":"Industriewg 8/A",
    "sg:city":"Culemborg",
    "sg:orig_category":"Verpakkingen En Verpakkingsmaterialen",
    "sg:phone":"+31 345 521 316",
    "sg:postcode":"4104 AR",
    "sg:province":"Gelderland",
    "sg:website":"http://www.danisco.com",
    "wof:name":"Danisco Flexible Ned Bv",
    "wof:placetype":"venue"
},
  "geometry": {"coordinates":[5.219905,51.942551],"type":"Point"}
}