{
  "type": "Feature",
  "properties": {
    "addr:full":"V Weelstr 10 Ooltgensplaat Zuid-Holland 3257 BB",
    "addr:housenumber":"10",
    "addr:postcode":"3257 bb",
    "iso:country":"NL",
    "sg:address":"V Weelstr 10",
    "sg:city":"Ooltgensplaat",
    "sg:orig_category":"Zalenverhuur",
    "sg:phone":"+31 187 631 781",
    "sg:postcode":"3257 BB",
    "sg:province":"Zuid-Holland",
    "wof:name":"Vos, J De",
    "wof:placetype":"venue"
},
  "geometry": {"coordinates":[4.349385,51.681679],"type":"Point"}
}