{
  "type": "Feature",
  "properties": {
    "iso:country":"NL",
    "sg:address":"Hooiland 10",
    "sg:city":"Stolwyk",
    "sg:orig_category":"Kantoormachines",
    "sg:phone":"+31 182 341 135",
    "sg:postcode":"2821 ZG",
    "sg:province":"Zuid-Holland",
    "wof:name":"Reprotechniek",
    "wof:placetype":"venue"
},
  "geometry": {"coordinates":[8.5479898453,47.1645584106],"type":"Point"}
}