{
  "type": "Feature",
  "properties": {
    "addr:full":"Den Burghstr 34 Voorburg Zuid-Holland 2275 TN",
    "addr:housenumber":"34",
    "addr:postcode":"2275",
    "iso:country":"NL",
    "sg:address":"Den Burghstr 34",
    "sg:city":"Voorburg",
    "sg:orig_category":"Horloges En Klokken",
    "sg:phone":"+31 70 346 3868",
    "sg:postcode":"2275 TN",
    "sg:province":"Zuid-Holland",
    "wof:name":"Gaemers Chronometrie, A",
    "wof:placetype":"venue"
},
  "geometry": {"coordinates":[4.347906,52.059387],"type":"Point"}
}