{
  "type": "Feature",
  "properties": {
    "addr:full":"Heemskerckstr 15 Oudeschild North Holland 1792 AA",
    "addr:housenumber":"15",
    "addr:postcode":"1792 aa",
    "addr:street":"Heemskerckstr",
    "iso:country":"NL",
    "sg:address":"Heemskerckstr 15",
    "sg:city":"Oudeschild",
    "sg:orig_category":"Loodgieters",
    "sg:phone":"+31 222 321 444",
    "sg:postcode":"1792 AA",
    "sg:province":"North Holland",
    "wof:name":"Slik, Rob",
    "wof:placetype":"venue"
},
  "geometry": {"coordinates":[4.847627,53.039234],"type":"Point"}
}