{
  "type": "Feature",
  "properties": {
    "addr:full":"Scholverbos 3 Ryen Noord-Brabant 5122 HN",
    "addr:housenumber":"3",
    "addr:postcode":"5122 hn",
    "addr:street":"Scholverbos",
    "iso:country":"NL",
    "sg:address":"Scholverbos 3",
    "sg:city":"Ryen",
    "sg:orig_category":"Kappers",
    "sg:phone":"+31 161 220 384",
    "sg:postcode":"5122 HN",
    "sg:province":"Noord-Brabant",
    "wof:name":"Annelies",
    "wof:placetype":"venue"
},
  "geometry": {"coordinates":[4.9275197983,51.5927696228],"type":"Point"}
}