{
  "type": "Feature",
  "properties": {
    "iso:country":"NL",
    "sg:address":"Zilvermeeuw 21",
    "sg:city":"Etten Leur",
    "sg:classifiers":[
        {
            "category":"Cinema",
            "subcategory":"Drive-in Theater",
            "type":"Entertainment"
        }
    ],
    "sg:phone":"+31 76 501 9838",
    "sg:postcode":"4872 RM",
    "sg:province":"Noord-Brabant",
    "sg:tags":[
        "drive-in-shows"
    ],
    "sg:website":"http://www.mpdorst.demon.nl",
    "wof:name":"Enjoy Sounds",
    "wof:placetype":"venue"
},
  "geometry": {"coordinates":[4.657619,51.579376],"type":"Point"}
}