{
  "type": "Feature",
  "properties": {
    "addr:full":"Lindestr 7 Nistelrode Noord-Brabant 5388 HT",
    "addr:housenumber":"7",
    "addr:postcode":"5388 ht",
    "addr:street":"Lindestr",
    "iso:country":"NL",
    "sg:address":"Lindestr 7",
    "sg:city":"Nistelrode",
    "sg:orig_category":"Beeldende Kunstenaars",
    "sg:phone":"+31 412 613 737",
    "sg:postcode":"5388 HT",
    "sg:province":"Noord-Brabant",
    "wof:name":"Replica, Sticht",
    "wof:placetype":"venue"
},
  "geometry": {"coordinates":[5.562672,51.700214],"type":"Point"}
}