{
  "type": "Feature",
  "properties": {
    "iso:country":"NL",
    "sg:address":"Lange Tuinstraat 6",
    "sg:city":"'S Hertogenbosch",
    "sg:orig_category":"Vertaal- And Tolkenbureaus",
    "sg:phone":"+31 73 614 1287",
    "sg:postcode":"5212 SH",
    "sg:province":"Noord-Brabant",
    "wof:name":"Laroussi",
    "wof:placetype":"venue"
},
  "geometry": {"coordinates":[5.308733,51.696171],"type":"Point"}
}