{
  "type": "Feature",
  "properties": {
    "addr:full":"Park Vredehof 7 Soest Utrecht 3762 DT",
    "addr:housenumber":"7",
    "addr:postcode":"3762 dt",
    "addr:street":"Park Vredehof",
    "iso:country":"NL",
    "sg:address":"Park Vredehof 7",
    "sg:city":"Soest",
    "sg:orig_category":"Film-, Tv- And Videoproductie",
    "sg:phone":"+31 35 601 9649",
    "sg:postcode":"3762 DT",
    "sg:province":"Utrecht",
    "wof:name":"De Kermisklanten Bv",
    "wof:placetype":"venue"
},
  "geometry": {"coordinates":[5.280495,52.190254],"type":"Point"}
}