{
  "type": "Feature",
  "properties": {
    "addr:full":"Albert Plesmanstraat 20 Barneveld Gelderland 3772 MN",
    "addr:housenumber":"20",
    "addr:postcode":"3772 mn",
    "addr:street":"Albert Plesmanstraat;Gelderland",
    "iso:country":"NL",
    "sg:address":"Albert Plesmanstraat 20",
    "sg:city":"Barneveld",
    "sg:orig_category":"Autokeuringen",
    "sg:phone":"+31 342 413 535",
    "sg:postcode":"3772 MN",
    "sg:province":"Gelderland",
    "wof:name":"Andre De Vor Bv",
    "wof:placetype":"venue"
},
  "geometry": {"coordinates":[5.567096,52.124779],"type":"Point"}
}