{
  "type": "Feature",
  "properties": {
    "iso:country":"NL",
    "sg:address":"Gildepln 42",
    "sg:city":"Purmerend",
    "sg:orig_category":"Boekhandels",
    "sg:phone":"+31 299 644 670",
    "sg:postcode":"1445 BM",
    "sg:province":"North Holland",
    "wof:name":"Gildeplein Cv",
    "wof:placetype":"venue"
},
  "geometry": {"coordinates":[4.985873,52.506023],"type":"Point"}
}