{
  "type": "Feature",
  "properties": {
    "addr:full":"Diepenveensewg 76 Deventer Overijssel 7413 AS",
    "addr:housenumber":"76",
    "addr:postcode":"7413 as",
    "addr:street":"Diepenveensewg",
    "iso:country":"NL",
    "sg:address":"Diepenveensewg 76",
    "sg:city":"Deventer",
    "sg:orig_category":"Begrafenisverzorging",
    "sg:phone":"+31 570 622 535",
    "sg:postcode":"7413 AS",
    "sg:province":"Overijssel",
    "wof:name":"Roelofs, Uitvaartverzorging",
    "wof:placetype":"venue"
},
  "geometry": {"coordinates":[6.159176,52.258987],"type":"Point"}
}