{
  "type": "Feature",
  "properties": {
    "iso:country":"NL",
    "sg:address":"Sint Catharinastraat 20",
    "sg:city":"Ulestraten",
    "sg:orig_category":"Banken And Kredietinstellingen",
    "sg:phone":"+31 43 364 3722",
    "sg:postcode":"6235 BE",
    "sg:province":"Limburg",
    "wof:name":"Postkantoor",
    "wof:placetype":"venue"
},
  "geometry": {"coordinates":[5.782891,50.905857],"type":"Point"}
}