{
  "type": "Feature",
  "properties": {
    "addr:full":"Ruimtesonde 15 Amersfoort Utrecht 3824 MZ",
    "addr:housenumber":"15",
    "addr:postcode":"3824 mz",
    "addr:street":"Ruimtesonde",
    "iso:country":"NL",
    "sg:address":"Ruimtesonde 15",
    "sg:city":"Amersfoort",
    "sg:orig_category":"Verzekeringen",
    "sg:phone":"+31 33 453 0105",
    "sg:postcode":"3824 MZ",
    "sg:province":"Utrecht",
    "wof:name":"Bv Adviesburo Lxy",
    "wof:placetype":"venue"
},
  "geometry": {"coordinates":[5.388931,52.201176],"type":"Point"}
}