{
  "type": "Feature",
  "properties": {
    "addr:full":"Lindenlaan 16 Groesbeek Gelderland 6561 CG",
    "addr:housenumber":"16",
    "addr:postcode":"6561 cg",
    "addr:street":"Lindenlaan;Gelderland",
    "iso:country":"NL",
    "sg:address":"Lindenlaan 16",
    "sg:city":"Groesbeek",
    "sg:orig_category":"Metalen And Ertsen Gh",
    "sg:phone":"+31 24 397 6982",
    "sg:postcode":"6561 CG",
    "sg:province":"Gelderland",
    "wof:name":"Groothandel H.F.W.M. Janssen",
    "wof:placetype":"venue"
},
  "geometry": {"coordinates":[5.92787,51.780903],"type":"Point"}
}