{
  "type": "Feature",
  "properties": {
    "addr:full":"Provincialeweg 1 Lienden Gelderland 4033 BP",
    "addr:housenumber":"1",
    "addr:postcode":"4033 bp",
    "addr:street":"Provincialeweg;Gelderland",
    "iso:country":"NL",
    "sg:address":"Provincialeweg 1",
    "sg:city":"Lienden",
    "sg:orig_category":"Bloemen And Planten Gh",
    "sg:phone":"+31 488 481 580",
    "sg:postcode":"4033 BP",
    "sg:province":"Gelderland",
    "wof:name":"J.D. Van De Bijl En Zn",
    "wof:placetype":"venue"
},
  "geometry": {"coordinates":[5.527312,51.936207],"type":"Point"}
}