{
  "type": "Feature",
  "properties": {
    "iso:country":"NL",
    "sg:address":"Spuistr 4",
    "sg:city":"Arnhem",
    "sg:orig_category":"Artiesten/Gezelschappen",
    "sg:phone":"+31 26 362 0978",
    "sg:postcode":"6826 GS",
    "sg:province":"Gelderland",
    "wof:name":"Tata Mirando",
    "wof:placetype":"venue"
},
  "geometry": {"coordinates":[5.946481,51.980415],"type":"Point"}
}