{
  "type": "Feature",
  "properties": {
    "addr:full":"Stikkenwg 7 Zelhem Gelderland 7021 BN",
    "addr:housenumber":"7",
    "addr:postcode":"7021 bn",
    "addr:street":"Stikkenwg;Gelderland",
    "iso:country":"NL",
    "sg:address":"Stikkenwg 7",
    "sg:city":"Zelhem",
    "sg:orig_category":"Houtvezelperserijen",
    "sg:phone":"+31 314 622 295",
    "sg:postcode":"7021 BN",
    "sg:province":"Gelderland",
    "wof:name":"Beumer Bv",
    "wof:placetype":"venue"
},
  "geometry": {"coordinates":[6.30445,52.010796],"type":"Point"}
}