{
  "type": "Feature",
  "properties": {
    "addr:full":"Palissander 212 Dordrecht South Holland 3315 MR",
    "addr:housenumber":"212",
    "addr:postcode":"3315 mr",
    "addr:street":"Palissander",
    "iso:country":"NL",
    "sg:address":"Palissander 212",
    "sg:city":"Dordrecht",
    "sg:classifiers":[
        {
            "category":"Professional",
            "subcategory":"Accounting & Tax Preparation",
            "type":"Services"
        }
    ],
    "sg:phone":"+31 78 621 4976",
    "sg:postcode":"3315 MR",
    "sg:province":"South Holland",
    "sg:tags":[
        "accountant"
    ],
    "wof:name":"Van Lonkhuizen Bv",
    "wof:placetype":"venue"
},
  "geometry": {"coordinates":[4.709655,51.803879],"type":"Point"}
}