{
  "type": "Feature",
  "properties": {
    "addr:full":"Robynstr 19B Breda Noord-Brabant 4817 JE",
    "addr:housenumber":"19b",
    "addr:postcode":"4817 je",
    "addr:street":"Robynstr",
    "iso:country":"NL",
    "sg:address":"Robynstr 19B",
    "sg:city":"Breda",
    "sg:orig_category":"Werving En Selectie",
    "sg:phone":"+31 76 520 0043",
    "sg:postcode":"4817 JE",
    "sg:province":"Noord-Brabant",
    "wof:name":"Recrasport",
    "wof:placetype":"venue"
},
  "geometry": {"coordinates":[4.7716851234,51.5913505554],"type":"Point"}
}