{
  "type": "Feature",
  "properties": {
    "addr:full":"Martinus Burkensstraat 14 Rotterdam Zuid-Holland 3065 LA",
    "addr:housenumber":"14",
    "addr:postcode":"3065 la",
    "addr:street":"Martinus Burkensstraat",
    "iso:country":"NL",
    "sg:address":"Martinus Burkensstraat 14",
    "sg:city":"Rotterdam",
    "sg:orig_category":"Bedrijfs- And Managementsconsultants",
    "sg:phone":"+31 10 288 0114",
    "sg:postcode":"3065 LA",
    "sg:province":"Zuid-Holland",
    "wof:name":"Dearbourne & Teuy Bv",
    "wof:placetype":"venue"
},
  "geometry": {"coordinates":[4.552034,51.922909],"type":"Point"}
}