{
  "type": "Feature",
  "properties": {
    "addr:full":"Nieuwez Voorburgw 120 Amsterdam North Holland 1012 SH",
    "addr:housenumber":"120",
    "addr:postcode":"1012 sh",
    "iso:country":"NL",
    "sg:address":"Nieuwez Voorburgw 120",
    "sg:city":"Amsterdam",
    "sg:orig_category":"Kinderopvang",
    "sg:phone":"+31 20 412 1200",
    "sg:postcode":"1012 SH",
    "sg:province":"North Holland",
    "wof:name":"Prokino, Sticht",
    "wof:placetype":"venue"
},
  "geometry": {"coordinates":[4.891899,52.375206],"type":"Point"}
}