{
  "type": "Feature",
  "properties": {
    "iso:country":"NL",
    "sg:address":"Daltonstraat 16",
    "sg:city":"Rijssen",
    "sg:orig_category":"Goederenvervoer Over De Weg",
    "sg:phone":"+31 548 513 865",
    "sg:postcode":"7461 AC",
    "sg:province":"NL.08",
    "wof:name":"Zwaar Transport Twente Bv",
    "wof:placetype":"venue"
},
  "geometry": {"coordinates":[6.507956,52.313759],"type":"Point"}
}