{
  "type": "Feature",
  "properties": {
    "iso:country":"NL",
    "sg:address":"Wulverhorst 51",
    "sg:city":"Montfoort",
    "sg:orig_category":"Onderhoudswerken",
    "sg:phone":"+31 348 472 839",
    "sg:postcode":"3417 TH",
    "sg:province":"Utrecht",
    "wof:name":"Boomkamp",
    "wof:placetype":"venue"
},
  "geometry": {"coordinates":[4.947714,52.040165],"type":"Point"}
}