{
  "type": "Feature",
  "properties": {
    "addr:full":"Tollensstraat 100 Gouda South Holland 2802 LR",
    "addr:housenumber":"100",
    "addr:postcode":"2802 lr",
    "addr:street":"Tollensstraat",
    "iso:country":"NL",
    "sg:address":"Tollensstraat 100",
    "sg:city":"Gouda",
    "sg:orig_category":"Kappers",
    "sg:phone":"+31 182 526 937",
    "sg:postcode":"2802 LR",
    "sg:province":"South Holland",
    "wof:name":"Kapsalon Dini",
    "wof:placetype":"venue"
},
  "geometry": {"coordinates":[4.7011060715,52.0048561096],"type":"Point"}
}