{
  "type": "Feature",
  "properties": {
    "addr:full":"H H Dowwg 5 Hoek Zeeland 4542 NM",
    "addr:housenumber":"5",
    "addr:postcode":"4542",
    "iso:country":"NL",
    "sg:address":"H H Dowwg 5",
    "sg:city":"Hoek",
    "sg:orig_category":"Materiaalonderzoek",
    "sg:phone":"+31 115 613 975",
    "sg:postcode":"4542 NM",
    "sg:province":"Zeeland",
    "wof:name":"Rtd",
    "wof:placetype":"venue"
},
  "geometry": {"coordinates":[3.796773,51.330513],"type":"Point"}
}