{
  "type": "Feature",
  "properties": {
    "addr:full":"Hemmerbuurt 169 Hem Noord-Holland 1607 CG",
    "addr:housenumber":"169",
    "addr:postcode":"1607 cg",
    "addr:street":"Hemmerbuurt",
    "iso:country":"NL",
    "sg:address":"Hemmerbuurt 169",
    "sg:city":"Hem",
    "sg:orig_category":"Personenvervoer Zonder Dienstregeling",
    "sg:phone":"+31 228 542 424",
    "sg:postcode":"1607 CG",
    "sg:province":"Noord-Holland",
    "wof:name":"Alpha Tours Hem Bv",
    "wof:placetype":"venue"
},
  "geometry": {"coordinates":[5.176255,52.657482],"type":"Point"}
}