{
  "type": "Feature",
  "properties": {
    "addr:full":"Borstelwg 46 Enschede Overijssel 7545 MS",
    "addr:housenumber":"46",
    "addr:postcode":"7545 ms",
    "addr:street":"Borstelwg",
    "iso:country":"NL",
    "sg:address":"Borstelwg 46",
    "sg:city":"Enschede",
    "sg:orig_category":"Schilders",
    "sg:phone":"+31 53 431 7831",
    "sg:postcode":"7545 MS",
    "sg:province":"Overijssel",
    "wof:name":"Logtmeijer Schilderwerken Bv",
    "wof:placetype":"venue"
},
  "geometry": {"coordinates":[6.872763,52.218719],"type":"Point"}
}