{
  "type": "Feature",
  "properties": {
    "addr:full":"Boterstraat 2 Werkendam North Brabant 4251 CC",
    "addr:housenumber":"2",
    "addr:postcode":"4251 cc",
    "addr:street":"Boterstraat",
    "iso:country":"NL",
    "sg:address":"Boterstraat 2",
    "sg:city":"Werkendam",
    "sg:orig_category":"Loodgieterswerk, Verwarming And Sanitaire Installaties",
    "sg:phone":"+31 183 505 555",
    "sg:postcode":"4251 CC",
    "sg:province":"North Brabant",
    "wof:name":"Van Oord Installatietechniek",
    "wof:placetype":"venue"
},
  "geometry": {"coordinates":[4.892807,51.814316],"type":"Point"}
}