{
  "type": "Feature",
  "properties": {
    "addr:full":"Emmerikstr 6 Heeze Noord-Brabant 5591 HZ",
    "addr:housenumber":"6",
    "addr:postcode":"5591 hz",
    "addr:street":"Emmerikstr",
    "iso:country":"NL",
    "sg:address":"Emmerikstr 6",
    "sg:city":"Heeze",
    "sg:orig_category":"Cafetaria'S",
    "sg:phone":"+31 40 226 3166",
    "sg:postcode":"5591 HZ",
    "sg:province":"Noord-Brabant",
    "wof:name":"Knapen",
    "wof:placetype":"venue"
},
  "geometry": {"coordinates":[5.577094,51.376953],"type":"Point"}
}