{
  "type": "Feature",
  "properties": {
    "addr:full":"Panweg 6 Zeist Utrecht 3705 GD",
    "addr:housenumber":"6",
    "addr:postcode":"3705 gd",
    "addr:street":"Panweg",
    "iso:country":"NL",
    "sg:address":"Panweg 6",
    "sg:city":"Zeist",
    "sg:orig_category":"Banken And Kredietinstellingen",
    "sg:phone":"+31 30 696 0238",
    "sg:postcode":"3705 GD",
    "sg:province":"Utrecht",
    "wof:name":"Verenigde Spaarbank Nv",
    "wof:placetype":"venue"
},
  "geometry": {"coordinates":[5.243749,52.097656],"type":"Point"}
}