{
  "type": "Feature",
  "properties": {
    "iso:country":"NL",
    "sg:address":"Moeskroenstr 26",
    "sg:city":"Breda",
    "sg:orig_category":"Woningstoffeerders",
    "sg:phone":"+31 76 571 6853",
    "sg:postcode":"4826 AD",
    "sg:province":"North Brabant",
    "sg:website":"http://www.belatsi.nl",
    "wof:name":"B?latsi",
    "wof:placetype":"venue"
},
  "geometry": {"coordinates":[4.7772841454,51.6134185791],"type":"Point"}
}