{
  "type": "Feature",
  "properties": {
    "addr:full":"Maasstraat 12 Broekhuizenvorst Limburg 5871 AV",
    "addr:housenumber":"12",
    "addr:postcode":"5871 av",
    "addr:street":"Maasstraat",
    "iso:country":"NL",
    "sg:address":"Maasstraat 12",
    "sg:city":"Broekhuizenvorst",
    "sg:orig_category":"Bloemen And Planten",
    "sg:phone":"+31 77 463 1762",
    "sg:postcode":"5871 AV",
    "sg:province":"Limburg",
    "wof:name":"Bloemenboetiek Speycken-Lemmen",
    "wof:placetype":"venue"
},
  "geometry": {"coordinates":[6.161119,51.493889],"type":"Point"}
}