{
  "type": "Feature",
  "properties": {
    "addr:full":"Nyverheidstr 54 Bemmel Gelderland 6681 LN",
    "addr:housenumber":"54",
    "addr:postcode":"6681 ln",
    "addr:street":"Nyverheidstr;Gelderland",
    "iso:country":"NL",
    "sg:address":"Nyverheidstr 54",
    "sg:city":"Bemmel",
    "sg:orig_category":"Kassenbouw",
    "sg:phone":"+31 26 351 5717",
    "sg:postcode":"6681 LN",
    "sg:province":"Gelderland",
    "wof:name":"Rijkekas",
    "wof:placetype":"venue"
},
  "geometry": {"coordinates":[5.921897,51.907722],"type":"Point"}
}