{
  "type": "Feature",
  "properties": {
    "addr:full":"Nieuwstraat 16 Beesel Limburg 5954 CK",
    "addr:housenumber":"16",
    "addr:postcode":"5954 ck",
    "addr:street":"Nieuwstraat",
    "iso:country":"NL",
    "sg:address":"Nieuwstraat 16",
    "sg:city":"Beesel",
    "sg:orig_category":"Kappers",
    "sg:phone":"+31 77 474 4301",
    "sg:postcode":"5954 CK",
    "sg:province":"Limburg",
    "wof:name":"Kapper Thuisservice Mirjam Hegemann-Hend",
    "wof:placetype":"venue"
},
  "geometry": {"coordinates":[6.0418801308,51.2687644958],"type":"Point"}
}