{
  "type": "Feature",
  "properties": {
    "addr:full":"Markt 10 Lochem Gelderland 7241 AA",
    "addr:housenumber":"10",
    "addr:postcode":"7241 aa",
    "addr:street":"Markt;Gelderland",
    "iso:country":"NL",
    "sg:address":"Markt 10",
    "sg:city":"Lochem",
    "sg:orig_category":"Opticiens",
    "sg:phone":"+31 573 251 856",
    "sg:postcode":"7241 AA",
    "sg:province":"Gelderland",
    "wof:name":"Fa J.W. Swaters",
    "wof:placetype":"venue"
},
  "geometry": {"coordinates":[6.4151139259,52.161605835],"type":"Point"}
}