{
  "type": "Feature",
  "properties": {
    "addr:full":"Bleumerweg 12 Castricum Noord-Holland 1901 MJ",
    "addr:housenumber":"12",
    "addr:postcode":"1901 mj",
    "addr:street":"Bleumerweg",
    "iso:country":"NL",
    "sg:address":"Bleumerweg 12",
    "sg:city":"Castricum",
    "sg:orig_category":"Kampeerterreinen",
    "sg:phone":"+31 251 651 387",
    "sg:postcode":"1901 MJ",
    "sg:province":"Noord-Holland",
    "wof:name":"P.H. Twisk",
    "wof:placetype":"venue"
},
  "geometry": {"coordinates":[4.6573209763,52.5664787292],"type":"Point"}
}