{
  "type": "Feature",
  "properties": {
    "addr:full":"Celebesstraat 7 Bergen Op Zoom Noord-Brabant 4614 AA",
    "addr:housenumber":"7",
    "addr:postcode":"4614 aa",
    "addr:street":"Celebesstraat",
    "iso:country":"NL",
    "sg:address":"Celebesstraat 7",
    "sg:city":"Bergen Op Zoom",
    "sg:orig_category":"Algemene Werktuigbouw",
    "sg:phone":"+31 164 266 633",
    "sg:postcode":"4614 AA",
    "sg:province":"Noord-Brabant",
    "wof:name":"R.T.M. Metaal",
    "wof:placetype":"venue"
},
  "geometry": {"coordinates":[4.297164,51.499241],"type":"Point"}
}