{
  "type": "Feature",
  "properties": {
    "addr:full":"Hoofddorpwg 28 Amsterdam North Holland 1058 PC",
    "addr:housenumber":"28",
    "addr:postcode":"1058 pc",
    "addr:street":"Hoofddorpwg",
    "iso:country":"NL",
    "sg:address":"Hoofddorpwg 28",
    "sg:city":"Amsterdam",
    "sg:orig_category":"Verf En Lak",
    "sg:phone":"+31 20 617 0495",
    "sg:postcode":"1058 PC",
    "sg:province":"North Holland",
    "wof:name":"Duin, W Van",
    "wof:placetype":"venue"
},
  "geometry": {"coordinates":[4.85093,52.351151],"type":"Point"}
}