{
  "type": "Feature",
  "properties": {
    "addr:full":"F Hendrikln 164 S Gravenhage Zuid-Holland 2582 BJ",
    "addr:housenumber":"164;gravenhage",
    "addr:postcode":"2582 bj",
    "addr:street":"S",
    "iso:country":"NL",
    "sg:address":"F Hendrikln 164",
    "sg:city":"S Gravenhage",
    "sg:orig_category":"Boeken En Tijdschriften",
    "sg:phone":"+31 70 358 9209",
    "sg:postcode":"2582 BJ",
    "sg:province":"Zuid-Holland",
    "wof:name":"Nayler & Co",
    "wof:placetype":"venue"
},
  "geometry": {"coordinates":[4.2785201073,52.0924110413],"type":"Point"}
}