{
  "type": "Feature",
  "properties": {
    "addr:full":"Rykswg 78A Gronsveld Limburg 6247 AK",
    "addr:housenumber":"78a",
    "addr:postcode":"6247 ak",
    "addr:street":"Rykswg",
    "iso:country":"NL",
    "sg:address":"Rykswg 78A",
    "sg:city":"Gronsveld",
    "sg:orig_category":"Accountants - Administratie- Consulenten En -Kantoren",
    "sg:phone":"+31 43 408 4003",
    "sg:postcode":"6247 AK",
    "sg:province":"Limburg",
    "wof:name":"Irsen Bv, Van",
    "wof:placetype":"venue"
},
  "geometry": {"coordinates":[5.730784,50.810822],"type":"Point"}
}