{
  "type": "Feature",
  "properties": {
    "addr:full":"Heiligharn 424 Den Helder Noord-Holland 1785 SX",
    "addr:housenumber":"424",
    "addr:postcode":"1785 sx",
    "addr:street":"Heiligharn",
    "iso:country":"NL",
    "sg:address":"Heiligharn 424",
    "sg:city":"Den Helder",
    "sg:classifiers":[
        {
            "category":"Education",
            "subcategory":"Preschool",
            "type":"Public Place"
        }
    ],
    "sg:phone":"+31 223 660 846",
    "sg:postcode":"1785 SX",
    "sg:province":"Noord-Holland",
    "sg:tags":[
        "kleuteronderwijs",
        "basis-"
    ],
    "wof:name":"Openbare Basisschool De Dijk",
    "wof:placetype":"venue"
},
  "geometry": {"coordinates":[4.773662,52.933754],"type":"Point"}
}