{
  "type": "Feature",
  "properties": {
    "addr:full":"Bagynestr 59 Leeuwarden Friesland 8911 DN",
    "addr:housenumber":"59",
    "addr:postcode":"8911 dn",
    "addr:street":"Bagynestr",
    "iso:country":"NL",
    "sg:address":"Bagynestr 59",
    "sg:city":"Leeuwarden",
    "sg:orig_category":"Verenigingen En Stichtingen",
    "sg:phone":"+31 58 213 4105",
    "sg:postcode":"8911 DN",
    "sg:province":"Friesland",
    "wof:name":"Zomerpodium, Sticht",
    "wof:placetype":"venue"
},
  "geometry": {"coordinates":[5.79389,53.201935],"type":"Point"}
}