{
  "type": "Feature",
  "properties": {
    "addr:full":"Nusterwg 69 Sittard Limburg 6136 KT",
    "addr:housenumber":"69",
    "addr:postcode":"6136 kt",
    "addr:street":"Nusterwg",
    "iso:country":"NL",
    "sg:address":"Nusterwg 69",
    "sg:city":"Sittard",
    "sg:orig_category":"Machinefabrieken",
    "sg:phone":"+31 46 457 2555",
    "sg:postcode":"6136 KT",
    "sg:province":"Limburg",
    "wof:name":"Hamers International Bv",
    "wof:placetype":"venue"
},
  "geometry": {"coordinates":[5.866566,51.015816],"type":"Point"}
}