{
  "type": "Feature",
  "properties": {
    "addr:full":"Bautscherweg 8 Heerlen Limburg 6418 EM",
    "addr:housenumber":"8",
    "addr:postcode":"6418 em",
    "addr:street":"Bautscherweg",
    "iso:country":"NL",
    "sg:address":"Bautscherweg 8",
    "sg:city":"Heerlen",
    "sg:orig_category":"Herenmodezaken",
    "sg:phone":"+31 45 542 8501",
    "sg:postcode":"6418 EM",
    "sg:province":"Limburg",
    "wof:name":"Roto Textiel",
    "wof:placetype":"venue"
},
  "geometry": {"coordinates":[6.002297,50.865978],"type":"Point"}
}