{
  "type": "Feature",
  "properties": {
    "addr:full":"Ridderhaven 8 Ridderkerk Zuid-Holland 2984 BT",
    "addr:housenumber":"8",
    "addr:postcode":"2984 bt",
    "addr:street":"Ridderhaven",
    "iso:country":"NL",
    "sg:address":"Ridderhaven 8",
    "sg:city":"Ridderkerk",
    "sg:classifiers":[
        {
            "category":"Retail",
            "subcategory":"Storage",
            "type":"Services"
        }
    ],
    "sg:phone":"+31 180 485 785",
    "sg:postcode":"2984 BT",
    "sg:province":"Zuid-Holland",
    "sg:tags":[
        "op-",
        "en",
        "overslagbedrijven"
    ],
    "wof:name":"Dacapo",
    "wof:placetype":"venue"
},
  "geometry": {"coordinates":[4.616444,51.874989],"type":"Point"}
}