{
  "type": "Feature",
  "properties": {
    "addr:full":"Mej. A. Talmaweg 2 Witteveen Drenthe 9439 PE",
    "addr:housenumber":"2",
    "addr:postcode":"9439 pe",
    "addr:street":"Mej. A. Talmaweg",
    "iso:country":"NL",
    "sg:address":"Mej. A. Talmaweg 2",
    "sg:city":"Witteveen",
    "sg:classifiers":[
        {
            "category":"Education",
            "subcategory":"Preschool",
            "type":"Public Place"
        }
    ],
    "sg:phone":"+31 593 552 307",
    "sg:postcode":"9439 PE",
    "sg:province":"Drenthe",
    "sg:tags":[
        "kleuteronderwijs",
        "basis-"
    ],
    "wof:name":"Openbare Basisschool De Tille",
    "wof:placetype":"venue"
},
  "geometry": {"coordinates":[-38.083542,-8.37738],"type":"Point"}
}