{
  "type": "Feature",
  "properties": {
    "addr:full":"Zoutketen 8 Enkhuizen North Holland 1601 EX",
    "addr:housenumber":"8",
    "addr:postcode":"1601 ex",
    "addr:street":"Zoutketen",
    "iso:country":"NL",
    "sg:address":"Zoutketen 8",
    "sg:city":"Enkhuizen",
    "sg:orig_category":"Jachthavens - Jachtwerven",
    "sg:phone":"+31 228 312 102",
    "sg:postcode":"1601 EX",
    "sg:province":"North Holland",
    "sg:website":"http://www.combi-jachtbouw.nl",
    "wof:name":"Combi Jacht Bouw Bv",
    "wof:placetype":"venue"
},
  "geometry": {"coordinates":[5.275345,52.691772],"type":"Point"}
}