{
  "type": "Feature",
  "properties": {
    "addr:full":"Grotestr 7 Ede Gld Gelderland 6711 AH",
    "addr:housenumber":"7",
    "addr:postcode":"6711 ah",
    "addr:street":"Grotestr;Gld Gelderland",
    "iso:country":"NL",
    "sg:address":"Grotestr 7",
    "sg:city":"Ede Gld",
    "sg:orig_category":"Boeken En Tijdschriften",
    "sg:phone":"+31 318 619 282",
    "sg:postcode":"6711 AH",
    "sg:province":"Gelderland",
    "wof:name":"Boekenvoordeel",
    "wof:placetype":"venue"
},
  "geometry": {"coordinates":[5.669735,52.044109],"type":"Point"}
}