{
  "type": "Feature",
  "properties": {
    "addr:full":"Melkweg 34 Klijndijk Drenthe 7871 PG",
    "addr:housenumber":"34",
    "addr:postcode":"7871 pg",
    "addr:street":"Melkweg",
    "iso:country":"NL",
    "sg:address":"Melkweg 34",
    "sg:city":"Klijndijk",
    "sg:orig_category":"Metaalbekleding And -Behandeling",
    "sg:phone":"+31 591 513 693",
    "sg:postcode":"7871 PG",
    "sg:province":"Drenthe",
    "wof:name":"Turga",
    "wof:placetype":"venue"
},
  "geometry": {"coordinates":[6.863075,52.832939],"type":"Point"}
}