{
  "type": "Feature",
  "properties": {
    "addr:full":"Eindhovensewg 75 Waalre North Brabant 5582 HR",
    "addr:housenumber":"75",
    "addr:postcode":"5582 hr",
    "addr:street":"Eindhovensewg",
    "iso:country":"NL",
    "sg:address":"Eindhovensewg 75",
    "sg:city":"Waalre",
    "sg:orig_category":"Licentiebemiddeling",
    "sg:phone":"+31 40 293 1219",
    "sg:postcode":"5582 HR",
    "sg:province":"North Brabant",
    "sg:website":"http://www.superjewelbox.com",
    "wof:name":"Business Development Eur Vof",
    "wof:placetype":"venue"
},
  "geometry": {"coordinates":[5.478051,51.398575],"type":"Point"}
}