{
  "type": "Feature",
  "properties": {
    "iso:country":"NL",
    "sg:address":"Bergerweg 48",
    "sg:city":"Bergen Nh",
    "sg:orig_category":"Koeriersdiensten",
    "sg:phone":"+31 72 581 8332",
    "sg:postcode":"1862 JV",
    "sg:province":"Noord-Holland",
    "wof:name":"A.C. Bakker Vof",
    "wof:placetype":"venue"
},
  "geometry": {"coordinates":[4.712741,52.6633],"type":"Point"}
}