{
  "type": "Feature",
  "properties": {
    "addr:full":"Aartshertogenln 332A S Hertogenbosch Noord-Brabant 5212 CT",
    "addr:housenumber":"332a",
    "addr:postcode":"5212 ct",
    "addr:street":"S Hertogenbosch",
    "iso:country":"NL",
    "sg:address":"Aartshertogenln 332A",
    "sg:city":"S Hertogenbosch",
    "sg:orig_category":"Wasmachines En Wasdrogers - Onderhoud En Reparatie",
    "sg:phone":"+31 73 641 2352",
    "sg:postcode":"5212 CT",
    "sg:province":"Noord-Brabant",
    "sg:website":"http://www.eutropart.nl",
    "wof:name":"Stofzuiger Wasmachine Centrale",
    "wof:placetype":"venue"
},
  "geometry": {"coordinates":[5.3147711754,51.6992683411],"type":"Point"}
}