{
  "type": "Feature",
  "properties": {
    "iso:country":"NL",
    "sg:address":"Molenwerf 9",
    "sg:city":"Koog Aan De Zaan",
    "sg:orig_category":"Apotheken",
    "sg:phone":"+31 75 635 5511",
    "sg:postcode":"1541 WR",
    "sg:province":"Noord-Holland",
    "wof:name":"Westzijderveld",
    "wof:placetype":"venue"
},
  "geometry": {"coordinates":[4.798188,52.457478],"type":"Point"}
}