{
  "type": "Feature",
  "properties": {
    "addr:full":"Molenmeesterslag 52 Gouda Zuid-Holland 2805 GW",
    "addr:housenumber":"52",
    "addr:postcode":"2805 gw",
    "addr:street":"Molenmeesterslag",
    "iso:country":"NL",
    "sg:address":"Molenmeesterslag 52",
    "sg:city":"Gouda",
    "sg:orig_category":"Metaalwerken",
    "sg:phone":"+31 182 522 044",
    "sg:postcode":"2805 GW",
    "sg:province":"Zuid-Holland",
    "wof:name":"Merkestijn",
    "wof:placetype":"venue"
},
  "geometry": {"coordinates":[4.722956,52.023758],"type":"Point"}
}