{
  "type": "Feature",
  "properties": {
    "addr:full":"Raadhuisstr 2/D Alphen Nb Noord-Brabant 5131 AL",
    "addr:housenumber":"2 / d",
    "addr:postcode":"5131 al",
    "addr:street":"Raadhuisstr",
    "iso:country":"NL",
    "sg:address":"Raadhuisstr 2/D",
    "sg:city":"Alphen Nb",
    "sg:orig_category":"Verloskundigen",
    "sg:phone":"+31 13 508 2773",
    "sg:postcode":"5131 AL",
    "sg:province":"Noord-Brabant",
    "wof:name":"Klavertje, Het",
    "wof:placetype":"venue"
},
  "geometry": {"coordinates":[4.955254,51.48444],"type":"Point"}
}