{
  "type": "Feature",
  "properties": {
    "addr:full":"Bergumermeerstraat 29 Lelystad NL. 8226 JK",
    "addr:housenumber":"29",
    "addr:postcode":"8226 jk",
    "addr:street":"Bergumermeerstraat;Nl.",
    "iso:country":"NL",
    "sg:address":"Bergumermeerstraat 29",
    "sg:city":"Lelystad",
    "sg:orig_category":"Boekhouders",
    "sg:phone":"+31 320 258 556",
    "sg:postcode":"8226 JK",
    "sg:province":"NL.",
    "wof:name":"Administratiekantoor Lelystad",
    "wof:placetype":"venue"
},
  "geometry": {"coordinates":[5.491897,52.490463],"type":"Point"}
}