{
  "type": "Feature",
  "properties": {
    "addr:full":"Hoefbladhof 9 Voorhout Zuid-Holland 2215 DV",
    "addr:housenumber":"9",
    "addr:postcode":"2215 dv",
    "addr:street":"Hoefbladhof",
    "iso:country":"NL",
    "sg:address":"Hoefbladhof 9",
    "sg:city":"Voorhout",
    "sg:orig_category":"Stukadoorsbedrijven",
    "sg:phone":"+31 252 221 919",
    "sg:postcode":"2215 DV",
    "sg:province":"Zuid-Holland",
    "wof:name":"Gertenaar, G E",
    "wof:placetype":"venue"
},
  "geometry": {"coordinates":[4.489434,52.221722],"type":"Point"}
}