{
  "type": "Feature",
  "properties": {
    "addr:full":"Beukenln 60 Eindhoven Noord-Brabant 5651 CD",
    "addr:housenumber":"60",
    "addr:postcode":"5651 cd",
    "addr:street":"Beukenln",
    "iso:country":"NL",
    "sg:address":"Beukenln 60",
    "sg:city":"Eindhoven",
    "sg:classifiers":[
        {
            "category":"Professional",
            "subcategory":"Accounting & Tax Preparation",
            "type":"Services"
        }
    ],
    "sg:phone":"+31 40 291 6111",
    "sg:postcode":"5651 CD",
    "sg:province":"Noord-Brabant",
    "sg:tags":[
        "accountant",
        "en",
        "-kantoren",
        "register-"
    ],
    "sg:website":"http://www.deloitte.nl",
    "wof:name":"Deloitte & Touche",
    "wof:placetype":"venue"
},
  "geometry": {"coordinates":[5.42676,51.463428],"type":"Point"}
}