{
  "type": "Feature",
  "properties": {
    "addr:full":"Roostenln 309 Eindhoven North Brabant 5644 BR",
    "addr:housenumber":"309",
    "addr:postcode":"5644 br",
    "iso:country":"NL",
    "sg:address":"Roostenln 309",
    "sg:city":"Eindhoven",
    "sg:classifiers":[
        {
            "category":"Sports & Exercise",
            "subcategory":"Stables",
            "type":"Entertainment"
        }
    ],
    "sg:phone":"+31 40 211 1237",
    "sg:postcode":"5644 BR",
    "sg:province":"North Brabant",
    "sg:tags":[
        "maneges"
    ],
    "wof:name":"Eindhovense Manege",
    "wof:placetype":"venue"
},
  "geometry": {"coordinates":[5.48331,51.41238],"type":"Point"}
}