{
  "type": "Feature",
  "properties": {
    "addr:full":"Spaklerweg 71 Amsterdam Noord-Holland 1099 BB",
    "addr:housenumber":"71",
    "addr:postcode":"1099 bb",
    "addr:street":"Spaklerweg",
    "iso:country":"NL",
    "sg:address":"Spaklerweg 71",
    "sg:city":"Amsterdam",
    "sg:orig_category":"Drukkerijen And Copyshops",
    "sg:phone":"+31 20 692 0192",
    "sg:postcode":"1099 BB",
    "sg:province":"Noord-Holland",
    "wof:name":"Drukkerij W.C. Den Ouden Bv",
    "wof:placetype":"venue"
},
  "geometry": {"coordinates":[4.921543,52.337284],"type":"Point"}
}