{
  "type": "Feature",
  "properties": {
    "addr:full":"Willemsstr 37 Elst Gld Gelderland 6662 DJ",
    "addr:housenumber":"37",
    "addr:postcode":"6662 dj",
    "addr:street":"Willemsstr;Gld Gelderland",
    "iso:country":"NL",
    "sg:address":"Willemsstr 37",
    "sg:city":"Elst Gld",
    "sg:orig_category":"Ontbijtservice",
    "sg:phone":"+31 481 376 253",
    "sg:postcode":"6662 DJ",
    "sg:province":"Gelderland",
    "wof:name":"Meeuwissen G M",
    "wof:placetype":"venue"
},
  "geometry": {"coordinates":[5.841266,51.917522],"type":"Point"}
}