{
  "type": "Feature",
  "properties": {
    "addr:full":"Javastr 40B Utrecht Utrecht 3531 PN",
    "addr:housenumber":"40b",
    "addr:postcode":"3531 pn",
    "addr:street":"Javastr",
    "iso:country":"NL",
    "sg:address":"Javastr 40B",
    "sg:city":"Utrecht",
    "sg:orig_category":"Webdesign Bureaus",
    "sg:phone":"+31 30 296 6960",
    "sg:postcode":"3531 PN",
    "sg:province":"Utrecht",
    "sg:website":"http://www.slimbit.nl",
    "wof:name":"Slimbit",
    "wof:placetype":"venue"
},
  "geometry": {"coordinates":[5.1021051407,52.0913887024],"type":"Point"}
}