{
  "type": "Feature",
  "properties": {
    "addr:full":"Tongelresestr 441 Eindhoven Noord-Brabant 5641 AV",
    "addr:housenumber":"441",
    "addr:postcode":"5641 av",
    "iso:country":"NL",
    "sg:address":"Tongelresestr 441",
    "sg:city":"Eindhoven",
    "sg:orig_category":"Woningstoffeerders",
    "sg:phone":"+31 40 237 1516",
    "sg:postcode":"5641 AV",
    "sg:province":"Noord-Brabant",
    "wof:name":"Geert Schepers Woningstoffeerder",
    "wof:placetype":"venue"
},
  "geometry": {"coordinates":[5.5136108398,51.4451828003],"type":"Point"}
}