{
  "type": "Feature",
  "properties": {
    "addr:full":"Meidoornln 13 Rotterdam Zuid-Holland 3053 WT",
    "addr:housenumber":"13",
    "addr:postcode":"3053 wt",
    "addr:street":"Meidoornln",
    "iso:country":"NL",
    "sg:address":"Meidoornln 13",
    "sg:city":"Rotterdam",
    "sg:orig_category":"Evenementenverzorging",
    "sg:phone":"+31 10 218 1129",
    "sg:postcode":"3053 WT",
    "sg:province":"Zuid-Holland",
    "wof:name":"Amuze Productions",
    "wof:placetype":"venue"
},
  "geometry": {"coordinates":[4.469561,51.955292],"type":"Point"}
}