{
  "type": "Feature",
  "properties": {
    "addr:full":"Korte Vijverberg 7 'S Gravenhage Zuid-Holland 2513 AB",
    "addr:housenumber":"7 '",
    "addr:postcode":"2513 ab",
    "addr:street":"Korte Vijverberg",
    "iso:country":"NL",
    "sg:address":"Korte Vijverberg 7",
    "sg:city":"'S Gravenhage",
    "sg:orig_category":"Musea And Historische Gebouwen",
    "sg:phone":"+31 70 364 6940",
    "sg:postcode":"2513 AB",
    "sg:province":"Zuid-Holland",
    "wof:name":"Haags Historisch Museum",
    "wof:placetype":"venue"
},
  "geometry": {"coordinates":[4.314008,52.081314],"type":"Point"}
}