{
  "type": "Feature",
  "properties": {
    "addr:full":"Aldenhofstr 78 Beek Lb Missouri 6191 GW",
    "addr:housenumber":"78",
    "addr:postcode":"6191 gw",
    "addr:street":"Aldenhofstr",
    "iso:country":"NL",
    "sg:address":"Aldenhofstr 78",
    "sg:city":"Beek Lb",
    "sg:orig_category":"Meubelen",
    "sg:phone":"+31 46 437 3388",
    "sg:postcode":"6191 GW",
    "sg:province":"Missouri",
    "wof:name":"Janssen",
    "wof:placetype":"venue"
},
  "geometry": {"coordinates":[-93.129936,36.705662],"type":"Point"}
}