{
  "type": "Feature",
  "properties": {
    "addr:full":"Arend 1 Veldhoven North Brabant 5508 KL",
    "addr:housenumber":"1",
    "addr:postcode":"5508 kl",
    "addr:street":"Arend",
    "iso:country":"NL",
    "sg:address":"Arend 1",
    "sg:city":"Veldhoven",
    "sg:orig_category":"Adviesbureaus Bedrijfsorganisatie",
    "sg:phone":"+31 40 206 9618",
    "sg:postcode":"5508 KL",
    "sg:province":"North Brabant",
    "wof:name":"Colen Bv",
    "wof:placetype":"venue"
},
  "geometry": {"coordinates":[5.387819,51.431805],"type":"Point"}
}