{
  "type": "Feature",
  "properties": {
    "addr:full":"Rykswg 59 Naarden Noord-Holland 1411 GE",
    "addr:housenumber":"59",
    "addr:postcode":"1411",
    "addr:street":"Rykswg",
    "iso:country":"NL",
    "sg:address":"Rykswg 59",
    "sg:city":"Naarden",
    "sg:orig_category":"Adviesbureaus Bedrijfsorganisatie",
    "sg:phone":"+31 35 694 0951",
    "sg:postcode":"1411 GE",
    "sg:province":"Noord-Holland",
    "wof:name":"Jager, De",
    "wof:placetype":"venue"
},
  "geometry": {"coordinates":[5.152463,52.289551],"type":"Point"}
}