{
  "type": "Feature",
  "properties": {
    "iso:country":"NL",
    "sg:address":"Pinksterbloemweg 49",
    "sg:city":"Zaandam",
    "sg:orig_category":"Onderhoud And Reparatie Kantoorapparatuur",
    "sg:phone":"+31 75 617 2519",
    "sg:postcode":"1508 BN",
    "sg:province":"Noord-Holland",
    "wof:name":"Computerclean",
    "wof:placetype":"venue"
},
  "geometry": {"coordinates":[4.823449,52.460121],"type":"Point"}
}