{
  "type": "Feature",
  "properties": {
    "addr:full":"Kleine Poellaan 15 Rijsenhout North Holland 1435 GL",
    "addr:housenumber":"15",
    "addr:postcode":"1435 gl",
    "addr:street":"Kleine Poellaan",
    "iso:country":"NL",
    "sg:address":"Kleine Poellaan 15",
    "sg:city":"Rijsenhout",
    "sg:orig_category":"Loodgieterswerk, Verwarming And Sanitaire Installaties",
    "sg:phone":"+31 297 343 702",
    "sg:postcode":"1435 GL",
    "sg:province":"North Holland",
    "wof:name":"Bugoson",
    "wof:placetype":"venue"
},
  "geometry": {"coordinates":[4.70542,52.255554],"type":"Point"}
}