{
  "type": "Feature",
  "properties": {
    "addr:full":"Cobetstr 12 Leiden Zuid-Holland 2313 KC",
    "addr:housenumber":"12",
    "addr:postcode":"2313 kc",
    "addr:street":"Cobetstr",
    "iso:country":"NL",
    "sg:address":"Cobetstr 12",
    "sg:city":"Leiden",
    "sg:orig_category":"Loodgieters",
    "sg:phone":"+31 71 512 5500",
    "sg:postcode":"2313 KC",
    "sg:province":"Zuid-Holland",
    "wof:name":"Bogaard, P A V/D",
    "wof:placetype":"venue"
},
  "geometry": {"coordinates":[4.505653,52.153641],"type":"Point"}
}