{
  "type": "Feature",
  "properties": {
    "addr:full":"J Dykstraln 3 Groningen Groningen 9744 DA",
    "addr:housenumber":"3",
    "addr:postcode":"9744 da",
    "iso:country":"NL",
    "sg:address":"J Dykstraln 3",
    "sg:city":"Groningen",
    "sg:orig_category":"Artsen - Huisartsen",
    "sg:phone":"+31 50 553 1800",
    "sg:postcode":"9744 DA",
    "sg:province":"Groningen",
    "wof:name":"Scholten & S A Scholten-Bolhuis, E",
    "wof:placetype":"venue"
},
  "geometry": {"coordinates":[6.508757,53.205166],"type":"Point"}
}