{
  "type": "Feature",
  "properties": {
    "addr:full":"Oud Loosd Dk 11 Loosdrecht Noord-Holland 1231 LN",
    "addr:housenumber":"11",
    "addr:postcode":"1231 ln",
    "addr:street":"Oud;Dk",
    "iso:country":"NL",
    "sg:address":"Oud Loosd Dk 11",
    "sg:city":"Loosdrecht",
    "sg:orig_category":"Adviesbureaus Bedrijfsorganisatie",
    "sg:phone":"+31 35 582 8523",
    "sg:postcode":"1231 LN",
    "sg:province":"Noord-Holland",
    "sg:website":"http://www.deark.com",
    "wof:name":"Ark, De",
    "wof:placetype":"venue"
},
  "geometry": {"coordinates":[5.124702,52.205887],"type":"Point"}
}