{
  "type": "Feature",
  "properties": {
    "iso:country":"NL",
    "sg:address":"Parkwg 81",
    "sg:city":"Ede Gld",
    "sg:orig_category":"Kappers",
    "sg:phone":"+31 318 622 821",
    "sg:postcode":"6717 HM",
    "sg:province":"Gelderland",
    "wof:name":"People Behind The Mirror",
    "wof:placetype":"venue"
},
  "geometry": {"coordinates":[5.667264,52.02779],"type":"Point"}
}