{
  "type": "Feature",
  "properties": {
    "addr:full":"Postbus 19 Edam Noord-Holland 1135 ZG",
    "addr:housenumber":"19",
    "addr:postcode":"1135 zg",
    "addr:street":"Postbus",
    "iso:country":"NL",
    "sg:address":"Postbus 19",
    "sg:city":"Edam",
    "sg:orig_category":"Horecabenodigdheden",
    "sg:phone":"+31 229 544 321",
    "sg:postcode":"1135 ZG",
    "sg:province":"Noord-Holland",
    "wof:name":"Party Systems",
    "wof:placetype":"venue"
},
  "geometry": {"coordinates":[5.053218,52.511219],"type":"Point"}
}