{
  "type": "Feature",
  "properties": {
    "addr:full":"A M G Schmidtwg 229 Almere Flevoland 1321 NA",
    "addr:housenumber":"229",
    "addr:postcode":"1321 na",
    "addr:street":"A M;Flevoland",
    "iso:country":"NL",
    "sg:address":"A M G Schmidtwg 229",
    "sg:city":"Almere",
    "sg:orig_category":"Koeltechniek",
    "sg:phone":"+31 36 533 2587",
    "sg:postcode":"1321 NA",
    "sg:province":"Flevoland",
    "sg:website":"http://www.ciat.nl",
    "wof:name":"Ciat Ned Bv",
    "wof:placetype":"venue"
},
  "geometry": {"coordinates":[5.178222,52.350845],"type":"Point"}
}