{
  "type": "Feature",
  "properties": {
    "addr:full":"S Signoretstr 27 Almere Flevoland 1325 LC",
    "addr:housenumber":"27",
    "addr:postcode":"1325 lc",
    "addr:street":"Flevoland",
    "iso:country":"NL",
    "sg:address":"S Signoretstr 27",
    "sg:city":"Almere",
    "sg:orig_category":"Verenigingen En Stichtingen",
    "sg:phone":"+31 36 536 9115",
    "sg:postcode":"1325 LC",
    "sg:province":"Flevoland",
    "wof:name":"Ntc, Secretariaat",
    "wof:placetype":"venue"
},
  "geometry": {"coordinates":[5.236061,52.368851],"type":"Point"}
}