{
  "type": "Feature",
  "properties": {
    "iso:country":"NL",
    "sg:address":"Zuidhoven 9 M",
    "sg:city":"Roermond",
    "sg:orig_category":"Koffiebranderijen",
    "sg:phone":"+31 475 457 700",
    "sg:postcode":"6042 PB",
    "sg:province":"Limburg",
    "sg:website":"http://www.beanscoffee.nl",
    "wof:name":"Beans Coffee Bv",
    "wof:placetype":"venue"
},
  "geometry": {"coordinates":[6.048408,51.19352],"type":"Point"}
}