{
  "type": "Feature",
  "properties": {
    "addr:full":"Pr Margrietln 23 Ouderkerk Amstel Noord-Holland 1191 BW",
    "addr:housenumber":"23",
    "addr:postcode":"1191 bw",
    "addr:street":"Ouderkerk Amstel",
    "iso:country":"NL",
    "sg:address":"Pr Margrietln 23",
    "sg:city":"Ouderkerk Amstel",
    "sg:orig_category":"Makelaars En Adviseurs Onroerende Goederen",
    "sg:phone":"+31 20 472 4216",
    "sg:postcode":"1191 BW",
    "sg:province":"Noord-Holland",
    "wof:name":"Loo, Paul Van De",
    "wof:placetype":"venue"
},
  "geometry": {"coordinates":[4.904776,52.296631],"type":"Point"}
}