{
  "type": "Feature",
  "properties": {
    "addr:full":"Molenstr 43 S Gravenhage Zuid-Holland 2513 BJ",
    "addr:housenumber":"43;gravenhage",
    "addr:postcode":"2513 bj",
    "addr:street":"Molenstr;S",
    "iso:country":"NL",
    "sg:address":"Molenstr 43",
    "sg:city":"S Gravenhage",
    "sg:orig_category":"Kunstenaars- Benodigdheden",
    "sg:phone":"+31 70 363 8303",
    "sg:postcode":"2513 BJ",
    "sg:province":"Zuid-Holland",
    "wof:name":"Goedman Molenstraat, V/H",
    "wof:placetype":"venue"
},
  "geometry": {"coordinates":[4.30339,52.078442],"type":"Point"}
}