{
  "type": "Feature",
  "properties": {
    "addr:full":"Jachtlustpln 3 Twello Gelderland 7391 BW",
    "addr:housenumber":"3",
    "addr:postcode":"7391 bw",
    "addr:street":"Jachtlustpln;Gelderland",
    "iso:country":"NL",
    "sg:address":"Jachtlustpln 3",
    "sg:city":"Twello",
    "sg:orig_category":"Zonnebank- En Solariumcentra",
    "sg:phone":"+31 571 276 443",
    "sg:postcode":"7391 BW",
    "sg:province":"Gelderland",
    "wof:name":"Verano",
    "wof:placetype":"venue"
},
  "geometry": {"coordinates":[6.098439,52.234455],"type":"Point"}
}