{
  "type": "Feature",
  "properties": {
    "addr:full":"Cantharelln 23 Ermelo Gelderland 3852 ZR",
    "addr:housenumber":"23",
    "addr:postcode":"3852",
    "addr:street":"Cantharelln;Gelderland",
    "iso:country":"NL",
    "sg:address":"Cantharelln 23",
    "sg:city":"Ermelo",
    "sg:orig_category":"Adviesbureaus Chemische Techniek",
    "sg:phone":"+31 341 561 630",
    "sg:postcode":"3852 ZR",
    "sg:province":"Gelderland",
    "sg:website":"http://www.cebema.com",
    "wof:name":"Cebema",
    "wof:placetype":"venue"
},
  "geometry": {"coordinates":[5.636714,52.292709],"type":"Point"}
}