{
  "type": "Feature",
  "properties": {
    "addr:full":"Raadhuisstr 22 Oosthuizen Noord-Holland 1474 HG",
    "addr:housenumber":"22",
    "addr:postcode":"1474 hg",
    "addr:street":"Raadhuisstr",
    "iso:country":"NL",
    "sg:address":"Raadhuisstr 22",
    "sg:city":"Oosthuizen",
    "sg:orig_category":"Veiligheidsuitrusting En -Kleding",
    "sg:phone":"+31 299 404 449",
    "sg:postcode":"1474 HG",
    "sg:province":"Noord-Holland",
    "sg:website":"http://www.helutex.nl",
    "wof:name":"Helutex-Irenum Bv",
    "wof:placetype":"venue"
},
  "geometry": {"coordinates":[4.995761,52.573189],"type":"Point"}
}