{
  "type": "Feature",
  "properties": {
    "addr:full":"V Heutszln 60A Ede Gelderland 6711 KR",
    "addr:housenumber":"60a",
    "addr:postcode":"6711 kr",
    "addr:street":"Gelderland",
    "iso:country":"NL",
    "sg:address":"V Heutszln 60A",
    "sg:city":"Ede",
    "sg:orig_category":"Verenigingsgebouwen",
    "sg:phone":"+31 318 617 381",
    "sg:postcode":"6711 KR",
    "sg:province":"Gelderland",
    "wof:name":"Spaans Centr",
    "wof:placetype":"venue"
},
  "geometry": {"coordinates":[5.667675,52.044979],"type":"Point"}
}