{
  "type": "Feature",
  "properties": {
    "iso:country":"NL",
    "sg:address":"Ketelstr 45",
    "sg:city":"Arnhem",
    "sg:orig_category":"Warenhuizen",
    "sg:phone":"+31 26 371 5700",
    "sg:postcode":"6811 CZ",
    "sg:province":"Gelderland",
    "sg:website":"http://www.bijenkorf.nl",
    "wof:name":"Bijenkorf Bv, De",
    "wof:placetype":"venue"
},
  "geometry": {"coordinates":[5.908654213,51.9817352295],"type":"Point"}
}