{
  "type": "Feature",
  "properties": {
    "addr:full":"De Reigerstraat 2 Delden Overijssel 7491 XS",
    "addr:housenumber":"2",
    "addr:postcode":"7491 xs",
    "addr:street":"De Reigerstraat",
    "iso:country":"NL",
    "sg:address":"De Reigerstraat 2",
    "sg:city":"Delden",
    "sg:orig_category":"Public Relationbureaus",
    "sg:phone":"+31 74 376 6556",
    "sg:postcode":"7491 XS",
    "sg:province":"Overijssel",
    "wof:name":"Dash 2",
    "wof:placetype":"venue"
},
  "geometry": {"coordinates":[6.712191,52.259441],"type":"Point"}
}