{
  "type": "Feature",
  "properties": {
    "addr:full":"Dooiwg 9A Amerongen Utrecht 3958 BD",
    "addr:housenumber":"9a",
    "addr:postcode":"3958 bd",
    "addr:street":"Dooiwg",
    "iso:country":"NL",
    "sg:address":"Dooiwg 9A",
    "sg:city":"Amerongen",
    "sg:orig_category":"Adviesbureaus Bedrijfsorganisatie",
    "sg:phone":"+31 343 461 623",
    "sg:postcode":"3958 BD",
    "sg:province":"Utrecht",
    "wof:name":"Derksema",
    "wof:placetype":"venue"
},
  "geometry": {"coordinates":[5.452961,51.998997],"type":"Point"}
}