{
  "type": "Feature",
  "properties": {
    "iso:country":"NL",
    "sg:address":"Bergwg 2",
    "sg:city":"Leersum",
    "sg:classifiers":[
        {
            "category":"Shopping",
            "subcategory":"Gifts & Souvenirs",
            "type":"Retail Goods"
        }
    ],
    "sg:phone":"+31 343 456 191",
    "sg:postcode":"3956 BJ",
    "sg:province":"Utrecht",
    "sg:tags":[
        "wens-",
        "en",
        "prentbriefkaarten"
    ],
    "wof:name":"Hannelieke Van De Beek",
    "wof:placetype":"venue"
},
  "geometry": {"coordinates":[5.4304728508,52.0168647766],"type":"Point"}
}