{
  "type": "Feature",
  "properties": {
    "addr:full":"Hoofdwg 169A Oldeholtpade Friesland 8474 CD",
    "addr:housenumber":"169a",
    "addr:postcode":"8474 cd",
    "iso:country":"NL",
    "sg:address":"Hoofdwg 169A",
    "sg:city":"Oldeholtpade",
    "sg:orig_category":"Peuterspeelzalen",
    "sg:phone":"+31 561 688 400",
    "sg:postcode":"8474 CD",
    "sg:province":"Friesland",
    "wof:name":"Anlopien, 'T",
    "wof:placetype":"venue"
},
  "geometry": {"coordinates":[6.046571,52.89307],"type":"Point"}
}