{
  "type": "Feature",
  "properties": {
    "addr:full":"Keizersgr 11 Eindhoven North Brabant 5611 GC",
    "addr:housenumber":"11",
    "addr:postcode":"5611 gc",
    "addr:street":"Keizersgr",
    "iso:country":"NL",
    "sg:address":"Keizersgr 11",
    "sg:city":"Eindhoven",
    "sg:orig_category":"Opticiens",
    "sg:phone":"+31 40 245 5977",
    "sg:postcode":"5611 GC",
    "sg:province":"North Brabant",
    "sg:website":"http://www.hansanders.nl",
    "wof:name":"Hans Anders",
    "wof:placetype":"venue"
},
  "geometry": {"coordinates":[5.4767251015,51.4377174377],"type":"Point"}
}