{
  "type": "Feature",
  "properties": {
    "addr:full":"Blerckweg 19 'T Harde Gelderland 8084 EX",
    "addr:housenumber":"19",
    "addr:postcode":"8084 ex",
    "addr:street":"Blerckweg",
    "iso:country":"NL",
    "sg:address":"Blerckweg 19",
    "sg:city":"'T Harde",
    "sg:classifiers":[
        {
            "category":"Education",
            "subcategory":"Preschool",
            "type":"Public Place"
        }
    ],
    "sg:phone":"+31 525 651 272",
    "sg:postcode":"8084 EX",
    "sg:province":"Gelderland",
    "sg:tags":[
        "kleuteronderwijs",
        "basis-"
    ],
    "wof:name":"Openbare Basisschool Locatie De Blerck",
    "wof:placetype":"venue"
},
  "geometry": {"coordinates":[5.877917,52.417839],"type":"Point"}
}