{
  "type": "Feature",
  "properties": {
    "addr:full":"Schuilenburgerweg 8 Hellendoorn Overijssel 7447 RP",
    "addr:housenumber":"8",
    "addr:postcode":"7447 rp",
    "addr:street":"Schuilenburgerweg",
    "iso:country":"NL",
    "sg:address":"Schuilenburgerweg 8",
    "sg:city":"Hellendoorn",
    "sg:orig_category":"Overheidsdiensten",
    "sg:phone":"+31 548 655 753",
    "sg:postcode":"7447 RP",
    "sg:province":"Overijssel",
    "wof:name":"Heldern Clubhuis",
    "wof:placetype":"venue"
},
  "geometry": {"coordinates":[6.4546990395,52.3937950134],"type":"Point"}
}