{
  "type": "Feature",
  "properties": {
    "iso:country":"NL",
    "sg:address":"Julianastraat 7",
    "sg:city":"Andel",
    "sg:orig_category":"Kappers",
    "sg:phone":"+31 183 443 541",
    "sg:postcode":"4281 NR",
    "sg:province":"Noord-Brabant",
    "wof:name":"Kapsalon Knip Inn",
    "wof:placetype":"venue"
},
  "geometry": {"coordinates":[5.0542759895,51.7847061157],"type":"Point"}
}