{
  "type": "Feature",
  "properties": {
    "addr:full":"Vissedk 46A Almelo Overijssel 7602 CR",
    "addr:housenumber":"46a",
    "addr:postcode":"7602 cr",
    "addr:street":"Vissedk",
    "iso:country":"NL",
    "sg:address":"Vissedk 46A",
    "sg:city":"Almelo",
    "sg:orig_category":"Beeldende Kunstenaars",
    "sg:phone":"+31 546 871 706",
    "sg:postcode":"7602 CR",
    "sg:province":"Overijssel",
    "sg:website":"http://www.robertwjansen.nl",
    "wof:name":"Robert W Jansen",
    "wof:placetype":"venue"
},
  "geometry": {"coordinates":[6.654456,52.364712],"type":"Point"}
}