{
  "type": "Feature",
  "properties": {
    "addr:full":"Blauwe Berg 5 Hoorn Nh Noord-Holland 1625 NT",
    "addr:housenumber":"5",
    "addr:postcode":"1625 nt",
    "addr:street":"Blauwe Berg",
    "iso:country":"NL",
    "sg:address":"Blauwe Berg 5",
    "sg:city":"Hoorn Nh",
    "sg:orig_category":"Artsen - Huisartsen",
    "sg:phone":"+31 229 240 140",
    "sg:postcode":"1625 NT",
    "sg:province":"Noord-Holland",
    "wof:name":"Hoornse Huisartsenver",
    "wof:placetype":"venue"
},
  "geometry": {"coordinates":[5.042034,52.647938],"type":"Point"}
}