{
  "type": "Feature",
  "properties": {
    "addr:full":"Brink 3 Annen Drenthe 9468 BP",
    "addr:housenumber":"3",
    "addr:postcode":"9468 bp",
    "addr:street":"Brink",
    "iso:country":"NL",
    "sg:address":"Brink 3",
    "sg:city":"Annen",
    "sg:orig_category":"Adviesbureaus Bedrijfsorganisatie",
    "sg:phone":"+31 592 278 222",
    "sg:postcode":"9468 BP",
    "sg:province":"Drenthe",
    "sg:website":"http://www.marveladvies.nl",
    "wof:name":"Marvel",
    "wof:placetype":"venue"
},
  "geometry": {"coordinates":[-79.253815,33.471233],"type":"Point"}
}