{
  "type": "Feature",
  "properties": {
    "iso:country":"NL",
    "sg:address":"Visseringwg 11B",
    "sg:city":"Diemen",
    "sg:orig_category":"Glasdakenfabrieken",
    "sg:phone":"+31 20 690 1232",
    "sg:postcode":"1112 AS",
    "sg:province":"Noord-Holland",
    "wof:name":"Glaspost, De",
    "wof:placetype":"venue"
},
  "geometry": {"coordinates":[4.968351,52.333153],"type":"Point"}
}