{
  "type": "Feature",
  "properties": {
    "addr:full":"Waterweg 30 Nunspeet Gelderland 8071 RT",
    "addr:housenumber":"30",
    "addr:postcode":"8071 rt",
    "addr:street":"Waterweg;Gelderland",
    "iso:country":"NL",
    "sg:address":"Waterweg 30",
    "sg:city":"Nunspeet",
    "sg:orig_category":"Bloemen And Planten",
    "sg:phone":"+31 341 257 437",
    "sg:postcode":"8071 RT",
    "sg:province":"Gelderland",
    "wof:name":"Handels- En Boomkwekerij M. Van Den Berg",
    "wof:placetype":"venue"
},
  "geometry": {"coordinates":[5.7722048759,52.3749809265],"type":"Point"}
}