{
  "type": "Feature",
  "properties": {
    "iso:country":"NL",
    "sg:address":"Waarderwg 31",
    "sg:city":"Haarlem",
    "sg:orig_category":"Accumulatoren - Fabrieken En Groothandel",
    "sg:phone":"+31 23 532 9855",
    "sg:postcode":"2031 BN",
    "sg:province":"Noord-Holland",
    "wof:name":"Wilco Nederland Bv",
    "wof:placetype":"venue"
},
  "geometry": {"coordinates":[4.662559,52.389687],"type":"Point"}
}