{
  "type": "Feature",
  "properties": {
    "addr:full":"Melkpad 45 Hilversum Noord-Holland 1217 KB",
    "addr:housenumber":"45",
    "addr:postcode":"1217 kb",
    "addr:street":"Melkpad",
    "iso:country":"NL",
    "sg:address":"Melkpad 45",
    "sg:city":"Hilversum",
    "sg:orig_category":"Advocaten And Juridische Adviseurs",
    "sg:phone":"+31 35 628 4877",
    "sg:postcode":"1217 KB",
    "sg:province":"Noord-Holland",
    "wof:name":"Man & Martens Advocaten",
    "wof:placetype":"venue"
},
  "geometry": {"coordinates":[5.170163,52.22723],"type":"Point"}
}