{
  "type": "Feature",
  "properties": {
    "iso:country":"NL",
    "sg:address":"Vierstr 20",
    "sg:city":"Yerseke",
    "sg:orig_category":"Kinderkleding",
    "sg:phone":"+31 113 571 594",
    "sg:postcode":"4401 EA",
    "sg:province":"Zeeland",
    "wof:name":"Hollestelle, A",
    "wof:placetype":"venue"
},
  "geometry": {"coordinates":[4.050408,51.491516],"type":"Point"}
}