{
  "type": "Feature",
  "properties": {
    "addr:full":"Oude Molenwg 56 Hengelo Ov Overijssel 7551 HD",
    "addr:housenumber":"56",
    "addr:postcode":"7551 hd",
    "addr:street":"Oude Molenwg;Ov",
    "iso:country":"NL",
    "sg:address":"Oude Molenwg 56",
    "sg:city":"Hengelo Ov",
    "sg:orig_category":"Modevakscholen",
    "sg:phone":"+31 74 242 1326",
    "sg:postcode":"7551 HD",
    "sg:province":"Overijssel",
    "wof:name":"Ensaid",
    "wof:placetype":"venue"
},
  "geometry": {"coordinates":[6.789712,52.266361],"type":"Point"}
}