{
  "type": "Feature",
  "properties": {
    "addr:full":"Hoofdstraat 36 Terborg Gelderland 7061 CL",
    "addr:housenumber":"36",
    "addr:postcode":"7061",
    "addr:street":"Hoofdstraat;Gelderland",
    "iso:country":"NL",
    "sg:address":"Hoofdstraat 36",
    "sg:city":"Terborg",
    "sg:orig_category":"Bloemen And Planten",
    "sg:phone":"+31 315 330 530",
    "sg:postcode":"7061 CL",
    "sg:province":"Gelderland",
    "wof:name":"Bloemsierkunst De Waterlelie",
    "wof:placetype":"venue"
},
  "geometry": {"coordinates":[6.359265,51.919563],"type":"Point"}
}