{
  "type": "Feature",
  "properties": {
    "addr:full":"Swaenswykplaats 15 Alphen Aan Den Ryn Zuid-Holland 2405 AV",
    "addr:housenumber":"15",
    "addr:postcode":"2405 av",
    "addr:street":"Swaenswykplaats;Aan Den Ryn",
    "iso:country":"NL",
    "sg:address":"Swaenswykplaats 15",
    "sg:city":"Alphen Aan Den Ryn",
    "sg:orig_category":"Projectinrichting",
    "sg:phone":"+31 172 584 458",
    "sg:postcode":"2405 AV",
    "sg:province":"Zuid-Holland",
    "sg:website":"http://www.inter-act.nl",
    "wof:name":"Interact",
    "wof:placetype":"venue"
},
  "geometry": {"coordinates":[4.662265,52.125671],"type":"Point"}
}