{
  "type": "Feature",
  "properties": {
    "addr:full":"Kanaalstraat 77 Utrecht Utrecht 3531 CB",
    "addr:housenumber":"77",
    "addr:postcode":"3531 cb",
    "addr:street":"Kanaalstraat",
    "iso:country":"NL",
    "sg:address":"Kanaalstraat 77",
    "sg:city":"Utrecht",
    "sg:orig_category":"Huishoudapparatuur, Televisies And Radio'S",
    "sg:phone":"+31 30 294 4340",
    "sg:postcode":"3531 CB",
    "sg:province":"Utrecht",
    "wof:name":"Elma",
    "wof:placetype":"venue"
},
  "geometry": {"coordinates":[5.102199,52.091583],"type":"Point"}
}