{
  "type": "Feature",
  "properties": {
    "addr:full":"Postbus 446 Houten Utrecht 3990 GE",
    "addr:housenumber":"446",
    "addr:postcode":"3990",
    "addr:street":"Postbus",
    "iso:country":"NL",
    "sg:address":"Postbus 446",
    "sg:city":"Houten",
    "sg:orig_category":"Sportverenigingen En Ontspannings- Verenigingen",
    "sg:phone":"+31 30 635 3075",
    "sg:postcode":"3990 GE",
    "sg:province":"Utrecht",
    "wof:name":"Groot Houten Judover",
    "wof:placetype":"venue"
},
  "geometry": {"coordinates":[5.169435,52.036541],"type":"Point"}
}