{
  "type": "Feature",
  "properties": {
    "addr:full":"Sitiopk 1A Doorn Utrecht 3941 PP",
    "addr:housenumber":"1a",
    "addr:postcode":"3941 pp",
    "addr:street":"Sitiopk",
    "iso:country":"NL",
    "sg:address":"Sitiopk 1A",
    "sg:city":"Doorn",
    "sg:orig_category":"Kinderopvang",
    "sg:phone":"+31 343 413 033",
    "sg:postcode":"3941 PP",
    "sg:province":"Utrecht",
    "wof:name":"Hobbelpaard, 'T",
    "wof:placetype":"venue"
},
  "geometry": {"coordinates":[5.346446,52.030704],"type":"Point"}
}