{
  "type": "Feature",
  "properties": {
    "iso:country":"NL",
    "sg:address":"Kon Wilhelminastr 2",
    "sg:city":"Nootdorp",
    "sg:classifiers":[
        {
            "category":"Education",
            "subcategory":"Special Training",
            "type":"Public Place"
        }
    ],
    "sg:phone":"+31 15 310 1047",
    "sg:postcode":"2631 CW",
    "sg:province":"Zuid-Holland",
    "sg:tags":[
        "expertise"
    ],
    "wof:name":"Traffic Control",
    "wof:placetype":"venue"
},
  "geometry": {"coordinates":[4.395514,52.044102],"type":"Point"}
}