{
  "type": "Feature",
  "properties": {
    "addr:full":"Bilderdijklaan 36 Hazerswoude Rijndijk South Holland 2394 EM",
    "addr:housenumber":"36",
    "addr:postcode":"2394 em",
    "addr:street":"Bilderdijklaan;Rijndijk",
    "iso:country":"NL",
    "sg:address":"Bilderdijklaan 36",
    "sg:city":"Hazerswoude Rijndijk",
    "sg:orig_category":"Bedrijfsinventaris Gh",
    "sg:phone":"+31 71 341 4437",
    "sg:postcode":"2394 EM",
    "sg:province":"South Holland",
    "wof:name":"Derks Koeltechniek",
    "wof:placetype":"venue"
},
  "geometry": {"coordinates":[4.589542,52.128487],"type":"Point"}
}