{
  "type": "Feature",
  "properties": {
    "addr:full":"Sint-Mariastraat 75 Rotterdam South Holland 3014 SH",
    "addr:housenumber":"75",
    "addr:postcode":"3014 sh",
    "addr:street":"Sint-Mariastraat",
    "iso:country":"NL",
    "sg:address":"Sint-Mariastraat 75",
    "sg:city":"Rotterdam",
    "sg:orig_category":"Artsen And Specialisten",
    "sg:phone":"+31 10 436 3265",
    "sg:postcode":"3014 SH",
    "sg:province":"South Holland",
    "wof:name":"J. Hekman",
    "wof:placetype":"venue"
},
  "geometry": {"coordinates":[4.468054,51.918324],"type":"Point"}
}