{
  "type": "Feature",
  "properties": {
    "addr:full":"Potgieterstraat 9 Eindhoven Noord-Brabant 5615 GC",
    "addr:housenumber":"9",
    "addr:postcode":"5615 gc",
    "addr:street":"Potgieterstraat",
    "iso:country":"NL",
    "sg:address":"Potgieterstraat 9",
    "sg:city":"Eindhoven",
    "sg:orig_category":"Beursorganisaties And Standbouw",
    "sg:phone":"+31 40 246 5442",
    "sg:postcode":"5615 GC",
    "sg:province":"Noord-Brabant",
    "wof:name":"Muto",
    "wof:placetype":"venue"
},
  "geometry": {"coordinates":[5.475481,51.430546],"type":"Point"}
}