{
  "type": "Feature",
  "properties": {
    "iso:country":"NL",
    "sg:address":"Prins Willem-Alexanderln 1437",
    "sg:city":"Apeldoorn",
    "sg:orig_category":"Autokeuringen",
    "sg:phone":"+31 55 355 5005",
    "sg:postcode":"7312 GB",
    "sg:province":"Gelderland",
    "wof:name":"Garage F. Veeneman",
    "wof:placetype":"venue"
},
  "geometry": {"coordinates":[5.947573,52.205853],"type":"Point"}
}