{
  "type": "Feature",
  "properties": {
    "iso:country":"NL",
    "sg:address":"Mulderstraat 15",
    "sg:city":"Haaksbergen",
    "sg:orig_category":"Loodgieterswerk, Verwarming And Sanitaire Installaties",
    "sg:phone":"+31 74 357 5233",
    "sg:postcode":"7482 NC",
    "sg:province":"NL.08",
    "wof:name":"H.H. Ten Thije Boonkkamp Bronbemaling",
    "wof:placetype":"venue"
},
  "geometry": {"coordinates":[6.699956,52.176628],"type":"Point"}
}