{
  "type": "Feature",
  "properties": {
    "iso:country":"NL",
    "sg:address":"Markt 10",
    "sg:city":"Maassluis",
    "sg:orig_category":"Wasmachines En Wasdrogers",
    "sg:phone":"+31 10 599 0056",
    "sg:postcode":"3142 GG",
    "sg:province":"Zuid-Holland",
    "sg:website":"http://www.stigter-electro.nl",
    "wof:name":"Stigter Electro",
    "wof:placetype":"venue"
},
  "geometry": {"coordinates":[4.254483223,51.9221038818],"type":"Point"}
}