{
  "type": "Feature",
  "properties": {
    "iso:country":"NL",
    "sg:address":"Bonifatiuspolder 21",
    "sg:city":"Dokkum",
    "sg:orig_category":"Satellietontvangst- En Antenne-Installaties",
    "sg:phone":"+31 519 293 627",
    "sg:postcode":"9101 EP",
    "sg:province":"Friesland",
    "wof:name":"Lg Dokkum",
    "wof:placetype":"venue"
},
  "geometry": {"coordinates":[6.00695,53.319679],"type":"Point"}
}