{
  "type": "Feature",
  "properties": {
    "iso:country":"NL",
    "sg:address":"Kerkstr 7A",
    "sg:city":"Eindhoven",
    "sg:orig_category":"Sportverenigingen En Ontspannings- Verenigingen",
    "sg:phone":"+31 40 244 1828",
    "sg:postcode":"5611 GH",
    "sg:province":"Noord-Brabant",
    "sg:website":"http://www.hajraa.nl",
    "wof:name":"Hajraa, Volleybalver",
    "wof:placetype":"venue"
},
  "geometry": {"coordinates":[5.484105,51.434471],"type":"Point"}
}