{
  "type": "Feature",
  "properties": {
    "addr:full":"Van Tillstraat 4 Valkenburg Lb Limburg 6301 DJ",
    "addr:housenumber":"4",
    "addr:postcode":"lb;6301 dj",
    "addr:street":"Van Tillstraat",
    "iso:country":"NL",
    "sg:address":"Van Tillstraat 4",
    "sg:city":"Valkenburg Lb",
    "sg:orig_category":"Verhuur Audiovisuele Apparatuur",
    "sg:phone":"+31 43 601 5730",
    "sg:postcode":"6301 DJ",
    "sg:province":"Limburg",
    "wof:name":"Mixed Music",
    "wof:placetype":"venue"
},
  "geometry": {"coordinates":[5.836787,50.864979],"type":"Point"}
}