{
  "type": "Feature",
  "properties": {
    "addr:full":"Dorpsstr 81 Halsteren North Brabant 4661 HN",
    "addr:housenumber":"81",
    "addr:postcode":"4661 hn",
    "addr:street":"Dorpsstr",
    "iso:country":"NL",
    "sg:address":"Dorpsstr 81",
    "sg:city":"Halsteren",
    "sg:orig_category":"Verzekeringen - Verzekeringskantoren",
    "sg:phone":"+31 164 686 867",
    "sg:postcode":"4661 HN",
    "sg:province":"North Brabant",
    "wof:name":"Baas Assurantien En De Hypotheekshop",
    "wof:placetype":"venue"
},
  "geometry": {"coordinates":[4.271375,51.52354],"type":"Point"}
}