{
  "type": "Feature",
  "properties": {
    "iso:country":"NL",
    "sg:address":"P Krugerstr 41",
    "sg:city":"Assen",
    "sg:orig_category":"Fotografie Reclame En Mode",
    "sg:phone":"+31 6 21564904",
    "sg:postcode":"9401 AG",
    "sg:province":"Drenthe",
    "wof:name":"Fotowerck",
    "wof:placetype":"venue"
},
  "geometry": {"coordinates":[6.568423,52.997646],"type":"Point"}
}