{
  "type": "Feature",
  "properties": {
    "addr:full":"Molendijk 22 Klaaswaal Zuid-Holland 3286 BH",
    "addr:housenumber":"22",
    "addr:postcode":"3286 bh",
    "addr:street":"Molendijk",
    "iso:country":"NL",
    "sg:address":"Molendijk 22",
    "sg:city":"Klaaswaal",
    "sg:classifiers":[
        {
            "category":"Retail",
            "subcategory":"Photofinishing",
            "type":"Services"
        }
    ],
    "sg:phone":"+31 186 572 888",
    "sg:postcode":"3286 BH",
    "sg:province":"Zuid-Holland",
    "sg:tags":[
        "foto",
        "film"
    ],
    "wof:name":"Foto Klein Bv",
    "wof:placetype":"venue"
},
  "geometry": {"coordinates":[4.44329,51.769653],"type":"Point"}
}