{
  "type": "Feature",
  "properties": {
    "addr:full":"Bozenhoven 16A Mydrecht Utrecht 3641 AG",
    "addr:housenumber":"16a",
    "addr:street":"Bozenhoven",
    "iso:country":"NL",
    "sg:address":"Bozenhoven 16A",
    "sg:city":"Mydrecht",
    "sg:orig_category":"Scholen Voor Basisonderwijs",
    "sg:phone":"+31 297 257 459",
    "sg:postcode":"3641 AG",
    "sg:province":"Utrecht",
    "wof:name":"Opdracht Prot Chr, De",
    "wof:placetype":"venue"
},
  "geometry": {"coordinates":[4.866121,52.205021],"type":"Point"}
}