{
  "type": "Feature",
  "properties": {
    "addr:full":"Heemsteedse Dreef 17 Heemstede Noord-Holland 2103 LL",
    "addr:housenumber":"17",
    "addr:postcode":"2103 ll",
    "addr:street":"Heemsteedse Dreef",
    "iso:country":"NL",
    "sg:address":"Heemsteedse Dreef 17",
    "sg:city":"Heemstede",
    "sg:orig_category":"Verzekeringen",
    "sg:phone":"+31 23 528 6626",
    "sg:postcode":"2103 LL",
    "sg:province":"Noord-Holland",
    "wof:name":"Adcentrass Geurts",
    "wof:placetype":"venue"
},
  "geometry": {"coordinates":[4.622498,52.345177],"type":"Point"}
}