{
  "type": "Feature",
  "properties": {
    "iso:country":"NL",
    "sg:address":"Miggelenbergwg 65",
    "sg:city":"Hoenderloo",
    "sg:orig_category":"Vakantieverblijven",
    "sg:phone":"+31 55 378 1251",
    "sg:postcode":"7351 BP",
    "sg:province":"Gelderland",
    "wof:name":"Landal Greenparks Miggelenberg",
    "wof:placetype":"venue"
},
  "geometry": {"coordinates":[5.902962,52.128845],"type":"Point"}
}