{
  "type": "Feature",
  "properties": {
    "iso:country":"NL",
    "sg:address":"Vyfmeiwg 14",
    "sg:city":"Sassenheim",
    "sg:orig_category":"Juridische Adviseurs",
    "sg:phone":"+31 252 230 808",
    "sg:postcode":"2172 VL",
    "sg:province":"Zuid-Holland",
    "wof:name":"Stellingwerf",
    "wof:placetype":"venue"
},
  "geometry": {"coordinates":[4.52183,52.219505],"type":"Point"}
}