{
  "type": "Feature",
  "properties": {
    "iso:country":"NL",
    "sg:address":"Heihoeven 83",
    "sg:city":"Rosmalen",
    "sg:orig_category":"Wegen And Sportterreinen",
    "sg:phone":"+31 73 521 4870",
    "sg:postcode":"5244 GL",
    "sg:province":"North Brabant",
    "wof:name":"Straatmakersbedrijf Kerkhof Bv",
    "wof:placetype":"venue"
},
  "geometry": {"coordinates":[5.3774309158,51.7138214111],"type":"Point"}
}