{
  "type": "Feature",
  "properties": {
    "addr:full":"Grafelykheidswg 82 Dordrecht Zuid-Holland 3328 EM",
    "addr:housenumber":"82",
    "addr:postcode":"3328 em",
    "addr:street":"Grafelykheidswg",
    "iso:country":"NL",
    "sg:address":"Grafelykheidswg 82",
    "sg:city":"Dordrecht",
    "sg:orig_category":"Gehandicapteninformatie",
    "sg:phone":"+31 78 652 5725",
    "sg:postcode":"3328 EM",
    "sg:province":"Zuid-Holland",
    "sg:website":"http://www.sheerenloo.nl",
    "wof:name":"Heeren Loo/Kwadrant, 'S",
    "wof:placetype":"venue"
},
  "geometry": {"coordinates":[4.677292,51.778694],"type":"Point"}
}