{
  "type": "Feature",
  "properties": {
    "addr:full":"Galgenkampsweg 12 Meppel Drenthe 7942 HD",
    "addr:housenumber":"12",
    "addr:postcode":"7942 hd",
    "addr:street":"Galgenkampsweg",
    "iso:country":"NL",
    "sg:address":"Galgenkampsweg 12",
    "sg:city":"Meppel",
    "sg:orig_category":"Zuivelproducten And Spijsoli?n Gh",
    "sg:phone":"+31 522 255 767",
    "sg:postcode":"7942 HD",
    "sg:province":"Drenthe",
    "wof:name":"Ruinemans Kaas Import Export",
    "wof:placetype":"venue"
},
  "geometry": {"coordinates":[6.185032,52.704575],"type":"Point"}
}