{
  "type": "Feature",
  "properties": {
    "iso:country":"NL",
    "sg:address":"B Zweersstr 2",
    "sg:city":"Zaandyk",
    "sg:orig_category":"Woningstoffeerders",
    "sg:phone":"+31 75 771 5550",
    "sg:postcode":"1544 MB",
    "sg:province":"North Holland",
    "wof:name":"Hollander, J H",
    "wof:placetype":"venue"
},
  "geometry": {"coordinates":[4.8120779991,52.4757194519],"type":"Point"}
}