{
  "type": "Feature",
  "properties": {
    "addr:full":"Pr Margrietln 39A Rotterdam Zuid-Holland 3051 AP",
    "addr:housenumber":"39a",
    "addr:postcode":"3051 ap",
    "iso:country":"NL",
    "sg:address":"Pr Margrietln 39A",
    "sg:city":"Rotterdam",
    "sg:orig_category":"Verzekeringen - Verzekeringskantoren",
    "sg:phone":"+31 10 418 6554",
    "sg:postcode":"3051 AP",
    "sg:province":"Zuid-Holland",
    "wof:name":"Gans Bv",
    "wof:placetype":"venue"
},
  "geometry": {"coordinates":[4.486982,51.946495],"type":"Point"}
}