{
  "type": "Feature",
  "properties": {
    "addr:full":"Ninaberlaan 55 Hellendoorn NL.08 7447 AB",
    "addr:housenumber":"55;nl.08",
    "addr:postcode":"7447 ab",
    "addr:street":"Ninaberlaan",
    "iso:country":"NL",
    "sg:address":"Ninaberlaan 55",
    "sg:city":"Hellendoorn",
    "sg:orig_category":"Verzekeringen",
    "sg:phone":"+31 548 655 455",
    "sg:postcode":"7447 AB",
    "sg:province":"NL.08",
    "wof:name":"Assurantieadviesbureau En Adm.Kantoor Je",
    "wof:placetype":"venue"
},
  "geometry": {"coordinates":[6.451066,52.383022],"type":"Point"}
}