{
  "type": "Feature",
  "properties": {
    "addr:full":"Rietven 9 Goirle Noord-Brabant 5051 BX",
    "addr:housenumber":"9",
    "addr:postcode":"5051 bx",
    "addr:street":"Rietven",
    "iso:country":"NL",
    "sg:address":"Rietven 9",
    "sg:city":"Goirle",
    "sg:orig_category":"Accountants - Administratie- Consulenten En -Kantoren",
    "sg:phone":"+31 13 580 0502",
    "sg:postcode":"5051 BX",
    "sg:province":"Noord-Brabant",
    "wof:name":"Gestel Bv, Van",
    "wof:placetype":"venue"
},
  "geometry": {"coordinates":[5.056865,51.525166],"type":"Point"}
}