{
  "type": "Feature",
  "properties": {
    "addr:full":"Emmastraat 36 Hilversum North Holland 1211 NH",
    "addr:housenumber":"36",
    "addr:postcode":"1211 nh",
    "addr:street":"Emmastraat",
    "iso:country":"NL",
    "sg:address":"Emmastraat 36",
    "sg:city":"Hilversum",
    "sg:classifiers":[
        {
            "category":"Retail",
            "subcategory":"Photofinishing",
            "type":"Services"
        }
    ],
    "sg:phone":"+31 35 624 7423",
    "sg:postcode":"1211 NH",
    "sg:province":"North Holland",
    "sg:tags":[
        "foto",
        "film"
    ],
    "wof:name":"Foto Cees V.D. Graaf",
    "wof:placetype":"venue"
},
  "geometry": {"coordinates":[5.179357,52.220867],"type":"Point"}
}