{
  "type": "Feature",
  "properties": {
    "iso:country":"NL",
    "sg:address":"Venusln 4",
    "sg:city":"Bilthoven",
    "sg:orig_category":"Schilders",
    "sg:phone":"+31 6 54782660",
    "sg:postcode":"3721 VG",
    "sg:province":"Utrecht",
    "wof:name":"Vbs",
    "wof:placetype":"venue"
},
  "geometry": {"coordinates":[5.18986,52.12133],"type":"Point"}
}