{
  "type": "Feature",
  "properties": {
    "addr:full":"De Clercqstraat 67 Amsterdam Noord-Holland 1053 AE",
    "addr:housenumber":"67",
    "addr:postcode":"1053 ae",
    "addr:street":"De Clercqstraat",
    "iso:country":"NL",
    "sg:address":"De Clercqstraat 67",
    "sg:city":"Amsterdam",
    "sg:orig_category":"Kappers",
    "sg:phone":"+31 20 618 2713",
    "sg:postcode":"1053 AE",
    "sg:province":"Noord-Holland",
    "wof:name":"Maison Henri",
    "wof:placetype":"venue"
},
  "geometry": {"coordinates":[4.869436,52.370548],"type":"Point"}
}