{
  "type": "Feature",
  "properties": {
    "iso:country":"NL",
    "sg:address":"Wordragensestr 40",
    "sg:city":"Ammerzoden",
    "sg:orig_category":"Loonbedrijven",
    "sg:phone":"+31 73 599 4244",
    "sg:postcode":"5324 JM",
    "sg:province":"Gelderland",
    "wof:name":"Hemert, Joep Van",
    "wof:placetype":"venue"
},
  "geometry": {"coordinates":[5.214351,51.757809],"type":"Point"}
}