{
  "type": "Feature",
  "properties": {
    "addr:full":"Zuiderdiep 531 Nieuw Buinen Drenthe 9521 AP",
    "addr:housenumber":"531",
    "addr:postcode":"9521 ap",
    "addr:street":"Zuiderdiep;Nieuw Buinen",
    "iso:country":"NL",
    "sg:address":"Zuiderdiep 531",
    "sg:city":"Nieuw Buinen",
    "sg:orig_category":"Antiquiteiten",
    "sg:phone":"+31 599 615 303",
    "sg:postcode":"9521 AP",
    "sg:province":"Drenthe",
    "wof:name":"Aalbers, Frits",
    "wof:placetype":"venue"
},
  "geometry": {"coordinates":[6.953297,52.963902],"type":"Point"}
}