{
  "type": "Feature",
  "properties": {
    "addr:full":"J J Willingestr 6 Eenrum Groningen 9967 PB",
    "addr:housenumber":"6",
    "addr:postcode":"9967 pb",
    "addr:street":"Eenrum",
    "iso:country":"NL",
    "sg:address":"J J Willingestr 6",
    "sg:city":"Eenrum",
    "sg:orig_category":"Geluidsinstallaties - Verhuur",
    "sg:phone":"+31 595 491 895",
    "sg:postcode":"9967 PB",
    "sg:province":"Groningen",
    "wof:name":"Nd Power Syst",
    "wof:placetype":"venue"
},
  "geometry": {"coordinates":[6.460662,53.361259],"type":"Point"}
}