{
  "type": "Feature",
  "properties": {
    "iso:country":"NL",
    "sg:address":"Postbus 239",
    "sg:city":"Berkel En Rodenrys",
    "sg:orig_category":"Hek- En Rasterwerken",
    "sg:phone":"+31 900 8212427",
    "sg:postcode":"2650 AE",
    "sg:province":"South Holland",
    "sg:website":"http://www.abchekwerk.nl",
    "wof:name":"Abc Hekwerk Westland",
    "wof:placetype":"venue"
},
  "geometry": {"coordinates":[4.47855,51.992531],"type":"Point"}
}