{
  "type": "Feature",
  "properties": {
    "iso:country":"NL",
    "sg:address":"Oude Molenmeent 9",
    "sg:city":"Loosdrecht",
    "sg:orig_category":"Horecabenodigdheden",
    "sg:phone":"+31 35 582 5450",
    "sg:postcode":"1231 BD",
    "sg:province":"Noord-Holland",
    "wof:name":"Horeva",
    "wof:placetype":"venue"
},
  "geometry": {"coordinates":[5.139221,52.206799],"type":"Point"}
}