{
  "type": "Feature",
  "properties": {
    "addr:full":"Kroeskarper 4 Leiden Zuid-Holland 2318 NG",
    "addr:housenumber":"4",
    "addr:postcode":"2318 ng",
    "addr:street":"Kroeskarper",
    "iso:country":"NL",
    "sg:address":"Kroeskarper 4",
    "sg:city":"Leiden",
    "sg:orig_category":"Organisatiebureaus",
    "sg:phone":"+31 6 51492200",
    "sg:postcode":"2318 NG",
    "sg:province":"Zuid-Holland",
    "wof:name":"Mels",
    "wof:placetype":"venue"
},
  "geometry": {"coordinates":[4.5018582344,52.1831703186],"type":"Point"}
}