{
  "type": "Feature",
  "properties": {
    "addr:full":"J Oldenburgln 14 Bergen Nh Noord-Holland 1861 JT",
    "addr:housenumber":"14",
    "addr:postcode":"1861 jt",
    "iso:country":"NL",
    "sg:address":"J Oldenburgln 14",
    "sg:city":"Bergen Nh",
    "sg:classifiers":[
        {
            "category":"Farming",
            "subcategory":"Fish & Marine Products",
            "type":"Manufacturing & Wholesale Goods"
        }
    ],
    "sg:phone":"+31 72 581 4338",
    "sg:postcode":"1861 JT",
    "sg:province":"Noord-Holland",
    "sg:tags":[
        "vi"
    ],
    "wof:name":"Michel",
    "wof:placetype":"venue"
},
  "geometry": {"coordinates":[4.70248,52.670452],"type":"Point"}
}