{
  "type": "Feature",
  "properties": {
    "addr:full":"Grevinkweg 16 Aalten Gelderland 7122 NE",
    "addr:housenumber":"16",
    "addr:postcode":"7122",
    "addr:street":"Grevinkweg;Gelderland;Ne",
    "iso:country":"NL",
    "sg:address":"Grevinkweg 16",
    "sg:city":"Aalten",
    "sg:orig_category":"Autokeuringen",
    "sg:phone":"+31 543 472 594",
    "sg:postcode":"7122 NE",
    "sg:province":"Gelderland",
    "wof:name":"Vof Autobedrijf Wisselink",
    "wof:placetype":"venue"
},
  "geometry": {"coordinates":[6.561419,51.932274],"type":"Point"}
}