{
  "type": "Feature",
  "properties": {
    "addr:full":"Hasselsestraat 9 Luyksgestel Noord-Brabant 5575 CG",
    "addr:housenumber":"9",
    "addr:postcode":"5575 cg",
    "addr:street":"Hasselsestraat",
    "iso:country":"NL",
    "sg:address":"Hasselsestraat 9",
    "sg:city":"Luyksgestel",
    "sg:orig_category":"Kappers",
    "sg:phone":"+31 497 542 373",
    "sg:postcode":"5575 CG",
    "sg:province":"Noord-Brabant",
    "wof:name":"Linda Look",
    "wof:placetype":"venue"
},
  "geometry": {"coordinates":[5.321212,51.290649],"type":"Point"}
}