{
  "type": "Feature",
  "properties": {
    "addr:full":"Zamenhofdreef 25 Utrecht Utrecht 3562 JT",
    "addr:housenumber":"25",
    "addr:postcode":"3562 jt",
    "addr:street":"Zamenhofdreef",
    "iso:country":"NL",
    "sg:address":"Zamenhofdreef 25",
    "sg:city":"Utrecht",
    "sg:orig_category":"Kaas",
    "sg:phone":"+31 30 261 0962",
    "sg:postcode":"3562 JT",
    "sg:province":"Utrecht",
    "wof:name":"Rebel",
    "wof:placetype":"venue"
},
  "geometry": {"coordinates":[5.1120629311,52.1144676208],"type":"Point"}
}