{
  "type": "Feature",
  "properties": {
    "addr:full":"Baarsln 50 Voorhout South Holland 2215 XL",
    "addr:housenumber":"50",
    "addr:postcode":"2215 xl",
    "addr:street":"Baarsln",
    "iso:country":"NL",
    "sg:address":"Baarsln 50",
    "sg:city":"Voorhout",
    "sg:orig_category":"Kinderopvang",
    "sg:phone":"+31 252 215 835",
    "sg:postcode":"2215 XL",
    "sg:province":"South Holland",
    "wof:name":"Kroostopvang",
    "wof:placetype":"venue"
},
  "geometry": {"coordinates":[4.48252,52.221874],"type":"Point"}
}