{
  "type": "Feature",
  "properties": {
    "addr:full":"Vrijheidslaan 16 Delft Zuid-Holland 2625 RD",
    "addr:housenumber":"16",
    "addr:postcode":"2625 rd",
    "addr:street":"Vrijheidslaan",
    "iso:country":"NL",
    "sg:address":"Vrijheidslaan 16",
    "sg:city":"Delft",
    "sg:classifiers":[
        {
            "category":"Fast Food",
            "type":"Food & Drink"
        }
    ],
    "sg:phone":"+31 15 256 6048",
    "sg:postcode":"2625 RD",
    "sg:province":"Zuid-Holland",
    "sg:tags":[
        "afhaal",
        "restaurant"
    ],
    "wof:name":"Snackbar Balou",
    "wof:placetype":"venue"
},
  "geometry": {"coordinates":[4.346176,51.9879],"type":"Point"}
}