{
  "type": "Feature",
  "properties": {
    "addr:full":"Hoefkade 1004 'S Gravenhage South Holland 2525 LJ",
    "addr:housenumber":"1004 '",
    "addr:postcode":"2525 lj",
    "addr:street":"Hoefkade",
    "iso:country":"NL",
    "sg:address":"Hoefkade 1004",
    "sg:city":"'S Gravenhage",
    "sg:orig_category":"Gespecialiseerde Voeding",
    "sg:phone":"+31 70 389 4343",
    "sg:postcode":"2525 LJ",
    "sg:province":"South Holland",
    "wof:name":"Vof Demir",
    "wof:placetype":"venue"
},
  "geometry": {"coordinates":[4.30601,52.064728],"type":"Point"}
}