{
  "type": "Feature",
  "properties": {
    "iso:country":"NL",
    "sg:address":"Postbus 31376",
    "sg:city":"Nymegen",
    "sg:orig_category":"Adviesbureaus Bedrijfsorganisatie",
    "sg:phone":"+31 24 360 6760",
    "sg:postcode":"6503 CJ",
    "sg:province":"Zuid-Holland",
    "sg:website":"http://www.instituut-iem.nl",
    "wof:name":"Iem Bv",
    "wof:placetype":"venue"
},
  "geometry": {"coordinates":[-106.0737,28.630581],"type":"Point"}
}