{
  "type": "Feature",
  "properties": {
    "addr:full":"Steven Van Rumelaerstr 48 Mijdrecht Utrecht 3641 CM",
    "addr:housenumber":"48",
    "addr:postcode":"3641 cm",
    "addr:street":"Steven;Rumelaerstr",
    "iso:country":"NL",
    "sg:address":"Steven Van Rumelaerstr 48",
    "sg:city":"Mijdrecht",
    "sg:orig_category":"Kappers",
    "sg:phone":"+31 297 283 106",
    "sg:postcode":"3641 CM",
    "sg:province":"Utrecht",
    "wof:name":"Kapsalon Gemma",
    "wof:placetype":"venue"
},
  "geometry": {"coordinates":[4.8618087769,52.2018013],"type":"Point"}
}