{
  "type": "Feature",
  "properties": {
    "addr:full":"Plein 16 'S Gravenhage Zuid-Holland 2511 CR",
    "addr:housenumber":"16",
    "addr:postcode":"2511 cr",
    "addr:street":"Plein;' S",
    "iso:country":"NL",
    "sg:address":"Plein 16",
    "sg:city":"'S Gravenhage",
    "sg:orig_category":"Werving And Selectie Van Tijdelijk Personeel And Uitzendkantoren",
    "sg:phone":"+31 70 362 4661",
    "sg:postcode":"2511 CR",
    "sg:province":"Zuid-Holland",
    "wof:name":"Manpower Uitzendorganisatie Bv",
    "wof:placetype":"venue"
},
  "geometry": {"coordinates":[4.316742897,52.079864502],"type":"Point"}
}