{
  "type": "Feature",
  "properties": {
    "addr:full":"Transvaalstraat 1 Dordrecht Zuid-Holland 3312 EX",
    "addr:housenumber":"1",
    "addr:postcode":"3312 ex",
    "addr:street":"Transvaalstraat",
    "iso:country":"NL",
    "sg:address":"Transvaalstraat 1",
    "sg:city":"Dordrecht",
    "sg:orig_category":"Fietshandelaren",
    "sg:phone":"+31 78 613 8505",
    "sg:postcode":"3312 EX",
    "sg:province":"Zuid-Holland",
    "wof:name":"Dokman Tweewielers",
    "wof:placetype":"venue"
},
  "geometry": {"coordinates":[4.679449,51.80645],"type":"Point"}
}