{
  "type": "Feature",
  "properties": {
    "addr:full":"Blankenhammerweg 12 Luttelgeest Flevoland 8315 PJ",
    "addr:housenumber":"12",
    "addr:postcode":"8315 pj",
    "addr:street":"Blankenhammerweg;Flevoland",
    "iso:country":"NL",
    "sg:address":"Blankenhammerweg 12",
    "sg:city":"Luttelgeest",
    "sg:orig_category":"Verzekeringen",
    "sg:phone":"+31 527 202 505",
    "sg:postcode":"8315 PJ",
    "sg:province":"Flevoland",
    "wof:name":"Geschiere Assurantien",
    "wof:placetype":"venue"
},
  "geometry": {"coordinates":[5.857333,52.74781],"type":"Point"}
}