{
  "type": "Feature",
  "properties": {
    "addr:full":"Bosln 137 Veenendaal Utrecht 3904 KG",
    "addr:housenumber":"137",
    "addr:postcode":"3904 kg",
    "iso:country":"NL",
    "sg:address":"Bosln 137",
    "sg:city":"Veenendaal",
    "sg:orig_category":"Onderhoudswerken",
    "sg:phone":"+31 318 526 995",
    "sg:postcode":"3904 KG",
    "sg:province":"Utrecht",
    "wof:name":"Roest",
    "wof:placetype":"venue"
},
  "geometry": {"coordinates":[5.55418,52.024902],"type":"Point"}
}