{
  "type": "Feature",
  "properties": {
    "addr:full":"Zijlweg 314 Haarlem North Holland 2015 CP",
    "addr:housenumber":"314",
    "addr:postcode":"2015 cp",
    "addr:street":"Zijlweg",
    "iso:country":"NL",
    "sg:address":"Zijlweg 314",
    "sg:city":"Haarlem",
    "sg:orig_category":"Boekhouders",
    "sg:phone":"+31 23 527 7283",
    "sg:postcode":"2015 CP",
    "sg:province":"North Holland",
    "wof:name":"Serka Bv",
    "wof:placetype":"venue"
},
  "geometry": {"coordinates":[4.610832,52.387192],"type":"Point"}
}