{
  "type": "Feature",
  "properties": {
    "addr:full":"Brugstr 23 Roermond Limburg 6041 EP",
    "addr:housenumber":"23",
    "addr:postcode":"6041 ep",
    "addr:street":"Brugstr",
    "iso:country":"NL",
    "sg:address":"Brugstr 23",
    "sg:city":"Roermond",
    "sg:orig_category":"Cafetaria'S",
    "sg:phone":"+31 475 319 051",
    "sg:postcode":"6041 EP",
    "sg:province":"Limburg",
    "wof:name":"Mi-Ja",
    "wof:placetype":"venue"
},
  "geometry": {"coordinates":[5.984182,51.194458],"type":"Point"}
}