{
  "type": "Feature",
  "properties": {
    "addr:full":"Nw Herengr 91 Amsterdam North Holland 1011 RX",
    "addr:housenumber":"91",
    "addr:postcode":"1011 rx",
    "addr:street":"Herengr",
    "iso:country":"NL",
    "sg:address":"Nw Herengr 91",
    "sg:city":"Amsterdam",
    "sg:orig_category":"Beeldende Kunstenaars",
    "sg:phone":"+31 20 625 8458",
    "sg:postcode":"1011 RX",
    "sg:province":"North Holland",
    "wof:name":"Terpstra, Ronald",
    "wof:placetype":"venue"
},
  "geometry": {"coordinates":[4.907434,52.368069],"type":"Point"}
}