{
  "type": "Feature",
  "properties": {
    "addr:full":"Pr Hendrikkd 67A Rotterdam Zuid-Holland 3071 KC",
    "addr:housenumber":"67a",
    "addr:postcode":"3071 kc",
    "iso:country":"NL",
    "sg:address":"Pr Hendrikkd 67A",
    "sg:city":"Rotterdam",
    "sg:orig_category":"Orthopedische Artikelen - Fabrieken En Groothandel",
    "sg:phone":"+31 10 450 1934",
    "sg:postcode":"3071 KC",
    "sg:province":"Zuid-Holland",
    "sg:website":"http://www.als.nl",
    "wof:name":"Abdominal En Lumbal Supp Gear",
    "wof:placetype":"venue"
},
  "geometry": {"coordinates":[4.4971780777,51.9137153625],"type":"Point"}
}