{
  "type": "Feature",
  "properties": {
    "addr:full":"1E Laurierdwstr 35 Amsterdam Noord-Holland 1016 PW",
    "addr:housenumber":"35",
    "addr:postcode":"1016 pw",
    "addr:street":"1E Laurierdwstr",
    "iso:country":"NL",
    "sg:address":"1E Laurierdwstr 35",
    "sg:city":"Amsterdam",
    "sg:orig_category":"Verzekeringen - Verzekeringskantoren",
    "sg:phone":"+31 20 623 6956",
    "sg:postcode":"1016 PW",
    "sg:province":"Noord-Holland",
    "wof:name":"Kalfsvel",
    "wof:placetype":"venue"
},
  "geometry": {"coordinates":[4.88129,52.37204],"type":"Point"}
}