{
  "type": "Feature",
  "properties": {
    "addr:full":"Ambachtswg 14 Andelst Gelderland 6673 DK",
    "addr:housenumber":"14",
    "addr:postcode":"6673 dk",
    "addr:street":"Ambachtswg;Gelderland",
    "iso:country":"NL",
    "sg:address":"Ambachtswg 14",
    "sg:city":"Andelst",
    "sg:orig_category":"Bedrijfsopleidingen",
    "sg:phone":"+31 488 454 368",
    "sg:postcode":"6673 DK",
    "sg:province":"Gelderland",
    "sg:website":"http://www.mondra.nl",
    "wof:name":"Mondra Bv",
    "wof:placetype":"venue"
},
  "geometry": {"coordinates":[5.727265,51.907478],"type":"Point"}
}