{
  "type": "Feature",
  "properties": {
    "addr:full":"Vierwiekenpln 46 Oud Beyerland Zuid-Holland 3262 AN",
    "addr:housenumber":"46",
    "addr:postcode":"3262 an",
    "addr:street":"Vierwiekenpln;Oud Beyerland",
    "iso:country":"NL",
    "sg:address":"Vierwiekenpln 46",
    "sg:city":"Oud Beyerland",
    "sg:orig_category":"Kaas",
    "sg:phone":"+31 186 614 251",
    "sg:postcode":"3262 AN",
    "sg:province":"Zuid-Holland",
    "wof:name":"Besten Bv, Den",
    "wof:placetype":"venue"
},
  "geometry": {"coordinates":[4.4104189873,51.827709198],"type":"Point"}
}