{
  "type": "Feature",
  "properties": {
    "iso:country":"NL",
    "sg:address":"Annevilleln 208",
    "sg:city":"Ulvenhout Ac",
    "sg:orig_category":"Elektrotechnische Installatiebureaus",
    "sg:phone":"+31 76 565 0991",
    "sg:postcode":"4858 RB",
    "sg:province":"Noord-Brabant",
    "sg:website":"http://www.gooyers.nl",
    "wof:name":"Gooyers Bv",
    "wof:placetype":"venue"
},
  "geometry": {"coordinates":[4.821917,51.539097],"type":"Point"}
}