{
  "type": "Feature",
  "properties": {
    "addr:full":"Heerestraat 208 Roden Drenthe 9301 AH",
    "addr:housenumber":"208",
    "addr:postcode":"9301 ah",
    "addr:street":"Heerestraat",
    "iso:country":"NL",
    "sg:address":"Heerestraat 208",
    "sg:city":"Roden",
    "sg:orig_category":"Auto'S And Voertuigen",
    "sg:phone":"+31 50 501 3390",
    "sg:postcode":"9301 AH",
    "sg:province":"Drenthe",
    "wof:name":"A. En H. Jager Bv",
    "wof:placetype":"venue"
},
  "geometry": {"coordinates":[6.429458,53.139153],"type":"Point"}
}