{
  "type": "Feature",
  "properties": {
    "addr:full":"Westerstraat 76 Enkhuizen Noord-Holland 1601 AL",
    "addr:housenumber":"76;1601",
    "addr:postcode":"al",
    "addr:street":"Westerstraat",
    "iso:country":"NL",
    "sg:address":"Westerstraat 76",
    "sg:city":"Enkhuizen",
    "sg:classifiers":[
        {
            "category":"Bakery",
            "type":"Food & Drink"
        }
    ],
    "sg:phone":"+31 228 313 713",
    "sg:postcode":"1601 AL",
    "sg:province":"Noord-Holland",
    "sg:tags":[
        "brood",
        "banket"
    ],
    "wof:name":"Echte Bakker Ko & Trudy Koenis",
    "wof:placetype":"venue"
},
  "geometry": {"coordinates":[5.290804,52.704079],"type":"Point"}
}