{
  "type": "Feature",
  "properties": {
    "addr:full":"Oudeland 120 Zwijndrecht South Holland 3335 VJ",
    "addr:housenumber":"120",
    "addr:postcode":"3335 vj",
    "addr:street":"Oudeland",
    "iso:country":"NL",
    "sg:address":"Oudeland 120",
    "sg:city":"Zwijndrecht",
    "sg:classifiers":[
        {
            "category":"Fast Food",
            "type":"Food & Drink"
        }
    ],
    "sg:phone":"+31 78 610 1436",
    "sg:postcode":"3335 VJ",
    "sg:province":"South Holland",
    "sg:tags":[
        "afhaal",
        "restaurant"
    ],
    "wof:name":"Oudeland Cafetaria",
    "wof:placetype":"venue"
},
  "geometry": {"coordinates":[4.65647,51.822247],"type":"Point"}
}