{
  "type": "Feature",
  "properties": {
    "addr:full":"De Holle Bilt 1 De Bilt Utrecht 3732 HM",
    "addr:housenumber":"1",
    "addr:postcode":"3732 hm",
    "addr:street":"De Holle Bilt",
    "iso:country":"NL",
    "sg:address":"De Holle Bilt 1",
    "sg:city":"De Bilt",
    "sg:classifiers":[
        {
            "category":"Travel",
            "subcategory":"Hotels & Motels",
            "type":"Entertainment"
        }
    ],
    "sg:phone":"+31 30 220 5811",
    "sg:postcode":"3732 HM",
    "sg:province":"Utrecht",
    "sg:website":"http://www.valk.com",
    "wof:name":"Biltsche Hoek Hotel, De",
    "wof:placetype":"venue"
},
  "geometry": {"coordinates":[5.192848,52.102737],"type":"Point"}
}