{
  "type": "Feature",
  "properties": {
    "addr:full":"Tussen De Bruggen 83 Meerssen Limburg 6231 CB",
    "addr:housenumber":"83",
    "addr:postcode":"6231 cb",
    "addr:street":"Tussen De Bruggen",
    "iso:country":"NL",
    "sg:address":"Tussen De Bruggen 83",
    "sg:city":"Meerssen",
    "sg:orig_category":"Hijswerktuigen",
    "sg:phone":"+31 43 364 2232",
    "sg:postcode":"6231 CB",
    "sg:province":"Limburg",
    "wof:name":"Daenen Bv",
    "wof:placetype":"venue"
},
  "geometry": {"coordinates":[5.74682,50.87981],"type":"Point"}
}