{
  "type": "Feature",
  "properties": {
    "iso:country":"NL",
    "sg:address":"Raadhuispln 16",
    "sg:city":"Heemstede",
    "sg:orig_category":"Adviesbureaus Bedrijfsorganisatie",
    "sg:phone":"+31 23 547 2535",
    "sg:postcode":"2101 HB",
    "sg:province":"Noord-Holland",
    "wof:name":"Bosman, Peter J",
    "wof:placetype":"venue"
},
  "geometry": {"coordinates":[4.62043,52.34639],"type":"Point"}
}