{
  "type": "Feature",
  "properties": {
    "addr:full":"Cannenburg 10 Hillegom Zuid-Holland 2181 GT",
    "addr:housenumber":"10",
    "addr:postcode":"2181 gt",
    "addr:street":"Cannenburg",
    "iso:country":"NL",
    "sg:address":"Cannenburg 10",
    "sg:city":"Hillegom",
    "sg:orig_category":"Verzekeringen",
    "sg:phone":"+31 252 516 409",
    "sg:postcode":"2181 GT",
    "sg:province":"Zuid-Holland",
    "wof:name":"Ass Kant J W A Tromp",
    "wof:placetype":"venue"
},
  "geometry": {"coordinates":[4.586765,52.299213],"type":"Point"}
}