{
  "type": "Feature",
  "properties": {
    "addr:full":"Hoofdstr 69 Amstenrade Limburg 6436 CC",
    "addr:housenumber":"69",
    "addr:postcode":"6436 cc",
    "addr:street":"Hoofdstr",
    "iso:country":"NL",
    "sg:address":"Hoofdstr 69",
    "sg:city":"Amstenrade",
    "sg:classifiers":[
        {
            "category":"Real Estate",
            "subcategory":"Real Estate Operator",
            "type":"Services"
        }
    ],
    "sg:phone":"+31 46 442 8038",
    "sg:postcode":"6436 CC",
    "sg:province":"Limburg",
    "sg:tags":[
        "appartementen",
        "en",
        "flat"
    ],
    "wof:name":"Heijlands, P J M",
    "wof:placetype":"venue"
},
  "geometry": {"coordinates":[5.923537,50.941383],"type":"Point"}
}