{
  "type": "Feature",
  "properties": {
    "iso:country":"NL",
    "sg:address":"Hessenstr 20",
    "sg:city":"Borculo",
    "sg:orig_category":"Kabelexploitanten",
    "sg:phone":"+31 545 271 155",
    "sg:postcode":"7271 EC",
    "sg:province":"Gelderland",
    "wof:name":"Cai, Sticht",
    "wof:placetype":"venue"
},
  "geometry": {"coordinates":[6.5151000023,52.1118583679],"type":"Point"}
}