{
  "type": "Feature",
  "properties": {
    "addr:full":"Noordmolenstr 3 Rotterdam Zuid-Holland 3035 RC",
    "addr:housenumber":"3",
    "addr:postcode":"3035 rc",
    "addr:street":"Noordmolenstr",
    "iso:country":"NL",
    "sg:address":"Noordmolenstr 3",
    "sg:city":"Rotterdam",
    "sg:orig_category":"Juweliers",
    "sg:phone":"+31 10 265 1618",
    "sg:postcode":"3035 RC",
    "sg:province":"Zuid-Holland",
    "wof:name":"Casa Blanca",
    "wof:placetype":"venue"
},
  "geometry": {"coordinates":[4.4843440056,51.9311904907],"type":"Point"}
}