{
  "type": "Feature",
  "properties": {
    "addr:full":"Schoolstr 43 Musselkanaal Groningen 9581 GC",
    "addr:housenumber":"43",
    "addr:postcode":"9581 gc",
    "addr:street":"Schoolstr",
    "iso:country":"NL",
    "sg:address":"Schoolstr 43",
    "sg:city":"Musselkanaal",
    "sg:orig_category":"Kamerverhuur En -Bemiddeling",
    "sg:phone":"+31 599 618 552",
    "sg:postcode":"9581 GC",
    "sg:province":"Groningen",
    "wof:name":"Kanaalstreek, De",
    "wof:placetype":"venue"
},
  "geometry": {"coordinates":[6.9749031067,52.9637184143],"type":"Point"}
}