{
  "type": "Feature",
  "properties": {
    "iso:country":"NL",
    "sg:address":"Magazynwg 23",
    "sg:city":"Best",
    "sg:orig_category":"Kantoor- En Bedrijfsmeubelen",
    "sg:phone":"+31 499 393 748",
    "sg:postcode":"5683 CV",
    "sg:province":"Texas",
    "wof:name":"Budget",
    "wof:placetype":"venue"
},
  "geometry": {"coordinates":[-101.6181335449,31.2242507935],"type":"Point"}
}