{
  "type": "Feature",
  "properties": {
    "addr:full":"Postbus 76 Bolsward Provincie Friesland 8700 AB",
    "addr:housenumber":"76",
    "addr:postcode":"8700 ab",
    "addr:street":"Postbus;Provincie Friesland",
    "iso:country":"NL",
    "sg:address":"Postbus 76",
    "sg:city":"Bolsward",
    "sg:orig_category":"Voegwerken",
    "sg:phone":"+31 515 577 105",
    "sg:postcode":"8700 AB",
    "sg:province":"Provincie Friesland",
    "sg:website":"http://www.restauratie.nl",
    "wof:name":"Vogelzang, Snijvoegbedrijf",
    "wof:placetype":"venue"
},
  "geometry": {"coordinates":[5.52312,53.061871],"type":"Point"}
}