{
  "type": "Feature",
  "properties": {
    "addr:full":"Westerkerkweg 60 Venhuizen Noord-Holland 1606 BE",
    "addr:housenumber":"60",
    "addr:postcode":"1606",
    "addr:street":"Westerkerkweg",
    "iso:country":"NL",
    "sg:address":"Westerkerkweg 60",
    "sg:city":"Venhuizen",
    "sg:orig_category":"Granen, Zaden And Diervoeders Gh",
    "sg:phone":"+31 228 541 331",
    "sg:postcode":"1606 BE",
    "sg:province":"Noord-Holland",
    "wof:name":"Gebroeders Langedijk Bv",
    "wof:placetype":"venue"
},
  "geometry": {"coordinates":[5.201482,52.66663],"type":"Point"}
}