{
  "type": "Feature",
  "properties": {
    "addr:full":"Telvorenstraat 2 Hasselt Overijssel 8061 CB",
    "addr:housenumber":"2",
    "addr:postcode":"8061 cb",
    "addr:street":"Telvorenstraat",
    "iso:country":"NL",
    "sg:address":"Telvorenstraat 2",
    "sg:city":"Hasselt",
    "sg:orig_category":"Overheidsdiensten",
    "sg:phone":"+31 38 385 3000",
    "sg:postcode":"8061 CB",
    "sg:province":"Overijssel",
    "wof:name":"Gemeente Zwartewaterland",
    "wof:placetype":"venue"
},
  "geometry": {"coordinates":[6.0961909294,52.5923881531],"type":"Point"}
}