{
  "type": "Feature",
  "properties": {
    "addr:full":"Europaboulev 174 Alkmaar Noord-Holland 1825 SH",
    "addr:housenumber":"174",
    "addr:postcode":"1825 sh",
    "iso:country":"NL",
    "sg:address":"Europaboulev 174",
    "sg:city":"Alkmaar",
    "sg:orig_category":"Fietsen En Bromfietsen",
    "sg:phone":"+31 72 562 3225",
    "sg:postcode":"1825 SH",
    "sg:province":"Noord-Holland",
    "wof:name":"Profile Alkmaar",
    "wof:placetype":"venue"
},
  "geometry": {"coordinates":[4.756811,52.654636],"type":"Point"}
}