{
  "type": "Feature",
  "properties": {
    "addr:full":"Willemstr 36A Delfzyl Groningen 9934 BC",
    "addr:housenumber":"36a",
    "addr:postcode":"9934 bc",
    "addr:street":"Willemstr",
    "iso:country":"NL",
    "sg:address":"Willemstr 36A",
    "sg:city":"Delfzyl",
    "sg:orig_category":"Noten",
    "sg:phone":"+31 596 614 579",
    "sg:postcode":"9934 BC",
    "sg:province":"Groningen",
    "wof:name":"Sweets",
    "wof:placetype":"venue"
},
  "geometry": {"coordinates":[6.928115,53.332031],"type":"Point"}
}