{
  "type": "Feature",
  "properties": {
    "iso:country":"NL",
    "sg:address":"Scheendk 11",
    "sg:city":"Breukelen Ut",
    "sg:orig_category":"Jachthavens - Jachtwerven",
    "sg:phone":"+31 346 261 295",
    "sg:postcode":"3621 VC",
    "sg:province":"Utrecht",
    "wof:name":"Toekomst, De",
    "wof:placetype":"venue"
},
  "geometry": {"coordinates":[5.019177,52.183056],"type":"Point"}
}