{
  "type": "Feature",
  "properties": {
    "addr:full":"Vijzelstraat 22 Amsterdam North Holland 1017 HK",
    "addr:housenumber":"22",
    "addr:postcode":"1017 hk",
    "addr:street":"Vijzelstraat",
    "iso:country":"NL",
    "sg:address":"Vijzelstraat 22",
    "sg:city":"Amsterdam",
    "sg:classifiers":[
        {
            "category":"Shopping",
            "subcategory":"Gifts & Souvenirs",
            "type":"Retail Goods"
        }
    ],
    "sg:phone":"+31 20 423 0230",
    "sg:postcode":"1017 HK",
    "sg:province":"North Holland",
    "sg:tags":[
        "geschenken"
    ],
    "wof:name":"Gone With The Wind",
    "wof:placetype":"venue"
},
  "geometry": {"coordinates":[4.892723,52.365623],"type":"Point"}
}