{
  "type": "Feature",
  "properties": {
    "iso:country":"NL",
    "sg:address":"Oranjesingel 17",
    "sg:city":"Nijmegen",
    "sg:orig_category":"Diverse Grafische Activiteiten",
    "sg:phone":"+31 24 323 7019",
    "sg:postcode":"6511 NL",
    "sg:province":"Gelderland",
    "wof:name":"Forma Bureau Voor Grafische Vormgeving",
    "wof:placetype":"venue"
},
  "geometry": {"coordinates":[5.863646,51.841759],"type":"Point"}
}