{
  "type": "Feature",
  "properties": {
    "addr:full":"Birkstr 79 Soest Utrecht 3768 HC",
    "addr:housenumber":"79",
    "addr:postcode":"3768 hc",
    "addr:street":"Birkstr",
    "iso:country":"NL",
    "sg:address":"Birkstr 79",
    "sg:city":"Soest",
    "sg:orig_category":"Adviesbureaus Bedrijfsorganisatie",
    "sg:phone":"+31 35 601 9275",
    "sg:postcode":"3768 HC",
    "sg:province":"Utrecht",
    "sg:website":"http://www.unitedsense.nl",
    "wof:name":"United Sense",
    "wof:placetype":"venue"
},
  "geometry": {"coordinates":[5.31249,52.162926],"type":"Point"}
}