{
  "type": "Feature",
  "properties": {
    "addr:full":"Oud Over 4 Loenen A/D Vecht Utrecht 3632 VD",
    "addr:housenumber":"4;a / d",
    "addr:postcode":"3632 vd",
    "addr:street":"Oud Over;Vecht",
    "iso:country":"NL",
    "sg:address":"Oud Over 4",
    "sg:city":"Loenen A/D Vecht",
    "sg:orig_category":"Boekhouders",
    "sg:phone":"+31 294 234 965",
    "sg:postcode":"3632 VD",
    "sg:province":"Utrecht",
    "wof:name":"Cooperatieve Werkvereniging Mana Ua",
    "wof:placetype":"venue"
},
  "geometry": {"coordinates":[5.022678,52.206333],"type":"Point"}
}