{
  "type": "Feature",
  "properties": {
    "addr:full":"Wolfswinkel 3 Budel North Brabant 6021 ED",
    "addr:housenumber":"3",
    "addr:postcode":"6021 ed",
    "addr:street":"Wolfswinkel",
    "iso:country":"NL",
    "sg:address":"Wolfswinkel 3",
    "sg:city":"Budel",
    "sg:orig_category":"Kampeerauto'S",
    "sg:phone":"+31 495 430 594",
    "sg:postcode":"6021 ED",
    "sg:province":"North Brabant",
    "wof:name":"Deurzen, Van",
    "wof:placetype":"venue"
},
  "geometry": {"coordinates":[5.5803041458,51.2774505615],"type":"Point"}
}