{
  "type": "Feature",
  "properties": {
    "addr:full":"Heerestraat 24 Baflo Groningen 9953 PJ",
    "addr:housenumber":"24",
    "addr:postcode":"9953 pj",
    "addr:street":"Heerestraat",
    "iso:country":"NL",
    "sg:address":"Heerestraat 24",
    "sg:city":"Baflo",
    "sg:orig_category":"Meubelreparatie And -Restauratie",
    "sg:phone":"+31 595 424 715",
    "sg:postcode":"9953 PJ",
    "sg:province":"Groningen",
    "wof:name":"Jmt Meubelstoffering",
    "wof:placetype":"venue"
},
  "geometry": {"coordinates":[6.513228,53.363461],"type":"Point"}
}