{
  "type": "Feature",
  "properties": {
    "addr:full":"Veldweg 1 Ter Aar Zuid-Holland 2461 GE",
    "addr:housenumber":"1",
    "addr:postcode":"aar;2461",
    "addr:street":"Veldweg;Ter",
    "iso:country":"NL",
    "sg:address":"Veldweg 1",
    "sg:city":"Ter Aar",
    "sg:orig_category":"Bloemen And Planten",
    "sg:phone":"+31 172 602 241",
    "sg:postcode":"2461 GE",
    "sg:province":"Zuid-Holland",
    "wof:name":"Intratuin Ter Aar Bv",
    "wof:placetype":"venue"
},
  "geometry": {"coordinates":[4.717862,52.165146],"type":"Point"}
}