{
  "type": "Feature",
  "properties": {
    "addr:full":"Weissenbruchstr 28Bg Amsterdam Noord-Holland 1058 KN",
    "addr:housenumber":"28bg",
    "addr:postcode":"1058 kn",
    "addr:street":"Weissenbruchstr",
    "iso:country":"NL",
    "sg:address":"Weissenbruchstr 28Bg",
    "sg:city":"Amsterdam",
    "sg:orig_category":"Fournituren - Fabrieken En Groothandel",
    "sg:phone":"+31 20 617 3036",
    "sg:postcode":"1058 KN",
    "sg:province":"Noord-Holland",
    "wof:name":"Star",
    "wof:placetype":"venue"
},
  "geometry": {"coordinates":[4.849875,52.353649],"type":"Point"}
}