{
  "type": "Feature",
  "properties": {
    "addr:full":"Axelsestraat 178 Terneuzen Zeeland 4537 AS",
    "addr:housenumber":"178",
    "addr:postcode":"4537 as",
    "addr:street":"Axelsestraat",
    "iso:country":"NL",
    "sg:address":"Axelsestraat 178",
    "sg:city":"Terneuzen",
    "sg:orig_category":"Verzekeringen",
    "sg:phone":"+31 115 618 344",
    "sg:postcode":"4537 AS",
    "sg:province":"Zeeland",
    "wof:name":"Witte Boussen Assurantien Bv",
    "wof:placetype":"venue"
},
  "geometry": {"coordinates":[3.835821,51.327961],"type":"Point"}
}