{
  "type": "Feature",
  "properties": {
    "iso:country":"NL",
    "sg:address":"Stationspln 4",
    "sg:city":"Voorburg",
    "sg:orig_category":"Waterleidingbedrijven",
    "sg:phone":"+31 70 357 7500",
    "sg:postcode":"2275 AZ",
    "sg:province":"South Holland",
    "wof:name":"Duinwaterbedrijf Zuid-Holl Nv",
    "wof:placetype":"venue"
},
  "geometry": {"coordinates":[4.3585190773,52.0663909912],"type":"Point"}
}