{
  "type": "Feature",
  "properties": {
    "iso:country":"NL",
    "sg:address":"Persoonsdam 137",
    "sg:city":"Rotterdam",
    "sg:orig_category":"Sportverenigingen En Ontspannings- Verenigingen",
    "sg:phone":"+31 10 483 6286",
    "sg:postcode":"3071 EE",
    "sg:province":"Zuid-Holland",
    "wof:name":"Feijenoord Van Teylingen-De Keij Tafeltennisver",
    "wof:placetype":"venue"
},
  "geometry": {"coordinates":[4.5096797943,51.9103813171],"type":"Point"}
}