{
  "type": "Feature",
  "properties": {
    "addr:full":"Valkenboslaan 134A 'S Gravenhage Zuid-Holland 2563 CP",
    "addr:housenumber":"134a '",
    "addr:postcode":"2563 cp",
    "addr:street":"Valkenboslaan",
    "iso:country":"NL",
    "sg:address":"Valkenboslaan 134A",
    "sg:city":"'S Gravenhage",
    "sg:orig_category":"Kunst And Kunstenaarsbenodigdheden",
    "sg:phone":"+31 70 365 2787",
    "sg:postcode":"2563 CP",
    "sg:province":"Zuid-Holland",
    "wof:name":"Lijstengroothandel Maxim",
    "wof:placetype":"venue"
},
  "geometry": {"coordinates":[4.27564,52.074387],"type":"Point"}
}