{
  "type": "Feature",
  "properties": {
    "addr:full":"Lampongstraat 17 Doetinchem Gelderland 7001 CX",
    "addr:housenumber":"17",
    "addr:postcode":"7001 cx",
    "addr:street":"Lampongstraat;Gelderland",
    "iso:country":"NL",
    "sg:address":"Lampongstraat 17",
    "sg:city":"Doetinchem",
    "sg:orig_category":"Kappers",
    "sg:phone":"+31 314 332 387",
    "sg:postcode":"7001 CX",
    "sg:province":"Gelderland",
    "wof:name":"Hairstylist Maroel",
    "wof:placetype":"venue"
},
  "geometry": {"coordinates":[6.2903661728,51.9704666138],"type":"Point"}
}