{
  "type": "Feature",
  "properties": {
    "iso:country":"NL",
    "sg:address":"Rembrandtln 21A",
    "sg:city":"Maassluis",
    "sg:orig_category":"Administratie- En Boekhoudkantoren",
    "sg:phone":"+31 10 592 2345",
    "sg:postcode":"3141 HH",
    "sg:province":"Zuid-Holland",
    "wof:name":"Ifza",
    "wof:placetype":"venue"
},
  "geometry": {"coordinates":[4.26253,51.91811],"type":"Point"}
}