{
  "type": "Feature",
  "properties": {
    "iso:country":"NL",
    "sg:address":"Wisseloordpln 52",
    "sg:city":"Amsterdam Zuidoost",
    "sg:orig_category":"Apotheken",
    "sg:phone":"+31 20 697 3020",
    "sg:postcode":"1106 MH",
    "sg:province":"Noord-Holland",
    "wof:name":"Gein, Apotheek Gezondheidscentrum",
    "wof:placetype":"venue"
},
  "geometry": {"coordinates":[4.987302,52.297611],"type":"Point"}
}