{
  "type": "Feature",
  "properties": {
    "iso:country":"NL",
    "sg:address":"Sluisjesdk 108B",
    "sg:city":"Rotterdam",
    "sg:orig_category":"Verenigingen En Stichtingen",
    "sg:phone":"+31 10 429 9088",
    "sg:postcode":"3087 AJ",
    "sg:province":"Zuid-Holland",
    "wof:name":"Sds, Sticht",
    "wof:placetype":"venue"
},
  "geometry": {"coordinates":[4.452487,51.896259],"type":"Point"}
}