{
  "type": "Feature",
  "properties": {
    "addr:full":"Doctor C J K Van Aalstwg 12 Hoorn Nh Noord-Holland 1625 NV",
    "addr:housenumber":"12",
    "addr:postcode":"1625 nv",
    "addr:street":"Doctor C J K Van Aalstwg",
    "iso:country":"NL",
    "sg:address":"Doctor C J K Van Aalstwg 12",
    "sg:city":"Hoorn Nh",
    "sg:orig_category":"Meubelzaken, Woning- And Keukeninrichting",
    "sg:phone":"+31 229 271 884",
    "sg:postcode":"1625 NV",
    "sg:province":"Noord-Holland",
    "wof:name":"Beter Bed",
    "wof:placetype":"venue"
},
  "geometry": {"coordinates":[5.05207,52.642399],"type":"Point"}
}