{
  "type": "Feature",
  "properties": {
    "addr:full":"Tuurdk 43 T Goy Utrecht 3997 MS",
    "addr:housenumber":"43",
    "addr:postcode":"3997 ms",
    "addr:street":"Tuurdk;T Goy",
    "iso:country":"NL",
    "sg:address":"Tuurdk 43",
    "sg:city":"T Goy",
    "sg:orig_category":"Koel- En Vrieshuizen",
    "sg:phone":"+31 30 601 2144",
    "sg:postcode":"3997 MS",
    "sg:province":"Utrecht",
    "sg:website":"http://www.oostrom-ok.com",
    "wof:name":"Oostrom'S, Koel- En Opslagbedrijf",
    "wof:placetype":"venue"
},
  "geometry": {"coordinates":[5.241352,51.998413],"type":"Point"}
}