{
  "type": "Feature",
  "properties": {
    "addr:full":"Kerkweg-Oost 230 Waddinxveen Zuid-Holland 2741 HA",
    "addr:housenumber":"230",
    "addr:postcode":"2741 ha",
    "addr:street":"Kerkweg-Oost",
    "iso:country":"NL",
    "sg:address":"Kerkweg-Oost 230",
    "sg:city":"Waddinxveen",
    "sg:classifiers":[
        {
            "category":"Education",
            "subcategory":"Preschool",
            "type":"Public Place"
        }
    ],
    "sg:phone":"+31 182 614 421",
    "sg:postcode":"2741 HA",
    "sg:province":"Zuid-Holland",
    "sg:tags":[
        "kleuteronderwijs",
        "basis-"
    ],
    "wof:name":"Theo Thijssen School",
    "wof:placetype":"venue"
},
  "geometry": {"coordinates":[4.658318,52.044247],"type":"Point"}
}