{
  "type": "Feature",
  "properties": {
    "addr:full":"Oranjelaan 173 Rijnsburg Zuid-Holland 2231 DH",
    "addr:housenumber":"173",
    "addr:postcode":"2231 dh",
    "addr:street":"Oranjelaan",
    "iso:country":"NL",
    "sg:address":"Oranjelaan 173",
    "sg:city":"Rijnsburg",
    "sg:orig_category":"Bloemen And Planten",
    "sg:phone":"+31 71 402 2859",
    "sg:postcode":"2231 DH",
    "sg:province":"Zuid-Holland",
    "wof:name":"C. Zwaan",
    "wof:placetype":"venue"
},
  "geometry": {"coordinates":[4.442896,52.185249],"type":"Point"}
}