{
  "type": "Feature",
  "properties": {
    "addr:full":"Nijverheidsstraat 3 Heerhugowaard Noord-Holland 1704 RA",
    "addr:housenumber":"3",
    "addr:postcode":"1704 ra",
    "addr:street":"Nijverheidsstraat",
    "iso:country":"NL",
    "sg:address":"Nijverheidsstraat 3",
    "sg:city":"Heerhugowaard",
    "sg:orig_category":"Boekenuitgeverijen",
    "sg:phone":"+31 72 571 8025",
    "sg:postcode":"1704 RA",
    "sg:province":"Noord-Holland",
    "wof:name":"Adu Bv Drukkerij Uitgeverij",
    "wof:placetype":"venue"
},
  "geometry": {"coordinates":[4.824903,52.672081],"type":"Point"}
}