{
  "type": "Feature",
  "properties": {
    "addr:full":"Berkelkade 14B Zutphen Gelderland 7201 JE",
    "addr:housenumber":"14b",
    "addr:postcode":"7201 je",
    "addr:street":"Berkelkade;Gelderland",
    "iso:country":"NL",
    "sg:address":"Berkelkade 14B",
    "sg:city":"Zutphen",
    "sg:orig_category":"Organisaties And Verenigingen",
    "sg:phone":"+31 575 518 524",
    "sg:postcode":"7201 JE",
    "sg:province":"Gelderland",
    "wof:name":"Kunstuitleen Sbk",
    "wof:placetype":"venue"
},
  "geometry": {"coordinates":[6.1919298172,52.1412506104],"type":"Point"}
}