{
  "type": "Feature",
  "properties": {
    "addr:full":"Van Riesenstraat 3 Heerenveen Friesland 8442 CC",
    "addr:housenumber":"3",
    "addr:postcode":"8442 cc",
    "addr:street":"Van Riesenstraat",
    "iso:country":"NL",
    "sg:address":"Van Riesenstraat 3",
    "sg:city":"Heerenveen",
    "sg:orig_category":"Fietshandelaren",
    "sg:phone":"+31 513 653 033",
    "sg:postcode":"8442 CC",
    "sg:province":"Friesland",
    "wof:name":"Nationale Fiets Projecten Bv",
    "wof:placetype":"venue"
},
  "geometry": {"coordinates":[5.92654,52.956833],"type":"Point"}
}