{
  "type": "Feature",
  "properties": {
    "iso:country":"NL",
    "sg:address":"Handelswg 7",
    "sg:city":"Tynaarlo",
    "sg:classifiers":[
        {
            "category":"Retail",
            "subcategory":"Auto Repair",
            "type":"Services"
        }
    ],
    "sg:phone":"+31 592 543 650",
    "sg:postcode":"9482 WG",
    "sg:province":"Drenthe",
    "sg:tags":[
        "garage"
    ],
    "wof:name":"Oldenhuis, B",
    "wof:placetype":"venue"
},
  "geometry": {"coordinates":[6.600256,53.081779],"type":"Point"}
}