{
  "type": "Feature",
  "properties": {
    "addr:full":"Salmstr 54 Geleen Limburg 6161 EN",
    "addr:housenumber":"54",
    "addr:postcode":"6161 en",
    "addr:street":"Salmstr",
    "iso:country":"NL",
    "sg:address":"Salmstr 54",
    "sg:city":"Geleen",
    "sg:orig_category":"Opticiens",
    "sg:phone":"+31 46 474 9171",
    "sg:postcode":"6161 EN",
    "sg:province":"Limburg",
    "wof:name":"Bemelmans Optiek Bv",
    "wof:placetype":"venue"
},
  "geometry": {"coordinates":[5.8290472031,50.9695549011],"type":"Point"}
}