{
  "type": "Feature",
  "properties": {
    "iso:country":"NL",
    "sg:address":"Archimedesstraat 9",
    "sg:city":"Nijmegen",
    "sg:orig_category":"Overheidsdiensten",
    "sg:phone":"+31 24 356 6520",
    "sg:postcode":"6533 MA",
    "sg:province":"Gelderland",
    "wof:name":"De Schakel",
    "wof:placetype":"venue"
},
  "geometry": {"coordinates":[5.8454198837,51.8100242615],"type":"Point"}
}