{
  "type": "Feature",
  "properties": {
    "iso:country":"NL",
    "sg:address":"Zwarte Kolkstraat 96",
    "sg:city":"Wilp Gld",
    "sg:orig_category":"Huisdierenvoer Fab",
    "sg:phone":"+31 55 323 1827",
    "sg:postcode":"7384 DE",
    "sg:province":"Gelderland",
    "wof:name":"Bosgoed Bv",
    "wof:placetype":"venue"
},
  "geometry": {"coordinates":[6.075706,52.21077],"type":"Point"}
}