{
  "type": "Feature",
  "properties": {
    "addr:full":"De Bergen 28 Helmond North Brabant 5706 RX",
    "addr:housenumber":"28",
    "addr:postcode":"5706 rx",
    "addr:street":"De Bergen",
    "iso:country":"NL",
    "sg:address":"De Bergen 28",
    "sg:city":"Helmond",
    "sg:orig_category":"Technische Studies And Onderzoek",
    "sg:phone":"+31 492 475 013",
    "sg:postcode":"5706 RX",
    "sg:province":"North Brabant",
    "wof:name":"Raynell Technique",
    "wof:placetype":"venue"
},
  "geometry": {"coordinates":[5.643486,51.465714],"type":"Point"}
}