{
  "type": "Feature",
  "properties": {
    "addr:full":"Postbus 11729 'S-Gravenhage 2502 AS",
    "addr:housenumber":"11729",
    "addr:postcode":"2502 as",
    "addr:street":"Postbus",
    "iso:country":"NL",
    "sg:address":"Postbus 11729",
    "sg:city":"'S-Gravenhage",
    "sg:orig_category":"Verenigingen En Stichtingen",
    "sg:phone":"+31 70 347 8871",
    "sg:postcode":"2502 AS",
    "wof:name":"Nogepa",
    "wof:placetype":"venue"
},
  "geometry": {"coordinates":[4.31741,52.083988],"type":"Point"}
}