{
  "type": "Feature",
  "properties": {
    "addr:full":"Lansinkeswg 4 Hengelo Ov Overijssel 7553 AE",
    "addr:housenumber":"4",
    "addr:postcode":"7553 ae",
    "addr:street":"Lansinkeswg;Ov",
    "iso:country":"NL",
    "sg:address":"Lansinkeswg 4",
    "sg:city":"Hengelo Ov",
    "sg:orig_category":"Verzekeringen - Verzekeringskantoren",
    "sg:phone":"+31 74 256 8224",
    "sg:postcode":"7553 AE",
    "sg:province":"Overijssel",
    "wof:name":"Matrix",
    "wof:placetype":"venue"
},
  "geometry": {"coordinates":[6.787897,52.261509],"type":"Point"}
}