{
  "type": "Feature",
  "properties": {
    "iso:country":"NL",
    "sg:address":"De Hoogjens 57",
    "sg:city":"Sleeuwyk",
    "sg:orig_category":"Levensmiddelen - Fabrieken En Groothandel",
    "sg:phone":"+31 183 304 811",
    "sg:postcode":"4254 XV",
    "sg:province":"North Brabant",
    "wof:name":"Bresc Bv",
    "wof:placetype":"venue"
},
  "geometry": {"coordinates":[4.954986,51.809505],"type":"Point"}
}