{
  "type": "Feature",
  "properties": {
    "addr:full":"Dorpstraat 82 Heel Limburg 6097 AR",
    "addr:housenumber":"82",
    "addr:postcode":"6097",
    "addr:street":"Dorpstraat",
    "iso:country":"NL",
    "sg:address":"Dorpstraat 82",
    "sg:city":"Heel",
    "sg:orig_category":"Verzekeringen",
    "sg:phone":"+31 475 571 551",
    "sg:postcode":"6097 AR",
    "sg:province":"Limburg",
    "wof:name":"Fassbender Assurantie En Financiele Dien",
    "wof:placetype":"venue"
},
  "geometry": {"coordinates":[-78.789642,34.73262],"type":"Point"}
}