{
  "type": "Feature",
  "properties": {
    "addr:full":"Parkln 19 Groningen Groningen 9724 AN",
    "addr:housenumber":"19",
    "addr:postcode":"9724 an",
    "addr:street":"Parkln",
    "iso:country":"NL",
    "sg:address":"Parkln 19",
    "sg:city":"Groningen",
    "sg:orig_category":"Piano'S",
    "sg:phone":"+31 50 312 6629",
    "sg:postcode":"9724 AN",
    "sg:province":"Groningen",
    "wof:name":"Klunder Piano'S",
    "wof:placetype":"venue"
},
  "geometry": {"coordinates":[6.57675,53.211639],"type":"Point"}
}