{
  "type": "Feature",
  "properties": {
    "addr:full":"Ribeslaan 27 Sint Pancras North Holland 1834 KP",
    "addr:housenumber":"27",
    "addr:postcode":"1834 kp",
    "addr:street":"Ribeslaan",
    "iso:country":"NL",
    "sg:address":"Ribeslaan 27",
    "sg:city":"Sint Pancras",
    "sg:orig_category":"Kappers",
    "sg:phone":"+31 72 562 6228",
    "sg:postcode":"1834 KP",
    "sg:province":"North Holland",
    "wof:name":"Haircare At Home",
    "wof:placetype":"venue"
},
  "geometry": {"coordinates":[4.7902851105,52.6592102051],"type":"Point"}
}