{
  "type": "Feature",
  "properties": {
    "addr:full":"Zwaferinksweg 5 Losser NL.08 7582 RB",
    "addr:housenumber":"5;nl.08",
    "addr:postcode":"7582 rb",
    "addr:street":"Zwaferinksweg",
    "iso:country":"NL",
    "sg:address":"Zwaferinksweg 5",
    "sg:city":"Losser",
    "sg:orig_category":"Metaalafval, Schrootrecycling And Sloperijen",
    "sg:phone":"+31 53 538 1701",
    "sg:postcode":"7582 RB",
    "sg:province":"NL.08",
    "wof:name":"Autobedrijf Westerhof",
    "wof:placetype":"venue"
},
  "geometry": {"coordinates":[6.999064,52.241665],"type":"Point"}
}