{
  "type": "Feature",
  "properties": {
    "addr:full":"Veldkersln 9 Enschede Overijssel 7534 JS",
    "addr:housenumber":"9",
    "addr:postcode":"7534 js",
    "addr:street":"Veldkersln",
    "iso:country":"NL",
    "sg:address":"Veldkersln 9",
    "sg:city":"Enschede",
    "sg:orig_category":"Huidverzorgingsartikelen",
    "sg:phone":"+31 53 461 4589",
    "sg:postcode":"7534 JS",
    "sg:province":"Overijssel",
    "wof:name":"Merlynda Bv",
    "wof:placetype":"venue"
},
  "geometry": {"coordinates":[6.970155,52.215504],"type":"Point"}
}