{
  "type": "Feature",
  "properties": {
    "addr:full":"Hammerstraat 12 Vroomshoop Overijssel 7681 DC",
    "addr:housenumber":"12",
    "addr:postcode":"7681",
    "addr:street":"Hammerstraat",
    "iso:country":"NL",
    "sg:address":"Hammerstraat 12",
    "sg:city":"Vroomshoop",
    "sg:orig_category":"Opticiens",
    "sg:phone":"+31 546 642 389",
    "sg:postcode":"7681 DC",
    "sg:province":"Overijssel",
    "wof:name":"Pearle Opticiens",
    "wof:placetype":"venue"
},
  "geometry": {"coordinates":[6.5711169243,52.4613685608],"type":"Point"}
}