{
  "type": "Feature",
  "properties": {
    "addr:full":"Stationsplein 7 Roermond Limburg 6041 GN",
    "addr:housenumber":"7",
    "addr:postcode":"6041 gn",
    "addr:street":"Stationsplein",
    "iso:country":"NL",
    "sg:address":"Stationsplein 7",
    "sg:city":"Roermond",
    "sg:orig_category":"Werving And Selectie Van Vast Personeel",
    "sg:phone":"+31 475 317 646",
    "sg:postcode":"6041 GN",
    "sg:province":"Limburg",
    "wof:name":"Extens Detacheringsbureau",
    "wof:placetype":"venue"
},
  "geometry": {"coordinates":[5.9932789803,51.1923027039],"type":"Point"}
}