{
  "type": "Feature",
  "properties": {
    "addr:full":"Kocherplnts 1 Muiderberg North Holland 1399 VW",
    "addr:housenumber":"1",
    "addr:postcode":"1399 vw",
    "addr:street":"Kocherplnts",
    "iso:country":"NL",
    "sg:address":"Kocherplnts 1",
    "sg:city":"Muiderberg",
    "sg:orig_category":"Bejaarden - Verzorgingstehuizen",
    "sg:phone":"+31 294 263 351",
    "sg:postcode":"1399 VW",
    "sg:province":"North Holland",
    "wof:name":"Florisberg Zorgcentrum",
    "wof:placetype":"venue"
},
  "geometry": {"coordinates":[5.116071,52.327091],"type":"Point"}
}