{
  "type": "Feature",
  "properties": {
    "addr:full":"Polderwg O 10 Molenaarsgraaf South Holland 2973 AN",
    "addr:housenumber":"10",
    "addr:postcode":"2973 an",
    "iso:country":"NL",
    "sg:address":"Polderwg O 10",
    "sg:city":"Molenaarsgraaf",
    "sg:orig_category":"Autoschade- Herstelbedrijven",
    "sg:phone":"+31 184 642 432",
    "sg:postcode":"2973 AN",
    "sg:province":"South Holland",
    "wof:name":"Dirks",
    "wof:placetype":"venue"
},
  "geometry": {"coordinates":[4.829187,51.876385],"type":"Point"}
}