{
  "type": "Feature",
  "properties": {
    "addr:full":"Flottielje 3 Uithoorn Noord-Holland 1423 AL",
    "addr:housenumber":"3",
    "addr:postcode":"1423 al",
    "addr:street":"Flottielje",
    "iso:country":"NL",
    "sg:address":"Flottielje 3",
    "sg:city":"Uithoorn",
    "sg:orig_category":"Kinderopvang Behalve Thuis",
    "sg:phone":"+31 297 562 280",
    "sg:postcode":"1423 AL",
    "sg:province":"Noord-Holland",
    "wof:name":"Ook (Organisatie Voor Opvang Van Kindere",
    "wof:placetype":"venue"
},
  "geometry": {"coordinates":[4.823868,52.231953],"type":"Point"}
}