{
  "type": "Feature",
  "properties": {
    "addr:full":"Benedenrywg 186 Ridderkerk South Holland 2987 VB",
    "addr:housenumber":"186",
    "addr:postcode":"2987 vb",
    "iso:country":"NL",
    "sg:address":"Benedenrywg 186",
    "sg:city":"Ridderkerk",
    "sg:orig_category":"Plaatwerk",
    "sg:phone":"+31 180 441 800",
    "sg:postcode":"2987 VB",
    "sg:province":"South Holland",
    "wof:name":"Dam Bv, Van",
    "wof:placetype":"venue"
},
  "geometry": {"coordinates":[4.583866,51.895206],"type":"Point"}
}