{
  "type": "Feature",
  "properties": {
    "iso:country":"NL",
    "sg:address":"Vryheidspln 58-64",
    "sg:city":"Zeist",
    "sg:orig_category":"Postkantoren",
    "sg:phone":"+31 30 294 2640",
    "sg:postcode":"3705 PS",
    "sg:province":"Utrecht",
    "sg:website":"http://www.postkantoor.nl",
    "wof:name":"Postkantoor",
    "wof:placetype":"venue"
},
  "geometry": {"coordinates":[5.244998,52.10146],"type":"Point"}
}