{
  "type": "Feature",
  "properties": {
    "addr:full":"Postbus 279 Krimpen Aan Den Ijssel Zuid-Holland 2920 AG",
    "addr:housenumber":"279",
    "addr:postcode":"2920",
    "addr:street":"Postbus",
    "iso:country":"NL",
    "sg:address":"Postbus 279",
    "sg:city":"Krimpen Aan Den Ijssel",
    "sg:orig_category":"Omroep",
    "sg:phone":"+31 180 552 111",
    "sg:postcode":"2920 AG",
    "sg:province":"Zuid-Holland",
    "wof:name":"Lok Omroep Krimpen",
    "wof:placetype":"venue"
},
  "geometry": {"coordinates":[4.587152,51.914452],"type":"Point"}
}