{
  "type": "Feature",
  "properties": {
    "addr:full":"Zuiddijk 424 Zaandam Noord-Holland 1505 HE",
    "addr:housenumber":"424",
    "addr:postcode":"1505 he",
    "addr:street":"Zuiddijk",
    "iso:country":"NL",
    "sg:address":"Zuiddijk 424",
    "sg:city":"Zaandam",
    "sg:classifiers":[
        {
            "category":"Education",
            "subcategory":"Preschool",
            "type":"Public Place"
        }
    ],
    "sg:phone":"+31 75 617 7392",
    "sg:postcode":"1505 HE",
    "sg:province":"Noord-Holland",
    "sg:tags":[
        "kleuteronderwijs",
        "basis-"
    ],
    "wof:name":"Chief Body Repair Systems Bv",
    "wof:placetype":"venue"
},
  "geometry": {"coordinates":[4.84131,52.424725],"type":"Point"}
}