{
  "type": "Feature",
  "properties": {
    "iso:country":"NL",
    "sg:address":"Baarlo 4",
    "sg:city":"Baarlo Ov",
    "sg:orig_category":"Diverse Consumentenartikelen Gh",
    "sg:phone":"+31 527 291 982",
    "sg:postcode":"8372 VJ",
    "sg:province":"Overijssel",
    "wof:name":"Rutger Ten Broeke",
    "wof:placetype":"venue"
},
  "geometry": {"coordinates":[5.949505,52.738033],"type":"Point"}
}