{
  "type": "Feature",
  "properties": {
    "iso:country":"NL",
    "sg:address":"Nijverheidssingel 313",
    "sg:city":"Breda",
    "sg:orig_category":"Bedrijfs- And Managementsconsultants",
    "sg:phone":"+31 76 533 0440",
    "sg:postcode":"4811 ZW",
    "sg:province":"Noord-Brabant",
    "wof:name":"Groenewout Consultants & Engineers",
    "wof:placetype":"venue"
},
  "geometry": {"coordinates":[4.767663,51.590752],"type":"Point"}
}