{
  "type": "Feature",
  "properties": {
    "addr:full":"Tollensstr 27 Schiedam Zuid-Holland 3117 SW",
    "addr:housenumber":"27",
    "addr:postcode":"3117 sw",
    "addr:street":"Tollensstr",
    "iso:country":"NL",
    "sg:address":"Tollensstr 27",
    "sg:city":"Schiedam",
    "sg:orig_category":"Agenturen En Commissiehandel",
    "sg:phone":"+31 10 473 6635",
    "sg:postcode":"3117 SW",
    "sg:province":"Zuid-Holland",
    "wof:name":"Oop",
    "wof:placetype":"venue"
},
  "geometry": {"coordinates":[4.387429,51.914551],"type":"Point"}
}