{
  "type": "Feature",
  "properties": {
    "iso:country":"NL",
    "sg:address":"Dorpsplein 15",
    "sg:city":"Callantsoog",
    "sg:orig_category":"Warenhuizen",
    "sg:phone":"+31 224 581 781",
    "sg:postcode":"1759 GM",
    "sg:province":"Noord-Holland",
    "wof:name":"Firma Warenhuis Hoko",
    "wof:placetype":"venue"
},
  "geometry": {"coordinates":[4.6937460899,52.8355674744],"type":"Point"}
}