{
  "type": "Feature",
  "properties": {
    "addr:full":"Elststraat 1 Rosmalen North Brabant 5242 AE",
    "addr:housenumber":"1",
    "addr:postcode":"5242 ae",
    "addr:street":"Elststraat",
    "iso:country":"NL",
    "sg:address":"Elststraat 1",
    "sg:city":"Rosmalen",
    "sg:orig_category":"Verzekeringen",
    "sg:phone":"+31 73 522 0100",
    "sg:postcode":"5242 AE",
    "sg:province":"North Brabant",
    "wof:name":"Van Sambeek & Oeben Bv",
    "wof:placetype":"venue"
},
  "geometry": {"coordinates":[5.356592,51.706284],"type":"Point"}
}