{
  "type": "Feature",
  "properties": {
    "addr:full":"Legmeerstr 79 Amsterdam Noord-Holland 1058 NC",
    "addr:housenumber":"79;1058",
    "addr:postcode":"nc",
    "addr:street":"Legmeerstr",
    "iso:country":"NL",
    "sg:address":"Legmeerstr 79",
    "sg:city":"Amsterdam",
    "sg:orig_category":"Beeldende Kunstenaars",
    "sg:phone":"+31 20 614 0327",
    "sg:postcode":"1058 NC",
    "sg:province":"Noord-Holland",
    "wof:name":"Kar, P J A M Van De",
    "wof:placetype":"venue"
},
  "geometry": {"coordinates":[4.851119,52.351528],"type":"Point"}
}