{
  "type": "Feature",
  "properties": {
    "addr:full":"Handelstraat 52 Aalsmeer Noord-Holland 1431 ZE",
    "addr:housenumber":"52",
    "addr:postcode":"1431 ze",
    "addr:street":"Handelstraat",
    "iso:country":"NL",
    "sg:address":"Handelstraat 52",
    "sg:city":"Aalsmeer",
    "sg:orig_category":"Bedrijfs- And Managementsconsultants",
    "sg:phone":"+31 297 327 329",
    "sg:postcode":"1431 ZE",
    "sg:province":"Noord-Holland",
    "wof:name":"Duyster Consultancy",
    "wof:placetype":"venue"
},
  "geometry": {"coordinates":[4.76884,52.250675],"type":"Point"}
}