{
  "type": "Feature",
  "properties": {
    "addr:full":"Poststraat 32 Zierikzee Zeeland 4301 AD",
    "addr:housenumber":"32",
    "addr:postcode":"4301 ad",
    "addr:street":"Poststraat",
    "iso:country":"NL",
    "sg:address":"Poststraat 32",
    "sg:city":"Zierikzee",
    "sg:orig_category":"Juridische Dienstverlening",
    "sg:phone":"+31 111 450 445",
    "sg:postcode":"4301 AD",
    "sg:province":"Zeeland",
    "wof:name":"F.T. Van Rotterdam",
    "wof:placetype":"venue"
},
  "geometry": {"coordinates":[3.917895,51.650169],"type":"Point"}
}