{
  "type": "Feature",
  "properties": {
    "addr:full":"Kerkweg 10 Brandwijk Zuid-Holland 2974 LH",
    "addr:housenumber":"10",
    "addr:postcode":"2974 lh",
    "addr:street":"Kerkweg",
    "iso:country":"NL",
    "sg:address":"Kerkweg 10",
    "sg:city":"Brandwijk",
    "sg:classifiers":[
        {
            "category":"Education",
            "subcategory":"Preschool",
            "type":"Public Place"
        }
    ],
    "sg:phone":"+31 184 641 950",
    "sg:postcode":"2974 LH",
    "sg:province":"Zuid-Holland",
    "sg:tags":[
        "kleuteronderwijs",
        "basis-"
    ],
    "wof:name":"Openbare Basisschool De Overstap",
    "wof:placetype":"venue"
},
  "geometry": {"coordinates":[4.822158,51.878296],"type":"Point"}
}