{
  "type": "Feature",
  "properties": {
    "addr:full":"Breukelsestr 2 Boxtel Noord-Brabant 5281 HD",
    "addr:housenumber":"2",
    "addr:postcode":"5281 hd",
    "addr:street":"Breukelsestr",
    "iso:country":"NL",
    "sg:address":"Breukelsestr 2",
    "sg:city":"Boxtel",
    "sg:orig_category":"Sportverenigingen En Ontspannings- Verenigingen",
    "sg:phone":"+31 411 672 068",
    "sg:postcode":"5281 HD",
    "sg:province":"Noord-Brabant",
    "wof:name":"Handboog Sport Boxtel",
    "wof:placetype":"venue"
},
  "geometry": {"coordinates":[5.321227,51.587387],"type":"Point"}
}