{
  "type": "Feature",
  "properties": {
    "iso:country":"NL",
    "sg:address":"Hulster Nieuwlandweg 1",
    "sg:city":"Hulst",
    "sg:orig_category":"Boekhouders",
    "sg:phone":"+31 114 320 212",
    "sg:postcode":"4561 HA",
    "sg:province":"Zeeland",
    "wof:name":"Accountants- En Admin Kantoor Goedbloed",
    "wof:placetype":"venue"
},
  "geometry": {"coordinates":[4.049021,51.28463],"type":"Point"}
}