{
  "type": "Feature",
  "properties": {
    "addr:full":"Fatimastraat 81 Tilburg Noord-Brabant 5021 AM",
    "addr:housenumber":"81",
    "addr:postcode":"5021",
    "addr:street":"Fatimastraat",
    "iso:country":"NL",
    "sg:address":"Fatimastraat 81",
    "sg:city":"Tilburg",
    "sg:orig_category":"Diverse Grafische Activiteiten",
    "sg:phone":"+31 13 580 0426",
    "sg:postcode":"5021 AM",
    "sg:province":"Noord-Brabant",
    "wof:name":"Dgs Visueel",
    "wof:placetype":"venue"
},
  "geometry": {"coordinates":[5.100021,51.550694],"type":"Point"}
}