{
  "type": "Feature",
  "properties": {
    "iso:country":"NL",
    "sg:address":"Mozartlaan 13",
    "sg:city":"Vlaardingen",
    "sg:orig_category":"Begrafenisondernemers",
    "sg:phone":"+31 10 460 0509",
    "sg:postcode":"3131 ES",
    "sg:province":"Zuid-Holland",
    "wof:name":"Begrafenisonderneming T. Den Hollander",
    "wof:placetype":"venue"
},
  "geometry": {"coordinates":[4.338195,51.906998],"type":"Point"}
}