{
  "type": "Feature",
  "properties": {
    "addr:full":"Mozartlaan 13 Vlaardingen Zuid-Holland 3131 ES",
    "addr:housenumber":"13",
    "addr:postcode":"3131 es",
    "addr:street":"Mozartlaan",
    "iso:country":"NL",
    "sg:address":"Mozartlaan 13",
    "sg:city":"Vlaardingen",
    "sg:orig_category":"Begrafenisondernemers",
    "sg:phone":"+31 10 460 0509",
    "sg:postcode":"3131 ES",
    "sg:province":"Zuid-Holland",
    "wof:name":"Begrafenisonderneming T. Den Hollander",
    "wof:placetype":"venue"
},
  "geometry": {"coordinates":[4.338195,51.906998],"type":"Point"}
}