{
  "type": "Feature",
  "properties": {
    "iso:country":"NL",
    "sg:address":"T Grachtje 5",
    "sg:city":"Blaricum",
    "sg:orig_category":"Kantoor- En Bedrijfsmeubelen",
    "sg:phone":"+31 35 526 2740",
    "sg:postcode":"1261 MZ",
    "sg:province":"Noord-Holland",
    "wof:name":"Kappetein",
    "wof:placetype":"venue"
},
  "geometry": {"coordinates":[5.2646789551,52.2872123718],"type":"Point"}
}