{
  "type": "Feature",
  "properties": {
    "addr:full":"Sibeliusstr 48 Bergen Op Zoom Noord-Brabant 4614 VD",
    "addr:housenumber":"48",
    "addr:postcode":"4614 vd",
    "addr:street":"Sibeliusstr",
    "iso:country":"NL",
    "sg:address":"Sibeliusstr 48",
    "sg:city":"Bergen Op Zoom",
    "sg:orig_category":"Cafetaria'S",
    "sg:phone":"+31 164 242 178",
    "sg:postcode":"4614 VD",
    "sg:province":"Noord-Brabant",
    "wof:name":"Sibelius",
    "wof:placetype":"venue"
},
  "geometry": {"coordinates":[4.296054,51.505001],"type":"Point"}
}