{
  "type": "Feature",
  "properties": {
    "addr:full":"Veerwg 110 Papendrecht Zuid-Holland 3353 GW",
    "addr:housenumber":"110",
    "addr:postcode":"papendrecht;3353 gw",
    "iso:country":"NL",
    "sg:address":"Veerwg 110",
    "sg:city":"Papendrecht",
    "sg:orig_category":"Airconditioning",
    "sg:phone":"+31 78 641 5100",
    "sg:postcode":"3353 GW",
    "sg:province":"Zuid-Holland",
    "wof:name":"Everywair",
    "wof:placetype":"venue"
},
  "geometry": {"coordinates":[4.6867828369,51.8291282654],"type":"Point"}
}