{
  "type": "Feature",
  "properties": {
    "addr:full":"Vosseleane 69 Woudsend Friesland 8551 ML",
    "addr:housenumber":"69",
    "addr:postcode":"8551 ml",
    "addr:street":"Vosseleane",
    "iso:country":"NL",
    "sg:address":"Vosseleane 69",
    "sg:city":"Woudsend",
    "sg:orig_category":"Pleziervaartuigen And Reparatie",
    "sg:phone":"+31 514 592 233",
    "sg:postcode":"8551 ML",
    "sg:province":"Friesland",
    "wof:name":"Breehorn Bv",
    "wof:placetype":"venue"
},
  "geometry": {"coordinates":[5.641174,52.942795],"type":"Point"}
}