{
  "type": "Feature",
  "properties": {
    "addr:full":"Koninginnegr 41 S Gravenhage Zuid-Holland 2514 AD",
    "addr:housenumber":"41;gravenhage",
    "addr:postcode":"2514 ad",
    "addr:street":"Koninginnegr;S",
    "iso:country":"NL",
    "sg:address":"Koninginnegr 41",
    "sg:city":"S Gravenhage",
    "sg:orig_category":"Hypotheken",
    "sg:phone":"+31 70 364 1752",
    "sg:postcode":"2514 AD",
    "sg:province":"Zuid-Holland",
    "wof:name":"Bruggen, Van",
    "wof:placetype":"venue"
},
  "geometry": {"coordinates":[4.30935,52.084148],"type":"Point"}
}