{
  "type": "Feature",
  "properties": {
    "addr:full":"De Kievit 2 Zevenhuizen Zh Zuid-Holland 2761 SR",
    "addr:housenumber":"2",
    "addr:postcode":"2761 sr",
    "addr:street":"De Kievit",
    "iso:country":"NL",
    "sg:address":"De Kievit 2",
    "sg:city":"Zevenhuizen Zh",
    "sg:classifiers":[
        {
            "category":"Food & Beverages",
            "subcategory":"Fruits & Vegetables",
            "type":"Retail Goods"
        }
    ],
    "sg:phone":"+31 180 631 151",
    "sg:postcode":"2761 SR",
    "sg:province":"Zuid-Holland",
    "sg:tags":[
        "groenten"
    ],
    "wof:name":"Vof Van Diemen Van Teylingen",
    "wof:placetype":"venue"
},
  "geometry": {"coordinates":[4.581542,52.007355],"type":"Point"}
}