{
  "type": "Feature",
  "properties": {
    "addr:full":"Heidebloemstraat 57 Groesbeek Gelderland 6561 WP",
    "addr:housenumber":"57",
    "addr:postcode":"6561 wp",
    "addr:street":"Heidebloemstraat;Gelderland",
    "iso:country":"NL",
    "sg:address":"Heidebloemstraat 57",
    "sg:city":"Groesbeek",
    "sg:orig_category":"Meubelzaken, Woning- And Keukeninrichting",
    "sg:phone":"+31 24 397 4897",
    "sg:postcode":"6561 WP",
    "sg:province":"Gelderland",
    "wof:name":"Bos Perfect Wonen",
    "wof:placetype":"venue"
},
  "geometry": {"coordinates":[5.920422,51.785954],"type":"Point"}
}