{
  "type": "Feature",
  "properties": {
    "addr:full":"Jan Deckerstraat 11 Valkenburg Lb Limburg 6301 GX",
    "addr:housenumber":"11",
    "addr:postcode":"lb;6301 gx",
    "addr:street":"Jan Deckerstraat",
    "iso:country":"NL",
    "sg:address":"Jan Deckerstraat 11",
    "sg:city":"Valkenburg Lb",
    "sg:orig_category":"Opticiens",
    "sg:phone":"+31 43 601 0455",
    "sg:postcode":"6301 GX",
    "sg:province":"Limburg",
    "wof:name":"Hub Ramakers De Brillenspecialist",
    "wof:placetype":"venue"
},
  "geometry": {"coordinates":[5.830780983,50.8651428223],"type":"Point"}
}