{
  "type": "Feature",
  "properties": {
    "addr:full":"Katwyksestr 2 Noordwyk Zh Zuid-Holland 2201 RX",
    "addr:housenumber":"2",
    "addr:postcode":"2201 rx",
    "addr:street":"Katwyksestr",
    "iso:country":"NL",
    "sg:address":"Katwyksestr 2",
    "sg:city":"Noordwyk Zh",
    "sg:orig_category":"Metselwerken",
    "sg:phone":"+31 71 361 3341",
    "sg:postcode":"2201 RX",
    "sg:province":"Zuid-Holland",
    "wof:name":"Nieuwenburg",
    "wof:placetype":"venue"
},
  "geometry": {"coordinates":[4.447704,52.234268],"type":"Point"}
}