{
  "type": "Feature",
  "properties": {
    "addr:full":"Hoofdstraat 10 Sassenheim Zuid-Holland 2171 AT",
    "addr:housenumber":"10",
    "addr:postcode":"2171",
    "addr:street":"Hoofdstraat",
    "iso:country":"NL",
    "sg:address":"Hoofdstraat 10",
    "sg:city":"Sassenheim",
    "sg:orig_category":"Architecten",
    "sg:phone":"+31 252 222 303",
    "sg:postcode":"2171 AT",
    "sg:province":"Zuid-Holland",
    "wof:name":"Bureau Volker De Groot",
    "wof:placetype":"venue"
},
  "geometry": {"coordinates":[4.502938,52.215157],"type":"Point"}
}