{
  "type": "Feature",
  "properties": {
    "addr:full":"Marktveldpassage Vught Noord-Brabant 5261 EA",
    "addr:postcode":"5261 ea",
    "addr:street":"Marktveldpassage",
    "iso:country":"NL",
    "sg:address":"Marktveldpassage",
    "sg:city":"Vught",
    "sg:orig_category":"Winkelcentra",
    "sg:phone":"+31 349",
    "sg:postcode":"5261 EA",
    "sg:province":"Noord-Brabant",
    "wof:name":"Vught Binnenstad",
    "wof:placetype":"venue"
},
  "geometry": {"coordinates":[5.300825119,51.658493042],"type":"Point"}
}