{
  "type": "Feature",
  "properties": {
    "addr:full":"Meridiaan 2 De Meern Utrecht 3454 SB",
    "addr:housenumber":"2",
    "addr:postcode":"3454 sb",
    "addr:street":"Meridiaan",
    "iso:country":"NL",
    "sg:address":"Meridiaan 2",
    "sg:city":"De Meern",
    "sg:orig_category":"Verzekeringen - Verzekeringskantoren",
    "sg:phone":"+31 30 666 2099",
    "sg:postcode":"3454 SB",
    "sg:province":"Utrecht",
    "wof:name":"Jager-Hoogendoorn, De",
    "wof:placetype":"venue"
},
  "geometry": {"coordinates":[5.031814,52.084347],"type":"Point"}
}