{
  "type": "Feature",
  "properties": {
    "addr:full":"J Wierln 76 Den Dolder Utrecht 3734 XE",
    "addr:housenumber":"76",
    "addr:postcode":"3734 xe",
    "iso:country":"NL",
    "sg:address":"J Wierln 76",
    "sg:city":"Den Dolder",
    "sg:orig_category":"Fotoreportages",
    "sg:phone":"+31 30 228 5896",
    "sg:postcode":"3734 XE",
    "sg:province":"Utrecht",
    "wof:name":"Rijk Van Tuil",
    "wof:placetype":"venue"
},
  "geometry": {"coordinates":[5.241445,52.139938],"type":"Point"}
}