{
  "type": "Feature",
  "properties": {
    "addr:full":"Scheutenbergweg 3 Kessel Lb Limburg 5995 PE",
    "addr:housenumber":"3",
    "addr:postcode":"lb;5995 pe",
    "addr:street":"Scheutenbergweg",
    "iso:country":"NL",
    "sg:address":"Scheutenbergweg 3",
    "sg:city":"Kessel Lb",
    "sg:orig_category":"Meubelreparatie And -Restauratie",
    "sg:phone":"+31 77 462 1537",
    "sg:postcode":"5995 PE",
    "sg:province":"Limburg",
    "wof:name":"Atelier C. Wijen",
    "wof:placetype":"venue"
},
  "geometry": {"coordinates":[6.045593,51.289162],"type":"Point"}
}