{
  "type": "Feature",
  "properties": {
    "iso:country":"NL",
    "sg:address":"Dorpsstraat 22",
    "sg:city":"Lunteren",
    "sg:orig_category":"Notarissen",
    "sg:phone":"+31 318 483 151",
    "sg:postcode":"6741 AK",
    "sg:province":"Gelderland",
    "wof:name":"Van Putten Van Apeldoorn Notarissen",
    "wof:placetype":"venue"
},
  "geometry": {"coordinates":[5.623853,52.082394],"type":"Point"}
}