{
  "type": "Feature",
  "properties": {
    "addr:full":"Galjoenstraat 5 Tilburg North Brabant 5017 CL",
    "addr:housenumber":"5",
    "addr:postcode":"5017",
    "addr:street":"Galjoenstraat",
    "iso:country":"NL",
    "sg:address":"Galjoenstraat 5",
    "sg:city":"Tilburg",
    "sg:orig_category":"Vaste And Vloeibare Brandstoffen",
    "sg:phone":"+31 13 542 4224",
    "sg:postcode":"5017 CL",
    "sg:province":"North Brabant",
    "wof:name":"Tank- En Inbouwstation Gebr. V Beurden Bv",
    "wof:placetype":"venue"
},
  "geometry": {"coordinates":[5.100001,51.55423],"type":"Point"}
}