{
  "type": "Feature",
  "properties": {
    "addr:full":"Holterhofwg 325 Enschede Overijssel 7534 PT",
    "addr:housenumber":"325",
    "addr:postcode":"7534 pt",
    "iso:country":"NL",
    "sg:address":"Holterhofwg 325",
    "sg:city":"Enschede",
    "sg:classifiers":[
        {
            "category":"Travel",
            "subcategory":"Hotels & Motels",
            "type":"Entertainment"
        }
    ],
    "sg:phone":"+31 53 461 1306",
    "sg:postcode":"7534 PT",
    "sg:province":"Overijssel",
    "wof:name":"H\u00f7Lterhof, De",
    "wof:placetype":"venue"
},
  "geometry": {"coordinates":[6.9411,52.194572],"type":"Point"}
}