{
  "type": "Feature",
  "properties": {
    "iso:country":"NL",
    "sg:address":"Olmendreef 100",
    "sg:city":"Vlaardingen",
    "sg:orig_category":"Scholen Voor Basisonderwijs",
    "sg:phone":"+31 10 249 9280",
    "sg:postcode":"3137 CR",
    "sg:province":"South Holland",
    "wof:name":"Hoeksteen Rk, De",
    "wof:placetype":"venue"
},
  "geometry": {"coordinates":[4.33588,51.937641],"type":"Point"}
}