{
  "type": "Feature",
  "properties": {
    "addr:full":"Fornheselaan 198 Den Dolder Utrecht 3734 GE",
    "addr:housenumber":"198",
    "addr:postcode":"3734",
    "addr:street":"Fornheselaan",
    "iso:country":"NL",
    "sg:address":"Fornheselaan 198",
    "sg:city":"Den Dolder",
    "sg:orig_category":"Metaalafval, Schrootrecycling And Sloperijen",
    "sg:phone":"+31 30 229 2824",
    "sg:postcode":"3734 GE",
    "sg:province":"Utrecht",
    "wof:name":"Hoffland Metaalhandel En Sloopwerken Bv",
    "wof:placetype":"venue"
},
  "geometry": {"coordinates":[5.25017,52.14196],"type":"Point"}
}