{
  "type": "Feature",
  "properties": {
    "iso:country":"NL",
    "sg:address":"Concordiastr 18",
    "sg:city":"Margraten",
    "sg:orig_category":"Voegwerken",
    "sg:phone":"+31 43 458 1415",
    "sg:postcode":"6269 GB",
    "sg:province":"Limburg",
    "wof:name":"Plasier",
    "wof:placetype":"venue"
},
  "geometry": {"coordinates":[5.820991,50.825871],"type":"Point"}
}