{
  "type": "Feature",
  "properties": {
    "addr:full":"T Haantje 2 Bavel Noord-Brabant 4854 MV",
    "addr:housenumber":"2",
    "addr:postcode":"4854 mv",
    "addr:street":"T Haantje",
    "iso:country":"NL",
    "sg:address":"T Haantje 2",
    "sg:city":"Bavel",
    "sg:orig_category":"Adviesbureaus",
    "sg:phone":"+31 161 433 818",
    "sg:postcode":"4854 MV",
    "sg:province":"Noord-Brabant",
    "sg:website":"http://www.jobcoach.nl",
    "wof:name":"Halem Bv, Van",
    "wof:placetype":"venue"
},
  "geometry": {"coordinates":[4.825683,51.570248],"type":"Point"}
}