{
  "type": "Feature",
  "properties": {
    "addr:full":"Planetenstr 71 Hilversum Noord-Holland 1223 GS",
    "addr:housenumber":"71",
    "addr:postcode":"1223 gs",
    "addr:street":"Planetenstr",
    "iso:country":"NL",
    "sg:address":"Planetenstr 71",
    "sg:city":"Hilversum",
    "sg:orig_category":"Postorderbedrijven",
    "sg:phone":"+31 35 683 2502",
    "sg:postcode":"1223 GS",
    "sg:province":"Noord-Holland",
    "wof:name":"Euroshop-Nl",
    "wof:placetype":"venue"
},
  "geometry": {"coordinates":[5.198687,52.230503],"type":"Point"}
}