{
  "type": "Feature",
  "properties": {
    "addr:full":"Smalle Reep 1 Breda Noord-Brabant 4816 JB",
    "addr:housenumber":"1",
    "addr:postcode":"4816 jb",
    "addr:street":"Smalle Reep",
    "iso:country":"NL",
    "sg:address":"Smalle Reep 1",
    "sg:city":"Breda",
    "sg:classifiers":[
        {
            "category":"Retail",
            "subcategory":"Auto Repair",
            "type":"Services"
        }
    ],
    "sg:phone":"+31 76 571 2539",
    "sg:postcode":"4816 JB",
    "sg:province":"Noord-Brabant",
    "sg:tags":[
        "garage"
    ],
    "wof:name":"Nuijten Garage, W",
    "wof:placetype":"venue"
},
  "geometry": {"coordinates":[4.795511,51.596508],"type":"Point"}
}