{
  "type": "Feature",
  "properties": {
    "addr:full":"Kelvinstr 10 Ede Gld Gelderland 6716 BW",
    "addr:housenumber":"10",
    "addr:postcode":"6716 bw",
    "addr:street":"Kelvinstr;Gld Gelderland",
    "iso:country":"NL",
    "sg:address":"Kelvinstr 10",
    "sg:city":"Ede Gld",
    "sg:classifiers":[
        {
            "category":"Retail",
            "subcategory":"Auto Repair",
            "type":"Services"
        }
    ],
    "sg:phone":"+31 318 646 300",
    "sg:postcode":"6716 BW",
    "sg:province":"Gelderland",
    "sg:tags":[
        "garage"
    ],
    "sg:website":"http://www.ottink.nl",
    "wof:name":"Ottink",
    "wof:placetype":"venue"
},
  "geometry": {"coordinates":[5.624415,52.029282],"type":"Point"}
}