{
  "type": "Feature",
  "properties": {
    "addr:full":"Bloemgr 123 Amsterdam North Holland 1016 KK",
    "addr:housenumber":"123",
    "addr:postcode":"1016 kk",
    "iso:country":"NL",
    "sg:address":"Bloemgr 123",
    "sg:city":"Amsterdam",
    "sg:classifiers":[
        {
            "category":"Shopping",
            "subcategory":"Gifts & Souvenirs",
            "type":"Retail Goods"
        }
    ],
    "sg:phone":"+31 20 627 6382",
    "sg:postcode":"1016 KK",
    "sg:province":"North Holland",
    "sg:tags":[
        "wens-",
        "en",
        "prentbriefkaarten"
    ],
    "wof:name":"Co:Pro",
    "wof:placetype":"venue"
},
  "geometry": {"coordinates":[4.8786811829,52.3739776611],"type":"Point"}
}