{
  "type": "Feature",
  "properties": {
    "addr:full":"Vianendreef 93 Prinsenbeek Noord-Brabant 4841 LE",
    "addr:housenumber":"93",
    "addr:postcode":"4841 le",
    "addr:street":"Vianendreef",
    "iso:country":"NL",
    "sg:address":"Vianendreef 93",
    "sg:city":"Prinsenbeek",
    "sg:orig_category":"Bloemen En Planten",
    "sg:phone":"+31 76 541 2254",
    "sg:postcode":"4841 LE",
    "sg:province":"Noord-Brabant",
    "wof:name":"Kooy, N",
    "wof:placetype":"venue"
},
  "geometry": {"coordinates":[4.696614,51.597881],"type":"Point"}
}