{
  "type": "Feature",
  "properties": {
    "addr:full":"Frederik Van De Paltshof 20 Rhenen Utrecht 3911 LB",
    "addr:housenumber":"20",
    "addr:postcode":"3911 lb",
    "addr:street":"Frederik Van De Paltshof",
    "iso:country":"NL",
    "sg:address":"Frederik Van De Paltshof 20",
    "sg:city":"Rhenen",
    "sg:classifiers":[
        {
            "category":"Bakery",
            "type":"Food & Drink"
        }
    ],
    "sg:phone":"+31 317 614 477",
    "sg:postcode":"3911 LB",
    "sg:province":"Utrecht",
    "sg:tags":[
        "brood",
        "banket"
    ],
    "wof:name":"Echte Bakker Stroop",
    "wof:placetype":"venue"
},
  "geometry": {"coordinates":[5.56505,51.957607],"type":"Point"}
}