{
  "type": "Feature",
  "properties": {
    "addr:full":"Morsweg 176 Leiden Zuid-Holland 2332 ES",
    "addr:housenumber":"176",
    "addr:postcode":"2332 es",
    "addr:street":"Morsweg",
    "iso:country":"NL",
    "sg:address":"Morsweg 176",
    "sg:city":"Leiden",
    "sg:orig_category":"Autokeuringen",
    "sg:phone":"+31 71 579 0534",
    "sg:postcode":"2332 ES",
    "sg:province":"Zuid-Holland",
    "wof:name":"Witmer En Odijk",
    "wof:placetype":"venue"
},
  "geometry": {"coordinates":[4.472981,52.159046],"type":"Point"}
}