{
  "type": "Feature",
  "properties": {
    "addr:full":"Industrieweg 25 Nijverdal Overijssel 7442 CV",
    "addr:housenumber":"25",
    "addr:postcode":"7442 cv",
    "addr:street":"Industrieweg",
    "iso:country":"NL",
    "sg:address":"Industrieweg 25",
    "sg:city":"Nijverdal",
    "sg:orig_category":"Kunst And Kunstenaarsbenodigdheden",
    "sg:phone":"+31 548 613 630",
    "sg:postcode":"7442 CV",
    "sg:province":"Overijssel",
    "wof:name":"Proficol Lijsten",
    "wof:placetype":"venue"
},
  "geometry": {"coordinates":[6.498338,52.357307],"type":"Point"}
}