{
  "type": "Feature",
  "properties": {
    "addr:full":"Wynserdyk 10 Easterein Friesland 8734 GG",
    "addr:housenumber":"10",
    "addr:postcode":"8734 gg",
    "addr:street":"Wynserdyk",
    "iso:country":"NL",
    "sg:address":"Wynserdyk 10",
    "sg:city":"Easterein",
    "sg:orig_category":"Schilderwerk",
    "sg:phone":"+31 515 331 313",
    "sg:postcode":"8734 GG",
    "sg:province":"Friesland",
    "wof:name":"Posthuma'S Skildersbedriuw",
    "wof:placetype":"venue"
},
  "geometry": {"coordinates":[5.617057,53.09676],"type":"Point"}
}