{
  "type": "Feature",
  "properties": {
    "addr:full":"Prins Bernhardstraat 40 Berkenwoude Zuid-Holland 2825 BE",
    "addr:housenumber":"40",
    "addr:postcode":"2825",
    "addr:street":"Prins Bernhardstraat",
    "iso:country":"NL",
    "sg:address":"Prins Bernhardstraat 40",
    "sg:city":"Berkenwoude",
    "sg:classifiers":[
        {
            "category":"Education",
            "subcategory":"Preschool",
            "type":"Public Place"
        }
    ],
    "sg:phone":"+31 182 362 540",
    "sg:postcode":"2825 BE",
    "sg:province":"Zuid-Holland",
    "sg:tags":[
        "kleuteronderwijs",
        "basis-"
    ],
    "wof:name":"Openbare Basisschool De Polsstok",
    "wof:placetype":"venue"
},
  "geometry": {"coordinates":[4.70604,51.945171],"type":"Point"}
}