{
  "type": "Feature",
  "properties": {
    "addr:full":"Wickenburghsewg 98-100 T Goy Utrecht 3997 MX",
    "addr:housenumber":"98-100",
    "addr:postcode":"3997 mx",
    "addr:street":"Wickenburghsewg;T Goy",
    "iso:country":"NL",
    "sg:address":"Wickenburghsewg 98-100",
    "sg:city":"T Goy",
    "sg:orig_category":"Koel- En Vrieshuizen",
    "sg:phone":"+31 30 601 1997",
    "sg:postcode":"3997 MX",
    "sg:province":"Utrecht",
    "wof:name":"Maaswaal, N Van",
    "wof:placetype":"venue"
},
  "geometry": {"coordinates":[5.212302,52.005852],"type":"Point"}
}