{
  "type": "Feature",
  "properties": {
    "iso:country":"NL",
    "sg:address":"Westvest 46",
    "sg:city":"Schiedam",
    "sg:orig_category":"Accountants - Administratie- Consulenten En -Kantoren",
    "sg:phone":"+31 10 426 1956",
    "sg:postcode":"3111 BW",
    "sg:province":"South Holland",
    "sg:website":"http://www.box.nl/mraccountants",
    "wof:name":"M & R",
    "wof:placetype":"venue"
},
  "geometry": {"coordinates":[4.397414,51.914082],"type":"Point"}
}