{
  "type": "Feature",
  "properties": {
    "addr:full":"Horsterwg 64B Sevenum Limburg 5975 NB",
    "addr:housenumber":"64b",
    "addr:postcode":"5975 nb",
    "addr:street":"Horsterwg",
    "iso:country":"NL",
    "sg:address":"Horsterwg 64B",
    "sg:city":"Sevenum",
    "sg:orig_category":"Gordijnenateliers",
    "sg:phone":"+31 77 467 2197",
    "sg:postcode":"5975 NB",
    "sg:province":"Limburg",
    "wof:name":"Salet Gordijnenatelier Vof",
    "wof:placetype":"venue"
},
  "geometry": {"coordinates":[6.035179,51.42318],"type":"Point"}
}