{
  "type": "Feature",
  "properties": {
    "addr:full":"Tongerseplein 9 Maastricht Limburg 6214 BH",
    "addr:housenumber":"9",
    "addr:postcode":"6214 bh",
    "addr:street":"Tongerseplein",
    "iso:country":"NL",
    "sg:address":"Tongerseplein 9",
    "sg:city":"Maastricht",
    "sg:orig_category":"Advocaten And Juridische Adviseurs",
    "sg:phone":"+31 43 321 9114",
    "sg:postcode":"6214 BH",
    "sg:province":"Limburg",
    "wof:name":"Advocatenkantoor Mr P W P M Simons",
    "wof:placetype":"venue"
},
  "geometry": {"coordinates":[5.681236,50.844746],"type":"Point"}
}