{
  "type": "Feature",
  "properties": {
    "addr:full":"Batelaar 5 Oosterhout Nb Noord-Brabant 4907 KH",
    "addr:housenumber":"5",
    "addr:postcode":"4907 kh",
    "addr:street":"Batelaar",
    "iso:country":"NL",
    "sg:address":"Batelaar 5",
    "sg:city":"Oosterhout Nb",
    "sg:orig_category":"Boekhouders",
    "sg:phone":"+31 162 438 350",
    "sg:postcode":"4907 KH",
    "sg:province":"Noord-Brabant",
    "wof:name":"Mepol",
    "wof:placetype":"venue"
},
  "geometry": {"coordinates":[4.864716,51.661942],"type":"Point"}
}