{
  "type": "Feature",
  "properties": {
    "addr:full":"Bovendijk 32B Kwintsheul South Holland 2295 RZ",
    "addr:housenumber":"32b",
    "addr:postcode":"2295 rz",
    "addr:street":"Bovendijk",
    "iso:country":"NL",
    "sg:address":"Bovendijk 32B",
    "sg:city":"Kwintsheul",
    "sg:orig_category":"Autokeuringen",
    "sg:phone":"+31 174 290 648",
    "sg:postcode":"2295 RZ",
    "sg:province":"South Holland",
    "wof:name":"M.C. Van Riel",
    "wof:placetype":"venue"
},
  "geometry": {"coordinates":[4.261367,52.014648],"type":"Point"}
}