{
  "type": "Feature",
  "properties": {
    "addr:full":"Westerblokker 23 Blokker Noord-Holland 1695 AA",
    "addr:housenumber":"23",
    "addr:postcode":"1695 aa",
    "addr:street":"Westerblokker",
    "iso:country":"NL",
    "sg:address":"Westerblokker 23",
    "sg:city":"Blokker",
    "sg:orig_category":"Meubelzaken, Woning- And Keukeninrichting",
    "sg:phone":"+31 229 261 959",
    "sg:postcode":"1695 AA",
    "sg:province":"Noord-Holland",
    "wof:name":"Vof Karsten Slaapcomfort",
    "wof:placetype":"venue"
},
  "geometry": {"coordinates":[5.1012358665,52.6642875671],"type":"Point"}
}