{
  "type": "Feature",
  "properties": {
    "addr:full":"Bleekln 94 Leeuwarden Friesland 8921 HD",
    "addr:housenumber":"94",
    "addr:postcode":"8921 hd",
    "addr:street":"Bleekln",
    "iso:country":"NL",
    "sg:address":"Bleekln 94",
    "sg:city":"Leeuwarden",
    "sg:orig_category":"Persbureaus",
    "sg:phone":"+31 6 25471317",
    "sg:postcode":"8921 HD",
    "sg:province":"Friesland",
    "wof:name":"Stegenga, Tessa",
    "wof:placetype":"venue"
},
  "geometry": {"coordinates":[5.81099,53.205589],"type":"Point"}
}