{
  "type": "Feature",
  "properties": {
    "addr:full":"Ds Witteveenln 1A Ermelo Gelderland 3852 BP",
    "addr:housenumber":"1a",
    "addr:postcode":"3852 bp",
    "addr:street":"Ds Witteveenln;Gelderland",
    "iso:country":"NL",
    "sg:address":"Ds Witteveenln 1A",
    "sg:city":"Ermelo",
    "sg:orig_category":"Arbeidsbemiddeling",
    "sg:phone":"+31 341 565 400",
    "sg:postcode":"3852 BP",
    "sg:province":"Gelderland",
    "sg:website":"http://www.intervens.nl",
    "wof:name":"Inclusief Intervens Bv",
    "wof:placetype":"venue"
},
  "geometry": {"coordinates":[5.634019,52.301308],"type":"Point"}
}