{
  "type": "Feature",
  "properties": {
    "iso:country":"NL",
    "sg:address":"Oranje Nassauplein 100",
    "sg:city":"Huizen",
    "sg:orig_category":"Bejaardeninstellingen And Serviceflats",
    "sg:phone":"+31 35 525 6044",
    "sg:postcode":"1272 KV",
    "sg:province":"Noord-Holland",
    "wof:name":"Zorgpalet Locatie Voor Anker",
    "wof:placetype":"venue"
},
  "geometry": {"coordinates":[5.234425,52.292095],"type":"Point"}
}