{
  "type": "Feature",
  "properties": {
    "addr:full":"T V Poortvlietstr 361 Hoogezand Groningen 9602 PJ",
    "addr:housenumber":"361",
    "addr:postcode":"9602 pj",
    "addr:street":"T;Poortvlietstr",
    "iso:country":"NL",
    "sg:address":"T V Poortvlietstr 361",
    "sg:city":"Hoogezand",
    "sg:orig_category":"Zalenverhuur",
    "sg:phone":"+31 598 322 664",
    "sg:postcode":"9602 PJ",
    "sg:province":"Groningen",
    "wof:name":"Reensche Compagnie, De",
    "wof:placetype":"venue"
},
  "geometry": {"coordinates":[6.754265,53.15551],"type":"Point"}
}