{
  "type": "Feature",
  "properties": {
    "addr:full":"Larenseweg 39 Hilversum Noord-Holland 1221 CJ",
    "addr:housenumber":"39",
    "addr:postcode":"1221 cj",
    "addr:street":"Larenseweg",
    "iso:country":"NL",
    "sg:address":"Larenseweg 39",
    "sg:city":"Hilversum",
    "sg:classifiers":[
        {
            "category":"Communications",
            "subcategory":"Television Station",
            "type":"Services"
        }
    ],
    "sg:phone":"+31 35 683 4994",
    "sg:postcode":"1221 CJ",
    "sg:province":"Noord-Holland",
    "sg:tags":[
        "video",
        "audio",
        "verhuur"
    ],
    "wof:name":"Videoland",
    "wof:placetype":"venue"
},
  "geometry": {"coordinates":[5.183837,52.227821],"type":"Point"}
}