{
  "type": "Feature",
  "properties": {
    "iso:country":"NL",
    "sg:address":"Bolbaren 10",
    "sg:city":"Zaandam",
    "sg:orig_category":"Beursorganisaties And Standbouw",
    "sg:phone":"+31 75 617 7071",
    "sg:postcode":"1505 HV",
    "sg:province":"Noord-Holland",
    "wof:name":"Van Der Zee Ontwerpbureau",
    "wof:placetype":"venue"
},
  "geometry": {"coordinates":[4.84765,52.427151],"type":"Point"}
}