{
  "type": "Feature",
  "properties": {
    "addr:full":"Dorpsstraat 98 Vlieland Friesland 8899 AL",
    "addr:housenumber":"98",
    "addr:postcode":"8899 al",
    "addr:street":"Dorpsstraat",
    "iso:country":"NL",
    "sg:address":"Dorpsstraat 98",
    "sg:city":"Vlieland",
    "sg:classifiers":[
        {
            "category":"Bakery",
            "type":"Food & Drink"
        }
    ],
    "sg:phone":"+31 562 451 221",
    "sg:postcode":"8899 AL",
    "sg:province":"Friesland",
    "sg:tags":[
        "brood",
        "banket"
    ],
    "wof:name":"F. Westers",
    "wof:placetype":"venue"
},
  "geometry": {"coordinates":[5.068292,53.295761],"type":"Point"}
}