{
  "type": "Feature",
  "properties": {
    "addr:full":"Postbus 14 Leimuiden Zuid-Holland 2450 AA",
    "addr:housenumber":"14",
    "addr:postcode":"2450 aa",
    "addr:street":"Postbus",
    "iso:country":"NL",
    "sg:address":"Postbus 14",
    "sg:city":"Leimuiden",
    "sg:orig_category":"Verenigingen En Stichtingen",
    "sg:phone":"+31 172 509 135",
    "sg:postcode":"2450 AA",
    "sg:province":"Zuid-Holland",
    "wof:name":"Kickers '69 Vv",
    "wof:placetype":"venue"
},
  "geometry": {"coordinates":[4.67296,52.22448],"type":"Point"}
}