{
  "type": "Feature",
  "properties": {
    "addr:full":"Breedschotsestraat 10 Rijsbergen North Brabant 4891 PL",
    "addr:housenumber":"10",
    "addr:postcode":"4891 pl",
    "addr:street":"Breedschotsestraat",
    "iso:country":"NL",
    "sg:address":"Breedschotsestraat 10",
    "sg:city":"Rijsbergen",
    "sg:orig_category":"Kampeerterreinen",
    "sg:phone":"+31 76 596 1775",
    "sg:postcode":"4891 PL",
    "sg:province":"North Brabant",
    "wof:name":"Camping 'T Oekeltje",
    "wof:placetype":"venue"
},
  "geometry": {"coordinates":[4.705329895,51.4988861084],"type":"Point"}
}