{
  "type": "Feature",
  "properties": {
    "addr:full":"Schilderweg 269 Oudeschild Noord-Holland 1792 CJ",
    "addr:housenumber":"269",
    "addr:postcode":"1792 cj",
    "addr:street":"Schilderweg",
    "iso:country":"NL",
    "sg:address":"Schilderweg 269",
    "sg:city":"Oudeschild",
    "sg:orig_category":"Verhuisdiensten",
    "sg:phone":"+31 222 315 795",
    "sg:postcode":"1792 CJ",
    "sg:province":"Noord-Holland",
    "wof:name":"Nettenreparatie- En -Opslagbedrijf E.M. Kalf",
    "wof:placetype":"venue"
},
  "geometry": {"coordinates":[4.848113,53.042145],"type":"Point"}
}