{
  "type": "Feature",
  "properties": {
    "addr:full":"Klm Ln 9 Hoogerheide Noord-Brabant 4631 JT",
    "addr:housenumber":"9",
    "addr:postcode":"4631 jt",
    "addr:street":"Klm Ln",
    "iso:country":"NL",
    "sg:address":"Klm Ln 9",
    "sg:city":"Hoogerheide",
    "sg:orig_category":"Nagelstudio'S",
    "sg:phone":"+31 164 620 128",
    "sg:postcode":"4631 JT",
    "sg:province":"Noord-Brabant",
    "sg:website":"http://www.nagelstylistebianca.nl",
    "wof:name":"Bianca Vof",
    "wof:placetype":"venue"
},
  "geometry": {"coordinates":[4.327549,51.427002],"type":"Point"}
}