{
  "type": "Feature",
  "properties": {
    "iso:country":"NL",
    "sg:address":"Otterloseweg 64",
    "sg:city":"Wekerom",
    "sg:orig_category":"Bouwmaterialen Gh",
    "sg:phone":"+31 318 591 973",
    "sg:postcode":"6733 AN",
    "sg:province":"Gelderland",
    "wof:name":"Bouwmaterialengroothandel W.A. Duits Bv",
    "wof:placetype":"venue"
},
  "geometry": {"coordinates":[5.733168,52.106373],"type":"Point"}
}