{
  "type": "Feature",
  "properties": {
    "iso:country":"NL",
    "sg:address":"Vijverveld 34",
    "sg:city":"Wouw",
    "sg:orig_category":"Verpakkingen En Verpakkingsmaterialen",
    "sg:phone":"+31 165 304 379",
    "sg:postcode":"4724 EB",
    "sg:province":"Noord-Brabant",
    "wof:name":"Extenso",
    "wof:placetype":"venue"
},
  "geometry": {"coordinates":[4.387532,51.523155],"type":"Point"}
}