{
  "type": "Feature",
  "properties": {
    "addr:full":"W Witsenln 34 Ede Gelderland 6717 JD",
    "addr:housenumber":"34",
    "addr:postcode":"6717 jd",
    "addr:street":"W;Gelderland",
    "iso:country":"NL",
    "sg:address":"W Witsenln 34",
    "sg:city":"Ede",
    "sg:orig_category":"Pianostemmen En -Reparatie",
    "sg:phone":"+31 318 634 901",
    "sg:postcode":"6717 JD",
    "sg:province":"Gelderland",
    "wof:name":"Both, J",
    "wof:placetype":"venue"
},
  "geometry": {"coordinates":[5.666888,52.02705],"type":"Point"}
}