{
  "type": "Feature",
  "properties": {
    "addr:full":"M J G Molierestr 1 Almere Flevoland 1333 KB",
    "addr:housenumber":"1",
    "addr:postcode":"1333 kb",
    "addr:street":"M J G Molierestr;Flevoland",
    "iso:country":"NL",
    "sg:address":"M J G Molierestr 1",
    "sg:city":"Almere",
    "sg:orig_category":"Kinderactiviteiten",
    "sg:phone":"+31 36 532 2731",
    "sg:postcode":"1333 KB",
    "sg:province":"Flevoland",
    "wof:name":"Beestenbende, De",
    "wof:placetype":"venue"
},
  "geometry": {"coordinates":[5.265875,52.396851],"type":"Point"}
}