{
  "type": "Feature",
  "properties": {
    "addr:full":"Essendreef 52 Gouderak Zuid-Holland 2831 XN",
    "addr:housenumber":"52",
    "addr:postcode":"2831 xn",
    "addr:street":"Essendreef",
    "iso:country":"NL",
    "sg:address":"Essendreef 52",
    "sg:city":"Gouderak",
    "sg:orig_category":"Tandartsen",
    "sg:phone":"+31 182 373 709",
    "sg:postcode":"2831 XN",
    "sg:province":"Zuid-Holland",
    "wof:name":"J.H. V.D. Panne",
    "wof:placetype":"venue"
},
  "geometry": {"coordinates":[4.679038,51.983662],"type":"Point"}
}