{
  "type": "Feature",
  "properties": {
    "iso:country":"NL",
    "sg:address":"Hemonystraat 20",
    "sg:city":"Amsterdam",
    "sg:orig_category":"Bedrijfs- And Managementsconsultants",
    "sg:phone":"+31 20 671 9453",
    "sg:postcode":"1074 BP",
    "sg:province":"Noord-Holland",
    "wof:name":"Bremer",
    "wof:placetype":"venue"
},
  "geometry": {"coordinates":[4.902172,52.357224],"type":"Point"}
}