{
  "type": "Feature",
  "properties": {
    "iso:country":"NL",
    "sg:address":"Droogoven 1",
    "sg:city":"Wyk By Duurstede",
    "sg:classifiers":[
        {
            "category":"Sports & Exercise",
            "subcategory":"Stables",
            "type":"Entertainment"
        }
    ],
    "sg:phone":"+31 343 573 343",
    "sg:postcode":"3961 EW",
    "sg:province":"Utrecht",
    "sg:tags":[
        "maneges"
    ],
    "wof:name":"Kleine Ros, Het",
    "wof:placetype":"venue"
},
  "geometry": {"coordinates":[5.33133,51.978409],"type":"Point"}
}