{
  "type": "Feature",
  "properties": {
    "addr:full":"Bosveen 24 Nieuwerkerk Yssel Zuid-Holland 2912 SJ",
    "addr:housenumber":"24",
    "addr:postcode":"2912",
    "addr:street":"Bosveen",
    "iso:country":"NL",
    "sg:address":"Bosveen 24",
    "sg:city":"Nieuwerkerk Yssel",
    "sg:orig_category":"Vertaalbureaus",
    "sg:phone":"+31 6 51590851",
    "sg:postcode":"2912 SJ",
    "sg:province":"Zuid-Holland",
    "wof:name":"Dorcas, J F",
    "wof:placetype":"venue"
},
  "geometry": {"coordinates":[4.613334,51.963879],"type":"Point"}
}