{
  "type": "Feature",
  "properties": {
    "addr:full":"Stationsweg West 87 Woudenberg Utrecht 3931 EL",
    "addr:housenumber":"87",
    "addr:postcode":"3931 el",
    "addr:street":"Stationsweg West",
    "iso:country":"NL",
    "sg:address":"Stationsweg West 87",
    "sg:city":"Woudenberg",
    "sg:classifiers":[
        {
            "category":"Food & Beverages",
            "subcategory":"Fruits & Vegetables",
            "type":"Retail Goods"
        }
    ],
    "sg:phone":"+31 33 286 1308",
    "sg:postcode":"3931 EL",
    "sg:province":"Utrecht",
    "sg:tags":[
        "groenten"
    ],
    "wof:name":"Poultry Farm",
    "wof:placetype":"venue"
},
  "geometry": {"coordinates":[5.427152,52.080627],"type":"Point"}
}