{
  "type": "Feature",
  "properties": {
    "addr:full":"De Langeloop 17 Schagen Noord-Holland 1742 PA",
    "addr:housenumber":"17",
    "addr:postcode":"1742 pa",
    "addr:street":"De Langeloop",
    "iso:country":"NL",
    "sg:address":"De Langeloop 17",
    "sg:city":"Schagen",
    "sg:orig_category":"Autopoetsbedrijven",
    "sg:phone":"+31 6 53714575",
    "sg:postcode":"1742 PA",
    "sg:province":"Noord-Holland",
    "wof:name":"Condor Car Cleaning",
    "wof:placetype":"venue"
},
  "geometry": {"coordinates":[4.781309,52.7948],"type":"Point"}
}