{
  "type": "Feature",
  "properties": {
    "addr:full":"Bodegraafsestrwg 47 Gouda Zuid-Holland 2805 GL",
    "addr:housenumber":"47",
    "addr:postcode":"2805 gl",
    "addr:street":"Bodegraafsestrwg",
    "iso:country":"NL",
    "sg:address":"Bodegraafsestrwg 47",
    "sg:city":"Gouda",
    "sg:orig_category":"Adviesbureaus Bouwkunde",
    "sg:phone":"+31 182 539 044",
    "sg:postcode":"2805 GL",
    "sg:province":"Zuid-Holland",
    "wof:name":"Wageningen, W J Van",
    "wof:placetype":"venue"
},
  "geometry": {"coordinates":[4.719112,52.028214],"type":"Point"}
}