{
  "type": "Feature",
  "properties": {
    "addr:full":"Grt Hertoginneln 1A S Gravenhage Zuid-Holland 2517 EA",
    "addr:housenumber":"1a;gravenhage",
    "addr:postcode":"2517 ea",
    "addr:street":"Hertoginneln;S",
    "iso:country":"NL",
    "sg:address":"Grt Hertoginneln 1A",
    "sg:city":"S Gravenhage",
    "sg:orig_category":"Bedrijfsorganisaties",
    "sg:phone":"+31 70 364 7500",
    "sg:postcode":"2517 EA",
    "sg:province":"Zuid-Holland",
    "sg:website":"http://www.uitvaart.nl/nuvu/index.html",
    "wof:name":"Nuvu",
    "wof:placetype":"venue"
},
  "geometry": {"coordinates":[4.28708,52.08667],"type":"Point"}
}