{
  "type": "Feature",
  "properties": {
    "addr:full":"Graverstr 40 Kerkrade Limburg 6466 KW",
    "addr:housenumber":"40",
    "addr:postcode":"6466 kw",
    "addr:street":"Graverstr",
    "iso:country":"NL",
    "sg:address":"Graverstr 40",
    "sg:city":"Kerkrade",
    "sg:orig_category":"Autoschade- Herstelbedrijven",
    "sg:phone":"+31 45 542 5696",
    "sg:postcode":"6466 KW",
    "sg:province":"Limburg",
    "wof:name":"Atm",
    "wof:placetype":"venue"
},
  "geometry": {"coordinates":[6.023682,50.857754],"type":"Point"}
}