{
  "type": "Feature",
  "properties": {
    "addr:full":"Spuipad 12 Stellendam Zuid-Holland 3251 LS",
    "addr:housenumber":"12",
    "addr:postcode":"3251 ls",
    "addr:street":"Spuipad",
    "iso:country":"NL",
    "sg:address":"Spuipad 12",
    "sg:city":"Stellendam",
    "sg:orig_category":"Beveiliging",
    "sg:phone":"+31 187 491 961",
    "sg:postcode":"3251 LS",
    "sg:province":"Zuid-Holland",
    "wof:name":"Dam, Van",
    "wof:placetype":"venue"
},
  "geometry": {"coordinates":[4.029739,51.806114],"type":"Point"}
}