{
  "type": "Feature",
  "properties": {
    "addr:full":"Molenstr 22 Grypskerke Zeeland 4364 AA",
    "addr:housenumber":"22",
    "addr:postcode":"4364 aa",
    "addr:street":"Molenstr;Zeeland",
    "iso:country":"NL",
    "sg:address":"Molenstr 22",
    "sg:city":"Grypskerke",
    "sg:orig_category":"Schilders",
    "sg:phone":"+31 118 591 658",
    "sg:postcode":"4364 AA",
    "sg:province":"Zeeland",
    "wof:name":"Schiboo Grijpskerke",
    "wof:placetype":"venue"
},
  "geometry": {"coordinates":[3.561873,51.530636],"type":"Point"}
}