{
  "type": "Feature",
  "properties": {
    "iso:country":"NL",
    "sg:address":"Voltairetuin 1",
    "sg:city":"Capelle Ad Yssel",
    "sg:orig_category":"Verzekeringen - Verzekeringskantoren",
    "sg:phone":"+31 10 284 0437",
    "sg:postcode":"2908 XJ",
    "sg:province":"Zuid-Holland",
    "wof:name":"Rimaco",
    "wof:placetype":"venue"
},
  "geometry": {"coordinates":[4.592669,51.955978],"type":"Point"}
}