{
  "type": "Feature",
  "properties": {
    "addr:full":"Frieslandstraat 12 Waalwijk Noord-Brabant 5144 EG",
    "addr:housenumber":"12",
    "addr:postcode":"5144 eg",
    "addr:street":"Frieslandstraat",
    "iso:country":"NL",
    "sg:address":"Frieslandstraat 12",
    "sg:city":"Waalwijk",
    "sg:orig_category":"Handelsbemiddeling Textiel And Lederwaren",
    "sg:phone":"+31 416 561 581",
    "sg:postcode":"5144 EG",
    "sg:province":"Noord-Brabant",
    "wof:name":"Jos Schrauwers Agenturen",
    "wof:placetype":"venue"
},
  "geometry": {"coordinates":[5.076011,51.674896],"type":"Point"}
}