{
  "type": "Feature",
  "properties": {
    "iso:country":"NL",
    "sg:address":"Olterdissenstraat 25",
    "sg:city":"Geleen",
    "sg:orig_category":"Schilderwerk",
    "sg:phone":"+31 46 475 2484",
    "sg:postcode":"6164 JA",
    "sg:province":"Limburg",
    "wof:name":"Will Geurts Schildersbedrijf",
    "wof:placetype":"venue"
},
  "geometry": {"coordinates":[5.836588,50.958862],"type":"Point"}
}