{
  "type": "Feature",
  "properties": {
    "addr:full":"Vlinderveen 217 Spykenisse Zuid-Holland 3205 EB",
    "addr:housenumber":"217",
    "addr:postcode":"3205 eb",
    "addr:street":"Vlinderveen",
    "iso:country":"NL",
    "sg:address":"Vlinderveen 217",
    "sg:city":"Spykenisse",
    "sg:orig_category":"Biljartzalen",
    "sg:phone":"+31 181 641 622",
    "sg:postcode":"3205 EB",
    "sg:province":"Zuid-Holland",
    "wof:name":"Snookercentr Spykenisse",
    "wof:placetype":"venue"
},
  "geometry": {"coordinates":[4.342427,51.833603],"type":"Point"}
}