{
  "type": "Feature",
  "properties": {
    "iso:country":"NL",
    "sg:address":"Walhofstr 101",
    "sg:city":"Enschede",
    "sg:orig_category":"Grafisch Ontwerpers",
    "sg:phone":"+31 53 430 2797",
    "sg:postcode":"7522 BJ",
    "sg:province":"Overijssel",
    "wof:name":"Clason Bv",
    "wof:placetype":"venue"
},
  "geometry": {"coordinates":[6.885106,52.227833],"type":"Point"}
}