{
  "type": "Feature",
  "properties": {
    "addr:full":"Walhofstr 101 Enschede Overijssel 7522 BJ",
    "addr:housenumber":"101",
    "addr:postcode":"7522 bj",
    "iso:country":"NL",
    "sg:address":"Walhofstr 101",
    "sg:city":"Enschede",
    "sg:orig_category":"Grafisch Ontwerpers",
    "sg:phone":"+31 53 430 2797",
    "sg:postcode":"7522 BJ",
    "sg:province":"Overijssel",
    "wof:name":"Clason Bv",
    "wof:placetype":"venue"
},
  "geometry": {"coordinates":[6.885106,52.227833],"type":"Point"}
}