{
  "type": "Feature",
  "properties": {
    "addr:full":"Hg Markt 4 Scherpenisse Zeeland 4694 CG",
    "addr:housenumber":"4",
    "addr:postcode":"4694 cg",
    "addr:street":"Markt",
    "iso:country":"NL",
    "sg:address":"Hg Markt 4",
    "sg:city":"Scherpenisse",
    "sg:orig_category":"Kappers",
    "sg:phone":"+31 166 662 772",
    "sg:postcode":"4694 CG",
    "sg:province":"Zeeland",
    "wof:name":"Reest, Van Der",
    "wof:placetype":"venue"
},
  "geometry": {"coordinates":[4.105828,51.546928],"type":"Point"}
}