{
  "type": "Feature",
  "properties": {
    "iso:country":"NL",
    "sg:address":"Herenstr 8",
    "sg:city":"Raalte",
    "sg:orig_category":"Postkantoren",
    "sg:phone":"+31 572 352 101",
    "sg:postcode":"8102 CP",
    "sg:province":"Overijssel",
    "sg:website":"http://www.postkantoor.nl",
    "wof:name":"Postkantoor",
    "wof:placetype":"venue"
},
  "geometry": {"coordinates":[6.275134,52.386505],"type":"Point"}
}