{
  "type": "Feature",
  "properties": {
    "addr:full":"Gouw 1-3 Hoorn Nh Noord-Holland 1621 HA",
    "addr:housenumber":"1-3",
    "addr:postcode":"1621 ha",
    "addr:street":"Gouw",
    "iso:country":"NL",
    "sg:address":"Gouw 1-3",
    "sg:city":"Hoorn Nh",
    "sg:orig_category":"Meubelen",
    "sg:phone":"+31 229 214 006",
    "sg:postcode":"1621 HA",
    "sg:province":"Noord-Holland",
    "wof:name":"Kieft Interieur",
    "wof:placetype":"venue"
},
  "geometry": {"coordinates":[5.059311,52.642452],"type":"Point"}
}