{
  "type": "Feature",
  "properties": {
    "iso:country":"NL",
    "sg:address":"Gerrit Raapstraat 39",
    "sg:city":"Appingedam",
    "sg:orig_category":"Diverse Dierenfokkers",
    "sg:phone":"+31 596 625 238",
    "sg:postcode":"9902 EG",
    "sg:province":"Groningen",
    "wof:name":"J D Bogema",
    "wof:placetype":"venue"
},
  "geometry": {"coordinates":[6.865926,53.316925],"type":"Point"}
}