{
  "type": "Feature",
  "properties": {
    "iso:country":"NL",
    "sg:address":"Heerderwg 8",
    "sg:city":"Epe",
    "sg:orig_category":"Verzekeringen - Verzekeringskantoren",
    "sg:phone":"+31 578 621 990",
    "sg:postcode":"8161 BM",
    "sg:province":"Gelderland",
    "wof:name":"Lange, Yvonne De",
    "wof:placetype":"venue"
},
  "geometry": {"coordinates":[5.989177,52.354111],"type":"Point"}
}