{
  "type": "Feature",
  "properties": {
    "addr:full":"Chopinln 36 Hazerswoude Ryndyk Zuid-Holland 2394 GL",
    "addr:housenumber":"36;ryndyk",
    "addr:postcode":"2394 gl",
    "addr:street":"Chopinln",
    "iso:country":"NL",
    "sg:address":"Chopinln 36",
    "sg:city":"Hazerswoude Ryndyk",
    "sg:orig_category":"Loodgieters",
    "sg:phone":"+31 71 341 4393",
    "sg:postcode":"2394 GL",
    "sg:province":"Zuid-Holland",
    "wof:name":"Kampen, H Van",
    "wof:placetype":"venue"
},
  "geometry": {"coordinates":[4.593722,52.130527],"type":"Point"}
}