{
  "type": "Feature",
  "properties": {
    "addr:full":"Westhavenweg 61 Amsterdam North Holland 1042 AL",
    "addr:housenumber":"61",
    "addr:postcode":"1042 al",
    "addr:street":"Westhavenweg",
    "iso:country":"NL",
    "sg:address":"Westhavenweg 61",
    "sg:city":"Amsterdam",
    "sg:classifiers":[
        {
            "category":"Parking",
            "subcategory":"Lot",
            "type":"Transportation"
        }
    ],
    "sg:phone":"+31 20 448 1558",
    "sg:postcode":"1042 AL",
    "sg:province":"North Holland",
    "sg:tags":[
        "fab",
        "metalen",
        "tank"
    ],
    "wof:name":"Levels Puinbroek Bv",
    "wof:placetype":"venue"
},
  "geometry": {"coordinates":[4.828182,52.408749],"type":"Point"}
}