{
  "type": "Feature",
  "properties": {
    "iso:country":"NL",
    "sg:address":"Baandert 16",
    "sg:city":"Sittard",
    "sg:orig_category":"Boekenuitgeverijen",
    "sg:phone":"+31 46 452 2931",
    "sg:postcode":"6136 ER",
    "sg:province":"Limburg",
    "wof:name":"Uitgeversmaatschappij De Trompetter Bv",
    "wof:placetype":"venue"
},
  "geometry": {"coordinates":[5.872048,51.001869],"type":"Point"}
}