{
  "type": "Feature",
  "properties": {
    "addr:full":"Waagpassage 138 Lelystad NL. 8232 DW",
    "addr:housenumber":"138",
    "addr:postcode":"8232 dw",
    "addr:street":"Waagpassage;Nl.",
    "iso:country":"NL",
    "sg:address":"Waagpassage 138",
    "sg:city":"Lelystad",
    "sg:orig_category":"Kappers",
    "sg:phone":"+31 320 242 027",
    "sg:postcode":"8232 DW",
    "sg:province":"NL.",
    "wof:name":"Leo",
    "wof:placetype":"venue"
},
  "geometry": {"coordinates":[5.475117,52.511307],"type":"Point"}
}