{
  "type": "Feature",
  "properties": {
    "addr:full":"V Houweningepk 1 Medemblik Noord-Holland 1671 CK",
    "addr:housenumber":"1",
    "addr:postcode":"1671 ck",
    "addr:street":"Houweningepk",
    "iso:country":"NL",
    "sg:address":"V Houweningepk 1",
    "sg:city":"Medemblik",
    "sg:orig_category":"Wereldwinkels",
    "sg:phone":"+31 227 548 086",
    "sg:postcode":"1671 CK",
    "sg:province":"Noord-Holland",
    "wof:name":"Wereldwinkel",
    "wof:placetype":"venue"
},
  "geometry": {"coordinates":[5.1067152023,52.7719421387],"type":"Point"}
}