{
  "type": "Feature",
  "properties": {
    "addr:full":"Kerkln 92 Nieuwerkerk Yssel Zuid-Holland 2912 CL",
    "addr:housenumber":"92",
    "addr:postcode":"2912",
    "addr:street":"Kerkln",
    "iso:country":"NL",
    "sg:address":"Kerkln 92",
    "sg:city":"Nieuwerkerk Yssel",
    "sg:orig_category":"Accountants - Administratie- Consulenten En -Kantoren",
    "sg:phone":"+31 180 317 500",
    "sg:postcode":"2912 CL",
    "sg:province":"Zuid-Holland",
    "wof:name":"Weelde Bv, Van",
    "wof:placetype":"venue"
},
  "geometry": {"coordinates":[4.6028,51.963692],"type":"Point"}
}