{
  "type": "Feature",
  "properties": {
    "addr:full":"Aleidastraat 62 Schiedam Zuid-Holland 3117 DK",
    "addr:housenumber":"62",
    "addr:postcode":"3117 dk",
    "addr:street":"Aleidastraat",
    "iso:country":"NL",
    "sg:address":"Aleidastraat 62",
    "sg:city":"Schiedam",
    "sg:orig_category":"Meubelreparatie And -Restauratie",
    "sg:phone":"+31 10 426 8581",
    "sg:postcode":"3117 DK",
    "sg:province":"Zuid-Holland",
    "wof:name":"Meubelstofferderij Fa J.H. Ruygrok",
    "wof:placetype":"venue"
},
  "geometry": {"coordinates":[4.389113,51.913376],"type":"Point"}
}