{
  "type": "Feature",
  "properties": {
    "addr:full":"Kamelenspoor 147 Maarssen Utrecht 3605 EH",
    "addr:housenumber":"147",
    "addr:postcode":"3605 eh",
    "addr:street":"Kamelenspoor",
    "iso:country":"NL",
    "sg:address":"Kamelenspoor 147",
    "sg:city":"Maarssen",
    "sg:orig_category":"Glazenwasserijen",
    "sg:phone":"+31 346 574 581",
    "sg:postcode":"3605 EH",
    "sg:province":"Utrecht",
    "wof:name":"Bosch",
    "wof:placetype":"venue"
},
  "geometry": {"coordinates":[5.024871,52.138371],"type":"Point"}
}