{
  "type": "Feature",
  "properties": {
    "iso:country":"NL",
    "sg:address":"Hulswitwg 24",
    "sg:city":"Haarlem",
    "sg:orig_category":"Grafische Bedrijven",
    "sg:phone":"+31 23 553 3066",
    "sg:postcode":"2031 BG",
    "sg:province":"North Holland",
    "sg:website":"http://www.in-touch-int.nl",
    "wof:name":"In Touch Int Bv",
    "wof:placetype":"venue"
},
  "geometry": {"coordinates":[4.667823,52.38829],"type":"Point"}
}