{
  "type": "Feature",
  "properties": {
    "addr:full":"Overmeerseweg 3 Nederhorst Den Berg British Columbia 1394 BC",
    "addr:housenumber":"3",
    "addr:postcode":"1394 bc",
    "addr:street":"Overmeerseweg",
    "iso:country":"NL",
    "sg:address":"Overmeerseweg 3",
    "sg:city":"Nederhorst Den Berg",
    "sg:classifiers":[
        {
            "category":"Food & Beverages",
            "subcategory":"Fruits & Vegetables",
            "type":"Retail Goods"
        }
    ],
    "sg:phone":"+31 294 252 694",
    "sg:postcode":"1394 BC",
    "sg:province":"British Columbia",
    "sg:tags":[
        "groenten"
    ],
    "wof:name":"D. Van Der Panne",
    "wof:placetype":"venue"
},
  "geometry": {"coordinates":[-126.555511,54.485668],"type":"Point"}
}