{
  "type": "Feature",
  "properties": {
    "addr:full":"Vlierln 214 Oosterhout Nb Noord-Brabant 4907 AX",
    "addr:housenumber":"214",
    "addr:postcode":"4907 ax",
    "iso:country":"NL",
    "sg:address":"Vlierln 214",
    "sg:city":"Oosterhout Nb",
    "sg:orig_category":"Binnenhuisarchitectuur",
    "sg:phone":"+31 6 10344191",
    "sg:postcode":"4907 AX",
    "sg:province":"Noord-Brabant",
    "wof:name":"Binnen",
    "wof:placetype":"venue"
},
  "geometry": {"coordinates":[4.85625,51.643051],"type":"Point"}
}