{
  "type": "Feature",
  "properties": {
    "addr:full":"Otterlaan 6 Delft Zuid-Holland 2623 CX",
    "addr:housenumber":"6",
    "addr:postcode":"2623 cx",
    "addr:street":"Otterlaan",
    "iso:country":"NL",
    "sg:address":"Otterlaan 6",
    "sg:city":"Delft",
    "sg:orig_category":"Watersport-, Sport- And Kampeerbenodigdheden Verhuur",
    "sg:phone":"+31 15 257 1504",
    "sg:postcode":"2623 CX",
    "sg:province":"Zuid-Holland",
    "wof:name":"Kano Delft Verkerk Buitensport",
    "wof:placetype":"venue"
},
  "geometry": {"coordinates":[4.362393856,51.9868736267],"type":"Point"}
}