{
  "type": "Feature",
  "properties": {
    "addr:full":"Elviraland 5C S Gravenhage Zuid-Holland 2591 GE",
    "addr:housenumber":"5c s",
    "addr:postcode":"2591",
    "addr:street":"Elviraland",
    "iso:country":"NL",
    "sg:address":"Elviraland 5C",
    "sg:city":"S Gravenhage",
    "sg:orig_category":"Telecommunicatie - Apparatuur",
    "sg:phone":"+31 70 350 4500",
    "sg:postcode":"2591 GE",
    "sg:province":"Zuid-Holland",
    "sg:website":"http://www.bumicom.nl",
    "wof:name":"Bumicom Bv",
    "wof:placetype":"venue"
},
  "geometry": {"coordinates":[4.3639,52.09351],"type":"Point"}
}