{
  "type": "Feature",
  "properties": {
    "addr:full":"Computerwg 12C Amersfoort Utrecht 3821 AB",
    "addr:housenumber":"12c",
    "addr:postcode":"3821 ab",
    "addr:street":"Computerwg",
    "iso:country":"NL",
    "sg:address":"Computerwg 12C",
    "sg:city":"Amersfoort",
    "sg:orig_category":"Vertaalbureaus",
    "sg:phone":"+31 33 453 5535",
    "sg:postcode":"3821 AB",
    "sg:province":"Utrecht",
    "sg:website":"http://www.olyslager.nl",
    "wof:name":"Olyslager Organisation Bv",
    "wof:placetype":"venue"
},
  "geometry": {"coordinates":[5.409016,52.175255],"type":"Point"}
}