{
  "type": "Feature",
  "properties": {
    "iso:country":"NL",
    "sg:address":"Rdr V Rappardln 3",
    "sg:city":"Doorwerth",
    "sg:orig_category":"Adviesbureaus Land- En Tuinbouw",
    "sg:phone":"+31 317 350 523",
    "sg:postcode":"6865 BV",
    "sg:province":"Gelderland",
    "wof:name":"Asg Holl Bv",
    "wof:placetype":"venue"
},
  "geometry": {"coordinates":[5.811587,51.974442],"type":"Point"}
}