{
  "type": "Feature",
  "properties": {
    "addr:full":"Leghornstr 21 Amsterdam Zuidoost Noord-Holland 1109 BW",
    "addr:housenumber":"21",
    "addr:postcode":"zuidoost;1109 bw",
    "addr:street":"Leghornstr",
    "iso:country":"NL",
    "sg:address":"Leghornstr 21",
    "sg:city":"Amsterdam Zuidoost",
    "sg:orig_category":"Adviesbureaus Bouwkunde",
    "sg:phone":"+31 294 416 699",
    "sg:postcode":"1109 BW",
    "sg:province":"Noord-Holland",
    "wof:name":"Estro",
    "wof:placetype":"venue"
},
  "geometry": {"coordinates":[5.015273,52.30582],"type":"Point"}
}