{
  "type": "Feature",
  "properties": {
    "addr:full":"Vlietlaan 76 Bussum North Holland 1404 CE",
    "addr:housenumber":"76",
    "addr:postcode":"1404 ce",
    "addr:street":"Vlietlaan",
    "iso:country":"NL",
    "sg:address":"Vlietlaan 76",
    "sg:city":"Bussum",
    "sg:orig_category":"Kunst And Kunstenaarsbenodigdheden",
    "sg:phone":"+31 35 693 3069",
    "sg:postcode":"1404 CE",
    "sg:province":"North Holland",
    "wof:name":"Kunsthandel De Lijstenmakerij Theo Petri",
    "wof:placetype":"venue"
},
  "geometry": {"coordinates":[5.158375,52.278942],"type":"Point"}
}