{
  "type": "Feature",
  "properties": {
    "addr:full":"Kanaalweg 6 Asten Noord-Brabant 5721 MZ",
    "addr:housenumber":"6",
    "addr:postcode":"5721 mz",
    "addr:street":"Kanaalweg",
    "iso:country":"NL",
    "sg:address":"Kanaalweg 6",
    "sg:city":"Asten",
    "sg:orig_category":"Huisdierenvoer Fab",
    "sg:phone":"+31 493 693 784",
    "sg:postcode":"5721 MZ",
    "sg:province":"Noord-Brabant",
    "wof:name":"Brandenburch Bv",
    "wof:placetype":"venue"
},
  "geometry": {"coordinates":[5.725728,51.397118],"type":"Point"}
}