{
  "type": "Feature",
  "properties": {
    "addr:full":"Gelkingestr 30 Groningen Groningen 9711 ND",
    "addr:housenumber":"30",
    "addr:postcode":"9711 nd",
    "addr:street":"Gelkingestr",
    "iso:country":"NL",
    "sg:address":"Gelkingestr 30",
    "sg:city":"Groningen",
    "sg:orig_category":"Wereldwinkels",
    "sg:phone":"+31 50 313 2095",
    "sg:postcode":"9711 ND",
    "sg:province":"Groningen",
    "wof:name":"Wereldwinkel",
    "wof:placetype":"venue"
},
  "geometry": {"coordinates":[6.568582058,53.2174491882],"type":"Point"}
}