{
  "type": "Feature",
  "properties": {
    "addr:full":"Langweide 4 Beek Lb Limburg 6191 ES",
    "addr:housenumber":"4",
    "addr:postcode":"lb;6191 es",
    "addr:street":"Langweide",
    "iso:country":"NL",
    "sg:address":"Langweide 4",
    "sg:city":"Beek Lb",
    "sg:orig_category":"Artsen And Specialisten",
    "sg:phone":"+31 46 437 8341",
    "sg:postcode":"6191 ES",
    "sg:province":"Limburg",
    "wof:name":"H.J.H. Smeets",
    "wof:placetype":"venue"
},
  "geometry": {"coordinates":[-93.129936,36.705662],"type":"Point"}
}