{
  "type": "Feature",
  "properties": {
    "addr:full":"F A Molynln 75 Nunspeet Gelderland 8071 AC",
    "addr:housenumber":"75",
    "addr:postcode":"8071 ac",
    "addr:street":"F;Molynln;Gelderland",
    "iso:country":"NL",
    "sg:address":"F A Molynln 75",
    "sg:city":"Nunspeet",
    "sg:orig_category":"Adviesbureaus Bedrijfsorganisatie",
    "sg:phone":"+31 341 250 888",
    "sg:postcode":"8071 AC",
    "sg:province":"Gelderland",
    "sg:website":"http://www.vdk.org",
    "wof:name":"Vdk",
    "wof:placetype":"venue"
},
  "geometry": {"coordinates":[5.772205,52.374981],"type":"Point"}
}