{
  "type": "Feature",
  "properties": {
    "addr:full":"Rembrandtkd 13 Wormerveer North Holland 1521 SM",
    "addr:housenumber":"13",
    "addr:postcode":"1521 sm",
    "addr:street":"Rembrandtkd",
    "iso:country":"NL",
    "sg:address":"Rembrandtkd 13",
    "sg:city":"Wormerveer",
    "sg:orig_category":"Honden- En Kattentrimsalons",
    "sg:phone":"+31 75 640 2700",
    "sg:postcode":"1521 SM",
    "sg:province":"North Holland",
    "wof:name":"Buys, E",
    "wof:placetype":"venue"
},
  "geometry": {"coordinates":[4.8054280281,52.4816246033],"type":"Point"}
}