{
  "type": "Feature",
  "properties": {
    "addr:full":"Acaciaweg 4 Venlo Limburg 5915 GD",
    "addr:housenumber":"4",
    "addr:postcode":"5915 gd",
    "addr:street":"Acaciaweg",
    "iso:country":"NL",
    "sg:address":"Acaciaweg 4",
    "sg:city":"Venlo",
    "sg:orig_category":"Loodgieterswerk, Verwarming And Sanitaire Installaties",
    "sg:phone":"+31 77 354 4058",
    "sg:postcode":"5915 GD",
    "sg:province":"Limburg",
    "wof:name":"Gasservice Venlo",
    "wof:placetype":"venue"
},
  "geometry": {"coordinates":[6.189177,51.355347],"type":"Point"}
}