{
  "type": "Feature",
  "properties": {
    "addr:full":"Pr Constantynln 4 T Harde Gelderland 8084 AG",
    "addr:housenumber":"4",
    "addr:postcode":"8084",
    "addr:street":"T Harde Gelderland",
    "iso:country":"NL",
    "sg:address":"Pr Constantynln 4",
    "sg:city":"T Harde",
    "sg:orig_category":"Adviesbureaus Bedrijfsorganisatie",
    "sg:phone":"+31 525 654 880",
    "sg:postcode":"8084 AG",
    "sg:province":"Gelderland",
    "wof:name":"Brakel, Dr Ir A",
    "wof:placetype":"venue"
},
  "geometry": {"coordinates":[5.881998,52.409084],"type":"Point"}
}