{
  "type": "Feature",
  "properties": {
    "addr:full":"Berschotten 6 Bladel Noord-Brabant 5531 NW",
    "addr:housenumber":"6",
    "addr:postcode":"5531 nw",
    "addr:street":"Berschotten",
    "iso:country":"NL",
    "sg:address":"Berschotten 6",
    "sg:city":"Bladel",
    "sg:orig_category":"Elektrotechnische Installatiebureaus",
    "sg:phone":"+31 497 360 245",
    "sg:postcode":"5531 NW",
    "sg:province":"Noord-Brabant",
    "wof:name":"Ad Soontiens, Elektro Installaties",
    "wof:placetype":"venue"
},
  "geometry": {"coordinates":[5.207565,51.359074],"type":"Point"}
}