{
  "type": "Feature",
  "properties": {
    "addr:full":"Bruggeln 6 Eindhoven Noord-Brabant 5628 RH",
    "addr:housenumber":"6",
    "addr:postcode":"5628 rh",
    "addr:street":"Bruggeln",
    "iso:country":"NL",
    "sg:address":"Bruggeln 6",
    "sg:city":"Eindhoven",
    "sg:orig_category":"Verenigingen En Stichtingen",
    "sg:phone":"+31 40 248 4696",
    "sg:postcode":"5628 RH",
    "sg:province":"Noord-Brabant",
    "wof:name":"Master In Quartz Ver",
    "wof:placetype":"venue"
},
  "geometry": {"coordinates":[5.47191,51.48011],"type":"Point"}
}