{
  "type": "Feature",
  "properties": {
    "addr:full":"Weissenbruchstraat 6 Amsterdam Noord-Holland 1058 KM",
    "addr:housenumber":"6",
    "addr:postcode":"1058 km",
    "addr:street":"Weissenbruchstraat",
    "iso:country":"NL",
    "sg:address":"Weissenbruchstraat 6",
    "sg:city":"Amsterdam",
    "sg:orig_category":"Public Relationbureaus",
    "sg:phone":"+31 20 615 3953",
    "sg:postcode":"1058 KM",
    "sg:province":"Noord-Holland",
    "wof:name":"Verheij Fair Promotions",
    "wof:placetype":"venue"
},
  "geometry": {"coordinates":[4.851893,52.353504],"type":"Point"}
}