{
  "type": "Feature",
  "properties": {
    "addr:full":"Heuvelstraat 74 Tilburg Noord-Brabant 5038 AG",
    "addr:housenumber":"74",
    "addr:postcode":"5038",
    "addr:street":"Heuvelstraat",
    "iso:country":"NL",
    "sg:address":"Heuvelstraat 74",
    "sg:city":"Tilburg",
    "sg:orig_category":"Juweliers",
    "sg:phone":"+31 13 544 1047",
    "sg:postcode":"5038 AG",
    "sg:province":"Noord-Brabant",
    "wof:name":"Siebel Juweliers Bv",
    "wof:placetype":"venue"
},
  "geometry": {"coordinates":[5.08615,51.55571],"type":"Point"}
}