{
  "type": "Feature",
  "properties": {
    "addr:full":"Tilwg 1 Roodeschool Groningen 9983 SP",
    "addr:housenumber":"1",
    "addr:postcode":"9983 sp",
    "addr:street":"Tilwg",
    "iso:country":"NL",
    "sg:address":"Tilwg 1",
    "sg:city":"Roodeschool",
    "sg:orig_category":"Land- En Tuinbouw - Mechanisatie",
    "sg:phone":"+31 595 412 810",
    "sg:postcode":"9983 SP",
    "sg:province":"Groningen",
    "wof:name":"Oosterhof Bv",
    "wof:placetype":"venue"
},
  "geometry": {"coordinates":[6.763337,53.420235],"type":"Point"}
}