{
  "type": "Feature",
  "properties": {
    "addr:full":"Oude Apeld Wg 11 Vaassen Gelderland 8171 LV",
    "addr:housenumber":"11",
    "addr:postcode":"8171",
    "addr:street":"Oude;Wg;Gelderland",
    "iso:country":"NL",
    "sg:address":"Oude Apeld Wg 11",
    "sg:city":"Vaassen",
    "sg:orig_category":"Kantoorbenodigdheden",
    "sg:phone":"+31 578 576 728",
    "sg:postcode":"8171 LV",
    "sg:province":"Gelderland",
    "sg:website":"http://www.offi.nl",
    "wof:name":"Officiency",
    "wof:placetype":"venue"
},
  "geometry": {"coordinates":[5.9685730934,52.283706665],"type":"Point"}
}