{
  "type": "Feature",
  "properties": {
    "addr:full":"Zuidkd 88 Drachten Friesland 9203 CP",
    "addr:housenumber":"88",
    "addr:postcode":"9203 cp",
    "addr:street":"Zuidkd",
    "iso:country":"NL",
    "sg:address":"Zuidkd 88",
    "sg:city":"Drachten",
    "sg:orig_category":"Makelaars En Adviseurs Onroerende Goederen",
    "sg:phone":"+31 512 538 857",
    "sg:postcode":"9203 CP",
    "sg:province":"Friesland",
    "sg:website":"http://www.jrs-vbomakelaars.nl",
    "wof:name":"Jrs",
    "wof:placetype":"venue"
},
  "geometry": {"coordinates":[6.098565,53.102871],"type":"Point"}
}