{
  "type": "Feature",
  "properties": {
    "addr:full":"Dautzenbergstr 17 Heerlen Limburg 6411 LA",
    "addr:housenumber":"17",
    "addr:postcode":"6411 la",
    "addr:street":"Dautzenbergstr",
    "iso:country":"NL",
    "sg:address":"Dautzenbergstr 17",
    "sg:city":"Heerlen",
    "sg:orig_category":"Bloemen En Planten",
    "sg:phone":"+31 45 562 4351",
    "sg:postcode":"6411 LA",
    "sg:province":"Limburg",
    "wof:name":"Fiore Bv, Il",
    "wof:placetype":"venue"
},
  "geometry": {"coordinates":[5.978823,50.888729],"type":"Point"}
}