{
  "type": "Feature",
  "properties": {
    "addr:full":"Kromstr 9C Veldhoven North Brabant 5504 BA",
    "addr:housenumber":"9c",
    "addr:postcode":"5504 ba",
    "addr:street":"Kromstr",
    "iso:country":"NL",
    "sg:address":"Kromstr 9C",
    "sg:city":"Veldhoven",
    "sg:orig_category":"Kunsthandel",
    "sg:phone":"+31 40 254 0561",
    "sg:postcode":"5504 BA",
    "sg:province":"North Brabant",
    "sg:website":"http://www.kunstenkader.nl",
    "wof:name":"Hans Persoon, Kunst En Kader",
    "wof:placetype":"venue"
},
  "geometry": {"coordinates":[5.395604,51.40361],"type":"Point"}
}