{
  "type": "Feature",
  "properties": {
    "addr:full":"Hoofdwg 204 Taarlo Drenthe 9485 TA",
    "addr:housenumber":"204",
    "addr:postcode":"9485 ta",
    "iso:country":"NL",
    "sg:address":"Hoofdwg 204",
    "sg:city":"Taarlo",
    "sg:orig_category":"Administratie- En Boekhoudkantoren",
    "sg:phone":"+31 592 231 279",
    "sg:postcode":"9485 TA",
    "sg:province":"Drenthe",
    "wof:name":"Brinkman, J",
    "wof:placetype":"venue"
},
  "geometry": {"coordinates":[6.626301,53.037762],"type":"Point"}
}