{
  "type": "Feature",
  "properties": {
    "iso:country":"NL",
    "sg:address":"Rijksstraatweg 195",
    "sg:city":"Beek Ubbergen",
    "sg:orig_category":"Glaszetten",
    "sg:phone":"+31 24 684 3610",
    "sg:postcode":"6573 CR",
    "sg:province":"Gelderland",
    "wof:name":"A.P. Bos En Zonen B.V.",
    "wof:placetype":"venue"
},
  "geometry": {"coordinates":[5.926535,51.828255],"type":"Point"}
}