{
  "type": "Feature",
  "properties": {
    "addr:full":"Planciusstr 5D Amsterdam Noord-Holland 1013 MD",
    "addr:housenumber":"5d",
    "addr:postcode":"1013",
    "iso:country":"NL",
    "sg:address":"Planciusstr 5D",
    "sg:city":"Amsterdam",
    "sg:orig_category":"Artiesten/Gezelschappen",
    "sg:phone":"+31 20 684 5387",
    "sg:postcode":"1013 MD",
    "sg:province":"Noord-Holland",
    "sg:website":"http://www.tiramisu-acts.nl",
    "wof:name":"Tiramisu Bv",
    "wof:placetype":"venue"
},
  "geometry": {"coordinates":[4.885575,52.387691],"type":"Point"}
}