{
  "type": "Feature",
  "properties": {
    "addr:full":"Mozartstraat 45 Heemskerk Noord-Holland 1962 AA",
    "addr:housenumber":"45",
    "addr:postcode":"1962 aa",
    "addr:street":"Mozartstraat",
    "iso:country":"NL",
    "sg:address":"Mozartstraat 45",
    "sg:city":"Heemskerk",
    "sg:orig_category":"Geluidsopnamen",
    "sg:phone":"+31 251 232 093",
    "sg:postcode":"1962 AA",
    "sg:province":"Noord-Holland",
    "wof:name":"Clarison",
    "wof:placetype":"venue"
},
  "geometry": {"coordinates":[4.671153,52.516682],"type":"Point"}
}