{
  "type": "Feature",
  "properties": {
    "iso:country":"NL",
    "sg:address":"Oude Doetinchemseweg 1",
    "sg:city":"Zeddam",
    "sg:orig_category":"Wegen And Sportterreinen",
    "sg:phone":"+31 314 651 337",
    "sg:postcode":"7038 BD",
    "sg:province":"Gelderland",
    "wof:name":"Vof Aannemersbedrijf Arendsen Zeddam",
    "wof:placetype":"venue"
},
  "geometry": {"coordinates":[6.2636008263,51.8958015442],"type":"Point"}
}