{
  "type": "Feature",
  "properties": {
    "addr:full":"Vryheidsln 99 Amsterdam Noord-Holland 1079 KJ",
    "addr:housenumber":"99",
    "addr:postcode":"1079 kj",
    "addr:street":"Vryheidsln",
    "iso:country":"NL",
    "sg:address":"Vryheidsln 99",
    "sg:city":"Amsterdam",
    "sg:orig_category":"Modelbouw",
    "sg:phone":"+31 20 642 3386",
    "sg:postcode":"1079 KJ",
    "sg:province":"Noord-Holland",
    "wof:name":"Formule 1 Shop Raceworld",
    "wof:placetype":"venue"
},
  "geometry": {"coordinates":[4.89319,52.373119],"type":"Point"}
}