{
  "type": "Feature",
  "properties": {
    "addr:full":"J De Wittln 30 Arnhem Gelderland 6828 WG",
    "addr:housenumber":"30",
    "addr:postcode":"6828 wg",
    "addr:street":"J De Wittln",
    "iso:country":"NL",
    "sg:address":"J De Wittln 30",
    "sg:city":"Arnhem",
    "sg:orig_category":"Binnenhuisarchitectuur",
    "sg:phone":"+31 26 442 2904",
    "sg:postcode":"6828 WG",
    "sg:province":"Gelderland",
    "wof:name":"Frings, Hans",
    "wof:placetype":"venue"
},
  "geometry": {"coordinates":[5.92598,51.98053],"type":"Point"}
}