{
  "type": "Feature",
  "properties": {
    "addr:full":"Muurbloemtuin 24 Zoetermeer South Holland 2724 PN",
    "addr:housenumber":"24",
    "addr:postcode":"2724 pn",
    "addr:street":"Muurbloemtuin",
    "iso:country":"NL",
    "sg:address":"Muurbloemtuin 24",
    "sg:city":"Zoetermeer",
    "sg:orig_category":"Onderhoudswerken",
    "sg:phone":"+31 79 342 4727",
    "sg:postcode":"2724 PN",
    "sg:province":"South Holland",
    "wof:name":"Excellent & Zorgeloos",
    "wof:placetype":"venue"
},
  "geometry": {"coordinates":[4.516278,52.064884],"type":"Point"}
}