{
  "type": "Feature",
  "properties": {
    "addr:full":"Breukerwg 183B Heerlen Limburg 6412 ZK",
    "addr:housenumber":"183b",
    "addr:postcode":"6412",
    "addr:street":"Zk",
    "iso:country":"NL",
    "sg:address":"Breukerwg 183B",
    "sg:city":"Heerlen",
    "sg:orig_category":"Autoverhuur",
    "sg:phone":"+31 45 400 9666",
    "sg:postcode":"6412 ZK",
    "sg:province":"Limburg",
    "sg:website":"http://www.budget.nl",
    "wof:name":"Budget Rent A Car",
    "wof:placetype":"venue"
},
  "geometry": {"coordinates":[5.942164,50.903568],"type":"Point"}
}