{
  "type": "Feature",
  "properties": {
    "addr:full":"Boomweg 8 Landgraaf Limburg 6371 CZ",
    "addr:housenumber":"8",
    "addr:postcode":"6371",
    "addr:street":"Boomweg",
    "iso:country":"NL",
    "sg:address":"Boomweg 8",
    "sg:city":"Landgraaf",
    "sg:orig_category":"Binnenhuisarchitecten",
    "sg:phone":"+31 45 531 7813",
    "sg:postcode":"6371 CZ",
    "sg:province":"Limburg",
    "wof:name":"E.H.M. Vijgen",
    "wof:placetype":"venue"
},
  "geometry": {"coordinates":[5.998072,50.906193],"type":"Point"}
}