{
  "type": "Feature",
  "properties": {
    "iso:country":"NL",
    "sg:address":"De Genestetln 109",
    "sg:city":"S Gravenhage",
    "sg:orig_category":"Poeliers",
    "sg:phone":"+31 70 393 7758",
    "sg:postcode":"2522 LD",
    "sg:province":"Zuid-Holland",
    "wof:name":"Langezaal, R",
    "wof:placetype":"venue"
},
  "geometry": {"coordinates":[4.32729,52.060848],"type":"Point"}
}