{
  "type": "Feature",
  "properties": {
    "iso:country":"NL",
    "sg:address":"Brederodelaan 18",
    "sg:city":"Bloemendaal",
    "sg:orig_category":"Fitnesscentra",
    "sg:phone":"+31 23 537 9944",
    "sg:postcode":"2061 KK",
    "sg:province":"Noord-Holland",
    "wof:name":"Kras Sport Zwem Schaat- En Skeelerschool",
    "wof:placetype":"venue"
},
  "geometry": {"coordinates":[4.617946,52.415432],"type":"Point"}
}