{
  "type": "Feature",
  "properties": {
    "addr:full":"Oud Kyk It Jatstr 59 Groningen Groningen 9712 EC",
    "addr:housenumber":"59",
    "addr:postcode":"9712 ec",
    "addr:street":"Oud",
    "iso:country":"NL",
    "sg:address":"Oud Kyk It Jatstr 59",
    "sg:city":"Groningen",
    "sg:orig_category":"Meubelen",
    "sg:phone":"+31 50 312 5916",
    "sg:postcode":"9712 EC",
    "sg:province":"Groningen",
    "wof:name":"Compaen, De",
    "wof:placetype":"venue"
},
  "geometry": {"coordinates":[6.561535,53.22007],"type":"Point"}
}