{
  "type": "Feature",
  "properties": {
    "addr:full":"Langewolderweg 7 Oldekerk Groningen 9821 PM",
    "addr:housenumber":"7",
    "addr:postcode":"9821 pm",
    "addr:street":"Langewolderweg",
    "iso:country":"NL",
    "sg:address":"Langewolderweg 7",
    "sg:city":"Oldekerk",
    "sg:orig_category":"Levende Dieren Gh",
    "sg:phone":"+31 594 503 151",
    "sg:postcode":"9821 PM",
    "sg:province":"Groningen",
    "wof:name":"J Kazemier",
    "wof:placetype":"venue"
},
  "geometry": {"coordinates":[6.332144,53.220997],"type":"Point"}
}