{
  "type": "Feature",
  "properties": {
    "iso:country":"NL",
    "sg:address":"Kraneweg 8",
    "sg:city":"Groningen",
    "sg:orig_category":"Artsen And Specialisten",
    "sg:phone":"+31 50 312 2954",
    "sg:postcode":"9718 JP",
    "sg:province":"Groningen",
    "wof:name":"H.J.H. Wielinga",
    "wof:placetype":"venue"
},
  "geometry": {"coordinates":[6.554246,53.217922],"type":"Point"}
}