{
  "type": "Feature",
  "properties": {
    "addr:full":"Ebenhaezerstr 103 Rotterdam Zuid-Holland 3083 RL",
    "addr:housenumber":"103",
    "addr:postcode":"3083 rl",
    "iso:country":"NL",
    "sg:address":"Ebenhaezerstr 103",
    "sg:city":"Rotterdam",
    "sg:orig_category":"Onderhoudswerken",
    "sg:phone":"+31 10 410 0291",
    "sg:postcode":"3083 RL",
    "sg:province":"Zuid-Holland",
    "wof:name":"Kos",
    "wof:placetype":"venue"
},
  "geometry": {"coordinates":[4.481163,51.887287],"type":"Point"}
}