{
  "type": "Feature",
  "properties": {
    "addr:full":"Leutsestraat 29 Angeren Gelderland 6687 LJ",
    "addr:housenumber":"29;lj",
    "addr:postcode":"6687",
    "addr:street":"Leutsestraat;Gelderland",
    "iso:country":"NL",
    "sg:address":"Leutsestraat 29",
    "sg:city":"Angeren",
    "sg:orig_category":"Hout Gh",
    "sg:phone":"+31 26 325 1465",
    "sg:postcode":"6687 LJ",
    "sg:province":"Gelderland",
    "wof:name":"Kroon Serres & Kassenbouw",
    "wof:placetype":"venue"
},
  "geometry": {"coordinates":[5.946456,51.921013],"type":"Point"}
}