{
  "type": "Feature",
  "properties": {
    "addr:full":"Meentweg 134 De Meern Utrecht 3454 AX",
    "addr:housenumber":"134",
    "addr:postcode":"3454 ax",
    "addr:street":"Meentweg",
    "iso:country":"NL",
    "sg:address":"Meentweg 134",
    "sg:city":"De Meern",
    "sg:orig_category":"Paramedische Behandelingen",
    "sg:phone":"+31 30 662 1408",
    "sg:postcode":"3454 AX",
    "sg:province":"Utrecht",
    "wof:name":"W. Janszen",
    "wof:placetype":"venue"
},
  "geometry": {"coordinates":[5.041136,52.075554],"type":"Point"}
}