{
  "type": "Feature",
  "properties": {
    "iso:country":"NL",
    "sg:address":"Onderduikerswg 38",
    "sg:city":"Espel",
    "sg:orig_category":"Koel- En Vrieshuizen",
    "sg:phone":"+31 527 271 340",
    "sg:postcode":"8311 RE",
    "sg:province":"Flevoland",
    "wof:name":"Snippe Vof, W",
    "wof:placetype":"venue"
},
  "geometry": {"coordinates":[-95.71624799999999,48.223763],"type":"Point"}
}