{
  "type": "Feature",
  "properties": {
    "addr:full":"Zwanebloem 20 Leeuwarden Provincie Friesland 8935 NX",
    "addr:housenumber":"20",
    "addr:postcode":"8935 nx",
    "addr:street":"Zwanebloem;Provincie Friesland",
    "iso:country":"NL",
    "sg:address":"Zwanebloem 20",
    "sg:city":"Leeuwarden",
    "sg:orig_category":"Sportverenigingen En Ontspannings- Verenigingen",
    "sg:phone":"+31 58 288 1273",
    "sg:postcode":"8935 NX",
    "sg:province":"Provincie Friesland",
    "wof:name":"Dov, Gehandicaptensportver",
    "wof:placetype":"venue"
},
  "geometry": {"coordinates":[5.833873,53.191368],"type":"Point"}
}