{
  "type": "Feature",
  "properties": {
    "addr:full":"De Roef 13 Drachten Provincie Friesland 9206 AK",
    "addr:housenumber":"13",
    "addr:postcode":"9206 ak",
    "addr:street":"De Roef;Provincie Friesland",
    "iso:country":"NL",
    "sg:address":"De Roef 13",
    "sg:city":"Drachten",
    "sg:orig_category":"Autokeuringen",
    "sg:phone":"+31 512 516 835",
    "sg:postcode":"9206 AK",
    "sg:province":"Provincie Friesland",
    "wof:name":"Rits Van Der Velde Autoschadebedrijf",
    "wof:placetype":"venue"
},
  "geometry": {"coordinates":[6.077059,53.115177],"type":"Point"}
}