{
  "type": "Feature",
  "properties": {
    "addr:full":"Bovenkerksew 11 Stolwijk Zuid-Holland 2821 XS",
    "addr:housenumber":"11",
    "addr:postcode":"2821 xs",
    "addr:street":"Bovenkerksew",
    "iso:country":"NL",
    "sg:address":"Bovenkerksew 11",
    "sg:city":"Stolwijk",
    "sg:orig_category":"Fietsen En Bromfietsen",
    "sg:phone":"+31 182 341 345",
    "sg:postcode":"2821 XS",
    "sg:province":"Zuid-Holland",
    "wof:name":"Berends, M J",
    "wof:placetype":"venue"
},
  "geometry": {"coordinates":[4.772877,51.972561],"type":"Point"}
}