{
  "type": "Feature",
  "properties": {
    "iso:country":"NL",
    "sg:address":"Caumerbeek 13",
    "sg:city":"Geleen",
    "sg:orig_category":"Webdesign Bureaus",
    "sg:phone":"+31 46 475 8139",
    "sg:postcode":"6166 GD",
    "sg:province":"Limburg",
    "sg:website":"http://www.fisheye.nl",
    "wof:name":"Fisheye",
    "wof:placetype":"venue"
},
  "geometry": {"coordinates":[5.8457050323,50.9724769592],"type":"Point"}
}