{
  "type": "Feature",
  "properties": {
    "addr:full":"Pioenstr 30 Enschede Overijssel 7531 KC",
    "addr:housenumber":"30",
    "addr:postcode":"7531 kc",
    "addr:street":"Pioenstr",
    "iso:country":"NL",
    "sg:address":"Pioenstr 30",
    "sg:city":"Enschede",
    "sg:orig_category":"Kappers",
    "sg:phone":"+31 53 433 8822",
    "sg:postcode":"7531 KC",
    "sg:province":"Overijssel",
    "wof:name":"Scissors",
    "wof:placetype":"venue"
},
  "geometry": {"coordinates":[6.921116,52.228321],"type":"Point"}
}