{
  "type": "Feature",
  "properties": {
    "addr:full":"W Nieuwenkampstraat 42 Volendam North Holland 1132 XH",
    "addr:housenumber":"42",
    "addr:postcode":"1132 xh",
    "addr:street":"W Nieuwenkampstraat",
    "iso:country":"NL",
    "sg:address":"W Nieuwenkampstraat 42",
    "sg:city":"Volendam",
    "sg:orig_category":"Boekhouders",
    "sg:phone":"+31 299 364 668",
    "sg:postcode":"1132 XH",
    "sg:province":"North Holland",
    "wof:name":"Administratiekantoor J.M.J.A. Tol",
    "wof:placetype":"venue"
},
  "geometry": {"coordinates":[5.05879,52.495926],"type":"Point"}
}