{
  "type": "Feature",
  "properties": {
    "addr:full":"Terpstraat 42 Wieringerwerf Noord-Holland 1771 AD",
    "addr:housenumber":"42",
    "addr:postcode":"1771 ad",
    "addr:street":"Terpstraat",
    "iso:country":"NL",
    "sg:address":"Terpstraat 42",
    "sg:city":"Wieringerwerf",
    "sg:classifiers":[
        {
            "category":"Education",
            "subcategory":"Preschool",
            "type":"Public Place"
        }
    ],
    "sg:phone":"+31 227 601 954",
    "sg:postcode":"1771 AD",
    "sg:province":"Noord-Holland",
    "sg:tags":[
        "kleuteronderwijs",
        "basis-"
    ],
    "wof:name":"Openbare Basisschool De Triangel",
    "wof:placetype":"venue"
},
  "geometry": {"coordinates":[5.022337,52.853748],"type":"Point"}
}