{
  "type": "Feature",
  "properties": {
    "addr:full":"Mathenesserdk 81 Rotterdam Zuid-Holland 3027 BD",
    "addr:housenumber":"81",
    "addr:postcode":"3027 bd",
    "addr:street":"Mathenesserdk",
    "iso:country":"NL",
    "sg:address":"Mathenesserdk 81",
    "sg:city":"Rotterdam",
    "sg:classifiers":[
        {
            "category":"Retail",
            "subcategory":"Auto Repair",
            "type":"Services"
        }
    ],
    "sg:phone":"+31 10 415 3512",
    "sg:postcode":"3027 BD",
    "sg:province":"Zuid-Holland",
    "sg:tags":[
        "garage"
    ],
    "wof:name":"Mathenesse Ltd",
    "wof:placetype":"venue"
},
  "geometry": {"coordinates":[4.435193,51.915131],"type":"Point"}
}