{
  "type": "Feature",
  "properties": {
    "addr:full":"Arnhemsestrwg 85 Rheden Gelderland 6991 AK",
    "addr:housenumber":"85",
    "addr:postcode":"6991 ak",
    "addr:street":"Arnhemsestrwg;Gelderland",
    "iso:country":"NL",
    "sg:address":"Arnhemsestrwg 85",
    "sg:city":"Rheden",
    "sg:orig_category":"Adviesbureaus Chemische Techniek",
    "sg:phone":"+31 26 495 5186",
    "sg:postcode":"6991 AK",
    "sg:province":"Gelderland",
    "wof:name":"Stratechem",
    "wof:placetype":"venue"
},
  "geometry": {"coordinates":[6.03264,52.002544],"type":"Point"}
}