{
  "type": "Feature",
  "properties": {
    "addr:full":"Stadhouderln 99 Mydrecht Utrecht 3641 KG",
    "addr:housenumber":"99",
    "addr:postcode":"kg",
    "addr:street":"Stadhouderln",
    "iso:country":"NL",
    "sg:address":"Stadhouderln 99",
    "sg:city":"Mydrecht",
    "sg:orig_category":"Kunsthandel",
    "sg:phone":"+31 297 288 634",
    "sg:postcode":"3641 KG",
    "sg:province":"Utrecht",
    "wof:name":"Serenia",
    "wof:placetype":"venue"
},
  "geometry": {"coordinates":[4.86178,52.20578],"type":"Point"}
}