{
  "type": "Feature",
  "properties": {
    "iso:country":"NL",
    "sg:address":"V Ryckevorselstr 29",
    "sg:city":"Driebergen Rysenb",
    "sg:orig_category":"Verhuur",
    "sg:phone":"+31 6 53106220",
    "sg:postcode":"3972 EP",
    "sg:province":"Utrecht",
    "wof:name":"Comfort Beheer",
    "wof:placetype":"venue"
},
  "geometry": {"coordinates":[5.283655,52.051552],"type":"Point"}
}