{
  "type": "Feature",
  "properties": {
    "addr:full":"Tt Vasumweg 4D Amsterdam Noord-Holland 1033 SC",
    "addr:housenumber":"4d",
    "addr:postcode":"1033 sc",
    "addr:street":"Vasumweg",
    "iso:country":"NL",
    "sg:address":"Tt Vasumweg 4D",
    "sg:city":"Amsterdam",
    "sg:orig_category":"Wasserettes, Stomerijen And Reiniging",
    "sg:phone":"+31 20 634 4647",
    "sg:postcode":"1033 SC",
    "sg:province":"Noord-Holland",
    "wof:name":"Chem-Dry",
    "wof:placetype":"venue"
},
  "geometry": {"coordinates":[4.8986701965,52.4017486572],"type":"Point"}
}