{
  "type": "Feature",
  "properties": {
    "addr:full":"Bisonspoor 1230 Maarssen Utrecht 3605 KZ",
    "addr:housenumber":"1230",
    "addr:postcode":"3605",
    "addr:street":"Bisonspoor",
    "iso:country":"NL",
    "sg:address":"Bisonspoor 1230",
    "sg:city":"Maarssen",
    "sg:orig_category":"Verenigingen En Stichtingen",
    "sg:phone":"+31 346 571 004",
    "sg:postcode":"3605 KZ",
    "sg:province":"Utrecht",
    "wof:name":"Dienstverlening Personenvervoer, Sticht",
    "wof:placetype":"venue"
},
  "geometry": {"coordinates":[5.028252,52.135685],"type":"Point"}
}