{
  "type": "Feature",
  "properties": {
    "addr:full":"Stationsstr 30 Ryen Noord-Brabant 5121 ED",
    "addr:housenumber":"30",
    "addr:postcode":"5121 ed",
    "addr:street":"Stationsstr",
    "iso:country":"NL",
    "sg:address":"Stationsstr 30",
    "sg:city":"Ryen",
    "sg:orig_category":"Wasmachines En Wasdrogers",
    "sg:phone":"+31 161 222 849",
    "sg:postcode":"5121 ED",
    "sg:province":"Noord-Brabant",
    "wof:name":"Heijden, W Van Der",
    "wof:placetype":"venue"
},
  "geometry": {"coordinates":[4.9197001457,51.58801651],"type":"Point"}
}