{
  "type": "Feature",
  "properties": {
    "addr:full":"Dorpsstraat 46 Renswoude Utrecht 3927 BD",
    "addr:housenumber":"46",
    "addr:postcode":"3927 bd",
    "addr:street":"Dorpsstraat",
    "iso:country":"NL",
    "sg:address":"Dorpsstraat 46",
    "sg:city":"Renswoude",
    "sg:orig_category":"Verlichting And Huishoudartikelen",
    "sg:phone":"+31 318 571 306",
    "sg:postcode":"3927 BD",
    "sg:province":"Utrecht",
    "wof:name":"Interieurverzorging Van Raaij",
    "wof:placetype":"venue"
},
  "geometry": {"coordinates":[5.543335,52.072792],"type":"Point"}
}