{
  "type": "Feature",
  "properties": {
    "addr:full":"Brummelstr 15 Hollandscheveld Provincie Drenthe 7913 BE",
    "addr:housenumber":"15",
    "addr:postcode":"7913",
    "addr:street":"Brummelstr;Provincie Drenthe",
    "iso:country":"NL",
    "sg:address":"Brummelstr 15",
    "sg:city":"Hollandscheveld",
    "sg:orig_category":"Voetbalverenigingen",
    "sg:phone":"+31 6 20449382",
    "sg:postcode":"7913 BE",
    "sg:province":"Provincie Drenthe",
    "wof:name":"Hollandscheveld Vv",
    "wof:placetype":"venue"
},
  "geometry": {"coordinates":[6.534708,52.704826],"type":"Point"}
}