{
  "type": "Feature",
  "properties": {
    "addr:full":"Hinthamereinde 59 S Hertogenbosch Noord-Brabant 5211 PM",
    "addr:housenumber":"59",
    "addr:postcode":"5211 pm",
    "addr:street":"Hinthamereinde;S Hertogenbosch",
    "iso:country":"NL",
    "sg:address":"Hinthamereinde 59",
    "sg:city":"S Hertogenbosch",
    "sg:orig_category":"Boeken En Tijdschriften",
    "sg:phone":"+31 73 613 5073",
    "sg:postcode":"5211 PM",
    "sg:province":"Noord-Brabant",
    "wof:name":"Kleijne Tabak En Gemak",
    "wof:placetype":"venue"
},
  "geometry": {"coordinates":[5.316175,51.690243],"type":"Point"}
}