{
  "type": "Feature",
  "properties": {
    "addr:full":"Pottenbakker 52 Halsteren North Brabant 4661 NH",
    "addr:housenumber":"52",
    "addr:postcode":"4661 nh",
    "addr:street":"Pottenbakker",
    "iso:country":"NL",
    "sg:address":"Pottenbakker 52",
    "sg:city":"Halsteren",
    "sg:orig_category":"Fotoreportages",
    "sg:phone":"+31 164 685 820",
    "sg:postcode":"4661 NH",
    "sg:province":"North Brabant",
    "wof:name":"Zachariasse, J A",
    "wof:placetype":"venue"
},
  "geometry": {"coordinates":[4.280786,51.52351],"type":"Point"}
}