{
  "type": "Feature",
  "properties": {
    "addr:full":"Buizerdhorst 107 Leiden South Holland 2317 DC",
    "addr:housenumber":"107",
    "addr:postcode":"2317",
    "addr:street":"Buizerdhorst",
    "iso:country":"NL",
    "sg:address":"Buizerdhorst 107",
    "sg:city":"Leiden",
    "sg:orig_category":"Makelaars En Adviseurs Onroerende Goederen",
    "sg:phone":"+31 71 521 4521",
    "sg:postcode":"2317 DC",
    "sg:province":"South Holland",
    "wof:name":"Beukering, Van",
    "wof:placetype":"venue"
},
  "geometry": {"coordinates":[4.504757,52.175461],"type":"Point"}
}