{
  "type": "Feature",
  "properties": {
    "addr:full":"Enkweg 23 Renkum Gelderland 6871 GN",
    "addr:housenumber":"23",
    "addr:postcode":"6871 gn",
    "addr:street":"Enkweg;Gelderland",
    "iso:country":"NL",
    "sg:address":"Enkweg 23",
    "sg:city":"Renkum",
    "sg:orig_category":"Bloemen And Planten",
    "sg:phone":"+31 317 312 978",
    "sg:postcode":"6871 GN",
    "sg:province":"Gelderland",
    "wof:name":"Vof Bloemenhandel Antura",
    "wof:placetype":"venue"
},
  "geometry": {"coordinates":[5.731459,51.976555],"type":"Point"}
}