{
  "type": "Feature",
  "properties": {
    "addr:full":"Ln V Meerdervoort 659 S Gravenhage Zuid-Holland 2564 AB",
    "addr:housenumber":"659;gravenhage",
    "addr:postcode":"2564 ab",
    "addr:street":"Ln;Meerdervoort;S",
    "iso:country":"NL",
    "sg:address":"Ln V Meerdervoort 659",
    "sg:city":"S Gravenhage",
    "sg:orig_category":"Adviesbureaus",
    "sg:phone":"+31 70 345 5301",
    "sg:postcode":"2564 AB",
    "sg:province":"Zuid-Holland",
    "wof:name":"Hartman, Herman",
    "wof:placetype":"venue"
},
  "geometry": {"coordinates":[4.25946,52.06805],"type":"Point"}
}