{
  "type": "Feature",
  "properties": {
    "addr:full":"Haven 70 Schoonhoven Zuid-Holland 2871 CR",
    "addr:housenumber":"70",
    "addr:postcode":"2871 cr",
    "addr:street":"Haven",
    "iso:country":"NL",
    "sg:address":"Haven 70",
    "sg:city":"Schoonhoven",
    "sg:orig_category":"Reisbureaus",
    "sg:phone":"+31 182 320 188",
    "sg:postcode":"2871 CR",
    "sg:province":"Zuid-Holland",
    "sg:website":"http://www.opmaatreizen.nl",
    "wof:name":"Opmaat, De",
    "wof:placetype":"venue"
},
  "geometry": {"coordinates":[4.85135,51.945675],"type":"Point"}
}