{
  "type": "Feature",
  "properties": {
    "addr:full":"Haagwg 162 Ryswyk Zh Zuid-Holland 2282 AJ",
    "addr:housenumber":"162",
    "addr:postcode":"2282 aj",
    "addr:street":"Ryswyk",
    "iso:country":"NL",
    "sg:address":"Haagwg 162",
    "sg:city":"Ryswyk Zh",
    "sg:orig_category":"Verzekeringen - Verzekeringskantoren",
    "sg:phone":"+31 70 307 7620",
    "sg:postcode":"2282 AJ",
    "sg:province":"Zuid-Holland",
    "wof:name":"Witvliet En Solleveld",
    "wof:placetype":"venue"
},
  "geometry": {"coordinates":[4.33694,52.056503],"type":"Point"}
}