{
  "type": "Feature",
  "properties": {
    "iso:country":"NL",
    "sg:address":"Lochemsew 7",
    "sg:city":"Borculo",
    "sg:orig_category":"Fietsen En Bromfietsen",
    "sg:phone":"+31 545 272 648",
    "sg:postcode":"7271 WB",
    "sg:province":"Gelderland",
    "wof:name":"Top",
    "wof:placetype":"venue"
},
  "geometry": {"coordinates":[6.522683,52.120079],"type":"Point"}
}