{
  "type": "Feature",
  "properties": {
    "addr:full":"Lochemsew 7 Borculo Gelderland 7271 WB",
    "addr:housenumber":"7",
    "addr:postcode":"7271 wb",
    "addr:street":"Lochemsew;Gelderland",
    "iso:country":"NL",
    "sg:address":"Lochemsew 7",
    "sg:city":"Borculo",
    "sg:orig_category":"Fietsen En Bromfietsen",
    "sg:phone":"+31 545 272 648",
    "sg:postcode":"7271 WB",
    "sg:province":"Gelderland",
    "wof:name":"Top",
    "wof:placetype":"venue"
},
  "geometry": {"coordinates":[6.522683,52.120079],"type":"Point"}
}