{
  "type": "Feature",
  "properties": {
    "addr:full":"Mosselbank 11 Leiden South Holland 2317 MD",
    "addr:housenumber":"11",
    "addr:postcode":"2317",
    "addr:street":"Mosselbank",
    "iso:country":"NL",
    "sg:address":"Mosselbank 11",
    "sg:city":"Leiden",
    "sg:orig_category":"Wegen And Sportterreinen",
    "sg:phone":"+31 71 521 0196",
    "sg:postcode":"2317 MD",
    "sg:province":"South Holland",
    "wof:name":"H.A.J.Van Den Berg",
    "wof:placetype":"venue"
},
  "geometry": {"coordinates":[4.5020861626,52.1781349182],"type":"Point"}
}