{
  "type": "Feature",
  "properties": {
    "iso:country":"NL",
    "sg:address":"Ceresstr 41",
    "sg:city":"Stadskanaal",
    "sg:orig_category":"Bloemen En Planten",
    "sg:phone":"+31 599 652 170",
    "sg:postcode":"9502 EB",
    "sg:province":"Groningen",
    "wof:name":"Wit, De",
    "wof:placetype":"venue"
},
  "geometry": {"coordinates":[6.974106,52.972351],"type":"Point"}
}