{
  "type": "Feature",
  "properties": {
    "addr:full":"Weena 202 Rotterdam South Holland 3012 NJ",
    "addr:housenumber":"202",
    "addr:postcode":"3012 nj",
    "addr:street":"Weena",
    "iso:country":"NL",
    "sg:address":"Weena 202",
    "sg:city":"Rotterdam",
    "sg:orig_category":"Banken And Kredietinstellingen",
    "sg:phone":"+31 10 413 5080",
    "sg:postcode":"3012 NJ",
    "sg:province":"South Holland",
    "wof:name":"Fortis Bank",
    "wof:placetype":"venue"
},
  "geometry": {"coordinates":[4.474275,51.923435],"type":"Point"}
}