{
  "type": "Feature",
  "properties": {
    "addr:full":"Heistraat 4 Boxmeer North Brabant 5831 AR",
    "addr:housenumber":"4",
    "addr:postcode":"5831",
    "addr:street":"Heistraat",
    "iso:country":"NL",
    "sg:address":"Heistraat 4",
    "sg:city":"Boxmeer",
    "sg:orig_category":"Bloemen And Planten",
    "sg:phone":"+31 485 571 695",
    "sg:postcode":"5831 AR",
    "sg:province":"North Brabant",
    "wof:name":"J.A.M. Verberkt",
    "wof:placetype":"venue"
},
  "geometry": {"coordinates":[5.943524,51.635696],"type":"Point"}
}