{
  "type": "Feature",
  "properties": {
    "addr:full":"Nw Binnenwg 189A Rotterdam Zuid-Holland 3021 GA",
    "addr:housenumber":"189a",
    "addr:postcode":"3021 ga",
    "iso:country":"NL",
    "sg:address":"Nw Binnenwg 189A",
    "sg:city":"Rotterdam",
    "sg:orig_category":"Opticiens",
    "sg:phone":"+31 10 244 0903",
    "sg:postcode":"3021 GA",
    "sg:province":"Zuid-Holland",
    "wof:name":"Brilleman, De",
    "wof:placetype":"venue"
},
  "geometry": {"coordinates":[4.4629201889,51.91381073],"type":"Point"}
}