{
  "type": "Feature",
  "properties": {
    "iso:country":"NL",
    "sg:address":"Warande 43",
    "sg:city":"Nieuw Vennep",
    "sg:orig_category":"Gebouwenafwerking, Renovaties And Reiniging",
    "sg:phone":"+31 229 244 397",
    "sg:postcode":"2152 CK",
    "sg:province":"Noord-Holland",
    "wof:name":"Lucien Petiet Timmer- En Onderhoudsbedrijf",
    "wof:placetype":"venue"
},
  "geometry": {"coordinates":[4.632991,52.270622],"type":"Point"}
}