{
  "type": "Feature",
  "properties": {
    "addr:full":"Bergseln 352A Rotterdam Zuid-Holland 3038 CR",
    "addr:housenumber":"352a",
    "addr:postcode":"3038 cr",
    "iso:country":"NL",
    "sg:address":"Bergseln 352A",
    "sg:city":"Rotterdam",
    "sg:orig_category":"Schilders",
    "sg:phone":"+31 10 467 6749",
    "sg:postcode":"3038 CR",
    "sg:province":"Zuid-Holland",
    "wof:name":"Boender, C",
    "wof:placetype":"venue"
},
  "geometry": {"coordinates":[4.46465,51.935558],"type":"Point"}
}