{
  "type": "Feature",
  "properties": {
    "addr:full":"Hofstr 38 Nederhemert Gelderland 5317 JN",
    "addr:housenumber":"38",
    "addr:postcode":"5317 jn",
    "addr:street":"Hofstr;Gelderland",
    "iso:country":"NL",
    "sg:address":"Hofstr 38",
    "sg:city":"Nederhemert",
    "sg:orig_category":"Behangers",
    "sg:phone":"+31 418 552 281",
    "sg:postcode":"5317 JN",
    "sg:province":"Gelderland",
    "wof:name":"Aalst, Gebroeders Van",
    "wof:placetype":"venue"
},
  "geometry": {"coordinates":[5.168302,51.765179],"type":"Point"}
}