{
  "type": "Feature",
  "properties": {
    "addr:full":"Lonnekerbrugstr 78 Enschede NL.08 7547 AJ",
    "addr:housenumber":"78",
    "addr:postcode":"7547 aj",
    "addr:street":"Lonnekerbrugstr",
    "iso:country":"NL",
    "sg:address":"Lonnekerbrugstr 78",
    "sg:city":"Enschede",
    "sg:orig_category":"Plastic Producten - Fabrieken En Groothandel",
    "sg:phone":"+31 53 483 0040",
    "sg:postcode":"7547 AJ",
    "sg:province":"NL.08",
    "sg:website":"http://www.impact-forme.com",
    "wof:name":"Impact Forme Bv",
    "wof:placetype":"venue"
},
  "geometry": {"coordinates":[6.856756,52.225563],"type":"Point"}
}