{
  "type": "Feature",
  "properties": {
    "addr:full":"Vianenstr 37 Velp Gld Gelderland 6882 NT",
    "addr:housenumber":"37",
    "addr:postcode":"6882 nt",
    "addr:street":"Vianenstr;Gld Gelderland",
    "iso:country":"NL",
    "sg:address":"Vianenstr 37",
    "sg:city":"Velp Gld",
    "sg:orig_category":"Beeldende Kunstenaars",
    "sg:phone":"+31 26 361 0551",
    "sg:postcode":"6882 NT",
    "sg:province":"Gelderland",
    "wof:name":"Tax, Lettie",
    "wof:placetype":"venue"
},
  "geometry": {"coordinates":[5.976851,51.992043],"type":"Point"}
}