{
  "type": "Feature",
  "properties": {
    "addr:full":"Eilandstr 21 Papendrecht Zuid-Holland 3351 AB",
    "addr:housenumber":"21",
    "addr:postcode":"3351 ab",
    "addr:street":"Eilandstr",
    "iso:country":"NL",
    "sg:address":"Eilandstr 21",
    "sg:city":"Papendrecht",
    "sg:orig_category":"Verhuizingen",
    "sg:phone":"+31 78 642 5578",
    "sg:postcode":"3351 AB",
    "sg:province":"Zuid-Holland",
    "wof:name":"Internationale Verhuizer, De",
    "wof:placetype":"venue"
},
  "geometry": {"coordinates":[4.681811,51.823982],"type":"Point"}
}