{
  "type": "Feature",
  "properties": {
    "iso:country":"NL",
    "sg:address":"Eilandstr 21",
    "sg:city":"Papendrecht",
    "sg:orig_category":"Verhuizingen",
    "sg:phone":"+31 78 642 5578",
    "sg:postcode":"3351 AB",
    "sg:province":"Zuid-Holland",
    "wof:name":"Internationale Verhuizer, De",
    "wof:placetype":"venue"
},
  "geometry": {"coordinates":[4.681811,51.823982],"type":"Point"}
}