{
  "type": "Feature",
  "properties": {
    "iso:country":"NL",
    "sg:address":"Fabristr 57",
    "sg:city":"Schiedam",
    "sg:orig_category":"Schoenen - Reparaties",
    "sg:phone":"+31 10 426 5523",
    "sg:postcode":"3117 MH",
    "sg:province":"Zuid-Holland",
    "wof:name":"Hommel & Zn, Fa F",
    "wof:placetype":"venue"
},
  "geometry": {"coordinates":[4.391477,51.914604],"type":"Point"}
}