{
  "type": "Feature",
  "properties": {
    "addr:full":"Amperestr 2 Deurne Noord-Brabant 5753 ST",
    "addr:housenumber":"2",
    "addr:postcode":"5753 st",
    "addr:street":"Amperestr",
    "iso:country":"NL",
    "sg:address":"Amperestr 2",
    "sg:city":"Deurne",
    "sg:orig_category":"Kantoorbenodigdheden - Fabrieken En Groothandel",
    "sg:phone":"+31 493 311 016",
    "sg:postcode":"5753 ST",
    "sg:province":"Noord-Brabant",
    "sg:website":"HTTP://www.vleveka.com",
    "wof:name":"Vleveka Bv",
    "wof:placetype":"venue"
},
  "geometry": {"coordinates":[5.8009529114,51.4490737915],"type":"Point"}
}