{
  "type": "Feature",
  "properties": {
    "addr:full":"Nieuwstr 19 Made California 4921 CT",
    "addr:housenumber":"19",
    "addr:postcode":"4921 ct",
    "addr:street":"Nieuwstr",
    "iso:country":"NL",
    "sg:address":"Nieuwstr 19",
    "sg:city":"Made",
    "sg:orig_category":"Bloemen En Planten",
    "sg:phone":"+31 162 682 562",
    "sg:postcode":"4921 CT",
    "sg:province":"California",
    "wof:name":"Insulinde",
    "wof:placetype":"venue"
},
  "geometry": {"coordinates":[-120.197731,37.032848],"type":"Point"}
}