{
  "type": "Feature",
  "properties": {
    "addr:full":"Lynbaan 171 Rotterdam Zuid-Holland 3012 EN",
    "addr:housenumber":"171",
    "addr:postcode":"3012 en",
    "iso:country":"NL",
    "sg:address":"Lynbaan 171",
    "sg:city":"Rotterdam",
    "sg:orig_category":"Dameskleding",
    "sg:phone":"+31 10 411 0014",
    "sg:postcode":"3012 EN",
    "sg:province":"Zuid-Holland",
    "wof:name":"Esprit",
    "wof:placetype":"venue"
},
  "geometry": {"coordinates":[4.4784550667,51.9228363037],"type":"Point"}
}