{
  "type": "Feature",
  "properties": {
    "addr:full":"Hooge Steenweg 32 'S Hertogenbosch North Brabant 5211 JP",
    "addr:housenumber":"32",
    "addr:postcode":"5211 jp",
    "addr:street":"Hooge Steenweg;' S Hertogenbosch",
    "iso:country":"NL",
    "sg:address":"Hooge Steenweg 32",
    "sg:city":"'S Hertogenbosch",
    "sg:orig_category":"Verlichting And Huishoudartikelen",
    "sg:phone":"+31 73 613 8427",
    "sg:postcode":"5211 JP",
    "sg:province":"North Brabant",
    "wof:name":"Enesco Collectibles",
    "wof:placetype":"venue"
},
  "geometry": {"coordinates":[5.301424,51.690338],"type":"Point"}
}