{
  "type": "Feature",
  "properties": {
    "addr:full":"Laurierberg 9A Roosendaal North Brabant 4708 LD",
    "addr:housenumber":"9a",
    "addr:postcode":"4708 ld",
    "addr:street":"Laurierberg",
    "iso:country":"NL",
    "sg:address":"Laurierberg 9A",
    "sg:city":"Roosendaal",
    "sg:orig_category":"Autorijscholen",
    "sg:phone":"+31 165 535 363",
    "sg:postcode":"4708 LD",
    "sg:province":"North Brabant",
    "wof:name":"Goossens",
    "wof:placetype":"venue"
},
  "geometry": {"coordinates":[4.431494,51.517681],"type":"Point"}
}