{
  "type": "Feature",
  "properties": {
    "addr:full":"Beethovenstr 72 Amsterdam North Holland 1077 JM",
    "addr:housenumber":"72",
    "addr:postcode":"1077 jm",
    "addr:street":"Beethovenstr",
    "iso:country":"NL",
    "sg:address":"Beethovenstr 72",
    "sg:city":"Amsterdam",
    "sg:orig_category":"Banket",
    "sg:phone":"+31 20 662 2009",
    "sg:postcode":"1077 JM",
    "sg:province":"North Holland",
    "sg:website":"http://www.huizevanwely.nl",
    "wof:name":"Wely Sinds 1922, Huize Van",
    "wof:placetype":"venue"
},
  "geometry": {"coordinates":[4.876806,52.347847],"type":"Point"}
}