{
  "type": "Feature",
  "properties": {
    "addr:full":"Kompasstraat 1 Lutjegast Groningen 9866 AP",
    "addr:housenumber":"1",
    "addr:postcode":"9866 ap",
    "addr:street":"Kompasstraat",
    "iso:country":"NL",
    "sg:address":"Kompasstraat 1",
    "sg:city":"Lutjegast",
    "sg:orig_category":"Bibliotheken And Openbare Archieven",
    "sg:phone":"+31 594 612 431",
    "sg:postcode":"9866 AP",
    "sg:province":"Groningen",
    "wof:name":"Openbare Bibliotheek",
    "wof:placetype":"venue"
},
  "geometry": {"coordinates":[6.259245,53.234619],"type":"Point"}
}