{
  "type": "Feature",
  "properties": {
    "addr:full":"Paardeweide 24A Breda Noord-Brabant 4824 EH",
    "addr:housenumber":"24a",
    "addr:postcode":"4824 eh",
    "addr:street":"Paardeweide",
    "iso:country":"NL",
    "sg:address":"Paardeweide 24A",
    "sg:city":"Breda",
    "sg:orig_category":"Adviesbureaus Bedrijfsorganisatie",
    "sg:phone":"+31 76 542 0335",
    "sg:postcode":"4824 EH",
    "sg:province":"Noord-Brabant",
    "sg:website":"http://www.coevering.nl",
    "wof:name":"Coevering Bv",
    "wof:placetype":"venue"
},
  "geometry": {"coordinates":[4.75169,51.609779],"type":"Point"}
}