{
  "type": "Feature",
  "properties": {
    "iso:country":"NL",
    "sg:address":"Oosteinderweg 266",
    "sg:city":"Aalsmeer",
    "sg:orig_category":"Artsen And Specialisten",
    "sg:phone":"+31 297 327 717",
    "sg:postcode":"1432 BC",
    "sg:province":"Noord-Holland",
    "wof:name":"J.A. Van Kessel",
    "wof:placetype":"venue"
},
  "geometry": {"coordinates":[4.788596,52.280872],"type":"Point"}
}