{
  "type": "Feature",
  "properties": {
    "addr:full":"Waterhoenln 17 Vinkeveen Utrecht 3645 JR",
    "addr:housenumber":"17",
    "addr:postcode":"3645 jr",
    "addr:street":"Waterhoenln",
    "iso:country":"NL",
    "sg:address":"Waterhoenln 17",
    "sg:city":"Vinkeveen",
    "sg:orig_category":"Elektronica - Ontwikkeling En Groothandel",
    "sg:phone":"+31 297 263 047",
    "sg:postcode":"3645 JR",
    "sg:province":"Utrecht",
    "wof:name":"Kamahi",
    "wof:placetype":"venue"
},
  "geometry": {"coordinates":[4.921273,52.213032],"type":"Point"}
}