{
  "type": "Feature",
  "properties": {
    "addr:full":"Ruiterswg 32 Hilversum Noord-Holland 1211 KW",
    "addr:housenumber":"32",
    "addr:postcode":"1211 kw",
    "addr:street":"Ruiterswg",
    "iso:country":"NL",
    "sg:address":"Ruiterswg 32",
    "sg:city":"Hilversum",
    "sg:orig_category":"Orthopedagogen",
    "sg:phone":"+31 35 628 1903",
    "sg:postcode":"1211 KW",
    "sg:province":"Noord-Holland",
    "wof:name":"Gooi, Praktijk 'T",
    "wof:placetype":"venue"
},
  "geometry": {"coordinates":[5.1721777916,52.2219352722],"type":"Point"}
}