{
  "type": "Feature",
  "properties": {
    "addr:full":"Van Lennepstraat 50 Putten Gelderland 3881 WT",
    "addr:housenumber":"50",
    "addr:postcode":"3881 wt",
    "addr:street":"Van Lennepstraat;Gelderland",
    "iso:country":"NL",
    "sg:address":"Van Lennepstraat 50",
    "sg:city":"Putten",
    "sg:orig_category":"Elektronische Bedrijfsinstallaties",
    "sg:phone":"+31 341 361 704",
    "sg:postcode":"3881 WT",
    "sg:province":"Gelderland",
    "wof:name":"Dvh Handelsonderneming",
    "wof:placetype":"venue"
},
  "geometry": {"coordinates":[5.611859,52.25108],"type":"Point"}
}