{
  "type": "Feature",
  "properties": {
    "addr:full":"Jasper Leijnsenstraat 29 Amsterdam North Holland 1056 XW",
    "addr:housenumber":"29",
    "addr:postcode":"1056 xw",
    "addr:street":"Jasper Leijnsenstraat",
    "iso:country":"NL",
    "sg:address":"Jasper Leijnsenstraat 29",
    "sg:city":"Amsterdam",
    "sg:orig_category":"Kappers",
    "sg:phone":"+31 20 612 2531",
    "sg:postcode":"1056 XW",
    "sg:province":"North Holland",
    "wof:name":"Gerard Hairshop",
    "wof:placetype":"venue"
},
  "geometry": {"coordinates":[4.8613491058,52.3763694763],"type":"Point"}
}