{
  "type": "Feature",
  "properties": {
    "addr:full":"Pontwg 2 Den Hoorn Texel Noord-Holland 1797 SR",
    "addr:housenumber":"2",
    "addr:postcode":"1797 sr",
    "addr:street":"Pontwg",
    "iso:country":"NL",
    "sg:address":"Pontwg 2",
    "sg:city":"Den Hoorn Texel",
    "sg:orig_category":"Fietsen En Bromfietsen Verhuur",
    "sg:phone":"+31 222 319 588",
    "sg:postcode":"1797 SR",
    "sg:province":"Noord-Holland",
    "wof:name":"Horntje, 'T",
    "wof:placetype":"venue"
},
  "geometry": {"coordinates":[4.779209,53.004562],"type":"Point"}
}