{
  "type": "Feature",
  "properties": {
    "iso:country":"NL",
    "sg:address":"Grt Sloot 356",
    "sg:city":"Schagerbrug",
    "sg:orig_category":"Autorijscholen",
    "sg:phone":"+31 224 571 466",
    "sg:postcode":"1751 LL",
    "sg:province":"Noord-Holland",
    "sg:website":"http://www.wilkuit.nl",
    "wof:name":"Kuit, Wil",
    "wof:placetype":"venue"
},
  "geometry": {"coordinates":[4.760099,52.802349],"type":"Point"}
}