{
  "type": "Feature",
  "properties": {
    "addr:full":"Engelenkampstr 86 Sittard Limburg 6131 JJ",
    "addr:housenumber":"86",
    "addr:postcode":"6131 jj",
    "addr:street":"Engelenkampstr",
    "iso:country":"NL",
    "sg:address":"Engelenkampstr 86",
    "sg:city":"Sittard",
    "sg:orig_category":"Adviesbureaus Bedrijfsorganisatie",
    "sg:phone":"+31 46 420 6630",
    "sg:postcode":"6131 JJ",
    "sg:province":"Limburg",
    "wof:name":"Bude Bv",
    "wof:placetype":"venue"
},
  "geometry": {"coordinates":[5.864729,50.997128],"type":"Point"}
}