{
  "type": "Feature",
  "properties": {
    "addr:full":"Binnenweg 206-208 Heemstede Noord-Holland 2101 JT",
    "addr:housenumber":"206-208",
    "addr:postcode":"2101 jt",
    "addr:street":"Binnenweg",
    "iso:country":"NL",
    "sg:address":"Binnenweg 206-208",
    "sg:city":"Heemstede",
    "sg:orig_category":"Apothekers",
    "sg:phone":"+31 23 528 8252",
    "sg:postcode":"2101 JT",
    "sg:province":"Noord-Holland",
    "wof:name":"Bronstee Apotheek",
    "wof:placetype":"venue"
},
  "geometry": {"coordinates":[4.6219,52.356445],"type":"Point"}
}