{
  "type": "Feature",
  "properties": {
    "iso:country":"NL",
    "sg:address":"C Stulemeyerwg 2",
    "sg:city":"Tilburg",
    "sg:orig_category":"Postorderbedrijven",
    "sg:phone":"+31 13 466 6666",
    "sg:postcode":"5026 RT",
    "sg:province":"Noord-Brabant",
    "wof:name":"Otto Bv",
    "wof:placetype":"venue"
},
  "geometry": {"coordinates":[5.0607700348,51.5383605957],"type":"Point"}
}