{
  "type": "Feature",
  "properties": {
    "addr:full":"Hertoginnelaan 10 Appingedam Groningen 9901 HV",
    "addr:housenumber":"10",
    "addr:postcode":"9901 hv",
    "addr:street":"Hertoginnelaan",
    "iso:country":"NL",
    "sg:address":"Hertoginnelaan 10",
    "sg:city":"Appingedam",
    "sg:orig_category":"Boekhouders",
    "sg:phone":"+31 596 626 057",
    "sg:postcode":"9901 HV",
    "sg:province":"Groningen",
    "wof:name":"Administratiekantoor Quaedackers",
    "wof:placetype":"venue"
},
  "geometry": {"coordinates":[6.841482,53.32217],"type":"Point"}
}