{
  "type": "Feature",
  "properties": {
    "addr:full":"J Aartestr 31 Tilburg North Brabant 5017 EC",
    "addr:housenumber":"31",
    "addr:postcode":"5017 ec",
    "iso:country":"NL",
    "sg:address":"J Aartestr 31",
    "sg:city":"Tilburg",
    "sg:orig_category":"Bakkerijmachines En -Gereedschappen",
    "sg:phone":"+31 13 581 0015",
    "sg:postcode":"5017 EC",
    "sg:province":"North Brabant",
    "wof:name":"Mazzeltov Int Bv",
    "wof:placetype":"venue"
},
  "geometry": {"coordinates":[5.091852,51.556072],"type":"Point"}
}