{
  "type": "Feature",
  "properties": {
    "addr:full":"Kapelstr 5 Wageningen Gelderland 6701 DD",
    "addr:housenumber":"5",
    "addr:postcode":"6701 dd",
    "addr:street":"Kapelstr;Gelderland",
    "iso:country":"NL",
    "sg:address":"Kapelstr 5",
    "sg:city":"Wageningen",
    "sg:orig_category":"Geschenkartikelen",
    "sg:phone":"+31 317 411 928",
    "sg:postcode":"6701 DD",
    "sg:province":"Gelderland",
    "wof:name":"Split Level",
    "wof:placetype":"venue"
},
  "geometry": {"coordinates":[5.66341,51.965477],"type":"Point"}
}