{
  "type": "Feature",
  "properties": {
    "addr:full":"Broekwg 3 Leersum Utrecht 3956 NE",
    "addr:housenumber":"3",
    "addr:postcode":"3956 ne",
    "addr:street":"Broekwg",
    "iso:country":"NL",
    "sg:address":"Broekwg 3",
    "sg:city":"Leersum",
    "sg:orig_category":"Bloemen En Planten - Verhuur",
    "sg:phone":"+31 343 473 777",
    "sg:postcode":"3956 NE",
    "sg:province":"Utrecht",
    "sg:website":"http://www.oase-lease.nl",
    "wof:name":"Darthuizer Oase Lease",
    "wof:placetype":"venue"
},
  "geometry": {"coordinates":[5.380368,52.014946],"type":"Point"}
}