{
  "type": "Feature",
  "properties": {
    "addr:full":"Sluisoordlaan 311 Apeldoorn Gelderland 7323 EN",
    "addr:housenumber":"311",
    "addr:postcode":"7323 en",
    "addr:street":"Sluisoordlaan;Gelderland",
    "iso:country":"NL",
    "sg:address":"Sluisoordlaan 311",
    "sg:city":"Apeldoorn",
    "sg:orig_category":"Paramedische Behandelingen",
    "sg:phone":"+31 55 366 7521",
    "sg:postcode":"7323 EN",
    "sg:province":"Gelderland",
    "wof:name":"Logopedie A. Naarding-Schippers",
    "wof:placetype":"venue"
},
  "geometry": {"coordinates":[5.988674,52.230148],"type":"Point"}
}