{
  "type": "Feature",
  "properties": {
    "addr:full":"Zweilandln 4 Leiden Zuid-Holland 2334 CS",
    "addr:housenumber":"4",
    "addr:postcode":"2334 cs",
    "addr:street":"Zweilandln",
    "iso:country":"NL",
    "sg:address":"Zweilandln 4",
    "sg:city":"Leiden",
    "sg:orig_category":"Fitnesscentra",
    "sg:phone":"+31 71 517 6204",
    "sg:postcode":"2334 CS",
    "sg:province":"Zuid-Holland",
    "wof:name":"Zweiland Sportcentrum",
    "wof:placetype":"venue"
},
  "geometry": {"coordinates":[4.485544,52.173344],"type":"Point"}
}