{
  "type": "Feature",
  "properties": {
    "iso:country":"NL",
    "sg:address":"Industriewg 6",
    "sg:city":"Oost W Middelbeers",
    "sg:classifiers":[
        {
            "category":"Manufacturing",
            "subcategory":"Motor Vehicles & Parts",
            "type":"Manufacturing & Wholesale Goods"
        }
    ],
    "sg:phone":"+31 13 514 1140",
    "sg:postcode":"5091 BG",
    "sg:province":"Noord-Brabant",
    "sg:tags":[
        "verhuur",
        "scooter",
        "en",
        "-"
    ],
    "sg:website":"http://www.motopoint.nl",
    "wof:name":"Moto-Point Rentals",
    "wof:placetype":"venue"
},
  "geometry": {"coordinates":[25.9494,43.04475],"type":"Point"}
}