{
  "type": "Feature",
  "properties": {
    "addr:full":"Roerstraat 14 Amersfoort Utrecht 3812 EX",
    "addr:housenumber":"14",
    "addr:postcode":"3812 ex",
    "addr:street":"Roerstraat",
    "iso:country":"NL",
    "sg:address":"Roerstraat 14",
    "sg:city":"Amersfoort",
    "sg:orig_category":"Wegen And Sportterreinen",
    "sg:phone":"+31 33 463 5451",
    "sg:postcode":"3812 EX",
    "sg:province":"Utrecht",
    "wof:name":"Bestratingen Alex Van Der Blom",
    "wof:placetype":"venue"
},
  "geometry": {"coordinates":[5.370871067,52.1595230103],"type":"Point"}
}