{
  "type": "Feature",
  "properties": {
    "addr:full":"Burgtakkerdreef 104 Oisterwyk Noord-Brabant 5061 XK",
    "addr:housenumber":"104",
    "addr:postcode":"5061 xk",
    "addr:street":"Burgtakkerdreef",
    "iso:country":"NL",
    "sg:address":"Burgtakkerdreef 104",
    "sg:city":"Oisterwyk",
    "sg:orig_category":"Koeriersdiensten",
    "sg:phone":"+31 13 528 5873",
    "sg:postcode":"5061 XK",
    "sg:province":"Noord-Brabant",
    "wof:name":"B C O",
    "wof:placetype":"venue"
},
  "geometry": {"coordinates":[5.208147,51.583233],"type":"Point"}
}