{
  "type": "Feature",
  "properties": {
    "addr:full":"Keer Weer 17 Zoeterwoude Zuid-Holland 2381 GC",
    "addr:housenumber":"17",
    "addr:postcode":"2381 gc",
    "addr:street":"Weer",
    "iso:country":"NL",
    "sg:address":"Keer Weer 17",
    "sg:city":"Zoeterwoude",
    "sg:orig_category":"Touringcars",
    "sg:phone":"+31 71 580 1459",
    "sg:postcode":"2381 GC",
    "sg:province":"Zuid-Holland",
    "wof:name":"Lubbe Bv, T H",
    "wof:placetype":"venue"
},
  "geometry": {"coordinates":[4.497263,52.127106],"type":"Point"}
}