{
  "type": "Feature",
  "properties": {
    "addr:full":"Lijkweg 25 Groessen Gelderland 6923 CB",
    "addr:housenumber":"25",
    "addr:postcode":"6923 cb",
    "addr:street":"Lijkweg;Gelderland",
    "iso:country":"NL",
    "sg:address":"Lijkweg 25",
    "sg:city":"Groessen",
    "sg:orig_category":"Fietshandelaren",
    "sg:phone":"+31 316 332 818",
    "sg:postcode":"6923 CB",
    "sg:province":"Gelderland",
    "wof:name":"Witjes Rijwielhandel",
    "wof:placetype":"venue"
},
  "geometry": {"coordinates":[6.007532,51.924732],"type":"Point"}
}