{
  "type": "Feature",
  "properties": {
    "addr:full":"Bronkhorststr 2 Steenbergen Nb Noord-Brabant 4651 SZ",
    "addr:housenumber":"2",
    "addr:postcode":"4651 sz",
    "addr:street":"Bronkhorststr",
    "iso:country":"NL",
    "sg:address":"Bronkhorststr 2",
    "sg:city":"Steenbergen Nb",
    "sg:classifiers":[
        {
            "category":"Wholesale",
            "subcategory":"Meat",
            "type":"Manufacturing & Wholesale Goods"
        }
    ],
    "sg:phone":"+31 167 562 550",
    "sg:postcode":"4651 SZ",
    "sg:province":"Noord-Brabant",
    "sg:tags":[
        "regeltechniek",
        "en",
        "meet-"
    ],
    "wof:name":"Metatemp Vof",
    "wof:placetype":"venue"
},
  "geometry": {"coordinates":[4.308382,51.590244],"type":"Point"}
}