{
  "type": "Feature",
  "properties": {
    "addr:full":"Maanlanderhof 12 Ijsselstein Ut Utrecht 3402 ZW",
    "addr:housenumber":"12",
    "addr:postcode":"3402 zw",
    "addr:street":"Maanlanderhof",
    "iso:country":"NL",
    "sg:address":"Maanlanderhof 12",
    "sg:city":"Ijsselstein Ut",
    "sg:orig_category":"Verzekeringen",
    "sg:phone":"+31 30 688 3316",
    "sg:postcode":"3402 ZW",
    "sg:province":"Utrecht",
    "wof:name":"Assurantiekantoor K.J. Zomer",
    "wof:placetype":"venue"
},
  "geometry": {"coordinates":[5.055514,52.027794],"type":"Point"}
}