{
  "type": "Feature",
  "properties": {
    "addr:full":"Hoogstr 16 Hasselt Overijssel 8061 HC",
    "addr:housenumber":"16",
    "addr:postcode":"8061 hc",
    "addr:street":"Hoogstr",
    "iso:country":"NL",
    "sg:address":"Hoogstr 16",
    "sg:city":"Hasselt",
    "sg:orig_category":"Woninginrichting",
    "sg:phone":"+31 38 477 4409",
    "sg:postcode":"8061 HC",
    "sg:province":"Overijssel",
    "wof:name":"De Stenen Dijk",
    "wof:placetype":"venue"
},
  "geometry": {"coordinates":[6.0887050629,52.5914840698],"type":"Point"}
}