{
  "type": "Feature",
  "properties": {
    "addr:full":"Breitnerlaan 146 'S Gravenhage South Holland 2596 HG",
    "addr:housenumber":"146 '",
    "addr:postcode":"2596 hg",
    "addr:street":"Breitnerlaan",
    "iso:country":"NL",
    "sg:address":"Breitnerlaan 146",
    "sg:city":"'S Gravenhage",
    "sg:orig_category":"Vertaal- And Tolkenbureaus",
    "sg:phone":"+31 70 324 2623",
    "sg:postcode":"2596 HG",
    "sg:province":"South Holland",
    "wof:name":"Hapat International Bv",
    "wof:placetype":"venue"
},
  "geometry": {"coordinates":[4.32785,52.0938],"type":"Point"}
}