{
  "type": "Feature",
  "properties": {
    "addr:full":"Gruttostr 12 Odiliapeel North Brabant 5409 AM",
    "addr:housenumber":"12",
    "addr:postcode":"5409",
    "addr:street":"Gruttostr",
    "iso:country":"NL",
    "sg:address":"Gruttostr 12",
    "sg:city":"Odiliapeel",
    "sg:orig_category":"Autorijscholen",
    "sg:phone":"+31 413 275 880",
    "sg:postcode":"5409 AM",
    "sg:province":"North Brabant",
    "sg:website":"http://www.autorijschoolvansleuwen.nl",
    "wof:name":"Sleuwen, Van",
    "wof:placetype":"venue"
},
  "geometry": {"coordinates":[5.70161,51.642601],"type":"Point"}
}