{
  "type": "Feature",
  "properties": {
    "iso:country":"NL",
    "sg:address":"Poppenhareln 10",
    "sg:city":"Coevorden",
    "sg:orig_category":"Artsen - Huisartsen",
    "sg:phone":"+31 524 512 772",
    "sg:postcode":"7741 CS",
    "sg:province":"Drenthe",
    "wof:name":"Koelemeijer & B G J Geertjes, H W",
    "wof:placetype":"venue"
},
  "geometry": {"coordinates":[6.743673,52.667439],"type":"Point"}
}