{
  "type": "Feature",
  "properties": {
    "iso:country":"NL",
    "sg:address":"Rederserf 10",
    "sg:city":"'S Gravenhage",
    "sg:orig_category":"Verzekeringen",
    "sg:phone":"+31 70 352 2788",
    "sg:postcode":"2586 KA",
    "sg:province":"South Holland",
    "wof:name":"Ass & Adv Kant W C Groot",
    "wof:placetype":"venue"
},
  "geometry": {"coordinates":[4.279242,52.111809],"type":"Point"}
}