{
  "type": "Feature",
  "properties": {
    "addr:full":"L Voorhout 61 S Gravenhage Zuid-Holland 2514 EC",
    "addr:housenumber":"61;gravenhage",
    "addr:postcode":"2514 ec",
    "addr:street":"L Voorhout;S",
    "iso:country":"NL",
    "sg:address":"L Voorhout 61",
    "sg:city":"S Gravenhage",
    "sg:orig_category":"Beveiliging",
    "sg:phone":"+31 70 361 4042",
    "sg:postcode":"2514 EC",
    "sg:province":"Zuid-Holland",
    "sg:website":"http://www.secad.com",
    "wof:name":"Secad Bv",
    "wof:placetype":"venue"
},
  "geometry": {"coordinates":[4.30935,52.084148],"type":"Point"}
}