{
  "type": "Feature",
  "properties": {
    "addr:full":"Lagendk 184 Ridderkerk Zuid-Holland 2988 AD",
    "addr:housenumber":"184",
    "addr:postcode":"2988 ad",
    "iso:country":"NL",
    "sg:address":"Lagendk 184",
    "sg:city":"Ridderkerk",
    "sg:orig_category":"Betonwerken",
    "sg:phone":"+31 6 53545115",
    "sg:postcode":"2988 AD",
    "sg:province":"Zuid-Holland",
    "wof:name":"Bildig Technologies",
    "wof:placetype":"venue"
},
  "geometry": {"coordinates":[4.585909,51.854805],"type":"Point"}
}