{
  "type": "Feature",
  "properties": {
    "addr:full":"Sibeliusstraat 1 Culemborg Gelderland 4102 AZ",
    "addr:housenumber":"1",
    "addr:postcode":"4102",
    "addr:street":"Sibeliusstraat;Gelderland",
    "iso:country":"NL",
    "sg:address":"Sibeliusstraat 1",
    "sg:city":"Culemborg",
    "sg:orig_category":"Boekhouders",
    "sg:phone":"+31 345 514 627",
    "sg:postcode":"4102 AZ",
    "sg:province":"Gelderland",
    "wof:name":"A.B.Boeschoten",
    "wof:placetype":"venue"
},
  "geometry": {"coordinates":[5.232839,51.952564],"type":"Point"}
}