{
  "type": "Feature",
  "properties": {
    "iso:country":"NL",
    "sg:address":"Meerkoetln 6",
    "sg:city":"Appingedam",
    "sg:orig_category":"Woningstoffeerders",
    "sg:phone":"+31 596 623 773",
    "sg:postcode":"9903 EP",
    "sg:province":"Groningen",
    "wof:name":"Ivi",
    "wof:placetype":"venue"
},
  "geometry": {"coordinates":[6.8578882217,53.322593689],"type":"Point"}
}