{
  "type": "Feature",
  "properties": {
    "addr:full":"De Alblashof 1 Alblasserdam Zuid-Holland 2951 XR",
    "addr:housenumber":"1",
    "addr:postcode":"2951 xr",
    "addr:street":"De Alblashof",
    "iso:country":"NL",
    "sg:address":"De Alblashof 1",
    "sg:city":"Alblasserdam",
    "sg:orig_category":"Hulpverlening Sociaal",
    "sg:phone":"+31 78 692 1611",
    "sg:postcode":"2951 XR",
    "sg:province":"Zuid-Holland",
    "wof:name":"Sociale Raadslieden, Bur",
    "wof:placetype":"venue"
},
  "geometry": {"coordinates":[4.665283,51.867119],"type":"Point"}
}