{
  "type": "Feature",
  "properties": {
    "addr:full":"Maliestraat 3 'S Gravenhage Zuid-Holland 2514 CA",
    "addr:housenumber":"3 '",
    "addr:postcode":"2514 ca",
    "addr:street":"Maliestraat",
    "iso:country":"NL",
    "sg:address":"Maliestraat 3",
    "sg:city":"'S Gravenhage",
    "sg:orig_category":"Kappers",
    "sg:phone":"+31 70 427 2060",
    "sg:postcode":"2514 CA",
    "sg:province":"Zuid-Holland",
    "wof:name":"Kapsalon Tati",
    "wof:placetype":"venue"
},
  "geometry": {"coordinates":[4.3137331009,52.084274292],"type":"Point"}
}