{
  "type": "Feature",
  "properties": {
    "addr:full":"Reijmerstokkerdorpsstr 130 Reijmerstok Limburg 6274 NN",
    "addr:housenumber":"130",
    "addr:postcode":"6274 nn",
    "iso:country":"NL",
    "sg:address":"Reijmerstokkerdorpsstr 130",
    "sg:city":"Reijmerstok",
    "sg:orig_category":"Kampeerterreinen",
    "sg:phone":"+31 43 457 1326",
    "sg:postcode":"6274 NN",
    "sg:province":"Limburg",
    "wof:name":"De Puthof",
    "wof:placetype":"venue"
},
  "geometry": {"coordinates":[5.8363471031,50.7972564697],"type":"Point"}
}