{
  "type": "Feature",
  "properties": {
    "addr:full":"Gr Waltgerln 2 Tiel Gelderland 4001 KG",
    "addr:housenumber":"2",
    "addr:postcode":"4001 kg",
    "addr:street":"Gelderland",
    "iso:country":"NL",
    "sg:address":"Gr Waltgerln 2",
    "sg:city":"Tiel",
    "sg:orig_category":"Biljartzalen",
    "sg:phone":"+31 344 618 999",
    "sg:postcode":"4001 KG",
    "sg:province":"Gelderland",
    "wof:name":"Manhattan",
    "wof:placetype":"venue"
},
  "geometry": {"coordinates":[5.430696,51.888096],"type":"Point"}
}