{
  "type": "Feature",
  "properties": {
    "iso:country":"NL",
    "sg:address":"Jutfaasstr 5",
    "sg:city":"S Gravenhage",
    "sg:classifiers":[
        {
            "category":"Food & Beverages",
            "subcategory":"Bakery",
            "type":"Retail Goods"
        }
    ],
    "sg:phone":"+31 70 329 4061",
    "sg:postcode":"2546 XZ",
    "sg:province":"Zuid-Holland",
    "sg:tags":[
        "brood",
        "en",
        "banket"
    ],
    "wof:name":"Steijger Bv, A",
    "wof:placetype":"venue"
},
  "geometry": {"coordinates":[4.274271,52.058716],"type":"Point"}
}