{
  "type": "Feature",
  "properties": {
    "addr:full":"Ryksstrwg 111 Sleeuwyk Noord-Brabant 4254 XC",
    "addr:housenumber":"111",
    "addr:postcode":"4254 xc",
    "addr:street":"Sleeuwyk",
    "iso:country":"NL",
    "sg:address":"Ryksstrwg 111",
    "sg:city":"Sleeuwyk",
    "sg:orig_category":"Houtindustrie",
    "sg:phone":"+31 183 301 733",
    "sg:postcode":"4254 XC",
    "sg:province":"Noord-Brabant",
    "wof:name":"Brogorak",
    "wof:placetype":"venue"
},
  "geometry": {"coordinates":[4.950798,51.813931],"type":"Point"}
}