{
  "type": "Feature",
  "properties": {
    "addr:full":"Oud Camp 12 Maasland South Holland 3155 DL",
    "addr:housenumber":"12",
    "addr:postcode":"3155 dl",
    "addr:street":"Oud Camp",
    "iso:country":"NL",
    "sg:address":"Oud Camp 12",
    "sg:city":"Maasland",
    "sg:orig_category":"Plafonds",
    "sg:phone":"+31 174 523 475",
    "sg:postcode":"3155 DL",
    "sg:province":"South Holland",
    "wof:name":"Baan & Warnaar Bv, De",
    "wof:placetype":"venue"
},
  "geometry": {"coordinates":[4.239357,51.954605],"type":"Point"}
}