{
  "type": "Feature",
  "properties": {
    "addr:full":"Gasthuisstr 29 Gorinchem South Holland 4201 JN",
    "addr:housenumber":"29",
    "addr:postcode":"4201 jn",
    "addr:street":"Gasthuisstr",
    "iso:country":"NL",
    "sg:address":"Gasthuisstr 29",
    "sg:city":"Gorinchem",
    "sg:orig_category":"Kaas",
    "sg:phone":"+31 183 636 926",
    "sg:postcode":"4201 JN",
    "sg:province":"South Holland",
    "wof:name":"Besten Bv, Den",
    "wof:placetype":"venue"
},
  "geometry": {"coordinates":[4.9740481377,51.8302993774],"type":"Point"}
}