{
  "type": "Feature",
  "properties": {
    "iso:country":"NL",
    "sg:address":"Skagerrak 210",
    "sg:city":"Hoofddorp",
    "sg:orig_category":"Postkantoren",
    "sg:phone":"+31 23 563 1305",
    "sg:postcode":"2133 DW",
    "sg:province":"Noord-Holland",
    "sg:website":"http://www.postkantoor.nl",
    "wof:name":"Postkantoor",
    "wof:placetype":"venue"
},
  "geometry": {"coordinates":[4.671735,52.309765],"type":"Point"}
}