{
  "type": "Feature",
  "properties": {
    "addr:full":"Noord Buitensingel 1 Venlo Limburg 5911 EL",
    "addr:housenumber":"1",
    "addr:postcode":"5911 el",
    "addr:street":"Noord Buitensingel",
    "iso:country":"NL",
    "sg:address":"Noord Buitensingel 1",
    "sg:city":"Venlo",
    "sg:orig_category":"Verlichting And Huishoudartikelen",
    "sg:phone":"+31 77 351 3522",
    "sg:postcode":"5911 EL",
    "sg:province":"Limburg",
    "wof:name":"Venlo Licht",
    "wof:placetype":"venue"
},
  "geometry": {"coordinates":[6.173021,51.373463],"type":"Point"}
}