{
  "type": "Feature",
  "properties": {
    "iso:country":"NL",
    "sg:address":"Kaasmarkt 16",
    "sg:city":"Purmerend",
    "sg:orig_category":"Organisaties And Verenigingen",
    "sg:phone":"+31 299 422 605",
    "sg:postcode":"1441 BG",
    "sg:province":"Noord-Holland",
    "wof:name":"Museum Waterland",
    "wof:placetype":"venue"
},
  "geometry": {"coordinates":[4.9465689659,52.5097503662],"type":"Point"}
}