{
  "type": "Feature",
  "properties": {
    "addr:full":"Uiverstr 39 Oldenzaal Overijssel 7574 BA",
    "addr:housenumber":"39",
    "addr:postcode":"7574 ba",
    "addr:street":"Uiverstr",
    "iso:country":"NL",
    "sg:address":"Uiverstr 39",
    "sg:city":"Oldenzaal",
    "sg:orig_category":"Schoonheidsinstituten",
    "sg:phone":"+31 541 538 153",
    "sg:postcode":"7574 BA",
    "sg:province":"Overijssel",
    "sg:website":"http://www.salonwendy.nl",
    "wof:name":"Wendy",
    "wof:placetype":"venue"
},
  "geometry": {"coordinates":[6.93817,52.299294],"type":"Point"}
}