{
  "type": "Feature",
  "properties": {
    "addr:full":"Schoutln 2 Weert Limburg 6002 EA",
    "addr:housenumber":"2",
    "addr:postcode":"6002 ea",
    "addr:street":"Schoutln",
    "iso:country":"NL",
    "sg:address":"Schoutln 2",
    "sg:city":"Weert",
    "sg:orig_category":"Accountants - Administratie- Consulenten En -Kantoren",
    "sg:phone":"+31 46 420 7500",
    "sg:postcode":"6002 EA",
    "sg:province":"Limburg",
    "sg:website":"http://www.aagroep.nl",
    "wof:name":"A & A Groep",
    "wof:placetype":"venue"
},
  "geometry": {"coordinates":[5.703781,51.255016],"type":"Point"}
}