{
  "type": "Feature",
  "properties": {
    "addr:full":"Kleine Gracht 30 Hattem Gelderland 8051 VK",
    "addr:housenumber":"30",
    "addr:postcode":"8051 vk",
    "addr:street":"Kleine Gracht;Gelderland",
    "iso:country":"NL",
    "sg:address":"Kleine Gracht 30",
    "sg:city":"Hattem",
    "sg:orig_category":"Bloemen And Planten",
    "sg:phone":"+31 38 444 5920",
    "sg:postcode":"8051 VK",
    "sg:province":"Gelderland",
    "wof:name":"Bloemenshop Blok",
    "wof:placetype":"venue"
},
  "geometry": {"coordinates":[6.065333,52.475342],"type":"Point"}
}