{
  "type": "Feature",
  "properties": {
    "iso:country":"NL",
    "sg:address":"Essenstr 23",
    "sg:city":"Deventer",
    "sg:orig_category":"Woninginrichting",
    "sg:phone":"+31 570 503 950",
    "sg:postcode":"7418 BM",
    "sg:province":"Overijssel",
    "wof:name":"Morres Bv",
    "wof:placetype":"venue"
},
  "geometry": {"coordinates":[6.1956019402,52.2470817566],"type":"Point"}
}