{
  "type": "Feature",
  "properties": {
    "addr:full":"Spoorlaan 328 Tilburg North Brabant 5038 CC",
    "addr:housenumber":"328",
    "addr:postcode":"5038 cc",
    "addr:street":"Spoorlaan",
    "iso:country":"NL",
    "sg:address":"Spoorlaan 328",
    "sg:city":"Tilburg",
    "sg:orig_category":"Public Relationbureaus",
    "sg:phone":"+31 13 542 7675",
    "sg:postcode":"5038 CC",
    "sg:province":"North Brabant",
    "wof:name":"Mercuur Communicatie-Adviesbureau",
    "wof:placetype":"venue"
},
  "geometry": {"coordinates":[5.089938,51.55949],"type":"Point"}
}