{
  "type": "Feature",
  "properties": {
    "addr:full":"De Goorn 53 De Goorn North Holland 1648 JR",
    "addr:housenumber":"53",
    "addr:postcode":"1648 jr",
    "addr:street":"De Goorn",
    "iso:country":"NL",
    "sg:address":"De Goorn 53",
    "sg:city":"De Goorn",
    "sg:orig_category":"Banken And Kredietinstellingen",
    "sg:phone":"+31 229 543 894",
    "sg:postcode":"1648 JR",
    "sg:province":"North Holland",
    "wof:name":"Postagentschap De Goorn",
    "wof:placetype":"venue"
},
  "geometry": {"coordinates":[4.945549,52.627331],"type":"Point"}
}