{
  "type": "Feature",
  "properties": {
    "iso:country":"NL",
    "sg:address":"Azielaan 322",
    "sg:city":"Utrecht",
    "sg:orig_category":"Bedrijfs- And Managementsconsultants",
    "sg:phone":"+31 30 289 6130",
    "sg:postcode":"3526 SK",
    "sg:province":"Utrecht",
    "wof:name":"Van Sterkenburg Consultancy",
    "wof:placetype":"venue"
},
  "geometry": {"coordinates":[5.104547,52.065926],"type":"Point"}
}