{
  "type": "Feature",
  "properties": {
    "addr:full":"Fivelingo 125 Utrecht Utrecht 3524 BK",
    "addr:housenumber":"125",
    "addr:postcode":"3524 bk",
    "addr:street":"Fivelingo",
    "iso:country":"NL",
    "sg:address":"Fivelingo 125",
    "sg:city":"Utrecht",
    "sg:orig_category":"Boekenuitgeverijen",
    "sg:phone":"+31 30 288 3163",
    "sg:postcode":"3524 BK",
    "sg:province":"Utrecht",
    "wof:name":"Cartofantasy",
    "wof:placetype":"venue"
},
  "geometry": {"coordinates":[5.140033,52.066547],"type":"Point"}
}