{
  "type": "Feature",
  "properties": {
    "iso:country":"NL",
    "sg:address":"Ganzenzyde 7",
    "sg:city":"Leiden",
    "sg:orig_category":"Wegenbouw",
    "sg:phone":"+31 71 523 3002",
    "sg:postcode":"2317 XG",
    "sg:province":"Zuid-Holland",
    "wof:name":"Via Petri",
    "wof:placetype":"venue"
},
  "geometry": {"coordinates":[4.5161747932,52.1801834106],"type":"Point"}
}