{
  "type": "Feature",
  "properties": {
    "addr:full":"Ertveldweg 31 'S Hertogenbosch North Brabant 5231 XA",
    "addr:housenumber":"31",
    "addr:postcode":"5231 xa",
    "addr:street":"Ertveldweg;' S Hertogenbosch",
    "iso:country":"NL",
    "sg:address":"Ertveldweg 31",
    "sg:city":"'S Hertogenbosch",
    "sg:orig_category":"Wegen And Sportterreinen",
    "sg:phone":"+31 73 648 4111",
    "sg:postcode":"5231 XA",
    "sg:province":"North Brabant",
    "wof:name":"Heijmans Wegen- En Verkeerstechnieken Bv",
    "wof:placetype":"venue"
},
  "geometry": {"coordinates":[5.2978038788,51.7028274536],"type":"Point"}
}