{
  "type": "Feature",
  "properties": {
    "iso:country":"NL",
    "sg:address":"Electronweg 1",
    "sg:city":"Hoorn Nh",
    "sg:orig_category":"Huishoudapparatuur, Televisies And Radio'S",
    "sg:phone":"+31 229 281 200",
    "sg:postcode":"1627 LB",
    "sg:province":"Noord-Holland",
    "wof:name":"Stago Bv",
    "wof:placetype":"venue"
},
  "geometry": {"coordinates":[5.098688,52.645023],"type":"Point"}
}