{
  "type": "Feature",
  "properties": {
    "addr:full":"Slingerduinln 4 Ymuiden Noord-Holland 1971 JT",
    "addr:housenumber":"4",
    "addr:postcode":"1971 jt",
    "addr:street":"Slingerduinln",
    "iso:country":"NL",
    "sg:address":"Slingerduinln 4",
    "sg:city":"Ymuiden",
    "sg:orig_category":"Begraafplaatsen",
    "sg:phone":"+31 255 515 778",
    "sg:postcode":"1971 JT",
    "sg:province":"Noord-Holland",
    "wof:name":"Duinhof, Alg Begraafplaats",
    "wof:placetype":"venue"
},
  "geometry": {"coordinates":[4.622616,52.446404],"type":"Point"}
}