{
  "type": "Feature",
  "properties": {
    "addr:full":"Jan Van Riebeecklaan 61 Gouda Zuid-Holland 2803 WS",
    "addr:housenumber":"61",
    "addr:postcode":"2803 ws",
    "addr:street":"Jan Van Riebeecklaan",
    "iso:country":"NL",
    "sg:address":"Jan Van Riebeecklaan 61",
    "sg:city":"Gouda",
    "sg:orig_category":"Diverse Consumentenartikelen Gh",
    "sg:phone":"+31 182 535 620",
    "sg:postcode":"2803 WS",
    "sg:province":"Zuid-Holland",
    "wof:name":"Eur As Trading House Bv",
    "wof:placetype":"venue"
},
  "geometry": {"coordinates":[4.694399,52.020908],"type":"Point"}
}