{
  "type": "Feature",
  "properties": {
    "addr:full":"Loveren 24 Westerhoven North Brabant 5563 AD",
    "addr:housenumber":"24",
    "addr:postcode":"5563 ad",
    "addr:street":"Loveren",
    "iso:country":"NL",
    "sg:address":"Loveren 24",
    "sg:city":"Westerhoven",
    "sg:orig_category":"Verhuur",
    "sg:phone":"+31 40 204 0074",
    "sg:postcode":"5563 AD",
    "sg:province":"North Brabant",
    "wof:name":"Loomans Vof",
    "wof:placetype":"venue"
},
  "geometry": {"coordinates":[5.410193,51.337067],"type":"Point"}
}