{
  "type": "Feature",
  "properties": {
    "addr:full":"Graafpad 7 Almere Flevoland 1312 AS",
    "addr:housenumber":"7",
    "addr:postcode":"1312 as",
    "addr:street":"Graafpad;Flevoland",
    "iso:country":"NL",
    "sg:address":"Graafpad 7",
    "sg:city":"Almere",
    "sg:orig_category":"Adviesbureaus Bouwkunde",
    "sg:phone":"+31 36 844 8346",
    "sg:postcode":"1312 AS",
    "sg:province":"Flevoland",
    "sg:website":"http://www.asdesign.nl",
    "wof:name":"A & S Design",
    "wof:placetype":"venue"
},
  "geometry": {"coordinates":[5.209875,52.375477],"type":"Point"}
}