{
  "type": "Feature",
  "properties": {
    "addr:full":"De Meeren 189 Zevenbergen Noord-Brabant 4761 SH",
    "addr:housenumber":"189",
    "addr:postcode":"4761 sh",
    "addr:street":"De Meeren",
    "iso:country":"NL",
    "sg:address":"De Meeren 189",
    "sg:city":"Zevenbergen",
    "sg:orig_category":"Boekhouders",
    "sg:phone":"+31 168 329 097",
    "sg:postcode":"4761 SH",
    "sg:province":"Noord-Brabant",
    "wof:name":"Aktiva Administratie",
    "wof:placetype":"venue"
},
  "geometry": {"coordinates":[4.591199,51.649326],"type":"Point"}
}