{
  "type": "Feature",
  "properties": {
    "iso:country":"NL",
    "sg:address":"Smedestr 24",
    "sg:city":"Elburg",
    "sg:orig_category":"Kappers",
    "sg:phone":"+31 525 680 321",
    "sg:postcode":"8081 EH",
    "sg:province":"Gelderland",
    "wof:name":"Raisha Haar Plezier",
    "wof:placetype":"venue"
},
  "geometry": {"coordinates":[5.831901,52.448391],"type":"Point"}
}