{
  "type": "Feature",
  "properties": {
    "addr:full":"Kolkweiden 2 Wijhe NL.08 8131 WE",
    "addr:housenumber":"2;nl.08",
    "addr:postcode":"8131 we",
    "addr:street":"Kolkweiden",
    "iso:country":"NL",
    "sg:address":"Kolkweiden 2",
    "sg:city":"Wijhe",
    "sg:classifiers":[
        {
            "category":"Education",
            "subcategory":"Preschool",
            "type":"Public Place"
        }
    ],
    "sg:phone":"+31 570 522 377",
    "sg:postcode":"8131 WE",
    "sg:province":"NL.08",
    "sg:tags":[
        "kleuteronderwijs",
        "basis-"
    ],
    "wof:name":"De Peperhof",
    "wof:placetype":"venue"
},
  "geometry": {"coordinates":[6.139379,52.381702],"type":"Point"}
}