{
  "type": "Feature",
  "properties": {
    "addr:full":"Hogeweg 85 Venlo Limburg 5914 BC",
    "addr:housenumber":"85",
    "addr:postcode":"5914 bc",
    "addr:street":"Hogeweg",
    "iso:country":"NL",
    "sg:address":"Hogeweg 85",
    "sg:city":"Venlo",
    "sg:orig_category":"Overheidsdiensten",
    "sg:phone":"+31 77 321 5000",
    "sg:postcode":"5914 BC",
    "sg:province":"Limburg",
    "wof:name":"Belastingdienst Particulieren Ondernemingen Venlo",
    "wof:placetype":"venue"
},
  "geometry": {"coordinates":[6.1736798286,51.3769073486],"type":"Point"}
}