{
  "type": "Feature",
  "properties": {
    "addr:full":"Tulpenstraat 39 Meppel Drenthe 7943 AN",
    "addr:housenumber":"39",
    "addr:postcode":"7943 an",
    "addr:street":"Tulpenstraat",
    "iso:country":"NL",
    "sg:address":"Tulpenstraat 39",
    "sg:city":"Meppel",
    "sg:orig_category":"Drukkerijen And Copyshops",
    "sg:phone":"+31 522 256 930",
    "sg:postcode":"7943 AN",
    "sg:province":"Drenthe",
    "wof:name":"R. Hagedoorn",
    "wof:placetype":"venue"
},
  "geometry": {"coordinates":[6.200303,52.691444],"type":"Point"}
}