{
  "type": "Feature",
  "properties": {
    "addr:full":"Energiewg 7 Hapert Noord-Brabant 5527 AH",
    "addr:housenumber":"7",
    "addr:postcode":"5527 ah",
    "addr:street":"Energiewg",
    "iso:country":"NL",
    "sg:address":"Energiewg 7",
    "sg:city":"Hapert",
    "sg:orig_category":"Graveerbedrijven",
    "sg:phone":"+31 497 384 252",
    "sg:postcode":"5527 AH",
    "sg:province":"Noord-Brabant",
    "sg:website":"http://www.graveertechnieken.nl",
    "wof:name":"Mook Graveertechnieken Bv, Van",
    "wof:placetype":"venue"
},
  "geometry": {"coordinates":[5.270093,51.37093],"type":"Point"}
}