{
  "type": "Feature",
  "properties": {
    "iso:country":"NL",
    "sg:address":"Lysterbesgaard 61",
    "sg:city":"Boxtel",
    "sg:orig_category":"Plafonds",
    "sg:phone":"+31 411 683 991",
    "sg:postcode":"5283 EZ",
    "sg:province":"Noord-Brabant",
    "wof:name":"Vb",
    "wof:placetype":"venue"
},
  "geometry": {"coordinates":[5.340766,51.590481],"type":"Point"}
}