{
  "type": "Feature",
  "properties": {
    "iso:country":"NL",
    "sg:address":"Chopinln 9",
    "sg:city":"Voorthuizen",
    "sg:classifiers":[
        {
            "category":"Personal",
            "subcategory":"Nail Salon",
            "type":"Services"
        }
    ],
    "sg:phone":"+31 342 491 515",
    "sg:postcode":"3781 HA",
    "sg:province":"Gelderland",
    "sg:tags":[
        "pedicure"
    ],
    "wof:name":"Voet-Fit",
    "wof:placetype":"venue"
},
  "geometry": {"coordinates":[5.602702,52.181076],"type":"Point"}
}