{
  "type": "Feature",
  "properties": {
    "addr:full":"Sportlaan 16 Heerjansdam South Holland 2995 VN",
    "addr:housenumber":"16",
    "addr:postcode":"2995 vn",
    "addr:street":"Sportlaan",
    "iso:country":"NL",
    "sg:address":"Sportlaan 16",
    "sg:city":"Heerjansdam",
    "sg:classifiers":[
        {
            "category":"Education",
            "subcategory":"Preschool",
            "type":"Public Place"
        }
    ],
    "sg:phone":"+31 78 677 2190",
    "sg:postcode":"2995 VN",
    "sg:province":"South Holland",
    "sg:tags":[
        "kleuteronderwijs",
        "basis-"
    ],
    "wof:name":"T Drempeltje",
    "wof:placetype":"venue"
},
  "geometry": {"coordinates":[4.566124,51.833893],"type":"Point"}
}