{
  "type": "Feature",
  "properties": {
    "addr:full":"Kruisweg 545 Hoofddorp Noord-Holland 2132 NA",
    "addr:housenumber":"545",
    "addr:postcode":"2132 na",
    "addr:street":"Kruisweg",
    "iso:country":"NL",
    "sg:address":"Kruisweg 545",
    "sg:city":"Hoofddorp",
    "sg:orig_category":"Goederenvervoer Over De Weg",
    "sg:phone":"+31 20 653 4534",
    "sg:postcode":"2132 NA",
    "sg:province":"Noord-Holland",
    "wof:name":"Hoektrans",
    "wof:placetype":"venue"
},
  "geometry": {"coordinates":[4.724114,52.288731],"type":"Point"}
}