{
  "type": "Feature",
  "properties": {
    "iso:country":"NL",
    "sg:address":"Mijlweg 96",
    "sg:city":"'S Gravendeel",
    "sg:orig_category":"Fruit And Groenten Gh",
    "sg:phone":"+31 78 673 6523",
    "sg:postcode":"3295 KH",
    "sg:province":"Zuid-Holland",
    "wof:name":"Firma A. En Z. Robbemont",
    "wof:placetype":"venue"
},
  "geometry": {"coordinates":[4.610209,51.786877],"type":"Point"}
}