{
  "type": "Feature",
  "properties": {
    "addr:full":"V Grotenhuisstr 42 Oosterhout Nb Noord-Brabant 4904 LR",
    "addr:housenumber":"42",
    "addr:postcode":"4904 lr",
    "iso:country":"NL",
    "sg:address":"V Grotenhuisstr 42",
    "sg:city":"Oosterhout Nb",
    "sg:orig_category":"Artiesten/Gezelschappen",
    "sg:phone":"+31 162 428 129",
    "sg:postcode":"4904 LR",
    "sg:province":"Noord-Brabant",
    "wof:name":"John Brass",
    "wof:placetype":"venue"
},
  "geometry": {"coordinates":[4.85625,51.643051],"type":"Point"}
}