{
  "type": "Feature",
  "properties": {
    "addr:full":"Kurhausweg 1 'S Gravenhage South Holland 2587 RT",
    "addr:housenumber":"1 '",
    "addr:postcode":"2587 rt",
    "addr:street":"Kurhausweg",
    "iso:country":"NL",
    "sg:address":"Kurhausweg 1",
    "sg:city":"'S Gravenhage",
    "sg:orig_category":"Kansspelen",
    "sg:phone":"+31 70 306 7777",
    "sg:postcode":"2587 RT",
    "sg:province":"South Holland",
    "wof:name":"Holland Casino Scheveningen",
    "wof:placetype":"venue"
},
  "geometry": {"coordinates":[4.2835001945,52.1119689941],"type":"Point"}
}