{
  "type": "Feature",
  "properties": {
    "addr:full":"Postbus 108 Hardenberg Overijssel 7770 AC",
    "addr:housenumber":"108",
    "addr:postcode":"7770 ac",
    "addr:street":"Postbus",
    "iso:country":"NL",
    "sg:address":"Postbus 108",
    "sg:city":"Hardenberg",
    "sg:orig_category":"Verpakkingsmachines",
    "sg:phone":"+31 523 260 407",
    "sg:postcode":"7770 AC",
    "sg:province":"Overijssel",
    "sg:website":"http://www.markhorst.nl",
    "wof:name":"Markhorst Bv",
    "wof:placetype":"venue"
},
  "geometry": {"coordinates":[6.622884,52.57534],"type":"Point"}
}