{
  "type": "Feature",
  "properties": {
    "addr:full":"Haltestr 53A Rilland Zeeland 4411 NE",
    "addr:housenumber":"53a",
    "addr:postcode":"4411 ne",
    "addr:street":"Haltestr",
    "iso:country":"NL",
    "sg:address":"Haltestr 53A",
    "sg:city":"Rilland",
    "sg:orig_category":"Weegbruggen",
    "sg:phone":"+31 113 551 391",
    "sg:postcode":"4411 NE",
    "sg:province":"Zeeland",
    "wof:name":"Weegbrug Rilland",
    "wof:placetype":"venue"
},
  "geometry": {"coordinates":[4.1653900146,51.4212303162],"type":"Point"}
}