{
  "type": "Feature",
  "properties": {
    "iso:country":"NL",
    "sg:address":"Noordweg 5",
    "sg:city":"Middelburg",
    "sg:orig_category":"Kappers",
    "sg:phone":"+31 118 611 834",
    "sg:postcode":"4333 GA",
    "sg:province":"Zeeland",
    "wof:name":"Coiffures Liberte",
    "wof:placetype":"venue"
},
  "geometry": {"coordinates":[3.6096971035,51.5053901672],"type":"Point"}
}