{
  "type": "Feature",
  "properties": {
    "addr:full":"Grondmolen 74 Papendrecht South Holland 3352 CC",
    "addr:housenumber":"74",
    "addr:postcode":"3352 cc",
    "addr:street":"Grondmolen",
    "iso:country":"NL",
    "sg:address":"Grondmolen 74",
    "sg:city":"Papendrecht",
    "sg:orig_category":"Montagebedrijven",
    "sg:phone":"+31 78 641 0345",
    "sg:postcode":"3352 CC",
    "sg:province":"South Holland",
    "wof:name":"Vip",
    "wof:placetype":"venue"
},
  "geometry": {"coordinates":[4.691564,51.842815],"type":"Point"}
}