{
  "type": "Feature",
  "properties": {
    "addr:full":"Peperstraat 33 Groningen Groningen 9711 PC",
    "addr:housenumber":"33",
    "addr:postcode":"9711 pc",
    "addr:street":"Peperstraat",
    "iso:country":"NL",
    "sg:address":"Peperstraat 33",
    "sg:city":"Groningen",
    "sg:orig_category":"Public Relationbureaus",
    "sg:phone":"+31 50 318 9391",
    "sg:postcode":"9711 PC",
    "sg:province":"Groningen",
    "wof:name":"Tris Van Der Wal Public Relations",
    "wof:placetype":"venue"
},
  "geometry": {"coordinates":[6.570961,53.217171],"type":"Point"}
}