{
  "type": "Feature",
  "properties": {
    "addr:full":"Atoomwg 19A Groningen Groningen 9743 AJ",
    "addr:housenumber":"19a",
    "addr:postcode":"9743 aj",
    "addr:street":"Atoomwg",
    "iso:country":"NL",
    "sg:address":"Atoomwg 19A",
    "sg:city":"Groningen",
    "sg:classifiers":[
        {
            "category":"Retail",
            "subcategory":"Storage",
            "type":"Services"
        }
    ],
    "sg:phone":"+31 50 589 1448",
    "sg:postcode":"9743 AJ",
    "sg:province":"Groningen",
    "sg:tags":[
        "op-",
        "en",
        "overslagbedrijven"
    ],
    "sg:website":"http://www.drenthtransport.nl",
    "wof:name":"Drenth Warehousing",
    "wof:placetype":"venue"
},
  "geometry": {"coordinates":[6.538501,53.216499],"type":"Point"}
}