{
  "type": "Feature",
  "properties": {
    "addr:full":"Wezenln 189 Nymegen Gelderland 6531 MN",
    "addr:housenumber":"189",
    "addr:postcode":"6531 mn",
    "addr:street":"Nymegen Gelderland",
    "iso:country":"NL",
    "sg:address":"Wezenln 189",
    "sg:city":"Nymegen",
    "sg:orig_category":"Verhuur",
    "sg:phone":"+31 24 355 3455",
    "sg:postcode":"6531 MN",
    "sg:province":"Gelderland",
    "wof:name":"Anjo",
    "wof:placetype":"venue"
},
  "geometry": {"coordinates":[-93.365471,46.441929],"type":"Point"}
}