{
  "type": "Feature",
  "properties": {
    "addr:full":"Overcingelln 15 Assen Drenthe 9401 LA",
    "addr:housenumber":"15",
    "addr:postcode":"9401 la",
    "addr:street":"Overcingelln",
    "iso:country":"NL",
    "sg:address":"Overcingelln 15",
    "sg:city":"Assen",
    "sg:orig_category":"Verzekeringen - Verzekeringskantoren",
    "sg:phone":"+31 592 305 081",
    "sg:postcode":"9401 LA",
    "sg:province":"Drenthe",
    "wof:name":"Boelens Jorritsma",
    "wof:placetype":"venue"
},
  "geometry": {"coordinates":[6.569501,52.990147],"type":"Point"}
}