{
  "type": "Feature",
  "properties": {
    "addr:full":"Heraln 68 Apeldoorn Gelderland 7321 DM",
    "addr:housenumber":"68",
    "addr:postcode":"7321 dm",
    "addr:street":"Heraln;Gelderland",
    "iso:country":"NL",
    "sg:address":"Heraln 68",
    "sg:city":"Apeldoorn",
    "sg:orig_category":"Kinderkleding",
    "sg:phone":"+31 55 366 8826",
    "sg:postcode":"7321 DM",
    "sg:province":"Gelderland",
    "wof:name":"Cotton Kids",
    "wof:placetype":"venue"
},
  "geometry": {"coordinates":[5.98598,52.21265],"type":"Point"}
}