{
  "type": "Feature",
  "properties": {
    "addr:full":"De Passage 7 Vroomshoop Overijssel 7681 DC",
    "addr:housenumber":"7",
    "addr:postcode":"7681",
    "addr:street":"De Passage",
    "iso:country":"NL",
    "sg:address":"De Passage 7",
    "sg:city":"Vroomshoop",
    "sg:orig_category":"Kinderkleding",
    "sg:phone":"+31 546 642 204",
    "sg:postcode":"7681 DC",
    "sg:province":"Overijssel",
    "wof:name":"Balou",
    "wof:placetype":"venue"
},
  "geometry": {"coordinates":[6.57245,52.461201],"type":"Point"}
}