{
  "type": "Feature",
  "properties": {
    "iso:country":"NL",
    "sg:address":"De Grt Elst 70",
    "sg:city":"Rosmalen",
    "sg:orig_category":"Orthopedische Artikelen - Fabrieken En Groothandel",
    "sg:phone":"+31 73 631 2355",
    "sg:postcode":"5246 JR",
    "sg:province":"Noord-Brabant",
    "wof:name":"Amoena Nederland Bv",
    "wof:placetype":"venue"
},
  "geometry": {"coordinates":[5.3428449631,51.7061080933],"type":"Point"}
}