{
  "type": "Feature",
  "properties": {
    "addr:full":"Nieuwstraat 8 Oosterhout Nb Noord-Brabant 4901 JH",
    "addr:housenumber":"8",
    "addr:postcode":"4901 jh",
    "addr:street":"Nieuwstraat",
    "iso:country":"NL",
    "sg:address":"Nieuwstraat 8",
    "sg:city":"Oosterhout Nb",
    "sg:orig_category":"Meubelzaken, Woning- And Keukeninrichting",
    "sg:phone":"+31 162 435 649",
    "sg:postcode":"4901 JH",
    "sg:province":"Noord-Brabant",
    "wof:name":"J. Leenaarts",
    "wof:placetype":"venue"
},
  "geometry": {"coordinates":[4.858583,51.644138],"type":"Point"}
}