{
  "type": "Feature",
  "properties": {
    "iso:country":"NL",
    "sg:address":"Hoofdstraat 90",
    "sg:city":"Terheijden",
    "sg:orig_category":"Boekhouders",
    "sg:phone":"+31 76 593 3440",
    "sg:postcode":"4844 CH",
    "sg:province":"Noord-Brabant",
    "wof:name":"Raad De Baronie",
    "wof:placetype":"venue"
},
  "geometry": {"coordinates":[4.759043,51.638451],"type":"Point"}
}