{
  "type": "Feature",
  "properties": {
    "addr:full":"Deurningerstraat 38 Enschede NL.08 7514 BJ",
    "addr:housenumber":"38",
    "addr:postcode":"7514 bj",
    "addr:street":"Deurningerstraat",
    "iso:country":"NL",
    "sg:address":"Deurningerstraat 38",
    "sg:city":"Enschede",
    "sg:orig_category":"Public Relationbureaus",
    "sg:phone":"+31 53 433 4364",
    "sg:postcode":"7514 BJ",
    "sg:province":"NL.08",
    "wof:name":"Van Beek & Geerts & Soepboer",
    "wof:placetype":"venue"
},
  "geometry": {"coordinates":[6.891124,52.22646],"type":"Point"}
}