{
  "type": "Feature",
  "properties": {
    "addr:full":"Oldenzaalsestr 161 Hengelo Ov Overijssel 7557 GJ",
    "addr:housenumber":"161",
    "addr:postcode":"7557 gj",
    "addr:street":"Ov",
    "iso:country":"NL",
    "sg:address":"Oldenzaalsestr 161",
    "sg:city":"Hengelo Ov",
    "sg:orig_category":"Verlichting",
    "sg:phone":"+31 74 291 3395",
    "sg:postcode":"7557 GJ",
    "sg:province":"Overijssel",
    "wof:name":"Lichtcentrum Hengelo",
    "wof:placetype":"venue"
},
  "geometry": {"coordinates":[6.802426,52.269684],"type":"Point"}
}