{
  "type": "Feature",
  "properties": {
    "addr:full":"Kerkplein 10 Zeewolde NL. 3891 ED",
    "addr:housenumber":"10",
    "addr:postcode":"3891 ed",
    "addr:street":"Kerkplein;Nl.",
    "iso:country":"NL",
    "sg:address":"Kerkplein 10",
    "sg:city":"Zeewolde",
    "sg:orig_category":"Banken And Kredietinstellingen",
    "sg:phone":"+31 36 522 1614",
    "sg:postcode":"3891 ED",
    "sg:province":"NL.",
    "wof:name":"Abn Amro",
    "wof:placetype":"venue"
},
  "geometry": {"coordinates":[5.542125,52.330986],"type":"Point"}
}