{
  "type": "Feature",
  "properties": {
    "iso:country":"NL",
    "sg:address":"De Mersken 14",
    "sg:city":"Ureterp",
    "sg:classifiers":[
        {
            "category":"Personal",
            "subcategory":"Nail Salon",
            "type":"Services"
        }
    ],
    "sg:phone":"+31 512 301 936",
    "sg:postcode":"9247 WK",
    "sg:province":"Friesland",
    "sg:tags":[
        "pedicure"
    ],
    "wof:name":"Jong, Paula De",
    "wof:placetype":"venue"
},
  "geometry": {"coordinates":[6.165997,53.074425],"type":"Point"}
}