{
  "type": "Feature",
  "properties": {
    "addr:full":"Ovenbouwershoek 8 Apeldoorn Gelderland 7328 JH",
    "addr:housenumber":"8",
    "addr:postcode":"7328 jh",
    "addr:street":"Ovenbouwershoek;Gelderland",
    "iso:country":"NL",
    "sg:address":"Ovenbouwershoek 8",
    "sg:city":"Apeldoorn",
    "sg:orig_category":"Autopoetsbedrijven",
    "sg:phone":"+31 55 367 0865",
    "sg:postcode":"7328 JH",
    "sg:province":"Gelderland",
    "wof:name":"Kleiboer Vof",
    "wof:placetype":"venue"
},
  "geometry": {"coordinates":[5.980021,52.207733],"type":"Point"}
}