{
  "type": "Feature",
  "properties": {
    "iso:country":"NL",
    "sg:address":"Seminariewg 21",
    "sg:city":"Bavel",
    "sg:orig_category":"Horeca-Inrichtingen En -Uitrustingen",
    "sg:phone":"+31 161 433 483",
    "sg:postcode":"4854 PA",
    "sg:province":"Noord-Brabant",
    "wof:name":"Scorpio Design Bv",
    "wof:placetype":"venue"
},
  "geometry": {"coordinates":[4.819283,51.574226],"type":"Point"}
}