{
  "type": "Feature",
  "properties": {
    "addr:full":"Hogerop 21 Zoetermeer South Holland 2711 AX",
    "addr:housenumber":"21",
    "addr:postcode":"2711 ax",
    "addr:street":"Hogerop",
    "iso:country":"NL",
    "sg:address":"Hogerop 21",
    "sg:city":"Zoetermeer",
    "sg:orig_category":"Kinderkleding",
    "sg:phone":"+31 79 352 3615",
    "sg:postcode":"2711 AX",
    "sg:province":"South Holland",
    "wof:name":"Mexx",
    "wof:placetype":"venue"
},
  "geometry": {"coordinates":[4.487609,52.062233],"type":"Point"}
}