{
  "type": "Feature",
  "properties": {
    "iso:country":"NL",
    "sg:address":"Maarnse Grindwg 18A",
    "sg:city":"Maarn",
    "sg:orig_category":"Koeltechniek",
    "sg:phone":"+31 343 444 210",
    "sg:postcode":"3951 LK",
    "sg:province":"Utrecht",
    "sg:website":"http://www.hti-europe.com",
    "wof:name":"Hti Benelux Bv",
    "wof:placetype":"venue"
},
  "geometry": {"coordinates":[5.359952,52.062103],"type":"Point"}
}