{
  "type": "Feature",
  "properties": {
    "addr:full":"Vaartweg 129 Hilversum North Holland 1217 SN",
    "addr:housenumber":"129",
    "addr:postcode":"1217 sn",
    "addr:street":"Vaartweg",
    "iso:country":"NL",
    "sg:address":"Vaartweg 129",
    "sg:city":"Hilversum",
    "sg:orig_category":"Kantoorapparatuur Gh",
    "sg:phone":"+31 35 624 7000",
    "sg:postcode":"1217 SN",
    "sg:province":"North Holland",
    "wof:name":"A Vd Gooisch Kantoorcentrum Bv",
    "wof:placetype":"venue"
},
  "geometry": {"coordinates":[5.1583509445,52.2230262756],"type":"Point"}
}