{
  "type": "Feature",
  "properties": {
    "addr:full":"Berkwg 69 Hengelo Ov NL.08 7556 CM",
    "addr:housenumber":"69",
    "addr:postcode":"7556 cm",
    "addr:street":"Berkwg;Ov",
    "iso:country":"NL",
    "sg:address":"Berkwg 69",
    "sg:city":"Hengelo Ov",
    "sg:orig_category":"Fitnesscentra",
    "sg:phone":"+31 74 243 8757",
    "sg:postcode":"7556 CM",
    "sg:province":"NL.08",
    "wof:name":"Total",
    "wof:placetype":"venue"
},
  "geometry": {"coordinates":[6.78971,52.266331],"type":"Point"}
}