{
  "type": "Feature",
  "properties": {
    "iso:country":"NL",
    "sg:address":"Prealle 15",
    "sg:city":"Etten Leur",
    "sg:orig_category":"Kinderopvang",
    "sg:phone":"+31 76 501 6008",
    "sg:postcode":"4876 XG",
    "sg:province":"Noord-Brabant",
    "wof:name":"Gong, De",
    "wof:placetype":"venue"
},
  "geometry": {"coordinates":[4.632681,51.562302],"type":"Point"}
}