{
  "type": "Feature",
  "properties": {
    "addr:full":"Postbus 60137 Almere Limburg 1320 AC",
    "addr:postcode":"60137;1320 ac",
    "addr:street":"Postbus",
    "iso:country":"NL",
    "sg:address":"Postbus 60137",
    "sg:city":"Almere",
    "sg:orig_category":"Adviesbureaus Bedrijfsorganisatie",
    "sg:phone":"+31 36 547 2090",
    "sg:postcode":"1320 AC",
    "sg:province":"Limburg",
    "sg:website":"http://www.promagna.nl",
    "wof:name":"Promagna Consult Bv",
    "wof:placetype":"venue"
},
  "geometry": {"coordinates":[5.21802,52.372211],"type":"Point"}
}