{
  "type": "Feature",
  "properties": {
    "iso:country":"NL",
    "sg:address":"Molenstraat 10",
    "sg:city":"Zundert",
    "sg:orig_category":"Kappers",
    "sg:phone":"+31 76 597 1114",
    "sg:postcode":"4881 CS",
    "sg:province":"Noord-Brabant",
    "wof:name":"A) De Mallemolen",
    "wof:placetype":"venue"
},
  "geometry": {"coordinates":[4.6638450623,51.4717254639],"type":"Point"}
}