{
  "type": "Feature",
  "properties": {
    "addr:full":"Marskant 21 Hengelo Ov Overijssel 7551 BS",
    "addr:housenumber":"21",
    "addr:postcode":"7551 bs",
    "addr:street":"Marskant;Ov",
    "iso:country":"NL",
    "sg:address":"Marskant 21",
    "sg:city":"Hengelo Ov",
    "sg:orig_category":"Woningbouw- Verenigingen En -Stichtingen",
    "sg:phone":"+31 74 247 7720",
    "sg:postcode":"7551 BS",
    "sg:province":"Overijssel",
    "sg:website":"http://www.woonpartner.com",
    "wof:name":"Woonpartner Zuid",
    "wof:placetype":"venue"
},
  "geometry": {"coordinates":[6.790473938,52.2635955811],"type":"Point"}
}