{
  "type": "Feature",
  "properties": {
    "addr:full":"Anna Van Engelandstraat 8 Eindhoven Noord-Brabant 5616 AZ",
    "addr:housenumber":"8",
    "addr:postcode":"5616 az",
    "addr:street":"Anna Van Engelandstraat",
    "iso:country":"NL",
    "sg:address":"Anna Van Engelandstraat 8",
    "sg:city":"Eindhoven",
    "sg:orig_category":"Overheidsdiensten",
    "sg:phone":"+31 40 259 2911",
    "sg:postcode":"5616 AZ",
    "sg:province":"Noord-Brabant",
    "wof:name":"Kadaster Zuid Vestiging Eindhoven",
    "wof:placetype":"venue"
},
  "geometry": {"coordinates":[5.4657611847,51.4339408875],"type":"Point"}
}