{
  "type": "Feature",
  "properties": {
    "iso:country":"NL",
    "sg:address":"Dorpsstraat 27",
    "sg:city":"Ruurlo",
    "sg:orig_category":"Verlichting And Huishoudartikelen",
    "sg:phone":"+31 573 453 193",
    "sg:postcode":"7261 AV",
    "sg:province":"Gelderland",
    "wof:name":"De Spannevogel",
    "wof:placetype":"venue"
},
  "geometry": {"coordinates":[6.449227,52.087082],"type":"Point"}
}