{
  "type": "Feature",
  "properties": {
    "iso:country":"NL",
    "sg:address":"Hoge Rijndijk 23M",
    "sg:city":"Leiden",
    "sg:orig_category":"Makelaars En Adviseurs Onroerende Goederen",
    "sg:phone":"+31 6 12807509",
    "sg:postcode":"2313 KE",
    "sg:province":"Zuid-Holland",
    "wof:name":"Ponsteen",
    "wof:placetype":"venue"
},
  "geometry": {"coordinates":[4.506852,52.155121],"type":"Point"}
}