{
  "type": "Feature",
  "properties": {
    "addr:full":"Bernhardstr 33 Breukelen Ut Utrecht 3621 EM",
    "addr:housenumber":"33",
    "addr:postcode":"3621 em",
    "addr:street":"Bernhardstr",
    "iso:country":"NL",
    "sg:address":"Bernhardstr 33",
    "sg:city":"Breukelen Ut",
    "sg:orig_category":"Watersportartikelen",
    "sg:phone":"+31 346 264 619",
    "sg:postcode":"3621 EM",
    "sg:province":"Utrecht",
    "sg:website":"http://www.waterservice.nl",
    "wof:name":"Lock",
    "wof:placetype":"venue"
},
  "geometry": {"coordinates":[5.0015850067,52.172958374],"type":"Point"}
}