{
  "type": "Feature",
  "properties": {
    "addr:full":"Dalwg 2 Soest Utrecht 3764 BX",
    "addr:housenumber":"2",
    "addr:postcode":"3764 bx",
    "addr:street":"Dalwg",
    "iso:country":"NL",
    "sg:address":"Dalwg 2",
    "sg:city":"Soest",
    "sg:orig_category":"Onroerende Goederen",
    "sg:phone":"+31 35 602 5867",
    "sg:postcode":"3764 BX",
    "sg:province":"Utrecht",
    "wof:name":"Zwart",
    "wof:placetype":"venue"
},
  "geometry": {"coordinates":[5.301312,52.180595],"type":"Point"}
}