{
  "type": "Feature",
  "properties": {
    "iso:country":"NL",
    "sg:address":"Het Achtkant 60",
    "sg:city":"Limmen",
    "sg:orig_category":"Schoonheidssalons",
    "sg:phone":"+31 72 505 2177",
    "sg:postcode":"1906 GE",
    "sg:province":"Noord-Holland",
    "wof:name":"Schoonheidssalon Conny Lahoye",
    "wof:placetype":"venue"
},
  "geometry": {"coordinates":[4.685461,52.570576],"type":"Point"}
}