{
  "type": "Feature",
  "properties": {
    "addr:full":"Wilhelminaln 10 Ermelo Gelderland 3851 XW",
    "addr:housenumber":"10",
    "addr:postcode":"3851 xw",
    "addr:street":"Wilhelminaln;Gelderland",
    "iso:country":"NL",
    "sg:address":"Wilhelminaln 10",
    "sg:city":"Ermelo",
    "sg:orig_category":"Verenigingen En Stichtingen",
    "sg:phone":"+31 341 554 023",
    "sg:postcode":"3851 XW",
    "sg:province":"Gelderland",
    "sg:website":"http://www.natuur-gezondheidsproducten.nl",
    "wof:name":"Npn",
    "wof:placetype":"venue"
},
  "geometry": {"coordinates":[5.627003,52.304897],"type":"Point"}
}