{
  "type": "Feature",
  "properties": {
    "addr:full":"Zandzuigerstraat 18 Almere NL. 1333 HD",
    "addr:housenumber":"18",
    "addr:postcode":"1333 hd",
    "addr:street":"Zandzuigerstraat;Nl.",
    "iso:country":"NL",
    "sg:address":"Zandzuigerstraat 18",
    "sg:city":"Almere",
    "sg:orig_category":"Bouwmaterialen Gh",
    "sg:phone":"+31 36 529 1041",
    "sg:postcode":"1333 HD",
    "sg:province":"NL.",
    "wof:name":"Marlin Natuursteen",
    "wof:placetype":"venue"
},
  "geometry": {"coordinates":[5.260558,52.40184],"type":"Point"}
}