{
  "type": "Feature",
  "properties": {
    "iso:country":"NL",
    "sg:address":"Het Kant 45",
    "sg:city":"Houten",
    "sg:orig_category":"Yoga-Instituten",
    "sg:phone":"+31 30 635 0275",
    "sg:postcode":"3995 DZ",
    "sg:province":"Utrecht",
    "wof:name":"Amadorra",
    "wof:placetype":"venue"
},
  "geometry": {"coordinates":[5.165692,52.034809],"type":"Point"}
}