{
  "type": "Feature",
  "properties": {
    "iso:country":"NL",
    "sg:address":"Grt Egtenraysewg 76",
    "sg:city":"Venlo",
    "sg:orig_category":"Verlichtingsartikelen - Fabrieken",
    "sg:phone":"+31 77 324 4888",
    "sg:postcode":"5928 PA",
    "sg:province":"Limburg",
    "sg:website":"http://www.marlinlighting.com",
    "wof:name":"Qcfactory Bv",
    "wof:placetype":"venue"
},
  "geometry": {"coordinates":[6.139237,51.387447],"type":"Point"}
}