{
  "type": "Feature",
  "properties": {
    "addr:full":"Overstortwg 7 Drunen Noord-Brabant 5151 AD",
    "addr:housenumber":"7",
    "addr:postcode":"5151 ad",
    "addr:street":"Overstortwg",
    "iso:country":"NL",
    "sg:address":"Overstortwg 7",
    "sg:city":"Drunen",
    "sg:orig_category":"Kaas",
    "sg:phone":"+31 416 380 312",
    "sg:postcode":"5151 AD",
    "sg:province":"Noord-Brabant",
    "wof:name":"Kern, De",
    "wof:placetype":"venue"
},
  "geometry": {"coordinates":[5.1104440689,51.6869544983],"type":"Point"}
}