{
  "type": "Feature",
  "properties": {
    "addr:full":"Langewyk 275 Drachten Provincie Friesland 9202 CN",
    "addr:housenumber":"275",
    "addr:postcode":"9202 cn",
    "addr:street":"Langewyk;Provincie Friesland",
    "iso:country":"NL",
    "sg:address":"Langewyk 275",
    "sg:city":"Drachten",
    "sg:classifiers":[
        {
            "category":"Education",
            "subcategory":"Preschool",
            "type":"Public Place"
        }
    ],
    "sg:phone":"+31 512 544 530",
    "sg:postcode":"9202 CN",
    "sg:province":"Provincie Friesland",
    "sg:tags":[
        "kleuteronderwijs",
        "basis-"
    ],
    "wof:name":"Basisschool Het Mozaiek Pcbo Smallingerland",
    "wof:placetype":"venue"
},
  "geometry": {"coordinates":[6.120396,53.109512],"type":"Point"}
}