{
  "type": "Feature",
  "properties": {
    "addr:full":"Zwaluwenburg 43 Dordrecht South Holland 3328 CP",
    "addr:housenumber":"43",
    "addr:postcode":"3328 cp",
    "addr:street":"Zwaluwenburg",
    "iso:country":"NL",
    "sg:address":"Zwaluwenburg 43",
    "sg:city":"Dordrecht",
    "sg:orig_category":"Architecten",
    "sg:phone":"+31 78 617 1173",
    "sg:postcode":"3328 CP",
    "sg:province":"South Holland",
    "wof:name":"F.D.G. Prins Bv",
    "wof:placetype":"venue"
},
  "geometry": {"coordinates":[4.671842,51.77721],"type":"Point"}
}