{
  "type": "Feature",
  "properties": {
    "addr:full":"Koningshoek 93101 Maassluis Zuid-Holland 3144 BA",
    "addr:housenumber":"93101",
    "addr:postcode":"3144 ba",
    "addr:street":"Koningshoek",
    "iso:country":"NL",
    "sg:address":"Koningshoek 93101",
    "sg:city":"Maassluis",
    "sg:orig_category":"Bloemen En Planten",
    "sg:phone":"+31 10 592 5151",
    "sg:postcode":"3144 BA",
    "sg:province":"Zuid-Holland",
    "wof:name":"Guus",
    "wof:placetype":"venue"
},
  "geometry": {"coordinates":[4.239762,51.928013],"type":"Point"}
}