{
  "type": "Feature",
  "properties": {
    "addr:full":"Heldersestraat 5 Oirschot Noord-Brabant 5688 NE",
    "addr:housenumber":"5",
    "addr:postcode":"5688 ne",
    "addr:street":"Heldersestraat",
    "iso:country":"NL",
    "sg:address":"Heldersestraat 5",
    "sg:city":"Oirschot",
    "sg:orig_category":"Wegen And Sportterreinen",
    "sg:phone":"+31 499 571 470",
    "sg:postcode":"5688 NE",
    "sg:province":"Noord-Brabant",
    "wof:name":"Gebroeders Van Den Bosch Bv",
    "wof:placetype":"venue"
},
  "geometry": {"coordinates":[5.3346791267,51.522567749],"type":"Point"}
}