{
  "type": "Feature",
  "properties": {
    "iso:country":"NL",
    "sg:address":"Westerwg 36A",
    "sg:city":"Bergen Nh",
    "sg:orig_category":"Paardenhandelaren",
    "sg:phone":"+31 72 581 3038",
    "sg:postcode":"1862 CE",
    "sg:province":"Noord-Holland",
    "wof:name":"Stammis, J",
    "wof:placetype":"venue"
},
  "geometry": {"coordinates":[4.715133,52.672916],"type":"Point"}
}