{
  "type": "Feature",
  "properties": {
    "addr:full":"Hg Ryndk 141 Leiden Zuid-Holland 2314 AB",
    "addr:housenumber":"141",
    "addr:postcode":"2314 ab",
    "iso:country":"NL",
    "sg:address":"Hg Ryndk 141",
    "sg:city":"Leiden",
    "sg:orig_category":"Onderhoudswerken",
    "sg:phone":"+31 71 523 8933",
    "sg:postcode":"2314 AB",
    "sg:province":"Zuid-Holland",
    "wof:name":"Smink, Ben",
    "wof:placetype":"venue"
},
  "geometry": {"coordinates":[4.517094,52.154491],"type":"Point"}
}