{
  "type": "Feature",
  "properties": {
    "addr:full":"Maasdk 19 Ryswyk Nb North Brabant 4284 VA",
    "addr:housenumber":"19;nb",
    "addr:postcode":"4284",
    "addr:street":"Maasdk",
    "iso:country":"NL",
    "sg:address":"Maasdk 19",
    "sg:city":"Ryswyk Nb",
    "sg:orig_category":"Artsen - Huisartsen",
    "sg:phone":"+31 183 441 780",
    "sg:postcode":"4284 VA",
    "sg:province":"North Brabant",
    "wof:name":"Egmond, B Van",
    "wof:placetype":"venue"
},
  "geometry": {"coordinates":[5.02701,51.797668],"type":"Point"}
}