{
  "type": "Feature",
  "properties": {
    "addr:full":"Wijmersweg 13 Loppersum Groningen 9919 BH",
    "addr:housenumber":"13",
    "addr:postcode":"9919 bh",
    "addr:street":"Wijmersweg",
    "iso:country":"NL",
    "sg:address":"Wijmersweg 13",
    "sg:city":"Loppersum",
    "sg:orig_category":"Woningbouwverenigingen",
    "sg:phone":"+31 596 572 172",
    "sg:postcode":"9919 BH",
    "sg:province":"Groningen",
    "wof:name":"Woningstichting Loppersum",
    "wof:placetype":"venue"
},
  "geometry": {"coordinates":[6.7397627831,53.3307418823],"type":"Point"}
}