{
  "type": "Feature",
  "properties": {
    "addr:full":"Zuidhaven 173 Zevenbergen North Brabant 4761 CX",
    "addr:housenumber":"173",
    "addr:postcode":"4761 cx",
    "addr:street":"Zuidhaven",
    "iso:country":"NL",
    "sg:address":"Zuidhaven 173",
    "sg:city":"Zevenbergen",
    "sg:orig_category":"Postkantoren",
    "sg:phone":"+31 168 329 822",
    "sg:postcode":"4761 CX",
    "sg:province":"North Brabant",
    "sg:website":"http://www.postkantoor.nl",
    "wof:name":"Postkantoor",
    "wof:placetype":"venue"
},
  "geometry": {"coordinates":[4.602853,51.643738],"type":"Point"}
}