{
  "type": "Feature",
  "properties": {
    "addr:full":"Vryheidsln 55 Nieuwerkerk Yssel Zuid-Holland 2912 EA",
    "addr:housenumber":"55",
    "addr:postcode":"2912 ea",
    "addr:street":"Vryheidsln",
    "iso:country":"NL",
    "sg:address":"Vryheidsln 55",
    "sg:city":"Nieuwerkerk Yssel",
    "sg:orig_category":"Orgels",
    "sg:phone":"+31 180 315 652",
    "sg:postcode":"2912 EA",
    "sg:province":"Zuid-Holland",
    "wof:name":"Stolk",
    "wof:placetype":"venue"
},
  "geometry": {"coordinates":[4.6027998924,51.9636917114],"type":"Point"}
}