{
  "type": "Feature",
  "properties": {
    "addr:full":"Postbus 85337 Utrecht Utrecht 3508 AH",
    "addr:postcode":"85337;3508 ah",
    "addr:street":"Postbus",
    "iso:country":"NL",
    "sg:address":"Postbus 85337",
    "sg:city":"Utrecht",
    "sg:orig_category":"Wasserettes, Stomerijen And Reiniging",
    "sg:phone":"+31 30 230 2100",
    "sg:postcode":"3508 AH",
    "sg:province":"Utrecht",
    "wof:name":"Chemdry",
    "wof:placetype":"venue"
},
  "geometry": {"coordinates":[5.1228899956,52.0909996033],"type":"Point"}
}