{
  "type": "Feature",
  "properties": {
    "addr:full":"Verrijn Stuartweg 5 Diemen Noord-Holland 1112 AW",
    "addr:housenumber":"5",
    "addr:postcode":"1112 aw",
    "addr:street":"Verrijn Stuartweg",
    "iso:country":"NL",
    "sg:address":"Verrijn Stuartweg 5",
    "sg:city":"Diemen",
    "sg:orig_category":"Kantoorartikelen",
    "sg:phone":"+31 20 416 1333",
    "sg:postcode":"1112 AW",
    "sg:province":"Noord-Holland",
    "wof:name":"Mmore International Bv",
    "wof:placetype":"venue"
},
  "geometry": {"coordinates":[4.9627099037,52.332447052],"type":"Point"}
}