{
  "type": "Feature",
  "properties": {
    "addr:full":"Molendijk 15 Hoek Zeeland 4542 BJ",
    "addr:housenumber":"15",
    "addr:postcode":"4542 bj",
    "addr:street":"Molendijk",
    "iso:country":"NL",
    "sg:address":"Molendijk 15",
    "sg:city":"Hoek",
    "sg:orig_category":"Meubelzaken, Woning- And Keukeninrichting",
    "sg:phone":"+31 115 441 235",
    "sg:postcode":"4542 BJ",
    "sg:province":"Zeeland",
    "wof:name":"Firma Gebr. Van 'T Hoff",
    "wof:placetype":"venue"
},
  "geometry": {"coordinates":[3.779761,51.310116],"type":"Point"}
}