{
  "type": "Feature",
  "properties": {
    "iso:country":"NL",
    "sg:address":"Sittarderweg 124",
    "sg:city":"Heerlen",
    "sg:classifiers":[
        {
            "category":"Food & Beverages",
            "subcategory":"Fruits & Vegetables",
            "type":"Retail Goods"
        }
    ],
    "sg:phone":"+31 45 572 1649",
    "sg:postcode":"6412 CL",
    "sg:province":"Limburg",
    "sg:tags":[
        "groenten"
    ],
    "wof:name":"T Oogappeltje",
    "wof:placetype":"venue"
},
  "geometry": {"coordinates":[5.971351,50.899963],"type":"Point"}
}