{
  "type": "Feature",
  "properties": {
    "addr:full":"Scherluitweg 2 Kessel Lb Limburg 5995 RB",
    "addr:housenumber":"2",
    "addr:postcode":"lb;5995 rb",
    "addr:street":"Scherluitweg",
    "iso:country":"NL",
    "sg:address":"Scherluitweg 2",
    "sg:city":"Kessel Lb",
    "sg:orig_category":"Huisdierenfokkers",
    "sg:phone":"+31 77 462 2721",
    "sg:postcode":"5995 RB",
    "sg:province":"Limburg",
    "wof:name":"Of Sylvi'S Jewelbox",
    "wof:placetype":"venue"
},
  "geometry": {"coordinates":[6.054281,51.307438],"type":"Point"}
}