{
  "type": "Feature",
  "properties": {
    "iso:country":"NL",
    "sg:address":"Lage Witsiebaan 112",
    "sg:city":"Tilburg",
    "sg:orig_category":"Gebouwenafwerking, Renovaties And Reiniging",
    "sg:phone":"+31 13 467 8477",
    "sg:postcode":"5042 DC",
    "sg:province":"Noord-Brabant",
    "wof:name":"Britcleaning",
    "wof:placetype":"venue"
},
  "geometry": {"coordinates":[5.056374,51.573418],"type":"Point"}
}