{
  "type": "Feature",
  "properties": {
    "addr:full":"L Voren 22 Eersel Noord-Brabant 5521 DD",
    "addr:housenumber":"22",
    "addr:postcode":"5521 dd",
    "addr:street":"L Voren",
    "iso:country":"NL",
    "sg:address":"L Voren 22",
    "sg:city":"Eersel",
    "sg:orig_category":"Autoschade- Herstelbedrijven",
    "sg:phone":"+31 497 517 521",
    "sg:postcode":"5521 DD",
    "sg:province":"Noord-Brabant",
    "wof:name":"Tongeren Vof, P Van",
    "wof:placetype":"venue"
},
  "geometry": {"coordinates":[5.316576,51.366268],"type":"Point"}
}