{
  "type": "Feature",
  "properties": {
    "addr:full":"Postbus 15 Veenendaal Utrecht 3900 AA",
    "addr:housenumber":"15",
    "addr:postcode":"3900 aa",
    "addr:street":"Postbus",
    "iso:country":"NL",
    "sg:address":"Postbus 15",
    "sg:city":"Veenendaal",
    "sg:orig_category":"Adviesbureaus Gezondheidszorg",
    "sg:phone":"+31 318 553 634",
    "sg:postcode":"3900 AA",
    "sg:province":"Utrecht",
    "sg:website":"http://www.pgb-abc.nl",
    "wof:name":"Pgb/Abc",
    "wof:placetype":"venue"
},
  "geometry": {"coordinates":[5.55418,52.024902],"type":"Point"}
}