{
  "type": "Feature",
  "properties": {
    "iso:country":"NL",
    "sg:address":"Parallelweg 7",
    "sg:city":"Maasbree",
    "sg:orig_category":"Goederenvervoer Over De Weg",
    "sg:phone":"+31 77 465 3831",
    "sg:postcode":"5993 BG",
    "sg:province":"Limburg",
    "wof:name":"H.M. Weber Transporten",
    "wof:placetype":"venue"
},
  "geometry": {"coordinates":[24.020149231,43.2265701294],"type":"Point"}
}