{
  "type": "Feature",
  "properties": {
    "addr:full":"J V Arkelstr 72 Utrecht Utrecht 3523 VH",
    "addr:housenumber":"72",
    "addr:postcode":"3523 vh",
    "addr:street":"J;Arkelstr",
    "iso:country":"NL",
    "sg:address":"J V Arkelstr 72",
    "sg:city":"Utrecht",
    "sg:orig_category":"Woninginrichting",
    "sg:phone":"+31 30 289 4312",
    "sg:postcode":"3523 VH",
    "sg:province":"Utrecht",
    "wof:name":"Buysman, Pierre",
    "wof:placetype":"venue"
},
  "geometry": {"coordinates":[5.1263198853,52.0720405579],"type":"Point"}
}