{
  "type": "Feature",
  "properties": {
    "addr:full":"Minervum 7068 Breda Noord-Brabant 4817 ZK",
    "addr:housenumber":"7068",
    "addr:postcode":"breda;4817",
    "addr:street":"Minervum;Zk",
    "iso:country":"NL",
    "sg:address":"Minervum 7068",
    "sg:city":"Breda",
    "sg:orig_category":"Etiketten",
    "sg:phone":"+31 76 571 7630",
    "sg:postcode":"4817 ZK",
    "sg:province":"Noord-Brabant",
    "sg:website":"http://www.eurolabel.nl",
    "wof:name":"Eurolabel",
    "wof:placetype":"venue"
},
  "geometry": {"coordinates":[4.832494,51.589001],"type":"Point"}
}