{
  "type": "Feature",
  "properties": {
    "addr:full":"Stationsstr 40 Maastricht Limburg 6221 BR",
    "addr:housenumber":"40",
    "addr:postcode":"6221 br",
    "addr:street":"Stationsstr",
    "iso:country":"NL",
    "sg:address":"Stationsstr 40",
    "sg:city":"Maastricht",
    "sg:classifiers":[
        {
            "category":"Travel",
            "subcategory":"Hotels & Motels",
            "type":"Entertainment"
        }
    ],
    "sg:phone":"+31 43 328 2525",
    "sg:postcode":"6221 BR",
    "sg:province":"Limburg",
    "sg:website":"http://www.la-bergere.com",
    "wof:name":"Berg?re Hotel En Housing, La",
    "wof:placetype":"venue"
},
  "geometry": {"coordinates":[5.702679,50.849808],"type":"Point"}
}