{
  "type": "Feature",
  "properties": {
    "iso:country":"NL",
    "sg:address":"Walenburgerwg 74",
    "sg:city":"Rotterdam",
    "sg:orig_category":"Verenigingen En Stichtingen",
    "sg:phone":"+31 10 265 0011",
    "sg:postcode":"3033 AG",
    "sg:province":"Zuid-Holland",
    "wof:name":"Conforte Koepel",
    "wof:placetype":"venue"
},
  "geometry": {"coordinates":[4.466447,51.928268],"type":"Point"}
}