{
  "type": "Feature",
  "properties": {
    "iso:country":"NL",
    "sg:address":"Grootvenstr 9",
    "sg:city":"Tilburg",
    "sg:orig_category":"Verenigingen En Stichtingen",
    "sg:phone":"+31 13 456 0707",
    "sg:postcode":"5048 AT",
    "sg:province":"Noord-Brabant",
    "wof:name":"Scherpschuttersver Tilburg",
    "wof:placetype":"venue"
},
  "geometry": {"coordinates":[5.058175,51.590511],"type":"Point"}
}