{
  "type": "Feature",
  "properties": {
    "iso:country":"NL",
    "sg:address":"Schouwburgring 11",
    "sg:city":"Tilburg",
    "sg:classifiers":[
        {
            "category":"Shopping",
            "subcategory":"Adult",
            "type":"Retail Goods"
        }
    ],
    "sg:phone":"+31 13 536 5163",
    "sg:postcode":"5038 TK",
    "sg:province":"Noord-Brabant",
    "sg:tags":[
        "lingerie",
        "en",
        "tricotage"
    ],
    "wof:name":"Paolo Paysani Bv",
    "wof:placetype":"venue"
},
  "geometry": {"coordinates":[5.082579,51.554649],"type":"Point"}
}