{
  "type": "Feature",
  "properties": {
    "addr:full":"Gewandewg 19 Geleen Limburg 6161 DJ",
    "addr:housenumber":"19",
    "addr:postcode":"6161 dj",
    "addr:street":"Gewandewg",
    "iso:country":"NL",
    "sg:address":"Gewandewg 19",
    "sg:city":"Geleen",
    "sg:orig_category":"Ventilatiesystemen",
    "sg:phone":"+31 46 475 1670",
    "sg:postcode":"6161 DJ",
    "sg:province":"Limburg",
    "wof:name":"Mevent",
    "wof:placetype":"venue"
},
  "geometry": {"coordinates":[5.810169,50.961082],"type":"Point"}
}