{
  "type": "Feature",
  "properties": {
    "addr:full":"Ln V Het Kwekebos 183 Emmen Drenthe 7823 KD",
    "addr:housenumber":"183",
    "addr:postcode":"7823 kd",
    "addr:street":"Ln V Het Kwekebos",
    "iso:country":"NL",
    "sg:address":"Ln V Het Kwekebos 183",
    "sg:city":"Emmen",
    "sg:orig_category":"Pensioenen",
    "sg:phone":"+31 591 620 376",
    "sg:postcode":"7823 KD",
    "sg:province":"Drenthe",
    "wof:name":"Water, Van De",
    "wof:placetype":"venue"
},
  "geometry": {"coordinates":[6.9445,52.796104],"type":"Point"}
}