{
  "type": "Feature",
  "properties": {
    "addr:full":"Oceanie 6 Ittervoort Limburg 6014 DB",
    "addr:housenumber":"6",
    "addr:postcode":"6014 db",
    "addr:street":"Oceanie",
    "iso:country":"NL",
    "sg:address":"Oceanie 6",
    "sg:city":"Ittervoort",
    "sg:orig_category":"Graniet-, Granito- En Terrazzowerken",
    "sg:phone":"+31 475 561 003",
    "sg:postcode":"6014 DB",
    "sg:province":"Limburg",
    "wof:name":"Adams Terrazzo",
    "wof:placetype":"venue"
},
  "geometry": {"coordinates":[5.830763,51.1744],"type":"Point"}
}