{
  "type": "Feature",
  "properties": {
    "addr:full":"Spuistr 35 Schiedam Zuid-Holland 3114 CR",
    "addr:housenumber":"35",
    "addr:postcode":"3114 cr",
    "addr:street":"Spuistr",
    "iso:country":"NL",
    "sg:address":"Spuistr 35",
    "sg:city":"Schiedam",
    "sg:orig_category":"Administratie- En Boekhoudkantoren",
    "sg:phone":"+31 10 427 0870",
    "sg:postcode":"3114 CR",
    "sg:province":"Zuid-Holland",
    "wof:name":"Alert",
    "wof:placetype":"venue"
},
  "geometry": {"coordinates":[4.402347,51.908188],"type":"Point"}
}