{
  "type": "Feature",
  "properties": {
    "addr:full":"Smitsbreeweg 9 Losser Overijssel 7581 HE",
    "addr:housenumber":"9",
    "addr:postcode":"7581 he",
    "addr:street":"Smitsbreeweg",
    "iso:country":"NL",
    "sg:address":"Smitsbreeweg 9",
    "sg:city":"Losser",
    "sg:orig_category":"Overheidsdiensten",
    "sg:phone":"+31 53 538 6122",
    "sg:postcode":"7581 HE",
    "sg:province":"Overijssel",
    "wof:name":"De Welp",
    "wof:placetype":"venue"
},
  "geometry": {"coordinates":[7.0139808655,52.2592124939],"type":"Point"}
}