{
  "type": "Feature",
  "properties": {
    "addr:full":"Nieuwegracht 29 Soest Utrecht 3763 LP",
    "addr:housenumber":"29",
    "addr:postcode":"3763 lp",
    "addr:street":"Nieuwegracht",
    "iso:country":"NL",
    "sg:address":"Nieuwegracht 29",
    "sg:city":"Soest",
    "sg:orig_category":"Autokeuringen",
    "sg:phone":"+31 35 602 2744",
    "sg:postcode":"3763 LP",
    "sg:province":"Utrecht",
    "wof:name":"P.W. Stalenhoef Bv",
    "wof:placetype":"venue"
},
  "geometry": {"coordinates":[5.300385,52.184044],"type":"Point"}
}