{
  "type": "Feature",
  "properties": {
    "addr:full":"Markt 19 Roosendaal North Brabant 4701 PB",
    "addr:housenumber":"19",
    "addr:postcode":"4701 pb",
    "addr:street":"Markt",
    "iso:country":"NL",
    "sg:address":"Markt 19",
    "sg:city":"Roosendaal",
    "sg:orig_category":"Banken And Kredietinstellingen",
    "sg:phone":"+31 165 581 600",
    "sg:postcode":"4701 PB",
    "sg:province":"North Brabant",
    "wof:name":"Ing Bank",
    "wof:placetype":"venue"
},
  "geometry": {"coordinates":[4.455772,51.532913],"type":"Point"}
}