{
  "type": "Feature",
  "properties": {
    "addr:full":"Regulierenring 3 Bunnik Utrecht 3981 LA",
    "addr:housenumber":"3",
    "addr:postcode":"3981 la",
    "addr:street":"Regulierenring",
    "iso:country":"NL",
    "sg:address":"Regulierenring 3",
    "sg:city":"Bunnik",
    "sg:orig_category":"Waterbehandeling En Waterzuiverings- Systemen",
    "sg:phone":"+31 30 657 0208",
    "sg:postcode":"3981 LA",
    "sg:province":"Utrecht",
    "wof:name":"Raak, Van",
    "wof:placetype":"venue"
},
  "geometry": {"coordinates":[5.1922020912,52.0636062622],"type":"Point"}
}