{
  "type": "Feature",
  "properties": {
    "addr:full":"Stationsstr 108 Deurne North Brabant 5751 HJ",
    "addr:housenumber":"108",
    "addr:postcode":"5751 hj",
    "iso:country":"NL",
    "sg:address":"Stationsstr 108",
    "sg:city":"Deurne",
    "sg:orig_category":"Fietsen En Bromfietsen",
    "sg:phone":"+31 493 312 354",
    "sg:postcode":"5751 HJ",
    "sg:province":"North Brabant",
    "wof:name":"Manders",
    "wof:placetype":"venue"
},
  "geometry": {"coordinates":[5.786883,51.459068],"type":"Point"}
}