{
  "type": "Feature",
  "properties": {
    "iso:country":"NL",
    "sg:address":"Not Oostingstr 4",
    "sg:city":"Emmen",
    "sg:orig_category":"Juweliers",
    "sg:phone":"+31 591 616 960",
    "sg:postcode":"7811 CT",
    "sg:province":"Drenthe",
    "wof:name":"Arn Van Ess Juwelier",
    "wof:placetype":"venue"
},
  "geometry": {"coordinates":[6.895438,52.784485],"type":"Point"}
}