{
  "type": "Feature",
  "properties": {
    "addr:full":"Kimwierde 166 Almere Flevoland 1353 DT",
    "addr:housenumber":"166",
    "addr:postcode":"1353 dt",
    "addr:street":"Kimwierde;Flevoland",
    "iso:country":"NL",
    "sg:address":"Kimwierde 166",
    "sg:city":"Almere",
    "sg:orig_category":"Loodgieterswerk, Verwarming And Sanitaire Installaties",
    "sg:phone":"+31 36 531 9846",
    "sg:postcode":"1353 DT",
    "sg:province":"Flevoland",
    "wof:name":"Warners Huis & Tuin",
    "wof:placetype":"venue"
},
  "geometry": {"coordinates":[5.203666,52.336327],"type":"Point"}
}