{
  "type": "Feature",
  "properties": {
    "addr:full":"Nyverheidswg 4 Appingedam Groningen 9902 AE",
    "addr:housenumber":"4",
    "addr:postcode":"9902 ae",
    "addr:street":"Nyverheidswg",
    "iso:country":"NL",
    "sg:address":"Nyverheidswg 4",
    "sg:city":"Appingedam",
    "sg:orig_category":"Geluidsinstallaties",
    "sg:phone":"+31 596 680 364",
    "sg:postcode":"9902 AE",
    "sg:province":"Groningen",
    "wof:name":"Audition",
    "wof:placetype":"venue"
},
  "geometry": {"coordinates":[6.850968,53.309029],"type":"Point"}
}