{
  "type": "Feature",
  "properties": {
    "addr:full":"Spaarnwouderweg 1119 Vijfhuizen Noord-Holland 2141 BN",
    "addr:housenumber":"1119",
    "addr:postcode":"vijfhuizen;2141 bn",
    "addr:street":"Spaarnwouderweg",
    "iso:country":"NL",
    "sg:address":"Spaarnwouderweg 1119",
    "sg:city":"Vijfhuizen",
    "sg:orig_category":"Loodgieterswerk, Verwarming And Sanitaire Installaties",
    "sg:phone":"+31 23 540 2925",
    "sg:postcode":"2141 BN",
    "sg:province":"Noord-Holland",
    "wof:name":"Volta",
    "wof:placetype":"venue"
},
  "geometry": {"coordinates":[4.703618,52.37191],"type":"Point"}
}