{
  "type": "Feature",
  "properties": {
    "iso:country":"NL",
    "sg:address":"Laar 27",
    "sg:city":"Nistelrode",
    "sg:orig_category":"Fietsen En Bromfietsen",
    "sg:phone":"+31 412 611 231",
    "sg:postcode":"5388 HB",
    "sg:province":"North Brabant",
    "wof:name":"Martens Bv, Jack",
    "wof:placetype":"venue"
},
  "geometry": {"coordinates":[5.562015,51.702484],"type":"Point"}
}