{
  "type": "Feature",
  "properties": {
    "addr:full":"Laar 27 Nistelrode North Brabant 5388 HB",
    "addr:housenumber":"27",
    "addr:postcode":"5388 hb",
    "addr:street":"Laar",
    "iso:country":"NL",
    "sg:address":"Laar 27",
    "sg:city":"Nistelrode",
    "sg:orig_category":"Fietsen En Bromfietsen",
    "sg:phone":"+31 412 611 231",
    "sg:postcode":"5388 HB",
    "sg:province":"North Brabant",
    "wof:name":"Martens Bv, Jack",
    "wof:placetype":"venue"
},
  "geometry": {"coordinates":[5.562015,51.702484],"type":"Point"}
}