{
  "type": "Feature",
  "properties": {
    "addr:full":"Industriestr 11 Sittard Limburg 6135 KE",
    "addr:housenumber":"11",
    "addr:postcode":"6135 ke",
    "addr:street":"Industriestr",
    "iso:country":"NL",
    "sg:address":"Industriestr 11",
    "sg:city":"Sittard",
    "sg:orig_category":"Meubelstoffering",
    "sg:phone":"+31 46 452 3443",
    "sg:postcode":"6135 KE",
    "sg:province":"Limburg",
    "wof:name":"Ben De Graaff",
    "wof:placetype":"venue"
},
  "geometry": {"coordinates":[5.845702,50.998875],"type":"Point"}
}