{
  "type": "Feature",
  "properties": {
    "addr:full":"De Merodestr 3 Leeuwarden Friesland 8937 AA",
    "addr:housenumber":"3",
    "addr:postcode":"8937 aa",
    "iso:country":"NL",
    "sg:address":"De Merodestr 3",
    "sg:city":"Leeuwarden",
    "sg:orig_category":"Meel - Fabrieken En Groothandel",
    "sg:phone":"+31 58 294 8494",
    "sg:postcode":"8937 AA",
    "sg:province":"Friesland",
    "wof:name":"Koopmans Bv",
    "wof:placetype":"venue"
},
  "geometry": {"coordinates":[5.821958,53.199993],"type":"Point"}
}