{
  "type": "Feature",
  "properties": {
    "addr:full":"Stevenswg 34 Dordrecht Zuid-Holland 3319 AK",
    "addr:housenumber":"34",
    "addr:postcode":"3319 ak",
    "addr:street":"Stevenswg",
    "iso:country":"NL",
    "sg:address":"Stevenswg 34",
    "sg:city":"Dordrecht",
    "sg:orig_category":"Ziekenvervoer",
    "sg:phone":"+31 78 616 2111",
    "sg:postcode":"3319 AK",
    "sg:province":"Zuid-Holland",
    "wof:name":"Stam Bv",
    "wof:placetype":"venue"
},
  "geometry": {"coordinates":[4.693077,51.787605],"type":"Point"}
}