{
  "type": "Feature",
  "properties": {
    "addr:full":"Bugel 11 Zevenaar Gelderland 6904 PL",
    "addr:housenumber":"11",
    "addr:postcode":"6904 pl",
    "addr:street":"Bugel",
    "iso:country":"NL",
    "sg:address":"Bugel 11",
    "sg:city":"Zevenaar",
    "sg:orig_category":"Adviesbureaus Bedrijfsorganisatie",
    "sg:phone":"+31 316 528 361",
    "sg:postcode":"6904 PL",
    "sg:province":"Gelderland",
    "wof:name":"Skill",
    "wof:placetype":"venue"
},
  "geometry": {"coordinates":[6.052935,51.936832],"type":"Point"}
}