{
  "type": "Feature",
  "properties": {
    "iso:country":"NL",
    "sg:address":"Schiedamsedijk 61",
    "sg:city":"Rotterdam",
    "sg:orig_category":"Makelaars In Onroerend Goed",
    "sg:phone":"+31 10 213 2488",
    "sg:postcode":"3011 EH",
    "sg:province":"Zuid-Holland",
    "wof:name":"Wmh Bv",
    "wof:placetype":"venue"
},
  "geometry": {"coordinates":[4.481703,51.915707],"type":"Point"}
}