{
  "type": "Feature",
  "properties": {
    "addr:full":"Klaproosln 47 Hoevelaken Gelderland 3871 GG",
    "addr:housenumber":"47",
    "addr:postcode":"3871 gg",
    "addr:street":"Klaproosln;Gelderland",
    "iso:country":"NL",
    "sg:address":"Klaproosln 47",
    "sg:city":"Hoevelaken",
    "sg:orig_category":"Fietsen En Bromfietsen Onderdelen - Fabr. En Grooth",
    "sg:phone":"+31 33 253 5582",
    "sg:postcode":"3871 GG",
    "sg:province":"Gelderland",
    "wof:name":"Bosman, J N",
    "wof:placetype":"venue"
},
  "geometry": {"coordinates":[5.462118,52.174427],"type":"Point"}
}