{
  "type": "Feature",
  "properties": {
    "addr:full":"Stationspln 16 Zutphen Gelderland 7201 ML",
    "addr:housenumber":"16",
    "addr:postcode":"7201 ml",
    "addr:street":"Stationspln;Gelderland",
    "iso:country":"NL",
    "sg:address":"Stationspln 16",
    "sg:city":"Zutphen",
    "sg:orig_category":"Bloemen En Planten",
    "sg:phone":"+31 575 512 155",
    "sg:postcode":"7201 ML",
    "sg:province":"Gelderland",
    "wof:name":"Stations Bloemenshop, Zutphen",
    "wof:placetype":"venue"
},
  "geometry": {"coordinates":[6.191525,52.140202],"type":"Point"}
}