{
  "type": "Feature",
  "properties": {
    "iso:country":"NL",
    "sg:address":"Entrepotdok 52",
    "sg:city":"Amsterdam",
    "sg:orig_category":"Binnenhuisarchitecten",
    "sg:phone":"+31 20 623 4285",
    "sg:postcode":"1018 AD",
    "sg:province":"Noord-Holland",
    "wof:name":"Van Dijk En Partners Bv",
    "wof:placetype":"venue"
},
  "geometry": {"coordinates":[4.915635,52.368423],"type":"Point"}
}