{
  "type": "Feature",
  "properties": {
    "addr:full":"Hoofdstraat 25 Ossenzijl Overijssel 8376 HC",
    "addr:housenumber":"25",
    "addr:postcode":"8376 hc",
    "addr:street":"Hoofdstraat",
    "iso:country":"NL",
    "sg:address":"Hoofdstraat 25",
    "sg:city":"Ossenzijl",
    "sg:orig_category":"Loodgieterswerk, Verwarming And Sanitaire Installaties",
    "sg:phone":"+31 561 477 464",
    "sg:postcode":"8376 HC",
    "sg:province":"Overijssel",
    "wof:name":"Onderhouds En Klussenbedrijf Limburg",
    "wof:placetype":"venue"
},
  "geometry": {"coordinates":[5.919143,52.808525],"type":"Point"}
}