{
  "type": "Feature",
  "properties": {
    "addr:full":"Havenstr 17 Huizen Noord-Holland 1271 AB",
    "addr:housenumber":"17",
    "addr:postcode":"1271 ab",
    "addr:street":"Havenstr",
    "iso:country":"NL",
    "sg:address":"Havenstr 17",
    "sg:city":"Huizen",
    "sg:orig_category":"Huishoudapparatuur, Televisies And Radio'S",
    "sg:phone":"+31 35 525 3631",
    "sg:postcode":"1271 AB",
    "sg:province":"Noord-Holland",
    "wof:name":"Rob Schipper Bang & Olufsen Center",
    "wof:placetype":"venue"
},
  "geometry": {"coordinates":[5.234408,52.298813],"type":"Point"}
}