{
  "type": "Feature",
  "properties": {
    "addr:full":"Godsweerderstraat 33 Roermond Limburg 6041 GH",
    "addr:housenumber":"33",
    "addr:postcode":"6041 gh",
    "addr:street":"Godsweerderstraat",
    "iso:country":"NL",
    "sg:address":"Godsweerderstraat 33",
    "sg:city":"Roermond",
    "sg:orig_category":"Krantenuitgeverijen",
    "sg:phone":"+31 475 330 332",
    "sg:postcode":"6041 GH",
    "sg:province":"Limburg",
    "wof:name":"Adrem Roermond Bv",
    "wof:placetype":"venue"
},
  "geometry": {"coordinates":[5.992447,51.195366],"type":"Point"}
}