{
  "type": "Feature",
  "properties": {
    "addr:full":"Krommeweegje 8 Nieuwe Tonge Zuid-Holland 3244 LL",
    "addr:housenumber":"8",
    "addr:postcode":"3244 ll",
    "addr:street":"Krommeweegje;Nieuwe Tonge",
    "iso:country":"NL",
    "sg:address":"Krommeweegje 8",
    "sg:city":"Nieuwe Tonge",
    "sg:orig_category":"Pluimveebedrijven En -Handelaren",
    "sg:phone":"+31 187 657 005",
    "sg:postcode":"3244 LL",
    "sg:province":"Zuid-Holland",
    "wof:name":"Boed, De",
    "wof:placetype":"venue"
},
  "geometry": {"coordinates":[4.180041,51.716984],"type":"Point"}
}