{
  "type": "Feature",
  "properties": {
    "addr:full":"Valkenhorst 15 Delfzijl Groningen 9932 LS",
    "addr:housenumber":"15",
    "addr:postcode":"9932 ls",
    "addr:street":"Valkenhorst",
    "iso:country":"NL",
    "sg:address":"Valkenhorst 15",
    "sg:city":"Delfzijl",
    "sg:orig_category":"Wasserettes, Stomerijen And Reiniging",
    "sg:phone":"+31 596 624 596",
    "sg:postcode":"9932 LS",
    "sg:province":"Groningen",
    "wof:name":"Chemdry",
    "wof:placetype":"venue"
},
  "geometry": {"coordinates":[6.9012098312,53.3173904419],"type":"Point"}
}