{
  "type": "Feature",
  "properties": {
    "iso:country":"NL",
    "sg:address":"Kamperfoelie 13",
    "sg:city":"Tiel",
    "sg:classifiers":[
        {
            "category":"Fast Food",
            "type":"Food & Drink"
        }
    ],
    "sg:phone":"+31 344 627 422",
    "sg:postcode":"4007 TK",
    "sg:province":"Gelderland",
    "sg:tags":[
        "afhaal",
        "restaurant"
    ],
    "wof:name":"Pierrot",
    "wof:placetype":"venue"
},
  "geometry": {"coordinates":[5.400243,51.870647],"type":"Point"}
}