{
  "type": "Feature",
  "properties": {
    "addr:full":"Prof Gerbrandywg 25 Botlek Rt South Holland 3197 KK",
    "addr:housenumber":"25",
    "addr:postcode":"3197 kk",
    "addr:street":"Botlek Rt South",
    "iso:country":"NL",
    "sg:address":"Prof Gerbrandywg 25",
    "sg:city":"Botlek Rt",
    "sg:orig_category":"Materiaalonderzoek",
    "sg:phone":"+31 800 2863865",
    "sg:postcode":"3197 KK",
    "sg:province":"South Holland",
    "wof:name":"Aib-Vin\u00e7otte Ned Bv",
    "wof:placetype":"venue"
},
  "geometry": {"coordinates":[4.287312,51.89447],"type":"Point"}
}