{
  "type": "Feature",
  "properties": {
    "addr:full":"Koningin Wilhelminastr 2 De Lier South Holland 2678 EM",
    "addr:housenumber":"2",
    "addr:postcode":"2678 em",
    "addr:street":"Koningin Wilhelminastr",
    "iso:country":"NL",
    "sg:address":"Koningin Wilhelminastr 2",
    "sg:city":"De Lier",
    "sg:orig_category":"Granen, Zaden And Diervoeders Gh",
    "sg:phone":"+31 174 512 701",
    "sg:postcode":"2678 EM",
    "sg:province":"South Holland",
    "wof:name":"Van Berkel Zaden",
    "wof:placetype":"venue"
},
  "geometry": {"coordinates":[4.251622,51.974369],"type":"Point"}
}