{
  "type": "Feature",
  "properties": {
    "iso:country":"NL",
    "sg:address":"Jellinghausstr 25",
    "sg:city":"Tilburg",
    "sg:orig_category":"Ventilatiesystemen",
    "sg:phone":"+31 13 455 1898",
    "sg:postcode":"5048 AZ",
    "sg:province":"Noord-Brabant",
    "wof:name":"Donders",
    "wof:placetype":"venue"
},
  "geometry": {"coordinates":[5.052284,51.592258],"type":"Point"}
}