{
  "type": "Feature",
  "properties": {
    "addr:full":"Beugsloepweg 11 Vlaardingen Zuid-Holland 3133 KV",
    "addr:housenumber":"11",
    "addr:postcode":"3133 kv",
    "addr:street":"Beugsloepweg",
    "iso:country":"NL",
    "sg:address":"Beugsloepweg 11",
    "sg:city":"Vlaardingen",
    "sg:orig_category":"Huishoudapparatuur, Televisies And Radio'S",
    "sg:phone":"+31 10 248 3444",
    "sg:postcode":"3133 KV",
    "sg:province":"Zuid-Holland",
    "wof:name":"Nexans Nederland Bv",
    "wof:placetype":"venue"
},
  "geometry": {"coordinates":[4.317282,51.898464],"type":"Point"}
}