{
  "type": "Feature",
  "properties": {
    "addr:full":"Borgwg 100 Uithuizen Groningen 9981 CJ",
    "addr:housenumber":"100",
    "addr:postcode":"9981 cj",
    "addr:street":"Uithuizen",
    "iso:country":"NL",
    "sg:address":"Borgwg 100",
    "sg:city":"Uithuizen",
    "sg:orig_category":"Bejaarden - Verzorgingstehuizen",
    "sg:phone":"+31 595 437 100",
    "sg:postcode":"9981 CJ",
    "sg:province":"Groningen",
    "wof:name":"Hunsingoheerd",
    "wof:placetype":"venue"
},
  "geometry": {"coordinates":[6.679284,53.407345],"type":"Point"}
}