{
  "type": "Feature",
  "properties": {
    "addr:full":"G Doustr 50 Amsterdam Noord-Holland 1072 VT",
    "addr:housenumber":"50",
    "addr:postcode":"1072",
    "iso:country":"NL",
    "sg:address":"G Doustr 50",
    "sg:city":"Amsterdam",
    "sg:orig_category":"Bedrijfsopleidingen",
    "sg:phone":"+31 20 676 6006",
    "sg:postcode":"1072 VT",
    "sg:province":"Noord-Holland",
    "wof:name":"Impulsus",
    "wof:placetype":"venue"
},
  "geometry": {"coordinates":[4.88969,52.355137],"type":"Point"}
}