{
  "type": "Feature",
  "properties": {
    "addr:full":"Poolster 195 Hoorn Nh North Holland 1622 EN",
    "addr:housenumber":"195",
    "addr:postcode":"1622 en",
    "addr:street":"Poolster;Nh North",
    "iso:country":"NL",
    "sg:address":"Poolster 195",
    "sg:city":"Hoorn Nh",
    "sg:orig_category":"Boekhouders",
    "sg:phone":"+31 229 214 706",
    "sg:postcode":"1622 EN",
    "sg:province":"North Holland",
    "wof:name":"Administratiekantoor H.F. De Geus",
    "wof:placetype":"venue"
},
  "geometry": {"coordinates":[5.037726,52.639065],"type":"Point"}
}