{
  "type": "Feature",
  "properties": {
    "addr:full":"Herengracht 46 'S Gravenhage South Holland 2511 EJ",
    "addr:housenumber":"46",
    "addr:postcode":"2511 ej",
    "addr:street":"Herengracht;' S Gravenhage",
    "iso:country":"NL",
    "sg:address":"Herengracht 46",
    "sg:city":"'S Gravenhage",
    "sg:orig_category":"Werving And Selectie Van Tijdelijk Personeel And Uitzendkantoren",
    "sg:phone":"+31 70 346 8820",
    "sg:postcode":"2511 EJ",
    "sg:province":"South Holland",
    "wof:name":"Uitz. Bur. Olympia",
    "wof:placetype":"venue"
},
  "geometry": {"coordinates":[4.3195128441,52.0810928345],"type":"Point"}
}