{
  "type": "Feature",
  "properties": {
    "addr:full":"Jhr. Von Heijdenstraat 2 Haaksbergen Overijssel 7481 ED",
    "addr:housenumber":"2",
    "addr:postcode":"7481 ed",
    "addr:street":"Jhr. Von Heijdenstraat",
    "iso:country":"NL",
    "sg:address":"Jhr. Von Heijdenstraat 2",
    "sg:city":"Haaksbergen",
    "sg:classifiers":[
        {
            "category":"Shopping",
            "subcategory":"Gifts & Souvenirs",
            "type":"Retail Goods"
        }
    ],
    "sg:phone":"+31 53 572 8979",
    "sg:postcode":"7481 ED",
    "sg:province":"Overijssel",
    "sg:tags":[
        "geschenken"
    ],
    "wof:name":"Wereldwinkel",
    "wof:placetype":"venue"
},
  "geometry": {"coordinates":[6.742764,52.154301],"type":"Point"}
}