{
  "type": "Feature",
  "properties": {
    "addr:full":"Wirdumerdk 4 Leeuwarden Friesland 8911 CD",
    "addr:housenumber":"4",
    "addr:postcode":"8911 cd",
    "addr:street":"Wirdumerdk",
    "iso:country":"NL",
    "sg:address":"Wirdumerdk 4",
    "sg:city":"Leeuwarden",
    "sg:orig_category":"Fotozaken",
    "sg:phone":"+31 58 213 0683",
    "sg:postcode":"8911 CD",
    "sg:province":"Friesland",
    "wof:name":"Super Photo",
    "wof:placetype":"venue"
},
  "geometry": {"coordinates":[5.796655,53.200581],"type":"Point"}
}