{
  "type": "Feature",
  "properties": {
    "iso:country":"NL",
    "sg:address":"Haarweg 4",
    "sg:city":"Spijk Gem Lingewaal",
    "sg:orig_category":"Verhuur Catering-, Feest- En Evenementbenodigdheden",
    "sg:phone":"+31 183 623 227",
    "sg:postcode":"4212 KJ",
    "sg:province":"South Holland",
    "wof:name":"Fa. Hagra",
    "wof:placetype":"venue"
},
  "geometry": {"coordinates":[5.009242,51.857021],"type":"Point"}
}