{
  "type": "Feature",
  "properties": {
    "addr:full":"Louwestraat 22 Katwijk Zh South Holland 2225 GJ",
    "addr:housenumber":"22",
    "addr:postcode":"zh;2225 gj",
    "addr:street":"Louwestraat",
    "iso:country":"NL",
    "sg:address":"Louwestraat 22",
    "sg:city":"Katwijk Zh",
    "sg:orig_category":"Schilderwerk",
    "sg:phone":"+31 71 401 2035",
    "sg:postcode":"2225 GJ",
    "sg:province":"South Holland",
    "wof:name":"Schildersbedrijf Gerco",
    "wof:placetype":"venue"
},
  "geometry": {"coordinates":[4.394379,52.202633],"type":"Point"}
}