{
  "type": "Feature",
  "properties": {
    "iso:country":"NL",
    "sg:address":"Koekoekslaan 85",
    "sg:city":"Schiedam",
    "sg:orig_category":"Boekhouders",
    "sg:phone":"+31 10 471 4835",
    "sg:postcode":"3121 XJ",
    "sg:province":"South Holland",
    "wof:name":"Drs. C.A. Vollebregt Administratie",
    "wof:placetype":"venue"
},
  "geometry": {"coordinates":[4.382214,51.936073],"type":"Point"}
}