{
  "type": "Feature",
  "properties": {
    "addr:full":"Antwerpsestraat 244 Putte North Brabant 4645 BR",
    "addr:housenumber":"244",
    "addr:postcode":"4645 br",
    "addr:street":"Antwerpsestraat",
    "iso:country":"NL",
    "sg:address":"Antwerpsestraat 244",
    "sg:city":"Putte",
    "sg:orig_category":"Autokeuringen",
    "sg:phone":"+31 164 602 510",
    "sg:postcode":"4645 BR",
    "sg:province":"North Brabant",
    "wof:name":"Garagebedrijf En Servicestation A. Van Oers",
    "wof:placetype":"venue"
},
  "geometry": {"coordinates":[4.390054,51.365761],"type":"Point"}
}