{
  "type": "Feature",
  "properties": {
    "addr:full":"Middelgraaf 1 Ulft Gelderland 7071 WT",
    "addr:housenumber":"1",
    "addr:postcode":"7071 wt",
    "addr:street":"Middelgraaf;Gelderland",
    "iso:country":"NL",
    "sg:address":"Middelgraaf 1",
    "sg:city":"Ulft",
    "sg:orig_category":"Banken And Kredietinstellingen",
    "sg:phone":"+31 315 683 925",
    "sg:postcode":"7071 WT",
    "sg:province":"Gelderland",
    "wof:name":"Ing Bank",
    "wof:placetype":"venue"
},
  "geometry": {"coordinates":[6.381138,51.890995],"type":"Point"}
}