{
  "type": "Feature",
  "properties": {
    "addr:full":"J Byhouwerstr 28 Ysselstein Ut Utrecht 3404 AM",
    "addr:housenumber":"28",
    "addr:postcode":"3404",
    "addr:street":"Ysselstein",
    "iso:country":"NL",
    "sg:address":"J Byhouwerstr 28",
    "sg:city":"Ysselstein Ut",
    "sg:orig_category":"Woningstoffeerders",
    "sg:phone":"+31 30 687 4324",
    "sg:postcode":"3404 AM",
    "sg:province":"Utrecht",
    "wof:name":"Friends",
    "wof:placetype":"venue"
},
  "geometry": {"coordinates":[5.0453209877,52.0117874146],"type":"Point"}
}