{
  "type": "Feature",
  "properties": {
    "addr:full":"Nautiluswg 33 Utrecht Utrecht 3542 AT",
    "addr:housenumber":"33",
    "addr:postcode":"3542",
    "addr:street":"Nautiluswg",
    "iso:country":"NL",
    "sg:address":"Nautiluswg 33",
    "sg:city":"Utrecht",
    "sg:orig_category":"Lpg-Installaties - Fabrieken En Groothandel",
    "sg:phone":"+31 30 241 2333",
    "sg:postcode":"3542 AT",
    "sg:province":"Utrecht",
    "sg:website":"http://www.eurogas.nl",
    "wof:name":"Eurogas Utrecht Bv",
    "wof:placetype":"venue"
},
  "geometry": {"coordinates":[5.044513,52.116425],"type":"Point"}
}