{
  "type": "Feature",
  "properties": {
    "iso:country":"NL",
    "sg:address":"Patersstr 60A",
    "sg:city":"Venray",
    "sg:orig_category":"Verzekeringen - Verzekeringskantoren",
    "sg:phone":"+31 478 513 600",
    "sg:postcode":"5801 AV",
    "sg:province":"Limburg",
    "wof:name":"Gritter & Sevink",
    "wof:placetype":"venue"
},
  "geometry": {"coordinates":[5.976008,51.522621],"type":"Point"}
}