{
  "type": "Feature",
  "properties": {
    "addr:full":"Kasteeldrift 60 Nieuwegein Utrecht 3436 TP",
    "addr:housenumber":"60",
    "addr:postcode":"3436 tp",
    "addr:street":"Kasteeldrift",
    "iso:country":"NL",
    "sg:address":"Kasteeldrift 60",
    "sg:city":"Nieuwegein",
    "sg:orig_category":"Koeriersdiensten",
    "sg:phone":"+31 30 605 5196",
    "sg:postcode":"3436 TP",
    "sg:province":"Utrecht",
    "wof:name":"East- Side",
    "wof:placetype":"venue"
},
  "geometry": {"coordinates":[5.074141,52.037998],"type":"Point"}
}