{
  "type": "Feature",
  "properties": {
    "addr:full":"Corversplein 12 Maastricht Limburg 6221 EZ",
    "addr:housenumber":"12",
    "addr:postcode":"6221 ez",
    "addr:street":"Corversplein",
    "iso:country":"NL",
    "sg:address":"Corversplein 12",
    "sg:city":"Maastricht",
    "sg:orig_category":"Herenmodezaken",
    "sg:phone":"+31 43 321 7300",
    "sg:postcode":"6221 EZ",
    "sg:province":"Limburg",
    "wof:name":"T Jacquetsje",
    "wof:placetype":"venue"
},
  "geometry": {"coordinates":[5.697732,50.848976],"type":"Point"}
}