{
  "type": "Feature",
  "properties": {
    "addr:full":"Handelskd 2E Den Helder Noord-Holland 1785 AC",
    "addr:housenumber":"2e",
    "addr:postcode":"1785 ac",
    "addr:street":"Handelskd",
    "iso:country":"NL",
    "sg:address":"Handelskd 2E",
    "sg:city":"Den Helder",
    "sg:orig_category":"Koeltechniek",
    "sg:phone":"+31 223 610 122",
    "sg:postcode":"1785 AC",
    "sg:province":"Noord-Holland",
    "wof:name":"Kl",
    "wof:placetype":"venue"
},
  "geometry": {"coordinates":[4.758825,52.958191],"type":"Point"}
}