{
  "type": "Feature",
  "properties": {
    "addr:full":"Doetinchemsewg 53 Doetinchem Gelderland 7007 CB",
    "addr:housenumber":"53",
    "addr:postcode":"7007 cb",
    "addr:street":"Doetinchemsewg;Gelderland",
    "iso:country":"NL",
    "sg:address":"Doetinchemsewg 53",
    "sg:city":"Doetinchem",
    "sg:orig_category":"Haarden En Kachels",
    "sg:phone":"+31 314 345 016",
    "sg:postcode":"7007 CB",
    "sg:province":"Gelderland",
    "sg:website":"http://www.kachelbouw.nl",
    "wof:name":"Kachelbouw Doetinchem",
    "wof:placetype":"venue"
},
  "geometry": {"coordinates":[6.284721,51.948696],"type":"Point"}
}