{
  "type": "Feature",
  "properties": {
    "iso:country":"NL",
    "sg:address":"Gerben Sondermanstraat 8",
    "sg:city":"Heerlen",
    "sg:orig_category":"Hoger Onderwijs",
    "sg:phone":"+31 45 542 1471",
    "sg:postcode":"6417 GD",
    "sg:province":"Limburg",
    "wof:name":"Modevakschool Ensaid Marleen Coolen",
    "wof:placetype":"venue"
},
  "geometry": {"coordinates":[5.985367,50.874878],"type":"Point"}
}