{
  "type": "Feature",
  "properties": {
    "addr:full":"Pr W Alexanderstr 2 Lopik Utrecht 3411 BG",
    "addr:housenumber":"2",
    "addr:postcode":"3411",
    "addr:street":"W Alexanderstr",
    "iso:country":"NL",
    "sg:address":"Pr W Alexanderstr 2",
    "sg:city":"Lopik",
    "sg:orig_category":"Postkantoren",
    "sg:phone":"+31 348 554 093",
    "sg:postcode":"3411 BG",
    "sg:province":"Utrecht",
    "sg:website":"http://www.postkantoor.nl",
    "wof:name":"Postkantoor",
    "wof:placetype":"venue"
},
  "geometry": {"coordinates":[4.949712,51.974659],"type":"Point"}
}