{
  "type": "Feature",
  "properties": {
    "addr:full":"Hazelaarstraat 16 Sint Willebrord North Brabant 4711 RE",
    "addr:housenumber":"16",
    "addr:postcode":"4711 re",
    "addr:street":"Hazelaarstraat",
    "iso:country":"NL",
    "sg:address":"Hazelaarstraat 16",
    "sg:city":"Sint Willebrord",
    "sg:orig_category":"Autokeuringen",
    "sg:phone":"+31 165 383 551",
    "sg:postcode":"4711 RE",
    "sg:province":"North Brabant",
    "wof:name":"Kemaco Bv",
    "wof:placetype":"venue"
},
  "geometry": {"coordinates":[4.578501,51.54689],"type":"Point"}
}