{
  "type": "Feature",
  "properties": {
    "addr:full":"Gedempte Pol 26 Sneek Provincie Friesland 8601 BZ",
    "addr:housenumber":"26",
    "addr:postcode":"8601 bz",
    "addr:street":"Gedempte Pol;Provincie Friesland",
    "iso:country":"NL",
    "sg:address":"Gedempte Pol 26",
    "sg:city":"Sneek",
    "sg:orig_category":"Fotostudio'S And Fotografen",
    "sg:phone":"+31 515 414 732",
    "sg:postcode":"8601 BZ",
    "sg:province":"Provincie Friesland",
    "wof:name":"Fotografie Wim Obbema",
    "wof:placetype":"venue"
},
  "geometry": {"coordinates":[5.661765,53.033756],"type":"Point"}
}