{
  "type": "Feature",
  "properties": {
    "addr:full":"Past Jongeriusstr 19 Klazienaveen Drenthe 7891 KM",
    "addr:housenumber":"19",
    "addr:postcode":"7891 km",
    "iso:country":"NL",
    "sg:address":"Past Jongeriusstr 19",
    "sg:city":"Klazienaveen",
    "sg:orig_category":"Automaterialen En Gereedschappen",
    "sg:phone":"+31 591 315 832",
    "sg:postcode":"7891 KM",
    "sg:province":"Drenthe",
    "wof:name":"Blaauwgeers",
    "wof:placetype":"venue"
},
  "geometry": {"coordinates":[6.994521,52.723293],"type":"Point"}
}