{
  "type": "Feature",
  "properties": {
    "iso:country":"NL",
    "sg:address":"Tournooi 1",
    "sg:city":"Krimpen A/D Ijssel",
    "sg:orig_category":"Verzekeringen",
    "sg:phone":"+31 180 513 366",
    "sg:postcode":"2924 VD",
    "sg:province":"South Holland",
    "wof:name":"J M Schox Assurantien",
    "wof:placetype":"venue"
},
  "geometry": {"coordinates":[4.603595,51.923283],"type":"Point"}
}