{
  "type": "Feature",
  "properties": {
    "iso:country":"NL",
    "sg:address":"Raadhuisstraat 6",
    "sg:city":"Heerhugowaard",
    "sg:orig_category":"Baby- And Kinderkleding",
    "sg:phone":"+31 72 572 5566",
    "sg:postcode":"1701 EK",
    "sg:province":"North Holland",
    "wof:name":"Jasper En Jasmijn",
    "wof:placetype":"venue"
},
  "geometry": {"coordinates":[4.84505,52.669678],"type":"Point"}
}