{
  "type": "Feature",
  "properties": {
    "addr:full":"Pomonapln 75 S Gravenhage South Holland 2564 XT",
    "addr:housenumber":"75",
    "addr:postcode":"2564 xt",
    "addr:street":"Pomonapln;S Gravenhage",
    "iso:country":"NL",
    "sg:address":"Pomonapln 75",
    "sg:city":"S Gravenhage",
    "sg:orig_category":"Administratie- En Boekhoudkantoren",
    "sg:phone":"+31 70 323 5963",
    "sg:postcode":"2564 XT",
    "sg:province":"South Holland",
    "wof:name":"Bernard",
    "wof:placetype":"venue"
},
  "geometry": {"coordinates":[4.25946,52.06805],"type":"Point"}
}