{
  "type": "Feature",
  "properties": {
    "addr:full":"Heuvel Galerie 15 Eindhoven Noord-Brabant 5611 DK",
    "addr:housenumber":"15",
    "addr:postcode":"5611 dk",
    "addr:street":"Heuvel Galerie",
    "iso:country":"NL",
    "sg:address":"Heuvel Galerie 15",
    "sg:city":"Eindhoven",
    "sg:orig_category":"Zuivelproducten",
    "sg:phone":"+31 40 245 6275",
    "sg:postcode":"5611 DK",
    "sg:province":"Noord-Brabant",
    "wof:name":"Kaasshop Heuvelgalerie",
    "wof:placetype":"venue"
},
  "geometry": {"coordinates":[5.484105,51.434471],"type":"Point"}
}