{
  "type": "Feature",
  "properties": {
    "iso:country":"NL",
    "sg:address":"Hulst 126",
    "sg:city":"Geldrop",
    "sg:orig_category":"Honden- En Kattentrimsalons",
    "sg:phone":"+31 40 286 8061",
    "sg:postcode":"5662 TK",
    "sg:province":"Noord-Brabant",
    "wof:name":"Bonna Vista Trimsalon",
    "wof:placetype":"venue"
},
  "geometry": {"coordinates":[5.54186,51.431423],"type":"Point"}
}