{
  "type": "Feature",
  "properties": {
    "iso:country":"NL",
    "sg:address":"Burg Verderln 13",
    "sg:city":"Utrecht",
    "sg:orig_category":"Vakorganisaties",
    "sg:phone":"+31 30 669 1966",
    "sg:postcode":"3544 AD",
    "sg:province":"Utrecht",
    "wof:name":"Gasturbine, Ver",
    "wof:placetype":"venue"
},
  "geometry": {"coordinates":[5.05156,52.091202],"type":"Point"}
}