{
  "type": "Feature",
  "properties": {
    "addr:full":"Rivierkade 1 Geertruidenberg North Brabant 4931 AA",
    "addr:housenumber":"1",
    "addr:postcode":"4931 aa",
    "addr:street":"Rivierkade",
    "iso:country":"NL",
    "sg:address":"Rivierkade 1",
    "sg:city":"Geertruidenberg",
    "sg:orig_category":"Pleziervaartuigen And Reparatie",
    "sg:phone":"+31 162 512 290",
    "sg:postcode":"4931 AA",
    "sg:province":"North Brabant",
    "wof:name":"Nederlof Scheepsbouw Bv",
    "wof:placetype":"venue"
},
  "geometry": {"coordinates":[4.860261,51.706284],"type":"Point"}
}