{
  "type": "Feature",
  "properties": {
    "iso:country":"NL",
    "sg:address":"Monsterseweg 5",
    "sg:city":"'S Gravenzande",
    "sg:orig_category":"Fitnesscentra",
    "sg:phone":"+31 174 417 092",
    "sg:postcode":"2691 JA",
    "sg:province":"Zuid-Holland",
    "wof:name":"High Line",
    "wof:placetype":"venue"
},
  "geometry": {"coordinates":[4.158682,52.005566],"type":"Point"}
}