{
  "type": "Feature",
  "properties": {
    "addr:full":"Vondelweg 538 Haarlem Noord-Holland 2026 BH",
    "addr:housenumber":"538",
    "addr:postcode":"2026 bh",
    "addr:street":"Vondelweg",
    "iso:country":"NL",
    "sg:address":"Vondelweg 538",
    "sg:city":"Haarlem",
    "sg:orig_category":"Boekhouders",
    "sg:phone":"+31 23 537 2653",
    "sg:postcode":"2026 BH",
    "sg:province":"Noord-Holland",
    "wof:name":"Administratiekantoor J. Visser",
    "wof:placetype":"venue"
},
  "geometry": {"coordinates":[4.651911,52.420998],"type":"Point"}
}