{
  "type": "Feature",
  "properties": {
    "addr:full":"Abel Tasmanplantsoen 16 Voorschoten Zuid-Holland 2253 KA",
    "addr:housenumber":"16",
    "addr:postcode":"2253 ka",
    "addr:street":"Abel Tasmanplantsoen",
    "iso:country":"NL",
    "sg:address":"Abel Tasmanplantsoen 16",
    "sg:city":"Voorschoten",
    "sg:orig_category":"Vertaal- And Tolkenbureaus",
    "sg:phone":"+31 71 531 5030",
    "sg:postcode":"2253 KA",
    "sg:province":"Zuid-Holland",
    "wof:name":"Japan Research",
    "wof:placetype":"venue"
},
  "geometry": {"coordinates":[4.462776,52.138409],"type":"Point"}
}