{
  "type": "Feature",
  "properties": {
    "addr:full":"Haarlemmerstraat 87 Amsterdam Noord-Holland 1013 EL",
    "addr:housenumber":"87;1013",
    "addr:postcode":"el",
    "addr:street":"Haarlemmerstraat",
    "iso:country":"NL",
    "sg:address":"Haarlemmerstraat 87",
    "sg:city":"Amsterdam",
    "sg:orig_category":"Boekenuitgeverijen",
    "sg:phone":"+31 20 625 5640",
    "sg:postcode":"1013 EL",
    "sg:province":"Noord-Holland",
    "wof:name":"De Klaroenstoot",
    "wof:placetype":"venue"
},
  "geometry": {"coordinates":[4.891175,52.380348],"type":"Point"}
}