{
  "type": "Feature",
  "properties": {
    "iso:country":"NL",
    "sg:address":"Geuzingerbrink 4",
    "sg:city":"Emmen",
    "sg:orig_category":"Administratie- En Boekhoudkantoren",
    "sg:phone":"+31 591 614 638",
    "sg:postcode":"7812 NV",
    "sg:province":"Drenthe",
    "wof:name":"Bouman",
    "wof:placetype":"venue"
},
  "geometry": {"coordinates":[6.88234,52.76696],"type":"Point"}
}