{
  "type": "Feature",
  "properties": {
    "addr:full":"Berkhofwg 42 Lunteren Gelderland 6741 XS",
    "addr:housenumber":"42",
    "addr:postcode":"6741 xs",
    "addr:street":"Berkhofwg;Gelderland",
    "iso:country":"NL",
    "sg:address":"Berkhofwg 42",
    "sg:city":"Lunteren",
    "sg:orig_category":"Koeriersdiensten",
    "sg:phone":"+31 318 487 774",
    "sg:postcode":"6741 XS",
    "sg:province":"Gelderland",
    "sg:website":"HTTP://www.sneltransportpater.nl",
    "wof:name":"Pater Sneltransport",
    "wof:placetype":"venue"
},
  "geometry": {"coordinates":[5.613584,52.091568],"type":"Point"}
}