{
  "type": "Feature",
  "properties": {
    "iso:country":"NL",
    "sg:address":"Kanaalwg 14C",
    "sg:city":"Harlingen",
    "sg:orig_category":"Satellietontvangst- En Antenne-Installaties",
    "sg:phone":"+31 517 431 291",
    "sg:postcode":"8861 KE",
    "sg:province":"Friesland",
    "sg:website":"http://www.telesto.nl",
    "wof:name":"Telesto",
    "wof:placetype":"venue"
},
  "geometry": {"coordinates":[5.428613,53.174225],"type":"Point"}
}