{
  "type": "Feature",
  "properties": {
    "iso:country":"NL",
    "sg:address":"Fruitlaan 87",
    "sg:city":"Zwaag",
    "sg:classifiers":[
        {
            "category":"Professional",
            "subcategory":"Accounting & Tax Preparation",
            "type":"Services"
        }
    ],
    "sg:phone":"+31 229 238 151",
    "sg:postcode":"1689 HH",
    "sg:province":"North Holland",
    "sg:tags":[
        "accountant"
    ],
    "wof:name":"Bot",
    "wof:placetype":"venue"
},
  "geometry": {"coordinates":[5.071458,52.665894],"type":"Point"}
}