{
  "type": "Feature",
  "properties": {
    "iso:country":"NL",
    "sg:address":"Ringvaartwg 12",
    "sg:city":"Beverwyk",
    "sg:orig_category":"Koel- En Vrieshuizen",
    "sg:phone":"+31 251 212 538",
    "sg:postcode":"1948 PE",
    "sg:province":"North Holland",
    "wof:name":"Vink",
    "wof:placetype":"venue"
},
  "geometry": {"coordinates":[4.673322,52.479103],"type":"Point"}
}