{
  "type": "Feature",
  "properties": {
    "addr:full":"Amsterdamseweg 1 Ede Gld Gelderland 6711 BE",
    "addr:housenumber":"1",
    "addr:postcode":"6711",
    "addr:street":"Amsterdamseweg;Gld Gelderland",
    "iso:country":"NL",
    "sg:address":"Amsterdamseweg 1",
    "sg:city":"Ede Gld",
    "sg:orig_category":"Autokeuringen",
    "sg:phone":"+31 318 610 382",
    "sg:postcode":"6711 BE",
    "sg:province":"Gelderland",
    "wof:name":"Automobielbedrijf Brouwer",
    "wof:placetype":"venue"
},
  "geometry": {"coordinates":[5.6703,52.048981],"type":"Point"}
}