{
  "type": "Feature",
  "properties": {
    "addr:full":"H R Holststr 29 Tiel Gelderland 4003 DS",
    "addr:housenumber":"29",
    "addr:postcode":"4003 ds",
    "addr:street":"H;Holststr;Gelderland",
    "iso:country":"NL",
    "sg:address":"H R Holststr 29",
    "sg:city":"Tiel",
    "sg:orig_category":"Zonnebank- En Solariumcentra",
    "sg:phone":"+31 344 621 965",
    "sg:postcode":"4003 DS",
    "sg:province":"Gelderland",
    "wof:name":"Paradise",
    "wof:placetype":"venue"
},
  "geometry": {"coordinates":[5.430696,51.888096],"type":"Point"}
}