{
  "type": "Feature",
  "properties": {
    "addr:full":"Harpij 5 Heerhugowaard Noord-Holland 1704 TA",
    "addr:housenumber":"5",
    "addr:postcode":"1704 ta",
    "addr:street":"Harpij",
    "iso:country":"NL",
    "sg:address":"Harpij 5",
    "sg:city":"Heerhugowaard",
    "sg:orig_category":"Schilderwerk",
    "sg:phone":"+31 72 571 7450",
    "sg:postcode":"1704 TA",
    "sg:province":"Noord-Holland",
    "wof:name":"Schildersbedrijf Ab Vreeker",
    "wof:placetype":"venue"
},
  "geometry": {"coordinates":[4.816932,52.655167],"type":"Point"}
}