{
  "type": "Feature",
  "properties": {
    "iso:country":"NL",
    "sg:address":"Pater Van De Elsenstraat 2",
    "sg:city":"Oisterwijk",
    "sg:orig_category":"Kappers",
    "sg:phone":"+31 13 528 3157",
    "sg:postcode":"5062 CX",
    "sg:province":"North Brabant",
    "wof:name":"Marijke Van Der Poel Dameskapster",
    "wof:placetype":"venue"
},
  "geometry": {"coordinates":[5.197906,51.574883],"type":"Point"}
}