{
  "type": "Feature",
  "properties": {
    "addr:full":"Drossaardslag 122 Gouda Zuid-Holland 2805 DD",
    "addr:housenumber":"122",
    "addr:postcode":"2805 dd",
    "addr:street":"Drossaardslag",
    "iso:country":"NL",
    "sg:address":"Drossaardslag 122",
    "sg:city":"Gouda",
    "sg:orig_category":"Fitnesscentra",
    "sg:phone":"+31 182 525 141",
    "sg:postcode":"2805 DD",
    "sg:province":"Zuid-Holland",
    "wof:name":"Sportschool Van Elten",
    "wof:placetype":"venue"
},
  "geometry": {"coordinates":[4.726143,52.022049],"type":"Point"}
}