{
  "type": "Feature",
  "properties": {
    "addr:full":"Etnastraat 20 Breda Noord-Brabant 4814 AA",
    "addr:housenumber":"20",
    "addr:postcode":"4814 aa",
    "addr:street":"Etnastraat",
    "iso:country":"NL",
    "sg:address":"Etnastraat 20",
    "sg:city":"Breda",
    "sg:orig_category":"Public Relationbureaus",
    "sg:phone":"+31 76 520 0567",
    "sg:postcode":"4814 AA",
    "sg:province":"Noord-Brabant",
    "wof:name":"Imc Partners",
    "wof:placetype":"venue"
},
  "geometry": {"coordinates":[4.769433,51.592804],"type":"Point"}
}