{
  "type": "Feature",
  "properties": {
    "iso:country":"NL",
    "sg:address":"Van Bijlandtplaats 31",
    "sg:city":"Rotterdam",
    "sg:orig_category":"Diverse Consumentenartikelen Gh",
    "sg:phone":"+31 10 404 9099",
    "sg:postcode":"3012 GA",
    "sg:province":"Zuid-Holland",
    "wof:name":"Heer Beer Promoties & Trading Bv",
    "wof:placetype":"venue"
},
  "geometry": {"coordinates":[4.476181,51.918835],"type":"Point"}
}