{
  "type": "Feature",
  "properties": {
    "iso:country":"NL",
    "sg:address":"Achterstestr 103",
    "sg:city":"Weert",
    "sg:orig_category":"Verlichtingsartikelen - Groothandel",
    "sg:phone":"+31 495 535 688",
    "sg:postcode":"6004 AW",
    "sg:province":"Limburg",
    "wof:name":"Boxtel, Van",
    "wof:placetype":"venue"
},
  "geometry": {"coordinates":[5.736737,51.253735],"type":"Point"}
}