{
  "type": "Feature",
  "properties": {
    "addr:full":"Grote Woerdlaan 8 Naaldwijk Zuid-Holland 2671 CL",
    "addr:housenumber":"8",
    "addr:postcode":"2671",
    "addr:street":"Grote Woerdlaan",
    "iso:country":"NL",
    "sg:address":"Grote Woerdlaan 8",
    "sg:city":"Naaldwijk",
    "sg:orig_category":"Goederenvervoer Over De Weg",
    "sg:phone":"+31 174 624 774",
    "sg:postcode":"2671 CL",
    "sg:province":"Zuid-Holland",
    "wof:name":"Vof Leo De Jong Autodiensten",
    "wof:placetype":"venue"
},
  "geometry": {"coordinates":[4.210357,51.99844],"type":"Point"}
}