{
  "type": "Feature",
  "properties": {
    "iso:country":"NL",
    "sg:address":"Grote Woerdlaan 8",
    "sg:city":"Naaldwijk",
    "sg:orig_category":"Goederenvervoer Over De Weg",
    "sg:phone":"+31 174 624 774",
    "sg:postcode":"2671 CL",
    "sg:province":"Zuid-Holland",
    "wof:name":"Vof Leo De Jong Autodiensten",
    "wof:placetype":"venue"
},
  "geometry": {"coordinates":[4.210357,51.99844],"type":"Point"}
}