{
  "type": "Feature",
  "properties": {
    "addr:full":"Dokter Holtropstraat 148 Ermelo Gelderland 3851 JM",
    "addr:housenumber":"148",
    "addr:postcode":"3851 jm",
    "addr:street":"Dokter Holtropstraat;Gelderland",
    "iso:country":"NL",
    "sg:address":"Dokter Holtropstraat 148",
    "sg:city":"Ermelo",
    "sg:orig_category":"Kappers",
    "sg:phone":"+31 341 557 759",
    "sg:postcode":"3851 JM",
    "sg:province":"Gelderland",
    "wof:name":"Kapsalon Elegance",
    "wof:placetype":"venue"
},
  "geometry": {"coordinates":[5.6122322083,52.2975692749],"type":"Point"}
}