{
  "type": "Feature",
  "properties": {
    "iso:country":"NL",
    "sg:address":"Margrietstraat 22",
    "sg:city":"'S Gravenhage",
    "sg:orig_category":"Technische Studies And Onderzoek",
    "sg:phone":"+31 70 368 7062",
    "sg:postcode":"2555 PW",
    "sg:province":"Zuid-Holland",
    "wof:name":"Pollution Prevention Consulting Bv",
    "wof:placetype":"venue"
},
  "geometry": {"coordinates":[4.237352,52.065941],"type":"Point"}
}