{
  "type": "Feature",
  "properties": {
    "addr:full":"Heuvel 19 Oosterhout Nb Noord-Brabant 4901 KB",
    "addr:housenumber":"19",
    "addr:postcode":"4901 kb",
    "addr:street":"Heuvel",
    "iso:country":"NL",
    "sg:address":"Heuvel 19",
    "sg:city":"Oosterhout Nb",
    "sg:orig_category":"Dansscholen",
    "sg:phone":"+31 162 422 025",
    "sg:postcode":"4901 KB",
    "sg:province":"Noord-Brabant",
    "wof:name":"Stichting Kunstzinnige Vorming H 19",
    "wof:placetype":"venue"
},
  "geometry": {"coordinates":[4.856084,51.642719],"type":"Point"}
}