{
  "type": "Feature",
  "properties": {
    "addr:full":"Olmenhof 20 Sleeuwyk North Brabant 4254 BN",
    "addr:housenumber":"20",
    "addr:postcode":"4254 bn",
    "addr:street":"Olmenhof",
    "iso:country":"NL",
    "sg:address":"Olmenhof 20",
    "sg:city":"Sleeuwyk",
    "sg:orig_category":"Psychologen",
    "sg:phone":"+31 183 307 375",
    "sg:postcode":"4254 BN",
    "sg:province":"North Brabant",
    "wof:name":"Hartman, M S C H",
    "wof:placetype":"venue"
},
  "geometry": {"coordinates":[4.947924,51.815575],"type":"Point"}
}