{
  "type": "Feature",
  "properties": {
    "addr:full":"Rinnewaard 31 Alkmaar Noord-Holland 1824 JB",
    "addr:housenumber":"31",
    "addr:postcode":"1824 jb",
    "addr:street":"Rinnewaard",
    "iso:country":"NL",
    "sg:address":"Rinnewaard 31",
    "sg:city":"Alkmaar",
    "sg:orig_category":"Journalisten Freelance",
    "sg:phone":"+31 72 562 4543",
    "sg:postcode":"1824 JB",
    "sg:province":"Noord-Holland",
    "wof:name":"Brink, C Van Den",
    "wof:placetype":"venue"
},
  "geometry": {"coordinates":[4.756244,52.641369],"type":"Point"}
}