{
  "type": "Feature",
  "properties": {
    "addr:full":"Reinier Noomsstraat 33 Ouderkerk A/D Amstel North Holland 1191 ET",
    "addr:housenumber":"33;a / d",
    "addr:postcode":"1191 et",
    "addr:street":"Reinier Noomsstraat;Amstel North",
    "iso:country":"NL",
    "sg:address":"Reinier Noomsstraat 33",
    "sg:city":"Ouderkerk A/D Amstel",
    "sg:orig_category":"Loodgieterswerk, Verwarming And Sanitaire Installaties",
    "sg:phone":"+31 20 496 5210",
    "sg:postcode":"1191 ET",
    "sg:province":"North Holland",
    "wof:name":"Loodgieter- En Installatiebedrijf B. Snijder",
    "wof:placetype":"venue"
},
  "geometry": {"coordinates":[4.915538,52.299637],"type":"Point"}
}