{
  "type": "Feature",
  "properties": {
    "iso:country":"NL",
    "sg:address":"Stationsstr 46",
    "sg:city":"Zelhem",
    "sg:orig_category":"Kinderkleding",
    "sg:phone":"+31 314 624 194",
    "sg:postcode":"7021 CK",
    "sg:province":"Gelderland",
    "wof:name":"Duddul & Biebel",
    "wof:placetype":"venue"
},
  "geometry": {"coordinates":[6.351377,52.00507],"type":"Point"}
}