{
  "type": "Feature",
  "properties": {
    "iso:country":"NL",
    "sg:address":"Torendk 13",
    "sg:city":"Ambt Delden",
    "sg:orig_category":"Pluimveebedrijven En -Handelaren",
    "sg:phone":"+31 547 292 335",
    "sg:postcode":"7495 PX",
    "sg:province":"Overijssel",
    "wof:name":"Jannink, J G M",
    "wof:placetype":"venue"
},
  "geometry": {"coordinates":[6.710581,52.250076],"type":"Point"}
}