{
  "type": "Feature",
  "properties": {
    "addr:full":"Torendk 13 Ambt Delden Overijssel 7495 PX",
    "addr:housenumber":"13",
    "addr:postcode":"7495 px",
    "addr:street":"Torendk",
    "iso:country":"NL",
    "sg:address":"Torendk 13",
    "sg:city":"Ambt Delden",
    "sg:orig_category":"Pluimveebedrijven En -Handelaren",
    "sg:phone":"+31 547 292 335",
    "sg:postcode":"7495 PX",
    "sg:province":"Overijssel",
    "wof:name":"Jannink, J G M",
    "wof:placetype":"venue"
},
  "geometry": {"coordinates":[6.710581,52.250076],"type":"Point"}
}