{
  "type": "Feature",
  "properties": {
    "addr:full":"Heerlerbaan 134 Heerlen Limburg 6418 CJ",
    "addr:housenumber":"134",
    "addr:postcode":"6418 cj",
    "addr:street":"Heerlerbaan",
    "iso:country":"NL",
    "sg:address":"Heerlerbaan 134",
    "sg:city":"Heerlen",
    "sg:orig_category":"Schilders",
    "sg:phone":"+31 45 542 5550",
    "sg:postcode":"6418 CJ",
    "sg:province":"Limburg",
    "wof:name":"Bijsmans Heerlen Bv",
    "wof:placetype":"venue"
},
  "geometry": {"coordinates":[5.998738,50.868118],"type":"Point"}
}