{
  "type": "Feature",
  "properties": {
    "iso:country":"NL",
    "sg:address":"Rynln 45",
    "sg:city":"Utrecht",
    "sg:orig_category":"Adviesbureaus Bedrijfsorganisatie",
    "sg:phone":"+31 30 280 0926",
    "sg:postcode":"3522 BC",
    "sg:province":"Utrecht",
    "wof:name":"Ikat",
    "wof:placetype":"venue"
},
  "geometry": {"coordinates":[5.11568,52.070339],"type":"Point"}
}