{
  "type": "Feature",
  "properties": {
    "iso:country":"NL",
    "sg:address":"Kruisstraat 39",
    "sg:city":"'S Hertogenbosch",
    "sg:orig_category":"Makelaars In Onroerend Goed",
    "sg:phone":"+31 73 614 7733",
    "sg:postcode":"5211 DT",
    "sg:province":"North Brabant",
    "wof:name":"Direkt Wonen Den Bosch",
    "wof:placetype":"venue"
},
  "geometry": {"coordinates":[5.300601,51.690086],"type":"Point"}
}