{
  "type": "Feature",
  "properties": {
    "addr:full":"Strekel 6 Vriezenveen NL.08 7671 NV",
    "addr:housenumber":"6;nl.08",
    "addr:postcode":"7671 nv",
    "addr:street":"Strekel",
    "iso:country":"NL",
    "sg:address":"Strekel 6",
    "sg:city":"Vriezenveen",
    "sg:orig_category":"Landbouwmachines Gh",
    "sg:phone":"+31 546 561 020",
    "sg:postcode":"7671 NV",
    "sg:province":"NL.08",
    "wof:name":"Ims Holland Bv",
    "wof:placetype":"venue"
},
  "geometry": {"coordinates":[6.603331,52.409847],"type":"Point"}
}