{
  "type": "Feature",
  "properties": {
    "iso:country":"NL",
    "sg:address":"Ronerbrink 134",
    "sg:city":"Emmen",
    "sg:orig_category":"Public Relationbureaus",
    "sg:phone":"+31 591 642 047",
    "sg:postcode":"7812 LZ",
    "sg:province":"Provincie Drenthe",
    "wof:name":"Elshout Public Relations",
    "wof:placetype":"venue"
},
  "geometry": {"coordinates":[6.888876,52.770123],"type":"Point"}
}