{
  "type": "Feature",
  "properties": {
    "addr:full":"Najaarswg 38A Enschede Overijssel 7532 SK",
    "addr:housenumber":"38a",
    "addr:street":"Najaarswg;7532",
    "iso:country":"NL",
    "sg:address":"Najaarswg 38A",
    "sg:city":"Enschede",
    "sg:classifiers":[
        {
            "category":"Retail",
            "subcategory":"Auto Repair",
            "type":"Services"
        }
    ],
    "sg:phone":"+31 53 461 6275",
    "sg:postcode":"7532 SK",
    "sg:province":"Overijssel",
    "sg:tags":[
        "garage"
    ],
    "wof:name":"Center Car",
    "wof:placetype":"venue"
},
  "geometry": {"coordinates":[6.956982,52.222301],"type":"Point"}
}