{
  "type": "Feature",
  "properties": {
    "addr:full":"De Gast 4 Grootegast Groningen 9861 BM",
    "addr:housenumber":"4",
    "addr:postcode":"9861 bm",
    "addr:street":"De Gast",
    "iso:country":"NL",
    "sg:address":"De Gast 4",
    "sg:city":"Grootegast",
    "sg:orig_category":"Bejaarden - Verzorgingstehuizen",
    "sg:phone":"+31 594 695 800",
    "sg:postcode":"9861 BM",
    "sg:province":"Groningen",
    "wof:name":"Hooge Heem, Het",
    "wof:placetype":"venue"
},
  "geometry": {"coordinates":[6.280232,53.21151],"type":"Point"}
}