{
  "type": "Feature",
  "properties": {
    "addr:full":"Van Weerden Poelmanweg 5 Almelo NL.08 7602 PC",
    "addr:housenumber":"5;nl.08",
    "addr:postcode":"7602 pc",
    "addr:street":"Van Weerden Poelmanweg",
    "iso:country":"NL",
    "sg:address":"Van Weerden Poelmanweg 5",
    "sg:city":"Almelo",
    "sg:orig_category":"Loodgieterswerk, Verwarming And Sanitaire Installaties",
    "sg:phone":"+31 546 473 673",
    "sg:postcode":"7602 PC",
    "sg:province":"NL.08",
    "wof:name":"Hoogstraten Verwarming Bv",
    "wof:placetype":"venue"
},
  "geometry": {"coordinates":[6.646769,52.374924],"type":"Point"}
}