{
  "type": "Feature",
  "properties": {
    "iso:country":"NL",
    "sg:address":"Brilweg 46",
    "sg:city":"Briltil",
    "sg:orig_category":"Goederenvervoer Over De Weg",
    "sg:phone":"+31 50 589 1448",
    "sg:postcode":"9805 TE",
    "sg:province":"Groningen",
    "wof:name":"Drenth Internationaal Transportbedrijf",
    "wof:placetype":"venue"
},
  "geometry": {"coordinates":[6.390491,53.242847],"type":"Point"}
}