{
  "type": "Feature",
  "properties": {
    "addr:full":"Helmondsewg 65 Deurne North Brabant 5751 GB",
    "addr:housenumber":"65",
    "addr:postcode":"5751 gb",
    "addr:street":"Helmondsewg",
    "iso:country":"NL",
    "sg:address":"Helmondsewg 65",
    "sg:city":"Deurne",
    "sg:orig_category":"Cafetaria'S",
    "sg:phone":"+31 493 311 085",
    "sg:postcode":"5751 GB",
    "sg:province":"North Brabant",
    "wof:name":"Smulhoek, De",
    "wof:placetype":"venue"
},
  "geometry": {"coordinates":[5.785137,51.46233],"type":"Point"}
}