{
  "type": "Feature",
  "properties": {
    "iso:country":"NL",
    "sg:address":"Industriewg 38C",
    "sg:city":"Mydrecht",
    "sg:orig_category":"Keukens",
    "sg:phone":"+31 297 273 838",
    "sg:postcode":"3641 RM",
    "sg:province":"Utrecht",
    "sg:website":"http://www.nederlands.com/keuken",
    "wof:name":"Keukenkampioen, De",
    "wof:placetype":"venue"
},
  "geometry": {"coordinates":[4.875343,52.206455],"type":"Point"}
}