{
  "type": "Feature",
  "properties": {
    "addr:full":"Tolhuisln 41 Etten Leur Noord-Brabant 4875 AH",
    "addr:housenumber":"41",
    "addr:postcode":"4875 ah",
    "addr:street":"Tolhuisln",
    "iso:country":"NL",
    "sg:address":"Tolhuisln 41",
    "sg:city":"Etten Leur",
    "sg:orig_category":"Beeldende Kunstenaars",
    "sg:phone":"+31 76 502 3888",
    "sg:postcode":"4875 AH",
    "sg:province":"Noord-Brabant",
    "sg:website":"http://www.marijekos.com",
    "wof:name":"Kos, Marije",
    "wof:placetype":"venue"
},
  "geometry": {"coordinates":[4.639522,51.570694],"type":"Point"}
}