{
  "type": "Feature",
  "properties": {
    "addr:full":"Havezateweg 4 Collendoorn NL.08 7798 CC",
    "addr:housenumber":"4;nl.08",
    "addr:postcode":"7798 cc",
    "addr:street":"Havezateweg",
    "iso:country":"NL",
    "sg:address":"Havezateweg 4",
    "sg:city":"Collendoorn",
    "sg:orig_category":"Kappers",
    "sg:phone":"+31 523 261 762",
    "sg:postcode":"7798 CC",
    "sg:province":"NL.08",
    "wof:name":"Miranda",
    "wof:placetype":"venue"
},
  "geometry": {"coordinates":[6.608981,52.592476],"type":"Point"}
}