{
  "type": "Feature",
  "properties": {
    "addr:full":"Planetenlaan 80 Nieuw Lekkerland Zuid-Holland 2957 SN",
    "addr:housenumber":"80",
    "addr:postcode":"lekkerland;2957 sn",
    "addr:street":"Planetenlaan",
    "iso:country":"NL",
    "sg:address":"Planetenlaan 80",
    "sg:city":"Nieuw Lekkerland",
    "sg:orig_category":"Bloemen And Planten",
    "sg:phone":"+31 184 684 159",
    "sg:postcode":"2957 SN",
    "sg:province":"Zuid-Holland",
    "wof:name":"Europatuin Nieuw Lekkerland",
    "wof:placetype":"venue"
},
  "geometry": {"coordinates":[4.677399,51.886642],"type":"Point"}
}