{
  "type": "Feature",
  "properties": {
    "addr:full":"Lange Heul 14 Bussum North Holland 1403 NL",
    "addr:housenumber":"14",
    "addr:postcode":"1403 nl",
    "addr:street":"Lange Heul",
    "iso:country":"NL",
    "sg:address":"Lange Heul 14",
    "sg:city":"Bussum",
    "sg:orig_category":"Kappers",
    "sg:phone":"+31 35 691 5984",
    "sg:postcode":"1403 NL",
    "sg:province":"North Holland",
    "wof:name":"Ewa Coiffures",
    "wof:placetype":"venue"
},
  "geometry": {"coordinates":[5.1688370705,52.2663269043],"type":"Point"}
}