{
  "type": "Feature",
  "properties": {
    "addr:full":"Vismarkt 8 Zaltbommel Gelderland 5301 CW",
    "addr:housenumber":"8",
    "addr:postcode":"5301 cw",
    "addr:street":"Vismarkt;Gelderland",
    "iso:country":"NL",
    "sg:address":"Vismarkt 8",
    "sg:city":"Zaltbommel",
    "sg:orig_category":"Public Relationbureaus",
    "sg:phone":"+31 418 515 355",
    "sg:postcode":"5301 CW",
    "sg:province":"Gelderland",
    "wof:name":"Publiciteit Service Bureau Van Luyk",
    "wof:placetype":"venue"
},
  "geometry": {"coordinates":[5.250399,51.813461],"type":"Point"}
}