{
  "type": "Feature",
  "properties": {
    "iso:country":"NL",
    "sg:address":"Sommerscamp 32",
    "sg:city":"Asten",
    "sg:orig_category":"Bedrijfs- And Managementsconsultants",
    "sg:phone":"+31 493 692 866",
    "sg:postcode":"5721 LT",
    "sg:province":"Noord-Brabant",
    "wof:name":"Arion",
    "wof:placetype":"venue"
},
  "geometry": {"coordinates":[5.738874,51.400944],"type":"Point"}
}