{
  "type": "Feature",
  "properties": {
    "iso:country":"NL",
    "sg:address":"De Zoom 4-6",
    "sg:city":"Renesse",
    "sg:orig_category":"Discotheken",
    "sg:phone":"+31 111 461 763",
    "sg:postcode":"4325 BG",
    "sg:province":"Zeeland",
    "wof:name":"Roefke, 'T",
    "wof:placetype":"venue"
},
  "geometry": {"coordinates":[3.772231,51.731686],"type":"Point"}
}