{
  "type": "Feature",
  "properties": {
    "iso:country":"NL",
    "sg:address":"Lomanstr 71",
    "sg:city":"Amsterdam",
    "sg:orig_category":"Verenigingen En Stichtingen",
    "sg:phone":"+31 20 673 8602",
    "sg:postcode":"1075 PW",
    "sg:province":"Noord-Holland",
    "wof:name":"Chr Scholen Te Amsterdam Zuid, Ver",
    "wof:placetype":"venue"
},
  "geometry": {"coordinates":[4.858799,52.350849],"type":"Point"}
}