{
  "type": "Feature",
  "properties": {
    "addr:full":"Piazza 3 Eindhoven Noord-Brabant 5611 AE",
    "addr:housenumber":"3",
    "addr:postcode":"5611 ae",
    "addr:street":"Piazza",
    "iso:country":"NL",
    "sg:address":"Piazza 3",
    "sg:city":"Eindhoven",
    "sg:orig_category":"Bloemen And Planten",
    "sg:phone":"+31 40 244 0041",
    "sg:postcode":"5611 AE",
    "sg:province":"Noord-Brabant",
    "wof:name":"Bv De Biedermeier",
    "wof:placetype":"venue"
},
  "geometry": {"coordinates":[5.476535,51.441982],"type":"Point"}
}