{
  "type": "Feature",
  "properties": {
    "addr:full":"Kluyverwg 4 Delft South Holland 2629 HT",
    "addr:housenumber":"4",
    "addr:postcode":"2629 ht",
    "addr:street":"Kluyverwg",
    "iso:country":"NL",
    "sg:address":"Kluyverwg 4",
    "sg:city":"Delft",
    "sg:orig_category":"Onderzoekbureaus",
    "sg:phone":"+31 15 278 6046",
    "sg:postcode":"2629 HT",
    "sg:province":"South Holland",
    "wof:name":"Trail",
    "wof:placetype":"venue"
},
  "geometry": {"coordinates":[4.377366,51.989887],"type":"Point"}
}