{
  "type": "Feature",
  "properties": {
    "addr:full":"Brinklaan 2 Epe Gelderland 8161 CX",
    "addr:housenumber":"2",
    "addr:postcode":"8161 cx",
    "addr:street":"Brinklaan;Gelderland",
    "iso:country":"NL",
    "sg:address":"Brinklaan 2",
    "sg:city":"Epe",
    "sg:orig_category":"Loodgieterswerk, Verwarming And Sanitaire Installaties",
    "sg:phone":"+31 578 616 567",
    "sg:postcode":"8161 CX",
    "sg:province":"Gelderland",
    "wof:name":"Van Dijk Installatietechniek",
    "wof:placetype":"venue"
},
  "geometry": {"coordinates":[5.984764,52.347561],"type":"Point"}
}