{
  "type": "Feature",
  "properties": {
    "iso:country":"NL",
    "sg:address":"De Bindery 46-48",
    "sg:city":"Almere",
    "sg:orig_category":"Verhuizingen",
    "sg:phone":"+31 36 530 9966",
    "sg:postcode":"1321 EK",
    "sg:province":"Flevoland",
    "wof:name":"Koenders & Zonen Bv, Verhuizingen",
    "wof:placetype":"venue"
},
  "geometry": {"coordinates":[5.181285,52.362419],"type":"Point"}
}