{
  "type": "Feature",
  "properties": {
    "addr:full":"Stokstr 1A Maastricht Limburg 6211 GB",
    "addr:housenumber":"1a",
    "addr:postcode":"6211 gb",
    "addr:street":"Stokstr",
    "iso:country":"NL",
    "sg:address":"Stokstr 1A",
    "sg:city":"Maastricht",
    "sg:orig_category":"Bodemsanering",
    "sg:phone":"+31 43 350 0175",
    "sg:postcode":"6211 GB",
    "sg:province":"Limburg",
    "wof:name":"Logisan Bv",
    "wof:placetype":"venue"
},
  "geometry": {"coordinates":[5.694092,50.848919],"type":"Point"}
}