{
  "type": "Feature",
  "properties": {
    "addr:full":"Ryswykstr 185 Amsterdam North Holland 1062 EV",
    "addr:housenumber":"185",
    "iso:country":"NL",
    "sg:address":"Ryswykstr 185",
    "sg:city":"Amsterdam",
    "sg:orig_category":"Mode Artikelen Dames En Heren - Fabrieken En Groothandel",
    "sg:phone":"+31 20 615 1261",
    "sg:postcode":"1062 EV",
    "sg:province":"North Holland",
    "wof:name":"Baneke, Fa",
    "wof:placetype":"venue"
},
  "geometry": {"coordinates":[4.83975,52.351082],"type":"Point"}
}