{
  "type": "Feature",
  "properties": {
    "addr:full":"Hofstedewg 78 Enschede Overijssel 7535 CW",
    "addr:housenumber":"78",
    "addr:postcode":"7535 cw",
    "addr:street":"Hofstedewg",
    "iso:country":"NL",
    "sg:address":"Hofstedewg 78",
    "sg:city":"Enschede",
    "sg:orig_category":"Adviesbureaus Bedrijfsorganisatie",
    "sg:phone":"+31 53 432 8289",
    "sg:postcode":"7535 CW",
    "sg:province":"Overijssel",
    "wof:name":"Gevicon",
    "wof:placetype":"venue"
},
  "geometry": {"coordinates":[6.916992,52.216503],"type":"Point"}
}