{
  "type": "Feature",
  "properties": {
    "iso:country":"NL",
    "sg:address":"M V Meelwg 15A",
    "sg:city":"Eindhoven",
    "sg:orig_category":"Luchtvrachtexpediteurs",
    "sg:phone":"+31 40 251 2191",
    "sg:postcode":"5657 EN",
    "sg:province":"Noord-Brabant",
    "wof:name":"Road Air",
    "wof:placetype":"venue"
},
  "geometry": {"coordinates":[5.39235,51.456921],"type":"Point"}
}