{
  "type": "Feature",
  "properties": {
    "addr:full":"V Faukenbergepln 24 Voorburg South Holland 2274 SG",
    "addr:housenumber":"24",
    "addr:postcode":"2274 sg",
    "iso:country":"NL",
    "sg:address":"V Faukenbergepln 24",
    "sg:city":"Voorburg",
    "sg:orig_category":"Fotopersbureaus",
    "sg:phone":"+31 70 385 4670",
    "sg:postcode":"2274 SG",
    "sg:province":"South Holland",
    "sg:website":"http://www.pevry-press.nl",
    "wof:name":"Pevry Press",
    "wof:placetype":"venue"
},
  "geometry": {"coordinates":[4.34872,52.074894],"type":"Point"}
}