{
  "type": "Feature",
  "properties": {
    "addr:full":"Noordvest 20B Schiedam Zuid-Holland 3111 PH",
    "addr:housenumber":"20b",
    "addr:postcode":"3111",
    "addr:street":"Noordvest",
    "iso:country":"NL",
    "sg:address":"Noordvest 20B",
    "sg:city":"Schiedam",
    "sg:orig_category":"Loopbaanbegeleiding",
    "sg:phone":"+31 10 204 0222",
    "sg:postcode":"3111 PH",
    "sg:province":"Zuid-Holland",
    "wof:name":"Kliq",
    "wof:placetype":"venue"
},
  "geometry": {"coordinates":[4.39898,51.920681],"type":"Point"}
}