{
  "type": "Feature",
  "properties": {
    "iso:country":"NL",
    "sg:address":"Kampina 5",
    "sg:city":"Amsterdam",
    "sg:orig_category":"Scholen Voor Basisonderwijs",
    "sg:phone":"+31 20 637 1194",
    "sg:postcode":"1025 DD",
    "sg:province":"North Holland",
    "wof:name":"Boven 'T Ij Openb Montessori",
    "wof:placetype":"venue"
},
  "geometry": {"coordinates":[4.939484,52.403316],"type":"Point"}
}