{
  "type": "Feature",
  "properties": {
    "addr:full":"Vierhond Polderdk 10 Cadzand Zeeland 4506 HL",
    "addr:housenumber":"10",
    "addr:postcode":"4506 hl",
    "iso:country":"NL",
    "sg:address":"Vierhond Polderdk 10",
    "sg:city":"Cadzand",
    "sg:orig_category":"Scholen Voor Basisonderwijs",
    "sg:phone":"+31 117 391 192",
    "sg:postcode":"4506 HL",
    "sg:province":"Zeeland",
    "wof:name":"Horizon Azc, De",
    "wof:placetype":"venue"
},
  "geometry": {"coordinates":[3.391363,51.37888],"type":"Point"}
}