{
  "type": "Feature",
  "properties": {
    "iso:country":"NL",
    "sg:address":"V Pallandtmarke 74",
    "sg:city":"Zwolle",
    "sg:orig_category":"Psychologen",
    "sg:phone":"+31 38 465 2175",
    "sg:postcode":"8016 CX",
    "sg:province":"Overijssel",
    "wof:name":"Houwing, Drs C H",
    "wof:placetype":"venue"
},
  "geometry": {"coordinates":[6.09836,52.483524],"type":"Point"}
}