{
  "type": "Feature",
  "properties": {
    "addr:full":"Amsteldiep 81 (Winkelcentrum De Terp)\\\\ Capelle Ad Yssel Zuid-Holland 2904 EB",
    "addr:housenumber":"81;\\ \\",
    "addr:postcode":"2904 eb",
    "addr:street":"Amsteldiep;De Terp",
    "iso:country":"NL",
    "sg:address":"Amsteldiep 81 (Winkelcentrum De Terp)\\\\",
    "sg:city":"Capelle Ad Yssel",
    "sg:orig_category":"Juweliers",
    "sg:phone":"+31 10 442 4913",
    "sg:postcode":"2904 EB",
    "sg:province":"Zuid-Holland",
    "wof:name":"Ooms",
    "wof:placetype":"venue"
},
  "geometry": {"coordinates":[4.601997,51.936321],"type":"Point"}
}