{
  "type": "Feature",
  "properties": {
    "addr:full":"Korenmolenplein 8 Goirle Noord-Brabant 5051 LZ",
    "addr:housenumber":"8",
    "addr:postcode":"5051 lz",
    "addr:street":"Korenmolenplein",
    "iso:country":"NL",
    "sg:address":"Korenmolenplein 8",
    "sg:city":"Goirle",
    "sg:orig_category":"Fietshandelaren",
    "sg:phone":"+31 13 534 5321",
    "sg:postcode":"5051 LZ",
    "sg:province":"Noord-Brabant",
    "sg:website":"http://www.rings-goirle.nl",
    "wof:name":"Rings Goirle",
    "wof:placetype":"venue"
},
  "geometry": {"coordinates":[5.073724,51.520325],"type":"Point"}
}