{
  "type": "Feature",
  "properties": {
    "iso:country":"NL",
    "sg:address":"Benedenrywg 4",
    "sg:city":"Ridderkerk",
    "sg:orig_category":"Haarwerken",
    "sg:phone":"+31 180 423 807",
    "sg:postcode":"2981 EB",
    "sg:province":"Zuid-Holland",
    "wof:name":"Artistic Ficial",
    "wof:placetype":"venue"
},
  "geometry": {"coordinates":[4.603289,51.871132],"type":"Point"}
}