{
  "type": "Feature",
  "properties": {
    "addr:full":"V Ostadeln 120 Schiedam Zuid-Holland 3117 XM",
    "addr:housenumber":"120",
    "addr:postcode":"3117 xm",
    "iso:country":"NL",
    "sg:address":"V Ostadeln 120",
    "sg:city":"Schiedam",
    "sg:orig_category":"Kinderopvang",
    "sg:phone":"+31 10 426 5819",
    "sg:postcode":"3117 XM",
    "sg:province":"Zuid-Holland",
    "wof:name":"Gastouderbureau",
    "wof:placetype":"venue"
},
  "geometry": {"coordinates":[4.39816,51.918472],"type":"Point"}
}