{
  "type": "Feature",
  "properties": {
    "addr:full":"Volkerstraat 10 Goes Zeeland 4462 GH",
    "addr:housenumber":"10",
    "addr:postcode":"4462 gh",
    "addr:street":"Volkerstraat",
    "iso:country":"NL",
    "sg:address":"Volkerstraat 10",
    "sg:city":"Goes",
    "sg:orig_category":"Wegen And Sportterreinen",
    "sg:phone":"+31 113 230 342",
    "sg:postcode":"4462 GH",
    "sg:province":"Zeeland",
    "wof:name":"Hbg Civiel West Zuid",
    "wof:placetype":"venue"
},
  "geometry": {"coordinates":[3.8763840199,51.4950408936],"type":"Point"}
}