{
  "type": "Feature",
  "properties": {
    "addr:full":"Wielewaalhof 141 Stadskanaal Groningen 9502 ST",
    "addr:housenumber":"141",
    "addr:postcode":"9502 st",
    "addr:street":"Wielewaalhof",
    "iso:country":"NL",
    "sg:address":"Wielewaalhof 141",
    "sg:city":"Stadskanaal",
    "sg:orig_category":"Kappers",
    "sg:phone":"+31 599 611 110",
    "sg:postcode":"9502 ST",
    "sg:province":"Groningen",
    "wof:name":"La-Pols Haarmode",
    "wof:placetype":"venue"
},
  "geometry": {"coordinates":[6.979212,52.987286],"type":"Point"}
}