{
  "type": "Feature",
  "properties": {
    "addr:full":"V Hogendorpln 1A Hilversum Noord-Holland 1215 EG",
    "addr:housenumber":"1a",
    "addr:postcode":"1215 eg",
    "addr:street":"Hogendorpln",
    "iso:country":"NL",
    "sg:address":"V Hogendorpln 1A",
    "sg:city":"Hilversum",
    "sg:orig_category":"Scholen Voor Basisonderwijs",
    "sg:phone":"+31 35 624 9150",
    "sg:postcode":"1215 EG",
    "sg:province":"Noord-Holland",
    "wof:name":"Elckerlyc Obs",
    "wof:placetype":"venue"
},
  "geometry": {"coordinates":[5.1695,52.228565],"type":"Point"}
}