{
  "type": "Feature",
  "properties": {
    "addr:full":"Achterstraat 14A-B Putten Gelderland 3882 AG",
    "addr:housenumber":"14a-b",
    "addr:postcode":"3882",
    "addr:street":"Achterstraat;Gelderland",
    "iso:country":"NL",
    "sg:address":"Achterstraat 14A-B",
    "sg:city":"Putten",
    "sg:orig_category":"Kappers",
    "sg:phone":"+31 341 360 747",
    "sg:postcode":"3882 AG",
    "sg:province":"Gelderland",
    "wof:name":"Leeuwis Bv, Wim",
    "wof:placetype":"venue"
},
  "geometry": {"coordinates":[5.605482,52.257221],"type":"Point"}
}