{
  "type": "Feature",
  "properties": {
    "addr:full":"Bertelindislaan 29 Waalre Noord-Brabant 5581 CS",
    "addr:housenumber":"29",
    "addr:postcode":"5581 cs",
    "addr:street":"Bertelindislaan",
    "iso:country":"NL",
    "sg:address":"Bertelindislaan 29",
    "sg:city":"Waalre",
    "sg:orig_category":"Binnenhuisarchitecten",
    "sg:phone":"+31 40 221 8497",
    "sg:postcode":"5581 CS",
    "sg:province":"Noord-Brabant",
    "wof:name":"Welbo",
    "wof:placetype":"venue"
},
  "geometry": {"coordinates":[5.448701,51.389267],"type":"Point"}
}