{
  "type": "Feature",
  "properties": {
    "iso:country":"NL",
    "sg:address":"Isaac Beekmanstraat 4",
    "sg:city":"Wijchen",
    "sg:orig_category":"Boekenuitgeverijen",
    "sg:phone":"+31 24 645 3539",
    "sg:postcode":"6603 BZ",
    "sg:province":"Gelderland",
    "wof:name":"Kloek Nijmegen Bv",
    "wof:placetype":"venue"
},
  "geometry": {"coordinates":[5.758355,51.815624],"type":"Point"}
}