{
  "type": "Feature",
  "properties": {
    "addr:full":"Lg Gouwe 12A Gouda Zuid-Holland 2801 LG",
    "addr:housenumber":"12a",
    "addr:postcode":"2801 lg",
    "addr:street":"Lg Gouwe",
    "iso:country":"NL",
    "sg:address":"Lg Gouwe 12A",
    "sg:city":"Gouda",
    "sg:orig_category":"Glas, Porselein En Aardewerk",
    "sg:phone":"+31 182 586 586",
    "sg:postcode":"2801 LG",
    "sg:province":"Zuid-Holland",
    "wof:name":"Casa Mia",
    "wof:placetype":"venue"
},
  "geometry": {"coordinates":[4.709669,52.010338],"type":"Point"}
}