{
  "type": "Feature",
  "properties": {
    "iso:country":"NL",
    "sg:address":"Krommesteeg 5",
    "sg:city":"Ede Gld",
    "sg:orig_category":"Levende Dieren Gh",
    "sg:phone":"+31 318 610 632",
    "sg:postcode":"6718 TV",
    "sg:province":"Gelderland",
    "wof:name":"H. Dirksen Veehouderij Bv",
    "wof:placetype":"venue"
},
  "geometry": {"coordinates":[5.636671,52.057446],"type":"Point"}
}