{
  "type": "Feature",
  "properties": {
    "addr:full":"V Zeggelenpln 83 Haarlem Noord-Holland 2032 KD",
    "addr:housenumber":"83",
    "addr:postcode":"2032 kd",
    "iso:country":"NL",
    "sg:address":"V Zeggelenpln 83",
    "sg:city":"Haarlem",
    "sg:orig_category":"Kappers",
    "sg:phone":"+31 23 535 0682",
    "sg:postcode":"2032 KD",
    "sg:province":"Noord-Holland",
    "wof:name":"Nina En Monique",
    "wof:placetype":"venue"
},
  "geometry": {"coordinates":[4.65117,52.378342],"type":"Point"}
}