{
  "type": "Feature",
  "properties": {
    "addr:full":"Postbus 1445 Amsterdam North Holland 1000 BK",
    "addr:housenumber":"1445",
    "addr:postcode":"1000 bk",
    "addr:street":"Postbus",
    "iso:country":"NL",
    "sg:address":"Postbus 1445",
    "sg:city":"Amsterdam",
    "sg:orig_category":"Verenigingen En Stichtingen",
    "sg:phone":"+31 20 638 1978",
    "sg:postcode":"1000 BK",
    "sg:province":"North Holland",
    "wof:name":"Buitenkunst, Sticht",
    "wof:placetype":"venue"
},
  "geometry": {"coordinates":[4.89319,52.373119],"type":"Point"}
}