{
  "type": "Feature",
  "properties": {
    "addr:full":"Irenestraat 2 Breda North Brabant 4811 SC",
    "addr:housenumber":"2",
    "addr:postcode":"4811 sc",
    "addr:street":"Irenestraat",
    "iso:country":"NL",
    "sg:address":"Irenestraat 2",
    "sg:city":"Breda",
    "sg:orig_category":"Verhuur Huishoudartikelen",
    "sg:phone":"+31 76 530 9680",
    "sg:postcode":"4811 SC",
    "sg:province":"North Brabant",
    "wof:name":"Aagje Decorating",
    "wof:placetype":"venue"
},
  "geometry": {"coordinates":[4.770806,51.581795],"type":"Point"}
}