{
  "type": "Feature",
  "properties": {
    "addr:full":"Korevaarstr 30 Leiden South Holland 2311 JV",
    "addr:housenumber":"30",
    "addr:postcode":"2311 jv",
    "addr:street":"Korevaarstr",
    "iso:country":"NL",
    "sg:address":"Korevaarstr 30",
    "sg:city":"Leiden",
    "sg:orig_category":"Woningbouw- Verenigingen En -Stichtingen",
    "sg:phone":"+31 71 512 2859",
    "sg:postcode":"2311 JV",
    "sg:province":"South Holland",
    "sg:website":"http://www.zijlenvliet.nl",
    "wof:name":"Zijl En Vliet",
    "wof:placetype":"venue"
},
  "geometry": {"coordinates":[4.493806839,52.1542701721],"type":"Point"}
}