{
  "type": "Feature",
  "properties": {
    "addr:full":"Dr Kuyperkade 14 Maassluis Zuid-Holland 3142 GB",
    "addr:housenumber":"14",
    "addr:postcode":"3142 gb",
    "addr:street":"Dr Kuyperkade",
    "iso:country":"NL",
    "sg:address":"Dr Kuyperkade 14",
    "sg:city":"Maassluis",
    "sg:orig_category":"Damesmodezaken",
    "sg:phone":"+31 10 591 6763",
    "sg:postcode":"3142 GB",
    "sg:province":"Zuid-Holland",
    "wof:name":"Modehuis Lever",
    "wof:placetype":"venue"
},
  "geometry": {"coordinates":[4.255336,51.922192],"type":"Point"}
}