{
  "type": "Feature",
  "properties": {
    "addr:full":"Pres Rooseveltln 4A Helmond North Brabant 5707 GD",
    "addr:housenumber":"4a",
    "addr:postcode":"5707 gd",
    "iso:country":"NL",
    "sg:address":"Pres Rooseveltln 4A",
    "sg:city":"Helmond",
    "sg:orig_category":"Accountants - Administratie- Consulenten En -Kantoren",
    "sg:phone":"+31 492 550 775",
    "sg:postcode":"5707 GD",
    "sg:province":"North Brabant",
    "wof:name":"Rsw",
    "wof:placetype":"venue"
},
  "geometry": {"coordinates":[5.658284,51.482239],"type":"Point"}
}