{
  "type": "Feature",
  "properties": {
    "addr:full":"Noordersngl 11 Hoogezand Groningen 9601 CJ",
    "addr:housenumber":"11",
    "addr:postcode":"9601 cj",
    "addr:street":"Noordersngl",
    "iso:country":"NL",
    "sg:address":"Noordersngl 11",
    "sg:city":"Hoogezand",
    "sg:orig_category":"Fitnesscentra",
    "sg:phone":"+31 598 398 551",
    "sg:postcode":"9601 CJ",
    "sg:province":"Groningen",
    "wof:name":"Drenth",
    "wof:placetype":"venue"
},
  "geometry": {"coordinates":[6.74858,53.165501],"type":"Point"}
}