{
  "type": "Feature",
  "properties": {
    "iso:country":"NL",
    "sg:address":"Past V Breugelstr 138",
    "sg:city":"Bosschenhoofd",
    "sg:orig_category":"Bloemen En Planten",
    "sg:phone":"+31 165 317 068",
    "sg:postcode":"4744 AG",
    "sg:province":"Noord-Brabant",
    "wof:name":"Goudsbloem, De",
    "wof:placetype":"venue"
},
  "geometry": {"coordinates":[4.5443,51.561401],"type":"Point"}
}