{
  "type": "Feature",
  "properties": {
    "iso:country":"NL",
    "sg:address":"Koningstraat 78",
    "sg:city":"Arnhem",
    "sg:orig_category":"Zuivelproducten",
    "sg:phone":"+31 26 443 5353",
    "sg:postcode":"6811 DK",
    "sg:province":"Gelderland",
    "wof:name":"Kaashandel Van Dee",
    "wof:placetype":"venue"
},
  "geometry": {"coordinates":[5.909824,51.981575],"type":"Point"}
}