{
  "type": "Feature",
  "properties": {
    "addr:full":"Lammertiend 22 Teteringen Noord-Brabant 4847 HV",
    "addr:housenumber":"22",
    "addr:postcode":"4847 hv",
    "addr:street":"Lammertiend",
    "iso:country":"NL",
    "sg:address":"Lammertiend 22",
    "sg:city":"Teteringen",
    "sg:orig_category":"Verzekeringen",
    "sg:phone":"+31 76 571 3487",
    "sg:postcode":"4847 HV",
    "sg:province":"Noord-Brabant",
    "wof:name":"W.P.J. Van Gaal Assurantien",
    "wof:placetype":"venue"
},
  "geometry": {"coordinates":[4.813371,51.608749],"type":"Point"}
}