{
  "type": "Feature",
  "properties": {
    "addr:full":"Dorpsstraat 1014 Assendelft Noord-Holland 1566 JK",
    "addr:housenumber":"1014",
    "addr:postcode":"1566 jk",
    "addr:street":"Dorpsstraat",
    "iso:country":"NL",
    "sg:address":"Dorpsstraat 1014",
    "sg:city":"Assendelft",
    "sg:orig_category":"Kappers",
    "sg:phone":"+31 75 621 8533",
    "sg:postcode":"1566 JK",
    "sg:province":"Noord-Holland",
    "wof:name":"Kapsalon Cor Schavemaker",
    "wof:placetype":"venue"
},
  "geometry": {"coordinates":[4.7619829178,52.4911689758],"type":"Point"}
}