{
  "type": "Feature",
  "properties": {
    "addr:full":"Kortewg 4 Hooge Zwaluwe Noord-Brabant 4927 AE",
    "addr:housenumber":"4",
    "addr:postcode":"4927 ae",
    "addr:street":"Kortewg",
    "iso:country":"NL",
    "sg:address":"Kortewg 4",
    "sg:city":"Hooge Zwaluwe",
    "sg:orig_category":"Keuken- Groot-Installaties",
    "sg:phone":"+31 168 483 831",
    "sg:postcode":"4927 AE",
    "sg:province":"Noord-Brabant",
    "wof:name":"Rijswijk, Van",
    "wof:placetype":"venue"
},
  "geometry": {"coordinates":[4.739129,51.690708],"type":"Point"}
}