{
  "type": "Feature",
  "properties": {
    "addr:full":"Berkelplein 99 Valkenburg Lb Limburg 6301 ZC",
    "addr:housenumber":"99",
    "addr:postcode":"lb;6301 zc",
    "addr:street":"Berkelplein",
    "iso:country":"NL",
    "sg:address":"Berkelplein 99",
    "sg:city":"Valkenburg Lb",
    "sg:orig_category":"Bibliotheken And Openbare Archieven",
    "sg:phone":"+31 43 601 2063",
    "sg:postcode":"6301 ZC",
    "sg:province":"Limburg",
    "wof:name":"Openbare Bibliotheken",
    "wof:placetype":"venue"
},
  "geometry": {"coordinates":[5.835974,50.862827],"type":"Point"}
}