{
  "type": "Feature",
  "properties": {
    "iso:country":"NL",
    "sg:address":"Loskd 3-5-7",
    "sg:city":"Middelburg",
    "sg:classifiers":[
        {
            "category":"Travel",
            "subcategory":"Hotels & Motels",
            "type":"Entertainment"
        }
    ],
    "sg:phone":"+31 118 612 121",
    "sg:postcode":"4331 HV",
    "sg:province":"Zeeland",
    "wof:name":"Nieuwe Doelen, Hotel-Restaurant De",
    "wof:placetype":"venue"
},
  "geometry": {"coordinates":[3.609615,51.495415],"type":"Point"}
}