{
  "type": "Feature",
  "properties": {
    "addr:full":"Finse Golf 6 Woerden Utrecht 3446 CK",
    "addr:housenumber":"6",
    "addr:postcode":"3446 ck",
    "addr:street":"Finse Golf",
    "iso:country":"NL",
    "sg:address":"Finse Golf 6",
    "sg:city":"Woerden",
    "sg:orig_category":"Woninginrichting",
    "sg:phone":"+31 348 480 800",
    "sg:postcode":"3446 CK",
    "sg:province":"Utrecht",
    "wof:name":"Kwantum",
    "wof:placetype":"venue"
},
  "geometry": {"coordinates":[4.9078550339,52.0781059265],"type":"Point"}
}