{
  "type": "Feature",
  "properties": {
    "iso:country":"NL",
    "sg:address":"Van Loenshof 68",
    "sg:city":"Enschede",
    "sg:orig_category":"Boekenuitgeverijen",
    "sg:phone":"+31 53 431 3679",
    "sg:postcode":"7511 NJ",
    "sg:province":"Overijssel",
    "wof:name":"Ako Enschede",
    "wof:placetype":"venue"
},
  "geometry": {"coordinates":[6.894971,52.218643],"type":"Point"}
}