{
  "type": "Feature",
  "properties": {
    "addr:full":"Fitterstr 50 Leiden Zuid-Holland 2321 PK",
    "addr:housenumber":"50",
    "addr:postcode":"2321 pk",
    "addr:street":"Fitterstr",
    "iso:country":"NL",
    "sg:address":"Fitterstr 50",
    "sg:city":"Leiden",
    "sg:orig_category":"Vertaalbureaus",
    "sg:phone":"+31 71 522 0683",
    "sg:postcode":"2321 PK",
    "sg:province":"Zuid-Holland",
    "sg:website":"http://www.expage.com/vbvietnam",
    "wof:name":"Vietnam",
    "wof:placetype":"venue"
},
  "geometry": {"coordinates":[4.481714,52.148624],"type":"Point"}
}