{
  "type": "Feature",
  "properties": {
    "addr:full":"Donselaarsweg 33 Oene Gelderland 8167 NH",
    "addr:housenumber":"33",
    "addr:postcode":"8167 nh",
    "addr:street":"Donselaarsweg;Gelderland",
    "iso:country":"NL",
    "sg:address":"Donselaarsweg 33",
    "sg:city":"Oene",
    "sg:orig_category":"Alternatieve Geneeskunde",
    "sg:phone":"+31 578 641 278",
    "sg:postcode":"8167 NH",
    "sg:province":"Gelderland",
    "wof:name":"Fysiotherapiepraktijk Epe Oene",
    "wof:placetype":"venue"
},
  "geometry": {"coordinates":[-71.632828,44.001301],"type":"Point"}
}