{
  "type": "Feature",
  "properties": {
    "iso:country":"NL",
    "sg:address":"L Brailleln 100",
    "sg:city":"Zoetermeer",
    "sg:orig_category":"Verzekeringen - Verzekeringskantoren",
    "sg:phone":"+31 79 363 6987",
    "sg:postcode":"2719 EK",
    "sg:province":"South Holland",
    "sg:website":"http://www.relan.nl",
    "wof:name":"Relan Zekerheid",
    "wof:placetype":"venue"
},
  "geometry": {"coordinates":[4.488925,52.06308],"type":"Point"}
}