{
  "type": "Feature",
  "properties": {
    "addr:full":"Piccardtstr 2 Harkstede Groningen 9617 AX",
    "addr:housenumber":"2",
    "addr:postcode":"9617 ax",
    "addr:street":"Piccardtstr",
    "iso:country":"NL",
    "sg:address":"Piccardtstr 2",
    "sg:city":"Harkstede",
    "sg:orig_category":"Scholen Voor Basisonderwijs",
    "sg:phone":"+31 50 404 1338",
    "sg:postcode":"9617 AX",
    "sg:province":"Groningen",
    "wof:name":"Eben Ha?zer Sch Met De Bijbel",
    "wof:placetype":"venue"
},
  "geometry": {"coordinates":[6.694979,53.21096],"type":"Point"}
}