{
  "type": "Feature",
  "properties": {
    "addr:full":"Randweg 155 Uithoorn Noord-Holland 1422 ND",
    "addr:housenumber":"155",
    "addr:postcode":"1422 nd",
    "addr:street":"Randweg",
    "iso:country":"NL",
    "sg:address":"Randweg 155",
    "sg:city":"Uithoorn",
    "sg:orig_category":"Meubels And Huishoudapparatuur Gh",
    "sg:phone":"+31 20 640 1631",
    "sg:postcode":"1422 ND",
    "sg:province":"Noord-Holland",
    "wof:name":"Liaan Handelsonderneming",
    "wof:placetype":"venue"
},
  "geometry": {"coordinates":[4.801693,52.259071],"type":"Point"}
}