{
  "type": "Feature",
  "properties": {
    "addr:full":"Heetveld 50 St Jansklooster NL.08 8326 BK",
    "addr:housenumber":"50",
    "addr:postcode":"nl.08 8326 bk",
    "addr:street":"Heetveld",
    "iso:country":"NL",
    "sg:address":"Heetveld 50",
    "sg:city":"St Jansklooster",
    "sg:orig_category":"Jachten - Schilderwerken En Onderhoud",
    "sg:phone":"+31 527 246 109",
    "sg:postcode":"8326 BK",
    "sg:province":"NL.08",
    "wof:name":"Hansman",
    "wof:placetype":"venue"
},
  "geometry": {"coordinates":[6.01049,52.662849],"type":"Point"}
}