{
  "type": "Feature",
  "properties": {
    "addr:full":"Wilhelminastraat 2 Ulicoten North Brabant 5113 TH",
    "addr:housenumber":"2",
    "addr:postcode":"5113 th",
    "addr:street":"Wilhelminastraat",
    "iso:country":"NL",
    "sg:address":"Wilhelminastraat 2",
    "sg:city":"Ulicoten",
    "sg:orig_category":"Kappers",
    "sg:phone":"+31 13 519 9412",
    "sg:postcode":"5113 TH",
    "sg:province":"North Brabant",
    "wof:name":"Angela'S Coiffure",
    "wof:placetype":"venue"
},
  "geometry": {"coordinates":[4.8596467972,51.4566001892],"type":"Point"}
}