{
  "type": "Feature",
  "properties": {
    "addr:full":"Dorpsstr 4A Oeffelt Noord-Brabant 5441 AC",
    "addr:housenumber":"4a",
    "addr:postcode":"5441 ac",
    "addr:street":"Dorpsstr",
    "iso:country":"NL",
    "sg:address":"Dorpsstr 4A",
    "sg:city":"Oeffelt",
    "sg:orig_category":"Cafetaria'S",
    "sg:phone":"+31 485 362 860",
    "sg:postcode":"5441 AC",
    "sg:province":"Noord-Brabant",
    "wof:name":"Smulhuukske, 'T",
    "wof:placetype":"venue"
},
  "geometry": {"coordinates":[5.937569,51.694775],"type":"Point"}
}