{
  "type": "Feature",
  "properties": {
    "addr:full":"Zeestr 35 Zandvoort Noord-Holland 2042 LA",
    "addr:housenumber":"35",
    "addr:postcode":"2042 la",
    "addr:street":"Zeestr",
    "iso:country":"NL",
    "sg:address":"Zeestr 35",
    "sg:city":"Zandvoort",
    "sg:classifiers":[
        {
            "category":"Banks & Credit Unions",
            "subcategory":"Investment Brokerage",
            "type":"Services"
        }
    ],
    "sg:phone":"+31 23 571 6953",
    "sg:postcode":"2042 LA",
    "sg:province":"Noord-Holland",
    "sg:tags":[
        "pension"
    ],
    "wof:name":"Hendriks",
    "wof:placetype":"venue"
},
  "geometry": {"coordinates":[4.530058,52.375298],"type":"Point"}
}