{
  "type": "Feature",
  "properties": {
    "addr:full":"Eindsestraat 24 Balgoij Gelderland 6613 AS",
    "addr:housenumber":"24",
    "addr:postcode":"6613 as",
    "addr:street":"Eindsestraat;Gelderland",
    "iso:country":"NL",
    "sg:address":"Eindsestraat 24",
    "sg:city":"Balgoij",
    "sg:orig_category":"Metaalwerken",
    "sg:phone":"+31 24 645 0724",
    "sg:postcode":"6613 AS",
    "sg:province":"Gelderland",
    "wof:name":"Abmo",
    "wof:placetype":"venue"
},
  "geometry": {"coordinates":[5.725327,51.777115],"type":"Point"}
}