{
  "type": "Feature",
  "properties": {
    "addr:full":"Vaandelstraat 1 Delft Zuid-Holland 2611 BW",
    "addr:housenumber":"1",
    "addr:postcode":"2611 bw",
    "addr:street":"Vaandelstraat",
    "iso:country":"NL",
    "sg:address":"Vaandelstraat 1",
    "sg:city":"Delft",
    "sg:orig_category":"Zuivelproducten",
    "sg:phone":"+31 15 212 0545",
    "sg:postcode":"2611 BW",
    "sg:province":"Zuid-Holland",
    "wof:name":"Boter- En Kaashandel Overgaag Bv",
    "wof:placetype":"venue"
},
  "geometry": {"coordinates":[4.358724,52.014462],"type":"Point"}
}