{
  "type": "Feature",
  "properties": {
    "addr:full":"Zuidereinde 66 'S Graveland North Holland 1243 KH",
    "addr:housenumber":"66",
    "addr:postcode":"1243 kh",
    "addr:street":"Zuidereinde;' S Graveland North",
    "iso:country":"NL",
    "sg:address":"Zuidereinde 66",
    "sg:city":"'S Graveland",
    "sg:orig_category":"Film-, Tv- And Videoproductie",
    "sg:phone":"+31 35 656 4499",
    "sg:postcode":"1243 KH",
    "sg:province":"North Holland",
    "wof:name":"Audio Concept Company Bv",
    "wof:placetype":"venue"
},
  "geometry": {"coordinates":[5.121616,52.234142],"type":"Point"}
}