{
  "type": "Feature",
  "properties": {
    "addr:full":"Trompetln 47 Etten Leur Noord-Brabant 4876 XH",
    "addr:housenumber":"47",
    "addr:postcode":"4876 xh",
    "addr:street":"Trompetln",
    "iso:country":"NL",
    "sg:address":"Trompetln 47",
    "sg:city":"Etten Leur",
    "sg:orig_category":"Verenigingen En Stichtingen",
    "sg:phone":"+31 76 501 6755",
    "sg:postcode":"4876 XH",
    "sg:province":"Noord-Brabant",
    "wof:name":"Panfluit, De",
    "wof:placetype":"venue"
},
  "geometry": {"coordinates":[4.634053,51.562862],"type":"Point"}
}