{
  "type": "Feature",
  "properties": {
    "addr:full":"Ceintuurbaan 32 Huizen Noord-Holland 1271 BJ",
    "addr:housenumber":"32",
    "addr:postcode":"1271 bj",
    "addr:street":"Ceintuurbaan",
    "iso:country":"NL",
    "sg:address":"Ceintuurbaan 32",
    "sg:city":"Huizen",
    "sg:orig_category":"Boekenuitgeverijen",
    "sg:phone":"+31 35 525 3293",
    "sg:postcode":"1271 BJ",
    "sg:province":"Noord-Holland",
    "wof:name":"Drukkerij En Uitgeversbedrijf J. Bout & Zonen",
    "wof:placetype":"venue"
},
  "geometry": {"coordinates":[5.235681,52.2939],"type":"Point"}
}