{
  "type": "Feature",
  "properties": {
    "addr:full":"De Singel 67 Drachten Friesland 9203 XZ",
    "addr:housenumber":"67",
    "addr:postcode":"9203 xz",
    "addr:street":"De Singel",
    "iso:country":"NL",
    "sg:address":"De Singel 67",
    "sg:city":"Drachten",
    "sg:classifiers":[
        {
            "category":"Fast Food",
            "type":"Food & Drink"
        }
    ],
    "sg:phone":"+31 512 522 196",
    "sg:postcode":"9203 XZ",
    "sg:province":"Friesland",
    "sg:tags":[
        "afhaal",
        "restaurant"
    ],
    "wof:name":"Kiosk De Singel",
    "wof:placetype":"venue"
},
  "geometry": {"coordinates":[6.106292,53.104057],"type":"Point"}
}