{
  "type": "Feature",
  "properties": {
    "iso:country":"NL",
    "sg:address":"Lombokstr 2A",
    "sg:city":"Den Helder",
    "sg:orig_category":"Peuterspeelzalen",
    "sg:phone":"+31 223 610 589",
    "sg:postcode":"1782 SR",
    "sg:province":"Noord-Holland",
    "wof:name":"Holderdebolder",
    "wof:placetype":"venue"
},
  "geometry": {"coordinates":[4.750279,52.958706],"type":"Point"}
}