{
  "type": "Feature",
  "properties": {
    "addr:full":"Molenstr 3 Waalre Noord-Brabant 5581 JT",
    "addr:housenumber":"3",
    "addr:postcode":"5581 jt",
    "addr:street":"Molenstr",
    "iso:country":"NL",
    "sg:address":"Molenstr 3",
    "sg:city":"Waalre",
    "sg:orig_category":"Autopoetsbedrijven",
    "sg:phone":"+31 40 221 2912",
    "sg:postcode":"5581 JT",
    "sg:province":"Noord-Brabant",
    "sg:website":"http://www.servicestationvanschijndel.nl",
    "wof:name":"Avia",
    "wof:placetype":"venue"
},
  "geometry": {"coordinates":[5.443154,51.385643],"type":"Point"}
}