{
  "type": "Feature",
  "properties": {
    "addr:full":"Deltaplein 526 'S Gravenhage South Holland 2554 GH",
    "addr:housenumber":"526 '",
    "addr:postcode":"2554 gh",
    "addr:street":"Deltaplein",
    "iso:country":"NL",
    "sg:address":"Deltaplein 526",
    "sg:city":"'S Gravenhage",
    "sg:orig_category":"Damesmodezaken",
    "sg:phone":"+31 70 323 4927",
    "sg:postcode":"2554 GH",
    "sg:province":"South Holland",
    "wof:name":"Boetiek High Lights",
    "wof:placetype":"venue"
},
  "geometry": {"coordinates":[4.220205,52.067902],"type":"Point"}
}