{
  "type": "Feature",
  "properties": {
    "addr:full":"Vlierbaan 24-26 Capelle Ad Yssel Zuid-Holland 2908 LR",
    "addr:housenumber":"24-26",
    "addr:postcode":"2908 lr",
    "addr:street":"Vlierbaan",
    "iso:country":"NL",
    "sg:address":"Vlierbaan 24-26",
    "sg:city":"Capelle Ad Yssel",
    "sg:orig_category":"Facilitaire Dienstverlening",
    "sg:phone":"+31 10 258 1117",
    "sg:postcode":"2908 LR",
    "sg:province":"Zuid-Holland",
    "sg:website":"http://www.hollandruiter.nl",
    "wof:name":"Beresteijn Bv",
    "wof:placetype":"venue"
},
  "geometry": {"coordinates":[4.573179,51.958],"type":"Point"}
}