{
  "type": "Feature",
  "properties": {
    "addr:full":"Heyendaalseweg 192 Nijmegen Gelderland 6525 SJ",
    "addr:housenumber":"192",
    "addr:postcode":"6525",
    "addr:street":"Heyendaalseweg;Gelderland",
    "iso:country":"NL",
    "sg:address":"Heyendaalseweg 192",
    "sg:city":"Nijmegen",
    "sg:orig_category":"Kappers",
    "sg:phone":"+31 24 355 4235",
    "sg:postcode":"6525 SJ",
    "sg:province":"Gelderland",
    "wof:name":"A C Prudon",
    "wof:placetype":"venue"
},
  "geometry": {"coordinates":[5.8667759895,51.8151626587],"type":"Point"}
}