{
  "type": "Feature",
  "properties": {
    "addr:full":"Veenwg 7 Epe Gelderland 8162 RJ",
    "addr:housenumber":"7",
    "addr:postcode":"8162 rj",
    "addr:street":"Veenwg;Gelderland",
    "iso:country":"NL",
    "sg:address":"Veenwg 7",
    "sg:city":"Epe",
    "sg:classifiers":[
        {
            "category":"Bus Charters",
            "type":"Transportation"
        }
    ],
    "sg:phone":"+31 578 627 770",
    "sg:postcode":"8162 RJ",
    "sg:province":"Gelderland",
    "sg:tags":[
        "caravan"
    ],
    "wof:name":"Rietveld, Caravans",
    "wof:placetype":"venue"
},
  "geometry": {"coordinates":[5.946418,52.335808],"type":"Point"}
}