{
  "type": "Feature",
  "properties": {
    "iso:country":"NL",
    "sg:address":"Steegstraat 19",
    "sg:city":"Linden",
    "sg:orig_category":"Kampeerterreinen",
    "sg:phone":"+31 485 314 650",
    "sg:postcode":"5439 NL",
    "sg:province":"Noord-Brabant",
    "wof:name":"Op Den Brul",
    "wof:placetype":"venue"
},
  "geometry": {"coordinates":[5.8361859322,51.7389755249],"type":"Point"}
}