{
  "type": "Feature",
  "properties": {
    "addr:full":"Peizerwg 2 Bunne Provincie Drenthe 9496 PC",
    "addr:housenumber":"2",
    "addr:postcode":"9496 pc",
    "addr:street":"Peizerwg;Provincie Drenthe",
    "iso:country":"NL",
    "sg:address":"Peizerwg 2",
    "sg:city":"Bunne",
    "sg:orig_category":"Metaalwaren - Fabrieken",
    "sg:phone":"+31 50 309 3116",
    "sg:postcode":"9496 PC",
    "sg:province":"Provincie Drenthe",
    "wof:name":"Bunne",
    "wof:placetype":"venue"
},
  "geometry": {"coordinates":[6.534066,53.117989],"type":"Point"}
}