{
  "type": "Feature",
  "properties": {
    "addr:full":"Schoolstr 2 Oostkapelle Zeeland 4356 BX",
    "addr:housenumber":"2",
    "addr:postcode":"4356 bx",
    "addr:street":"Schoolstr",
    "iso:country":"NL",
    "sg:address":"Schoolstr 2",
    "sg:city":"Oostkapelle",
    "sg:orig_category":"Verenigingsgebouwen",
    "sg:phone":"+31 118 582 006",
    "sg:postcode":"4356 BX",
    "sg:province":"Zeeland",
    "wof:name":"Halve Maan, De",
    "wof:placetype":"venue"
},
  "geometry": {"coordinates":[3.550562,51.56525],"type":"Point"}
}