{
  "type": "Feature",
  "properties": {
    "addr:full":"Steijnstraat 22 Hengelo Ov NL.08 7551 GL",
    "addr:housenumber":"22",
    "addr:postcode":"7551 gl",
    "addr:street":"Steijnstraat;Ov",
    "iso:country":"NL",
    "sg:address":"Steijnstraat 22",
    "sg:city":"Hengelo Ov",
    "sg:orig_category":"Glaszetten",
    "sg:phone":"+31 74 242 3139",
    "sg:postcode":"7551 GL",
    "sg:province":"NL.08",
    "wof:name":"Schildersbedrijf Moldovan Bv",
    "wof:placetype":"venue"
},
  "geometry": {"coordinates":[6.796521,52.266373],"type":"Point"}
}