{
  "type": "Feature",
  "properties": {
    "addr:full":"President Rooseveltlaan 731 Vlissingen Zeeland 4383 NG",
    "addr:housenumber":"731",
    "addr:postcode":"4383 ng",
    "addr:street":"President Rooseveltlaan",
    "iso:country":"NL",
    "sg:address":"President Rooseveltlaan 731",
    "sg:city":"Vlissingen",
    "sg:orig_category":"Autokeuringen",
    "sg:phone":"+31 118 414 926",
    "sg:postcode":"4383 NG",
    "sg:province":"Zeeland",
    "wof:name":"Esso",
    "wof:placetype":"venue"
},
  "geometry": {"coordinates":[3.581568,51.455105],"type":"Point"}
}