{
  "type": "Feature",
  "properties": {
    "addr:full":"Harderwijkerweg 88 Nunspeet Gelderland 8071 GC",
    "addr:housenumber":"88",
    "addr:postcode":"8071 gc",
    "addr:street":"Harderwijkerweg;Gelderland",
    "iso:country":"NL",
    "sg:address":"Harderwijkerweg 88",
    "sg:city":"Nunspeet",
    "sg:orig_category":"Verhuur Audiovisuele Apparatuur",
    "sg:phone":"+31 341 258 311",
    "sg:postcode":"8071 GC",
    "sg:province":"Gelderland",
    "wof:name":"Video 88",
    "wof:placetype":"venue"
},
  "geometry": {"coordinates":[5.772035,52.375092],"type":"Point"}
}