{
  "type": "Feature",
  "properties": {
    "iso:country":"NL",
    "sg:address":"G Vd Veenstr 14",
    "sg:city":"Middelburg",
    "sg:orig_category":"Scheepvaartservice- Bureaus",
    "sg:phone":"+31 118 628 114",
    "sg:postcode":"4333 AT",
    "sg:province":"Zeeland",
    "wof:name":"Schalk, G A J",
    "wof:placetype":"venue"
},
  "geometry": {"coordinates":[3.61638,51.508011],"type":"Point"}
}