{
  "type": "Feature",
  "properties": {
    "iso:country":"NL",
    "sg:address":"Voorstr 602",
    "sg:city":"Lelystad",
    "sg:orig_category":"Kinderopvang",
    "sg:phone":"+31 320 250 500",
    "sg:postcode":"8226 KZ",
    "sg:province":"NL.",
    "wof:name":"Ziezo",
    "wof:placetype":"venue"
},
  "geometry": {"coordinates":[5.49662,52.493771],"type":"Point"}
}