{
  "type": "Feature",
  "properties": {
    "addr:full":"Bonnefantenstr 43 Amsterdam Noord-Holland 1064 PP",
    "addr:housenumber":"43",
    "addr:postcode":"1064 pp",
    "addr:street":"Bonnefantenstr",
    "iso:country":"NL",
    "sg:address":"Bonnefantenstr 43",
    "sg:city":"Amsterdam",
    "sg:orig_category":"Adviesbureaus Bedrijfsorganisatie",
    "sg:phone":"+31 20 448 1083",
    "sg:postcode":"1064 PP",
    "sg:province":"Noord-Holland",
    "sg:website":"http://www.bitinglynx.com",
    "wof:name":"Biting Lynx",
    "wof:placetype":"venue"
},
  "geometry": {"coordinates":[4.830321,52.365837],"type":"Point"}
}