{
  "type": "Feature",
  "properties": {
    "iso:country":"NL",
    "sg:address":"Torenstraat 5",
    "sg:city":"Westzaan",
    "sg:classifiers":[
        {
            "category":"Education",
            "subcategory":"Preschool",
            "type":"Public Place"
        }
    ],
    "sg:phone":"+31 75 628 5761",
    "sg:postcode":"1551 BK",
    "sg:province":"Noord-Holland",
    "sg:tags":[
        "kleuteronderwijs",
        "basis-"
    ],
    "wof:name":"Openbare Basisschool De Kroosduiker",
    "wof:placetype":"venue"
},
  "geometry": {"coordinates":[4.7708959579,52.4630432129],"type":"Point"}
}