{
  "type": "Feature",
  "properties": {
    "addr:full":"Bergschild 39 Deventer NL.08 7411 EL",
    "addr:housenumber":"39;nl.08",
    "addr:postcode":"7411 el",
    "addr:street":"Bergschild",
    "iso:country":"NL",
    "sg:address":"Bergschild 39",
    "sg:city":"Deventer",
    "sg:orig_category":"Hulpverlening Sociaal",
    "sg:phone":"+31 570 641 863",
    "sg:postcode":"7411 EL",
    "sg:province":"NL.08",
    "wof:name":"Anti Discriminatie Bureau Oost",
    "wof:placetype":"venue"
},
  "geometry": {"coordinates":[6.1636,52.251648],"type":"Point"}
}