{
  "type": "Feature",
  "properties": {
    "addr:full":"Moergestelsewg 52 Oisterwyk Noord-Brabant 5062 SP",
    "addr:housenumber":"52",
    "addr:postcode":"5062 sp",
    "addr:street":"Moergestelsewg",
    "iso:country":"NL",
    "sg:address":"Moergestelsewg 52",
    "sg:city":"Oisterwyk",
    "sg:orig_category":"Adviesbureaus Bedrijfsorganisatie",
    "sg:phone":"+31 13 543 0180",
    "sg:postcode":"5062 SP",
    "sg:province":"Noord-Brabant",
    "wof:name":"Roskam Partners",
    "wof:placetype":"venue"
},
  "geometry": {"coordinates":[5.181492,51.566357],"type":"Point"}
}