{
  "type": "Feature",
  "properties": {
    "iso:country":"NL",
    "sg:address":"Molenstr 69",
    "sg:city":"Deurne",
    "sg:orig_category":"Administratie- En Boekhoudkantoren",
    "sg:phone":"+31 493 351 851",
    "sg:postcode":"5751 LC",
    "sg:province":"Noord-Brabant",
    "sg:website":"http://www.kantoorvandemortel.nl",
    "wof:name":"Mortel, Van De",
    "wof:placetype":"venue"
},
  "geometry": {"coordinates":[5.80171,51.462563],"type":"Point"}
}