{
  "type": "Feature",
  "properties": {
    "addr:full":"Birkstraat 136 Soest Utrecht 3768 HM",
    "addr:housenumber":"136",
    "addr:postcode":"3768 hm",
    "addr:street":"Birkstraat",
    "iso:country":"NL",
    "sg:address":"Birkstraat 136",
    "sg:city":"Soest",
    "sg:orig_category":"Werving And Selectie Van Vast Personeel",
    "sg:phone":"+31 33 462 6299",
    "sg:postcode":"3768 HM",
    "sg:province":"Utrecht",
    "wof:name":"Eugenie Ruyters Loopbaancounseling",
    "wof:placetype":"venue"
},
  "geometry": {"coordinates":[5.3374261856,52.1599464417],"type":"Point"}
}