{
  "type": "Feature",
  "properties": {
    "addr:full":"Koudekerksewg 126 Middelburg Zeeland 4335 HD",
    "addr:housenumber":"126",
    "addr:postcode":"4335 hd",
    "iso:country":"NL",
    "sg:address":"Koudekerksewg 126",
    "sg:city":"Middelburg",
    "sg:orig_category":"Vertaalbureaus",
    "sg:phone":"+31 118 634 319",
    "sg:postcode":"4335 HD",
    "sg:province":"Zeeland",
    "wof:name":"Abcdaire",
    "wof:placetype":"venue"
},
  "geometry": {"coordinates":[3.598662,51.491669],"type":"Point"}
}