{
  "type": "Feature",
  "properties": {
    "addr:full":"Dongensewg 13B Ryen Noord-Brabant 5121 PB",
    "addr:housenumber":"13b",
    "addr:postcode":"5121 pb",
    "addr:street":"Dongensewg",
    "iso:country":"NL",
    "sg:address":"Dongensewg 13B",
    "sg:city":"Ryen",
    "sg:orig_category":"Elektrotechnische Installatiebureaus",
    "sg:phone":"+31 6 24787184",
    "sg:postcode":"5121 PB",
    "sg:province":"Noord-Brabant",
    "wof:name":"Bartelse Bv",
    "wof:placetype":"venue"
},
  "geometry": {"coordinates":[4.9197,51.588017],"type":"Point"}
}