{
  "type": "Feature",
  "properties": {
    "addr:full":"Rozenstr 9 Purmerend North Holland 1441 HV",
    "addr:housenumber":"9",
    "addr:postcode":"1441 hv",
    "addr:street":"Rozenstr",
    "iso:country":"NL",
    "sg:address":"Rozenstr 9",
    "sg:city":"Purmerend",
    "sg:orig_category":"Plafonds",
    "sg:phone":"+31 299 642 784",
    "sg:postcode":"1441 HV",
    "sg:province":"North Holland",
    "wof:name":"Plamos, Systeemplafonds",
    "wof:placetype":"venue"
},
  "geometry": {"coordinates":[4.946772,52.502457],"type":"Point"}
}