{
  "type": "Feature",
  "properties": {
    "addr:full":"Langendk 34-36 Breda Noord-Brabant 4819 EW",
    "addr:housenumber":"34-36",
    "addr:postcode":"breda;4819 ew",
    "iso:country":"NL",
    "sg:address":"Langendk 34-36",
    "sg:city":"Breda",
    "sg:classifiers":[
        {
            "category":"Professional",
            "subcategory":"Accounting & Tax Preparation",
            "type":"Services"
        }
    ],
    "sg:phone":"+31 76 524 0500",
    "sg:postcode":"4819 EW",
    "sg:province":"Noord-Brabant",
    "sg:tags":[
        "accountant",
        "en",
        "-kantoren",
        "register-"
    ],
    "sg:website":"http://www.pwcglobal.com/nl",
    "wof:name":"Pricewaterhousecoopers",
    "wof:placetype":"venue"
},
  "geometry": {"coordinates":[4.765185,51.575348],"type":"Point"}
}