{
  "type": "Feature",
  "properties": {
    "addr:full":"Jodenberg 15 Nijmegen Gelderland 6511 CS",
    "addr:housenumber":"15",
    "addr:postcode":"6511 cs",
    "addr:street":"Jodenberg;Gelderland",
    "iso:country":"NL",
    "sg:address":"Jodenberg 15",
    "sg:city":"Nijmegen",
    "sg:orig_category":"Artiesten",
    "sg:phone":"+31 24 360 4999",
    "sg:postcode":"6511 CS",
    "sg:province":"Gelderland",
    "wof:name":"Inez Lenders",
    "wof:placetype":"venue"
},
  "geometry": {"coordinates":[5.860967,51.847374],"type":"Point"}
}