{
  "type": "Feature",
  "properties": {
    "addr:full":"Kampstr 9 Baarn Utrecht 3741 AP",
    "addr:housenumber":"9",
    "addr:postcode":"3741 ap",
    "addr:street":"Kampstr",
    "iso:country":"NL",
    "sg:address":"Kampstr 9",
    "sg:city":"Baarn",
    "sg:orig_category":"Logopedisten",
    "sg:phone":"+31 35 542 6900",
    "sg:postcode":"3741 AP",
    "sg:province":"Utrecht",
    "wof:name":"Logopediepraktijk Voor Kinderen",
    "wof:placetype":"venue"
},
  "geometry": {"coordinates":[5.291782,52.213665],"type":"Point"}
}