{
  "type": "Feature",
  "properties": {
    "addr:full":"Van Harenstraat 52 Wolvega Friesland 8471 JG",
    "addr:housenumber":"52",
    "addr:postcode":"8471 jg",
    "addr:street":"Van Harenstraat",
    "iso:country":"NL",
    "sg:address":"Van Harenstraat 52",
    "sg:city":"Wolvega",
    "sg:orig_category":"Verlichting And Huishoudartikelen",
    "sg:phone":"+31 561 612 226",
    "sg:postcode":"8471 JG",
    "sg:province":"Friesland",
    "wof:name":"Blokker",
    "wof:placetype":"venue"
},
  "geometry": {"coordinates":[5.998168,52.875362],"type":"Point"}
}