{
  "type": "Feature",
  "properties": {
    "addr:full":"Zeekant 104 'S Gravenhage Zuid-Holland 2586 JJ",
    "addr:housenumber":"104 '",
    "addr:postcode":"2586 jj",
    "addr:street":"Zeekant",
    "iso:country":"NL",
    "sg:address":"Zeekant 104",
    "sg:city":"'S Gravenhage",
    "sg:orig_category":"Vertaal- And Tolkenbureaus",
    "sg:phone":"+31 70 351 4294",
    "sg:postcode":"2586 JJ",
    "sg:province":"Zuid-Holland",
    "wof:name":"Translinea",
    "wof:placetype":"venue"
},
  "geometry": {"coordinates":[4.286356,52.116394],"type":"Point"}
}