{
  "type": "Feature",
  "properties": {
    "iso:country":"NL",
    "sg:address":"Groningerstraat 59-61",
    "sg:city":"Assen",
    "sg:orig_category":"Meubelzaken, Woning- And Keukeninrichting",
    "sg:phone":"+31 592 302 033",
    "sg:postcode":"9401 BJ",
    "sg:province":"Drenthe",
    "wof:name":"Bed Direkt Bv",
    "wof:placetype":"venue"
},
  "geometry": {"coordinates":[6.56492,52.998035],"type":"Point"}
}