{
  "type": "Feature",
  "properties": {
    "iso:country":"NL",
    "sg:address":"Overcingelln 17",
    "sg:city":"Assen",
    "sg:classifiers":[
        {
            "category":"Shopping",
            "subcategory":"News",
            "type":"Retail Goods"
        }
    ],
    "sg:phone":"+31 592 329 500",
    "sg:postcode":"9401 LA",
    "sg:province":"Provincie Drenthe",
    "sg:tags":[
        "maandbladen",
        "en",
        "week-"
    ],
    "wof:name":"Gezinsblad, Het",
    "wof:placetype":"venue"
},
  "geometry": {"coordinates":[6.5695610046,52.9903182983],"type":"Point"}
}