{
  "type": "Feature",
  "properties": {
    "addr:full":"Keenstraat 45 Rotterdam Zuid-Holland 3044 CD",
    "addr:housenumber":"45",
    "addr:postcode":"3044 cd",
    "addr:street":"Keenstraat",
    "iso:country":"NL",
    "sg:address":"Keenstraat 45",
    "sg:city":"Rotterdam",
    "sg:orig_category":"Goederenvervoer Over De Weg",
    "sg:phone":"+31 10 262 3378",
    "sg:postcode":"3044 CD",
    "sg:province":"Zuid-Holland",
    "wof:name":"Campina Melkunie Rotterdam Bedrijf Spaanse Polder",
    "wof:placetype":"venue"
},
  "geometry": {"coordinates":[4.417248,51.929981],"type":"Point"}
}