{
  "type": "Feature",
  "properties": {
    "iso:country":"NL",
    "sg:address":"De Boelelaan 7",
    "sg:city":"Amsterdam",
    "sg:orig_category":"Luchtvaart",
    "sg:phone":"+31 20 504 0606",
    "sg:postcode":"1083 HJ",
    "sg:province":"Noord-Holland",
    "wof:name":"Delta Air Lines Schiphol",
    "wof:placetype":"venue"
},
  "geometry": {"coordinates":[4.885723,52.334583],"type":"Point"}
}