{
  "type": "Feature",
  "properties": {
    "iso:country":"NL",
    "sg:address":"Nykampenwg 146",
    "sg:city":"Emmen",
    "sg:orig_category":"Kappers",
    "sg:phone":"+31 591 641 767",
    "sg:postcode":"7815 GS",
    "sg:province":"Drenthe",
    "wof:name":"House For Hair",
    "wof:placetype":"venue"
},
  "geometry": {"coordinates":[6.8946771622,52.7976531982],"type":"Point"}
}