{
  "type": "Feature",
  "properties": {
    "addr:full":"Burgemeester De Bruineln 115 Zwijndrecht South Holland 3331 AD",
    "addr:housenumber":"115",
    "addr:postcode":"3331 ad",
    "addr:street":"Burgemeester De Bruineln",
    "iso:country":"NL",
    "sg:address":"Burgemeester De Bruineln 115",
    "sg:city":"Zwijndrecht",
    "sg:classifiers":[
        {
            "category":"Fast Food",
            "type":"Food & Drink"
        }
    ],
    "sg:phone":"+31 78 610 0107",
    "sg:postcode":"3331 AD",
    "sg:province":"South Holland",
    "sg:tags":[
        "afhaal",
        "restaurant"
    ],
    "wof:name":"Pizzaland Di Mario",
    "wof:placetype":"venue"
},
  "geometry": {"coordinates":[4.646851,51.815388],"type":"Point"}
}