{
  "type": "Feature",
  "properties": {
    "addr:full":"Thijssestraat 59 'S Gravenhage South Holland 2521 ZE",
    "addr:housenumber":"59",
    "addr:postcode":"2521 ze",
    "addr:street":"Thijssestraat;' S Gravenhage",
    "iso:country":"NL",
    "sg:address":"Thijssestraat 59",
    "sg:city":"'S Gravenhage",
    "sg:classifiers":[
        {
            "category":"Fast Food",
            "type":"Food & Drink"
        }
    ],
    "sg:phone":"+31 70 399 9761",
    "sg:postcode":"2521 ZE",
    "sg:province":"South Holland",
    "sg:tags":[
        "afhaal",
        "restaurant"
    ],
    "wof:name":"Restaurant Pearl Corner",
    "wof:placetype":"venue"
},
  "geometry": {"coordinates":[4.321153,52.063068],"type":"Point"}
}