{
  "type": "Feature",
  "properties": {
    "iso:country":"NL",
    "sg:address":"Zaanstr 232",
    "sg:city":"Amsterdam",
    "sg:orig_category":"Onderhoudswerken",
    "sg:phone":"+31 6 54286233",
    "sg:postcode":"1013 RX",
    "sg:province":"Noord-Holland",
    "wof:name":"Dopheide, J",
    "wof:placetype":"venue"
},
  "geometry": {"coordinates":[4.87326,52.390247],"type":"Point"}
}