{
  "type": "Feature",
  "properties": {
    "iso:country":"NL",
    "sg:address":"Kolhornerkade 9",
    "sg:city":"Kolhorn",
    "sg:orig_category":"Alternatieve Geneeskunde",
    "sg:phone":"+31 224 533 068",
    "sg:postcode":"1767 CA",
    "sg:province":"Noord-Holland",
    "wof:name":"Klassieke Homeopathie A.M.K. Van De Wel",
    "wof:placetype":"venue"
},
  "geometry": {"coordinates":[4.881237,52.788437],"type":"Point"}
}