{
  "type": "Feature",
  "properties": {
    "addr:full":"Diepenveensewg 13 Deventer Overijssel 7413 AK",
    "addr:housenumber":"13",
    "addr:postcode":"7413 ak",
    "addr:street":"Diepenveensewg",
    "iso:country":"NL",
    "sg:address":"Diepenveensewg 13",
    "sg:city":"Deventer",
    "sg:orig_category":"Zoetwaren - Winkels",
    "sg:phone":"+31 6 22434838",
    "sg:postcode":"7413 AK",
    "sg:province":"Overijssel",
    "wof:name":"Schimmel, J",
    "wof:placetype":"venue"
},
  "geometry": {"coordinates":[6.157112,52.26046],"type":"Point"}
}