{
  "type": "Feature",
  "properties": {
    "addr:full":"De Hessellepln 13 Heerlen Limburg 6411 CG",
    "addr:housenumber":"13",
    "addr:postcode":"6411 cg",
    "iso:country":"NL",
    "sg:address":"De Hessellepln 13",
    "sg:city":"Heerlen",
    "sg:orig_category":"Makelaars En Adviseurs Onroerende Goederen",
    "sg:phone":"+31 45 574 1616",
    "sg:postcode":"6411 CG",
    "sg:province":"Limburg",
    "sg:website":"http://www.vandepas.nl",
    "wof:name":"Pas, Van De",
    "wof:placetype":"venue"
},
  "geometry": {"coordinates":[5.975672,50.884235],"type":"Point"}
}