{
  "type": "Feature",
  "properties": {
    "addr:full":"Veldstraat 2 Baarn Utrecht 3741 AS",
    "addr:housenumber":"2",
    "addr:postcode":"3741 as",
    "addr:street":"Veldstraat",
    "iso:country":"NL",
    "sg:address":"Veldstraat 2",
    "sg:city":"Baarn",
    "sg:orig_category":"Verhuur Diversen",
    "sg:phone":"+31 35 541 7933",
    "sg:postcode":"3741 AS",
    "sg:province":"Utrecht",
    "wof:name":"Marktkramen-Exploitant A.M. Majoor",
    "wof:placetype":"venue"
},
  "geometry": {"coordinates":[5.29046,52.213043],"type":"Point"}
}