{
  "type": "Feature",
  "properties": {
    "addr:full":"Sportln 20 Oldenzaal Overijssel 7576 WV",
    "addr:housenumber":"20",
    "addr:postcode":"7576 wv",
    "addr:street":"Sportln",
    "iso:country":"NL",
    "sg:address":"Sportln 20",
    "sg:city":"Oldenzaal",
    "sg:orig_category":"Adviesbureaus Bedrijfsorganisatie",
    "sg:phone":"+31 541 532 399",
    "sg:postcode":"7576 WV",
    "sg:province":"Overijssel",
    "wof:name":"Garinco Bv",
    "wof:placetype":"venue"
},
  "geometry": {"coordinates":[6.927277,52.309284],"type":"Point"}
}