{
  "type": "Feature",
  "properties": {
    "addr:full":"Bergpolderpln 7A Rotterdam Zuid-Holland 3051 GA",
    "addr:housenumber":"7a",
    "addr:postcode":"3051 ga",
    "addr:street":"Bergpolderpln",
    "iso:country":"NL",
    "sg:address":"Bergpolderpln 7A",
    "sg:city":"Rotterdam",
    "sg:classifiers":[
        {
            "category":"Food & Beverages",
            "subcategory":"Bakery",
            "type":"Retail Goods"
        }
    ],
    "sg:phone":"+31 10 218 8572",
    "sg:postcode":"3051 GA",
    "sg:province":"Zuid-Holland",
    "sg:tags":[
        "pizza"
    ],
    "wof:name":"Hillegersberg",
    "wof:placetype":"venue"
},
  "geometry": {"coordinates":[4.475673,51.94495],"type":"Point"}
}