{
  "type": "Feature",
  "properties": {
    "addr:full":"Streeperstraat 29 Landgraaf Limburg 6371 GL",
    "addr:housenumber":"29",
    "addr:postcode":"6371 gl",
    "addr:street":"Streeperstraat",
    "iso:country":"NL",
    "sg:address":"Streeperstraat 29",
    "sg:city":"Landgraaf",
    "sg:orig_category":"Medische Apparatuur And Prothesen Fab",
    "sg:phone":"+31 45 531 5921",
    "sg:postcode":"6371 GL",
    "sg:province":"Limburg",
    "wof:name":"Tandtechniek Borsboom-Moers",
    "wof:placetype":"venue"
},
  "geometry": {"coordinates":[6.015387,50.898296],"type":"Point"}
}