{
  "type": "Feature",
  "properties": {
    "iso:country":"NL",
    "sg:address":"Luxemburgstr 11",
    "sg:city":"Oisterwyk",
    "sg:orig_category":"Houtgroothandel",
    "sg:phone":"+31 13 522 0033",
    "sg:postcode":"5061 JW",
    "sg:province":"Noord-Brabant",
    "wof:name":"Holland Laminaat Bv",
    "wof:placetype":"venue"
},
  "geometry": {"coordinates":[5.1905,51.583092],"type":"Point"}
}