{
  "type": "Feature",
  "properties": {
    "addr:full":"Elbertsveen 19 Blaricum North Holland 1261 VP",
    "addr:housenumber":"19",
    "addr:postcode":"1261 vp",
    "addr:street":"Elbertsveen",
    "iso:country":"NL",
    "sg:address":"Elbertsveen 19",
    "sg:city":"Blaricum",
    "sg:orig_category":"Binnenhuisarchitecten",
    "sg:phone":"+31 35 538 2439",
    "sg:postcode":"1261 VP",
    "sg:province":"North Holland",
    "wof:name":"Art & Styling Elly Pijpers",
    "wof:placetype":"venue"
},
  "geometry": {"coordinates":[5.255488,52.270081],"type":"Point"}
}