{
  "type": "Feature",
  "properties": {
    "addr:full":"Middelwyk 31 Drachten Provincie Friesland 9202 GN",
    "addr:housenumber":"31",
    "addr:postcode":"9202 gn",
    "addr:street":"Middelwyk;Provincie Friesland",
    "iso:country":"NL",
    "sg:address":"Middelwyk 31",
    "sg:city":"Drachten",
    "sg:orig_category":"Postkantoren",
    "sg:phone":"+31 512 546 588",
    "sg:postcode":"9202 GN",
    "sg:province":"Provincie Friesland",
    "sg:website":"http://www.postkantoor.nl",
    "wof:name":"Postkantoor",
    "wof:placetype":"venue"
},
  "geometry": {"coordinates":[6.110765,53.109615],"type":"Point"}
}