{
  "type": "Feature",
  "properties": {
    "addr:full":"Zylbaan 14 Leiderdorp Zuid-Holland 2352 BN",
    "addr:housenumber":"14",
    "addr:postcode":"2352 bn",
    "addr:street":"Zylbaan",
    "iso:country":"NL",
    "sg:address":"Zylbaan 14",
    "sg:city":"Leiderdorp",
    "sg:orig_category":"Keukens",
    "sg:phone":"+31 71 331 1063",
    "sg:postcode":"2352 BN",
    "sg:province":"Zuid-Holland",
    "wof:name":"Bons, E",
    "wof:placetype":"venue"
},
  "geometry": {"coordinates":[4.534218,52.156174],"type":"Point"}
}