{
  "type": "Feature",
  "properties": {
    "addr:full":"Peizerweg 132 Groningen Groningen 9727 AN",
    "addr:housenumber":"132",
    "addr:postcode":"9727 an",
    "addr:street":"Peizerweg",
    "iso:country":"NL",
    "sg:address":"Peizerweg 132",
    "sg:city":"Groningen",
    "sg:orig_category":"Drukkerijen And Copyshops",
    "sg:phone":"+31 50 525 9340",
    "sg:postcode":"9727 AN",
    "sg:province":"Groningen",
    "wof:name":"Reco - Studio",
    "wof:placetype":"venue"
},
  "geometry": {"coordinates":[6.540903,53.208508],"type":"Point"}
}