{
  "type": "Feature",
  "properties": {
    "addr:full":"Raadhuisstraat 114 Hoogerheide Noord-Brabant 4631 NJ",
    "addr:housenumber":"114",
    "addr:postcode":"4631 nj",
    "addr:street":"Raadhuisstraat",
    "iso:country":"NL",
    "sg:address":"Raadhuisstraat 114",
    "sg:city":"Hoogerheide",
    "sg:orig_category":"Opticiens",
    "sg:phone":"+31 164 613 692",
    "sg:postcode":"4631 NJ",
    "sg:province":"Noord-Brabant",
    "wof:name":"Govaert Optiek",
    "wof:placetype":"venue"
},
  "geometry": {"coordinates":[4.3233180046,51.4239501953],"type":"Point"}
}