{
  "type": "Feature",
  "properties": {
    "addr:full":"Maliesngl 13 Utrecht Utrecht 3581 BC",
    "addr:housenumber":"13",
    "addr:postcode":"3581 bc",
    "addr:street":"Maliesngl",
    "iso:country":"NL",
    "sg:address":"Maliesngl 13",
    "sg:city":"Utrecht",
    "sg:orig_category":"Verzekeringen - Verzekeringskantoren",
    "sg:phone":"+31 30 236 8668",
    "sg:postcode":"3581 BC",
    "sg:province":"Utrecht",
    "sg:website":"http://www.vanluin.nl",
    "wof:name":"Luin Assuranti\u00ebn Bv, Van",
    "wof:placetype":"venue"
},
  "geometry": {"coordinates":[5.13447,52.089989],"type":"Point"}
}