{
  "type": "Feature",
  "properties": {
    "addr:full":"Noldijk 124 Barendrecht Zuid-Holland 2991 VL",
    "addr:housenumber":"124",
    "addr:postcode":"2991 vl",
    "addr:street":"Noldijk",
    "iso:country":"NL",
    "sg:address":"Noldijk 124",
    "sg:city":"Barendrecht",
    "sg:orig_category":"Architecten",
    "sg:phone":"+31 78 677 2425",
    "sg:postcode":"2991 VL",
    "sg:province":"Zuid-Holland",
    "wof:name":"Labyrinth Tuinexterieur",
    "wof:placetype":"venue"
},
  "geometry": {"coordinates":[4.563034,51.842102],"type":"Point"}
}