{
  "type": "Feature",
  "properties": {
    "iso:country":"NL",
    "sg:address":"Keienbergwg 11",
    "sg:city":"Amsterdam Zuidoost",
    "sg:orig_category":"Drukwerkverspreiding",
    "sg:phone":"+31 20 691 0331",
    "sg:postcode":"1101 EZ",
    "sg:province":"Noord-Holland",
    "sg:website":"http://www.arv-bv.nl",
    "wof:name":"Amsterdamse Reclame Verspreiding",
    "wof:placetype":"venue"
},
  "geometry": {"coordinates":[4.936445,52.307793],"type":"Point"}
}