{
  "type": "Feature",
  "properties": {
    "iso:country":"NL",
    "sg:address":"J Vermeerstr 35",
    "sg:city":"Heemstede",
    "sg:orig_category":"Adviesbureaus Bedrijfsorganisatie",
    "sg:phone":"+31 23 529 5342",
    "sg:postcode":"2102 BT",
    "sg:province":"Noord-Holland",
    "wof:name":"Hs&P",
    "wof:placetype":"venue"
},
  "geometry": {"coordinates":[4.63118,52.359856],"type":"Point"}
}