{
  "type": "Feature",
  "properties": {
    "addr:full":"De Genestetstraat 2 Leiden Zuid-Holland 2321 XM",
    "addr:housenumber":"2",
    "addr:postcode":"2321 xm",
    "addr:street":"De Genestetstraat",
    "iso:country":"NL",
    "sg:address":"De Genestetstraat 2",
    "sg:city":"Leiden",
    "sg:classifiers":[
        {
            "category":"Bakery",
            "type":"Food & Drink"
        }
    ],
    "sg:phone":"+31 71 531 0300",
    "sg:postcode":"2321 XM",
    "sg:province":"Zuid-Holland",
    "sg:tags":[
        "brood",
        "banket"
    ],
    "wof:name":"N.P. Van Cassel Vof",
    "wof:placetype":"venue"
},
  "geometry": {"coordinates":[4.476219,52.158794],"type":"Point"}
}