{
  "type": "Feature",
  "properties": {
    "addr:full":"J H Leopoldhof 12 Weesp North Holland 1382 TJ",
    "addr:housenumber":"12",
    "addr:postcode":"1382 tj",
    "iso:country":"NL",
    "sg:address":"J H Leopoldhof 12",
    "sg:city":"Weesp",
    "sg:orig_category":"Fotostudio'S And Fotografen",
    "sg:phone":"+31 294 415 641",
    "sg:postcode":"1382 TJ",
    "sg:province":"North Holland",
    "wof:name":"Luchtfotografie Snow-White",
    "wof:placetype":"venue"
},
  "geometry": {"coordinates":[5.039397,52.312691],"type":"Point"}
}