{
  "type": "Feature",
  "properties": {
    "addr:full":"Provinciepassage 35 Alphen Aan Den Ryn Zuid-Holland 2408 GT",
    "addr:housenumber":"35",
    "addr:postcode":"2408 gt",
    "addr:street":"Provinciepassage;Aan Den Ryn",
    "iso:country":"NL",
    "sg:address":"Provinciepassage 35",
    "sg:city":"Alphen Aan Den Ryn",
    "sg:classifiers":[
        {
            "category":"Food & Beverages",
            "subcategory":"Fruits & Vegetables",
            "type":"Retail Goods"
        }
    ],
    "sg:phone":"+31 172 478 434",
    "sg:postcode":"2408 GT",
    "sg:province":"Zuid-Holland",
    "sg:tags":[
        "en",
        "groenten"
    ],
    "wof:name":"Vergunst, K",
    "wof:placetype":"venue"
},
  "geometry": {"coordinates":[4.651865,52.124977],"type":"Point"}
}