{
  "type": "Feature",
  "properties": {
    "addr:full":"Esdoornlaan 9 Sleeuwijk Noord-Brabant 4254 AT",
    "addr:housenumber":"9",
    "addr:postcode":"4254",
    "addr:street":"Esdoornlaan",
    "iso:country":"NL",
    "sg:address":"Esdoornlaan 9",
    "sg:city":"Sleeuwijk",
    "sg:orig_category":"Banken And Kredietinstellingen",
    "sg:phone":"+31 183 301 221",
    "sg:postcode":"4254 AT",
    "sg:province":"Noord-Brabant",
    "wof:name":"Postkantoor",
    "wof:placetype":"venue"
},
  "geometry": {"coordinates":[4.951049,51.813957],"type":"Point"}
}