{
  "type": "Feature",
  "properties": {
    "addr:full":"Spartapk O 1315 Rotterdam Flevoland 3027 VX",
    "addr:housenumber":"1315",
    "addr:postcode":"3027 vx",
    "addr:street":"Flevoland",
    "iso:country":"NL",
    "sg:address":"Spartapk O 1315",
    "sg:city":"Rotterdam",
    "sg:orig_category":"Omroep",
    "sg:phone":"+31 10 244 0929",
    "sg:postcode":"3027 VX",
    "sg:province":"Flevoland",
    "sg:website":"http://www.amorfm.nl",
    "wof:name":"Amor Fm",
    "wof:placetype":"venue"
},
  "geometry": {"coordinates":[4.433507,51.920094],"type":"Point"}
}