{
  "type": "Feature",
  "properties": {
    "iso:country":"NL",
    "sg:address":"Oostermeent-Noord 198",
    "sg:city":"Huizen",
    "sg:orig_category":"Wasserettes And Stomerijen",
    "sg:phone":"+31 35 526 0063",
    "sg:postcode":"1274 SH",
    "sg:province":"North Holland",
    "wof:name":"Cleaning Cristal",
    "wof:placetype":"venue"
},
  "geometry": {"coordinates":[5.2641601562,52.2948875427],"type":"Point"}
}