{
  "type": "Feature",
  "properties": {
    "addr:full":"Bik En Arnoldkade 15 Ijmuiden Noord-Holland 1975 CG",
    "addr:housenumber":"15",
    "addr:postcode":"1975 cg",
    "addr:street":"Bik En Arnoldkade",
    "iso:country":"NL",
    "sg:address":"Bik En Arnoldkade 15",
    "sg:city":"Ijmuiden",
    "sg:orig_category":"Autokeuringen",
    "sg:phone":"+31 255 522 459",
    "sg:postcode":"1975 CG",
    "sg:province":"Noord-Holland",
    "wof:name":"Garage Alliance",
    "wof:placetype":"venue"
},
  "geometry": {"coordinates":[4.588315,52.462227],"type":"Point"}
}