{
  "type": "Feature",
  "properties": {
    "iso:country":"NL",
    "sg:address":"Bik En Arnoldkade 15",
    "sg:city":"Ijmuiden",
    "sg:orig_category":"Autokeuringen",
    "sg:phone":"+31 255 522 459",
    "sg:postcode":"1975 CG",
    "sg:province":"Noord-Holland",
    "wof:name":"Garage Alliance",
    "wof:placetype":"venue"
},
  "geometry": {"coordinates":[4.588315,52.462227],"type":"Point"}
}