{
  "type": "Feature",
  "properties": {
    "iso:country":"NL",
    "sg:address":"Dirk Boutslaan 24",
    "sg:city":"Eindhoven",
    "sg:orig_category":"Autokeuringen",
    "sg:phone":"+31 40 211 3843",
    "sg:postcode":"5613 LH",
    "sg:province":"North Brabant",
    "wof:name":"Citroenspecialistjan Van Gompel",
    "wof:placetype":"venue"
},
  "geometry": {"coordinates":[5.497694,51.434341],"type":"Point"}
}