{
  "type": "Feature",
  "properties": {
    "addr:full":"Koninginnehof 2 Tilburg North Brabant 5046 PC",
    "addr:housenumber":"2",
    "addr:postcode":"5046 pc",
    "addr:street":"Koninginnehof",
    "iso:country":"NL",
    "sg:address":"Koninginnehof 2",
    "sg:city":"Tilburg",
    "sg:orig_category":"Vertaal- And Tolkenbureaus",
    "sg:phone":"+31 13 543 3040",
    "sg:postcode":"5046 PC",
    "sg:province":"North Brabant",
    "wof:name":"Vof Van Cuijlenborg En Bredman",
    "wof:placetype":"venue"
},
  "geometry": {"coordinates":[5.067527,51.573776],"type":"Point"}
}