{
  "type": "Feature",
  "properties": {
    "addr:full":"Linnaeusdreef 24 Breukelen Ut Utrecht 3621 XW",
    "addr:housenumber":"24",
    "addr:postcode":"3621 xw",
    "addr:street":"Linnaeusdreef",
    "iso:country":"NL",
    "sg:address":"Linnaeusdreef 24",
    "sg:city":"Breukelen Ut",
    "sg:classifiers":[
        {
            "category":"Professional",
            "subcategory":"Accounting & Tax Preparation",
            "type":"Services"
        }
    ],
    "sg:phone":"+31 346 263 662",
    "sg:postcode":"3621 XW",
    "sg:province":"Utrecht",
    "sg:tags":[
        "accountant"
    ],
    "wof:name":"Werkpoot Accountancy",
    "wof:placetype":"venue"
},
  "geometry": {"coordinates":[5.001797,52.18549],"type":"Point"}
}