{
  "type": "Feature",
  "properties": {
    "addr:full":"Nw Bogerdstr 47 Zierikzee Zeeland 4301 CW",
    "addr:housenumber":"47",
    "addr:postcode":"4301 cw",
    "iso:country":"NL",
    "sg:address":"Nw Bogerdstr 47",
    "sg:city":"Zierikzee",
    "sg:orig_category":"Schilders",
    "sg:phone":"+31 111 412 567",
    "sg:postcode":"4301 CW",
    "sg:province":"Zeeland",
    "wof:name":"Koster Bv, Gebr",
    "wof:placetype":"venue"
},
  "geometry": {"coordinates":[3.919972,51.647503],"type":"Point"}
}