{
  "type": "Feature",
  "properties": {
    "addr:full":"Conradweg 14 Arnhem Gelderland 6827 BZ",
    "addr:housenumber":"14",
    "addr:postcode":"6827 bz",
    "addr:street":"Conradweg",
    "iso:country":"NL",
    "sg:address":"Conradweg 14",
    "sg:city":"Arnhem",
    "sg:orig_category":"Fotostudio'S And Fotografen",
    "sg:phone":"+31 26 311 3871",
    "sg:postcode":"6827 BZ",
    "sg:province":"Gelderland",
    "wof:name":"Foto Wilco",
    "wof:placetype":"venue"
},
  "geometry": {"coordinates":[5.945207,51.977528],"type":"Point"}
}