{
  "type": "Feature",
  "properties": {
    "addr:full":"Sikkeldreef 184 Doetinchem Gelderland 7006 KZ",
    "addr:housenumber":"184",
    "addr:postcode":"7006",
    "addr:street":"Sikkeldreef;Gelderland",
    "iso:country":"NL",
    "sg:address":"Sikkeldreef 184",
    "sg:city":"Doetinchem",
    "sg:orig_category":"Kantoorbenodigdheden",
    "sg:phone":"+31 314 378 760",
    "sg:postcode":"7006 KZ",
    "sg:province":"Gelderland",
    "sg:website":"http://www.view.nl",
    "wof:name":"View Archiefsystemen",
    "wof:placetype":"venue"
},
  "geometry": {"coordinates":[6.2507910728,51.9679412842],"type":"Point"}
}