{
  "type": "Feature",
  "properties": {
    "addr:full":"Berkenln 32 Sittard Limburg 6133 WZ",
    "addr:housenumber":"32",
    "addr:postcode":"6133 wz",
    "addr:street":"Berkenln",
    "iso:country":"NL",
    "sg:address":"Berkenln 32",
    "sg:city":"Sittard",
    "sg:orig_category":"Accountants - Administratie- Consulenten En -Kantoren",
    "sg:phone":"+31 46 458 0552",
    "sg:postcode":"6133 WZ",
    "sg:province":"Limburg",
    "wof:name":"Reinders & Partners Bv",
    "wof:placetype":"venue"
},
  "geometry": {"coordinates":[5.86046,50.991581],"type":"Point"}
}