{
  "type": "Feature",
  "properties": {
    "iso:country":"NL",
    "sg:address":"Breudk 33",
    "sg:city":"Harmelen",
    "sg:orig_category":"Adviesbureaus Bouwkunde",
    "sg:phone":"+31 348 445 144",
    "sg:postcode":"3481 LN",
    "sg:province":"Utrecht",
    "wof:name":"Meijst",
    "wof:placetype":"venue"
},
  "geometry": {"coordinates":[4.961517,52.102108],"type":"Point"}
}