{
  "type": "Feature",
  "properties": {
    "iso:country":"NL",
    "sg:address":"Slibbroek 10",
    "sg:city":"Hilvarenbeek",
    "sg:orig_category":"Drukkerijen And Copyshops",
    "sg:phone":"+31 13 505 3758",
    "sg:postcode":"5081 NS",
    "sg:province":"Noord-Brabant",
    "wof:name":"Drukkerij Van De Ven Vof",
    "wof:placetype":"venue"
},
  "geometry": {"coordinates":[5.1379,51.493298],"type":"Point"}
}