{
  "type": "Feature",
  "properties": {
    "addr:full":"Spykerstr 110 Arnhem Gelderland 6828 DN",
    "addr:housenumber":"110",
    "addr:postcode":"6828 dn",
    "iso:country":"NL",
    "sg:address":"Spykerstr 110",
    "sg:city":"Arnhem",
    "sg:orig_category":"Galeries",
    "sg:phone":"+31 26 446 1893",
    "sg:postcode":"6828 DN",
    "sg:province":"Gelderland",
    "wof:name":"Kousbroek, Rudy",
    "wof:placetype":"venue"
},
  "geometry": {"coordinates":[5.918875,51.982529],"type":"Point"}
}