{
  "type": "Feature",
  "properties": {
    "addr:full":"W Pyrmontln 28 Doorwerth Gelderland 6865 HH",
    "addr:housenumber":"28",
    "addr:postcode":"6865 hh",
    "addr:street":"W;Gelderland",
    "iso:country":"NL",
    "sg:address":"W Pyrmontln 28",
    "sg:city":"Doorwerth",
    "sg:orig_category":"Verzekeringen - Verzekeringskantoren",
    "sg:phone":"+31 26 333 7550",
    "sg:postcode":"6865 HH",
    "sg:province":"Gelderland",
    "wof:name":"Sietsma",
    "wof:placetype":"venue"
},
  "geometry": {"coordinates":[5.80089,51.980515],"type":"Point"}
}