{
  "type": "Feature",
  "properties": {
    "addr:full":"Bloemendalerwg 12 Weesp North Holland 1382 KC",
    "addr:housenumber":"12",
    "addr:postcode":"1382 kc",
    "addr:street":"Bloemendalerwg",
    "iso:country":"NL",
    "sg:address":"Bloemendalerwg 12",
    "sg:city":"Weesp",
    "sg:orig_category":"Elektronica - Ontwikkeling En Groothandel",
    "sg:phone":"+31 294 491 777",
    "sg:postcode":"1382 KC",
    "sg:province":"North Holland",
    "wof:name":"Key Electronica Bv",
    "wof:placetype":"venue"
},
  "geometry": {"coordinates":[5.02871,52.318562],"type":"Point"}
}