{
  "type": "Feature",
  "properties": {
    "addr:full":"Dorpsstr 35C Castricum North Holland 1901 EH",
    "addr:housenumber":"35c",
    "addr:postcode":"1901 eh",
    "addr:street":"Dorpsstr",
    "iso:country":"NL",
    "sg:address":"Dorpsstr 35C",
    "sg:city":"Castricum",
    "sg:classifiers":[
        {
            "category":"Shopping",
            "subcategory":"News",
            "type":"Retail Goods"
        }
    ],
    "sg:phone":"+31 251 658 850",
    "sg:postcode":"1901 EH",
    "sg:province":"North Holland",
    "sg:tags":[
        "maandbladen",
        "en",
        "week-"
    ],
    "wof:name":"Nieuwsblad Voor Castricum",
    "wof:placetype":"venue"
},
  "geometry": {"coordinates":[4.6620731354,52.5463027954],"type":"Point"}
}