{
  "type": "Feature",
  "properties": {
    "iso:country":"NL",
    "sg:address":"Krimwg 10",
    "sg:city":"Oostvoorne",
    "sg:orig_category":"Vakantieverblijven",
    "sg:phone":"+31 181 483 564",
    "sg:postcode":"3233 NB",
    "sg:province":"Zuid-Holland",
    "wof:name":"Samuel Naardenhuis, Het",
    "wof:placetype":"venue"
},
  "geometry": {"coordinates":[4.10962,51.93478],"type":"Point"}
}