{
  "type": "Feature",
  "properties": {
    "addr:full":"Fiifgeawei 33C Offingawier Provincie Friesland 8626 GB",
    "addr:housenumber":"33c",
    "addr:postcode":"8626 gb",
    "addr:street":"Fiifgeawei;Provincie Friesland",
    "iso:country":"NL",
    "sg:address":"Fiifgeawei 33C",
    "sg:city":"Offingawier",
    "sg:orig_category":"Watersportartikelen",
    "sg:phone":"+31 515 432 183",
    "sg:postcode":"8626 GB",
    "sg:province":"Provincie Friesland",
    "wof:name":"Tromp Agenturen",
    "wof:placetype":"venue"
},
  "geometry": {"coordinates":[5.6983299255,53.0324287415],"type":"Point"}
}