{
  "type": "Feature",
  "properties": {
    "addr:full":"Rijnstraat 143 Haarlem Noord-Holland 2025 RR",
    "addr:housenumber":"143",
    "addr:postcode":"2025 rr",
    "addr:street":"Rijnstraat",
    "iso:country":"NL",
    "sg:address":"Rijnstraat 143",
    "sg:city":"Haarlem",
    "sg:orig_category":"Manueel Therapeuten",
    "sg:phone":"+31 23 537 7069",
    "sg:postcode":"2025 RR",
    "sg:province":"Noord-Holland",
    "wof:name":"Smeets",
    "wof:placetype":"venue"
},
  "geometry": {"coordinates":[4.64832,52.416309],"type":"Point"}
}