{
  "type": "Feature",
  "properties": {
    "addr:full":"Rotterdamsedk 7 Schiedam Zuid-Holland 3112 AA",
    "addr:housenumber":"7",
    "addr:postcode":"3112 aa",
    "addr:street":"Rotterdamsedk",
    "iso:country":"NL",
    "sg:address":"Rotterdamsedk 7",
    "sg:city":"Schiedam",
    "sg:classifiers":[
        {
            "category":"Recreation",
            "subcategory":"Dog Park",
            "type":"Entertainment"
        }
    ],
    "sg:phone":"+31 10 426 4050",
    "sg:postcode":"3112 AA",
    "sg:province":"Zuid-Holland",
    "sg:tags":[
        "chauffeur",
        "met",
        "autoverhuur"
    ],
    "sg:website":"http://www.silverstar-limousine.nl",
    "wof:name":"Arb Silverstar",
    "wof:placetype":"venue"
},
  "geometry": {"coordinates":[4.411628,51.914047],"type":"Point"}
}