{
  "type": "Feature",
  "properties": {
    "addr:full":"M Da Costahof 5 Amsterdam Noord-Holland 1067 ZN",
    "addr:housenumber":"5",
    "addr:postcode":"1067 zn",
    "addr:street":"Da Costahof",
    "iso:country":"NL",
    "sg:address":"M Da Costahof 5",
    "sg:city":"Amsterdam",
    "sg:orig_category":"Video - Faciliteiten En Producties",
    "sg:phone":"+31 20 613 4087",
    "sg:postcode":"1067 ZN",
    "sg:province":"Noord-Holland",
    "sg:website":"http://www.artisan.nl",
    "wof:name":"Artisan",
    "wof:placetype":"venue"
},
  "geometry": {"coordinates":[4.798842,52.376316],"type":"Point"}
}