{
  "type": "Feature",
  "properties": {
    "addr:full":"De Waag 13 Dalen Provincie Drenthe 7751 GW",
    "addr:housenumber":"13",
    "addr:postcode":"7751 gw",
    "addr:street":"De Waag;Provincie Drenthe",
    "iso:country":"NL",
    "sg:address":"De Waag 13",
    "sg:city":"Dalen",
    "sg:orig_category":"Kinderkleding",
    "sg:phone":"+31 524 553 395",
    "sg:postcode":"7751 GW",
    "sg:province":"Provincie Drenthe",
    "wof:name":"Dily",
    "wof:placetype":"venue"
},
  "geometry": {"coordinates":[6.755609,52.699181],"type":"Point"}
}