{
  "type": "Feature",
  "properties": {
    "iso:country":"NL",
    "sg:address":"Industriewg 14",
    "sg:city":"Heusden Gem Heusd",
    "sg:classifiers":[
        {
            "category":"Retail",
            "subcategory":"Storage",
            "type":"Services"
        }
    ],
    "sg:phone":"+31 416 661 123",
    "sg:postcode":"5256 PN",
    "sg:province":"North Brabant",
    "sg:tags":[
        "op-",
        "en",
        "overslagbedrijven"
    ],
    "wof:name":"Hart Bv, De",
    "wof:placetype":"venue"
},
  "geometry": {"coordinates":[5.12174,51.732449],"type":"Point"}
}