{
  "type": "Feature",
  "properties": {
    "addr:full":"Marktstr 15 Dedemsvaart Overijssel 7701 GT",
    "addr:housenumber":"15",
    "addr:postcode":"7701 gt",
    "addr:street":"Marktstr",
    "iso:country":"NL",
    "sg:address":"Marktstr 15",
    "sg:city":"Dedemsvaart",
    "sg:orig_category":"Bloemen En Planten",
    "sg:phone":"+31 523 613 386",
    "sg:postcode":"7701 GT",
    "sg:province":"Overijssel",
    "wof:name":"Lelie, De",
    "wof:placetype":"venue"
},
  "geometry": {"coordinates":[6.456313,52.600029],"type":"Point"}
}