{
  "type": "Feature",
  "properties": {
    "addr:full":"Hertenkampstraat 3 Mierlo Noord-Brabant 5731 JB",
    "addr:housenumber":"3",
    "addr:postcode":"5731 jb",
    "addr:street":"Hertenkampstraat",
    "iso:country":"NL",
    "sg:address":"Hertenkampstraat 3",
    "sg:city":"Mierlo",
    "sg:orig_category":"Bloemen And Planten",
    "sg:phone":"+31 492 662 582",
    "sg:postcode":"5731 JB",
    "sg:province":"Noord-Brabant",
    "wof:name":"Markthandel A. Butz",
    "wof:placetype":"venue"
},
  "geometry": {"coordinates":[5.616808,51.444771],"type":"Point"}
}