{
  "type": "Feature",
  "properties": {
    "addr:full":"Zz Haven 17 Goedereede Zuid-Holland 3252 BZ",
    "addr:housenumber":"17",
    "addr:postcode":"3252 bz",
    "addr:street":"Zz Haven",
    "iso:country":"NL",
    "sg:address":"Zz Haven 17",
    "sg:city":"Goedereede",
    "sg:orig_category":"Kappers",
    "sg:phone":"+31 187 491 107",
    "sg:postcode":"3252 BZ",
    "sg:province":"Zuid-Holland",
    "wof:name":"Petit Goeree",
    "wof:placetype":"venue"
},
  "geometry": {"coordinates":[3.982881,51.817432],"type":"Point"}
}