{
  "type": "Feature",
  "properties": {
    "iso:country":"NL",
    "sg:address":"Vliegveldwg 333",
    "sg:city":"Enschede",
    "sg:orig_category":"Luchthavens En Vliegvelden",
    "sg:phone":"+31 53 486 2222",
    "sg:postcode":"7524 PT",
    "sg:province":"Overijssel",
    "sg:website":"http://www.enschede-airport.nl",
    "wof:name":"Enschede Airport Twente",
    "wof:placetype":"venue"
},
  "geometry": {"coordinates":[6.894911,52.263981],"type":"Point"}
}