{
  "type": "Feature",
  "properties": {
    "addr:full":"Stationsweg 3 Oostvoorne Zuid-Holland 3233 CR",
    "addr:housenumber":"3",
    "addr:postcode":"3233 cr",
    "addr:street":"Stationsweg",
    "iso:country":"NL",
    "sg:address":"Stationsweg 3",
    "sg:city":"Oostvoorne",
    "sg:orig_category":"Herenmodezaken",
    "sg:phone":"+31 181 483 143",
    "sg:postcode":"3233 CR",
    "sg:province":"Zuid-Holland",
    "wof:name":"Lotte'S Boetiek En Mannenmode",
    "wof:placetype":"venue"
},
  "geometry": {"coordinates":[4.102709,51.913795],"type":"Point"}
}