{
  "type": "Feature",
  "properties": {
    "addr:full":"Gerard Scholtenstraat 88 Rotterdam South Holland 3035 SP",
    "addr:housenumber":"88",
    "addr:postcode":"3035 sp",
    "addr:street":"Gerard Scholtenstraat",
    "iso:country":"NL",
    "sg:address":"Gerard Scholtenstraat 88",
    "sg:city":"Rotterdam",
    "sg:orig_category":"Muziekinstrumenten",
    "sg:phone":"+31 10 467 6568",
    "sg:postcode":"3035 SP",
    "sg:province":"South Holland",
    "wof:name":"T.P. Haringsma",
    "wof:placetype":"venue"
},
  "geometry": {"coordinates":[4.477241,51.934155],"type":"Point"}
}