{
  "type": "Feature",
  "properties": {
    "iso:country":"NL",
    "sg:address":"Rosenburgln 38",
    "sg:city":"Vlissingen",
    "sg:orig_category":"Voetbalverenigingen",
    "sg:phone":"+31 118 471 426",
    "sg:postcode":"4385 JD",
    "sg:province":"Zeeland",
    "wof:name":"Bza Vlissingen",
    "wof:placetype":"venue"
},
  "geometry": {"coordinates":[3.567009,51.461121],"type":"Point"}
}