{
  "type": "Feature",
  "properties": {
    "addr:full":"Karel Doormanstraat 2 Rijssen Overijssel 7461 ER",
    "addr:housenumber":"2",
    "addr:postcode":"7461 er",
    "addr:street":"Karel Doormanstraat",
    "iso:country":"NL",
    "sg:address":"Karel Doormanstraat 2",
    "sg:city":"Rijssen",
    "sg:classifiers":[
        {
            "category":"Professional",
            "subcategory":"Accounting & Tax Preparation",
            "type":"Services"
        }
    ],
    "sg:phone":"+31 548 535 000",
    "sg:postcode":"7461 ER",
    "sg:province":"Overijssel",
    "sg:tags":[
        "accountant"
    ],
    "wof:name":"Hendriksen Accountants En Adviseurs",
    "wof:placetype":"venue"
},
  "geometry": {"coordinates":[6.528547,52.305847],"type":"Point"}
}