{
  "type": "Feature",
  "properties": {
    "addr:full":"Stationsstr 84-86 Ermelo Gelderland 3851 NK",
    "addr:housenumber":"84-86",
    "addr:postcode":"3851 nk",
    "addr:street":"Gelderland",
    "iso:country":"NL",
    "sg:address":"Stationsstr 84-86",
    "sg:city":"Ermelo",
    "sg:orig_category":"Apotheken",
    "sg:phone":"+31 341 552 301",
    "sg:postcode":"3851 NK",
    "sg:province":"Gelderland",
    "wof:name":"Ermel",
    "wof:placetype":"venue"
},
  "geometry": {"coordinates":[5.620086,52.29974],"type":"Point"}
}