{
  "type": "Feature",
  "properties": {
    "addr:full":"Gedempte Gr 4 Schagen North Holland 1741 GC",
    "addr:housenumber":"4",
    "addr:postcode":"1741 gc",
    "addr:street":"Gedempte Gr",
    "iso:country":"NL",
    "sg:address":"Gedempte Gr 4",
    "sg:city":"Schagen",
    "sg:orig_category":"Herenkleding",
    "sg:phone":"+31 224 297 500",
    "sg:postcode":"1741 GC",
    "sg:province":"North Holland",
    "wof:name":"B & G",
    "wof:placetype":"venue"
},
  "geometry": {"coordinates":[4.797609,52.786427],"type":"Point"}
}