{
  "type": "Feature",
  "properties": {
    "addr:full":"Skrinserdyk 10 Oosterlittens Friesland 8835 XE",
    "addr:housenumber":"10",
    "addr:postcode":"8835 xe",
    "addr:street":"Skrinserdyk",
    "iso:country":"NL",
    "sg:address":"Skrinserdyk 10",
    "sg:city":"Oosterlittens",
    "sg:orig_category":"Kampeerterreinen",
    "sg:phone":"+31 517 342 508",
    "sg:postcode":"8835 XE",
    "sg:province":"Friesland",
    "wof:name":"It Kruswetter",
    "wof:placetype":"venue"
},
  "geometry": {"coordinates":[5.6501097679,53.135219574],"type":"Point"}
}