{
  "type": "Feature",
  "properties": {
    "addr:full":"Mussenveld 56 Emmen Drenthe 7827 AD",
    "addr:housenumber":"56",
    "addr:postcode":"7827 ad",
    "addr:street":"Mussenveld",
    "iso:country":"NL",
    "sg:address":"Mussenveld 56",
    "sg:city":"Emmen",
    "sg:orig_category":"Verhuur Voertuigen Behalve Auto'S",
    "sg:phone":"+31 591 630 724",
    "sg:postcode":"7827 AD",
    "sg:province":"Drenthe",
    "wof:name":"J.W. Siebring",
    "wof:placetype":"venue"
},
  "geometry": {"coordinates":[6.908044,52.746231],"type":"Point"}
}