{
  "type": "Feature",
  "properties": {
    "addr:full":"Nieuwstr 4 Nuland Noord-Brabant 5391 EM",
    "addr:housenumber":"4",
    "addr:postcode":"5391 em",
    "addr:street":"Nieuwstr",
    "iso:country":"NL",
    "sg:address":"Nieuwstr 4",
    "sg:city":"Nuland",
    "sg:orig_category":"Bestratingen",
    "sg:phone":"+31 73 532 1415",
    "sg:postcode":"5391 EM",
    "sg:province":"Noord-Brabant",
    "wof:name":"Miomi",
    "wof:placetype":"venue"
},
  "geometry": {"coordinates":[5.431717,51.726715],"type":"Point"}
}