{
  "type": "Feature",
  "properties": {
    "addr:full":"L Nering 20A Emmeloord Flevoland 8302 EC",
    "addr:housenumber":"20a",
    "addr:postcode":"8302 ec",
    "addr:street":"Nering;Flevoland",
    "iso:country":"NL",
    "sg:address":"L Nering 20A",
    "sg:city":"Emmeloord",
    "sg:orig_category":"New Age-Artikelen En -Diensten",
    "sg:phone":"+31 527 615 461",
    "sg:postcode":"8302 EC",
    "sg:province":"Flevoland",
    "wof:name":"Betere Hand, De",
    "wof:placetype":"venue"
},
  "geometry": {"coordinates":[5.755396,52.711159],"type":"Point"}
}