{
  "type": "Feature",
  "properties": {
    "addr:full":"Sint Wirosingel 199 Roermond Limburg 6042 KZ",
    "addr:housenumber":"199",
    "addr:postcode":"6042 kz",
    "addr:street":"Sint Wirosingel",
    "iso:country":"NL",
    "sg:address":"Sint Wirosingel 199",
    "sg:city":"Roermond",
    "sg:orig_category":"Autokeuringen",
    "sg:phone":"+31 475 328 027",
    "sg:postcode":"6042 KZ",
    "sg:province":"Limburg",
    "wof:name":"Shell",
    "wof:placetype":"venue"
},
  "geometry": {"coordinates":[6.025742,51.200569],"type":"Point"}
}