{
  "type": "Feature",
  "properties": {
    "iso:country":"NL",
    "sg:address":"Molenstraat 43",
    "sg:city":"'S Gravenhage",
    "sg:orig_category":"Kunst And Kunstenaarsbenodigdheden",
    "sg:phone":"+31 70 363 8303",
    "sg:postcode":"2513 BJ",
    "sg:province":"South Holland",
    "wof:name":"A. Goedman",
    "wof:placetype":"venue"
},
  "geometry": {"coordinates":[4.305924,52.079811],"type":"Point"}
}