{
  "type": "Feature",
  "properties": {
    "addr:full":"Breukelengr 2 Almere NL. 1324 NE",
    "addr:housenumber":"2;1324",
    "addr:street":"Breukelengr;Nl.;Ne",
    "iso:country":"NL",
    "sg:address":"Breukelengr 2",
    "sg:city":"Almere",
    "sg:orig_category":"Verenigingen En Stichtingen",
    "sg:phone":"+31 6 17372377",
    "sg:postcode":"1324 NE",
    "sg:province":"NL.",
    "sg:website":"http://www.tolex.tk",
    "wof:name":"Tolex",
    "wof:placetype":"venue"
},
  "geometry": {"coordinates":[5.206296,52.365208],"type":"Point"}
}