{
  "type": "Feature",
  "properties": {
    "addr:full":"Muzenhof 31 Maastricht Limburg 6215 EV",
    "addr:housenumber":"31",
    "addr:postcode":"6215 ev",
    "addr:street":"Muzenhof",
    "iso:country":"NL",
    "sg:address":"Muzenhof 31",
    "sg:city":"Maastricht",
    "sg:orig_category":"Kantoorbenodigdheden",
    "sg:phone":"+31 6 55288285",
    "sg:postcode":"6215 EV",
    "sg:province":"Limburg",
    "wof:name":"Itc Born",
    "wof:placetype":"venue"
},
  "geometry": {"coordinates":[5.6434669495,50.8410644531],"type":"Point"}
}