{
  "type": "Feature",
  "properties": {
    "addr:full":"Burgemeester Lodderstr 20 Opheusden Gelderland 4043 KM",
    "addr:housenumber":"20",
    "addr:postcode":"4043",
    "addr:street":"Burgemeester Lodderstr;Gelderland;Km",
    "iso:country":"NL",
    "sg:address":"Burgemeester Lodderstr 20",
    "sg:city":"Opheusden",
    "sg:orig_category":"Overheidsdiensten",
    "sg:phone":"+31 488 441 541",
    "sg:postcode":"4043 KM",
    "sg:province":"Gelderland",
    "wof:name":"Gemeente Kesteren",
    "wof:placetype":"venue"
},
  "geometry": {"coordinates":[5.6299381256,51.9335594177],"type":"Point"}
}