{
  "type": "Feature",
  "properties": {
    "addr:full":"Woudrichemsewg 9 Almkerk North Brabant 4286 LA",
    "addr:housenumber":"9",
    "addr:postcode":"4286 la",
    "addr:street":"Woudrichemsewg",
    "iso:country":"NL",
    "sg:address":"Woudrichemsewg 9",
    "sg:city":"Almkerk",
    "sg:orig_category":"Mobiele- En Autotelefoons",
    "sg:phone":"+31 183 409 256",
    "sg:postcode":"4286 LA",
    "sg:province":"North Brabant",
    "wof:name":"Cascais",
    "wof:placetype":"venue"
},
  "geometry": {"coordinates":[4.963597,51.773354],"type":"Point"}
}