{
  "type": "Feature",
  "properties": {
    "iso:country":"NL",
    "sg:address":"Kornsche Buitenkade 6",
    "sg:city":"Dussen",
    "sg:orig_category":"Pleziervaartuigen And Reparatie",
    "sg:phone":"+31 416 391 370",
    "sg:postcode":"4271 LN",
    "sg:province":"Noord-Brabant",
    "wof:name":"J.H. Colijn",
    "wof:placetype":"venue"
},
  "geometry": {"coordinates":[4.95207,51.750774],"type":"Point"}
}