{
  "type": "Feature",
  "properties": {
    "iso:country":"NL",
    "sg:address":"Ged Binnengr 23",
    "sg:city":"Woerden",
    "sg:orig_category":"Kaasgroothandel",
    "sg:phone":"+31 348 412 777",
    "sg:postcode":"3441 AE",
    "sg:province":"Utrecht",
    "wof:name":"Blok, J M",
    "wof:placetype":"venue"
},
  "geometry": {"coordinates":[4.8813281059,52.0852394104],"type":"Point"}
}