{
  "type": "Feature",
  "properties": {
    "iso:country":"NL",
    "sg:address":"Meerstr 25",
    "sg:city":"Bunde",
    "sg:orig_category":"Onroerende Goederen",
    "sg:phone":"+31 43 358 5790",
    "sg:postcode":"6241 ND",
    "sg:province":"Limburg",
    "wof:name":"Rooden Griffioen Bv, In Den",
    "wof:placetype":"venue"
},
  "geometry": {"coordinates":[5.723913,50.900845],"type":"Point"}
}