{
  "type": "Feature",
  "properties": {
    "addr:full":"Parkwg 56 Voorburg South Holland 2271 AL",
    "addr:housenumber":"56",
    "addr:postcode":"2271 al",
    "addr:street":"Parkwg",
    "iso:country":"NL",
    "sg:address":"Parkwg 56",
    "sg:city":"Voorburg",
    "sg:orig_category":"Juweliers",
    "sg:phone":"+31 70 386 3311",
    "sg:postcode":"2271 AL",
    "sg:province":"South Holland",
    "wof:name":"Toetenel Juwelier",
    "wof:placetype":"venue"
},
  "geometry": {"coordinates":[4.364221,52.068359],"type":"Point"}
}