{
  "type": "Feature",
  "properties": {
    "addr:full":"Hoofdstraat 39 Krimpen A/D Lek South Holland 2931 CE",
    "addr:housenumber":"39;a / d",
    "addr:postcode":"2931 ce",
    "addr:street":"Hoofdstraat",
    "iso:country":"NL",
    "sg:address":"Hoofdstraat 39",
    "sg:city":"Krimpen A/D Lek",
    "sg:classifiers":[
        {
            "category":"Retail",
            "subcategory":"Photofinishing",
            "type":"Services"
        }
    ],
    "sg:phone":"+31 180 510 373",
    "sg:postcode":"2931 CE",
    "sg:province":"South Holland",
    "sg:tags":[
        "foto",
        "film"
    ],
    "wof:name":"Foto Video De Lek",
    "wof:placetype":"venue"
},
  "geometry": {"coordinates":[4.628965,51.893635],"type":"Point"}
}