{
  "type": "Feature",
  "properties": {
    "addr:full":"Emmasingel 9 Weert Limburg 6001 BA",
    "addr:housenumber":"9",
    "addr:postcode":"6001 ba",
    "addr:street":"Emmasingel",
    "iso:country":"NL",
    "sg:address":"Emmasingel 9",
    "sg:city":"Weert",
    "sg:orig_category":"Hypotheken And Hypotheekbanken",
    "sg:phone":"+31 495 520 795",
    "sg:postcode":"6001 BA",
    "sg:province":"Limburg",
    "wof:name":"F.D.C. Hypotheekadviseurs Weert",
    "wof:placetype":"venue"
},
  "geometry": {"coordinates":[5.709535,51.255302],"type":"Point"}
}