{
  "type": "Feature",
  "properties": {
    "iso:country":"NL",
    "sg:address":"Slinge 1",
    "sg:city":"Assen",
    "sg:orig_category":"Bejaardeninstellingen And Serviceflats",
    "sg:phone":"+31 592 395 888",
    "sg:postcode":"9406 EA",
    "sg:province":"Drenthe",
    "wof:name":"Zorgcentrum Het Larikshart Locatie De Sl",
    "wof:placetype":"venue"
},
  "geometry": {"coordinates":[6.54023,52.996906],"type":"Point"}
}