{
  "type": "Feature",
  "properties": {
    "addr:full":"Paardeweide 48 Breda Noord-Brabant 4824 EH",
    "addr:housenumber":"48",
    "addr:postcode":"4824 eh",
    "addr:street":"Paardeweide",
    "iso:country":"NL",
    "sg:address":"Paardeweide 48",
    "sg:city":"Breda",
    "sg:orig_category":"Elektrotechnische Apparatuur - Fabrieken En Groothandel",
    "sg:phone":"+31 76 541 9885",
    "sg:postcode":"4824 EH",
    "sg:province":"Noord-Brabant",
    "sg:website":"http://www.alprint.nl",
    "wof:name":"Alprint Vof",
    "wof:placetype":"venue"
},
  "geometry": {"coordinates":[4.752069,51.610409],"type":"Point"}
}