{
  "type": "Feature",
  "properties": {
    "addr:full":"Kemphaanstraat 36 Wormer Noord-Holland 1531 VE",
    "addr:housenumber":"36",
    "addr:postcode":"1531",
    "addr:street":"Kemphaanstraat;Ve",
    "iso:country":"NL",
    "sg:address":"Kemphaanstraat 36",
    "sg:city":"Wormer",
    "sg:orig_category":"Fotostudio'S And Fotografen",
    "sg:phone":"+31 75 642 6873",
    "sg:postcode":"1531 VE",
    "sg:province":"Noord-Holland",
    "wof:name":"Hans Van Der Meijden Fotografie",
    "wof:placetype":"venue"
},
  "geometry": {"coordinates":[4.810271,52.499989],"type":"Point"}
}