{
  "type": "Feature",
  "properties": {
    "iso:country":"NL",
    "sg:address":"Papestraat 1A",
    "sg:city":"'S Gravenhage",
    "sg:classifiers":[
        {
            "category":"Fast Food",
            "type":"Food & Drink"
        }
    ],
    "sg:phone":"+31 70 346 3202",
    "sg:postcode":"2513 AV",
    "sg:province":"Zuid-Holland",
    "sg:tags":[
        "afhaal",
        "restaurant"
    ],
    "wof:name":"Vlaams Friethuis Het Kleinste Winkeltje",
    "wof:placetype":"venue"
},
  "geometry": {"coordinates":[4.30843,52.079472],"type":"Point"}
}