{
  "type": "Feature",
  "properties": {
    "addr:full":"Snyderwei 6 Valkenswaard Noord-Brabant 5551 RK",
    "addr:housenumber":"6",
    "addr:postcode":"5551 rk",
    "addr:street":"Snyderwei",
    "iso:country":"NL",
    "sg:address":"Snyderwei 6",
    "sg:city":"Valkenswaard",
    "sg:orig_category":"Psychologen",
    "sg:phone":"+31 40 201 5498",
    "sg:postcode":"5551 RK",
    "sg:province":"Noord-Brabant",
    "wof:name":"Becker, Drs U",
    "wof:placetype":"venue"
},
  "geometry": {"coordinates":[5.435406,51.349888],"type":"Point"}
}