{
  "type": "Feature",
  "properties": {
    "addr:full":"Molendk 11 Rockanje South Holland 3235 XE",
    "addr:housenumber":"11",
    "addr:postcode":"3235 xe",
    "addr:street":"Molendk",
    "iso:country":"NL",
    "sg:address":"Molendk 11",
    "sg:city":"Rockanje",
    "sg:classifiers":[
        {
            "category":"Manufacturing",
            "subcategory":"Motor Vehicles & Parts",
            "type":"Manufacturing & Wholesale Goods"
        }
    ],
    "sg:phone":"+31 181 403 202",
    "sg:postcode":"3235 XE",
    "sg:province":"South Holland",
    "sg:tags":[
        "verhuur",
        "scooter",
        "en",
        "-"
    ],
    "sg:website":"http://www.trikecenter.com",
    "wof:name":"E & G Trikes",
    "wof:placetype":"venue"
},
  "geometry": {"coordinates":[4.076371,51.875793],"type":"Point"}
}