{
  "type": "Feature",
  "properties": {
    "addr:full":"Blankenburgerstraat 10 Haaksbergen NL.08 7481 EB",
    "addr:housenumber":"10;nl.08",
    "addr:postcode":"7481 eb",
    "addr:street":"Blankenburgerstraat",
    "iso:country":"NL",
    "sg:address":"Blankenburgerstraat 10",
    "sg:city":"Haaksbergen",
    "sg:orig_category":"Juweliers",
    "sg:phone":"+31 53 572 1219",
    "sg:postcode":"7481 EB",
    "sg:province":"NL.08",
    "wof:name":"G. Muller",
    "wof:placetype":"venue"
},
  "geometry": {"coordinates":[6.741682,52.155888],"type":"Point"}
}