{
  "type": "Feature",
  "properties": {
    "iso:country":"NL",
    "sg:address":"Ootmarsumsestraat 354",
    "sg:city":"Almelo",
    "sg:orig_category":"Bloemen And Planten",
    "sg:phone":"+31 546 861 141",
    "sg:postcode":"7603 AV",
    "sg:province":"NL.08",
    "wof:name":"Fa J.J. Koenderink & Zonen",
    "wof:placetype":"venue"
},
  "geometry": {"coordinates":[6.6836118698,52.36901474],"type":"Point"}
}