{
  "type": "Feature",
  "properties": {
    "addr:full":"Spui 21 Amsterdam Noord-Holland 1012 WX",
    "addr:housenumber":"21",
    "addr:postcode":"1012 wx",
    "addr:street":"Spui",
    "iso:country":"NL",
    "sg:address":"Spui 21",
    "sg:city":"Amsterdam",
    "sg:orig_category":"Hoger Onderwijs",
    "sg:phone":"+31 20 525 9111",
    "sg:postcode":"1012 WX",
    "sg:province":"Noord-Holland",
    "wof:name":"Uva Universiteit Van Amsterdam",
    "wof:placetype":"venue"
},
  "geometry": {"coordinates":[4.890176,52.368652],"type":"Point"}
}