{
  "type": "Feature",
  "properties": {
    "iso:country":"NL",
    "sg:address":"Pr Hendrikstr 228",
    "sg:city":"Hoek Van Holland",
    "sg:orig_category":"Kunstnijverheid",
    "sg:phone":"+31 174 310 693",
    "sg:postcode":"3151 AW",
    "sg:province":"Zuid-Holland",
    "wof:name":"Artaparti",
    "wof:placetype":"venue"
},
  "geometry": {"coordinates":[4.131569,51.976562],"type":"Point"}
}