{
  "type": "Feature",
  "properties": {
    "addr:full":"Bergkampen 15A St Jansklooster Overijssel 8326 AS",
    "addr:housenumber":"15a",
    "addr:postcode":"8326 as",
    "addr:street":"Bergkampen;St Jansklooster Overijssel",
    "iso:country":"NL",
    "sg:address":"Bergkampen 15A",
    "sg:city":"St Jansklooster",
    "sg:classifiers":[
        {
            "category":"Sports & Exercise",
            "subcategory":"Stables",
            "type":"Entertainment"
        }
    ],
    "sg:phone":"+31 527 246 619",
    "sg:postcode":"8326 AS",
    "sg:province":"Overijssel",
    "sg:tags":[
        "maneges"
    ],
    "wof:name":"Dalen, Stal Grietje Van",
    "wof:placetype":"venue"
},
  "geometry": {"coordinates":[5.999877,52.674652],"type":"Point"}
}