{
  "type": "Feature",
  "properties": {
    "addr:full":"Schoolstr 54 Voorschoten Zuid-Holland 2251 BK",
    "addr:housenumber":"54",
    "addr:postcode":"2251 bk",
    "addr:street":"Schoolstr",
    "iso:country":"NL",
    "sg:address":"Schoolstr 54",
    "sg:city":"Voorschoten",
    "sg:orig_category":"Herenkleding",
    "sg:phone":"+31 71 561 2309",
    "sg:postcode":"2251 BK",
    "sg:province":"Zuid-Holland",
    "wof:name":"Wees Mannenmode Bv, Van",
    "wof:placetype":"venue"
},
  "geometry": {"coordinates":[4.446818,52.125854],"type":"Point"}
}