{
  "type": "Feature",
  "properties": {
    "addr:full":"Postbus 310 Gorinchem South Holland 4200 AH",
    "addr:housenumber":"310",
    "addr:postcode":"4200 ah",
    "addr:street":"Postbus",
    "iso:country":"NL",
    "sg:address":"Postbus 310",
    "sg:city":"Gorinchem",
    "sg:orig_category":"Adviesbureaus",
    "sg:phone":"+31 183 621 153",
    "sg:postcode":"4200 AH",
    "sg:province":"South Holland",
    "sg:website":"http://www.roa-advies.nl",
    "wof:name":"Raad Van Organisatieadviesbureaus",
    "wof:placetype":"venue"
},
  "geometry": {"coordinates":[4.969185,51.830631],"type":"Point"}
}