{
  "type": "Feature",
  "properties": {
    "addr:full":"Stationsstr 17 Heerde Gelderland 8181 CW",
    "addr:housenumber":"17",
    "addr:postcode":"8181 cw",
    "addr:street":"Stationsstr;Gelderland",
    "iso:country":"NL",
    "sg:address":"Stationsstr 17",
    "sg:city":"Heerde",
    "sg:orig_category":"Kappers",
    "sg:phone":"+31 578 691 857",
    "sg:postcode":"8181 CW",
    "sg:province":"Gelderland",
    "wof:name":"Put, G J Van De",
    "wof:placetype":"venue"
},
  "geometry": {"coordinates":[6.038921,52.389072],"type":"Point"}
}