{
  "type": "Feature",
  "properties": {
    "addr:full":"Zinkstr 20 Breda North Brabant 4823 AD",
    "addr:housenumber":"20",
    "addr:postcode":"4823 ad",
    "addr:street":"Zinkstr",
    "iso:country":"NL",
    "sg:address":"Zinkstr 20",
    "sg:city":"Breda",
    "sg:orig_category":"Adviesbureaus Personeel",
    "sg:phone":"+31 76 541 9580",
    "sg:postcode":"4823 AD",
    "sg:province":"North Brabant",
    "sg:website":"http://www.cheops.nl",
    "wof:name":"Cheops Bv",
    "wof:placetype":"venue"
},
  "geometry": {"coordinates":[4.718815,51.611702],"type":"Point"}
}