{
  "type": "Feature",
  "properties": {
    "iso:country":"NL",
    "sg:address":"Postbus 400",
    "sg:city":"Leiden",
    "sg:orig_category":"Verzekerings- Maatschappijen",
    "sg:phone":"+31 71 582 5825",
    "sg:postcode":"2300 AK",
    "sg:province":"Zuid-Holland",
    "sg:website":"http://www.zorgenzekerheid.nl",
    "wof:name":"Zorg En Zekerheid",
    "wof:placetype":"venue"
},
  "geometry": {"coordinates":[4.49015,52.161091],"type":"Point"}
}