{
  "type": "Feature",
  "properties": {
    "iso:country":"NL",
    "sg:address":"De Heerd 2",
    "sg:city":"Raalte",
    "sg:orig_category":"Glaszetten",
    "sg:phone":"+31 572 357 384",
    "sg:postcode":"8102 LH",
    "sg:province":"Overijssel",
    "wof:name":"B. Van Lenthe",
    "wof:placetype":"venue"
},
  "geometry": {"coordinates":[6.274335,52.375038],"type":"Point"}
}