{
  "type": "Feature",
  "properties": {
    "iso:country":"NL",
    "sg:address":"Lavendelstr 9",
    "sg:city":"Amersfoort",
    "sg:orig_category":"Zalenverhuur",
    "sg:phone":"+31 33 461 2247",
    "sg:postcode":"3811 CN",
    "sg:province":"Utrecht",
    "wof:name":"Rumours Inn & Swing",
    "wof:placetype":"venue"
},
  "geometry": {"coordinates":[5.389697,52.157166],"type":"Point"}
}