{
  "type": "Feature",
  "properties": {
    "addr:full":"Kerkwg 39K5 Oene Gelderland 8167 PG",
    "addr:housenumber":"39k5",
    "addr:postcode":"8167",
    "addr:street":"Kerkwg;Gelderland;Pg",
    "iso:country":"NL",
    "sg:address":"Kerkwg 39K5",
    "sg:city":"Oene",
    "sg:orig_category":"Projectontwikkeling",
    "sg:phone":"+31 578 641 341",
    "sg:postcode":"8167 PG",
    "sg:province":"Gelderland",
    "wof:name":"Zenith-Corts Bv",
    "wof:placetype":"venue"
},
  "geometry": {"coordinates":[6.050372,52.351414],"type":"Point"}
}