{
  "type": "Feature",
  "properties": {
    "addr:full":"Gaffelstraat 63 Rotterdam Zuid-Holland 3014 RC",
    "addr:housenumber":"63",
    "addr:postcode":"3014 rc",
    "addr:street":"Gaffelstraat",
    "iso:country":"NL",
    "sg:address":"Gaffelstraat 63",
    "sg:city":"Rotterdam",
    "sg:orig_category":"Overheidsdiensten",
    "sg:phone":"+31 10 436 2098",
    "sg:postcode":"3014 RC",
    "sg:province":"Zuid-Holland",
    "wof:name":"Clubhuis De Gaffel",
    "wof:placetype":"venue"
},
  "geometry": {"coordinates":[4.467525959,51.9177207947],"type":"Point"}
}