{
  "type": "Feature",
  "properties": {
    "addr:full":"Nw Mathenesserstr 1 Schiedam Zuid-Holland 3113 AD",
    "addr:housenumber":"1",
    "addr:postcode":"3113 ad",
    "addr:street":"Mathenesserstr",
    "iso:country":"NL",
    "sg:address":"Nw Mathenesserstr 1",
    "sg:city":"Schiedam",
    "sg:orig_category":"Wasserijen",
    "sg:phone":"+31 10 473 9899",
    "sg:postcode":"3113 AD",
    "sg:province":"Zuid-Holland",
    "wof:name":"Piet Hein",
    "wof:placetype":"venue"
},
  "geometry": {"coordinates":[4.408780098,51.9140014648],"type":"Point"}
}