{
  "type": "Feature",
  "properties": {
    "addr:full":"Televisiestraat 2 'S Gravenhage South Holland 2525 KD",
    "addr:housenumber":"2 '",
    "addr:postcode":"2525 kd",
    "addr:street":"Televisiestraat",
    "iso:country":"NL",
    "sg:address":"Televisiestraat 2",
    "sg:city":"'S Gravenhage",
    "sg:orig_category":"Werving And Selectie Van Tijdelijk Personeel And Uitzendkantoren",
    "sg:phone":"+31 70 389 9428",
    "sg:postcode":"2525 KD",
    "sg:province":"South Holland",
    "wof:name":"Mase Uitzendbureau",
    "wof:placetype":"venue"
},
  "geometry": {"coordinates":[4.304022789,52.0577850342],"type":"Point"}
}