{
  "type": "Feature",
  "properties": {
    "addr:full":"Het Spaarne 13 Dronten Flevoland 8253 PE",
    "addr:housenumber":"13",
    "addr:postcode":"8253 pe",
    "addr:street":"Het Spaarne;Flevoland",
    "iso:country":"NL",
    "sg:address":"Het Spaarne 13",
    "sg:city":"Dronten",
    "sg:orig_category":"Drukkerijen",
    "sg:phone":"+31 321 315 020",
    "sg:postcode":"8253 PE",
    "sg:province":"Flevoland",
    "wof:name":"Wilmaco",
    "wof:placetype":"venue"
},
  "geometry": {"coordinates":[5.702812,52.539345],"type":"Point"}
}