{
  "type": "Feature",
  "properties": {
    "iso:country":"NL",
    "sg:address":"Sophiastraat 1",
    "sg:city":"Haarlem",
    "sg:orig_category":"Boekenuitgeverijen",
    "sg:phone":"+31 23 531 9014",
    "sg:postcode":"2011 VT",
    "sg:province":"Noord-Holland",
    "wof:name":"Holland Bocaal Business Press",
    "wof:placetype":"venue"
},
  "geometry": {"coordinates":[4.628208,52.379532],"type":"Point"}
}