{
  "type": "Feature",
  "properties": {
    "addr:full":"Berberiswg 4 Rotterdam South Holland 3053 PJ",
    "addr:housenumber":"4",
    "addr:postcode":"3053 pj",
    "addr:street":"Berberiswg",
    "iso:country":"NL",
    "sg:address":"Berberiswg 4",
    "sg:city":"Rotterdam",
    "sg:orig_category":"Psychologen",
    "sg:phone":"+31 10 278 0212",
    "sg:postcode":"3053 PJ",
    "sg:province":"South Holland",
    "wof:name":"Lotgerink, Drs M B",
    "wof:placetype":"venue"
},
  "geometry": {"coordinates":[4.474851,51.964661],"type":"Point"}
}