{
  "type": "Feature",
  "properties": {
    "addr:full":"Daalstr 51 Geleen Limburg 6165 TJ",
    "addr:housenumber":"51",
    "addr:postcode":"6165 tj",
    "addr:street":"Daalstr",
    "iso:country":"NL",
    "sg:address":"Daalstr 51",
    "sg:city":"Geleen",
    "sg:orig_category":"Feestartikelen",
    "sg:phone":"+31 46 474 9302",
    "sg:postcode":"6165 TJ",
    "sg:province":"Limburg",
    "wof:name":"Hieperdepiep",
    "wof:placetype":"venue"
},
  "geometry": {"coordinates":[5.828041,50.962189],"type":"Point"}
}