{
  "type": "Feature",
  "properties": {
    "addr:full":"Molenlaan 88 Rotterdam South Holland 3055 EN",
    "addr:housenumber":"88",
    "addr:postcode":"3055 en",
    "addr:street":"Molenlaan",
    "iso:country":"NL",
    "sg:address":"Molenlaan 88",
    "sg:city":"Rotterdam",
    "sg:orig_category":"Bedrijfs- And Managementsconsultants",
    "sg:phone":"+31 10 422 1580",
    "sg:postcode":"3055 EN",
    "sg:province":"South Holland",
    "wof:name":"Bv Organisatie En Adviesbureau A & Fm",
    "wof:placetype":"venue"
},
  "geometry": {"coordinates":[4.50162,51.960495],"type":"Point"}
}