{
  "type": "Feature",
  "properties": {
    "addr:full":"De Hallen 9 Groningen Groningen 9723 TW",
    "addr:housenumber":"9",
    "addr:postcode":"9723 tw",
    "addr:street":"De Hallen",
    "iso:country":"NL",
    "sg:address":"De Hallen 9",
    "sg:city":"Groningen",
    "sg:orig_category":"Fruit And Groenten Gh",
    "sg:phone":"+31 50 544 5588",
    "sg:postcode":"9723 TW",
    "sg:province":"Groningen",
    "wof:name":"Stavasius Grootverbruik Bv",
    "wof:placetype":"venue"
},
  "geometry": {"coordinates":[6.617853,53.207939],"type":"Point"}
}