{
  "type": "Feature",
  "properties": {
    "iso:country":"NL",
    "sg:address":"Beethovensingel 46",
    "sg:city":"Alkmaar",
    "sg:orig_category":"Boekhouders",
    "sg:phone":"+31 72 511 7378",
    "sg:postcode":"1817 HK",
    "sg:province":"Noord-Holland",
    "wof:name":"Adm Kant Th Hoogkamer Bv",
    "wof:placetype":"venue"
},
  "geometry": {"coordinates":[4.735362,52.642067],"type":"Point"}
}