{
  "type": "Feature",
  "properties": {
    "addr:full":"Barentszstraat 18 Lisse Zuid-Holland 2161 TL",
    "addr:housenumber":"18",
    "addr:postcode":"2161 tl",
    "addr:street":"Barentszstraat",
    "iso:country":"NL",
    "sg:address":"Barentszstraat 18",
    "sg:city":"Lisse",
    "sg:orig_category":"Auto-Onderdelen And -Accessoires Gh",
    "sg:phone":"+31 252 413 450",
    "sg:postcode":"2161 TL",
    "sg:province":"Zuid-Holland",
    "wof:name":"Hobimex Lisse Automaterialen En Gereedschappen Bv",
    "wof:placetype":"venue"
},
  "geometry": {"coordinates":[4.565086,52.258186],"type":"Point"}
}