{
  "type": "Feature",
  "properties": {
    "addr:full":"Veenhuizerveldwg 31/A Putten Gelderland 3881 RE",
    "addr:housenumber":"31 / a",
    "addr:postcode":"3881",
    "addr:street":"Veenhuizerveldwg;Gelderland",
    "iso:country":"NL",
    "sg:address":"Veenhuizerveldwg 31/A",
    "sg:city":"Putten",
    "sg:orig_category":"Poeliers",
    "sg:phone":"+31 341 491 717",
    "sg:postcode":"3881 RE",
    "sg:province":"Gelderland",
    "wof:name":"Doppenberg",
    "wof:placetype":"venue"
},
  "geometry": {"coordinates":[5.625344,52.216091],"type":"Point"}
}