{
  "type": "Feature",
  "properties": {
    "addr:full":"Hoogwerfln 6 S Gravenhage South Holland 2594 BJ",
    "addr:housenumber":"6",
    "addr:postcode":"2594 bj",
    "addr:street":"Hoogwerfln;S Gravenhage",
    "iso:country":"NL",
    "sg:address":"Hoogwerfln 6",
    "sg:city":"S Gravenhage",
    "sg:orig_category":"Onderhoudswerken",
    "sg:phone":"+31 6 55868532",
    "sg:postcode":"2594 BJ",
    "sg:province":"South Holland",
    "wof:name":"Kawee",
    "wof:placetype":"venue"
},
  "geometry": {"coordinates":[4.317415,52.083992],"type":"Point"}
}