{
  "type": "Feature",
  "properties": {
    "addr:full":"S Gravelandsewg 31 Hilversum Noord-Holland 1211 BP",
    "addr:housenumber":"31",
    "addr:postcode":"1211 bp",
    "iso:country":"NL",
    "sg:address":"S Gravelandsewg 31",
    "sg:city":"Hilversum",
    "sg:orig_category":"Makelaars En Adviseurs Onroerende Goederen",
    "sg:phone":"+31 35 628 4444",
    "sg:postcode":"1211 BP",
    "sg:province":"Noord-Holland",
    "wof:name":"Kappelle",
    "wof:placetype":"venue"
},
  "geometry": {"coordinates":[5.170735,52.225906],"type":"Point"}
}