{
  "type": "Feature",
  "properties": {
    "addr:full":"Kerkeheidestr 5A Sprundel North Brabant 4714 RC",
    "addr:housenumber":"5a",
    "addr:postcode":"4714 rc",
    "addr:street":"Kerkeheidestr",
    "iso:country":"NL",
    "sg:address":"Kerkeheidestr 5A",
    "sg:city":"Sprundel",
    "sg:orig_category":"Wegenbouw",
    "sg:phone":"+31 165 383 105",
    "sg:postcode":"4714 RC",
    "sg:province":"North Brabant",
    "wof:name":"Oomen Bv, Gebr J & P",
    "wof:placetype":"venue"
},
  "geometry": {"coordinates":[4.5880470276,51.5346488953],"type":"Point"}
}