{
  "type": "Feature",
  "properties": {
    "addr:full":"Hammerwg 41 Ommen NL.08 7731 AH",
    "addr:housenumber":"41;nl.08",
    "addr:postcode":"7731 ah",
    "addr:street":"Hammerwg",
    "iso:country":"NL",
    "sg:address":"Hammerwg 41",
    "sg:city":"Ommen",
    "sg:orig_category":"Verhuur",
    "sg:phone":"+31 529 452 652",
    "sg:postcode":"7731 AH",
    "sg:province":"NL.08",
    "wof:name":"Schuurman",
    "wof:placetype":"venue"
},
  "geometry": {"coordinates":[6.421589,52.504417],"type":"Point"}
}