{
  "type": "Feature",
  "properties": {
    "addr:full":"Van Woustraat 118 Amsterdam Noord-Holland 1073 LS",
    "addr:housenumber":"118",
    "addr:postcode":"1073 ls",
    "addr:street":"Van Woustraat",
    "iso:country":"NL",
    "sg:address":"Van Woustraat 118",
    "sg:city":"Amsterdam",
    "sg:orig_category":"Wasserettes And Stomerijen",
    "sg:phone":"+31 20 679 2204",
    "sg:postcode":"1073 LS",
    "sg:province":"Noord-Holland",
    "wof:name":"Wasserette Van Wou",
    "wof:placetype":"venue"
},
  "geometry": {"coordinates":[4.9018659592,52.35389328],"type":"Point"}
}