{
  "type": "Feature",
  "properties": {
    "iso:country":"NL",
    "sg:address":"Spyksedk 2",
    "sg:city":"Gorinchem",
    "sg:orig_category":"Verlichtingsartikelen - Groothandel",
    "sg:phone":"+31 183 631 378",
    "sg:postcode":"4207 GN",
    "sg:province":"South Holland",
    "sg:website":"http://www.expotrading.nl",
    "wof:name":"Expo Trading Holland Bv",
    "wof:placetype":"venue"
},
  "geometry": {"coordinates":[4.992657,51.843269],"type":"Point"}
}