{
  "type": "Feature",
  "properties": {
    "iso:country":"NL",
    "sg:address":"Bretagnestr 11",
    "sg:city":"Sittard",
    "sg:orig_category":"Autoruiten",
    "sg:phone":"+31 6 48253172",
    "sg:postcode":"6137 JE",
    "sg:province":"Limburg",
    "wof:name":"Glasweld Venlo",
    "wof:placetype":"venue"
},
  "geometry": {"coordinates":[5.897185,50.999184],"type":"Point"}
}