{
  "type": "Feature",
  "properties": {
    "iso:country":"NL",
    "sg:address":"Oud Loosd Dk 276A",
    "sg:city":"Loosdrecht",
    "sg:orig_category":"Kinderkleding - Fabrieken En Groothandel",
    "sg:phone":"+31 35 582 4006",
    "sg:postcode":"1231 NK",
    "sg:province":"Noord-Holland",
    "wof:name":"Re-Membertex Bv",
    "wof:placetype":"venue"
},
  "geometry": {"coordinates":[5.071351,52.2071],"type":"Point"}
}