{
  "type": "Feature",
  "properties": {
    "addr:full":"Quellynstr 138Hs Amsterdam Noord-Holland 1073 XM",
    "addr:housenumber":"138hs",
    "addr:postcode":"1073 xm",
    "addr:street":"Quellynstr",
    "iso:country":"NL",
    "sg:address":"Quellynstr 138Hs",
    "sg:city":"Amsterdam",
    "sg:orig_category":"Natuur- En Milieuorganisaties",
    "sg:phone":"+31 20 664 7537",
    "sg:postcode":"1073 XM",
    "sg:province":"Noord-Holland",
    "wof:name":"Leefmilieu Stad En Land",
    "wof:placetype":"venue"
},
  "geometry": {"coordinates":[4.894153,52.356438],"type":"Point"}
}