{
  "type": "Feature",
  "properties": {
    "addr:full":"D Flemmingstr 2 Sprang Capelle Noord-Brabant 5161 CB",
    "addr:housenumber":"2",
    "addr:postcode":"5161 cb",
    "iso:country":"NL",
    "sg:address":"D Flemmingstr 2",
    "sg:city":"Sprang Capelle",
    "sg:orig_category":"Haarden En Kachels",
    "sg:phone":"+31 416 272 356",
    "sg:postcode":"5161 CB",
    "sg:province":"Noord-Brabant",
    "wof:name":"Bruijn Kachels & Open Haarden, J De",
    "wof:placetype":"venue"
},
  "geometry": {"coordinates":[5.029981,51.6693],"type":"Point"}
}