{
  "type": "Feature",
  "properties": {
    "addr:full":"Vlindermeent 22 Hilversum Noord-Holland 1218 CS",
    "addr:housenumber":"22",
    "addr:postcode":"1218 cs",
    "addr:street":"Vlindermeent",
    "iso:country":"NL",
    "sg:address":"Vlindermeent 22",
    "sg:city":"Hilversum",
    "sg:orig_category":"Bedrijfsopleidingen",
    "sg:phone":"+31 35 693 2629",
    "sg:postcode":"1218 CS",
    "sg:province":"Noord-Holland",
    "wof:name":"Laak, Ellen Ter",
    "wof:placetype":"venue"
},
  "geometry": {"coordinates":[5.138544,52.268456],"type":"Point"}
}