{
  "type": "Feature",
  "properties": {
    "addr:full":"Huizermaatwg 570 Huizen Noord-Holland 1276 LN",
    "addr:housenumber":"570",
    "addr:postcode":"1276 ln",
    "iso:country":"NL",
    "sg:address":"Huizermaatwg 570",
    "sg:city":"Huizen",
    "sg:orig_category":"Makelaars En Adviseurs Onroerende Goederen",
    "sg:phone":"+31 35 541 7846",
    "sg:postcode":"1276 LN",
    "sg:province":"Noord-Holland",
    "sg:website":"http://www.planburo.com",
    "wof:name":"Financieel Planburo",
    "wof:placetype":"venue"
},
  "geometry": {"coordinates":[5.25378,52.296928],"type":"Point"}
}