{
  "type": "Feature",
  "properties": {
    "iso:country":"NL",
    "sg:address":"G Vd Nissestr 13",
    "sg:city":"Zaamslag",
    "sg:orig_category":"Scholen Voor Basisonderwijs",
    "sg:phone":"+31 115 431 646",
    "sg:postcode":"4543 AD",
    "sg:province":"Zeeland",
    "wof:name":"Irisschool",
    "wof:placetype":"venue"
},
  "geometry": {"coordinates":[3.914403,51.315578],"type":"Point"}
}