{
  "type": "Feature",
  "properties": {
    "addr:full":"V Vollenhovenln 2G Ryswyk Zh Zuid-Holland 2283 LT",
    "addr:postcode":"2283 lt",
    "iso:country":"NL",
    "sg:address":"V Vollenhovenln 2G",
    "sg:city":"Ryswyk Zh",
    "sg:orig_category":"Verzekeringen - Verzekeringskantoren",
    "sg:phone":"+31 70 394 4103",
    "sg:postcode":"2283 LT",
    "sg:province":"Zuid-Holland",
    "wof:name":"Hesko",
    "wof:placetype":"venue"
},
  "geometry": {"coordinates":[4.32436,52.037251],"type":"Point"}
}