{
  "type": "Feature",
  "properties": {
    "addr:full":"Stratumsedijk 101 Eindhoven Noord-Brabant 5614 HP",
    "addr:housenumber":"101",
    "addr:postcode":"5614 hp",
    "addr:street":"Stratumsedijk",
    "iso:country":"NL",
    "sg:address":"Stratumsedijk 101",
    "sg:city":"Eindhoven",
    "sg:orig_category":"Antiekzaken",
    "sg:phone":"+31 40 211 2059",
    "sg:postcode":"5614 HP",
    "sg:province":"Noord-Brabant",
    "wof:name":"Kunsthandel Colinda",
    "wof:placetype":"venue"
},
  "geometry": {"coordinates":[5.487087,51.428696],"type":"Point"}
}