{
  "type": "Feature",
  "properties": {
    "addr:full":"Hazerswoudestr 117 Zoetermeer Zuid-Holland 2729 CL",
    "addr:housenumber":"117",
    "addr:postcode":"2729",
    "iso:country":"NL",
    "sg:address":"Hazerswoudestr 117",
    "sg:city":"Zoetermeer",
    "sg:orig_category":"Kunststof Ramen",
    "sg:phone":"+31 79 321 0575",
    "sg:postcode":"2729 CL",
    "sg:province":"Zuid-Holland",
    "wof:name":"Roba Onderhouds- En Montagebedr",
    "wof:placetype":"venue"
},
  "geometry": {"coordinates":[4.534919,52.066727],"type":"Point"}
}