{
  "type": "Feature",
  "properties": {
    "addr:full":"Engelandlaan 168 Zoetermeer South Holland 2711 DW",
    "addr:housenumber":"168",
    "addr:postcode":"2711 dw",
    "addr:street":"Engelandlaan",
    "iso:country":"NL",
    "sg:address":"Engelandlaan 168",
    "sg:city":"Zoetermeer",
    "sg:orig_category":"Verhuisdiensten",
    "sg:phone":"+31 79 342 8820",
    "sg:postcode":"2711 DW",
    "sg:province":"South Holland",
    "wof:name":"Pvh Allround Movers",
    "wof:placetype":"venue"
},
  "geometry": {"coordinates":[4.489261,52.059769],"type":"Point"}
}