{
  "type": "Feature",
  "properties": {
    "addr:full":"Brouwerijweg 109 Arnhem Gelderland 6814 EK",
    "addr:housenumber":"109",
    "addr:postcode":"6814 ek",
    "addr:street":"Brouwerijweg",
    "iso:country":"NL",
    "sg:address":"Brouwerijweg 109",
    "sg:city":"Arnhem",
    "sg:orig_category":"Fotostudio'S And Fotografen",
    "sg:phone":"+31 26 443 4791",
    "sg:postcode":"6814 EK",
    "sg:province":"Gelderland",
    "wof:name":"Jan M Fotografie",
    "wof:placetype":"venue"
},
  "geometry": {"coordinates":[5.89134,51.988682],"type":"Point"}
}