{
  "type": "Feature",
  "properties": {
    "addr:full":"Backershagen 19 Amsterdam Noord-Holland 1082 GR",
    "addr:housenumber":"19",
    "addr:postcode":"1082",
    "addr:street":"Backershagen",
    "iso:country":"NL",
    "sg:address":"Backershagen 19",
    "sg:city":"Amsterdam",
    "sg:orig_category":"Verzekeringen - Verzekeringskantoren",
    "sg:phone":"+31 20 646 5700",
    "sg:postcode":"1082 GR",
    "sg:province":"Noord-Holland",
    "wof:name":"Burger, A B P Den",
    "wof:placetype":"venue"
},
  "geometry": {"coordinates":[4.876368,52.327797],"type":"Point"}
}