{
  "type": "Feature",
  "properties": {
    "addr:full":"De Factorij 59 N Zwaag Noord-Holland 1689  A",
    "addr:housenumber":"59 n;1689 a",
    "addr:street":"De Factorij",
    "iso:country":"NL",
    "sg:address":"De Factorij 59 N",
    "sg:city":"Zwaag",
    "sg:orig_category":"Algemene Werktuigbouw",
    "sg:phone":"+31 229 271 713",
    "sg:postcode":"1689  A",
    "sg:province":"Noord-Holland",
    "wof:name":"Riechelmann Fijnmechanische Techniek",
    "wof:placetype":"venue"
},
  "geometry": {"coordinates":[5.074855,52.668491],"type":"Point"}
}