{
  "type": "Feature",
  "properties": {
    "addr:full":"Parkstr 68 Zaandam Noord-Holland 1506 WE",
    "addr:housenumber":"68",
    "addr:postcode":"1506 we",
    "addr:street":"Parkstr",
    "iso:country":"NL",
    "sg:address":"Parkstr 68",
    "sg:city":"Zaandam",
    "sg:orig_category":"Goudsmeden En Zilversmeden",
    "sg:phone":"+31 75 635 7189",
    "sg:postcode":"1506 WE",
    "sg:province":"Noord-Holland",
    "wof:name":"Ingrid De Marie",
    "wof:placetype":"venue"
},
  "geometry": {"coordinates":[4.816704,52.444324],"type":"Point"}
}