{
  "type": "Feature",
  "properties": {
    "iso:country":"NL",
    "sg:address":"Kanaalweg 8/D",
    "sg:city":"De Lier",
    "sg:orig_category":"Goederenvervoer Over De Weg",
    "sg:phone":"+31 174 513 016",
    "sg:postcode":"2678 LX",
    "sg:province":"Zuid-Holland",
    "wof:name":"Firma B. Spreen & Zoon",
    "wof:placetype":"venue"
},
  "geometry": {"coordinates":[4.232491,51.980919],"type":"Point"}
}