{
  "type": "Feature",
  "properties": {
    "addr:full":"Voorstr 244 Dordrecht Zuid-Holland 3311 ET",
    "addr:housenumber":"244",
    "addr:postcode":"3311 et",
    "iso:country":"NL",
    "sg:address":"Voorstr 244",
    "sg:city":"Dordrecht",
    "sg:orig_category":"Meubelen",
    "sg:phone":"+31 78 613 1432",
    "sg:postcode":"3311 ET",
    "sg:province":"Zuid-Holland",
    "wof:name":"Monti",
    "wof:placetype":"venue"
},
  "geometry": {"coordinates":[4.668185,51.815132],"type":"Point"}
}