{
  "type": "Feature",
  "properties": {
    "addr:full":"Lopikstraat 10 Rotterdam South Holland 3079 DV",
    "addr:housenumber":"10",
    "addr:postcode":"3079 dv",
    "addr:street":"Lopikstraat",
    "iso:country":"NL",
    "sg:address":"Lopikstraat 10",
    "sg:city":"Rotterdam",
    "sg:orig_category":"Politie",
    "sg:phone":"+31 10 274 0915",
    "sg:postcode":"3079 DV",
    "sg:province":"South Holland",
    "wof:name":"Politie Rotterdam Rijnmond District Feijenoord Rid",
    "wof:placetype":"venue"
},
  "geometry": {"coordinates":[4.534878,51.880245],"type":"Point"}
}