{
  "type": "Feature",
  "properties": {
    "addr:full":"Stationsplein 17 Eindhoven Noord-Brabant 5611 AC",
    "addr:housenumber":"17",
    "addr:postcode":"5611 ac",
    "addr:street":"Stationsplein",
    "iso:country":"NL",
    "sg:address":"Stationsplein 17",
    "sg:city":"Eindhoven",
    "sg:orig_category":"Diverse Kredietdiensten",
    "sg:postcode":"5611 AC",
    "sg:province":"Noord-Brabant",
    "wof:name":"Rabobank Geldautomaat",
    "wof:placetype":"venue"
},
  "geometry": {"coordinates":[5.484105,51.434471],"type":"Point"}
}