{
  "type": "Feature",
  "properties": {
    "addr:full":"Vijfde Uitgang 70 Gorinchem Zuid-Holland 4201 XH",
    "addr:housenumber":"70",
    "addr:postcode":"4201 xh",
    "addr:street":"Vijfde Uitgang",
    "iso:country":"NL",
    "sg:address":"Vijfde Uitgang 70",
    "sg:city":"Gorinchem",
    "sg:orig_category":"Makelaars In Onroerend Goed",
    "sg:phone":"+31 183 665 589",
    "sg:postcode":"4201 XH",
    "sg:province":"Zuid-Holland",
    "wof:name":"Trijs En Partners",
    "wof:placetype":"venue"
},
  "geometry": {"coordinates":[4.978374,51.832474],"type":"Point"}
}