{
  "type": "Feature",
  "properties": {
    "addr:full":"Van Uvenweg 274 Wageningen Gelderland 6707 BN",
    "addr:housenumber":"274",
    "addr:postcode":"6707 bn",
    "addr:street":"Van Uvenweg;Gelderland",
    "iso:country":"NL",
    "sg:address":"Van Uvenweg 274",
    "sg:city":"Wageningen",
    "sg:orig_category":"Koeriersdiensten",
    "sg:phone":"+31 317 416 815",
    "sg:postcode":"6707 BN",
    "sg:province":"Gelderland",
    "wof:name":"De Jong Koeriersdiensten",
    "wof:placetype":"venue"
},
  "geometry": {"coordinates":[5.670013,51.976608],"type":"Point"}
}