{
  "type": "Feature",
  "properties": {
    "iso:country":"NL",
    "sg:address":"Markt 6",
    "sg:city":"Wijchen",
    "sg:orig_category":"Opticiens",
    "sg:phone":"+31 24 641 7641",
    "sg:postcode":"6602 AM",
    "sg:province":"Gelderland",
    "wof:name":"Optica Bogaerts Bv",
    "wof:placetype":"venue"
},
  "geometry": {"coordinates":[5.7259812355,51.8073425293],"type":"Point"}
}