{
  "type": "Feature",
  "properties": {
    "addr:full":"Kerkstr 44 Heerenveen Friesland 8441 EZ",
    "addr:housenumber":"44",
    "addr:postcode":"8441 ez",
    "addr:street":"Kerkstr",
    "iso:country":"NL",
    "sg:address":"Kerkstr 44",
    "sg:city":"Heerenveen",
    "sg:orig_category":"Discotheken",
    "sg:phone":"+31 513 624 412",
    "sg:postcode":"8441 EZ",
    "sg:province":"Friesland",
    "wof:name":"Muis, De",
    "wof:placetype":"venue"
},
  "geometry": {"coordinates":[5.929095,52.95845],"type":"Point"}
}