{
  "type": "Feature",
  "properties": {
    "addr:full":"Ardennen 32 Leusden Utrecht 3831 EX",
    "addr:housenumber":"32",
    "addr:postcode":"3831 ex",
    "addr:street":"Ardennen",
    "iso:country":"NL",
    "sg:address":"Ardennen 32",
    "sg:city":"Leusden",
    "sg:orig_category":"Verzekeringen",
    "sg:phone":"+31 33 494 0483",
    "sg:postcode":"3831 EX",
    "sg:province":"Utrecht",
    "wof:name":"J.Hoogendoorn",
    "wof:placetype":"venue"
},
  "geometry": {"coordinates":[5.432598,52.133312],"type":"Point"}
}