{
  "type": "Feature",
  "properties": {
    "addr:full":"Elspeterweg 12 Nunspeet Gelderland 8071 PA",
    "addr:housenumber":"12",
    "addr:postcode":"8071",
    "addr:street":"Elspeterweg;Gelderland",
    "iso:country":"NL",
    "sg:address":"Elspeterweg 12",
    "sg:city":"Nunspeet",
    "sg:orig_category":"Politieke Organisaties",
    "sg:phone":"+31 341 256 744",
    "sg:postcode":"8071 PA",
    "sg:province":"Gelderland",
    "wof:name":"Reformatorische Politieke Federatie (Rpf)",
    "wof:placetype":"venue"
},
  "geometry": {"coordinates":[5.782996,52.367817],"type":"Point"}
}