{
  "type": "Feature",
  "properties": {
    "addr:full":"Truffautstraat 4 Almere Flevoland 1325 PN",
    "addr:housenumber":"4",
    "addr:postcode":"1325 pn",
    "addr:street":"Truffautstraat;Flevoland",
    "iso:country":"NL",
    "sg:address":"Truffautstraat 4",
    "sg:city":"Almere",
    "sg:orig_category":"Beautyfarms And Sauna'S",
    "sg:phone":"+31 36 545 2747",
    "sg:postcode":"1325 PN",
    "sg:province":"Flevoland",
    "wof:name":"Cynthia Schrauwers-Hoefakker",
    "wof:placetype":"venue"
},
  "geometry": {"coordinates":[5.244286,52.363602],"type":"Point"}
}