{
  "type": "Feature",
  "properties": {
    "iso:country":"NL",
    "sg:address":"Westerdreef 43",
    "sg:city":"Lisse",
    "sg:orig_category":"Artsen - Huisartsen",
    "sg:phone":"+31 252 413 685",
    "sg:postcode":"2161 EN",
    "sg:province":"Zuid-Holland",
    "wof:name":"Haase En J J F M Brinkmann, F G W M",
    "wof:placetype":"venue"
},
  "geometry": {"coordinates":[4.5539,52.261177],"type":"Point"}
}