{
  "type": "Feature",
  "properties": {
    "addr:full":"Hooglandsekerkgracht 19-21 Leiden Zuid-Holland 2312 HS",
    "addr:housenumber":"19-21",
    "addr:postcode":"2312 hs",
    "addr:street":"Hooglandsekerkgracht",
    "iso:country":"NL",
    "sg:address":"Hooglandsekerkgracht 19-21",
    "sg:city":"Leiden",
    "sg:orig_category":"Organisaties And Verenigingen",
    "sg:phone":"+31 71 516 5369",
    "sg:postcode":"2312 HS",
    "sg:province":"Zuid-Holland",
    "wof:name":"Kunstuitleen (Cbk)",
    "wof:placetype":"venue"
},
  "geometry": {"coordinates":[4.4940390587,52.1590232849],"type":"Point"}
}