{
  "type": "Feature",
  "properties": {
    "iso:country":"NL",
    "sg:address":"Marconistr 142H",
    "sg:city":"Amsterdam",
    "sg:orig_category":"Onderhoudswerken",
    "sg:phone":"+31 20 468 1937",
    "sg:postcode":"1098 TH",
    "sg:province":"Noord-Holland",
    "wof:name":"Vellema, R",
    "wof:placetype":"venue"
},
  "geometry": {"coordinates":[4.94496,52.351109],"type":"Point"}
}