{
  "type": "Feature",
  "properties": {
    "addr:full":"Industriewg 92A Zutphen Gelderland 7202 CB",
    "addr:housenumber":"92a",
    "addr:postcode":"7202 cb",
    "addr:street":"Industriewg;Gelderland",
    "iso:country":"NL",
    "sg:address":"Industriewg 92A",
    "sg:city":"Zutphen",
    "sg:orig_category":"Verlichting",
    "sg:phone":"+31 575 525 549",
    "sg:postcode":"7202 CB",
    "sg:province":"Gelderland",
    "wof:name":"L T N Lichttechniek Ned Bv",
    "wof:placetype":"venue"
},
  "geometry": {"coordinates":[6.199144,52.15477],"type":"Point"}
}