{
  "type": "Feature",
  "properties": {
    "addr:full":"T Goylaan 84 Utrecht Utrecht 3525 AJ",
    "addr:housenumber":"84",
    "addr:postcode":"3525 aj",
    "addr:street":"T Goylaan",
    "iso:country":"NL",
    "sg:address":"T Goylaan 84",
    "sg:city":"Utrecht",
    "sg:classifiers":[
        {
            "category":"Fast Food",
            "type":"Food & Drink"
        }
    ],
    "sg:phone":"+31 30 288 0405",
    "sg:postcode":"3525 AJ",
    "sg:province":"Utrecht",
    "sg:tags":[
        "afhaal",
        "restaurant"
    ],
    "wof:name":"Cafetaria Choy",
    "wof:placetype":"venue"
},
  "geometry": {"coordinates":[5.120527,52.066296],"type":"Point"}
}