{
  "type": "Feature",
  "properties": {
    "addr:full":"Rotscherwg 61 Landgraaf Limburg 6374 XW",
    "addr:housenumber":"61",
    "addr:postcode":"6374 xw",
    "addr:street":"Rotscherwg",
    "iso:country":"NL",
    "sg:address":"Rotscherwg 61",
    "sg:city":"Landgraaf",
    "sg:orig_category":"Elektronica - Ontwikkeling En Groothandel",
    "sg:phone":"+31 45 532 7755",
    "sg:postcode":"6374 XW",
    "sg:province":"Limburg",
    "wof:name":"Genotronics Bv",
    "wof:placetype":"venue"
},
  "geometry": {"coordinates":[6.042715,50.908249],"type":"Point"}
}