{
  "type": "Feature",
  "properties": {
    "addr:full":"Brouwerstr 144 Rynsburg South Holland 2231 HV",
    "addr:housenumber":"144",
    "addr:postcode":"2231 hv",
    "addr:street":"Rynsburg South",
    "iso:country":"NL",
    "sg:address":"Brouwerstr 144",
    "sg:city":"Rynsburg",
    "sg:orig_category":"Bloemen En Planten - Groothandel",
    "sg:phone":"+31 71 402 1459",
    "sg:postcode":"2231 HV",
    "sg:province":"South Holland",
    "wof:name":"Paauw, A",
    "wof:placetype":"venue"
},
  "geometry": {"coordinates":[4.447899,52.19109],"type":"Point"}
}