{
  "type": "Feature",
  "properties": {
    "addr:full":"Floris Schoutenstraat 3 Sassenheim South Holland 2172 SK",
    "addr:housenumber":"3",
    "addr:street":"Floris Schoutenstraat;2172",
    "iso:country":"NL",
    "sg:address":"Floris Schoutenstraat 3",
    "sg:city":"Sassenheim",
    "sg:orig_category":"Bedrijfs- And Managementsconsultants",
    "sg:phone":"+31 252 231 403",
    "sg:postcode":"2172 SK",
    "sg:province":"South Holland",
    "wof:name":"Bob Voorbraak",
    "wof:placetype":"venue"
},
  "geometry": {"coordinates":[4.518379,52.223454],"type":"Point"}
}