{
  "type": "Feature",
  "properties": {
    "addr:full":"Noorderdracht 20 Oosterblokker Noord-Holland 1696 AD",
    "addr:housenumber":"20",
    "addr:postcode":"1696 ad",
    "addr:street":"Noorderdracht",
    "iso:country":"NL",
    "sg:address":"Noorderdracht 20",
    "sg:city":"Oosterblokker",
    "sg:orig_category":"Koffie- En Theehuizen",
    "sg:phone":"+31 229 261 818",
    "sg:postcode":"1696 AD",
    "sg:province":"Noord-Holland",
    "wof:name":"Tuincafe",
    "wof:placetype":"venue"
},
  "geometry": {"coordinates":[5.102246,52.667137],"type":"Point"}
}