{
  "type": "Feature",
  "properties": {
    "iso:country":"NL",
    "sg:address":"Wenckebachstr 1",
    "sg:city":"Velsen Noord",
    "sg:orig_category":"Projectontwikkeling",
    "sg:phone":"+31 251 493 516",
    "sg:postcode":"1951 JZ",
    "sg:province":"Noord-Holland",
    "sg:website":"http://www.businessparkymond.nl",
    "wof:name":"Business Park Ymond Cv",
    "wof:placetype":"venue"
},
  "geometry": {"coordinates":[4.626953,52.473907],"type":"Point"}
}