{
  "type": "Feature",
  "properties": {
    "addr:full":"Burg Eijckelhofstr 46 Millingen A/D Rijn Gelderland 6566 AV",
    "addr:housenumber":"46;a / d;6566",
    "addr:postcode":"av",
    "addr:street":"Burg;Rijn Gelderland",
    "iso:country":"NL",
    "sg:address":"Burg Eijckelhofstr 46",
    "sg:city":"Millingen A/D Rijn",
    "sg:orig_category":"Kunst And Kunstenaarsbenodigdheden",
    "sg:phone":"+31 481 431 696",
    "sg:postcode":"6566 AV",
    "sg:province":"Gelderland",
    "wof:name":"Lijstenmakerij Van Kuil",
    "wof:placetype":"venue"
},
  "geometry": {"coordinates":[6.046855,51.864063],"type":"Point"}
}