{
  "type": "Feature",
  "properties": {
    "addr:full":"Stekelvaren 24 Bergschenhoek Zuid-Holland 2661 PZ",
    "addr:housenumber":"24",
    "addr:postcode":"2661 pz",
    "addr:street":"Stekelvaren",
    "iso:country":"NL",
    "sg:address":"Stekelvaren 24",
    "sg:city":"Bergschenhoek",
    "sg:orig_category":"Marktonderzoekbureaus",
    "sg:phone":"+31 10 522 3234",
    "sg:postcode":"2661 PZ",
    "sg:province":"Zuid-Holland",
    "wof:name":"Environs Int",
    "wof:placetype":"venue"
},
  "geometry": {"coordinates":[4.502385,51.991356],"type":"Point"}
}