{
  "type": "Feature",
  "properties": {
    "addr:full":"Limburglaan 51 Eindhoven Noord-Brabant 5616 HR",
    "addr:housenumber":"51",
    "addr:postcode":"5616 hr",
    "addr:street":"Limburglaan",
    "iso:country":"NL",
    "sg:address":"Limburglaan 51",
    "sg:city":"Eindhoven",
    "sg:orig_category":"Drukkerijen And Copyshops",
    "sg:phone":"+31 40 251 0015",
    "sg:postcode":"5616 HR",
    "sg:province":"Noord-Brabant",
    "wof:name":"Vrijdag Label Bv",
    "wof:placetype":"venue"
},
  "geometry": {"coordinates":[5.45409,51.432793],"type":"Point"}
}