{
  "type": "Feature",
  "properties": {
    "addr:full":"Jan R Stuutstraat F 60 Nieuwe Pekela Groningen 9663 SH",
    "addr:housenumber":"60",
    "addr:postcode":"9663 sh",
    "addr:street":"Jan R Stuutstraat F",
    "iso:country":"NL",
    "sg:address":"Jan R Stuutstraat F 60",
    "sg:city":"Nieuwe Pekela",
    "sg:orig_category":"Discountwinkels",
    "sg:phone":"+31 597 646 352",
    "sg:postcode":"9663 SH",
    "sg:province":"Groningen",
    "wof:name":"Feye'S Koopjespark",
    "wof:placetype":"venue"
},
  "geometry": {"coordinates":[6.943988,53.058575],"type":"Point"}
}