{
  "type": "Feature",
  "properties": {
    "addr:full":"Terhagen 9 Elsloo Lb Limburg 6181 HR",
    "addr:housenumber":"9",
    "addr:postcode":"lb;6181 hr",
    "addr:street":"Terhagen",
    "iso:country":"NL",
    "sg:address":"Terhagen 9",
    "sg:city":"Elsloo Lb",
    "sg:orig_category":"Fotostudio'S And Fotografen",
    "sg:phone":"+31 46 437 6113",
    "sg:postcode":"6181 HR",
    "sg:province":"Limburg",
    "wof:name":"Fotografie Frank Van Helfteren",
    "wof:placetype":"venue"
},
  "geometry": {"coordinates":[5.758482,50.943451],"type":"Point"}
}