{
  "type": "Feature",
  "properties": {
    "addr:full":"Ryksstrwg 117 Leersum Utrecht 3956 CK",
    "addr:housenumber":"117",
    "addr:postcode":"3956 ck",
    "addr:street":"Leersum",
    "iso:country":"NL",
    "sg:address":"Ryksstrwg 117",
    "sg:city":"Leersum",
    "sg:orig_category":"Adviesbureaus Bouwkosten",
    "sg:phone":"+31 343 453 052",
    "sg:postcode":"3956 CK",
    "sg:province":"Utrecht",
    "wof:name":"Leersum Bv",
    "wof:placetype":"venue"
},
  "geometry": {"coordinates":[5.43237,52.010792],"type":"Point"}
}