{
  "type": "Feature",
  "properties": {
    "addr:full":"Havenwg 28 Waalwyk Noord-Brabant 5145 NJ",
    "addr:housenumber":"28",
    "addr:postcode":"5145 nj",
    "addr:street":"Havenwg",
    "iso:country":"NL",
    "sg:address":"Havenwg 28",
    "sg:city":"Waalwyk",
    "sg:orig_category":"Beveiliging",
    "sg:phone":"+31 416 541 010",
    "sg:postcode":"5145 NJ",
    "sg:province":"Noord-Brabant",
    "sg:website":"http://www.vcs-int.nl",
    "wof:name":"Vcs Internationaal Bv",
    "wof:placetype":"venue"
},
  "geometry": {"coordinates":[5.042707,51.69363],"type":"Point"}
}