{
  "type": "Feature",
  "properties": {
    "addr:full":"Burghardt Vd Berghstr 86 Nijmegen Gelderland 6512 DP",
    "addr:housenumber":"86",
    "addr:postcode":"6512 dp",
    "addr:street":"Gelderland",
    "iso:country":"NL",
    "sg:address":"Burghardt Vd Berghstr 86",
    "sg:city":"Nijmegen",
    "sg:orig_category":"Fietshandelaren",
    "sg:phone":"+31 24 360 4874",
    "sg:postcode":"6512 DP",
    "sg:province":"Gelderland",
    "wof:name":"Jo Velo",
    "wof:placetype":"venue"
},
  "geometry": {"coordinates":[5.855977,51.839542],"type":"Point"}
}