{
  "type": "Feature",
  "properties": {
    "addr:full":"Kameraarsweide 18 Nieuwegein Utrecht 3437 CB",
    "addr:housenumber":"18",
    "addr:postcode":"3437 cb",
    "addr:street":"Kameraarsweide",
    "iso:country":"NL",
    "sg:address":"Kameraarsweide 18",
    "sg:city":"Nieuwegein",
    "sg:orig_category":"Manueel Therapeuten",
    "sg:phone":"+31 30 603 8611",
    "sg:postcode":"3437 CB",
    "sg:province":"Utrecht",
    "wof:name":"Roowaan, A J",
    "wof:placetype":"venue"
},
  "geometry": {"coordinates":[5.071202,52.040932],"type":"Point"}
}