{
  "type": "Feature",
  "properties": {
    "addr:full":"Bouwerij 7 Amstelveen Noord-Holland 1185 XW",
    "addr:housenumber":"7",
    "addr:postcode":"1185 xw",
    "addr:street":"Bouwerij",
    "iso:country":"NL",
    "sg:address":"Bouwerij 7",
    "sg:city":"Amstelveen",
    "sg:orig_category":"Diverse Consumentenartikelen Gh",
    "sg:phone":"+31 20 640 7232",
    "sg:postcode":"1185 XW",
    "sg:province":"Noord-Holland",
    "wof:name":"Wectra Bv",
    "wof:placetype":"venue"
},
  "geometry": {"coordinates":[4.839231,52.283585],"type":"Point"}
}