{
  "type": "Feature",
  "properties": {
    "addr:full":"N Keyserstr 2 Sleeuwyk North Brabant 4254 EP",
    "addr:housenumber":"2",
    "addr:postcode":"4254 ep",
    "addr:street":"N Keyserstr",
    "iso:country":"NL",
    "sg:address":"N Keyserstr 2",
    "sg:city":"Sleeuwyk",
    "sg:orig_category":"Bibliotheken En Leeszalen Openbare",
    "sg:phone":"+31 183 309 033",
    "sg:postcode":"4254 EP",
    "sg:province":"North Brabant",
    "wof:name":"Openb Bibliotheek",
    "wof:placetype":"venue"
},
  "geometry": {"coordinates":[4.950798,51.813931],"type":"Point"}
}