{
  "type": "Feature",
  "properties": {
    "iso:country":"NL",
    "sg:address":"Lageweg 14",
    "sg:city":"Wedde",
    "sg:classifiers":[
        {
            "category":"Retail",
            "subcategory":"Photofinishing",
            "type":"Services"
        }
    ],
    "sg:phone":"+31 597 562 940",
    "sg:postcode":"9698 BN",
    "sg:province":"Groningen",
    "sg:tags":[
        "foto",
        "film"
    ],
    "wof:name":"Vof Foto Van Oest",
    "wof:placetype":"venue"
},
  "geometry": {"coordinates":[7.084046,53.066792],"type":"Point"}
}