{
  "type": "Feature",
  "properties": {
    "iso:country":"NL",
    "sg:address":"Dam 5-7",
    "sg:city":"Amsterdam",
    "sg:orig_category":"Vertaalbureaus",
    "sg:phone":"+31 20 639 0119",
    "sg:postcode":"1012 JS",
    "sg:province":"Noord-Holland",
    "sg:website":"http://www.e-kern.com",
    "wof:name":"Kern Amsterdam",
    "wof:placetype":"venue"
},
  "geometry": {"coordinates":[4.894047,52.373158],"type":"Point"}
}