{
  "type": "Feature",
  "properties": {
    "iso:country":"NL",
    "sg:address":"Noordweg 265",
    "sg:city":"Middelburg",
    "sg:orig_category":"Loodgieterswerk, Verwarming And Sanitaire Installaties",
    "sg:phone":"+31 118 639 351",
    "sg:postcode":"4333 GG",
    "sg:province":"Zeeland",
    "wof:name":"K. Kagenaar",
    "wof:placetype":"venue"
},
  "geometry": {"coordinates":[3.60513,51.512821],"type":"Point"}
}