{
  "type": "Feature",
  "properties": {
    "addr:full":"Kl Beer 5 Bleiswyk Zuid-Holland 2665 WP",
    "addr:housenumber":"5",
    "addr:postcode":"2665 wp",
    "addr:street":"Beer",
    "iso:country":"NL",
    "sg:address":"Kl Beer 5",
    "sg:city":"Bleiswyk",
    "sg:orig_category":"Fotoreportages",
    "sg:phone":"+31 6 23273033",
    "sg:postcode":"2665 WP",
    "sg:province":"Zuid-Holland",
    "sg:website":"http://www.dijkfotografie.nl",
    "wof:name":"Dijk, Van",
    "wof:placetype":"venue"
},
  "geometry": {"coordinates":[4.531235,52.012997],"type":"Point"}
}