{
  "type": "Feature",
  "properties": {
    "iso:country":"NL",
    "sg:address":"Kalshoven 7",
    "sg:city":"Breda",
    "sg:orig_category":"Huishoudapparatuur, Televisies And Radio'S",
    "sg:phone":"+31 76 571 5010",
    "sg:postcode":"4825 AL",
    "sg:province":"Noord-Brabant",
    "wof:name":"O.L.S. Audio Technology",
    "wof:placetype":"venue"
},
  "geometry": {"coordinates":[4.768944,51.604374],"type":"Point"}
}