{
  "type": "Feature",
  "properties": {
    "addr:full":"J V Stolbergln 5 Rozenburg Zh Zuid-Holland 3181 HH",
    "addr:housenumber":"5",
    "addr:postcode":"zh;3181 hh",
    "addr:street":"J;Stolbergln",
    "iso:country":"NL",
    "sg:address":"J V Stolbergln 5",
    "sg:city":"Rozenburg Zh",
    "sg:orig_category":"Accountants - Administratie- Consulenten En -Kantoren",
    "sg:phone":"+31 181 213 366",
    "sg:postcode":"3181 HH",
    "sg:province":"Zuid-Holland",
    "wof:name":"Dalum Bv, F Van",
    "wof:placetype":"venue"
},
  "geometry": {"coordinates":[4.249615,51.904446],"type":"Point"}
}