{
  "type": "Feature",
  "properties": {
    "addr:full":"Koningshoek 92311 Maassluis Friesland 3144 BA",
    "addr:housenumber":"92311",
    "addr:postcode":"3144 ba",
    "addr:street":"Koningshoek",
    "iso:country":"NL",
    "sg:address":"Koningshoek 92311",
    "sg:city":"Maassluis",
    "sg:orig_category":"Zoetwaren - Winkels",
    "sg:phone":"+31 10 590 0298",
    "sg:postcode":"3144 BA",
    "sg:province":"Friesland",
    "wof:name":"Ivy",
    "wof:placetype":"venue"
},
  "geometry": {"coordinates":[4.239944,51.927898],"type":"Point"}
}