{
  "type": "Feature",
  "properties": {
    "addr:full":"Voorstraat 186 Roosendaal North Brabant 4702 EW",
    "addr:housenumber":"186",
    "addr:postcode":"4702 ew",
    "addr:street":"Voorstraat",
    "iso:country":"NL",
    "sg:address":"Voorstraat 186",
    "sg:city":"Roosendaal",
    "sg:orig_category":"Technische Studies And Onderzoek",
    "sg:phone":"+31 165 567 610",
    "sg:postcode":"4702 EW",
    "sg:province":"North Brabant",
    "wof:name":"Koevoets Engineering",
    "wof:placetype":"venue"
},
  "geometry": {"coordinates":[4.476298,51.530602],"type":"Point"}
}