{
  "type": "Feature",
  "properties": {
    "addr:full":"Luchterweg 32 Noordwijkerhout South Holland 2211 SZ",
    "addr:housenumber":"32",
    "addr:postcode":"2211 sz",
    "addr:street":"Luchterweg",
    "iso:country":"NL",
    "sg:address":"Luchterweg 32",
    "sg:city":"Noordwijkerhout",
    "sg:orig_category":"Verpakkingsbedrijven",
    "sg:phone":"+31 252 374 846",
    "sg:postcode":"2211 SZ",
    "sg:province":"South Holland",
    "wof:name":"Loonverpakkingsbedrijf Leo De Wit Vof",
    "wof:placetype":"venue"
},
  "geometry": {"coordinates":[4.527138,52.287766],"type":"Point"}
}