{
  "type": "Feature",
  "properties": {
    "addr:full":"K Doormanln 21 Huizen North Holland 1271 CA",
    "addr:housenumber":"21",
    "addr:postcode":"1271 ca",
    "addr:street":"Doormanln",
    "iso:country":"NL",
    "sg:address":"K Doormanln 21",
    "sg:city":"Huizen",
    "sg:orig_category":"Grafisch Ontwerpers",
    "sg:phone":"+31 35 525 7754",
    "sg:postcode":"1271 CA",
    "sg:province":"North Holland",
    "wof:name":"Esmee",
    "wof:placetype":"venue"
},
  "geometry": {"coordinates":[5.226804,52.29813],"type":"Point"}
}