{
  "type": "Feature",
  "properties": {
    "addr:full":"Celsiusstraat 5 Heerhugowaard Noord-Holland 1704 RX",
    "addr:housenumber":"5",
    "addr:postcode":"1704 rx",
    "addr:street":"Celsiusstraat",
    "iso:country":"NL",
    "sg:address":"Celsiusstraat 5",
    "sg:city":"Heerhugowaard",
    "sg:orig_category":"Loodgieterswerk, Verwarming And Sanitaire Installaties",
    "sg:phone":"+31 72 571 0501",
    "sg:postcode":"1704 RX",
    "sg:province":"Noord-Holland",
    "wof:name":"Breman Noord Holland Bv",
    "wof:placetype":"venue"
},
  "geometry": {"coordinates":[4.837051,52.68568],"type":"Point"}
}