{
  "type": "Feature",
  "properties": {
    "iso:country":"NL",
    "sg:address":"Provincialewg 77",
    "sg:city":"Bunnik",
    "sg:orig_category":"Goudsmeden En Zilversmeden",
    "sg:phone":"+31 30 656 0822",
    "sg:postcode":"3981 AM",
    "sg:province":"Utrecht",
    "sg:website":"http://www.runnenburg.nl",
    "wof:name":"Runnenburg Atelier",
    "wof:placetype":"venue"
},
  "geometry": {"coordinates":[5.18694,52.063835],"type":"Point"}
}