{
  "type": "Feature",
  "properties": {
    "addr:full":"Steenweg 2 Zaltbommel Gelderland 5301 HL",
    "addr:housenumber":"2",
    "addr:postcode":"5301 hl",
    "addr:street":"Steenweg;Gelderland",
    "iso:country":"NL",
    "sg:address":"Steenweg 2",
    "sg:city":"Zaltbommel",
    "sg:classifiers":[
        {
            "category":"Travel",
            "subcategory":"Hotels & Motels",
            "type":"Entertainment"
        }
    ],
    "sg:phone":"+31 418 512 517",
    "sg:postcode":"5301 HL",
    "sg:province":"Gelderland",
    "wof:name":"Hotel Tivoli",
    "wof:placetype":"venue"
},
  "geometry": {"coordinates":[5.249919,51.793297],"type":"Point"}
}