{
  "type": "Feature",
  "properties": {
    "addr:full":"Bakkerstraat 12 Utrecht Utrecht 3511 JW",
    "addr:housenumber":"12",
    "addr:postcode":"3511 jw",
    "addr:street":"Bakkerstraat",
    "iso:country":"NL",
    "sg:address":"Bakkerstraat 12",
    "sg:city":"Utrecht",
    "sg:orig_category":"Bruidskleding",
    "sg:phone":"+31 30 231 6767",
    "sg:postcode":"3511 JW",
    "sg:province":"Utrecht",
    "wof:name":"Fa. Jos Van Dijck",
    "wof:placetype":"venue"
},
  "geometry": {"coordinates":[5.117151,52.091419],"type":"Point"}
}