{
  "type": "Feature",
  "properties": {
    "addr:full":"Amstellaan 3 Heemstede Noord-Holland 2105 VD",
    "addr:housenumber":"3",
    "addr:postcode":"2105 vd",
    "addr:street":"Amstellaan",
    "iso:country":"NL",
    "sg:address":"Amstellaan 3",
    "sg:city":"Heemstede",
    "sg:orig_category":"Kappers",
    "sg:phone":"+31 23 528 1918",
    "sg:postcode":"2105 VD",
    "sg:province":"Noord-Holland",
    "wof:name":"Vof Henk Prijs Haarmode",
    "wof:placetype":"venue"
},
  "geometry": {"coordinates":[4.602854,52.344372],"type":"Point"}
}