{
  "type": "Feature",
  "properties": {
    "iso:country":"NL",
    "sg:address":"P Joostenln 2",
    "sg:city":"Wilnis",
    "sg:orig_category":"Verenigingsgebouwen",
    "sg:phone":"+31 297 285 247",
    "sg:postcode":"3648 XR",
    "sg:province":"Utrecht",
    "wof:name":"Csw Vv",
    "wof:placetype":"venue"
},
  "geometry": {"coordinates":[4.897164,52.19426],"type":"Point"}
}