{
  "type": "Feature",
  "properties": {
    "addr:full":"Meidoornpassage 9 Wezep Gelderland 8091 KS",
    "addr:housenumber":"9",
    "addr:postcode":"8091 ks",
    "addr:street":"Meidoornpassage",
    "iso:country":"NL",
    "sg:address":"Meidoornpassage 9",
    "sg:city":"Wezep",
    "sg:orig_category":"Banken And Kredietinstellingen",
    "sg:phone":"+31 38 375 6500",
    "sg:postcode":"8091 KS",
    "sg:province":"Gelderland",
    "wof:name":"Rabobank",
    "wof:placetype":"venue"
},
  "geometry": {"coordinates":[5.99873,52.461636],"type":"Point"}
}