{
  "type": "Feature",
  "properties": {
    "iso:country":"NL",
    "sg:address":"Molenweg 12",
    "sg:city":"Maasland",
    "sg:orig_category":"Wegen And Sportterreinen",
    "sg:phone":"+31 10 592 2022",
    "sg:postcode":"3155 AV",
    "sg:province":"Zuid-Holland",
    "wof:name":"Aannemingsbedrijf Verboon Maasland Bv",
    "wof:placetype":"venue"
},
  "geometry": {"coordinates":[4.2778778076,51.9501838684],"type":"Point"}
}