{
  "type": "Feature",
  "properties": {
    "addr:full":"Teteringsedk 87C Breda Noord-Brabant 4817 MB",
    "addr:housenumber":"87c",
    "addr:postcode":"4817 mb",
    "addr:street":"Teteringsedk",
    "iso:country":"NL",
    "sg:address":"Teteringsedk 87C",
    "sg:city":"Breda",
    "sg:classifiers":[
        {
            "category":"Retail",
            "subcategory":"Auto Repair",
            "type":"Services"
        }
    ],
    "sg:phone":"+31 76 520 9694",
    "sg:postcode":"4817 MB",
    "sg:province":"Noord-Brabant",
    "sg:tags":[
        "garage"
    ],
    "wof:name":"Raf",
    "wof:placetype":"venue"
},
  "geometry": {"coordinates":[4.796278,51.593739],"type":"Point"}
}