{
  "type": "Feature",
  "properties": {
    "addr:full":"Gildeln 41A Eindhoven Noord-Brabant 5612 AG",
    "addr:housenumber":"41a",
    "addr:postcode":"5612",
    "addr:street":"Gildeln",
    "iso:country":"NL",
    "sg:address":"Gildeln 41A",
    "sg:city":"Eindhoven",
    "sg:orig_category":"Schoenen",
    "sg:phone":"+31 40 296 3380",
    "sg:postcode":"5612 AG",
    "sg:province":"Noord-Brabant",
    "sg:website":"http://www.nickyschoenmode.nl",
    "wof:name":"Nicky Schoenmode",
    "wof:placetype":"venue"
},
  "geometry": {"coordinates":[5.484105,51.434471],"type":"Point"}
}