{
  "type": "Feature",
  "properties": {
    "addr:full":"Hooftln 22 Bussum North Holland 1401 EE",
    "addr:housenumber":"22",
    "addr:postcode":"1401 ee",
    "addr:street":"Hooftln",
    "iso:country":"NL",
    "sg:address":"Hooftln 22",
    "sg:city":"Bussum",
    "sg:orig_category":"Pianostemmen En -Reparatie",
    "sg:phone":"+31 35 691 0168",
    "sg:postcode":"1401 EE",
    "sg:province":"North Holland",
    "wof:name":"Boersma",
    "wof:placetype":"venue"
},
  "geometry": {"coordinates":[5.162605,52.276829],"type":"Point"}
}