{
  "type": "Feature",
  "properties": {
    "addr:full":"Pres Rooseveltln 63 Helmond Noord-Brabant 5707 GC",
    "addr:housenumber":"63",
    "addr:postcode":"5707 gc",
    "iso:country":"NL",
    "sg:address":"Pres Rooseveltln 63",
    "sg:city":"Helmond",
    "sg:orig_category":"Adviesbureaus Elektrotechniek",
    "sg:phone":"+31 492 549 050",
    "sg:postcode":"5707 GC",
    "sg:province":"Noord-Brabant",
    "wof:name":"Leenen, W A",
    "wof:placetype":"venue"
},
  "geometry": {"coordinates":[5.658284,51.482239],"type":"Point"}
}