{
  "type": "Feature",
  "properties": {
    "addr:full":"Hoefkestr 62 Eindhoven North Brabant 5611 RN",
    "addr:housenumber":"62",
    "addr:postcode":"5611 rn",
    "addr:street":"Hoefkestr",
    "iso:country":"NL",
    "sg:address":"Hoefkestr 62",
    "sg:city":"Eindhoven",
    "sg:orig_category":"Grafisch Ontwerpers",
    "sg:phone":"+31 40 212 0182",
    "sg:postcode":"5611 RN",
    "sg:province":"North Brabant",
    "wof:name":"Laar, K Van De",
    "wof:placetype":"venue"
},
  "geometry": {"coordinates":[5.489021,51.431492],"type":"Point"}
}