{
  "type": "Feature",
  "properties": {
    "iso:country":"NL",
    "sg:address":"Julianastr 13",
    "sg:city":"Steenbergen Nb",
    "sg:orig_category":"Kappers",
    "sg:phone":"+31 167 565 641",
    "sg:postcode":"4651 BX",
    "sg:province":"Noord-Brabant",
    "wof:name":"Clara Coiffures",
    "wof:placetype":"venue"
},
  "geometry": {"coordinates":[4.3145551682,51.5855941772],"type":"Point"}
}