{
  "type": "Feature",
  "properties": {
    "addr:full":"Hermelijnlaan 7 Den Dolder Utrecht 3734 HC",
    "addr:housenumber":"7",
    "addr:postcode":"3734 hc",
    "addr:street":"Hermelijnlaan",
    "iso:country":"NL",
    "sg:address":"Hermelijnlaan 7",
    "sg:city":"Den Dolder",
    "sg:orig_category":"Kinderopvang Behalve Thuis",
    "sg:phone":"+31 30 229 1956",
    "sg:postcode":"3734 HC",
    "sg:province":"Utrecht",
    "wof:name":"Olivier",
    "wof:placetype":"venue"
},
  "geometry": {"coordinates":[5.238809,52.136845],"type":"Point"}
}