{
  "type": "Feature",
  "properties": {
    "addr:full":"Stevinstraat 1 'S Gravenhage Zuid-Holland 2587 EA",
    "addr:housenumber":"1 '",
    "addr:postcode":"2587 ea",
    "addr:street":"Stevinstraat",
    "iso:country":"NL",
    "sg:address":"Stevinstraat 1",
    "sg:city":"'S Gravenhage",
    "sg:orig_category":"Huishoudapparatuur, Televisies And Radio'S",
    "sg:phone":"+31 70 306 0475",
    "sg:postcode":"2587 EA",
    "sg:province":"Zuid-Holland",
    "wof:name":"Alex Radio- En Tv-Service",
    "wof:placetype":"venue"
},
  "geometry": {"coordinates":[4.292007,52.110809],"type":"Point"}
}