{
  "type": "Feature",
  "properties": {
    "addr:full":"Werkersdk 5 Rhoon Zuid-Holland 3161 BL",
    "addr:housenumber":"5",
    "addr:postcode":"3161 bl",
    "addr:street":"Werkersdk",
    "iso:country":"NL",
    "sg:address":"Werkersdk 5",
    "sg:city":"Rhoon",
    "sg:orig_category":"Fotoreportages",
    "sg:phone":"+31 10 501 1722",
    "sg:postcode":"3161 BL",
    "sg:province":"Zuid-Holland",
    "sg:website":"http://www.fotoaad.nl",
    "wof:name":"Aad",
    "wof:placetype":"venue"
},
  "geometry": {"coordinates":[4.419564,51.855724],"type":"Point"}
}