{
  "type": "Feature",
  "properties": {
    "addr:full":"Repelweg 10 Marknesse NL. 8316 PV",
    "addr:housenumber":"10",
    "addr:postcode":"8316 pv",
    "addr:street":"Repelweg;Nl.",
    "iso:country":"NL",
    "sg:address":"Repelweg 10",
    "sg:city":"Marknesse",
    "sg:orig_category":"Huishoudapparatuur, Televisies And Radio'S",
    "sg:phone":"+31 527 241 857",
    "sg:postcode":"8316 PV",
    "sg:province":"NL.",
    "wof:name":"Idento Electronics Bv",
    "wof:placetype":"venue"
},
  "geometry": {"coordinates":[5.928914,52.673359],"type":"Point"}
}