{
  "type": "Feature",
  "properties": {
    "addr:full":"Glashorst 25 Scherpenzeel Gld Gelderland 3925 BN",
    "addr:housenumber":"25",
    "addr:postcode":"3925 bn",
    "addr:street":"Glashorst;Gld Gelderland",
    "iso:country":"NL",
    "sg:address":"Glashorst 25",
    "sg:city":"Scherpenzeel Gld",
    "sg:orig_category":"Loodgieterswerk, Verwarming And Sanitaire Installaties",
    "sg:phone":"+31 33 277 1291",
    "sg:postcode":"3925 BN",
    "sg:province":"Gelderland",
    "wof:name":"J.W. De Leeuw",
    "wof:placetype":"venue"
},
  "geometry": {"coordinates":[5.479998,52.080296],"type":"Point"}
}