{
  "type": "Feature",
  "properties": {
    "addr:full":"Zuidplaswg 1 Zevenhuizen Zh South Holland 2761 JK",
    "addr:housenumber":"1;zh",
    "addr:postcode":"2761 jk",
    "addr:street":"Zuidplaswg",
    "iso:country":"NL",
    "sg:address":"Zuidplaswg 1",
    "sg:city":"Zevenhuizen Zh",
    "sg:orig_category":"Loodgieters",
    "sg:phone":"+31 180 631 494",
    "sg:postcode":"2761 JK",
    "sg:province":"South Holland",
    "wof:name":"Fw",
    "wof:placetype":"venue"
},
  "geometry": {"coordinates":[4.585963,52.009361],"type":"Point"}
}