{
  "type": "Feature",
  "properties": {
    "addr:full":"Molenwg 1A Maastricht Limburg 6225 NB",
    "addr:housenumber":"1a",
    "addr:postcode":"6225 nb",
    "addr:street":"Molenwg",
    "iso:country":"NL",
    "sg:address":"Molenwg 1A",
    "sg:city":"Maastricht",
    "sg:orig_category":"Loonbedrijven",
    "sg:phone":"+31 43 362 0627",
    "sg:postcode":"6225 NB",
    "sg:province":"Limburg",
    "wof:name":"Prickaerts, Gebr",
    "wof:placetype":"venue"
},
  "geometry": {"coordinates":[5.738046,50.853844],"type":"Point"}
}