{
  "type": "Feature",
  "properties": {
    "addr:full":"Bleekveld 1 Abbenbroek Zuid-Holland 3216 AC",
    "addr:housenumber":"1",
    "addr:postcode":"3216 ac",
    "addr:street":"Bleekveld",
    "iso:country":"NL",
    "sg:address":"Bleekveld 1",
    "sg:city":"Abbenbroek",
    "sg:orig_category":"Antiekzaken",
    "sg:phone":"+31 181 661 776",
    "sg:postcode":"3216 AC",
    "sg:province":"Zuid-Holland",
    "wof:name":"Handel In Antiek En Curiosa Toen En Nu",
    "wof:placetype":"venue"
},
  "geometry": {"coordinates":[4.243586,51.849396],"type":"Point"}
}