{
  "type": "Feature",
  "properties": {
    "addr:full":"1E Rozendwstr 11Hs Amsterdam North Holland 1016 PC",
    "addr:housenumber":"11hs",
    "addr:postcode":"1016 pc",
    "addr:street":"1E Rozendwstr",
    "iso:country":"NL",
    "sg:address":"1E Rozendwstr 11Hs",
    "sg:city":"Amsterdam",
    "sg:orig_category":"Boeken Antiquarische En Gebruikte",
    "sg:phone":"+31 20 623 1128",
    "sg:postcode":"1016 PC",
    "sg:province":"North Holland",
    "wof:name":"Abc",
    "wof:placetype":"venue"
},
  "geometry": {"coordinates":[4.880599,52.373016],"type":"Point"}
}