{
  "type": "Feature",
  "properties": {
    "addr:full":"Goudwespmeent 44 Hilversum North Holland 1218 GN",
    "addr:housenumber":"44",
    "addr:postcode":"1218 gn",
    "addr:street":"Goudwespmeent",
    "iso:country":"NL",
    "sg:address":"Goudwespmeent 44",
    "sg:city":"Hilversum",
    "sg:orig_category":"Puien",
    "sg:phone":"+31 35 691 7933",
    "sg:postcode":"1218 GN",
    "sg:province":"North Holland",
    "sg:website":"http://www.componed.net",
    "wof:name":"Componed Bv",
    "wof:placetype":"venue"
},
  "geometry": {"coordinates":[5.13863,52.266296],"type":"Point"}
}