{
  "type": "Feature",
  "properties": {
    "addr:full":"Roerstraat 15 Doetinchem Gelderland 7005 BS",
    "addr:housenumber":"15",
    "addr:postcode":"7005 bs",
    "addr:street":"Roerstraat;Gelderland",
    "iso:country":"NL",
    "sg:address":"Roerstraat 15",
    "sg:city":"Doetinchem",
    "sg:orig_category":"Metaalafval, Schrootrecycling And Sloperijen",
    "sg:phone":"+31 314 330 656",
    "sg:postcode":"7005 BS",
    "sg:province":"Gelderland",
    "wof:name":"Autosloperij Van Haarlem Doetinchem Bv",
    "wof:placetype":"venue"
},
  "geometry": {"coordinates":[6.298801,51.946033],"type":"Point"}
}