{
  "type": "Feature",
  "properties": {
    "iso:country":"NL",
    "sg:address":"Burgemeester Cremerspln 13",
    "sg:city":"Pannerden",
    "sg:orig_category":"Metaalwerken",
    "sg:phone":"+31 316 371 617",
    "sg:postcode":"6911 KT",
    "sg:province":"Gelderland",
    "wof:name":"Vof Eurozon",
    "wof:placetype":"venue"
},
  "geometry": {"coordinates":[6.038045,51.893562],"type":"Point"}
}