{
  "type": "Feature",
  "properties": {
    "addr:full":"Lauwersstr 54 Groningen Groningen 9725 HH",
    "addr:housenumber":"54",
    "addr:postcode":"9725 hh",
    "addr:street":"Lauwersstr",
    "iso:country":"NL",
    "sg:address":"Lauwersstr 54",
    "sg:city":"Groningen",
    "sg:orig_category":"Beeldende Kunstenaars",
    "sg:phone":"+31 50 527 3578",
    "sg:postcode":"9725 HH",
    "sg:province":"Groningen",
    "sg:website":"http://www.jeanetmetselaar.nl",
    "wof:name":"Metselaar Sieraden Jeanet",
    "wof:placetype":"venue"
},
  "geometry": {"coordinates":[6.565382,53.204929],"type":"Point"}
}