{
  "type": "Feature",
  "properties": {
    "addr:full":"Stelmakerstr 9 Assen Drenthe 9403 VB",
    "addr:housenumber":"9",
    "addr:postcode":"9403 vb",
    "addr:street":"Stelmakerstr",
    "iso:country":"NL",
    "sg:address":"Stelmakerstr 9",
    "sg:city":"Assen",
    "sg:orig_category":"Wegenbouw",
    "sg:phone":"+31 592 372 952",
    "sg:postcode":"9403 VB",
    "sg:province":"Drenthe",
    "wof:name":"Steeg En Zoon, Van Der",
    "wof:placetype":"venue"
},
  "geometry": {"coordinates":[6.584373951,53.0106124878],"type":"Point"}
}