{
  "type": "Feature",
  "properties": {
    "iso:country":"NL",
    "sg:address":"Paaptilsterwg 21",
    "sg:city":"Uithuizermeeden",
    "sg:orig_category":"Pluimveebedrijven En -Handelaren",
    "sg:phone":"+31 595 464 548",
    "sg:postcode":"9982 XP",
    "sg:province":"Groningen",
    "wof:name":"Visscher-Keppel",
    "wof:placetype":"venue"
},
  "geometry": {"coordinates":[6.728304,53.400265],"type":"Point"}
}