{
  "type": "Feature",
  "properties": {
    "addr:full":"Tulpstr 25 Heerlen Limburg 6414 RB",
    "addr:housenumber":"25",
    "addr:postcode":"6414 rb",
    "addr:street":"Tulpstr",
    "iso:country":"NL",
    "sg:address":"Tulpstr 25",
    "sg:city":"Heerlen",
    "sg:orig_category":"Verhuizingen",
    "sg:phone":"+31 45 522 8564",
    "sg:postcode":"6414 RB",
    "sg:province":"Limburg",
    "sg:website":"http://www.wiermans.nl",
    "wof:name":"Frans Wiermans",
    "wof:placetype":"venue"
},
  "geometry": {"coordinates":[5.9644,50.924755],"type":"Point"}
}