{
  "type": "Feature",
  "properties": {
    "iso:country":"NL",
    "sg:address":"Postbus 175",
    "sg:city":"Drachten",
    "sg:classifiers":[
        {
            "category":"Professional",
            "subcategory":"Accounting & Tax Preparation",
            "type":"Services"
        }
    ],
    "sg:phone":"+31 512 514 887",
    "sg:postcode":"9200 AD",
    "sg:province":"Friesland",
    "sg:tags":[
        "accountant",
        "en",
        "-kantoren",
        "register-"
    ],
    "sg:website":"http://www.kromhout.com",
    "wof:name":"Veen & Kromhout, Van Der",
    "wof:placetype":"venue"
},
  "geometry": {"coordinates":[6.09005,53.10788],"type":"Point"}
}