{
  "type": "Feature",
  "properties": {
    "addr:full":"Zuideinde 222 Westzaan Noord-Holland 1551 EN",
    "addr:housenumber":"222",
    "addr:postcode":"1551 en",
    "addr:street":"Zuideinde",
    "iso:country":"NL",
    "sg:address":"Zuideinde 222",
    "sg:city":"Westzaan",
    "sg:orig_category":"Pluimveehouderijen",
    "sg:phone":"+31 75 616 0635",
    "sg:postcode":"1551 EN",
    "sg:province":"Noord-Holland",
    "wof:name":"G. De Boer",
    "wof:placetype":"venue"
},
  "geometry": {"coordinates":[4.778089,52.441841],"type":"Point"}
}