{
  "type": "Feature",
  "properties": {
    "iso:country":"NL",
    "sg:address":"Langeleegte 179",
    "sg:city":"Veendam",
    "sg:orig_category":"Schilderwerk",
    "sg:phone":"+31 598 626 380",
    "sg:postcode":"9641 GX",
    "sg:province":"Groningen",
    "wof:name":"Willy Deuze Schilders- En Behangersbedrijf",
    "wof:placetype":"venue"
},
  "geometry": {"coordinates":[6.845452,53.107822],"type":"Point"}
}