{
  "type": "Feature",
  "properties": {
    "addr:full":"Heemraadstraat 30B Rotterdam Zuid-Holland 3023 VG",
    "addr:housenumber":"30b",
    "addr:postcode":"3023 vg",
    "addr:street":"Heemraadstraat",
    "iso:country":"NL",
    "sg:address":"Heemraadstraat 30B",
    "sg:city":"Rotterdam",
    "sg:orig_category":"Drukkerijen And Copyshops",
    "sg:phone":"+31 10 425 3060",
    "sg:postcode":"3023 VG",
    "sg:province":"Zuid-Holland",
    "wof:name":"Drukkerij Van Biert",
    "wof:placetype":"venue"
},
  "geometry": {"coordinates":[4.452341,51.912422],"type":"Point"}
}