{
  "type": "Feature",
  "properties": {
    "iso:country":"NL",
    "sg:address":"Johan Willem Frisostraat 12",
    "sg:city":"Sneek",
    "sg:orig_category":"Kappers",
    "sg:phone":"+31 515 414 878",
    "sg:postcode":"8606 CV",
    "sg:province":"Friesland",
    "wof:name":"De Knipperij Voor Hem & Haar",
    "wof:placetype":"venue"
},
  "geometry": {"coordinates":[5.6652951241,53.029838562],"type":"Point"}
}