{
  "type": "Feature",
  "properties": {
    "addr:full":"Markt 10 Papendrecht South Holland 3351 PB",
    "addr:housenumber":"10",
    "addr:postcode":"3351 pb",
    "addr:street":"Markt",
    "iso:country":"NL",
    "sg:address":"Markt 10",
    "sg:city":"Papendrecht",
    "sg:orig_category":"Kappers",
    "sg:phone":"+31 78 615 8304",
    "sg:postcode":"3351 PB",
    "sg:province":"South Holland",
    "wof:name":"Hairstyling Huib Zanen",
    "wof:placetype":"venue"
},
  "geometry": {"coordinates":[4.6832799911,51.8266105652],"type":"Point"}
}