{
  "type": "Feature",
  "properties": {
    "addr:full":"Oosterweg 115 Wijchen Gelderland 6602 HK",
    "addr:housenumber":"115",
    "addr:postcode":"6602 hk",
    "addr:street":"Oosterweg;Gelderland",
    "iso:country":"NL",
    "sg:address":"Oosterweg 115",
    "sg:city":"Wijchen",
    "sg:orig_category":"Architecten",
    "sg:phone":"+31 24 641 4429",
    "sg:postcode":"6602 HK",
    "sg:province":"Gelderland",
    "wof:name":"Theo Binnendijk Architekt",
    "wof:placetype":"venue"
},
  "geometry": {"coordinates":[5.729318,51.805779],"type":"Point"}
}