{
  "type": "Feature",
  "properties": {
    "addr:full":"Herenwg 46 Donkerbroek Friesland 8435 WV",
    "addr:housenumber":"46",
    "addr:postcode":"8435 wv",
    "addr:street":"Herenwg",
    "iso:country":"NL",
    "sg:address":"Herenwg 46",
    "sg:city":"Donkerbroek",
    "sg:orig_category":"Banken",
    "sg:phone":"+31 516 438 343",
    "sg:postcode":"8435 WV",
    "sg:province":"Friesland",
    "sg:website":"http://www.rabobank.nl",
    "wof:name":"Rabobank",
    "wof:placetype":"venue"
},
  "geometry": {"coordinates":[-80.181808,38.920101],"type":"Point"}
}