{
  "type": "Feature",
  "properties": {
    "addr:full":"Voorstraat 13 Stavoren Friesland 8715 HW",
    "addr:housenumber":"13",
    "addr:postcode":"8715 hw",
    "addr:street":"Voorstraat",
    "iso:country":"NL",
    "sg:address":"Voorstraat 13",
    "sg:city":"Stavoren",
    "sg:orig_category":"Keramische Producten Fab",
    "sg:phone":"+31 514 681 978",
    "sg:postcode":"8715 HW",
    "sg:province":"Friesland",
    "wof:name":"Atelier Basalt",
    "wof:placetype":"venue"
},
  "geometry": {"coordinates":[5.359041,52.883911],"type":"Point"}
}