{
  "type": "Feature",
  "properties": {
    "addr:full":"F H Van Kempenstraat 10 Montfoort Utrecht 3417 WT",
    "addr:housenumber":"10",
    "addr:postcode":"3417 wt",
    "addr:street":"F H Van Kempenstraat",
    "iso:country":"NL",
    "sg:address":"F H Van Kempenstraat 10",
    "sg:city":"Montfoort",
    "sg:orig_category":"Technische Studies And Onderzoek",
    "sg:phone":"+31 348 473 751",
    "sg:postcode":"3417 WT",
    "sg:province":"Utrecht",
    "wof:name":"Landmark Consultancy",
    "wof:placetype":"venue"
},
  "geometry": {"coordinates":[4.955575,52.038548],"type":"Point"}
}