{
  "type": "Feature",
  "properties": {
    "addr:full":"Iepenlaan 12 Alkmaar North Holland 1815 EE",
    "addr:housenumber":"12",
    "addr:postcode":"1815 ee",
    "addr:street":"Iepenlaan",
    "iso:country":"NL",
    "sg:address":"Iepenlaan 12",
    "sg:city":"Alkmaar",
    "sg:orig_category":"Loodgieterswerk, Verwarming And Sanitaire Installaties",
    "sg:phone":"+31 72 515 2041",
    "sg:postcode":"1815 EE",
    "sg:province":"North Holland",
    "wof:name":"Firma T. Richardson",
    "wof:placetype":"venue"
},
  "geometry": {"coordinates":[4.730456,52.63131],"type":"Point"}
}