{
  "type": "Feature",
  "properties": {
    "iso:country":"NL",
    "sg:address":"Iepenlaan 12",
    "sg:city":"Alkmaar",
    "sg:orig_category":"Loodgieterswerk, Verwarming And Sanitaire Installaties",
    "sg:phone":"+31 72 515 2041",
    "sg:postcode":"1815 EE",
    "sg:province":"North Holland",
    "wof:name":"Firma T. Richardson",
    "wof:placetype":"venue"
},
  "geometry": {"coordinates":[4.730456,52.63131],"type":"Point"}
}