{
  "type": "Feature",
  "properties": {
    "addr:full":"Hengelosestraat 10 Oldenzaal NL.08 7572 BP",
    "addr:housenumber":"10;nl.08",
    "addr:postcode":"7572 bp",
    "addr:street":"Hengelosestraat",
    "iso:country":"NL",
    "sg:address":"Hengelosestraat 10",
    "sg:city":"Oldenzaal",
    "sg:orig_category":"Kunst And Kunstenaarsbenodigdheden",
    "sg:phone":"+31 6 22764151",
    "sg:postcode":"7572 BP",
    "sg:province":"NL.08",
    "wof:name":"House Of Stone",
    "wof:placetype":"venue"
},
  "geometry": {"coordinates":[6.923697,52.311462],"type":"Point"}
}