{
  "type": "Feature",
  "properties": {
    "addr:full":"Markt 6 Dedemsvaart Overijssel 7701 GV",
    "addr:housenumber":"6",
    "addr:postcode":"7701 gv",
    "addr:street":"Markt",
    "iso:country":"NL",
    "sg:address":"Markt 6",
    "sg:city":"Dedemsvaart",
    "sg:orig_category":"Krantenuitgeverijen",
    "sg:phone":"+31 523 612 804",
    "sg:postcode":"7701 GV",
    "sg:province":"Overijssel",
    "wof:name":"Uitgeverij Mercator",
    "wof:placetype":"venue"
},
  "geometry": {"coordinates":[6.455874,52.599987],"type":"Point"}
}