{
  "type": "Feature",
  "properties": {
    "addr:full":"Nassaukade 16 Amsterdam Noord-Holland 1052 CG",
    "addr:housenumber":"16",
    "addr:postcode":"1052 cg",
    "addr:street":"Nassaukade",
    "iso:country":"NL",
    "sg:address":"Nassaukade 16",
    "sg:city":"Amsterdam",
    "sg:orig_category":"Bedrijfs- And Managementsconsultants",
    "sg:phone":"+31 20 684 3947",
    "sg:postcode":"1052 CG",
    "sg:province":"Noord-Holland",
    "wof:name":"Pommeline Promotions Int. Guestmanagemen",
    "wof:placetype":"venue"
},
  "geometry": {"coordinates":[4.880799,52.383896],"type":"Point"}
}