{
  "type": "Feature",
  "properties": {
    "addr:full":"Dr Jan Van Den Tempelln 18 Willemstad Nb Noord-Brabant 4797 CE",
    "addr:housenumber":"18",
    "addr:postcode":"4797 ce",
    "addr:street":"Dr Jan Van Den Tempelln",
    "iso:country":"NL",
    "sg:address":"Dr Jan Van Den Tempelln 18",
    "sg:city":"Willemstad Nb",
    "sg:orig_category":"Wegen And Sportterreinen",
    "sg:phone":"+31 168 472 091",
    "sg:postcode":"4797 CE",
    "sg:province":"Noord-Brabant",
    "wof:name":"M A Vd Stratenmakersbedrijf Cingel",
    "wof:placetype":"venue"
},
  "geometry": {"coordinates":[4.4393568039,51.6870384216],"type":"Point"}
}