{
  "type": "Feature",
  "properties": {
    "addr:full":"Scheepmakershaven 6 Oud Beyerland South Holland 3261 KN",
    "addr:housenumber":"6",
    "addr:postcode":"3261 kn",
    "addr:street":"Scheepmakershaven;Oud Beyerland",
    "iso:country":"NL",
    "sg:address":"Scheepmakershaven 6",
    "sg:city":"Oud Beyerland",
    "sg:orig_category":"Politie",
    "sg:phone":"+31 900 8844",
    "sg:postcode":"3261 KN",
    "sg:province":"South Holland",
    "wof:name":"Politie",
    "wof:placetype":"venue"
},
  "geometry": {"coordinates":[4.414605,51.826805],"type":"Point"}
}