{
  "type": "Feature",
  "properties": {
    "addr:full":"Buikslotermeerplein 430 Amsterdam North Holland 1025 WP",
    "addr:housenumber":"430",
    "addr:postcode":"1025 wp",
    "addr:street":"Buikslotermeerplein",
    "iso:country":"NL",
    "sg:address":"Buikslotermeerplein 430",
    "sg:city":"Amsterdam",
    "sg:orig_category":"Werving And Selectie Van Tijdelijk Personeel And Uitzendkantoren",
    "sg:phone":"+31 20 494 0974",
    "sg:postcode":"1025 WP",
    "sg:province":"North Holland",
    "wof:name":"Content",
    "wof:placetype":"venue"
},
  "geometry": {"coordinates":[4.941614151,52.3978462219],"type":"Point"}
}