{
  "type": "Feature",
  "properties": {
    "addr:full":"Oosterstr 28 Nieuwegein Utrecht 3434 BZ",
    "addr:housenumber":"28",
    "addr:postcode":"3434 bz",
    "addr:street":"Oosterstr",
    "iso:country":"NL",
    "sg:address":"Oosterstr 28",
    "sg:city":"Nieuwegein",
    "sg:orig_category":"Kinderhuizen",
    "sg:phone":"+31 30 606 3981",
    "sg:postcode":"3434 BZ",
    "sg:province":"Utrecht",
    "wof:name":"Meerwijck Ama, Sticht",
    "wof:placetype":"venue"
},
  "geometry": {"coordinates":[5.091931,52.00967],"type":"Point"}
}