{
  "type": "Feature",
  "properties": {
    "addr:full":"Spaarnwouderstr 96 Haarlem Noord-Holland 2011 AG",
    "addr:housenumber":"96",
    "addr:postcode":"2011",
    "addr:street":"Spaarnwouderstr",
    "iso:country":"NL",
    "sg:address":"Spaarnwouderstr 96",
    "sg:city":"Haarlem",
    "sg:orig_category":"Geluidsinstallaties - Verhuur",
    "sg:phone":"+31 23 533 6912",
    "sg:postcode":"2011 AG",
    "sg:province":"Noord-Holland",
    "wof:name":"Loek Kiekens",
    "wof:placetype":"venue"
},
  "geometry": {"coordinates":[4.644222,52.38007],"type":"Point"}
}