{
  "type": "Feature",
  "properties": {
    "addr:full":"Logtenburg 6A Prinsenbeek Noord-Brabant 4841 PA",
    "addr:housenumber":"6a",
    "addr:postcode":"4841 pa",
    "addr:street":"Logtenburg",
    "iso:country":"NL",
    "sg:address":"Logtenburg 6A",
    "sg:city":"Prinsenbeek",
    "sg:orig_category":"Adviesbureaus Bedrijfsveiligheid",
    "sg:phone":"+31 76 520 4999",
    "sg:postcode":"4841 PA",
    "sg:province":"Noord-Brabant",
    "wof:name":"Aoc Snijders Bv",
    "wof:placetype":"venue"
},
  "geometry": {"coordinates":[4.705584,51.606354],"type":"Point"}
}