{
  "type": "Feature",
  "properties": {
    "addr:full":"Bovensteweg 56 Mook Limburg 6585 KD",
    "addr:housenumber":"56",
    "addr:postcode":"6585 kd",
    "addr:street":"Bovensteweg",
    "iso:country":"NL",
    "sg:address":"Bovensteweg 56",
    "sg:city":"Mook",
    "sg:orig_category":"Metaalbekleding And -Behandeling",
    "sg:phone":"+31 24 696 2041",
    "sg:postcode":"6585 KD",
    "sg:province":"Limburg",
    "wof:name":"Verzinkerij Mook Bv",
    "wof:placetype":"venue"
},
  "geometry": {"coordinates":[5.884345,51.749493],"type":"Point"}
}