{
  "type": "Feature",
  "properties": {
    "addr:full":"Beethovenstraat 84 Amsterdam Noord-Holland 1077 JN",
    "addr:housenumber":"84",
    "addr:postcode":"1077 jn",
    "addr:street":"Beethovenstraat",
    "iso:country":"NL",
    "sg:address":"Beethovenstraat 84",
    "sg:city":"Amsterdam",
    "sg:orig_category":"Hypotheken And Hypotheekbanken",
    "sg:phone":"+31 20 471 4204",
    "sg:postcode":"1077 JN",
    "sg:province":"Noord-Holland",
    "wof:name":"Holland Huis Financiele Diensten",
    "wof:placetype":"venue"
},
  "geometry": {"coordinates":[4.876716,52.347397],"type":"Point"}
}