{
  "type": "Feature",
  "properties": {
    "iso:country":"NL",
    "sg:address":"Past Sickingstr 7",
    "sg:city":"Eindhoven",
    "sg:orig_category":"Boekhandels",
    "sg:phone":"+31 40 238 0275",
    "sg:postcode":"5614 HV",
    "sg:province":"Noord-Brabant",
    "sg:website":"http://www.gianotten.nl",
    "wof:name":"Gianotten Hbo Opleiding Service",
    "wof:placetype":"venue"
},
  "geometry": {"coordinates":[5.488064,51.428333],"type":"Point"}
}