{
  "type": "Feature",
  "properties": {
    "addr:full":"Vasco Da Gamalaan 21 Utrecht Utrecht 3526 ER",
    "addr:housenumber":"21",
    "addr:postcode":"3526 er",
    "addr:street":"Vasco Da Gamalaan",
    "iso:country":"NL",
    "sg:address":"Vasco Da Gamalaan 21",
    "sg:city":"Utrecht",
    "sg:orig_category":"Schoenen",
    "sg:phone":"+31 30 288 2659",
    "sg:postcode":"3526 ER",
    "sg:province":"Utrecht",
    "wof:name":"De Brabander",
    "wof:placetype":"venue"
},
  "geometry": {"coordinates":[5.098626,52.066669],"type":"Point"}
}