{
  "type": "Feature",
  "properties": {
    "addr:full":"Rozenstr 14 Meppel Drenthe 7943 AK",
    "addr:housenumber":"14",
    "addr:postcode":"7943 ak",
    "addr:street":"Rozenstr",
    "iso:country":"NL",
    "sg:address":"Rozenstr 14",
    "sg:city":"Meppel",
    "sg:orig_category":"Horloges En Klokken - Reparatie En Onderhoud",
    "sg:phone":"+31 522 262 159",
    "sg:postcode":"7943 AK",
    "sg:province":"Drenthe",
    "wof:name":"Wijk, W V J Van De",
    "wof:placetype":"venue"
},
  "geometry": {"coordinates":[6.201128,52.692261],"type":"Point"}
}