{
  "type": "Feature",
  "properties": {
    "addr:full":"Poldermolen 47 Bergschenhoek Zuid-Holland 2661 LB",
    "addr:housenumber":"47",
    "addr:postcode":"2661 lb",
    "addr:street":"Poldermolen",
    "iso:country":"NL",
    "sg:address":"Poldermolen 47",
    "sg:city":"Bergschenhoek",
    "sg:orig_category":"Vertaal- And Tolkenbureaus",
    "sg:phone":"+31 10 529 0871",
    "sg:postcode":"2661 LB",
    "sg:province":"Zuid-Holland",
    "wof:name":"Tdvs",
    "wof:placetype":"venue"
},
  "geometry": {"coordinates":[4.501786,51.99065],"type":"Point"}
}