{
  "type": "Feature",
  "properties": {
    "addr:full":"J Vd Grintenstr 23 Tilburg Noord-Brabant 5042 NH",
    "addr:housenumber":"23",
    "addr:postcode":"5042 nh",
    "iso:country":"NL",
    "sg:address":"J Vd Grintenstr 23",
    "sg:city":"Tilburg",
    "sg:orig_category":"Juridische Adviseurs",
    "sg:phone":"+31 13 467 5042",
    "sg:postcode":"5042 NH",
    "sg:province":"Noord-Brabant",
    "wof:name":"Oudheusden, H J C Van",
    "wof:placetype":"venue"
},
  "geometry": {"coordinates":[5.056203,51.568569],"type":"Point"}
}