{
  "type": "Feature",
  "properties": {
    "addr:full":"K Hasselaarstr 381 Vlissingen Zeeland 4382 AJ",
    "addr:housenumber":"381",
    "addr:postcode":"4382 aj",
    "iso:country":"NL",
    "sg:address":"K Hasselaarstr 381",
    "sg:city":"Vlissingen",
    "sg:orig_category":"Jachthavens - Jachtwerven",
    "sg:phone":"+31 118 440 125",
    "sg:postcode":"4382 AJ",
    "sg:province":"Zeeland",
    "wof:name":"Marina Veere Bv",
    "wof:placetype":"venue"
},
  "geometry": {"coordinates":[3.56181,51.448399],"type":"Point"}
}