{
  "type": "Feature",
  "properties": {
    "addr:full":"Amsterdamstr 38 Haarlem Noord-Holland 2032 PR",
    "addr:housenumber":"38",
    "addr:postcode":"2032 pr",
    "addr:street":"Amsterdamstr",
    "iso:country":"NL",
    "sg:address":"Amsterdamstr 38",
    "sg:city":"Haarlem",
    "sg:classifiers":[
        {
            "category":"Food & Beverages",
            "subcategory":"Bakery",
            "type":"Retail Goods"
        }
    ],
    "sg:phone":"+31 23 540 6925",
    "sg:postcode":"2032 PR",
    "sg:province":"Noord-Holland",
    "sg:tags":[
        "pizza"
    ],
    "wof:name":"Snelly",
    "wof:placetype":"venue"
},
  "geometry": {"coordinates":[4.647647,52.379036],"type":"Point"}
}