{
  "type": "Feature",
  "properties": {
    "addr:full":"V Utrechtwg 71 Krimpen Ad Yssel South Holland 2921 LN",
    "addr:housenumber":"71;2921",
    "addr:postcode":"ln",
    "addr:street":"Yssel",
    "iso:country":"NL",
    "sg:address":"V Utrechtwg 71",
    "sg:city":"Krimpen Ad Yssel",
    "sg:orig_category":"Winkelinrichting",
    "sg:phone":"+31 180 520 391",
    "sg:postcode":"2921 LN",
    "sg:province":"South Holland",
    "sg:website":"http://www.kpw.nl",
    "wof:name":"Kpw International",
    "wof:placetype":"venue"
},
  "geometry": {"coordinates":[4.57310009,51.9099082947],"type":"Point"}
}