{
  "type": "Feature",
  "properties": {
    "addr:full":"Echelpoelweg 12 Weerselo NL.08 7595 KA",
    "addr:housenumber":"12;nl.08",
    "addr:postcode":"7595 ka",
    "addr:street":"Echelpoelweg",
    "iso:country":"NL",
    "sg:address":"Echelpoelweg 12",
    "sg:city":"Weerselo",
    "sg:orig_category":"Granen, Zaden And Diervoeders Gh",
    "sg:phone":"+31 541 662 292",
    "sg:postcode":"7595 KA",
    "sg:province":"NL.08",
    "wof:name":"G. Sonder",
    "wof:placetype":"venue"
},
  "geometry": {"coordinates":[6.85683,52.34597],"type":"Point"}
}