{
  "type": "Feature",
  "properties": {
    "addr:full":"Peizerweg 1 Bunne Provincie Drenthe 9496 PC",
    "addr:housenumber":"1",
    "addr:postcode":"9496 pc",
    "addr:street":"Peizerweg;Provincie Drenthe",
    "iso:country":"NL",
    "sg:address":"Peizerweg 1",
    "sg:city":"Bunne",
    "sg:orig_category":"Pleziervaartuigen And Reparatie",
    "sg:phone":"+31 50 309 4871",
    "sg:postcode":"9496 PC",
    "sg:province":"Provincie Drenthe",
    "wof:name":"Roel Nijdam Botenbouw",
    "wof:placetype":"venue"
},
  "geometry": {"coordinates":[6.533779,53.118294],"type":"Point"}
}