{
  "type": "Feature",
  "properties": {
    "addr:full":"Kielstraat 2 Maasbracht Limburg 6051 LT",
    "addr:housenumber":"2",
    "addr:postcode":"6051 lt",
    "addr:street":"Kielstraat",
    "iso:country":"NL",
    "sg:address":"Kielstraat 2",
    "sg:city":"Maasbracht",
    "sg:orig_category":"Verzekeringen",
    "sg:phone":"+31 475 465 458",
    "sg:postcode":"6051 LT",
    "sg:province":"Limburg",
    "wof:name":"Van Buggenum Assurantien A.C.M. Van Bugg",
    "wof:placetype":"venue"
},
  "geometry": {"coordinates":[5.879536,51.137913],"type":"Point"}
}