{
  "type": "Feature",
  "properties": {
    "addr:full":"Burg Godschalxstr 44 'S Hertogenbosch North Brabant 5236 AC",
    "addr:housenumber":"44",
    "addr:postcode":"5236 ac",
    "addr:street":"Burg;' S Hertogenbosch",
    "iso:country":"NL",
    "sg:address":"Burg Godschalxstr 44",
    "sg:city":"'S Hertogenbosch",
    "sg:orig_category":"Kappers",
    "sg:phone":"+31 73 645 0440",
    "sg:postcode":"5236 AC",
    "sg:province":"North Brabant",
    "wof:name":"Kapsalon Nico Hoepelman",
    "wof:placetype":"venue"
},
  "geometry": {"coordinates":[5.3256602287,51.7303924561],"type":"Point"}
}