{
  "type": "Feature",
  "properties": {
    "addr:full":"Europaln 2 Son Noord-Brabant 5691 EN",
    "addr:housenumber":"2",
    "addr:postcode":"5691 en",
    "addr:street":"Europaln",
    "iso:country":"NL",
    "sg:address":"Europaln 2",
    "sg:city":"Son",
    "sg:orig_category":"Adviesbureaus",
    "sg:phone":"+31 499 490 115",
    "sg:postcode":"5691 EN",
    "sg:province":"Noord-Brabant",
    "wof:name":"S & B Consult Bv",
    "wof:placetype":"venue"
},
  "geometry": {"coordinates":[-101.937622,35.189621],"type":"Point"}
}