{
  "type": "Feature",
  "properties": {
    "addr:full":"Fagotstr 22 Ryswyk Zh South Holland 2287 BD",
    "addr:housenumber":"22;zh",
    "addr:postcode":"2287 bd",
    "addr:street":"Fagotstr",
    "iso:country":"NL",
    "sg:address":"Fagotstr 22",
    "sg:city":"Ryswyk Zh",
    "sg:orig_category":"Medische Keuringen",
    "sg:phone":"+31 70 394 6324",
    "sg:postcode":"2287 BD",
    "sg:province":"South Holland",
    "wof:name":"Wijk, Dr L Van",
    "wof:placetype":"venue"
},
  "geometry": {"coordinates":[4.32436,52.037251],"type":"Point"}
}