{
  "type": "Feature",
  "properties": {
    "addr:full":"E G Balchstraat 32 Groningen Groningen 9728 WB",
    "addr:housenumber":"32",
    "addr:postcode":"9728 wb",
    "addr:street":"E G Balchstraat",
    "iso:country":"NL",
    "sg:address":"E G Balchstraat 32",
    "sg:city":"Groningen",
    "sg:orig_category":"Bedrijfs- And Managementsconsultants",
    "sg:phone":"+31 50 311 2425",
    "sg:postcode":"9728 WB",
    "sg:province":"Groningen",
    "wof:name":"Coop Nrd Nederlands Ergonomen Collectief Ua",
    "wof:placetype":"venue"
},
  "geometry": {"coordinates":[6.553356,53.188232],"type":"Point"}
}