{
  "type": "Feature",
  "properties": {
    "addr:full":"Karel Doormanstraat 32 Roermond Limburg 6045 EC",
    "addr:housenumber":"32",
    "addr:postcode":"6045 ec",
    "addr:street":"Karel Doormanstraat",
    "iso:country":"NL",
    "sg:address":"Karel Doormanstraat 32",
    "sg:city":"Roermond",
    "sg:orig_category":"Architecten",
    "sg:phone":"+31 475 328 905",
    "sg:postcode":"6045 EC",
    "sg:province":"Limburg",
    "wof:name":"A. Schreur",
    "wof:placetype":"venue"
},
  "geometry": {"coordinates":[6.002449,51.178955],"type":"Point"}
}