{
  "type": "Feature",
  "properties": {
    "addr:full":"Transportbaan 46 Winschoten Groningen 9672 BK",
    "addr:housenumber":"46",
    "addr:postcode":"9672 bk",
    "addr:street":"Transportbaan",
    "iso:country":"NL",
    "sg:address":"Transportbaan 46",
    "sg:city":"Winschoten",
    "sg:orig_category":"Autokeuringen",
    "sg:phone":"+31 597 424 000",
    "sg:postcode":"9672 BK",
    "sg:province":"Groningen",
    "wof:name":"Autotaalglas",
    "wof:placetype":"venue"
},
  "geometry": {"coordinates":[7.053151,53.148293],"type":"Point"}
}