{
  "type": "Feature",
  "properties": {
    "addr:full":"Gedempte Zuiderdiep 99 Groningen Groningen 9711 HD",
    "addr:housenumber":"99",
    "addr:postcode":"9711 hd",
    "addr:street":"Gedempte Zuiderdiep",
    "iso:country":"NL",
    "sg:address":"Gedempte Zuiderdiep 99",
    "sg:city":"Groningen",
    "sg:classifiers":[
        {
            "category":"Fast Food",
            "type":"Food & Drink"
        }
    ],
    "sg:phone":"+31 50 311 9566",
    "sg:postcode":"9711 HD",
    "sg:province":"Groningen",
    "sg:tags":[
        "afhaal",
        "restaurant"
    ],
    "wof:name":"Snackpoint",
    "wof:placetype":"venue"
},
  "geometry": {"coordinates":[6.564622879,53.2147445679],"type":"Point"}
}