{
  "type": "Feature",
  "properties": {
    "addr:full":"Gr Adaln 2 Nieuwegein Utrecht 3434 DC",
    "addr:housenumber":"2",
    "addr:postcode":"3434",
    "iso:country":"NL",
    "sg:address":"Gr Adaln 2",
    "sg:city":"Nieuwegein",
    "sg:orig_category":"Kantoor- En Secretariaatsservice",
    "sg:phone":"+31 30 601 8733",
    "sg:postcode":"3434 DC",
    "sg:province":"Utrecht",
    "wof:name":"Graaf, Fenny De",
    "wof:placetype":"venue"
},
  "geometry": {"coordinates":[5.0821971893,52.0273246765],"type":"Point"}
}