{
  "type": "Feature",
  "properties": {
    "addr:full":"Sjanghailaan 275 Rotterdam South Holland 3066 SJ",
    "addr:housenumber":"275",
    "addr:postcode":"3066",
    "addr:street":"Sjanghailaan",
    "iso:country":"NL",
    "sg:address":"Sjanghailaan 275",
    "sg:city":"Rotterdam",
    "sg:orig_category":"Kinderopvang Behalve Thuis",
    "sg:phone":"+31 10 455 4608",
    "sg:postcode":"3066 SJ",
    "sg:province":"South Holland",
    "wof:name":"Minie/Bso Oosterflank",
    "wof:placetype":"venue"
},
  "geometry": {"coordinates":[4.558287,51.939873],"type":"Point"}
}