{
  "type": "Feature",
  "properties": {
    "addr:full":"Strijenseweg 123 'S Gravendeel Zuid-Holland 3295 KP",
    "addr:housenumber":"123 ' s",
    "addr:postcode":"3295 kp",
    "addr:street":"Strijenseweg",
    "iso:country":"NL",
    "sg:address":"Strijenseweg 123",
    "sg:city":"'S Gravendeel",
    "sg:orig_category":"Technische Studies And Onderzoek",
    "sg:phone":"+31 78 673 3740",
    "sg:postcode":"3295 KP",
    "sg:province":"Zuid-Holland",
    "wof:name":"M.G.S. (Mol General Services)",
    "wof:placetype":"venue"
},
  "geometry": {"coordinates":[4.611562,51.76622],"type":"Point"}
}