{
  "type": "Feature",
  "properties": {
    "addr:full":"Burgemeester Wernerplein 1 Sint Oedenrode Noord-Brabant 5492 GD",
    "addr:housenumber":"1;oedenrode",
    "addr:postcode":"5492 gd",
    "addr:street":"Burgemeester Wernerplein",
    "iso:country":"NL",
    "sg:address":"Burgemeester Wernerplein 1",
    "sg:city":"Sint Oedenrode",
    "sg:orig_category":"Overheidsdiensten",
    "sg:phone":"+31 413 481 911",
    "sg:postcode":"5492 GD",
    "sg:province":"Noord-Brabant",
    "wof:name":"Gemeente Sint Oedenrode",
    "wof:placetype":"venue"
},
  "geometry": {"coordinates":[5.4607028961,51.5603942871],"type":"Point"}
}