{
  "type": "Feature",
  "properties": {
    "addr:full":"Lavendelstraat 37 Bergeyk North Brabant 5571 HM",
    "addr:housenumber":"37",
    "addr:postcode":"5571 hm",
    "addr:street":"Lavendelstraat",
    "iso:country":"NL",
    "sg:address":"Lavendelstraat 37",
    "sg:city":"Bergeyk",
    "sg:orig_category":"Wasserettes And Stomerijen",
    "sg:phone":"+31 497 574 686",
    "sg:postcode":"5571 HM",
    "sg:province":"North Brabant",
    "wof:name":"De Cleaning-Boetiek",
    "wof:placetype":"venue"
},
  "geometry": {"coordinates":[5.3564929962,51.3186950684],"type":"Point"}
}