{
  "type": "Feature",
  "properties": {
    "addr:full":"Westersingel 106 Rotterdam Zuid-Holland 3015 LD",
    "addr:housenumber":"106",
    "addr:postcode":"3015 ld",
    "addr:street":"Westersingel",
    "iso:country":"NL",
    "sg:address":"Westersingel 106",
    "sg:city":"Rotterdam",
    "sg:orig_category":"Advocaten And Juridische Adviseurs",
    "sg:phone":"+31 10 436 2800",
    "sg:postcode":"3015 LD",
    "sg:province":"Zuid-Holland",
    "wof:name":"Advocatenkantoor Ceelen Bosveld Van De Bos",
    "wof:placetype":"venue"
},
  "geometry": {"coordinates":[4.474563,51.914497],"type":"Point"}
}