{
  "type": "Feature",
  "properties": {
    "iso:country":"NL",
    "sg:address":"K Zandpad 17",
    "sg:city":"Lopikerkapel",
    "sg:orig_category":"Voegwerken",
    "sg:phone":"+31 348 552 813",
    "sg:postcode":"3412 KV",
    "sg:province":"Utrecht",
    "wof:name":"Elteren, J Van",
    "wof:placetype":"venue"
},
  "geometry": {"coordinates":[5.012609,51.982319],"type":"Point"}
}