{
  "type": "Feature",
  "properties": {
    "iso:country":"NL",
    "sg:address":"De Moriaan 9",
    "sg:city":"Oirschot",
    "sg:classifiers":[
        {
            "category":"Professional",
            "subcategory":"Accounting & Tax Preparation",
            "type":"Services"
        }
    ],
    "sg:phone":"+31 499 571 772",
    "sg:postcode":"5688 ER",
    "sg:province":"Noord-Brabant",
    "sg:tags":[
        "accountant"
    ],
    "wof:name":"Kab Accountants",
    "wof:placetype":"venue"
},
  "geometry": {"coordinates":[5.307517,51.502342],"type":"Point"}
}