{
  "type": "Feature",
  "properties": {
    "addr:full":"Hooiijzer 48 Oostzaan Noord-Holland 1511 KD",
    "addr:housenumber":"48",
    "addr:postcode":"1511 kd",
    "addr:street":"Hooiijzer",
    "iso:country":"NL",
    "sg:address":"Hooiijzer 48",
    "sg:city":"Oostzaan",
    "sg:classifiers":[
        {
            "category":"Bakery",
            "type":"Food & Drink"
        }
    ],
    "sg:phone":"+31 20 386 8844",
    "sg:postcode":"1511 KD",
    "sg:province":"Noord-Holland",
    "sg:tags":[
        "brood",
        "banket"
    ],
    "wof:name":"Vof Michael Raadschelders De Bezorgbakke",
    "wof:placetype":"venue"
},
  "geometry": {"coordinates":[4.873346,52.433228],"type":"Point"}
}