{
  "type": "Feature",
  "properties": {
    "iso:country":"NL",
    "sg:address":"Past Ohlln 15",
    "sg:city":"Vleuten",
    "sg:orig_category":"Bloemen En Planten",
    "sg:phone":"+31 30 677 1733",
    "sg:postcode":"3451 CB",
    "sg:province":"Utrecht",
    "wof:name":"Floraville",
    "wof:placetype":"venue"
},
  "geometry": {"coordinates":[5.012663,52.104889],"type":"Point"}
}