{
  "type": "Feature",
  "properties": {
    "addr:full":"Dorpsstraat 57 Aarlanderveen Zuid-Holland 2445 AK",
    "addr:housenumber":"57",
    "addr:postcode":"2445 ak",
    "addr:street":"Dorpsstraat",
    "iso:country":"NL",
    "sg:address":"Dorpsstraat 57",
    "sg:city":"Aarlanderveen",
    "sg:orig_category":"Zuivelproducten",
    "sg:phone":"+31 172 572 196",
    "sg:postcode":"2445 AK",
    "sg:province":"Zuid-Holland",
    "wof:name":"J.J.G. Van Den Berg",
    "wof:placetype":"venue"
},
  "geometry": {"coordinates":[4.72917,52.140663],"type":"Point"}
}