{
  "type": "Feature",
  "properties": {
    "addr:full":"Modemwg 9 Amersfoort Utrecht 3821 BS",
    "addr:housenumber":"9",
    "addr:postcode":"3821 bs",
    "addr:street":"Modemwg",
    "iso:country":"NL",
    "sg:address":"Modemwg 9",
    "sg:city":"Amersfoort",
    "sg:orig_category":"Verbouwingen",
    "sg:phone":"+31 33 477 9223",
    "sg:postcode":"3821 BS",
    "sg:province":"Utrecht",
    "sg:website":"http://www.concepta.nl",
    "wof:name":"Concepta Dienst Bv",
    "wof:placetype":"venue"
},
  "geometry": {"coordinates":[5.417992,52.172245],"type":"Point"}
}