{
  "type": "Feature",
  "properties": {
    "addr:full":"Nobelstraat 82 Brielle Zuid-Holland 3231 BD",
    "addr:housenumber":"82",
    "addr:postcode":"3231 bd",
    "addr:street":"Nobelstraat",
    "iso:country":"NL",
    "sg:address":"Nobelstraat 82",
    "sg:city":"Brielle",
    "sg:orig_category":"Binnenhuisarchitecten",
    "sg:phone":"+31 181 417 000",
    "sg:postcode":"3231 BD",
    "sg:province":"Zuid-Holland",
    "wof:name":"Binnenhuisarchitectuur Langeveld",
    "wof:placetype":"venue"
},
  "geometry": {"coordinates":[4.162258,51.900284],"type":"Point"}
}