{
  "type": "Feature",
  "properties": {
    "addr:full":"Viottakd 52 Dordrecht South Holland 3314 ES",
    "addr:housenumber":"52",
    "addr:postcode":"3314 es",
    "addr:street":"Viottakd",
    "iso:country":"NL",
    "sg:address":"Viottakd 52",
    "sg:city":"Dordrecht",
    "sg:orig_category":"Juridische Adviseurs",
    "sg:phone":"+31 78 613 7655",
    "sg:postcode":"3314 ES",
    "sg:province":"South Holland",
    "wof:name":"Rov",
    "wof:placetype":"venue"
},
  "geometry": {"coordinates":[4.656506,51.811916],"type":"Point"}
}