{
  "type": "Feature",
  "properties": {
    "addr:full":"Stationswg 22 Budel Schoot North Brabant 6023 AE",
    "addr:housenumber":"22",
    "addr:postcode":"6023 ae",
    "addr:street":"Stationswg",
    "iso:country":"NL",
    "sg:address":"Stationswg 22",
    "sg:city":"Budel Schoot",
    "sg:orig_category":"Begrafenisverzorging",
    "sg:phone":"+31 495 519 516",
    "sg:postcode":"6023 AE",
    "sg:province":"North Brabant",
    "wof:name":"Cranendonck",
    "wof:placetype":"venue"
},
  "geometry": {"coordinates":[5.565174,51.245308],"type":"Point"}
}