{
  "type": "Feature",
  "properties": {
    "addr:full":"Hazelaarwg 25 Rotterdam Zuid-Holland 3053 PM",
    "addr:housenumber":"25",
    "addr:postcode":"3053 pm",
    "addr:street":"Hazelaarwg",
    "iso:country":"NL",
    "sg:address":"Hazelaarwg 25",
    "sg:city":"Rotterdam",
    "sg:classifiers":[
        {
            "category":"Sports & Exercise",
            "subcategory":"Stables",
            "type":"Entertainment"
        }
    ],
    "sg:phone":"+31 10 418 1560",
    "sg:postcode":"3053 PM",
    "sg:province":"Zuid-Holland",
    "sg:tags":[
        "maneges"
    ],
    "wof:name":"Hazelaar, De",
    "wof:placetype":"venue"
},
  "geometry": {"coordinates":[4.480411,51.967854],"type":"Point"}
}