{
  "type": "Feature",
  "properties": {
    "iso:country":"NL",
    "sg:address":"Nieuwe Veer 65",
    "sg:city":"Streefkerk",
    "sg:orig_category":"Goederenvervoer Over De Weg",
    "sg:phone":"+31 184 681 266",
    "sg:postcode":"2959 AL",
    "sg:province":"South Holland",
    "wof:name":"Transportbedrijf Firma Eskes",
    "wof:placetype":"venue"
},
  "geometry": {"coordinates":[4.751251,51.906799],"type":"Point"}
}