{
  "type": "Feature",
  "properties": {
    "addr:full":"Kerkstraat 12 Noordwijk Zh Zuid-Holland 2201 KM",
    "addr:housenumber":"12",
    "addr:street":"Kerkstraat;2201 Km",
    "iso:country":"NL",
    "sg:address":"Kerkstraat 12",
    "sg:city":"Noordwijk Zh",
    "sg:classifiers":[
        {
            "category":"Bakery",
            "type":"Food & Drink"
        }
    ],
    "sg:phone":"+31 71 361 8643",
    "sg:postcode":"2201 KM",
    "sg:province":"Zuid-Holland",
    "sg:tags":[
        "brood",
        "banket"
    ],
    "wof:name":"Echte Bakker Van Maanen",
    "wof:placetype":"venue"
},
  "geometry": {"coordinates":[4.447072,52.234325],"type":"Point"}
}