{
  "type": "Feature",
  "properties": {
    "addr:full":"1E Middellandstr 91 Rotterdam South Holland 3021 BC",
    "addr:housenumber":"91",
    "addr:postcode":"3021 bc",
    "addr:street":"1E Middellandstr",
    "iso:country":"NL",
    "sg:address":"1E Middellandstr 91",
    "sg:city":"Rotterdam",
    "sg:orig_category":"Juweliers",
    "sg:phone":"+31 10 425 7016",
    "sg:postcode":"3021 BC",
    "sg:province":"South Holland",
    "wof:name":"Gotu Koloku",
    "wof:placetype":"venue"
},
  "geometry": {"coordinates":[4.461098,51.918785],"type":"Point"}
}