{
  "type": "Feature",
  "properties": {
    "addr:full":"Zuidstr 59 Westkapelle Zeeland 4361 AB",
    "addr:housenumber":"59",
    "addr:postcode":"4361 ab",
    "addr:street":"Zuidstr",
    "iso:country":"NL",
    "sg:address":"Zuidstr 59",
    "sg:city":"Westkapelle",
    "sg:orig_category":"Hengelsportartikelen",
    "sg:phone":"+31 118 571 580",
    "sg:postcode":"4361 AB",
    "sg:province":"Zeeland",
    "wof:name":"Melis, A",
    "wof:placetype":"venue"
},
  "geometry": {"coordinates":[3.442421,51.528019],"type":"Point"}
}