{
  "type": "Feature",
  "properties": {
    "addr:full":"Ln V Eikenrode 62 Loosdrecht Noord-Holland 1231 BR",
    "addr:housenumber":"62",
    "addr:postcode":"1231 br",
    "addr:street":"Ln V Eikenrode",
    "iso:country":"NL",
    "sg:address":"Ln V Eikenrode 62",
    "sg:city":"Loosdrecht",
    "sg:orig_category":"Verkoopautomaten",
    "sg:phone":"+31 35 582 8217",
    "sg:postcode":"1231 BR",
    "sg:province":"Noord-Holland",
    "wof:name":"Javako Bv",
    "wof:placetype":"venue"
},
  "geometry": {"coordinates":[5.081635,52.206875],"type":"Point"}
}