{
  "type": "Feature",
  "properties": {
    "iso:country":"NL",
    "sg:address":"Radeweg 27",
    "sg:city":"Vaassen",
    "sg:orig_category":"Feestartikelen",
    "sg:phone":"+31 578 576 016",
    "sg:postcode":"8171 MD",
    "sg:province":"Gelderland",
    "wof:name":"Vlagcorrector Bv",
    "wof:placetype":"venue"
},
  "geometry": {"coordinates":[5.985777,52.301357],"type":"Point"}
}