{
  "type": "Feature",
  "properties": {
    "addr:full":"Roestenbergstr 71 Kaatsheuvel North Brabant 5171 JB",
    "addr:housenumber":"71",
    "addr:postcode":"5171 jb",
    "addr:street":"Roestenbergstr",
    "iso:country":"NL",
    "sg:address":"Roestenbergstr 71",
    "sg:city":"Kaatsheuvel",
    "sg:classifiers":[
        {
            "category":"Bus Charters",
            "type":"Transportation"
        }
    ],
    "sg:phone":"+31 416 272 875",
    "sg:postcode":"5171 JB",
    "sg:province":"North Brabant",
    "sg:tags":[
        "caravan"
    ],
    "wof:name":"Slaats, C",
    "wof:placetype":"venue"
},
  "geometry": {"coordinates":[5.0428,51.662796],"type":"Point"}
}