{
  "type": "Feature",
  "properties": {
    "iso:country":"NL",
    "sg:address":"Canadalaan 2",
    "sg:city":"Sas Van Gent",
    "sg:classifiers":[
        {
            "category":"Education",
            "subcategory":"Preschool",
            "type":"Public Place"
        }
    ],
    "sg:phone":"+31 115 460 028",
    "sg:postcode":"4551 AL",
    "sg:province":"Zeeland",
    "sg:tags":[
        "kleuteronderwijs",
        "basis-"
    ],
    "wof:name":"Esdoornveste",
    "wof:placetype":"venue"
},
  "geometry": {"coordinates":[3.794403,51.22821],"type":"Point"}
}