{
  "type": "Feature",
  "properties": {
    "addr:full":"Walstr 16 Deventer NL.08 7411 GM",
    "addr:housenumber":"16;nl.08",
    "addr:postcode":"7411 gm",
    "addr:street":"Walstr",
    "iso:country":"NL",
    "sg:address":"Walstr 16",
    "sg:city":"Deventer",
    "sg:orig_category":"Binnenhuisarchitectuur",
    "sg:phone":"+31 570 612 379",
    "sg:postcode":"7411 GM",
    "sg:province":"NL.08",
    "wof:name":"Spall'S Traditionals, Van",
    "wof:placetype":"venue"
},
  "geometry": {"coordinates":[6.160957,52.25325],"type":"Point"}
}