{
  "type": "Feature",
  "properties": {
    "addr:full":"Sweelinckplein 80 'S Gravenhage South Holland 2517 GL",
    "addr:housenumber":"80",
    "addr:postcode":"2517 gl",
    "addr:street":"Sweelinckplein;' S Gravenhage",
    "iso:country":"NL",
    "sg:address":"Sweelinckplein 80",
    "sg:city":"'S Gravenhage",
    "sg:orig_category":"Verhuisdiensten",
    "sg:phone":"+31 70 346 7141",
    "sg:postcode":"2517 GL",
    "sg:province":"South Holland",
    "wof:name":"Int Verhuisond J J Janssen Nv",
    "wof:placetype":"venue"
},
  "geometry": {"coordinates":[4.286473,52.083591],"type":"Point"}
}