{
  "type": "Feature",
  "properties": {
    "addr:full":"Melissewg 81A Groningen Groningen 9731 BM",
    "addr:housenumber":"81a",
    "addr:postcode":"9731 bm",
    "addr:street":"Melissewg",
    "iso:country":"NL",
    "sg:address":"Melissewg 81A",
    "sg:city":"Groningen",
    "sg:orig_category":"Hijswerktuigen",
    "sg:phone":"+31 50 542 4411",
    "sg:postcode":"9731 BM",
    "sg:province":"Groningen",
    "wof:name":"Rodijco Van Den Berg Bros Bv",
    "wof:placetype":"venue"
},
  "geometry": {"coordinates":[6.592078,53.235035],"type":"Point"}
}