{
  "type": "Feature",
  "properties": {
    "addr:full":"Kieftskamp 26 Doetinchem Gelderland 7006 JH",
    "addr:housenumber":"26",
    "addr:postcode":"7006 jh",
    "addr:street":"Kieftskamp;Gelderland",
    "iso:country":"NL",
    "sg:address":"Kieftskamp 26",
    "sg:city":"Doetinchem",
    "sg:orig_category":"Administratie- En Boekhoudkantoren",
    "sg:phone":"+31 314 361 766",
    "sg:postcode":"7006 JH",
    "sg:province":"Gelderland",
    "wof:name":"Ando",
    "wof:placetype":"venue"
},
  "geometry": {"coordinates":[6.259394,51.966137],"type":"Point"}
}