{
  "type": "Feature",
  "properties": {
    "addr:full":"Randwg 102 Rotterdam Zuid-Holland 3074 BT",
    "addr:housenumber":"102",
    "addr:postcode":"3074 bt",
    "iso:country":"NL",
    "sg:address":"Randwg 102",
    "sg:city":"Rotterdam",
    "sg:orig_category":"Accountants - Administratie- Consulenten En -Kantoren",
    "sg:phone":"+31 10 432 4555",
    "sg:postcode":"3074 BT",
    "sg:province":"Zuid-Holland",
    "wof:name":"Geus Bv, L De",
    "wof:placetype":"venue"
},
  "geometry": {"coordinates":[4.513213,51.891777],"type":"Point"}
}