{
  "type": "Feature",
  "properties": {
    "addr:full":"Spaklerwg 75 Amsterdam North Holland 1099 BB",
    "addr:housenumber":"75",
    "addr:postcode":"1099 bb",
    "addr:street":"Spaklerwg",
    "iso:country":"NL",
    "sg:address":"Spaklerwg 75",
    "sg:city":"Amsterdam",
    "sg:orig_category":"Hoogwerkers",
    "sg:phone":"+31 20 665 4006",
    "sg:postcode":"1099 BB",
    "sg:province":"North Holland",
    "wof:name":"Huurland Bv",
    "wof:placetype":"venue"
},
  "geometry": {"coordinates":[4.921568,52.337257],"type":"Point"}
}