{
  "type": "Feature",
  "properties": {
    "iso:country":"NL",
    "sg:address":"Kleingraverstr 63",
    "sg:city":"Kerkrade",
    "sg:orig_category":"Schoenen",
    "sg:phone":"+31 45 541 3030",
    "sg:postcode":"6466 EB",
    "sg:province":"Limburg",
    "wof:name":"Luth",
    "wof:placetype":"venue"
},
  "geometry": {"coordinates":[6.034479,50.858723],"type":"Point"}
}