{
  "type": "Feature",
  "properties": {
    "iso:country":"NL",
    "sg:address":"Noordersingel 9",
    "sg:city":"Assen",
    "sg:orig_category":"Hypotheken And Hypotheekbanken",
    "sg:phone":"+31 592 319 122",
    "sg:postcode":"9401 JV",
    "sg:province":"Drenthe",
    "wof:name":"De Hypotheekshop",
    "wof:placetype":"venue"
},
  "geometry": {"coordinates":[6.564137,52.995125],"type":"Point"}
}