{
  "type": "Feature",
  "properties": {
    "addr:full":"Koning Lodewijklaan 554 Apeldoorn Gelderland 7314 GV",
    "addr:housenumber":"554",
    "addr:postcode":"7314 gv",
    "addr:street":"Koning Lodewijklaan;Gelderland",
    "iso:country":"NL",
    "sg:address":"Koning Lodewijklaan 554",
    "sg:city":"Apeldoorn",
    "sg:orig_category":"Artsen And Specialisten",
    "sg:phone":"+31 55 355 8575",
    "sg:postcode":"7314 GV",
    "sg:province":"Gelderland",
    "wof:name":"Drs. H. Piket",
    "wof:placetype":"venue"
},
  "geometry": {"coordinates":[5.946284,52.216698],"type":"Point"}
}