{
  "type": "Feature",
  "properties": {
    "iso:country":"NL",
    "sg:address":"Atmosfeerstraat 34",
    "sg:city":"Dordrecht",
    "sg:classifiers":[
        {
            "category":"Education",
            "subcategory":"Preschool",
            "type":"Public Place"
        }
    ],
    "sg:phone":"+31 78 618 1637",
    "sg:postcode":"3328 GD",
    "sg:province":"Zuid-Holland",
    "sg:tags":[
        "kleuteronderwijs",
        "basis-"
    ],
    "wof:name":"Ds. J. Polyanderschool",
    "wof:placetype":"venue"
},
  "geometry": {"coordinates":[4.677378,51.779312],"type":"Point"}
}