{
  "type": "Feature",
  "properties": {
    "iso:country":"NL",
    "sg:address":"Langstraat 54",
    "sg:city":"Achthuizen",
    "sg:orig_category":"Autokeuringen",
    "sg:phone":"+31 187 632 575",
    "sg:postcode":"3256 AM",
    "sg:province":"South Holland",
    "wof:name":"Enu",
    "wof:placetype":"venue"
},
  "geometry": {"coordinates":[4.280508,51.674355],"type":"Point"}
}