{
  "type": "Feature",
  "properties": {
    "addr:full":"Nassaustr 66 Roermond Limburg 6043 ED",
    "addr:housenumber":"66",
    "addr:postcode":"6043 ed",
    "addr:street":"Nassaustr",
    "iso:country":"NL",
    "sg:address":"Nassaustr 66",
    "sg:city":"Roermond",
    "sg:orig_category":"Bloemen En Planten",
    "sg:phone":"+31 475 316 824",
    "sg:postcode":"6043 ED",
    "sg:province":"Limburg",
    "wof:name":"Hermien",
    "wof:placetype":"venue"
},
  "geometry": {"coordinates":[5.998095,51.190022],"type":"Point"}
}