{
  "type": "Feature",
  "properties": {
    "iso:country":"NL",
    "sg:address":"Oosterhamrikkd 44",
    "sg:city":"Groningen",
    "sg:orig_category":"Fietsen En Bromfietsen",
    "sg:phone":"+31 50 573 0965",
    "sg:postcode":"9714 BD",
    "sg:province":"Groningen",
    "sg:website":"http://www.hermanvandermeulen.nl",
    "wof:name":"Herman Van Der Meulen",
    "wof:placetype":"venue"
},
  "geometry": {"coordinates":[6.578297,53.233578],"type":"Point"}
}