{
  "type": "Feature",
  "properties": {
    "addr:full":"Hogewg 27 Zandvoort North Holland 2042 GD",
    "addr:housenumber":"27",
    "addr:postcode":"2042 gd",
    "addr:street":"Hogewg",
    "iso:country":"NL",
    "sg:address":"Hogewg 27",
    "sg:city":"Zandvoort",
    "sg:orig_category":"Kappers",
    "sg:phone":"+31 23 571 6969",
    "sg:postcode":"2042 GD",
    "sg:province":"North Holland",
    "wof:name":"Mp",
    "wof:placetype":"venue"
},
  "geometry": {"coordinates":[4.526934,52.370941],"type":"Point"}
}