{
  "type": "Feature",
  "properties": {
    "addr:full":"Fazantenlaan 32 Egmond-Binnen Noord-Holland 1935 EE",
    "addr:housenumber":"32",
    "addr:postcode":"1935 ee",
    "addr:street":"Fazantenlaan",
    "iso:country":"NL",
    "sg:address":"Fazantenlaan 32",
    "sg:city":"Egmond-Binnen",
    "sg:orig_category":"Meubelreparatie And -Restauratie",
    "sg:phone":"+31 72 506 6153",
    "sg:postcode":"1935 EE",
    "sg:province":"Noord-Holland",
    "wof:name":"H.E.J. Jonker",
    "wof:placetype":"venue"
},
  "geometry": {"coordinates":[4.654566,52.597858],"type":"Point"}
}