{
  "type": "Feature",
  "properties": {
    "iso:country":"NL",
    "sg:address":"Fazantenlaan 32",
    "sg:city":"Egmond-Binnen",
    "sg:orig_category":"Meubelreparatie And -Restauratie",
    "sg:phone":"+31 72 506 6153",
    "sg:postcode":"1935 EE",
    "sg:province":"Noord-Holland",
    "wof:name":"H.E.J. Jonker",
    "wof:placetype":"venue"
},
  "geometry": {"coordinates":[4.654566,52.597858],"type":"Point"}
}