{
  "type": "Feature",
  "properties": {
    "addr:full":"Jasmynhof 16 Nootdorp Zuid-Holland 2631 JB",
    "addr:housenumber":"16",
    "addr:postcode":"2631 jb",
    "addr:street":"Jasmynhof",
    "iso:country":"NL",
    "sg:address":"Jasmynhof 16",
    "sg:city":"Nootdorp",
    "sg:orig_category":"Sanitaire Artikelen - Installatie En Onderhoud",
    "sg:phone":"+31 6 53188631",
    "sg:postcode":"2631 JB",
    "sg:province":"Zuid-Holland",
    "wof:name":"Bergh, Firma H Van Den",
    "wof:placetype":"venue"
},
  "geometry": {"coordinates":[4.40199,52.047905],"type":"Point"}
}