{
  "type": "Feature",
  "properties": {
    "iso:country":"NL",
    "sg:address":"Mynbouwpln 11",
    "sg:city":"Delft",
    "sg:orig_category":"Architecten En Architectenbureaus",
    "sg:phone":"+31 15 251 0049",
    "sg:postcode":"2628 RT",
    "sg:province":"Zuid-Holland",
    "wof:name":"Noorderlicht Bv",
    "wof:placetype":"venue"
},
  "geometry": {"coordinates":[4.367201,52.006405],"type":"Point"}
}