{
  "type": "Feature",
  "properties": {
    "addr:full":"Graafs Horneln 129 Weert Limburg 6001 AC",
    "addr:housenumber":"129",
    "addr:postcode":"6001 ac",
    "addr:street":"Weert Limburg",
    "iso:country":"NL",
    "sg:address":"Graafs Horneln 129",
    "sg:city":"Weert",
    "sg:orig_category":"Pompen - Verhuur",
    "sg:phone":"+31 495 521 956",
    "sg:postcode":"6001 AC",
    "sg:province":"Limburg",
    "wof:name":"Eekels Bv",
    "wof:placetype":"venue"
},
  "geometry": {"coordinates":[5.703781,51.255016],"type":"Point"}
}