{
  "type": "Feature",
  "properties": {
    "addr:full":"Rynstr 86 Amsterdam Noord-Holland 1079 HL",
    "addr:housenumber":"86",
    "addr:postcode":"1079 hl",
    "addr:street":"Rynstr",
    "iso:country":"NL",
    "sg:address":"Rynstr 86",
    "sg:city":"Amsterdam",
    "sg:orig_category":"Boeken En Tijdschriften",
    "sg:phone":"+31 20 646 0272",
    "sg:postcode":"1079 HL",
    "sg:province":"Noord-Holland",
    "wof:name":"Paperback",
    "wof:placetype":"venue"
},
  "geometry": {"coordinates":[4.89319,52.373119],"type":"Point"}
}