{
  "type": "Feature",
  "properties": {
    "addr:full":"Uelserwg 20 Tubbergen Overijssel 7651 KW",
    "addr:housenumber":"20",
    "addr:postcode":"7651 kw",
    "addr:street":"Uelserwg",
    "iso:country":"NL",
    "sg:address":"Uelserwg 20",
    "sg:city":"Tubbergen",
    "sg:orig_category":"Administratie- En Boekhoudkantoren",
    "sg:phone":"+31 546 621 879",
    "sg:postcode":"7651 KW",
    "sg:province":"Overijssel",
    "wof:name":"Boer, De",
    "wof:placetype":"venue"
},
  "geometry": {"coordinates":[6.783181,52.409527],"type":"Point"}
}