{
  "type": "Feature",
  "properties": {
    "addr:full":"Osdorper Ban 25C Amsterdam North Holland 1068 LD",
    "addr:housenumber":"25c",
    "addr:postcode":"1068 ld",
    "addr:street":"Osdorper Ban",
    "iso:country":"NL",
    "sg:address":"Osdorper Ban 25C",
    "sg:city":"Amsterdam",
    "sg:orig_category":"Accountants - Administratie- Consulenten En -Kantoren",
    "sg:phone":"+31 20 610 6636",
    "sg:postcode":"1068 LD",
    "sg:province":"North Holland",
    "wof:name":"Pol & Aalders, Van",
    "wof:placetype":"venue"
},
  "geometry": {"coordinates":[4.803888,52.362152],"type":"Point"}
}