{
  "type": "Feature",
  "properties": {
    "addr:full":"Maasstraat 188 Amsterdam North Holland 1079 BL",
    "addr:housenumber":"188",
    "addr:postcode":"1079 bl",
    "addr:street":"Maasstraat",
    "iso:country":"NL",
    "sg:address":"Maasstraat 188",
    "sg:city":"Amsterdam",
    "sg:orig_category":"Huishoudapparatuur, Televisies And Radio'S",
    "sg:phone":"+31 20 644 5131",
    "sg:postcode":"1079 BL",
    "sg:province":"North Holland",
    "wof:name":"Radio & T.V. Knapp",
    "wof:placetype":"venue"
},
  "geometry": {"coordinates":[4.897303,52.341511],"type":"Point"}
}