{
  "type": "Feature",
  "properties": {
    "addr:full":"Nijverheidsterrein 17 Ursem Noord-Holland 1645 VX",
    "addr:housenumber":"17",
    "addr:postcode":"1645 vx",
    "addr:street":"Nijverheidsterrein",
    "iso:country":"NL",
    "sg:address":"Nijverheidsterrein 17",
    "sg:city":"Ursem",
    "sg:orig_category":"Wegen And Sportterreinen",
    "sg:phone":"+31 72 502 3276",
    "sg:postcode":"1645 VX",
    "sg:province":"Noord-Holland",
    "wof:name":"Aannemingsmij. Gres Bv",
    "wof:placetype":"venue"
},
  "geometry": {"coordinates":[4.8930921555,52.6338310242],"type":"Point"}
}