{
  "type": "Feature",
  "properties": {
    "addr:full":"Maasstr 15 Ijmuiden Noord-Holland 1972 ZA",
    "addr:housenumber":"15",
    "addr:postcode":"1972",
    "addr:street":"Maasstr",
    "iso:country":"NL",
    "sg:address":"Maasstr 15",
    "sg:city":"Ijmuiden",
    "sg:orig_category":"Artsen - Huisartsen",
    "sg:phone":"+31 255 516 388",
    "sg:postcode":"1972 ZA",
    "sg:province":"Noord-Holland",
    "wof:name":"Wermenbol, R",
    "wof:placetype":"venue"
},
  "geometry": {"coordinates":[4.611235,52.454338],"type":"Point"}
}