{
  "type": "Feature",
  "properties": {
    "addr:full":"Langeweg 48 Middelharnis South Holland 3241 KA",
    "addr:housenumber":"48",
    "addr:postcode":"3241 ka",
    "addr:street":"Langeweg",
    "iso:country":"NL",
    "sg:address":"Langeweg 48",
    "sg:city":"Middelharnis",
    "sg:orig_category":"Overheidsdiensten",
    "sg:phone":"+31 187 486 309",
    "sg:postcode":"3241 KA",
    "sg:province":"South Holland",
    "wof:name":"Rk Jeugdgeb",
    "wof:placetype":"venue"
},
  "geometry": {"coordinates":[4.156047821,51.758430481],"type":"Point"}
}