{
  "type": "Feature",
  "properties": {
    "addr:full":"Nyverheidsstr 2 Huissen Gelderland 6851 EJ",
    "addr:housenumber":"2",
    "addr:postcode":"6851 ej",
    "addr:street":"Nyverheidsstr;Gelderland",
    "iso:country":"NL",
    "sg:address":"Nyverheidsstr 2",
    "sg:city":"Huissen",
    "sg:classifiers":[
        {
            "category":"Home & Garden",
            "subcategory":"Building Materials",
            "type":"Retail Goods"
        }
    ],
    "sg:phone":"+31 26 325 7215",
    "sg:postcode":"6851 EJ",
    "sg:province":"Gelderland",
    "sg:tags":[
        "hout",
        "en",
        "board",
        "triplex"
    ],
    "sg:website":"http://www.houtmarkt.com",
    "wof:name":"Scanabouw Houtmarkt Bv",
    "wof:placetype":"venue"
},
  "geometry": {"coordinates":[5.916618,51.91135],"type":"Point"}
}