{
  "type": "Feature",
  "properties": {
    "iso:country":"NL",
    "sg:address":"Wilgengaard 3",
    "sg:city":"Goirle",
    "sg:orig_category":"Public Relationbureaus",
    "sg:phone":"+31 13 530 2234",
    "sg:postcode":"5051 XT",
    "sg:province":"North Brabant",
    "wof:name":"R Van Der Meer",
    "wof:placetype":"venue"
},
  "geometry": {"coordinates":[5.051067,51.522194],"type":"Point"}
}