{
  "type": "Feature",
  "properties": {
    "addr:full":"Stadswg 24 Lauwerzyl Groningen 9885 PB",
    "addr:housenumber":"24",
    "addr:postcode":"9885 pb",
    "addr:street":"Stadswg",
    "iso:country":"NL",
    "sg:address":"Stadswg 24",
    "sg:city":"Lauwerzyl",
    "sg:orig_category":"Wegenbouw",
    "sg:phone":"+31 594 688 202",
    "sg:postcode":"9885 PB",
    "sg:province":"Groningen",
    "wof:name":"Roorda & Zn, Fa P H",
    "wof:placetype":"venue"
},
  "geometry": {"coordinates":[6.2964978218,53.3106193542],"type":"Point"}
}