{
  "type": "Feature",
  "properties": {
    "addr:full":"Kanaalstr 7 Oosterhout Nb Noord-Brabant 4905 BH",
    "addr:housenumber":"7",
    "addr:postcode":"4905 bh",
    "addr:street":"Kanaalstr",
    "iso:country":"NL",
    "sg:address":"Kanaalstr 7",
    "sg:city":"Oosterhout Nb",
    "sg:orig_category":"Machinefabrieken",
    "sg:phone":"+31 162 454 935",
    "sg:postcode":"4905 BH",
    "sg:province":"Noord-Brabant",
    "wof:name":"Bonnier & Louwerse Bv",
    "wof:placetype":"venue"
},
  "geometry": {"coordinates":[4.849208,51.647186],"type":"Point"}
}