{
  "type": "Feature",
  "properties": {
    "addr:full":"De Vlinderhoven 43 Schiedam South Holland 3124 BR",
    "addr:housenumber":"43",
    "addr:postcode":"3124 br",
    "addr:street":"De Vlinderhoven",
    "iso:country":"NL",
    "sg:address":"De Vlinderhoven 43",
    "sg:city":"Schiedam",
    "sg:orig_category":"Honden- En Kattentrimsalons",
    "sg:phone":"+31 10 470 0119",
    "sg:postcode":"3124 BR",
    "sg:province":"South Holland",
    "wof:name":"Kleine Honden",
    "wof:placetype":"venue"
},
  "geometry": {"coordinates":[4.37964,51.941547],"type":"Point"}
}