{
  "type": "Feature",
  "properties": {
    "iso:country":"NL",
    "sg:address":"Voorhaven 21",
    "sg:city":"Rotterdam",
    "sg:orig_category":"Artiesten/Gezelschappen",
    "sg:phone":"+31 10 244 0968",
    "sg:postcode":"3025 HC",
    "sg:province":"Zuid-Holland",
    "sg:website":"http://www.rogie-company.nl",
    "wof:name":"Rogie & Company",
    "wof:placetype":"venue"
},
  "geometry": {"coordinates":[4.447892,51.907845],"type":"Point"}
}