{
  "type": "Feature",
  "properties": {
    "addr:full":"Structuurbaan 40 Nieuwegein Utrecht 3439 MB",
    "addr:housenumber":"40",
    "addr:postcode":"3439 mb",
    "addr:street":"Structuurbaan",
    "iso:country":"NL",
    "sg:address":"Structuurbaan 40",
    "sg:city":"Nieuwegein",
    "sg:orig_category":"Onderhoud And Reparatie Kantoorapparatuur",
    "sg:phone":"+31 30 246 4726",
    "sg:postcode":"3439 MB",
    "sg:province":"Utrecht",
    "wof:name":"Ingram Micro Bv",
    "wof:placetype":"venue"
},
  "geometry": {"coordinates":[5.109617,52.036549],"type":"Point"}
}