{
  "type": "Feature",
  "properties": {
    "addr:full":"Den Daal 18 Eersel Noord-Brabant 5521 HC",
    "addr:housenumber":"18",
    "addr:postcode":"5521 hc",
    "addr:street":"Den Daal",
    "iso:country":"NL",
    "sg:address":"Den Daal 18",
    "sg:city":"Eersel",
    "sg:orig_category":"Adviesbureaus Bedrijfsorganisatie",
    "sg:phone":"+31 497 515 861",
    "sg:postcode":"5521 HC",
    "sg:province":"Noord-Brabant",
    "wof:name":"Jbs",
    "wof:placetype":"venue"
},
  "geometry": {"coordinates":[5.30905,51.358311],"type":"Point"}
}