{
  "type": "Feature",
  "properties": {
    "addr:full":"Poptahof N 20 Delft Zuid-Holland 2624 PW",
    "addr:housenumber":"20",
    "addr:postcode":"2624 pw",
    "addr:street":"Poptahof N",
    "iso:country":"NL",
    "sg:address":"Poptahof N 20",
    "sg:city":"Delft",
    "sg:orig_category":"Administratie- En Boekhoudkantoren",
    "sg:phone":"+31 15 262 4388",
    "sg:postcode":"2624 PW",
    "sg:province":"Zuid-Holland",
    "wof:name":"Leeuwen, S C A Van",
    "wof:placetype":"venue"
},
  "geometry": {"coordinates":[4.352491,51.999866],"type":"Point"}
}