{
  "type": "Feature",
  "properties": {
    "iso:country":"NL",
    "sg:address":"Jan Lutmastraat 22",
    "sg:city":"Schoonhoven",
    "sg:orig_category":"Verzekeringen",
    "sg:phone":"+31 182 383 019",
    "sg:postcode":"2871 WP",
    "sg:province":"South Holland",
    "wof:name":"Assurantiekantoor A C Kromme",
    "wof:placetype":"venue"
},
  "geometry": {"coordinates":[4.847787,51.9533],"type":"Point"}
}