{
  "type": "Feature",
  "properties": {
    "addr:full":"Emmastr 71 Vlaardingen Zuid-Holland 3134 CH",
    "addr:housenumber":"71",
    "addr:postcode":"3134",
    "addr:street":"Emmastr",
    "iso:country":"NL",
    "sg:address":"Emmastr 71",
    "sg:city":"Vlaardingen",
    "sg:orig_category":"Verenigingen En Stichtingen",
    "sg:phone":"+31 10 435 4432",
    "sg:postcode":"3134 CH",
    "sg:province":"Zuid-Holland",
    "wof:name":"Turkse Culturele En Sociale Sticht",
    "wof:placetype":"venue"
},
  "geometry": {"coordinates":[4.349738,51.910309],"type":"Point"}
}