{
  "type": "Feature",
  "properties": {
    "addr:full":"Industriewg 33 Groesbeek Gelderland 6562 AP",
    "addr:housenumber":"33",
    "addr:postcode":"6562 ap",
    "addr:street":"Industriewg;Gelderland",
    "iso:country":"NL",
    "sg:address":"Industriewg 33",
    "sg:city":"Groesbeek",
    "sg:orig_category":"Parketvloeren",
    "sg:phone":"+31 24 397 1582",
    "sg:postcode":"6562 AP",
    "sg:province":"Gelderland",
    "wof:name":"Eeren",
    "wof:placetype":"venue"
},
  "geometry": {"coordinates":[5.947391,51.777],"type":"Point"}
}