{
  "type": "Feature",
  "properties": {
    "addr:full":"Achterweg 48 De Kwakel Noord-Holland 1424 PR",
    "addr:housenumber":"48",
    "addr:postcode":"1424 pr",
    "addr:street":"Achterweg",
    "iso:country":"NL",
    "sg:address":"Achterweg 48",
    "sg:city":"De Kwakel",
    "sg:orig_category":"Bloemen- And Plantenteelt",
    "sg:phone":"+31 297 329 416",
    "sg:postcode":"1424 PR",
    "sg:province":"Noord-Holland",
    "wof:name":"Vof Kwekerij Rozenhof",
    "wof:placetype":"venue"
},
  "geometry": {"coordinates":[4.794924,52.239151],"type":"Point"}
}