{
  "type": "Feature",
  "properties": {
    "addr:full":"Zeddamseweg 86 'S Heerenberg Gelderland 7041 CT",
    "addr:housenumber":"86",
    "addr:postcode":"7041 ct",
    "addr:street":"Zeddamseweg;' S Heerenberg Gelderland",
    "iso:country":"NL",
    "sg:address":"Zeddamseweg 86",
    "sg:city":"'S Heerenberg",
    "sg:orig_category":"Kappers",
    "sg:phone":"+31 314 663 087",
    "sg:postcode":"7041 CT",
    "sg:province":"Gelderland",
    "wof:name":"Kapsalon Hermien Van Malsen",
    "wof:placetype":"venue"
},
  "geometry": {"coordinates":[6.2499260902,51.8831138611],"type":"Point"}
}