{
  "type": "Feature",
  "properties": {
    "addr:full":"De Passage 7 Heerenveen Friesland 8442 PH",
    "addr:housenumber":"7",
    "addr:postcode":"8442",
    "addr:street":"De Passage",
    "iso:country":"NL",
    "sg:address":"De Passage 7",
    "sg:city":"Heerenveen",
    "sg:orig_category":"Boeken En Tijdschriften",
    "sg:phone":"+31 513 621 699",
    "sg:postcode":"8442 PH",
    "sg:province":"Friesland",
    "wof:name":"Ako",
    "wof:placetype":"venue"
},
  "geometry": {"coordinates":[5.929095,52.95845],"type":"Point"}
}