{
  "type": "Feature",
  "properties": {
    "addr:full":"Otterspol 2 De Wilp Gn Groningen 9367 TR",
    "addr:housenumber":"2",
    "addr:postcode":"gn;9367 tr",
    "addr:street":"Otterspol",
    "iso:country":"NL",
    "sg:address":"Otterspol 2",
    "sg:city":"De Wilp Gn",
    "sg:orig_category":"Vertaal- And Tolkenbureaus",
    "sg:phone":"+31 594 643 997",
    "sg:postcode":"9367 TR",
    "sg:province":"Groningen",
    "wof:name":"Hetty",
    "wof:placetype":"venue"
},
  "geometry": {"coordinates":[6.257933,53.121536],"type":"Point"}
}