{
  "type": "Feature",
  "properties": {
    "addr:full":"Appelstraat 33 Woerden Utrecht 3442 HH",
    "addr:housenumber":"33",
    "addr:postcode":"3442 hh",
    "addr:street":"Appelstraat",
    "iso:country":"NL",
    "sg:address":"Appelstraat 33",
    "sg:city":"Woerden",
    "sg:orig_category":"Fotostudio'S And Fotografen",
    "sg:phone":"+31 348 411 595",
    "sg:postcode":"3442 HH",
    "sg:province":"Utrecht",
    "wof:name":"Tjerk Kiesel Fotografie",
    "wof:placetype":"venue"
},
  "geometry": {"coordinates":[4.872349,52.083328],"type":"Point"}
}