{
  "type": "Feature",
  "properties": {
    "addr:full":"Julianastr 15 Haarlem Noord-Holland 2012 ER",
    "addr:housenumber":"15",
    "addr:postcode":"2012 er",
    "addr:street":"Julianastr",
    "iso:country":"NL",
    "sg:address":"Julianastr 15",
    "sg:city":"Haarlem",
    "sg:orig_category":"Onroerende Goederen",
    "sg:phone":"+31 23 534 3497",
    "sg:postcode":"2012 ER",
    "sg:province":"Noord-Holland",
    "wof:name":"Espana Universal",
    "wof:placetype":"venue"
},
  "geometry": {"coordinates":[4.626004,52.375252],"type":"Point"}
}