{
  "type": "Feature",
  "properties": {
    "addr:full":"Wandeldreef 4 Aardenburg Zeeland 4527 BX",
    "addr:housenumber":"4",
    "addr:postcode":"4527 bx",
    "addr:street":"Wandeldreef",
    "iso:country":"NL",
    "sg:address":"Wandeldreef 4",
    "sg:city":"Aardenburg",
    "sg:orig_category":"Verhuur Audiovisuele Apparatuur",
    "sg:phone":"+31 117 494 044",
    "sg:postcode":"4527 BX",
    "sg:province":"Zeeland",
    "wof:name":"Plug In Prof Geluid/Pa Verhuur",
    "wof:placetype":"venue"
},
  "geometry": {"coordinates":[3.444161,51.271839],"type":"Point"}
}