{
  "type": "Feature",
  "properties": {
    "addr:full":"Dennenweg 15 Bloemendaal Noord-Holland 2061 HW",
    "addr:housenumber":"15",
    "addr:postcode":"2061 hw",
    "addr:street":"Dennenweg",
    "iso:country":"NL",
    "sg:address":"Dennenweg 15",
    "sg:city":"Bloemendaal",
    "sg:orig_category":"Volwassenenonderwijs",
    "sg:phone":"+31 23 526 4806",
    "sg:postcode":"2061 HW",
    "sg:province":"Noord-Holland",
    "wof:name":"Geref Scholengemeenschap Guido De Bres",
    "wof:placetype":"venue"
},
  "geometry": {"coordinates":[4.624097,52.411118],"type":"Point"}
}