{
  "type": "Feature",
  "properties": {
    "addr:full":"Keizerstraat 43 Deventer Overijssel 7411 HE",
    "addr:housenumber":"43",
    "addr:postcode":"7411 he",
    "addr:street":"Keizerstraat",
    "iso:country":"NL",
    "sg:address":"Keizerstraat 43",
    "sg:city":"Deventer",
    "sg:orig_category":"Woningbouwverenigingen",
    "sg:phone":"+31 570 680 680",
    "sg:postcode":"7411 HE",
    "sg:province":"Overijssel",
    "wof:name":"Stichting Woonunie",
    "wof:placetype":"venue"
},
  "geometry": {"coordinates":[6.1605930328,52.2543640137],"type":"Point"}
}