{
  "type": "Feature",
  "properties": {
    "addr:full":"Ijsselmeerstraat 65 Den Helder Noord-Holland 1784 MB",
    "addr:housenumber":"65",
    "addr:postcode":"1784 mb",
    "addr:street":"Ijsselmeerstraat",
    "iso:country":"NL",
    "sg:address":"Ijsselmeerstraat 65",
    "sg:city":"Den Helder",
    "sg:classifiers":[
        {
            "category":"Fast Food",
            "type":"Food & Drink"
        }
    ],
    "sg:phone":"+31 223 636 541",
    "sg:postcode":"1784 MB",
    "sg:province":"Noord-Holland",
    "sg:tags":[
        "afhaal",
        "restaurant"
    ],
    "wof:name":"Snackbar De Boet",
    "wof:placetype":"venue"
},
  "geometry": {"coordinates":[4.748355,52.937611],"type":"Point"}
}