{
  "type": "Feature",
  "properties": {
    "iso:country":"NL",
    "sg:address":"W Disneyplnts 80",
    "sg:city":"Almere",
    "sg:orig_category":"Kaas",
    "sg:phone":"+31 36 535 7272",
    "sg:postcode":"1325 SX",
    "sg:province":"Flevoland",
    "wof:name":"Vomar",
    "wof:placetype":"venue"
},
  "geometry": {"coordinates":[5.2432551384,52.3597831726],"type":"Point"}
}