{
  "type": "Feature",
  "properties": {
    "addr:full":"Orderparkwg 7-2 Apeldoorn Gelderland 7312 EN",
    "addr:housenumber":"7-2",
    "addr:postcode":"7312 en",
    "addr:street":"Orderparkwg;Gelderland",
    "iso:country":"NL",
    "sg:address":"Orderparkwg 7-2",
    "sg:city":"Apeldoorn",
    "sg:orig_category":"Beeldende Kunstenaars",
    "sg:phone":"+31 55 355 0291",
    "sg:postcode":"7312 EN",
    "sg:province":"Gelderland",
    "wof:name":"John Ligtenberg",
    "wof:placetype":"venue"
},
  "geometry": {"coordinates":[5.939097,52.207733],"type":"Point"}
}