{
  "type": "Feature",
  "properties": {
    "addr:full":"Slotln 22 Etten Leur Noord-Brabant 4873 AG",
    "addr:housenumber":"22",
    "addr:postcode":"4873",
    "addr:street":"Slotln",
    "iso:country":"NL",
    "sg:address":"Slotln 22",
    "sg:city":"Etten Leur",
    "sg:orig_category":"Koeriersdiensten",
    "sg:phone":"+31 76 503 7261",
    "sg:postcode":"4873 AG",
    "sg:province":"Noord-Brabant",
    "wof:name":"Yellow Line",
    "wof:placetype":"venue"
},
  "geometry": {"coordinates":[4.639522,51.570694],"type":"Point"}
}