{
  "type": "Feature",
  "properties": {
    "addr:full":"Stationsstr 122 Deurne Noord-Brabant 5751 HJ",
    "addr:housenumber":"122",
    "addr:postcode":"5751 hj",
    "iso:country":"NL",
    "sg:address":"Stationsstr 122",
    "sg:city":"Deurne",
    "sg:classifiers":[
        {
            "category":"Shopping",
            "subcategory":"News",
            "type":"Retail Goods"
        }
    ],
    "sg:phone":"+31 493 328 128",
    "sg:postcode":"5751 HJ",
    "sg:province":"Noord-Brabant",
    "sg:tags":[
        "maandbladen",
        "en",
        "week-"
    ],
    "wof:name":"Deurne/Peelbelang, Weekblad Voor",
    "wof:placetype":"venue"
},
  "geometry": {"coordinates":[5.7846570015,51.4578323364],"type":"Point"}
}