{
  "type": "Feature",
  "properties": {
    "iso:country":"NL",
    "sg:address":"Hogewg 101",
    "sg:city":"Venlo",
    "sg:orig_category":"Gehandicapteninformatie",
    "sg:phone":"+31 77 320 9400",
    "sg:postcode":"5914 BC",
    "sg:province":"Limburg",
    "wof:name":"Wendel, De",
    "wof:placetype":"venue"
},
  "geometry": {"coordinates":[6.174274,51.377792],"type":"Point"}
}