{
  "type": "Feature",
  "properties": {
    "addr:full":"Hoofdstr 116 Apeldoorn Gelderland 7311 KJ",
    "addr:housenumber":"116",
    "addr:postcode":"7311 kj",
    "addr:street":"Gelderland",
    "iso:country":"NL",
    "sg:address":"Hoofdstr 116",
    "sg:city":"Apeldoorn",
    "sg:orig_category":"Linnenshops",
    "sg:phone":"+31 55 578 9653",
    "sg:postcode":"7311 KJ",
    "sg:province":"Gelderland",
    "wof:name":"Burmann",
    "wof:placetype":"venue"
},
  "geometry": {"coordinates":[5.961694,52.21508],"type":"Point"}
}