{
  "type": "Feature",
  "properties": {
    "addr:full":"J Geesinkwg 306 Amsterdam Noord-Holland 1096 AW",
    "addr:housenumber":"306",
    "addr:postcode":"1096 aw",
    "iso:country":"NL",
    "sg:address":"J Geesinkwg 306",
    "sg:city":"Amsterdam",
    "sg:orig_category":"Kopieerservice",
    "sg:phone":"+31 20 462 1999",
    "sg:postcode":"1096 AW",
    "sg:province":"Noord-Holland",
    "sg:website":"http://www.multicopy.nl",
    "wof:name":"Multicopy Amsterdam Amstel",
    "wof:placetype":"venue"
},
  "geometry": {"coordinates":[4.929912,52.334534],"type":"Point"}
}