{
  "type": "Feature",
  "properties": {
    "addr:full":"Looiersweg 8 Terborg Gelderland 7061 CW",
    "addr:housenumber":"8",
    "addr:postcode":"7061 cw",
    "addr:street":"Looiersweg;Gelderland",
    "iso:country":"NL",
    "sg:address":"Looiersweg 8",
    "sg:city":"Terborg",
    "sg:orig_category":"Fietshandelaren",
    "sg:phone":"+31 315 324 395",
    "sg:postcode":"7061 CW",
    "sg:province":"Gelderland",
    "wof:name":"G Ten Have",
    "wof:placetype":"venue"
},
  "geometry": {"coordinates":[6.362078,51.920952],"type":"Point"}
}