{
  "type": "Feature",
  "properties": {
    "addr:full":"Van Hallstraat 238 Amsterdam Noord-Holland 1051 HL",
    "addr:housenumber":"238",
    "addr:postcode":"1051 hl",
    "addr:street":"Van Hallstraat",
    "iso:country":"NL",
    "sg:address":"Van Hallstraat 238",
    "sg:city":"Amsterdam",
    "sg:orig_category":"Kappers",
    "sg:phone":"+31 20 684 4273",
    "sg:postcode":"1051 HL",
    "sg:province":"Noord-Holland",
    "wof:name":"Vc Hairshop",
    "wof:placetype":"venue"
},
  "geometry": {"coordinates":[4.871563,52.380569],"type":"Point"}
}