{
  "type": "Feature",
  "properties": {
    "addr:full":"Molenveldwg 1214 Meerssen Limburg 6231 RX",
    "addr:postcode":"1214;6231 rx",
    "iso:country":"NL",
    "sg:address":"Molenveldwg 1214",
    "sg:city":"Meerssen",
    "sg:orig_category":"Levensmiddelen - Fabrieken En Groothandel",
    "sg:phone":"+31 6 53163945",
    "sg:postcode":"6231 RX",
    "sg:province":"Limburg",
    "wof:name":"Groote Molen Bv, De",
    "wof:placetype":"venue"
},
  "geometry": {"coordinates":[5.75422,50.879662],"type":"Point"}
}