{
  "type": "Feature",
  "properties": {
    "addr:full":"Nieuwemeerdijk 319 Badhoevedorp Noord-Holland 1171 NT",
    "addr:housenumber":"319",
    "addr:postcode":"1171 nt",
    "addr:street":"Nieuwemeerdijk",
    "iso:country":"NL",
    "sg:address":"Nieuwemeerdijk 319",
    "sg:city":"Badhoevedorp",
    "sg:orig_category":"Zuivelproducten",
    "sg:phone":"+31 20 601 0534",
    "sg:postcode":"1171 NT",
    "sg:province":"Noord-Holland",
    "wof:name":"H H J Vd Geest",
    "wof:placetype":"venue"
},
  "geometry": {"coordinates":[4.816959,52.326344],"type":"Point"}
}