{
  "type": "Feature",
  "properties": {
    "iso:country":"NL",
    "sg:address":"Nieuwemeerdijk 319",
    "sg:city":"Badhoevedorp",
    "sg:orig_category":"Zuivelproducten",
    "sg:phone":"+31 20 601 0534",
    "sg:postcode":"1171 NT",
    "sg:province":"Noord-Holland",
    "wof:name":"H H J Vd Geest",
    "wof:placetype":"venue"
},
  "geometry": {"coordinates":[4.816959,52.326344],"type":"Point"}
}