{
  "type": "Feature",
  "properties": {
    "addr:full":"Botreep 10 Hoogvliet Rt Zuid-Holland 3192 PD",
    "addr:housenumber":"10",
    "addr:postcode":"rt;3192 pd",
    "addr:street":"Botreep",
    "iso:country":"NL",
    "sg:address":"Botreep 10",
    "sg:city":"Hoogvliet Rt",
    "sg:orig_category":"Sportverenigingen En Ontspannings- Verenigingen",
    "sg:phone":"+31 10 438 6957",
    "sg:postcode":"3192 PD",
    "sg:province":"Zuid-Holland",
    "wof:name":"Etc Handbalver",
    "wof:placetype":"venue"
},
  "geometry": {"coordinates":[4.379152,51.851139],"type":"Point"}
}