{
  "type": "Feature",
  "properties": {
    "iso:country":"NL",
    "sg:address":"Minckelersstraat 37",
    "sg:city":"Eindhoven",
    "sg:orig_category":"Film-, Tv- And Videoproductie",
    "sg:phone":"+31 40 243 2319",
    "sg:postcode":"5621 GW",
    "sg:province":"North Brabant",
    "wof:name":"Doblo Prod",
    "wof:placetype":"venue"
},
  "geometry": {"coordinates":[5.457839,51.455284],"type":"Point"}
}