{
  "type": "Feature",
  "properties": {
    "addr:full":"Minckelersstraat 37 Eindhoven North Brabant 5621 GW",
    "addr:housenumber":"37",
    "addr:postcode":"5621 gw",
    "addr:street":"Minckelersstraat",
    "iso:country":"NL",
    "sg:address":"Minckelersstraat 37",
    "sg:city":"Eindhoven",
    "sg:orig_category":"Film-, Tv- And Videoproductie",
    "sg:phone":"+31 40 243 2319",
    "sg:postcode":"5621 GW",
    "sg:province":"North Brabant",
    "wof:name":"Doblo Prod",
    "wof:placetype":"venue"
},
  "geometry": {"coordinates":[5.457839,51.455284],"type":"Point"}
}