{
  "type": "Feature",
  "properties": {
    "addr:full":"Hoofdstr 78 De Lier Zuid-Holland 2678 CL",
    "addr:housenumber":"78",
    "addr:postcode":"2678",
    "addr:street":"Hoofdstr",
    "iso:country":"NL",
    "sg:address":"Hoofdstr 78",
    "sg:city":"De Lier",
    "sg:orig_category":"Banken",
    "sg:phone":"+31 174 527 800",
    "sg:postcode":"2678 CL",
    "sg:province":"Zuid-Holland",
    "sg:website":"http://www.rabobank.nl",
    "wof:name":"Rabobank",
    "wof:placetype":"venue"
},
  "geometry": {"coordinates":[4.251425,51.975002],"type":"Point"}
}