{
  "type": "Feature",
  "properties": {
    "addr:full":"Lijnbaansgracht 56 Amsterdam Noord-Holland 1015 GS",
    "addr:housenumber":"56",
    "addr:postcode":"1015 gs",
    "addr:street":"Lijnbaansgracht",
    "iso:country":"NL",
    "sg:address":"Lijnbaansgracht 56",
    "sg:city":"Amsterdam",
    "sg:orig_category":"Boekenuitgeverijen",
    "sg:phone":"+31 20 624 5044",
    "sg:postcode":"1015 GS",
    "sg:province":"Noord-Holland",
    "wof:name":"Uitgeverij Freewrite",
    "wof:placetype":"venue"
},
  "geometry": {"coordinates":[4.879988,52.378395],"type":"Point"}
}