{
  "type": "Feature",
  "properties": {
    "addr:full":"Postbus 5012 Venray Noord-Brabant 5800 GA",
    "addr:postcode":"5012 venray;5800 ga",
    "addr:street":"Postbus",
    "iso:country":"NL",
    "sg:address":"Postbus 5012",
    "sg:city":"Venray",
    "sg:orig_category":"Letselschadespecialisten",
    "sg:phone":"+31 478 521 038",
    "sg:postcode":"5800 GA",
    "sg:province":"Noord-Brabant",
    "wof:name":"Injurylawyers",
    "wof:placetype":"venue"
},
  "geometry": {"coordinates":[5.977073,51.527157],"type":"Point"}
}