{
  "type": "Feature",
  "properties": {
    "addr:full":"Steenbakkersweg 25 Hengelo Ov NL.08 7553 EH",
    "addr:housenumber":"25",
    "addr:postcode":"7553 eh",
    "addr:street":"Steenbakkersweg;Ov",
    "iso:country":"NL",
    "sg:address":"Steenbakkersweg 25",
    "sg:city":"Hengelo Ov",
    "sg:orig_category":"Makelaars In Onroerend Goed",
    "sg:phone":"+31 74 291 3222",
    "sg:postcode":"7553 EH",
    "sg:province":"NL.08",
    "wof:name":"Ondernemerscentrum Esrein",
    "wof:placetype":"venue"
},
  "geometry": {"coordinates":[6.785261,52.255184],"type":"Point"}
}