{
  "type": "Feature",
  "properties": {
    "addr:full":"Ewoudslaan 5 Honselersdijk South Holland 2675 KT",
    "addr:housenumber":"5",
    "addr:postcode":"2675 kt",
    "addr:street":"Ewoudslaan",
    "iso:country":"NL",
    "sg:address":"Ewoudslaan 5",
    "sg:city":"Honselersdijk",
    "sg:orig_category":"Bloemen And Planten",
    "sg:phone":"+31 174 627 563",
    "sg:postcode":"2675 KT",
    "sg:province":"South Holland",
    "wof:name":"J.W.M. Van Der Valk",
    "wof:placetype":"venue"
},
  "geometry": {"coordinates":[4.249025,52.005825],"type":"Point"}
}