{
  "type": "Feature",
  "properties": {
    "addr:full":"Waterman 20 Tolbert Texas 9356 DA",
    "addr:housenumber":"20",
    "addr:postcode":"9356 da",
    "addr:street":"Waterman",
    "iso:country":"NL",
    "sg:address":"Waterman 20",
    "sg:city":"Tolbert",
    "sg:orig_category":"Kappers",
    "sg:phone":"+31 594 518 290",
    "sg:postcode":"9356 DA",
    "sg:province":"Texas",
    "wof:name":"E. Kooi Welfing",
    "wof:placetype":"venue"
},
  "geometry": {"coordinates":[-99.4145355225,34.2266616821],"type":"Point"}
}