{
  "type": "Feature",
  "properties": {
    "addr:full":"Leggelostraat 79 'S Gravenhage Zuid-Holland 2541 HR",
    "addr:housenumber":"79",
    "addr:postcode":"2541 hr",
    "addr:street":"Leggelostraat;' S",
    "iso:country":"NL",
    "sg:address":"Leggelostraat 79",
    "sg:city":"'S Gravenhage",
    "sg:orig_category":"Bloemen And Planten",
    "sg:phone":"+31 70 366 8702",
    "sg:postcode":"2541 HR",
    "sg:province":"Zuid-Holland",
    "wof:name":"Bloemenmagazijn Fredy",
    "wof:placetype":"venue"
},
  "geometry": {"coordinates":[4.277391,52.042633],"type":"Point"}
}