{
  "type": "Feature",
  "properties": {
    "addr:full":"Schimmelstr 3 Amsterdam North Holland 1053 TA",
    "addr:housenumber":"3",
    "addr:postcode":"1053 ta",
    "addr:street":"Schimmelstr",
    "iso:country":"NL",
    "sg:address":"Schimmelstr 3",
    "sg:city":"Amsterdam",
    "sg:orig_category":"Fietsen En Bromfietsen Stalling",
    "sg:phone":"+31 20 618 4488",
    "sg:postcode":"1053 TA",
    "sg:province":"North Holland",
    "wof:name":"Braad, Jan",
    "wof:placetype":"venue"
},
  "geometry": {"coordinates":[4.866697,52.368744],"type":"Point"}
}