{
  "type": "Feature",
  "properties": {
    "addr:full":"Fabriekswg 2A Hoogeveen Drenthe 7902 NM",
    "addr:housenumber":"2a",
    "addr:postcode":"7902",
    "addr:street":"Fabriekswg",
    "iso:country":"NL",
    "sg:address":"Fabriekswg 2A",
    "sg:city":"Hoogeveen",
    "sg:orig_category":"Meubelstoffering",
    "sg:phone":"+31 528 265 194",
    "sg:postcode":"7902 NM",
    "sg:province":"Drenthe",
    "wof:name":"Liemburg, Henk",
    "wof:placetype":"venue"
},
  "geometry": {"coordinates":[6.487,52.726768],"type":"Point"}
}