{
  "type": "Feature",
  "properties": {
    "addr:full":"Roserye 119D Maastricht Limburg 6228 DK",
    "addr:housenumber":"119d",
    "addr:postcode":"6228 dk",
    "addr:street":"Roserye",
    "iso:country":"NL",
    "sg:address":"Roserye 119D",
    "sg:city":"Maastricht",
    "sg:orig_category":"Vertalers",
    "sg:phone":"+31 43 361 7809",
    "sg:postcode":"6228 DK",
    "sg:province":"Limburg",
    "wof:name":"Roessel, C Van",
    "wof:placetype":"venue"
},
  "geometry": {"coordinates":[5.732049942,50.8244590759],"type":"Point"}
}