{
  "type": "Feature",
  "properties": {
    "addr:full":"Wagenbergsestraat 11 Hooge Zwaluwe Noord-Brabant 4927 RD",
    "addr:housenumber":"11",
    "addr:postcode":"4927 rd",
    "addr:street":"Wagenbergsestraat",
    "iso:country":"NL",
    "sg:address":"Wagenbergsestraat 11",
    "sg:city":"Hooge Zwaluwe",
    "sg:orig_category":"Werk- And Beschermkleding Fab",
    "sg:phone":"+31 76 593 4465",
    "sg:postcode":"4927 RD",
    "sg:province":"Noord-Brabant",
    "wof:name":"Ml Produkties",
    "wof:placetype":"venue"
},
  "geometry": {"coordinates":[4.7515997887,51.6710548401],"type":"Point"}
}