{
  "type": "Feature",
  "properties": {
    "addr:full":"De Buurt 53 Hardinxveld Giessend Zuid-Holland 3372 DB",
    "addr:housenumber":"53;giessend",
    "addr:postcode":"3372 db",
    "addr:street":"De Buurt",
    "iso:country":"NL",
    "sg:address":"De Buurt 53",
    "sg:city":"Hardinxveld Giessend",
    "sg:orig_category":"Verzekeringen",
    "sg:phone":"+31 184 615 156",
    "sg:postcode":"3372 DB",
    "sg:province":"Zuid-Holland",
    "wof:name":"Bv Ass En Bemiddelingskantoor De Langendam",
    "wof:placetype":"venue"
},
  "geometry": {"coordinates":[4.881555,51.822025],"type":"Point"}
}