{
  "type": "Feature",
  "properties": {
    "addr:full":"Hg Molenstr 1 Zierikzee Zeeland 4301 KB",
    "addr:housenumber":"1",
    "addr:postcode":"4301 kb",
    "iso:country":"NL",
    "sg:address":"Hg Molenstr 1",
    "sg:city":"Zierikzee",
    "sg:orig_category":"Biljartzalen",
    "sg:phone":"+31 111 420 301",
    "sg:postcode":"4301 KB",
    "sg:province":"Zeeland",
    "wof:name":"Graanbeurs, De",
    "wof:placetype":"venue"
},
  "geometry": {"coordinates":[3.920478,51.650944],"type":"Point"}
}