{
  "type": "Feature",
  "properties": {
    "addr:full":"Mr Racerstr 12 Delden NL.08 7491 CJ",
    "addr:housenumber":"12;nl.08",
    "addr:postcode":"7491 cj",
    "iso:country":"NL",
    "sg:address":"Mr Racerstr 12",
    "sg:city":"Delden",
    "sg:orig_category":"Vertaalbureaus",
    "sg:phone":"+31 74 376 7505",
    "sg:postcode":"7491 CJ",
    "sg:province":"NL.08",
    "wof:name":"Taal & Co",
    "wof:placetype":"venue"
},
  "geometry": {"coordinates":[6.710841,52.261032],"type":"Point"}
}