{
  "type": "Feature",
  "properties": {
    "addr:full":"Braspenninghof 2 Valkenswaard Noord-Brabant 5551 DM",
    "addr:housenumber":"2",
    "addr:postcode":"5551 dm",
    "addr:street":"Braspenninghof",
    "iso:country":"NL",
    "sg:address":"Braspenninghof 2",
    "sg:city":"Valkenswaard",
    "sg:orig_category":"Ventilatiesystemen",
    "sg:phone":"+31 40 204 3747",
    "sg:postcode":"5551 DM",
    "sg:province":"Noord-Brabant",
    "wof:name":"Moluva Bv",
    "wof:placetype":"venue"
},
  "geometry": {"coordinates":[5.429047,51.356682],"type":"Point"}
}