{
  "type": "Feature",
  "properties": {
    "addr:full":"Prins Clausstraat 6 Nieuwegein Utrecht 3433 EN",
    "addr:housenumber":"6",
    "addr:postcode":"3433 en",
    "addr:street":"Prins Clausstraat",
    "iso:country":"NL",
    "sg:address":"Prins Clausstraat 6",
    "sg:city":"Nieuwegein",
    "sg:orig_category":"Binnenhuisarchitecten",
    "sg:phone":"+31 30 606 7417",
    "sg:postcode":"3433 EN",
    "sg:province":"Utrecht",
    "wof:name":"Marc Heldens Interieurarchitect",
    "wof:placetype":"venue"
},
  "geometry": {"coordinates":[5.096673,52.009754],"type":"Point"}
}