{
  "type": "Feature",
  "properties": {
    "addr:full":"Rogier Van Leefdaelstr 2 Hilvarenbeek Noord-Brabant 5081 JL",
    "addr:housenumber":"2",
    "addr:postcode":"5081 jl",
    "addr:street":"Rogier Van Leefdaelstr",
    "iso:country":"NL",
    "sg:address":"Rogier Van Leefdaelstr 2",
    "sg:city":"Hilvarenbeek",
    "sg:orig_category":"Kappers",
    "sg:phone":"+31 13 505 3029",
    "sg:postcode":"5081 JL",
    "sg:province":"Noord-Brabant",
    "wof:name":"M. Hoogers-Kluijtmans",
    "wof:placetype":"venue"
},
  "geometry": {"coordinates":[5.138127,51.482376],"type":"Point"}
}