{
  "type": "Feature",
  "properties": {
    "iso:country":"NL",
    "sg:address":"Nigtevechtsewg 120",
    "sg:city":"Vreeland",
    "sg:orig_category":"Glazenwasserijen",
    "sg:phone":"+31 294 254 523",
    "sg:postcode":"3633 XX",
    "sg:province":"Maryland",
    "wof:name":"Blum Glazenwasbedrijf, W",
    "wof:placetype":"venue"
},
  "geometry": {"coordinates":[-76.68330400000001,39.705425],"type":"Point"}
}