{
  "type": "Feature",
  "properties": {
    "addr:full":"Pr Frederikln 195 Leidschendam Zuid-Holland 2263 HA",
    "addr:housenumber":"195",
    "addr:postcode":"2263 ha",
    "iso:country":"NL",
    "sg:address":"Pr Frederikln 195",
    "sg:city":"Leidschendam",
    "sg:orig_category":"Drogisterijen",
    "sg:phone":"+31 70 327 1148",
    "sg:postcode":"2263 HA",
    "sg:province":"Zuid-Holland",
    "wof:name":"Kuhn",
    "wof:placetype":"venue"
},
  "geometry": {"coordinates":[4.41042,52.10218],"type":"Point"}
}