{
  "type": "Feature",
  "properties": {
    "iso:country":"NL",
    "sg:address":"Parklaan 11",
    "sg:city":"Rotterdam",
    "sg:orig_category":"Bedrijvencentra",
    "sg:phone":"+31 10 440 3555",
    "sg:postcode":"3016 BA",
    "sg:province":"South Holland",
    "wof:name":"Ect Beheer Bv",
    "wof:placetype":"venue"
},
  "geometry": {"coordinates":[4.474689,51.908043],"type":"Point"}
}