{
  "type": "Feature",
  "properties": {
    "addr:full":"Parklaan 11 Rotterdam South Holland 3016 BA",
    "addr:housenumber":"11",
    "addr:postcode":"3016 ba",
    "addr:street":"Parklaan",
    "iso:country":"NL",
    "sg:address":"Parklaan 11",
    "sg:city":"Rotterdam",
    "sg:orig_category":"Bedrijvencentra",
    "sg:phone":"+31 10 440 3555",
    "sg:postcode":"3016 BA",
    "sg:province":"South Holland",
    "wof:name":"Ect Beheer Bv",
    "wof:placetype":"venue"
},
  "geometry": {"coordinates":[4.474689,51.908043],"type":"Point"}
}