{
  "type": "Feature",
  "properties": {
    "iso:country":"NL",
    "sg:address":"Lieshoutsewg 28",
    "sg:city":"St Oedenrode",
    "sg:orig_category":"Artiesten/Gezelschappen",
    "sg:phone":"+31 413 476 921",
    "sg:postcode":"5492 HR",
    "sg:province":"Noord-Brabant",
    "wof:name":"King Size Trio",
    "wof:placetype":"venue"
},
  "geometry": {"coordinates":[5.483746,51.5518],"type":"Point"}
}