{
  "type": "Feature",
  "properties": {
    "addr:full":"Lieshoutsewg 28 St Oedenrode Noord-Brabant 5492 HR",
    "addr:housenumber":"28",
    "addr:postcode":"5492 hr",
    "addr:street":"Lieshoutsewg",
    "iso:country":"NL",
    "sg:address":"Lieshoutsewg 28",
    "sg:city":"St Oedenrode",
    "sg:orig_category":"Artiesten/Gezelschappen",
    "sg:phone":"+31 413 476 921",
    "sg:postcode":"5492 HR",
    "sg:province":"Noord-Brabant",
    "wof:name":"King Size Trio",
    "wof:placetype":"venue"
},
  "geometry": {"coordinates":[5.483746,51.5518],"type":"Point"}
}