{
  "type": "Feature",
  "properties": {
    "iso:country":"NL",
    "sg:address":"O Nassaustr 23",
    "sg:city":"Grave",
    "sg:orig_category":"Modevakscholen",
    "sg:phone":"+31 486 471 761",
    "sg:postcode":"5361 CG",
    "sg:province":"Noord-Brabant",
    "wof:name":"Paula, Modevakschool",
    "wof:placetype":"venue"
},
  "geometry": {"coordinates":[-92.151741,32.929253],"type":"Point"}
}