{
  "type": "Feature",
  "properties": {
    "addr:full":"Brandstraat 32 Sittard Limburg 6131 CT",
    "addr:housenumber":"32",
    "addr:postcode":"6131 ct",
    "addr:street":"Brandstraat",
    "iso:country":"NL",
    "sg:address":"Brandstraat 32",
    "sg:city":"Sittard",
    "sg:classifiers":[
        {
            "category":"Retail",
            "subcategory":"Photofinishing",
            "type":"Services"
        }
    ],
    "sg:phone":"+31 46 451 5819",
    "sg:postcode":"6131 CT",
    "sg:province":"Limburg",
    "sg:tags":[
        "foto",
        "film"
    ],
    "wof:name":"Foto Math En Marcel Maas",
    "wof:placetype":"venue"
},
  "geometry": {"coordinates":[5.865349,50.998474],"type":"Point"}
}