{
  "type": "Feature",
  "properties": {
    "addr:full":"Klokbekerstr 88 Maastricht Limburg 6216 TS",
    "addr:housenumber":"88",
    "addr:postcode":"6216 ts",
    "addr:street":"Klokbekerstr",
    "iso:country":"NL",
    "sg:address":"Klokbekerstr 88",
    "sg:city":"Maastricht",
    "sg:orig_category":"Schilders",
    "sg:phone":"+31 43 347 7432",
    "sg:postcode":"6216 TS",
    "sg:province":"Limburg",
    "wof:name":"Schellings, Ton",
    "wof:placetype":"venue"
},
  "geometry": {"coordinates":[5.65479,50.848866],"type":"Point"}
}