{
  "type": "Feature",
  "properties": {
    "iso:country":"NL",
    "sg:address":"T Hufke 3",
    "sg:city":"Bergharen",
    "sg:orig_category":"Wegen And Sportterreinen",
    "sg:phone":"+31 487 531 844",
    "sg:postcode":"6617 KL",
    "sg:province":"Gelderland",
    "wof:name":"Postma Grond Water En Wegenbouw Bv",
    "wof:placetype":"venue"
},
  "geometry": {"coordinates":[5.6552958488,51.8502883911],"type":"Point"}
}