{
  "type": "Feature",
  "properties": {
    "addr:full":"Vlaanderenpln 2 Sas Van Gent Zeeland 4551 DZ",
    "addr:housenumber":"2",
    "addr:postcode":"4551 dz",
    "addr:street":"Vlaanderenpln",
    "iso:country":"NL",
    "sg:address":"Vlaanderenpln 2",
    "sg:city":"Sas Van Gent",
    "sg:orig_category":"Fitnesscentra",
    "sg:phone":"+31 115 450 093",
    "sg:postcode":"4551 DZ",
    "sg:province":"Zeeland",
    "wof:name":"Leisure Company",
    "wof:placetype":"venue"
},
  "geometry": {"coordinates":[3.793055,51.225906],"type":"Point"}
}