{
  "type": "Feature",
  "properties": {
    "addr:full":"Piusstr 343/21 Tilburg Noord-Brabant 5038 WR",
    "addr:housenumber":"343 / 21",
    "addr:postcode":"5038 wr",
    "iso:country":"NL",
    "sg:address":"Piusstr 343/21",
    "sg:city":"Tilburg",
    "sg:orig_category":"Fotografie Reclame En Mode",
    "sg:phone":"+31 13 535 2446",
    "sg:postcode":"5038 WR",
    "sg:province":"Noord-Brabant",
    "wof:name":"Cohen, Studio Robin",
    "wof:placetype":"venue"
},
  "geometry": {"coordinates":[5.08904,51.551411],"type":"Point"}
}