{
  "type": "Feature",
  "properties": {
    "iso:country":"NL",
    "sg:address":"Lugtenburgsedk 2",
    "sg:city":"Stryen",
    "sg:orig_category":"Loonbedrijven",
    "sg:phone":"+31 78 674 1062",
    "sg:postcode":"3291 LK",
    "sg:province":"South Holland",
    "wof:name":"Schilperoort Vof",
    "wof:placetype":"venue"
},
  "geometry": {"coordinates":[4.54727,51.750832],"type":"Point"}
}