{
  "type": "Feature",
  "properties": {
    "addr:full":"Hogeweg 1 Harderwijk Gelderland 3841 KT",
    "addr:housenumber":"1",
    "addr:postcode":"3841 kt",
    "addr:street":"Hogeweg;Gelderland",
    "iso:country":"NL",
    "sg:address":"Hogeweg 1",
    "sg:city":"Harderwijk",
    "sg:orig_category":"Paramedische Behandelingen",
    "sg:phone":"+31 341 432 009",
    "sg:postcode":"3841 KT",
    "sg:province":"Gelderland",
    "wof:name":"O T Maarleveld-Kampherbeek",
    "wof:placetype":"venue"
},
  "geometry": {"coordinates":[5.623346,52.349655],"type":"Point"}
}