{
  "type": "Feature",
  "properties": {
    "addr:full":"Keizersgr 133 Amsterdam North Holland 1015 CJ",
    "addr:housenumber":"133",
    "addr:postcode":"1015 cj",
    "iso:country":"NL",
    "sg:address":"Keizersgr 133",
    "sg:city":"Amsterdam",
    "sg:orig_category":"Psychologen",
    "sg:phone":"+31 20 620 5413",
    "sg:postcode":"1015 CJ",
    "sg:province":"North Holland",
    "wof:name":"Veen-Wubben, Drs Y Van Der",
    "wof:placetype":"venue"
},
  "geometry": {"coordinates":[4.887238,52.376163],"type":"Point"}
}