{
  "type": "Feature",
  "properties": {
    "addr:full":"St. Hubertseweg 9 Cuijk North Brabant 5443 ND",
    "addr:housenumber":"9",
    "addr:postcode":"5443 nd",
    "iso:country":"NL",
    "sg:address":"St. Hubertseweg 9",
    "sg:city":"Cuijk",
    "sg:orig_category":"Zuivelproducten",
    "sg:phone":"+31 485 311 474",
    "sg:postcode":"5443 ND",
    "sg:province":"North Brabant",
    "wof:name":"Aalshof Eieren",
    "wof:placetype":"venue"
},
  "geometry": {"coordinates":[5.854364,51.684135],"type":"Point"}
}