{
  "type": "Feature",
  "properties": {
    "addr:full":"Friesewg 13 Alkmaar North Holland 1823 CA",
    "addr:housenumber":"13",
    "addr:postcode":"1823 ca",
    "addr:street":"Friesewg",
    "iso:country":"NL",
    "sg:address":"Friesewg 13",
    "sg:city":"Alkmaar",
    "sg:orig_category":"Keukens",
    "sg:phone":"+31 72 515 8899",
    "sg:postcode":"1823 CA",
    "sg:province":"North Holland",
    "sg:website":"http://www.oudejans-keukens.nl",
    "wof:name":"Oudejans Keukendesign",
    "wof:placetype":"venue"
},
  "geometry": {"coordinates":[4.754577,52.633255],"type":"Point"}
}