{
  "type": "Feature",
  "properties": {
    "addr:full":"Breitnerln 12 Hazerswoude Dorp Zuid-Holland 2391 GC",
    "addr:housenumber":"12",
    "addr:postcode":"2391 gc",
    "addr:street":"Breitnerln",
    "iso:country":"NL",
    "sg:address":"Breitnerln 12",
    "sg:city":"Hazerswoude Dorp",
    "sg:orig_category":"Administratie- En Boekhoudkantoren",
    "sg:phone":"+31 172 586 187",
    "sg:postcode":"2391 GC",
    "sg:province":"Zuid-Holland",
    "wof:name":"Hoogerwerf",
    "wof:placetype":"venue"
},
  "geometry": {"coordinates":[4.581486,52.094528],"type":"Point"}
}