{
  "type": "Feature",
  "properties": {
    "addr:full":"Ryksstrwg 20 Warnsveld Gelderland 7231 AG",
    "addr:housenumber":"20",
    "addr:postcode":"7231",
    "addr:street":"Ryksstrwg;Gelderland",
    "iso:country":"NL",
    "sg:address":"Ryksstrwg 20",
    "sg:city":"Warnsveld",
    "sg:orig_category":"Kappers",
    "sg:phone":"+31 575 523 138",
    "sg:postcode":"7231 AG",
    "sg:province":"Gelderland",
    "wof:name":"Velders, Maison",
    "wof:placetype":"venue"
},
  "geometry": {"coordinates":[6.225585,52.140984],"type":"Point"}
}