{
  "type": "Feature",
  "properties": {
    "iso:country":"NL",
    "sg:address":"Albert Cuypstraat 276",
    "sg:city":"Amsterdam",
    "sg:orig_category":"Herenmodezaken",
    "sg:phone":"+31 20 675 1710",
    "sg:postcode":"1073 BR",
    "sg:province":"Noord-Holland",
    "wof:name":"Smart Guy",
    "wof:placetype":"venue"
},
  "geometry": {"coordinates":[4.899425,52.35696],"type":"Point"}
}