{
  "type": "Feature",
  "properties": {
    "addr:full":"Dorpsmatenstraat 46 Hengelo Ov Overijssel 7551 BP",
    "addr:housenumber":"46",
    "addr:postcode":"7551 bp",
    "addr:street":"Dorpsmatenstraat;Ov",
    "iso:country":"NL",
    "sg:address":"Dorpsmatenstraat 46",
    "sg:city":"Hengelo Ov",
    "sg:orig_category":"Overheidsdiensten",
    "sg:phone":"+31 74 243 3750",
    "sg:postcode":"7551 BP",
    "sg:province":"Overijssel",
    "wof:name":"Da=Bar",
    "wof:placetype":"venue"
},
  "geometry": {"coordinates":[6.7898230553,52.2636833191],"type":"Point"}
}