{
  "type": "Feature",
  "properties": {
    "addr:full":"Julianastraat 21 Veghel Noord-Brabant 5462 HA",
    "addr:housenumber":"21",
    "addr:postcode":"5462 ha",
    "addr:street":"Julianastraat",
    "iso:country":"NL",
    "sg:address":"Julianastraat 21",
    "sg:city":"Veghel",
    "sg:orig_category":"Verzekeringen",
    "sg:phone":"+31 413 362 712",
    "sg:postcode":"5462 HA",
    "sg:province":"Noord-Brabant",
    "wof:name":"Assurantiekantoor A. Van Houtum",
    "wof:placetype":"venue"
},
  "geometry": {"coordinates":[5.535009,51.61721],"type":"Point"}
}