{
  "type": "Feature",
  "properties": {
    "addr:full":"Lupineberg 47 Roosendaal Noord-Brabant 4708 LW",
    "addr:housenumber":"47",
    "addr:postcode":"4708 lw",
    "addr:street":"Lupineberg",
    "iso:country":"NL",
    "sg:address":"Lupineberg 47",
    "sg:city":"Roosendaal",
    "sg:classifiers":[
        {
            "category":"Personal",
            "subcategory":"Nail Salon",
            "type":"Services"
        }
    ],
    "sg:phone":"+31 165 548 558",
    "sg:postcode":"4708 LW",
    "sg:province":"Noord-Brabant",
    "sg:tags":[
        "pedicure"
    ],
    "wof:name":"Marjan Torbijn",
    "wof:placetype":"venue"
},
  "geometry": {"coordinates":[4.428621,51.515755],"type":"Point"}
}