{
  "type": "Feature",
  "properties": {
    "addr:full":"Leidsestr 52 Amsterdam North Holland 1017 PC",
    "addr:housenumber":"52",
    "addr:postcode":"1017 pc",
    "addr:street":"Leidsestr",
    "iso:country":"NL",
    "sg:address":"Leidsestr 52",
    "sg:city":"Amsterdam",
    "sg:orig_category":"Boeken En Tijdschriften",
    "sg:phone":"+31 20 623 8283",
    "sg:postcode":"1017 PC",
    "sg:province":"North Holland",
    "wof:name":"New English Bookstore",
    "wof:placetype":"venue"
},
  "geometry": {"coordinates":[4.885647,52.365753],"type":"Point"}
}