{
  "type": "Feature",
  "properties": {
    "iso:country":"NL",
    "sg:address":"Beneluxweg 28",
    "sg:city":"Bodegraven",
    "sg:orig_category":"Zuivelproducten And Spijsoli?n Gh",
    "sg:phone":"+31 172 619 339",
    "sg:postcode":"2411 NG",
    "sg:province":"Zuid-Holland",
    "wof:name":"Den Hollander Kaas Bv",
    "wof:placetype":"venue"
},
  "geometry": {"coordinates":[4.756032,52.06889],"type":"Point"}
}