{
  "type": "Feature",
  "properties": {
    "addr:full":"Vliet Noord Zijde 70 Rijnsburg Zuid-Holland 2231 GP",
    "addr:housenumber":"70",
    "addr:postcode":"2231 gp",
    "addr:street":"Vliet;Zijde",
    "iso:country":"NL",
    "sg:address":"Vliet Noord Zijde 70",
    "sg:city":"Rijnsburg",
    "sg:orig_category":"Fruit And Groenten Gh",
    "sg:phone":"+31 71 402 1323",
    "sg:postcode":"2231 GP",
    "sg:province":"Zuid-Holland",
    "wof:name":"J. Van Vliet & Zonen Cv",
    "wof:placetype":"venue"
},
  "geometry": {"coordinates":[4.445998,52.191257],"type":"Point"}
}