{
  "type": "Feature",
  "properties": {
    "addr:full":"Westrupstraat 23 Sleen Provincie Drenthe 7841 AZ",
    "addr:housenumber":"23",
    "addr:postcode":"7841",
    "addr:street":"Westrupstraat;Provincie Drenthe",
    "iso:country":"NL",
    "sg:address":"Westrupstraat 23",
    "sg:city":"Sleen",
    "sg:orig_category":"Bibliotheken And Openbare Archieven",
    "sg:phone":"+31 591 361 688",
    "sg:postcode":"7841 AZ",
    "sg:province":"Provincie Drenthe",
    "wof:name":"Openbare Bibliotheek Sleen",
    "wof:placetype":"venue"
},
  "geometry": {"coordinates":[6.803185,52.767746],"type":"Point"}
}