{
  "type": "Feature",
  "properties": {
    "addr:full":"Pluuthaven 51 Zeewolde NL. 3891 AW",
    "addr:housenumber":"51",
    "addr:postcode":"3891 aw",
    "addr:street":"Pluuthaven;Nl.",
    "iso:country":"NL",
    "sg:address":"Pluuthaven 51",
    "sg:city":"Zeewolde",
    "sg:orig_category":"Video - Faciliteiten En Producties",
    "sg:phone":"+31 36 522 5252",
    "sg:postcode":"3891 AW",
    "sg:province":"NL.",
    "wof:name":"Adriaan Braamhorst",
    "wof:placetype":"venue"
},
  "geometry": {"coordinates":[5.548129,52.335125],"type":"Point"}
}