{
  "type": "Feature",
  "properties": {
    "iso:country":"NL",
    "sg:address":"De Boelakkers 13",
    "sg:city":"Heeze",
    "sg:orig_category":"Autoreclame",
    "sg:phone":"+31 40 226 2223",
    "sg:postcode":"5591 RA",
    "sg:province":"Noord-Brabant",
    "wof:name":"Marge",
    "wof:placetype":"venue"
},
  "geometry": {"coordinates":[5.585948,51.367413],"type":"Point"}
}