{
  "type": "Feature",
  "properties": {
    "iso:country":"NL",
    "sg:address":"Mierlosewg 16",
    "sg:city":"Helmond",
    "sg:orig_category":"Zoetwaren - Winkels",
    "sg:phone":"+31 492 550 124",
    "sg:postcode":"5707 AM",
    "sg:province":"North Brabant",
    "wof:name":"Drop Inn Helmond",
    "wof:placetype":"venue"
},
  "geometry": {"coordinates":[5.644788,51.476528],"type":"Point"}
}