{
  "type": "Feature",
  "properties": {
    "addr:full":"Mozartln 55 Waddinxveen Zuid-Holland 2742 BP",
    "addr:housenumber":"55",
    "addr:postcode":"2742 bp",
    "addr:street":"Mozartln",
    "iso:country":"NL",
    "sg:address":"Mozartln 55",
    "sg:city":"Waddinxveen",
    "sg:orig_category":"Postzegels",
    "sg:phone":"+31 182 615 136",
    "sg:postcode":"2742 BP",
    "sg:province":"Zuid-Holland",
    "wof:name":"Postzegelverzamelaars, Ned Ver Voor",
    "wof:placetype":"venue"
},
  "geometry": {"coordinates":[4.65507,52.044601],"type":"Point"}
}