{
  "type": "Feature",
  "properties": {
    "iso:country":"NL",
    "sg:address":"Eikenlaan 20",
    "sg:city":"Soest",
    "sg:orig_category":"Verzekeringen",
    "sg:phone":"+31 35 601 5721",
    "sg:postcode":"3768 EV",
    "sg:province":"Utrecht",
    "wof:name":"Ass Kant Secura",
    "wof:placetype":"venue"
},
  "geometry": {"coordinates":[5.307132,52.166569],"type":"Point"}
}