{
  "type": "Feature",
  "properties": {
    "addr:full":"Osdorperwg 247 Amsterdam Noord-Holland 1069 LL",
    "addr:housenumber":"247",
    "addr:postcode":"1069 ll",
    "iso:country":"NL",
    "sg:address":"Osdorperwg 247",
    "sg:city":"Amsterdam",
    "sg:orig_category":"Cafetaria'S",
    "sg:phone":"+31 20 667 1326",
    "sg:postcode":"1069 LL",
    "sg:province":"Noord-Holland",
    "wof:name":"Tuinterras, Het",
    "wof:placetype":"venue"
},
  "geometry": {"coordinates":[4.792563,52.351418],"type":"Point"}
}