{
  "type": "Feature",
  "properties": {
    "addr:full":"Voltastraat 3 Alblasserdam Zuid-Holland 2952 AW",
    "addr:housenumber":"3",
    "addr:postcode":"2952 aw",
    "addr:street":"Voltastraat",
    "iso:country":"NL",
    "sg:address":"Voltastraat 3",
    "sg:city":"Alblasserdam",
    "sg:orig_category":"Fitnesscentra",
    "sg:phone":"+31 78 691 4075",
    "sg:postcode":"2952 AW",
    "sg:province":"Zuid-Holland",
    "wof:name":"Fitness Centr Referee Bv",
    "wof:placetype":"venue"
},
  "geometry": {"coordinates":[4.667228,51.858856],"type":"Point"}
}