{
  "type": "Feature",
  "properties": {
    "addr:full":"Hosterd 23 Puiflyk Gelderland 6655 AD",
    "addr:housenumber":"23",
    "addr:postcode":"6655 ad",
    "addr:street":"Hosterd;Gelderland",
    "iso:country":"NL",
    "sg:address":"Hosterd 23",
    "sg:city":"Puiflyk",
    "sg:orig_category":"Fietsen En Bromfietsen",
    "sg:phone":"+31 487 514 493",
    "sg:postcode":"6655 AD",
    "sg:province":"Gelderland",
    "wof:name":"Dijk, Jos Van",
    "wof:placetype":"venue"
},
  "geometry": {"coordinates":[5.596005,51.880371],"type":"Point"}
}