{
  "type": "Feature",
  "properties": {
    "addr:full":"Geldropsewg 286 Eindhoven Noord-Brabant 5643 TS",
    "addr:housenumber":"286",
    "addr:postcode":"5643 ts",
    "iso:country":"NL",
    "sg:address":"Geldropsewg 286",
    "sg:city":"Eindhoven",
    "sg:orig_category":"Elektrotechnische Apparatuur - Fabrieken En Groothandel",
    "sg:phone":"+31 40 212 2831",
    "sg:postcode":"5643 TS",
    "sg:province":"Noord-Brabant",
    "sg:website":"http://www.marmitek.com",
    "wof:name":"Marmitek Bv",
    "wof:placetype":"venue"
},
  "geometry": {"coordinates":[5.503709,51.430988],"type":"Point"}
}