{
  "type": "Feature",
  "properties": {
    "iso:country":"NL",
    "sg:address":"V Diemenstr 196",
    "sg:city":"S Gravenhage",
    "sg:orig_category":"Zonnebank- En Solariumcentra",
    "sg:phone":"+31 70 427 3704",
    "sg:postcode":"2518 VH",
    "sg:province":"Zuid-Holland",
    "wof:name":"Soecic",
    "wof:placetype":"venue"
},
  "geometry": {"coordinates":[4.29348,52.080318],"type":"Point"}
}