{
  "type": "Feature",
  "properties": {
    "addr:full":"Groenezoom 1 Badhoevedorp North Holland 1171 JA",
    "addr:housenumber":"1",
    "addr:postcode":"1171 ja",
    "addr:street":"Groenezoom",
    "iso:country":"NL",
    "sg:address":"Groenezoom 1",
    "sg:city":"Badhoevedorp",
    "sg:orig_category":"Beveiliging",
    "sg:phone":"+31 20 449 8484",
    "sg:postcode":"1171 JA",
    "sg:province":"North Holland",
    "wof:name":"B & M",
    "wof:placetype":"venue"
},
  "geometry": {"coordinates":[4.786125,52.334839],"type":"Point"}
}