{
  "type": "Feature",
  "properties": {
    "addr:full":"Van Slingelandtplein 1 Amsterdam Noord-Holland 1051 DD",
    "addr:housenumber":"1",
    "addr:postcode":"1051 dd",
    "addr:street":"Van Slingelandtplein",
    "iso:country":"NL",
    "sg:address":"Van Slingelandtplein 1",
    "sg:city":"Amsterdam",
    "sg:orig_category":"Metaalbekleding And -Behandeling",
    "sg:phone":"+31 20 684 7540",
    "sg:postcode":"1051 DD",
    "sg:province":"Noord-Holland",
    "wof:name":"Senometaal",
    "wof:placetype":"venue"
},
  "geometry": {"coordinates":[4.864513,52.383774],"type":"Point"}
}