{
  "type": "Feature",
  "properties": {
    "addr:full":"Christinelaan 12 Weert Limburg 6006 CJ",
    "addr:housenumber":"12",
    "addr:postcode":"6006 cj",
    "addr:street":"Christinelaan",
    "iso:country":"NL",
    "sg:address":"Christinelaan 12",
    "sg:city":"Weert",
    "sg:orig_category":"Artsen And Specialisten",
    "sg:phone":"+31 495 534 526",
    "sg:postcode":"6006 CJ",
    "sg:province":"Limburg",
    "wof:name":"Huisartsenpraktijk",
    "wof:placetype":"venue"
},
  "geometry": {"coordinates":[5.710635,51.243114],"type":"Point"}
}