{
  "type": "Feature",
  "properties": {
    "addr:full":"Eddingtonwg 9 Dordrecht Zuid-Holland 3318 BE",
    "addr:housenumber":"9",
    "addr:postcode":"3318",
    "addr:street":"Eddingtonwg",
    "iso:country":"NL",
    "sg:address":"Eddingtonwg 9",
    "sg:city":"Dordrecht",
    "sg:orig_category":"Scholen Voor Basisonderwijs",
    "sg:phone":"+31 78 617 6490",
    "sg:postcode":"3318 BE",
    "sg:province":"Zuid-Holland",
    "wof:name":"Repelaer, Cbs De",
    "wof:placetype":"venue"
},
  "geometry": {"coordinates":[4.68293,51.789371],"type":"Point"}
}