{
  "type": "Feature",
  "properties": {
    "addr:full":"G Deynootwg 1302 S Gravenhage Zuid-Holland 2586 HP",
    "addr:housenumber":"1302;gravenhage",
    "addr:postcode":"2586 hp",
    "addr:street":"S",
    "iso:country":"NL",
    "sg:address":"G Deynootwg 1302",
    "sg:city":"S Gravenhage",
    "sg:classifiers":[
        {
            "category":"Travel",
            "subcategory":"Hotels & Motels",
            "type":"Entertainment"
        }
    ],
    "sg:phone":"+31 70 355 2606",
    "sg:postcode":"2586 HP",
    "sg:province":"Zuid-Holland",
    "sg:website":"http://www.hotelzonnester.nl",
    "wof:name":"Zonnester",
    "wof:placetype":"venue"
},
  "geometry": {"coordinates":[4.277215,52.10672],"type":"Point"}
}