{
  "type": "Feature",
  "properties": {
    "addr:full":"M Ravelstr 88 Zaandyk North Holland 1544 MN",
    "addr:housenumber":"88",
    "addr:postcode":"1544 mn",
    "addr:street":"Zaandyk North",
    "iso:country":"NL",
    "sg:address":"M Ravelstr 88",
    "sg:city":"Zaandyk",
    "sg:orig_category":"Autorijscholen",
    "sg:phone":"+31 75 621 0661",
    "sg:postcode":"1544 MN",
    "sg:province":"North Holland",
    "wof:name":"Integra",
    "wof:placetype":"venue"
},
  "geometry": {"coordinates":[4.812078,52.475719],"type":"Point"}
}