{
  "type": "Feature",
  "properties": {
    "iso:country":"NL",
    "sg:address":"Burgemeester V Waningln 88",
    "sg:city":"Leek",
    "sg:orig_category":"Paramedische Behandelingen",
    "sg:phone":"+31 594 513 345",
    "sg:postcode":"9351 LW",
    "sg:province":"Groningen",
    "wof:name":"E.G. Driehuizen-Miedema",
    "wof:placetype":"venue"
},
  "geometry": {"coordinates":[6.36884,53.167374],"type":"Point"}
}