{
  "type": "Feature",
  "properties": {
    "addr:full":"Baarlesewg 44 Chaam North Brabant 4861 BT",
    "addr:housenumber":"44",
    "addr:postcode":"4861 bt",
    "addr:street":"Baarlesewg",
    "iso:country":"NL",
    "sg:address":"Baarlesewg 44",
    "sg:city":"Chaam",
    "sg:orig_category":"Meubelen",
    "sg:phone":"+31 161 491 602",
    "sg:postcode":"4861 BT",
    "sg:province":"North Brabant",
    "wof:name":"Magra Meubelen",
    "wof:placetype":"venue"
},
  "geometry": {"coordinates":[4.87101,51.499966],"type":"Point"}
}