{
  "type": "Feature",
  "properties": {
    "iso:country":"NL",
    "sg:address":"Kerkpad 7",
    "sg:city":"Groesbeek",
    "sg:orig_category":"Verenigingsgebouwen",
    "sg:phone":"+31 24 397 1570",
    "sg:postcode":"6562 GA",
    "sg:province":"Gelderland",
    "wof:name":"K\u00f6rf, De",
    "wof:placetype":"venue"
},
  "geometry": {"coordinates":[5.940698,51.75798],"type":"Point"}
}