{
  "type": "Feature",
  "properties": {
    "addr:full":"Diedenwg 15 Wageningen Gelderland 6703 GS",
    "addr:housenumber":"15",
    "addr:postcode":"6703 gs",
    "addr:street":"Diedenwg;Gelderland",
    "iso:country":"NL",
    "sg:address":"Diedenwg 15",
    "sg:city":"Wageningen",
    "sg:orig_category":"Kantoor- En Secretariaatsservice",
    "sg:phone":"+31 317 417 892",
    "sg:postcode":"6703 GS",
    "sg:province":"Gelderland",
    "wof:name":"Roetgerink",
    "wof:placetype":"venue"
},
  "geometry": {"coordinates":[5.6839132309,51.9687576294],"type":"Point"}
}