{
  "type": "Feature",
  "properties": {
    "addr:full":"Achter Het Vleeshuis 42B Maastricht Limburg 6211 GS",
    "addr:housenumber":"42b",
    "addr:postcode":"6211 gs",
    "addr:street":"Achter Het Vleeshuis",
    "iso:country":"NL",
    "sg:address":"Achter Het Vleeshuis 42B",
    "sg:city":"Maastricht",
    "sg:orig_category":"Geluidsopnamen",
    "sg:phone":"+31 43 351 0900",
    "sg:postcode":"6211 GS",
    "sg:province":"Limburg",
    "wof:name":"Soundtrack Productions",
    "wof:placetype":"venue"
},
  "geometry": {"coordinates":[5.690962,50.849075],"type":"Point"}
}