{
  "type": "Feature",
  "properties": {
    "addr:full":"Simonskerkestr 27 Kerkwerve Zeeland 4321 AS",
    "addr:housenumber":"27",
    "addr:postcode":"4321 as",
    "addr:street":"Simonskerkestr",
    "iso:country":"NL",
    "sg:address":"Simonskerkestr 27",
    "sg:city":"Kerkwerve",
    "sg:orig_category":"Administratie- En Boekhoudkantoren",
    "sg:phone":"+31 6 53744472",
    "sg:postcode":"4321 AS",
    "sg:province":"Zeeland",
    "wof:name":"Kan, Van",
    "wof:placetype":"venue"
},
  "geometry": {"coordinates":[3.895498,51.684677],"type":"Point"}
}