{
  "type": "Feature",
  "properties": {
    "addr:full":"Schubertstr 6 Amsterdam Noord-Holland 1077 GS",
    "addr:housenumber":"6",
    "addr:postcode":"1077 gs",
    "addr:street":"Schubertstr",
    "iso:country":"NL",
    "sg:address":"Schubertstr 6",
    "sg:city":"Amsterdam",
    "sg:orig_category":"Vertalers",
    "sg:phone":"+31 20 671 4784",
    "sg:postcode":"1077 GS",
    "sg:province":"Noord-Holland",
    "wof:name":"Smithuysen-Bauschen, J M",
    "wof:placetype":"venue"
},
  "geometry": {"coordinates":[4.877889,52.34816],"type":"Point"}
}