{
  "type": "Feature",
  "properties": {
    "iso:country":"NL",
    "sg:address":"Antillenstraat 9",
    "sg:city":"Groningen",
    "sg:orig_category":"Fitnesscentra",
    "sg:phone":"+31 50 577 7343",
    "sg:postcode":"9714 JT",
    "sg:province":"Groningen",
    "wof:name":"The Total Workout",
    "wof:placetype":"venue"
},
  "geometry": {"coordinates":[6.579898,53.23447],"type":"Point"}
}