{
  "type": "Feature",
  "properties": {
    "iso:country":"NL",
    "sg:address":"Nobelstr 9",
    "sg:city":"Oud Beyerland",
    "sg:orig_category":"Verenigingen En Stichtingen",
    "sg:phone":"+31 186 614 193",
    "sg:postcode":"3262 PL",
    "sg:province":"South Holland",
    "wof:name":"Platform Uitkeringsgerechtigde, Sticht",
    "wof:placetype":"venue"
},
  "geometry": {"coordinates":[4.409651,51.826298],"type":"Point"}
}