{
  "type": "Feature",
  "properties": {
    "addr:full":"Tortonapln 13 Zevenaar Gelderland 6904 MK",
    "addr:housenumber":"13",
    "addr:postcode":"6904",
    "addr:street":"Tortonapln",
    "iso:country":"NL",
    "sg:address":"Tortonapln 13",
    "sg:city":"Zevenaar",
    "sg:orig_category":"Verzekeringen - Verzekeringskantoren",
    "sg:phone":"+31 316 341 613",
    "sg:postcode":"6904 MK",
    "sg:province":"Gelderland",
    "wof:name":"Feldmann",
    "wof:placetype":"venue"
},
  "geometry": {"coordinates":[6.055549,51.931461],"type":"Point"}
}