{
  "type": "Feature",
  "properties": {
    "addr:full":"Smedenstr 278 Deventer NL.08 7411 RD",
    "addr:housenumber":"278;nl.08",
    "addr:postcode":"7411 rd",
    "iso:country":"NL",
    "sg:address":"Smedenstr 278",
    "sg:city":"Deventer",
    "sg:orig_category":"Verenigingen En Stichtingen",
    "sg:phone":"+31 570 616 111",
    "sg:postcode":"7411 RD",
    "sg:province":"NL.08",
    "wof:name":"Hbv Kd Culture Ver",
    "wof:placetype":"venue"
},
  "geometry": {"coordinates":[6.153253,52.255859],"type":"Point"}
}