{
  "type": "Feature",
  "properties": {
    "addr:full":"Eikbosserwg 122 Hilversum Noord-Holland 1214 AL",
    "addr:housenumber":"122",
    "addr:postcode":"hilversum;1214 al",
    "iso:country":"NL",
    "sg:address":"Eikbosserwg 122",
    "sg:city":"Hilversum",
    "sg:orig_category":"Onroerende Goederen",
    "sg:phone":"+31 35 629 5666",
    "sg:postcode":"1214 AL",
    "sg:province":"Noord-Holland",
    "wof:name":"Kooistra, K R",
    "wof:placetype":"venue"
},
  "geometry": {"coordinates":[5.17442,52.215649],"type":"Point"}
}