{
  "type": "Feature",
  "properties": {
    "addr:full":"Nederlandplein 108 Eindhoven Noord-Brabant 5628 AJ",
    "addr:housenumber":"108",
    "addr:postcode":"5628 aj",
    "addr:street":"Nederlandplein",
    "iso:country":"NL",
    "sg:address":"Nederlandplein 108",
    "sg:city":"Eindhoven",
    "sg:classifiers":[
        {
            "category":"Fast Food",
            "type":"Food & Drink"
        }
    ],
    "sg:phone":"+31 40 241 2740",
    "sg:postcode":"5628 AJ",
    "sg:province":"Noord-Brabant",
    "sg:tags":[
        "afhaal",
        "restaurant"
    ],
    "wof:name":"Snackbar Woenselse Heide",
    "wof:placetype":"venue"
},
  "geometry": {"coordinates":[5.463122,51.478848],"type":"Point"}
}