{
  "type": "Feature",
  "properties": {
    "addr:full":"Burgemeester Falkenaweg 91 Heerenveen Friesland 8442 LB",
    "addr:housenumber":"91",
    "addr:postcode":"8442 lb",
    "addr:street":"Burgemeester Falkenaweg",
    "iso:country":"NL",
    "sg:address":"Burgemeester Falkenaweg 91",
    "sg:city":"Heerenveen",
    "sg:orig_category":"Metaalwerken",
    "sg:phone":"+31 513 622 666",
    "sg:postcode":"8442 LB",
    "sg:province":"Friesland",
    "wof:name":"Zonweringbedrijf A.Veldman Bv",
    "wof:placetype":"venue"
},
  "geometry": {"coordinates":[5.932046,52.952988],"type":"Point"}
}