{
  "type": "Feature",
  "properties": {
    "addr:full":"Raadhuisplein 2 Meerkerk Zuid-Holland 4231 BZ",
    "addr:housenumber":"2",
    "addr:postcode":"4231 bz",
    "addr:street":"Raadhuisplein",
    "iso:country":"NL",
    "sg:address":"Raadhuisplein 2",
    "sg:city":"Meerkerk",
    "sg:orig_category":"Fruit And Groenten Gh",
    "sg:phone":"+31 183 352 242",
    "sg:postcode":"4231 BZ",
    "sg:province":"Zuid-Holland",
    "wof:name":"Snelle Pieper",
    "wof:placetype":"venue"
},
  "geometry": {"coordinates":[4.995663,51.92086],"type":"Point"}
}