{
  "type": "Feature",
  "properties": {
    "addr:full":"Sportlaan 1 Andijk North Holland 1619 XE",
    "addr:housenumber":"1",
    "addr:postcode":"1619 xe",
    "addr:street":"Sportlaan",
    "iso:country":"NL",
    "sg:address":"Sportlaan 1",
    "sg:city":"Andijk",
    "sg:orig_category":"Overheidsdiensten",
    "sg:phone":"+31 228 591 289",
    "sg:postcode":"1619 XE",
    "sg:province":"North Holland",
    "wof:name":"Dorpshuis Andijk",
    "wof:placetype":"venue"
},
  "geometry": {"coordinates":[5.2208299637,52.7479743958],"type":"Point"}
}