{
  "type": "Feature",
  "properties": {
    "addr:full":"Kon Emmapln 1 Rotterdam Zuid-Holland 3016 AA",
    "addr:housenumber":"1",
    "addr:postcode":"3016 aa",
    "addr:street":"Kon Emmapln",
    "iso:country":"NL",
    "sg:address":"Kon Emmapln 1",
    "sg:city":"Rotterdam",
    "sg:orig_category":"Dameskleding",
    "sg:phone":"+31 10 436 7088",
    "sg:postcode":"3016 AA",
    "sg:province":"Zuid-Holland",
    "sg:website":"http://www.josexler.nl",
    "wof:name":"Exler, Jos",
    "wof:placetype":"venue"
},
  "geometry": {"coordinates":[4.475606,51.910561],"type":"Point"}
}