{
  "type": "Feature",
  "properties": {
    "addr:full":"Prestwickwg 56 Luchth Schiphol Noord-Holland 1118 LB",
    "addr:housenumber":"56",
    "addr:postcode":"1118 lb",
    "addr:street":"Prestwickwg",
    "iso:country":"NL",
    "sg:address":"Prestwickwg 56",
    "sg:city":"Luchth Schiphol",
    "sg:orig_category":"Luchtvrachtexpediteurs",
    "sg:phone":"+31 20 405 9900",
    "sg:postcode":"1118 LB",
    "sg:province":"Noord-Holland",
    "sg:website":"http://www.mollogistics.nl",
    "wof:name":"Mol Netherlands Bv",
    "wof:placetype":"venue"
},
  "geometry": {"coordinates":[4.766775,52.291405],"type":"Point"}
}