{
  "type": "Feature",
  "properties": {
    "addr:full":"Borgesiuslaan 47 Amersfoort Utrecht 3818 JV",
    "addr:housenumber":"47",
    "addr:postcode":"3818 jv",
    "addr:street":"Borgesiuslaan",
    "iso:country":"NL",
    "sg:address":"Borgesiuslaan 47",
    "sg:city":"Amersfoort",
    "sg:orig_category":"Vertaal- And Tolkenbureaus",
    "sg:phone":"+31 33 461 3313",
    "sg:postcode":"3818 JV",
    "sg:province":"Utrecht",
    "wof:name":"Spaans Vertaalbureau",
    "wof:placetype":"venue"
},
  "geometry": {"coordinates":[5.357954,52.150551],"type":"Point"}
}