{
  "type": "Feature",
  "properties": {
    "iso:country":"NL",
    "sg:address":"Wg-Plein 650",
    "sg:city":"Amsterdam",
    "sg:orig_category":"Verlichting And Huishoudartikelen",
    "sg:phone":"+31 20 689 2682",
    "sg:postcode":"1054 SK",
    "sg:province":"Noord-Holland",
    "wof:name":"Polti Products Bv",
    "wof:placetype":"venue"
},
  "geometry": {"coordinates":[4.871949,52.364506],"type":"Point"}
}