{
  "type": "Feature",
  "properties": {
    "addr:full":"Edisonstraat 22 Zevenaar Gelderland 6902 PK",
    "addr:housenumber":"22",
    "addr:postcode":"6902 pk",
    "addr:street":"Edisonstraat",
    "iso:country":"NL",
    "sg:address":"Edisonstraat 22",
    "sg:city":"Zevenaar",
    "sg:orig_category":"Goederenvervoer Over De Weg",
    "sg:phone":"+31 316 524 370",
    "sg:postcode":"6902 PK",
    "sg:province":"Gelderland",
    "wof:name":"G. Van Leeuwen",
    "wof:placetype":"venue"
},
  "geometry": {"coordinates":[6.085858,51.938931],"type":"Point"}
}