{
  "type": "Feature",
  "properties": {
    "iso:country":"NL",
    "sg:address":"Prunuslaan 9",
    "sg:city":"Amstelveen",
    "sg:orig_category":"Vertaal- And Tolkenbureaus",
    "sg:phone":"+31 20 641 2612",
    "sg:postcode":"1185 KS",
    "sg:province":"Noord-Holland",
    "wof:name":"Oraby Vertaalburo",
    "wof:placetype":"venue"
},
  "geometry": {"coordinates":[4.847416,52.295422],"type":"Point"}
}