{
  "type": "Feature",
  "properties": {
    "iso:country":"NL",
    "sg:address":"Molenstraat 19",
    "sg:city":"Berlicum Nb",
    "sg:orig_category":"Loodgieterswerk, Verwarming And Sanitaire Installaties",
    "sg:phone":"+31 73 503 1700",
    "sg:postcode":"5258 LH",
    "sg:province":"North Brabant",
    "wof:name":"Vof J. Wilmink En J.W. Wilmink",
    "wof:placetype":"venue"
},
  "geometry": {"coordinates":[5.419425,51.666],"type":"Point"}
}