{
  "type": "Feature",
  "properties": {
    "addr:full":"Burgemeester Bruntstraat 1 Nieuwerbrug Zuid-Holland 2415 AJ",
    "addr:housenumber":"1",
    "addr:postcode":"2415 aj",
    "addr:street":"Burgemeester Bruntstraat",
    "iso:country":"NL",
    "sg:address":"Burgemeester Bruntstraat 1",
    "sg:city":"Nieuwerbrug",
    "sg:orig_category":"Goederenvervoer Over De Weg",
    "sg:phone":"+31 348 688 269",
    "sg:postcode":"2415 AJ",
    "sg:province":"Zuid-Holland",
    "wof:name":"Transportbedrijf Th.J. Van Schaik Bv",
    "wof:placetype":"venue"
},
  "geometry": {"coordinates":[4.819272,52.077759],"type":"Point"}
}