{
  "type": "Feature",
  "properties": {
    "addr:full":"H Heyermansln 8 Vlissingen Zeeland 4382 BR",
    "addr:housenumber":"8",
    "addr:postcode":"4382 br",
    "iso:country":"NL",
    "sg:address":"H Heyermansln 8",
    "sg:city":"Vlissingen",
    "sg:orig_category":"Bloemen En Planten - Decoratie",
    "sg:phone":"+31 118 418 500",
    "sg:postcode":"4382 BR",
    "sg:province":"Zeeland",
    "wof:name":"Beach Rose, The",
    "wof:placetype":"venue"
},
  "geometry": {"coordinates":[3.561711,51.451897],"type":"Point"}
}