{
  "type": "Feature",
  "properties": {
    "addr:full":"Dissel 146 Maarheeze Noord-Brabant 6026 DD",
    "addr:housenumber":"146",
    "addr:postcode":"6026 dd",
    "addr:street":"Dissel",
    "iso:country":"NL",
    "sg:address":"Dissel 146",
    "sg:city":"Maarheeze",
    "sg:orig_category":"Adviesbureaus Bedrijfsorganisatie",
    "sg:phone":"+31 495 592 238",
    "sg:postcode":"6026 DD",
    "sg:province":"Noord-Brabant",
    "wof:name":"Li\u00e9geois Consult",
    "wof:placetype":"venue"
},
  "geometry": {"coordinates":[5.617186,51.318882],"type":"Point"}
}