{
  "type": "Feature",
  "properties": {
    "addr:full":"Magnoliastraat 19 Steenbergen Nb Noord-Brabant 4651 LC",
    "addr:housenumber":"19",
    "addr:postcode":"4651 lc",
    "addr:street":"Magnoliastraat",
    "iso:country":"NL",
    "sg:address":"Magnoliastraat 19",
    "sg:city":"Steenbergen Nb",
    "sg:orig_category":"Loodgieterswerk, Verwarming And Sanitaire Installaties",
    "sg:phone":"+31 167 561 501",
    "sg:postcode":"4651 LC",
    "sg:province":"Noord-Brabant",
    "wof:name":"V. Beers Installatietechniek",
    "wof:placetype":"venue"
},
  "geometry": {"coordinates":[4.317302,51.578251],"type":"Point"}
}