{
  "type": "Feature",
  "properties": {
    "addr:full":"Rusthoekstraat 9 'S Gravenhage South Holland 2584 CP",
    "addr:housenumber":"9 '",
    "addr:postcode":"2584 cp",
    "addr:street":"Rusthoekstraat",
    "iso:country":"NL",
    "sg:address":"Rusthoekstraat 9",
    "sg:city":"'S Gravenhage",
    "sg:orig_category":"Public Relationbureaus",
    "sg:phone":"+31 70 358 5450",
    "sg:postcode":"2584 CP",
    "sg:province":"South Holland",
    "wof:name":"Newdawn Tekstproductie",
    "wof:placetype":"venue"
},
  "geometry": {"coordinates":[4.281696,52.101467],"type":"Point"}
}