{
  "type": "Feature",
  "properties": {
    "iso:country":"NL",
    "sg:address":"Postbus 237",
    "sg:city":"Sas Van Gent",
    "sg:orig_category":"Scholen Voor Basisonderwijs",
    "sg:phone":"+31 115 460 041",
    "sg:postcode":"4550 AE",
    "sg:province":"Zeeland",
    "wof:name":"Valckeburcht Rk, De",
    "wof:placetype":"venue"
},
  "geometry": {"coordinates":[3.79446,51.2295],"type":"Point"}
}