{
  "type": "Feature",
  "properties": {
    "addr:full":"De Indus 15 Drunen Noord-Brabant 5152 VC",
    "addr:housenumber":"15",
    "addr:postcode":"5152 vc",
    "addr:street":"De Indus",
    "iso:country":"NL",
    "sg:address":"De Indus 15",
    "sg:city":"Drunen",
    "sg:orig_category":"Bloemen And Planten Gh",
    "sg:phone":"+31 416 375 491",
    "sg:postcode":"5152 VC",
    "sg:province":"Noord-Brabant",
    "wof:name":"Jack Van Hulten Vof",
    "wof:placetype":"venue"
},
  "geometry": {"coordinates":[5.11784,51.680527],"type":"Point"}
}