{
  "type": "Feature",
  "properties": {
    "addr:full":"V Roosmalenpln 4 S Hertogenbosch Noord-Brabant 5213 GC",
    "addr:housenumber":"4",
    "addr:postcode":"5213 gc",
    "addr:street":"Roosmalenpln",
    "iso:country":"NL",
    "sg:address":"V Roosmalenpln 4",
    "sg:city":"S Hertogenbosch",
    "sg:orig_category":"Kappers",
    "sg:phone":"+31 73 690 1250",
    "sg:postcode":"5213 GC",
    "sg:province":"Noord-Brabant",
    "sg:website":"http://www.hoepelman.nl",
    "wof:name":"Hoepelman",
    "wof:placetype":"venue"
},
  "geometry": {"coordinates":[5.2982401848,51.6907501221],"type":"Point"}
}