{
  "type": "Feature",
  "properties": {
    "iso:country":"NL",
    "sg:address":"Zeestr 24",
    "sg:city":"Beverwyk",
    "sg:orig_category":"Amusementshallen",
    "sg:phone":"+31 251 228 185",
    "sg:postcode":"1942 AR",
    "sg:province":"Noord-Holland",
    "wof:name":"Play Corner",
    "wof:placetype":"venue"
},
  "geometry": {"coordinates":[4.654041,52.481255],"type":"Point"}
}