{
  "type": "Feature",
  "properties": {
    "iso:country":"NL",
    "sg:address":"Minosstr 11",
    "sg:city":"Tilburg",
    "sg:orig_category":"Kunststof Ramen",
    "sg:phone":"+31 13 456 2426",
    "sg:postcode":"5048 CK",
    "sg:province":"Noord-Brabant",
    "sg:website":"http://www.abckozijnen.nl",
    "wof:name":"Abc Kozijnen Nederland",
    "wof:placetype":"venue"
},
  "geometry": {"coordinates":[5.032474,51.5966],"type":"Point"}
}