{
  "type": "Feature",
  "properties": {
    "iso:country":"NL",
    "sg:address":"Orchideestr 10A",
    "sg:city":"Hilversum",
    "sg:orig_category":"Kinderopvang",
    "sg:phone":"+31 35 621 0720",
    "sg:postcode":"1214 BJ",
    "sg:province":"North Holland",
    "wof:name":"Tovertuin, De",
    "wof:placetype":"venue"
},
  "geometry": {"coordinates":[5.171994,52.214966],"type":"Point"}
}