{
  "type": "Feature",
  "properties": {
    "addr:full":"Oude Markt 24 Enschede Overijssel 7511 GB",
    "addr:housenumber":"24",
    "addr:postcode":"7511 gb",
    "addr:street":"Oude Markt",
    "iso:country":"NL",
    "sg:address":"Oude Markt 24",
    "sg:city":"Enschede",
    "sg:orig_category":"Verenigingsgebouwen",
    "sg:phone":"+31 53 432 4357",
    "sg:postcode":"7511 GB",
    "sg:province":"Overijssel",
    "wof:name":"Soc T R A M, Sticht",
    "wof:placetype":"venue"
},
  "geometry": {"coordinates":[6.896439,52.22068],"type":"Point"}
}