{
  "type": "Feature",
  "properties": {
    "addr:full":"Gemeentewg 179 Staphorst Overijssel 7951 CJ",
    "addr:housenumber":"179",
    "addr:postcode":"7951 cj",
    "iso:country":"NL",
    "sg:address":"Gemeentewg 179",
    "sg:city":"Staphorst",
    "sg:orig_category":"Keukens",
    "sg:phone":"+31 522 461 255",
    "sg:postcode":"7951 CJ",
    "sg:province":"Overijssel",
    "wof:name":"Tuin & Zn Bv, B",
    "wof:placetype":"venue"
},
  "geometry": {"coordinates":[6.216083,52.649143],"type":"Point"}
}