{
  "type": "Feature",
  "properties": {
    "iso:country":"NL",
    "sg:address":"Postbus 2100",
    "sg:city":"Vlaardingen",
    "sg:orig_category":"Verenigingen En Stichtingen",
    "sg:phone":"+31 10 234 0035",
    "sg:postcode":"3130 BC",
    "sg:province":"South Holland",
    "sg:website":"http://www.junior-planet.com",
    "wof:name":"Junior, Stichting",
    "wof:placetype":"venue"
},
  "geometry": {"coordinates":[4.340359,51.910442],"type":"Point"}
}