{
  "type": "Feature",
  "properties": {
    "addr:full":"Postbus 592 Honselersdyk Zuid-Holland 2675 ZV",
    "addr:housenumber":"592",
    "addr:postcode":"2675 zv",
    "addr:street":"Postbus",
    "iso:country":"NL",
    "sg:address":"Postbus 592",
    "sg:city":"Honselersdyk",
    "sg:orig_category":"Bloemen En Planten - Decoratie",
    "sg:phone":"+31 174 629 888",
    "sg:postcode":"2675 ZV",
    "sg:province":"Zuid-Holland",
    "wof:name":"Wbe",
    "wof:placetype":"venue"
},
  "geometry": {"coordinates":[4.22951,52.008755],"type":"Point"}
}