{
  "type": "Feature",
  "properties": {
    "iso:country":"NL",
    "sg:address":"Hoofdwg 1334B",
    "sg:city":"Nieuw Vennep",
    "sg:orig_category":"Verzekeringen - Verzekeringskantoren",
    "sg:phone":"+31 252 623 010",
    "sg:postcode":"2153 LT",
    "sg:province":"North Holland",
    "sg:website":"http://www.fin-spec.nl",
    "wof:name":"Financieel Spectrum, 'T",
    "wof:placetype":"venue"
},
  "geometry": {"coordinates":[4.632583,52.263145],"type":"Point"}
}