{
  "type": "Feature",
  "properties": {
    "addr:full":"Schouwburgring 2 Tilburg North Brabant 5038 TL",
    "addr:housenumber":"2",
    "addr:postcode":"5038 tl",
    "addr:street":"Schouwburgring",
    "iso:country":"NL",
    "sg:address":"Schouwburgring 2",
    "sg:city":"Tilburg",
    "sg:orig_category":"Werving And Selectie Van Tijdelijk Personeel And Uitzendkantoren",
    "sg:phone":"+31 13 532 2700",
    "sg:postcode":"5038 TL",
    "sg:province":"North Brabant",
    "wof:name":"Randstad Uitzendbureau Bv",
    "wof:placetype":"venue"
},
  "geometry": {"coordinates":[5.0820121765,51.5545578003],"type":"Point"}
}