{
  "type": "Feature",
  "properties": {
    "iso:country":"NL",
    "sg:address":"Bornerbroeksestr 111",
    "sg:city":"Ambt Delden",
    "sg:orig_category":"Betonwerken",
    "sg:phone":"+31 74 384 1816",
    "sg:postcode":"7495 TT",
    "sg:province":"NL.08",
    "wof:name":"Platenkamp Bv",
    "wof:placetype":"venue"
},
  "geometry": {"coordinates":[6.671403,52.284904],"type":"Point"}
}