{
  "type": "Feature",
  "properties": {
    "iso:country":"NL",
    "sg:address":"Hoofdstraat 8",
    "sg:city":"Warffum",
    "sg:orig_category":"Metaalbekleding And -Behandeling",
    "sg:phone":"+31 595 423 366",
    "sg:postcode":"9989 AN",
    "sg:province":"Groningen",
    "wof:name":"Smederij/Atelier Ron Caspers",
    "wof:placetype":"venue"
},
  "geometry": {"coordinates":[6.560589,53.392719],"type":"Point"}
}