{
  "type": "Feature",
  "properties": {
    "addr:full":"Hoofdstraat 8 Warffum Groningen 9989 AN",
    "addr:housenumber":"8",
    "addr:postcode":"9989 an",
    "addr:street":"Hoofdstraat",
    "iso:country":"NL",
    "sg:address":"Hoofdstraat 8",
    "sg:city":"Warffum",
    "sg:orig_category":"Metaalbekleding And -Behandeling",
    "sg:phone":"+31 595 423 366",
    "sg:postcode":"9989 AN",
    "sg:province":"Groningen",
    "wof:name":"Smederij/Atelier Ron Caspers",
    "wof:placetype":"venue"
},
  "geometry": {"coordinates":[6.560589,53.392719],"type":"Point"}
}