{
  "type": "Feature",
  "properties": {
    "addr:full":"Balistr 51 S Gravenhage South Holland 2585 XM",
    "addr:housenumber":"51",
    "addr:postcode":"2585 xm",
    "addr:street":"Balistr;S Gravenhage",
    "iso:country":"NL",
    "sg:address":"Balistr 51",
    "sg:city":"S Gravenhage",
    "sg:orig_category":"Fotografie Reclame En Mode",
    "sg:phone":"+31 70 390 7501",
    "sg:postcode":"2585 XM",
    "sg:province":"South Holland",
    "sg:website":"http://www.michelmees.com",
    "wof:name":"Mees, Michel",
    "wof:placetype":"venue"
},
  "geometry": {"coordinates":[4.29777,52.094799],"type":"Point"}
}