{
  "type": "Feature",
  "properties": {
    "addr:full":"Alb Van Beierenstraat 73 Hoogwoud North Holland 1718 XH",
    "addr:housenumber":"73",
    "addr:postcode":"1718 xh",
    "addr:street":"Alb Van Beierenstraat",
    "iso:country":"NL",
    "sg:address":"Alb Van Beierenstraat 73",
    "sg:city":"Hoogwoud",
    "sg:orig_category":"Vertaal- And Tolkenbureaus",
    "sg:phone":"+31 226 355 424",
    "sg:postcode":"1718 XH",
    "sg:province":"North Holland",
    "wof:name":"Instituut Wartburg",
    "wof:placetype":"venue"
},
  "geometry": {"coordinates":[4.935764,52.711903],"type":"Point"}
}