{
  "type": "Feature",
  "properties": {
    "iso:country":"NL",
    "sg:address":"Marktstraat 27",
    "sg:city":"Meppel",
    "sg:orig_category":"Bibliotheken And Openbare Archieven",
    "sg:phone":"+31 522 241 814",
    "sg:postcode":"7941 KP",
    "sg:province":"Provincie Drenthe",
    "wof:name":"Openbare Bibliotheek",
    "wof:placetype":"venue"
},
  "geometry": {"coordinates":[6.195295,52.697865],"type":"Point"}
}