{
  "type": "Feature",
  "properties": {
    "addr:full":"Tolhuiswg 12 Heerenveen Friesland 8443 DW",
    "addr:housenumber":"12",
    "addr:postcode":"8443 dw",
    "addr:street":"Tolhuiswg",
    "iso:country":"NL",
    "sg:address":"Tolhuiswg 12",
    "sg:city":"Heerenveen",
    "sg:orig_category":"Banken",
    "sg:phone":"+31 513 655 380",
    "sg:postcode":"8443 DW",
    "sg:province":"Friesland",
    "sg:website":"http://www.rabobank.nl",
    "wof:name":"Rabobank",
    "wof:placetype":"venue"
},
  "geometry": {"coordinates":[5.943491,52.943153],"type":"Point"}
}