{
  "type": "Feature",
  "properties": {
    "addr:full":"Archimedesstraat 20 Dordrecht South Holland 3316 AB",
    "addr:housenumber":"20",
    "addr:postcode":"3316 ab",
    "addr:street":"Archimedesstraat",
    "iso:country":"NL",
    "sg:address":"Archimedesstraat 20",
    "sg:city":"Dordrecht",
    "sg:orig_category":"Etaleurs And Showroominrichters",
    "sg:phone":"+31 78 654 0095",
    "sg:postcode":"3316 AB",
    "sg:province":"South Holland",
    "wof:name":"Wemove",
    "wof:placetype":"venue"
},
  "geometry": {"coordinates":[4.646251,51.799686],"type":"Point"}
}