{
  "type": "Feature",
  "properties": {
    "iso:country":"NL",
    "sg:address":"Stationsln 34",
    "sg:city":"Nunspeet",
    "sg:orig_category":"Verenigingen En Stichtingen",
    "sg:phone":"+31 341 262 311",
    "sg:postcode":"8071 CM",
    "sg:province":"Gelderland",
    "wof:name":"Soc Cult Werk De Volksbond, Sticht",
    "wof:placetype":"venue"
},
  "geometry": {"coordinates":[5.772205,52.374981],"type":"Point"}
}