{
  "type": "Feature",
  "properties": {
    "iso:country":"NL",
    "sg:address":"Smithstraat 18",
    "sg:city":"Nunspeet",
    "sg:orig_category":"Schilderwerk",
    "sg:phone":"+31 341 256 305",
    "sg:postcode":"8071 KW",
    "sg:province":"Gelderland",
    "wof:name":"Nebro Schilderwerken",
    "wof:placetype":"venue"
},
  "geometry": {"coordinates":[5.762808,52.369858],"type":"Point"}
}