{
  "type": "Feature",
  "properties": {
    "addr:full":"Berenkoog 11 Alkmaar Noord-Holland 1822 BH",
    "addr:housenumber":"11",
    "addr:postcode":"1822 bh",
    "addr:street":"Berenkoog",
    "iso:country":"NL",
    "sg:address":"Berenkoog 11",
    "sg:city":"Alkmaar",
    "sg:orig_category":"Boekenuitgeverijen",
    "sg:phone":"+31 72 567 0000",
    "sg:postcode":"1822 BH",
    "sg:province":"Noord-Holland",
    "wof:name":"Buro Extern Bv",
    "wof:placetype":"venue"
},
  "geometry": {"coordinates":[4.781664,52.644268],"type":"Point"}
}