{
  "type": "Feature",
  "properties": {
    "addr:full":"Claudiusdreef 28 Valkenburg Zh Zuid-Holland 2235 AV",
    "addr:housenumber":"28",
    "addr:postcode":"2235 av",
    "addr:street":"Claudiusdreef",
    "iso:country":"NL",
    "sg:address":"Claudiusdreef 28",
    "sg:city":"Valkenburg Zh",
    "sg:orig_category":"Bloemen And Planten Gh",
    "sg:phone":"+31 71 401 7073",
    "sg:postcode":"2235 AV",
    "sg:province":"Zuid-Holland",
    "wof:name":"M.N. Fleurs",
    "wof:placetype":"venue"
},
  "geometry": {"coordinates":[4.428754,52.181484],"type":"Point"}
}