{
  "type": "Feature",
  "properties": {
    "addr:full":"Heeswyk 40 Montfoort Utrecht 3417 GR",
    "addr:housenumber":"40",
    "addr:postcode":"3417",
    "addr:street":"Heeswyk",
    "iso:country":"NL",
    "sg:address":"Heeswyk 40",
    "sg:city":"Montfoort",
    "sg:orig_category":"Kassenbouw",
    "sg:phone":"+31 348 470 735",
    "sg:postcode":"3417 GR",
    "sg:province":"Utrecht",
    "wof:name":"Elvi Tuincomfort",
    "wof:placetype":"venue"
},
  "geometry": {"coordinates":[4.946729,52.044067],"type":"Point"}
}