{
  "type": "Feature",
  "properties": {
    "addr:full":"Sportlaan 6 Giethoorn Overijssel 8355 BE",
    "addr:housenumber":"6",
    "addr:postcode":"8355",
    "addr:street":"Sportlaan",
    "iso:country":"NL",
    "sg:address":"Sportlaan 6",
    "sg:city":"Giethoorn",
    "sg:classifiers":[
        {
            "category":"Fast Food",
            "type":"Food & Drink"
        }
    ],
    "sg:phone":"+31 521 361 569",
    "sg:postcode":"8355 BE",
    "sg:province":"Overijssel",
    "sg:tags":[
        "afhaal",
        "restaurant"
    ],
    "wof:name":"Petter'S Bik-Bar",
    "wof:placetype":"venue"
},
  "geometry": {"coordinates":[6.080378,52.739979],"type":"Point"}
}