{
  "type": "Feature",
  "properties": {
    "iso:country":"NL",
    "sg:address":"Julianastr 1",
    "sg:city":"Dedemsvaart",
    "sg:orig_category":"Woninginrichting",
    "sg:phone":"+31 523 612 100",
    "sg:postcode":"7701 GH",
    "sg:province":"Overijssel",
    "wof:name":"Sipkema",
    "wof:placetype":"venue"
},
  "geometry": {"coordinates":[6.4586119652,52.6000328064],"type":"Point"}
}