{
  "type": "Feature",
  "properties": {
    "addr:full":"Wg-Plein 131 Amsterdam Noord-Holland 1054 SC",
    "addr:housenumber":"131",
    "addr:postcode":"1054 sc",
    "addr:street":"Wg-Plein",
    "iso:country":"NL",
    "sg:address":"Wg-Plein 131",
    "sg:city":"Amsterdam",
    "sg:orig_category":"Vers Brood And Banket Fab",
    "sg:phone":"+31 20 612 4852",
    "sg:postcode":"1054 SC",
    "sg:province":"Noord-Holland",
    "wof:name":"Zacco Patisserie",
    "wof:placetype":"venue"
},
  "geometry": {"coordinates":[4.871002,52.364208],"type":"Point"}
}