{
  "type": "Feature",
  "properties": {
    "addr:full":"Corvus 33 Hapert North Brabant 5527 EC",
    "addr:housenumber":"33",
    "addr:postcode":"5527 ec",
    "addr:street":"Corvus",
    "iso:country":"NL",
    "sg:address":"Corvus 33",
    "sg:city":"Hapert",
    "sg:orig_category":"Kappers",
    "sg:phone":"+31 497 382 751",
    "sg:postcode":"5527 EC",
    "sg:province":"North Brabant",
    "wof:name":"A Roymans",
    "wof:placetype":"venue"
},
  "geometry": {"coordinates":[5.2607321739,51.3674354553],"type":"Point"}
}