{
  "type": "Feature",
  "properties": {
    "addr:full":"Wibautstraat 129 Amsterdam Noord-Holland 1091 GL",
    "addr:housenumber":"129",
    "addr:postcode":"1091 gl",
    "addr:street":"Wibautstraat",
    "iso:country":"NL",
    "sg:address":"Wibautstraat 129",
    "sg:city":"Amsterdam",
    "sg:orig_category":"Luchtvaart",
    "sg:phone":"+31 20 582 9456",
    "sg:postcode":"1091 GL",
    "sg:province":"Noord-Holland",
    "wof:name":"Lufthansa",
    "wof:placetype":"venue"
},
  "geometry": {"coordinates":[4.912502,52.353985],"type":"Point"}
}