{
  "type": "Feature",
  "properties": {
    "addr:full":"Dorpsstr 97 St Willebrord North Brabant 4711 EG",
    "addr:housenumber":"97",
    "addr:postcode":"4711 eg",
    "addr:street":"Dorpsstr;St",
    "iso:country":"NL",
    "sg:address":"Dorpsstr 97",
    "sg:city":"St Willebrord",
    "sg:orig_category":"Onderhoudswerken",
    "sg:phone":"+31 165 384 827",
    "sg:postcode":"4711 EG",
    "sg:province":"North Brabant",
    "wof:name":"Heeren",
    "wof:placetype":"venue"
},
  "geometry": {"coordinates":[4.59148,51.549721],"type":"Point"}
}