{
  "type": "Feature",
  "properties": {
    "addr:full":"Kerkstraat 57 Oud Beijerland South Holland 3262 PG",
    "addr:housenumber":"57",
    "addr:postcode":"3262 pg",
    "addr:street":"Kerkstraat;Oud Beijerland",
    "iso:country":"NL",
    "sg:address":"Kerkstraat 57",
    "sg:city":"Oud Beijerland",
    "sg:orig_category":"Overheidsdiensten",
    "sg:phone":"+31 186 612 139",
    "sg:postcode":"3262 PG",
    "sg:province":"South Holland",
    "wof:name":"Maranatha",
    "wof:placetype":"venue"
},
  "geometry": {"coordinates":[4.4108748436,51.8243904114],"type":"Point"}
}