{
  "type": "Feature",
  "properties": {
    "iso:country":"NL",
    "sg:address":"Michelangelostr 26",
    "sg:city":"Rotterdam",
    "sg:orig_category":"Advocaten En Advocatenkantoren",
    "sg:phone":"+31 10 477 0000",
    "sg:postcode":"3066 NM",
    "sg:province":"Zuid-Holland",
    "wof:name":"Burgert & Eikenboom",
    "wof:placetype":"venue"
},
  "geometry": {"coordinates":[4.55175,51.93922],"type":"Point"}
}