{
  "type": "Feature",
  "properties": {
    "addr:full":"Turbinestr 24 Hengelo Ov Overijssel 7556 RB",
    "addr:housenumber":"24",
    "addr:postcode":"7556 rb",
    "addr:street":"Turbinestr;Ov",
    "iso:country":"NL",
    "sg:address":"Turbinestr 24",
    "sg:city":"Hengelo Ov",
    "sg:orig_category":"Behangers",
    "sg:phone":"+31 74 266 2541",
    "sg:postcode":"7556 RB",
    "sg:province":"Overijssel",
    "wof:name":"Blaauwgeers",
    "wof:placetype":"venue"
},
  "geometry": {"coordinates":[6.776998,52.27187],"type":"Point"}
}