{
  "type": "Feature",
  "properties": {
    "addr:full":"Hoofdstraat 3 Oostwold Scheemda Groningen 9682 PJ",
    "addr:housenumber":"3",
    "addr:postcode":"9682 pj",
    "addr:street":"Hoofdstraat",
    "iso:country":"NL",
    "sg:address":"Hoofdstraat 3",
    "sg:city":"Oostwold Scheemda",
    "sg:orig_category":"Autokeuringen",
    "sg:phone":"+31 597 551 231",
    "sg:postcode":"9682 PJ",
    "sg:province":"Groningen",
    "wof:name":"H. Jonker",
    "wof:placetype":"venue"
},
  "geometry": {"coordinates":[7.044108,53.20425],"type":"Point"}
}