{
  "type": "Feature",
  "properties": {
    "addr:full":"Spijkse Kweldijk 1 Heukelum Gelderland 4161 BP",
    "addr:housenumber":"1",
    "addr:postcode":"4161 bp",
    "addr:street":"Spijkse Kweldijk;Gelderland",
    "iso:country":"NL",
    "sg:address":"Spijkse Kweldijk 1",
    "sg:city":"Heukelum",
    "sg:orig_category":"Farmaceutische Producten Gh",
    "sg:phone":"+31 183 567 931",
    "sg:postcode":"4161 BP",
    "sg:province":"Gelderland",
    "wof:name":"Surya Products",
    "wof:placetype":"venue"
},
  "geometry": {"coordinates":[5.060681,51.857384],"type":"Point"}
}