{
  "type": "Feature",
  "properties": {
    "addr:full":"Palestinastr 105 Rotterdam Zuid-Holland 3061 HM",
    "addr:housenumber":"105",
    "addr:postcode":"3061 hm",
    "iso:country":"NL",
    "sg:address":"Palestinastr 105",
    "sg:city":"Rotterdam",
    "sg:orig_category":"Vertalers",
    "sg:phone":"+31 10 212 1018",
    "sg:postcode":"3061 HM",
    "sg:province":"Zuid-Holland",
    "wof:name":"Melville",
    "wof:placetype":"venue"
},
  "geometry": {"coordinates":[4.505527,51.930553],"type":"Point"}
}