{
  "type": "Feature",
  "properties": {
    "addr:full":"Rembrandtln 69 Voorburg Zuid-Holland 2271 GG",
    "addr:housenumber":"69",
    "addr:postcode":"2271 gg",
    "addr:street":"Rembrandtln",
    "iso:country":"NL",
    "sg:address":"Rembrandtln 69",
    "sg:city":"Voorburg",
    "sg:orig_category":"Woningstoffeerders",
    "sg:phone":"+31 70 300 0696",
    "sg:postcode":"2271 GG",
    "sg:province":"Zuid-Holland",
    "wof:name":"Carpet Fashion",
    "wof:placetype":"venue"
},
  "geometry": {"coordinates":[4.3737521172,52.0755577087],"type":"Point"}
}