{
  "type": "Feature",
  "properties": {
    "iso:country":"NL",
    "sg:address":"De Brink 126",
    "sg:city":"Zutphen",
    "sg:orig_category":"Scholen Voor Basisonderwijs",
    "sg:phone":"+31 575 524 213",
    "sg:postcode":"7206 KD",
    "sg:province":"Gelderland",
    "wof:name":"Achtsprong Rk, De",
    "wof:placetype":"venue"
},
  "geometry": {"coordinates":[6.191525,52.140202],"type":"Point"}
}