{
  "type": "Feature",
  "properties": {
    "iso:country":"NL",
    "sg:address":"Overysselhaven 87",
    "sg:city":"Nieuwegein",
    "sg:orig_category":"Autopoetsbedrijven",
    "sg:phone":"+31 30 606 0463",
    "sg:postcode":"3433 PH",
    "sg:province":"Utrecht",
    "sg:website":"http://www.sonax.nl",
    "wof:name":"Sonax Car Care Bv",
    "wof:placetype":"venue"
},
  "geometry": {"coordinates":[5.104821,52.020481],"type":"Point"}
}