{
  "type": "Feature",
  "properties": {
    "addr:full":"Schapenland 5 Broek Op Langedyk Noord-Holland 1721 CM",
    "addr:housenumber":"5",
    "addr:postcode":"1721 cm",
    "addr:street":"Schapenland;Op Langedyk",
    "iso:country":"NL",
    "sg:address":"Schapenland 5",
    "sg:city":"Broek Op Langedyk",
    "sg:orig_category":"Administratie- En Boekhoudkantoren",
    "sg:phone":"+31 226 312 747",
    "sg:postcode":"1721 CM",
    "sg:province":"Noord-Holland",
    "wof:name":"Karels",
    "wof:placetype":"venue"
},
  "geometry": {"coordinates":[4.80957,52.678673],"type":"Point"}
}