{
  "type": "Feature",
  "properties": {
    "addr:full":"Broersveld 68 Schiedam South Holland 3111 LJ",
    "addr:housenumber":"68",
    "addr:postcode":"3111 lj",
    "addr:street":"Broersveld",
    "iso:country":"NL",
    "sg:address":"Broersveld 68",
    "sg:city":"Schiedam",
    "sg:orig_category":"Kaas",
    "sg:phone":"+31 10 426 4686",
    "sg:postcode":"3111 LJ",
    "sg:province":"South Holland",
    "wof:name":"Farmshop",
    "wof:placetype":"venue"
},
  "geometry": {"coordinates":[4.4012908936,51.9156570435],"type":"Point"}
}