{
  "type": "Feature",
  "properties": {
    "addr:full":"Breedestr 40 Doesburg Gelderland 6983 AD",
    "addr:housenumber":"40",
    "addr:postcode":"6983 ad",
    "addr:street":"Breedestr;Gelderland",
    "iso:country":"NL",
    "sg:address":"Breedestr 40",
    "sg:city":"Doesburg",
    "sg:orig_category":"Artsen - Huisartsen",
    "sg:phone":"+31 313 476 415",
    "sg:postcode":"6983 AD",
    "sg:province":"Gelderland",
    "wof:name":"Trentelman, J C",
    "wof:placetype":"venue"
},
  "geometry": {"coordinates":[6.125439,52.002457],"type":"Point"}
}