{
  "type": "Feature",
  "properties": {
    "addr:full":"Korfgraaf 7 Hellouw Gelderland 4174 GL",
    "addr:housenumber":"7",
    "addr:postcode":"4174 gl",
    "addr:street":"Korfgraaf;Gelderland",
    "iso:country":"NL",
    "sg:address":"Korfgraaf 7",
    "sg:city":"Hellouw",
    "sg:orig_category":"Verzekeringen",
    "sg:phone":"+31 418 581 348",
    "sg:postcode":"4174 GL",
    "sg:province":"Gelderland",
    "wof:name":"Ass.Kantoor Cardol",
    "wof:placetype":"venue"
},
  "geometry": {"coordinates":[5.179244,51.827702],"type":"Point"}
}