{
  "type": "Feature",
  "properties": {
    "addr:full":"Hg Hoefloo 27 Laren Nh Noord-Holland 1251 EC",
    "addr:housenumber":"27",
    "addr:postcode":"1251 ec",
    "iso:country":"NL",
    "sg:address":"Hg Hoefloo 27",
    "sg:city":"Laren Nh",
    "sg:orig_category":"Adviesbureaus Bedrijfsorganisatie",
    "sg:phone":"+31 35 538 1803",
    "sg:postcode":"1251 EC",
    "sg:province":"Noord-Holland",
    "wof:name":"Zara Bv",
    "wof:placetype":"venue"
},
  "geometry": {"coordinates":[5.20966,52.252655],"type":"Point"}
}