{
  "type": "Feature",
  "properties": {
    "addr:full":"Baarskampstraat 29 Kessel Lb Limburg 5995 AT",
    "addr:housenumber":"29",
    "addr:postcode":"lb;5995",
    "addr:street":"Baarskampstraat",
    "iso:country":"NL",
    "sg:address":"Baarskampstraat 29",
    "sg:city":"Kessel Lb",
    "sg:orig_category":"Banken And Kredietinstellingen",
    "sg:phone":"+31 77 462 1340",
    "sg:postcode":"5995 AT",
    "sg:province":"Limburg",
    "wof:name":"Postkantoor",
    "wof:placetype":"venue"
},
  "geometry": {"coordinates":[6.048133,51.292236],"type":"Point"}
}