{
  "type": "Feature",
  "properties": {
    "iso:country":"NL",
    "sg:address":"Vd Puttestr 12",
    "sg:city":"Gouda",
    "sg:orig_category":"Adviesbureaus",
    "sg:phone":"+31 182 534 721",
    "sg:postcode":"2804 JP",
    "sg:province":"Zuid-Holland",
    "wof:name":"B3000",
    "wof:placetype":"venue"
},
  "geometry": {"coordinates":[4.709527,52.027004],"type":"Point"}
}