{
  "type": "Feature",
  "properties": {
    "iso:country":"NL",
    "sg:address":"Oosterhamrikkd 97",
    "sg:city":"Groningen",
    "sg:classifiers":[
        {
            "category":"Retail",
            "subcategory":"Auto Repair",
            "type":"Services"
        }
    ],
    "sg:phone":"+31 50 312 4846",
    "sg:postcode":"9713 KC",
    "sg:province":"Groningen",
    "sg:tags":[
        "garage"
    ],
    "sg:website":"http://www.vanheukelem.nl",
    "wof:name":"Heukelem, Autobedrijf Van",
    "wof:placetype":"venue"
},
  "geometry": {"coordinates":[6.577019,53.229561],"type":"Point"}
}