{
  "type": "Feature",
  "properties": {
    "addr:full":"Crailosewg 116 P/A Huizen Noord-Holland 1272 EX",
    "addr:housenumber":"116;/ a",
    "addr:postcode":"1272 ex",
    "addr:street":"P",
    "iso:country":"NL",
    "sg:address":"Crailosewg 116 P/A",
    "sg:city":"Huizen",
    "sg:orig_category":"Gehandicapteninformatie",
    "sg:phone":"+31 35 692 1623",
    "sg:postcode":"1272 EX",
    "sg:province":"Noord-Holland",
    "wof:name":"Sportservice Noord-Holland",
    "wof:placetype":"venue"
},
  "geometry": {"coordinates":[5.23421,52.29504],"type":"Point"}
}