{
  "type": "Feature",
  "properties": {
    "addr:full":"Provincienbaan 1 Rijen Noord-Brabant 5121 DK",
    "addr:housenumber":"1",
    "addr:postcode":"5121 dk",
    "addr:street":"Provincienbaan",
    "iso:country":"NL",
    "sg:address":"Provincienbaan 1",
    "sg:city":"Rijen",
    "sg:orig_category":"Metaalwerken",
    "sg:phone":"+31 161 232 623",
    "sg:postcode":"5121 DK",
    "sg:province":"Noord-Brabant",
    "wof:name":"Syco Bv",
    "wof:placetype":"venue"
},
  "geometry": {"coordinates":[4.938763,51.577698],"type":"Point"}
}