{
  "type": "Feature",
  "properties": {
    "addr:full":"Sophiastraat 9 Waalre Noord-Brabant 5583 CA",
    "addr:housenumber":"9",
    "addr:postcode":"5583 ca",
    "addr:street":"Sophiastraat",
    "iso:country":"NL",
    "sg:address":"Sophiastraat 9",
    "sg:city":"Waalre",
    "sg:orig_category":"Kantoorartikelen",
    "sg:phone":"+31 40 221 9010",
    "sg:postcode":"5583 CA",
    "sg:province":"Noord-Brabant",
    "wof:name":"Deltatec Produktiesystemen & Procestechn",
    "wof:placetype":"venue"
},
  "geometry": {"coordinates":[5.4824447632,51.396686554],"type":"Point"}
}