{
  "type": "Feature",
  "properties": {
    "iso:country":"NL",
    "sg:address":"J Dutilhwg 841",
    "sg:city":"Rotterdam",
    "sg:orig_category":"Verenigingen En Stichtingen",
    "sg:phone":"+31 10 447 0404",
    "sg:postcode":"3065 JH",
    "sg:province":"South Holland",
    "wof:name":"Kralingsche Troep Scouting",
    "wof:placetype":"venue"
},
  "geometry": {"coordinates":[4.539408,51.925739],"type":"Point"}
}