{
  "type": "Feature",
  "properties": {
    "iso:country":"NL",
    "sg:address":"De Overtuin 6",
    "sg:city":"Velp Gld",
    "sg:orig_category":"Banken And Kredietinstellingen",
    "sg:phone":"+31 26 371 4444",
    "sg:postcode":"6881 TT",
    "sg:province":"Gelderland",
    "wof:name":"Rabobank",
    "wof:placetype":"venue"
},
  "geometry": {"coordinates":[5.974078,51.995621],"type":"Point"}
}