{
  "type": "Feature",
  "properties": {
    "addr:full":"Raadhuispln 80B Krimpen Ad Yssel Zuid-Holland 2922 AH",
    "addr:housenumber":"80b",
    "addr:postcode":"2922 ah",
    "addr:street":"Raadhuispln",
    "iso:country":"NL",
    "sg:address":"Raadhuispln 80B",
    "sg:city":"Krimpen Ad Yssel",
    "sg:orig_category":"Linnenshops",
    "sg:phone":"+31 180 517 717",
    "sg:postcode":"2922 AH",
    "sg:province":"Zuid-Holland",
    "wof:name":"Linnenhof, De",
    "wof:placetype":"venue"
},
  "geometry": {"coordinates":[4.588417,51.91412],"type":"Point"}
}