{
  "type": "Feature",
  "properties": {
    "addr:full":"Burg Mesln 41A Tiel Gelderland 4003 CA",
    "addr:housenumber":"41a",
    "addr:postcode":"4003 ca",
    "addr:street":"Burg Mesln;Gelderland",
    "iso:country":"NL",
    "sg:address":"Burg Mesln 41A",
    "sg:city":"Tiel",
    "sg:orig_category":"Artsen - Huisartsen",
    "sg:phone":"+31 344 634 151",
    "sg:postcode":"4003 CA",
    "sg:province":"Gelderland",
    "wof:name":"Schreuders, A",
    "wof:placetype":"venue"
},
  "geometry": {"coordinates":[5.430696,51.888096],"type":"Point"}
}