{
  "type": "Feature",
  "properties": {
    "addr:full":"Churchillln 692 Terneuzen Zeeland 4532 JB",
    "addr:housenumber":"692",
    "addr:postcode":"4532 jb",
    "iso:country":"NL",
    "sg:address":"Churchillln 692",
    "sg:city":"Terneuzen",
    "sg:orig_category":"Makelaars En Adviseurs Onroerende Goederen",
    "sg:phone":"+31 115 675 094",
    "sg:postcode":"4532 JB",
    "sg:province":"Zeeland",
    "wof:name":"Simons, R",
    "wof:placetype":"venue"
},
  "geometry": {"coordinates":[3.827559,51.338146],"type":"Point"}
}