{
  "type": "Feature",
  "properties": {
    "addr:full":"Amsterdamsestrwg 600 Utrecht Utrecht 3553 EP",
    "addr:housenumber":"600",
    "addr:postcode":"3553 ep",
    "iso:country":"NL",
    "sg:address":"Amsterdamsestrwg 600",
    "sg:city":"Utrecht",
    "sg:orig_category":"Hoogwerkers",
    "sg:phone":"+31 30 242 7200",
    "sg:postcode":"3553 EP",
    "sg:province":"Utrecht",
    "sg:website":"http://www.dekroon.com",
    "wof:name":"Kroon Special Services, De",
    "wof:placetype":"venue"
},
  "geometry": {"coordinates":[5.081709,52.111069],"type":"Point"}
}