{
  "type": "Feature",
  "properties": {
    "iso:country":"NL",
    "sg:address":"Leidsemeerstraat 41",
    "sg:city":"Buitenkaag",
    "sg:orig_category":"Meubeltextiel Fab",
    "sg:phone":"+31 252 544 476",
    "sg:postcode":"2158 MJ",
    "sg:province":"Noord-Holland",
    "wof:name":"Zeilmakerij Zwetsloot Vof",
    "wof:placetype":"venue"
},
  "geometry": {"coordinates":[4.56193,52.219345],"type":"Point"}
}