{
  "type": "Feature",
  "properties": {
    "addr:full":"Overtoom 410 Amsterdam Noord-Holland 1054 JT",
    "addr:housenumber":"410",
    "addr:postcode":"1054 jt",
    "addr:street":"Overtoom",
    "iso:country":"NL",
    "sg:address":"Overtoom 410",
    "sg:city":"Amsterdam",
    "sg:orig_category":"Glaszetten",
    "sg:phone":"+31 20 612 4440",
    "sg:postcode":"1054 JT",
    "sg:province":"Noord-Holland",
    "wof:name":"A.J. Birkhoff",
    "wof:placetype":"venue"
},
  "geometry": {"coordinates":[4.864063,52.36018],"type":"Point"}
}