{
  "type": "Feature",
  "properties": {
    "addr:full":"Brugstr 1 Wilhelminadorp Zeeland 4475 AN",
    "addr:housenumber":"1",
    "addr:postcode":"4475 an",
    "addr:street":"Brugstr",
    "iso:country":"NL",
    "sg:address":"Brugstr 1",
    "sg:city":"Wilhelminadorp",
    "sg:orig_category":"Hoefsmederijen",
    "sg:phone":"+31 113 214 357",
    "sg:postcode":"4475 AN",
    "sg:province":"Zeeland",
    "wof:name":"Butijn & Zn, H D",
    "wof:placetype":"venue"
},
  "geometry": {"coordinates":[3.898077,51.52969],"type":"Point"}
}