{
  "type": "Feature",
  "properties": {
    "addr:full":"Hanzestr 195 Arnhem Gelderland 6826 MK",
    "addr:housenumber":"195",
    "addr:postcode":"6826",
    "iso:country":"NL",
    "sg:address":"Hanzestr 195",
    "sg:city":"Arnhem",
    "sg:orig_category":"Herenkleding",
    "sg:phone":"+31 26 361 3204",
    "sg:postcode":"6826 MK",
    "sg:province":"Gelderland",
    "wof:name":"Bouter Vof, Cris De",
    "wof:placetype":"venue"
},
  "geometry": {"coordinates":[5.95213,51.983612],"type":"Point"}
}