{
  "type": "Feature",
  "properties": {
    "addr:full":"De Steiger 21 Almere Flevoland 1351 AB",
    "addr:housenumber":"21",
    "addr:postcode":"1351 ab",
    "addr:street":"De Steiger;Flevoland",
    "iso:country":"NL",
    "sg:address":"De Steiger 21",
    "sg:city":"Almere",
    "sg:classifiers":[
        {
            "category":"Retail",
            "subcategory":"Auto Repair",
            "type":"Services"
        }
    ],
    "sg:phone":"+31 36 534 9911",
    "sg:postcode":"1351 AB",
    "sg:province":"Flevoland",
    "sg:tags":[
        "garage"
    ],
    "sg:website":"http://www.dorestad.nl",
    "wof:name":"Dorestad",
    "wof:placetype":"venue"
},
  "geometry": {"coordinates":[5.219421,52.349873],"type":"Point"}
}