{
  "type": "Feature",
  "properties": {
    "addr:full":"Grt Welsden 13 Margraten Limburg 6269 ET",
    "addr:housenumber":"13",
    "addr:postcode":"6269 et",
    "addr:street":"Grt Welsden",
    "iso:country":"NL",
    "sg:address":"Grt Welsden 13",
    "sg:city":"Margraten",
    "sg:classifiers":[
        {
            "category":"Travel",
            "subcategory":"Hotels & Motels",
            "type":"Entertainment"
        }
    ],
    "sg:phone":"+31 43 458 1891",
    "sg:postcode":"6269 ET",
    "sg:province":"Limburg",
    "sg:website":"http://www.wippelsdaal.nl",
    "wof:name":"Wippelsdaal",
    "wof:placetype":"venue"
},
  "geometry": {"coordinates":[5.81547,50.830235],"type":"Point"}
}