{
  "type": "Feature",
  "properties": {
    "addr:full":"Bezuidenhoutsewg 74 S Gravenhage South Holland 2594 AW",
    "addr:housenumber":"74",
    "addr:postcode":"2594 aw",
    "addr:street":"Bezuidenhoutsewg;S Gravenhage",
    "iso:country":"NL",
    "sg:address":"Bezuidenhoutsewg 74",
    "sg:city":"S Gravenhage",
    "sg:orig_category":"Olie - Exploratie",
    "sg:phone":"+31 70 333 7500",
    "sg:postcode":"2594 AW",
    "sg:province":"South Holland",
    "wof:name":"Bp Nederland Energie Bv",
    "wof:placetype":"venue"
},
  "geometry": {"coordinates":[4.317415,52.083992],"type":"Point"}
}