{
  "type": "Feature",
  "properties": {
    "addr:full":"Nieuwstraat 72 Sint Michielsgestel Noord-Brabant 5271 AE",
    "addr:housenumber":"72",
    "addr:postcode":"5271 ae",
    "addr:street":"Nieuwstraat;Sint Michielsgestel",
    "iso:country":"NL",
    "sg:address":"Nieuwstraat 72",
    "sg:city":"Sint Michielsgestel",
    "sg:orig_category":"Verzekeringen",
    "sg:phone":"+31 73 553 0610",
    "sg:postcode":"5271 AE",
    "sg:province":"Noord-Brabant",
    "wof:name":"Roel Van De Wal Assurantien",
    "wof:placetype":"venue"
},
  "geometry": {"coordinates":[5.353381,51.644615],"type":"Point"}
}