{
  "type": "Feature",
  "properties": {
    "addr:full":"Arkendonk 69 Oosterhout Nb Noord-Brabant 4907 XP",
    "addr:housenumber":"69",
    "addr:postcode":"4907 xp",
    "addr:street":"Arkendonk",
    "iso:country":"NL",
    "sg:address":"Arkendonk 69",
    "sg:city":"Oosterhout Nb",
    "sg:orig_category":"Graveerbedrijven",
    "sg:phone":"+31 162 457 751",
    "sg:postcode":"4907 XP",
    "sg:province":"Noord-Brabant",
    "wof:name":"Arkendonk",
    "wof:placetype":"venue"
},
  "geometry": {"coordinates":[4.85625,51.643051],"type":"Point"}
}