{
  "type": "Feature",
  "properties": {
    "addr:full":"Appeldijk 61 Gorinchem South Holland 4201 AG",
    "addr:housenumber":"61",
    "addr:postcode":"4201",
    "addr:street":"Appeldijk",
    "iso:country":"NL",
    "sg:address":"Appeldijk 61",
    "sg:city":"Gorinchem",
    "sg:orig_category":"Bioscopen",
    "sg:phone":"+31 183 631 058",
    "sg:postcode":"4201 AG",
    "sg:province":"South Holland",
    "wof:name":"Bioscoop Roxy Theater",
    "wof:placetype":"venue"
},
  "geometry": {"coordinates":[4.976836,51.828346],"type":"Point"}
}