{
  "type": "Feature",
  "properties": {
    "addr:full":"Wendakker 30 Biddinghuizen NL. 8256 BP",
    "addr:housenumber":"30",
    "addr:postcode":"8256 bp",
    "addr:street":"Wendakker;Nl.",
    "iso:country":"NL",
    "sg:address":"Wendakker 30",
    "sg:city":"Biddinghuizen",
    "sg:orig_category":"Bloemen En Planten",
    "sg:phone":"+31 321 332 526",
    "sg:postcode":"8256 BP",
    "sg:province":"NL.",
    "wof:name":"Bemmel, Van",
    "wof:placetype":"venue"
},
  "geometry": {"coordinates":[5.689379,52.455513],"type":"Point"}
}