{
  "type": "Feature",
  "properties": {
    "iso:country":"NL",
    "sg:address":"Dreef 29",
    "sg:city":"Eersel",
    "sg:orig_category":"Bedrijfsinventaris Gh",
    "sg:phone":"+31 497 516 252",
    "sg:postcode":"5521 GN",
    "sg:province":"Noord-Brabant",
    "wof:name":"Will Groothuizen",
    "wof:placetype":"venue"
},
  "geometry": {"coordinates":[5.329088,51.36187],"type":"Point"}
}