{
  "type": "Feature",
  "properties": {
    "addr:full":"Madame Curiestr 2 Alkmaar North Holland 1821 BM",
    "addr:housenumber":"2",
    "addr:postcode":"1821 bm",
    "iso:country":"NL",
    "sg:address":"Madame Curiestr 2",
    "sg:city":"Alkmaar",
    "sg:orig_category":"Verf En Lak - Fabrieken En Groothandel",
    "sg:phone":"+31 72 511 4743",
    "sg:postcode":"1821 BM",
    "sg:province":"North Holland",
    "wof:name":"Novegro",
    "wof:placetype":"venue"
},
  "geometry": {"coordinates":[4.766832,52.628208],"type":"Point"}
}