{
  "type": "Feature",
  "properties": {
    "addr:full":"Herenstr 34 Slagharen Overijssel 7776 AJ",
    "addr:housenumber":"34",
    "addr:postcode":"7776 aj",
    "addr:street":"Herenstr",
    "iso:country":"NL",
    "sg:address":"Herenstr 34",
    "sg:city":"Slagharen",
    "sg:classifiers":[
        {
            "category":"Food & Beverages",
            "subcategory":"Bakery",
            "type":"Retail Goods"
        }
    ],
    "sg:phone":"+31 523 681 355",
    "sg:postcode":"7776 AJ",
    "sg:province":"Overijssel",
    "sg:tags":[
        "brood",
        "en",
        "banket"
    ],
    "wof:name":"Eggen",
    "wof:placetype":"venue"
},
  "geometry": {"coordinates":[6.555526,52.626659],"type":"Point"}
}