{
  "type": "Feature",
  "properties": {
    "iso:country":"NL",
    "sg:address":"H Kamerlingh Onnesweg 43",
    "sg:city":"Bussum",
    "sg:orig_category":"Kappers",
    "sg:phone":"+31 35 691 2876",
    "sg:postcode":"1402 EC",
    "sg:province":"Noord-Holland",
    "wof:name":"Dameskapsalon H P E Van Zwam",
    "wof:placetype":"venue"
},
  "geometry": {"coordinates":[5.1824522018,52.2729187012],"type":"Point"}
}