{
  "type": "Feature",
  "properties": {
    "addr:full":"Van Hogendorpstraat 170 'S Gravenhage Zuid-Holland 2515 NX",
    "addr:housenumber":"170 '",
    "addr:postcode":"2515 nx",
    "addr:street":"Van Hogendorpstraat",
    "iso:country":"NL",
    "sg:address":"Van Hogendorpstraat 170",
    "sg:city":"'S Gravenhage",
    "sg:orig_category":"Muziekinstrumenten Fab",
    "sg:phone":"+31 70 389 8988",
    "sg:postcode":"2515 NX",
    "sg:province":"Zuid-Holland",
    "wof:name":"G Nicholson",
    "wof:placetype":"venue"
},
  "geometry": {"coordinates":[4.316471,52.071354],"type":"Point"}
}