{
  "type": "Feature",
  "properties": {
    "addr:full":"Molenstr 58 Bunschoten Spakenburg Utrecht 3752 CK",
    "addr:housenumber":"58",
    "addr:postcode":"3752 ck",
    "addr:street":"Molenstr",
    "iso:country":"NL",
    "sg:address":"Molenstr 58",
    "sg:city":"Bunschoten Spakenburg",
    "sg:orig_category":"Verzekeringen - Verzekeringskantoren",
    "sg:phone":"+31 33 298 6818",
    "sg:postcode":"3752 CK",
    "sg:province":"Utrecht",
    "wof:name":"Koelewijn",
    "wof:placetype":"venue"
},
  "geometry": {"coordinates":[5.376109,52.248405],"type":"Point"}
}