{
  "type": "Feature",
  "properties": {
    "addr:full":"Emingaheerd 10 Groningen Groningen 9736 GA",
    "addr:housenumber":"10",
    "addr:postcode":"9736 ga",
    "addr:street":"Emingaheerd",
    "iso:country":"NL",
    "sg:address":"Emingaheerd 10",
    "sg:city":"Groningen",
    "sg:orig_category":"Artsen - Huisartsen",
    "sg:phone":"+31 50 541 5200",
    "sg:postcode":"9736 GA",
    "sg:province":"Groningen",
    "wof:name":"Beijum",
    "wof:placetype":"venue"
},
  "geometry": {"coordinates":[6.593305,53.247402],"type":"Point"}
}