{
  "type": "Feature",
  "properties": {
    "addr:full":"St Gerardusstr 128 Emmen Drenthe 7826 CJ",
    "addr:housenumber":"128",
    "addr:postcode":"7826 cj",
    "iso:country":"NL",
    "sg:address":"St Gerardusstr 128",
    "sg:city":"Emmen",
    "sg:orig_category":"Bloemen En Planten - Decoratie",
    "sg:phone":"+31 591 625 541",
    "sg:postcode":"7826 CJ",
    "sg:province":"Drenthe",
    "wof:name":"Nezz",
    "wof:placetype":"venue"
},
  "geometry": {"coordinates":[6.961997,52.773399],"type":"Point"}
}