{
  "type": "Feature",
  "properties": {
    "addr:full":"Dr Augustijnlaan 25 Rijswijk Zh South Holland 2283 CA",
    "addr:housenumber":"25",
    "addr:postcode":"2283 ca",
    "addr:street":"Dr Augustijnlaan",
    "iso:country":"NL",
    "sg:address":"Dr Augustijnlaan 25",
    "sg:city":"Rijswijk Zh",
    "sg:orig_category":"Boekhouders",
    "sg:phone":"+31 70 336 1804",
    "sg:postcode":"2283 CA",
    "sg:province":"South Holland",
    "wof:name":"J M Van Tuyn",
    "wof:placetype":"venue"
},
  "geometry": {"coordinates":[4.315794,52.044872],"type":"Point"}
}