{
  "type": "Feature",
  "properties": {
    "addr:full":"Karel Van Egmondstraat 157 Venlo Limburg 5915 HT",
    "addr:housenumber":"157",
    "addr:postcode":"5915 ht",
    "addr:street":"Karel Van Egmondstraat",
    "iso:country":"NL",
    "sg:address":"Karel Van Egmondstraat 157",
    "sg:city":"Venlo",
    "sg:orig_category":"Bedrijfs- And Managementsconsultants",
    "sg:phone":"+31 77 320 0406",
    "sg:postcode":"5915 HT",
    "sg:province":"Limburg",
    "wof:name":"Thielen Organisatie- En Adviesburo",
    "wof:placetype":"venue"
},
  "geometry": {"coordinates":[6.195907,51.362785],"type":"Point"}
}