{
  "type": "Feature",
  "properties": {
    "iso:country":"NL",
    "sg:address":"Gelderse Rooslaan 16",
    "sg:city":"Arnhem",
    "sg:orig_category":"Kinderopvang Behalve Thuis",
    "sg:phone":"+31 26 321 3697",
    "sg:postcode":"6841 BE",
    "sg:province":"Gelderland",
    "wof:name":"Kinderdagverblijf De Klimop",
    "wof:placetype":"venue"
},
  "geometry": {"coordinates":[5.901384,51.970478],"type":"Point"}
}