{
  "type": "Feature",
  "properties": {
    "addr:full":"Nieuwegr 56 Utrecht Utrecht 3512 LT",
    "addr:housenumber":"56",
    "addr:postcode":"3512 lt",
    "addr:street":"Nieuwegr",
    "iso:country":"NL",
    "sg:address":"Nieuwegr 56",
    "sg:city":"Utrecht",
    "sg:orig_category":"Adviesbureaus Bedrijfsorganisatie",
    "sg:phone":"+31 30 231 8168",
    "sg:postcode":"3512 LT",
    "sg:province":"Utrecht",
    "wof:name":"Breugel Bv, Van",
    "wof:placetype":"venue"
},
  "geometry": {"coordinates":[5.12581,52.087791],"type":"Point"}
}