{
  "type": "Feature",
  "properties": {
    "addr:full":"Plantagewg 13A Alblasserdam South Holland 2951 GN",
    "addr:housenumber":"13a",
    "addr:postcode":"2951 gn",
    "addr:street":"Plantagewg",
    "iso:country":"NL",
    "sg:address":"Plantagewg 13A",
    "sg:city":"Alblasserdam",
    "sg:orig_category":"Boeken En Tijdschriften",
    "sg:phone":"+31 78 691 3068",
    "sg:postcode":"2951 GN",
    "sg:province":"South Holland",
    "wof:name":"Schuilplaats, De",
    "wof:placetype":"venue"
},
  "geometry": {"coordinates":[4.660818,51.862026],"type":"Point"}
}