{
  "type": "Feature",
  "properties": {
    "addr:full":"Roomweg 26 Grashoek Limburg 5985 NT",
    "addr:housenumber":"26",
    "addr:postcode":"5985 nt",
    "addr:street":"Roomweg",
    "iso:country":"NL",
    "sg:address":"Roomweg 26",
    "sg:city":"Grashoek",
    "sg:orig_category":"Levende Dieren Gh",
    "sg:phone":"+31 77 307 5421",
    "sg:postcode":"5985 NT",
    "sg:province":"Limburg",
    "wof:name":"Poeliersgroothandel M. Swinkels",
    "wof:placetype":"venue"
},
  "geometry": {"coordinates":[5.938912,51.359631],"type":"Point"}
}