{
  "type": "Feature",
  "properties": {
    "addr:full":"Edisonstraat 2 Oldenzaal NL.08 7575 AT",
    "addr:housenumber":"2;nl.08",
    "addr:postcode":"7575",
    "addr:street":"Edisonstraat",
    "iso:country":"NL",
    "sg:address":"Edisonstraat 2",
    "sg:city":"Oldenzaal",
    "sg:orig_category":"Pompen And Compressoren Fab",
    "sg:phone":"+31 541 584 500",
    "sg:postcode":"7575 AT",
    "sg:province":"NL.08",
    "wof:name":"Engineered Solutions Power Packer Europa Bv",
    "wof:placetype":"venue"
},
  "geometry": {"coordinates":[6.923155,52.299618],"type":"Point"}
}