{
  "type": "Feature",
  "properties": {
    "iso:country":"NL",
    "sg:address":"Hilversumstraat 322",
    "sg:city":"Amsterdam",
    "sg:orig_category":"Boekhouders",
    "sg:phone":"+31 20 635 2035",
    "sg:postcode":"1024 MB",
    "sg:province":"Noord-Holland",
    "wof:name":"Brouwer & Oudhof Administratieconsulenten",
    "wof:placetype":"venue"
},
  "geometry": {"coordinates":[4.96289,52.390923],"type":"Point"}
}