{
  "type": "Feature",
  "properties": {
    "iso:country":"NL",
    "sg:address":"Walstr 11",
    "sg:city":"Ommen",
    "sg:orig_category":"Beurzen",
    "sg:phone":"+31 529 454 072",
    "sg:postcode":"7731 HM",
    "sg:province":"Overijssel",
    "sg:website":"http://www.stichting-dorus.nl",
    "wof:name":"Dorus, Sticht",
    "wof:placetype":"venue"
},
  "geometry": {"coordinates":[6.424329,52.518703],"type":"Point"}
}