{
  "type": "Feature",
  "properties": {
    "addr:full":"Kruisnetln 410 Hoogvliet Rt Zuid-Holland 3192 KE",
    "addr:housenumber":"410",
    "addr:postcode":"rt;3192 ke",
    "iso:country":"NL",
    "sg:address":"Kruisnetln 410",
    "sg:city":"Hoogvliet Rt",
    "sg:orig_category":"Bejaarden - Verzorgingstehuizen",
    "sg:phone":"+31 10 263 0333",
    "sg:postcode":"3192 KE",
    "sg:province":"Zuid-Holland",
    "wof:name":"Siloam",
    "wof:placetype":"venue"
},
  "geometry": {"coordinates":[4.361473,51.851322],"type":"Point"}
}