{
  "type": "Feature",
  "properties": {
    "iso:country":"NL",
    "sg:address":"Dorpsstraat 49",
    "sg:city":"Renkum",
    "sg:orig_category":"Schoenen",
    "sg:phone":"+31 317 317 153",
    "sg:postcode":"6871 AD",
    "sg:province":"Gelderland",
    "wof:name":"El Paso",
    "wof:placetype":"venue"
},
  "geometry": {"coordinates":[5.727949,51.971809],"type":"Point"}
}