{
  "type": "Feature",
  "properties": {
    "addr:full":"Bilderdijkpark 18 Amsterdam Noord-Holland 1052 SC",
    "addr:housenumber":"18",
    "addr:postcode":"1052 sc",
    "addr:street":"Bilderdijkpark",
    "iso:country":"NL",
    "sg:address":"Bilderdijkpark 18",
    "sg:city":"Amsterdam",
    "sg:classifiers":[
        {
            "category":"Education",
            "subcategory":"Preschool",
            "type":"Public Place"
        }
    ],
    "sg:phone":"+31 20 612 0122",
    "sg:postcode":"1052 SC",
    "sg:province":"Noord-Holland",
    "sg:tags":[
        "kleuteronderwijs",
        "basis-"
    ],
    "wof:name":"De Waterkant",
    "wof:placetype":"venue"
},
  "geometry": {"coordinates":[4.868499,52.371319],"type":"Point"}
}