{
  "type": "Feature",
  "properties": {
    "iso:country":"NL",
    "sg:address":"Stationstr 102",
    "sg:city":"Boxtel",
    "sg:orig_category":"Kunstenaars- Benodigdheden",
    "sg:phone":"+31 411 616 686",
    "sg:postcode":"5281 GG",
    "sg:province":"Noord-Brabant",
    "wof:name":"Traverse, De",
    "wof:placetype":"venue"
},
  "geometry": {"coordinates":[5.31959,51.585258],"type":"Point"}
}