{
  "type": "Feature",
  "properties": {
    "addr:full":"Grachtstr 5 Simpelveld Limburg 6369 AL",
    "addr:housenumber":"5",
    "addr:postcode":"6369 al",
    "addr:street":"Grachtstr",
    "iso:country":"NL",
    "sg:address":"Grachtstr 5",
    "sg:city":"Simpelveld",
    "sg:orig_category":"Beeldende Kunstenaars",
    "sg:phone":"+31 45 544 4678",
    "sg:postcode":"6369 AL",
    "sg:province":"Limburg",
    "wof:name":"Knops, E",
    "wof:placetype":"venue"
},
  "geometry": {"coordinates":[5.981926,50.835815],"type":"Point"}
}