{
  "type": "Feature",
  "properties": {
    "addr:full":"Noordstr 62 Axel Zeeland 4571 GE",
    "addr:housenumber":"62",
    "addr:postcode":"4571",
    "addr:street":"Noordstr",
    "iso:country":"NL",
    "sg:address":"Noordstr 62",
    "sg:city":"Axel",
    "sg:orig_category":"Zonweringen",
    "sg:phone":"+31 115 563 565",
    "sg:postcode":"4571 GE",
    "sg:province":"Zeeland",
    "wof:name":"Everse Zonweringen",
    "wof:placetype":"venue"
},
  "geometry": {"coordinates":[3.907359,51.267017],"type":"Point"}
}