{
  "type": "Feature",
  "properties": {
    "addr:full":"V Loestr 12 Gemert Noord-Brabant 5421 BK",
    "addr:housenumber":"12",
    "addr:postcode":"5421 bk",
    "iso:country":"NL",
    "sg:address":"V Loestr 12",
    "sg:city":"Gemert",
    "sg:orig_category":"Meubelen",
    "sg:phone":"+31 492 367 444",
    "sg:postcode":"5421 BK",
    "sg:province":"Noord-Brabant",
    "wof:name":"Oog",
    "wof:placetype":"venue"
},
  "geometry": {"coordinates":[5.681675,51.556126],"type":"Point"}
}