{
  "type": "Feature",
  "properties": {
    "addr:full":"Heelsumstr 41 S Gravenhage Zuid-Holland 2573 NG",
    "addr:housenumber":"41;gravenhage",
    "addr:postcode":"2573 ng",
    "addr:street":"Heelsumstr;S",
    "iso:country":"NL",
    "sg:address":"Heelsumstr 41",
    "sg:city":"S Gravenhage",
    "sg:orig_category":"Adviesbureaus Bouwkunde",
    "sg:phone":"+31 70 447 0011",
    "sg:postcode":"2573 NG",
    "sg:province":"Zuid-Holland",
    "wof:name":"Woningonderhoud",
    "wof:placetype":"venue"
},
  "geometry": {"coordinates":[4.2844,52.064911],"type":"Point"}
}