{
  "type": "Feature",
  "properties": {
    "iso:country":"NL",
    "sg:address":"Annie Romeinsingel 152",
    "sg:city":"Leiden",
    "sg:orig_category":"Baby- And Kinderkleding",
    "sg:phone":"+31 71 572 1929",
    "sg:postcode":"2331 ST",
    "sg:province":"Zuid-Holland",
    "wof:name":"De Habbekrats",
    "wof:placetype":"venue"
},
  "geometry": {"coordinates":[4.453826,52.145908],"type":"Point"}
}