{
  "type": "Feature",
  "properties": {
    "addr:full":"Jelle Posthumapad 41 Amsterdam Zuidoost North Holland 1106 ZP",
    "addr:housenumber":"41",
    "addr:postcode":"1106 zp",
    "addr:street":"Jelle Posthumapad",
    "iso:country":"NL",
    "sg:address":"Jelle Posthumapad 41",
    "sg:city":"Amsterdam Zuidoost",
    "sg:orig_category":"Boekhouders",
    "sg:phone":"+31 20 691 2135",
    "sg:postcode":"1106 ZP",
    "sg:province":"North Holland",
    "wof:name":"M. De Langen",
    "wof:placetype":"venue"
},
  "geometry": {"coordinates":[4.997904,52.300274],"type":"Point"}
}