{
  "type": "Feature",
  "properties": {
    "iso:country":"NL",
    "sg:address":"Jelle Posthumapad 41",
    "sg:city":"Amsterdam Zuidoost",
    "sg:orig_category":"Boekhouders",
    "sg:phone":"+31 20 691 2135",
    "sg:postcode":"1106 ZP",
    "sg:province":"North Holland",
    "wof:name":"M. De Langen",
    "wof:placetype":"venue"
},
  "geometry": {"coordinates":[4.997904,52.300274],"type":"Point"}
}