{
  "type": "Feature",
  "properties": {
    "addr:full":"Dorpsstraat 31 Bemmel Gelderland 6681 BL",
    "addr:housenumber":"31",
    "addr:postcode":"6681 bl",
    "addr:street":"Dorpsstraat;Gelderland",
    "iso:country":"NL",
    "sg:address":"Dorpsstraat 31",
    "sg:city":"Bemmel",
    "sg:orig_category":"Juweliers",
    "sg:phone":"+31 481 465 823",
    "sg:postcode":"6681 BL",
    "sg:province":"Gelderland",
    "wof:name":"Kees Van Herkhuizen",
    "wof:placetype":"venue"
},
  "geometry": {"coordinates":[5.89899,51.89159],"type":"Point"}
}