{
  "type": "Feature",
  "properties": {
    "addr:full":"Bouwmeestersstraat 1 Appingedam Groningen 9901 AB",
    "addr:housenumber":"1",
    "addr:postcode":"9901 ab",
    "addr:street":"Bouwmeestersstraat",
    "iso:country":"NL",
    "sg:address":"Bouwmeestersstraat 1",
    "sg:city":"Appingedam",
    "sg:orig_category":"Loodgieterswerk, Verwarming And Sanitaire Installaties",
    "sg:phone":"+31 596 626 106",
    "sg:postcode":"9901 AB",
    "sg:province":"Groningen",
    "wof:name":"Loodgieters- En Installatie- Bedrijf Buissink Bv",
    "wof:placetype":"venue"
},
  "geometry": {"coordinates":[6.85372,53.320152],"type":"Point"}
}