{
  "type": "Feature",
  "properties": {
    "addr:full":"Hovenierswg 12 Zutphen Gelderland 7205 DA",
    "addr:housenumber":"12;7205",
    "addr:postcode":"da",
    "addr:street":"Hovenierswg;Gelderland",
    "iso:country":"NL",
    "sg:address":"Hovenierswg 12",
    "sg:city":"Zutphen",
    "sg:orig_category":"Bloemen En Planten",
    "sg:phone":"+31 575 512 208",
    "sg:postcode":"7205 DA",
    "sg:province":"Gelderland",
    "sg:website":"http://www.vandalenrozen.nl",
    "wof:name":"Dalen, Van",
    "wof:placetype":"venue"
},
  "geometry": {"coordinates":[6.1741261482,52.1468849182],"type":"Point"}
}