{
  "type": "Feature",
  "properties": {
    "addr:full":"K L De Vriesstr 3 St Jacobiparochie Friesland 9079 KK",
    "addr:housenumber":"3",
    "addr:postcode":"9079 kk",
    "addr:street":"K L De Vriesstr",
    "iso:country":"NL",
    "sg:address":"K L De Vriesstr 3",
    "sg:city":"St Jacobiparochie",
    "sg:orig_category":"Musea",
    "sg:phone":"+31 518 491 090",
    "sg:postcode":"9079 KK",
    "sg:province":"Friesland",
    "wof:name":"Kuipers",
    "wof:placetype":"venue"
},
  "geometry": {"coordinates":[5.605326,53.275242],"type":"Point"}
}