{
  "type": "Feature",
  "properties": {
    "addr:full":"Molenweg 4 De Krim Overijssel 7781 PH",
    "addr:housenumber":"4",
    "addr:postcode":"7781",
    "addr:street":"Molenweg",
    "iso:country":"NL",
    "sg:address":"Molenweg 4",
    "sg:city":"De Krim",
    "sg:orig_category":"Bloemen And Planten",
    "sg:phone":"+31 524 571 427",
    "sg:postcode":"7781 PH",
    "sg:province":"Overijssel",
    "wof:name":"Aling Bloembollen Combinatie Bv",
    "wof:placetype":"venue"
},
  "geometry": {"coordinates":[6.612333,52.639668],"type":"Point"}
}