{
  "type": "Feature",
  "properties": {
    "addr:full":"Wheeweg 1 Goor NL.08 7471 EV",
    "addr:housenumber":"1;nl.08",
    "addr:postcode":"7471 ev",
    "addr:street":"Wheeweg",
    "iso:country":"NL",
    "sg:address":"Wheeweg 1",
    "sg:city":"Goor",
    "sg:orig_category":"Levende Dieren Gh",
    "sg:phone":"+31 547 276 153",
    "sg:postcode":"7471 EV",
    "sg:province":"NL.08",
    "wof:name":"Gebroeders Bouwens Import Export Bv",
    "wof:placetype":"venue"
},
  "geometry": {"coordinates":[6.58524,52.241322],"type":"Point"}
}