{
  "type": "Feature",
  "properties": {
    "addr:full":"Molenwg 24 Zeist Utrecht 3708 SC",
    "addr:housenumber":"24",
    "addr:postcode":"3708",
    "addr:street":"Molenwg",
    "iso:country":"NL",
    "sg:address":"Molenwg 24",
    "sg:city":"Zeist",
    "sg:orig_category":"Administratie- En Boekhoudkantoren",
    "sg:phone":"+31 30 691 8928",
    "sg:postcode":"3708 SC",
    "sg:province":"Utrecht",
    "wof:name":"Jonge, A De",
    "wof:placetype":"venue"
},
  "geometry": {"coordinates":[5.246715,52.077816],"type":"Point"}
}