{
  "type": "Feature",
  "properties": {
    "addr:full":"Raadhuisstraat 3/24 Doetinchem Gelderland 7001 EW",
    "addr:housenumber":"3 / 24",
    "addr:postcode":"7001 ew",
    "addr:street":"Raadhuisstraat;Gelderland",
    "iso:country":"NL",
    "sg:address":"Raadhuisstraat 3/24",
    "sg:city":"Doetinchem",
    "sg:orig_category":"Public Relationbureaus",
    "sg:phone":"+31 314 326 462",
    "sg:postcode":"7001 EW",
    "sg:province":"Gelderland",
    "wof:name":"E.F.P.P. Velsink",
    "wof:placetype":"venue"
},
  "geometry": {"coordinates":[6.291662,51.963974],"type":"Point"}
}