{
  "type": "Feature",
  "properties": {
    "addr:full":"S Heer Boeyenstr 4 Dordrecht Zuid-Holland 3311 BN",
    "addr:housenumber":"4",
    "addr:postcode":"3311 bn",
    "addr:street":"S;Boeyenstr",
    "iso:country":"NL",
    "sg:address":"S Heer Boeyenstr 4",
    "sg:city":"Dordrecht",
    "sg:orig_category":"Pruiken",
    "sg:phone":"+31 78 614 3054",
    "sg:postcode":"3311 BN",
    "sg:province":"Zuid-Holland",
    "wof:name":"Chez Riandre",
    "wof:placetype":"venue"
},
  "geometry": {"coordinates":[4.667752,51.816174],"type":"Point"}
}