{
  "type": "Feature",
  "properties": {
    "iso:country":"NL",
    "sg:address":"Industrieweg 141",
    "sg:city":"Rotterdam",
    "sg:classifiers":[
        {
            "category":"Shopping",
            "subcategory":"Gifts & Souvenirs",
            "type":"Retail Goods"
        }
    ],
    "sg:phone":"+31 10 415 2166",
    "sg:postcode":"3044 AS",
    "sg:province":"Zuid-Holland",
    "sg:tags":[
        "geschenken"
    ],
    "wof:name":"J. Nielsen Bv",
    "wof:placetype":"venue"
},
  "geometry": {"coordinates":[4.422316,51.926598],"type":"Point"}
}