{
  "type": "Feature",
  "properties": {
    "iso:country":"NL",
    "sg:address":"Harwichwg 198",
    "sg:city":"Hoek Van Holland",
    "sg:orig_category":"Artiesten/Gezelschappen",
    "sg:phone":"+31 174 386 106",
    "sg:postcode":"3151 BR",
    "sg:province":"South Holland",
    "wof:name":"Tiritomba",
    "wof:placetype":"venue"
},
  "geometry": {"coordinates":[4.131552,51.981651],"type":"Point"}
}