{
  "type": "Feature",
  "properties": {
    "iso:country":"NL",
    "sg:address":"Ackershof 31",
    "sg:city":"Pynacker",
    "sg:orig_category":"Herenkleding",
    "sg:phone":"+31 15 361 7448",
    "sg:postcode":"2641 DZ",
    "sg:province":"Zuid-Holland",
    "wof:name":"Futuro Mannenmode",
    "wof:placetype":"venue"
},
  "geometry": {"coordinates":[4.43287,52.018974],"type":"Point"}
}