{
  "type": "Feature",
  "properties": {
    "addr:full":"Vroedschap 11 Naarden Noord-Holland 1412 NV",
    "addr:housenumber":"11",
    "addr:postcode":"1412 nv",
    "addr:street":"Vroedschap",
    "iso:country":"NL",
    "sg:address":"Vroedschap 11",
    "sg:city":"Naarden",
    "sg:classifiers":[
        {
            "category":"Education",
            "subcategory":"School",
            "type":"Public Place"
        }
    ],
    "sg:phone":"+31 35 695 0361",
    "sg:postcode":"1412 NV",
    "sg:province":"Noord-Holland",
    "sg:tags":[
        "studiebegeleiding",
        "en",
        "school-"
    ],
    "wof:name":"Korstanje, E",
    "wof:placetype":"venue"
},
  "geometry": {"coordinates":[5.147419,52.288338],"type":"Point"}
}