{
  "type": "Feature",
  "properties": {
    "iso:country":"NL",
    "sg:address":"Valkenburgerweg 2",
    "sg:city":"Voerendaal",
    "sg:orig_category":"Opticiens",
    "sg:phone":"+31 45 405 9304",
    "sg:postcode":"6367 GV",
    "sg:province":"Limburg",
    "wof:name":"Gerards Optiek",
    "wof:placetype":"venue"
},
  "geometry": {"coordinates":[5.9195928574,50.8764228821],"type":"Point"}
}