{
  "type": "Feature",
  "properties": {
    "addr:full":"Alphons Diepenbrockhof 67 'S Gravenhage South Holland 2551 KJ",
    "addr:housenumber":"67",
    "addr:postcode":"2551 kj",
    "addr:street":"Alphons Diepenbrockhof;' S Gravenhage",
    "iso:country":"NL",
    "sg:address":"Alphons Diepenbrockhof 67",
    "sg:city":"'S Gravenhage",
    "sg:orig_category":"Kunst And Kunstenaarsbenodigdheden",
    "sg:phone":"+31 174 220 332",
    "sg:postcode":"2551 KJ",
    "sg:province":"South Holland",
    "wof:name":"Kunsthandel Jesse Art & Frames",
    "wof:placetype":"venue"
},
  "geometry": {"coordinates":[4.231264,52.058556],"type":"Point"}
}