{
  "type": "Feature",
  "properties": {
    "addr:full":"Nassauln 55 Rynsburg South Holland 2231 VX",
    "addr:housenumber":"55",
    "addr:postcode":"2231 vx",
    "addr:street":"Nassauln",
    "iso:country":"NL",
    "sg:address":"Nassauln 55",
    "sg:city":"Rynsburg",
    "sg:orig_category":"Bloemen En Planten - Groothandel",
    "sg:phone":"+31 71 402 8008",
    "sg:postcode":"2231 VX",
    "sg:province":"South Holland",
    "wof:name":"Messemaker Bv, C",
    "wof:placetype":"venue"
},
  "geometry": {"coordinates":[4.443285,52.1884],"type":"Point"}
}