{
  "type": "Feature",
  "properties": {
    "addr:full":"Vingerling 31 Middelharnis Zuid-Holland 3241 EB",
    "addr:housenumber":"31",
    "addr:postcode":"3241 eb",
    "addr:street":"Vingerling",
    "iso:country":"NL",
    "sg:address":"Vingerling 31",
    "sg:city":"Middelharnis",
    "sg:orig_category":"Bloemen En Planten - Decoratie",
    "sg:phone":"+31 187 486 705",
    "sg:postcode":"3241 EB",
    "sg:province":"Zuid-Holland",
    "wof:name":"Guido Rottiers",
    "wof:placetype":"venue"
},
  "geometry": {"coordinates":[4.167751,51.761208],"type":"Point"}
}