{
  "type": "Feature",
  "properties": {
    "addr:full":"Thorbeckegr 26 Zwolle Overijssel 8011 VM",
    "addr:housenumber":"26",
    "addr:postcode":"8011 vm",
    "addr:street":"Thorbeckegr",
    "iso:country":"NL",
    "sg:address":"Thorbeckegr 26",
    "sg:city":"Zwolle",
    "sg:orig_category":"Galeries",
    "sg:phone":"+31 38 422 2388",
    "sg:postcode":"8011 VM",
    "sg:province":"Overijssel",
    "wof:name":"Kamphuis, J",
    "wof:placetype":"venue"
},
  "geometry": {"coordinates":[6.097344,52.514755],"type":"Point"}
}