{
  "type": "Feature",
  "properties": {
    "iso:country":"NL",
    "sg:address":"Houthavenkd 17",
    "sg:city":"Zaandam",
    "sg:orig_category":"Onderhoudswerken",
    "sg:phone":"+31 75 635 5218",
    "sg:postcode":"1506 PC",
    "sg:province":"Noord-Holland",
    "wof:name":"Volharding, De",
    "wof:placetype":"venue"
},
  "geometry": {"coordinates":[4.82114,52.434322],"type":"Point"}
}