{
  "type": "Feature",
  "properties": {
    "iso:country":"NL",
    "sg:address":"Hartwg 42",
    "sg:city":"Soest",
    "sg:orig_category":"Metselwerken",
    "sg:phone":"+31 35 601 7578",
    "sg:postcode":"3762 SG",
    "sg:province":"Utrecht",
    "wof:name":"Broek, C Van Den",
    "wof:placetype":"venue"
},
  "geometry": {"coordinates":[5.276378,52.183781],"type":"Point"}
}