{
  "type": "Feature",
  "properties": {
    "addr:full":"T M Kortenhorstln 2 Rosmalen Noord-Brabant 5244 GD",
    "addr:housenumber":"2",
    "addr:postcode":"5244 gd",
    "iso:country":"NL",
    "sg:address":"T M Kortenhorstln 2",
    "sg:city":"Rosmalen",
    "sg:orig_category":"Verenigingsgebouwen",
    "sg:phone":"+31 73 522 0982",
    "sg:postcode":"5244 GD",
    "sg:province":"Noord-Brabant",
    "wof:name":"Bron, De",
    "wof:placetype":"venue"
},
  "geometry": {"coordinates":[5.39558,51.718182],"type":"Point"}
}