{
  "type": "Feature",
  "properties": {
    "addr:full":"Goudseplein 262 Rotterdam South Holland 3031 ZH",
    "addr:housenumber":"262",
    "addr:postcode":"3031 zh",
    "addr:street":"Goudseplein",
    "iso:country":"NL",
    "sg:address":"Goudseplein 262",
    "sg:city":"Rotterdam",
    "sg:orig_category":"Kappers",
    "sg:phone":"+31 10 412 6910",
    "sg:postcode":"3031 ZH",
    "sg:province":"South Holland",
    "wof:name":"Kapsalon Latooy",
    "wof:placetype":"venue"
},
  "geometry": {"coordinates":[4.4902358055,51.9283676147],"type":"Point"}
}