{
  "type": "Feature",
  "properties": {
    "addr:full":"Finefrau 95 Kerkrade Limburg 6462 HT",
    "addr:housenumber":"95",
    "addr:postcode":"6462 ht",
    "addr:street":"Finefrau",
    "iso:country":"NL",
    "sg:address":"Finefrau 95",
    "sg:city":"Kerkrade",
    "sg:orig_category":"Schilders",
    "sg:phone":"+31 45 545 2016",
    "sg:postcode":"6462 HT",
    "sg:province":"Limburg",
    "wof:name":"Loenders",
    "wof:placetype":"venue"
},
  "geometry": {"coordinates":[6.074543,50.858425],"type":"Point"}
}