{
  "type": "Feature",
  "properties": {
    "addr:full":"Pr Bernhardstr 78 Asten North Brabant 5721 GD",
    "addr:housenumber":"78",
    "addr:postcode":"5721 gd",
    "iso:country":"NL",
    "sg:address":"Pr Bernhardstr 78",
    "sg:city":"Asten",
    "sg:orig_category":"Organisatiebureaus",
    "sg:phone":"+31 493 699 710",
    "sg:postcode":"5721 GD",
    "sg:province":"North Brabant",
    "wof:name":"Modok Prod",
    "wof:placetype":"venue"
},
  "geometry": {"coordinates":[5.7469749451,51.40782547],"type":"Point"}
}