{
  "type": "Feature",
  "properties": {
    "addr:full":"Westland 18 Moerkapelle Zuid-Holland 2751 EK",
    "addr:housenumber":"18",
    "addr:postcode":"2751 ek",
    "addr:street":"Westland",
    "iso:country":"NL",
    "sg:address":"Westland 18",
    "sg:city":"Moerkapelle",
    "sg:orig_category":"Autorijscholen",
    "sg:phone":"+31 79 593 1496",
    "sg:postcode":"2751 EK",
    "sg:province":"Zuid-Holland",
    "wof:name":"Rijn Vof, A Van",
    "wof:placetype":"venue"
},
  "geometry": {"coordinates":[4.567636,52.042561],"type":"Point"}
}