{
  "type": "Feature",
  "properties": {
    "iso:country":"NL",
    "sg:address":"Schutstraat 49",
    "sg:city":"Hoogeveen",
    "sg:orig_category":"Makelaars In Onroerend Goed",
    "sg:phone":"+31 528 266 851",
    "sg:postcode":"7907 CA",
    "sg:province":"Provincie Drenthe",
    "wof:name":"Vademo Bv",
    "wof:placetype":"venue"
},
  "geometry": {"coordinates":[6.475215,52.719959],"type":"Point"}
}