{
  "type": "Feature",
  "properties": {
    "addr:full":"Arendhorst 25 Roermond Limburg 6043 RR",
    "addr:housenumber":"25",
    "addr:postcode":"6043 rr",
    "addr:street":"Arendhorst",
    "iso:country":"NL",
    "sg:address":"Arendhorst 25",
    "sg:city":"Roermond",
    "sg:orig_category":"Artsen And Specialisten",
    "sg:phone":"+31 475 329 258",
    "sg:postcode":"6043 RR",
    "sg:province":"Limburg",
    "wof:name":"Huisartspraktijk R.W.M. Vosbeek",
    "wof:placetype":"venue"
},
  "geometry": {"coordinates":[6.023685,51.187443],"type":"Point"}
}