{
  "type": "Feature",
  "properties": {
    "addr:full":"Abbringstraat 50 Purmerend Noord-Holland 1447 PB",
    "addr:housenumber":"50",
    "addr:postcode":"1447 pb",
    "addr:street":"Abbringstraat",
    "iso:country":"NL",
    "sg:address":"Abbringstraat 50",
    "sg:city":"Purmerend",
    "sg:orig_category":"Juridische Dienstverlening",
    "sg:phone":"+31 299 646 864",
    "sg:postcode":"1447 PB",
    "sg:province":"Noord-Holland",
    "wof:name":"Adviesbureau Support",
    "wof:placetype":"venue"
},
  "geometry": {"coordinates":[4.972856,52.489037],"type":"Point"}
}