{
  "type": "Feature",
  "properties": {
    "iso:country":"NL",
    "sg:address":"Bartokln 33",
    "sg:city":"Raamsdonksveer",
    "sg:orig_category":"Adviesbureaus Elektrotechniek",
    "sg:phone":"+31 162 513 216",
    "sg:postcode":"4941 WG",
    "sg:province":"North Brabant",
    "wof:name":"Cwa",
    "wof:placetype":"venue"
},
  "geometry": {"coordinates":[4.87459,51.695774],"type":"Point"}
}