{
  "type": "Feature",
  "properties": {
    "iso:country":"NL",
    "sg:address":"Mozartstr 2B",
    "sg:city":"Gorinchem",
    "sg:orig_category":"Peuterspeelzalen",
    "sg:phone":"+31 183 628 851",
    "sg:postcode":"4207 DS",
    "sg:province":"Zuid-Holland",
    "wof:name":"Jip & Janneke",
    "wof:placetype":"venue"
},
  "geometry": {"coordinates":[4.991798,51.834743],"type":"Point"}
}