{
  "type": "Feature",
  "properties": {
    "addr:full":"Krullartstr 10 S Hertogenbosch North Brabant 5211 HR",
    "addr:housenumber":"10",
    "addr:postcode":"5211 hr",
    "addr:street":"Krullartstr;S Hertogenbosch",
    "iso:country":"NL",
    "sg:address":"Krullartstr 10",
    "sg:city":"S Hertogenbosch",
    "sg:orig_category":"Herenkleding",
    "sg:phone":"+31 73 689 0041",
    "sg:postcode":"5211 HR",
    "sg:province":"North Brabant",
    "sg:website":"http://www.mddomani.nl",
    "wof:name":"Moda Di Domani",
    "wof:placetype":"venue"
},
  "geometry": {"coordinates":[5.304894,51.688129],"type":"Point"}
}