{
  "type": "Feature",
  "properties": {
    "addr:full":"Luzernestr 75 Nieuw Vennep Noord-Holland 2153 GM",
    "addr:housenumber":"75",
    "addr:postcode":"2153 gm",
    "addr:street":"Luzernestr;Nieuw Vennep",
    "iso:country":"NL",
    "sg:address":"Luzernestr 75",
    "sg:city":"Nieuw Vennep",
    "sg:orig_category":"Geluidsinstallaties - Verhuur",
    "sg:phone":"+31 252 629 443",
    "sg:postcode":"2153 GM",
    "sg:province":"Noord-Holland",
    "sg:website":"HTTP://www.new-galaxy.nl",
    "wof:name":"New Galaxy",
    "wof:placetype":"venue"
},
  "geometry": {"coordinates":[4.651812,52.265202],"type":"Point"}
}