{
  "type": "Feature",
  "properties": {
    "addr:full":"Keizersweg 64 Holten Overijssel 7451 PG",
    "addr:housenumber":"64",
    "addr:postcode":"7451 pg",
    "addr:street":"Keizersweg",
    "iso:country":"NL",
    "sg:address":"Keizersweg 64",
    "sg:city":"Holten",
    "sg:orig_category":"Verhuur Landbouwmachines",
    "sg:phone":"+31 548 362 855",
    "sg:postcode":"7451 PG",
    "sg:province":"Overijssel",
    "wof:name":"Twentrac Bv",
    "wof:placetype":"venue"
},
  "geometry": {"coordinates":[6.407851,52.280048],"type":"Point"}
}