{
  "type": "Feature",
  "properties": {
    "addr:full":"Rivium 3E Str 7 Capelle Ad Yssel Zuid-Holland 2909 LH",
    "addr:housenumber":"7",
    "addr:postcode":"2909 lh",
    "addr:street":"Rivium 3E Str",
    "iso:country":"NL",
    "sg:address":"Rivium 3E Str 7",
    "sg:city":"Capelle Ad Yssel",
    "sg:orig_category":"Horeca-Inrichtingen En -Uitrustingen",
    "sg:phone":"+31 10 288 5779",
    "sg:postcode":"2909 LH",
    "sg:province":"Zuid-Holland",
    "wof:name":"Neo Metaal Bv",
    "wof:placetype":"venue"
},
  "geometry": {"coordinates":[4.54705,51.910053],"type":"Point"}
}