{
  "type": "Feature",
  "properties": {
    "iso:country":"NL",
    "sg:address":"Hollantlaan 15-19",
    "sg:city":"Utrecht",
    "sg:orig_category":"Meubelzaken, Woning- And Keukeninrichting",
    "sg:phone":"+31 30 289 5444",
    "sg:postcode":"3526 AL",
    "sg:province":"Utrecht",
    "wof:name":"Morgana",
    "wof:placetype":"venue"
},
  "geometry": {"coordinates":[5.105165,52.061989],"type":"Point"}
}