{
  "type": "Feature",
  "properties": {
    "addr:full":"Oudebildtdk 1218 Westhoek Friesland 9075 NR",
    "addr:housenumber":"1218",
    "addr:postcode":"westhoek;9075 nr",
    "iso:country":"NL",
    "sg:address":"Oudebildtdk 1218",
    "sg:city":"Westhoek",
    "sg:classifiers":[
        {
            "category":"Farming",
            "subcategory":"Fish & Marine Products",
            "type":"Manufacturing & Wholesale Goods"
        }
    ],
    "sg:phone":"+31 518 491 732",
    "sg:postcode":"9075 NR",
    "sg:province":"Friesland",
    "sg:tags":[
        "vi"
    ],
    "wof:name":"Kaper-Westra",
    "wof:placetype":"venue"
},
  "geometry": {"coordinates":[5.559024,53.272205],"type":"Point"}
}