{
  "type": "Feature",
  "properties": {
    "addr:full":"Brugakker 1010 Zeist Utrecht 3704 KT",
    "addr:housenumber":"1010",
    "addr:postcode":"3704 kt",
    "addr:street":"Brugakker",
    "iso:country":"NL",
    "sg:address":"Brugakker 1010",
    "sg:city":"Zeist",
    "sg:orig_category":"Bedrijfs- And Managementsconsultants",
    "sg:phone":"+31 30 699 4603",
    "sg:postcode":"3704 KT",
    "sg:province":"Utrecht",
    "wof:name":"Thales",
    "wof:placetype":"venue"
},
  "geometry": {"coordinates":[5.216013,52.081245],"type":"Point"}
}