{
  "type": "Feature",
  "properties": {
    "iso:country":"NL",
    "sg:address":"Prins Hendrikstraat 105",
    "sg:city":"Gouda",
    "sg:classifiers":[
        {
            "category":"Retail",
            "subcategory":"Storage",
            "type":"Services"
        }
    ],
    "sg:phone":"+31 182 519 728",
    "sg:postcode":"2802 JE",
    "sg:province":"South Holland",
    "sg:tags":[
        "opslag",
        "bewaring"
    ],
    "wof:name":"Handelsonderneming T. Van Der Valk",
    "wof:placetype":"venue"
},
  "geometry": {"coordinates":[4.7026519775,52.0087089539],"type":"Point"}
}