{
  "type": "Feature",
  "properties": {
    "addr:full":"Dorpswg 15 Ysselmuiden Overijssel 8271 BJ",
    "addr:housenumber":"15",
    "addr:postcode":"8271 bj",
    "addr:street":"Dorpswg;Overijssel",
    "iso:country":"NL",
    "sg:address":"Dorpswg 15",
    "sg:city":"Ysselmuiden",
    "sg:orig_category":"Kegelbanen",
    "sg:phone":"+31 38 332 0498",
    "sg:postcode":"8271 BJ",
    "sg:province":"Overijssel",
    "wof:name":"Bombardon",
    "wof:placetype":"venue"
},
  "geometry": {"coordinates":[5.931098,52.563881],"type":"Point"}
}