{
  "type": "Feature",
  "properties": {
    "iso:country":"NL",
    "sg:address":"Tuinpad 10",
    "sg:city":"Wassenaar",
    "sg:orig_category":"Verhuur Catering-, Feest- En Evenementbenodigdheden",
    "sg:phone":"+31 70 511 3997",
    "sg:postcode":"2242 TC",
    "sg:province":"South Holland",
    "wof:name":"Van Rhyn Speelautomaten Bv",
    "wof:placetype":"venue"
},
  "geometry": {"coordinates":[4.394113,52.143974],"type":"Point"}
}