{
  "type": "Feature",
  "properties": {
    "iso:country":"NL",
    "sg:address":"Kl Houtstr 53-51-49A",
    "sg:city":"Haarlem",
    "sg:orig_category":"Kampeerartikelen",
    "sg:phone":"+31 23 532 3735",
    "sg:postcode":"2011 DG",
    "sg:province":"Noord-Holland",
    "sg:website":"http://www.soellaart.nl",
    "wof:name":"Soellaart Ski Camping & Trekking",
    "wof:placetype":"venue"
},
  "geometry": {"coordinates":[4.6422529221,52.3805618286],"type":"Point"}
}