{
  "type": "Feature",
  "properties": {
    "iso:country":"NL",
    "sg:address":"Abc Westland 439",
    "sg:city":"Poeldyk",
    "sg:classifiers":[
        {
            "category":"Food & Beverages",
            "subcategory":"Fruits & Vegetables",
            "type":"Retail Goods"
        }
    ],
    "sg:phone":"+31 174 247 722",
    "sg:postcode":"2685 DE",
    "sg:province":"Zuid-Holland",
    "sg:tags":[
        "en",
        "groenten"
    ],
    "wof:name":"Dijk, Van",
    "wof:placetype":"venue"
},
  "geometry": {"coordinates":[4.23236,52.029255],"type":"Point"}
}