{
  "type": "Feature",
  "properties": {
    "iso:country":"NL",
    "sg:address":"Tollensstraat 8",
    "sg:city":"Rijswijk Zh",
    "sg:orig_category":"Architecten",
    "sg:phone":"+31 70 307 7445",
    "sg:postcode":"2282 BM",
    "sg:province":"Zuid-Holland",
    "wof:name":"Architectenbureau J. Vedder Bv",
    "wof:placetype":"venue"
},
  "geometry": {"coordinates":[4.334561,52.056232],"type":"Point"}
}