{
  "type": "Feature",
  "properties": {
    "iso:country":"NL",
    "sg:address":"Bargermeerwg 113",
    "sg:city":"Emmen",
    "sg:orig_category":"Scholen Voor Basisonderwijs",
    "sg:phone":"+31 591 659 842",
    "sg:postcode":"7811 LD",
    "sg:province":"Drenthe",
    "wof:name":"Vegter Openb, Meester",
    "wof:placetype":"venue"
},
  "geometry": {"coordinates":[6.898221,52.776268],"type":"Point"}
}