{
  "type": "Feature",
  "properties": {
    "addr:full":"Trompmoledyk 1 Ijlst Provincie Friesland 8651 ER",
    "addr:housenumber":"1",
    "addr:postcode":"8651 er",
    "addr:street":"Trompmoledyk;Provincie Friesland",
    "iso:country":"NL",
    "sg:address":"Trompmoledyk 1",
    "sg:city":"Ijlst",
    "sg:orig_category":"Film-, Tv- And Videoproductie",
    "sg:phone":"+31 515 533 212",
    "sg:postcode":"8651 ER",
    "sg:province":"Provincie Friesland",
    "wof:name":"D.H.J. Plantinga",
    "wof:placetype":"venue"
},
  "geometry": {"coordinates":[5.62004,53.011597],"type":"Point"}
}