{
  "type": "Feature",
  "properties": {
    "iso:country":"NL",
    "sg:address":"Gooiland 6",
    "sg:city":"Beverwyk",
    "sg:orig_category":"Offsetdrukkerijen",
    "sg:phone":"+31 251 225 841",
    "sg:postcode":"1948 RC",
    "sg:province":"North Holland",
    "wof:name":"Roel",
    "wof:placetype":"venue"
},
  "geometry": {"coordinates":[4.671694,52.468727],"type":"Point"}
}