{
  "type": "Feature",
  "properties": {
    "iso:country":"NL",
    "sg:address":"Lobeliastraat 12",
    "sg:city":"Spijkenisse",
    "sg:orig_category":"Vertaal- And Tolkenbureaus",
    "sg:phone":"+31 181 659 949",
    "sg:postcode":"3202 HS",
    "sg:province":"South Holland",
    "wof:name":"E Votsis-Kuijt",
    "wof:placetype":"venue"
},
  "geometry": {"coordinates":[4.320788,51.858624],"type":"Point"}
}