{
  "type": "Feature",
  "properties": {
    "addr:full":"Orthenstr 33 S Hertogenbosch Noord-Brabant 5211 SV",
    "addr:housenumber":"33",
    "addr:postcode":"5211 sv",
    "addr:street":"Orthenstr;S Hertogenbosch",
    "iso:country":"NL",
    "sg:address":"Orthenstr 33",
    "sg:city":"S Hertogenbosch",
    "sg:orig_category":"Kappers",
    "sg:phone":"+31 73 612 9845",
    "sg:postcode":"5211 SV",
    "sg:province":"Noord-Brabant",
    "wof:name":"Kinki",
    "wof:placetype":"venue"
},
  "geometry": {"coordinates":[5.3013057709,51.6912689209],"type":"Point"}
}