{
  "type": "Feature",
  "properties": {
    "addr:full":"Zuivelpln 9A Amsterdam North Holland 1097 XD",
    "addr:housenumber":"9a",
    "addr:postcode":"1097 xd",
    "addr:street":"Zuivelpln",
    "iso:country":"NL",
    "sg:address":"Zuivelpln 9A",
    "sg:city":"Amsterdam",
    "sg:orig_category":"Modevakscholen",
    "sg:phone":"+31 20 694 8470",
    "sg:postcode":"1097 XD",
    "sg:province":"North Holland",
    "sg:website":"http://www.modeschooldinykelly.nl",
    "wof:name":"Diny Kelly Stichting Modeschool",
    "wof:placetype":"venue"
},
  "geometry": {"coordinates":[4.946277,52.339649],"type":"Point"}
}