{
  "type": "Feature",
  "properties": {
    "addr:full":"Kleineweg 8 Gennep Limburg 6591 CR",
    "addr:housenumber":"8",
    "addr:postcode":"6591 cr",
    "addr:street":"Kleineweg",
    "iso:country":"NL",
    "sg:address":"Kleineweg 8",
    "sg:city":"Gennep",
    "sg:orig_category":"Bloemen- And Plantenteelt",
    "sg:phone":"+31 485 511 969",
    "sg:postcode":"6591 CR",
    "sg:province":"Limburg",
    "wof:name":"Rezo Bv",
    "wof:placetype":"venue"
},
  "geometry": {"coordinates":[5.973034,51.703907],"type":"Point"}
}