{
  "type": "Feature",
  "properties": {
    "addr:full":"Wierdensestr 131 Almelo Overijssel 7604 BD",
    "addr:housenumber":"131",
    "addr:postcode":"7604 bd",
    "iso:country":"NL",
    "sg:address":"Wierdensestr 131",
    "sg:city":"Almelo",
    "sg:orig_category":"Hulpverlening Sociaal",
    "sg:phone":"+31 546 488 300",
    "sg:postcode":"7604 BD",
    "sg:province":"Overijssel",
    "sg:website":"http://www.commujonlsg.nl",
    "wof:name":"Commujon, Sticht",
    "wof:placetype":"venue"
},
  "geometry": {"coordinates":[6.651977,52.355469],"type":"Point"}
}