{
  "type": "Feature",
  "properties": {
    "iso:country":"NL",
    "sg:address":"Duistervoordseweg 2",
    "sg:city":"Twello",
    "sg:orig_category":"Kappers",
    "sg:phone":"+31 571 271 423",
    "sg:postcode":"7391 CD",
    "sg:province":"Gelderland",
    "wof:name":"E.J. Koolman Jr",
    "wof:placetype":"venue"
},
  "geometry": {"coordinates":[6.1031031609,52.2369537354],"type":"Point"}
}