{
  "type": "Feature",
  "properties": {
    "iso:country":"NL",
    "sg:address":"Seringenstr 26",
    "sg:city":"Kerkrade",
    "sg:orig_category":"Kappers",
    "sg:phone":"+31 45 542 4820",
    "sg:postcode":"6466 XL",
    "sg:province":"Limburg",
    "wof:name":"Lizitta Hairfashion",
    "wof:placetype":"venue"
},
  "geometry": {"coordinates":[6.03757,50.864029],"type":"Point"}
}