{
  "type": "Feature",
  "properties": {
    "addr:full":"Provenierspln 7B Rotterdam Zuid-Holland 3033 EB",
    "addr:housenumber":"7b",
    "addr:postcode":"3033 eb",
    "addr:street":"Provenierspln",
    "iso:country":"NL",
    "sg:address":"Provenierspln 7B",
    "sg:city":"Rotterdam",
    "sg:orig_category":"Adviesbureaus Bedrijfsorganisatie",
    "sg:phone":"+31 10 467 3331",
    "sg:postcode":"3033 EB",
    "sg:province":"Zuid-Holland",
    "wof:name":"Burg, J F Van Der",
    "wof:placetype":"venue"
},
  "geometry": {"coordinates":[4.472769,51.928341],"type":"Point"}
}