{
  "type": "Feature",
  "properties": {
    "iso:country":"NL",
    "sg:address":"Hoofdwg Z 6",
    "sg:city":"Zuiddorpe",
    "sg:orig_category":"Verenigingen En Stichtingen",
    "sg:phone":"+31 115 606 062",
    "sg:postcode":"4574 RX",
    "sg:province":"Zeeland",
    "sg:website":"http://home.wxs.nl/~an.hoecke/siesa.htm",
    "wof:name":"Siesa Toneelver",
    "wof:placetype":"venue"
},
  "geometry": {"coordinates":[3.910741,51.238647],"type":"Point"}
}