{
  "type": "Feature",
  "properties": {
    "addr:full":"Rijksweg Centrum 23 Geleen Limburg 6161 EB",
    "addr:housenumber":"23",
    "addr:postcode":"6161 eb",
    "addr:street":"Rijksweg Centrum",
    "iso:country":"NL",
    "sg:address":"Rijksweg Centrum 23",
    "sg:city":"Geleen",
    "sg:classifiers":[
        {
            "category":"Fast Food",
            "type":"Food & Drink"
        }
    ],
    "sg:phone":"+31 46 475 2689",
    "sg:postcode":"6161 EB",
    "sg:province":"Limburg",
    "sg:tags":[
        "afhaal",
        "restaurant"
    ],
    "wof:name":"Shoarma En Pizzeria Walili",
    "wof:placetype":"venue"
},
  "geometry": {"coordinates":[5.830812,50.969543],"type":"Point"}
}