{
  "type": "Feature",
  "properties": {
    "addr:full":"Vlaardingerdk 1 Schiedam Zuid-Holland 3117 EA",
    "addr:housenumber":"1",
    "addr:postcode":"3117 ea",
    "addr:street":"Vlaardingerdk",
    "iso:country":"NL",
    "sg:address":"Vlaardingerdk 1",
    "sg:city":"Schiedam",
    "sg:classifiers":[
        {
            "category":"Travel",
            "subcategory":"Hotels & Motels",
            "type":"Entertainment"
        }
    ],
    "sg:phone":"+31 10 426 7007",
    "sg:postcode":"3117 EA",
    "sg:province":"Zuid-Holland",
    "wof:name":"Windmill",
    "wof:placetype":"venue"
},
  "geometry": {"coordinates":[4.392123,51.917179],"type":"Point"}
}