{
  "type": "Feature",
  "properties": {
    "addr:full":"Ubbeschoterweg 12 Renswoude Utrecht 3927 CJ",
    "addr:housenumber":"12",
    "addr:postcode":"3927 cj",
    "addr:street":"Ubbeschoterweg",
    "iso:country":"NL",
    "sg:address":"Ubbeschoterweg 12",
    "sg:city":"Renswoude",
    "sg:orig_category":"Kampeerterreinen",
    "sg:phone":"+31 6 54960937",
    "sg:postcode":"3927 CJ",
    "sg:province":"Utrecht",
    "wof:name":"De Nieuwe Beek",
    "wof:placetype":"venue"
},
  "geometry": {"coordinates":[5.5491719246,52.0843238831],"type":"Point"}
}