{
  "type": "Feature",
  "properties": {
    "addr:full":"Bruinvisstr 50 Amsterdam Noord-Holland 1035 HZ",
    "addr:housenumber":"50",
    "addr:postcode":"1035 hz",
    "addr:street":"Bruinvisstr",
    "iso:country":"NL",
    "sg:address":"Bruinvisstr 50",
    "sg:city":"Amsterdam",
    "sg:orig_category":"Schilders",
    "sg:phone":"+31 20 633 6829",
    "sg:postcode":"1035 HZ",
    "sg:province":"Noord-Holland",
    "wof:name":"Erdal Vof Decoratie",
    "wof:placetype":"venue"
},
  "geometry": {"coordinates":[4.8858628273,52.4237365723],"type":"Point"}
}