{
  "type": "Feature",
  "properties": {
    "addr:full":"Vissersdijk 35 Woudrichem North Brabant 4285 AM",
    "addr:housenumber":"35",
    "addr:postcode":"4285",
    "addr:street":"Vissersdijk",
    "iso:country":"NL",
    "sg:address":"Vissersdijk 35",
    "sg:city":"Woudrichem",
    "sg:orig_category":"Public Relationbureaus",
    "sg:phone":"+31 183 304 135",
    "sg:postcode":"4285 AM",
    "sg:province":"North Brabant",
    "wof:name":"Public Presentation",
    "wof:placetype":"venue"
},
  "geometry": {"coordinates":[5.004739,51.817139],"type":"Point"}
}