{
  "type": "Feature",
  "properties": {
    "iso:country":"NL",
    "sg:address":"Amsterdamsestraatweg 7C",
    "sg:city":"Naarden",
    "sg:orig_category":"Binnenhuisarchitecten",
    "sg:phone":"+31 35 695 3484",
    "sg:postcode":"1411 AW",
    "sg:province":"North Holland",
    "wof:name":"De Brouwer Binnenwerk",
    "wof:placetype":"venue"
},
  "geometry": {"coordinates":[5.153725,52.300159],"type":"Point"}
}