{
  "type": "Feature",
  "properties": {
    "iso:country":"NL",
    "sg:address":"Handelsweg 12",
    "sg:city":"Sint-Oedenrode",
    "sg:orig_category":"Werving And Selectie Van Tijdelijk Personeel And Uitzendkantoren",
    "sg:phone":"+31 413 490 088",
    "sg:postcode":"5492  N",
    "sg:province":"Noord-Brabant",
    "wof:name":"Progress Uitzendbureau",
    "wof:placetype":"venue"
},
  "geometry": {"coordinates":[5.4818201065,51.5580215454],"type":"Point"}
}