{
  "type": "Feature",
  "properties": {
    "addr:full":"Markt 20 St Maartensdyk Zeeland 4695 CG",
    "addr:housenumber":"20",
    "addr:postcode":"4695 cg",
    "addr:street":"Markt",
    "iso:country":"NL",
    "sg:address":"Markt 20",
    "sg:city":"St Maartensdyk",
    "sg:orig_category":"Drogisterijen",
    "sg:phone":"+31 166 664 946",
    "sg:postcode":"4695 CG",
    "sg:province":"Zeeland",
    "wof:name":"Ligtvoet, Drogisterij",
    "wof:placetype":"venue"
},
  "geometry": {"coordinates":[4.07773,51.549244],"type":"Point"}
}