{
  "type": "Feature",
  "properties": {
    "iso:country":"NL",
    "sg:address":"Postbus 23203",
    "sg:city":"Amsterdam Zuidoost",
    "sg:orig_category":"Pensioenen",
    "sg:phone":"+31 20 696 9121",
    "sg:postcode":"1100 DS",
    "sg:province":"North Holland",
    "wof:name":"Prometheus",
    "wof:placetype":"venue"
},
  "geometry": {"coordinates":[4.95131,52.316158],"type":"Point"}
}