{
  "type": "Feature",
  "properties": {
    "iso:country":"NL",
    "sg:address":"Patroonswg 23",
    "sg:city":"Zeewolde",
    "sg:orig_category":"Weegwerktuigen - Fabrieken En Groothandel",
    "sg:phone":"+31 36 522 2030",
    "sg:postcode":"3892 DA",
    "sg:province":"Flevoland",
    "sg:website":"http://www.weegtechniek.nl",
    "wof:name":"Weegtechniek Holland Bv",
    "wof:placetype":"venue"
},
  "geometry": {"coordinates":[5.5314497948,52.3243675232],"type":"Point"}
}