{
  "type": "Feature",
  "properties": {
    "addr:full":"Grift 42 Rotterdam Zuid-Holland 3075 SB",
    "addr:housenumber":"42",
    "addr:postcode":"3075 sb",
    "addr:street":"Grift",
    "iso:country":"NL",
    "sg:address":"Grift 42",
    "sg:city":"Rotterdam",
    "sg:classifiers":[
        {
            "category":"Education",
            "subcategory":"Preschool",
            "type":"Public Place"
        }
    ],
    "sg:phone":"+31 10 419 0434",
    "sg:postcode":"3075 SB",
    "sg:province":"Zuid-Holland",
    "sg:tags":[
        "kleuteronderwijs",
        "basis-"
    ],
    "wof:name":"Montessorischool De Mare",
    "wof:placetype":"venue"
},
  "geometry": {"coordinates":[4.508269,51.882645],"type":"Point"}
}