{
  "type": "Feature",
  "properties": {
    "iso:country":"NL",
    "sg:address":"Sportln 87A",
    "sg:city":"Emmeloord",
    "sg:orig_category":"Sportverenigingen En Ontspannings- Verenigingen",
    "sg:phone":"+31 527 613 878",
    "sg:postcode":"8302 AX",
    "sg:province":"Flevoland",
    "wof:name":"Emelwerth Tenniscl",
    "wof:placetype":"venue"
},
  "geometry": {"coordinates":[5.750635,52.709873],"type":"Point"}
}