{
  "type": "Feature",
  "properties": {
    "iso:country":"NL",
    "sg:address":"Stokweg 6",
    "sg:city":"Rhenen",
    "sg:orig_category":"Loodgieterswerk, Verwarming And Sanitaire Installaties",
    "sg:phone":"+31 317 616 900",
    "sg:postcode":"3911 TL",
    "sg:province":"Utrecht",
    "wof:name":"Floor Loonwerk",
    "wof:placetype":"venue"
},
  "geometry": {"coordinates":[5.549375,51.968838],"type":"Point"}
}