{
  "type": "Feature",
  "properties": {
    "addr:full":"Copernicusstr 21 Barneveld Gelderland 3772 CV",
    "addr:housenumber":"21",
    "addr:postcode":"3772 cv",
    "addr:street":"Copernicusstr;Gelderland",
    "iso:country":"NL",
    "sg:address":"Copernicusstr 21",
    "sg:city":"Barneveld",
    "sg:classifiers":[
        {
            "category":"Personal",
            "subcategory":"Nail Salon",
            "type":"Services"
        }
    ],
    "sg:phone":"+31 342 450 135",
    "sg:postcode":"3772 CV",
    "sg:province":"Gelderland",
    "sg:tags":[
        "pedicure"
    ],
    "wof:name":"Edith",
    "wof:placetype":"venue"
},
  "geometry": {"coordinates":[5.578667,52.136948],"type":"Point"}
}