{
  "type": "Feature",
  "properties": {
    "iso:country":"NL",
    "sg:address":"Noord Esmarkerrondweg 408",
    "sg:city":"Enschede",
    "sg:orig_category":"Bloemen And Planten",
    "sg:phone":"+31 53 431 7635",
    "sg:postcode":"7533 BH",
    "sg:province":"Overijssel",
    "wof:name":"Monica'S Flowers & Decoration",
    "wof:placetype":"venue"
},
  "geometry": {"coordinates":[6.927906,52.222366],"type":"Point"}
}