{
  "type": "Feature",
  "properties": {
    "addr:full":"Kapelstr 17 , (Mobiele Tel) Erp Noord-Brabant 5469 NC",
    "addr:housenumber":"17",
    "addr:postcode":"5469 nc",
    "addr:street":"Kapelstr;Tel",
    "iso:country":"NL",
    "sg:address":"Kapelstr 17 , (Mobiele Tel)",
    "sg:city":"Erp",
    "sg:orig_category":"Boomrooierijen",
    "sg:phone":"+31 6 53721228",
    "sg:postcode":"5469 NC",
    "sg:province":"Noord-Brabant",
    "sg:website":"http://www.boomverzorgingkanters.nl",
    "wof:name":"Jos Kanters",
    "wof:placetype":"venue"
},
  "geometry": {"coordinates":[-80.018333,35.21941],"type":"Point"}
}