{
  "type": "Feature",
  "properties": {
    "addr:full":"Schuylenburchstr 62 Delft Zuid-Holland 2614 CB",
    "addr:housenumber":"62",
    "addr:postcode":"2614 cb",
    "addr:street":"Schuylenburchstr",
    "iso:country":"NL",
    "sg:address":"Schuylenburchstr 62",
    "sg:city":"Delft",
    "sg:orig_category":"Fietsen En Bromfietsen",
    "sg:phone":"+31 15 215 9996",
    "sg:postcode":"2614 CB",
    "sg:province":"Zuid-Holland",
    "wof:name":"Opknapper, Rijwielhersteller",
    "wof:placetype":"venue"
},
  "geometry": {"coordinates":[4.33612,52.012318],"type":"Point"}
}