{
  "type": "Feature",
  "properties": {
    "addr:full":"Kennemerstraatweg 51 Heiloo Noord-Holland 1851 BA",
    "addr:housenumber":"51",
    "addr:postcode":"1851 ba",
    "addr:street":"Kennemerstraatweg",
    "iso:country":"NL",
    "sg:address":"Kennemerstraatweg 51",
    "sg:city":"Heiloo",
    "sg:orig_category":"Binnenhuisarchitecten",
    "sg:phone":"+31 72 532 0435",
    "sg:postcode":"1851 BA",
    "sg:province":"Noord-Holland",
    "wof:name":"Vivid Dreams",
    "wof:placetype":"venue"
},
  "geometry": {"coordinates":[4.716744,52.607487],"type":"Point"}
}