{
  "type": "Feature",
  "properties": {
    "addr:full":"Oosterend 10A Terschelling O End Friesland 8897 HZ",
    "addr:housenumber":"10a",
    "addr:postcode":"8897 hz",
    "addr:street":"Oosterend;O",
    "iso:country":"NL",
    "sg:address":"Oosterend 10A",
    "sg:city":"Terschelling O End",
    "sg:orig_category":"Zuivel - Fabrieken",
    "sg:phone":"+31 562 448 300",
    "sg:postcode":"8897 HZ",
    "sg:province":"Friesland",
    "wof:name":"Terschellinger, De",
    "wof:placetype":"venue"
},
  "geometry": {"coordinates":[5.377269,53.403782],"type":"Point"}
}