{
  "type": "Feature",
  "properties": {
    "iso:country":"NL",
    "sg:address":"Schoutenstraat 13",
    "sg:city":"Hilversum",
    "sg:classifiers":[
        {
            "category":"Fast Food",
            "type":"Food & Drink"
        }
    ],
    "sg:phone":"+31 35 624 5359",
    "sg:postcode":"1211 BM",
    "sg:province":"Noord-Holland",
    "sg:tags":[
        "afhaal",
        "restaurant"
    ],
    "wof:name":"Felice Lunchkamer & Koffiecafe",
    "wof:placetype":"venue"
},
  "geometry": {"coordinates":[5.172486,52.225227],"type":"Point"}
}