{
  "type": "Feature",
  "properties": {
    "addr:full":"Baarderburen 3 Arum Provincie Friesland 8822 WR",
    "addr:housenumber":"3",
    "addr:postcode":"8822",
    "addr:street":"Baarderburen;Provincie Friesland",
    "iso:country":"NL",
    "sg:address":"Baarderburen 3",
    "sg:city":"Arum",
    "sg:orig_category":"Wegenbouw - Materieel",
    "sg:phone":"+31 517 641 329",
    "sg:postcode":"8822 WR",
    "sg:province":"Provincie Friesland",
    "wof:name":"Anema & Zn Bv",
    "wof:placetype":"venue"
},
  "geometry": {"coordinates":[5.4763197899,53.1299667358],"type":"Point"}
}