{
  "type": "Feature",
  "properties": {
    "addr:full":"De Wetering 8 Goirle Noord-Brabant 5052 TE",
    "addr:housenumber":"8",
    "addr:postcode":"5052 te",
    "addr:street":"De Wetering",
    "iso:country":"NL",
    "sg:address":"De Wetering 8",
    "sg:city":"Goirle",
    "sg:orig_category":"Administratie- En Boekhoudkantoren",
    "sg:phone":"+31 13 534 2541",
    "sg:postcode":"5052 TE",
    "sg:province":"Noord-Brabant",
    "sg:website":"http://www.loohuw.com",
    "wof:name":"Loon, Van",
    "wof:placetype":"venue"
},
  "geometry": {"coordinates":[5.046275,51.525379],"type":"Point"}
}