{
  "type": "Feature",
  "properties": {
    "iso:country":"NL",
    "sg:address":"Techniekwg 17",
    "sg:city":"Leerdam",
    "sg:orig_category":"Beveiliging",
    "sg:phone":"+31 345 612 118",
    "sg:postcode":"4143 HW",
    "sg:province":"Zuid-Holland",
    "wof:name":"Verkuil Bv",
    "wof:placetype":"venue"
},
  "geometry": {"coordinates":[5.103432,51.901848],"type":"Point"}
}