{
  "type": "Feature",
  "properties": {
    "addr:full":"Heutzstraat 33 Venlo Limburg 5913 AH",
    "addr:housenumber":"33",
    "addr:postcode":"5913 ah",
    "addr:street":"Heutzstraat",
    "iso:country":"NL",
    "sg:address":"Heutzstraat 33",
    "sg:city":"Venlo",
    "sg:orig_category":"Wasserettes And Stomerijen",
    "sg:phone":"+31 77 351 4272",
    "sg:postcode":"5913 AH",
    "sg:province":"Limburg",
    "wof:name":"Christel'S Wassalon",
    "wof:placetype":"venue"
},
  "geometry": {"coordinates":[6.1744179726,51.365562439],"type":"Point"}
}