{
  "type": "Feature",
  "properties": {
    "addr:full":"Savelsbos 108 Zoetermeer Zuid-Holland 2716 HE",
    "addr:housenumber":"108",
    "addr:postcode":"2716 he",
    "addr:street":"Savelsbos",
    "iso:country":"NL",
    "sg:address":"Savelsbos 108",
    "sg:city":"Zoetermeer",
    "sg:classifiers":[
        {
            "category":"Professional",
            "subcategory":"Accounting & Tax Preparation",
            "type":"Services"
        }
    ],
    "sg:phone":"+31 79 352 3242",
    "sg:postcode":"2716 HE",
    "sg:province":"Zuid-Holland",
    "sg:tags":[
        "accountant"
    ],
    "wof:name":"O.E. V.D. Hoek",
    "wof:placetype":"venue"
},
  "geometry": {"coordinates":[4.467658,52.057194],"type":"Point"}
}