{
  "type": "Feature",
  "properties": {
    "addr:full":"Wycker Brugstr 45 Maastricht Limburg 6221 EB",
    "addr:housenumber":"45",
    "addr:postcode":"6221 eb",
    "addr:street":"Wycker",
    "iso:country":"NL",
    "sg:address":"Wycker Brugstr 45",
    "sg:city":"Maastricht",
    "sg:orig_category":"Dameskleding",
    "sg:phone":"+31 43 325 1935",
    "sg:postcode":"6221 EB",
    "sg:province":"Limburg",
    "wof:name":"Eve-S?lection",
    "wof:placetype":"venue"
},
  "geometry": {"coordinates":[5.698656,50.849354],"type":"Point"}
}