{
  "type": "Feature",
  "properties": {
    "addr:full":"Speelwagenstraat 122 Purmerend North Holland 1445 PJ",
    "addr:housenumber":"122",
    "addr:postcode":"1445 pj",
    "addr:street":"Speelwagenstraat",
    "iso:country":"NL",
    "sg:address":"Speelwagenstraat 122",
    "sg:city":"Purmerend",
    "sg:orig_category":"Boekhouders",
    "sg:phone":"+31 299 644 088",
    "sg:postcode":"1445 PJ",
    "sg:province":"North Holland",
    "wof:name":"Advies- En Administratiekantoor Drp",
    "wof:placetype":"venue"
},
  "geometry": {"coordinates":[4.975883,52.500237],"type":"Point"}
}