{
  "type": "Feature",
  "properties": {
    "addr:full":"B Leurinkstr 1-3 Losser Overijssel 7581 AR",
    "addr:housenumber":"1-3",
    "addr:postcode":"7581",
    "iso:country":"NL",
    "sg:address":"B Leurinkstr 1-3",
    "sg:city":"Losser",
    "sg:orig_category":"Apotheken",
    "sg:phone":"+31 53 536 9191",
    "sg:postcode":"7581 AR",
    "sg:province":"Overijssel",
    "wof:name":"Teylers",
    "wof:placetype":"venue"
},
  "geometry": {"coordinates":[7.003292,52.264015],"type":"Point"}
}