{
  "type": "Feature",
  "properties": {
    "iso:country":"NL",
    "sg:address":"Ster Bastion 44",
    "sg:city":"Velserbroek",
    "sg:classifiers":[
        {
            "category":"Food & Beverages",
            "subcategory":"Fruits & Vegetables",
            "type":"Retail Goods"
        }
    ],
    "sg:phone":"+31 23 538 7357",
    "sg:postcode":"1991 PN",
    "sg:province":"Noord-Holland",
    "sg:tags":[
        "groenten"
    ],
    "wof:name":"Spronk Groentespeciaalzaak",
    "wof:placetype":"venue"
},
  "geometry": {"coordinates":[4.659876,52.43494],"type":"Point"}
}