{
  "type": "Feature",
  "properties": {
    "addr:full":"Grondzeilerwg 6 Culemborg Gelderland 4105 HJ",
    "addr:housenumber":"6",
    "addr:postcode":"4105 hj",
    "addr:street":"Grondzeilerwg;Gelderland",
    "iso:country":"NL",
    "sg:address":"Grondzeilerwg 6",
    "sg:city":"Culemborg",
    "sg:orig_category":"Pensioenen",
    "sg:phone":"+31 345 510 363",
    "sg:postcode":"4105 HJ",
    "sg:province":"Gelderland",
    "wof:name":"Lamens Bv",
    "wof:placetype":"venue"
},
  "geometry": {"coordinates":[5.214529,51.950291],"type":"Point"}
}