{
  "type": "Feature",
  "properties": {
    "addr:full":"Kienstobbe 7 Zuidwolde Dr Drenthe 7921 EK",
    "addr:housenumber":"7",
    "addr:postcode":"7921 ek",
    "addr:street":"Kienstobbe;Dr",
    "iso:country":"NL",
    "sg:address":"Kienstobbe 7",
    "sg:city":"Zuidwolde Dr",
    "sg:orig_category":"Elektrotechnische Apparatuur - Fabrieken En Groothandel",
    "sg:phone":"+31 528 373 979",
    "sg:postcode":"7921 EK",
    "sg:province":"Drenthe",
    "wof:name":"Ko-Time Vof",
    "wof:placetype":"venue"
},
  "geometry": {"coordinates":[6.42853,52.67675],"type":"Point"}
}