{
  "type": "Feature",
  "properties": {
    "addr:full":"Ootmarsumsestr 20 Almelo NL.08 7607 BC",
    "addr:housenumber":"20;nl.08",
    "addr:postcode":"7607 bc",
    "addr:street":"Ootmarsumsestr",
    "iso:country":"NL",
    "sg:address":"Ootmarsumsestr 20",
    "sg:city":"Almelo",
    "sg:orig_category":"Fietsen En Bromfietsen",
    "sg:phone":"+31 546 817 660",
    "sg:postcode":"7607 BC",
    "sg:province":"NL.08",
    "wof:name":"Stuivenberg",
    "wof:placetype":"venue"
},
  "geometry": {"coordinates":[6.667665,52.36026],"type":"Point"}
}