{
  "type": "Feature",
  "properties": {
    "addr:full":"Ceciliawg 2 St Annaland Zeeland 4697 RV",
    "addr:housenumber":"2",
    "addr:postcode":"4697 rv",
    "addr:street":"Ceciliawg",
    "iso:country":"NL",
    "sg:address":"Ceciliawg 2",
    "sg:city":"St Annaland",
    "sg:orig_category":"Plafonds",
    "sg:phone":"+31 166 657 105",
    "sg:postcode":"4697 RV",
    "sg:province":"Zeeland",
    "sg:website":"http://www.cb-interieurafwerking.nl",
    "wof:name":"Cb, Spanplafonds",
    "wof:placetype":"venue"
},
  "geometry": {"coordinates":[4.1123,51.594898],"type":"Point"}
}