{
  "type": "Feature",
  "properties": {
    "iso:country":"NL",
    "sg:address":"St. Annastraat 8",
    "sg:city":"Breda",
    "sg:orig_category":"Verhuur Diversen",
    "sg:phone":"+31 76 521 7442",
    "sg:postcode":"4811 XK",
    "sg:province":"North Brabant",
    "wof:name":"Gebroeders Couvreur",
    "wof:placetype":"venue"
},
  "geometry": {"coordinates":[4.778204,51.588867],"type":"Point"}
}