{
  "type": "Feature",
  "properties": {
    "addr:full":"Parallel Boulev 21A Noordwyk Zh Zuid-Holland 2202 HK",
    "addr:housenumber":"21a",
    "addr:postcode":"2202 hk",
    "addr:street":"Noordwyk",
    "iso:country":"NL",
    "sg:address":"Parallel Boulev 21A",
    "sg:city":"Noordwyk Zh",
    "sg:orig_category":"Fotografie Reclame En Mode",
    "sg:phone":"+31 71 364 8114",
    "sg:postcode":"2202 HK",
    "sg:province":"Zuid-Holland",
    "sg:website":"http://www.velzeboer.com",
    "wof:name":"Velzeboer, Monique",
    "wof:placetype":"venue"
},
  "geometry": {"coordinates":[4.435614,52.248837],"type":"Point"}
}