{
  "type": "Feature",
  "properties": {
    "addr:full":"Jura 19 Utrecht Utrecht 3524 HK",
    "addr:housenumber":"19",
    "addr:postcode":"3524 hk",
    "addr:street":"Jura",
    "iso:country":"NL",
    "sg:address":"Jura 19",
    "sg:city":"Utrecht",
    "sg:orig_category":"Vertaalbureaus",
    "sg:phone":"+31 30 267 2219",
    "sg:postcode":"3524 HK",
    "sg:province":"Utrecht",
    "wof:name":"Weegh, Op De",
    "wof:placetype":"venue"
},
  "geometry": {"coordinates":[5.133201,52.059963],"type":"Point"}
}