{
  "type": "Feature",
  "properties": {
    "iso:country":"NL",
    "sg:address":"Dorpsstr 61",
    "sg:city":"De Bilt",
    "sg:orig_category":"Galeries",
    "sg:phone":"+31 30 220 0446",
    "sg:postcode":"3732 HH",
    "sg:province":"Utrecht",
    "sg:website":"http://www.hetoudedorp.nl",
    "wof:name":"Oude Dorp, Galerie Het",
    "wof:placetype":"venue"
},
  "geometry": {"coordinates":[5.18231,52.104057],"type":"Point"}
}