{
  "type": "Feature",
  "properties": {
    "addr:full":"Koekoeksbloemweg 30 Zaandam North Holland 1508 BK",
    "addr:housenumber":"30",
    "addr:postcode":"1508 bk",
    "addr:street":"Koekoeksbloemweg",
    "iso:country":"NL",
    "sg:address":"Koekoeksbloemweg 30",
    "sg:city":"Zaandam",
    "sg:orig_category":"Loodgieterswerk, Verwarming And Sanitaire Installaties",
    "sg:phone":"+31 75 614 9773",
    "sg:postcode":"1508 BK",
    "sg:province":"North Holland",
    "wof:name":"Allfixed",
    "wof:placetype":"venue"
},
  "geometry": {"coordinates":[4.824633,52.459557],"type":"Point"}
}