{
  "type": "Feature",
  "properties": {
    "addr:full":"Puntwg 18A Spykenisse South Holland 3208 LD",
    "addr:housenumber":"18a",
    "addr:postcode":"3208 ld",
    "addr:street":"Puntwg",
    "iso:country":"NL",
    "sg:address":"Puntwg 18A",
    "sg:city":"Spykenisse",
    "sg:classifiers":[
        {
            "category":"Shopping",
            "subcategory":"News",
            "type":"Retail Goods"
        }
    ],
    "sg:phone":"+31 181 657 281",
    "sg:postcode":"3208 LD",
    "sg:province":"South Holland",
    "sg:tags":[
        "maandbladen",
        "en",
        "week-"
    ],
    "wof:name":"Delta",
    "wof:placetype":"venue"
},
  "geometry": {"coordinates":[4.3028998375,51.8426399231],"type":"Point"}
}