{
  "type": "Feature",
  "properties": {
    "addr:full":"Vesperstr 68 Mierlo North Brabant 5731 GT",
    "addr:housenumber":"68",
    "addr:postcode":"5731 gt",
    "addr:street":"Vesperstr",
    "iso:country":"NL",
    "sg:address":"Vesperstr 68",
    "sg:city":"Mierlo",
    "sg:classifiers":[
        {
            "category":"Utilities",
            "subcategory":"Cable",
            "type":"Services"
        }
    ],
    "sg:phone":"+31 492 665 788",
    "sg:postcode":"5731 GT",
    "sg:province":"North Brabant",
    "sg:tags":[
        "masseur",
        "en",
        "heilgymnasten"
    ],
    "wof:name":"Balance For Health",
    "wof:placetype":"venue"
},
  "geometry": {"coordinates":[5.625254,51.442287],"type":"Point"}
}