{
  "type": "Feature",
  "properties": {
    "iso:country":"NL",
    "sg:address":"Barteljorisstraat 27",
    "sg:city":"Haarlem",
    "sg:orig_category":"Damesmodezaken",
    "sg:phone":"+31 23 532 0618",
    "sg:postcode":"2011 RA",
    "sg:province":"North Holland",
    "wof:name":"Modehuis Kemp Bv",
    "wof:placetype":"venue"
},
  "geometry": {"coordinates":[4.635427,52.38205],"type":"Point"}
}