{
  "type": "Feature",
  "properties": {
    "iso:country":"NL",
    "sg:address":"2E Schinkelstr 39",
    "sg:city":"Amsterdam",
    "sg:orig_category":"Meubelen",
    "sg:phone":"+31 20 671 2695",
    "sg:postcode":"1075 TR",
    "sg:province":"North Holland",
    "sg:website":"http://www.woontoko.nl",
    "wof:name":"Woontoko.Nl",
    "wof:placetype":"venue"
},
  "geometry": {"coordinates":[4.85412,52.353104],"type":"Point"}
}