{
  "type": "Feature",
  "properties": {
    "addr:full":"Melkwg 8 Doetinchem Gelderland 7005 AH",
    "addr:housenumber":"8",
    "addr:postcode":"7005 ah",
    "addr:street":"Melkwg;Gelderland",
    "iso:country":"NL",
    "sg:address":"Melkwg 8",
    "sg:city":"Doetinchem",
    "sg:orig_category":"Muziekinstrumenten En Bladmuziek",
    "sg:phone":"+31 314 340 858",
    "sg:postcode":"7005 AH",
    "sg:province":"Gelderland",
    "sg:website":"http://www.odeon.nl",
    "wof:name":"Odeon",
    "wof:placetype":"venue"
},
  "geometry": {"coordinates":[6.291864,51.961128],"type":"Point"}
}