{
  "type": "Feature",
  "properties": {
    "addr:full":"Waaier 10 Leimuiden Zuid-Holland 2451 VV",
    "addr:housenumber":"10",
    "addr:postcode":"2451 vv",
    "addr:street":"Waaier",
    "iso:country":"NL",
    "sg:address":"Waaier 10",
    "sg:city":"Leimuiden",
    "sg:orig_category":"Voeding, Dranken And Tabak Gh",
    "sg:phone":"+31 172 503 333",
    "sg:postcode":"2451 VV",
    "sg:province":"Zuid-Holland",
    "wof:name":"Terrasana Natuurvoeding Leimuiden Bv",
    "wof:placetype":"venue"
},
  "geometry": {"coordinates":[4.680758,52.222557],"type":"Point"}
}