{
  "type": "Feature",
  "properties": {
    "iso:country":"NL",
    "sg:address":"Waaier 10",
    "sg:city":"Leimuiden",
    "sg:orig_category":"Voeding, Dranken And Tabak Gh",
    "sg:phone":"+31 172 503 333",
    "sg:postcode":"2451 VV",
    "sg:province":"Zuid-Holland",
    "wof:name":"Terrasana Natuurvoeding Leimuiden Bv",
    "wof:placetype":"venue"
},
  "geometry": {"coordinates":[4.680758,52.222557],"type":"Point"}
}