{
  "type": "Feature",
  "properties": {
    "addr:full":"Schoolstr 16 Twello Gelderland 7391 DA",
    "addr:housenumber":"16",
    "addr:postcode":"7391 da",
    "addr:street":"Schoolstr;Gelderland",
    "iso:country":"NL",
    "sg:address":"Schoolstr 16",
    "sg:city":"Twello",
    "sg:orig_category":"Hypotheken",
    "sg:phone":"+31 571 271 100",
    "sg:postcode":"7391 DA",
    "sg:province":"Gelderland",
    "wof:name":"Safe",
    "wof:placetype":"venue"
},
  "geometry": {"coordinates":[6.105338,52.237198],"type":"Point"}
}