{
  "type": "Feature",
  "properties": {
    "addr:full":"Gasthuisstraat 1 Meerssen Limburg 6231 JV",
    "addr:housenumber":"1",
    "addr:postcode":"6231 jv",
    "addr:street":"Gasthuisstraat",
    "iso:country":"NL",
    "sg:address":"Gasthuisstraat 1",
    "sg:city":"Meerssen",
    "sg:classifiers":[
        {
            "category":"Bakery",
            "type":"Food & Drink"
        }
    ],
    "sg:phone":"+31 43 364 2323",
    "sg:postcode":"6231 JV",
    "sg:province":"Limburg",
    "sg:tags":[
        "brood",
        "banket"
    ],
    "wof:name":"Firma Bakkerij Bennenbroek",
    "wof:placetype":"venue"
},
  "geometry": {"coordinates":[5.753406,50.885185],"type":"Point"}
}