{
  "type": "Feature",
  "properties": {
    "addr:full":"Beekstraat 37 Meerssen Limburg 6231 LE",
    "addr:housenumber":"37",
    "addr:postcode":"6231 le",
    "addr:street":"Beekstraat",
    "iso:country":"NL",
    "sg:address":"Beekstraat 37",
    "sg:city":"Meerssen",
    "sg:orig_category":"Meubelzaken, Woning- And Keukeninrichting",
    "sg:phone":"+31 43 364 2941",
    "sg:postcode":"6231 LE",
    "sg:province":"Limburg",
    "wof:name":"Meubelen Verheij Warps Bv",
    "wof:placetype":"venue"
},
  "geometry": {"coordinates":[5.75448,50.884823],"type":"Point"}
}