{
  "type": "Feature",
  "properties": {
    "addr:full":"Klepelhoek 11 Leusden Utrecht 3833 GZ",
    "addr:housenumber":"11",
    "addr:postcode":"3833 gz",
    "addr:street":"Klepelhoek",
    "iso:country":"NL",
    "sg:address":"Klepelhoek 11",
    "sg:city":"Leusden",
    "sg:orig_category":"Farmaceutische Producten Gh",
    "sg:phone":"+31 33 494 3964",
    "sg:postcode":"3833 GZ",
    "sg:province":"Utrecht",
    "wof:name":"Cablon Medical Bv",
    "wof:placetype":"venue"
},
  "geometry": {"coordinates":[5.421028,52.119987],"type":"Point"}
}