{
  "type": "Feature",
  "properties": {
    "addr:full":"Linnaeusstr 119 Amsterdam Noord-Holland 1093 EN",
    "addr:housenumber":"119",
    "addr:postcode":"1093 en",
    "iso:country":"NL",
    "sg:address":"Linnaeusstr 119",
    "sg:city":"Amsterdam",
    "sg:orig_category":"Kappers",
    "sg:phone":"+31 20 692 8386",
    "sg:postcode":"1093 EN",
    "sg:province":"Noord-Holland",
    "wof:name":"Team Etos",
    "wof:placetype":"venue"
},
  "geometry": {"coordinates":[4.927244,52.357174],"type":"Point"}
}