{
  "type": "Feature",
  "properties": {
    "addr:full":"Industrieweg 15 Loppersum Groningen 9919 JE",
    "addr:housenumber":"15",
    "addr:postcode":"9919 je",
    "addr:street":"Industrieweg",
    "iso:country":"NL",
    "sg:address":"Industrieweg 15",
    "sg:city":"Loppersum",
    "sg:orig_category":"Schilderwerk",
    "sg:phone":"+31 596 572 130",
    "sg:postcode":"9919 JE",
    "sg:province":"Groningen",
    "wof:name":"J.J. Kiewiet",
    "wof:placetype":"venue"
},
  "geometry": {"coordinates":[6.73782,53.334843],"type":"Point"}
}