{
  "type": "Feature",
  "properties": {
    "addr:full":"Tussendiepen 61B Drachten Provincie Friesland 9206 AC",
    "addr:housenumber":"61b",
    "addr:postcode":"9206 ac",
    "addr:street":"Tussendiepen;Provincie Friesland",
    "iso:country":"NL",
    "sg:address":"Tussendiepen 61B",
    "sg:city":"Drachten",
    "sg:orig_category":"Parketvloeren - Fabrieken",
    "sg:phone":"+31 512 548 511",
    "sg:postcode":"9206 AC",
    "sg:province":"Provincie Friesland",
    "sg:website":"http://www.visser-oosten.nl",
    "wof:name":"Visser & Oosten Vof",
    "wof:placetype":"venue"
},
  "geometry": {"coordinates":[6.065177,53.105869],"type":"Point"}
}