{
  "type": "Feature",
  "properties": {
    "addr:full":"Dordsestr 12 Emmen Drenthe 7822 JR",
    "addr:housenumber":"12",
    "addr:postcode":"7822 jr",
    "addr:street":"Dordsestr",
    "iso:country":"NL",
    "sg:address":"Dordsestr 12",
    "sg:city":"Emmen",
    "sg:orig_category":"Kantoor- En Bedrijfsmeubelen - Fabrieken En Groothandel",
    "sg:phone":"+31 591 682 222",
    "sg:postcode":"7822 JR",
    "sg:province":"Drenthe",
    "wof:name":"Emmein Bv",
    "wof:placetype":"venue"
},
  "geometry": {"coordinates":[6.9003410339,52.7746734619],"type":"Point"}
}