{
  "type": "Feature",
  "properties": {
    "addr:full":"Loosduinse Hoofdstraat 76 'S Gravenhage Zuid-Holland 2552 AK",
    "addr:housenumber":"76",
    "addr:postcode":"2552 ak",
    "addr:street":"Loosduinse Hoofdstraat;' S",
    "iso:country":"NL",
    "sg:address":"Loosduinse Hoofdstraat 76",
    "sg:city":"'S Gravenhage",
    "sg:orig_category":"Herenmodezaken",
    "sg:phone":"+31 70 391 0462",
    "sg:postcode":"2552 AK",
    "sg:province":"Zuid-Holland",
    "wof:name":"Fa J.A. Geleynse",
    "wof:placetype":"venue"
},
  "geometry": {"coordinates":[4.238828,52.054222],"type":"Point"}
}