{
  "type": "Feature",
  "properties": {
    "addr:full":"Knokkel 67 Andijk North Holland 1619 AW",
    "addr:housenumber":"67",
    "addr:postcode":"1619 aw",
    "addr:street":"Knokkel",
    "iso:country":"NL",
    "sg:address":"Knokkel 67",
    "sg:city":"Andijk",
    "sg:orig_category":"Fruit And Groenten Gh",
    "sg:phone":"+31 228 591 571",
    "sg:postcode":"1619 AW",
    "sg:province":"North Holland",
    "wof:name":"P. Roosendaal",
    "wof:placetype":"venue"
},
  "geometry": {"coordinates":[5.241574,52.742386],"type":"Point"}
}