{
  "type": "Feature",
  "properties": {
    "addr:full":"De Kroon 21 Wyk En Aalburg Noord-Brabant 4261 TW",
    "addr:housenumber":"21",
    "addr:postcode":"4261 tw",
    "addr:street":"De Kroon",
    "iso:country":"NL",
    "sg:address":"De Kroon 21",
    "sg:city":"Wyk En Aalburg",
    "sg:orig_category":"Zuivel - Groothandel",
    "sg:phone":"+31 416 692 785",
    "sg:postcode":"4261 TW",
    "sg:province":"Noord-Brabant",
    "wof:name":"Pol En Zonen Bv, D Van Der",
    "wof:placetype":"venue"
},
  "geometry": {"coordinates":[5.123294,51.765221],"type":"Point"}
}