{
  "type": "Feature",
  "properties": {
    "addr:full":"Voorstraat 141 Egmond Aan Zee Noord-Holland 1931 AK",
    "addr:housenumber":"141",
    "addr:postcode":"1931 ak",
    "addr:street":"Voorstraat",
    "iso:country":"NL",
    "sg:address":"Voorstraat 141",
    "sg:city":"Egmond Aan Zee",
    "sg:orig_category":"Verlichting And Huishoudartikelen",
    "sg:phone":"+31 72 506 1473",
    "sg:postcode":"1931 AK",
    "sg:province":"Noord-Holland",
    "wof:name":"Vof Dekker En Dekker",
    "wof:placetype":"venue"
},
  "geometry": {"coordinates":[4.622051,52.61755],"type":"Point"}
}