{
  "type": "Feature",
  "properties": {
    "addr:full":"Venrayseweg 100 Venlo Limburg 5928 RH",
    "addr:housenumber":"100",
    "addr:postcode":"5928 rh",
    "addr:street":"Venrayseweg",
    "iso:country":"NL",
    "sg:address":"Venrayseweg 100",
    "sg:city":"Venlo",
    "sg:classifiers":[
        {
            "category":"Retail",
            "subcategory":"Storage",
            "type":"Services"
        }
    ],
    "sg:phone":"+31 77 389 7330",
    "sg:postcode":"5928 RH",
    "sg:province":"Limburg",
    "sg:tags":[
        "opslag",
        "bewaring"
    ],
    "wof:name":"Laadgoed Bv",
    "wof:placetype":"venue"
},
  "geometry": {"coordinates":[6.1327447891,51.402179718],"type":"Point"}
}