{
  "type": "Feature",
  "properties": {
    "addr:full":"Graanmolen 18 Maastricht Limburg 6229 PA",
    "addr:housenumber":"18",
    "addr:postcode":"6229 pa",
    "addr:street":"Graanmolen",
    "iso:country":"NL",
    "sg:address":"Graanmolen 18",
    "sg:city":"Maastricht",
    "sg:orig_category":"Drukkerijen",
    "sg:phone":"+31 43 367 0900",
    "sg:postcode":"6229 PA",
    "sg:province":"Limburg",
    "wof:name":"Plantijncasparie Maastricht",
    "wof:placetype":"venue"
},
  "geometry": {"coordinates":[5.713661,50.830196],"type":"Point"}
}