{
  "type": "Feature",
  "properties": {
    "addr:full":"Oranjeln 150 Rynsburg South Holland 2231 ZH",
    "addr:housenumber":"150",
    "addr:postcode":"2231 zh",
    "addr:street":"Rynsburg South",
    "iso:country":"NL",
    "sg:address":"Oranjeln 150",
    "sg:city":"Rynsburg",
    "sg:orig_category":"Bloemen En Planten - Groothandel",
    "sg:phone":"+31 71 402 0513",
    "sg:postcode":"2231 ZH",
    "sg:province":"South Holland",
    "wof:name":"Meij, J J Van Der",
    "wof:placetype":"venue"
},
  "geometry": {"coordinates":[4.442385,52.185966],"type":"Point"}
}