{
  "type": "Feature",
  "properties": {
    "addr:full":"Chagallpassage 11 Emmen Provincie Drenthe 7811 DG",
    "addr:housenumber":"11",
    "addr:postcode":"7811 dg",
    "addr:street":"Chagallpassage;Provincie Drenthe",
    "iso:country":"NL",
    "sg:address":"Chagallpassage 11",
    "sg:city":"Emmen",
    "sg:orig_category":"Fotolaboratoria",
    "sg:phone":"+31 591 648 997",
    "sg:postcode":"7811 DG",
    "sg:province":"Provincie Drenthe",
    "wof:name":"Super Photo Snelservice",
    "wof:placetype":"venue"
},
  "geometry": {"coordinates":[6.893585,52.78447],"type":"Point"}
}