{
  "type": "Feature",
  "properties": {
    "addr:full":"Waemelslant 169 Westervoort Gelderland 6931 HW",
    "addr:housenumber":"169",
    "addr:postcode":"6931 hw",
    "addr:street":"Waemelslant;Gelderland",
    "iso:country":"NL",
    "sg:address":"Waemelslant 169",
    "sg:city":"Westervoort",
    "sg:orig_category":"Adviesbureaus Bouwkunde",
    "sg:phone":"+31 26 312 1627",
    "sg:postcode":"6931 HW",
    "sg:province":"Gelderland",
    "wof:name":"Halbe",
    "wof:placetype":"venue"
},
  "geometry": {"coordinates":[5.970471,51.953793],"type":"Point"}
}