{
  "type": "Feature",
  "properties": {
    "addr:full":"Sorghvlietwg 10 Zwolle NL.08 8026 RJ",
    "addr:housenumber":"10",
    "addr:postcode":"8026 rj",
    "addr:street":"Sorghvlietwg",
    "iso:country":"NL",
    "sg:address":"Sorghvlietwg 10",
    "sg:city":"Zwolle",
    "sg:orig_category":"Psychotherapeuten",
    "sg:phone":"+31 38 454 8454",
    "sg:postcode":"8026 RJ",
    "sg:province":"NL.08",
    "wof:name":"Sluis, Van Der",
    "wof:placetype":"venue"
},
  "geometry": {"coordinates":[6.15806,52.510273],"type":"Point"}
}