{
  "type": "Feature",
  "properties": {
    "iso:country":"NL",
    "sg:address":"Bosseweg 45",
    "sg:city":"Best",
    "sg:classifiers":[
        {
            "category":"Professional",
            "subcategory":"Accounting & Tax Preparation",
            "type":"Services"
        }
    ],
    "sg:phone":"+31 499 339 777",
    "sg:postcode":"5682 PE",
    "sg:province":"Texas",
    "sg:tags":[
        "accountant"
    ],
    "wof:name":"Abab Accountants",
    "wof:placetype":"venue"
},
  "geometry": {"coordinates":[-101.618134,31.224251],"type":"Point"}
}