{
  "type": "Feature",
  "properties": {
    "addr:full":"Schelluinsestr 36 Gorinchem Zuid-Holland 4203 NM",
    "addr:housenumber":"36",
    "addr:postcode":"4203",
    "addr:street":"Schelluinsestr",
    "iso:country":"NL",
    "sg:address":"Schelluinsestr 36",
    "sg:city":"Gorinchem",
    "sg:orig_category":"Oldtimers",
    "sg:phone":"+31 183 666 621",
    "sg:postcode":"4203 NM",
    "sg:province":"Zuid-Holland",
    "wof:name":"Jag Parts & Cars",
    "wof:placetype":"venue"
},
  "geometry": {"coordinates":[4.955511,51.832386],"type":"Point"}
}