{
  "type": "Feature",
  "properties": {
    "addr:full":"Hoofdstr 55B Westerbork Drenthe 9431 AC",
    "addr:housenumber":"55b",
    "addr:postcode":"9431 ac",
    "addr:street":"Hoofdstr",
    "iso:country":"NL",
    "sg:address":"Hoofdstr 55B",
    "sg:city":"Westerbork",
    "sg:orig_category":"Fitnesscentra",
    "sg:phone":"+31 593 552 895",
    "sg:postcode":"9431 AC",
    "sg:province":"Drenthe",
    "wof:name":"Queno",
    "wof:placetype":"venue"
},
  "geometry": {"coordinates":[6.614947,52.84901],"type":"Point"}
}