{
  "type": "Feature",
  "properties": {
    "addr:full":"Burgemeester Selhorststr 9 Gorredijk Provincie Friesland 8401 NZ",
    "addr:housenumber":"9",
    "addr:postcode":"8401 nz",
    "addr:street":"Burgemeester Selhorststr;Provincie Friesland",
    "iso:country":"NL",
    "sg:address":"Burgemeester Selhorststr 9",
    "sg:city":"Gorredijk",
    "sg:orig_category":"Bedrijfsinventaris Gh",
    "sg:phone":"+31 513 463 013",
    "sg:postcode":"8401 NZ",
    "sg:province":"Provincie Friesland",
    "wof:name":"Overwijk Koffiesystemen",
    "wof:placetype":"venue"
},
  "geometry": {"coordinates":[6.069767,53.011429],"type":"Point"}
}