{
  "type": "Feature",
  "properties": {
    "addr:full":"Middenwaard 85 Heerhugowaard North Holland 1703 SC",
    "addr:housenumber":"85",
    "addr:postcode":"1703 sc",
    "addr:street":"Middenwaard",
    "iso:country":"NL",
    "sg:address":"Middenwaard 85",
    "sg:city":"Heerhugowaard",
    "sg:orig_category":"Boekenuitgeverijen",
    "sg:phone":"+31 72 572 5889",
    "sg:postcode":"1703 SC",
    "sg:province":"North Holland",
    "wof:name":"Boekenvoordeel Bv",
    "wof:placetype":"venue"
},
  "geometry": {"coordinates":[4.830968,52.661926],"type":"Point"}
}