{
  "type": "Feature",
  "properties": {
    "addr:full":"Secretaris Verhoeffweg 17 Naaldwijk South Holland 2671 HT",
    "addr:housenumber":"17",
    "addr:postcode":"2671 ht",
    "addr:street":"Secretaris Verhoeffweg",
    "iso:country":"NL",
    "sg:address":"Secretaris Verhoeffweg 17",
    "sg:city":"Naaldwijk",
    "sg:orig_category":"Verlichting And Huishoudartikelen",
    "sg:phone":"+31 174 624 747",
    "sg:postcode":"2671 HT",
    "sg:province":"South Holland",
    "wof:name":"Vof Garretsen Interieur",
    "wof:placetype":"venue"
},
  "geometry": {"coordinates":[4.20406,51.991581],"type":"Point"}
}