{
  "type": "Feature",
  "properties": {
    "addr:full":"Weteringschans 26 Amsterdam Noord-Holland 1017 SG",
    "addr:housenumber":"26",
    "addr:postcode":"1017 sg",
    "addr:street":"Weteringschans",
    "iso:country":"NL",
    "sg:address":"Weteringschans 26",
    "sg:city":"Amsterdam",
    "sg:classifiers":[
        {
            "category":"Building & Trades",
            "subcategory":"Electrical",
            "type":"Services"
        }
    ],
    "sg:phone":"+31 20 428 6556",
    "sg:postcode":"1017 SG",
    "sg:province":"Noord-Holland",
    "sg:tags":[
        "distributor"
    ],
    "wof:name":"Tcw",
    "wof:placetype":"venue"
},
  "geometry": {"coordinates":[4.886951,52.360851],"type":"Point"}
}