{
  "type": "Feature",
  "properties": {
    "addr:full":"Wagnerstr 18 Almere NL. 1323 CM",
    "addr:housenumber":"18",
    "addr:postcode":"1323 cm",
    "addr:street":"Wagnerstr;Nl.",
    "iso:country":"NL",
    "sg:address":"Wagnerstr 18",
    "sg:city":"Almere",
    "sg:orig_category":"Zonweringen",
    "sg:phone":"+31 36 536 2695",
    "sg:postcode":"1323 CM",
    "sg:province":"NL.",
    "wof:name":"Pege",
    "wof:placetype":"venue"
},
  "geometry": {"coordinates":[5.198646,52.364223],"type":"Point"}
}