{
  "type": "Feature",
  "properties": {
    "addr:full":"Ambachtsgaarde 40 S Gravenhage South Holland 2542 EG",
    "addr:housenumber":"40",
    "addr:postcode":"2542 eg",
    "addr:street":"Ambachtsgaarde;S Gravenhage",
    "iso:country":"NL",
    "sg:address":"Ambachtsgaarde 40",
    "sg:city":"S Gravenhage",
    "sg:classifiers":[
        {
            "category":"Food & Beverages",
            "subcategory":"Bakery",
            "type":"Retail Goods"
        }
    ],
    "sg:phone":"+31 70 366 3585",
    "sg:postcode":"2542 EG",
    "sg:province":"South Holland",
    "sg:tags":[
        "pizza"
    ],
    "wof:name":"Sorrento",
    "wof:placetype":"venue"
},
  "geometry": {"coordinates":[4.27035,52.03577],"type":"Point"}
}