{
  "type": "Feature",
  "properties": {
    "addr:full":"Berkenrodestraat 8 Haarlem Noord-Holland 2012 LB",
    "addr:housenumber":"8",
    "addr:postcode":"2012 lb",
    "addr:street":"Berkenrodestraat",
    "iso:country":"NL",
    "sg:address":"Berkenrodestraat 8",
    "sg:city":"Haarlem",
    "sg:orig_category":"Werving And Selectie Van Vast Personeel",
    "sg:phone":"+31 23 551 2508",
    "sg:postcode":"2012 LB",
    "sg:province":"Noord-Holland",
    "wof:name":"Search & Find",
    "wof:placetype":"venue"
},
  "geometry": {"coordinates":[4.6189389229,52.3705253601],"type":"Point"}
}