{
  "type": "Feature",
  "properties": {
    "addr:full":"Valreep 94 Groningen Groningen 9732 EK",
    "addr:housenumber":"94",
    "addr:postcode":"9732 ek",
    "addr:street":"Valreep",
    "iso:country":"NL",
    "sg:address":"Valreep 94",
    "sg:city":"Groningen",
    "sg:orig_category":"Vertaalbureaus",
    "sg:phone":"+31 50 541 6935",
    "sg:postcode":"9732 EK",
    "sg:province":"Groningen",
    "wof:name":"Logendran, K",
    "wof:placetype":"venue"
},
  "geometry": {"coordinates":[6.622437,53.235867],"type":"Point"}
}