{
  "type": "Feature",
  "properties": {
    "addr:full":"Twekkeler-Es 24 Enschede Overijssel 7547 SM",
    "addr:housenumber":"24",
    "addr:postcode":"7547 sm",
    "addr:street":"Twekkeler-Es",
    "iso:country":"NL",
    "sg:address":"Twekkeler-Es 24",
    "sg:city":"Enschede",
    "sg:orig_category":"Hypotheken",
    "sg:phone":"+31 53 484 4844",
    "sg:postcode":"7547 SM",
    "sg:province":"Overijssel",
    "sg:website":"http://www.gelink.nl",
    "wof:name":"Gelink Adviesgroep",
    "wof:placetype":"venue"
},
  "geometry": {"coordinates":[6.840079,52.219696],"type":"Point"}
}