{
  "type": "Feature",
  "properties": {
    "addr:full":"Entrepotstr 3 Rotterdam Zuid-Holland 3071 JA",
    "addr:housenumber":"3",
    "addr:postcode":"3071 ja",
    "addr:street":"Entrepotstr",
    "iso:country":"NL",
    "sg:address":"Entrepotstr 3",
    "sg:city":"Rotterdam",
    "sg:orig_category":"Logopedisten",
    "sg:phone":"+31 10 485 4338",
    "sg:postcode":"3071 JA",
    "sg:province":"Zuid-Holland",
    "wof:name":"Feijenoord Noordereiland",
    "wof:placetype":"venue"
},
  "geometry": {"coordinates":[4.500315,51.911385],"type":"Point"}
}