{
  "type": "Feature",
  "properties": {
    "addr:full":"Strengholtstraat 4 Ijmuiden North Holland 1971 EC",
    "addr:housenumber":"4",
    "addr:postcode":"1971 ec",
    "addr:street":"Strengholtstraat",
    "iso:country":"NL",
    "sg:address":"Strengholtstraat 4",
    "sg:city":"Ijmuiden",
    "sg:orig_category":"Fotostudio'S And Fotografen",
    "sg:phone":"+31 255 510 494",
    "sg:postcode":"1971 EC",
    "sg:province":"North Holland",
    "wof:name":"Foto Studio Ton Anderson",
    "wof:placetype":"venue"
},
  "geometry": {"coordinates":[4.623459,52.460632],"type":"Point"}
}