{
  "type": "Feature",
  "properties": {
    "addr:full":"Kwadk 130 Kwadyk Noord-Holland 1471 CH",
    "addr:housenumber":"130;1471",
    "addr:street":"Kwadyk Noord-Holland",
    "iso:country":"NL",
    "sg:address":"Kwadk 130",
    "sg:city":"Kwadyk",
    "sg:orig_category":"Hoefsmederijen",
    "sg:phone":"+31 299 621 203",
    "sg:postcode":"1471 CH",
    "sg:province":"Noord-Holland",
    "wof:name":"Huiberts, J",
    "wof:placetype":"venue"
},
  "geometry": {"coordinates":[4.987739,52.525387],"type":"Point"}
}