{
  "type": "Feature",
  "properties": {
    "addr:full":"Dennenbroek 43 Breda Noord-Brabant 4822 XC",
    "addr:housenumber":"43",
    "addr:postcode":"4822 xc",
    "addr:street":"Dennenbroek",
    "iso:country":"NL",
    "sg:address":"Dennenbroek 43",
    "sg:city":"Breda",
    "sg:orig_category":"Glaszetten",
    "sg:phone":"+31 76 541 8164",
    "sg:postcode":"4822 XC",
    "sg:province":"Noord-Brabant",
    "wof:name":"Hedisa",
    "wof:placetype":"venue"
},
  "geometry": {"coordinates":[4.729372,51.606861],"type":"Point"}
}