{
  "type": "Feature",
  "properties": {
    "addr:full":"Oude Verlaat 9 Blokzijl Overijssel 8356 DJ",
    "addr:housenumber":"9",
    "addr:postcode":"8356 dj",
    "addr:street":"Oude Verlaat",
    "iso:country":"NL",
    "sg:address":"Oude Verlaat 9",
    "sg:city":"Blokzijl",
    "sg:orig_category":"Schilders",
    "sg:phone":"+31 527 291 378",
    "sg:postcode":"8356 DJ",
    "sg:province":"Overijssel",
    "wof:name":"Bergkamp, K",
    "wof:placetype":"venue"
},
  "geometry": {"coordinates":[5.96031,52.727577],"type":"Point"}
}