{
  "type": "Feature",
  "properties": {
    "addr:full":"Drentsestr 14 Amersfoort Utrecht 3812 EH",
    "addr:housenumber":"14",
    "addr:postcode":"3812 eh",
    "addr:street":"Drentsestr",
    "iso:country":"NL",
    "sg:address":"Drentsestr 14",
    "sg:city":"Amersfoort",
    "sg:orig_category":"Kinderopvang",
    "sg:phone":"+31 33 477 9171",
    "sg:postcode":"3812 EH",
    "sg:province":"Utrecht",
    "sg:website":"http://www.welzijnamersfoort.nl",
    "wof:name":"Welzijn Amersfoort Stichting",
    "wof:placetype":"venue"
},
  "geometry": {"coordinates":[5.37558,52.159901],"type":"Point"}
}