{
  "type": "Feature",
  "properties": {
    "addr:full":"Koningstraat 48 Raamsdonksveer Noord-Brabant 4941 GX",
    "addr:housenumber":"48",
    "addr:postcode":"4941 gx",
    "addr:street":"Koningstraat",
    "iso:country":"NL",
    "sg:address":"Koningstraat 48",
    "sg:city":"Raamsdonksveer",
    "sg:orig_category":"Fotostudio'S And Fotografen",
    "sg:phone":"+31 162 570 362",
    "sg:postcode":"4941 GX",
    "sg:province":"Noord-Brabant",
    "wof:name":"Dongkei Fotografie",
    "wof:placetype":"venue"
},
  "geometry": {"coordinates":[4.872136,51.692314],"type":"Point"}
}