{
  "type": "Feature",
  "properties": {
    "addr:full":"Vijzelstr 70 Amsterdam Noord-Holland 1017 HL",
    "addr:housenumber":"70",
    "addr:postcode":"1017 hl",
    "addr:street":"Vijzelstr",
    "iso:country":"NL",
    "sg:address":"Vijzelstr 70",
    "sg:city":"Amsterdam",
    "sg:orig_category":"Drukkerijen",
    "sg:phone":"+31 20 625 4604",
    "sg:postcode":"1017 HL",
    "sg:province":"Noord-Holland",
    "wof:name":"Printerette Bv",
    "wof:placetype":"venue"
},
  "geometry": {"coordinates":[4.891883,52.363152],"type":"Point"}
}