{
  "type": "Feature",
  "properties": {
    "addr:full":"Het Wolbert 23 Enschede Overijssel 7547 RA",
    "addr:housenumber":"23",
    "addr:postcode":"7547 ra",
    "addr:street":"Het Wolbert",
    "iso:country":"NL",
    "sg:address":"Het Wolbert 23",
    "sg:city":"Enschede",
    "sg:orig_category":"Verf En Lak - Fabrieken En Groothandel",
    "sg:phone":"+31 53 431 2822",
    "sg:postcode":"7547 RA",
    "sg:province":"Overijssel",
    "wof:name":"Quartier",
    "wof:placetype":"venue"
},
  "geometry": {"coordinates":[6.846396,52.221386],"type":"Point"}
}