{
  "type": "Feature",
  "properties": {
    "iso:country":"NL",
    "sg:address":"Langeweg 13",
    "sg:city":"Aardenburg",
    "sg:orig_category":"Fruit And Groenten Gh",
    "sg:phone":"+31 117 491 479",
    "sg:postcode":"4527 PN",
    "sg:province":"Zeeland",
    "wof:name":"R.A. V.D. Vijver",
    "wof:placetype":"venue"
},
  "geometry": {"coordinates":[3.464273,51.295422],"type":"Point"}
}