{
  "type": "Feature",
  "properties": {
    "addr:full":"Postbus 229 Aalten Gelderland 7120 AE",
    "addr:housenumber":"229",
    "addr:postcode":"7120 ae",
    "addr:street":"Postbus;Gelderland",
    "iso:country":"NL",
    "sg:address":"Postbus 229",
    "sg:city":"Aalten",
    "sg:orig_category":"Video - Faciliteiten En Producties",
    "sg:phone":"+31 543 475 881",
    "sg:postcode":"7120 AE",
    "sg:province":"Gelderland",
    "wof:name":"Mebel Tv & Videoproducties, Te",
    "wof:placetype":"venue"
},
  "geometry": {"coordinates":[6.581215,51.915882],"type":"Point"}
}