{
  "type": "Feature",
  "properties": {
    "addr:full":"Katwijkerbroek 19 Katwijk Zh South Holland 2223 XN",
    "addr:housenumber":"19",
    "addr:postcode":"zh;2223 xn",
    "addr:street":"Katwijkerbroek",
    "iso:country":"NL",
    "sg:address":"Katwijkerbroek 19",
    "sg:city":"Katwijk Zh",
    "sg:orig_category":"Kantoorartikelen",
    "sg:phone":"+31 71 407 8494",
    "sg:postcode":"2223 XN",
    "sg:province":"South Holland",
    "wof:name":"Uniepapier Randstad Bv",
    "wof:placetype":"venue"
},
  "geometry": {"coordinates":[4.4248709679,52.1852455139],"type":"Point"}
}