{
  "type": "Feature",
  "properties": {
    "iso:country":"NL",
    "sg:address":"Liede 31",
    "sg:city":"Heerhugowaard",
    "sg:orig_category":"Geluidsopnamen",
    "sg:phone":"+31 72 503 9639",
    "sg:postcode":"1703 NW",
    "sg:province":"Noord-Holland",
    "wof:name":"Oterleek Recording",
    "wof:placetype":"venue"
},
  "geometry": {"coordinates":[4.827685,52.65406],"type":"Point"}
}