{
  "type": "Feature",
  "properties": {
    "addr:full":"Irisln 28 Heemstede Noord-Holland 2106 BG",
    "addr:housenumber":"28",
    "addr:postcode":"2106",
    "addr:street":"Irisln",
    "iso:country":"NL",
    "sg:address":"Irisln 28",
    "sg:city":"Heemstede",
    "sg:orig_category":"Adviesbureaus Bedrijfsorganisatie",
    "sg:phone":"+31 6 25027527",
    "sg:postcode":"2106 BG",
    "sg:province":"Noord-Holland",
    "wof:name":"Marijnen",
    "wof:placetype":"venue"
},
  "geometry": {"coordinates":[4.621248,52.345287],"type":"Point"}
}