{
  "type": "Feature",
  "properties": {
    "iso:country":"NL",
    "sg:address":"Spoelln 40",
    "sg:city":"Heemskerk",
    "sg:orig_category":"Arbo- En Bedrijfsgezondheids- Diensten",
    "sg:phone":"+31 251 236 823",
    "sg:postcode":"1964 TC",
    "sg:province":"Noord-Holland",
    "wof:name":"Goed, De",
    "wof:placetype":"venue"
},
  "geometry": {"coordinates":[4.66983,52.513546],"type":"Point"}
}