{
  "type": "Feature",
  "properties": {
    "iso:country":"NL",
    "sg:address":"Rapenburg 29",
    "sg:city":"Neede",
    "sg:orig_category":"Onroerende Goederen",
    "sg:phone":"+31 545 295 025",
    "sg:postcode":"7161 EB",
    "sg:province":"California",
    "wof:name":"Jab? Bv",
    "wof:placetype":"venue"
},
  "geometry": {"coordinates":[-121.31706200000001,38.299633],"type":"Point"}
}