{
  "type": "Feature",
  "properties": {
    "addr:full":"Gaffelaar 6 Franeker Friesland 8802 NS",
    "addr:housenumber":"6",
    "addr:postcode":"8802 ns",
    "addr:street":"Gaffelaar",
    "iso:country":"NL",
    "sg:address":"Gaffelaar 6",
    "sg:city":"Franeker",
    "sg:orig_category":"Administratie- En Boekhoudkantoren",
    "sg:phone":"+31 517 391 141",
    "sg:postcode":"8802 NS",
    "sg:province":"Friesland",
    "wof:name":"Friesland Accounts",
    "wof:placetype":"venue"
},
  "geometry": {"coordinates":[5.548733,53.197514],"type":"Point"}
}