{
  "type": "Feature",
  "properties": {
    "iso:country":"NL",
    "sg:address":"Bierstr 12",
    "sg:city":"Rotterdam",
    "sg:orig_category":"Kunsthandel",
    "sg:phone":"+31 10 433 1509",
    "sg:postcode":"3011 XA",
    "sg:province":"Zuid-Holland",
    "wof:name":"Masterpaintings Vof",
    "wof:placetype":"venue"
},
  "geometry": {"coordinates":[4.487788,51.916714],"type":"Point"}
}