{
  "type": "Feature",
  "properties": {
    "addr:full":"J Banckertstr 21 Huizen North Holland 1272 BE",
    "addr:housenumber":"21",
    "addr:postcode":"1272",
    "iso:country":"NL",
    "sg:address":"J Banckertstr 21",
    "sg:city":"Huizen",
    "sg:orig_category":"Parketvloeren - Onderhoud En Reparatie",
    "sg:phone":"+31 6 54202736",
    "sg:postcode":"1272 BE",
    "sg:province":"North Holland",
    "wof:name":"Timo Scheffer Parket Service",
    "wof:placetype":"venue"
},
  "geometry": {"coordinates":[5.225106,52.298187],"type":"Point"}
}