{
  "type": "Feature",
  "properties": {
    "addr:full":"Ambachtstraat 10 Laren Nh Noord-Holland 1251 PZ",
    "addr:housenumber":"10",
    "addr:postcode":"1251 pz",
    "addr:street":"Ambachtstraat",
    "iso:country":"NL",
    "sg:address":"Ambachtstraat 10",
    "sg:city":"Laren Nh",
    "sg:orig_category":"Fotostudio'S And Fotografen",
    "sg:phone":"+31 35 531 4990",
    "sg:postcode":"1251 PZ",
    "sg:province":"Noord-Holland",
    "wof:name":"Cyriel Cremers Bv",
    "wof:placetype":"venue"
},
  "geometry": {"coordinates":[5.226468,52.253689],"type":"Point"}
}