{
  "type": "Feature",
  "properties": {
    "addr:full":"Griffioenlaan 2 Grijpskerk Groningen 9843 BL",
    "addr:housenumber":"2",
    "addr:postcode":"9843 bl",
    "addr:street":"Griffioenlaan",
    "iso:country":"NL",
    "sg:address":"Griffioenlaan 2",
    "sg:city":"Grijpskerk",
    "sg:orig_category":"Vertaal- And Tolkenbureaus",
    "sg:phone":"+31 594 213 546",
    "sg:postcode":"9843 BL",
    "sg:province":"Groningen",
    "wof:name":"Drs M J Bosma",
    "wof:placetype":"venue"
},
  "geometry": {"coordinates":[6.309138,53.2603],"type":"Point"}
}