{
  "type": "Feature",
  "properties": {
    "addr:full":"Nw Wal 10 Middelburg Zeeland 4331 AX",
    "addr:housenumber":"10",
    "addr:postcode":"4331 ax",
    "addr:street":"Nw Wal",
    "iso:country":"NL",
    "sg:address":"Nw Wal 10",
    "sg:city":"Middelburg",
    "sg:orig_category":"Wereldwinkels",
    "sg:phone":"+31 118 643 525",
    "sg:postcode":"4331 AX",
    "sg:province":"Zeeland",
    "wof:name":"Wereldwinkel Middelburg",
    "wof:placetype":"venue"
},
  "geometry": {"coordinates":[3.6150660515,51.4990463257],"type":"Point"}
}