{
  "type": "Feature",
  "properties": {
    "addr:full":"Spoorstraat 11 Didam Gelderland 6942 EA",
    "addr:housenumber":"11",
    "addr:postcode":"6942 ea",
    "addr:street":"Spoorstraat;Gelderland",
    "iso:country":"NL",
    "sg:address":"Spoorstraat 11",
    "sg:city":"Didam",
    "sg:orig_category":"Herenmodezaken",
    "sg:phone":"+31 316 294 240",
    "sg:postcode":"6942 EA",
    "sg:province":"Gelderland",
    "wof:name":"Gilsing Herenmode Bv",
    "wof:placetype":"venue"
},
  "geometry": {"coordinates":[6.130245,51.935177],"type":"Point"}
}