{
  "type": "Feature",
  "properties": {
    "addr:full":"Dorpsstr 86 Amstelveen Noord-Holland 1182 JG",
    "addr:housenumber":"86",
    "addr:postcode":"1182 jg",
    "addr:street":"Dorpsstr",
    "iso:country":"NL",
    "sg:address":"Dorpsstr 86",
    "sg:city":"Amstelveen",
    "sg:orig_category":"Makelaars En Adviseurs Onroerende Goederen",
    "sg:phone":"+31 20 453 8970",
    "sg:postcode":"1182 JG",
    "sg:province":"Noord-Holland",
    "sg:website":"http://www.koophuis.nl",
    "wof:name":"Koophuis Amstelveen",
    "wof:placetype":"venue"
},
  "geometry": {"coordinates":[4.846563,52.302101],"type":"Point"}
}