{
  "type": "Feature",
  "properties": {
    "addr:full":"Espelerwg 21 Emmeloord Flevoland 8303 HW",
    "addr:housenumber":"21",
    "addr:postcode":"8303 hw",
    "addr:street":"Espelerwg;Flevoland",
    "iso:country":"NL",
    "sg:address":"Espelerwg 21",
    "sg:city":"Emmeloord",
    "sg:classifiers":[
        {
            "category":"Personal",
            "subcategory":"Nail Salon",
            "type":"Services"
        }
    ],
    "sg:phone":"+31 527 612 510",
    "sg:postcode":"8303 HW",
    "sg:province":"Flevoland",
    "sg:tags":[
        "pedicure"
    ],
    "wof:name":"Duursema-Wijk, A M",
    "wof:placetype":"venue"
},
  "geometry": {"coordinates":[5.702337,52.724033],"type":"Point"}
}