{
  "type": "Feature",
  "properties": {
    "addr:full":"Westwaarts 53 Zoetermeer South Holland 2711 AD",
    "addr:housenumber":"53",
    "addr:postcode":"2711 ad",
    "addr:street":"Westwaarts",
    "iso:country":"NL",
    "sg:address":"Westwaarts 53",
    "sg:city":"Zoetermeer",
    "sg:orig_category":"Kappers",
    "sg:phone":"+31 79 352 3456",
    "sg:postcode":"2711 AD",
    "sg:province":"South Holland",
    "wof:name":"Mario'S Hairsaloon",
    "wof:placetype":"venue"
},
  "geometry": {"coordinates":[4.485684,52.060856],"type":"Point"}
}