{
  "type": "Feature",
  "properties": {
    "addr:full":"Arnhemsestrwg 2 Velp Gld Gelderland 6881 NG",
    "addr:housenumber":"2",
    "addr:postcode":"6881 ng",
    "addr:street":"Arnhemsestrwg;Gld Gelderland",
    "iso:country":"NL",
    "sg:address":"Arnhemsestrwg 2",
    "sg:city":"Velp Gld",
    "sg:orig_category":"Keukens",
    "sg:phone":"+31 26 361 1341",
    "sg:postcode":"6881 NG",
    "sg:province":"Gelderland",
    "sg:website":"http://www.hans-verkerk.nl",
    "wof:name":"Hans Verkerk",
    "wof:placetype":"venue"
},
  "geometry": {"coordinates":[5.974033,51.996021],"type":"Point"}
}