{
  "type": "Feature",
  "properties": {
    "addr:full":"Zuiderln 134 Meppel Drenthe 7944 EJ",
    "addr:housenumber":"134",
    "addr:postcode":"7944 ej",
    "iso:country":"NL",
    "sg:address":"Zuiderln 134",
    "sg:city":"Meppel",
    "sg:orig_category":"Bejaarden - Verzorgingstehuizen",
    "sg:phone":"+31 522 255 444",
    "sg:postcode":"7944 EJ",
    "sg:province":"Drenthe",
    "wof:name":"Reestoord",
    "wof:placetype":"venue"
},
  "geometry": {"coordinates":[6.196295,52.699615],"type":"Point"}
}