{
  "type": "Feature",
  "properties": {
    "addr:full":"Handelsstr 6 Heerhugowaard Noord-Holland 1704 AB",
    "addr:housenumber":"6",
    "addr:postcode":"1704 ab",
    "addr:street":"Handelsstr",
    "iso:country":"NL",
    "sg:address":"Handelsstr 6",
    "sg:city":"Heerhugowaard",
    "sg:orig_category":"Drukkerijen",
    "sg:phone":"+31 72 571 8388",
    "sg:postcode":"1704 AB",
    "sg:province":"Noord-Holland",
    "sg:website":"http://www.artprint.nl",
    "wof:name":"Artprint",
    "wof:placetype":"venue"
},
  "geometry": {"coordinates":[4.82161,52.669834],"type":"Point"}
}