{
  "type": "Feature",
  "properties": {
    "addr:full":"Van Harenstraat 4 Wolvega Friesland 8471 JD",
    "addr:housenumber":"4",
    "addr:postcode":"8471 jd",
    "addr:street":"Van Harenstraat",
    "iso:country":"NL",
    "sg:address":"Van Harenstraat 4",
    "sg:city":"Wolvega",
    "sg:orig_category":"Drogisterijen",
    "sg:phone":"+31 561 617 531",
    "sg:postcode":"8471 JD",
    "sg:province":"Friesland",
    "wof:name":"Kruidvat",
    "wof:placetype":"venue"
},
  "geometry": {"coordinates":[6.001499,52.876488],"type":"Point"}
}