{
  "type": "Feature",
  "properties": {
    "addr:full":"Vordensebinnenwg 42 Warnsveld Gelderland 7231 BD",
    "addr:housenumber":"42",
    "addr:postcode":"7231 bd",
    "addr:street":"Vordensebinnenwg;Gelderland",
    "iso:country":"NL",
    "sg:address":"Vordensebinnenwg 42",
    "sg:city":"Warnsveld",
    "sg:orig_category":"Adviesbureaus Verzekeringen",
    "sg:phone":"+31 575 570 511",
    "sg:postcode":"7231 BD",
    "sg:province":"Gelderland",
    "wof:name":"Eku",
    "wof:placetype":"venue"
},
  "geometry": {"coordinates":[6.225585,52.140984],"type":"Point"}
}