{
  "type": "Feature",
  "properties": {
    "addr:full":"Postbus 38 Drunen North Brabant 5150 AA",
    "addr:housenumber":"38",
    "addr:postcode":"5150 aa",
    "addr:street":"Postbus",
    "iso:country":"NL",
    "sg:address":"Postbus 38",
    "sg:city":"Drunen",
    "sg:orig_category":"Verzekeringen - Verzekeringskantoren",
    "sg:phone":"+31 416 382 385",
    "sg:postcode":"5150 AA",
    "sg:province":"North Brabant",
    "sg:website":"http://www.paijmans.nl",
    "wof:name":"Paijmans",
    "wof:placetype":"venue"
},
  "geometry": {"coordinates":[5.13039,51.686031],"type":"Point"}
}