{
  "type": "Feature",
  "properties": {
    "addr:full":"Annastr 13A Geleen Limburg 6161 GV",
    "addr:housenumber":"13a",
    "addr:postcode":"6161 gv",
    "addr:street":"Annastr",
    "iso:country":"NL",
    "sg:address":"Annastr 13A",
    "sg:city":"Geleen",
    "sg:orig_category":"Wereldwinkels",
    "sg:phone":"+31 46 474 7027",
    "sg:postcode":"6161 GV",
    "sg:province":"Limburg",
    "wof:name":"Wereldwinkel, De",
    "wof:placetype":"venue"
},
  "geometry": {"coordinates":[5.8266592026,50.9710769653],"type":"Point"}
}