{
  "type": "Feature",
  "properties": {
    "iso:country":"NL",
    "sg:address":"Burgemeester Letteweg 12",
    "sg:city":"Oostvoorne",
    "sg:orig_category":"Meubelzaken, Woning- And Keukeninrichting",
    "sg:phone":"+31 181 485 134",
    "sg:postcode":"3233 AG",
    "sg:province":"South Holland",
    "wof:name":"Balustrade",
    "wof:placetype":"venue"
},
  "geometry": {"coordinates":[4.103023,51.914452],"type":"Point"}
}