{
  "type": "Feature",
  "properties": {
    "addr:full":"Hazelaar 20 Naaldwyk Zuid-Holland 2671 PE",
    "addr:housenumber":"20",
    "addr:postcode":"2671 pe",
    "addr:street":"Hazelaar",
    "iso:country":"NL",
    "sg:address":"Hazelaar 20",
    "sg:city":"Naaldwyk",
    "sg:orig_category":"Afslankinstituten",
    "sg:phone":"+31 174 631 667",
    "sg:postcode":"2671 PE",
    "sg:province":"Zuid-Holland",
    "wof:name":"Dam, Arie & Monic V",
    "wof:placetype":"venue"
},
  "geometry": {"coordinates":[4.199598,51.993027],"type":"Point"}
}