{
  "type": "Feature",
  "properties": {
    "addr:full":"Oberonwg 12-16 Spykenisse Zuid-Holland 3208 PE",
    "addr:housenumber":"12-16",
    "addr:postcode":"3208 pe",
    "addr:street":"Oberonwg",
    "iso:country":"NL",
    "sg:address":"Oberonwg 12-16",
    "sg:city":"Spykenisse",
    "sg:orig_category":"Automaterialen En Gereedschappen",
    "sg:phone":"+31 181 637 211",
    "sg:postcode":"3208 PE",
    "sg:province":"Zuid-Holland",
    "wof:name":"Cruuswaert Bv Autocenter/Automaterialen",
    "wof:placetype":"venue"
},
  "geometry": {"coordinates":[4.318457,51.836414],"type":"Point"}
}