{
  "type": "Feature",
  "properties": {
    "addr:full":"Hollandiahof 49 Schiedam South Holland 3119 ZD",
    "addr:housenumber":"49",
    "addr:postcode":"3119 zd",
    "addr:street":"Hollandiahof",
    "iso:country":"NL",
    "sg:address":"Hollandiahof 49",
    "sg:city":"Schiedam",
    "sg:orig_category":"Bloemen En Planten",
    "sg:phone":"+31 6 18407603",
    "sg:postcode":"3119 ZD",
    "sg:province":"South Holland",
    "sg:website":"http://www.bloomunlimited.nl",
    "wof:name":"Bloom Unltd",
    "wof:placetype":"venue"
},
  "geometry": {"coordinates":[4.404115,51.919937],"type":"Point"}
}