{
  "type": "Feature",
  "properties": {
    "addr:full":"Pesserdijk 2 Hoogeveen Provincie Drenthe 7903 TE",
    "addr:housenumber":"2;7903",
    "addr:street":"Pesserdijk;Provincie;Te",
    "iso:country":"NL",
    "sg:address":"Pesserdijk 2",
    "sg:city":"Hoogeveen",
    "sg:orig_category":"Medische Apparatuur And Prothesen Fab",
    "sg:phone":"+31 528 274 450",
    "sg:postcode":"7903 TE",
    "sg:province":"Provincie Drenthe",
    "wof:name":"Reijs Tandtechniek",
    "wof:placetype":"venue"
},
  "geometry": {"coordinates":[6.494306,52.732578],"type":"Point"}
}