{
  "type": "Feature",
  "properties": {
    "iso:country":"NL",
    "sg:address":"Napoleonswg 4",
    "sg:city":"Haelen",
    "sg:orig_category":"Kappers",
    "sg:phone":"+31 475 594 344",
    "sg:postcode":"6081 AD",
    "sg:province":"Limburg",
    "wof:name":"Brigitte",
    "wof:placetype":"venue"
},
  "geometry": {"coordinates":[5.9185738564,51.2122421265],"type":"Point"}
}