{
  "type": "Feature",
  "properties": {
    "iso:country":"NL",
    "sg:address":"Vergulden Wagen 24",
    "sg:city":"Diemen",
    "sg:orig_category":"Administratie- En Boekhoudkantoren",
    "sg:phone":"+31 20 453 7342",
    "sg:postcode":"1111 TE",
    "sg:province":"Noord-Holland",
    "wof:name":"Adpoc",
    "wof:placetype":"venue"
},
  "geometry": {"coordinates":[4.9714598656,52.3501853943],"type":"Point"}
}