{
  "type": "Feature",
  "properties": {
    "addr:full":"Van De Woestijneheem 81 Hillegom North Holland 2182 WN",
    "addr:housenumber":"81",
    "addr:postcode":"2182 wn",
    "addr:street":"Van De Woestijneheem",
    "iso:country":"NL",
    "sg:address":"Van De Woestijneheem 81",
    "sg:city":"Hillegom",
    "sg:orig_category":"Makelaars In Onroerend Goed",
    "sg:phone":"+31 252 531 057",
    "sg:postcode":"2182 WN",
    "sg:province":"North Holland",
    "wof:name":"Herman Van Kampen",
    "wof:placetype":"venue"
},
  "geometry": {"coordinates":[4.583212,52.281944],"type":"Point"}
}