{
  "type": "Feature",
  "properties": {
    "addr:full":"Pascalstraat 17 Heerhugowaard Noord-Holland 1704 RD",
    "addr:housenumber":"17",
    "addr:postcode":"1704 rd",
    "addr:street":"Pascalstraat",
    "iso:country":"NL",
    "sg:address":"Pascalstraat 17",
    "sg:city":"Heerhugowaard",
    "sg:orig_category":"Autokeuringen",
    "sg:phone":"+31 72 576 2220",
    "sg:postcode":"1704 RD",
    "sg:province":"Noord-Holland",
    "wof:name":"Stam Materieel Bv",
    "wof:placetype":"venue"
},
  "geometry": {"coordinates":[4.829021,52.681465],"type":"Point"}
}