{
  "type": "Feature",
  "properties": {
    "iso:country":"NL",
    "sg:address":"Vergierdeweg 203",
    "sg:city":"Haarlem",
    "sg:orig_category":"Kappers",
    "sg:phone":"+31 23 537 7656",
    "sg:postcode":"2026 ZD",
    "sg:province":"Noord-Holland",
    "wof:name":"Barbershop Hanny",
    "wof:placetype":"venue"
},
  "geometry": {"coordinates":[4.6547818184,52.4181137085],"type":"Point"}
}