{
  "type": "Feature",
  "properties": {
    "addr:full":"Zytak Wz 35 Nieuw Amsterdam Missouri 7833 BB",
    "addr:housenumber":"35",
    "addr:postcode":"7833 bb",
    "addr:street":"Zytak Wz",
    "iso:country":"NL",
    "sg:address":"Zytak Wz 35",
    "sg:city":"Nieuw Amsterdam",
    "sg:orig_category":"Fietsen En Bromfietsen",
    "sg:phone":"+31 591 556 499",
    "sg:postcode":"7833 BB",
    "sg:province":"Missouri",
    "wof:name":"Martin Jeuring",
    "wof:placetype":"venue"
},
  "geometry": {"coordinates":[-94.58503,38.350479],"type":"Point"}
}