{
  "type": "Feature",
  "properties": {
    "iso:country":"NL",
    "sg:address":"Kerkstraat 29",
    "sg:city":"Vianen Zh",
    "sg:orig_category":"Wasserettes And Stomerijen",
    "sg:phone":"+31 347 371 671",
    "sg:postcode":"4132 BD",
    "sg:province":"South Holland",
    "wof:name":"Ideal",
    "wof:placetype":"venue"
},
  "geometry": {"coordinates":[5.0931820869,51.9941635132],"type":"Point"}
}