{
  "type": "Feature",
  "properties": {
    "addr:full":"(Alleen Telefonisch Bereikbaar) Een Noord-Brabant 4825 AT",
    "addr:postcode":"4825",
    "addr:street":"Alleen;Bereikbaar",
    "iso:country":"NL",
    "sg:address":"(Alleen Telefonisch Bereikbaar)",
    "sg:city":"Een",
    "sg:orig_category":"Autokeuringen",
    "sg:phone":"+31 800 0525",
    "sg:postcode":"4825 AT",
    "sg:province":"Noord-Brabant",
    "wof:name":"Novus Autoglasspecialisten",
    "wof:placetype":"venue"
},
  "geometry": {"coordinates":[13.51947,47.553799],"type":"Point"}
}