{
  "type": "Feature",
  "properties": {
    "addr:full":"Midwouder Dorpsstraat 44 Midwoud Noord-Holland 1679 GC",
    "addr:housenumber":"44",
    "addr:postcode":"1679 gc",
    "addr:street":"Midwouder Dorpsstraat",
    "iso:country":"NL",
    "sg:address":"Midwouder Dorpsstraat 44",
    "sg:city":"Midwoud",
    "sg:orig_category":"Autokeuringen",
    "sg:phone":"+31 229 201 856",
    "sg:postcode":"1679 GC",
    "sg:province":"Noord-Holland",
    "wof:name":"Garage Keijzer",
    "wof:placetype":"venue"
},
  "geometry": {"coordinates":[5.063195,52.710625],"type":"Point"}
}