{
  "type": "Feature",
  "properties": {
    "iso:country":"NL",
    "sg:address":"Aldenhofpark 1",
    "sg:city":"Maastricht",
    "sg:orig_category":"Paramedische Behandelingen",
    "sg:phone":"+31 43 325 1850",
    "sg:postcode":"6211 LV",
    "sg:province":"Limburg",
    "wof:name":"J.M. Hofhuizen",
    "wof:placetype":"venue"
},
  "geometry": {"coordinates":[5.682992,50.844765],"type":"Point"}
}