{
  "type": "Feature",
  "properties": {
    "iso:country":"NL",
    "sg:address":"Anjeliersstraat 57-59",
    "sg:city":"Amsterdam",
    "sg:orig_category":"Diverse Grafische Activiteiten",
    "sg:phone":"+31 20 423 5109",
    "sg:postcode":"1012 EM",
    "sg:province":"Noord-Holland",
    "wof:name":"Studio Xpress",
    "wof:placetype":"venue"
},
  "geometry": {"coordinates":[4.884374,52.377834],"type":"Point"}
}