{
  "type": "Feature",
  "properties": {
    "addr:full":"Botersloot 12 Noordeloos South Holland 4225 PP",
    "addr:housenumber":"12",
    "addr:postcode":"4225 pp",
    "addr:street":"Botersloot",
    "iso:country":"NL",
    "sg:address":"Botersloot 12",
    "sg:city":"Noordeloos",
    "sg:orig_category":"Woninginrichting",
    "sg:phone":"+31 183 581 336",
    "sg:postcode":"4225 PP",
    "sg:province":"South Holland",
    "wof:name":"Bos & Zn, Fa",
    "wof:placetype":"venue"
},
  "geometry": {"coordinates":[4.9412550926,51.9033660889],"type":"Point"}
}