{
  "type": "Feature",
  "properties": {
    "iso:country":"NL",
    "sg:address":"Duiventorenstr 19",
    "sg:city":"Naaldwyk",
    "sg:orig_category":"Bedrijfskleding",
    "sg:phone":"+31 174 643 662",
    "sg:postcode":"2671 AH",
    "sg:province":"Zuid-Holland",
    "wof:name":"Xl",
    "wof:placetype":"venue"
},
  "geometry": {"coordinates":[4.20015,51.996307],"type":"Point"}
}