{
  "type": "Feature",
  "properties": {
    "iso:country":"NL",
    "sg:address":"C V Rennesplaats 29",
    "sg:city":"Haarlem",
    "sg:orig_category":"Loopbaanbegeleiding",
    "sg:phone":"+31 23 545 2276",
    "sg:postcode":"2033 NX",
    "sg:province":"Noord-Holland",
    "wof:name":"Lentezon, Bureau",
    "wof:placetype":"venue"
},
  "geometry": {"coordinates":[4.66298,52.37672],"type":"Point"}
}