{
  "type": "Feature",
  "properties": {
    "addr:full":"Lombardstr 2C Harlingen Provincie Friesland 8861 TD",
    "addr:housenumber":"2c",
    "addr:postcode":"8861 td",
    "addr:street":"Lombardstr;Provincie Friesland",
    "iso:country":"NL",
    "sg:address":"Lombardstr 2C",
    "sg:city":"Harlingen",
    "sg:orig_category":"Zeilbotenverhuur",
    "sg:phone":"+31 517 430 177",
    "sg:postcode":"8861 TD",
    "sg:province":"Provincie Friesland",
    "wof:name":"Ouds Bv, Van",
    "wof:placetype":"venue"
},
  "geometry": {"coordinates":[5.423004,53.176147],"type":"Point"}
}