{
  "type": "Feature",
  "properties": {
    "addr:full":"Enterstraat 13 B Rijssen Overijssel 7461 CE",
    "addr:housenumber":"13 b",
    "addr:postcode":"7461 ce",
    "addr:street":"Enterstraat",
    "iso:country":"NL",
    "sg:address":"Enterstraat 13 B",
    "sg:city":"Rijssen",
    "sg:orig_category":"Veilingen",
    "sg:phone":"+31 548 515 750",
    "sg:postcode":"7461 CE",
    "sg:province":"Overijssel",
    "wof:name":"Edelshop",
    "wof:placetype":"venue"
},
  "geometry": {"coordinates":[6.524452,52.308899],"type":"Point"}
}