{
  "type": "Feature",
  "properties": {
    "addr:full":"De Bleek 2 Venray Limburg 5801 MD",
    "addr:housenumber":"2",
    "addr:postcode":"5801",
    "addr:street":"De Bleek",
    "iso:country":"NL",
    "sg:address":"De Bleek 2",
    "sg:city":"Venray",
    "sg:orig_category":"Discountwinkels",
    "sg:phone":"+31 478 583 327",
    "sg:postcode":"5801 MD",
    "sg:province":"Limburg",
    "wof:name":"Supertex Venray Bv",
    "wof:placetype":"venue"
},
  "geometry": {"coordinates":[5.973725,51.526627],"type":"Point"}
}