{
  "type": "Feature",
  "properties": {
    "iso:country":"NL",
    "sg:address":"Vyverln 29",
    "sg:city":"Bodegraven",
    "sg:orig_category":"Logopedisten",
    "sg:phone":"+31 172 651 179",
    "sg:postcode":"2411 AK",
    "sg:province":"Zuid-Holland",
    "wof:name":"Muntjewerff-Stolwijk, M M",
    "wof:placetype":"venue"
},
  "geometry": {"coordinates":[4.747547,52.085552],"type":"Point"}
}