{
  "type": "Feature",
  "properties": {
    "iso:country":"NL",
    "sg:address":"Binnenwg 27",
    "sg:city":"Heemstede",
    "sg:orig_category":"Kaas",
    "sg:phone":"+31 23 528 6260",
    "sg:postcode":"2101 JA",
    "sg:province":"North Holland",
    "sg:website":"http://www.hetkaasboerinnetje.nl",
    "wof:name":"Kaasboerinnetje, Het",
    "wof:placetype":"venue"
},
  "geometry": {"coordinates":[4.6213960648,52.3510932922],"type":"Point"}
}