{
  "type": "Feature",
  "properties": {
    "iso:country":"NL",
    "sg:address":"Rustoordln 31",
    "sg:city":"Eefde",
    "sg:orig_category":"Notarissen En Notariskantoren",
    "sg:phone":"+31 575 514 534",
    "sg:postcode":"7211 AV",
    "sg:province":"Gelderland",
    "sg:website":"http://www.gallenotarispraktijk.nl",
    "wof:name":"Galle Notarispraktijk",
    "wof:placetype":"venue"
},
  "geometry": {"coordinates":[6.22587,52.167686],"type":"Point"}
}