{
  "type": "Feature",
  "properties": {
    "addr:full":"Laagte 2 Eibergen Gelderland 7151 BS",
    "addr:housenumber":"2",
    "addr:postcode":"7151 bs",
    "addr:street":"Laagte;Gelderland",
    "iso:country":"NL",
    "sg:address":"Laagte 2",
    "sg:city":"Eibergen",
    "sg:orig_category":"Postkantoren",
    "sg:phone":"+31 545 471 311",
    "sg:postcode":"7151 BS",
    "sg:province":"Gelderland",
    "sg:website":"http://www.postkantoor.nl",
    "wof:name":"Postkantoor",
    "wof:placetype":"venue"
},
  "geometry": {"coordinates":[6.644859,52.102867],"type":"Point"}
}