{
  "type": "Feature",
  "properties": {
    "addr:full":"Brandwijksedijk 20 Brandwijk Zuid-Holland 2974 LB",
    "addr:housenumber":"20",
    "addr:postcode":"2974 lb",
    "addr:street":"Brandwijksedijk",
    "iso:country":"NL",
    "sg:address":"Brandwijksedijk 20",
    "sg:city":"Brandwijk",
    "sg:orig_category":"Goederenvervoer Over De Weg",
    "sg:phone":"+31 184 642 408",
    "sg:postcode":"2974 LB",
    "sg:province":"Zuid-Holland",
    "wof:name":"Kobra Transport",
    "wof:placetype":"venue"
},
  "geometry": {"coordinates":[4.814751,51.889652],"type":"Point"}
}