{
  "type": "Feature",
  "properties": {
    "addr:full":"Airbornelaan 33 Eindhoven Noord-Brabant 5632 JA",
    "addr:housenumber":"33",
    "addr:postcode":"5632 ja",
    "addr:street":"Airbornelaan",
    "iso:country":"NL",
    "sg:address":"Airbornelaan 33",
    "sg:city":"Eindhoven",
    "sg:orig_category":"Metaalwerken",
    "sg:phone":"+31 40 242 4224",
    "sg:postcode":"5632 JA",
    "sg:province":"Noord-Brabant",
    "wof:name":"F.B.J.M. Bijnen Zonwering",
    "wof:placetype":"venue"
},
  "geometry": {"coordinates":[5.49806,51.475101],"type":"Point"}
}