{
  "type": "Feature",
  "properties": {
    "addr:full":"Meerndk 16 De Meern Utrecht 3454 HR",
    "addr:housenumber":"16",
    "addr:postcode":"3454 hr",
    "addr:street":"Meerndk",
    "iso:country":"NL",
    "sg:address":"Meerndk 16",
    "sg:city":"De Meern",
    "sg:orig_category":"Hypotheken",
    "sg:phone":"+31 30 677 5800",
    "sg:postcode":"3454 HR",
    "sg:province":"Utrecht",
    "sg:website":"http://www.demeern.hypotheekshop.nl/870",
    "wof:name":"Hypotheekshop, De",
    "wof:placetype":"venue"
},
  "geometry": {"coordinates":[5.036798,52.08194],"type":"Point"}
}