{
  "type": "Feature",
  "properties": {
    "addr:full":"Terra Cottaplein 4 Maastricht Limburg 6216 BH",
    "addr:housenumber":"4",
    "addr:postcode":"6216 bh",
    "addr:street":"Terra Cottaplein",
    "iso:country":"NL",
    "sg:address":"Terra Cottaplein 4",
    "sg:city":"Maastricht",
    "sg:orig_category":"Kappers",
    "sg:phone":"+31 43 347 7767",
    "sg:postcode":"6216 BH",
    "sg:province":"Limburg",
    "wof:name":"Kapsalon De Knipshop",
    "wof:placetype":"venue"
},
  "geometry": {"coordinates":[5.659183979,50.8518486023],"type":"Point"}
}