{
  "type": "Feature",
  "properties": {
    "iso:country":"NL",
    "sg:address":"De Rik 22",
    "sg:city":"Brielle",
    "sg:orig_category":"Bibliotheken En Leeszalen Openbare",
    "sg:phone":"+31 181 418 043",
    "sg:postcode":"3232 LA",
    "sg:province":"Zuid-Holland",
    "wof:name":"Streekarchief Voorne Putten Rozenburg",
    "wof:placetype":"venue"
},
  "geometry": {"coordinates":[4.15616,51.895042],"type":"Point"}
}