{
  "type": "Feature",
  "properties": {
    "iso:country":"NL",
    "sg:address":"Torenlaan 37",
    "sg:city":"Ermelo",
    "sg:orig_category":"Wasserettes And Stomerijen",
    "sg:phone":"+31 341 552 072",
    "sg:postcode":"3851 NP",
    "sg:province":"Gelderland",
    "wof:name":"Stomerij Actief",
    "wof:placetype":"venue"
},
  "geometry": {"coordinates":[5.6266708374,52.3002204895],"type":"Point"}
}