{
  "type": "Feature",
  "properties": {
    "addr:full":"Hoogstraat 26 Harlingen Friesland 8861 AG",
    "addr:housenumber":"26",
    "addr:postcode":"8861",
    "addr:street":"Hoogstraat",
    "iso:country":"NL",
    "sg:address":"Hoogstraat 26",
    "sg:city":"Harlingen",
    "sg:orig_category":"Pleziervaartuigen And Reparatie",
    "sg:phone":"+31 517 419 208",
    "sg:postcode":"8861 AG",
    "sg:province":"Friesland",
    "wof:name":"Van Dieren Scheepsbouw",
    "wof:placetype":"venue"
},
  "geometry": {"coordinates":[5.422222,53.176071],"type":"Point"}
}