{
  "type": "Feature",
  "properties": {
    "iso:country":"NL",
    "sg:address":"Lutmastraat 81",
    "sg:city":"Amsterdam",
    "sg:orig_category":"Peuterspeelzalen",
    "sg:phone":"+31 20 470 1638",
    "sg:postcode":"1073 GP",
    "sg:province":"Noord-Holland",
    "wof:name":"Dikkie Dik",
    "wof:placetype":"venue"
},
  "geometry": {"coordinates":[4.896662,52.350906],"type":"Point"}
}