{
  "type": "Feature",
  "properties": {
    "addr:full":"Westerplein 98 Berkel En Rodenrijs Zuid-Holland 2651 JM",
    "addr:housenumber":"98",
    "addr:postcode":"2651 jm",
    "addr:street":"Westerplein",
    "iso:country":"NL",
    "sg:address":"Westerplein 98",
    "sg:city":"Berkel En Rodenrijs",
    "sg:orig_category":"Visspeciaalzaken",
    "sg:phone":"+31 10 511 2975",
    "sg:postcode":"2651 JM",
    "sg:province":"Zuid-Holland",
    "wof:name":"Visshop Berkel En Rodenrijs",
    "wof:placetype":"venue"
},
  "geometry": {"coordinates":[4.474466,51.994267],"type":"Point"}
}