{
  "type": "Feature",
  "properties": {
    "addr:full":"Burg V Dommelenln 10 Waalre Noord-Brabant 5583 AR",
    "addr:housenumber":"10",
    "addr:postcode":"5583",
    "addr:street":"Burg V Dommelenln",
    "iso:country":"NL",
    "sg:address":"Burg V Dommelenln 10",
    "sg:city":"Waalre",
    "sg:orig_category":"Kunststoffen- Verwerkende Industrie",
    "sg:phone":"+31 40 221 7541",
    "sg:postcode":"5583 AR",
    "sg:province":"Noord-Brabant",
    "wof:name":"Brouwer & Zn Bv, J J De",
    "wof:placetype":"venue"
},
  "geometry": {"coordinates":[5.443459,51.386463],"type":"Point"}
}