{
  "type": "Feature",
  "properties": {
    "iso:country":"NL",
    "sg:address":"Radboud 19",
    "sg:city":"Landsmeer",
    "sg:orig_category":"Schoonheidssalons",
    "sg:phone":"+31 20 482 3590",
    "sg:postcode":"1121 HT",
    "sg:province":"North Holland",
    "wof:name":"Advies- En Huidverzorgingsst Gina Hilkman",
    "wof:placetype":"venue"
},
  "geometry": {"coordinates":[4.915945,52.426498],"type":"Point"}
}