{
  "type": "Feature",
  "properties": {
    "iso:country":"NL",
    "sg:address":"Veestraat 38",
    "sg:city":"Helmond",
    "sg:orig_category":"Discountwinkels",
    "sg:phone":"+31 492 549 519",
    "sg:postcode":"5701 RD",
    "sg:province":"Noord-Brabant",
    "wof:name":"Zeeman Textielsupers",
    "wof:placetype":"venue"
},
  "geometry": {"coordinates":[5.652528,51.479122],"type":"Point"}
}