{
  "type": "Feature",
  "properties": {
    "addr:full":"Morsestr 19 Tiel Gelderland 4004 JP",
    "addr:housenumber":"19",
    "addr:postcode":"4004 jp",
    "addr:street":"Morsestr;Gelderland",
    "iso:country":"NL",
    "sg:address":"Morsestr 19",
    "sg:city":"Tiel",
    "sg:orig_category":"Hang- En Sluitwerk - Fabrieken En Groothandel",
    "sg:phone":"+31 344 618 633",
    "sg:postcode":"4004 JP",
    "sg:province":"Gelderland",
    "sg:website":"http://www.syntec.nl",
    "wof:name":"Syntec Tiel",
    "wof:placetype":"venue"
},
  "geometry": {"coordinates":[5.43185,51.910133],"type":"Point"}
}