{
  "type": "Feature",
  "properties": {
    "addr:full":"Insulindestraat 226-228 Rotterdam Zuid-Holland 3037 BK",
    "addr:housenumber":"226-228",
    "addr:postcode":"3037 bk",
    "addr:street":"Insulindestraat",
    "iso:country":"NL",
    "sg:address":"Insulindestraat 226-228",
    "sg:city":"Rotterdam",
    "sg:orig_category":"Diverse Consumentenartikelen Gh",
    "sg:phone":"+31 10 467 0918",
    "sg:postcode":"3037 BK",
    "sg:province":"Zuid-Holland",
    "wof:name":"Parthal Rotterdam",
    "wof:placetype":"venue"
},
  "geometry": {"coordinates":[4.469315,51.932865],"type":"Point"}
}