{
  "type": "Feature",
  "properties": {
    "addr:full":"Keizershof 15 Arnhem Gelderland 6834 DG",
    "addr:housenumber":"15",
    "addr:postcode":"6834 dg",
    "addr:street":"Keizershof",
    "iso:country":"NL",
    "sg:address":"Keizershof 15",
    "sg:city":"Arnhem",
    "sg:orig_category":"Sportprijzen, Postzegels And Munten",
    "sg:phone":"+31 26 321 3149",
    "sg:postcode":"6834 DG",
    "sg:province":"Gelderland",
    "wof:name":"Vof Keizershof",
    "wof:placetype":"venue"
},
  "geometry": {"coordinates":[5.923954,51.953213],"type":"Point"}
}