{
  "type": "Feature",
  "properties": {
    "addr:full":"Pancratiusstr 24 Zoeterwoude Zuid-Holland 2382 HL",
    "addr:housenumber":"24",
    "addr:postcode":"2382 hl",
    "addr:street":"Pancratiusstr",
    "iso:country":"NL",
    "sg:address":"Pancratiusstr 24",
    "sg:city":"Zoeterwoude",
    "sg:orig_category":"Mensendieck - Oefentherapeuten",
    "sg:phone":"+31 71 542 5959",
    "sg:postcode":"2382 HL",
    "sg:province":"Zuid-Holland",
    "wof:name":"Beenackers C M",
    "wof:placetype":"venue"
},
  "geometry": {"coordinates":[4.529979,52.139919],"type":"Point"}
}