{
  "type": "Feature",
  "properties": {
    "addr:full":"Bellinckhof 22 Hengelo Ov Overijssel 7556 NL",
    "addr:housenumber":"22",
    "addr:postcode":"7556 nl",
    "addr:street":"Bellinckhof;Ov",
    "iso:country":"NL",
    "sg:address":"Bellinckhof 22",
    "sg:city":"Hengelo Ov",
    "sg:orig_category":"Paramedische Behandelingen",
    "sg:phone":"+31 74 242 4816",
    "sg:postcode":"7556 NL",
    "sg:province":"Overijssel",
    "wof:name":"I.C.M. De Jongh",
    "wof:placetype":"venue"
},
  "geometry": {"coordinates":[6.797762,52.276096],"type":"Point"}
}