{
  "type": "Feature",
  "properties": {
    "iso:country":"NL",
    "sg:address":"Sporkenhoutlaan 5",
    "sg:city":"Gouda",
    "sg:orig_category":"Opticiens",
    "sg:phone":"+31 182 535 220",
    "sg:postcode":"2803 VJ",
    "sg:province":"Zuid-Holland",
    "wof:name":"Schraagen Optiek Bv",
    "wof:placetype":"venue"
},
  "geometry": {"coordinates":[4.6943950653,52.0243492126],"type":"Point"}
}