{
  "type": "Feature",
  "properties": {
    "addr:full":"Ds Sicco Tjadenstraat C 59 Nieuwe Pekela Groningen 9663 RC",
    "addr:housenumber":"59",
    "addr:postcode":"9663 rc",
    "addr:street":"Ds Sicco Tjadenstraat C",
    "iso:country":"NL",
    "sg:address":"Ds Sicco Tjadenstraat C 59",
    "sg:city":"Nieuwe Pekela",
    "sg:orig_category":"Banken And Kredietinstellingen",
    "sg:phone":"+31 597 662 111",
    "sg:postcode":"9663 RC",
    "sg:province":"Groningen",
    "wof:name":"Sns Bank Groningen",
    "wof:placetype":"venue"
},
  "geometry": {"coordinates":[6.960551,53.0732],"type":"Point"}
}