{
  "type": "Feature",
  "properties": {
    "iso:country":"NL",
    "sg:address":"Waalstr 30",
    "sg:city":"Rotterdam",
    "sg:orig_category":"Hijswerktuigen",
    "sg:phone":"+31 10 429 1767",
    "sg:postcode":"3087 BP",
    "sg:province":"South Holland",
    "wof:name":"Mouthaan Patent Bv",
    "wof:placetype":"venue"
},
  "geometry": {"coordinates":[4.458727,51.885597],"type":"Point"}
}