{
  "type": "Feature",
  "properties": {
    "addr:full":"Waalstr 30 Rotterdam South Holland 3087 BP",
    "addr:housenumber":"30",
    "addr:postcode":"3087 bp",
    "addr:street":"Waalstr",
    "iso:country":"NL",
    "sg:address":"Waalstr 30",
    "sg:city":"Rotterdam",
    "sg:orig_category":"Hijswerktuigen",
    "sg:phone":"+31 10 429 1767",
    "sg:postcode":"3087 BP",
    "sg:province":"South Holland",
    "wof:name":"Mouthaan Patent Bv",
    "wof:placetype":"venue"
},
  "geometry": {"coordinates":[4.458727,51.885597],"type":"Point"}
}