{
  "type": "Feature",
  "properties": {
    "iso:country":"NL",
    "sg:address":"Noordlierweg 38",
    "sg:city":"De Lier",
    "sg:orig_category":"Gemengde Landbouwbedrijven",
    "sg:phone":"+31 174 514 639",
    "sg:postcode":"2678 LV",
    "sg:province":"South Holland",
    "wof:name":"A. Buitelaar Bv",
    "wof:placetype":"venue"
},
  "geometry": {"coordinates":[4.253628,51.99044],"type":"Point"}
}