{
  "type": "Feature",
  "properties": {
    "iso:country":"NL",
    "sg:address":"Heliotroopln 358B",
    "sg:city":"S Gravenhage",
    "sg:classifiers":[
        {
            "category":"Personal",
            "subcategory":"Nail Salon",
            "type":"Services"
        }
    ],
    "sg:phone":"+31 70 325 4265",
    "sg:postcode":"2555 MK",
    "sg:province":"South Holland",
    "sg:tags":[
        "pedicure"
    ],
    "wof:name":"Tartwijk, Van",
    "wof:placetype":"venue"
},
  "geometry": {"coordinates":[4.2417,52.06638],"type":"Point"}
}