{
  "type": "Feature",
  "properties": {
    "addr:full":"Langenholterwg 2 Zwolle Overijssel 8021 CD",
    "addr:housenumber":"2",
    "addr:postcode":"8021 cd",
    "addr:street":"Langenholterwg",
    "iso:country":"NL",
    "sg:address":"Langenholterwg 2",
    "sg:city":"Zwolle",
    "sg:orig_category":"Kappers",
    "sg:phone":"+31 38 453 5043",
    "sg:postcode":"8021 CD",
    "sg:province":"Overijssel",
    "wof:name":"Ines Salon",
    "wof:placetype":"venue"
},
  "geometry": {"coordinates":[6.1017551422,52.5167884827],"type":"Point"}
}