{
  "type": "Feature",
  "properties": {
    "addr:full":"Hertogsingel 26 Maastricht Limburg 6214 AD",
    "addr:housenumber":"26",
    "addr:postcode":"6214 ad",
    "addr:street":"Hertogsingel",
    "iso:country":"NL",
    "sg:address":"Hertogsingel 26",
    "sg:city":"Maastricht",
    "sg:orig_category":"Public Relationbureaus",
    "sg:phone":"+31 43 321 6558",
    "sg:postcode":"6214 AD",
    "sg:province":"Limburg",
    "wof:name":"Mart Zeekaf Productions",
    "wof:placetype":"venue"
},
  "geometry": {"coordinates":[5.678152,50.848091],"type":"Point"}
}