{
  "type": "Feature",
  "properties": {
    "addr:full":"Abersonpln 3 Warnsveld Gelderland 7231 CP",
    "addr:housenumber":"3",
    "addr:postcode":"7231 cp",
    "addr:street":"Abersonpln;Gelderland",
    "iso:country":"NL",
    "sg:address":"Abersonpln 3",
    "sg:city":"Warnsveld",
    "sg:orig_category":"Beveiliging",
    "sg:phone":"+31 575 530 845",
    "sg:postcode":"7231 CP",
    "sg:province":"Gelderland",
    "wof:name":"Aw Vof",
    "wof:placetype":"venue"
},
  "geometry": {"coordinates":[6.231253,52.140896],"type":"Point"}
}