{
  "type": "Feature",
  "properties": {
    "addr:full":"Donkerstr 19 Aalst Gld Gelderland 5308 KB",
    "addr:housenumber":"19",
    "addr:postcode":"5308 kb",
    "addr:street":"Donkerstr;Gld Gelderland",
    "iso:country":"NL",
    "sg:address":"Donkerstr 19",
    "sg:city":"Aalst Gld",
    "sg:orig_category":"Verenigingsgebouwen",
    "sg:phone":"+31 418 672 072",
    "sg:postcode":"5308 KB",
    "sg:province":"Gelderland",
    "wof:name":"Dorpshuis",
    "wof:placetype":"venue"
},
  "geometry": {"coordinates":[5.12592,51.783436],"type":"Point"}
}