{
  "type": "Feature",
  "properties": {
    "addr:full":"Ysselmeerdk 7A Warder Noord-Holland 1473 PP",
    "addr:housenumber":"7a",
    "addr:postcode":"1473 pp",
    "addr:street":"Ysselmeerdk",
    "iso:country":"NL",
    "sg:address":"Ysselmeerdk 7A",
    "sg:city":"Warder",
    "sg:classifiers":[
        {
            "category":"Travel",
            "subcategory":"Hotels & Motels",
            "type":"Entertainment"
        }
    ],
    "sg:phone":"+31 299 403 333",
    "sg:postcode":"1473 PP",
    "sg:province":"Noord-Holland",
    "wof:name":"Tolhuus, H E M 'T",
    "wof:placetype":"venue"
},
  "geometry": {"coordinates":[5.037793,52.562943],"type":"Point"}
}