{
  "type": "Feature",
  "properties": {
    "iso:country":"NL",
    "sg:address":"Ryvoortshoef 265",
    "sg:city":"Raamsdonksveer",
    "sg:orig_category":"Boeken En Tijdschriften",
    "sg:phone":"+31 162 513 425",
    "sg:postcode":"4941 VJ",
    "sg:province":"Noord-Brabant",
    "wof:name":"Ons Erfdeel",
    "wof:placetype":"venue"
},
  "geometry": {"coordinates":[4.885553,51.70414],"type":"Point"}
}