{
  "type": "Feature",
  "properties": {
    "addr:full":"Ramstraat 14 Leeuwarden Provincie Friesland 8921 PX",
    "addr:housenumber":"14",
    "addr:postcode":"8921 px",
    "addr:street":"Ramstraat;Provincie Friesland",
    "iso:country":"NL",
    "sg:address":"Ramstraat 14",
    "sg:city":"Leeuwarden",
    "sg:orig_category":"Bedrijfsinventaris Gh",
    "sg:phone":"+31 58 213 6971",
    "sg:postcode":"8921 PX",
    "sg:province":"Provincie Friesland",
    "wof:name":"V.S.R. (Van Stralen Rateaux)",
    "wof:placetype":"venue"
},
  "geometry": {"coordinates":[5.808846,53.208614],"type":"Point"}
}