{
  "type": "Feature",
  "properties": {
    "addr:full":"Meerweg 11 Abcoude Utrecht 1391 HG",
    "addr:housenumber":"11",
    "addr:postcode":"1391 hg",
    "addr:street":"Meerweg",
    "iso:country":"NL",
    "sg:address":"Meerweg 11",
    "sg:city":"Abcoude",
    "sg:orig_category":"Autokeuringen",
    "sg:phone":"+31 294 281 370",
    "sg:postcode":"1391 HG",
    "sg:province":"Utrecht",
    "wof:name":"Van Mourik",
    "wof:placetype":"venue"
},
  "geometry": {"coordinates":[4.971983,52.272728],"type":"Point"}
}