{
  "type": "Feature",
  "properties": {
    "addr:full":"Groningerstrwg 36 Leeuwarden Friesland 8921 TR",
    "addr:housenumber":"36",
    "addr:postcode":"8921 tr",
    "addr:street":"Groningerstrwg",
    "iso:country":"NL",
    "sg:address":"Groningerstrwg 36",
    "sg:city":"Leeuwarden",
    "sg:orig_category":"Beeldende Kunstenaars",
    "sg:phone":"+31 58 213 5809",
    "sg:postcode":"8921 TR",
    "sg:province":"Friesland",
    "wof:name":"Keikkeik",
    "wof:placetype":"venue"
},
  "geometry": {"coordinates":[5.804919,53.20816],"type":"Point"}
}