{
  "type": "Feature",
  "properties": {
    "addr:full":"Nova Zemblastraat 565 Amsterdam North Holland 1013 RJ",
    "addr:housenumber":"565",
    "addr:postcode":"1013 rj",
    "addr:street":"Nova Zemblastraat",
    "iso:country":"NL",
    "sg:address":"Nova Zemblastraat 565",
    "sg:city":"Amsterdam",
    "sg:orig_category":"Boekhandels",
    "sg:phone":"+31 20 682 9737",
    "sg:postcode":"1013 RJ",
    "sg:province":"North Holland",
    "wof:name":"Firma P.J. Visser",
    "wof:placetype":"venue"
},
  "geometry": {"coordinates":[4.878571,52.390724],"type":"Point"}
}