{
  "type": "Feature",
  "properties": {
    "addr:full":"Noorderln 15 Hillegom Zuid-Holland 2182 GZ",
    "addr:housenumber":"15",
    "addr:postcode":"2182 gz",
    "addr:street":"Noorderln",
    "iso:country":"NL",
    "sg:address":"Noorderln 15",
    "sg:city":"Hillegom",
    "sg:orig_category":"Bloembollen - Groothandel",
    "sg:phone":"+31 252 515 105",
    "sg:postcode":"2182 GZ",
    "sg:province":"Zuid-Holland",
    "wof:name":"Til Bv, Gebr Van",
    "wof:placetype":"venue"
},
  "geometry": {"coordinates":[4.578603,52.290993],"type":"Point"}
}