{
  "type": "Feature",
  "properties": {
    "addr:full":"K Ferrierln 15 Amstelveen North Holland 1183 CA",
    "addr:housenumber":"15",
    "addr:postcode":"1183 ca",
    "addr:street":"Ferrierln",
    "iso:country":"NL",
    "sg:address":"K Ferrierln 15",
    "sg:city":"Amstelveen",
    "sg:orig_category":"Vertaalbureaus",
    "sg:phone":"+31 20 647 7744",
    "sg:postcode":"1183 CA",
    "sg:province":"North Holland",
    "sg:website":"http://www.ccgroep.nl",
    "wof:name":"Cc Groep Bv",
    "wof:placetype":"venue"
},
  "geometry": {"coordinates":[4.856945,52.303444],"type":"Point"}
}