{
  "type": "Feature",
  "properties": {
    "addr:full":"Ericastraat 2 Geleen Limburg 6163 TT",
    "addr:housenumber":"2",
    "addr:postcode":"6163 tt",
    "addr:street":"Ericastraat",
    "iso:country":"NL",
    "sg:address":"Ericastraat 2",
    "sg:city":"Geleen",
    "sg:orig_category":"Autokeuringen",
    "sg:phone":"+31 46 474 1582",
    "sg:postcode":"6163 TT",
    "sg:province":"Limburg",
    "wof:name":"Kerstens",
    "wof:placetype":"venue"
},
  "geometry": {"coordinates":[5.823336,50.983929],"type":"Point"}
}