{
  "type": "Feature",
  "properties": {
    "addr:full":"Eurenderstraat 20 Kerkrade Limburg 6467 CS",
    "addr:housenumber":"20",
    "addr:postcode":"6467 cs",
    "addr:street":"Eurenderstraat",
    "iso:country":"NL",
    "sg:address":"Eurenderstraat 20",
    "sg:city":"Kerkrade",
    "sg:classifiers":[
        {
            "category":"Professional",
            "subcategory":"Accounting & Tax Preparation",
            "type":"Services"
        }
    ],
    "sg:phone":"+31 45 541 6145",
    "sg:postcode":"6467 CS",
    "sg:province":"Limburg",
    "sg:tags":[
        "accountant"
    ],
    "wof:name":"Administratiekant. Nico Bonfrere",
    "wof:placetype":"venue"
},
  "geometry": {"coordinates":[6.024584,50.864483],"type":"Point"}
}