{
  "type": "Feature",
  "properties": {
    "addr:full":"Kerkstraat 47 Didam Gelderland 6942 AP",
    "addr:housenumber":"47",
    "addr:postcode":"6942 ap",
    "addr:street":"Kerkstraat;Gelderland",
    "iso:country":"NL",
    "sg:address":"Kerkstraat 47",
    "sg:city":"Didam",
    "sg:orig_category":"Woningbouwverenigingen",
    "sg:phone":"+31 316 296 600",
    "sg:postcode":"6942 AP",
    "sg:province":"Gelderland",
    "wof:name":"Laris Wonen En Diensten",
    "wof:placetype":"venue"
},
  "geometry": {"coordinates":[6.1288399696,51.9441146851],"type":"Point"}
}