{
  "type": "Feature",
  "properties": {
    "iso:country":"NL",
    "sg:address":"Luthulisngl 48",
    "sg:city":"Culemborg",
    "sg:orig_category":"Accountants - Administratie- Consulenten En -Kantoren",
    "sg:phone":"+31 345 534 947",
    "sg:postcode":"4105 HA",
    "sg:province":"Gelderland",
    "wof:name":"Dam",
    "wof:placetype":"venue"
},
  "geometry": {"coordinates":[5.22148,51.952175],"type":"Point"}
}