{
  "type": "Feature",
  "properties": {
    "addr:full":"Dorpsstr 39 Oostkapelle Zeeland 4356 AH",
    "addr:housenumber":"39",
    "addr:postcode":"4356 ah",
    "addr:street":"Dorpsstr",
    "iso:country":"NL",
    "sg:address":"Dorpsstr 39",
    "sg:city":"Oostkapelle",
    "sg:classifiers":[
        {
            "category":"Travel",
            "subcategory":"Hotels & Motels",
            "type":"Entertainment"
        }
    ],
    "sg:phone":"+31 118 581 366",
    "sg:postcode":"4356 AH",
    "sg:province":"Zeeland",
    "wof:name":"Zeelandia",
    "wof:placetype":"venue"
},
  "geometry": {"coordinates":[3.55322,51.566402],"type":"Point"}
}