{
  "type": "Feature",
  "properties": {
    "addr:full":"Damstr 70 Utrecht Utrecht 3531 BW",
    "addr:housenumber":"70",
    "addr:postcode":"3531 bw",
    "addr:street":"Damstr",
    "iso:country":"NL",
    "sg:address":"Damstr 70",
    "sg:city":"Utrecht",
    "sg:orig_category":"Onderhoudswerken",
    "sg:phone":"+31 30 286 3906",
    "sg:postcode":"3531 BW",
    "sg:province":"Utrecht",
    "wof:name":"Bouwbureau West",
    "wof:placetype":"venue"
},
  "geometry": {"coordinates":[5.10313,52.092316],"type":"Point"}
}