{
  "type": "Feature",
  "properties": {
    "addr:full":"Boterwijksestr 10 Oirschot Noord-Brabant 5688 HX",
    "addr:housenumber":"10",
    "addr:postcode":"5688 hx",
    "addr:street":"Boterwijksestr",
    "iso:country":"NL",
    "sg:address":"Boterwijksestr 10",
    "sg:city":"Oirschot",
    "sg:orig_category":"Beeldende Kunstenaars",
    "sg:phone":"+31 499 572 042",
    "sg:postcode":"5688 HX",
    "sg:province":"Noord-Brabant",
    "wof:name":"Hans Van Eerd",
    "wof:placetype":"venue"
},
  "geometry": {"coordinates":[5.291926,51.506554],"type":"Point"}
}