{
  "type": "Feature",
  "properties": {
    "addr:full":"De Swaenenborgh 18 Meppel Drenthe 7941 BD",
    "addr:housenumber":"18",
    "addr:postcode":"7941 bd",
    "addr:street":"De Swaenenborgh",
    "iso:country":"NL",
    "sg:address":"De Swaenenborgh 18",
    "sg:city":"Meppel",
    "sg:orig_category":"Postkantoren",
    "sg:phone":"+31 522 258 484",
    "sg:postcode":"7941 BD",
    "sg:province":"Drenthe",
    "sg:website":"http://www.postkantoor.nl",
    "wof:name":"Postkantoor",
    "wof:placetype":"venue"
},
  "geometry": {"coordinates":[6.188374,52.698074],"type":"Point"}
}