{
  "type": "Feature",
  "properties": {
    "addr:full":"Mezenstraat 6 Gaanderen Gelderland 7011 DK",
    "addr:housenumber":"6",
    "addr:postcode":"7011 dk",
    "addr:street":"Mezenstraat;Gelderland",
    "iso:country":"NL",
    "sg:address":"Mezenstraat 6",
    "sg:city":"Gaanderen",
    "sg:orig_category":"Verzekeringen",
    "sg:phone":"+31 315 324 533",
    "sg:postcode":"7011 DK",
    "sg:province":"Gelderland",
    "wof:name":"H. Berentsen Assurantien",
    "wof:placetype":"venue"
},
  "geometry": {"coordinates":[6.353681,51.928192],"type":"Point"}
}