{
  "type": "Feature",
  "properties": {
    "addr:full":"Meerkreuk 64 Oude Wetering Zuid-Holland 2377 VM",
    "addr:housenumber":"64",
    "addr:postcode":"wetering;2377 vm",
    "addr:street":"Meerkreuk",
    "iso:country":"NL",
    "sg:address":"Meerkreuk 64",
    "sg:city":"Oude Wetering",
    "sg:orig_category":"Advocaten En Advocatenkantoren",
    "sg:phone":"+31 71 331 2099",
    "sg:postcode":"2377 VM",
    "sg:province":"Zuid-Holland",
    "wof:name":"Hartingsveldt En Roest, Van",
    "wof:placetype":"venue"
},
  "geometry": {"coordinates":[4.642081,52.207111],"type":"Point"}
}