{
  "type": "Feature",
  "properties": {
    "addr:full":"De Grt Elst 62 Rosmalen North Brabant 5246 JR",
    "addr:housenumber":"62",
    "addr:postcode":"5246 jr",
    "addr:street":"Elst",
    "iso:country":"NL",
    "sg:address":"De Grt Elst 62",
    "sg:city":"Rosmalen",
    "sg:orig_category":"Adviesbureaus Bedrijfsorganisatie",
    "sg:phone":"+31 73 643 2700",
    "sg:postcode":"5246 JR",
    "sg:province":"North Brabant",
    "sg:website":"http://www.rpgroep.nl",
    "wof:name":"R & P Groep",
    "wof:placetype":"venue"
},
  "geometry": {"coordinates":[5.343946,51.705669],"type":"Point"}
}