{
  "type": "Feature",
  "properties": {
    "addr:full":"Wyksestr 11 Wyk En Aalburg Noord-Brabant 4261 TV",
    "addr:housenumber":"11",
    "addr:postcode":"4261 tv",
    "addr:street":"Wyksestr",
    "iso:country":"NL",
    "sg:address":"Wyksestr 11",
    "sg:city":"Wyk En Aalburg",
    "sg:orig_category":"Bloemen En Planten - Groothandel",
    "sg:phone":"+31 416 691 362",
    "sg:postcode":"4261 TV",
    "sg:province":"Noord-Brabant",
    "wof:name":"Timmermans Veen Bv, F P",
    "wof:placetype":"venue"
},
  "geometry": {"coordinates":[5.13042,51.755196],"type":"Point"}
}