{
  "type": "Feature",
  "properties": {
    "iso:country":"NL",
    "sg:address":"Nieuwlanderwg 41",
    "sg:city":"De Waal",
    "sg:orig_category":"Vakantieverblijven",
    "sg:phone":"+31 222 327 554",
    "sg:postcode":"1793 ES",
    "sg:province":"Noord-Holland",
    "wof:name":"Sangers, G A",
    "wof:placetype":"venue"
},
  "geometry": {"coordinates":[4.798577,53.097042],"type":"Point"}
}