{
  "type": "Feature",
  "properties": {
    "addr:full":"J Gielenpln 8A Oudenbosch Noord-Brabant 4731 HL",
    "addr:housenumber":"8a",
    "addr:postcode":"4731 hl",
    "iso:country":"NL",
    "sg:address":"J Gielenpln 8A",
    "sg:city":"Oudenbosch",
    "sg:orig_category":"Logopedisten",
    "sg:phone":"+31 165 318 602",
    "sg:postcode":"4731 HL",
    "sg:province":"Noord-Brabant",
    "wof:name":"Vriens-Bol, A M",
    "wof:placetype":"venue"
},
  "geometry": {"coordinates":[4.527834,51.589512],"type":"Point"}
}