{
  "type": "Feature",
  "properties": {
    "addr:full":"Stationswg 3A Sliedrecht Zuid-Holland 3362 HA",
    "addr:housenumber":"3a",
    "addr:postcode":"3362 ha",
    "addr:street":"Stationswg",
    "iso:country":"NL",
    "sg:address":"Stationswg 3A",
    "sg:city":"Sliedrecht",
    "sg:orig_category":"Biljartzalen",
    "sg:phone":"+31 184 421 470",
    "sg:postcode":"3362 HA",
    "sg:province":"Zuid-Holland",
    "sg:website":"http://www.actief.nl/snookerparadijs/",
    "wof:name":"Snooker Paradijs",
    "wof:placetype":"venue"
},
  "geometry": {"coordinates":[4.772052,51.821953],"type":"Point"}
}