{
  "type": "Feature",
  "properties": {
    "addr:full":"Lynbaansgr 94 Amsterdam Noord-Holland 1015 GZ",
    "addr:housenumber":"94",
    "addr:postcode":"1015 gz",
    "addr:street":"Lynbaansgr",
    "iso:country":"NL",
    "sg:address":"Lynbaansgr 94",
    "sg:city":"Amsterdam",
    "sg:orig_category":"Horeca-Inrichtingen En -Uitrustingen",
    "sg:phone":"+31 20 638 2538",
    "sg:postcode":"1015 GZ",
    "sg:province":"Noord-Holland",
    "wof:name":"Ruiter, P De",
    "wof:placetype":"venue"
},
  "geometry": {"coordinates":[4.877562,52.37463],"type":"Point"}
}