{
  "type": "Feature",
  "properties": {
    "addr:full":"Wilhelminastr 26 Boekel Noord-Brabant 5427 CE",
    "addr:housenumber":"26",
    "addr:postcode":"5427 ce",
    "addr:street":"Wilhelminastr",
    "iso:country":"NL",
    "sg:address":"Wilhelminastr 26",
    "sg:city":"Boekel",
    "sg:orig_category":"Montagebedrijven",
    "sg:phone":"+31 492 323 324",
    "sg:postcode":"5427 CE",
    "sg:province":"Noord-Brabant",
    "wof:name":"Broek, Arie Van Den",
    "wof:placetype":"venue"
},
  "geometry": {"coordinates":[5.668126,51.604355],"type":"Point"}
}