{
  "type": "Feature",
  "properties": {
    "iso:country":"NL",
    "sg:address":"Bergse Dorpsstraat 32",
    "sg:city":"Rotterdam",
    "sg:classifiers":[
        {
            "category":"Retail",
            "subcategory":"Photofinishing",
            "type":"Services"
        }
    ],
    "sg:phone":"+31 10 461 0106",
    "sg:postcode":"3054 GD",
    "sg:province":"Zuid-Holland",
    "sg:tags":[
        "foto",
        "film"
    ],
    "wof:name":"Kinorama",
    "wof:placetype":"venue"
},
  "geometry": {"coordinates":[4.49412,51.956108],"type":"Point"}
}