{
  "type": "Feature",
  "properties": {
    "addr:full":"Kruisbessenstraat 17 Rockanje Zuid-Holland 3235 EE",
    "addr:housenumber":"17",
    "addr:postcode":"3235 ee",
    "addr:street":"Kruisbessenstraat",
    "iso:country":"NL",
    "sg:address":"Kruisbessenstraat 17",
    "sg:city":"Rockanje",
    "sg:orig_category":"Recreatie- And Lunaparken",
    "sg:phone":"+31 181 403 618",
    "sg:postcode":"3235 EE",
    "sg:province":"Zuid-Holland",
    "wof:name":"Verhuur Poldervaart",
    "wof:placetype":"venue"
},
  "geometry": {"coordinates":[4.066964,51.868675],"type":"Point"}
}