{
  "type": "Feature",
  "properties": {
    "iso:country":"NL",
    "sg:address":"Weefkamer 91",
    "sg:city":"Wierden",
    "sg:orig_category":"Bestratingen",
    "sg:phone":"+31 546 570 345",
    "sg:postcode":"7641 LM",
    "sg:province":"Overijssel",
    "wof:name":"Vrielink",
    "wof:placetype":"venue"
},
  "geometry": {"coordinates":[6.601345,52.369282],"type":"Point"}
}