{
  "type": "Feature",
  "properties": {
    "addr:full":"Bolensteinsestraat 30 Maarssen Utrecht 3603 AX",
    "addr:housenumber":"30",
    "addr:postcode":"3603 ax",
    "addr:street":"Bolensteinsestraat",
    "iso:country":"NL",
    "sg:address":"Bolensteinsestraat 30",
    "sg:city":"Maarssen",
    "sg:orig_category":"Kappers",
    "sg:phone":"+31 346 560 279",
    "sg:postcode":"3603 AX",
    "sg:province":"Utrecht",
    "wof:name":"Dameskapsalon Petra",
    "wof:placetype":"venue"
},
  "geometry": {"coordinates":[5.0382409096,52.1400985718],"type":"Point"}
}