{
  "type": "Feature",
  "properties": {
    "addr:full":"Bivakweg 1 Deurne Noord-Brabant 5752 PZ",
    "addr:housenumber":"1",
    "addr:postcode":"5752 pz",
    "addr:street":"Bivakweg",
    "iso:country":"NL",
    "sg:address":"Bivakweg 1",
    "sg:city":"Deurne",
    "sg:orig_category":"Loodgieterswerk, Verwarming And Sanitaire Installaties",
    "sg:phone":"+31 493 317 591",
    "sg:postcode":"5752 PZ",
    "sg:province":"Noord-Brabant",
    "wof:name":"Vof H. Knijnenburg",
    "wof:placetype":"venue"
},
  "geometry": {"coordinates":[5.82884,51.479919],"type":"Point"}
}