{
  "type": "Feature",
  "properties": {
    "addr:full":"Hg Ryndk 328A Leiden Zuid-Holland 2314 AN",
    "addr:housenumber":"328a",
    "addr:postcode":"2314 an",
    "iso:country":"NL",
    "sg:address":"Hg Ryndk 328A",
    "sg:city":"Leiden",
    "sg:orig_category":"Verzekeringen - Verzekeringskantoren",
    "sg:phone":"+31 71 581 3232",
    "sg:postcode":"2314 AN",
    "sg:province":"Zuid-Holland",
    "wof:name":"Multicare",
    "wof:placetype":"venue"
},
  "geometry": {"coordinates":[4.52202,52.14946],"type":"Point"}
}