{
  "type": "Feature",
  "properties": {
    "addr:full":"Julianastraat 51 Dedemsvaart Overijssel 7701 GJ",
    "addr:housenumber":"51",
    "addr:postcode":"7701 gj",
    "addr:street":"Julianastraat",
    "iso:country":"NL",
    "sg:address":"Julianastraat 51",
    "sg:city":"Dedemsvaart",
    "sg:classifiers":[
        {
            "category":"Retail",
            "subcategory":"Photofinishing",
            "type":"Services"
        }
    ],
    "sg:phone":"+31 523 612 101",
    "sg:postcode":"7701 GJ",
    "sg:province":"Overijssel",
    "sg:tags":[
        "foto",
        "film"
    ],
    "wof:name":"Foto Film Video Bennink Bv",
    "wof:placetype":"venue"
},
  "geometry": {"coordinates":[6.458166,52.602642],"type":"Point"}
}