{
  "type": "Feature",
  "properties": {
    "addr:full":"Ondernemingswg 18 Alphen Aan Den Ryn Zuid-Holland 2404 HN",
    "addr:housenumber":"18",
    "addr:postcode":"2404 hn",
    "addr:street":"Ondernemingswg;Aan Den Ryn",
    "iso:country":"NL",
    "sg:address":"Ondernemingswg 18",
    "sg:city":"Alphen Aan Den Ryn",
    "sg:orig_category":"Bloemen En Planten - Decoratie",
    "sg:phone":"+31 172 244 603",
    "sg:postcode":"2404 HN",
    "sg:province":"Zuid-Holland",
    "wof:name":"Anneveldt, B & P",
    "wof:placetype":"venue"
},
  "geometry": {"coordinates":[4.637191,52.138954],"type":"Point"}
}