{
  "type": "Feature",
  "properties": {
    "addr:full":"Pampuslaan 155 Weesp Noord-Holland 1382 JN",
    "addr:housenumber":"155",
    "addr:postcode":"1382 jn",
    "addr:street":"Pampuslaan",
    "iso:country":"NL",
    "sg:address":"Pampuslaan 155",
    "sg:city":"Weesp",
    "sg:orig_category":"Meubels And Huishoudapparatuur Gh",
    "sg:phone":"+31 294 492 525",
    "sg:postcode":"1382 JN",
    "sg:province":"Noord-Holland",
    "wof:name":"European Sleep Products Bv",
    "wof:placetype":"venue"
},
  "geometry": {"coordinates":[5.024627,52.316109],"type":"Point"}
}