{
  "type": "Feature",
  "properties": {
    "addr:full":"Bosuilln 143 Bilthoven Utrecht 3722 XJ",
    "addr:housenumber":"143",
    "addr:postcode":"3722 xj",
    "addr:street":"Bilthoven",
    "iso:country":"NL",
    "sg:address":"Bosuilln 143",
    "sg:city":"Bilthoven",
    "sg:classifiers":[
        {
            "category":"Real Estate",
            "subcategory":"Real Estate Operator",
            "type":"Services"
        }
    ],
    "sg:phone":"+31 30 229 8000",
    "sg:postcode":"3722 XJ",
    "sg:province":"Utrecht",
    "sg:tags":[
        "appartementen",
        "en",
        "flat"
    ],
    "wof:name":"Houdringe",
    "wof:placetype":"venue"
},
  "geometry": {"coordinates":[5.21093,52.121498],"type":"Point"}
}