{
  "type": "Feature",
  "properties": {
    "addr:full":"Eiber 130 Bodegraven South Holland 2411 LC",
    "addr:housenumber":"130",
    "addr:postcode":"2411 lc",
    "addr:street":"Eiber",
    "iso:country":"NL",
    "sg:address":"Eiber 130",
    "sg:city":"Bodegraven",
    "sg:orig_category":"Verenigingsgebouwen",
    "sg:phone":"+31 172 615 233",
    "sg:postcode":"2411 LC",
    "sg:province":"South Holland",
    "sg:website":"http://www.dezonbodegraven.nl",
    "wof:name":"Soc Cult Werk, Sticht",
    "wof:placetype":"venue"
},
  "geometry": {"coordinates":[4.744824,52.073872],"type":"Point"}
}