{
  "type": "Feature",
  "properties": {
    "addr:full":"Anysstr 6 Almere Flevoland 1314 JA",
    "addr:housenumber":"6",
    "addr:postcode":"1314 ja",
    "addr:street":"Anysstr;Flevoland",
    "iso:country":"NL",
    "sg:address":"Anysstr 6",
    "sg:city":"Almere",
    "sg:orig_category":"Adviesbureaus Bedrijfsorganisatie",
    "sg:phone":"+31 36 534 2445",
    "sg:postcode":"1314 JA",
    "sg:province":"Flevoland",
    "sg:website":"http://www.hwvanderleeuw.nl",
    "wof:name":"Leeuw Organisatie Onderzoek & Advies, Van Der",
    "wof:placetype":"venue"
},
  "geometry": {"coordinates":[5.22223,52.376598],"type":"Point"}
}