{
  "type": "Feature",
  "properties": {
    "iso:country":"NL",
    "sg:address":"Concordialaan 8",
    "sg:city":"Etten-Leur",
    "sg:orig_category":"Metaalwerken",
    "sg:phone":"+31 76 501 4594",
    "sg:postcode":"4874 NZ",
    "sg:province":"Noord-Brabant",
    "wof:name":"Stucadoorsbedrijf Hans Thijs Bv",
    "wof:placetype":"venue"
},
  "geometry": {"coordinates":[4.633201,51.576649],"type":"Point"}
}