{
  "type": "Feature",
  "properties": {
    "iso:country":"NL",
    "sg:address":"Billitonln 34",
    "sg:city":"Vlaardingen",
    "sg:orig_category":"Kappers",
    "sg:phone":"+31 10 435 0963",
    "sg:postcode":"3131 LK",
    "sg:province":"South Holland",
    "wof:name":"Fred",
    "wof:placetype":"venue"
},
  "geometry": {"coordinates":[4.3335142136,51.911781311],"type":"Point"}
}