{
  "type": "Feature",
  "properties": {
    "addr:full":"Dorpsstr 39A Ryswyk Nb North Brabant 4284 EG",
    "addr:housenumber":"39a;nb",
    "addr:postcode":"4284 eg",
    "addr:street":"Dorpsstr;North",
    "iso:country":"NL",
    "sg:address":"Dorpsstr 39A",
    "sg:city":"Ryswyk Nb",
    "sg:orig_category":"Kappers",
    "sg:phone":"+31 183 443 011",
    "sg:postcode":"4284 EG",
    "sg:province":"North Brabant",
    "wof:name":"Harry'S",
    "wof:placetype":"venue"
},
  "geometry": {"coordinates":[5.027009964,51.797668457],"type":"Point"}
}