{
  "type": "Feature",
  "properties": {
    "iso:country":"NL",
    "sg:address":"Rietveldenwg 64A",
    "sg:city":"S Hertogenbosch",
    "sg:orig_category":"Autoruiten",
    "sg:phone":"+31 73 621 3822",
    "sg:postcode":"5222 AS",
    "sg:province":"Noord-Brabant",
    "wof:name":"Autotaalglas",
    "wof:placetype":"venue"
},
  "geometry": {"coordinates":[5.268939,51.704384],"type":"Point"}
}