{
  "type": "Feature",
  "properties": {
    "addr:full":"Generaal Spoorlaan 12 Haarlem Noord-Holland 2025 NB",
    "addr:housenumber":"12",
    "addr:postcode":"2025 nb",
    "addr:street":"Generaal Spoorlaan",
    "iso:country":"NL",
    "sg:address":"Generaal Spoorlaan 12",
    "sg:city":"Haarlem",
    "sg:orig_category":"Wasserettes And Stomerijen",
    "sg:phone":"+31 23 537 4060",
    "sg:postcode":"2025 NB",
    "sg:province":"Noord-Holland",
    "wof:name":"Garant Stomerij",
    "wof:placetype":"venue"
},
  "geometry": {"coordinates":[4.6452050209,52.414024353],"type":"Point"}
}