{
  "type": "Feature",
  "properties": {
    "addr:full":"Von Liebigweg 39 Amsterdam North Holland 1097 RL",
    "addr:housenumber":"39",
    "addr:postcode":"1097 rl",
    "addr:street":"Von Liebigweg",
    "iso:country":"NL",
    "sg:address":"Von Liebigweg 39",
    "sg:city":"Amsterdam",
    "sg:orig_category":"Boekhouders",
    "sg:phone":"+31 20 693 8629",
    "sg:postcode":"1097 RL",
    "sg:province":"North Holland",
    "wof:name":"Administratiekantoor A. Broere",
    "wof:placetype":"venue"
},
  "geometry": {"coordinates":[4.926901,52.342812],"type":"Point"}
}