{
  "type": "Feature",
  "properties": {
    "addr:full":"Aartshertogenln 381 S Hertogenbosch Noord-Brabant 5212 CK",
    "addr:housenumber":"381",
    "addr:postcode":"5212 ck",
    "addr:street":"S",
    "iso:country":"NL",
    "sg:address":"Aartshertogenln 381",
    "sg:city":"S Hertogenbosch",
    "sg:orig_category":"Psychotherapeuten",
    "sg:phone":"+31 73 614 7336",
    "sg:postcode":"5212 CK",
    "sg:province":"Noord-Brabant",
    "sg:website":"http://www.gestalttherapeut.info",
    "wof:name":"Gestalttherapie, Praktijk Voor",
    "wof:placetype":"venue"
},
  "geometry": {"coordinates":[5.3155908585,51.698928833],"type":"Point"}
}