{
  "type": "Feature",
  "properties": {
    "addr:full":"Musselweg 2 Mussel Groningen 9584 AE",
    "addr:housenumber":"2",
    "addr:postcode":"9584 ae",
    "addr:street":"Musselweg",
    "iso:country":"NL",
    "sg:address":"Musselweg 2",
    "sg:city":"Mussel",
    "sg:orig_category":"Kappers",
    "sg:phone":"+31 599 413 606",
    "sg:postcode":"9584 AE",
    "sg:province":"Groningen",
    "wof:name":"Salon Annemarie",
    "wof:placetype":"venue"
},
  "geometry": {"coordinates":[-83.144104,39.370178],"type":"Point"}
}