{
  "type": "Feature",
  "properties": {
    "iso:country":"NL",
    "sg:address":"Kerkstr 2",
    "sg:city":"Kwintsheul",
    "sg:orig_category":"Fietsen En Bromfietsen",
    "sg:phone":"+31 174 292 394",
    "sg:postcode":"2295 LG",
    "sg:province":"Zuid-Holland",
    "wof:name":"Boutkan",
    "wof:placetype":"venue"
},
  "geometry": {"coordinates":[4.255479,52.015614],"type":"Point"}
}