{
  "type": "Feature",
  "properties": {
    "addr:full":"Ten Darperwg 104 Wapse Drenthe 7983 KP",
    "addr:housenumber":"104",
    "addr:postcode":"7983 kp",
    "addr:street":"Ten",
    "iso:country":"NL",
    "sg:address":"Ten Darperwg 104",
    "sg:city":"Wapse",
    "sg:classifiers":[
        {
            "category":"Travel",
            "subcategory":"Hotels & Motels",
            "type":"Entertainment"
        }
    ],
    "sg:phone":"+31 521 551 278",
    "sg:postcode":"7983 KP",
    "sg:province":"Drenthe",
    "sg:website":"http://www.wapserherberg.nl",
    "wof:name":"Wapser Herberg, De",
    "wof:placetype":"venue"
},
  "geometry": {"coordinates":[6.25478,52.855267],"type":"Point"}
}