{
  "type": "Feature",
  "properties": {
    "iso:country":"NL",
    "sg:address":"Ten Darperwg 104",
    "sg:city":"Wapse",
    "sg:classifiers":[
        {
            "category":"Travel",
            "subcategory":"Hotels & Motels",
            "type":"Entertainment"
        }
    ],
    "sg:phone":"+31 521 551 278",
    "sg:postcode":"7983 KP",
    "sg:province":"Drenthe",
    "sg:website":"http://www.wapserherberg.nl",
    "wof:name":"Wapser Herberg, De",
    "wof:placetype":"venue"
},
  "geometry": {"coordinates":[6.25478,52.855267],"type":"Point"}
}