{
  "type": "Feature",
  "properties": {
    "addr:full":"Rynstr 8 S Gravenhage Zuid-Holland 2515 XP",
    "addr:housenumber":"8 s",
    "addr:postcode":"2515 xp",
    "addr:street":"Rynstr",
    "iso:country":"NL",
    "sg:address":"Rynstr 8",
    "sg:city":"S Gravenhage",
    "sg:orig_category":"Ministeries En Overheidsinstellingen",
    "sg:phone":"+31 70 339 3939",
    "sg:postcode":"2515 XP",
    "sg:province":"Zuid-Holland",
    "sg:website":"http://www.minvrom.nl",
    "wof:name":"Ministerie Van Volkshuisvestting Ruimtelijke Ordening En Milieubeheer",
    "wof:placetype":"venue"
},
  "geometry": {"coordinates":[4.31741,52.083988],"type":"Point"}
}