{
  "type": "Feature",
  "properties": {
    "addr:full":"Koksweg 1 Koudekerke Zeeland 4371 RC",
    "addr:housenumber":"1",
    "addr:postcode":"4371 rc",
    "addr:street":"Koksweg",
    "iso:country":"NL",
    "sg:address":"Koksweg 1",
    "sg:city":"Koudekerke",
    "sg:orig_category":"Vakantiehuizen",
    "sg:phone":"+31 118 551 577",
    "sg:postcode":"4371 RC",
    "sg:province":"Zeeland",
    "wof:name":"Vakantieoord Broedershoek",
    "wof:placetype":"venue"
},
  "geometry": {"coordinates":[3.552886,51.476002],"type":"Point"}
}