{
  "type": "Feature",
  "properties": {
    "addr:full":"Praagsngl 484 Ysselstein Ut Utrecht 3404 VL",
    "addr:housenumber":"484",
    "addr:postcode":"3404 vl",
    "addr:street":"Ysselstein",
    "iso:country":"NL",
    "sg:address":"Praagsngl 484",
    "sg:city":"Ysselstein Ut",
    "sg:orig_category":"Adviesbureaus Bedrijfsorganisatie",
    "sg:phone":"+31 30 687 8338",
    "sg:postcode":"3404 VL",
    "sg:province":"Utrecht",
    "wof:name":"Ls",
    "wof:placetype":"venue"
},
  "geometry": {"coordinates":[5.04104,52.009521],"type":"Point"}
}