{
  "type": "Feature",
  "properties": {
    "addr:full":"Middelburgsestraat 53 Koudekerke Zeeland 4371 ER",
    "addr:housenumber":"53",
    "addr:postcode":"4371 er",
    "addr:street":"Middelburgsestraat",
    "iso:country":"NL",
    "sg:address":"Middelburgsestraat 53",
    "sg:city":"Koudekerke",
    "sg:orig_category":"Benzinestations And Brandstoffen",
    "sg:phone":"+31 118 556 060",
    "sg:postcode":"4371 ER",
    "sg:province":"Zeeland",
    "wof:name":"Shell",
    "wof:placetype":"venue"
},
  "geometry": {"coordinates":[3.557439,51.483349],"type":"Point"}
}