{
  "type": "Feature",
  "properties": {
    "iso:country":"NL",
    "sg:address":"Molenaar 1",
    "sg:city":"Oud Beijerland",
    "sg:orig_category":"Bejaardeninstellingen And Serviceflats",
    "sg:phone":"+31 186 618 744",
    "sg:postcode":"3262 DE",
    "sg:province":"Zuid-Holland",
    "wof:name":"Algemeen Woonzorg En Dienstencentrum De Open Waard",
    "wof:placetype":"venue"
},
  "geometry": {"coordinates":[4.396672,51.82254],"type":"Point"}
}