{
  "type": "Feature",
  "properties": {
    "iso:country":"NL",
    "sg:address":"Sprendlingenstr 53",
    "sg:city":"Oisterwyk",
    "sg:orig_category":"Keukens",
    "sg:phone":"+31 13 521 9010",
    "sg:postcode":"5061 KM",
    "sg:province":"Noord-Brabant",
    "wof:name":"Keuken Partners Bv",
    "wof:placetype":"venue"
},
  "geometry": {"coordinates":[5.198917,51.586746],"type":"Point"}
}