{
  "type": "Feature",
  "properties": {
    "iso:country":"NL",
    "sg:address":"Schaverystr 8",
    "sg:city":"Utrecht",
    "sg:orig_category":"Projectinrichting",
    "sg:phone":"+31 30 244 2236",
    "sg:postcode":"3534 AS",
    "sg:province":"Utrecht",
    "wof:name":"Solvation",
    "wof:placetype":"venue"
},
  "geometry": {"coordinates":[5.081217,52.10638],"type":"Point"}
}