{
  "type": "Feature",
  "properties": {
    "addr:full":"Zwaagdijk 424 Zwaagdijk Noord-Holland 1686 PJ",
    "addr:housenumber":"424",
    "addr:postcode":"1686 pj",
    "addr:street":"Zwaagdijk",
    "iso:country":"NL",
    "sg:address":"Zwaagdijk 424",
    "sg:city":"Zwaagdijk",
    "sg:orig_category":"Loodgieterswerk, Verwarming And Sanitaire Installaties",
    "sg:phone":"+31 229 572 495",
    "sg:postcode":"1686 PJ",
    "sg:province":"Noord-Holland",
    "wof:name":"Van Nuland",
    "wof:placetype":"venue"
},
  "geometry": {"coordinates":[5.13598,52.705639],"type":"Point"}
}