{
  "type": "Feature",
  "properties": {
    "addr:full":"De Ruiser 12 Biggekerke Zeeland 4373 RT",
    "addr:housenumber":"12",
    "addr:postcode":"4373 rt",
    "addr:street":"De Ruiser",
    "iso:country":"NL",
    "sg:address":"De Ruiser 12",
    "sg:city":"Biggekerke",
    "sg:orig_category":"Bedrijfsorganisaties",
    "sg:phone":"+31 118 562 215",
    "sg:postcode":"4373 RT",
    "sg:province":"Zeeland",
    "wof:name":"Reinhoudt Bv",
    "wof:placetype":"venue"
},
  "geometry": {"coordinates":[3.505061,51.493816],"type":"Point"}
}