{
  "type": "Feature",
  "properties": {
    "addr:full":"Prinsenstraat 19 Amsterdam North Holland 1015 DB",
    "addr:housenumber":"19",
    "addr:postcode":"1015 db",
    "addr:street":"Prinsenstraat",
    "iso:country":"NL",
    "sg:address":"Prinsenstraat 19",
    "sg:city":"Amsterdam",
    "sg:orig_category":"Bloemen And Planten",
    "sg:phone":"+31 20 622 3585",
    "sg:postcode":"1015 DB",
    "sg:province":"North Holland",
    "wof:name":"Rosa Rosa Bloemiste",
    "wof:placetype":"venue"
},
  "geometry": {"coordinates":[4.886791,52.377739],"type":"Point"}
}