{
  "type": "Feature",
  "properties": {
    "iso:country":"NL",
    "sg:address":"Zuidkade 110",
    "sg:city":"Waddinxveen",
    "sg:orig_category":"Architecten",
    "sg:phone":"+31 182 635 216",
    "sg:postcode":"2741 JG",
    "sg:province":"South Holland",
    "wof:name":"Veringmeier Verkeersmanagement",
    "wof:placetype":"venue"
},
  "geometry": {"coordinates":[4.658131,52.034489],"type":"Point"}
}