{
  "type": "Feature",
  "properties": {
    "addr:full":"Zuidkade 110 Waddinxveen South Holland 2741 JG",
    "addr:housenumber":"110",
    "addr:postcode":"2741 jg",
    "addr:street":"Zuidkade",
    "iso:country":"NL",
    "sg:address":"Zuidkade 110",
    "sg:city":"Waddinxveen",
    "sg:orig_category":"Architecten",
    "sg:phone":"+31 182 635 216",
    "sg:postcode":"2741 JG",
    "sg:province":"South Holland",
    "wof:name":"Veringmeier Verkeersmanagement",
    "wof:placetype":"venue"
},
  "geometry": {"coordinates":[4.658131,52.034489],"type":"Point"}
}