{
  "type": "Feature",
  "properties": {
    "addr:full":"S Heerenhoeksedk 22 S Heerenhoek Zeeland 4453 RB",
    "addr:housenumber":"22",
    "addr:postcode":"4453 rb",
    "addr:street":"S Heerenhoek Zeeland",
    "iso:country":"NL",
    "sg:address":"S Heerenhoeksedk 22",
    "sg:city":"S Heerenhoek",
    "sg:orig_category":"Keukens",
    "sg:phone":"+31 113 352 669",
    "sg:postcode":"4453 RB",
    "sg:province":"Zeeland",
    "wof:name":"Voet, Kees",
    "wof:placetype":"venue"
},
  "geometry": {"coordinates":[3.7679,51.447819],"type":"Point"}
}