{
  "type": "Feature",
  "properties": {
    "addr:full":"Kuinderbos 26 Hoofddorp Noord-Holland 2134 KP",
    "addr:housenumber":"26",
    "addr:postcode":"2134 kp",
    "addr:street":"Kuinderbos",
    "iso:country":"NL",
    "sg:address":"Kuinderbos 26",
    "sg:city":"Hoofddorp",
    "sg:orig_category":"Goederenvervoer Over De Weg",
    "sg:phone":"+31 23 563 8737",
    "sg:postcode":"2134 KP",
    "sg:province":"Noord-Holland",
    "wof:name":"Kamerman",
    "wof:placetype":"venue"
},
  "geometry": {"coordinates":[4.653893,52.309074],"type":"Point"}
}