{
  "type": "Feature",
  "properties": {
    "iso:country":"NL",
    "sg:address":"Hoofdstraat Oost 16",
    "sg:city":"Noordwolde Fr",
    "sg:orig_category":"Schilderwerk",
    "sg:phone":"+31 561 432 080",
    "sg:postcode":"8391 AV",
    "sg:province":"Friesland",
    "wof:name":"Vof Van Veen Schildersbedrijf",
    "wof:placetype":"venue"
},
  "geometry": {"coordinates":[6.14179,52.891121],"type":"Point"}
}