{
  "type": "Feature",
  "properties": {
    "addr:full":"Laanstr 105 Baarn Utrecht 3743 BD",
    "addr:housenumber":"105",
    "addr:postcode":"3743 bd",
    "iso:country":"NL",
    "sg:address":"Laanstr 105",
    "sg:city":"Baarn",
    "sg:orig_category":"Bloemen En Planten",
    "sg:phone":"+31 35 541 2673",
    "sg:postcode":"3743 BD",
    "sg:province":"Utrecht",
    "wof:name":"Mengerij, De",
    "wof:placetype":"venue"
},
  "geometry": {"coordinates":[5.284427,52.212147],"type":"Point"}
}