{
  "type": "Feature",
  "properties": {
    "addr:full":"Liendertseweg 49 Amersfoort Utrecht 3814 PJ",
    "addr:housenumber":"49",
    "addr:postcode":"3814 pj",
    "addr:street":"Liendertseweg",
    "iso:country":"NL",
    "sg:address":"Liendertseweg 49",
    "sg:city":"Amersfoort",
    "sg:orig_category":"Meubelreparatie And -Restauratie",
    "sg:phone":"+31 33 479 9777",
    "sg:postcode":"3814 PJ",
    "sg:province":"Utrecht",
    "wof:name":"Van Hamersveld Meubelstoffeerderij",
    "wof:placetype":"venue"
},
  "geometry": {"coordinates":[5.397471,52.163605],"type":"Point"}
}