{
  "type": "Feature",
  "properties": {
    "addr:full":"Homerusln 66 Utrecht Utrecht 3581 MJ",
    "addr:housenumber":"66",
    "addr:postcode":"3581 mj",
    "addr:street":"Homerusln",
    "iso:country":"NL",
    "sg:address":"Homerusln 66",
    "sg:city":"Utrecht",
    "sg:orig_category":"Artsen - Huisartsen",
    "sg:phone":"+31 30 251 3007",
    "sg:postcode":"3581 MJ",
    "sg:province":"Utrecht",
    "wof:name":"Muller, J L H W",
    "wof:placetype":"venue"
},
  "geometry": {"coordinates":[5.13447,52.089989],"type":"Point"}
}