{
  "type": "Feature",
  "properties": {
    "addr:full":"Zambiastr 32 Delft South Holland 2622 DG",
    "addr:housenumber":"32",
    "addr:postcode":"2622 dg",
    "addr:street":"Zambiastr",
    "iso:country":"NL",
    "sg:address":"Zambiastr 32",
    "sg:city":"Delft",
    "sg:orig_category":"Metselwerken",
    "sg:phone":"+31 15 261 2545",
    "sg:postcode":"2622 DG",
    "sg:province":"South Holland",
    "wof:name":"Kdk Bv",
    "wof:placetype":"venue"
},
  "geometry": {"coordinates":[4.339471,51.982094],"type":"Point"}
}