{
  "type": "Feature",
  "properties": {
    "addr:full":"Vd Aastr 6 S Gravenhage Zuid-Holland 2597 SL",
    "addr:housenumber":"6;gravenhage",
    "addr:postcode":"2597 sl",
    "addr:street":"S",
    "iso:country":"NL",
    "sg:address":"Vd Aastr 6",
    "sg:city":"S Gravenhage",
    "sg:orig_category":"Adviesbureaus",
    "sg:phone":"+31 70 324 8582",
    "sg:postcode":"2597 SL",
    "sg:province":"Zuid-Holland",
    "wof:name":"Remas Services",
    "wof:placetype":"venue"
},
  "geometry": {"coordinates":[4.31817,52.11031],"type":"Point"}
}