{
  "type": "Feature",
  "properties": {
    "addr:full":"Bovenstewg 69 Mook Limburg 6585 KB",
    "addr:housenumber":"69",
    "addr:postcode":"6585 kb",
    "addr:street":"Bovenstewg",
    "iso:country":"NL",
    "sg:address":"Bovenstewg 69",
    "sg:city":"Mook",
    "sg:orig_category":"Vetsmelterijen",
    "sg:phone":"+31 24 696 2393",
    "sg:postcode":"6585 KB",
    "sg:province":"Limburg",
    "wof:name":"Voogt Bv, J J J",
    "wof:placetype":"venue"
},
  "geometry": {"coordinates":[5.878289,51.759682],"type":"Point"}
}