{
  "type": "Feature",
  "properties": {
    "iso:country":"NL",
    "sg:address":"Gravensteinstr 30",
    "sg:city":"Bunde",
    "sg:orig_category":"Adviesbureaus Bedrijfsorganisatie",
    "sg:phone":"+31 43 365 2035",
    "sg:postcode":"6241 JJ",
    "sg:province":"Limburg",
    "wof:name":"Sillevis, Karin",
    "wof:placetype":"venue"
},
  "geometry": {"coordinates":[5.723481,50.895172],"type":"Point"}
}