{
  "type": "Feature",
  "properties": {
    "addr:full":"Strikkd 22 Berkel En Rodenrys Zuid-Holland 2651 KX",
    "addr:housenumber":"22",
    "addr:postcode":"2651 kx",
    "addr:street":"Strikkd;Berkel",
    "iso:country":"NL",
    "sg:address":"Strikkd 22",
    "sg:city":"Berkel En Rodenrys",
    "sg:orig_category":"Bloemen En Planten - Veilingen",
    "sg:phone":"+31 15 361 1080",
    "sg:postcode":"2651 KX",
    "sg:province":"Zuid-Holland",
    "wof:name":"Bekkers-Westerman, Fa",
    "wof:placetype":"venue"
},
  "geometry": {"coordinates":[4.478555,51.992535],"type":"Point"}
}