{
  "type": "Feature",
  "properties": {
    "iso:country":"NL",
    "sg:address":"Dobbe 24",
    "sg:city":"Zwolle",
    "sg:orig_category":"Postkantoren",
    "sg:phone":"+31 38 452 6616",
    "sg:postcode":"8032 JW",
    "sg:province":"NL.08",
    "sg:website":"http://www.postkantoor.nl",
    "wof:name":"Postkantoor",
    "wof:placetype":"venue"
},
  "geometry": {"coordinates":[6.101465,52.529377],"type":"Point"}
}