{
  "type": "Feature",
  "properties": {
    "iso:country":"NL",
    "sg:address":"Meridiaan 18B",
    "sg:city":"Amersfoort",
    "sg:orig_category":"Psychotherapeuten",
    "sg:phone":"+31 33 472 3989",
    "sg:postcode":"3813 AV",
    "sg:province":"Utrecht",
    "wof:name":"Beeldende Therapie & Expressie, Praktijk Voor",
    "wof:placetype":"venue"
},
  "geometry": {"coordinates":[5.385834,52.164436],"type":"Point"}
}