{
  "type": "Feature",
  "properties": {
    "addr:full":"Edisonstraat 170 'S Gravenhage Zuid-Holland 2561 BL",
    "addr:housenumber":"170 ';2561",
    "addr:postcode":"bl",
    "addr:street":"Edisonstraat",
    "iso:country":"NL",
    "sg:address":"Edisonstraat 170",
    "sg:city":"'S Gravenhage",
    "sg:orig_category":"Metaalwerken",
    "sg:phone":"+31 70 363 6000",
    "sg:postcode":"2561 BL",
    "sg:province":"Zuid-Holland",
    "wof:name":"Carpet Land",
    "wof:placetype":"venue"
},
  "geometry": {"coordinates":[4.272174,52.076324],"type":"Point"}
}