{
  "type": "Feature",
  "properties": {
    "addr:full":"Winkelhof 77 Leiderdorp Zuid-Holland 2353 TV",
    "addr:housenumber":"77",
    "addr:postcode":"2353 tv",
    "addr:street":"Winkelhof",
    "iso:country":"NL",
    "sg:address":"Winkelhof 77",
    "sg:city":"Leiderdorp",
    "sg:orig_category":"Nagelstudio'S",
    "sg:phone":"+31 71 515 2848",
    "sg:postcode":"2353 TV",
    "sg:province":"Zuid-Holland",
    "wof:name":"Best Image, The Nails & Beauty",
    "wof:placetype":"venue"
},
  "geometry": {"coordinates":[4.531699,52.162483],"type":"Point"}
}