{
  "type": "Feature",
  "properties": {
    "addr:full":"Gooimeer 3-20 Naarden Noord-Holland 1411 DC",
    "addr:housenumber":"3-20",
    "addr:postcode":"1411",
    "addr:street":"Gooimeer",
    "iso:country":"NL",
    "sg:address":"Gooimeer 3-20",
    "sg:city":"Naarden",
    "sg:orig_category":"Verenigingen En Stichtingen",
    "sg:phone":"+31 35 694 3150",
    "sg:postcode":"1411 DC",
    "sg:province":"Noord-Holland",
    "wof:name":"Nvva",
    "wof:placetype":"venue"
},
  "geometry": {"coordinates":[5.140359,52.307507],"type":"Point"}
}