{
  "type": "Feature",
  "properties": {
    "addr:full":"Waalstoep 3 Rossum Gld Gelderland 5328 CA",
    "addr:housenumber":"3",
    "addr:postcode":"5328 ca",
    "addr:street":"Waalstoep;Gld Gelderland",
    "iso:country":"NL",
    "sg:address":"Waalstoep 3",
    "sg:city":"Rossum Gld",
    "sg:orig_category":"Keukens",
    "sg:phone":"+31 418 663 445",
    "sg:postcode":"5328 CA",
    "sg:province":"Gelderland",
    "wof:name":"Kaaij, Van Der",
    "wof:placetype":"venue"
},
  "geometry": {"coordinates":[5.337022,51.803635],"type":"Point"}
}