{
  "type": "Feature",
  "properties": {
    "addr:full":"Ecustr 9 Etten Leur North Brabant 4879 NP",
    "addr:housenumber":"9",
    "addr:postcode":"4879 np",
    "addr:street":"Ecustr",
    "iso:country":"NL",
    "sg:address":"Ecustr 9",
    "sg:city":"Etten Leur",
    "sg:orig_category":"Kantoor- En Bedrijfsmeubelen",
    "sg:phone":"+31 76 503 3330",
    "sg:postcode":"4879 NP",
    "sg:province":"North Brabant",
    "sg:website":"http://www.roantex.nl",
    "wof:name":"Roantex Bv",
    "wof:placetype":"venue"
},
  "geometry": {"coordinates":[4.6107487679,51.557434082],"type":"Point"}
}