{
  "type": "Feature",
  "properties": {
    "addr:full":"Grevekeur 20 Schijndel Noord-Brabant 5481 MD",
    "addr:housenumber":"20",
    "addr:postcode":"5481",
    "addr:street":"Grevekeur",
    "iso:country":"NL",
    "sg:address":"Grevekeur 20",
    "sg:city":"Schijndel",
    "sg:orig_category":"Diverse Grafische Activiteiten",
    "sg:phone":"+31 73 547 9112",
    "sg:postcode":"5481 MD",
    "sg:province":"Noord-Brabant",
    "wof:name":"Liseth",
    "wof:placetype":"venue"
},
  "geometry": {"coordinates":[-75.923759,38.823399],"type":"Point"}
}