{
  "type": "Feature",
  "properties": {
    "addr:full":"Overflakkee 37 Emmeloord Flevoland 8302 NZ",
    "addr:housenumber":"37",
    "addr:postcode":"8302 nz",
    "addr:street":"Overflakkee;Flevoland",
    "iso:country":"NL",
    "sg:address":"Overflakkee 37",
    "sg:city":"Emmeloord",
    "sg:orig_category":"Waterbehandeling En Waterzuiverings- Systemen",
    "sg:phone":"+31 527 699 533",
    "sg:postcode":"8302 NZ",
    "sg:province":"Flevoland",
    "wof:name":"Waterservice Ned",
    "wof:placetype":"venue"
},
  "geometry": {"coordinates":[5.7218270302,52.7220954895],"type":"Point"}
}