{
  "type": "Feature",
  "properties": {
    "addr:full":"Hongkongstraat 9 Rotterdam Zuid-Holland 3047 BR",
    "addr:housenumber":"9",
    "addr:postcode":"3047 br",
    "addr:street":"Hongkongstraat",
    "iso:country":"NL",
    "sg:address":"Hongkongstraat 9",
    "sg:city":"Rotterdam",
    "sg:orig_category":"Goederenvervoer Over De Weg",
    "sg:phone":"+31 10 262 1844",
    "sg:postcode":"3047 BR",
    "sg:province":"Zuid-Holland",
    "wof:name":"Transportbedrijf P.J. Van Der Gaag En Zonen Bv",
    "wof:placetype":"venue"
},
  "geometry": {"coordinates":[4.407471,51.943623],"type":"Point"}
}