{
  "type": "Feature",
  "properties": {
    "addr:full":"Albrechtln 3 Bussum Noord-Holland 1404 AH",
    "addr:housenumber":"3",
    "addr:postcode":"1404 ah",
    "addr:street":"Albrechtln",
    "iso:country":"NL",
    "sg:address":"Albrechtln 3",
    "sg:city":"Bussum",
    "sg:orig_category":"Marktonderzoekbureaus",
    "sg:phone":"+31 35 694 1199",
    "sg:postcode":"1404 AH",
    "sg:province":"Noord-Holland",
    "wof:name":"Jan Schipper",
    "wof:placetype":"venue"
},
  "geometry": {"coordinates":[5.158534,52.279736],"type":"Point"}
}