{
  "type": "Feature",
  "properties": {
    "iso:country":"NL",
    "sg:address":"Flevoln 58",
    "sg:city":"Weesp",
    "sg:orig_category":"Kantoor- En Secretariaatsservice",
    "sg:phone":"+31 294 450 862",
    "sg:postcode":"1382 JZ",
    "sg:province":"Noord-Holland",
    "wof:name":"Topspin",
    "wof:placetype":"venue"
},
  "geometry": {"coordinates":[5.0382800102,52.3083152771],"type":"Point"}
}