{
  "type": "Feature",
  "properties": {
    "addr:full":"Hoogstraat 11 Swalmen Limburg 6071 JM",
    "addr:housenumber":"11",
    "addr:postcode":"6071 jm",
    "addr:street":"Hoogstraat",
    "iso:country":"NL",
    "sg:address":"Hoogstraat 11",
    "sg:city":"Swalmen",
    "sg:orig_category":"Boekhandels",
    "sg:phone":"+31 475 501 485",
    "sg:postcode":"6071 JM",
    "sg:province":"Limburg",
    "wof:name":"Sbk Kantoor",
    "wof:placetype":"venue"
},
  "geometry": {"coordinates":[6.035446,51.232796],"type":"Point"}
}