{
  "type": "Feature",
  "properties": {
    "addr:full":"Pigmentsngl 4 Zoetermeer Zuid-Holland 2718 AJ",
    "addr:housenumber":"4",
    "addr:postcode":"2718 aj",
    "addr:street":"Pigmentsngl",
    "iso:country":"NL",
    "sg:address":"Pigmentsngl 4",
    "sg:city":"Zoetermeer",
    "sg:orig_category":"Kantoor- En Secretariaatsservice",
    "sg:phone":"+31 79 342 8409",
    "sg:postcode":"2718 AJ",
    "sg:province":"Zuid-Holland",
    "wof:name":"Mboz Secretariaatsbeheer",
    "wof:placetype":"venue"
},
  "geometry": {"coordinates":[4.4824352264,52.0410804749],"type":"Point"}
}