{
  "type": "Feature",
  "properties": {
    "addr:full":"Schoolstr 50D Moergestel Noord-Brabant 5066 EE",
    "addr:housenumber":"50d",
    "addr:postcode":"5066 ee",
    "addr:street":"Schoolstr",
    "iso:country":"NL",
    "sg:address":"Schoolstr 50D",
    "sg:city":"Moergestel",
    "sg:orig_category":"Onderhoudswerken",
    "sg:phone":"+31 13 513 4006",
    "sg:postcode":"5066 EE",
    "sg:province":"Noord-Brabant",
    "sg:website":"http://www.bert-janevers.nl",
    "wof:name":"Bert-Jan Evers, Onderhoud",
    "wof:placetype":"venue"
},
  "geometry": {"coordinates":[5.183641,51.545498],"type":"Point"}
}