{
  "type": "Feature",
  "properties": {
    "addr:full":"Grazendonkstraat 13 Breda Noord-Brabant 4818 PH",
    "addr:housenumber":"13",
    "addr:postcode":"4818",
    "addr:street":"Grazendonkstraat",
    "iso:country":"NL",
    "sg:address":"Grazendonkstraat 13",
    "sg:city":"Breda",
    "sg:classifiers":[
        {
            "category":"Fast Food",
            "type":"Food & Drink"
        }
    ],
    "sg:phone":"+31 76 520 1926",
    "sg:postcode":"4818 PH",
    "sg:province":"Noord-Brabant",
    "sg:tags":[
        "afhaal",
        "restaurant"
    ],
    "wof:name":"Cafetaria 'T Leike",
    "wof:placetype":"venue"
},
  "geometry": {"coordinates":[4.778565,51.574348],"type":"Point"}
}