{
  "type": "Feature",
  "properties": {
    "addr:full":"Grutstraat 21 Doetinchem Gelderland 7001 BW",
    "addr:housenumber":"21",
    "addr:postcode":"7001 bw",
    "addr:street":"Grutstraat;Gelderland",
    "iso:country":"NL",
    "sg:address":"Grutstraat 21",
    "sg:city":"Doetinchem",
    "sg:orig_category":"Partycatering And -Organisatie",
    "sg:phone":"+31 314 365 696",
    "sg:postcode":"7001 BW",
    "sg:province":"Gelderland",
    "wof:name":"Nemrut Turks Restaurant",
    "wof:placetype":"venue"
},
  "geometry": {"coordinates":[6.287667,51.966206],"type":"Point"}
}