{
  "type": "Feature",
  "properties": {
    "iso:country":"NL",
    "sg:address":"Bottelaarpassage 69",
    "sg:city":"Almere",
    "sg:classifiers":[
        {
            "category":"Shopping",
            "subcategory":"Clothing, Apparel, & Fashions",
            "type":"Retail Goods"
        }
    ],
    "sg:phone":"+31 36 534 3566",
    "sg:postcode":"1315 EP",
    "sg:province":"NL.",
    "sg:tags":[
        "ondergoed",
        "lingerie"
    ],
    "wof:name":"Livera Last Lingerie",
    "wof:placetype":"venue"
},
  "geometry": {"coordinates":[5.215239,52.370598],"type":"Point"}
}