{
  "type": "Feature",
  "properties": {
    "addr:full":"Sleutelbloemdreef 6 Herkenbosch Limburg 6075 DJ",
    "addr:housenumber":"6",
    "addr:postcode":"6075 dj",
    "addr:street":"Sleutelbloemdreef",
    "iso:country":"NL",
    "sg:address":"Sleutelbloemdreef 6",
    "sg:city":"Herkenbosch",
    "sg:orig_category":"Verhuur Bouwmachines",
    "sg:phone":"+31 475 533 282",
    "sg:postcode":"6075 DJ",
    "sg:province":"Limburg",
    "wof:name":"M Schmidt",
    "wof:placetype":"venue"
},
  "geometry": {"coordinates":[6.067188,51.15213],"type":"Point"}
}