{
  "type": "Feature",
  "properties": {
    "iso:country":"NL",
    "sg:address":"Kamperzeedijk 145",
    "sg:city":"Genemuiden",
    "sg:orig_category":"Goederenvervoer Over De Weg",
    "sg:phone":"+31 38 344 6126",
    "sg:postcode":"8281 PE",
    "sg:province":"NL.08",
    "wof:name":"Van Der Roest & Zn",
    "wof:placetype":"venue"
},
  "geometry": {"coordinates":[6.021616,52.606598],"type":"Point"}
}