{
  "type": "Feature",
  "properties": {
    "addr:full":"Ordenpl 22 Apeldoorn Gelderland 7312 NL",
    "addr:housenumber":"22",
    "addr:postcode":"7312",
    "addr:street":"Ordenpl;Gelderland",
    "iso:country":"NL",
    "sg:address":"Ordenpl 22",
    "sg:city":"Apeldoorn",
    "sg:orig_category":"Bloemen En Planten",
    "sg:phone":"+31 55 355 1375",
    "sg:postcode":"7312 NL",
    "sg:province":"Gelderland",
    "wof:name":"Fresia Vof",
    "wof:placetype":"venue"
},
  "geometry": {"coordinates":[5.931896,52.201084],"type":"Point"}
}