{
  "type": "Feature",
  "properties": {
    "addr:full":"Paganinilaan 31 Assen Drenthe 9402 VH",
    "addr:housenumber":"31",
    "addr:postcode":"9402 vh",
    "addr:street":"Paganinilaan",
    "iso:country":"NL",
    "sg:address":"Paganinilaan 31",
    "sg:city":"Assen",
    "sg:classifiers":[
        {
            "category":"Fast Food",
            "type":"Food & Drink"
        }
    ],
    "sg:phone":"+31 592 372 832",
    "sg:postcode":"9402 VH",
    "sg:province":"Drenthe",
    "sg:tags":[
        "afhaal",
        "restaurant"
    ],
    "wof:name":"Snackbar Annie",
    "wof:placetype":"venue"
},
  "geometry": {"coordinates":[6.563967,53.009888],"type":"Point"}
}