{
  "type": "Feature",
  "properties": {
    "addr:full":"Heinsbergerwg 32 Posterholt Limburg 6061 AJ",
    "addr:housenumber":"32",
    "addr:postcode":"6061 aj",
    "addr:street":"Heinsbergerwg",
    "iso:country":"NL",
    "sg:address":"Heinsbergerwg 32",
    "sg:city":"Posterholt",
    "sg:orig_category":"Etalageverzorging",
    "sg:phone":"+31 475 375 145",
    "sg:postcode":"6061 AJ",
    "sg:province":"Limburg",
    "wof:name":"Ververgaert",
    "wof:placetype":"venue"
},
  "geometry": {"coordinates":[6.038655,51.116085],"type":"Point"}
}