{
  "type": "Feature",
  "properties": {
    "addr:full":"Zuiderpoort 23 Lelystad Flevoland 8239 AB",
    "addr:housenumber":"23",
    "addr:postcode":"8239 ab",
    "addr:street":"Zuiderpoort;Flevoland",
    "iso:country":"NL",
    "sg:address":"Zuiderpoort 23",
    "sg:city":"Lelystad",
    "sg:orig_category":"Keukens",
    "sg:phone":"+31 320 268 188",
    "sg:postcode":"8239 AB",
    "sg:province":"Flevoland",
    "sg:website":"http://www.grando.nl",
    "wof:name":"Grando",
    "wof:placetype":"venue"
},
  "geometry": {"coordinates":[5.484137,52.49136],"type":"Point"}
}