{
  "type": "Feature",
  "properties": {
    "addr:full":"Krabbenboswg 90 Hengelo Ov NL.08 7555 EM",
    "addr:housenumber":"90",
    "addr:postcode":"7555 em",
    "addr:street":"Krabbenboswg;Ov",
    "iso:country":"NL",
    "sg:address":"Krabbenboswg 90",
    "sg:city":"Hengelo Ov",
    "sg:orig_category":"Verenigingen En Stichtingen",
    "sg:phone":"+31 74 250 5038",
    "sg:postcode":"7555 EM",
    "sg:province":"NL.08",
    "wof:name":"Humanitas Onder Dak Twente, Sticht",
    "wof:placetype":"venue"
},
  "geometry": {"coordinates":[6.775114,52.26067],"type":"Point"}
}