{
  "type": "Feature",
  "properties": {
    "addr:full":"Zaailand 161 Leeuwarden Friesland 8911 BL",
    "addr:housenumber":"161",
    "addr:postcode":"8911 bl",
    "addr:street":"Zaailand",
    "iso:country":"NL",
    "sg:address":"Zaailand 161",
    "sg:city":"Leeuwarden",
    "sg:orig_category":"Kappers",
    "sg:phone":"+31 58 213 7020",
    "sg:postcode":"8911 BL",
    "sg:province":"Friesland",
    "wof:name":"La Vie",
    "wof:placetype":"venue"
},
  "geometry": {"coordinates":[5.795158,53.199333],"type":"Point"}
}