{
  "type": "Feature",
  "properties": {
    "addr:full":"J Provostln 91 Bilthoven Utrecht 3723 RP",
    "addr:housenumber":"91",
    "addr:postcode":"3723 rp",
    "iso:country":"NL",
    "sg:address":"J Provostln 91",
    "sg:city":"Bilthoven",
    "sg:orig_category":"Verloskundigen",
    "sg:phone":"+31 30 238 3400",
    "sg:postcode":"3723 RP",
    "sg:province":"Utrecht",
    "wof:name":"Praktijk Voor Verloskunde",
    "wof:placetype":"venue"
},
  "geometry": {"coordinates":[5.195765,52.131367],"type":"Point"}
}