{
  "type": "Feature",
  "properties": {
    "addr:full":"Creekpad 25 Vierpolders Zuid-Holland 3237 AH",
    "addr:housenumber":"25",
    "addr:postcode":"3237 ah",
    "addr:street":"Creekpad",
    "iso:country":"NL",
    "sg:address":"Creekpad 25",
    "sg:city":"Vierpolders",
    "sg:orig_category":"Goederenvervoer Over De Weg",
    "sg:phone":"+31 181 417 733",
    "sg:postcode":"3237 AH",
    "sg:province":"Zuid-Holland",
    "wof:name":"R H G Sneltransport Vof",
    "wof:placetype":"venue"
},
  "geometry": {"coordinates":[4.177201,51.879032],"type":"Point"}
}