{
  "type": "Feature",
  "properties": {
    "addr:full":"Meester Lovinklaan 13 Doetinchem Gelderland 7004 BG",
    "addr:housenumber":"13",
    "addr:postcode":"7004",
    "addr:street":"Meester Lovinklaan;Gelderland",
    "iso:country":"NL",
    "sg:address":"Meester Lovinklaan 13",
    "sg:city":"Doetinchem",
    "sg:orig_category":"Gespecialiseerde Bouw",
    "sg:phone":"+31 314 325 143",
    "sg:postcode":"7004 BG",
    "sg:province":"Gelderland",
    "wof:name":"Betonboorbedrijf Arentsen Doetinchem (B.A.D.)",
    "wof:placetype":"venue"
},
  "geometry": {"coordinates":[6.306291,51.952984],"type":"Point"}
}