{
  "type": "Feature",
  "properties": {
    "addr:full":"Kerklaan 58 Wateringen Zuid-Holland 2291 CJ",
    "addr:housenumber":"58",
    "addr:postcode":"2291 cj",
    "addr:street":"Kerklaan",
    "iso:country":"NL",
    "sg:address":"Kerklaan 58",
    "sg:city":"Wateringen",
    "sg:orig_category":"Loodgieterswerk, Verwarming And Sanitaire Installaties",
    "sg:phone":"+31 174 296 868",
    "sg:postcode":"2291 CJ",
    "sg:province":"Zuid-Holland",
    "wof:name":"Loodgietersbedrijf P.J. Boes Bv",
    "wof:placetype":"venue"
},
  "geometry": {"coordinates":[4.270585,52.028797],"type":"Point"}
}