{
  "type": "Feature",
  "properties": {
    "addr:full":"Apeldoornseln 2 , (Ook Ing De La Reywg) S Gravenhage Zuid-Holland 2573 LM",
    "addr:housenumber":"2",
    "addr:postcode":"2573 lm",
    "addr:street":"Apeldoornseln",
    "iso:country":"NL",
    "sg:address":"Apeldoornseln 2 , (Ook Ing De La Reywg)",
    "sg:city":"S Gravenhage",
    "sg:orig_category":"Boeken En Tijdschriften",
    "sg:phone":"+31 70 346 9729",
    "sg:postcode":"2573 LM",
    "sg:province":"Zuid-Holland",
    "wof:name":"Bijbelhuis, Chr Boekhandel Het",
    "wof:placetype":"venue"
},
  "geometry": {"coordinates":[4.2844,52.064911],"type":"Point"}
}