{
  "type": "Feature",
  "properties": {
    "addr:full":"Pieterstr 29A Geleen Limburg 6166 AN",
    "addr:housenumber":"29a",
    "addr:postcode":"6166 an",
    "addr:street":"Pieterstr",
    "iso:country":"NL",
    "sg:address":"Pieterstr 29A",
    "sg:city":"Geleen",
    "sg:orig_category":"Schilders",
    "sg:phone":"+31 46 474 2928",
    "sg:postcode":"6166 AN",
    "sg:province":"Limburg",
    "wof:name":"Geurts & Zn, L J",
    "wof:placetype":"venue"
},
  "geometry": {"coordinates":[5.840788,50.969563],"type":"Point"}
}