{
  "type": "Feature",
  "properties": {
    "addr:full":"Meeuwenln 112-114 Amsterdam Noord-Holland 1021 JM",
    "addr:housenumber":"112-114",
    "addr:postcode":"1021 jm",
    "iso:country":"NL",
    "sg:address":"Meeuwenln 112-114",
    "sg:city":"Amsterdam",
    "sg:classifiers":[
        {
            "category":"Retail",
            "subcategory":"Auto Repair",
            "type":"Services"
        }
    ],
    "sg:phone":"+31 20 632 9926",
    "sg:postcode":"1021 JM",
    "sg:province":"Noord-Holland",
    "sg:tags":[
        "garage"
    ],
    "wof:name":"Rio",
    "wof:placetype":"venue"
},
  "geometry": {"coordinates":[4.923037,52.386086],"type":"Point"}
}