{
  "type": "Feature",
  "properties": {
    "addr:full":"Riebroeksewg 9 Ermelo Gelderland 3853 PB",
    "addr:housenumber":"9",
    "addr:postcode":"3853 pb",
    "addr:street":"Riebroeksewg;Gelderland",
    "iso:country":"NL",
    "sg:address":"Riebroeksewg 9",
    "sg:city":"Ermelo",
    "sg:orig_category":"Poeliers",
    "sg:phone":"+31 341 553 273",
    "sg:postcode":"3853 PB",
    "sg:province":"Gelderland",
    "wof:name":"Brink, Poeliersbedr J H Hamstra V/D",
    "wof:placetype":"venue"
},
  "geometry": {"coordinates":[5.572233,52.294544],"type":"Point"}
}