{
  "type": "Feature",
  "properties": {
    "addr:full":"Grotestr 15 Gendringen Gelderland 7081 CA",
    "addr:housenumber":"15",
    "addr:postcode":"7081 ca",
    "addr:street":"Grotestr;Gelderland",
    "iso:country":"NL",
    "sg:address":"Grotestr 15",
    "sg:city":"Gendringen",
    "sg:orig_category":"Kappers",
    "sg:phone":"+31 315 683 333",
    "sg:postcode":"7081 CA",
    "sg:province":"Gelderland",
    "wof:name":"D?cha",
    "wof:placetype":"venue"
},
  "geometry": {"coordinates":[6.3784451485,51.8712043762],"type":"Point"}
}