{
  "type": "Feature",
  "properties": {
    "addr:full":"Scheldestraat 122 'S Gravenhage Zuid-Holland 2515 TG",
    "addr:housenumber":"122 ';2515",
    "addr:postcode":"tg",
    "addr:street":"Scheldestraat",
    "iso:country":"NL",
    "sg:address":"Scheldestraat 122",
    "sg:city":"'S Gravenhage",
    "sg:orig_category":"Kinderopvang Behalve Thuis",
    "sg:phone":"+31 70 382 0200",
    "sg:postcode":"2515 TG",
    "sg:province":"Zuid-Holland",
    "wof:name":"Merel En Merlijn Kinderopvang Dak",
    "wof:placetype":"venue"
},
  "geometry": {"coordinates":[4.326449,52.075878],"type":"Point"}
}