{
  "type": "Feature",
  "properties": {
    "addr:full":"Kerkstr 11 Makkum Fr Friesland 8754 CP",
    "addr:housenumber":"11",
    "addr:postcode":"8754 cp",
    "addr:street":"Kerkstr",
    "iso:country":"NL",
    "sg:address":"Kerkstr 11",
    "sg:city":"Makkum Fr",
    "sg:classifiers":[
        {
            "category":"Food & Beverages",
            "subcategory":"Bakery",
            "type":"Retail Goods"
        }
    ],
    "sg:phone":"+31 515 231 579",
    "sg:postcode":"8754 CP",
    "sg:province":"Friesland",
    "sg:tags":[
        "brood",
        "en",
        "banket"
    ],
    "wof:name":"Weerdt, Van Der",
    "wof:placetype":"venue"
},
  "geometry": {"coordinates":[5.402332,53.05574],"type":"Point"}
}