{
  "type": "Feature",
  "properties": {
    "addr:full":"Messiaenplnts 14 Almere Flevoland 1323 LA",
    "addr:housenumber":"14;1323",
    "addr:street":"Messiaenplnts;Flevoland",
    "iso:country":"NL",
    "sg:address":"Messiaenplnts 14",
    "sg:city":"Almere",
    "sg:orig_category":"Webdesign Bureaus",
    "sg:phone":"+31 36 529 0477",
    "sg:postcode":"1323 LA",
    "sg:province":"Flevoland",
    "sg:website":"http://www.commissio.nl",
    "wof:name":"Commissio Cv",
    "wof:placetype":"venue"
},
  "geometry": {"coordinates":[5.1939001083,52.3665885925],"type":"Point"}
}