{
  "type": "Feature",
  "properties": {
    "addr:full":"Moleneind 25 Teteringen Noord-Brabant 4847 CH",
    "addr:housenumber":"25",
    "addr:postcode":"4847",
    "addr:street":"Moleneind",
    "iso:country":"NL",
    "sg:address":"Moleneind 25",
    "sg:city":"Teteringen",
    "sg:orig_category":"Farmaceutische Producten Gh",
    "sg:phone":"+31 76 581 0357",
    "sg:postcode":"4847 CH",
    "sg:province":"Noord-Brabant",
    "wof:name":"Pharmalett International Bv",
    "wof:placetype":"venue"
},
  "geometry": {"coordinates":[4.818555,51.603676],"type":"Point"}
}