{
  "type": "Feature",
  "properties": {
    "addr:full":"Dorpsstraat 23 Ruurlo Gelderland 7261 AV",
    "addr:housenumber":"23;7261",
    "addr:postcode":"av",
    "addr:street":"Dorpsstraat;Gelderland",
    "iso:country":"NL",
    "sg:address":"Dorpsstraat 23",
    "sg:city":"Ruurlo",
    "sg:orig_category":"Huishoudapparatuur, Televisies And Radio'S",
    "sg:phone":"+31 573 451 414",
    "sg:postcode":"7261 AV",
    "sg:province":"Gelderland",
    "wof:name":"Installatiebedrijf Stegeman Bv",
    "wof:placetype":"venue"
},
  "geometry": {"coordinates":[6.449378,52.086868],"type":"Point"}
}