{
  "type": "Feature",
  "properties": {
    "addr:full":"Past J V Hovestr 44 Beesd Gelderland 4153 XV",
    "addr:housenumber":"44",
    "addr:postcode":"4153 xv",
    "addr:street":"Past J V Hovestr;Gelderland",
    "iso:country":"NL",
    "sg:address":"Past J V Hovestr 44",
    "sg:city":"Beesd",
    "sg:orig_category":"Zonnebank- En Solariumcentra",
    "sg:phone":"+31 345 682 591",
    "sg:postcode":"4153 XV",
    "sg:province":"Gelderland",
    "wof:name":"Pallandt, Elly",
    "wof:placetype":"venue"
},
  "geometry": {"coordinates":[5.194317,51.88805],"type":"Point"}
}