{
  "type": "Feature",
  "properties": {
    "addr:full":"Transportwg 4 Middelburg Zeeland 6517 50",
    "addr:housenumber":"4",
    "addr:postcode":"6517 50",
    "addr:street":"Transportwg",
    "iso:country":"NL",
    "sg:address":"Transportwg 4",
    "sg:city":"Middelburg",
    "sg:orig_category":"Beveiliging",
    "sg:phone":"+31 118 651 750",
    "sg:postcode":"6517 50",
    "sg:province":"Zeeland",
    "sg:website":"http://www.detec.nl",
    "wof:name":"Detec Beveiliging",
    "wof:placetype":"venue"
},
  "geometry": {"coordinates":[3.609615,51.495415],"type":"Point"}
}