{
  "type": "Feature",
  "properties": {
    "addr:full":"Wilhelminaln 25 Posterholt Limburg 6061 AX",
    "addr:housenumber":"25",
    "addr:postcode":"6061 ax",
    "addr:street":"Wilhelminaln",
    "iso:country":"NL",
    "sg:address":"Wilhelminaln 25",
    "sg:city":"Posterholt",
    "sg:orig_category":"Kappers",
    "sg:phone":"+31 475 402 616",
    "sg:postcode":"6061 AX",
    "sg:province":"Limburg",
    "wof:name":"Petra",
    "wof:placetype":"venue"
},
  "geometry": {"coordinates":[6.040598,51.116985],"type":"Point"}
}