{
  "type": "Feature",
  "properties": {
    "addr:full":"Kalverhof 11 Bunde Limburg 6241 CZ",
    "addr:housenumber":"11",
    "addr:postcode":"6241",
    "addr:street":"Kalverhof",
    "iso:country":"NL",
    "sg:address":"Kalverhof 11",
    "sg:city":"Bunde",
    "sg:orig_category":"Boekhouders",
    "sg:phone":"+31 43 364 1602",
    "sg:postcode":"6241 CZ",
    "sg:province":"Limburg",
    "wof:name":"Administratie/ Assurantiekantoor Robeerst",
    "wof:placetype":"venue"
},
  "geometry": {"coordinates":[5.730037,50.900063],"type":"Point"}
}