{
  "type": "Feature",
  "properties": {
    "addr:full":"Molenmakershoek 59A Apeldoorn Gelderland 7328 JK",
    "addr:housenumber":"59a",
    "addr:postcode":"7328 jk",
    "addr:street":"Molenmakershoek;Gelderland",
    "iso:country":"NL",
    "sg:address":"Molenmakershoek 59A",
    "sg:city":"Apeldoorn",
    "sg:orig_category":"Kermisexploitatie",
    "sg:phone":"+31 6 53160975",
    "sg:postcode":"7328 JK",
    "sg:province":"Gelderland",
    "wof:name":"Ordelman, A A",
    "wof:placetype":"venue"
},
  "geometry": {"coordinates":[5.984156,52.207497],"type":"Point"}
}