{
  "type": "Feature",
  "properties": {
    "addr:full":"Julianastr 59-61 Oud Beyerland South Holland 3262 SH",
    "addr:housenumber":"59-61",
    "addr:postcode":"3262 sh",
    "addr:street":"Oud Beyerland",
    "iso:country":"NL",
    "sg:address":"Julianastr 59-61",
    "sg:city":"Oud Beyerland",
    "sg:orig_category":"Bevrachting",
    "sg:phone":"+31 186 610 255",
    "sg:postcode":"3262 SH",
    "sg:province":"South Holland",
    "wof:name":"Groenendijk Bv, W",
    "wof:placetype":"venue"
},
  "geometry": {"coordinates":[4.416104,51.82346],"type":"Point"}
}