{
  "type": "Feature",
  "properties": {
    "iso:country":"NL",
    "sg:address":"Wijnhaven 17",
    "sg:city":"Rotterdam",
    "sg:orig_category":"Advocaten And Juridische Adviseurs",
    "sg:phone":"+31 10 412 3300",
    "sg:postcode":"3011 WH",
    "sg:province":"Zuid-Holland",
    "wof:name":"Advocatenkantoor Carels",
    "wof:placetype":"venue"
},
  "geometry": {"coordinates":[4.491194,51.918724],"type":"Point"}
}