{
  "type": "Feature",
  "properties": {
    "addr:full":"Oostelijke Handelskade 1061-1063 Amsterdam Noord-Holland 1019  B",
    "addr:housenumber":"1019 b",
    "addr:postcode":"1061-1063",
    "addr:street":"Oostelijke Handelskade",
    "iso:country":"NL",
    "sg:address":"Oostelijke Handelskade 1061-1063",
    "sg:city":"Amsterdam",
    "sg:orig_category":"Boekhandels",
    "sg:phone":"+31 20 419 7264",
    "sg:postcode":"1019  B",
    "sg:province":"Noord-Holland",
    "wof:name":"Bruna",
    "wof:placetype":"venue"
},
  "geometry": {"coordinates":[4.938388,52.37392],"type":"Point"}
}