{
  "type": "Feature",
  "properties": {
    "iso:country":"NL",
    "sg:address":"Eindstraat 21",
    "sg:city":"Ottersum",
    "sg:orig_category":"Levende Dieren Gh",
    "sg:phone":"+31 485 515 053",
    "sg:postcode":"6595 MR",
    "sg:province":"Limburg",
    "wof:name":"W.H.E. Voss",
    "wof:placetype":"venue"
},
  "geometry": {"coordinates":[6.017728,51.719784],"type":"Point"}
}