{
  "type": "Feature",
  "properties": {
    "addr:full":"F Halsstr 11 Haarlem Noord-Holland 2021 EG",
    "addr:housenumber":"11",
    "addr:postcode":"2021 eg",
    "iso:country":"NL",
    "sg:address":"F Halsstr 11",
    "sg:city":"Haarlem",
    "sg:orig_category":"Organisatiebureaus",
    "sg:phone":"+31 23 525 5247",
    "sg:postcode":"2021 EG",
    "sg:province":"Noord-Holland",
    "wof:name":"Bodewes, Jan T C",
    "wof:placetype":"venue"
},
  "geometry": {"coordinates":[4.6396150589,52.3910140991],"type":"Point"}
}