{
  "type": "Feature",
  "properties": {
    "addr:full":"Zwaanshals 420 Rotterdam South Holland 3035 KT",
    "addr:housenumber":"420",
    "addr:postcode":"3035 kt",
    "addr:street":"Zwaanshals",
    "iso:country":"NL",
    "sg:address":"Zwaanshals 420",
    "sg:city":"Rotterdam",
    "sg:orig_category":"Verlichting And Huishoudartikelen",
    "sg:phone":"+31 10 466 1407",
    "sg:postcode":"3035 KT",
    "sg:province":"South Holland",
    "wof:name":"Frans Westervoorde",
    "wof:placetype":"venue"
},
  "geometry": {"coordinates":[4.485783,51.932556],"type":"Point"}
}