{
  "type": "Feature",
  "properties": {
    "addr:full":"Kapelstr 53 Afferden Lb Limburg 5851 AS",
    "addr:housenumber":"53",
    "addr:postcode":"lb;5851 as",
    "addr:street":"Kapelstr",
    "iso:country":"NL",
    "sg:address":"Kapelstr 53",
    "sg:city":"Afferden Lb",
    "sg:orig_category":"Plotservice",
    "sg:phone":"+31 485 531 999",
    "sg:postcode":"5851 AS",
    "sg:province":"Limburg",
    "sg:website":"http://www.repro-wegmann.com",
    "wof:name":"Wegmann",
    "wof:placetype":"venue"
},
  "geometry": {"coordinates":[-93.129936,36.705662],"type":"Point"}
}