{
  "type": "Feature",
  "properties": {
    "addr:full":"Cort Van Der Lindenstr 23 Rijswijk Zh Zuid-Holland 2288 EV",
    "addr:housenumber":"23",
    "addr:postcode":"zh;2288 ev",
    "addr:street":"Cort Van Der Lindenstr",
    "iso:country":"NL",
    "sg:address":"Cort Van Der Lindenstr 23",
    "sg:city":"Rijswijk Zh",
    "sg:orig_category":"Metaalwerken",
    "sg:phone":"+31 70 307 0802",
    "sg:postcode":"2288 EV",
    "sg:province":"Zuid-Holland",
    "wof:name":"Nederlandse Zonwering Industrie Kamphuis Bv",
    "wof:placetype":"venue"
},
  "geometry": {"coordinates":[4.334511,52.041718],"type":"Point"}
}