{
  "type": "Feature",
  "properties": {
    "addr:full":"Portsmuiden 20 Amsterdam North Holland 1046 AJ",
    "addr:housenumber":"20",
    "addr:postcode":"1046 aj",
    "addr:street":"Portsmuiden",
    "iso:country":"NL",
    "sg:address":"Portsmuiden 20",
    "sg:city":"Amsterdam",
    "sg:orig_category":"Meubelmakerijen",
    "sg:phone":"+31 20 614 4986",
    "sg:postcode":"1046 AJ",
    "sg:province":"North Holland",
    "wof:name":"Zeil Design, De",
    "wof:placetype":"venue"
},
  "geometry": {"coordinates":[4.784044,52.390461],"type":"Point"}
}