{
  "type": "Feature",
  "properties": {
    "addr:full":"Statenweg 29 Emmen Drenthe 7824 CS",
    "addr:housenumber":"29",
    "addr:postcode":"7824 cs",
    "addr:street":"Statenweg",
    "iso:country":"NL",
    "sg:address":"Statenweg 29",
    "sg:city":"Emmen",
    "sg:orig_category":"Banken And Kredietinstellingen",
    "sg:phone":"+31 591 623 824",
    "sg:postcode":"7824 CS",
    "sg:province":"Drenthe",
    "wof:name":"Abn Amro",
    "wof:placetype":"venue"
},
  "geometry": {"coordinates":[6.921486,52.77948],"type":"Point"}
}