{
  "type": "Feature",
  "properties": {
    "addr:full":"Plesmanstr 8 Leusden Utrecht 3833 LA",
    "addr:housenumber":"8",
    "addr:postcode":"3833 la",
    "addr:street":"Plesmanstr",
    "iso:country":"NL",
    "sg:address":"Plesmanstr 8",
    "sg:city":"Leusden",
    "sg:orig_category":"Woninginrichting",
    "sg:phone":"+31 33 434 3311",
    "sg:postcode":"3833 LA",
    "sg:province":"Utrecht",
    "wof:name":"Hometrend Groep Bv",
    "wof:placetype":"venue"
},
  "geometry": {"coordinates":[5.4208431244,52.1449661255],"type":"Point"}
}