{
  "type": "Feature",
  "properties": {
    "addr:full":"Hoepelbuigersln 12 Nederhorst D Berg Noord-Holland 1394 LG",
    "addr:housenumber":"12",
    "addr:postcode":"1394 lg",
    "addr:street":"Hoepelbuigersln;Nederhorst D Berg",
    "iso:country":"NL",
    "sg:address":"Hoepelbuigersln 12",
    "sg:city":"Nederhorst D Berg",
    "sg:orig_category":"Adviesbureaus Bedrijfsorganisatie",
    "sg:phone":"+31 294 257 568",
    "sg:postcode":"1394 LG",
    "sg:province":"Noord-Holland",
    "wof:name":"Barten",
    "wof:placetype":"venue"
},
  "geometry": {"coordinates":[-121.624138,39.182121],"type":"Point"}
}