{
  "type": "Feature",
  "properties": {
    "addr:full":"Lorentzlaan 12 Ijsselstein Ut Utrecht 3401 MX",
    "addr:housenumber":"12",
    "addr:postcode":"3401 mx",
    "addr:street":"Lorentzlaan",
    "iso:country":"NL",
    "sg:address":"Lorentzlaan 12",
    "sg:city":"Ijsselstein Ut",
    "sg:orig_category":"Loodgieterswerk, Verwarming And Sanitaire Installaties",
    "sg:phone":"+31 30 686 8200",
    "sg:postcode":"3401 MX",
    "sg:province":"Utrecht",
    "wof:name":"Rudon Bv",
    "wof:placetype":"venue"
},
  "geometry": {"coordinates":[5.060319,52.012959],"type":"Point"}
}