{
  "type": "Feature",
  "properties": {
    "iso:country":"NL",
    "sg:address":"Sterremosstr 36",
    "sg:city":"Purmerend",
    "sg:orig_category":"Verzekeringen - Verzekeringskantoren",
    "sg:phone":"+31 299 773 580",
    "sg:postcode":"1441 LT",
    "sg:province":"Noord-Holland",
    "wof:name":"Waal Verzekeringen",
    "wof:placetype":"venue"
},
  "geometry": {"coordinates":[4.955161,52.499016],"type":"Point"}
}