{
  "type": "Feature",
  "properties": {
    "addr:full":"Sterremosstr 36 Purmerend Noord-Holland 1441 LT",
    "addr:housenumber":"36",
    "addr:postcode":"1441 lt",
    "addr:street":"Sterremosstr",
    "iso:country":"NL",
    "sg:address":"Sterremosstr 36",
    "sg:city":"Purmerend",
    "sg:orig_category":"Verzekeringen - Verzekeringskantoren",
    "sg:phone":"+31 299 773 580",
    "sg:postcode":"1441 LT",
    "sg:province":"Noord-Holland",
    "wof:name":"Waal Verzekeringen",
    "wof:placetype":"venue"
},
  "geometry": {"coordinates":[4.955161,52.499016],"type":"Point"}
}