{
  "type": "Feature",
  "properties": {
    "iso:country":"NL",
    "sg:address":"De Korf 35",
    "sg:city":"Krimpen Ad Yssel",
    "sg:orig_category":"Kinderkleding",
    "sg:phone":"+31 180 550 340",
    "sg:postcode":"2924 AH",
    "sg:province":"Zuid-Holland",
    "sg:website":"http://www.arcadedekorf.nl",
    "wof:name":"Anna Bj\u00f6rn",
    "wof:placetype":"venue"
},
  "geometry": {"coordinates":[4.610589,51.92308],"type":"Point"}
}