{
  "type": "Feature",
  "properties": {
    "iso:country":"NL",
    "sg:address":"Koningin Emmastraat 2",
    "sg:city":"Woudenberg",
    "sg:orig_category":"Meubelzaken, Woning- And Keukeninrichting",
    "sg:phone":"+31 33 286 1557",
    "sg:postcode":"3931 EC",
    "sg:province":"Utrecht",
    "wof:name":"Firma M. Veenendaal En Zn",
    "wof:placetype":"venue"
},
  "geometry": {"coordinates":[5.418256,52.082695],"type":"Point"}
}