{
  "type": "Feature",
  "properties": {
    "addr:full":"Koperstraat 60 Zoetermeer South Holland 2718 RE",
    "addr:housenumber":"60",
    "addr:postcode":"2718 re",
    "addr:street":"Koperstraat",
    "iso:country":"NL",
    "sg:address":"Koperstraat 60",
    "sg:city":"Zoetermeer",
    "sg:orig_category":"Verhuisdiensten",
    "sg:phone":"+31 79 362 8484",
    "sg:postcode":"2718 RE",
    "sg:province":"South Holland",
    "wof:name":"Svg Scholte Verhuis Groep",
    "wof:placetype":"venue"
},
  "geometry": {"coordinates":[4.509645,52.036713],"type":"Point"}
}