{
  "type": "Feature",
  "properties": {
    "addr:full":"Pr Hendrikstr 34 Naaldwyk Zuid-Holland 2671 JH",
    "addr:housenumber":"34",
    "addr:postcode":"2671 jh",
    "iso:country":"NL",
    "sg:address":"Pr Hendrikstr 34",
    "sg:city":"Naaldwyk",
    "sg:orig_category":"Kappers",
    "sg:phone":"+31 174 625 244",
    "sg:postcode":"2671 JH",
    "sg:province":"Zuid-Holland",
    "wof:name":"Il Mondo",
    "wof:placetype":"venue"
},
  "geometry": {"coordinates":[4.2071781158,51.9923095703],"type":"Point"}
}