{
  "type": "Feature",
  "properties": {
    "iso:country":"NL",
    "sg:address":"Segeersstr 21",
    "sg:city":"Middelburg",
    "sg:orig_category":"Hoeden",
    "sg:phone":"+31 118 651 501",
    "sg:postcode":"4331 JM",
    "sg:province":"Zeeland",
    "wof:name":"Modelize Hoedenspeciaalzaak",
    "wof:placetype":"venue"
},
  "geometry": {"coordinates":[3.615912,51.498135],"type":"Point"}
}