{
  "type": "Feature",
  "properties": {
    "addr:full":"Benedenkd 5-7 Willemstad Nb Noord-Brabant 4797 AV",
    "addr:housenumber":"5-7",
    "addr:postcode":"4797 av",
    "addr:street":"Benedenkd",
    "iso:country":"NL",
    "sg:address":"Benedenkd 5-7",
    "sg:city":"Willemstad Nb",
    "sg:orig_category":"Watersportartikelen",
    "sg:phone":"+31 168 472 855",
    "sg:postcode":"4797 AV",
    "sg:province":"Noord-Brabant",
    "sg:website":"http://www.yachtingwillemstad.nl",
    "wof:name":"Yachting Willemstad",
    "wof:placetype":"venue"
},
  "geometry": {"coordinates":[4.432363987,51.6744842529],"type":"Point"}
}