{
  "type": "Feature",
  "properties": {
    "addr:full":"Peperstr 7 Buren Gld Gelderland 4116 BG",
    "addr:housenumber":"7",
    "addr:postcode":"4116",
    "addr:street":"Peperstr;Gld Gelderland",
    "iso:country":"NL",
    "sg:address":"Peperstr 7",
    "sg:city":"Buren Gld",
    "sg:orig_category":"Kappers",
    "sg:phone":"+31 344 571 079",
    "sg:postcode":"4116 BG",
    "sg:province":"Gelderland",
    "wof:name":"Barbier Van Buren, De",
    "wof:placetype":"venue"
},
  "geometry": {"coordinates":[5.334856987,51.9109649658],"type":"Point"}
}