{
  "type": "Feature",
  "properties": {
    "iso:country":"NL",
    "sg:address":"Noordkant 19A",
    "sg:city":"St Anthonis",
    "sg:orig_category":"Verenigingen En Stichtingen",
    "sg:phone":"+31 485 385 439",
    "sg:postcode":"5845 EX",
    "sg:province":"Noord-Brabant",
    "wof:name":"Time Out Project",
    "wof:placetype":"venue"
},
  "geometry": {"coordinates":[5.88748,51.634125],"type":"Point"}
}