{
  "type": "Feature",
  "properties": {
    "addr:full":"Kerkpln 4A S Gravenhage Zuid-Holland 2513 AZ",
    "addr:housenumber":"4a;gravenhage",
    "addr:postcode":"2513 az",
    "addr:street":"Kerkpln;S",
    "iso:country":"NL",
    "sg:address":"Kerkpln 4A",
    "sg:city":"S Gravenhage",
    "sg:orig_category":"Parketvloeren",
    "sg:phone":"+31 70 345 2030",
    "sg:postcode":"2513 AZ",
    "sg:province":"Zuid-Holland",
    "wof:name":"Eemland Parket",
    "wof:placetype":"venue"
},
  "geometry": {"coordinates":[4.30339,52.078442],"type":"Point"}
}