{
  "type": "Feature",
  "properties": {
    "addr:full":"Mr Dr Froweinwg 38 Eys Limburg 6287 CC",
    "addr:housenumber":"38",
    "addr:postcode":"6287 cc",
    "addr:street":"Mr Dr Froweinwg",
    "iso:country":"NL",
    "sg:address":"Mr Dr Froweinwg 38",
    "sg:city":"Eys",
    "sg:orig_category":"Autorijscholen",
    "sg:phone":"+31 43 451 1835",
    "sg:postcode":"6287 CC",
    "sg:province":"Limburg",
    "wof:name":"Charlier",
    "wof:placetype":"venue"
},
  "geometry": {"coordinates":[5.948475,50.824215],"type":"Point"}
}