{
  "type": "Feature",
  "properties": {
    "iso:country":"NL",
    "sg:address":"Padakkers 11",
    "sg:city":"Diever",
    "sg:orig_category":"Administratie- En Boekhoudkantoren",
    "sg:phone":"+31 521 593 964",
    "sg:postcode":"7981 DW",
    "sg:province":"Provincie Drenthe",
    "wof:name":"Acs",
    "wof:placetype":"venue"
},
  "geometry": {"coordinates":[6.307807,52.854591],"type":"Point"}
}