{
  "type": "Feature",
  "properties": {
    "addr:full":"Nehalenniaweg 8 Domburg Zeeland 4357 AW",
    "addr:housenumber":"8",
    "addr:postcode":"4357 aw",
    "addr:street":"Nehalenniaweg",
    "iso:country":"NL",
    "sg:address":"Nehalenniaweg 8",
    "sg:city":"Domburg",
    "sg:classifiers":[
        {
            "category":"Travel",
            "subcategory":"Hotels & Motels",
            "type":"Entertainment"
        }
    ],
    "sg:phone":"+31 118 581 452",
    "sg:postcode":"4357 AW",
    "sg:province":"Zeeland",
    "wof:name":"Hotel Bos En Zee",
    "wof:placetype":"venue"
},
  "geometry": {"coordinates":[3.499048,51.566189],"type":"Point"}
}