{
  "type": "Feature",
  "properties": {
    "iso:country":"NL",
    "sg:address":"Ruiterpad 10",
    "sg:city":"Baarle Nassau",
    "sg:orig_category":"Goudsmeden En Zilversmeden",
    "sg:phone":"+31 13 507 8125",
    "sg:postcode":"5111 BZ",
    "sg:province":"Noord-Brabant",
    "wof:name":"Bezemer, P A",
    "wof:placetype":"venue"
},
  "geometry": {"coordinates":[4.925998,51.450134],"type":"Point"}
}