{
  "type": "Feature",
  "properties": {
    "addr:full":"Beekerheide 2 Beek En Donk Noord-Brabant 5741 HC",
    "addr:housenumber":"2",
    "addr:postcode":"5741 hc",
    "addr:street":"Beekerheide",
    "iso:country":"NL",
    "sg:address":"Beekerheide 2",
    "sg:city":"Beek En Donk",
    "sg:orig_category":"Antiekzaken",
    "sg:phone":"+31 492 461 301",
    "sg:postcode":"5741 HC",
    "sg:province":"Noord-Brabant",
    "wof:name":"Handelsonderneming Van Schijndel Vof",
    "wof:placetype":"venue"
},
  "geometry": {"coordinates":[5.641579,51.519932],"type":"Point"}
}