{
  "type": "Feature",
  "properties": {
    "addr:full":"Hobbemakd 81 Amsterdam Noord-Holland 1071 XP",
    "addr:housenumber":"81",
    "addr:postcode":"1071 xp",
    "addr:street":"Hobbemakd",
    "iso:country":"NL",
    "sg:address":"Hobbemakd 81",
    "sg:city":"Amsterdam",
    "sg:orig_category":"Beeldende Kunstenaars",
    "sg:phone":"+31 20 671 9248",
    "sg:postcode":"1071 XP",
    "sg:province":"Noord-Holland",
    "wof:name":"Burger, J P",
    "wof:placetype":"venue"
},
  "geometry": {"coordinates":[4.87701,52.355549],"type":"Point"}
}