{
  "type": "Feature",
  "properties": {
    "addr:full":"Florynruwe 52C Maastricht Limburg 6218 CE",
    "addr:housenumber":"52c",
    "addr:postcode":"6218 ce",
    "addr:street":"Florynruwe",
    "iso:country":"NL",
    "sg:address":"Florynruwe 52C",
    "sg:city":"Maastricht",
    "sg:orig_category":"Beeldende Kunstenaars",
    "sg:phone":"+31 43 343 4939",
    "sg:postcode":"6218 CE",
    "sg:province":"Limburg",
    "wof:name":"Summers, R",
    "wof:placetype":"venue"
},
  "geometry": {"coordinates":[5.657676,50.862114],"type":"Point"}
}