{
  "type": "Feature",
  "properties": {
    "addr:full":"Kerkstraat 66A Hilversum North Holland 1211 CR",
    "addr:housenumber":"66a",
    "addr:postcode":"1211 cr",
    "addr:street":"Kerkstraat",
    "iso:country":"NL",
    "sg:address":"Kerkstraat 66A",
    "sg:city":"Hilversum",
    "sg:orig_category":"Fotostudio'S And Fotografen",
    "sg:phone":"+31 35 628 9130",
    "sg:postcode":"1211 CR",
    "sg:province":"North Holland",
    "wof:name":"Fotografie Fred Jansen",
    "wof:placetype":"venue"
},
  "geometry": {"coordinates":[5.1695,52.228565],"type":"Point"}
}