{
  "type": "Feature",
  "properties": {
    "addr:full":"Benedenwg 117 St Pancras Noord-Holland 1834 AL",
    "addr:housenumber":"117",
    "addr:postcode":"1834 al",
    "iso:country":"NL",
    "sg:address":"Benedenwg 117",
    "sg:city":"St Pancras",
    "sg:orig_category":"Administratie- En Boekhoudkantoren",
    "sg:phone":"+31 72 564 7141",
    "sg:postcode":"1834 AL",
    "sg:province":"Noord-Holland",
    "wof:name":"Dekker",
    "wof:placetype":"venue"
},
  "geometry": {"coordinates":[4.782116,52.662109],"type":"Point"}
}