{
  "type": "Feature",
  "properties": {
    "iso:country":"NL",
    "sg:address":"Paardenmarkt 5",
    "sg:city":"Yerseke",
    "sg:classifiers":[
        {
            "category":"Shopping",
            "subcategory":"Adult",
            "type":"Retail Goods"
        }
    ],
    "sg:phone":"+31 113 572 084",
    "sg:postcode":"4401 EE",
    "sg:province":"Zeeland",
    "sg:tags":[
        "lingerie",
        "en",
        "tricotage"
    ],
    "wof:name":"Stobbelaar-Nolet",
    "wof:placetype":"venue"
},
  "geometry": {"coordinates":[4.049563,51.492977],"type":"Point"}
}