{
  "type": "Feature",
  "properties": {
    "iso:country":"NL",
    "sg:address":"Badhuisweg 11",
    "sg:city":"'S Gravenhage",
    "sg:orig_category":"Verzekeringen",
    "sg:phone":"+31 70 416 5858",
    "sg:postcode":"2587 CA",
    "sg:province":"Zuid-Holland",
    "wof:name":"Posthuma Partners",
    "wof:placetype":"venue"
},
  "geometry": {"coordinates":[4.285141,52.111057],"type":"Point"}
}