{
  "type": "Feature",
  "properties": {
    "addr:full":"J Poststr 69A Hoorn Nh North Holland 1624 CB",
    "addr:housenumber":"69a",
    "addr:postcode":"1624 cb",
    "addr:street":"Nh North",
    "iso:country":"NL",
    "sg:address":"J Poststr 69A",
    "sg:city":"Hoorn Nh",
    "sg:orig_category":"Verenigingen En Stichtingen",
    "sg:phone":"+31 229 219 003",
    "sg:postcode":"1624 CB",
    "sg:province":"North Holland",
    "wof:name":"Moskee Alfath, Sticht",
    "wof:placetype":"venue"
},
  "geometry": {"coordinates":[5.05207,52.642399],"type":"Point"}
}