{
  "type": "Feature",
  "properties": {
    "addr:full":"Kerkstraat 33 Hilversum North Holland 1211 CL",
    "addr:housenumber":"33",
    "addr:postcode":"1211",
    "addr:street":"Kerkstraat",
    "iso:country":"NL",
    "sg:address":"Kerkstraat 33",
    "sg:city":"Hilversum",
    "sg:orig_category":"Fotolaboratoria",
    "sg:phone":"+31 35 624 9210",
    "sg:postcode":"1211 CL",
    "sg:province":"North Holland",
    "wof:name":"Kral Super Photo",
    "wof:placetype":"venue"
},
  "geometry": {"coordinates":[5.1695,52.228565],"type":"Point"}
}