{
  "type": "Feature",
  "properties": {
    "addr:full":"Straatweg 66 Breukelen Ut Utrecht 3621 BR",
    "addr:housenumber":"66",
    "addr:postcode":"3621 br",
    "addr:street":"Straatweg",
    "iso:country":"NL",
    "sg:address":"Straatweg 66",
    "sg:city":"Breukelen Ut",
    "sg:orig_category":"Kantoorapparatuur Gh",
    "sg:phone":"+31 346 266 544",
    "sg:postcode":"3621 BR",
    "sg:province":"Utrecht",
    "wof:name":"Kcs Midden Nederland",
    "wof:placetype":"venue"
},
  "geometry": {"coordinates":[5.0072069168,52.1676864624],"type":"Point"}
}