{
  "type": "Feature",
  "properties": {
    "addr:full":"Agter De Hoven 39 Wanssum Limburg 5861 CH",
    "addr:housenumber":"39",
    "addr:postcode":"5861",
    "addr:street":"Agter De Hoven",
    "iso:country":"NL",
    "sg:address":"Agter De Hoven 39",
    "sg:city":"Wanssum",
    "sg:orig_category":"Motoren - Onderdelen",
    "sg:phone":"+31 478 532 716",
    "sg:postcode":"5861 CH",
    "sg:province":"Limburg",
    "wof:name":"Munsters, R",
    "wof:placetype":"venue"
},
  "geometry": {"coordinates":[6.070815,51.534077],"type":"Point"}
}