{
  "type": "Feature",
  "properties": {
    "iso:country":"NL",
    "sg:address":"Centrum 3A Poshuis",
    "sg:city":"'T Harde",
    "sg:orig_category":"Wereldwinkels",
    "sg:phone":"+31 525 654 399",
    "sg:postcode":"8084 BA",
    "sg:province":"Gelderland",
    "wof:name":"Harde, 'T",
    "wof:placetype":"venue"
},
  "geometry": {"coordinates":[5.8825011253,52.4147911072],"type":"Point"}
}