{
  "type": "Feature",
  "properties": {
    "addr:full":"Voorstr 49 Spykenisse Zuid-Holland 3201 BA",
    "addr:housenumber":"49",
    "addr:postcode":"3201 ba",
    "addr:street":"Voorstr",
    "iso:country":"NL",
    "sg:address":"Voorstr 49",
    "sg:city":"Spykenisse",
    "sg:orig_category":"Hypotheken",
    "sg:phone":"+31 181 690 444",
    "sg:postcode":"3201 BA",
    "sg:province":"Zuid-Holland",
    "sg:website":"http://www.spijkenisse.hypotheekshop.nl/1220",
    "wof:name":"Hypotheekshop, De",
    "wof:placetype":"venue"
},
  "geometry": {"coordinates":[4.325045,51.849525],"type":"Point"}
}