{
  "type": "Feature",
  "properties": {
    "addr:full":"De Vecht 14J Dronten Flevoland 8253 PH",
    "addr:housenumber":"14j",
    "addr:postcode":"8253",
    "addr:street":"De Vecht;Flevoland",
    "iso:country":"NL",
    "sg:address":"De Vecht 14J",
    "sg:city":"Dronten",
    "sg:orig_category":"Autoteststations",
    "sg:phone":"+31 321 322 887",
    "sg:postcode":"8253 PH",
    "sg:province":"Flevoland",
    "sg:website":"http://www.bullpower.nl",
    "wof:name":"Bull Power",
    "wof:placetype":"venue"
},
  "geometry": {"coordinates":[5.703783,52.542496],"type":"Point"}
}