{
  "type": "Feature",
  "properties": {
    "addr:full":"Burg V Houtln 43 Helmond Noord-Brabant 5701 GC",
    "addr:housenumber":"43",
    "addr:postcode":"5701 gc",
    "addr:street":"Burg V Houtln",
    "iso:country":"NL",
    "sg:address":"Burg V Houtln 43",
    "sg:city":"Helmond",
    "sg:orig_category":"Mensendieck - Oefentherapeuten",
    "sg:phone":"+31 492 392 193",
    "sg:postcode":"5701 GC",
    "sg:province":"Noord-Brabant",
    "wof:name":"Tinnemans, J",
    "wof:placetype":"venue"
},
  "geometry": {"coordinates":[5.658284,51.482239],"type":"Point"}
}