{
  "type": "Feature",
  "properties": {
    "addr:full":"Seringenlaan 109 Hoogeveen Drenthe 7906 JR",
    "addr:housenumber":"109",
    "addr:postcode":"7906 jr",
    "addr:street":"Seringenlaan",
    "iso:country":"NL",
    "sg:address":"Seringenlaan 109",
    "sg:city":"Hoogeveen",
    "sg:orig_category":"Boekhouders",
    "sg:phone":"+31 528 265 271",
    "sg:postcode":"7906 JR",
    "sg:province":"Drenthe",
    "wof:name":"Buning Boekhoud- En Belastingadviesburea",
    "wof:placetype":"venue"
},
  "geometry": {"coordinates":[6.492692,52.711807],"type":"Point"}
}