{
  "type": "Feature",
  "properties": {
    "addr:full":"Paternosterstraat 1 Alkmaar Noord-Holland 1811 KG",
    "addr:housenumber":"1",
    "addr:postcode":"1811 kg",
    "addr:street":"Paternosterstraat",
    "iso:country":"NL",
    "sg:address":"Paternosterstraat 1",
    "sg:city":"Alkmaar",
    "sg:orig_category":"Banken And Kredietinstellingen",
    "sg:phone":"+31 72 567 4210",
    "sg:postcode":"1811 KG",
    "sg:province":"Noord-Holland",
    "wof:name":"Rabobank",
    "wof:placetype":"venue"
},
  "geometry": {"coordinates":[4.74558,52.63438],"type":"Point"}
}