{
  "type": "Feature",
  "properties": {
    "addr:full":"Meerweg 46 Kropswolde Groningen 9606 PN",
    "addr:housenumber":"46",
    "addr:postcode":"9606 pn",
    "addr:street":"Meerweg",
    "iso:country":"NL",
    "sg:address":"Meerweg 46",
    "sg:city":"Kropswolde",
    "sg:orig_category":"Gespecialiseerde Bouw",
    "sg:phone":"+31 598 327 352",
    "sg:postcode":"9606 PN",
    "sg:province":"Groningen",
    "wof:name":"Dijkmeijer Engeneering Bv",
    "wof:placetype":"venue"
},
  "geometry": {"coordinates":[6.709608,53.144142],"type":"Point"}
}