{
  "type": "Feature",
  "properties": {
    "addr:full":"Ambachtsplein 9 Hazerswoude Dorp Zuid-Holland 2391 BD",
    "addr:housenumber":"9",
    "addr:postcode":"2391 bd",
    "addr:street":"Ambachtsplein",
    "iso:country":"NL",
    "sg:address":"Ambachtsplein 9",
    "sg:city":"Hazerswoude Dorp",
    "sg:orig_category":"Boekhandels",
    "sg:phone":"+31 172 586 300",
    "sg:postcode":"2391 BD",
    "sg:province":"Zuid-Holland",
    "wof:name":"The Read Shop Hazerswoude",
    "wof:placetype":"venue"
},
  "geometry": {"coordinates":[4.592916,52.097355],"type":"Point"}
}