{
  "type": "Feature",
  "properties": {
    "addr:full":"Nieuwstraat 16 Baarn Utrecht 3743 BL",
    "addr:housenumber":"16",
    "addr:postcode":"3743 bl",
    "addr:street":"Nieuwstraat",
    "iso:country":"NL",
    "sg:address":"Nieuwstraat 16",
    "sg:city":"Baarn",
    "sg:orig_category":"Muziekinstrumenten",
    "sg:phone":"+31 35 542 4183",
    "sg:postcode":"3743 BL",
    "sg:province":"Utrecht",
    "wof:name":"Van Der Knaap Vioolbouw",
    "wof:placetype":"venue"
},
  "geometry": {"coordinates":[5.292121,52.21101],"type":"Point"}
}