{
  "type": "Feature",
  "properties": {
    "iso:country":"NL",
    "sg:address":"Nassaulaan 1",
    "sg:city":"Oosterbeek",
    "sg:orig_category":"Film-, Tv- And Videoproductie",
    "sg:phone":"+31 26 333 5500",
    "sg:postcode":"6861 DA",
    "sg:province":"Gelderland",
    "wof:name":"Edwin Otter Audio Visuals",
    "wof:placetype":"venue"
},
  "geometry": {"coordinates":[5.83407,51.989441],"type":"Point"}
}