{
  "type": "Feature",
  "properties": {
    "addr:full":"Gietery 2 Noordwykerhout Zuid-Holland 2211 XK",
    "addr:housenumber":"2",
    "addr:postcode":"2211 xk",
    "addr:street":"Gietery",
    "iso:country":"NL",
    "sg:address":"Gietery 2",
    "sg:city":"Noordwykerhout",
    "sg:classifiers":[
        {
            "category":"Retail",
            "subcategory":"Auto Repair",
            "type":"Services"
        }
    ],
    "sg:phone":"+31 252 373 724",
    "sg:postcode":"2211 XK",
    "sg:province":"Zuid-Holland",
    "sg:tags":[
        "garage"
    ],
    "sg:website":"http://www.autobedrijfkleverlaan.nl",
    "wof:name":"Kleverlaan Bv",
    "wof:placetype":"venue"
},
  "geometry": {"coordinates":[4.490834,52.247692],"type":"Point"}
}