{
  "type": "Feature",
  "properties": {
    "iso:country":"NL",
    "sg:address":"Jhr. Van Coeverdenstraat 18",
    "sg:city":"Oldenzaal",
    "sg:orig_category":"Boekhouders",
    "sg:phone":"+31 541 535 915",
    "sg:postcode":"7576 ZL",
    "sg:province":"NL.08",
    "wof:name":"Raad Oldenzaal",
    "wof:placetype":"venue"
},
  "geometry": {"coordinates":[6.91119,52.315277],"type":"Point"}
}