{
  "type": "Feature",
  "properties": {
    "addr:full":"Koningswg 24B Soest Utrecht 3762 EC",
    "addr:housenumber":"24b",
    "addr:postcode":"3762 ec",
    "addr:street":"Koningswg",
    "iso:country":"NL",
    "sg:address":"Koningswg 24B",
    "sg:city":"Soest",
    "sg:orig_category":"Verhuizingen",
    "sg:phone":"+31 35 601 5063",
    "sg:postcode":"3762 EC",
    "sg:province":"Utrecht",
    "sg:website":"http://www.vannet.nl",
    "wof:name":"Buuren Bv, Van",
    "wof:placetype":"venue"
},
  "geometry": {"coordinates":[5.270368,52.178997],"type":"Point"}
}