{
  "type": "Feature",
  "properties": {
    "addr:full":"Abstederdk 317A Utrecht Utrecht 3582 BL",
    "addr:housenumber":"317a",
    "addr:postcode":"3582 bl",
    "iso:country":"NL",
    "sg:address":"Abstederdk 317A",
    "sg:city":"Utrecht",
    "sg:orig_category":"Vertaalbureaus",
    "sg:phone":"+31 30 252 1920",
    "sg:postcode":"3582 BL",
    "sg:province":"Utrecht",
    "wof:name":"Vernooy",
    "wof:placetype":"venue"
},
  "geometry": {"coordinates":[5.13666,52.083973],"type":"Point"}
}