{
  "type": "Feature",
  "properties": {
    "addr:full":"Sluiskolk 3 Vroomshoop Overijssel 7681 KC",
    "addr:housenumber":"3",
    "addr:postcode":"7681 kc",
    "addr:street":"Sluiskolk",
    "iso:country":"NL",
    "sg:address":"Sluiskolk 3",
    "sg:city":"Vroomshoop",
    "sg:orig_category":"Farmaceutische Producten Gh",
    "sg:phone":"+31 546 666 666",
    "sg:postcode":"7681 KC",
    "sg:province":"Overijssel",
    "wof:name":"Bio Enterprise Bv",
    "wof:placetype":"venue"
},
  "geometry": {"coordinates":[6.565036,52.450397],"type":"Point"}
}