{
  "type": "Feature",
  "properties": {
    "iso:country":"NL",
    "sg:address":"Lucas Van Hauthemlaan 1",
    "sg:city":"Nuenen",
    "sg:orig_category":"Zalenexploitatie",
    "sg:phone":"+31 40 283 2069",
    "sg:postcode":"5671 CJ",
    "sg:province":"North Brabant",
    "wof:name":"Galerie En Kunstuitleen 'T Weefhuis",
    "wof:placetype":"venue"
},
  "geometry": {"coordinates":[5.554794,51.480267],"type":"Point"}
}