{
  "type": "Feature",
  "properties": {
    "iso:country":"NL",
    "sg:address":"H Dunantwg 1618",
    "sg:city":"Alphen Aan Den Ryn",
    "sg:orig_category":"Gehandicapteninformatie",
    "sg:phone":"+31 172 468 646",
    "sg:postcode":"2402 NP",
    "sg:province":"Zuid-Holland",
    "sg:website":"http://www.handjehelpen.nl",
    "wof:name":"Praktische Thuishulp Alphen Aan Den Rijn",
    "wof:placetype":"venue"
},
  "geometry": {"coordinates":[4.65824,52.143768],"type":"Point"}
}