{
  "type": "Feature",
  "properties": {
    "addr:full":"P Krugerstr 9A Vlissingen Zeeland 4382 MA",
    "addr:housenumber":"9a",
    "addr:postcode":"4382 ma",
    "iso:country":"NL",
    "sg:address":"P Krugerstr 9A",
    "sg:city":"Vlissingen",
    "sg:orig_category":"Fietsen En Bromfietsen",
    "sg:phone":"+31 118 440 288",
    "sg:postcode":"4382 MA",
    "sg:province":"Zeeland",
    "wof:name":"Biko-Sportivo",
    "wof:placetype":"venue"
},
  "geometry": {"coordinates":[3.57237,51.449146],"type":"Point"}
}