{
  "type": "Feature",
  "properties": {
    "iso:country":"NL",
    "sg:address":"Florastr 1",
    "sg:city":"Beverwyk",
    "sg:orig_category":"Behangselpapier En Wandbekleding - Fabr. En Grooth",
    "sg:phone":"+31 251 211 177",
    "sg:postcode":"1943 LE",
    "sg:province":"Noord-Holland",
    "wof:name":"Portegies Bv",
    "wof:placetype":"venue"
},
  "geometry": {"coordinates":[4.648028,52.489017],"type":"Point"}
}