{
  "type": "Feature",
  "properties": {
    "iso:country":"NL",
    "sg:address":"Schepenveld 21-11",
    "sg:city":"Zeewolde",
    "sg:orig_category":"Zoetwaren - Fabrieken En Groothandel",
    "sg:phone":"+31 36 522 4751",
    "sg:postcode":"3891 ZK",
    "sg:province":"NL.",
    "sg:website":"http://www.chotryka.nl",
    "wof:name":"Chotryka Vof",
    "wof:placetype":"venue"
},
  "geometry": {"coordinates":[5.530101,52.336536],"type":"Point"}
}