{
  "type": "Feature",
  "properties": {
    "iso:country":"NL",
    "sg:address":"Nieuwstr 57",
    "sg:city":"Eibergen",
    "sg:classifiers":[
        {
            "category":"Food & Beverages",
            "subcategory":"Bakery",
            "type":"Retail Goods"
        }
    ],
    "sg:phone":"+31 545 476 726",
    "sg:postcode":"7151 CD",
    "sg:province":"Gelderland",
    "sg:tags":[
        "brood",
        "en",
        "banket"
    ],
    "wof:name":"Oude Hilbert, P H",
    "wof:placetype":"venue"
},
  "geometry": {"coordinates":[6.645358,52.100834],"type":"Point"}
}