{
  "type": "Feature",
  "properties": {
    "iso:country":"NL",
    "sg:address":"Kruiszwin 4532",
    "sg:city":"Den Helder",
    "sg:orig_category":"Schoonheidsinstituten",
    "sg:phone":"+31 223 645 542",
    "sg:postcode":"1788 RP",
    "sg:province":"North Holland",
    "wof:name":"Berg-Blok, S H V/D",
    "wof:placetype":"venue"
},
  "geometry": {"coordinates":[4.738676,52.886349],"type":"Point"}
}