{
  "type": "Feature",
  "properties": {
    "addr:full":"Burgemeester Gommansstr 171 Venlo Limburg 5922 AJ",
    "addr:housenumber":"171",
    "addr:postcode":"5922 aj",
    "addr:street":"Burgemeester Gommansstr",
    "iso:country":"NL",
    "sg:address":"Burgemeester Gommansstr 171",
    "sg:city":"Venlo",
    "sg:orig_category":"Kappers",
    "sg:phone":"+31 77 387 2992",
    "sg:postcode":"5922 AJ",
    "sg:province":"Limburg",
    "wof:name":"Hair Garden",
    "wof:placetype":"venue"
},
  "geometry": {"coordinates":[6.1447348595,51.3705673218],"type":"Point"}
}