{
  "type": "Feature",
  "properties": {
    "iso:country":"NL",
    "sg:address":"Korenbloemwg 9",
    "sg:city":"Alphen Aan Den Ryn",
    "sg:orig_category":"Verenigingen En Stichtingen",
    "sg:phone":"+31 172 422 310",
    "sg:postcode":"2403 GA",
    "sg:province":"Zuid-Holland",
    "wof:name":"Nrs Nationale Recreatie, Sticht",
    "wof:placetype":"venue"
},
  "geometry": {"coordinates":[4.684778,52.147415],"type":"Point"}
}