{
  "type": "Feature",
  "properties": {
    "addr:full":"Langestraat 82 Winschoten Groningen 9671 PK",
    "addr:housenumber":"82",
    "addr:postcode":"9671 pk",
    "addr:street":"Langestraat",
    "iso:country":"NL",
    "sg:address":"Langestraat 82",
    "sg:city":"Winschoten",
    "sg:classifiers":[
        {
            "category":"Fast Food",
            "type":"Food & Drink"
        }
    ],
    "sg:phone":"+31 597 418 718",
    "sg:postcode":"9671 PK",
    "sg:province":"Groningen",
    "sg:tags":[
        "afhaal",
        "restaurant"
    ],
    "wof:name":"Cafetaria De Lunchroom Tulp",
    "wof:placetype":"venue"
},
  "geometry": {"coordinates":[7.03463,53.145409],"type":"Point"}
}