{
  "type": "Feature",
  "properties": {
    "addr:full":"W Schoutenstr 1 Emmen Provincie Drenthe 7825 VV",
    "addr:housenumber":"1;7825",
    "addr:postcode":"vv",
    "addr:street":"W;Provincie Drenthe",
    "iso:country":"NL",
    "sg:address":"W Schoutenstr 1",
    "sg:city":"Emmen",
    "sg:orig_category":"Wegmarkering",
    "sg:phone":"+31 591 677 177",
    "sg:postcode":"7825 VV",
    "sg:province":"Provincie Drenthe",
    "wof:name":"Viamark Bv",
    "wof:placetype":"venue"
},
  "geometry": {"coordinates":[6.932929039,52.7532501221],"type":"Point"}
}