{
  "type": "Feature",
  "properties": {
    "iso:country":"NL",
    "sg:address":"Rooke Erf 11",
    "sg:city":"Hoogland",
    "sg:orig_category":"Onroerende Goederen",
    "sg:phone":"+31 33 456 3004",
    "sg:postcode":"3828 LK",
    "sg:province":"Utrecht",
    "wof:name":"Vi Doc",
    "wof:placetype":"venue"
},
  "geometry": {"coordinates":[5.372171,52.193226],"type":"Point"}
}