{
  "type": "Feature",
  "properties": {
    "addr:full":"Nachtegaalstr 36 Heerlen Limburg 6414 TW",
    "addr:housenumber":"36",
    "addr:postcode":"6414 tw",
    "addr:street":"Nachtegaalstr",
    "iso:country":"NL",
    "sg:address":"Nachtegaalstr 36",
    "sg:city":"Heerlen",
    "sg:orig_category":"Betonijzervlechten",
    "sg:phone":"+31 45 522 2449",
    "sg:postcode":"6414 TW",
    "sg:province":"Limburg",
    "wof:name":"Rozema",
    "wof:placetype":"venue"
},
  "geometry": {"coordinates":[5.970949,50.922176],"type":"Point"}
}