{
  "type": "Feature",
  "properties": {
    "addr:full":"Bellwg 1 Delft South Holland 2627 AW",
    "addr:housenumber":"1",
    "addr:postcode":"2627 aw",
    "addr:street":"Bellwg",
    "iso:country":"NL",
    "sg:address":"Bellwg 1",
    "sg:city":"Delft",
    "sg:orig_category":"Verhuizingen",
    "sg:phone":"+31 15 261 3110",
    "sg:postcode":"2627 AW",
    "sg:province":"South Holland",
    "sg:website":"http://www.fshaaglanden.nl",
    "wof:name":"Haaglanden",
    "wof:placetype":"venue"
},
  "geometry": {"coordinates":[4.370438,51.986816],"type":"Point"}
}