{
  "type": "Feature",
  "properties": {
    "iso:country":"NL",
    "sg:address":"Zwolsewg 31",
    "sg:city":"Eibergen",
    "sg:orig_category":"Vakantieverblijven",
    "sg:phone":"+31 544 461 820",
    "sg:postcode":"7152 DP",
    "sg:province":"Gelderland",
    "wof:name":"Reirinck, Het",
    "wof:placetype":"venue"
},
  "geometry": {"coordinates":[6.646464,52.02969],"type":"Point"}
}