{
  "type": "Feature",
  "properties": {
    "iso:country":"NL",
    "sg:address":"Overysselhaven 15",
    "sg:city":"Nieuwegein",
    "sg:orig_category":"Kunststoffen- Verwerkende Industrie",
    "sg:phone":"+31 30 606 7454",
    "sg:postcode":"3433 PH",
    "sg:province":"Utrecht",
    "wof:name":"Hoven, Van Den",
    "wof:placetype":"venue"
},
  "geometry": {"coordinates":[5.105938,52.022175],"type":"Point"}
}