{
  "type": "Feature",
  "properties": {
    "iso:country":"NL",
    "sg:address":"Koningin Wilhelminalaan 9",
    "sg:city":"Varsseveld",
    "sg:orig_category":"Fitnesscentra",
    "sg:phone":"+31 315 243 479",
    "sg:postcode":"7051 AR",
    "sg:province":"Gelderland",
    "wof:name":"Vof Vitalva",
    "wof:placetype":"venue"
},
  "geometry": {"coordinates":[6.458968,51.941673],"type":"Point"}
}