{
  "type": "Feature",
  "properties": {
    "addr:full":"Dorpsstr 41 Slenaken Limburg 6277 NC",
    "addr:housenumber":"41",
    "addr:postcode":"6277 nc",
    "addr:street":"Dorpsstr",
    "iso:country":"NL",
    "sg:address":"Dorpsstr 41",
    "sg:city":"Slenaken",
    "sg:orig_category":"Makelaars En Adviseurs Onroerende Goederen",
    "sg:phone":"+31 43 457 3676",
    "sg:postcode":"6277 NC",
    "sg:province":"Limburg",
    "wof:name":"Hofman Vastgoed",
    "wof:placetype":"venue"
},
  "geometry": {"coordinates":[5.859268,50.770229],"type":"Point"}
}