{
  "type": "Feature",
  "properties": {
    "addr:full":"Rosselswg 2 Nederweert Limburg 6031 PV",
    "addr:housenumber":"2",
    "addr:postcode":"6031 pv",
    "addr:street":"Rosselswg",
    "iso:country":"NL",
    "sg:address":"Rosselswg 2",
    "sg:city":"Nederweert",
    "sg:orig_category":"Poeliers",
    "sg:phone":"+31 495 631 591",
    "sg:postcode":"6031 PV",
    "sg:province":"Limburg",
    "wof:name":"Uit De Dop Bv",
    "wof:placetype":"venue"
},
  "geometry": {"coordinates":[5.717439,51.288097],"type":"Point"}
}