{
  "type": "Feature",
  "properties": {
    "addr:full":"Mockstraat 15 Maastricht Limburg 6226 CA",
    "addr:housenumber":"15",
    "addr:postcode":"6226 ca",
    "addr:street":"Mockstraat",
    "iso:country":"NL",
    "sg:address":"Mockstraat 15",
    "sg:city":"Maastricht",
    "sg:orig_category":"Bedrijfs- And Managementsconsultants",
    "sg:phone":"+31 43 362 0659",
    "sg:postcode":"6226 CA",
    "sg:province":"Limburg",
    "wof:name":"Adviesbureau Piet Neus",
    "wof:placetype":"venue"
},
  "geometry": {"coordinates":[5.7199101448,50.8451919556],"type":"Point"}
}