{
  "type": "Feature",
  "properties": {
    "addr:full":"Keizerstraat 142 Rotterdam Zuid-Holland 3011 GH",
    "addr:housenumber":"142",
    "addr:postcode":"3011 gh",
    "addr:street":"Keizerstraat",
    "iso:country":"NL",
    "sg:address":"Keizerstraat 142",
    "sg:city":"Rotterdam",
    "sg:orig_category":"Binnenhuisarchitecten",
    "sg:phone":"+31 10 433 3313",
    "sg:postcode":"3011 GH",
    "sg:province":"Zuid-Holland",
    "wof:name":"Niek Deuze Meubel- Object-Interieurontwe",
    "wof:placetype":"venue"
},
  "geometry": {"coordinates":[4.484062,51.919453],"type":"Point"}
}