{
  "type": "Feature",
  "properties": {
    "iso:country":"NL",
    "sg:address":"Flevoln 10",
    "sg:city":"Muiderberg",
    "sg:orig_category":"Bedrijfsopleidingen",
    "sg:phone":"+31 294 263 792",
    "sg:postcode":"1399 HG",
    "sg:province":"Noord-Holland",
    "wof:name":"Andela Consult",
    "wof:placetype":"venue"
},
  "geometry": {"coordinates":[5.116071,52.327091],"type":"Point"}
}