{
  "type": "Feature",
  "properties": {
    "addr:full":"Sperwerlaan 19 Amsterdam Noord-Holland 1021 EM",
    "addr:housenumber":"19",
    "addr:postcode":"1021 em",
    "addr:street":"Sperwerlaan",
    "iso:country":"NL",
    "sg:address":"Sperwerlaan 19",
    "sg:city":"Amsterdam",
    "sg:orig_category":"Kappers",
    "sg:phone":"+31 20 636 5334",
    "sg:postcode":"1021 EM",
    "sg:province":"Noord-Holland",
    "wof:name":"Hairstyling Mario",
    "wof:placetype":"venue"
},
  "geometry": {"coordinates":[4.9141578674,52.3854370117],"type":"Point"}
}