{
  "type": "Feature",
  "properties": {
    "iso:country":"NL",
    "sg:address":"Muzenln 24",
    "sg:city":"Leiderdorp",
    "sg:orig_category":"Belastingconsulenten/ Belastingadviseurs",
    "sg:phone":"+31 71 541 8363",
    "sg:postcode":"2353 KE",
    "sg:province":"South Holland",
    "wof:name":"Slats, J A Th",
    "wof:placetype":"venue"
},
  "geometry": {"coordinates":[4.53042,52.164883],"type":"Point"}
}