{
  "type": "Feature",
  "properties": {
    "iso:country":"NL",
    "sg:address":"Tuinstr 73",
    "sg:city":"De Bilt",
    "sg:orig_category":"Psychologen",
    "sg:phone":"+31 30 220 2856",
    "sg:postcode":"3732 VK",
    "sg:province":"Utrecht",
    "wof:name":"Peltzer, Drs E",
    "wof:placetype":"venue"
},
  "geometry": {"coordinates":[5.185401,52.107185],"type":"Point"}
}