{
  "type": "Feature",
  "properties": {
    "addr:full":"Jutestraat 31 Rijssen NL.08 7461 TS",
    "addr:housenumber":"31;nl.08",
    "addr:postcode":"7461 ts",
    "addr:street":"Jutestraat",
    "iso:country":"NL",
    "sg:address":"Jutestraat 31",
    "sg:city":"Rijssen",
    "sg:orig_category":"Diverse Consumentenartikelen Gh",
    "sg:phone":"+31 548 517 671",
    "sg:postcode":"7461 TS",
    "sg:province":"NL.08",
    "wof:name":"Mapro Bv",
    "wof:placetype":"venue"
},
  "geometry": {"coordinates":[6.509267,52.315948],"type":"Point"}
}