{
  "type": "Feature",
  "properties": {
    "addr:full":"Bosstr 12 Winschoten Groningen 9671 GG",
    "addr:housenumber":"12",
    "addr:postcode":"9671 gg",
    "addr:street":"Bosstr",
    "iso:country":"NL",
    "sg:address":"Bosstr 12",
    "sg:city":"Winschoten",
    "sg:orig_category":"Kappers",
    "sg:phone":"+31 597 412 694",
    "sg:postcode":"9671 GG",
    "sg:province":"Groningen",
    "wof:name":"Maja",
    "wof:placetype":"venue"
},
  "geometry": {"coordinates":[7.035596,53.14373],"type":"Point"}
}