{
  "type": "Feature",
  "properties": {
    "addr:full":"V Baerlestr 143 Vlaardingen Zuid-Holland 3132 EC",
    "addr:housenumber":"143",
    "addr:postcode":"3132 ec",
    "iso:country":"NL",
    "sg:address":"V Baerlestr 143",
    "sg:city":"Vlaardingen",
    "sg:orig_category":"Kaas",
    "sg:phone":"+31 10 435 8884",
    "sg:postcode":"3132 EC",
    "sg:province":"Zuid-Holland",
    "wof:name":"Farmshop",
    "wof:placetype":"venue"
},
  "geometry": {"coordinates":[4.340359211,51.9104423523],"type":"Point"}
}