{
  "type": "Feature",
  "properties": {
    "addr:full":"W Buytewechstr 178C Rotterdam Zuid-Holland 3024 VJ",
    "addr:housenumber":"178c",
    "addr:postcode":"3024 vj",
    "addr:street":"W",
    "iso:country":"NL",
    "sg:address":"W Buytewechstr 178C",
    "sg:city":"Rotterdam",
    "sg:orig_category":"Adviesbureaus Bouwkunde",
    "sg:phone":"+31 10 476 1218",
    "sg:postcode":"3024 VJ",
    "sg:province":"Zuid-Holland",
    "wof:name":"Ruim, Bureau",
    "wof:placetype":"venue"
},
  "geometry": {"coordinates":[4.453728,51.907009],"type":"Point"}
}