{
  "type": "Feature",
  "properties": {
    "addr:full":"Rodenrijseweg 393 Berkel En Rodenrijs South Holland 2651 AM",
    "addr:housenumber":"393",
    "addr:postcode":"2651",
    "addr:street":"Rodenrijseweg",
    "iso:country":"NL",
    "sg:address":"Rodenrijseweg 393",
    "sg:city":"Berkel En Rodenrijs",
    "sg:orig_category":"Bedrijfsinventaris Gh",
    "sg:phone":"+31 10 511 7481",
    "sg:postcode":"2651 AM",
    "sg:province":"South Holland",
    "wof:name":"Hogervorst Bakkerijservice",
    "wof:placetype":"venue"
},
  "geometry": {"coordinates":[4.45727,51.975674],"type":"Point"}
}