{
  "type": "Feature",
  "properties": {
    "addr:full":"Reigerlaan 1B Ursem Noord-Holland 1645 TA",
    "addr:housenumber":"1b",
    "addr:postcode":"1645 ta",
    "addr:street":"Reigerlaan",
    "iso:country":"NL",
    "sg:address":"Reigerlaan 1B",
    "sg:city":"Ursem",
    "sg:orig_category":"Boekhouders",
    "sg:phone":"+31 72 502 2561",
    "sg:postcode":"1645 TA",
    "sg:province":"Noord-Holland",
    "wof:name":"Administratiekantoor Ten Ham Van Loon",
    "wof:placetype":"venue"
},
  "geometry": {"coordinates":[4.889919,52.628761],"type":"Point"}
}