{
  "type": "Feature",
  "properties": {
    "iso:country":"NL",
    "sg:address":"Oude Binnenwg 133",
    "sg:city":"Rotterdam",
    "sg:orig_category":"Herenkleding",
    "sg:phone":"+31 10 412 9695",
    "sg:postcode":"3012 JD",
    "sg:province":"South Holland",
    "wof:name":"Byblos",
    "wof:placetype":"venue"
},
  "geometry": {"coordinates":[4.473361,51.91729],"type":"Point"}
}