{
  "type": "Feature",
  "properties": {
    "addr:full":"Spinnerstr 5 Haaksbergen NL.08 7481 KJ",
    "addr:housenumber":"5;nl.08",
    "addr:postcode":"7481 kj",
    "addr:street":"Spinnerstr",
    "iso:country":"NL",
    "sg:address":"Spinnerstr 5",
    "sg:city":"Haaksbergen",
    "sg:orig_category":"Machinefabrieken",
    "sg:phone":"+31 53 572 1937",
    "sg:postcode":"7481 KJ",
    "sg:province":"NL.08",
    "wof:name":"Boa Haaksbergen Bv",
    "wof:placetype":"venue"
},
  "geometry": {"coordinates":[6.729786,52.154755],"type":"Point"}
}