{
  "type": "Feature",
  "properties": {
    "addr:full":"Ijssel De Schepperstraat 5 Deventer Overijssel 7413 BP",
    "addr:housenumber":"5",
    "addr:postcode":"7413 bp",
    "addr:street":"Ijssel De Schepperstraat",
    "iso:country":"NL",
    "sg:address":"Ijssel De Schepperstraat 5",
    "sg:city":"Deventer",
    "sg:orig_category":"Verhuur Diversen",
    "sg:phone":"+31 570 623 845",
    "sg:postcode":"7413 BP",
    "sg:province":"Overijssel",
    "wof:name":"J Van Tongeren Marktexploitatiebedrijf",
    "wof:placetype":"venue"
},
  "geometry": {"coordinates":[6.162306,52.262604],"type":"Point"}
}