{
  "type": "Feature",
  "properties": {
    "iso:country":"NL",
    "sg:address":"Spoorstr 22",
    "sg:city":"Hattem",
    "sg:orig_category":"Scholen Voor Basisonderwijs",
    "sg:phone":"+31 38 444 2182",
    "sg:postcode":"8051 MZ",
    "sg:province":"Gelderland",
    "wof:name":"Andreassch, St",
    "wof:placetype":"venue"
},
  "geometry": {"coordinates":[6.063965,52.471531],"type":"Point"}
}