{
  "type": "Feature",
  "properties": {
    "addr:full":"Hamersveldseweg 22A Leusden Utrecht 3833 GP",
    "addr:housenumber":"22a",
    "addr:postcode":"3833 gp",
    "addr:street":"Hamersveldseweg",
    "iso:country":"NL",
    "sg:address":"Hamersveldseweg 22A",
    "sg:city":"Leusden",
    "sg:classifiers":[
        {
            "category":"Communications",
            "subcategory":"Television Station",
            "type":"Services"
        }
    ],
    "sg:phone":"+31 33 494 1400",
    "sg:postcode":"3833 GP",
    "sg:province":"Utrecht",
    "sg:tags":[
        "video",
        "audio",
        "verhuur"
    ],
    "wof:name":"Super Video En Computer Entertainment",
    "wof:placetype":"venue"
},
  "geometry": {"coordinates":[5.42711,52.134613],"type":"Point"}
}