{
  "type": "Feature",
  "properties": {
    "iso:country":"NL",
    "sg:address":"Klinkerstraat 28",
    "sg:city":"Grave",
    "sg:orig_category":"Autokeuringen",
    "sg:phone":"+31 486 472 575",
    "sg:postcode":"5361 GW",
    "sg:province":"Noord-Brabant",
    "wof:name":"Vof Garage Smits",
    "wof:placetype":"venue"
},
  "geometry": {"coordinates":[-93.64865899999999,34.872982],"type":"Point"}
}