{
  "type": "Feature",
  "properties": {
    "iso:country":"NL",
    "sg:address":"Sam Van Houtenstraat 74",
    "sg:city":"Amsterdam",
    "sg:classifiers":[
        {
            "category":"Education",
            "subcategory":"Preschool",
            "type":"Public Place"
        }
    ],
    "sg:phone":"+31 20 611 9769",
    "sg:postcode":"1067 JP",
    "sg:province":"North Holland",
    "sg:tags":[
        "kleuteronderwijs",
        "basis-"
    ],
    "wof:name":"Swwt Psz De Tuinkabouter",
    "wof:placetype":"venue"
},
  "geometry": {"coordinates":[4.803514,52.379173],"type":"Point"}
}