{
  "type": "Feature",
  "properties": {
    "iso:country":"NL",
    "sg:address":"Tieselensstraat 9",
    "sg:city":"Dordrecht",
    "sg:orig_category":"Fotostudio'S And Fotografen",
    "sg:phone":"+31 78 631 4725",
    "sg:postcode":"3312 PN",
    "sg:province":"Zuid-Holland",
    "wof:name":"Fotografie Chris Scholte",
    "wof:placetype":"venue"
},
  "geometry": {"coordinates":[4.680614,51.803154],"type":"Point"}
}