{
  "type": "Feature",
  "properties": {
    "addr:full":"Keurmeesterstr 14 Pynacker South Holland 2641 JV",
    "addr:housenumber":"14",
    "addr:postcode":"2641 jv",
    "addr:street":"Keurmeesterstr;Pynacker South",
    "iso:country":"NL",
    "sg:address":"Keurmeesterstr 14",
    "sg:city":"Pynacker",
    "sg:orig_category":"Autorijscholen",
    "sg:phone":"+31 15 369 7217",
    "sg:postcode":"2641 JV",
    "sg:province":"South Holland",
    "wof:name":"Jan",
    "wof:placetype":"venue"
},
  "geometry": {"coordinates":[4.436937,52.01799],"type":"Point"}
}