{
  "type": "Feature",
  "properties": {
    "addr:full":"Zwanewater 2 Zoetermeer Zuid-Holland 2715 BJ",
    "addr:housenumber":"2",
    "addr:postcode":"2715 bj",
    "addr:street":"Zwanewater",
    "iso:country":"NL",
    "sg:address":"Zwanewater 2",
    "sg:city":"Zoetermeer",
    "sg:orig_category":"Beursorganisaties And Standbouw",
    "sg:phone":"+31 79 321 3547",
    "sg:postcode":"2715 BJ",
    "sg:province":"Zuid-Holland",
    "wof:name":"Medcon",
    "wof:placetype":"venue"
},
  "geometry": {"coordinates":[4.471324,52.051922],"type":"Point"}
}