{
  "type": "Feature",
  "properties": {
    "addr:full":"Neerbeekerstr 52 Beek Lb Missouri 6191 HG",
    "addr:housenumber":"52",
    "addr:postcode":"6191 hg",
    "addr:street":"Neerbeekerstr",
    "iso:country":"NL",
    "sg:address":"Neerbeekerstr 52",
    "sg:city":"Beek Lb",
    "sg:orig_category":"Logopedisten",
    "sg:phone":"+31 46 437 9072",
    "sg:postcode":"6191 HG",
    "sg:province":"Missouri",
    "wof:name":"Sturmans-Janssen, M B B",
    "wof:placetype":"venue"
},
  "geometry": {"coordinates":[-93.129936,36.705662],"type":"Point"}
}