{
  "type": "Feature",
  "properties": {
    "addr:full":"Vlietln 44 Bussum North Holland 1404 CC",
    "addr:housenumber":"44",
    "addr:postcode":"1404 cc",
    "addr:street":"Vlietln",
    "iso:country":"NL",
    "sg:address":"Vlietln 44",
    "sg:city":"Bussum",
    "sg:orig_category":"Woninginrichting",
    "sg:phone":"+31 35 692 3793",
    "sg:postcode":"1404 CC",
    "sg:province":"North Holland",
    "wof:name":"Vliet, Woonland Van Der",
    "wof:placetype":"venue"
},
  "geometry": {"coordinates":[5.1626048088,52.2768287659],"type":"Point"}
}