{
  "type": "Feature",
  "properties": {
    "addr:full":"Hilsdk 37 Hattem Gelderland 8051 KC",
    "addr:housenumber":"37",
    "addr:postcode":"8051 kc",
    "addr:street":"Hilsdk;Gelderland",
    "iso:country":"NL",
    "sg:address":"Hilsdk 37",
    "sg:city":"Hattem",
    "sg:orig_category":"Schippers",
    "sg:phone":"+31 6 51434191",
    "sg:postcode":"8051 KC",
    "sg:province":"Gelderland",
    "wof:name":"Bruins, W",
    "wof:placetype":"venue"
},
  "geometry": {"coordinates":[6.051496,52.477566],"type":"Point"}
}