{
  "type": "Feature",
  "properties": {
    "iso:country":"NL",
    "sg:address":"De Roerdomp 14",
    "sg:city":"Sint Michielsgestel",
    "sg:orig_category":"Public Relationbureaus",
    "sg:phone":"+31 73 553 0235",
    "sg:postcode":"5271 LP",
    "sg:province":"Noord-Brabant",
    "wof:name":"Imago Factory On The Road",
    "wof:placetype":"venue"
},
  "geometry": {"coordinates":[5.361963,51.642857],"type":"Point"}
}