{
  "type": "Feature",
  "properties": {
    "addr:full":"Rykswg Z 4 Sittard Limburg 6131 AN",
    "addr:housenumber":"4",
    "addr:postcode":"6131 an",
    "addr:street":"Sittard Limburg",
    "iso:country":"NL",
    "sg:address":"Rykswg Z 4",
    "sg:city":"Sittard",
    "sg:orig_category":"Oldtimers",
    "sg:phone":"+31 46 451 5967",
    "sg:postcode":"6131 AN",
    "sg:province":"Limburg",
    "sg:website":"http://www.britishcarparts.nl",
    "wof:name":"British Car Parts",
    "wof:placetype":"venue"
},
  "geometry": {"coordinates":[5.86392,50.999493],"type":"Point"}
}