{
  "type": "Feature",
  "properties": {
    "addr:full":"W A Scholtenstr 19 Assen Provincie Drenthe 9403 AJ",
    "addr:housenumber":"19",
    "addr:postcode":"9403 aj",
    "addr:street":"W A Scholtenstr;Provincie Drenthe",
    "iso:country":"NL",
    "sg:address":"W A Scholtenstr 19",
    "sg:city":"Assen",
    "sg:orig_category":"Banden - Fabrieken En Groothandel",
    "sg:phone":"+31 592 372 719",
    "sg:postcode":"9403 AJ",
    "sg:province":"Provincie Drenthe",
    "sg:website":"http://www.middelbos.nl",
    "wof:name":"Middelbos Bv",
    "wof:placetype":"venue"
},
  "geometry": {"coordinates":[6.573798,53.00708],"type":"Point"}
}