{
  "type": "Feature",
  "properties": {
    "addr:full":"Goudenregensrt 26 Leeuwarden Provincie Friesland 8922 CR",
    "addr:housenumber":"26;8922",
    "addr:postcode":"cr",
    "addr:street":"Goudenregensrt;Provincie Friesland",
    "iso:country":"NL",
    "sg:address":"Goudenregensrt 26",
    "sg:city":"Leeuwarden",
    "sg:orig_category":"Loodgieterswerk, Verwarming And Sanitaire Installaties",
    "sg:phone":"+31 58 266 6937",
    "sg:postcode":"8922 CR",
    "sg:province":"Provincie Friesland",
    "wof:name":"Vissers Technisch Service Bedrijf",
    "wof:placetype":"venue"
},
  "geometry": {"coordinates":[5.805347,53.209949],"type":"Point"}
}