{
  "type": "Feature",
  "properties": {
    "addr:full":"Dorpstraat 69 Nuth Limburg 6361 AK",
    "addr:housenumber":"69",
    "addr:postcode":"6361 ak",
    "addr:street":"Dorpstraat",
    "iso:country":"NL",
    "sg:address":"Dorpstraat 69",
    "sg:city":"Nuth",
    "sg:classifiers":[
        {
            "category":"Fast Food",
            "type":"Food & Drink"
        }
    ],
    "sg:phone":"+31 45 524 6035",
    "sg:postcode":"6361 AK",
    "sg:province":"Limburg",
    "sg:tags":[
        "afhaal",
        "restaurant"
    ],
    "wof:name":"Pizzeria Grillroom Napoli",
    "wof:placetype":"venue"
},
  "geometry": {"coordinates":[5.885999,50.918785],"type":"Point"}
}