{
  "type": "Feature",
  "properties": {
    "addr:full":"Oltmansstr 70 Enschede NL.08 7514 GC",
    "addr:housenumber":"70",
    "addr:postcode":"7514 gc",
    "addr:street":"Oltmansstr",
    "iso:country":"NL",
    "sg:address":"Oltmansstr 70",
    "sg:city":"Enschede",
    "sg:orig_category":"Adviesbureaus Bedrijfsorganisatie",
    "sg:phone":"+31 53 433 5354",
    "sg:postcode":"7514 GC",
    "sg:province":"NL.08",
    "wof:name":"Paerl Bv, De",
    "wof:placetype":"venue"
},
  "geometry": {"coordinates":[6.892425,52.2243],"type":"Point"}
}