{
  "type": "Feature",
  "properties": {
    "addr:full":"Weerdsingel W.Z. 8B Utrecht Zuid-Holland 2513 BA",
    "addr:housenumber":"8b",
    "addr:postcode":"2513 ba",
    "addr:street":"Weerdsingel W.Z.",
    "iso:country":"NL",
    "sg:address":"Weerdsingel W.Z. 8B",
    "sg:city":"Utrecht",
    "sg:orig_category":"Diverse Grafische Activiteiten",
    "sg:phone":"+31 30 232 3060",
    "sg:postcode":"2513 BA",
    "sg:province":"Zuid-Holland",
    "wof:name":"En/Of Ontwerp",
    "wof:placetype":"venue"
},
  "geometry": {"coordinates":[5.109735,52.095673],"type":"Point"}
}