{
  "type": "Feature",
  "properties": {
    "addr:full":"Bremhorstln 6 Wassenaar South Holland 2244 ES",
    "addr:housenumber":"6",
    "addr:postcode":"2244 es",
    "addr:street":"Bremhorstln",
    "iso:country":"NL",
    "sg:address":"Bremhorstln 6",
    "sg:city":"Wassenaar",
    "sg:orig_category":"Verzekeringen - Verzekeringskantoren",
    "sg:phone":"+31 70 517 7447",
    "sg:postcode":"2244 ES",
    "sg:province":"South Holland",
    "wof:name":"Driessen Bv",
    "wof:placetype":"venue"
},
  "geometry": {"coordinates":[4.365925,52.113419],"type":"Point"}
}