{
  "type": "Feature",
  "properties": {
    "addr:full":"Hoek 3 Erp Noord-Brabant 5469 NK",
    "addr:housenumber":"3",
    "addr:postcode":"5469 nk",
    "addr:street":"Hoek",
    "iso:country":"NL",
    "sg:address":"Hoek 3",
    "sg:city":"Erp",
    "sg:orig_category":"Hoefdierhouderijen",
    "sg:phone":"+31 413 216 090",
    "sg:postcode":"5469 NK",
    "sg:province":"Noord-Brabant",
    "wof:name":"A.M.J.M. Hoefs",
    "wof:placetype":"venue"
},
  "geometry": {"coordinates":[5.630574,51.59536],"type":"Point"}
}