{
  "type": "Feature",
  "properties": {
    "addr:full":"Noordpolderkade 163 'S Gravenhage Zuid-Holland 2516 JD",
    "addr:housenumber":"163 '",
    "addr:postcode":"2516 jd",
    "addr:street":"Noordpolderkade",
    "iso:country":"NL",
    "sg:address":"Noordpolderkade 163",
    "sg:city":"'S Gravenhage",
    "sg:orig_category":"Bejaardeninstellingen And Serviceflats",
    "sg:phone":"+31 70 399 3881",
    "sg:postcode":"2516 JD",
    "sg:province":"Zuid-Holland",
    "wof:name":"Verzorgingshuis Wenckebach",
    "wof:placetype":"venue"
},
  "geometry": {"coordinates":[4.33374,52.062809],"type":"Point"}
}