{
  "type": "Feature",
  "properties": {
    "iso:country":"NL",
    "sg:address":"Traay 126",
    "sg:city":"Driebergen-Rijsenburg",
    "sg:orig_category":"Wasserettes And Stomerijen",
    "sg:phone":"+31 343 515 347",
    "sg:postcode":"3971 GS",
    "sg:province":"Utrecht",
    "wof:name":"A Lambermond",
    "wof:placetype":"venue"
},
  "geometry": {"coordinates":[5.292907238,52.0559387207],"type":"Point"}
}