{
  "type": "Feature",
  "properties": {
    "addr:full":"Notenhof 2 Schagen Noord-Holland 1741 VS",
    "addr:housenumber":"2",
    "addr:postcode":"1741 vs",
    "addr:street":"Notenhof",
    "iso:country":"NL",
    "sg:address":"Notenhof 2",
    "sg:city":"Schagen",
    "sg:orig_category":"Administratie- En Boekhoudkantoren",
    "sg:phone":"+31 224 214 208",
    "sg:postcode":"1741 VS",
    "sg:province":"Noord-Holland",
    "sg:website":"http://www.frilcon.nl",
    "wof:name":"Frilcon Bv",
    "wof:placetype":"venue"
},
  "geometry": {"coordinates":[4.794382,52.797409],"type":"Point"}
}