{
  "type": "Feature",
  "properties": {
    "addr:full":"Kerkstr 23 Waspik North Brabant 5165 CE",
    "addr:housenumber":"23",
    "addr:postcode":"5165 ce",
    "addr:street":"Kerkstr",
    "iso:country":"NL",
    "sg:address":"Kerkstr 23",
    "sg:city":"Waspik",
    "sg:orig_category":"Bejaarden - Verzorgingstehuizen",
    "sg:phone":"+31 416 311 370",
    "sg:postcode":"5165 CE",
    "sg:province":"North Brabant",
    "wof:name":"Riethorst, De",
    "wof:placetype":"venue"
},
  "geometry": {"coordinates":[4.943745,51.686607],"type":"Point"}
}