{
  "type": "Feature",
  "properties": {
    "addr:full":"Iwert 3 Wijckel Provincie Friesland 8563 AM",
    "addr:housenumber":"3",
    "addr:postcode":"8563",
    "addr:street":"Iwert;Provincie Friesland",
    "iso:country":"NL",
    "sg:address":"Iwert 3",
    "sg:city":"Wijckel",
    "sg:orig_category":"Meubelzaken, Woning- And Keukeninrichting",
    "sg:phone":"+31 514 603 781",
    "sg:postcode":"8563 AM",
    "sg:province":"Provincie Friesland",
    "wof:name":"J.J. Mous",
    "wof:placetype":"venue"
},
  "geometry": {"coordinates":[5.624455,52.88665],"type":"Point"}
}