{
  "type": "Feature",
  "properties": {
    "addr:full":"Gracht 115 Spanga Friesland 8482 KJ",
    "addr:housenumber":"115",
    "addr:postcode":"8482 kj",
    "addr:street":"Gracht",
    "iso:country":"NL",
    "sg:address":"Gracht 115",
    "sg:city":"Spanga",
    "sg:orig_category":"Land- En Tuinbouw - Loonbedrijven",
    "sg:phone":"+31 561 481 372",
    "sg:postcode":"8482 KJ",
    "sg:province":"Friesland",
    "wof:name":"Boezerooy",
    "wof:placetype":"venue"
},
  "geometry": {"coordinates":[5.868079,52.811096],"type":"Point"}
}