{
  "type": "Feature",
  "properties": {
    "addr:full":"Schoutenboswg 4 Heerhugowaard Noord-Holland 1704 PM",
    "addr:housenumber":"4",
    "addr:postcode":"1704 pm",
    "addr:street":"Schoutenboswg",
    "iso:country":"NL",
    "sg:address":"Schoutenboswg 4",
    "sg:city":"Heerhugowaard",
    "sg:orig_category":"Bloemen En Planten",
    "sg:phone":"+31 226 342 538",
    "sg:postcode":"1704 PM",
    "sg:province":"Noord-Holland",
    "wof:name":"Midway Vof",
    "wof:placetype":"venue"
},
  "geometry": {"coordinates":[4.836455,52.709484],"type":"Point"}
}