{
  "type": "Feature",
  "properties": {
    "addr:full":"Veeartsenijstraat 208 Utrecht Utrecht 3572 DG",
    "addr:housenumber":"208",
    "addr:postcode":"3572 dg",
    "addr:street":"Veeartsenijstraat",
    "iso:country":"NL",
    "sg:address":"Veeartsenijstraat 208",
    "sg:city":"Utrecht",
    "sg:orig_category":"Diverse Grafische Activiteiten",
    "sg:phone":"+31 30 271 9576",
    "sg:postcode":"3572 DG",
    "sg:province":"Utrecht",
    "wof:name":"F Smulders",
    "wof:placetype":"venue"
},
  "geometry": {"coordinates":[5.13735,52.097179],"type":"Point"}
}