{
  "type": "Feature",
  "properties": {
    "addr:full":"Hallsewg 21 Hall Gelderland 6964 AJ",
    "addr:housenumber":"21",
    "addr:postcode":"6964 aj",
    "addr:street":"Hallsewg;Gelderland",
    "iso:country":"NL",
    "sg:address":"Hallsewg 21",
    "sg:city":"Hall",
    "sg:orig_category":"Grafische Machines",
    "sg:phone":"+31 313 671 720",
    "sg:postcode":"6964 AJ",
    "sg:province":"Gelderland",
    "sg:website":"http://www.drent.com",
    "wof:name":"Trend Graphic Services Bv",
    "wof:placetype":"venue"
},
  "geometry": {"coordinates":[-89.62702899999999,35.915657],"type":"Point"}
}