{
  "type": "Feature",
  "properties": {
    "iso:country":"NL",
    "sg:address":"Molendwstr 27",
    "sg:city":"Apeldoorn",
    "sg:orig_category":"Verhuur",
    "sg:phone":"+31 55 576 1974",
    "sg:postcode":"7311 MX",
    "sg:province":"Gelderland",
    "wof:name":"Avco",
    "wof:placetype":"venue"
},
  "geometry": {"coordinates":[5.970018,52.212372],"type":"Point"}
}