{
  "type": "Feature",
  "properties": {
    "addr:full":"Prinsengracht 629 Amsterdam Noord-Holland 1016 HV",
    "addr:housenumber":"629",
    "addr:postcode":"1016 hv",
    "addr:street":"Prinsengracht",
    "iso:country":"NL",
    "sg:address":"Prinsengracht 629",
    "sg:city":"Amsterdam",
    "sg:orig_category":"Binnenhuisarchitecten",
    "sg:phone":"+31 20 622 9375",
    "sg:postcode":"1016 HV",
    "sg:province":"Noord-Holland",
    "wof:name":"The Frozen Fountain Vof",
    "wof:placetype":"venue"
},
  "geometry": {"coordinates":[4.882939,52.367382],"type":"Point"}
}