{
  "type": "Feature",
  "properties": {
    "iso:country":"NL",
    "sg:address":"Springendalln 131",
    "sg:city":"Almere",
    "sg:orig_category":"Verenigingen En Stichtingen",
    "sg:phone":"+31 36 532 4697",
    "sg:postcode":"1333 XH",
    "sg:province":"Flevoland",
    "sg:website":"http://www.heartbeatcorvette.nl",
    "wof:name":"Corvette Club Ned",
    "wof:placetype":"venue"
},
  "geometry": {"coordinates":[5.269558,52.390354],"type":"Point"}
}