{
  "type": "Feature",
  "properties": {
    "addr:full":"Kotterstraat 8 Oosterend Nh Noord-Holland 1794 BE",
    "addr:housenumber":"8",
    "addr:postcode":"1794",
    "addr:street":"Kotterstraat",
    "iso:country":"NL",
    "sg:address":"Kotterstraat 8",
    "sg:city":"Oosterend Nh",
    "sg:orig_category":"Visserij",
    "sg:phone":"+31 222 318 357",
    "sg:postcode":"1794 BE",
    "sg:province":"Noord-Holland",
    "wof:name":"Firma A. Ellen En Zonen",
    "wof:placetype":"venue"
},
  "geometry": {"coordinates":[4.877799,53.086239],"type":"Point"}
}