{
  "type": "Feature",
  "properties": {
    "iso:country":"NL",
    "sg:address":"Napelshof 96",
    "sg:city":"Rotterdam",
    "sg:orig_category":"Manueel Therapeuten",
    "sg:phone":"+31 10 421 2354",
    "sg:postcode":"3067 WJ",
    "sg:province":"Zuid-Holland",
    "wof:name":"Mall\u00e9e, J H",
    "wof:placetype":"venue"
},
  "geometry": {"coordinates":[4.562496,51.944702],"type":"Point"}
}