{
  "type": "Feature",
  "properties": {
    "addr:full":"Leendert Hellenberghof 19 Noordwijk Zh Zuid-Holland 2202 XS",
    "addr:housenumber":"19",
    "addr:postcode":"2202 xs",
    "addr:street":"Leendert Hellenberghof",
    "iso:country":"NL",
    "sg:address":"Leendert Hellenberghof 19",
    "sg:city":"Noordwijk Zh",
    "sg:orig_category":"Koeriersdiensten",
    "sg:phone":"+31 6 55192308",
    "sg:postcode":"2202 XS",
    "sg:province":"Zuid-Holland",
    "wof:name":"De Ridder",
    "wof:placetype":"venue"
},
  "geometry": {"coordinates":[4.445121,52.249969],"type":"Point"}
}