{
  "type": "Feature",
  "properties": {
    "addr:full":"Kerkstr 205 Bg Amsterdam Noord-Holland 1017 GJ",
    "addr:housenumber":"205",
    "addr:postcode":"bg;1017 gj",
    "iso:country":"NL",
    "sg:address":"Kerkstr 205 Bg",
    "sg:city":"Amsterdam",
    "sg:orig_category":"Juweliers",
    "sg:phone":"+31 20 422 0648",
    "sg:postcode":"1017 GJ",
    "sg:province":"Noord-Holland",
    "wof:name":"Binenbaum",
    "wof:placetype":"venue"
},
  "geometry": {"coordinates":[4.893195,52.373119],"type":"Point"}
}