{
  "type": "Feature",
  "properties": {
    "addr:full":"Molenwieken 44 Veghel Noord-Brabant 5461 KG",
    "addr:housenumber":"44",
    "addr:postcode":"5461 kg",
    "addr:street":"Molenwieken",
    "iso:country":"NL",
    "sg:address":"Molenwieken 44",
    "sg:city":"Veghel",
    "sg:orig_category":"Juweliers",
    "sg:phone":"+31 413 343 962",
    "sg:postcode":"5461 KG",
    "sg:province":"Noord-Brabant",
    "wof:name":"Het Sierraadje Vof",
    "wof:placetype":"venue"
},
  "geometry": {"coordinates":[5.544252,51.616894],"type":"Point"}
}