{
  "type": "Feature",
  "properties": {
    "addr:full":"Herenstaat 17 Slagharen Overijssel 7776 AG",
    "addr:housenumber":"17",
    "addr:postcode":"7776",
    "addr:street":"Herenstaat",
    "iso:country":"NL",
    "sg:address":"Herenstaat 17",
    "sg:city":"Slagharen",
    "sg:orig_category":"Fietshandelaren",
    "sg:phone":"+31 523 681 333",
    "sg:postcode":"7776 AG",
    "sg:province":"Overijssel",
    "sg:website":"http://www.kosse.nl",
    "wof:name":"Vosse Instalatietechnieken",
    "wof:placetype":"venue"
},
  "geometry": {"coordinates":[6.55249,52.629036],"type":"Point"}
}