{
  "type": "Feature",
  "properties": {
    "addr:full":"Postbus 91 Nieuwerkerk Ad Ijssel South Holland 2910 AB",
    "addr:housenumber":"91",
    "addr:postcode":"2910 ab",
    "addr:street":"Postbus;Ijssel",
    "iso:country":"NL",
    "sg:address":"Postbus 91",
    "sg:city":"Nieuwerkerk Ad Ijssel",
    "sg:orig_category":"Bejaarden - Verzorgingstehuizen",
    "sg:phone":"+31 180 312 844",
    "sg:postcode":"2910 AB",
    "sg:province":"South Holland",
    "wof:name":"Chrysanthemum",
    "wof:placetype":"venue"
},
  "geometry": {"coordinates":[4.60531,51.969898],"type":"Point"}
}