{
  "type": "Feature",
  "properties": {
    "addr:full":"Zesstedenweg 165 Grootebroek Noord-Holland 1613 JD",
    "addr:housenumber":"165",
    "addr:postcode":"1613 jd",
    "addr:street":"Zesstedenweg",
    "iso:country":"NL",
    "sg:address":"Zesstedenweg 165",
    "sg:city":"Grootebroek",
    "sg:orig_category":"Drukkerijen And Copyshops",
    "sg:phone":"+31 228 530 110",
    "sg:postcode":"1613 JD",
    "sg:province":"Noord-Holland",
    "wof:name":"Rosier Gravimedia Bv",
    "wof:placetype":"venue"
},
  "geometry": {"coordinates":[5.221763,52.697468],"type":"Point"}
}