{
  "type": "Feature",
  "properties": {
    "iso:country":"NL",
    "sg:address":"Traay 114",
    "sg:city":"Driebergen Rysenb",
    "sg:orig_category":"Onderhoudswerken",
    "sg:phone":"+31 343 516 146",
    "sg:postcode":"3971 GS",
    "sg:province":"Utrecht",
    "wof:name":"Nellestijn",
    "wof:placetype":"venue"
},
  "geometry": {"coordinates":[5.291989,52.055557],"type":"Point"}
}