{
  "type": "Feature",
  "properties": {
    "addr:full":"Rederijkershoeve 111 Apeldoorn Gelderland 7326 TJ",
    "addr:housenumber":"111",
    "addr:postcode":"7326 tj",
    "addr:street":"Rederijkershoeve;Gelderland",
    "iso:country":"NL",
    "sg:address":"Rederijkershoeve 111",
    "sg:city":"Apeldoorn",
    "sg:orig_category":"Elektronische Bedrijfsinstallaties",
    "sg:phone":"+31 55 533 9550",
    "sg:postcode":"7326 TJ",
    "sg:province":"Gelderland",
    "wof:name":"L.F. Kolmus",
    "wof:placetype":"venue"
},
  "geometry": {"coordinates":[6.008562,52.192261],"type":"Point"}
}