{
  "type": "Feature",
  "properties": {
    "iso:country":"NL",
    "sg:address":"Vreekesweid 2",
    "sg:city":"Broek Op Langedijk",
    "sg:orig_category":"Vers Brood And Banket Fab",
    "sg:phone":"+31 226 331 100",
    "sg:postcode":"1721 PR",
    "sg:province":"North Holland",
    "wof:name":"De Aviateur Banketbakkerijen Bv",
    "wof:placetype":"venue"
},
  "geometry": {"coordinates":[4.793732,52.674656],"type":"Point"}
}