{
  "type": "Feature",
  "properties": {
    "iso:country":"NL",
    "sg:address":"Bruggelaan 64",
    "sg:city":"Appelscha",
    "sg:orig_category":"Boekhouders",
    "sg:phone":"+31 516 433 900",
    "sg:postcode":"8426 BH",
    "sg:province":"Provincie Friesland",
    "wof:name":"Heimstra",
    "wof:placetype":"venue"
},
  "geometry": {"coordinates":[6.340309,52.95623],"type":"Point"}
}