{
  "type": "Feature",
  "properties": {
    "addr:full":"Osdorpplein 773 Amsterdam North Holland 1068 TC",
    "addr:housenumber":"773",
    "addr:postcode":"1068 tc",
    "addr:street":"Osdorpplein",
    "iso:country":"NL",
    "sg:address":"Osdorpplein 773",
    "sg:city":"Amsterdam",
    "sg:classifiers":[
        {
            "category":"Shopping",
            "subcategory":"Gifts & Souvenirs",
            "type":"Retail Goods"
        }
    ],
    "sg:phone":"+31 20 619 5382",
    "sg:postcode":"1068 TC",
    "sg:province":"North Holland",
    "sg:tags":[
        "geschenken"
    ],
    "wof:name":"Gaby'S Giftshop",
    "wof:placetype":"venue"
},
  "geometry": {"coordinates":[4.806687,52.358608],"type":"Point"}
}