{
  "type": "Feature",
  "properties": {
    "addr:full":"Den Ekkert 3 Herten Limburg 6049 KK",
    "addr:housenumber":"3",
    "addr:postcode":"6049 kk",
    "addr:street":"Den Ekkert",
    "iso:country":"NL",
    "sg:address":"Den Ekkert 3",
    "sg:city":"Herten",
    "sg:orig_category":"Wegen And Sportterreinen",
    "sg:phone":"+31 475 310 701",
    "sg:postcode":"6049 KK",
    "sg:province":"Limburg",
    "wof:name":"Esser Bv",
    "wof:placetype":"venue"
},
  "geometry": {"coordinates":[5.9605369568,51.1803131104],"type":"Point"}
}