{
  "type": "Feature",
  "properties": {
    "iso:country":"NL",
    "sg:address":"Cornelis Groenlandstraat 16",
    "sg:city":"Heemskerk",
    "sg:orig_category":"Loodgieterswerk, Verwarming And Sanitaire Installaties",
    "sg:phone":"+31 251 237 192",
    "sg:postcode":"1962 TG",
    "sg:province":"North Holland",
    "wof:name":"Loodgieters En Cv Bedrijf G.F. Bruins Bv",
    "wof:placetype":"venue"
},
  "geometry": {"coordinates":[4.674949,52.509933],"type":"Point"}
}