{
  "type": "Feature",
  "properties": {
    "addr:full":"Klinkenberg 51 Meerssen Limburg 6231 BA",
    "addr:housenumber":"51",
    "addr:postcode":"6231 ba",
    "addr:street":"Klinkenberg",
    "iso:country":"NL",
    "sg:address":"Klinkenberg 51",
    "sg:city":"Meerssen",
    "sg:orig_category":"Kegelbanen",
    "sg:phone":"+31 43 364 2731",
    "sg:postcode":"6231 BA",
    "sg:province":"Limburg",
    "wof:name":"Auwd Rothem",
    "wof:placetype":"venue"
},
  "geometry": {"coordinates":[5.736127,50.876774],"type":"Point"}
}