{
  "type": "Feature",
  "properties": {
    "iso:country":"NL",
    "sg:address":"Ryzendewg 6",
    "sg:city":"Woensdrecht",
    "sg:orig_category":"Boekbinderijen",
    "sg:phone":"+31 164 614 915",
    "sg:postcode":"4634 TX",
    "sg:province":"Noord-Brabant",
    "wof:name":"Verraes",
    "wof:placetype":"venue"
},
  "geometry": {"coordinates":[4.29925,51.429176],"type":"Point"}
}