{
  "type": "Feature",
  "properties": {
    "addr:full":"J J V Deinsestr 50 Oldenzaal NL.08 7576 VV",
    "addr:housenumber":"50;nl.08",
    "addr:postcode":"7576 vv",
    "addr:street":"V Deinsestr",
    "iso:country":"NL",
    "sg:address":"J J V Deinsestr 50",
    "sg:city":"Oldenzaal",
    "sg:orig_category":"Vertaalbureaus",
    "sg:phone":"+31 541 530 744",
    "sg:postcode":"7576 VV",
    "sg:province":"NL.08",
    "wof:name":"Intercommunication",
    "wof:placetype":"venue"
},
  "geometry": {"coordinates":[6.927277,52.309284],"type":"Point"}
}