{
  "type": "Feature",
  "properties": {
    "iso:country":"NL",
    "sg:address":"Akoleienstr 6",
    "sg:city":"Amsterdam",
    "sg:orig_category":"Verenigingen En Stichtingen",
    "sg:phone":"+31 20 626 0439",
    "sg:postcode":"1016 LN",
    "sg:province":"North Holland",
    "wof:name":"Ingeborgpop Pop En Theater",
    "wof:placetype":"venue"
},
  "geometry": {"coordinates":[4.878028,52.373062],"type":"Point"}
}