{
  "type": "Feature",
  "properties": {
    "addr:full":"Dorpsstraat 87 Wormer North Holland 1531  H",
    "addr:housenumber":"87;1531 h",
    "addr:street":"Dorpsstraat",
    "iso:country":"NL",
    "sg:address":"Dorpsstraat 87",
    "sg:city":"Wormer",
    "sg:orig_category":"Boekenuitgeverijen",
    "sg:phone":"+31 75 642 0165",
    "sg:postcode":"1531  H",
    "sg:province":"North Holland",
    "wof:name":"Bruna",
    "wof:placetype":"venue"
},
  "geometry": {"coordinates":[4.814151,52.498981],"type":"Point"}
}