{
  "type": "Feature",
  "properties": {
    "iso:country":"NL",
    "sg:address":"Prins Frederiklaan 10",
    "sg:city":"Amersfoort",
    "sg:orig_category":"Krantenuitgeverijen",
    "sg:phone":"+31 33 461 3718",
    "sg:postcode":"3818 KC",
    "sg:province":"Utrecht",
    "wof:name":"Museum Cards Bv",
    "wof:placetype":"venue"
},
  "geometry": {"coordinates":[5.370812,52.148312],"type":"Point"}
}