{
  "type": "Feature",
  "properties": {
    "addr:full":"Dr V Raaltestr 23 Ommen NL.08 7731 GP",
    "addr:housenumber":"23;nl.08",
    "addr:postcode":"7731 gp",
    "addr:street":"Dr;Raaltestr",
    "iso:country":"NL",
    "sg:address":"Dr V Raaltestr 23",
    "sg:city":"Ommen",
    "sg:orig_category":"Verenigingen En Stichtingen",
    "sg:phone":"+31 529 452 597",
    "sg:postcode":"7731 GP",
    "sg:province":"NL.08",
    "wof:name":"Dunamis, Sticht",
    "wof:placetype":"venue"
},
  "geometry": {"coordinates":[6.42297,52.517754],"type":"Point"}
}