{
  "type": "Feature",
  "properties": {
    "addr:full":"Osseveldweg 29 Apeldoorn Gelderland 7321 CN",
    "addr:housenumber":"29",
    "addr:postcode":"7321 cn",
    "addr:street":"Osseveldweg;Gelderland",
    "iso:country":"NL",
    "sg:address":"Osseveldweg 29",
    "sg:city":"Apeldoorn",
    "sg:orig_category":"Bloemen And Planten",
    "sg:phone":"+31 55 366 6347",
    "sg:postcode":"7321 CN",
    "sg:province":"Gelderland",
    "wof:name":"L Van Maanen",
    "wof:placetype":"venue"
},
  "geometry": {"coordinates":[5.992821,52.214996],"type":"Point"}
}