{
  "type": "Feature",
  "properties": {
    "addr:full":"Huigenbos 32 Amsterdam Zuidoost Noord-Holland 1102 KA",
    "addr:housenumber":"32",
    "addr:postcode":"zuidoost;1102 ka",
    "addr:street":"Huigenbos",
    "iso:country":"NL",
    "sg:address":"Huigenbos 32",
    "sg:city":"Amsterdam Zuidoost",
    "sg:orig_category":"Bedrijfs- And Managementsconsultants",
    "sg:phone":"+31 20 691 2214",
    "sg:postcode":"1102 KA",
    "sg:province":"Noord-Holland",
    "wof:name":"Y. Buma Communicatie En Advies",
    "wof:placetype":"venue"
},
  "geometry": {"coordinates":[4.960014,52.306923],"type":"Point"}
}