{
  "type": "Feature",
  "properties": {
    "addr:full":"Dekemastate 17 Huizen North Holland 1275 CM",
    "addr:housenumber":"17",
    "addr:postcode":"1275 cm",
    "addr:street":"Dekemastate",
    "iso:country":"NL",
    "sg:address":"Dekemastate 17",
    "sg:city":"Huizen",
    "sg:orig_category":"Keukens",
    "sg:phone":"+31 35 628 4151",
    "sg:postcode":"1275 CM",
    "sg:province":"North Holland",
    "sg:website":"http://www.holidaykeukens.nl",
    "wof:name":"Holiday",
    "wof:placetype":"venue"
},
  "geometry": {"coordinates":[5.262895,52.289978],"type":"Point"}
}