{
  "type": "Feature",
  "properties": {
    "iso:country":"NL",
    "sg:address":"Energieweg 45",
    "sg:city":"Alphen A/D Rijn",
    "sg:orig_category":"Bouwmaterialen Gh",
    "sg:phone":"+31 172 241 515",
    "sg:postcode":"2404 HE",
    "sg:province":"Zuid-Holland",
    "wof:name":"Rakon Bouwprofiel Bv",
    "wof:placetype":"venue"
},
  "geometry": {"coordinates":[4.644576,52.13979],"type":"Point"}
}