{
  "type": "Feature",
  "properties": {
    "addr:full":"Dr Benthemstr 29 Enschede NL.08 7514 CK",
    "addr:housenumber":"29",
    "addr:postcode":"7514 ck",
    "iso:country":"NL",
    "sg:address":"Dr Benthemstr 29",
    "sg:city":"Enschede",
    "sg:orig_category":"Verenigingen En Stichtingen",
    "sg:phone":"+31 53 435 1078",
    "sg:postcode":"7514 CK",
    "sg:province":"NL.08",
    "wof:name":"Islam Ver Enschede",
    "wof:placetype":"venue"
},
  "geometry": {"coordinates":[6.893065,52.225571],"type":"Point"}
}