{
  "type": "Feature",
  "properties": {
    "iso:country":"NL",
    "sg:address":"De Ryn 2",
    "sg:city":"Best",
    "sg:orig_category":"Verlichting",
    "sg:phone":"+31 499 339 444",
    "sg:postcode":"5684 PJ",
    "sg:province":"Noord-Brabant",
    "sg:website":"http://www.lumileds.com",
    "wof:name":"Lumileds Lighting Bv",
    "wof:placetype":"venue"
},
  "geometry": {"coordinates":[-101.45208700000001,31.191275],"type":"Point"}
}