{
  "type": "Feature",
  "properties": {
    "addr:full":"Flemingstr 140 Zandvoort Noord-Holland 2041 VM",
    "addr:housenumber":"140",
    "addr:postcode":"2041 vm",
    "addr:street":"Zandvoort",
    "iso:country":"NL",
    "sg:address":"Flemingstr 140",
    "sg:city":"Zandvoort",
    "sg:orig_category":"Geluidsinstallaties - Verhuur",
    "sg:phone":"+31 23 571 7832",
    "sg:postcode":"2041 VM",
    "sg:province":"Noord-Holland",
    "sg:website":"http://goedh@euronet.nl",
    "wof:name":"Goedhart Audio",
    "wof:placetype":"venue"
},
  "geometry": {"coordinates":[4.548603,52.378166],"type":"Point"}
}