{
  "type": "Feature",
  "properties": {
    "addr:full":"De Clercqstr 27 Amsterdam Noord-Holland 1053 AA",
    "addr:housenumber":"27",
    "addr:postcode":"1053 aa",
    "iso:country":"NL",
    "sg:address":"De Clercqstr 27",
    "sg:city":"Amsterdam",
    "sg:orig_category":"Beeldende Kunstenaars",
    "sg:phone":"+31 20 618 1969",
    "sg:postcode":"1053 AA",
    "sg:province":"Noord-Holland",
    "wof:name":"Joop Rooijers",
    "wof:placetype":"venue"
},
  "geometry": {"coordinates":[4.87253,52.371361],"type":"Point"}
}