{
  "type": "Feature",
  "properties": {
    "addr:full":"Zonnedauw 1 Sneek Provincie Friesland 8607 DX",
    "addr:housenumber":"1",
    "addr:postcode":"8607 dx",
    "addr:street":"Zonnedauw;Provincie Friesland",
    "iso:country":"NL",
    "sg:address":"Zonnedauw 1",
    "sg:city":"Sneek",
    "sg:orig_category":"Bloemen And Planten",
    "sg:phone":"+31 515 423 474",
    "sg:postcode":"8607 DX",
    "sg:province":"Provincie Friesland",
    "wof:name":"Europatuin Sneek",
    "wof:placetype":"venue"
},
  "geometry": {"coordinates":[5.664118,53.019974],"type":"Point"}
}