{
  "type": "Feature",
  "properties": {
    "iso:country":"NL",
    "sg:address":"Zonnedauw 1",
    "sg:city":"Sneek",
    "sg:orig_category":"Bloemen And Planten",
    "sg:phone":"+31 515 423 474",
    "sg:postcode":"8607 DX",
    "sg:province":"Provincie Friesland",
    "wof:name":"Europatuin Sneek",
    "wof:placetype":"venue"
},
  "geometry": {"coordinates":[5.664118,53.019974],"type":"Point"}
}