{
  "type": "Feature",
  "properties": {
    "addr:full":"Populierenlaan 146 Krimpen A/D Ijssel Zuid-Holland 2925 CV",
    "addr:housenumber":"146;a / d",
    "addr:postcode":"2925 cv",
    "addr:street":"Populierenlaan;Krimpen",
    "iso:country":"NL",
    "sg:address":"Populierenlaan 146",
    "sg:city":"Krimpen A/D Ijssel",
    "sg:classifiers":[
        {
            "category":"Fast Food",
            "type":"Food & Drink"
        }
    ],
    "sg:phone":"+31 180 520 421",
    "sg:postcode":"2925 CV",
    "sg:province":"Zuid-Holland",
    "sg:tags":[
        "afhaal",
        "restaurant"
    ],
    "wof:name":"Snackbar De Krim",
    "wof:placetype":"venue"
},
  "geometry": {"coordinates":[4.616843,51.914593],"type":"Point"}
}