{
  "type": "Feature",
  "properties": {
    "addr:full":"Oude Doesburgsewg 9-11 Zevenaar Gelderland 6901 HG",
    "addr:housenumber":"9-11",
    "addr:postcode":"6901 hg",
    "addr:street":"Oude Doesburgsewg",
    "iso:country":"NL",
    "sg:address":"Oude Doesburgsewg 9-11",
    "sg:city":"Zevenaar",
    "sg:orig_category":"Notarissen En Notariskantoren",
    "sg:phone":"+31 316 524 948",
    "sg:postcode":"6901 HG",
    "sg:province":"Gelderland",
    "wof:name":"Hasperhoven En Prick",
    "wof:placetype":"venue"
},
  "geometry": {"coordinates":[6.076816,51.931492],"type":"Point"}
}