{
  "type": "Feature",
  "properties": {
    "addr:full":"Jupiterln 71 Dordrecht Zuid-Holland 3318 JC",
    "addr:housenumber":"71",
    "addr:postcode":"3318 jc",
    "addr:street":"Jupiterln",
    "iso:country":"NL",
    "sg:address":"Jupiterln 71",
    "sg:city":"Dordrecht",
    "sg:orig_category":"Hulpverlening Sociaal",
    "sg:phone":"+31 78 651 2941",
    "sg:postcode":"3318 JC",
    "sg:province":"Zuid-Holland",
    "wof:name":"Auriga",
    "wof:placetype":"venue"
},
  "geometry": {"coordinates":[4.656506,51.811916],"type":"Point"}
}