{
  "type": "Feature",
  "properties": {
    "iso:country":"NL",
    "sg:address":"Egginkskamp 15",
    "sg:city":"Eefde",
    "sg:orig_category":"Horloges En Klokken - Reparatie En Onderhoud",
    "sg:phone":"+31 575 540 180",
    "sg:postcode":"7211 CW",
    "sg:province":"Gelderland",
    "wof:name":"Heuven, P Van",
    "wof:placetype":"venue"
},
  "geometry": {"coordinates":[6.229696,52.169987],"type":"Point"}
}