{
  "type": "Feature",
  "properties": {
    "addr:full":"Breestraat 77 Leiden Zuid-Holland 2311 CJ",
    "addr:housenumber":"77",
    "addr:postcode":"2311 cj",
    "addr:street":"Breestraat",
    "iso:country":"NL",
    "sg:address":"Breestraat 77",
    "sg:city":"Leiden",
    "sg:orig_category":"Schoenen",
    "sg:phone":"+31 71 512 1189",
    "sg:postcode":"2311 CJ",
    "sg:province":"Zuid-Holland",
    "wof:name":"Manfield",
    "wof:placetype":"venue"
},
  "geometry": {"coordinates":[4.489015,52.159042],"type":"Point"}
}