{
  "type": "Feature",
  "properties": {
    "iso:country":"NL",
    "sg:address":"Herenstraat 10",
    "sg:city":"Rhenen",
    "sg:orig_category":"Opticiens",
    "sg:phone":"+31 317 612 701",
    "sg:postcode":"3911 JE",
    "sg:province":"Utrecht",
    "wof:name":"Bos Brillen Bv",
    "wof:placetype":"venue"
},
  "geometry": {"coordinates":[5.5668010712,51.9575119019],"type":"Point"}
}