{
  "type": "Feature",
  "properties": {
    "addr:full":"Sluispolderwg 25A Zaandam Noord-Holland 1505 HJ",
    "addr:housenumber":"25a",
    "addr:postcode":"1505 hj",
    "addr:street":"Sluispolderwg",
    "iso:country":"NL",
    "sg:address":"Sluispolderwg 25A",
    "sg:city":"Zaandam",
    "sg:orig_category":"Kunststoffen- Verwerkende Industrie",
    "sg:phone":"+31 75 616 3900",
    "sg:postcode":"1505 HJ",
    "sg:province":"Noord-Holland",
    "sg:website":"http://www.kesta.nl",
    "wof:name":"Kesta",
    "wof:placetype":"venue"
},
  "geometry": {"coordinates":[4.857177,52.422619],"type":"Point"}
}