{
  "type": "Feature",
  "properties": {
    "iso:country":"NL",
    "sg:address":"Dorpsweg 173",
    "sg:city":"Rotterdam",
    "sg:orig_category":"Wasserettes And Stomerijen",
    "sg:phone":"+31 10 429 4190",
    "sg:postcode":"3082 LK",
    "sg:province":"South Holland",
    "wof:name":"De Stomerij",
    "wof:placetype":"venue"
},
  "geometry": {"coordinates":[4.4714069366,51.8873443604],"type":"Point"}
}