{
  "type": "Feature",
  "properties": {
    "addr:full":"Bosweg 17 'T Zand Nh North Holland 1756 CH",
    "addr:housenumber":"17",
    "addr:postcode":"1756",
    "addr:street":"Bosweg",
    "iso:country":"NL",
    "sg:address":"Bosweg 17",
    "sg:city":"'T Zand Nh",
    "sg:orig_category":"Bloemen- And Plantenteelt",
    "sg:phone":"+31 224 571 323",
    "sg:postcode":"1756 CH",
    "sg:province":"North Holland",
    "wof:name":"D. Van Diepen En Zonen",
    "wof:placetype":"venue"
},
  "geometry": {"coordinates":[4.737669,52.82753],"type":"Point"}
}