{
  "type": "Feature",
  "properties": {
    "addr:full":"Postbus 5282 Arnhem Noord-Brabant 6802 EG",
    "addr:housenumber":"5282",
    "addr:postcode":"6802 eg",
    "addr:street":"Postbus",
    "iso:country":"NL",
    "sg:address":"Postbus 5282",
    "sg:city":"Arnhem",
    "sg:orig_category":"Projectontwikkeling",
    "sg:phone":"+31 26 370 5576",
    "sg:postcode":"6802 EG",
    "sg:province":"Noord-Brabant",
    "wof:name":"Westerbeek Vof",
    "wof:placetype":"venue"
},
  "geometry": {"coordinates":[5.9124,51.979729],"type":"Point"}
}