{
  "type": "Feature",
  "properties": {
    "iso:country":"NL",
    "sg:address":"Burgemeester Van Reenensingel 121",
    "sg:city":"Gouda",
    "sg:orig_category":"Verhuur Bouwmachines",
    "sg:phone":"+31 182 565 555",
    "sg:postcode":"2803 PA",
    "sg:province":"South Holland",
    "sg:website":"http://www.nederhoff.nl",
    "wof:name":"Kraanbedrijf Nederhoff Bv",
    "wof:placetype":"venue"
},
  "geometry": {"coordinates":[4.680554,52.022396],"type":"Point"}
}