{
  "type": "Feature",
  "properties": {
    "addr:full":"Molenstr 24 Lochem Gelderland 7241 AE",
    "addr:housenumber":"24",
    "addr:postcode":"7241 ae",
    "addr:street":"Molenstr;Gelderland",
    "iso:country":"NL",
    "sg:address":"Molenstr 24",
    "sg:city":"Lochem",
    "sg:orig_category":"Zoetwaren - Winkels",
    "sg:phone":"+31 573 252 900",
    "sg:postcode":"7241 AE",
    "sg:province":"Gelderland",
    "wof:name":"Merwe Vof, Van De",
    "wof:placetype":"venue"
},
  "geometry": {"coordinates":[6.417198,52.161896],"type":"Point"}
}