{
  "type": "Feature",
  "properties": {
    "addr:full":"Burg M V Veenln 118 Enschede Overijssel 7543 AB",
    "addr:housenumber":"118",
    "addr:postcode":"7543 ab",
    "addr:street":"Burg",
    "iso:country":"NL",
    "sg:address":"Burg M V Veenln 118",
    "sg:city":"Enschede",
    "sg:orig_category":"Kappers",
    "sg:phone":"+31 53 476 3242",
    "sg:postcode":"7543 AB",
    "sg:province":"Overijssel",
    "wof:name":"Achterberg, J D",
    "wof:placetype":"venue"
},
  "geometry": {"coordinates":[6.878757,52.2055778503],"type":"Point"}
}