{
  "type": "Feature",
  "properties": {
    "addr:full":"Wiersse 36 Doetinchem Gelderland 7006 HX",
    "addr:housenumber":"36",
    "addr:postcode":"7006 hx",
    "addr:street":"Wiersse;Gelderland",
    "iso:country":"NL",
    "sg:address":"Wiersse 36",
    "sg:city":"Doetinchem",
    "sg:orig_category":"Pijpleidingen - Installatie En Onderhoud",
    "sg:phone":"+31 314 335 666",
    "sg:postcode":"7006 HX",
    "sg:province":"Gelderland",
    "wof:name":"Kloppenburg, B",
    "wof:placetype":"venue"
},
  "geometry": {"coordinates":[6.263558,51.963257],"type":"Point"}
}