{
  "type": "Feature",
  "properties": {
    "iso:country":"NL",
    "sg:address":"Straelsewg 193",
    "sg:city":"Venlo",
    "sg:orig_category":"Artsen - Huisartsen",
    "sg:phone":"+31 77 351 7652",
    "sg:postcode":"5914 AL",
    "sg:province":"Limburg",
    "wof:name":"Gezondheidscentrum Withuis",
    "wof:placetype":"venue"
},
  "geometry": {"coordinates":[6.181544,51.378433],"type":"Point"}
}