{
  "type": "Feature",
  "properties": {
    "addr:full":"De Linie 1 Capelle Ad Yssel South Holland 2905 AX",
    "addr:housenumber":"1",
    "addr:postcode":"2905 ax",
    "addr:street":"De Linie;Yssel",
    "iso:country":"NL",
    "sg:address":"De Linie 1",
    "sg:city":"Capelle Ad Yssel",
    "sg:orig_category":"Verzekeringen - Verzekeringskantoren",
    "sg:phone":"+31 10 451 1447",
    "sg:postcode":"2905 AX",
    "sg:province":"South Holland",
    "sg:website":"http://www.axi-plan.nl",
    "wof:name":"Axi-Plan Adviesgroep",
    "wof:placetype":"venue"
},
  "geometry": {"coordinates":[4.597194,51.93409],"type":"Point"}
}