{
  "type": "Feature",
  "properties": {
    "addr:full":"Buitendijk 4 Helmond North Brabant 5705 CD",
    "addr:housenumber":"4",
    "addr:postcode":"5705 cd",
    "addr:street":"Buitendijk",
    "iso:country":"NL",
    "sg:address":"Buitendijk 4",
    "sg:city":"Helmond",
    "sg:orig_category":"Autokeuringen",
    "sg:phone":"+31 492 534 349",
    "sg:postcode":"5705 CD",
    "sg:province":"North Brabant",
    "wof:name":"Helmondse Motoren Revisie Bv",
    "wof:placetype":"venue"
},
  "geometry": {"coordinates":[5.68343,51.469692],"type":"Point"}
}