{
  "type": "Feature",
  "properties": {
    "iso:country":"NL",
    "sg:address":"Meeuwenln 23",
    "sg:city":"Nieuwerkerk",
    "sg:orig_category":"Adviesbureaus Bedrijfsorganisatie",
    "sg:phone":"+31 111 647 046",
    "sg:postcode":"4306 BS",
    "sg:province":"Zeeland",
    "wof:name":"Trema",
    "wof:placetype":"venue"
},
  "geometry": {"coordinates":[3.997004,51.646664],"type":"Point"}
}