{
  "type": "Feature",
  "properties": {
    "addr:full":"Merendreef 2 Valkenswaard North Brabant 5553 CD",
    "addr:housenumber":"2",
    "addr:postcode":"5553 cd",
    "addr:street":"Merendreef",
    "iso:country":"NL",
    "sg:address":"Merendreef 2",
    "sg:city":"Valkenswaard",
    "sg:orig_category":"Zoetwaren - Fabrieken En Groothandel",
    "sg:phone":"+31 40 204 2932",
    "sg:postcode":"5553 CD",
    "sg:province":"North Brabant",
    "wof:name":"Better & More",
    "wof:placetype":"venue"
},
  "geometry": {"coordinates":[5.463705,51.361847],"type":"Point"}
}