{
  "type": "Feature",
  "properties": {
    "addr:full":"Tolnegenweg 31 Stroe Gelderland 3776 PT",
    "addr:housenumber":"31",
    "addr:postcode":"3776",
    "addr:street":"Tolnegenweg;Gelderland;Pt",
    "iso:country":"NL",
    "sg:address":"Tolnegenweg 31",
    "sg:city":"Stroe",
    "sg:orig_category":"Loodgieterswerk, Verwarming And Sanitaire Installaties",
    "sg:phone":"+31 342 441 528",
    "sg:postcode":"3776 PT",
    "sg:province":"Gelderland",
    "wof:name":"R. Soetendaal",
    "wof:placetype":"venue"
},
  "geometry": {"coordinates":[5.686749,52.190128],"type":"Point"}
}