{
  "type": "Feature",
  "properties": {
    "addr:full":"Groot Hertoginnelaan 42 'S Gravenhage Zuid-Holland 2517 EH",
    "addr:housenumber":"42",
    "addr:postcode":"2517 eh",
    "addr:street":"Groot Hertoginnelaan;' S",
    "iso:country":"NL",
    "sg:address":"Groot Hertoginnelaan 42",
    "sg:city":"'S Gravenhage",
    "sg:classifiers":[
        {
            "category":"Travel",
            "subcategory":"Hotels & Motels",
            "type":"Entertainment"
        }
    ],
    "sg:phone":"+31 70 346 5500",
    "sg:postcode":"2517 EH",
    "sg:province":"Zuid-Holland",
    "wof:name":"Hotel Petit",
    "wof:placetype":"venue"
},
  "geometry": {"coordinates":[4.286224,52.085125],"type":"Point"}
}