{
  "type": "Feature",
  "properties": {
    "addr:full":"Simon Stevinweg 23 Arnhem Gelderland 6827 BS",
    "addr:housenumber":"23",
    "addr:postcode":"6827 bs",
    "addr:street":"Simon Stevinweg",
    "iso:country":"NL",
    "sg:address":"Simon Stevinweg 23",
    "sg:city":"Arnhem",
    "sg:orig_category":"Medische And Orthopedische Artikelen",
    "sg:phone":"+31 26 361 6741",
    "sg:postcode":"6827 BS",
    "sg:province":"Gelderland",
    "wof:name":"Welzorg Revalidatie Techniek",
    "wof:placetype":"venue"
},
  "geometry": {"coordinates":[5.943485,51.973675],"type":"Point"}
}