{
  "type": "Feature",
  "properties": {
    "addr:full":"Kerkstr 293A Gaanderen Gelderland 7011 CN",
    "addr:housenumber":"293a",
    "addr:postcode":"7011 cn",
    "addr:street":"Gelderland",
    "iso:country":"NL",
    "sg:address":"Kerkstr 293A",
    "sg:city":"Gaanderen",
    "sg:orig_category":"Hondenscholen",
    "sg:phone":"+31 315 327 691",
    "sg:postcode":"7011 CN",
    "sg:province":"Gelderland",
    "wof:name":"Mens En Hond Consultancy",
    "wof:placetype":"venue"
},
  "geometry": {"coordinates":[6.358469,51.926655],"type":"Point"}
}