{
  "type": "Feature",
  "properties": {
    "addr:full":"De Liesbosch 12 L Nieuwegein Utrecht 3439 LC",
    "addr:housenumber":"12 l",
    "addr:postcode":"3439 lc",
    "addr:street":"De Liesbosch",
    "iso:country":"NL",
    "sg:address":"De Liesbosch 12 L",
    "sg:city":"Nieuwegein",
    "sg:orig_category":"Koeriersdiensten",
    "sg:phone":"+31 30 280 2308",
    "sg:postcode":"3439 LC",
    "sg:province":"Utrecht",
    "sg:website":"http://www.aone.nl",
    "wof:name":"A-One Spoedkoeriers",
    "wof:placetype":"venue"
},
  "geometry": {"coordinates":[5.082197,52.027325],"type":"Point"}
}