{
  "type": "Feature",
  "properties": {
    "addr:full":"Lievevrouwestr 23 Bergen Op Zoom North Brabant 4611 JJ",
    "addr:housenumber":"23",
    "addr:postcode":"4611 jj",
    "addr:street":"Lievevrouwestr",
    "iso:country":"NL",
    "sg:address":"Lievevrouwestr 23",
    "sg:city":"Bergen Op Zoom",
    "sg:orig_category":"Modelbouw",
    "sg:phone":"+31 164 210 887",
    "sg:postcode":"4611 JJ",
    "sg:province":"North Brabant",
    "sg:website":"http://www.harskamp.com",
    "wof:name":"Harskamp Hobbycentre Bv",
    "wof:placetype":"venue"
},
  "geometry": {"coordinates":[4.283756,51.494968],"type":"Point"}
}