{
  "type": "Feature",
  "properties": {
    "addr:full":"Noard 74 Workum Friesland 8711 AK",
    "addr:housenumber":"74",
    "addr:postcode":"8711 ak",
    "addr:street":"Noard",
    "iso:country":"NL",
    "sg:address":"Noard 74",
    "sg:city":"Workum",
    "sg:orig_category":"Handelscentra",
    "sg:phone":"+31 515 542 414",
    "sg:postcode":"8711 AK",
    "sg:province":"Friesland",
    "wof:name":"Kuipers",
    "wof:placetype":"venue"
},
  "geometry": {"coordinates":[5.445506,52.981266],"type":"Point"}
}