{
  "type": "Feature",
  "properties": {
    "addr:full":"Liendenln 123 Tiel Gelderland 4006 CD",
    "addr:housenumber":"123",
    "addr:postcode":"4006 cd",
    "addr:street":"Gelderland",
    "iso:country":"NL",
    "sg:address":"Liendenln 123",
    "sg:city":"Tiel",
    "sg:orig_category":"Administratie- En Boekhoudkantoren",
    "sg:phone":"+31 344 612 242",
    "sg:postcode":"4006 CD",
    "sg:province":"Gelderland",
    "wof:name":"Doesburg, J Van",
    "wof:placetype":"venue"
},
  "geometry": {"coordinates":[5.430696,51.888096],"type":"Point"}
}