{
  "type": "Feature",
  "properties": {
    "addr:full":"Amsterdamsestraatweg 322F Utrecht Utrecht 3551 CV",
    "addr:housenumber":"322f",
    "addr:postcode":"3551 cv",
    "addr:street":"Amsterdamsestraatweg",
    "iso:country":"NL",
    "sg:address":"Amsterdamsestraatweg 322F",
    "sg:city":"Utrecht",
    "sg:orig_category":"Erotische Etablissementen",
    "sg:phone":"+31 30 242 2387",
    "sg:postcode":"3551 CV",
    "sg:province":"Utrecht",
    "wof:name":"Sangphim",
    "wof:placetype":"venue"
},
  "geometry": {"coordinates":[5.097051,52.102257],"type":"Point"}
}