{
  "type": "Feature",
  "properties": {
    "addr:full":"Keizersgr 560-562 Amsterdam North Holland 1017 EM",
    "addr:housenumber":"560-562",
    "addr:postcode":"1017 em",
    "iso:country":"NL",
    "sg:address":"Keizersgr 560-562",
    "sg:city":"Amsterdam",
    "sg:orig_category":"Adviesbureaus Bedrijfsorganisatie",
    "sg:phone":"+31 20 626 1911",
    "sg:postcode":"1017 EM",
    "sg:province":"North Holland",
    "wof:name":"Vdv Bv",
    "wof:placetype":"venue"
},
  "geometry": {"coordinates":[4.887855,52.364708],"type":"Point"}
}