{
  "type": "Feature",
  "properties": {
    "addr:full":"Tweevoren 23 Nuenen Noord-Brabant 5672 SB",
    "addr:housenumber":"23",
    "addr:postcode":"5672 sb",
    "addr:street":"Tweevoren",
    "iso:country":"NL",
    "sg:address":"Tweevoren 23",
    "sg:city":"Nuenen",
    "sg:orig_category":"Public Relationbureaus",
    "sg:phone":"+31 40 211 6626",
    "sg:postcode":"5672 SB",
    "sg:province":"Noord-Brabant",
    "wof:name":"A.D.G. Trachsel",
    "wof:placetype":"venue"
},
  "geometry": {"coordinates":[5.554568,51.463169],"type":"Point"}
}