{
  "type": "Feature",
  "properties": {
    "addr:full":"Axelsestraat 16 Terneuzen Zeeland 4537 AK",
    "addr:housenumber":"16",
    "addr:postcode":"4537 ak",
    "addr:street":"Axelsestraat",
    "iso:country":"NL",
    "sg:address":"Axelsestraat 16",
    "sg:city":"Terneuzen",
    "sg:orig_category":"Krantenuitgeverijen",
    "sg:phone":"+31 115 686 000",
    "sg:postcode":"4537 AK",
    "sg:province":"Zeeland",
    "wof:name":"Uitgeverij Provinciale Zeeuwse Courant B",
    "wof:placetype":"venue"
},
  "geometry": {"coordinates":[3.830557,51.333801],"type":"Point"}
}