{
  "type": "Feature",
  "properties": {
    "iso:country":"NL",
    "sg:address":"Parmentierstr 2",
    "sg:city":"Beverwijk",
    "sg:orig_category":"Verenigingsgebouwen",
    "sg:phone":"+31 251 238 067",
    "sg:postcode":"1945 XC",
    "sg:province":"Noord-Holland",
    "wof:name":"Centro Espanol",
    "wof:placetype":"venue"
},
  "geometry": {"coordinates":[4.666013,52.499352],"type":"Point"}
}