{
  "type": "Feature",
  "properties": {
    "addr:full":"Parmentierstr 2 Beverwijk Noord-Holland 1945 XC",
    "addr:housenumber":"2",
    "addr:postcode":"1945 xc",
    "addr:street":"Parmentierstr",
    "iso:country":"NL",
    "sg:address":"Parmentierstr 2",
    "sg:city":"Beverwijk",
    "sg:orig_category":"Verenigingsgebouwen",
    "sg:phone":"+31 251 238 067",
    "sg:postcode":"1945 XC",
    "sg:province":"Noord-Holland",
    "wof:name":"Centro Espanol",
    "wof:placetype":"venue"
},
  "geometry": {"coordinates":[4.666013,52.499352],"type":"Point"}
}