{
  "type": "Feature",
  "properties": {
    "addr:full":"Adelaarstraat 23 Utrecht Utrecht 3514 CA",
    "addr:housenumber":"23",
    "addr:postcode":"3514 ca",
    "addr:street":"Adelaarstraat",
    "iso:country":"NL",
    "sg:address":"Adelaarstraat 23",
    "sg:city":"Utrecht",
    "sg:classifiers":[
        {
            "category":"Bars & Pubs",
            "type":"Food & Drink"
        }
    ],
    "sg:phone":"+31 30 271 3680",
    "sg:postcode":"3514 CA",
    "sg:province":"Utrecht",
    "wof:name":"Pub O'Leary'S",
    "wof:placetype":"venue"
},
  "geometry": {"coordinates":[5.11563,52.099068],"type":"Point"}
}