{
  "type": "Feature",
  "properties": {
    "addr:full":"Loevestraat 14 Horst Limburg 5961 TX",
    "addr:housenumber":"14",
    "addr:postcode":"5961 tx",
    "addr:street":"Loevestraat",
    "iso:country":"NL",
    "sg:address":"Loevestraat 14",
    "sg:city":"Horst",
    "sg:classifiers":[
        {
            "category":"Fast Food",
            "type":"Food & Drink"
        }
    ],
    "sg:phone":"+31 77 398 3203",
    "sg:postcode":"5961 TX",
    "sg:province":"Limburg",
    "sg:tags":[
        "afhaal",
        "restaurant"
    ],
    "wof:name":"Snackbar 'T Trapke",
    "wof:placetype":"venue"
},
  "geometry": {"coordinates":[-100.07679,31.168989],"type":"Point"}
}