{
  "type": "Feature",
  "properties": {
    "iso:country":"NL",
    "sg:address":"Buitendams 91",
    "sg:city":"Hardinxveld Giessend",
    "sg:orig_category":"Boekhouders",
    "sg:phone":"+31 184 615 008",
    "sg:postcode":"3371 BB",
    "sg:province":"Zuid-Holland",
    "wof:name":"Adfidas Bv",
    "wof:placetype":"venue"
},
  "geometry": {"coordinates":[4.829375,51.826084],"type":"Point"}
}