{
  "type": "Feature",
  "properties": {
    "addr:full":"Tolakkerwg 5A Hollandsche Rading Utrecht 3739 JG",
    "addr:housenumber":"5a",
    "addr:postcode":"3739 jg",
    "addr:street":"Tolakkerwg",
    "iso:country":"NL",
    "sg:address":"Tolakkerwg 5A",
    "sg:city":"Hollandsche Rading",
    "sg:orig_category":"Juridische Adviseurs",
    "sg:phone":"+31 35 577 1591",
    "sg:postcode":"3739 JG",
    "sg:province":"Utrecht",
    "wof:name":"Bierhoff, Mr H H M",
    "wof:placetype":"venue"
},
  "geometry": {"coordinates":[5.176847,52.177429],"type":"Point"}
}