{
  "type": "Feature",
  "properties": {
    "iso:country":"NL",
    "sg:address":"De Dam 30",
    "sg:city":"Blaricum",
    "sg:orig_category":"Adviesbureaus Bedrijfsorganisatie",
    "sg:phone":"+31 35 525 2101",
    "sg:postcode":"1261 KT",
    "sg:province":"Noord-Holland",
    "wof:name":"Mandersloot",
    "wof:placetype":"venue"
},
  "geometry": {"coordinates":[5.243439,52.273277],"type":"Point"}
}