{
  "type": "Feature",
  "properties": {
    "addr:full":"Zutphensewg 7 Vorden Gelderland 7251 DG",
    "addr:housenumber":"7",
    "addr:postcode":"7251 dg",
    "addr:street":"Zutphensewg;Gelderland",
    "iso:country":"NL",
    "sg:address":"Zutphensewg 7",
    "sg:city":"Vorden",
    "sg:orig_category":"Opticiens",
    "sg:phone":"+31 575 551 505",
    "sg:postcode":"7251 DG",
    "sg:province":"Gelderland",
    "wof:name":"Siemerink, M A A",
    "wof:placetype":"venue"
},
  "geometry": {"coordinates":[6.3112988472,52.104347229],"type":"Point"}
}