{
  "type": "Feature",
  "properties": {
    "iso:country":"NL",
    "sg:address":"Kruitberg 295",
    "sg:city":"Amsterdam",
    "sg:orig_category":"Werving And Selectie Van Tijdelijk Personeel And Uitzendkantoren",
    "sg:phone":"+31 20 778 6510",
    "sg:postcode":"1104 BP",
    "sg:province":"North Holland",
    "wof:name":"Van Oort",
    "wof:placetype":"venue"
},
  "geometry": {"coordinates":[4.9756631851,52.3165817261],"type":"Point"}
}