{
  "type": "Feature",
  "properties": {
    "iso:country":"NL",
    "sg:address":"Vikingrade 24",
    "sg:city":"Nieuwerkerk Yssel",
    "sg:orig_category":"Administratie- En Boekhoudkantoren",
    "sg:phone":"+31 180 312 346",
    "sg:postcode":"2912 PM",
    "sg:province":"Zuid-Holland",
    "wof:name":"Berkel, Van",
    "wof:placetype":"venue"
},
  "geometry": {"coordinates":[4.610726,51.964729],"type":"Point"}
}