{
  "type": "Feature",
  "properties": {
    "addr:full":"Klaproosweg 8 Heerde Gelderland 8181 ZV",
    "addr:housenumber":"8",
    "addr:postcode":"8181 zv",
    "addr:street":"Klaproosweg;Gelderland",
    "iso:country":"NL",
    "sg:address":"Klaproosweg 8",
    "sg:city":"Heerde",
    "sg:orig_category":"Loodgieterswerk, Verwarming And Sanitaire Installaties",
    "sg:phone":"+31 578 692 273",
    "sg:postcode":"8181 ZV",
    "sg:province":"Gelderland",
    "wof:name":"J. Sprokholt",
    "wof:placetype":"venue"
},
  "geometry": {"coordinates":[6.035766,52.394508],"type":"Point"}
}