{
  "type": "Feature",
  "properties": {
    "addr:full":"Withuisveld 5 Maastricht Limburg 6226 NV",
    "addr:housenumber":"5",
    "addr:postcode":"6226 nv",
    "addr:street":"Withuisveld",
    "iso:country":"NL",
    "sg:address":"Withuisveld 5",
    "sg:city":"Maastricht",
    "sg:orig_category":"Verhuizingen",
    "sg:phone":"+31 43 362 3508",
    "sg:postcode":"6226 NV",
    "sg:province":"Limburg",
    "wof:name":"Verhesen",
    "wof:placetype":"venue"
},
  "geometry": {"coordinates":[5.73338,50.85498],"type":"Point"}
}