{
  "type": "Feature",
  "properties": {
    "iso:country":"NL",
    "sg:address":"P Malherbestr 15",
    "sg:city":"Heerlen",
    "sg:orig_category":"Verzekeringen - Verzekeringskantoren",
    "sg:phone":"+31 45 541 5230",
    "sg:postcode":"6417 GR",
    "sg:province":"Limburg",
    "wof:name":"Hoevenaars",
    "wof:placetype":"venue"
},
  "geometry": {"coordinates":[5.982717,50.873692],"type":"Point"}
}