{
  "type": "Feature",
  "properties": {
    "addr:full":"Saturnusstr 41 Purmerend Noord-Holland 1443 AA",
    "addr:housenumber":"41",
    "addr:postcode":"1443 aa",
    "addr:street":"Saturnusstr",
    "iso:country":"NL",
    "sg:address":"Saturnusstr 41",
    "sg:city":"Purmerend",
    "sg:orig_category":"Pianostemmen En -Reparatie",
    "sg:phone":"+31 299 471 051",
    "sg:postcode":"1443 AA",
    "sg:province":"Noord-Holland",
    "wof:name":"Hans V/D Wateren, Pianostemmer",
    "wof:placetype":"venue"
},
  "geometry": {"coordinates":[4.959727,52.507729],"type":"Point"}
}