{
  "type": "Feature",
  "properties": {
    "addr:full":"Broeksittarderwg 161 Sittard Limburg 6137 BJ",
    "addr:housenumber":"161",
    "addr:postcode":"6137 bj",
    "addr:street":"Sittard Limburg",
    "iso:country":"NL",
    "sg:address":"Broeksittarderwg 161",
    "sg:city":"Sittard",
    "sg:orig_category":"Verbouwingen",
    "sg:phone":"+31 46 452 9868",
    "sg:postcode":"6137 BJ",
    "sg:province":"Limburg",
    "wof:name":"Bastings, Norbert",
    "wof:placetype":"venue"
},
  "geometry": {"coordinates":[5.886143,51.001038],"type":"Point"}
}