{
  "type": "Feature",
  "properties": {
    "addr:full":"Bedrijvenstraat 25 Wierden Overijssel 7641 AM",
    "addr:housenumber":"25",
    "addr:postcode":"7641",
    "addr:street":"Bedrijvenstraat",
    "iso:country":"NL",
    "sg:address":"Bedrijvenstraat 25",
    "sg:city":"Wierden",
    "sg:orig_category":"Metaalbekleding And -Behandeling",
    "sg:phone":"+31 546 575 787",
    "sg:postcode":"7641 AM",
    "sg:province":"Overijssel",
    "wof:name":"Lastechniek Oost",
    "wof:placetype":"venue"
},
  "geometry": {"coordinates":[6.580682,52.36198],"type":"Point"}
}