{
  "type": "Feature",
  "properties": {
    "iso:country":"NL",
    "sg:address":"Essenburgsingel 109",
    "sg:city":"Rotterdam",
    "sg:orig_category":"Hoger Onderwijs",
    "sg:phone":"+31 10 418 9979",
    "sg:postcode":"3022 EH",
    "sg:province":"South Holland",
    "wof:name":"3D Id Interieur En Vormgeving",
    "wof:placetype":"venue"
},
  "geometry": {"coordinates":[4.447108,51.92131],"type":"Point"}
}