{
  "type": "Feature",
  "properties": {
    "iso:country":"NL",
    "sg:address":"Touwslagersdreef 83",
    "sg:city":"Tholen",
    "sg:orig_category":"Beveiliging",
    "sg:phone":"+31 166 605 192",
    "sg:postcode":"4691 LW",
    "sg:province":"Zeeland",
    "wof:name":"Cps",
    "wof:placetype":"venue"
},
  "geometry": {"coordinates":[4.214087,51.526402],"type":"Point"}
}