{
  "type": "Feature",
  "properties": {
    "addr:full":"Burg Albertipln 26 Krommenie Noord-Holland 1561 WJ",
    "addr:housenumber":"26",
    "addr:postcode":"1561 wj",
    "addr:street":"Burg",
    "iso:country":"NL",
    "sg:address":"Burg Albertipln 26",
    "sg:city":"Krommenie",
    "sg:orig_category":"Adviesbureaus Bedrijfsorganisatie",
    "sg:phone":"+31 75 628 6611",
    "sg:postcode":"1561 WJ",
    "sg:province":"Noord-Holland",
    "wof:name":"Plat Consultancy Bv",
    "wof:placetype":"venue"
},
  "geometry": {"coordinates":[4.759551,52.501125],"type":"Point"}
}