{
  "type": "Feature",
  "properties": {
    "iso:country":"NL",
    "sg:address":"Annevilleln 11A",
    "sg:city":"Ulvenhout",
    "sg:orig_category":"Wegenbouw",
    "sg:phone":"+31 76 560 2254",
    "sg:postcode":"4851 CA",
    "sg:province":"Noord-Brabant",
    "wof:name":"Broek Bv, Wegenbouwbedrijf J M Van Den",
    "wof:placetype":"venue"
},
  "geometry": {"coordinates":[4.7990999222,51.5496177673],"type":"Point"}
}