{
  "type": "Feature",
  "properties": {
    "addr:full":"Bredasewg 62 Roosendaal Noord-Brabant 4702 KV",
    "addr:housenumber":"62",
    "addr:postcode":"4702 kv",
    "addr:street":"Bredasewg",
    "iso:country":"NL",
    "sg:address":"Bredasewg 62",
    "sg:city":"Roosendaal",
    "sg:orig_category":"Adviesbureaus Bedrijfsorganisatie",
    "sg:phone":"+31 165 535 090",
    "sg:postcode":"4702 KV",
    "sg:province":"Noord-Brabant",
    "sg:website":"http://www.silverscan.nl",
    "wof:name":"Silverscan Organisatie Advies, De",
    "wof:placetype":"venue"
},
  "geometry": {"coordinates":[4.474453,51.538094],"type":"Point"}
}