{
  "type": "Feature",
  "properties": {
    "iso:country":"NL",
    "sg:address":"Schuitendiep 47",
    "sg:city":"Groningen",
    "sg:orig_category":"Webdesign Bureaus",
    "sg:phone":"+31 50 313 0788",
    "sg:postcode":"9711 RB",
    "sg:province":"Groningen",
    "sg:website":"http://www.mrmedia.nl",
    "wof:name":"Mrmedia Groningen",
    "wof:placetype":"venue"
},
  "geometry": {"coordinates":[6.5729107857,53.2176208496],"type":"Point"}
}