{
  "type": "Feature",
  "properties": {
    "iso:country":"NL",
    "sg:address":"Willige Laagt 12",
    "sg:city":"Liessel",
    "sg:orig_category":"Heftrucks",
    "sg:phone":"+31 493 341 493",
    "sg:postcode":"5757 PZ",
    "sg:province":"North Brabant",
    "wof:name":"Feller",
    "wof:placetype":"venue"
},
  "geometry": {"coordinates":[5.825728,51.418179],"type":"Point"}
}