{
  "type": "Feature",
  "properties": {
    "addr:full":"J F Kennedyplein 3 Ulft Gelderland 7071 BT",
    "addr:housenumber":"3",
    "addr:postcode":"7071 bt",
    "addr:street":"J F Kennedyplein;Gelderland",
    "iso:country":"NL",
    "sg:address":"J F Kennedyplein 3",
    "sg:city":"Ulft",
    "sg:classifiers":[
        {
            "category":"Retail",
            "subcategory":"Photofinishing",
            "type":"Services"
        }
    ],
    "sg:phone":"+31 315 681 440",
    "sg:postcode":"7071 BT",
    "sg:province":"Gelderland",
    "sg:tags":[
        "foto",
        "film"
    ],
    "wof:name":"Fotostudio Van Onna",
    "wof:placetype":"venue"
},
  "geometry": {"coordinates":[6.383461,51.891148],"type":"Point"}
}