{
  "type": "Feature",
  "properties": {
    "addr:full":"Hoofdstr O 2 Winsum Gn Groningen 9951 AH",
    "addr:housenumber":"2",
    "addr:postcode":"gn;9951 ah",
    "iso:country":"NL",
    "sg:address":"Hoofdstr O 2",
    "sg:city":"Winsum Gn",
    "sg:orig_category":"Juweliers",
    "sg:phone":"+31 595 441 433",
    "sg:postcode":"9951 AH",
    "sg:province":"Groningen",
    "wof:name":"Pannekoek, P M J",
    "wof:placetype":"venue"
},
  "geometry": {"coordinates":[6.517395,53.334412],"type":"Point"}
}