{
  "type": "Feature",
  "properties": {
    "addr:full":"Kamperstr 10 Deventer NL.08 7418 CB",
    "addr:housenumber":"10;nl.08",
    "addr:postcode":"7418 cb",
    "addr:street":"Kamperstr",
    "iso:country":"NL",
    "sg:address":"Kamperstr 10",
    "sg:city":"Deventer",
    "sg:orig_category":"Autoschade- Herstelbedrijven",
    "sg:phone":"+31 570 622 155",
    "sg:postcode":"7418 CB",
    "sg:province":"NL.08",
    "wof:name":"Autoschade Deventer Bv",
    "wof:placetype":"venue"
},
  "geometry": {"coordinates":[6.17491,52.249836],"type":"Point"}
}