{
  "type": "Feature",
  "properties": {
    "addr:full":"Bandykwg 28 Maasland Zuid-Holland 3155 RT",
    "addr:housenumber":"28",
    "addr:postcode":"3155 rt",
    "addr:street":"Bandykwg",
    "iso:country":"NL",
    "sg:address":"Bandykwg 28",
    "sg:city":"Maasland",
    "sg:orig_category":"Metaalbewerking",
    "sg:phone":"+31 174 518 694",
    "sg:postcode":"3155 RT",
    "sg:province":"Zuid-Holland",
    "wof:name":"Akmeta",
    "wof:placetype":"venue"
},
  "geometry": {"coordinates":[4.275135,51.936325],"type":"Point"}
}