{
  "type": "Feature",
  "properties": {
    "addr:full":"Phileas Foggstraat 33 Emmen Drenthe 7825 AK",
    "addr:housenumber":"33",
    "addr:postcode":"7825 ak",
    "addr:street":"Phileas Foggstraat",
    "iso:country":"NL",
    "sg:address":"Phileas Foggstraat 33",
    "sg:city":"Emmen",
    "sg:orig_category":"Autoverhuur",
    "sg:phone":"+31 591 630 830",
    "sg:postcode":"7825 AK",
    "sg:province":"Drenthe",
    "wof:name":"Autoverhuur De Grote Emmen Bv",
    "wof:placetype":"venue"
},
  "geometry": {"coordinates":[6.932197,52.756721],"type":"Point"}
}