{
  "type": "Feature",
  "properties": {
    "addr:full":"Transistorstraat 28 Almere NL. 1322 CE",
    "addr:housenumber":"28",
    "addr:postcode":"1322 ce",
    "addr:street":"Transistorstraat;Nl.",
    "iso:country":"NL",
    "sg:address":"Transistorstraat 28",
    "sg:city":"Almere",
    "sg:orig_category":"Kantoor- And Schoolbenodigdheden Gh",
    "sg:phone":"+31 36 546 3111",
    "sg:postcode":"1322 CE",
    "sg:province":"NL.",
    "wof:name":"Interform Bv",
    "wof:placetype":"venue"
},
  "geometry": {"coordinates":[5.1807742119,52.3464927673],"type":"Point"}
}