{
  "type": "Feature",
  "properties": {
    "addr:full":"P V Ostayenstr 10 Landgraaf Limburg 6372 HX",
    "addr:housenumber":"10",
    "addr:postcode":"6372 hx",
    "addr:street":"Ostayenstr",
    "iso:country":"NL",
    "sg:address":"P V Ostayenstr 10",
    "sg:city":"Landgraaf",
    "sg:orig_category":"Artiesten/Gezelschappen",
    "sg:phone":"+31 45 532 4651",
    "sg:postcode":"6372 HX",
    "sg:province":"Limburg",
    "wof:name":"Pee Point",
    "wof:placetype":"venue"
},
  "geometry": {"coordinates":[6.024073,50.906536],"type":"Point"}
}