{
  "type": "Feature",
  "properties": {
    "iso:country":"NL",
    "sg:address":"Koningstr 2",
    "sg:city":"Velp Gld",
    "sg:orig_category":"Geluidsopnamestudio'S",
    "sg:phone":"+31 26 362 2875",
    "sg:postcode":"6881 MR",
    "sg:province":"Gelderland",
    "wof:name":"Audio Facilities",
    "wof:placetype":"venue"
},
  "geometry": {"coordinates":[5.967394,51.998993],"type":"Point"}
}