{
  "type": "Feature",
  "properties": {
    "addr:full":"Dorpsstraat 88A Nootdorp Zuid-Holland 2631 CV",
    "addr:housenumber":"88a",
    "addr:postcode":"2631 cv",
    "addr:street":"Dorpsstraat",
    "iso:country":"NL",
    "sg:address":"Dorpsstraat 88A",
    "sg:city":"Nootdorp",
    "sg:orig_category":"Makelaars In Onroerend Goed",
    "sg:phone":"+31 15 310 1003",
    "sg:postcode":"2631 CV",
    "sg:province":"Zuid-Holland",
    "wof:name":"Fonk Makelaardij",
    "wof:placetype":"venue"
},
  "geometry": {"coordinates":[4.397936,52.044319],"type":"Point"}
}