{
  "type": "Feature",
  "properties": {
    "addr:full":"Deventerstr 7 Apeldoorn Gelderland 7311 BH",
    "addr:housenumber":"7",
    "addr:postcode":"7311 bh",
    "addr:street":"Deventerstr;Gelderland",
    "iso:country":"NL",
    "sg:address":"Deventerstr 7",
    "sg:city":"Apeldoorn",
    "sg:orig_category":"Warenhuizen",
    "sg:phone":"+31 55 576 1946",
    "sg:postcode":"7311 BH",
    "sg:province":"Gelderland",
    "wof:name":"Xenos Bv",
    "wof:placetype":"venue"
},
  "geometry": {"coordinates":[5.9620828629,52.2157745361],"type":"Point"}
}