{
  "type": "Feature",
  "properties": {
    "iso:country":"NL",
    "sg:address":"Gangesdreef 110",
    "sg:city":"Utrecht",
    "sg:classifiers":[
        {
            "category":"Fast Food",
            "type":"Food & Drink"
        }
    ],
    "sg:phone":"+31 30 262 2127",
    "sg:postcode":"3564 SN",
    "sg:province":"Utrecht",
    "sg:tags":[
        "afhaal",
        "restaurant"
    ],
    "wof:name":"Eetsalon Theo",
    "wof:placetype":"venue"
},
  "geometry": {"coordinates":[5.104626,52.124046],"type":"Point"}
}