{
  "type": "Feature",
  "properties": {
    "iso:country":"NL",
    "sg:address":"Koopmansplein 1",
    "sg:city":"Assen",
    "sg:orig_category":"Huishoudapparatuur, Televisies And Radio'S",
    "sg:phone":"+31 592 317 837",
    "sg:postcode":"9401 EL",
    "sg:province":"Provincie Drenthe",
    "wof:name":"Jongmans Audio En Video",
    "wof:placetype":"venue"
},
  "geometry": {"coordinates":[6.559849,52.995041],"type":"Point"}
}