{
  "type": "Feature",
  "properties": {
    "addr:full":"Guldenweg 69 Hendrik Ido Ambacht Zuid-Holland 3341 CJ",
    "addr:housenumber":"69",
    "addr:postcode":"ido ambacht;3341 cj",
    "addr:street":"Guldenweg",
    "iso:country":"NL",
    "sg:address":"Guldenweg 69",
    "sg:city":"Hendrik Ido Ambacht",
    "sg:orig_category":"Elektronische Bedrijfsinstallaties",
    "sg:phone":"+31 78 681 6011",
    "sg:postcode":"3341 CJ",
    "sg:province":"Zuid-Holland",
    "wof:name":"Apt-Groep",
    "wof:placetype":"venue"
},
  "geometry": {"coordinates":[4.648862,51.846542],"type":"Point"}
}