{
  "type": "Feature",
  "properties": {
    "addr:full":"Stephensonstr 30 Zoetermeer South Holland 2723 RN",
    "addr:housenumber":"30",
    "addr:postcode":"2723 rn",
    "addr:street":"Stephensonstr",
    "iso:country":"NL",
    "sg:address":"Stephensonstr 30",
    "sg:city":"Zoetermeer",
    "sg:orig_category":"Pijpleidingen",
    "sg:phone":"+31 79 341 7714",
    "sg:postcode":"2723 RN",
    "sg:province":"South Holland",
    "sg:website":"http://www.peb.nl",
    "wof:name":"Peb Bv",
    "wof:placetype":"venue"
},
  "geometry": {"coordinates":[4.526801,52.062881],"type":"Point"}
}