{
  "type": "Feature",
  "properties": {
    "addr:full":"Lingedk 28 Leerdam Zuid-Holland 4142 LD",
    "addr:housenumber":"28",
    "addr:postcode":"4142 ld",
    "addr:street":"Lingedk",
    "iso:country":"NL",
    "sg:address":"Lingedk 28",
    "sg:city":"Leerdam",
    "sg:orig_category":"Musea",
    "sg:phone":"+31 345 612 714",
    "sg:postcode":"4142 LD",
    "sg:province":"Zuid-Holland",
    "wof:name":"Nat Glasmuseum, Sticht",
    "wof:placetype":"venue"
},
  "geometry": {"coordinates":[5.086151,51.882915],"type":"Point"}
}