{
  "type": "Feature",
  "properties": {
    "addr:full":"Industrieweg 61 Wormerveer Noord-Holland 1521 NE",
    "addr:housenumber":"61;1521",
    "addr:postcode":"ne",
    "addr:street":"Industrieweg",
    "iso:country":"NL",
    "sg:address":"Industrieweg 61",
    "sg:city":"Wormerveer",
    "sg:orig_category":"Diverse Grafische Activiteiten",
    "sg:phone":"+31 75 640 2030",
    "sg:postcode":"1521 NE",
    "sg:province":"Noord-Holland",
    "wof:name":"Hewi Bv",
    "wof:placetype":"venue"
},
  "geometry": {"coordinates":[4.780848,52.5144],"type":"Point"}
}