{
  "type": "Feature",
  "properties": {
    "addr:full":"Monnikenmoer 14 Sprundel Noord-Brabant 4714 HR",
    "addr:housenumber":"14",
    "addr:postcode":"4714 hr",
    "addr:street":"Monnikenmoer",
    "iso:country":"NL",
    "sg:address":"Monnikenmoer 14",
    "sg:city":"Sprundel",
    "sg:orig_category":"Nagelstudio'S",
    "sg:phone":"+31 165 384 292",
    "sg:postcode":"4714 HR",
    "sg:province":"Noord-Brabant",
    "wof:name":"Carla",
    "wof:placetype":"venue"
},
  "geometry": {"coordinates":[4.600951,51.539604],"type":"Point"}
}