{
  "type": "Feature",
  "properties": {
    "iso:country":"NL",
    "sg:address":"Monnikenmoer 14",
    "sg:city":"Sprundel",
    "sg:orig_category":"Nagelstudio'S",
    "sg:phone":"+31 165 384 292",
    "sg:postcode":"4714 HR",
    "sg:province":"Noord-Brabant",
    "wof:name":"Carla",
    "wof:placetype":"venue"
},
  "geometry": {"coordinates":[4.600951,51.539604],"type":"Point"}
}