{
  "type": "Feature",
  "properties": {
    "addr:full":"St Jobstr 27 Rotterdam Zuid-Holland 3024 EG",
    "addr:housenumber":"27",
    "addr:postcode":"3024 eg",
    "iso:country":"NL",
    "sg:address":"St Jobstr 27",
    "sg:city":"Rotterdam",
    "sg:orig_category":"Werving En Selectie",
    "sg:phone":"+31 6 20400755",
    "sg:postcode":"3024 EG",
    "sg:province":"Zuid-Holland",
    "wof:name":"Eye For You",
    "wof:placetype":"venue"
},
  "geometry": {"coordinates":[4.4618830681,51.9046783447],"type":"Point"}
}