{
  "type": "Feature",
  "properties": {
    "addr:full":"Tienmorgen 5 Huissen Gelderland 6851 DV",
    "addr:housenumber":"5",
    "addr:postcode":"6851",
    "addr:street":"Tienmorgen;Gelderland",
    "iso:country":"NL",
    "sg:address":"Tienmorgen 5",
    "sg:city":"Huissen",
    "sg:orig_category":"Bloemen And Planten",
    "sg:phone":"+31 26 325 1950",
    "sg:postcode":"6851 DV",
    "sg:province":"Gelderland",
    "wof:name":"Vof A.J. Kempkens",
    "wof:placetype":"venue"
},
  "geometry": {"coordinates":[5.936436,51.91975],"type":"Point"}
}