{
  "type": "Feature",
  "properties": {
    "addr:full":"Quickstepstraat 39 Almere NL. 1326 PW",
    "addr:housenumber":"39",
    "addr:postcode":"1326 pw",
    "addr:street":"Quickstepstraat;Nl.",
    "iso:country":"NL",
    "sg:address":"Quickstepstraat 39",
    "sg:city":"Almere",
    "sg:orig_category":"Kappers",
    "sg:phone":"+31 36 537 8381",
    "sg:postcode":"1326 PW",
    "sg:province":"NL.",
    "wof:name":"Looking Good",
    "wof:placetype":"venue"
},
  "geometry": {"coordinates":[5.259625,52.365475],"type":"Point"}
}