{
  "type": "Feature",
  "properties": {
    "addr:full":"Derksstr 2 Emmen Drenthe 7811 AJ",
    "addr:housenumber":"2",
    "addr:postcode":"7811 aj",
    "addr:street":"Derksstr",
    "iso:country":"NL",
    "sg:address":"Derksstr 2",
    "sg:city":"Emmen",
    "sg:orig_category":"Woninginrichting",
    "sg:phone":"+31 591 642 159",
    "sg:postcode":"7811 AJ",
    "sg:province":"Drenthe",
    "wof:name":"Koning Emmen Bv",
    "wof:placetype":"venue"
},
  "geometry": {"coordinates":[6.8945522308,52.7883987427],"type":"Point"}
}