{
  "type": "Feature",
  "properties": {
    "addr:full":"Amsterdamsestrwg 605 Utrecht Utrecht 3553 EJ",
    "addr:housenumber":"605",
    "addr:postcode":"3553 ej",
    "iso:country":"NL",
    "sg:address":"Amsterdamsestrwg 605",
    "sg:city":"Utrecht",
    "sg:orig_category":"Boeken En Tijdschriften",
    "sg:phone":"+31 30 244 3044",
    "sg:postcode":"3553 EJ",
    "sg:province":"Utrecht",
    "sg:website":"http://www.bruna.nl/",
    "wof:name":"Bruna",
    "wof:placetype":"venue"
},
  "geometry": {"coordinates":[5.083738,52.110306],"type":"Point"}
}