{
  "type": "Feature",
  "properties": {
    "addr:full":"Zeemandreef 7 Maassluis Zuid-Holland 3146 BV",
    "addr:housenumber":"7",
    "addr:postcode":"3146 bv",
    "addr:street":"Zeemandreef",
    "iso:country":"NL",
    "sg:address":"Zeemandreef 7",
    "sg:city":"Maassluis",
    "sg:orig_category":"Sportclubs",
    "sg:phone":"+31 10 474 3250",
    "sg:postcode":"3146 BV",
    "sg:province":"Zuid-Holland",
    "wof:name":"Stichting Zeekadetkorps Vlaardingen Jeugdverenigin",
    "wof:placetype":"venue"
},
  "geometry": {"coordinates":[4.220782,51.936768],"type":"Point"}
}