{
  "type": "Feature",
  "properties": {
    "addr:full":"Brazilielaan 10 Overveen North Holland 2051 LT",
    "addr:housenumber":"10",
    "addr:postcode":"2051 lt",
    "addr:street":"Brazilielaan",
    "iso:country":"NL",
    "sg:address":"Brazilielaan 10",
    "sg:city":"Overveen",
    "sg:orig_category":"Binnenhuisarchitecten",
    "sg:phone":"+31 23 527 6575",
    "sg:postcode":"2051 LT",
    "sg:province":"North Holland",
    "wof:name":"Willemijn Damave",
    "wof:placetype":"venue"
},
  "geometry": {"coordinates":[4.614142,52.394676],"type":"Point"}
}