{
  "type": "Feature",
  "properties": {
    "addr:full":"T Inne 2 Budel Noord-Brabant 6021 DA",
    "addr:housenumber":"2",
    "addr:postcode":"6021 da",
    "addr:street":"T Inne",
    "iso:country":"NL",
    "sg:address":"T Inne 2",
    "sg:city":"Budel",
    "sg:orig_category":"Gespecialiseerde Voeding",
    "sg:phone":"+31 495 492 162",
    "sg:postcode":"6021 DA",
    "sg:province":"Noord-Brabant",
    "wof:name":"Jem'S Koeken",
    "wof:placetype":"venue"
},
  "geometry": {"coordinates":[5.58211,51.267986],"type":"Point"}
}