{
  "type": "Feature",
  "properties": {
    "addr:full":"H Brouwerstr 10 Haskerhorne Provincie Friesland 8506 BK",
    "addr:housenumber":"10",
    "addr:postcode":"8506 bk",
    "addr:street":"Provincie Friesland",
    "iso:country":"NL",
    "sg:address":"H Brouwerstr 10",
    "sg:city":"Haskerhorne",
    "sg:orig_category":"Autoruiten",
    "sg:phone":"+31 513 411 426",
    "sg:postcode":"8506 BK",
    "sg:province":"Provincie Friesland",
    "wof:name":"Minnema, Andr\u00e9",
    "wof:placetype":"venue"
},
  "geometry": {"coordinates":[5.829661,52.951939],"type":"Point"}
}