{
  "type": "Feature",
  "properties": {
    "addr:full":"Madridplnts 25 Haarlem Noord-Holland 2034 VN",
    "addr:housenumber":"25",
    "addr:postcode":"2034 vn",
    "addr:street":"Madridplnts",
    "iso:country":"NL",
    "sg:address":"Madridplnts 25",
    "sg:city":"Haarlem",
    "sg:orig_category":"Schilders",
    "sg:phone":"+31 23 536 1668",
    "sg:postcode":"2034 VN",
    "sg:province":"Noord-Holland",
    "wof:name":"Bob Prins",
    "wof:placetype":"venue"
},
  "geometry": {"coordinates":[4.650171,52.361286],"type":"Point"}
}