{
  "type": "Feature",
  "properties": {
    "addr:full":"Noorderkroon 40 Amstelveen Noord-Holland 1188 AD",
    "addr:housenumber":"40",
    "addr:postcode":"1188 ad",
    "addr:street":"Noorderkroon",
    "iso:country":"NL",
    "sg:address":"Noorderkroon 40",
    "sg:city":"Amstelveen",
    "sg:orig_category":"Webdesign Bureaus",
    "sg:phone":"+31 20 647 3563",
    "sg:postcode":"1188 AD",
    "sg:province":"Noord-Holland",
    "sg:website":"http://www.prospect-designs.nl",
    "wof:name":"Prospect Design",
    "wof:placetype":"venue"
},
  "geometry": {"coordinates":[4.8547058105,52.2832679749],"type":"Point"}
}