{
  "type": "Feature",
  "properties": {
    "addr:full":"Dorpstr 32 Sittard Limburg 6137 SV",
    "addr:housenumber":"32",
    "addr:postcode":"6137 sv",
    "addr:street":"Dorpstr",
    "iso:country":"NL",
    "sg:address":"Dorpstr 32",
    "sg:city":"Sittard",
    "sg:orig_category":"Vertalers",
    "sg:phone":"+31 46 452 8545",
    "sg:postcode":"6137 SV",
    "sg:province":"Limburg",
    "wof:name":"Berg, Maartje Van Den",
    "wof:placetype":"venue"
},
  "geometry": {"coordinates":[5.894533,51.002254],"type":"Point"}
}