{
  "type": "Feature",
  "properties": {
    "addr:full":"Somerlustweg 54A Veendam Groningen 9645 CB",
    "addr:housenumber":"54a",
    "addr:postcode":"9645 cb",
    "addr:street":"Somerlustweg",
    "iso:country":"NL",
    "sg:address":"Somerlustweg 54A",
    "sg:city":"Veendam",
    "sg:orig_category":"Kinderopvang Behalve Thuis",
    "sg:phone":"+31 598 617 540",
    "sg:postcode":"9645 CB",
    "sg:province":"Groningen",
    "wof:name":"De Lappendeken Veendam",
    "wof:placetype":"venue"
},
  "geometry": {"coordinates":[6.878227,53.117451],"type":"Point"}
}