{
  "type": "Feature",
  "properties": {
    "addr:full":"De Klinck 8 Wessem Limburg 6019 EK",
    "addr:housenumber":"8",
    "addr:postcode":"6019 ek",
    "addr:street":"De Klinck",
    "iso:country":"NL",
    "sg:address":"De Klinck 8",
    "sg:city":"Wessem",
    "sg:orig_category":"Kappers",
    "sg:phone":"+31 475 566 288",
    "sg:postcode":"6019 EK",
    "sg:province":"Limburg",
    "wof:name":"Mathy",
    "wof:placetype":"venue"
},
  "geometry": {"coordinates":[5.875425,51.162991],"type":"Point"}
}