{
  "type": "Feature",
  "properties": {
    "addr:full":"Zwolseweg 44 Heerde Gelderland 8181 AE",
    "addr:housenumber":"44",
    "addr:postcode":"8181 ae",
    "addr:street":"Zwolseweg;Gelderland",
    "iso:country":"NL",
    "sg:address":"Zwolseweg 44",
    "sg:city":"Heerde",
    "sg:orig_category":"Architecten",
    "sg:phone":"+31 578 695 445",
    "sg:postcode":"8181 AE",
    "sg:province":"Gelderland",
    "wof:name":"Architectenburo Guido Oude Vrielink",
    "wof:placetype":"venue"
},
  "geometry": {"coordinates":[6.044777,52.392353],"type":"Point"}
}