{
  "type": "Feature",
  "properties": {
    "addr:full":"Stationspln 1 Amersfoort Utrecht 3818 LE",
    "addr:housenumber":"1",
    "addr:postcode":"3818 le",
    "addr:street":"Stationspln",
    "iso:country":"NL",
    "sg:address":"Stationspln 1",
    "sg:city":"Amersfoort",
    "sg:orig_category":"Organisatiebureaus",
    "sg:phone":"+31 33 467 7777",
    "sg:postcode":"3818 LE",
    "sg:province":"Utrecht",
    "sg:website":"http://www.twijnstragudde.com",
    "wof:name":"Degw-Twijnstra Bv",
    "wof:placetype":"venue"
},
  "geometry": {"coordinates":[5.3860850334,52.1523246765],"type":"Point"}
}