{
  "type": "Feature",
  "properties": {
    "addr:full":"Bereklauw 9 Werkendam North Brabant 4251 KP",
    "addr:housenumber":"9",
    "addr:postcode":"4251 kp",
    "addr:street":"Bereklauw",
    "iso:country":"NL",
    "sg:address":"Bereklauw 9",
    "sg:city":"Werkendam",
    "sg:orig_category":"Adviesbureaus Bouwkunde",
    "sg:phone":"+31 183 504 964",
    "sg:postcode":"4251 KP",
    "sg:province":"North Brabant",
    "wof:name":"Voordendag",
    "wof:placetype":"venue"
},
  "geometry": {"coordinates":[4.886883,51.808167],"type":"Point"}
}