{
  "type": "Feature",
  "properties": {
    "addr:full":"Handelsweg 7 Emmen Provincie Drenthe 7826 TC",
    "addr:housenumber":"7",
    "addr:postcode":"7826 tc",
    "addr:street":"Handelsweg;Provincie Drenthe",
    "iso:country":"NL",
    "sg:address":"Handelsweg 7",
    "sg:city":"Emmen",
    "sg:orig_category":"Bouwmaterialen Gh",
    "sg:phone":"+31 591 623 501",
    "sg:postcode":"7826 TC",
    "sg:province":"Provincie Drenthe",
    "wof:name":"Wivo Coatings",
    "wof:placetype":"venue"
},
  "geometry": {"coordinates":[6.951637,52.775063],"type":"Point"}
}