{
  "type": "Feature",
  "properties": {
    "iso:country":"NL",
    "sg:address":"Schutstr 43",
    "sg:city":"Hoogeveen",
    "sg:orig_category":"Verenigingen En Stichtingen",
    "sg:phone":"+31 528 275 355",
    "sg:postcode":"7907 CA",
    "sg:province":"Provincie Drenthe",
    "wof:name":"Podium, Het",
    "wof:placetype":"venue"
},
  "geometry": {"coordinates":[6.476041,52.720097],"type":"Point"}
}