{
  "type": "Feature",
  "properties": {
    "addr:full":"Schutstr 43 Hoogeveen Provincie Drenthe 7907 CA",
    "addr:housenumber":"43",
    "addr:postcode":"7907 ca",
    "addr:street":"Schutstr;Provincie",
    "iso:country":"NL",
    "sg:address":"Schutstr 43",
    "sg:city":"Hoogeveen",
    "sg:orig_category":"Verenigingen En Stichtingen",
    "sg:phone":"+31 528 275 355",
    "sg:postcode":"7907 CA",
    "sg:province":"Provincie Drenthe",
    "wof:name":"Podium, Het",
    "wof:placetype":"venue"
},
  "geometry": {"coordinates":[6.476041,52.720097],"type":"Point"}
}