{
  "type": "Feature",
  "properties": {
    "addr:full":"Herenstraat 31 Leiden Zuid-Holland 2313 AE",
    "addr:housenumber":"31",
    "addr:postcode":"2313 ae",
    "addr:street":"Herenstraat",
    "iso:country":"NL",
    "sg:address":"Herenstraat 31",
    "sg:city":"Leiden",
    "sg:orig_category":"Antiekzaken",
    "sg:phone":"+31 71 514 0942",
    "sg:postcode":"2313 AE",
    "sg:province":"Zuid-Holland",
    "wof:name":"De Antiekhoek",
    "wof:placetype":"venue"
},
  "geometry": {"coordinates":[4.489129,52.152271],"type":"Point"}
}