{
  "type": "Feature",
  "properties": {
    "addr:full":"Brugstraat 20 Groningen Groningen 9711 HZ",
    "addr:housenumber":"20",
    "addr:postcode":"9711 hz",
    "addr:street":"Brugstraat",
    "iso:country":"NL",
    "sg:address":"Brugstraat 20",
    "sg:city":"Groningen",
    "sg:orig_category":"Opticiens",
    "sg:phone":"+31 50 311 7404",
    "sg:postcode":"9711 HZ",
    "sg:province":"Groningen",
    "wof:name":"Stadsoptiek Groningen",
    "wof:placetype":"venue"
},
  "geometry": {"coordinates":[6.5602588654,53.2163085938],"type":"Point"}
}