{
  "type": "Feature",
  "properties": {
    "addr:full":"Veilingweg 18 Rotterdam Zuid-Holland 3034 KB",
    "addr:housenumber":"18",
    "addr:postcode":"3034 kb",
    "addr:street":"Veilingweg",
    "iso:country":"NL",
    "sg:address":"Veilingweg 18",
    "sg:city":"Rotterdam",
    "sg:orig_category":"Bouwmaterialen Gh",
    "sg:phone":"+31 10 413 0650",
    "sg:postcode":"3034 KB",
    "sg:province":"Zuid-Holland",
    "wof:name":"T. Mulder Rotterdam Bv",
    "wof:placetype":"venue"
},
  "geometry": {"coordinates":[4.494843,51.943031],"type":"Point"}
}