{
  "type": "Feature",
  "properties": {
    "addr:full":"Meander 5 Surhuisterveen Friesland 9231 DB",
    "addr:housenumber":"5",
    "addr:postcode":"9231 db",
    "addr:street":"Meander",
    "iso:country":"NL",
    "sg:address":"Meander 5",
    "sg:city":"Surhuisterveen",
    "sg:orig_category":"Automaterialen En Gereedschappen",
    "sg:phone":"+31 512 365 227",
    "sg:postcode":"9231 DB",
    "sg:province":"Friesland",
    "sg:website":"http://www.brezan.nl",
    "wof:name":"Brezan",
    "wof:placetype":"venue"
},
  "geometry": {"coordinates":[6.186483,53.182381],"type":"Point"}
}