{
  "type": "Feature",
  "properties": {
    "addr:full":"Bruggehoofd 1 Hellevoetsluis Zuid-Holland 3223 DB",
    "addr:housenumber":"1",
    "addr:postcode":"3223 db",
    "addr:street":"Bruggehoofd",
    "iso:country":"NL",
    "sg:address":"Bruggehoofd 1",
    "sg:city":"Hellevoetsluis",
    "sg:orig_category":"Woningbouw- Verenigingen En -Stichtingen",
    "sg:phone":"+31 181 392 392",
    "sg:postcode":"3223 DB",
    "sg:province":"Zuid-Holland",
    "sg:website":"http://www.maasdelta.nl",
    "wof:name":"Trefpunt Maasdelta",
    "wof:placetype":"venue"
},
  "geometry": {"coordinates":[4.1448750496,51.8347396851],"type":"Point"}
}