{
  "type": "Feature",
  "properties": {
    "iso:country":"NL",
    "sg:address":"Industriestr 3",
    "sg:city":"Noordwolde Fr",
    "sg:orig_category":"Meubelen",
    "sg:phone":"+31 561 432 225",
    "sg:postcode":"8391 AG",
    "sg:province":"Friesland",
    "wof:name":"Noordwolde Bv",
    "wof:placetype":"venue"
},
  "geometry": {"coordinates":[6.13903,52.893353],"type":"Point"}
}