{
  "type": "Feature",
  "properties": {
    "addr:full":"Rhonewg 56 Amsterdam Noord-Holland 1043 AH",
    "addr:housenumber":"56",
    "addr:postcode":"1043 ah",
    "addr:street":"Rhonewg",
    "iso:country":"NL",
    "sg:address":"Rhonewg 56",
    "sg:city":"Amsterdam",
    "sg:orig_category":"Wasserijen",
    "sg:phone":"+31 20 613 9035",
    "sg:postcode":"1043 AH",
    "sg:province":"Noord-Holland",
    "wof:name":"Sga Bv",
    "wof:placetype":"venue"
},
  "geometry": {"coordinates":[4.8195290565,52.3904075623],"type":"Point"}
}