{
  "type": "Feature",
  "properties": {
    "addr:full":"Meerpaal 5 Oosterhout Nb Noord-Brabant 4904 SK",
    "addr:housenumber":"5",
    "addr:postcode":"4904 sk",
    "addr:street":"Meerpaal",
    "iso:country":"NL",
    "sg:address":"Meerpaal 5",
    "sg:city":"Oosterhout Nb",
    "sg:orig_category":"Granen, Zaden And Diervoeders Gh",
    "sg:phone":"+31 162 456 183",
    "sg:postcode":"4904 SK",
    "sg:province":"Noord-Brabant",
    "wof:name":"Lac Bv",
    "wof:placetype":"venue"
},
  "geometry": {"coordinates":[4.866334,51.630394],"type":"Point"}
}