{
  "type": "Feature",
  "properties": {
    "addr:full":"Barteljorisstr 35 Haarlem North Holland 2011 RA",
    "addr:housenumber":"35",
    "addr:postcode":"2011 ra",
    "addr:street":"Barteljorisstr",
    "iso:country":"NL",
    "sg:address":"Barteljorisstr 35",
    "sg:city":"Haarlem",
    "sg:orig_category":"Boeken En Tijdschriften",
    "sg:phone":"+31 23 531 9198",
    "sg:postcode":"2011 RA",
    "sg:province":"North Holland",
    "wof:name":"Standaard",
    "wof:placetype":"venue"
},
  "geometry": {"coordinates":[4.635425,52.381897],"type":"Point"}
}