{
  "type": "Feature",
  "properties": {
    "addr:full":"Dalwg 7B Surhuisterveen Friesland 9231 HW",
    "addr:housenumber":"7b",
    "addr:postcode":"9231 hw",
    "addr:street":"Dalwg",
    "iso:country":"NL",
    "sg:address":"Dalwg 7B",
    "sg:city":"Surhuisterveen",
    "sg:orig_category":"Pottenbakkersmaterialen",
    "sg:phone":"+31 512 360 496",
    "sg:postcode":"9231 HW",
    "sg:province":"Friesland",
    "wof:name":"Creavisie",
    "wof:placetype":"venue"
},
  "geometry": {"coordinates":[6.183534,53.18071],"type":"Point"}
}