{
  "type": "Feature",
  "properties": {
    "iso:country":"NL",
    "sg:address":"Verlengde Broekdijk 29",
    "sg:city":"Kloosterhaar",
    "sg:classifiers":[
        {
            "category":"Sports & Exercise",
            "subcategory":"Skate Park",
            "type":"Entertainment"
        }
    ],
    "sg:phone":"+31 523 241 543",
    "sg:postcode":"7694 TD",
    "sg:province":"NL.08",
    "sg:tags":[
        "zandwinning",
        "grind-"
    ],
    "wof:name":"Balderhaar Bv",
    "wof:placetype":"venue"
},
  "geometry": {"coordinates":[6.693661,52.512379],"type":"Point"}
}