{
  "type": "Feature",
  "properties": {
    "addr:full":"Burgemeester De Manlaan 2 Breda North Brabant 4837 BN",
    "addr:housenumber":"2",
    "addr:postcode":"4837 bn",
    "addr:street":"Burgemeester De Manlaan",
    "iso:country":"NL",
    "sg:address":"Burgemeester De Manlaan 2",
    "sg:city":"Breda",
    "sg:classifiers":[
        {
            "category":"Professional",
            "subcategory":"Accounting & Tax Preparation",
            "type":"Services"
        }
    ],
    "sg:phone":"+31 76 560 2020",
    "sg:postcode":"4837 BN",
    "sg:province":"North Brabant",
    "sg:tags":[
        "accountant"
    ],
    "wof:name":"Abab Accountants",
    "wof:placetype":"venue"
},
  "geometry": {"coordinates":[4.758801,51.56287],"type":"Point"}
}