{
  "type": "Feature",
  "properties": {
    "addr:full":"Hofstee 10 Beuningen Gld Gelderland 6641 VP",
    "addr:housenumber":"10",
    "addr:postcode":"6641 vp",
    "addr:street":"Hofstee",
    "iso:country":"NL",
    "sg:address":"Hofstee 10",
    "sg:city":"Beuningen Gld",
    "sg:orig_category":"Marktonderzoekbureaus",
    "sg:phone":"+31 24 677 0110",
    "sg:postcode":"6641 VP",
    "sg:province":"Gelderland",
    "wof:name":"Gezondheidskundig Methodologisch Inst. (",
    "wof:placetype":"venue"
},
  "geometry": {"coordinates":[5.771297,51.854107],"type":"Point"}
}