{
  "type": "Feature",
  "properties": {
    "addr:full":"Broekseweg 40 Meerkerk South Holland 4231 VG",
    "addr:housenumber":"40",
    "addr:postcode":"4231 vg",
    "addr:street":"Broekseweg",
    "iso:country":"NL",
    "sg:address":"Broekseweg 40",
    "sg:city":"Meerkerk",
    "sg:orig_category":"Rijscholen",
    "sg:phone":"+31 183 352 520",
    "sg:postcode":"4231 VG",
    "sg:province":"South Holland",
    "wof:name":"Autorijschool Brakband",
    "wof:placetype":"venue"
},
  "geometry": {"coordinates":[4.985132,51.93206],"type":"Point"}
}