{
  "type": "Feature",
  "properties": {
    "iso:country":"NL",
    "sg:address":"Dotterbloem 8",
    "sg:city":"Kockengen",
    "sg:orig_category":"Adviesbureaus Bedrijfsorganisatie",
    "sg:phone":"+31 346 330 418",
    "sg:postcode":"3628 NM",
    "sg:province":"Utrecht",
    "wof:name":"Dehoko",
    "wof:placetype":"venue"
},
  "geometry": {"coordinates":[4.956584,52.151642],"type":"Point"}
}