{
  "type": "Feature",
  "properties": {
    "addr:full":"G Slagterln 15 Wognum North Holland 1687 CA",
    "addr:housenumber":"15",
    "addr:postcode":"1687 ca",
    "iso:country":"NL",
    "sg:address":"G Slagterln 15",
    "sg:city":"Wognum",
    "sg:orig_category":"Gordijnen",
    "sg:phone":"+31 229 573 000",
    "sg:postcode":"1687 CA",
    "sg:province":"North Holland",
    "wof:name":"Kamp, Nico",
    "wof:placetype":"venue"
},
  "geometry": {"coordinates":[5.025024,52.688263],"type":"Point"}
}