{
  "type": "Feature",
  "properties": {
    "addr:full":"Pr Hendrikstr 202 Gouda South Holland 2802 JN",
    "addr:housenumber":"202",
    "addr:postcode":"2802 jn",
    "iso:country":"NL",
    "sg:address":"Pr Hendrikstr 202",
    "sg:city":"Gouda",
    "sg:orig_category":"Wasmachines En Wasdrogers",
    "sg:phone":"+31 182 513 554",
    "sg:postcode":"2802 JN",
    "sg:province":"South Holland",
    "wof:name":"Louwerenburg Bv",
    "wof:placetype":"venue"
},
  "geometry": {"coordinates":[4.7022781372,52.0107307434],"type":"Point"}
}