{
  "type": "Feature",
  "properties": {
    "addr:full":"Nieuweweg 40-44 Valkenburg Lb Limburg 6301 EV",
    "addr:housenumber":"40-44",
    "addr:postcode":"lb",
    "addr:street":"Nieuweweg",
    "iso:country":"NL",
    "sg:address":"Nieuweweg 40-44",
    "sg:city":"Valkenburg Lb",
    "sg:classifiers":[
        {
            "category":"Travel",
            "subcategory":"Hotels & Motels",
            "type":"Entertainment"
        }
    ],
    "sg:phone":"+31 43 601 2000",
    "sg:postcode":"6301 EV",
    "sg:province":"Limburg",
    "wof:name":"Hotel Exploitatie J.H. Jaspers Bv",
    "wof:placetype":"venue"
},
  "geometry": {"coordinates":[5.835249,50.869091],"type":"Point"}
}