{
  "type": "Feature",
  "properties": {
    "addr:full":"Broekln 117 Tegelen Limburg 5931 KP",
    "addr:housenumber":"117",
    "addr:postcode":"5931 kp",
    "iso:country":"NL",
    "sg:address":"Broekln 117",
    "sg:city":"Tegelen",
    "sg:orig_category":"Automaterialen En Gereedschappen",
    "sg:phone":"+31 77 374 0145",
    "sg:postcode":"5931 KP",
    "sg:province":"Limburg",
    "sg:website":"http://www.brezan.nl",
    "wof:name":"Brezan",
    "wof:placetype":"venue"
},
  "geometry": {"coordinates":[6.13711,51.34362],"type":"Point"}
}