{
  "type": "Feature",
  "properties": {
    "iso:country":"NL",
    "sg:address":"Hofkamp 4",
    "sg:city":"Geleen",
    "sg:orig_category":"Pijpleidingen - Installatie En Onderhoud",
    "sg:phone":"+31 46 475 4800",
    "sg:postcode":"6161 DC",
    "sg:province":"Limburg",
    "wof:name":"Ouwerkerk Bv",
    "wof:placetype":"venue"
},
  "geometry": {"coordinates":[5.812131,50.961479],"type":"Point"}
}