{
  "type": "Feature",
  "properties": {
    "addr:full":"Zaanwg 69 En 72 Wormerveer Noord-Holland 1521 DM",
    "addr:housenumber":"69",
    "addr:postcode":"1521 dm",
    "addr:street":"Zaanwg;En 72",
    "iso:country":"NL",
    "sg:address":"Zaanwg 69 En 72",
    "sg:city":"Wormerveer",
    "sg:orig_category":"Behangselpapier En Wandbekleding",
    "sg:phone":"+31 75 621 8040",
    "sg:postcode":"1521 DM",
    "sg:province":"Noord-Holland",
    "wof:name":"Superwand Constant",
    "wof:placetype":"venue"
},
  "geometry": {"coordinates":[4.791767,52.493217],"type":"Point"}
}