{
  "type": "Feature",
  "properties": {
    "iso:country":"NL",
    "sg:address":"Berglustlaan 92",
    "sg:city":"Rotterdam",
    "sg:orig_category":"Verlichting And Huishoudartikelen",
    "sg:phone":"+31 10 418 2636",
    "sg:postcode":"3054 BK",
    "sg:province":"South Holland",
    "wof:name":"In-Lite",
    "wof:placetype":"venue"
},
  "geometry": {"coordinates":[4.488162,51.95636],"type":"Point"}
}