{
  "type": "Feature",
  "properties": {
    "iso:country":"NL",
    "sg:address":"Mauritsstr 38",
    "sg:city":"Eindhoven",
    "sg:orig_category":"Accountants - Administratie- Consulenten En -Kantoren",
    "sg:phone":"+31 40 244 8914",
    "sg:postcode":"5616 AB",
    "sg:province":"Noord-Brabant",
    "wof:name":"Bam",
    "wof:placetype":"venue"
},
  "geometry": {"coordinates":[5.469814,51.436317],"type":"Point"}
}