{
  "type": "Feature",
  "properties": {
    "iso:country":"NL",
    "sg:address":"Bronsbergen 4C",
    "sg:city":"Zutphen",
    "sg:classifiers":[
        {
            "category":"Sports & Exercise",
            "subcategory":"Stables",
            "type":"Entertainment"
        }
    ],
    "sg:phone":"+31 575 525 939",
    "sg:postcode":"7207 AA",
    "sg:province":"Gelderland",
    "sg:tags":[
        "maneges"
    ],
    "sg:website":"http://www.eenhoorn.org",
    "wof:name":"Eenhoorn, De",
    "wof:placetype":"venue"
},
  "geometry": {"coordinates":[6.197265,52.117123],"type":"Point"}
}