{
  "type": "Feature",
  "properties": {
    "addr:full":"Lageweg 2 Sint Maartensdijk Zeeland 4695 PT",
    "addr:housenumber":"2",
    "addr:postcode":"4695 pt",
    "addr:street":"Lageweg",
    "iso:country":"NL",
    "sg:address":"Lageweg 2",
    "sg:city":"Sint Maartensdijk",
    "sg:orig_category":"Fotografie Reclame En Mode",
    "sg:phone":"+31 166 653 351",
    "sg:postcode":"4695 PT",
    "sg:province":"Zeeland",
    "wof:name":"Groenewege, Corry",
    "wof:placetype":"venue"
},
  "geometry": {"coordinates":[4.075759,51.58786],"type":"Point"}
}