{
  "type": "Feature",
  "properties": {
    "iso:country":"NL",
    "sg:address":"H W Mesdagln 4",
    "sg:city":"Heemstede",
    "sg:orig_category":"Facilitaire Dienstverlening",
    "sg:phone":"+31 23 528 8514",
    "sg:postcode":"2102 BD",
    "sg:province":"Noord-Holland",
    "wof:name":"Vesta",
    "wof:placetype":"venue"
},
  "geometry": {"coordinates":[4.621248,52.345287],"type":"Point"}
}