{
  "type": "Feature",
  "properties": {
    "addr:full":"Heemraadwg 417 Weesp Noord-Holland 1382 HJ",
    "addr:housenumber":"417",
    "addr:postcode":"1382 hj",
    "iso:country":"NL",
    "sg:address":"Heemraadwg 417",
    "sg:city":"Weesp",
    "sg:orig_category":"Elektrotechnische Installatiebureaus",
    "sg:phone":"+31 6 22912131",
    "sg:postcode":"1382 HJ",
    "sg:province":"Noord-Holland",
    "wof:name":"Mvo",
    "wof:placetype":"venue"
},
  "geometry": {"coordinates":[5.028755,52.315563],"type":"Point"}
}