{
  "type": "Feature",
  "properties": {
    "iso:country":"NL",
    "sg:address":"Oranje Nassaulaan 63",
    "sg:city":"Culemborg",
    "sg:orig_category":"Boekhouders",
    "sg:phone":"+31 345 512 405",
    "sg:postcode":"4101 JS",
    "sg:province":"Gelderland",
    "wof:name":"Administratiekantoor L.H. Gommans",
    "wof:placetype":"venue"
},
  "geometry": {"coordinates":[5.239259,51.95686],"type":"Point"}
}