{
  "type": "Feature",
  "properties": {
    "iso:country":"NL",
    "sg:address":"Duinweg 11",
    "sg:city":"Castricum",
    "sg:orig_category":"Architecten",
    "sg:phone":"+31 72 505 2623",
    "sg:postcode":"1901 ML",
    "sg:province":"Noord-Holland",
    "wof:name":"C J Berkhout",
    "wof:placetype":"venue"
},
  "geometry": {"coordinates":[4.662434,52.577927],"type":"Point"}
}