{
  "type": "Feature",
  "properties": {
    "addr:full":"Duinweg 11 Castricum Noord-Holland 1901 ML",
    "addr:housenumber":"11",
    "addr:postcode":"1901 ml",
    "addr:street":"Duinweg",
    "iso:country":"NL",
    "sg:address":"Duinweg 11",
    "sg:city":"Castricum",
    "sg:orig_category":"Architecten",
    "sg:phone":"+31 72 505 2623",
    "sg:postcode":"1901 ML",
    "sg:province":"Noord-Holland",
    "wof:name":"C J Berkhout",
    "wof:placetype":"venue"
},
  "geometry": {"coordinates":[4.662434,52.577927],"type":"Point"}
}