{
  "type": "Feature",
  "properties": {
    "addr:full":"Postbus 19365 S Gravenhage South Holland 2500 CJ",
    "addr:housenumber":"19365",
    "addr:postcode":"2500 cj",
    "addr:street":"Postbus;S Gravenhage",
    "iso:country":"NL",
    "sg:address":"Postbus 19365",
    "sg:city":"S Gravenhage",
    "sg:orig_category":"Bedrijfsorganisaties",
    "sg:phone":"+31 70 375 1751",
    "sg:postcode":"2500 CJ",
    "sg:province":"South Holland",
    "wof:name":"Transfrigoroute Holland",
    "wof:placetype":"venue"
},
  "geometry": {"coordinates":[4.31741,52.083988],"type":"Point"}
}