{
  "type": "Feature",
  "properties": {
    "iso:country":"NL",
    "sg:address":"Commandeurskd 46A",
    "sg:city":"Maasland",
    "sg:orig_category":"Adviesbureaus Elektrotechniek",
    "sg:phone":"+31 10 590 3040",
    "sg:postcode":"3155 AD",
    "sg:province":"Zuid-Holland",
    "wof:name":"Bepect Bv",
    "wof:placetype":"venue"
},
  "geometry": {"coordinates":[4.275135,51.936325],"type":"Point"}
}