{
  "type": "Feature",
  "properties": {
    "addr:full":"Tesselschadestr 4-12 Amsterdam Noord-Holland 1054 ET",
    "addr:housenumber":"4-12",
    "addr:postcode":"1054 et",
    "iso:country":"NL",
    "sg:address":"Tesselschadestr 4-12",
    "sg:city":"Amsterdam",
    "sg:orig_category":"Bedrijfsopleidingen",
    "sg:phone":"+31 20 412 4120",
    "sg:postcode":"1054 ET",
    "sg:province":"Noord-Holland",
    "sg:website":"http://www.mtenv.nl",
    "wof:name":"Mt&V Werving & Selectie",
    "wof:placetype":"venue"
},
  "geometry": {"coordinates":[4.879409,52.362209],"type":"Point"}
}