{
  "type": "Feature",
  "properties": {
    "iso:country":"NL",
    "sg:address":"Troubadourweg 2",
    "sg:city":"Alphen A/D Rijn",
    "sg:orig_category":"Overheidsdiensten",
    "sg:phone":"+31 172 421 190",
    "sg:postcode":"2402 EP",
    "sg:province":"South Holland",
    "wof:name":"De Rotonde",
    "wof:placetype":"venue"
},
  "geometry": {"coordinates":[4.6736679077,52.1457557678],"type":"Point"}
}