{
  "type": "Feature",
  "properties": {
    "addr:full":"Sweelincklaan 40 Boxtel Noord-Brabant 5283 HR",
    "addr:housenumber":"40",
    "addr:postcode":"5283 hr",
    "addr:street":"Sweelincklaan",
    "iso:country":"NL",
    "sg:address":"Sweelincklaan 40",
    "sg:city":"Boxtel",
    "sg:orig_category":"Loodgieterswerk, Verwarming And Sanitaire Installaties",
    "sg:phone":"+31 411 682 249",
    "sg:postcode":"5283 HR",
    "sg:province":"Noord-Brabant",
    "wof:name":"Van Ruremonde",
    "wof:placetype":"venue"
},
  "geometry": {"coordinates":[5.344375,51.585957],"type":"Point"}
}