{
  "type": "Feature",
  "properties": {
    "addr:full":"Gasthuisstraat 56 Winterswijk Gelderland 7101 DW",
    "addr:housenumber":"56",
    "addr:postcode":"7101 dw",
    "addr:street":"Gasthuisstraat;Gelderland",
    "iso:country":"NL",
    "sg:address":"Gasthuisstraat 56",
    "sg:city":"Winterswijk",
    "sg:orig_category":"Fietshandelaren",
    "sg:phone":"+31 543 512 384",
    "sg:postcode":"7101 DW",
    "sg:province":"Gelderland",
    "wof:name":"J.B. Bruggers",
    "wof:placetype":"venue"
},
  "geometry": {"coordinates":[6.715039,51.972439],"type":"Point"}
}