{
  "type": "Feature",
  "properties": {
    "addr:full":"Hamburgerweg 141 Ermelo Gelderland 3851 EJ",
    "addr:housenumber":"141",
    "addr:postcode":"3851 ej",
    "addr:street":"Hamburgerweg;Gelderland",
    "iso:country":"NL",
    "sg:address":"Hamburgerweg 141",
    "sg:city":"Ermelo",
    "sg:classifiers":[
        {
            "category":"Education",
            "subcategory":"Preschool",
            "type":"Public Place"
        }
    ],
    "sg:phone":"+31 341 557 900",
    "sg:postcode":"3851 EJ",
    "sg:province":"Gelderland",
    "sg:tags":[
        "kleuteronderwijs",
        "basis-"
    ],
    "wof:name":"Prot Chr Basisschool Margriet",
    "wof:placetype":"venue"
},
  "geometry": {"coordinates":[5.617223,52.295574],"type":"Point"}
}