{
  "type": "Feature",
  "properties": {
    "addr:full":"Ollandsewg 134 St Oedenrode North Brabant 5491 XC",
    "addr:housenumber":"134",
    "addr:postcode":"5491 xc",
    "addr:street":"St Oedenrode",
    "iso:country":"NL",
    "sg:address":"Ollandsewg 134",
    "sg:city":"St Oedenrode",
    "sg:orig_category":"Houtgroothandel",
    "sg:phone":"+31 413 472 169",
    "sg:postcode":"5491 XC",
    "sg:province":"North Brabant",
    "wof:name":"Smetsers, Gebroeders",
    "wof:placetype":"venue"
},
  "geometry": {"coordinates":[5.437627,51.569599],"type":"Point"}
}