{
  "type": "Feature",
  "properties": {
    "addr:full":"Schiedamsedk 68A Rotterdam Zuid-Holland 3011 EK",
    "addr:housenumber":"68a",
    "addr:postcode":"3011 ek",
    "addr:street":"Schiedamsedk",
    "iso:country":"NL",
    "sg:address":"Schiedamsedk 68A",
    "sg:city":"Rotterdam",
    "sg:orig_category":"Makelaars En Adviseurs Onroerende Goederen",
    "sg:phone":"+31 10 433 1160",
    "sg:postcode":"3011 EK",
    "sg:province":"Zuid-Holland",
    "wof:name":"Vroedt, De",
    "wof:placetype":"venue"
},
  "geometry": {"coordinates":[4.481705,51.915089],"type":"Point"}
}