{
  "type": "Feature",
  "properties": {
    "addr:full":"Dr Ruysstr 17A Ravenstein Noord-Brabant 5371 PS",
    "addr:housenumber":"17a",
    "addr:postcode":"5371 ps",
    "iso:country":"NL",
    "sg:address":"Dr Ruysstr 17A",
    "sg:city":"Ravenstein",
    "sg:orig_category":"Scholen Voor Basisonderwijs",
    "sg:phone":"+31 486 411 696",
    "sg:postcode":"5371 PS",
    "sg:province":"Noord-Brabant",
    "wof:name":"Antonius Abt, St",
    "wof:placetype":"venue"
},
  "geometry": {"coordinates":[5.671612,51.775166],"type":"Point"}
}