{
  "type": "Feature",
  "properties": {
    "addr:full":"Sint Jorisweg 8 Dordrecht Zuid-Holland 3311 PL",
    "addr:housenumber":"8",
    "addr:postcode":"3311 pl",
    "addr:street":"Sint Jorisweg",
    "iso:country":"NL",
    "sg:address":"Sint Jorisweg 8",
    "sg:city":"Dordrecht",
    "sg:classifiers":[
        {
            "category":"Bakery",
            "type":"Food & Drink"
        }
    ],
    "sg:phone":"+31 78 635 0514",
    "sg:postcode":"3311 PL",
    "sg:province":"Zuid-Holland",
    "sg:tags":[
        "brood",
        "banket"
    ],
    "wof:name":"Lale",
    "wof:placetype":"venue"
},
  "geometry": {"coordinates":[4.674565,51.814507],"type":"Point"}
}