{
  "type": "Feature",
  "properties": {
    "addr:full":"Nude 1 Wageningen Gelderland 6702 DH",
    "addr:housenumber":"1",
    "addr:postcode":"6702 dh",
    "addr:street":"Nude;Gelderland",
    "iso:country":"NL",
    "sg:address":"Nude 1",
    "sg:city":"Wageningen",
    "sg:classifiers":[
        {
            "category":"Home & Garden",
            "subcategory":"Garden Supply",
            "type":"Retail Goods"
        }
    ],
    "sg:phone":"+31 317 412 274",
    "sg:postcode":"6702 DH",
    "sg:province":"Gelderland",
    "sg:tags":[
        "zand",
        "en",
        "grind"
    ],
    "wof:name":"Leusden Bv, Van",
    "wof:placetype":"venue"
},
  "geometry": {"coordinates":[5.658435,51.962753],"type":"Point"}
}