{
  "type": "Feature",
  "properties": {
    "addr:full":"Jo Vincentlaan 2 Oegstgeest Zuid-Holland 2343 PK",
    "addr:housenumber":"2",
    "addr:postcode":"2343 pk",
    "addr:street":"Jo Vincentlaan",
    "iso:country":"NL",
    "sg:address":"Jo Vincentlaan 2",
    "sg:city":"Oegstgeest",
    "sg:orig_category":"Artsen And Specialisten",
    "sg:phone":"+31 71 517 5220",
    "sg:postcode":"2343 PK",
    "sg:province":"Zuid-Holland",
    "wof:name":"Drs. F.Th. Lunshof-Klein",
    "wof:placetype":"venue"
},
  "geometry": {"coordinates":[4.474403,52.193653],"type":"Point"}
}