{
  "type": "Feature",
  "properties": {
    "addr:full":"Beatrixstraat 17 Den Helder North Holland 1781 EM",
    "addr:housenumber":"17",
    "addr:postcode":"1781 em",
    "addr:street":"Beatrixstraat",
    "iso:country":"NL",
    "sg:address":"Beatrixstraat 17",
    "sg:city":"Den Helder",
    "sg:orig_category":"Werving And Selectie Van Tijdelijk Personeel And Uitzendkantoren",
    "sg:phone":"+31 223 628 059",
    "sg:postcode":"1781 EM",
    "sg:province":"North Holland",
    "wof:name":"Dactylo",
    "wof:placetype":"venue"
},
  "geometry": {"coordinates":[4.7649960518,52.9575996399],"type":"Point"}
}