{
  "type": "Feature",
  "properties": {
    "addr:full":"Bosboom Touss Str 8 Dordrecht South Holland 3314 GD",
    "addr:housenumber":"8",
    "addr:postcode":"3314 gd",
    "addr:street":"Bosboom;Str",
    "iso:country":"NL",
    "sg:address":"Bosboom Touss Str 8",
    "sg:city":"Dordrecht",
    "sg:orig_category":"Bloemen En Planten",
    "sg:phone":"+31 78 613 6777",
    "sg:postcode":"3314 GD",
    "sg:province":"South Holland",
    "wof:name":"Super Flora",
    "wof:placetype":"venue"
},
  "geometry": {"coordinates":[4.66349,51.803535],"type":"Point"}
}