{
  "type": "Feature",
  "properties": {
    "addr:full":"Dorpstraat 13 Dreumel Gelderland 6621 CC",
    "addr:housenumber":"13",
    "addr:postcode":"6621 cc",
    "addr:street":"Dorpstraat;Gelderland",
    "iso:country":"NL",
    "sg:address":"Dorpstraat 13",
    "sg:city":"Dreumel",
    "sg:orig_category":"Kappers",
    "sg:phone":"+31 487 571 782",
    "sg:postcode":"6621 CC",
    "sg:province":"Gelderland",
    "wof:name":"M G Verbruggen",
    "wof:placetype":"venue"
},
  "geometry": {"coordinates":[5.434067,51.849686],"type":"Point"}
}