{
  "type": "Feature",
  "properties": {
    "addr:full":"Gele Ryders Pln 1 Arnhem Gelderland 6811 AN",
    "addr:housenumber":"1",
    "addr:postcode":"6811 an",
    "addr:street":"Gele;Pln",
    "iso:country":"NL",
    "sg:address":"Gele Ryders Pln 1",
    "sg:city":"Arnhem",
    "sg:orig_category":"Parketvloeren",
    "sg:phone":"+31 26 443 6522",
    "sg:postcode":"6811 AN",
    "sg:province":"Gelderland",
    "wof:name":"Parketland",
    "wof:placetype":"venue"
},
  "geometry": {"coordinates":[5.907391,51.983192],"type":"Point"}
}