{
  "type": "Feature",
  "properties": {
    "addr:full":"Roodenburgerstr 60 Leiden Zuid-Holland 2313 HL",
    "addr:housenumber":"60",
    "addr:postcode":"2313 hl",
    "addr:street":"Roodenburgerstr",
    "iso:country":"NL",
    "sg:address":"Roodenburgerstr 60",
    "sg:city":"Leiden",
    "sg:orig_category":"Houtbewerking",
    "sg:phone":"+31 71 513 2050",
    "sg:postcode":"2313 HL",
    "sg:province":"Zuid-Holland",
    "sg:website":"http://www.prodart.nl",
    "wof:name":"A & V Prodart",
    "wof:placetype":"venue"
},
  "geometry": {"coordinates":[4.501909,52.150002],"type":"Point"}
}