{
  "type": "Feature",
  "properties": {
    "iso:country":"NL",
    "sg:address":"Dennenlaan 63",
    "sg:city":"Zwanenburg",
    "sg:orig_category":"Bloemen And Planten",
    "sg:phone":"+31 20 497 4856",
    "sg:postcode":"1161 JM",
    "sg:province":"Noord-Holland",
    "wof:name":"Bloemsierkunst Van Velsen",
    "wof:placetype":"venue"
},
  "geometry": {"coordinates":[4.749727,52.378601],"type":"Point"}
}