{
  "type": "Feature",
  "properties": {
    "addr:full":"Gooiland 8 Beverwijk Noord-Holland 1948 RC",
    "addr:housenumber":"8",
    "addr:postcode":"1948 rc",
    "addr:street":"Gooiland",
    "iso:country":"NL",
    "sg:address":"Gooiland 8",
    "sg:city":"Beverwijk",
    "sg:orig_category":"Technische Studies And Onderzoek",
    "sg:phone":"+31 251 229 160",
    "sg:postcode":"1948 RC",
    "sg:province":"Noord-Holland",
    "wof:name":"Van Tongeren Kennemer Bv",
    "wof:placetype":"venue"
},
  "geometry": {"coordinates":[4.670966,52.468952],"type":"Point"}
}