{
  "type": "Feature",
  "properties": {
    "addr:full":"Bosstr 11 Driebergen Rysenb Utrecht 3971 XA",
    "addr:housenumber":"11",
    "addr:postcode":"3971 xa",
    "addr:street":"Bosstr;Rysenb",
    "iso:country":"NL",
    "sg:address":"Bosstr 11",
    "sg:city":"Driebergen Rysenb",
    "sg:orig_category":"Fotoreportages",
    "sg:phone":"+31 343 518 073",
    "sg:postcode":"3971 XA",
    "sg:province":"Utrecht",
    "wof:name":"Kuijk, D",
    "wof:placetype":"venue"
},
  "geometry": {"coordinates":[5.281589,52.053543],"type":"Point"}
}