{
  "type": "Feature",
  "properties": {
    "iso:country":"NL",
    "sg:address":"Panderpad 1",
    "sg:city":"Gieten",
    "sg:orig_category":"Woninginrichting",
    "sg:phone":"+31 592 262 037",
    "sg:postcode":"9461 GZ",
    "sg:province":"Provincie Drenthe",
    "wof:name":"Hcv",
    "wof:placetype":"venue"
},
  "geometry": {"coordinates":[6.7678480148,52.9973678589],"type":"Point"}
}