{
  "type": "Feature",
  "properties": {
    "addr:full":"Flevowg 13 Leiden South Holland 2318 BZ",
    "addr:housenumber":"13",
    "addr:postcode":"2318 bz",
    "addr:street":"Flevowg",
    "iso:country":"NL",
    "sg:address":"Flevowg 13",
    "sg:city":"Leiden",
    "sg:orig_category":"Adviesbureaus Bouwkunde",
    "sg:phone":"+31 71 523 2595",
    "sg:postcode":"2318 BZ",
    "sg:province":"South Holland",
    "wof:name":"Berg, Herms Van Den",
    "wof:placetype":"venue"
},
  "geometry": {"coordinates":[4.497511,52.176331],"type":"Point"}
}