{
  "type": "Feature",
  "properties": {
    "addr:full":"Lusthofstr 45 Rotterdam Zuid-Holland 3061 WK",
    "addr:housenumber":"45",
    "addr:postcode":"3061 wk",
    "addr:street":"Lusthofstr",
    "iso:country":"NL",
    "sg:address":"Lusthofstr 45",
    "sg:city":"Rotterdam",
    "sg:classifiers":[
        {
            "category":"Food & Beverages",
            "subcategory":"Bakery",
            "type":"Retail Goods"
        }
    ],
    "sg:phone":"+31 10 214 0684",
    "sg:postcode":"3061 WK",
    "sg:province":"Zuid-Holland",
    "sg:tags":[
        "pizza"
    ],
    "wof:name":"King",
    "wof:placetype":"venue"
},
  "geometry": {"coordinates":[4.511104,51.923943],"type":"Point"}
}