{
  "type": "Feature",
  "properties": {
    "addr:full":"Hallincqln 2 Dordrecht Zuid-Holland 3311 SC",
    "addr:housenumber":"2",
    "addr:postcode":"3311 sc",
    "addr:street":"Hallincqln",
    "iso:country":"NL",
    "sg:address":"Hallincqln 2",
    "sg:city":"Dordrecht",
    "sg:classifiers":[
        {
            "category":"Personal",
            "subcategory":"Nail Salon",
            "type":"Services"
        }
    ],
    "sg:phone":"+31 78 631 7551",
    "sg:postcode":"3311 SC",
    "sg:province":"Zuid-Holland",
    "sg:tags":[
        "pedicure"
    ],
    "wof:name":"Zonnehoek, De",
    "wof:placetype":"venue"
},
  "geometry": {"coordinates":[4.677767,51.813442],"type":"Point"}
}