{
  "type": "Feature",
  "properties": {
    "addr:full":"Bergstraat 20 Deventer Overijssel 7411 ET",
    "addr:housenumber":"20",
    "addr:postcode":"7411 et",
    "addr:street":"Bergstraat",
    "iso:country":"NL",
    "sg:address":"Bergstraat 20",
    "sg:city":"Deventer",
    "sg:orig_category":"Beautyfarms And Sauna'S",
    "sg:phone":"+31 570 644 927",
    "sg:postcode":"7411 ET",
    "sg:province":"Overijssel",
    "wof:name":"Kuur En Natuur",
    "wof:placetype":"venue"
},
  "geometry": {"coordinates":[6.161846,52.251884],"type":"Point"}
}