{
  "type": "Feature",
  "properties": {
    "addr:full":"Pr Bernhardln 2 Utrecht Utrecht 3555 AD",
    "addr:housenumber":"2",
    "addr:postcode":"3555 ad",
    "iso:country":"NL",
    "sg:address":"Pr Bernhardln 2",
    "sg:city":"Utrecht",
    "sg:orig_category":"Verenigingen En Stichtingen",
    "sg:phone":"+31 30 244 2110",
    "sg:postcode":"3555 AD",
    "sg:province":"Utrecht",
    "wof:name":"Dienstencentr Zuilen",
    "wof:placetype":"venue"
},
  "geometry": {"coordinates":[5.07365,52.119228],"type":"Point"}
}