{
  "type": "Feature",
  "properties": {
    "addr:full":"Rozentuin 92 Voorburg Zuid-Holland 2272 XE",
    "addr:housenumber":"92",
    "addr:postcode":"2272 xe",
    "addr:street":"Rozentuin",
    "iso:country":"NL",
    "sg:address":"Rozentuin 92",
    "sg:city":"Voorburg",
    "sg:orig_category":"Chemische Producten Gh",
    "sg:phone":"+31 70 386 5084",
    "sg:postcode":"2272 XE",
    "sg:province":"Zuid-Holland",
    "wof:name":"Lenmar Chemicals",
    "wof:placetype":"venue"
},
  "geometry": {"coordinates":[4.368468,52.082672],"type":"Point"}
}