{
  "type": "Feature",
  "properties": {
    "addr:full":"Groeneweg 166 Bunnik Utrecht 3981 CP",
    "addr:housenumber":"166",
    "addr:postcode":"3981 cp",
    "addr:street":"Groeneweg",
    "iso:country":"NL",
    "sg:address":"Groeneweg 166",
    "sg:city":"Bunnik",
    "sg:orig_category":"Verhuur Catering-, Feest- En Evenementbenodigdheden",
    "sg:phone":"+31 30 656 4120",
    "sg:postcode":"3981 CP",
    "sg:province":"Utrecht",
    "wof:name":"Palux Bv",
    "wof:placetype":"venue"
},
  "geometry": {"coordinates":[5.192152,52.062767],"type":"Point"}
}