{
  "type": "Feature",
  "properties": {
    "addr:full":"De Giem 6 Enschede Overijssel 7547 SV",
    "addr:housenumber":"6",
    "addr:postcode":"7547 sv",
    "addr:street":"De Giem",
    "iso:country":"NL",
    "sg:address":"De Giem 6",
    "sg:city":"Enschede",
    "sg:orig_category":"Administratie- En Boekhoudkantoren",
    "sg:phone":"+31 53 431 8328",
    "sg:postcode":"7547 SV",
    "sg:province":"Overijssel",
    "wof:name":"Berkouwer Bv, A",
    "wof:placetype":"venue"
},
  "geometry": {"coordinates":[6.837763,52.220177],"type":"Point"}
}