{
  "type": "Feature",
  "properties": {
    "addr:full":"Prof Rutgersstr 10 Vlaardingen South Holland 3132 NK",
    "addr:housenumber":"10",
    "addr:postcode":"3132 nk",
    "iso:country":"NL",
    "sg:address":"Prof Rutgersstr 10",
    "sg:city":"Vlaardingen",
    "sg:orig_category":"Biljartzalen",
    "sg:phone":"+31 10 434 1863",
    "sg:postcode":"3132 NK",
    "sg:province":"South Holland",
    "wof:name":"Ouwe Rein, D'",
    "wof:placetype":"venue"
},
  "geometry": {"coordinates":[4.318435,51.909927],"type":"Point"}
}