{
  "type": "Feature",
  "properties": {
    "addr:full":"Wilhelminaln 11 Baarn Utrecht 3743 DB",
    "addr:housenumber":"11",
    "addr:postcode":"3743 db",
    "addr:street":"Wilhelminaln",
    "iso:country":"NL",
    "sg:address":"Wilhelminaln 11",
    "sg:city":"Baarn",
    "sg:orig_category":"Adviesbureaus Bedrijfsorganisatie",
    "sg:phone":"+31 35 542 9105",
    "sg:postcode":"3743 DB",
    "sg:province":"Utrecht",
    "wof:name":"Kruijff Baarn",
    "wof:placetype":"venue"
},
  "geometry": {"coordinates":[5.275867,52.210106],"type":"Point"}
}