{
  "type": "Feature",
  "properties": {
    "iso:country":"NL",
    "sg:address":"Dracht 55",
    "sg:city":"Heerenveen",
    "sg:orig_category":"Drogisterijen",
    "sg:phone":"+31 513 654 844",
    "sg:postcode":"8442 BL",
    "sg:province":"Friesland",
    "wof:name":"Da Drogisterij Yvonne Prinsen",
    "wof:placetype":"venue"
},
  "geometry": {"coordinates":[5.924828,52.958618],"type":"Point"}
}