{
  "type": "Feature",
  "properties": {
    "iso:country":"NL",
    "sg:address":"Rijnlaan 165",
    "sg:city":"Utrecht",
    "sg:orig_category":"Juweliers",
    "sg:phone":"+31 30 288 1107",
    "sg:postcode":"3522 BJ",
    "sg:province":"Utrecht",
    "wof:name":"Juwelier - Goudsmid Fa. Braster",
    "wof:placetype":"venue"
},
  "geometry": {"coordinates":[5.113185,52.070675],"type":"Point"}
}