{
  "type": "Feature",
  "properties": {
    "addr:full":"Gitaarhof 6 Etten-Leur Noord-Brabant 4876 VB",
    "addr:housenumber":"6",
    "addr:postcode":"4876 vb",
    "addr:street":"Gitaarhof",
    "iso:country":"NL",
    "sg:address":"Gitaarhof 6",
    "sg:city":"Etten-Leur",
    "sg:orig_category":"Boekhouders",
    "sg:phone":"+31 76 501 3342",
    "sg:postcode":"4876 VB",
    "sg:province":"Noord-Brabant",
    "wof:name":"Administratiekantoor Baremans",
    "wof:placetype":"venue"
},
  "geometry": {"coordinates":[4.630348,51.558937],"type":"Point"}
}