{
  "type": "Feature",
  "properties": {
    "addr:full":"Lysterln 8 Apeldoorn Gelderland 7331 TV",
    "addr:housenumber":"8",
    "addr:postcode":"7331 tv",
    "addr:street":"Lysterln;Gelderland",
    "iso:country":"NL",
    "sg:address":"Lysterln 8",
    "sg:city":"Apeldoorn",
    "sg:orig_category":"Voegwerken",
    "sg:phone":"+31 55 533 4563",
    "sg:postcode":"7331 TV",
    "sg:province":"Gelderland",
    "wof:name":"Bosch, F Van Den",
    "wof:placetype":"venue"
},
  "geometry": {"coordinates":[5.96886,52.201382],"type":"Point"}
}