{
  "type": "Feature",
  "properties": {
    "addr:full":"Nautilustraat 3 K Emmen Drenthe 7821 AG",
    "addr:housenumber":"3 k",
    "addr:postcode":"7821",
    "addr:street":"Nautilustraat",
    "iso:country":"NL",
    "sg:address":"Nautilustraat 3 K",
    "sg:city":"Emmen",
    "sg:orig_category":"Drukkerijen And Copyshops",
    "sg:phone":"+31 591 611 099",
    "sg:postcode":"7821 AG",
    "sg:province":"Drenthe",
    "wof:name":"Drukkerij Van Liere",
    "wof:placetype":"venue"
},
  "geometry": {"coordinates":[6.91446,52.767658],"type":"Point"}
}