{
  "type": "Feature",
  "properties": {
    "addr:full":"Zuilenstr 100 Breda Noord-Brabant 4814 ND",
    "addr:housenumber":"100",
    "addr:postcode":"4814 nd",
    "iso:country":"NL",
    "sg:address":"Zuilenstr 100",
    "sg:city":"Breda",
    "sg:orig_category":"Arbo- En Bedrijfsgezondheids- Diensten",
    "sg:phone":"+31 76 523 1950",
    "sg:postcode":"4814 ND",
    "sg:province":"Noord-Brabant",
    "wof:name":"Arbo Groep Gak Bv",
    "wof:placetype":"venue"
},
  "geometry": {"coordinates":[4.7455,51.582481],"type":"Point"}
}