{
  "type": "Feature",
  "properties": {
    "iso:country":"NL",
    "sg:address":"Sebastiaanstraat 10",
    "sg:city":"Ell",
    "sg:orig_category":"Overheidsdiensten",
    "sg:phone":"+31 495 551 931",
    "sg:postcode":"6011 RE",
    "sg:province":"Limburg",
    "wof:name":"Ellenhof",
    "wof:placetype":"venue"
},
  "geometry": {"coordinates":[-98.10106658940001,27.5270004272],"type":"Point"}
}