{
  "type": "Feature",
  "properties": {
    "addr:full":"Sebastiaanstraat 10 Ell Limburg 6011 RE",
    "addr:housenumber":"10",
    "addr:postcode":"6011 re",
    "addr:street":"Sebastiaanstraat",
    "iso:country":"NL",
    "sg:address":"Sebastiaanstraat 10",
    "sg:city":"Ell",
    "sg:orig_category":"Overheidsdiensten",
    "sg:phone":"+31 495 551 931",
    "sg:postcode":"6011 RE",
    "sg:province":"Limburg",
    "wof:name":"Ellenhof",
    "wof:placetype":"venue"
},
  "geometry": {"coordinates":[-98.10106658940001,27.5270004272],"type":"Point"}
}