{
  "type": "Feature",
  "properties": {
    "iso:country":"NL",
    "sg:address":"Veldzigt 12",
    "sg:city":"De Meern",
    "sg:orig_category":"Kantoor- En Bedrijfsmeubelen",
    "sg:phone":"+31 30 662 1929",
    "sg:postcode":"3454 PW",
    "sg:province":"Utrecht",
    "sg:website":"http://www.nivoburo.nl",
    "wof:name":"Nivoburo Bv",
    "wof:placetype":"venue"
},
  "geometry": {"coordinates":[5.0488080978,52.0735321045],"type":"Point"}
}