{
  "type": "Feature",
  "properties": {
    "addr:full":"Industriewg 6C Assendelft Noord-Holland 1566 JP",
    "addr:housenumber":"6c",
    "addr:postcode":"1566 jp",
    "addr:street":"Industriewg",
    "iso:country":"NL",
    "sg:address":"Industriewg 6C",
    "sg:city":"Assendelft",
    "sg:orig_category":"Grafische Bedrijven",
    "sg:phone":"+31 75 640 7422",
    "sg:postcode":"1566 JP",
    "sg:province":"Noord-Holland",
    "wof:name":"Stepa Bv",
    "wof:placetype":"venue"
},
  "geometry": {"coordinates":[4.766501,52.491207],"type":"Point"}
}