{
  "type": "Feature",
  "properties": {
    "addr:full":"Lijsterbesstraat 67 'S Gravenhage South Holland 2563 KR",
    "addr:housenumber":"67",
    "addr:postcode":"2563 kr",
    "addr:street":"Lijsterbesstraat;' S Gravenhage",
    "iso:country":"NL",
    "sg:address":"Lijsterbesstraat 67",
    "sg:city":"'S Gravenhage",
    "sg:orig_category":"Vaste And Vloeibare Brandstoffen",
    "sg:phone":"+31 70 345 2243",
    "sg:postcode":"2563 KR",
    "sg:province":"South Holland",
    "wof:name":"Fa Vreeburg",
    "wof:placetype":"venue"
},
  "geometry": {"coordinates":[4.265155,52.073544],"type":"Point"}
}