{
  "type": "Feature",
  "properties": {
    "addr:full":"Padangstr 16 Enschede Overijssel 7535 AD",
    "addr:housenumber":"16",
    "addr:postcode":"7535 ad",
    "addr:street":"Padangstr",
    "iso:country":"NL",
    "sg:address":"Padangstr 16",
    "sg:city":"Enschede",
    "sg:orig_category":"Honden- En Kattentrimsalons",
    "sg:phone":"+31 53 431 0434",
    "sg:postcode":"7535 AD",
    "sg:province":"Overijssel",
    "wof:name":"Dingo Hondensalon",
    "wof:placetype":"venue"
},
  "geometry": {"coordinates":[6.909593,52.213028],"type":"Point"}
}