{
  "type": "Feature",
  "properties": {
    "addr:full":"Hoofdstraat 33 Schimmert Limburg 6333 BE",
    "addr:housenumber":"33",
    "addr:postcode":"6333",
    "addr:street":"Hoofdstraat",
    "iso:country":"NL",
    "sg:address":"Hoofdstraat 33",
    "sg:city":"Schimmert",
    "sg:classifiers":[
        {
            "category":"Fast Food",
            "type":"Food & Drink"
        }
    ],
    "sg:phone":"+31 45 404 1253",
    "sg:postcode":"6333 BE",
    "sg:province":"Limburg",
    "sg:tags":[
        "afhaal",
        "restaurant"
    ],
    "wof:name":"Friture 'T Hoentje",
    "wof:placetype":"venue"
},
  "geometry": {"coordinates":[5.822997,50.900604],"type":"Point"}
}