{
  "type": "Feature",
  "properties": {
    "addr:full":"Dames Jolinkweg 2 Varsseveld Gelderland 7051 DK",
    "addr:housenumber":"2",
    "addr:postcode":"7051 dk",
    "addr:street":"Dames Jolinkweg;Gelderland",
    "iso:country":"NL",
    "sg:address":"Dames Jolinkweg 2",
    "sg:city":"Varsseveld",
    "sg:orig_category":"Discountwinkels",
    "sg:phone":"+31 315 230 050",
    "sg:postcode":"7051 DK",
    "sg:province":"Gelderland",
    "wof:name":"Zeeman Textielsupers",
    "wof:placetype":"venue"
},
  "geometry": {"coordinates":[6.463628,51.943169],"type":"Point"}
}