{
  "type": "Feature",
  "properties": {
    "addr:full":"T Edisonwg 10 Drunen Noord-Brabant 5151 DJ",
    "addr:housenumber":"10",
    "addr:postcode":"5151 dj",
    "iso:country":"NL",
    "sg:address":"T Edisonwg 10",
    "sg:city":"Drunen",
    "sg:classifiers":[
        {
            "category":"Wholesale",
            "subcategory":"Meat",
            "type":"Manufacturing & Wholesale Goods"
        }
    ],
    "sg:phone":"+31 416 373 176",
    "sg:postcode":"5151 DJ",
    "sg:province":"Noord-Brabant",
    "sg:tags":[
        "regeltechniek",
        "en",
        "meet-"
    ],
    "sg:website":"http://www.spminstrument.nl",
    "wof:name":"Spm Bv",
    "wof:placetype":"venue"
},
  "geometry": {"coordinates":[5.158782,51.695152],"type":"Point"}
}