{
  "type": "Feature",
  "properties": {
    "addr:full":"Industriepk 8 Zelhem Gelderland 7021 BL",
    "addr:housenumber":"8",
    "addr:postcode":"7021 bl",
    "addr:street":"Industriepk;Gelderland",
    "iso:country":"NL",
    "sg:address":"Industriepk 8",
    "sg:city":"Zelhem",
    "sg:orig_category":"Metaalbewerking",
    "sg:phone":"+31 314 623 701",
    "sg:postcode":"7021 BL",
    "sg:province":"Gelderland",
    "sg:website":"http://www.transil.com",
    "wof:name":"Transil Bv",
    "wof:placetype":"venue"
},
  "geometry": {"coordinates":[6.348084,52.000874],"type":"Point"}
}