{
  "type": "Feature",
  "properties": {
    "iso:country":"NL",
    "sg:address":"G Doupln 17",
    "sg:city":"Amsterdam",
    "sg:orig_category":"Metselwerken",
    "sg:phone":"+31 20 673 5461",
    "sg:postcode":"1073 XE",
    "sg:province":"Noord-Holland",
    "wof:name":"Luiken",
    "wof:placetype":"venue"
},
  "geometry": {"coordinates":[4.89317,52.35611],"type":"Point"}
}