{
  "type": "Feature",
  "properties": {
    "addr:full":"De Mors 69 Oud Ootmarsum Overijssel 7637 PD",
    "addr:housenumber":"69",
    "addr:postcode":"7637 pd",
    "addr:street":"De Mors",
    "iso:country":"NL",
    "sg:address":"De Mors 69",
    "sg:city":"Oud Ootmarsum",
    "sg:orig_category":"Hoefdierhouderijen",
    "sg:phone":"+31 541 221 416",
    "sg:postcode":"7637 PD",
    "sg:province":"Overijssel",
    "wof:name":"Stal De Wiemselbach Bv",
    "wof:placetype":"venue"
},
  "geometry": {"coordinates":[6.928159,52.408173],"type":"Point"}
}