{
  "type": "Feature",
  "properties": {
    "addr:full":"Soldatendijkje 6 Leeuwarden Provincie Friesland 8924 JM",
    "addr:housenumber":"6",
    "addr:postcode":"8924 jm",
    "addr:street":"Soldatendijkje;Provincie Friesland",
    "iso:country":"NL",
    "sg:address":"Soldatendijkje 6",
    "sg:city":"Leeuwarden",
    "sg:orig_category":"Fitnesscentra",
    "sg:phone":"+31 58 267 3256",
    "sg:postcode":"8924 JM",
    "sg:province":"Provincie Friesland",
    "wof:name":"De Sport Citadel",
    "wof:placetype":"venue"
},
  "geometry": {"coordinates":[5.828761,53.209946],"type":"Point"}
}