{
  "type": "Feature",
  "properties": {
    "addr:full":"Houtwijk 99 Dronten NL. 8251 GD",
    "addr:housenumber":"99",
    "addr:postcode":"8251 gd",
    "addr:street":"Houtwijk;Nl.",
    "iso:country":"NL",
    "sg:address":"Houtwijk 99",
    "sg:city":"Dronten",
    "sg:orig_category":"Metaalbekleding And -Behandeling",
    "sg:phone":"+31 321 315 586",
    "sg:postcode":"8251 GD",
    "sg:province":"NL.",
    "wof:name":"Werucon Technische Industrie",
    "wof:placetype":"venue"
},
  "geometry": {"coordinates":[5.731143,52.53513],"type":"Point"}
}