{
  "type": "Feature",
  "properties": {
    "iso:country":"NL",
    "sg:address":"Archipel 1549",
    "sg:city":"Lelystad",
    "sg:orig_category":"Woninginrichting",
    "sg:phone":"+31 320 220 004",
    "sg:postcode":"8224 GD",
    "sg:province":"NL.",
    "wof:name":"Denidosa",
    "wof:placetype":"venue"
},
  "geometry": {"coordinates":[5.48498106,52.5090560913],"type":"Point"}
}