{
  "type": "Feature",
  "properties": {
    "addr:full":"Willem De Zwijgerlaan 92 Castricum Noord-Holland 1901 CT",
    "addr:housenumber":"92",
    "addr:postcode":"1901 ct",
    "addr:street":"Willem De Zwijgerlaan",
    "iso:country":"NL",
    "sg:address":"Willem De Zwijgerlaan 92",
    "sg:city":"Castricum",
    "sg:orig_category":"Paramedische Behandelingen",
    "sg:phone":"+31 251 656 141",
    "sg:postcode":"1901 CT",
    "sg:province":"Noord-Holland",
    "wof:name":"Logopedie Praktijk R. Kuipers En A. Nuytinck",
    "wof:placetype":"venue"
},
  "geometry": {"coordinates":[4.669605,52.552612],"type":"Point"}
}