{
  "type": "Feature",
  "properties": {
    "addr:full":"Westzijdeweg 31 Hazerswoude Dorp Zuid-Holland 2391 JE",
    "addr:housenumber":"31",
    "addr:postcode":"2391 je",
    "addr:street":"Westzijdeweg",
    "iso:country":"NL",
    "sg:address":"Westzijdeweg 31",
    "sg:city":"Hazerswoude Dorp",
    "sg:orig_category":"Diverse Dierenfokkers",
    "sg:phone":"+31 172 589 874",
    "sg:postcode":"2391 JE",
    "sg:province":"Zuid-Holland",
    "wof:name":"J. Karens Bv",
    "wof:placetype":"venue"
},
  "geometry": {"coordinates":[4.556314,52.091648],"type":"Point"}
}