{
  "type": "Feature",
  "properties": {
    "addr:full":"Gouwe 5 Barendrecht South Holland 2991 CJ",
    "addr:housenumber":"5",
    "addr:postcode":"2991 cj",
    "addr:street":"Gouwe",
    "iso:country":"NL",
    "sg:address":"Gouwe 5",
    "sg:city":"Barendrecht",
    "sg:orig_category":"Public Relationbureaus",
    "sg:phone":"+31 180 613 266",
    "sg:postcode":"2991 CJ",
    "sg:province":"South Holland",
    "wof:name":"Reklame Adviesburo Maan Bv",
    "wof:placetype":"venue"
},
  "geometry": {"coordinates":[4.548783,51.852413],"type":"Point"}
}