{
  "type": "Feature",
  "properties": {
    "addr:full":"T Dorp 37 Heesch Noord-Brabant 5384 MB",
    "addr:housenumber":"37",
    "addr:postcode":"5384 mb",
    "addr:street":"T Dorp",
    "iso:country":"NL",
    "sg:address":"T Dorp 37",
    "sg:city":"Heesch",
    "sg:orig_category":"Artsen - Huisartsen",
    "sg:phone":"+31 412 451 355",
    "sg:postcode":"5384 MB",
    "sg:province":"Noord-Brabant",
    "wof:name":"Cruchten, L H H Van",
    "wof:placetype":"venue"
},
  "geometry": {"coordinates":[5.52997,51.735504],"type":"Point"}
}