{
  "type": "Feature",
  "properties": {
    "addr:full":"Kottenseweg 85 Winterswijk Gelderland 7101 JS",
    "addr:housenumber":"85",
    "addr:postcode":"7101 js",
    "addr:street":"Kottenseweg;Gelderland",
    "iso:country":"NL",
    "sg:address":"Kottenseweg 85",
    "sg:city":"Winterswijk",
    "sg:orig_category":"Geluidsopnamen",
    "sg:phone":"+31 543 522 022",
    "sg:postcode":"7101 JS",
    "sg:province":"Gelderland",
    "wof:name":"Beverly Beat Productions",
    "wof:placetype":"venue"
},
  "geometry": {"coordinates":[6.73508,51.96093],"type":"Point"}
}