{
  "type": "Feature",
  "properties": {
    "iso:country":"NL",
    "sg:address":"Rynstr 12",
    "sg:city":"Amsterdam",
    "sg:orig_category":"Geluidsbanden - Fabrieken En Groothandel",
    "sg:phone":"+31 20 673 0067",
    "sg:postcode":"1078 RA",
    "sg:province":"Noord-Holland",
    "wof:name":"Tapes Amsterdam Bv",
    "wof:placetype":"venue"
},
  "geometry": {"coordinates":[4.89178,52.34341],"type":"Point"}
}