{
  "type": "Feature",
  "properties": {
    "addr:full":"Hoogstr 20 Mill Noord-Brabant 5451 BJ",
    "addr:housenumber":"20",
    "addr:postcode":"5451 bj",
    "addr:street":"Hoogstr",
    "iso:country":"NL",
    "sg:address":"Hoogstr 20",
    "sg:city":"Mill",
    "sg:orig_category":"Orthopedische Artikelen",
    "sg:phone":"+31 413 250 181",
    "sg:postcode":"5451 BJ",
    "sg:province":"Noord-Brabant",
    "wof:name":"Medibanda",
    "wof:placetype":"venue"
},
  "geometry": {"coordinates":[-106.3908538818,42.8552055359],"type":"Point"}
}