{
  "type": "Feature",
  "properties": {
    "iso:country":"NL",
    "sg:address":"Handvastwater 40",
    "sg:city":"Enkhuizen",
    "sg:orig_category":"Jachthavens - Jachtwerven",
    "sg:phone":"+31 228 318 953",
    "sg:postcode":"1601 PR",
    "sg:province":"Noord-Holland",
    "wof:name":"Gemini",
    "wof:placetype":"venue"
},
  "geometry": {"coordinates":[5.284296,52.707165],"type":"Point"}
}