{
  "type": "Feature",
  "properties": {
    "addr:full":"Klavecimbelwg 2 Barendrecht Zuid-Holland 2992 NE",
    "addr:housenumber":"2",
    "addr:postcode":"2992 ne",
    "addr:street":"Klavecimbelwg",
    "iso:country":"NL",
    "sg:address":"Klavecimbelwg 2",
    "sg:city":"Barendrecht",
    "sg:orig_category":"Autoschade- Herstelbedrijven",
    "sg:phone":"+31 180 627 598",
    "sg:postcode":"2992 NE",
    "sg:province":"Zuid-Holland",
    "wof:name":"Auto-Care",
    "wof:placetype":"venue"
},
  "geometry": {"coordinates":[4.523921,51.854931],"type":"Point"}
}