{
  "type": "Feature",
  "properties": {
    "addr:full":"De Hofstede 49 Lienden Gelderland 4033 BV",
    "addr:housenumber":"49",
    "addr:postcode":"4033 bv",
    "addr:street":"De Hofstede;Gelderland",
    "iso:country":"NL",
    "sg:address":"De Hofstede 49",
    "sg:city":"Lienden",
    "sg:orig_category":"Fotoreportages",
    "sg:phone":"+31 344 602 961",
    "sg:postcode":"4033 BV",
    "sg:province":"Gelderland",
    "wof:name":"Design & Zo",
    "wof:placetype":"venue"
},
  "geometry": {"coordinates":[5.522044,51.938442],"type":"Point"}
}