{
  "type": "Feature",
  "properties": {
    "addr:full":"Industriestr 24 Delft Zuid-Holland 2624 BB",
    "addr:housenumber":"24",
    "addr:postcode":"2624 bb",
    "addr:street":"Industriestr",
    "iso:country":"NL",
    "sg:address":"Industriestr 24",
    "sg:city":"Delft",
    "sg:orig_category":"Fotoapparatuur En -Artikelen - Groothandel",
    "sg:phone":"+31 15 285 5338",
    "sg:postcode":"2624 BB",
    "sg:province":"Zuid-Holland",
    "wof:name":"Driessen Trading, F J",
    "wof:placetype":"venue"
},
  "geometry": {"coordinates":[4.355746,52.001308],"type":"Point"}
}