{
  "type": "Feature",
  "properties": {
    "addr:full":"Burg. Van Leentstraat 66 Grubbenvorst Limburg 5971 AJ",
    "addr:housenumber":"66",
    "addr:postcode":"5971 aj",
    "addr:street":"Burg. Van Leentstraat",
    "iso:country":"NL",
    "sg:address":"Burg. Van Leentstraat 66",
    "sg:city":"Grubbenvorst",
    "sg:orig_category":"Koeriersdiensten",
    "sg:phone":"+31 77 366 2274",
    "sg:postcode":"5971 AJ",
    "sg:province":"Limburg",
    "wof:name":"Quick Drive Service",
    "wof:placetype":"venue"
},
  "geometry": {"coordinates":[6.1394,51.421124],"type":"Point"}
}