{
  "type": "Feature",
  "properties": {
    "addr:full":"Loopkantstr 14A Uden North Brabant 5405 NB",
    "addr:housenumber":"14a",
    "addr:postcode":"5405 nb",
    "addr:street":"Loopkantstr",
    "iso:country":"NL",
    "sg:address":"Loopkantstr 14A",
    "sg:city":"Uden",
    "sg:orig_category":"Parketvloeren",
    "sg:phone":"+31 413 257 570",
    "sg:postcode":"5405 NB",
    "sg:province":"North Brabant",
    "sg:website":"http://www.doevloer.nl",
    "wof:name":"Doevloer Bv",
    "wof:placetype":"venue"
},
  "geometry": {"coordinates":[5.633695,51.657066],"type":"Point"}
}