{
  "type": "Feature",
  "properties": {
    "addr:full":"Lagedk 4 Helmond Noord-Brabant 5705 BZ",
    "addr:housenumber":"4",
    "addr:postcode":"5705 bz",
    "addr:street":"Lagedk",
    "iso:country":"NL",
    "sg:address":"Lagedk 4",
    "sg:city":"Helmond",
    "sg:orig_category":"Sanitaire Artikelen",
    "sg:phone":"+31 492 523 989",
    "sg:postcode":"5705 BZ",
    "sg:province":"Noord-Brabant",
    "wof:name":"Nederlands Badkamer Centrum",
    "wof:placetype":"venue"
},
  "geometry": {"coordinates":[5.678633,51.470711],"type":"Point"}
}