{
  "type": "Feature",
  "properties": {
    "addr:full":"Johannes Vermeerstraat 53 Amsterdam Noord-Holland 1071 DM",
    "addr:housenumber":"53",
    "addr:postcode":"1071 dm",
    "addr:street":"Johannes Vermeerstraat",
    "iso:country":"NL",
    "sg:address":"Johannes Vermeerstraat 53",
    "sg:city":"Amsterdam",
    "sg:orig_category":"Adviesbureaus Bedrijfsorganisatie",
    "sg:phone":"+31 20 662 8354",
    "sg:postcode":"1071 DM",
    "sg:province":"Noord-Holland",
    "wof:name":"Ka Bv",
    "wof:placetype":"venue"
},
  "geometry": {"coordinates":[4.884223,52.355949],"type":"Point"}
}