{
  "type": "Feature",
  "properties": {
    "addr:full":"Ln C V Cattenb 127 S Gravenhage South Holland 2585 EZ",
    "addr:housenumber":"127",
    "addr:postcode":"2585 ez",
    "addr:street":"Ln C;Cattenb;S Gravenhage",
    "iso:country":"NL",
    "sg:address":"Ln C V Cattenb 127",
    "sg:city":"S Gravenhage",
    "sg:orig_category":"Makelaars En Adviseurs Onroerende Goederen",
    "sg:phone":"+31 70 360 0913",
    "sg:postcode":"2585 EZ",
    "sg:province":"South Holland",
    "sg:website":"http://www.vanderhorst-makelaardij.nl",
    "wof:name":"Horst Makelaardij Bv, Van Der",
    "wof:placetype":"venue"
},
  "geometry": {"coordinates":[4.29777,52.094799],"type":"Point"}
}