{
  "type": "Feature",
  "properties": {
    "addr:full":"Resedastr 20 Breda Noord-Brabant 4818 GR",
    "addr:housenumber":"20",
    "addr:postcode":"4818",
    "addr:street":"Resedastr",
    "iso:country":"NL",
    "sg:address":"Resedastr 20",
    "sg:city":"Breda",
    "sg:orig_category":"Tekstschrijversters",
    "sg:phone":"+31 76 520 0744",
    "sg:postcode":"4818 GR",
    "sg:province":"Noord-Brabant",
    "wof:name":"Tekst & Taal",
    "wof:placetype":"venue"
},
  "geometry": {"coordinates":[4.785035,51.579742],"type":"Point"}
}