{
  "type": "Feature",
  "properties": {
    "addr:full":"Boterbloem 27 Purmerend North Holland 1441 TT",
    "addr:housenumber":"27",
    "addr:postcode":"1441 tt",
    "addr:street":"Boterbloem",
    "iso:country":"NL",
    "sg:address":"Boterbloem 27",
    "sg:city":"Purmerend",
    "sg:orig_category":"Beleggingen",
    "sg:phone":"+31 299 432 073",
    "sg:postcode":"1441 TT",
    "sg:province":"North Holland",
    "wof:name":"Muurvast Bv",
    "wof:placetype":"venue"
},
  "geometry": {"coordinates":[4.950278,52.494118],"type":"Point"}
}