{
  "type": "Feature",
  "properties": {
    "iso:country":"NL",
    "sg:address":"Amberboomstr 38",
    "sg:city":"Terneuzen",
    "sg:orig_category":"Werving En Selectie",
    "sg:phone":"+31 115 697 513",
    "sg:postcode":"4537 XA",
    "sg:province":"Zeeland",
    "sg:website":"http://www.jobdean.nl",
    "wof:name":"Global Inter//Face",
    "wof:placetype":"venue"
},
  "geometry": {"coordinates":[3.8328430653,51.3258895874],"type":"Point"}
}