{
  "type": "Feature",
  "properties": {
    "addr:full":"Dorpsstr 65 Geesteren Ov NL.08 7678 AV",
    "addr:housenumber":"65;7678",
    "addr:street":"Dorpsstr;Ov;Av",
    "iso:country":"NL",
    "sg:address":"Dorpsstr 65",
    "sg:city":"Geesteren Ov",
    "sg:orig_category":"Schoenen",
    "sg:phone":"+31 546 631 292",
    "sg:postcode":"7678 AV",
    "sg:province":"NL.08",
    "wof:name":"Hamer Casual, Sportschoenen",
    "wof:placetype":"venue"
},
  "geometry": {"coordinates":[6.734953,52.4203],"type":"Point"}
}