{
  "type": "Feature",
  "properties": {
    "addr:full":"Brederode 21 Landsmeer Noord-Holland 1121 CX",
    "addr:housenumber":"21",
    "addr:postcode":"1121 cx",
    "addr:street":"Brederode",
    "iso:country":"NL",
    "sg:address":"Brederode 21",
    "sg:city":"Landsmeer",
    "sg:orig_category":"Diverse Grafische Activiteiten",
    "sg:phone":"+31 20 482 1001",
    "sg:postcode":"1121 CX",
    "sg:province":"Noord-Holland",
    "wof:name":"M. Meijer Art-Designstudio",
    "wof:placetype":"venue"
},
  "geometry": {"coordinates":[4.914755,52.426586],"type":"Point"}
}