{
  "type": "Feature",
  "properties": {
    "addr:full":"C V Rennesln 7 Bussum Noord-Holland 1403 EP",
    "addr:housenumber":"7",
    "addr:postcode":"1403 ep",
    "addr:street":"V Rennesln",
    "iso:country":"NL",
    "sg:address":"C V Rennesln 7",
    "sg:city":"Bussum",
    "sg:orig_category":"Kappers",
    "sg:phone":"+31 35 691 5987",
    "sg:postcode":"1403 EP",
    "sg:province":"Noord-Holland",
    "wof:name":"Beck, Ineke",
    "wof:placetype":"venue"
},
  "geometry": {"coordinates":[5.1626048088,52.2768287659],"type":"Point"}
}