{
  "type": "Feature",
  "properties": {
    "addr:full":"Julianastraat 54 Zuidland Zuid-Holland 3214 CJ",
    "addr:housenumber":"54",
    "addr:postcode":"3214 cj",
    "addr:street":"Julianastraat",
    "iso:country":"NL",
    "sg:address":"Julianastraat 54",
    "sg:city":"Zuidland",
    "sg:classifiers":[
        {
            "category":"Education",
            "subcategory":"Preschool",
            "type":"Public Place"
        }
    ],
    "sg:phone":"+31 181 459 256",
    "sg:postcode":"3214 CJ",
    "sg:province":"Zuid-Holland",
    "sg:tags":[
        "kleuteronderwijs",
        "basis-"
    ],
    "wof:name":"De Bongerd",
    "wof:placetype":"venue"
},
  "geometry": {"coordinates":[4.254535,51.823563],"type":"Point"}
}