{
  "type": "Feature",
  "properties": {
    "iso:country":"NL",
    "sg:address":"Heidelbergln 100",
    "sg:city":"Utrecht",
    "sg:orig_category":"Fietsen En Bromfietsen",
    "sg:phone":"+31 30 252 0231",
    "sg:postcode":"3584 CX",
    "sg:province":"Utrecht",
    "wof:name":"Bike In",
    "wof:placetype":"venue"
},
  "geometry": {"coordinates":[5.17536,52.084888],"type":"Point"}
}