{
  "type": "Feature",
  "properties": {
    "iso:country":"NL",
    "sg:address":"Keizerstr 58",
    "sg:city":"Yzendoorn",
    "sg:orig_category":"Loopbaanbegeleiding",
    "sg:phone":"+31 344 643 294",
    "sg:postcode":"4053 HK",
    "sg:province":"Gelderland",
    "wof:name":"L4Balance",
    "wof:placetype":"venue"
},
  "geometry": {"coordinates":[5.535515,51.907501],"type":"Point"}
}