{
  "type": "Feature",
  "properties": {
    "addr:full":"Hoogstr 157 Rotterdam South Holland 3011 PM",
    "addr:housenumber":"157",
    "addr:postcode":"3011 pm",
    "iso:country":"NL",
    "sg:address":"Hoogstr 157",
    "sg:city":"Rotterdam",
    "sg:orig_category":"Opticiens",
    "sg:phone":"+31 10 233 0869",
    "sg:postcode":"3011 PM",
    "sg:province":"South Holland",
    "sg:website":"http://www.hansanders.nl",
    "wof:name":"Hans Anders",
    "wof:placetype":"venue"
},
  "geometry": {"coordinates":[4.4859981537,51.921043396],"type":"Point"}
}