{
  "type": "Feature",
  "properties": {
    "addr:full":"Elandweg 51 Swifterbant Flevoland 8255 RH",
    "addr:housenumber":"51",
    "addr:postcode":"8255 rh",
    "addr:street":"Elandweg;Flevoland",
    "iso:country":"NL",
    "sg:address":"Elandweg 51",
    "sg:city":"Swifterbant",
    "sg:orig_category":"Bloemen And Planten",
    "sg:phone":"+31 321 321 293",
    "sg:postcode":"8255 RH",
    "sg:province":"Flevoland",
    "wof:name":"De Bloemenhoeve",
    "wof:placetype":"venue"
},
  "geometry": {"coordinates":[5.64805,52.543201],"type":"Point"}
}