{
  "type": "Feature",
  "properties": {
    "addr:full":"Bickersgr 22 Amsterdam North Holland 1013 LE",
    "addr:housenumber":"22",
    "addr:postcode":"1013 le",
    "addr:street":"Bickersgr",
    "iso:country":"NL",
    "sg:address":"Bickersgr 22",
    "sg:city":"Amsterdam",
    "sg:orig_category":"Podotherapeuten",
    "sg:phone":"+31 20 627 4213",
    "sg:postcode":"1013 LE",
    "sg:province":"North Holland",
    "wof:name":"Goslau Podotherapeut, E A",
    "wof:placetype":"venue"
},
  "geometry": {"coordinates":[4.88883,52.384342],"type":"Point"}
}