{
  "type": "Feature",
  "properties": {
    "addr:full":"P Cornelisz Hooftstr 127 Amsterdam Noord-Holland 1071 BS",
    "addr:housenumber":"127",
    "addr:postcode":"1071 bs",
    "addr:street":"P Cornelisz Hooftstr",
    "iso:country":"NL",
    "sg:address":"P Cornelisz Hooftstr 127",
    "sg:city":"Amsterdam",
    "sg:orig_category":"Advocaten And Juridische Adviseurs",
    "sg:phone":"+31 20 572 2727",
    "sg:postcode":"1071 BS",
    "sg:province":"Noord-Holland",
    "wof:name":"Advocatenkantoor Mr. Carolien A. Herweijer",
    "wof:placetype":"venue"
},
  "geometry": {"coordinates":[4.878084,52.359409],"type":"Point"}
}