{
  "type": "Feature",
  "properties": {
    "addr:full":"Cannerweg 26 Maastricht Limburg 6213 BG",
    "addr:housenumber":"26",
    "addr:postcode":"6213",
    "addr:street":"Cannerweg",
    "iso:country":"NL",
    "sg:address":"Cannerweg 26",
    "sg:city":"Maastricht",
    "sg:classifiers":[
        {
            "category":"Fast Food",
            "type":"Food & Drink"
        }
    ],
    "sg:phone":"+31 43 325 8956",
    "sg:postcode":"6213 BG",
    "sg:province":"Limburg",
    "sg:tags":[
        "afhaal",
        "restaurant"
    ],
    "wof:name":"M.A.J. Karssing-Lion",
    "wof:placetype":"venue"
},
  "geometry": {"coordinates":[5.679092,50.843071],"type":"Point"}
}