{
  "type": "Feature",
  "properties": {
    "addr:full":"Dijk 2 Enkhuizen North Holland 1601 GJ",
    "addr:housenumber":"2",
    "addr:postcode":"1601 gj",
    "addr:street":"Dijk",
    "iso:country":"NL",
    "sg:address":"Dijk 2",
    "sg:city":"Enkhuizen",
    "sg:orig_category":"Boekhouders",
    "sg:phone":"+31 228 322 722",
    "sg:postcode":"1601 GJ",
    "sg:province":"North Holland",
    "wof:name":"Administratie- En Ass Kantoor Westendorp",
    "wof:placetype":"venue"
},
  "geometry": {"coordinates":[5.293107,52.701408],"type":"Point"}
}