{
  "type": "Feature",
  "properties": {
    "addr:full":"Zeilmakerstr 18 Assen Drenthe 9403 VA",
    "addr:housenumber":"18",
    "addr:postcode":"9403",
    "addr:street":"Zeilmakerstr",
    "iso:country":"NL",
    "sg:address":"Zeilmakerstr 18",
    "sg:city":"Assen",
    "sg:orig_category":"Parketvloeren",
    "sg:phone":"+31 592 300 860",
    "sg:postcode":"9403 VA",
    "sg:province":"Drenthe",
    "wof:name":"Meuta",
    "wof:placetype":"venue"
},
  "geometry": {"coordinates":[6.578787,53.010681],"type":"Point"}
}