{
  "type": "Feature",
  "properties": {
    "iso:country":"NL",
    "sg:address":"Joseph Haydnlaan 13",
    "sg:city":"Utrecht",
    "sg:orig_category":"Boekhouders",
    "sg:phone":"+31 30 293 6506",
    "sg:postcode":"3533 AB",
    "sg:province":"Utrecht",
    "wof:name":"Administratiekantoor Kuijpers",
    "wof:placetype":"venue"
},
  "geometry": {"coordinates":[5.085265,52.083675],"type":"Point"}
}