{
  "type": "Feature",
  "properties": {
    "addr:full":"Slagwg 6 Dalfsen Overijssel 7722 TZ",
    "addr:housenumber":"6",
    "addr:postcode":"7722 tz",
    "addr:street":"Slagwg",
    "iso:country":"NL",
    "sg:address":"Slagwg 6",
    "sg:city":"Dalfsen",
    "sg:orig_category":"Waterbehandeling En Waterzuiverings- Systemen",
    "sg:phone":"+31 529 471 111",
    "sg:postcode":"7722 TZ",
    "sg:province":"Overijssel",
    "wof:name":"Leliveld",
    "wof:placetype":"venue"
},
  "geometry": {"coordinates":[6.295331955,52.5407142639],"type":"Point"}
}