{
  "type": "Feature",
  "properties": {
    "addr:full":"Gedempte Nieuwesloot 129 Alkmaar Noord-Holland 1811 KR",
    "addr:housenumber":"129",
    "addr:postcode":"1811 kr",
    "addr:street":"Gedempte Nieuwesloot",
    "iso:country":"NL",
    "sg:address":"Gedempte Nieuwesloot 129",
    "sg:city":"Alkmaar",
    "sg:orig_category":"Kappers",
    "sg:phone":"+31 72 511 9100",
    "sg:postcode":"1811 KR",
    "sg:province":"Noord-Holland",
    "wof:name":"Gladys Hair Styling",
    "wof:placetype":"venue"
},
  "geometry": {"coordinates":[4.7463841438,52.6324958801],"type":"Point"}
}