{
  "type": "Feature",
  "properties": {
    "addr:full":"Groenhof 149 Amstelveen Noord-Holland 1186 EZ",
    "addr:housenumber":"149",
    "addr:postcode":"1186 ez",
    "addr:street":"Groenhof",
    "iso:country":"NL",
    "sg:address":"Groenhof 149",
    "sg:city":"Amstelveen",
    "sg:orig_category":"Kappers",
    "sg:phone":"+31 20 645 7676",
    "sg:postcode":"1186 EZ",
    "sg:province":"Noord-Holland",
    "wof:name":"Nexxus",
    "wof:placetype":"venue"
},
  "geometry": {"coordinates":[4.870339,52.289368],"type":"Point"}
}