{
  "type": "Feature",
  "properties": {
    "addr:full":"Frans Fennishof 33 Ankeveen North Holland 1244 RK",
    "addr:housenumber":"33",
    "addr:postcode":"1244 rk",
    "addr:street":"Frans Fennishof",
    "iso:country":"NL",
    "sg:address":"Frans Fennishof 33",
    "sg:city":"Ankeveen",
    "sg:orig_category":"Boekhouders",
    "sg:phone":"+31 35 656 5433",
    "sg:postcode":"1244 RK",
    "sg:province":"North Holland",
    "wof:name":"Bemat",
    "wof:placetype":"venue"
},
  "geometry": {"coordinates":[5.095859,52.260757],"type":"Point"}
}