{
  "type": "Feature",
  "properties": {
    "addr:full":"Vlasakker 26 Schoonebeek Provincie Drenthe 7761 RC",
    "addr:housenumber":"26",
    "addr:postcode":"7761 rc",
    "addr:street":"Vlasakker;Provincie Drenthe",
    "iso:country":"NL",
    "sg:address":"Vlasakker 26",
    "sg:city":"Schoonebeek",
    "sg:orig_category":"Koeriersdiensten",
    "sg:phone":"+31 524 532 863",
    "sg:postcode":"7761 RC",
    "sg:province":"Provincie Drenthe",
    "wof:name":"Hartman Sneltransport",
    "wof:placetype":"venue"
},
  "geometry": {"coordinates":[6.872055,52.686234],"type":"Point"}
}