{
  "type": "Feature",
  "properties": {
    "addr:full":"Troelstrawg 44 Dordrecht South Holland 3317 TJ",
    "addr:housenumber":"44",
    "addr:postcode":"3317 tj",
    "addr:street":"Troelstrawg",
    "iso:country":"NL",
    "sg:address":"Troelstrawg 44",
    "sg:city":"Dordrecht",
    "sg:orig_category":"Woningstoffeerders",
    "sg:phone":"+31 78 617 1456",
    "sg:postcode":"3317 TJ",
    "sg:province":"South Holland",
    "wof:name":"Bos, Woningstoffeerders",
    "wof:placetype":"venue"
},
  "geometry": {"coordinates":[4.6565060616,51.8119163513],"type":"Point"}
}