{
  "type": "Feature",
  "properties": {
    "addr:full":"Orlandopassage 8 Kerkrade Limburg 6461 AM",
    "addr:housenumber":"8",
    "addr:postcode":"6461",
    "addr:street":"Orlandopassage",
    "iso:country":"NL",
    "sg:address":"Orlandopassage 8",
    "sg:city":"Kerkrade",
    "sg:orig_category":"Opticiens",
    "sg:phone":"+31 45 567 0188",
    "sg:postcode":"6461 AM",
    "sg:province":"Limburg",
    "wof:name":"Pearle",
    "wof:placetype":"venue"
},
  "geometry": {"coordinates":[6.0638852119,50.8656234741],"type":"Point"}
}