{
  "type": "Feature",
  "properties": {
    "addr:full":"Nevenakker 17 Oirschot Noord-Brabant 5688 PK",
    "addr:housenumber":"17",
    "addr:postcode":"5688 pk",
    "addr:street":"Nevenakker",
    "iso:country":"NL",
    "sg:address":"Nevenakker 17",
    "sg:city":"Oirschot",
    "sg:orig_category":"Adviesbureaus Bouwkunde",
    "sg:phone":"+31 499 572 453",
    "sg:postcode":"5688 PK",
    "sg:province":"Noord-Brabant",
    "wof:name":"Buul, Van",
    "wof:placetype":"venue"
},
  "geometry": {"coordinates":[5.316383,51.512791],"type":"Point"}
}