{
  "type": "Feature",
  "properties": {
    "addr:full":"Nes 142 Wervershoof North Holland 1693 CK",
    "addr:housenumber":"142",
    "addr:postcode":"1693 ck",
    "addr:street":"Nes",
    "iso:country":"NL",
    "sg:address":"Nes 142",
    "sg:city":"Wervershoof",
    "sg:orig_category":"Goederenvervoer Over De Weg",
    "sg:phone":"+31 228 581 206",
    "sg:postcode":"1693 CK",
    "sg:province":"North Holland",
    "wof:name":"Transportbedrijf P.J. Grent En Zn Vof",
    "wof:placetype":"venue"
},
  "geometry": {"coordinates":[5.142885,52.739826],"type":"Point"}
}