{
  "type": "Feature",
  "properties": {
    "addr:full":"Bertus Van Grouwstraat 7 Amsterdam Noord-Holland 1063 AS",
    "addr:housenumber":"7",
    "addr:postcode":"1063 as",
    "addr:street":"Bertus Van Grouwstraat",
    "iso:country":"NL",
    "sg:address":"Bertus Van Grouwstraat 7",
    "sg:city":"Amsterdam",
    "sg:orig_category":"Schilders",
    "sg:phone":"+31 20 613 5786",
    "sg:postcode":"1063 AS",
    "sg:province":"Noord-Holland",
    "wof:name":"Krijger, E",
    "wof:placetype":"venue"
},
  "geometry": {"coordinates":[4.837242,52.382767],"type":"Point"}
}