{
  "type": "Feature",
  "properties": {
    "iso:country":"NL",
    "sg:address":"De Kempenstr 1",
    "sg:city":"Alkmaar",
    "sg:orig_category":"Autorijscholen",
    "sg:phone":"+31 72 561 5836",
    "sg:postcode":"1827 AG",
    "sg:province":"North Holland",
    "wof:name":"Bruschke, Tine",
    "wof:placetype":"venue"
},
  "geometry": {"coordinates":[4.759408,52.669109],"type":"Point"}
}