{
  "type": "Feature",
  "properties": {
    "addr:full":"Schaaksport 100-102 Groningen Groningen 9728 PG",
    "addr:housenumber":"100-102",
    "addr:postcode":"9728 pg",
    "addr:street":"Schaaksport",
    "iso:country":"NL",
    "sg:address":"Schaaksport 100-102",
    "sg:city":"Groningen",
    "sg:orig_category":"Ziekenhuizen, Sanatoria, Verpleeghuizen",
    "sg:phone":"+31 50 522 4400",
    "sg:postcode":"9728 PG",
    "sg:province":"Groningen",
    "wof:name":"Maartenshof",
    "wof:placetype":"venue"
},
  "geometry": {"coordinates":[6.560388,53.19194],"type":"Point"}
}