{
  "type": "Feature",
  "properties": {
    "addr:full":"Bentinckplein 45 Rotterdam South Holland 3039 KM",
    "addr:housenumber":"45",
    "addr:postcode":"3039 km",
    "addr:street":"Bentinckplein",
    "iso:country":"NL",
    "sg:address":"Bentinckplein 45",
    "sg:city":"Rotterdam",
    "sg:orig_category":"Drogisterijen",
    "sg:phone":"+31 10 466 4770",
    "sg:postcode":"3039 KM",
    "sg:province":"South Holland",
    "wof:name":"Farma Drogisterijen Bv",
    "wof:placetype":"venue"
},
  "geometry": {"coordinates":[4.461584,51.9272],"type":"Point"}
}