{
  "type": "Feature",
  "properties": {
    "addr:full":"Dynamostr 5 S Gravenhage South Holland 2525 KB",
    "addr:housenumber":"5",
    "addr:postcode":"2525 kb",
    "addr:street":"Dynamostr;S Gravenhage",
    "iso:country":"NL",
    "sg:address":"Dynamostr 5",
    "sg:city":"S Gravenhage",
    "sg:orig_category":"Verf En Lak - Fabrieken En Groothandel",
    "sg:phone":"+31 70 380 9411",
    "sg:postcode":"2525 KB",
    "sg:province":"South Holland",
    "wof:name":"Molenaar Bv, P C",
    "wof:placetype":"venue"
},
  "geometry": {"coordinates":[4.30248,52.062462],"type":"Point"}
}