{
  "type": "Feature",
  "properties": {
    "addr:full":"G Boelensstr 114 Drachten Provincie Friesland 9203 RS",
    "addr:housenumber":"114",
    "addr:postcode":"9203 rs",
    "addr:street":"Provincie Friesland",
    "iso:country":"NL",
    "sg:address":"G Boelensstr 114",
    "sg:city":"Drachten",
    "sg:orig_category":"Metaaldraaierijen",
    "sg:phone":"+31 512 532 297",
    "sg:postcode":"9203 RS",
    "sg:province":"Provincie Friesland",
    "wof:name":"Krist, A",
    "wof:placetype":"venue"
},
  "geometry": {"coordinates":[6.083637,53.103153],"type":"Point"}
}