{
  "type": "Feature",
  "properties": {
    "addr:full":"P W Janssenlaan 14 Vledderveen Dr Drenthe 8385 GB",
    "addr:housenumber":"14",
    "addr:postcode":"8385 gb",
    "addr:street":"P W Janssenlaan;Vledderveen Dr",
    "iso:country":"NL",
    "sg:address":"P W Janssenlaan 14",
    "sg:city":"Vledderveen Dr",
    "sg:orig_category":"Meubelreparatie And -Restauratie",
    "sg:phone":"+31 521 381 924",
    "sg:postcode":"8385 GB",
    "sg:province":"Drenthe",
    "wof:name":"Atelier Vrojo",
    "wof:placetype":"venue"
},
  "geometry": {"coordinates":[6.185128,52.875275],"type":"Point"}
}