{
  "type": "Feature",
  "properties": {
    "addr:full":"Maasdijk 36 Ravenstein Noord-Brabant 5371 AA",
    "addr:housenumber":"36",
    "addr:postcode":"5371 aa",
    "addr:street":"Maasdijk",
    "iso:country":"NL",
    "sg:address":"Maasdijk 36",
    "sg:city":"Ravenstein",
    "sg:orig_category":"Biljart- And Snookerzalen",
    "sg:phone":"+31 486 412 748",
    "sg:postcode":"5371 AA",
    "sg:province":"Noord-Brabant",
    "wof:name":"Cafe 'T Pumpke",
    "wof:placetype":"venue"
},
  "geometry": {"coordinates":[5.654587,51.796757],"type":"Point"}
}