{
  "type": "Feature",
  "properties": {
    "iso:country":"NL",
    "sg:address":"1E Sweelinckstr 20",
    "sg:city":"Amsterdam",
    "sg:orig_category":"Kunsthandel",
    "sg:phone":"+31 20 625 1565",
    "sg:postcode":"1073 CM",
    "sg:province":"North Holland",
    "wof:name":"Schiffmacher Bv",
    "wof:placetype":"venue"
},
  "geometry": {"coordinates":[4.897533,52.356136],"type":"Point"}
}