{
  "type": "Feature",
  "properties": {
    "iso:country":"NL",
    "sg:address":"Elzenberg 45",
    "sg:city":"Roosendaal",
    "sg:orig_category":"Werving And Selectie Van Tijdelijk Personeel And Uitzendkantoren",
    "sg:phone":"+31 6 21828497",
    "sg:postcode":"4708 EZ",
    "sg:province":"North Brabant",
    "wof:name":"Add",
    "wof:placetype":"venue"
},
  "geometry": {"coordinates":[4.4403190613,51.5146636963],"type":"Point"}
}