{
  "type": "Feature",
  "properties": {
    "iso:country":"NL",
    "sg:address":"Loswal 14",
    "sg:city":"Hardenberg",
    "sg:orig_category":"Lasbedrijven",
    "sg:phone":"+31 523 268 280",
    "sg:postcode":"7772 TT",
    "sg:province":"Overijssel",
    "wof:name":"Menso",
    "wof:placetype":"venue"
},
  "geometry": {"coordinates":[6.633727,52.559772],"type":"Point"}
}