{
  "type": "Feature",
  "properties": {
    "iso:country":"NL",
    "sg:address":"Visstraat 11",
    "sg:city":"'S Hertogenbosch",
    "sg:classifiers":[
        {
            "category":"Shopping",
            "subcategory":"Clothing, Apparel, & Fashions",
            "type":"Retail Goods"
        }
    ],
    "sg:phone":"+31 73 613 4344",
    "sg:postcode":"5211 DM",
    "sg:province":"Noord-Brabant",
    "sg:tags":[
        "ondergoed",
        "lingerie"
    ],
    "wof:name":"Blom Kousen Bv",
    "wof:placetype":"venue"
},
  "geometry": {"coordinates":[5.301125,51.690552],"type":"Point"}
}