{
  "type": "Feature",
  "properties": {
    "addr:full":"C V Bourbonln 2 Eerbeek Gelderland 6961 ER",
    "addr:housenumber":"2",
    "addr:postcode":"6961 er",
    "addr:street":"V Bourbonln;Gelderland",
    "iso:country":"NL",
    "sg:address":"C V Bourbonln 2",
    "sg:city":"Eerbeek",
    "sg:orig_category":"Psychotherapeuten",
    "sg:phone":"+31 313 653 833",
    "sg:postcode":"6961 ER",
    "sg:province":"Gelderland",
    "wof:name":"Stoll, Drs F G",
    "wof:placetype":"venue"
},
  "geometry": {"coordinates":[6.06472,52.10537],"type":"Point"}
}