{
  "type": "Feature",
  "properties": {
    "addr:full":"De Stad 7B Oirschot Noord-Brabant 5688 NX",
    "addr:housenumber":"7b",
    "addr:postcode":"5688 nx",
    "addr:street":"De Stad",
    "iso:country":"NL",
    "sg:address":"De Stad 7B",
    "sg:city":"Oirschot",
    "sg:orig_category":"Drukkerijen",
    "sg:phone":"+31 499 570 345",
    "sg:postcode":"5688 NX",
    "sg:province":"Noord-Brabant",
    "wof:name":"Hensen Bv",
    "wof:placetype":"venue"
},
  "geometry": {"coordinates":[5.332123,51.50296],"type":"Point"}
}