{
  "type": "Feature",
  "properties": {
    "iso:country":"NL",
    "sg:address":"Panovenwg 34",
    "sg:city":"Helmond",
    "sg:orig_category":"Autoruiten",
    "sg:phone":"+31 492 520 873",
    "sg:postcode":"5708 HR",
    "sg:province":"Noord-Brabant",
    "sg:website":"http://www.ster-autoservice.nl",
    "wof:name":"Ster Autoservice Bv",
    "wof:placetype":"venue"
},
  "geometry": {"coordinates":[5.630109,51.474468],"type":"Point"}
}