{
  "type": "Feature",
  "properties": {
    "addr:full":"Nw Marktpassage 19 Gouda Zuid-Holland 2801 HW",
    "addr:housenumber":"19",
    "addr:postcode":"2801 hw",
    "addr:street":"Marktpassage",
    "iso:country":"NL",
    "sg:address":"Nw Marktpassage 19",
    "sg:city":"Gouda",
    "sg:orig_category":"Boeken En Tijdschriften",
    "sg:phone":"+31 182 584 308",
    "sg:postcode":"2801 HW",
    "sg:province":"Zuid-Holland",
    "sg:website":"http://www.bruna.nl",
    "wof:name":"Bruna",
    "wof:placetype":"venue"
},
  "geometry": {"coordinates":[4.711533,52.013809],"type":"Point"}
}