{
  "type": "Feature",
  "properties": {
    "addr:full":"Tuindreef 34 Zoetermeer Zuid-Holland 2724 PT",
    "addr:housenumber":"34",
    "addr:postcode":"2724 pt",
    "addr:street":"Tuindreef",
    "iso:country":"NL",
    "sg:address":"Tuindreef 34",
    "sg:city":"Zoetermeer",
    "sg:orig_category":"Vertalers",
    "sg:phone":"+31 79 341 0378",
    "sg:postcode":"2724 PT",
    "sg:province":"Zuid-Holland",
    "wof:name":"Scherpbier-Hagedoorn, A",
    "wof:placetype":"venue"
},
  "geometry": {"coordinates":[4.514982,52.066425],"type":"Point"}
}