{
  "type": "Feature",
  "properties": {
    "addr:full":"Reinaartln 4 Oudenbosch Noord-Brabant 4731 AH",
    "addr:housenumber":"4",
    "addr:postcode":"4731 ah",
    "addr:street":"Reinaartln",
    "iso:country":"NL",
    "sg:address":"Reinaartln 4",
    "sg:city":"Oudenbosch",
    "sg:orig_category":"Pijpleidingen",
    "sg:phone":"+31 165 314 999",
    "sg:postcode":"4731 AH",
    "sg:province":"Noord-Brabant",
    "wof:name":"Hecotec Bv",
    "wof:placetype":"venue"
},
  "geometry": {"coordinates":[4.52967,51.588776],"type":"Point"}
}