{
  "type": "Feature",
  "properties": {
    "addr:full":"Mastwijkerdijk 15 Montfoort Utrecht 3417 BP",
    "addr:housenumber":"15",
    "addr:postcode":"3417 bp",
    "addr:street":"Mastwijkerdijk",
    "iso:country":"NL",
    "sg:address":"Mastwijkerdijk 15",
    "sg:city":"Montfoort",
    "sg:orig_category":"Boekhouders",
    "sg:phone":"+31 348 471 931",
    "sg:postcode":"3417 BP",
    "sg:province":"Utrecht",
    "wof:name":"Hek Administratie En Fiscaliteiten",
    "wof:placetype":"venue"
},
  "geometry": {"coordinates":[4.954161,52.05373],"type":"Point"}
}