{
  "type": "Feature",
  "properties": {
    "addr:full":"Postbus 108 Gulpen Limburg 6270 AC",
    "addr:housenumber":"108",
    "addr:postcode":"6270 ac",
    "addr:street":"Postbus",
    "iso:country":"NL",
    "sg:address":"Postbus 108",
    "sg:city":"Gulpen",
    "sg:orig_category":"Verenigingen En Stichtingen",
    "sg:phone":"+31 45 544 7161",
    "sg:postcode":"6270 AC",
    "sg:province":"Limburg",
    "wof:name":"Mergelland Corporatie",
    "wof:placetype":"venue"
},
  "geometry": {"coordinates":[5.88998,50.817322],"type":"Point"}
}