{
  "type": "Feature",
  "properties": {
    "iso:country":"NL",
    "sg:address":"Hartkampweg 135",
    "sg:city":"Raalte",
    "sg:classifiers":[
        {
            "category":"Education",
            "subcategory":"Preschool",
            "type":"Public Place"
        }
    ],
    "sg:phone":"+31 572 353 748",
    "sg:postcode":"8101 WC",
    "sg:province":"Overijssel",
    "sg:tags":[
        "kleuteronderwijs",
        "basis-"
    ],
    "wof:name":"Openbare Basisschool Hartkamp",
    "wof:placetype":"venue"
},
  "geometry": {"coordinates":[6.262646,52.378708],"type":"Point"}
}