{
  "type": "Feature",
  "properties": {
    "iso:country":"NL",
    "sg:address":"Hoogakker 2 C",
    "sg:city":"Hapert",
    "sg:classifiers":[
        {
            "category":"Wholesale",
            "subcategory":"Motor Vehicles",
            "type":"Manufacturing & Wholesale Goods"
        }
    ],
    "sg:phone":"+31 497 360 255",
    "sg:postcode":"5527 AE",
    "sg:province":"Noord-Brabant",
    "sg:tags":[
        "scooter",
        "en"
    ],
    "sg:website":"http://www.roefs.nl",
    "wof:name":"Roefs",
    "wof:placetype":"venue"
},
  "geometry": {"coordinates":[5.263047,51.372486],"type":"Point"}
}