{
  "type": "Feature",
  "properties": {
    "addr:full":"Dorpsdk 206 Rhoon South Holland 3161 CH",
    "addr:housenumber":"206",
    "addr:postcode":"3161",
    "iso:country":"NL",
    "sg:address":"Dorpsdk 206",
    "sg:city":"Rhoon",
    "sg:classifiers":[
        {
            "category":"Retail",
            "subcategory":"Auto Repair",
            "type":"Services"
        }
    ],
    "sg:phone":"+31 10 501 4433",
    "sg:postcode":"3161 CH",
    "sg:province":"South Holland",
    "sg:tags":[
        "garage"
    ],
    "wof:name":"Wijngaarden, W C J Van",
    "wof:placetype":"venue"
},
  "geometry": {"coordinates":[4.420872,51.852234],"type":"Point"}
}