{
  "type": "Feature",
  "properties": {
    "addr:full":"Boomwg 4 Landgraaf Limburg 6371 CZ",
    "addr:housenumber":"4",
    "addr:postcode":"6371",
    "addr:street":"Boomwg",
    "iso:country":"NL",
    "sg:address":"Boomwg 4",
    "sg:city":"Landgraaf",
    "sg:classifiers":[
        {
            "category":"Sports & Exercise",
            "subcategory":"Stables",
            "type":"Entertainment"
        }
    ],
    "sg:phone":"+31 45 532 4313",
    "sg:postcode":"6371 CZ",
    "sg:province":"Limburg",
    "sg:tags":[
        "maneges"
    ],
    "wof:name":"Personality",
    "wof:placetype":"venue"
},
  "geometry": {"coordinates":[6.004605,50.906635],"type":"Point"}
}