{
  "type": "Feature",
  "properties": {
    "iso:country":"NL",
    "sg:address":"Everard Meijsterweg 46",
    "sg:city":"Amersfoort",
    "sg:classifiers":[
        {
            "category":"Fast Food",
            "type":"Food & Drink"
        }
    ],
    "sg:phone":"+31 33 465 9001",
    "sg:postcode":"3817 HE",
    "sg:province":"Utrecht",
    "sg:tags":[
        "afhaal",
        "restaurant"
    ],
    "wof:name":"Snackbar Sjors",
    "wof:placetype":"venue"
},
  "geometry": {"coordinates":[5.387891,52.144085],"type":"Point"}
}