{
  "type": "Feature",
  "properties": {
    "iso:country":"NL",
    "sg:address":"President Steynstraat 16",
    "sg:city":"Amsterdam",
    "sg:orig_category":"Onderhoud And Reparatie Kantoorapparatuur",
    "sg:phone":"+31 6 55785117",
    "sg:postcode":"1091 NC",
    "sg:province":"Noord-Holland",
    "wof:name":"Guz",
    "wof:placetype":"venue"
},
  "geometry": {"coordinates":[4.916014,52.351418],"type":"Point"}
}