{
  "type": "Feature",
  "properties": {
    "addr:full":"Lysterstr 19 Bergen Lb Limburg 5854 GR",
    "addr:housenumber":"19",
    "addr:postcode":"lb;5854",
    "addr:street":"Lysterstr",
    "iso:country":"NL",
    "sg:address":"Lysterstr 19",
    "sg:city":"Bergen Lb",
    "sg:orig_category":"Milieu",
    "sg:phone":"+31 485 343 437",
    "sg:postcode":"5854 GR",
    "sg:province":"Limburg",
    "wof:name":"U & M",
    "wof:placetype":"venue"
},
  "geometry": {"coordinates":[-93.129936,36.705662],"type":"Point"}
}