{
  "type": "Feature",
  "properties": {
    "addr:full":"Heldensedijk 9 Meijel Limburg 5768 RK",
    "addr:housenumber":"9",
    "addr:postcode":"5768 rk",
    "addr:street":"Heldensedijk",
    "iso:country":"NL",
    "sg:address":"Heldensedijk 9",
    "sg:city":"Meijel",
    "sg:orig_category":"Huishoudapparatuur, Televisies And Radio'S",
    "sg:phone":"+31 77 466 3178",
    "sg:postcode":"5768 RK",
    "sg:province":"Limburg",
    "wof:name":"Van Heugten Elektro",
    "wof:placetype":"venue"
},
  "geometry": {"coordinates":[5.893938,51.34465],"type":"Point"}
}