{
  "type": "Feature",
  "properties": {
    "addr:full":"Stadhuisplein 2 Gorinchem Zuid-Holland 4205 AX",
    "addr:housenumber":"2",
    "addr:postcode":"4205 ax",
    "addr:street":"Stadhuisplein",
    "iso:country":"NL",
    "sg:address":"Stadhuisplein 2",
    "sg:city":"Gorinchem",
    "sg:orig_category":"Banken And Kredietinstellingen",
    "sg:phone":"+31 183 655 222",
    "sg:postcode":"4205 AX",
    "sg:province":"Zuid-Holland",
    "wof:name":"Ing Bank",
    "wof:placetype":"venue"
},
  "geometry": {"coordinates":[4.965026,51.831936],"type":"Point"}
}