{
  "type": "Feature",
  "properties": {
    "addr:full":"Sevenumsewg 3 Helenaveen Noord-Brabant 5759 RM",
    "addr:housenumber":"3",
    "addr:postcode":"5759 rm",
    "addr:street":"Sevenumsewg",
    "iso:country":"NL",
    "sg:address":"Sevenumsewg 3",
    "sg:city":"Helenaveen",
    "sg:orig_category":"Adviesbureaus Bedrijfsorganisatie",
    "sg:phone":"+31 493 536 081",
    "sg:postcode":"5759 RM",
    "sg:province":"Noord-Brabant",
    "sg:website":"http://www.freshmove.nl",
    "wof:name":"Freshmove Bv",
    "wof:placetype":"venue"
},
  "geometry": {"coordinates":[5.922252,51.389908],"type":"Point"}
}