{
  "type": "Feature",
  "properties": {
    "addr:full":"De Plas 1 Raalte NL.08 8102 CS",
    "addr:housenumber":"1;nl.08",
    "addr:postcode":"8102 cs",
    "addr:street":"De Plas",
    "iso:country":"NL",
    "sg:address":"De Plas 1",
    "sg:city":"Raalte",
    "sg:orig_category":"Verlichting",
    "sg:phone":"+31 572 353 075",
    "sg:postcode":"8102 CS",
    "sg:province":"NL.08",
    "wof:name":"Elskamp",
    "wof:placetype":"venue"
},
  "geometry": {"coordinates":[6.2748541832,52.3856506348],"type":"Point"}
}