{
  "type": "Feature",
  "properties": {
    "iso:country":"NL",
    "sg:address":"De Plas 1",
    "sg:city":"Raalte",
    "sg:orig_category":"Verlichting",
    "sg:phone":"+31 572 353 075",
    "sg:postcode":"8102 CS",
    "sg:province":"NL.08",
    "wof:name":"Elskamp",
    "wof:placetype":"venue"
},
  "geometry": {"coordinates":[6.2748541832,52.3856506348],"type":"Point"}
}