{
  "type": "Feature",
  "properties": {
    "addr:full":"Christiaan Huijgensweg 16 Alphen A/D Rijn Zuid-Holland 2408 AJ",
    "addr:housenumber":"16",
    "addr:postcode":"2408 aj",
    "addr:street":"Christiaan Huijgensweg",
    "iso:country":"NL",
    "sg:address":"Christiaan Huijgensweg 16",
    "sg:city":"Alphen A/D Rijn",
    "sg:orig_category":"Verhuur Bouwmachines",
    "sg:phone":"+31 172 438 839",
    "sg:postcode":"2408 AJ",
    "sg:province":"Zuid-Holland",
    "wof:name":"Awk Verhuur Bv",
    "wof:placetype":"venue"
},
  "geometry": {"coordinates":[4.645408,52.126751],"type":"Point"}
}