{
  "type": "Feature",
  "properties": {
    "addr:full":"Dr Lelykd 12 S Gravenhage Zuid-Holland 2583 CM",
    "addr:housenumber":"12;gravenhage",
    "addr:postcode":"2583 cm",
    "addr:street":"S",
    "iso:country":"NL",
    "sg:address":"Dr Lelykd 12",
    "sg:city":"S Gravenhage",
    "sg:orig_category":"Watersportartikelen",
    "sg:phone":"+31 70 306 7130",
    "sg:postcode":"2583 CM",
    "sg:province":"Zuid-Holland",
    "sg:website":"http://www.aquastore.nl",
    "wof:name":"Aqua Store",
    "wof:placetype":"venue"
},
  "geometry": {"coordinates":[4.2552599907,52.0912399292],"type":"Point"}
}