{
  "type": "Feature",
  "properties": {
    "iso:country":"NL",
    "sg:address":"Hoofdstr 13",
    "sg:city":"Heeswyk Dinther",
    "sg:orig_category":"Schoenen",
    "sg:phone":"+31 413 296 005",
    "sg:postcode":"5473 AN",
    "sg:province":"North Brabant",
    "wof:name":"Kemenade, Van",
    "wof:placetype":"venue"
},
  "geometry": {"coordinates":[5.471758,51.649696],"type":"Point"}
}