{
  "type": "Feature",
  "properties": {
    "addr:full":"Volmarynstr 88A Rotterdam South Holland 3021 XV",
    "addr:housenumber":"88a",
    "addr:postcode":"3021 xv",
    "addr:street":"Volmarynstr",
    "iso:country":"NL",
    "sg:address":"Volmarynstr 88A",
    "sg:city":"Rotterdam",
    "sg:orig_category":"Verenigingsgebouwen",
    "sg:phone":"+31 10 478 2001",
    "sg:postcode":"3021 XV",
    "sg:province":"South Holland",
    "wof:name":"Rosa",
    "wof:placetype":"venue"
},
  "geometry": {"coordinates":[4.459271,51.913441],"type":"Point"}
}