{
  "type": "Feature",
  "properties": {
    "addr:full":"Waddenstr 711 Haarlem North Holland 2036 LV",
    "addr:housenumber":"711",
    "addr:postcode":"2036",
    "iso:country":"NL",
    "sg:address":"Waddenstr 711",
    "sg:city":"Haarlem",
    "sg:orig_category":"Autorijscholen",
    "sg:phone":"+31 23 540 9430",
    "sg:postcode":"2036 LV",
    "sg:province":"North Holland",
    "sg:website":"http://www.rijschoolhartewens.com",
    "wof:name":"Hartewens, Autorijschool",
    "wof:placetype":"venue"
},
  "geometry": {"coordinates":[4.653332,52.353943],"type":"Point"}
}