{
  "type": "Feature",
  "properties": {
    "addr:full":"Hooigr 60 Leiden Zuid-Holland 2312 KV",
    "addr:housenumber":"60",
    "addr:postcode":"2312 kv",
    "addr:street":"Hooigr",
    "iso:country":"NL",
    "sg:address":"Hooigr 60",
    "sg:city":"Leiden",
    "sg:orig_category":"Adviesbureaus Bedrijfsorganisatie",
    "sg:phone":"+31 71 514 1543",
    "sg:postcode":"2312 KV",
    "sg:province":"Zuid-Holland",
    "wof:name":"Luba Bv",
    "wof:placetype":"venue"
},
  "geometry": {"coordinates":[4.495928,52.158703],"type":"Point"}
}