{
  "type": "Feature",
  "properties": {
    "addr:full":"Kraaiheide 50 Eerbeek Gelderland 6961 PD",
    "addr:housenumber":"50",
    "addr:postcode":"6961 pd",
    "addr:street":"Kraaiheide;Gelderland",
    "iso:country":"NL",
    "sg:address":"Kraaiheide 50",
    "sg:city":"Eerbeek",
    "sg:orig_category":"Adviesbureaus Bedrijfsorganisatie",
    "sg:phone":"+31 313 650 694",
    "sg:postcode":"6961 PD",
    "sg:province":"Gelderland",
    "wof:name":"Wagenaar",
    "wof:placetype":"venue"
},
  "geometry": {"coordinates":[6.050822,52.113968],"type":"Point"}
}