{
  "type": "Feature",
  "properties": {
    "iso:country":"NL",
    "sg:address":"Zenderstr 13",
    "sg:city":"Hilversum",
    "sg:orig_category":"Glazenwasserijen",
    "sg:phone":"+31 35 642 4336",
    "sg:postcode":"1223 DR",
    "sg:province":"North Holland",
    "wof:name":"Dk Vof",
    "wof:placetype":"venue"
},
  "geometry": {"coordinates":[5.195343,52.233059],"type":"Point"}
}