{
  "type": "Feature",
  "properties": {
    "iso:country":"NL",
    "sg:address":"Hoeksekade 113",
    "sg:city":"Bergschenhoek",
    "sg:orig_category":"Parketvloeren",
    "sg:phone":"+31 10 529 9390",
    "sg:postcode":"2661 JL",
    "sg:province":"Zuid-Holland",
    "sg:website":"http://www.hulsthout.nl",
    "wof:name":"Hulst Bv",
    "wof:placetype":"venue"
},
  "geometry": {"coordinates":[4.524407,51.978008],"type":"Point"}
}