{
  "type": "Feature",
  "properties": {
    "addr:full":"Amsterdamsewg 15 Amersfoort Utrecht 3812 RN",
    "addr:housenumber":"15",
    "addr:postcode":"3812 rn",
    "addr:street":"Amsterdamsewg",
    "iso:country":"NL",
    "sg:address":"Amsterdamsewg 15",
    "sg:city":"Amersfoort",
    "sg:orig_category":"Meubelen",
    "sg:phone":"+31 33 461 1622",
    "sg:postcode":"3812 RN",
    "sg:province":"Utrecht",
    "wof:name":"Meubelvoordeel",
    "wof:placetype":"venue"
},
  "geometry": {"coordinates":[5.374228,52.161465],"type":"Point"}
}