{
  "type": "Feature",
  "properties": {
    "addr:full":"Zevenhuizen 8 Franeker Friesland 8801 AW",
    "addr:housenumber":"8",
    "addr:postcode":"8801 aw",
    "addr:street":"Zevenhuizen",
    "iso:country":"NL",
    "sg:address":"Zevenhuizen 8",
    "sg:city":"Franeker",
    "sg:orig_category":"Verzekeringen",
    "sg:phone":"+31 517 394 242",
    "sg:postcode":"8801 AW",
    "sg:province":"Friesland",
    "wof:name":"Htl Friesland Bv",
    "wof:placetype":"venue"
},
  "geometry": {"coordinates":[5.559067,53.184315],"type":"Point"}
}