{
  "type": "Feature",
  "properties": {
    "addr:full":"Raadhuislaan 47 Oude Pekela Groningen 9665 JA",
    "addr:housenumber":"47",
    "addr:postcode":"pekela;9665 ja",
    "addr:street":"Raadhuislaan",
    "iso:country":"NL",
    "sg:address":"Raadhuislaan 47",
    "sg:city":"Oude Pekela",
    "sg:orig_category":"Overheidsdiensten",
    "sg:phone":"+31 597 612 980",
    "sg:postcode":"9665 JA",
    "sg:province":"Groningen",
    "wof:name":"De Snikke",
    "wof:placetype":"venue"
},
  "geometry": {"coordinates":[7.0072951317,53.1043777466],"type":"Point"}
}