{
  "type": "Feature",
  "properties": {
    "addr:full":"Martin Luther Kingsngl 28 Drachten Friesland 9203 JC",
    "addr:housenumber":"28",
    "addr:postcode":"9203 jc",
    "addr:street":"Martin",
    "iso:country":"NL",
    "sg:address":"Martin Luther Kingsngl 28",
    "sg:city":"Drachten",
    "sg:orig_category":"Meubelzaken, Woning- And Keukeninrichting",
    "sg:phone":"+31 512 520 838",
    "sg:postcode":"9203 JC",
    "sg:province":"Friesland",
    "wof:name":"Bentja Bv",
    "wof:placetype":"venue"
},
  "geometry": {"coordinates":[6.105437,53.096287],"type":"Point"}
}