{
  "type": "Feature",
  "properties": {
    "addr:full":"Pr Hendrikstr 90 Alphen Aan Den Ryn Zuid-Holland 2405 AL",
    "addr:housenumber":"90",
    "addr:postcode":"2405 al",
    "addr:street":"Aan Den Ryn",
    "iso:country":"NL",
    "sg:address":"Pr Hendrikstr 90",
    "sg:city":"Alphen Aan Den Ryn",
    "sg:orig_category":"Verzekeringen - Verzekeringskantoren",
    "sg:phone":"+31 172 494 041",
    "sg:postcode":"2405 AL",
    "sg:province":"Zuid-Holland",
    "sg:website":"http://www.deerenberg.nl",
    "wof:name":"Deerenberg & Van Leeuwen",
    "wof:placetype":"venue"
},
  "geometry": {"coordinates":[4.6625947952,52.1235389709],"type":"Point"}
}