{
  "type": "Feature",
  "properties": {
    "addr:full":"Hoofd 3 Hoorn Nh Noord-Holland 1621 AM",
    "addr:housenumber":"3",
    "addr:postcode":"1621",
    "addr:street":"Hoofd",
    "iso:country":"NL",
    "sg:address":"Hoofd 3",
    "sg:city":"Hoorn Nh",
    "sg:classifiers":[
        {
            "category":"Fast Food",
            "type":"Food & Drink"
        }
    ],
    "sg:phone":"+31 229 216 950",
    "sg:postcode":"1621 AM",
    "sg:province":"Noord-Holland",
    "sg:tags":[
        "afhaal",
        "restaurant"
    ],
    "wof:name":"Snackbar 'T Hoofd",
    "wof:placetype":"venue"
},
  "geometry": {"coordinates":[5.062774,52.63665],"type":"Point"}
}