{
  "type": "Feature",
  "properties": {
    "addr:full":"J V Maerlantln 17 Heerhugowaard Noord-Holland 1702 GL",
    "addr:housenumber":"17",
    "addr:postcode":"1702 gl",
    "addr:street":"J;Maerlantln",
    "iso:country":"NL",
    "sg:address":"J V Maerlantln 17",
    "sg:city":"Heerhugowaard",
    "sg:classifiers":[
        {
            "category":"Personal",
            "subcategory":"Nail Salon",
            "type":"Services"
        }
    ],
    "sg:phone":"+31 72 571 4127",
    "sg:postcode":"1702 GL",
    "sg:province":"Noord-Holland",
    "sg:tags":[
        "pedicure"
    ],
    "wof:name":"Kleut-Smit, M B Van De",
    "wof:placetype":"venue"
},
  "geometry": {"coordinates":[4.827522,52.665195],"type":"Point"}
}