{
  "type": "Feature",
  "properties": {
    "addr:full":"Broekweg 14 Ouddorp Zh Zuid-Holland 3253 XB",
    "addr:housenumber":"14",
    "addr:postcode":"3253 xb",
    "addr:street":"Broekweg",
    "iso:country":"NL",
    "sg:address":"Broekweg 14",
    "sg:city":"Ouddorp Zh",
    "sg:classifiers":[
        {
            "category":"Fast Food",
            "type":"Food & Drink"
        }
    ],
    "sg:phone":"+31 187 681 235",
    "sg:postcode":"3253 XB",
    "sg:province":"Zuid-Holland",
    "sg:tags":[
        "afhaal",
        "restaurant"
    ],
    "wof:name":"De Koophandel",
    "wof:placetype":"venue"
},
  "geometry": {"coordinates":[3.937539,51.809135],"type":"Point"}
}