{
  "type": "Feature",
  "properties": {
    "addr:full":"Vlinderveen 628 Spykenisse Zuid-Holland 3205 EP",
    "addr:housenumber":"628",
    "addr:postcode":"3205 ep",
    "addr:street":"Vlinderveen",
    "iso:country":"NL",
    "sg:address":"Vlinderveen 628",
    "sg:city":"Spykenisse",
    "sg:orig_category":"Kappers",
    "sg:phone":"+31 181 645 673",
    "sg:postcode":"3205 EP",
    "sg:province":"Zuid-Holland",
    "wof:name":"All You Need",
    "wof:placetype":"venue"
},
  "geometry": {"coordinates":[4.3425211906,51.8324966431],"type":"Point"}
}