{
  "type": "Feature",
  "properties": {
    "addr:full":"Jacob Catsstraat 3 Kesteren Gelderland 4041 XV",
    "addr:housenumber":"3",
    "addr:postcode":"4041 xv",
    "addr:street":"Jacob Catsstraat;Gelderland",
    "iso:country":"NL",
    "sg:address":"Jacob Catsstraat 3",
    "sg:city":"Kesteren",
    "sg:orig_category":"Paramedische Behandelingen",
    "sg:phone":"+31 488 482 151",
    "sg:postcode":"4041 XV",
    "sg:province":"Gelderland",
    "wof:name":"Particulier Kraamzorgburo Kesteren Eo",
    "wof:placetype":"venue"
},
  "geometry": {"coordinates":[5.569974,51.931461],"type":"Point"}
}