{
  "type": "Feature",
  "properties": {
    "addr:full":"Maasdk 103 Aalst Gld Gelderland 5308 JC",
    "addr:housenumber":"103",
    "addr:postcode":"5308 jc",
    "addr:street":"Gld Gelderland",
    "iso:country":"NL",
    "sg:address":"Maasdk 103",
    "sg:city":"Aalst Gld",
    "sg:orig_category":"Administratie- En Boekhoudkantoren",
    "sg:phone":"+31 418 673 287",
    "sg:postcode":"5308 JC",
    "sg:province":"Gelderland",
    "wof:name":"Kaasjager",
    "wof:placetype":"venue"
},
  "geometry": {"coordinates":[5.121485,51.784462],"type":"Point"}
}