{
  "type": "Feature",
  "properties": {
    "addr:full":"V Ittersumstr 1 Zwolle NL.08 8011 JN",
    "addr:housenumber":"1",
    "addr:postcode":"8011 jn",
    "addr:street":"Ittersumstr",
    "iso:country":"NL",
    "sg:address":"V Ittersumstr 1",
    "sg:city":"Zwolle",
    "sg:orig_category":"Hoortoestellen",
    "sg:phone":"+31 38 422 6303",
    "sg:postcode":"8011 JN",
    "sg:province":"NL.08",
    "sg:website":"http://www.ijpea.nl",
    "wof:name":"Dehoor",
    "wof:placetype":"venue"
},
  "geometry": {"coordinates":[6.088738,52.512566],"type":"Point"}
}