{
  "type": "Feature",
  "properties": {
    "iso:country":"NL",
    "sg:address":"Emmastr 7",
    "sg:city":"Roosendaal",
    "sg:orig_category":"Parkeergarages",
    "sg:phone":"+31 165 529 400",
    "sg:postcode":"4701 GD",
    "sg:province":"North Brabant",
    "sg:website":"http://www.parkeerbeheer.nl",
    "wof:name":"Parkeer Beheer Roosendaal Bv",
    "wof:placetype":"venue"
},
  "geometry": {"coordinates":[4.462818,51.531052],"type":"Point"}
}