{
  "type": "Feature",
  "properties": {
    "addr:full":"Ter Heerdtspad 12 Vaassen Gelderland 8171 CH",
    "addr:housenumber":"12",
    "addr:postcode":"8171",
    "addr:street":"Ter Heerdtspad;Gelderland",
    "iso:country":"NL",
    "sg:address":"Ter Heerdtspad 12",
    "sg:city":"Vaassen",
    "sg:orig_category":"Juridische Dienstverlening",
    "sg:phone":"+31 578 575 344",
    "sg:postcode":"8171 CH",
    "sg:province":"Gelderland",
    "wof:name":"Valent C.S.",
    "wof:placetype":"venue"
},
  "geometry": {"coordinates":[5.967213,52.289314],"type":"Point"}
}