{
  "type": "Feature",
  "properties": {
    "addr:full":"Laan Ten Roode 34 Someren Noord-Brabant 5711 GC",
    "addr:housenumber":"34",
    "addr:postcode":"5711 gc",
    "addr:street":"Laan Ten Roode",
    "iso:country":"NL",
    "sg:address":"Laan Ten Roode 34",
    "sg:city":"Someren",
    "sg:classifiers":[
        {
            "category":"Education",
            "subcategory":"Preschool",
            "type":"Public Place"
        }
    ],
    "sg:phone":"+31 493 491 348",
    "sg:postcode":"5711 GC",
    "sg:province":"Noord-Brabant",
    "sg:tags":[
        "kleuteronderwijs",
        "basis-"
    ],
    "wof:name":"Mariaschool",
    "wof:placetype":"venue"
},
  "geometry": {"coordinates":[5.714191,51.382397],"type":"Point"}
}