{
  "type": "Feature",
  "properties": {
    "addr:full":"David Ben Goerionstraat 5 Utrecht Utrecht 3573 XL",
    "addr:housenumber":"5",
    "addr:postcode":"3573 xl",
    "addr:street":"David Ben Goerionstraat",
    "iso:country":"NL",
    "sg:address":"David Ben Goerionstraat 5",
    "sg:city":"Utrecht",
    "sg:orig_category":"Kappers",
    "sg:phone":"+31 30 271 5130",
    "sg:postcode":"3573 XL",
    "sg:province":"Utrecht",
    "wof:name":"Hairstyling Your Hair",
    "wof:placetype":"venue"
},
  "geometry": {"coordinates":[5.1472578049,52.1129226685],"type":"Point"}
}