{
  "type": "Feature",
  "properties": {
    "addr:full":"Gasthuisvest 21 Haarlem Noord-Holland 2011 ET",
    "addr:housenumber":"21",
    "addr:postcode":"2011 et",
    "addr:street":"Gasthuisvest",
    "iso:country":"NL",
    "sg:address":"Gasthuisvest 21",
    "sg:city":"Haarlem",
    "sg:orig_category":"Kappers",
    "sg:phone":"+31 23 531 4461",
    "sg:postcode":"2011 ET",
    "sg:province":"Noord-Holland",
    "wof:name":"Dameskapsalon Paul",
    "wof:placetype":"venue"
},
  "geometry": {"coordinates":[4.6325669289,52.3762626648],"type":"Point"}
}