{
  "type": "Feature",
  "properties": {
    "addr:full":"Koedijk 17 Lochem Gelderland 7241 CL",
    "addr:housenumber":"17",
    "addr:postcode":"7241",
    "addr:street":"Koedijk;Gelderland",
    "iso:country":"NL",
    "sg:address":"Koedijk 17",
    "sg:city":"Lochem",
    "sg:orig_category":"Kinderopvang",
    "sg:phone":"+31 573 257 017",
    "sg:postcode":"7241 CL",
    "sg:province":"Gelderland",
    "sg:website":"http://www.degarve.nl",
    "wof:name":"Garve Merlijn, Sticht De",
    "wof:placetype":"venue"
},
  "geometry": {"coordinates":[6.40627,52.162861],"type":"Point"}
}