{
  "type": "Feature",
  "properties": {
    "iso:country":"NL",
    "sg:address":"Emmerwolderwg 4",
    "sg:city":"Ten Boer",
    "sg:orig_category":"Autorijscholen",
    "sg:phone":"+31 50 302 4219",
    "sg:postcode":"9791 JA",
    "sg:province":"Groningen",
    "wof:name":"Kamminga",
    "wof:placetype":"venue"
},
  "geometry": {"coordinates":[6.694468,53.279449],"type":"Point"}
}