{
  "type": "Feature",
  "properties": {
    "addr:full":"Veerdk 32 Wormer Noord-Holland 1531 MS",
    "addr:housenumber":"32",
    "addr:postcode":"1531 ms",
    "addr:street":"Veerdk",
    "iso:country":"NL",
    "sg:address":"Veerdk 32",
    "sg:city":"Wormer",
    "sg:orig_category":"Verenigingen En Stichtingen",
    "sg:phone":"+31 75 647 4513",
    "sg:postcode":"1531 MS",
    "sg:province":"Noord-Holland",
    "wof:name":"Steunpunt Cult Erfgoed, Sticht",
    "wof:placetype":"venue"
},
  "geometry": {"coordinates":[4.802297,52.490105],"type":"Point"}
}