{
  "type": "Feature",
  "properties": {
    "addr:full":"Burg Breebaartstr 30 Hoogwoud North Holland 1718 BC",
    "addr:housenumber":"30",
    "addr:postcode":"1718 bc",
    "addr:street":"Burg",
    "iso:country":"NL",
    "sg:address":"Burg Breebaartstr 30",
    "sg:city":"Hoogwoud",
    "sg:orig_category":"Onderhoudswerken",
    "sg:phone":"+31 226 351 143",
    "sg:postcode":"1718 BC",
    "sg:province":"North Holland",
    "wof:name":"Berg, Martien Van Den",
    "wof:placetype":"venue"
},
  "geometry": {"coordinates":[4.938623,52.71946],"type":"Point"}
}