{
  "type": "Feature",
  "properties": {
    "addr:full":"Groenewg 19 Wyk En Aalburg Gelderland 4261 RG",
    "addr:housenumber":"19",
    "addr:postcode":"4261 rg",
    "addr:street":"Groenewg",
    "iso:country":"NL",
    "sg:address":"Groenewg 19",
    "sg:city":"Wyk En Aalburg",
    "sg:orig_category":"Bloemen En Planten - Groothandel",
    "sg:phone":"+31 416 696 066",
    "sg:postcode":"4261 RG",
    "sg:province":"Gelderland",
    "wof:name":"Timmermans En Zn, A",
    "wof:placetype":"venue"
},
  "geometry": {"coordinates":[5.10457,51.76635],"type":"Point"}
}