{
  "type": "Feature",
  "properties": {
    "addr:full":"Van Leeuwenhoekweg 20 Dordrecht Zuid-Holland 3316 AV",
    "addr:housenumber":"20",
    "addr:postcode":"3316 av",
    "addr:street":"Van Leeuwenhoekweg",
    "iso:country":"NL",
    "sg:address":"Van Leeuwenhoekweg 20",
    "sg:city":"Dordrecht",
    "sg:orig_category":"Overheidsdiensten",
    "sg:phone":"+31 78 632 2500",
    "sg:postcode":"3316 AV",
    "sg:province":"Zuid-Holland",
    "wof:name":"Rijkswaterstaat",
    "wof:placetype":"venue"
},
  "geometry": {"coordinates":[4.6370830536,51.7998924255],"type":"Point"}
}