{
  "type": "Feature",
  "properties": {
    "addr:full":"Oude Binnenwg 91-93 Rotterdam South Holland 3012 JA",
    "addr:housenumber":"91-93",
    "addr:postcode":"3012 ja",
    "addr:street":"Oude Binnenwg",
    "iso:country":"NL",
    "sg:address":"Oude Binnenwg 91-93",
    "sg:city":"Rotterdam",
    "sg:orig_category":"Modelbouw",
    "sg:phone":"+31 10 413 5923",
    "sg:postcode":"3012 JA",
    "sg:province":"South Holland",
    "wof:name":"Nieuwenhuyzen, Van",
    "wof:placetype":"venue"
},
  "geometry": {"coordinates":[4.475451,51.917774],"type":"Point"}
}