{
  "type": "Feature",
  "properties": {
    "addr:full":"Luttenbergerweg 22 Hellendoorn Overijssel 7447 PB",
    "addr:housenumber":"22",
    "addr:postcode":"7447 pb",
    "addr:street":"Luttenbergerweg",
    "iso:country":"NL",
    "sg:address":"Luttenbergerweg 22",
    "sg:city":"Hellendoorn",
    "sg:orig_category":"Kermissen And Pretparken",
    "sg:phone":"+31 548 659 159",
    "sg:postcode":"7447 PB",
    "sg:province":"Overijssel",
    "wof:name":"Avonturenpark Hellendoorn",
    "wof:placetype":"venue"
},
  "geometry": {"coordinates":[-36.777691,-7.16501],"type":"Point"}
}