{
  "type": "Feature",
  "properties": {
    "iso:country":"NL",
    "sg:address":"Oranjeplnts 82",
    "sg:city":"Diemen",
    "sg:orig_category":"Administratie- En Boekhoudkantoren",
    "sg:phone":"+31 20 690 0244",
    "sg:postcode":"1111 CH",
    "sg:province":"Noord-Holland",
    "wof:name":"Monchy, De",
    "wof:placetype":"venue"
},
  "geometry": {"coordinates":[4.958799,52.3428],"type":"Point"}
}