{
  "type": "Feature",
  "properties": {
    "addr:full":"Julianastraat 55 Dedemsvaart Overijssel 7701 GJ",
    "addr:housenumber":"55",
    "addr:postcode":"7701 gj",
    "addr:street":"Julianastraat",
    "iso:country":"NL",
    "sg:address":"Julianastraat 55",
    "sg:city":"Dedemsvaart",
    "sg:orig_category":"Fietshandelaren",
    "sg:phone":"+31 523 613 600",
    "sg:postcode":"7701 GJ",
    "sg:province":"Overijssel",
    "wof:name":"Stegeman Tweewielercentrum",
    "wof:placetype":"venue"
},
  "geometry": {"coordinates":[6.458079,52.602737],"type":"Point"}
}