{
  "type": "Feature",
  "properties": {
    "addr:full":"Postbus 1174 Almere 1300 BD",
    "addr:housenumber":"1174",
    "addr:postcode":"1300 bd",
    "addr:street":"Postbus",
    "iso:country":"NL",
    "sg:address":"Postbus 1174",
    "sg:city":"Almere",
    "sg:orig_category":"Cd'S, Grammofoonpl. En Muziekcass.-Maatschapp. En Grooth",
    "sg:phone":"+31 6 50593527",
    "sg:postcode":"1300 BD",
    "sg:website":"http://www.xsessivetrance.com",
    "wof:name":"Xsessive Trance",
    "wof:placetype":"venue"
},
  "geometry": {"coordinates":[5.22223,52.376591],"type":"Point"}
}