{
  "type": "Feature",
  "properties": {
    "addr:full":"Bredevoortsestrwg 64 Aalten Gelderland 7121 BK",
    "addr:housenumber":"64",
    "addr:postcode":"7121 bk",
    "addr:street":"Bredevoortsestrwg;Gelderland",
    "iso:country":"NL",
    "sg:address":"Bredevoortsestrwg 64",
    "sg:city":"Aalten",
    "sg:orig_category":"Verzekeringen - Verzekeringskantoren",
    "sg:phone":"+31 543 472 703",
    "sg:postcode":"7121 BK",
    "sg:province":"Gelderland",
    "wof:name":"Kremer En Partners",
    "wof:placetype":"venue"
},
  "geometry": {"coordinates":[6.590047,51.930511],"type":"Point"}
}