{
  "type": "Feature",
  "properties": {
    "addr:full":"Jacob Catslaan 3 Ermelo Gelderland 3852 BT",
    "addr:housenumber":"3",
    "addr:postcode":"3852 bt",
    "addr:street":"Jacob Catslaan;Gelderland",
    "iso:country":"NL",
    "sg:address":"Jacob Catslaan 3",
    "sg:city":"Ermelo",
    "sg:orig_category":"Vertaal- And Tolkenbureaus",
    "sg:phone":"+31 341 562 322",
    "sg:postcode":"3852 BT",
    "sg:province":"Gelderland",
    "wof:name":"Cms Vertalingen",
    "wof:placetype":"venue"
},
  "geometry": {"coordinates":[5.637419,52.301334],"type":"Point"}
}