{
  "type": "Feature",
  "properties": {
    "addr:full":"Kruburg 76 Eindhoven Noord-Brabant 5632 PJ",
    "addr:housenumber":"76",
    "addr:postcode":"5632 pj",
    "addr:street":"Kruburg",
    "iso:country":"NL",
    "sg:address":"Kruburg 76",
    "sg:city":"Eindhoven",
    "sg:orig_category":"Adviesbureaus Onderhoudswerken",
    "sg:phone":"+31 6 51299647",
    "sg:postcode":"5632 PJ",
    "sg:province":"Noord-Brabant",
    "sg:website":"http://www.verfvraagbaak.info",
    "wof:name":"Couteaux, Marc",
    "wof:placetype":"venue"
},
  "geometry": {"coordinates":[5.49848,51.477058],"type":"Point"}
}