{
  "type": "Feature",
  "properties": {
    "addr:full":"Graafseweg 274 Nijmegen Gelderland 6532 ZV",
    "addr:housenumber":"274",
    "addr:postcode":"6532 zv",
    "addr:street":"Graafseweg;Gelderland",
    "iso:country":"NL",
    "sg:address":"Graafseweg 274",
    "sg:city":"Nijmegen",
    "sg:orig_category":"Binnenhuisarchitecten",
    "sg:phone":"+31 24 378 9577",
    "sg:postcode":"6532 ZV",
    "sg:province":"Gelderland",
    "wof:name":"Gery Van Haaren Ontwerpburo",
    "wof:placetype":"venue"
},
  "geometry": {"coordinates":[5.837122,51.833652],"type":"Point"}
}