{
  "type": "Feature",
  "properties": {
    "addr:full":"Bisonspoor 2052 Maarssen Utrecht 3605 LG",
    "addr:housenumber":"2052",
    "addr:postcode":"3605 lg",
    "addr:street":"Bisonspoor",
    "iso:country":"NL",
    "sg:address":"Bisonspoor 2052",
    "sg:city":"Maarssen",
    "sg:orig_category":"Wasmachines En Wasdrogers",
    "sg:phone":"+31 346 576 111",
    "sg:postcode":"3605 LG",
    "sg:province":"Utrecht",
    "wof:name":"Bcc",
    "wof:placetype":"venue"
},
  "geometry": {"coordinates":[5.0305418968,52.1355285645],"type":"Point"}
}