{
  "type": "Feature",
  "properties": {
    "addr:full":"Wykerstraatwg . Velsen Noord Noord-Holland 1951 EJ",
    "addr:postcode":"1951 ej",
    "iso:country":"NL",
    "sg:address":"Wykerstraatwg .",
    "sg:city":"Velsen Noord",
    "sg:classifiers":[
        {
            "category":"Farming",
            "subcategory":"Fish & Marine Products",
            "type":"Manufacturing & Wholesale Goods"
        }
    ],
    "sg:phone":"+31 251 222 450",
    "sg:postcode":"1951 EJ",
    "sg:province":"Noord-Holland",
    "sg:tags":[
        "vi"
    ],
    "wof:name":"Vissende Beer, De",
    "wof:placetype":"venue"
},
  "geometry": {"coordinates":[4.645905,52.472397],"type":"Point"}
}