{
  "type": "Feature",
  "properties": {
    "addr:full":"Churchilllaan 7 Eygelshoven Limburg 6471 VT",
    "addr:housenumber":"7",
    "addr:postcode":"6471",
    "addr:street":"Churchilllaan",
    "iso:country":"NL",
    "sg:address":"Churchilllaan 7",
    "sg:city":"Eygelshoven",
    "sg:classifiers":[
        {
            "category":"Shopping",
            "subcategory":"Gifts & Souvenirs",
            "type":"Retail Goods"
        }
    ],
    "sg:phone":"+31 45 567 0400",
    "sg:postcode":"6471 VT",
    "sg:province":"Limburg",
    "sg:tags":[
        "geschenken"
    ],
    "wof:name":"Jh",
    "wof:placetype":"venue"
},
  "geometry": {"coordinates":[6.054366,50.897427],"type":"Point"}
}