{
  "type": "Feature",
  "properties": {
    "addr:full":"Colijnstraat 32 Velp Gld Gelderland 6882 JR",
    "addr:housenumber":"32;6882",
    "addr:street":"Colijnstraat;Gld Gelderland",
    "iso:country":"NL",
    "sg:address":"Colijnstraat 32",
    "sg:city":"Velp Gld",
    "sg:orig_category":"Loodgieterswerk, Verwarming And Sanitaire Installaties",
    "sg:phone":"+31 26 361 6725",
    "sg:postcode":"6882 JR",
    "sg:province":"Gelderland",
    "wof:name":"J G Grondman",
    "wof:placetype":"venue"
},
  "geometry": {"coordinates":[5.970005,51.9893],"type":"Point"}
}