{
  "type": "Feature",
  "properties": {
    "addr:full":"Kayersdijk 81 Apeldoorn Gelderland 7332 AL",
    "addr:housenumber":"81",
    "addr:postcode":"7332",
    "addr:street":"Kayersdijk;Gelderland",
    "iso:country":"NL",
    "sg:address":"Kayersdijk 81",
    "sg:city":"Apeldoorn",
    "sg:orig_category":"Krantenuitgeverijen",
    "sg:phone":"+31 55 539 9200",
    "sg:postcode":"7332 AL",
    "sg:province":"Gelderland",
    "wof:name":"Nieuws-Tv",
    "wof:placetype":"venue"
},
  "geometry": {"coordinates":[5.979261,52.201317],"type":"Point"}
}