{
  "type": "Feature",
  "properties": {
    "iso:country":"NL",
    "sg:address":"Van Heutszpark 22",
    "sg:city":"Vlaardingen",
    "sg:orig_category":"Meubelzaken, Woning- And Keukeninrichting",
    "sg:phone":"+31 10 434 2681",
    "sg:postcode":"3131 NG",
    "sg:province":"Zuid-Holland",
    "wof:name":"International Furniture Trading",
    "wof:placetype":"venue"
},
  "geometry": {"coordinates":[4.332347,51.915981],"type":"Point"}
}