{
  "type": "Feature",
  "properties": {
    "addr:full":"A Kuyperstr 66 Harlingen Friesland 8862 VV",
    "addr:housenumber":"66",
    "addr:postcode":"8862 vv",
    "iso:country":"NL",
    "sg:address":"A Kuyperstr 66",
    "sg:city":"Harlingen",
    "sg:orig_category":"Geluidsinstallaties",
    "sg:phone":"+31 517 418 118",
    "sg:postcode":"8862 VV",
    "sg:province":"Friesland",
    "sg:website":"http://www.new-line.nl",
    "wof:name":"New Line Licht & Geluid",
    "wof:placetype":"venue"
},
  "geometry": {"coordinates":[5.436516,53.166676],"type":"Point"}
}