{
  "type": "Feature",
  "properties": {
    "addr:full":"Rhynkant 18 Berkel Enschot North Brabant 5056 JH",
    "addr:housenumber":"18",
    "addr:postcode":"5056 jh",
    "addr:street":"Rhynkant;Enschot",
    "iso:country":"NL",
    "sg:address":"Rhynkant 18",
    "sg:city":"Berkel Enschot",
    "sg:orig_category":"Ziekenvervoer",
    "sg:phone":"+31 13 536 5555",
    "sg:postcode":"5056 JH",
    "sg:province":"North Brabant",
    "wof:name":"Centraal Ziekenvervoer Tilburg",
    "wof:placetype":"venue"
},
  "geometry": {"coordinates":[5.143466,51.592312],"type":"Point"}
}