{
  "type": "Feature",
  "properties": {
    "iso:country":"NL",
    "sg:address":"Bato Swg 2",
    "sg:city":"Oosterbeek",
    "sg:orig_category":"Onderhoudswerken",
    "sg:phone":"+31 26 333 7012",
    "sg:postcode":"6862 ET",
    "sg:province":"Gelderland",
    "wof:name":"Middelham, J",
    "wof:placetype":"venue"
},
  "geometry": {"coordinates":[5.846281,51.981812],"type":"Point"}
}