{
  "type": "Feature",
  "properties": {
    "addr:full":"Wolfhezerwg 101 Wolfheze Gelderland 6874 AD",
    "addr:housenumber":"101",
    "addr:postcode":"6874 ad",
    "addr:street":"Gelderland",
    "iso:country":"NL",
    "sg:address":"Wolfhezerwg 101",
    "sg:city":"Wolfheze",
    "sg:orig_category":"Bejaarden - Verzorgingstehuizen",
    "sg:phone":"+31 26 482 1177",
    "sg:postcode":"6874 AD",
    "sg:province":"Gelderland",
    "wof:name":"Schild, Het",
    "wof:placetype":"venue"
},
  "geometry": {"coordinates":[5.793545,52.00724],"type":"Point"}
}