{
  "type": "Feature",
  "properties": {
    "addr:full":"Zevenkampse Ring 240 Rotterdam South Holland 3068 PZ",
    "addr:housenumber":"240",
    "addr:postcode":"3068 pz",
    "addr:street":"Zevenkampse Ring",
    "iso:country":"NL",
    "sg:address":"Zevenkampse Ring 240",
    "sg:city":"Rotterdam",
    "sg:orig_category":"Verzekeringen",
    "sg:phone":"+31 10 456 1661",
    "sg:postcode":"3068 PZ",
    "sg:province":"South Holland",
    "wof:name":"Urgent Assurantien",
    "wof:placetype":"venue"
},
  "geometry": {"coordinates":[4.577659,51.966274],"type":"Point"}
}