{
  "type": "Feature",
  "properties": {
    "addr:full":"Blaer 2 Koedijk Noord-Holland 1831 AB",
    "addr:housenumber":"2",
    "addr:postcode":"1831 ab",
    "addr:street":"Blaer",
    "iso:country":"NL",
    "sg:address":"Blaer 2",
    "sg:city":"Koedijk",
    "sg:orig_category":"Banken And Kredietinstellingen",
    "sg:phone":"+31 72 561 4950",
    "sg:postcode":"1831 AB",
    "sg:province":"Noord-Holland",
    "wof:name":"Rabobank",
    "wof:placetype":"venue"
},
  "geometry": {"coordinates":[4.755393,52.673374],"type":"Point"}
}