{
  "type": "Feature",
  "properties": {
    "iso:country":"NL",
    "sg:address":"Eikvaren 34",
    "sg:city":"Deventer",
    "sg:orig_category":"Metaalbekleding And -Behandeling",
    "sg:phone":"+31 570 658 357",
    "sg:postcode":"7422 NS",
    "sg:province":"NL.08",
    "wof:name":"Stofvrij Straalbedrijf Roesink Bv",
    "wof:placetype":"venue"
},
  "geometry": {"coordinates":[6.209863,52.245182],"type":"Point"}
}