{
  "type": "Feature",
  "properties": {
    "addr:full":"Eikvaren 34 Deventer NL.08 7422 NS",
    "addr:housenumber":"34;nl.08",
    "addr:postcode":"7422 ns",
    "addr:street":"Eikvaren",
    "iso:country":"NL",
    "sg:address":"Eikvaren 34",
    "sg:city":"Deventer",
    "sg:orig_category":"Metaalbekleding And -Behandeling",
    "sg:phone":"+31 570 658 357",
    "sg:postcode":"7422 NS",
    "sg:province":"NL.08",
    "wof:name":"Stofvrij Straalbedrijf Roesink Bv",
    "wof:placetype":"venue"
},
  "geometry": {"coordinates":[6.209863,52.245182],"type":"Point"}
}