{
  "type": "Feature",
  "properties": {
    "addr:full":"Stationsstraat 1 Aalten Gelderland 7122 AR",
    "addr:housenumber":"1",
    "addr:postcode":"7122",
    "addr:street":"Stationsstraat;Gelderland",
    "iso:country":"NL",
    "sg:address":"Stationsstraat 1",
    "sg:city":"Aalten",
    "sg:orig_category":"Vertaal- And Tolkenbureaus",
    "sg:phone":"+31 543 472 134",
    "sg:postcode":"7122 AR",
    "sg:province":"Gelderland",
    "wof:name":"J. Tolkamp",
    "wof:placetype":"venue"
},
  "geometry": {"coordinates":[6.517522,51.92363],"type":"Point"}
}