{
  "type": "Feature",
  "properties": {
    "addr:full":"Katwijkerlaan 119 Pijnacker Zuid-Holland 2641 PE",
    "addr:housenumber":"119",
    "addr:postcode":"2641 pe",
    "addr:street":"Katwijkerlaan",
    "iso:country":"NL",
    "sg:address":"Katwijkerlaan 119",
    "sg:city":"Pijnacker",
    "sg:orig_category":"Gebouwenafwerking, Renovaties And Reiniging",
    "sg:phone":"+31 15 369 9364",
    "sg:postcode":"2641 PE",
    "sg:province":"Zuid-Holland",
    "wof:name":"Venibo Bv",
    "wof:placetype":"venue"
},
  "geometry": {"coordinates":[4.466482,52.03759],"type":"Point"}
}