{
  "type": "Feature",
  "properties": {
    "addr:full":"Postbus 3396 Breda Noord-Brabant 4800 DJ",
    "addr:housenumber":"3396",
    "addr:postcode":"breda;4800 dj",
    "addr:street":"Postbus",
    "iso:country":"NL",
    "sg:address":"Postbus 3396",
    "sg:city":"Breda",
    "sg:orig_category":"Adviesbureaus Bedrijfsorganisatie",
    "sg:phone":"+31 76 523 2750",
    "sg:postcode":"4800 DJ",
    "sg:province":"Noord-Brabant",
    "sg:website":"http://www.tripconsult.nl",
    "wof:name":"Tripconsult Bv",
    "wof:placetype":"venue"
},
  "geometry": {"coordinates":[4.77492,51.588699],"type":"Point"}
}