{
  "type": "Feature",
  "properties": {
    "addr:full":"Langelermaatwg 59 Hengelo Ov NL.08 7553 JE",
    "addr:housenumber":"59",
    "addr:postcode":"7553 je",
    "addr:street":"Langelermaatwg;Ov",
    "iso:country":"NL",
    "sg:address":"Langelermaatwg 59",
    "sg:city":"Hengelo Ov",
    "sg:orig_category":"Honden- En Kattentrimsalons",
    "sg:phone":"+31 74 291 6662",
    "sg:postcode":"7553 JE",
    "sg:province":"NL.08",
    "wof:name":"Polman, Sandra",
    "wof:placetype":"venue"
},
  "geometry": {"coordinates":[6.7933931351,52.2580947876],"type":"Point"}
}