{
  "type": "Feature",
  "properties": {
    "addr:full":"De Galery 3 Wyk En Aalburg Gelderland 4261 DG",
    "addr:housenumber":"3",
    "addr:postcode":"4261 dg",
    "addr:street":"Wyk En Aalburg Gelderland",
    "iso:country":"NL",
    "sg:address":"De Galery 3",
    "sg:city":"Wyk En Aalburg",
    "sg:orig_category":"Warenhuizen",
    "sg:phone":"+31 416 691 490",
    "sg:postcode":"4261 DG",
    "sg:province":"Gelderland",
    "wof:name":"Vewea",
    "wof:placetype":"venue"
},
  "geometry": {"coordinates":[5.130420208,51.7551956177],"type":"Point"}
}