{
  "type": "Feature",
  "properties": {
    "addr:full":"Oostdijk 12 Hellevoetsluis South Holland 3223 CB",
    "addr:housenumber":"12",
    "addr:postcode":"3223 cb",
    "addr:street":"Oostdijk",
    "iso:country":"NL",
    "sg:address":"Oostdijk 12",
    "sg:city":"Hellevoetsluis",
    "sg:classifiers":[
        {
            "category":"Shopping",
            "subcategory":"Gifts & Souvenirs",
            "type":"Retail Goods"
        }
    ],
    "sg:phone":"+31 181 321 655",
    "sg:postcode":"3223 CB",
    "sg:province":"South Holland",
    "sg:tags":[
        "geschenken"
    ],
    "wof:name":"Fancyfleur",
    "wof:placetype":"venue"
},
  "geometry": {"coordinates":[4.142285,51.841549],"type":"Point"}
}