{
  "type": "Feature",
  "properties": {
    "addr:full":"Willem De Zwijgerlaan 28 Leusden Utrecht 3832 CR",
    "addr:housenumber":"28",
    "addr:postcode":"3832 cr",
    "addr:street":"Willem De Zwijgerlaan",
    "iso:country":"NL",
    "sg:address":"Willem De Zwijgerlaan 28",
    "sg:city":"Leusden",
    "sg:orig_category":"Muziekinstrumenten",
    "sg:phone":"+31 33 494 0470",
    "sg:postcode":"3832 CR",
    "sg:province":"Utrecht",
    "wof:name":"R. V.D. Burg",
    "wof:placetype":"venue"
},
  "geometry": {"coordinates":[5.407046,52.118347],"type":"Point"}
}