{
  "type": "Feature",
  "properties": {
    "addr:full":"Beukelaar 37 Someren Noord-Brabant 5711 BK",
    "addr:housenumber":"37",
    "addr:postcode":"5711 bk",
    "addr:street":"Beukelaar",
    "iso:country":"NL",
    "sg:address":"Beukelaar 37",
    "sg:city":"Someren",
    "sg:orig_category":"Waterbehandeling En Waterzuiverings- Systemen",
    "sg:phone":"+31 493 471 481",
    "sg:postcode":"5711 BK",
    "sg:province":"Noord-Brabant",
    "wof:name":"Water Systems Int",
    "wof:placetype":"venue"
},
  "geometry": {"coordinates":[5.7187538147,51.3908348083],"type":"Point"}
}