{
  "type": "Feature",
  "properties": {
    "addr:full":"Pr Hendrikkd 12 Diemen Noord-Holland 1112 AK",
    "addr:housenumber":"12",
    "addr:postcode":"1112 ak",
    "iso:country":"NL",
    "sg:address":"Pr Hendrikkd 12",
    "sg:city":"Diemen",
    "sg:orig_category":"Bedrijfsopleidingen",
    "sg:phone":"+31 20 690 9779",
    "sg:postcode":"1112 AK",
    "sg:province":"Noord-Holland",
    "wof:name":"Mounfik, Marjolein",
    "wof:placetype":"venue"
},
  "geometry": {"coordinates":[4.962428,52.337601],"type":"Point"}
}