{
  "type": "Feature",
  "properties": {
    "iso:country":"NL",
    "sg:address":"J Catsstr 32",
    "sg:city":"Groningen",
    "sg:orig_category":"Vertalers",
    "sg:phone":"+31 50 579 7820",
    "sg:postcode":"9716 GD",
    "sg:province":"Groningen",
    "wof:name":"Transtext",
    "wof:placetype":"venue"
},
  "geometry": {"coordinates":[6.561673,53.23362],"type":"Point"}
}