{
  "type": "Feature",
  "properties": {
    "addr:full":"De Ruiten 3 Rutten Flevoland 8313 AW",
    "addr:housenumber":"3",
    "addr:postcode":"8313 aw",
    "addr:street":"De Ruiten;Flevoland",
    "iso:country":"NL",
    "sg:address":"De Ruiten 3",
    "sg:city":"Rutten",
    "sg:orig_category":"Adviesbureaus Bedrijfsorganisatie",
    "sg:phone":"+31 527 262 608",
    "sg:postcode":"8313 AW",
    "sg:province":"Flevoland",
    "wof:name":"Bosma Bv",
    "wof:placetype":"venue"
},
  "geometry": {"coordinates":[5.695124,52.805801],"type":"Point"}
}