{
  "type": "Feature",
  "properties": {
    "iso:country":"NL",
    "sg:address":"Atoomwg 77",
    "sg:city":"Utrecht",
    "sg:orig_category":"Keukens",
    "sg:phone":"+31 30 247 5151",
    "sg:postcode":"3542 AA",
    "sg:province":"Utrecht",
    "sg:website":"http://www.vennesluis.nl",
    "wof:name":"Venne Van Der Sluis, Van De",
    "wof:placetype":"venue"
},
  "geometry": {"coordinates":[5.052912,52.116348],"type":"Point"}
}