{
  "type": "Feature",
  "properties": {
    "addr:full":"Emrikweg 26 Haarlem North Holland 2031 BT",
    "addr:housenumber":"26",
    "addr:postcode":"2031 bt",
    "addr:street":"Emrikweg",
    "iso:country":"NL",
    "sg:address":"Emrikweg 26",
    "sg:city":"Haarlem",
    "sg:orig_category":"Huishoudapparatuur, Televisies And Radio'S",
    "sg:phone":"+31 23 531 9472",
    "sg:postcode":"2031 BT",
    "sg:province":"North Holland",
    "wof:name":"Helios Recording Broadcast Bv",
    "wof:placetype":"venue"
},
  "geometry": {"coordinates":[4.663592,52.397339],"type":"Point"}
}