{
  "type": "Feature",
  "properties": {
    "addr:full":"De Lage Wick 5 Oosterhout Gld Gelderland 6678 DA",
    "addr:housenumber":"5;6678",
    "addr:postcode":"da",
    "addr:street":"De Lage Wick;Gld Gelderland",
    "iso:country":"NL",
    "sg:address":"De Lage Wick 5",
    "sg:city":"Oosterhout Gld",
    "sg:orig_category":"Kappers",
    "sg:phone":"+31 481 481 210",
    "sg:postcode":"6678 DA",
    "sg:province":"Gelderland",
    "wof:name":"J. Jansen",
    "wof:placetype":"venue"
},
  "geometry": {"coordinates":[5.8205618858,51.8814620972],"type":"Point"}
}