{
  "type": "Feature",
  "properties": {
    "addr:full":"E Schilderinkstr 52 Doetinchem Gelderland 7002 JG",
    "addr:housenumber":"52",
    "addr:postcode":"7002 jg",
    "addr:street":"Gelderland",
    "iso:country":"NL",
    "sg:address":"E Schilderinkstr 52",
    "sg:city":"Doetinchem",
    "sg:orig_category":"Sportverenigingen En Ontspannings- Verenigingen",
    "sg:phone":"+31 314 378 272",
    "sg:postcode":"7002 JG",
    "sg:province":"Gelderland",
    "sg:website":"http://www.gelderse-keepersschool.nl",
    "wof:name":"Gelderse-Keepers-School",
    "wof:placetype":"venue"
},
  "geometry": {"coordinates":[6.309464,51.97316],"type":"Point"}
}