{
  "type": "Feature",
  "properties": {
    "addr:full":"Vlierweg 75 Houten Utrecht 3991 BB",
    "addr:housenumber":"75",
    "addr:postcode":"3991 bb",
    "addr:street":"Vlierweg",
    "iso:country":"NL",
    "sg:address":"Vlierweg 75",
    "sg:city":"Houten",
    "sg:orig_category":"Boekhouders",
    "sg:phone":"+31 30 634 2499",
    "sg:postcode":"3991 BB",
    "sg:province":"Utrecht",
    "wof:name":"Computerboekhoudpraktijk Joke Van Dijk",
    "wof:placetype":"venue"
},
  "geometry": {"coordinates":[5.169203,52.028637],"type":"Point"}
}