{
  "type": "Feature",
  "properties": {
    "addr:full":"Zweringweg 157 Enschede Overijssel 7545 CT",
    "addr:housenumber":"157",
    "addr:postcode":"7545 ct",
    "addr:street":"Zweringweg",
    "iso:country":"NL",
    "sg:address":"Zweringweg 157",
    "sg:city":"Enschede",
    "sg:orig_category":"Kappers",
    "sg:phone":"+31 53 430 1849",
    "sg:postcode":"7545 CT",
    "sg:province":"Overijssel",
    "wof:name":"Ingrid Te Riet",
    "wof:placetype":"venue"
},
  "geometry": {"coordinates":[6.8662948608,52.21118927],"type":"Point"}
}