{
  "type": "Feature",
  "properties": {
    "addr:full":"Oetewalerstr 73 Amsterdam Noord-Holland 1093 MD",
    "addr:housenumber":"73",
    "addr:postcode":"1093",
    "addr:street":"Oetewalerstr",
    "iso:country":"NL",
    "sg:address":"Oetewalerstr 73",
    "sg:city":"Amsterdam",
    "sg:orig_category":"Galeries",
    "sg:phone":"+31 20 693 1389",
    "sg:postcode":"1093 MD",
    "sg:province":"Noord-Holland",
    "sg:website":"http://www.outlineamsterdam.nl",
    "wof:name":"Outline, Sticht",
    "wof:placetype":"venue"
},
  "geometry": {"coordinates":[4.927431,52.359104],"type":"Point"}
}