{
  "type": "Feature",
  "properties": {
    "iso:country":"NL",
    "sg:address":"Sophialn 5",
    "sg:city":"Utrecht",
    "sg:orig_category":"Beeldende Kunstenaars",
    "sg:phone":"+31 30 241 3171",
    "sg:postcode":"3542 AR",
    "sg:province":"Utrecht",
    "wof:name":"Schollaardt, A",
    "wof:placetype":"venue"
},
  "geometry": {"coordinates":[5.05485,52.114029],"type":"Point"}
}