{
  "type": "Feature",
  "properties": {
    "addr:full":"Bedryvenwg 4 St Michielsgestel Noord-Brabant 5272 PB",
    "addr:housenumber":"4",
    "addr:postcode":"5272 pb",
    "addr:street":"Bedryvenwg",
    "iso:country":"NL",
    "sg:address":"Bedryvenwg 4",
    "sg:city":"St Michielsgestel",
    "sg:orig_category":"Keukens",
    "sg:phone":"+31 73 551 2096",
    "sg:postcode":"5272 PB",
    "sg:province":"Noord-Brabant",
    "wof:name":"Broks Vof, W P M",
    "wof:placetype":"venue"
},
  "geometry": {"coordinates":[5.360728,51.648777],"type":"Point"}
}