{
  "type": "Feature",
  "properties": {
    "addr:full":"Markt 75 Maastricht Limburg 6211 CL",
    "addr:housenumber":"75",
    "addr:postcode":"6211",
    "addr:street":"Markt",
    "iso:country":"NL",
    "sg:address":"Markt 75",
    "sg:city":"Maastricht",
    "sg:classifiers":[
        {
            "category":"Fast Food",
            "type":"Food & Drink"
        }
    ],
    "sg:phone":"+31 43 321 5706",
    "sg:postcode":"6211 CL",
    "sg:province":"Limburg",
    "sg:tags":[
        "afhaal",
        "restaurant"
    ],
    "wof:name":"Markt Friture Maastricht Bv",
    "wof:placetype":"venue"
},
  "geometry": {"coordinates":[5.69069,50.850742],"type":"Point"}
}