{
  "type": "Feature",
  "properties": {
    "addr:full":"David Teniersstraat 10 Helmond Noord-Brabant 5702 CG",
    "addr:housenumber":"10",
    "addr:postcode":"5702 cg",
    "addr:street":"David Teniersstraat",
    "iso:country":"NL",
    "sg:address":"David Teniersstraat 10",
    "sg:city":"Helmond",
    "sg:orig_category":"Goederenvervoer Over De Weg",
    "sg:phone":"+31 492 543 614",
    "sg:postcode":"5702 CG",
    "sg:province":"Noord-Brabant",
    "wof:name":"Dilintra Bv",
    "wof:placetype":"venue"
},
  "geometry": {"coordinates":[5.677146,51.492088],"type":"Point"}
}