{
  "type": "Feature",
  "properties": {
    "iso:country":"NL",
    "sg:address":"Raam 21A",
    "sg:city":"Delft",
    "sg:orig_category":"Autoschade- Herstelbedrijven",
    "sg:phone":"+31 15 213 0776",
    "sg:postcode":"2611 LS",
    "sg:province":"South Holland",
    "wof:name":"Herman, D",
    "wof:placetype":"venue"
},
  "geometry": {"coordinates":[4.360924,52.014557],"type":"Point"}
}