{
  "type": "Feature",
  "properties": {
    "addr:full":"Oosterpark 2 Amsterdam Noord-Holland 1091 AC",
    "addr:housenumber":"2",
    "addr:postcode":"1091 ac",
    "addr:street":"Oosterpark",
    "iso:country":"NL",
    "sg:address":"Oosterpark 2",
    "sg:city":"Amsterdam",
    "sg:orig_category":"Boekhouders",
    "sg:phone":"+31 20 693 8933",
    "sg:postcode":"1091 AC",
    "sg:province":"Noord-Holland",
    "wof:name":"Ff Etc",
    "wof:placetype":"venue"
},
  "geometry": {"coordinates":[4.915582,52.360283],"type":"Point"}
}