{
  "type": "Feature",
  "properties": {
    "iso:country":"NL",
    "sg:address":"West Havendijk 10",
    "sg:city":"Middelharnis",
    "sg:orig_category":"Pleziervaartuigen And Reparatie",
    "sg:phone":"+31 187 484 797",
    "sg:postcode":"3241 LP",
    "sg:province":"South Holland",
    "wof:name":"Offerhaus Watersport",
    "wof:placetype":"venue"
},
  "geometry": {"coordinates":[4.174697,51.765015],"type":"Point"}
}