{
  "type": "Feature",
  "properties": {
    "addr:full":"Stationsstr 110 Ermelo Gelderland 3851 NL",
    "addr:housenumber":"110",
    "addr:postcode":"3851",
    "addr:street":"Gelderland",
    "iso:country":"NL",
    "sg:address":"Stationsstr 110",
    "sg:city":"Ermelo",
    "sg:orig_category":"Natuurvoeding En Reformartikelen",
    "sg:phone":"+31 341 559 997",
    "sg:postcode":"3851 NL",
    "sg:province":"Gelderland",
    "wof:name":"Natuurwinkel",
    "wof:placetype":"venue"
},
  "geometry": {"coordinates":[5.618277,52.299961],"type":"Point"}
}