{
  "type": "Feature",
  "properties": {
    "addr:full":"De Akkers 9 Zuidbroek Groningen 9636 CB",
    "addr:housenumber":"9",
    "addr:postcode":"9636 cb",
    "addr:street":"De Akkers",
    "iso:country":"NL",
    "sg:address":"De Akkers 9",
    "sg:city":"Zuidbroek",
    "sg:orig_category":"Bloemen And Planten",
    "sg:phone":"+31 598 453 066",
    "sg:postcode":"9636 CB",
    "sg:province":"Groningen",
    "wof:name":"Firma Bronsema-Van Aarle",
    "wof:placetype":"venue"
},
  "geometry": {"coordinates":[6.846167,53.159443],"type":"Point"}
}