{
  "type": "Feature",
  "properties": {
    "iso:country":"NL",
    "sg:address":"Klarenberg 30",
    "sg:city":"Breda",
    "sg:orig_category":"Facilitaire Dienstverlening",
    "sg:phone":"+31 76 544 0543",
    "sg:postcode":"4822 SH",
    "sg:province":"North Brabant",
    "sg:website":"http://www.keyict.nl",
    "wof:name":"Key Bv",
    "wof:placetype":"venue"
},
  "geometry": {"coordinates":[4.72604,51.617073],"type":"Point"}
}