{
  "type": "Feature",
  "properties": {
    "addr:full":"Hoogstraat 62A Rosmalen Noord-Brabant 5241 CT",
    "addr:housenumber":"62a",
    "addr:postcode":"5241 ct",
    "addr:street":"Hoogstraat",
    "iso:country":"NL",
    "sg:address":"Hoogstraat 62A",
    "sg:city":"Rosmalen",
    "sg:orig_category":"Verlichting And Huishoudartikelen",
    "sg:phone":"+31 73 521 8691",
    "sg:postcode":"5241 CT",
    "sg:province":"Noord-Brabant",
    "wof:name":"Super Stunt Shop",
    "wof:placetype":"venue"
},
  "geometry": {"coordinates":[5.36095,51.718281],"type":"Point"}
}