{
  "type": "Feature",
  "properties": {
    "addr:full":"Postbus 66029 S Gravenhage Gelderland 2506 GA",
    "addr:housenumber":"66029",
    "addr:postcode":"2506 ga",
    "addr:street":"Postbus;S Gravenhage Gelderland",
    "iso:country":"NL",
    "sg:address":"Postbus 66029",
    "sg:city":"S Gravenhage",
    "sg:orig_category":"Artiesten/Gezelschappen",
    "sg:phone":"+31 6 28880575",
    "sg:postcode":"2506 GA",
    "sg:province":"Gelderland",
    "sg:website":"http://www.zwiebels.nl",
    "wof:name":"Zwiebels, De",
    "wof:placetype":"venue"
},
  "geometry": {"coordinates":[4.31361,52.07832],"type":"Point"}
}