{
  "type": "Feature",
  "properties": {
    "iso:country":"NL",
    "sg:address":"Zandhorstln 60",
    "sg:city":"Oldenzaal",
    "sg:orig_category":"Webdesign Bureaus",
    "sg:phone":"+31 541 532 378",
    "sg:postcode":"7576 VL",
    "sg:province":"NL.08",
    "sg:website":"http://www.digiwacht.nl",
    "wof:name":"Digiwacht",
    "wof:placetype":"venue"
},
  "geometry": {"coordinates":[6.9032330513,52.3163261414],"type":"Point"}
}