{
  "type": "Feature",
  "properties": {
    "iso:country":"NL",
    "sg:address":"Poeijersstr 96",
    "sg:city":"Eindhoven",
    "sg:orig_category":"Autorijscholen",
    "sg:phone":"+31 40 281 3589",
    "sg:postcode":"5642 GE",
    "sg:province":"Noord-Brabant",
    "wof:name":"Vernooy, J",
    "wof:placetype":"venue"
},
  "geometry": {"coordinates":[5.506982,51.437336],"type":"Point"}
}