{
  "type": "Feature",
  "properties": {
    "addr:full":"Schoorwg 22 Papendrecht Zuid-Holland 3356 BX",
    "addr:housenumber":"22",
    "addr:postcode":"3356 bx",
    "addr:street":"Schoorwg",
    "iso:country":"NL",
    "sg:address":"Schoorwg 22",
    "sg:city":"Papendrecht",
    "sg:orig_category":"Zonne-Energie",
    "sg:phone":"+31 78 641 0222",
    "sg:postcode":"3356 BX",
    "sg:province":"Zuid-Holland",
    "wof:name":"Solartec",
    "wof:placetype":"venue"
},
  "geometry": {"coordinates":[4.707404,51.827541],"type":"Point"}
}