{
  "type": "Feature",
  "properties": {
    "iso:country":"NL",
    "sg:address":"Trekvogelwg 43",
    "sg:city":"Amersfoort",
    "sg:orig_category":"Nagelstudio'S",
    "sg:phone":"+31 6 14825248",
    "sg:postcode":"3815 LA",
    "sg:province":"Utrecht",
    "wof:name":"Just Nails",
    "wof:placetype":"venue"
},
  "geometry": {"coordinates":[5.41228,52.163502],"type":"Point"}
}