{
  "type": "Feature",
  "properties": {
    "addr:full":"Trekvogelwg 43 Amersfoort Utrecht 3815 LA",
    "addr:housenumber":"43",
    "addr:postcode":"3815 la",
    "addr:street":"Trekvogelwg",
    "iso:country":"NL",
    "sg:address":"Trekvogelwg 43",
    "sg:city":"Amersfoort",
    "sg:orig_category":"Nagelstudio'S",
    "sg:phone":"+31 6 14825248",
    "sg:postcode":"3815 LA",
    "sg:province":"Utrecht",
    "wof:name":"Just Nails",
    "wof:placetype":"venue"
},
  "geometry": {"coordinates":[5.41228,52.163502],"type":"Point"}
}