{
  "type": "Feature",
  "properties": {
    "addr:full":"Waalhaven O.Z. 113 Rotterdam South Holland 3087 BM",
    "addr:housenumber":"113",
    "addr:postcode":"3087 bm",
    "addr:street":"Waalhaven O.Z.",
    "iso:country":"NL",
    "sg:address":"Waalhaven O.Z. 113",
    "sg:city":"Rotterdam",
    "sg:orig_category":"Werving And Selectie Van Tijdelijk Personeel And Uitzendkantoren",
    "sg:phone":"+31 10 495 4872",
    "sg:postcode":"3087 BM",
    "sg:province":"South Holland",
    "wof:name":"Flexnet Uitzendorganisatie Bv",
    "wof:placetype":"venue"
},
  "geometry": {"coordinates":[4.4563231468,51.8840637207],"type":"Point"}
}