{
  "type": "Feature",
  "properties": {
    "addr:full":"Stationsweg 66 Ede Gld Gelderland 6711 PV",
    "addr:housenumber":"66",
    "addr:postcode":"6711 pv",
    "addr:street":"Stationsweg;Gld Gelderland",
    "iso:country":"NL",
    "sg:address":"Stationsweg 66",
    "sg:city":"Ede Gld",
    "sg:orig_category":"Artsen And Specialisten",
    "sg:phone":"+31 318 615 212",
    "sg:postcode":"6711 PV",
    "sg:province":"Gelderland",
    "wof:name":"Huisartsenpraktijk W.P.M. Van Jaarsveld",
    "wof:placetype":"venue"
},
  "geometry": {"coordinates":[5.66894,52.036491],"type":"Point"}
}