{
  "type": "Feature",
  "properties": {
    "addr:full":"Sparrendal 350 Maassluis Zuid-Holland 3142 LM",
    "addr:housenumber":"350",
    "addr:postcode":"3142 lm",
    "addr:street":"Sparrendal",
    "iso:country":"NL",
    "sg:address":"Sparrendal 350",
    "sg:city":"Maassluis",
    "sg:orig_category":"Metaalwerken",
    "sg:phone":"+31 10 591 0466",
    "sg:postcode":"3142 LM",
    "sg:province":"Zuid-Holland",
    "wof:name":"R.O.S. V.D. Land",
    "wof:placetype":"venue"
},
  "geometry": {"coordinates":[4.249285,51.930878],"type":"Point"}
}