{
  "type": "Feature",
  "properties": {
    "addr:full":"Rietorchis 8 Limmen Noord-Holland 1906 DR",
    "addr:housenumber":"8;1906",
    "addr:postcode":"dr",
    "addr:street":"Rietorchis",
    "iso:country":"NL",
    "sg:address":"Rietorchis 8",
    "sg:city":"Limmen",
    "sg:orig_category":"Adviesbureaus Personeel",
    "sg:phone":"+31 72 502 0345",
    "sg:postcode":"1906 DR",
    "sg:province":"Noord-Holland",
    "sg:website":"http://www.ommezwaai.nl",
    "wof:name":"Ommezwaai, De",
    "wof:placetype":"venue"
},
  "geometry": {"coordinates":[4.692436,52.570141],"type":"Point"}
}