{
  "type": "Feature",
  "properties": {
    "iso:country":"NL",
    "sg:address":"Clermontstr 10",
    "sg:city":"Margraten",
    "sg:orig_category":"Omroep",
    "sg:phone":"+31 43 458 1424",
    "sg:postcode":"6269 CE",
    "sg:province":"Limburg",
    "wof:name":"Radio Mergelland",
    "wof:placetype":"venue"
},
  "geometry": {"coordinates":[5.820832,50.822075],"type":"Point"}
}