{
  "type": "Feature",
  "properties": {
    "addr:full":"Groenezoom 299 Rotterdam South Holland 3075 GG",
    "addr:housenumber":"299",
    "addr:postcode":"3075 gg",
    "addr:street":"Groenezoom",
    "iso:country":"NL",
    "sg:address":"Groenezoom 299",
    "sg:city":"Rotterdam",
    "sg:orig_category":"Goudsmeden En Zilversmeden",
    "sg:phone":"+31 10 432 6911",
    "sg:postcode":"3075 GG",
    "sg:province":"South Holland",
    "wof:name":"Luu",
    "wof:placetype":"venue"
},
  "geometry": {"coordinates":[4.508939,51.884659],"type":"Point"}
}