{
  "type": "Feature",
  "properties": {
    "addr:full":"Oppenhuizerwg 1 Sneek Provincie Friesland 8606 AP",
    "addr:housenumber":"1",
    "addr:postcode":"8606 ap",
    "addr:street":"Oppenhuizerwg;Provincie Friesland",
    "iso:country":"NL",
    "sg:address":"Oppenhuizerwg 1",
    "sg:city":"Sneek",
    "sg:orig_category":"Kappers",
    "sg:phone":"+31 515 411 282",
    "sg:postcode":"8606 AP",
    "sg:province":"Provincie Friesland",
    "wof:name":"Conny",
    "wof:placetype":"venue"
},
  "geometry": {"coordinates":[5.6669411659,53.0323181152],"type":"Point"}
}