{
  "type": "Feature",
  "properties": {
    "addr:full":"Plompetorengr 15A Utrecht Utrecht 3512 CB",
    "addr:housenumber":"15a",
    "addr:postcode":"3512 cb",
    "addr:street":"Plompetorengr",
    "iso:country":"NL",
    "sg:address":"Plompetorengr 15A",
    "sg:city":"Utrecht",
    "sg:orig_category":"Verenigingen En Stichtingen",
    "sg:phone":"+31 30 231 9844",
    "sg:postcode":"3512 CB",
    "sg:province":"Utrecht",
    "sg:website":"http://www.nov.nl",
    "wof:name":"Ned Organisaties Vrijwilligerswerk",
    "wof:placetype":"venue"
},
  "geometry": {"coordinates":[5.123952,52.09626],"type":"Point"}
}