{
  "type": "Feature",
  "properties": {
    "addr:full":"Kerkstraat 4 Noordwijk Zh Zuid-Holland 2201 KM",
    "addr:housenumber":"4",
    "addr:street":"Kerkstraat;2201 Km",
    "iso:country":"NL",
    "sg:address":"Kerkstraat 4",
    "sg:city":"Noordwijk Zh",
    "sg:classifiers":[
        {
            "category":"Fast Food",
            "type":"Food & Drink"
        }
    ],
    "sg:phone":"+31 71 364 8909",
    "sg:postcode":"2201 KM",
    "sg:province":"Zuid-Holland",
    "sg:tags":[
        "afhaal",
        "restaurant"
    ],
    "wof:name":"Pyramide Shoarma En Grillroom",
    "wof:placetype":"venue"
},
  "geometry": {"coordinates":[4.447213,52.234173],"type":"Point"}
}