{
  "type": "Feature",
  "properties": {
    "addr:full":"Lekstr 28 Alblasserdam Zuid-Holland 2953 CE",
    "addr:housenumber":"28",
    "addr:postcode":"2953 ce",
    "addr:street":"Lekstr",
    "iso:country":"NL",
    "sg:address":"Lekstr 28",
    "sg:city":"Alblasserdam",
    "sg:orig_category":"Autorijscholen",
    "sg:phone":"+31 78 691 2864",
    "sg:postcode":"2953 CE",
    "sg:province":"Zuid-Holland",
    "wof:name":"Zwart, Autorijschool L De",
    "wof:placetype":"venue"
},
  "geometry": {"coordinates":[4.644278,51.870083],"type":"Point"}
}