{
  "type": "Feature",
  "properties": {
    "addr:full":"Bagijnhof 4 Dordrecht South Holland 3311 KE",
    "addr:housenumber":"4",
    "addr:postcode":"3311 ke",
    "addr:street":"Bagijnhof",
    "iso:country":"NL",
    "sg:address":"Bagijnhof 4",
    "sg:city":"Dordrecht",
    "sg:orig_category":"Paramedische Behandelingen",
    "sg:phone":"+31 78 613 3421",
    "sg:postcode":"3311 KE",
    "sg:province":"South Holland",
    "wof:name":"Van Bennekom",
    "wof:placetype":"venue"
},
  "geometry": {"coordinates":[4.666561,51.813297],"type":"Point"}
}