{
  "type": "Feature",
  "properties": {
    "addr:full":"Nieuweburen 96 Leeuwarden Friesland 8911 GA",
    "addr:housenumber":"96",
    "addr:postcode":"8911 ga",
    "addr:street":"Nieuweburen",
    "iso:country":"NL",
    "sg:address":"Nieuweburen 96",
    "sg:city":"Leeuwarden",
    "sg:orig_category":"Bloemen En Planten",
    "sg:phone":"+31 58 212 7369",
    "sg:postcode":"8911 GA",
    "sg:province":"Friesland",
    "wof:name":"Panhuis, L",
    "wof:placetype":"venue"
},
  "geometry": {"coordinates":[5.799039,53.204678],"type":"Point"}
}