{
  "type": "Feature",
  "properties": {
    "addr:full":"Rottekade 213 Bergschenhoek Zuid-Holland 2661 JW",
    "addr:housenumber":"213",
    "addr:postcode":"2661 jw",
    "addr:street":"Rottekade",
    "iso:country":"NL",
    "sg:address":"Rottekade 213",
    "sg:city":"Bergschenhoek",
    "sg:orig_category":"Goederenvervoer Over De Weg",
    "sg:phone":"+31 10 521 6213",
    "sg:postcode":"2661 JW",
    "sg:province":"Zuid-Holland",
    "wof:name":"Vof Van Eijk Transport",
    "wof:placetype":"venue"
},
  "geometry": {"coordinates":[4.522493,51.96402],"type":"Point"}
}