{
  "type": "Feature",
  "properties": {
    "addr:full":"Rijnsburgerweg 17 Voorhout Zuid-Holland 2215 RC",
    "addr:housenumber":"17",
    "addr:postcode":"2215 rc",
    "addr:street":"Rijnsburgerweg",
    "iso:country":"NL",
    "sg:address":"Rijnsburgerweg 17",
    "sg:city":"Voorhout",
    "sg:orig_category":"Bloemen And Planten",
    "sg:phone":"+31 252 210 252",
    "sg:postcode":"2215 RC",
    "sg:province":"Zuid-Holland",
    "wof:name":"Firma J.M. Van Steyn En Zn",
    "wof:placetype":"venue"
},
  "geometry": {"coordinates":[4.4733810425,52.2132034302],"type":"Point"}
}