{
  "type": "Feature",
  "properties": {
    "addr:full":"Dorpsstraat 113 Helmond Noord-Brabant 5708 GG",
    "addr:housenumber":"113",
    "addr:postcode":"5708 gg",
    "addr:street":"Dorpsstraat",
    "iso:country":"NL",
    "sg:address":"Dorpsstraat 113",
    "sg:city":"Helmond",
    "sg:orig_category":"Fietshandelaren",
    "sg:phone":"+31 492 525 198",
    "sg:postcode":"5708 GG",
    "sg:province":"Noord-Brabant",
    "wof:name":"Vof A.P.E.M. Sanders En H.M. Sanders-Maa",
    "wof:placetype":"venue"
},
  "geometry": {"coordinates":[5.623547,51.483879],"type":"Point"}
}