{
  "type": "Feature",
  "properties": {
    "addr:full":"Rozemarijnstraat 13 Schimmert Limburg 6333 BT",
    "addr:housenumber":"13",
    "addr:postcode":"6333 bt",
    "addr:street":"Rozemarijnstraat",
    "iso:country":"NL",
    "sg:address":"Rozemarijnstraat 13",
    "sg:city":"Schimmert",
    "sg:orig_category":"Verhuur Catering-, Feest- En Evenementbenodigdheden",
    "sg:phone":"+31 45 404 1587",
    "sg:postcode":"6333 BT",
    "sg:province":"Limburg",
    "wof:name":"Chris Lark Automatics",
    "wof:placetype":"venue"
},
  "geometry": {"coordinates":[5.828596,50.910915],"type":"Point"}
}