{
  "type": "Feature",
  "properties": {
    "addr:full":"M Sneevliet-Draaijerstr 8 Spijkenisse South Holland 3207 GH",
    "addr:housenumber":"8",
    "addr:postcode":"3207 gh",
    "iso:country":"NL",
    "sg:address":"M Sneevliet-Draaijerstr 8",
    "sg:city":"Spijkenisse",
    "sg:orig_category":"Paramedische Behandelingen",
    "sg:phone":"+31 181 637 790",
    "sg:postcode":"3207 GH",
    "sg:province":"South Holland",
    "wof:name":"F.J.G. Koning",
    "wof:placetype":"venue"
},
  "geometry": {"coordinates":[4.355672,51.832748],"type":"Point"}
}