{
  "type": "Feature",
  "properties": {
    "addr:full":"Insulindestr 153A Rotterdam Zuid-Holland 3038 JL",
    "addr:housenumber":"153a",
    "addr:postcode":"3038 jl",
    "iso:country":"NL",
    "sg:address":"Insulindestr 153A",
    "sg:city":"Rotterdam",
    "sg:orig_category":"Meubelmakerijen",
    "sg:phone":"+31 10 412 4034",
    "sg:postcode":"3038 JL",
    "sg:province":"Zuid-Holland",
    "wof:name":"Bok, Gert Jan",
    "wof:placetype":"venue"
},
  "geometry": {"coordinates":[4.46819,51.935402],"type":"Point"}
}