{
  "type": "Feature",
  "properties": {
    "iso:country":"NL",
    "sg:address":"Ginnekenwg 31",
    "sg:city":"Breda",
    "sg:orig_category":"Herenkleding",
    "sg:phone":"+31 76 522 1466",
    "sg:postcode":"4818 JA",
    "sg:province":"North Brabant",
    "wof:name":"Viel, Bert",
    "wof:placetype":"venue"
},
  "geometry": {"coordinates":[4.780178,51.577831],"type":"Point"}
}