{
  "type": "Feature",
  "properties": {
    "addr:full":"Past V Muyenwg 13 Heiloo Noord-Holland 1852 EG",
    "addr:housenumber":"13",
    "addr:postcode":"1852 eg",
    "addr:street":"Past;Muyenwg",
    "iso:country":"NL",
    "sg:address":"Past V Muyenwg 13",
    "sg:city":"Heiloo",
    "sg:orig_category":"Meubelen",
    "sg:phone":"+31 72 534 0032",
    "sg:postcode":"1852 EG",
    "sg:province":"Noord-Holland",
    "wof:name":"Meubel & Spiegel Huis, Het",
    "wof:placetype":"venue"
},
  "geometry": {"coordinates":[4.713702,52.604191],"type":"Point"}
}