{
  "type": "Feature",
  "properties": {
    "iso:country":"NL",
    "sg:address":"G Borgesiusstr 38",
    "sg:city":"Almelo",
    "sg:orig_category":"Koffie- En Theehuizen",
    "sg:phone":"+31 546 827 121",
    "sg:postcode":"7604 XH",
    "sg:province":"NL.08",
    "wof:name":"Saray",
    "wof:placetype":"venue"
},
  "geometry": {"coordinates":[6.652504,52.357025],"type":"Point"}
}