{
  "type": "Feature",
  "properties": {
    "addr:full":"Weena Z 152 Rotterdam Zuid-Holland 3012 NC",
    "addr:housenumber":"152",
    "addr:postcode":"3012 nc",
    "addr:street":"Weena Z",
    "iso:country":"NL",
    "sg:address":"Weena Z 152",
    "sg:city":"Rotterdam",
    "sg:orig_category":"Kunsthandel",
    "sg:phone":"+31 10 281 0642",
    "sg:postcode":"3012 NC",
    "sg:province":"Zuid-Holland",
    "wof:name":"Cornelis & Pluim",
    "wof:placetype":"venue"
},
  "geometry": {"coordinates":[4.474551,51.923496],"type":"Point"}
}