{
  "type": "Feature",
  "properties": {
    "iso:country":"NL",
    "sg:address":"Prof Tulpstr 2",
    "sg:city":"Amsterdam",
    "sg:orig_category":"Vakorganisaties",
    "sg:phone":"+31 20 400 4306",
    "sg:postcode":"1018 HA",
    "sg:province":"Noord-Holland",
    "wof:name":"Federatie Filmbelangen",
    "wof:placetype":"venue"
},
  "geometry": {"coordinates":[4.905881,52.360008],"type":"Point"}
}