{
  "type": "Feature",
  "properties": {
    "addr:full":"Meteorenwg 158 Amsterdam Noord-Holland 1033 HH",
    "addr:housenumber":"158",
    "addr:postcode":"1033 hh",
    "iso:country":"NL",
    "sg:address":"Meteorenwg 158",
    "sg:city":"Amsterdam",
    "sg:orig_category":"Drukkerijen",
    "sg:phone":"+31 20 633 6911",
    "sg:postcode":"1033 HH",
    "sg:province":"Noord-Holland",
    "sg:website":"http://www.oudebadhuis.nl",
    "wof:name":"Peters",
    "wof:placetype":"venue"
},
  "geometry": {"coordinates":[4.886868,52.412365],"type":"Point"}
}