{
  "type": "Feature",
  "properties": {
    "addr:full":"Jan Tooropstraat 13 Weesp Noord-Holland 1382 TZ",
    "addr:housenumber":"13",
    "addr:postcode":"1382 tz",
    "addr:street":"Jan Tooropstraat",
    "iso:country":"NL",
    "sg:address":"Jan Tooropstraat 13",
    "sg:city":"Weesp",
    "sg:orig_category":"Boekhouders",
    "sg:phone":"+31 294 419 452",
    "sg:postcode":"1382 TZ",
    "sg:province":"Noord-Holland",
    "wof:name":"Administratiekantoor En Belastingsadvies",
    "wof:placetype":"venue"
},
  "geometry": {"coordinates":[5.037275,52.311275],"type":"Point"}
}