{
  "type": "Feature",
  "properties": {
    "addr:full":"Siersteenlaan 211 Groningen Groningen 9743 EM",
    "addr:housenumber":"211",
    "addr:postcode":"9743 em",
    "addr:street":"Siersteenlaan",
    "iso:country":"NL",
    "sg:address":"Siersteenlaan 211",
    "sg:city":"Groningen",
    "sg:classifiers":[
        {
            "category":"Food & Beverages",
            "subcategory":"Fruits & Vegetables",
            "type":"Retail Goods"
        }
    ],
    "sg:phone":"+31 50 573 0685",
    "sg:postcode":"9743 EM",
    "sg:province":"Groningen",
    "sg:tags":[
        "groenten"
    ],
    "wof:name":"M F Rasker",
    "wof:placetype":"venue"
},
  "geometry": {"coordinates":[6.526775,53.225674],"type":"Point"}
}