{
  "type": "Feature",
  "properties": {
    "addr:full":"Bunderstr 59 Meerssen Limburg 6231 EH",
    "addr:housenumber":"59",
    "addr:postcode":"6231 eh",
    "addr:street":"Bunderstr",
    "iso:country":"NL",
    "sg:address":"Bunderstr 59",
    "sg:city":"Meerssen",
    "sg:orig_category":"Banken",
    "sg:phone":"+31 43 358 6311",
    "sg:postcode":"6231 EH",
    "sg:province":"Limburg",
    "sg:website":"http://www.sns.nl",
    "wof:name":"Sns",
    "wof:placetype":"venue"
},
  "geometry": {"coordinates":[5.749881,50.885326],"type":"Point"}
}