{
  "type": "Feature",
  "properties": {
    "addr:full":"Hoefslag 70 Nykerk Gld Gelderland 3862 KC",
    "addr:housenumber":"70",
    "addr:postcode":"3862 kc",
    "addr:street":"Hoefslag;Gld Gelderland",
    "iso:country":"NL",
    "sg:address":"Hoefslag 70",
    "sg:city":"Nykerk Gld",
    "sg:orig_category":"Kappers",
    "sg:phone":"+31 33 245 4132",
    "sg:postcode":"3862 KC",
    "sg:province":"Gelderland",
    "wof:name":"Mieke",
    "wof:placetype":"venue"
},
  "geometry": {"coordinates":[5.51415,52.21376],"type":"Point"}
}