{
  "type": "Feature",
  "properties": {
    "addr:full":"Pannekoekstr 83A Rotterdam Zuid-Holland 3011 LD",
    "addr:housenumber":"83a",
    "addr:postcode":"3011 ld",
    "addr:street":"Pannekoekstr",
    "iso:country":"NL",
    "sg:address":"Pannekoekstr 83A",
    "sg:city":"Rotterdam",
    "sg:orig_category":"Modeontwerpen",
    "sg:phone":"+31 10 414 3138",
    "sg:postcode":"3011 LD",
    "sg:province":"Zuid-Holland",
    "sg:website":"http://www.dutchfashiondesigners.com",
    "wof:name":"Aspirations",
    "wof:placetype":"venue"
},
  "geometry": {"coordinates":[4.488512,51.922188],"type":"Point"}
}