{
  "type": "Feature",
  "properties": {
    "addr:full":"Marktln 21 Hoofddorp North Holland 2132 DL",
    "addr:housenumber":"21",
    "addr:postcode":"2132 dl",
    "addr:street":"Marktln",
    "iso:country":"NL",
    "sg:address":"Marktln 21",
    "sg:city":"Hoofddorp",
    "sg:orig_category":"Logopedisten",
    "sg:phone":"+31 23 563 6933",
    "sg:postcode":"2132 DL",
    "sg:province":"North Holland",
    "wof:name":"Logopediepraktijk Hoofddorp Centrum",
    "wof:placetype":"venue"
},
  "geometry": {"coordinates":[4.69296,52.305393],"type":"Point"}
}