{
  "type": "Feature",
  "properties": {
    "addr:full":"Prins Bernhardstraat 2 Asten North Brabant 5721 GC",
    "addr:housenumber":"2",
    "addr:postcode":"5721 gc",
    "addr:street":"Prins Bernhardstraat",
    "iso:country":"NL",
    "sg:address":"Prins Bernhardstraat 2",
    "sg:city":"Asten",
    "sg:orig_category":"Werving And Selectie Van Tijdelijk Personeel And Uitzendkantoren",
    "sg:phone":"+31 493 698 181",
    "sg:postcode":"5721 GC",
    "sg:province":"North Brabant",
    "wof:name":"Randstad",
    "wof:placetype":"venue"
},
  "geometry": {"coordinates":[5.7462420464,51.4045982361],"type":"Point"}
}