{
  "type": "Feature",
  "properties": {
    "addr:full":"Gasthuisstr 23A Heerlen Limburg 6411 KD",
    "addr:housenumber":"23a",
    "addr:postcode":"6411 kd",
    "addr:street":"Gasthuisstr",
    "iso:country":"NL",
    "sg:address":"Gasthuisstr 23A",
    "sg:city":"Heerlen",
    "sg:orig_category":"Makelaars En Adviseurs Onroerende Goederen",
    "sg:phone":"+31 45 560 0025",
    "sg:postcode":"6411 KD",
    "sg:province":"Limburg",
    "wof:name":"Ernens",
    "wof:placetype":"venue"
},
  "geometry": {"coordinates":[5.982827,50.888145],"type":"Point"}
}