{
  "type": "Feature",
  "properties": {
    "addr:full":"Harderwykerwg 201 Ermelo Gelderland 3852 AC",
    "addr:housenumber":"201",
    "addr:postcode":"3852 ac",
    "addr:street":"Gelderland",
    "iso:country":"NL",
    "sg:address":"Harderwykerwg 201",
    "sg:city":"Ermelo",
    "sg:orig_category":"Medische Keuringen",
    "sg:phone":"+31 341 418 907",
    "sg:postcode":"3852 AC",
    "sg:province":"Gelderland",
    "wof:name":"Ngab",
    "wof:placetype":"venue"
},
  "geometry": {"coordinates":[5.621414,52.324345],"type":"Point"}
}