{
  "type": "Feature",
  "properties": {
    "addr:full":"Keizerstraat 63 Den Helder North Holland 1781 GE",
    "addr:housenumber":"63",
    "addr:postcode":"1781",
    "addr:street":"Keizerstraat",
    "iso:country":"NL",
    "sg:address":"Keizerstraat 63",
    "sg:city":"Den Helder",
    "sg:orig_category":"Fotozaken",
    "sg:phone":"+31 223 684 600",
    "sg:postcode":"1781 GE",
    "sg:province":"North Holland",
    "wof:name":"Combi Den Helder",
    "wof:placetype":"venue"
},
  "geometry": {"coordinates":[4.763953,52.957863],"type":"Point"}
}