{
  "type": "Feature",
  "properties": {
    "addr:full":"De Compagnie 45 Zwaag Noord-Holland 1689 AG",
    "addr:housenumber":"45",
    "addr:postcode":"1689",
    "addr:street":"De Compagnie",
    "iso:country":"NL",
    "sg:address":"De Compagnie 45",
    "sg:city":"Zwaag",
    "sg:orig_category":"Kansspelen",
    "sg:phone":"+31 229 216 080",
    "sg:postcode":"1689 AG",
    "sg:province":"Noord-Holland",
    "wof:name":"Vof Komeet Flamingo",
    "wof:placetype":"venue"
},
  "geometry": {"coordinates":[5.0565800667,52.6712646484],"type":"Point"}
}