{
  "type": "Feature",
  "properties": {
    "iso:country":"NL",
    "sg:address":"H Jonaspln 6",
    "sg:city":"Kerkrade",
    "sg:orig_category":"Verzekeringen - Verzekeringskantoren",
    "sg:phone":"+31 45 545 2249",
    "sg:postcode":"6462 CR",
    "sg:province":"Limburg",
    "wof:name":"Derix",
    "wof:placetype":"venue"
},
  "geometry": {"coordinates":[6.068958,50.851868],"type":"Point"}
}