{
  "type": "Feature",
  "properties": {
    "addr:full":"Dotterbloem 17 Scheemda Groningen 9679 MA",
    "addr:housenumber":"17",
    "addr:postcode":"9679 ma",
    "addr:street":"Dotterbloem",
    "iso:country":"NL",
    "sg:address":"Dotterbloem 17",
    "sg:city":"Scheemda",
    "sg:orig_category":"Bedrijfs- And Managementsconsultants",
    "sg:phone":"+31 597 591 131",
    "sg:postcode":"9679 MA",
    "sg:province":"Groningen",
    "wof:name":"D.Bosker Management Bv",
    "wof:placetype":"venue"
},
  "geometry": {"coordinates":[6.982554,53.172951],"type":"Point"}
}