{
  "type": "Feature",
  "properties": {
    "addr:full":"Skans 1 Winsum Fr Friesland 8831 XS",
    "addr:housenumber":"1",
    "addr:postcode":"8831 xs",
    "addr:street":"Skans",
    "iso:country":"NL",
    "sg:address":"Skans 1",
    "sg:city":"Winsum Fr",
    "sg:orig_category":"Cafetaria'S",
    "sg:phone":"+31 517 341 232",
    "sg:postcode":"8831 XS",
    "sg:province":"Friesland",
    "wof:name":"Driesprong, De",
    "wof:placetype":"venue"
},
  "geometry": {"coordinates":[5.632524,53.152363],"type":"Point"}
}