{
  "type": "Feature",
  "properties": {
    "addr:full":"Herenstraat 23 Voorhout Zuid-Holland 2215 KB",
    "addr:housenumber":"23",
    "addr:postcode":"2215 kb",
    "addr:street":"Herenstraat",
    "iso:country":"NL",
    "sg:address":"Herenstraat 23",
    "sg:city":"Voorhout",
    "sg:orig_category":"Damesmodezaken",
    "sg:phone":"+31 252 211 604",
    "sg:postcode":"2215 KB",
    "sg:province":"Zuid-Holland",
    "wof:name":"Noordermeer Mode",
    "wof:placetype":"venue"
},
  "geometry": {"coordinates":[4.479894,52.220062],"type":"Point"}
}