{
  "type": "Feature",
  "properties": {
    "addr:full":"De Merodeln 30 Ridderkerk Zuid-Holland 2985 BD",
    "addr:housenumber":"30",
    "addr:postcode":"2985 bd",
    "iso:country":"NL",
    "sg:address":"De Merodeln 30",
    "sg:city":"Ridderkerk",
    "sg:orig_category":"Administratie- En Boekhoudkantoren",
    "sg:phone":"+31 180 423 076",
    "sg:postcode":"2985 BD",
    "sg:province":"Zuid-Holland",
    "wof:name":"Hofmans",
    "wof:placetype":"venue"
},
  "geometry": {"coordinates":[4.604044,51.86113],"type":"Point"}
}