{
  "type": "Feature",
  "properties": {
    "addr:full":"Ringbaan W 306C Tilburg Noord-Brabant 5025 VB",
    "addr:housenumber":"306c",
    "addr:postcode":"5025 vb",
    "addr:street":"Ringbaan W",
    "iso:country":"NL",
    "sg:address":"Ringbaan W 306C",
    "sg:city":"Tilburg",
    "sg:orig_category":"Architecten En Architectenbureaus",
    "sg:phone":"+31 13 468 1070",
    "sg:postcode":"5025 VB",
    "sg:province":"Noord-Brabant",
    "sg:website":"http://www.charcoal.nl",
    "wof:name":"Hout En Kolen, Van Den",
    "wof:placetype":"venue"
},
  "geometry": {"coordinates":[5.061867,51.55196],"type":"Point"}
}