{
  "type": "Feature",
  "properties": {
    "addr:full":"Liesveldsestg 19 Brakel Gelderland 5306 EX",
    "addr:housenumber":"19",
    "addr:postcode":"5306 ex",
    "addr:street":"Liesveldsestg;Gelderland",
    "iso:country":"NL",
    "sg:address":"Liesveldsestg 19",
    "sg:city":"Brakel",
    "sg:orig_category":"Voetverzorging",
    "sg:phone":"+31 418 677 142",
    "sg:postcode":"5306 EX",
    "sg:province":"Gelderland",
    "wof:name":"Langebeeke, G P",
    "wof:placetype":"venue"
},
  "geometry": {"coordinates":[5.111674,51.813972],"type":"Point"}
}