{
  "type": "Feature",
  "properties": {
    "addr:full":"Langedreef 5 Zuiddorpe Zeeland 4574 NK",
    "addr:housenumber":"5",
    "addr:postcode":"4574 nk",
    "addr:street":"Langedreef",
    "iso:country":"NL",
    "sg:address":"Langedreef 5",
    "sg:city":"Zuiddorpe",
    "sg:orig_category":"Kappers",
    "sg:phone":"+31 115 608 217",
    "sg:postcode":"4574 NK",
    "sg:province":"Zeeland",
    "wof:name":"O D M De Ridder-Vervaet",
    "wof:placetype":"venue"
},
  "geometry": {"coordinates":[3.864664,51.216457],"type":"Point"}
}