{
  "type": "Feature",
  "properties": {
    "addr:full":"S Gravelandsewg 80 Hilversum Noord-Holland 1217 EW",
    "addr:housenumber":"80",
    "addr:postcode":"1217 ew",
    "iso:country":"NL",
    "sg:address":"S Gravelandsewg 80",
    "sg:city":"Hilversum",
    "sg:orig_category":"Omroep",
    "sg:phone":"+31 35 671 3911",
    "sg:postcode":"1217 EW",
    "sg:province":"Noord-Holland",
    "sg:website":"http://www.omroep.nl/kro",
    "wof:name":"Kro",
    "wof:placetype":"venue"
},
  "geometry": {"coordinates":[5.162974,52.230656],"type":"Point"}
}