{
  "type": "Feature",
  "properties": {
    "iso:country":"NL",
    "sg:address":"Reiger 10",
    "sg:city":"Hoorn Nh",
    "sg:orig_category":"Boekenuitgeverijen",
    "sg:phone":"+31 229 248 610",
    "sg:postcode":"1628 BA",
    "sg:province":"Noord-Holland",
    "wof:name":"Mpa Amsterdam Vof",
    "wof:placetype":"venue"
},
  "geometry": {"coordinates":[5.079901,52.654366],"type":"Point"}
}