{
  "type": "Feature",
  "properties": {
    "addr:full":"De Elzen 22 Veenwouden Provincie Friesland 9269 SK",
    "addr:housenumber":"22;9269",
    "addr:street":"De Elzen;Provincie Friesland",
    "iso:country":"NL",
    "sg:address":"De Elzen 22",
    "sg:city":"Veenwouden",
    "sg:orig_category":"Betonijzervlechten",
    "sg:phone":"+31 511 447 276",
    "sg:postcode":"9269 SK",
    "sg:province":"Provincie Friesland",
    "sg:website":"http://www.taekema.nl",
    "wof:name":"Taekema Bv",
    "wof:placetype":"venue"
},
  "geometry": {"coordinates":[5.996355,53.244164],"type":"Point"}
}