{
  "type": "Feature",
  "properties": {
    "iso:country":"NL",
    "sg:address":"Dr Hoijngstraat 5",
    "sg:city":"Bemmel",
    "sg:classifiers":[
        {
            "category":"Education",
            "subcategory":"Preschool",
            "type":"Public Place"
        }
    ],
    "sg:phone":"+31 481 464 694",
    "sg:postcode":"6681 XL",
    "sg:province":"Gelderland",
    "sg:tags":[
        "kleuteronderwijs",
        "basis-"
    ],
    "wof:name":"Mariaschool",
    "wof:placetype":"venue"
},
  "geometry": {"coordinates":[5.904272,51.891895],"type":"Point"}
}