{
  "type": "Feature",
  "properties": {
    "addr:full":"Veilingweg 21 Bovenkarspel North Holland 1611 BN",
    "addr:housenumber":"21",
    "addr:postcode":"1611 bn",
    "addr:street":"Veilingweg",
    "iso:country":"NL",
    "sg:address":"Veilingweg 21",
    "sg:city":"Bovenkarspel",
    "sg:orig_category":"Recreatie",
    "sg:phone":"+31 228 516 925",
    "sg:postcode":"1611 BN",
    "sg:province":"North Holland",
    "wof:name":"Recreatiecentrum Streekbos",
    "wof:placetype":"venue"
},
  "geometry": {"coordinates":[5.250998,52.699642],"type":"Point"}
}