{
  "type": "Feature",
  "properties": {
    "addr:full":"Akerstraat 54 Kerkrade Limburg 6466 HK",
    "addr:housenumber":"54",
    "addr:postcode":"6466 hk",
    "addr:street":"Akerstraat",
    "iso:country":"NL",
    "sg:address":"Akerstraat 54",
    "sg:city":"Kerkrade",
    "sg:orig_category":"Munten En Penningen",
    "sg:phone":"+31 45 542 5758",
    "sg:postcode":"6466 HK",
    "sg:province":"Limburg",
    "wof:name":"Vossen, Tom",
    "wof:placetype":"venue"
},
  "geometry": {"coordinates":[6.026399,50.857372],"type":"Point"}
}