{
  "type": "Feature",
  "properties": {
    "iso:country":"NL",
    "sg:address":"De Voorn 8",
    "sg:city":"Makkum Fr",
    "sg:orig_category":"Stukadoorsbedrijven",
    "sg:phone":"+31 515 233 669",
    "sg:postcode":"8754 BB",
    "sg:province":"Provincie Friesland",
    "sg:website":"http://www.stucadoorsbedrijfgaasbeek.nl",
    "wof:name":"Gaasbeek, S R",
    "wof:placetype":"venue"
},
  "geometry": {"coordinates":[5.408357,53.06039],"type":"Point"}
}