{
  "type": "Feature",
  "properties": {
    "addr:full":"Westerkade 30 Utrecht Utrecht 3511 HC",
    "addr:housenumber":"30",
    "addr:postcode":"3511 hc",
    "addr:street":"Westerkade",
    "iso:country":"NL",
    "sg:address":"Westerkade 30",
    "sg:city":"Utrecht",
    "sg:orig_category":"Drukkerijen And Copyshops",
    "sg:phone":"+31 30 231 7880",
    "sg:postcode":"3511 HC",
    "sg:province":"Utrecht",
    "wof:name":"Drukkerij Usp Bv",
    "wof:placetype":"venue"
},
  "geometry": {"coordinates":[5.12242,52.079426],"type":"Point"}
}