{
  "type": "Feature",
  "properties": {
    "addr:full":"Ruitenbergln 25 Arnhem Gelderland 6826 CC",
    "addr:housenumber":"25",
    "addr:postcode":"6826 cc",
    "addr:street":"Ruitenbergln",
    "iso:country":"NL",
    "sg:address":"Ruitenbergln 25",
    "sg:city":"Arnhem",
    "sg:classifiers":[
        {
            "category":"Education",
            "subcategory":"School",
            "type":"Public Place"
        }
    ],
    "sg:phone":"+31 26 369 1800",
    "sg:postcode":"6826 CC",
    "sg:province":"Gelderland",
    "sg:tags":[
        "studiebegeleiding",
        "en",
        "school-"
    ],
    "sg:website":"http://www.marant-ed.nl",
    "wof:name":"Marant",
    "wof:placetype":"venue"
},
  "geometry": {"coordinates":[5.94946,51.988098],"type":"Point"}
}