{
  "type": "Feature",
  "properties": {
    "addr:full":"Koningshoek 92053 Maassluis Friesland 3144 BA",
    "addr:housenumber":"92053",
    "addr:postcode":"3144 ba",
    "addr:street":"Koningshoek",
    "iso:country":"NL",
    "sg:address":"Koningshoek 92053",
    "sg:city":"Maassluis",
    "sg:orig_category":"Opticiens",
    "sg:phone":"+31 10 591 9039",
    "sg:postcode":"3144 BA",
    "sg:province":"Friesland",
    "sg:website":"http://www.hethuis.nl",
    "wof:name":"Huis Argus, Het",
    "wof:placetype":"venue"
},
  "geometry": {"coordinates":[4.240003109,51.9278640747],"type":"Point"}
}