{
  "type": "Feature",
  "properties": {
    "addr:full":"Adelaar 105 Oss Noord-Brabant 5348 EJ",
    "addr:housenumber":"105",
    "addr:postcode":"5348 ej",
    "addr:street":"Adelaar",
    "iso:country":"NL",
    "sg:address":"Adelaar 105",
    "sg:city":"Oss",
    "sg:orig_category":"Adviesbureaus Financieel",
    "sg:phone":"+31 412 645 727",
    "sg:postcode":"5348 EJ",
    "sg:province":"Noord-Brabant",
    "wof:name":"Sherha Bv",
    "wof:placetype":"venue"
},
  "geometry": {"coordinates":[-77.235214,38.312599],"type":"Point"}
}