{
  "type": "Feature",
  "properties": {
    "addr:full":"Wycker Grachtstr 38 Maastricht Limburg 6221 CX",
    "addr:housenumber":"38",
    "addr:postcode":"6221 cx",
    "addr:street":"Wycker",
    "iso:country":"NL",
    "sg:address":"Wycker Grachtstr 38",
    "sg:city":"Maastricht",
    "sg:orig_category":"Werving En Selectie",
    "sg:phone":"+31 43 350 2999",
    "sg:postcode":"6221 CX",
    "sg:province":"Limburg",
    "sg:website":"http://www.pruijs.nl",
    "wof:name":"Pruijs & Partners",
    "wof:placetype":"venue"
},
  "geometry": {"coordinates":[5.699326992,50.8478050232],"type":"Point"}
}