{
  "type": "Feature",
  "properties": {
    "iso:country":"NL",
    "sg:address":"Willibrordusstr 10",
    "sg:city":"Buren Fr",
    "sg:orig_category":"Groepsaccommodaties",
    "sg:phone":"+31 519 542 053",
    "sg:postcode":"9164 KV",
    "sg:province":"Friesland",
    "wof:name":"Kienstra Hoeve",
    "wof:placetype":"venue"
},
  "geometry": {"coordinates":[5.798379,53.445763],"type":"Point"}
}