{
  "type": "Feature",
  "properties": {
    "addr:full":"Herengr 10 Leiden Zuid-Holland 2312 LD",
    "addr:housenumber":"10",
    "addr:postcode":"2312 ld",
    "addr:street":"Herengr",
    "iso:country":"NL",
    "sg:address":"Herengr 10",
    "sg:city":"Leiden",
    "sg:orig_category":"Verhuur",
    "sg:phone":"+31 71 514 9281",
    "sg:postcode":"2312 LD",
    "sg:province":"Zuid-Holland",
    "wof:name":"Amuse Kiddy-Rides Bv",
    "wof:placetype":"venue"
},
  "geometry": {"coordinates":[4.498756,52.156647],"type":"Point"}
}