{
  "type": "Feature",
  "properties": {
    "addr:full":"Beukvaren 39 Bergschenhoek Zuid-Holland 2661 PE",
    "addr:housenumber":"39",
    "addr:postcode":"2661 pe",
    "addr:street":"Beukvaren",
    "iso:country":"NL",
    "sg:address":"Beukvaren 39",
    "sg:city":"Bergschenhoek",
    "sg:orig_category":"Adviesbureaus Bouwkunde",
    "sg:phone":"+31 10 521 4723",
    "sg:postcode":"2661 PE",
    "sg:province":"Zuid-Holland",
    "wof:name":"Berg Bv, M D Van Den",
    "wof:placetype":"venue"
},
  "geometry": {"coordinates":[4.495058,51.995979],"type":"Point"}
}