{
  "type": "Feature",
  "properties": {
    "iso:country":"NL",
    "sg:address":"Maasln 10",
    "sg:city":"Bergen Op Zoom",
    "sg:orig_category":"Scholen Voor Basisonderwijs",
    "sg:phone":"+31 164 233 839",
    "sg:postcode":"4615 BP",
    "sg:province":"Noord-Brabant",
    "sg:website":"http://www.3mastersbo.nl",
    "wof:name":"Driemaster Sbo, De",
    "wof:placetype":"venue"
},
  "geometry": {"coordinates":[4.281987,51.495953],"type":"Point"}
}