{
  "type": "Feature",
  "properties": {
    "addr:full":"Vondelln 60-62 Utrecht Utrecht 3521 GH",
    "addr:housenumber":"60-62",
    "addr:postcode":"3521 gh",
    "iso:country":"NL",
    "sg:address":"Vondelln 60-62",
    "sg:city":"Utrecht",
    "sg:orig_category":"Administratie- En Boekhoudkantoren",
    "sg:phone":"+31 30 281 9755",
    "sg:postcode":"3521 GH",
    "sg:province":"Utrecht",
    "sg:website":"http://www.gbml.nl",
    "wof:name":"Gbml",
    "wof:placetype":"venue"
},
  "geometry": {"coordinates":[5.11037,52.084572],"type":"Point"}
}