{
  "type": "Feature",
  "properties": {
    "iso:country":"NL",
    "sg:address":"Binnenhof 51",
    "sg:city":"Almelo",
    "sg:orig_category":"Peuterspeelzalen",
    "sg:phone":"+31 546 490 526",
    "sg:postcode":"7608 KH",
    "sg:province":"Overijssel",
    "wof:name":"Hummelburcht, De",
    "wof:placetype":"venue"
},
  "geometry": {"coordinates":[6.676725,52.378757],"type":"Point"}
}