{
  "type": "Feature",
  "properties": {
    "addr:full":"Schraleweidsestraat 3 Groessen Gelderland 6923 SG",
    "addr:housenumber":"3",
    "addr:postcode":"6923",
    "addr:street":"Schraleweidsestraat;Gelderland",
    "iso:country":"NL",
    "sg:address":"Schraleweidsestraat 3",
    "sg:city":"Groessen",
    "sg:classifiers":[
        {
            "category":"Food & Beverages",
            "subcategory":"Fruits & Vegetables",
            "type":"Retail Goods"
        }
    ],
    "sg:phone":"+31 316 343 687",
    "sg:postcode":"6923 SG",
    "sg:province":"Gelderland",
    "sg:tags":[
        "groenten"
    ],
    "wof:name":"De Stokhorst",
    "wof:placetype":"venue"
},
  "geometry": {"coordinates":[6.021641,51.924992],"type":"Point"}
}