{
  "type": "Feature",
  "properties": {
    "iso:country":"NL",
    "sg:address":"Schutstraat 17",
    "sg:city":"Hoogeveen",
    "sg:orig_category":"Meubelzaken, Woning- And Keukeninrichting",
    "sg:phone":"+31 528 263 961",
    "sg:postcode":"7907 CA",
    "sg:province":"Provincie Drenthe",
    "wof:name":"Giraffe Bv",
    "wof:placetype":"venue"
},
  "geometry": {"coordinates":[6.476612,52.720135],"type":"Point"}
}