{
  "type": "Feature",
  "properties": {
    "addr:full":"Pr Constantynwg 2 Capelle Ad Yssel Zuid-Holland 2906 ZC",
    "addr:housenumber":"2",
    "addr:postcode":"2906 zc",
    "iso:country":"NL",
    "sg:address":"Pr Constantynwg 2",
    "sg:city":"Capelle Ad Yssel",
    "sg:orig_category":"Ziekenhuizen, Sanatoria, Verpleeghuizen",
    "sg:phone":"+31 10 258 5000",
    "sg:postcode":"2906 ZC",
    "sg:province":"Zuid-Holland",
    "wof:name":"Ijsselland",
    "wof:placetype":"venue"
},
  "geometry": {"coordinates":[4.57061,51.936211],"type":"Point"}
}