{
  "type": "Feature",
  "properties": {
    "addr:full":"Laan Van Meerdervoort 985 'S Gravenhage Zuid-Holland 2564 AJ",
    "addr:housenumber":"985 '",
    "addr:postcode":"2564 aj",
    "addr:street":"Laan Van Meerdervoort",
    "iso:country":"NL",
    "sg:address":"Laan Van Meerdervoort 985",
    "sg:city":"'S Gravenhage",
    "sg:orig_category":"Verzekeringen",
    "sg:phone":"+31 70 368 1379",
    "sg:postcode":"2564 AJ",
    "sg:province":"Zuid-Holland",
    "wof:name":"Ass Kant J W Swart Cv",
    "wof:placetype":"venue"
},
  "geometry": {"coordinates":[4.247949,52.068577],"type":"Point"}
}