{
  "type": "Feature",
  "properties": {
    "addr:full":"Crooswyksebocht 10A Rotterdam South Holland 3034 NA",
    "addr:housenumber":"10a",
    "addr:postcode":"3034 na",
    "addr:street":"Crooswyksebocht",
    "iso:country":"NL",
    "sg:address":"Crooswyksebocht 10A",
    "sg:city":"Rotterdam",
    "sg:orig_category":"Plaatwerk",
    "sg:phone":"+31 10 412 5853",
    "sg:postcode":"3034 NA",
    "sg:province":"South Holland",
    "wof:name":"Chaboo",
    "wof:placetype":"venue"
},
  "geometry": {"coordinates":[4.48936,51.935966],"type":"Point"}
}