{
  "type": "Feature",
  "properties": {
    "addr:full":"Slotlaan 297 Zeist Utrecht 3701 GJ",
    "addr:housenumber":"297",
    "addr:postcode":"3701 gj",
    "addr:street":"Slotlaan",
    "iso:country":"NL",
    "sg:address":"Slotlaan 297",
    "sg:city":"Zeist",
    "sg:orig_category":"Juweliers",
    "sg:phone":"+31 30 691 4157",
    "sg:postcode":"3701 GJ",
    "sg:province":"Utrecht",
    "wof:name":"Juweliersbedrijf Eggersman Bv",
    "wof:placetype":"venue"
},
  "geometry": {"coordinates":[5.247818,52.088432],"type":"Point"}
}