{
  "type": "Feature",
  "properties": {
    "addr:full":"Hoofdweg 24 Wedde Groningen 9698 AE",
    "addr:housenumber":"24",
    "addr:postcode":"9698 ae",
    "addr:street":"Hoofdweg",
    "iso:country":"NL",
    "sg:address":"Hoofdweg 24",
    "sg:city":"Wedde",
    "sg:orig_category":"Banken And Kredietinstellingen",
    "sg:phone":"+31 597 562 814",
    "sg:postcode":"9698 AE",
    "sg:province":"Groningen",
    "wof:name":"Rabobank",
    "wof:placetype":"venue"
},
  "geometry": {"coordinates":[7.074975,53.068836],"type":"Point"}
}