{
  "type": "Feature",
  "properties": {
    "iso:country":"NL",
    "sg:address":"Rapenburg 43",
    "sg:city":"Leiden",
    "sg:orig_category":"Notarissen En Notariskantoren",
    "sg:phone":"+31 71 513 1645",
    "sg:postcode":"2311 GG",
    "sg:province":"Zuid-Holland",
    "wof:name":"Meiners",
    "wof:placetype":"venue"
},
  "geometry": {"coordinates":[4.484755,52.158558],"type":"Point"}
}