{
  "type": "Feature",
  "properties": {
    "iso:country":"NL",
    "sg:address":"Roggeakker 14",
    "sg:city":"Wezep",
    "sg:classifiers":[
        {
            "category":"Personal",
            "subcategory":"Nail Salon",
            "type":"Services"
        }
    ],
    "sg:phone":"+31 38 376 5991",
    "sg:postcode":"8091 NH",
    "sg:province":"Gelderland",
    "sg:tags":[
        "pedicure"
    ],
    "wof:name":"Diepen-Wolf, G Van",
    "wof:placetype":"venue"
},
  "geometry": {"coordinates":[5.990356,52.456108],"type":"Point"}
}