{
  "type": "Feature",
  "properties": {
    "iso:country":"NL",
    "sg:address":"Lindenln 2",
    "sg:city":"Ede",
    "sg:orig_category":"Kappers",
    "sg:phone":"+31 318 612 320",
    "sg:postcode":"6711 MT",
    "sg:province":"Gelderland",
    "wof:name":"Kok, W J",
    "wof:placetype":"venue"
},
  "geometry": {"coordinates":[5.668462,52.03944],"type":"Point"}
}