{
  "type": "Feature",
  "properties": {
    "iso:country":"NL",
    "sg:address":"Utrechtsewg 69B",
    "sg:city":"Amersfoort",
    "sg:orig_category":"Honden- En Kattentrimsalons",
    "sg:phone":"+31 33 465 4467",
    "sg:postcode":"3818 EB",
    "sg:province":"Utrecht",
    "wof:name":"Knappe Hond, De",
    "wof:placetype":"venue"
},
  "geometry": {"coordinates":[5.378656,52.1502],"type":"Point"}
}