{
  "type": "Feature",
  "properties": {
    "addr:full":"Bornsestraat 50 Hengelo Ov Overijssel 7556 BG",
    "addr:housenumber":"50",
    "addr:postcode":"7556",
    "addr:street":"Bornsestraat;Ov",
    "iso:country":"NL",
    "sg:address":"Bornsestraat 50",
    "sg:city":"Hengelo Ov",
    "sg:orig_category":"Medische Apparatuur And Prothesen Fab",
    "sg:phone":"+31 74 291 7919",
    "sg:postcode":"7556 BG",
    "sg:province":"Overijssel",
    "wof:name":"L. De Haan Hoorapparaten Twenthe Bv",
    "wof:placetype":"venue"
},
  "geometry": {"coordinates":[6.791242,52.269238],"type":"Point"}
}