{
  "type": "Feature",
  "properties": {
    "iso:country":"NL",
    "sg:address":"Handelswg 13",
    "sg:city":"Bunschoten Spakenb",
    "sg:orig_category":"Poeliers",
    "sg:phone":"+31 33 246 3772",
    "sg:postcode":"3751 LR",
    "sg:province":"Utrecht",
    "wof:name":"Twillert & Koster Poeliers En Fileerbedrijf, Van",
    "wof:placetype":"venue"
},
  "geometry": {"coordinates":[5.37908,52.231113],"type":"Point"}
}