{
  "type": "Feature",
  "properties": {
    "addr:full":"Lonnekerbrugstr 120 Enschede Overijssel 7547 AM",
    "addr:housenumber":"120",
    "addr:postcode":"7547",
    "iso:country":"NL",
    "sg:address":"Lonnekerbrugstr 120",
    "sg:city":"Enschede",
    "sg:orig_category":"Kamerverhuur En -Bemiddeling",
    "sg:phone":"+31 53 436 4536",
    "sg:postcode":"7547 AM",
    "sg:province":"Overijssel",
    "wof:name":"Rabon Bv",
    "wof:placetype":"venue"
},
  "geometry": {"coordinates":[6.8492307663,52.2303161621],"type":"Point"}
}