{
  "type": "Feature",
  "properties": {
    "addr:full":"Hoofdstr 122 Hoogeveen Drenthe 7901 JV",
    "addr:housenumber":"122",
    "addr:postcode":"7901 jv",
    "iso:country":"NL",
    "sg:address":"Hoofdstr 122",
    "sg:city":"Hoogeveen",
    "sg:orig_category":"Projectinrichting",
    "sg:phone":"+31 528 265 131",
    "sg:postcode":"7901 JV",
    "sg:province":"Drenthe",
    "sg:website":"http://www.cpet.nl",
    "wof:name":"Pet Bv, C",
    "wof:placetype":"venue"
},
  "geometry": {"coordinates":[6.477578,52.7239],"type":"Point"}
}