{
  "type": "Feature",
  "properties": {
    "addr:full":"Binckhorstlaan 3 Voorburg Zuid-Holland 2275 VK",
    "addr:housenumber":"3",
    "addr:postcode":"2275 vk",
    "addr:street":"Binckhorstlaan",
    "iso:country":"NL",
    "sg:address":"Binckhorstlaan 3",
    "sg:city":"Voorburg",
    "sg:orig_category":"Verzekeringen",
    "sg:phone":"+31 70 327 1919",
    "sg:postcode":"2275 VK",
    "sg:province":"Zuid-Holland",
    "wof:name":"Poliskring Brabant West Bv",
    "wof:placetype":"venue"
},
  "geometry": {"coordinates":[4.345684,52.061302],"type":"Point"}
}