{
  "type": "Feature",
  "properties": {
    "addr:full":"J Lievensplnts 6 Rynsburg Zuid-Holland 2231 BS",
    "addr:housenumber":"6",
    "addr:postcode":"2231 bs",
    "iso:country":"NL",
    "sg:address":"J Lievensplnts 6",
    "sg:city":"Rynsburg",
    "sg:orig_category":"Adviesbureaus Bedrijfsorganisatie",
    "sg:phone":"+31 71 408 2714",
    "sg:postcode":"2231 BS",
    "sg:province":"Zuid-Holland",
    "wof:name":"Winsas Special Service Bv",
    "wof:placetype":"venue"
},
  "geometry": {"coordinates":[4.443285,52.1884],"type":"Point"}
}