{
  "type": "Feature",
  "properties": {
    "addr:full":"Haarlemmerstraat 84 Leiden South Holland 2312 GD",
    "addr:housenumber":"84",
    "addr:postcode":"2312 gd",
    "addr:street":"Haarlemmerstraat",
    "iso:country":"NL",
    "sg:address":"Haarlemmerstraat 84",
    "sg:city":"Leiden",
    "sg:orig_category":"Herenmodezaken",
    "sg:phone":"+31 71 514 9540",
    "sg:postcode":"2312 GD",
    "sg:province":"South Holland",
    "wof:name":"Bv Boetiek De Saint",
    "wof:placetype":"venue"
},
  "geometry": {"coordinates":[4.489943,52.160645],"type":"Point"}
}