{
  "type": "Feature",
  "properties": {
    "addr:full":"Speelhuislaan 38 Breda Noord-Brabant 4815 CG",
    "addr:housenumber":"38",
    "addr:postcode":"4815 cg",
    "addr:street":"Speelhuislaan",
    "iso:country":"NL",
    "sg:address":"Speelhuislaan 38",
    "sg:city":"Breda",
    "sg:classifiers":[
        {
            "category":"Communications",
            "subcategory":"Television Station",
            "type":"Services"
        }
    ],
    "sg:phone":"+31 76 572 0110",
    "sg:postcode":"4815 CG",
    "sg:province":"Noord-Brabant",
    "sg:tags":[
        "video",
        "audio",
        "verhuur"
    ],
    "wof:name":"Videotheek Cult Nextpage",
    "wof:placetype":"venue"
},
  "geometry": {"coordinates":[4.778221,51.596954],"type":"Point"}
}