{
  "type": "Feature",
  "properties": {
    "iso:country":"NL",
    "sg:address":"Binnendongenstr 1",
    "sg:city":"Helmond",
    "sg:orig_category":"Automaterialen En Gereedschappen",
    "sg:phone":"+31 492 535 430",
    "sg:postcode":"5707 TA",
    "sg:province":"North Brabant",
    "wof:name":"Wasser Helmond Bv",
    "wof:placetype":"venue"
},
  "geometry": {"coordinates":[5.639124,51.476028],"type":"Point"}
}