{
  "type": "Feature",
  "properties": {
    "addr:full":"Dorpstr 33 Roermond Limburg 6042 LA",
    "addr:housenumber":"33",
    "addr:postcode":"6042 la",
    "addr:street":"Dorpstr",
    "iso:country":"NL",
    "sg:address":"Dorpstr 33",
    "sg:city":"Roermond",
    "sg:orig_category":"Verpakkingen En Verpakkingsmaterialen",
    "sg:phone":"+31 475 328 561",
    "sg:postcode":"6042 LA",
    "sg:province":"Limburg",
    "sg:website":"http://www.twinpack.nl",
    "wof:name":"Twinpack",
    "wof:placetype":"venue"
},
  "geometry": {"coordinates":[6.05051,51.190048],"type":"Point"}
}