{
  "type": "Feature",
  "properties": {
    "addr:full":"Ingenieur Visstraat 7 Doetinchem Gelderland 7001 CR",
    "addr:housenumber":"7;7001",
    "addr:postcode":"cr",
    "addr:street":"Ingenieur Visstraat;Gelderland",
    "iso:country":"NL",
    "sg:address":"Ingenieur Visstraat 7",
    "sg:city":"Doetinchem",
    "sg:orig_category":"Werving And Selectie Van Vast Personeel",
    "sg:phone":"+31 314 343 689",
    "sg:postcode":"7001 CR",
    "sg:province":"Gelderland",
    "wof:name":"Performens Bv",
    "wof:placetype":"venue"
},
  "geometry": {"coordinates":[6.2851791382,51.9670143127],"type":"Point"}
}