{
  "type": "Feature",
  "properties": {
    "addr:full":"Roggestr 30 Nieuw Vennep North Holland 2153 GC",
    "addr:housenumber":"30",
    "addr:postcode":"2153 gc",
    "addr:street":"Roggestr;Nieuw Vennep North",
    "iso:country":"NL",
    "sg:address":"Roggestr 30",
    "sg:city":"Nieuw Vennep",
    "sg:orig_category":"Wijnkoperijen En -Groothandel",
    "sg:phone":"+31 252 686 741",
    "sg:postcode":"2153 GC",
    "sg:province":"North Holland",
    "wof:name":"Kwast",
    "wof:placetype":"venue"
},
  "geometry": {"coordinates":[4.6437997818,52.2677268982],"type":"Point"}
}