{
  "type": "Feature",
  "properties": {
    "iso:country":"NL",
    "sg:address":"Hoofdstraat 198",
    "sg:city":"Velp",
    "sg:orig_category":"Boekenuitgeverijen",
    "sg:phone":"+31 26 362 0192",
    "sg:postcode":"6881  T",
    "sg:province":"Gelderland",
    "wof:name":"Bruna",
    "wof:placetype":"venue"
},
  "geometry": {"coordinates":[5.971941,51.996037],"type":"Point"}
}