{
  "type": "Feature",
  "properties": {
    "addr:full":"Groene Hilledk 410A Rotterdam South Holland 3075 EE",
    "addr:housenumber":"410a",
    "addr:postcode":"3075 ee",
    "addr:street":"Groene Hilledk",
    "iso:country":"NL",
    "sg:address":"Groene Hilledk 410A",
    "sg:city":"Rotterdam",
    "sg:orig_category":"Acupunctuur",
    "sg:phone":"+31 10 422 0328",
    "sg:postcode":"3075 EE",
    "sg:province":"South Holland",
    "wof:name":"Helwig, A R",
    "wof:placetype":"venue"
},
  "geometry": {"coordinates":[4.506737,51.886814],"type":"Point"}
}