{
  "type": "Feature",
  "properties": {
    "addr:full":"Ijdinkerf 2 Eerbeek Gelderland 6961 MX",
    "addr:housenumber":"2",
    "addr:postcode":"6961 mx",
    "addr:street":"Ijdinkerf;Gelderland",
    "iso:country":"NL",
    "sg:address":"Ijdinkerf 2",
    "sg:city":"Eerbeek",
    "sg:orig_category":"Boekhouders",
    "sg:phone":"+31 313 653 110",
    "sg:postcode":"6961 MX",
    "sg:province":"Gelderland",
    "wof:name":"H.J. Van Sloten",
    "wof:placetype":"venue"
},
  "geometry": {"coordinates":[6.061022,52.110352],"type":"Point"}
}