{
  "type": "Feature",
  "properties": {
    "addr:full":"Veerhaven 4 Rotterdam Zuid-Holland 3016 CJ",
    "addr:housenumber":"4",
    "addr:postcode":"3016 cj",
    "addr:street":"Veerhaven",
    "iso:country":"NL",
    "sg:address":"Veerhaven 4",
    "sg:city":"Rotterdam",
    "sg:orig_category":"Facilitaire Dienstverlening",
    "sg:phone":"+31 10 436 2667",
    "sg:postcode":"3016 CJ",
    "sg:province":"Zuid-Holland",
    "wof:name":"Ifg Intergrale Facilitymanagement Groep Bv",
    "wof:placetype":"venue"
},
  "geometry": {"coordinates":[4.477658,51.907619],"type":"Point"}
}