{
  "type": "Feature",
  "properties": {
    "addr:full":"Oekelsbos 42 Rijsbergen Noord-Brabant 4891 RL",
    "addr:housenumber":"42",
    "addr:postcode":"4891 rl",
    "addr:street":"Oekelsbos",
    "iso:country":"NL",
    "sg:address":"Oekelsbos 42",
    "sg:city":"Rijsbergen",
    "sg:orig_category":"Boekhouders",
    "sg:phone":"+31 76 596 3896",
    "sg:postcode":"4891 RL",
    "sg:province":"Noord-Brabant",
    "wof:name":"Stichting Administratie Kantoor",
    "wof:placetype":"venue"
},
  "geometry": {"coordinates":[4.701162,51.497871],"type":"Point"}
}