{
  "type": "Feature",
  "properties": {
    "iso:country":"NL",
    "sg:address":"J.J.A. Goeverneurstraat 7",
    "sg:city":"Dordrecht",
    "sg:orig_category":"Kappers",
    "sg:phone":"+31 78 614 0636",
    "sg:postcode":"3314 RK",
    "sg:province":"Zuid-Holland",
    "wof:name":"Dameskapsalon H Van Der Kraan-Van Es",
    "wof:placetype":"venue"
},
  "geometry": {"coordinates":[4.6614480019,51.8027267456],"type":"Point"}
}