{
  "type": "Feature",
  "properties": {
    "addr:full":"Dorpsstraat 78 Nootdorp Zuid-Holland 2631 CV",
    "addr:housenumber":"78",
    "addr:postcode":"2631 cv",
    "addr:street":"Dorpsstraat",
    "iso:country":"NL",
    "sg:address":"Dorpsstraat 78",
    "sg:city":"Nootdorp",
    "sg:orig_category":"Huishoudapparatuur, Televisies And Radio'S",
    "sg:phone":"+31 15 310 9319",
    "sg:postcode":"2631 CV",
    "sg:province":"Zuid-Holland",
    "wof:name":"J.C. Oudshoorn En Zoon",
    "wof:placetype":"venue"
},
  "geometry": {"coordinates":[4.397796,52.04425],"type":"Point"}
}