{
  "type": "Feature",
  "properties": {
    "iso:country":"NL",
    "sg:address":"T Harde 44",
    "sg:city":"Haren Gn",
    "sg:orig_category":"Verzekeringen",
    "sg:phone":"+31 50 534 9100",
    "sg:postcode":"9752 VE",
    "sg:province":"Groningen",
    "wof:name":"Bordewijk Assurantien",
    "wof:placetype":"venue"
},
  "geometry": {"coordinates":[6.612036,53.160782],"type":"Point"}
}