{
  "type": "Feature",
  "properties": {
    "addr:full":"Gerbrandystr 56A Vlissingen Zeeland 4384 NJ",
    "addr:housenumber":"56a",
    "addr:postcode":"4384 nj",
    "addr:street":"Gerbrandystr",
    "iso:country":"NL",
    "sg:address":"Gerbrandystr 56A",
    "sg:city":"Vlissingen",
    "sg:orig_category":"Mensendieck - Oefentherapeuten",
    "sg:phone":"+31 118 465 474",
    "sg:postcode":"4384 NJ",
    "sg:province":"Zeeland",
    "wof:name":"Bosga, S A",
    "wof:placetype":"venue"
},
  "geometry": {"coordinates":[3.559024,51.461563],"type":"Point"}
}