{
  "type": "Feature",
  "properties": {
    "addr:full":"Wisselkom 9 Steenbergen Nb Noord-Brabant 4651 WP",
    "addr:housenumber":"9",
    "addr:postcode":"4651 wp",
    "addr:street":"Wisselkom",
    "iso:country":"NL",
    "sg:address":"Wisselkom 9",
    "sg:city":"Steenbergen Nb",
    "sg:classifiers":[
        {
            "category":"Building & Trades",
            "subcategory":"Electrical",
            "type":"Services"
        }
    ],
    "sg:phone":"+31 167 563 682",
    "sg:postcode":"4651 WP",
    "sg:province":"Noord-Brabant",
    "sg:tags":[
        "distributor"
    ],
    "wof:name":"Pro-Traxx",
    "wof:placetype":"venue"
},
  "geometry": {"coordinates":[4.326939,51.592815],"type":"Point"}
}