{
  "type": "Feature",
  "properties": {
    "addr:full":"Da Costakd 58 Utrecht Utrecht 3521 VV",
    "addr:housenumber":"58",
    "addr:postcode":"3521 vv",
    "iso:country":"NL",
    "sg:address":"Da Costakd 58",
    "sg:city":"Utrecht",
    "sg:orig_category":"Artsen - Huisartsen",
    "sg:phone":"+31 30 293 8441",
    "sg:postcode":"3521 VV",
    "sg:province":"Utrecht",
    "wof:name":"Wesselius, A M",
    "wof:placetype":"venue"
},
  "geometry": {"coordinates":[5.11037,52.084572],"type":"Point"}
}