{
  "type": "Feature",
  "properties": {
    "addr:full":"Marykeln 1 Maurik Gelderland 4021 EA",
    "addr:housenumber":"1",
    "addr:postcode":"4021 ea",
    "addr:street":"Marykeln;Gelderland",
    "iso:country":"NL",
    "sg:address":"Marykeln 1",
    "sg:city":"Maurik",
    "sg:orig_category":"Journalisten Freelance",
    "sg:phone":"+31 344 692 177",
    "sg:postcode":"4021 EA",
    "sg:province":"Gelderland",
    "wof:name":"Helmink, J H V",
    "wof:placetype":"venue"
},
  "geometry": {"coordinates":[5.419951,51.962208],"type":"Point"}
}