{
  "type": "Feature",
  "properties": {
    "addr:full":"Kamillelaan 34 Arnhem Gelderland 6833 GL",
    "addr:housenumber":"34",
    "addr:postcode":"6833 gl",
    "addr:street":"Kamillelaan",
    "iso:country":"NL",
    "sg:address":"Kamillelaan 34",
    "sg:city":"Arnhem",
    "sg:orig_category":"Loodgieterswerk, Verwarming And Sanitaire Installaties",
    "sg:phone":"+31 26 321 1398",
    "sg:postcode":"6833 GL",
    "sg:province":"Gelderland",
    "wof:name":"J. Hueting Klussen- En Onderhoudsbedrijf",
    "wof:placetype":"venue"
},
  "geometry": {"coordinates":[5.919897,51.964851],"type":"Point"}
}