{
  "type": "Feature",
  "properties": {
    "iso:country":"NL",
    "sg:address":"Oosterdk 39",
    "sg:city":"Sneek",
    "sg:orig_category":"Adviesbureaus Bedrijfsorganisatie",
    "sg:phone":"+31 515 429 850",
    "sg:postcode":"8601 BP",
    "sg:province":"Friesland",
    "wof:name":"Hamilton Bright",
    "wof:placetype":"venue"
},
  "geometry": {"coordinates":[5.66197,53.033459],"type":"Point"}
}