{
  "type": "Feature",
  "properties": {
    "addr:full":"V Halewynln 264-266 Voorburg Zuid-Holland 2274 TV",
    "addr:postcode":"264-266;2274 tv",
    "iso:country":"NL",
    "sg:address":"V Halewynln 264-266",
    "sg:city":"Voorburg",
    "sg:orig_category":"Wassalons",
    "sg:phone":"+31 70 385 3526",
    "sg:postcode":"2274 TV",
    "sg:province":"Zuid-Holland",
    "wof:name":"Halewijn Wassalon",
    "wof:placetype":"venue"
},
  "geometry": {"coordinates":[4.3495202065,52.0737915039],"type":"Point"}
}