{
  "type": "Feature",
  "properties": {
    "addr:full":"De Stok 4 Roosendaal Noord-Brabant 4703 SZ",
    "addr:housenumber":"4",
    "addr:postcode":"4703 sz",
    "addr:street":"De Stok",
    "iso:country":"NL",
    "sg:address":"De Stok 4",
    "sg:city":"Roosendaal",
    "sg:orig_category":"Sportcentra",
    "sg:phone":"+31 165 545 898",
    "sg:postcode":"4703 SZ",
    "sg:province":"Noord-Brabant",
    "wof:name":"Sieben Rekreatie C.V.",
    "wof:placetype":"venue"
},
  "geometry": {"coordinates":[4.432445,51.536095],"type":"Point"}
}