{
  "type": "Feature",
  "properties": {
    "addr:full":"Hoofdstr 49 Westerbork Drenthe 9431 AC",
    "addr:housenumber":"49",
    "addr:postcode":"9431 ac",
    "addr:street":"Hoofdstr",
    "iso:country":"NL",
    "sg:address":"Hoofdstr 49",
    "sg:city":"Westerbork",
    "sg:orig_category":"Kappers",
    "sg:phone":"+31 593 332 920",
    "sg:postcode":"9431 AC",
    "sg:province":"Drenthe",
    "wof:name":"Mari\u00eblle'S Hairstyling",
    "wof:placetype":"venue"
},
  "geometry": {"coordinates":[6.613825,52.84938],"type":"Point"}
}