{
  "type": "Feature",
  "properties": {
    "addr:full":"1E Hogeweg 160 Zeist Utrecht 3701 HL",
    "addr:housenumber":"160",
    "addr:postcode":"3701 hl",
    "addr:street":"1E Hogeweg",
    "iso:country":"NL",
    "sg:address":"1E Hogeweg 160",
    "sg:city":"Zeist",
    "sg:classifiers":[
        {
            "category":"Shopping",
            "subcategory":"Gifts & Souvenirs",
            "type":"Retail Goods"
        }
    ],
    "sg:phone":"+31 30 692 3943",
    "sg:postcode":"3701 HL",
    "sg:province":"Utrecht",
    "sg:tags":[
        "geschenken"
    ],
    "wof:name":"Quattro Design",
    "wof:placetype":"venue"
},
  "geometry": {"coordinates":[5.241757,52.085094],"type":"Point"}
}