{
  "type": "Feature",
  "properties": {
    "addr:full":"T Woud 9 Brielle South Holland 3232 LN",
    "addr:housenumber":"9",
    "addr:postcode":"3232 ln",
    "addr:street":"T Woud",
    "iso:country":"NL",
    "sg:address":"T Woud 9",
    "sg:city":"Brielle",
    "sg:orig_category":"Keukens",
    "sg:phone":"+31 181 415 253",
    "sg:postcode":"3232 LN",
    "sg:province":"South Holland",
    "sg:website":"http://www.portas.nl",
    "wof:name":"Portas",
    "wof:placetype":"venue"
},
  "geometry": {"coordinates":[4.162637,51.888401],"type":"Point"}
}