{
  "type": "Feature",
  "properties": {
    "addr:full":"Govert Flinckstraat 11 Oud Beijerland Zuid-Holland 3262 TD",
    "addr:housenumber":"11",
    "addr:postcode":"3262 td",
    "addr:street":"Govert Flinckstraat;Oud Beijerland",
    "iso:country":"NL",
    "sg:address":"Govert Flinckstraat 11",
    "sg:city":"Oud Beijerland",
    "sg:orig_category":"Chemische Producten Gh",
    "sg:phone":"+31 186 615 129",
    "sg:postcode":"3262 TD",
    "sg:province":"Zuid-Holland",
    "wof:name":"New Systems Bogarde Bv",
    "wof:placetype":"venue"
},
  "geometry": {"coordinates":[4.407272,51.817093],"type":"Point"}
}