{
  "type": "Feature",
  "properties": {
    "addr:full":"Kemminkhorstwg 40 Amsterdam Zuidoost North Holland 1104 MJ",
    "addr:housenumber":"40",
    "addr:postcode":"1104 mj",
    "addr:street":"Kemminkhorstwg",
    "iso:country":"NL",
    "sg:address":"Kemminkhorstwg 40",
    "sg:city":"Amsterdam Zuidoost",
    "sg:orig_category":"Onderhoudswerken",
    "sg:phone":"+31 20 695 4787",
    "sg:postcode":"1104 MJ",
    "sg:province":"North Holland",
    "wof:name":"Bosch, R Van Den",
    "wof:placetype":"venue"
},
  "geometry": {"coordinates":[4.966287,52.316025],"type":"Point"}
}