{
  "type": "Feature",
  "properties": {
    "iso:country":"NL",
    "sg:address":"Kemminkhorstwg 40",
    "sg:city":"Amsterdam Zuidoost",
    "sg:orig_category":"Onderhoudswerken",
    "sg:phone":"+31 20 695 4787",
    "sg:postcode":"1104 MJ",
    "sg:province":"North Holland",
    "wof:name":"Bosch, R Van Den",
    "wof:placetype":"venue"
},
  "geometry": {"coordinates":[4.966287,52.316025],"type":"Point"}
}