{
  "type": "Feature",
  "properties": {
    "iso:country":"NL",
    "sg:address":"Ginnekenweg 7",
    "sg:city":"Breda",
    "sg:orig_category":"Boekenuitgeverijen",
    "sg:phone":"+31 76 521 1124",
    "sg:postcode":"4818  J",
    "sg:province":"North Brabant",
    "wof:name":"Bruna",
    "wof:placetype":"venue"
},
  "geometry": {"coordinates":[4.779286,51.578514],"type":"Point"}
}