{
  "type": "Feature",
  "properties": {
    "addr:full":"V Oldenbarnev Pln 19 Dordrecht South Holland 3317 EP",
    "addr:housenumber":"19",
    "addr:postcode":"3317 ep",
    "addr:street":"Pln",
    "iso:country":"NL",
    "sg:address":"V Oldenbarnev Pln 19",
    "sg:city":"Dordrecht",
    "sg:classifiers":[
        {
            "category":"Food & Beverages",
            "subcategory":"Bakery",
            "type":"Retail Goods"
        }
    ],
    "sg:phone":"+31 78 617 3859",
    "sg:postcode":"3317 EP",
    "sg:province":"South Holland",
    "sg:tags":[
        "brood",
        "en",
        "banket"
    ],
    "wof:name":"Korteweg, J",
    "wof:placetype":"venue"
},
  "geometry": {"coordinates":[4.656506,51.811916],"type":"Point"}
}