{
  "type": "Feature",
  "properties": {
    "addr:full":"Hogeschoolln 55 Tilburg Noord-Brabant 5037 BE",
    "addr:housenumber":"55",
    "addr:postcode":"5037",
    "addr:street":"Hogeschoolln",
    "iso:country":"NL",
    "sg:address":"Hogeschoolln 55",
    "sg:city":"Tilburg",
    "sg:orig_category":"Tekstverwerking - Servicebureaus",
    "sg:phone":"+31 13 463 6472",
    "sg:postcode":"5037 BE",
    "sg:province":"Noord-Brabant",
    "wof:name":"Bogaert, Paul",
    "wof:placetype":"venue"
},
  "geometry": {"coordinates":[5.05094,51.556992],"type":"Point"}
}