{
  "type": "Feature",
  "properties": {
    "addr:full":"Bram Streeflandweg 59 Renkum Gelderland 6871 HV",
    "addr:housenumber":"59",
    "addr:postcode":"6871 hv",
    "addr:street":"Bram Streeflandweg;Gelderland",
    "iso:country":"NL",
    "sg:address":"Bram Streeflandweg 59",
    "sg:city":"Renkum",
    "sg:orig_category":"Fitnesscentra",
    "sg:phone":"+31 317 310 925",
    "sg:postcode":"6871 HV",
    "sg:province":"Gelderland",
    "wof:name":"Sportinstituut Sjabbens",
    "wof:placetype":"venue"
},
  "geometry": {"coordinates":[5.74367,51.982212],"type":"Point"}
}