{
  "type": "Feature",
  "properties": {
    "addr:full":"Berkeboom 14 Culemborg Utrecht 4101 WP",
    "addr:housenumber":"14",
    "addr:postcode":"4101 wp",
    "addr:street":"Berkeboom",
    "iso:country":"NL",
    "sg:address":"Berkeboom 14",
    "sg:city":"Culemborg",
    "sg:orig_category":"Waterkoelers En Drinkwaterinstallaties",
    "sg:phone":"+31 345 531 493",
    "sg:postcode":"4101 WP",
    "sg:province":"Utrecht",
    "sg:website":"http://www.aquabowl.nl",
    "wof:name":"Aqua Bowl",
    "wof:placetype":"venue"
},
  "geometry": {"coordinates":[5.2388701439,51.9599571228],"type":"Point"}
}