{
  "type": "Feature",
  "properties": {
    "addr:full":"Hoofdwg 20 Wedde Groningen 9698 AE",
    "addr:housenumber":"20",
    "addr:postcode":"9698 ae",
    "addr:street":"Hoofdwg",
    "iso:country":"NL",
    "sg:address":"Hoofdwg 20",
    "sg:city":"Wedde",
    "sg:orig_category":"Kappers",
    "sg:phone":"+31 597 562 151",
    "sg:postcode":"9698 AE",
    "sg:province":"Groningen",
    "wof:name":"Good Looking",
    "wof:placetype":"venue"
},
  "geometry": {"coordinates":[7.0737857819,53.0687446594],"type":"Point"}
}