{
  "type": "Feature",
  "properties": {
    "addr:full":"G V Prinstererln 91 Amstelveen North Holland 1181 TR",
    "addr:housenumber":"91",
    "addr:postcode":"1181 tr",
    "addr:street":"V Prinstererln",
    "iso:country":"NL",
    "sg:address":"G V Prinstererln 91",
    "sg:city":"Amstelveen",
    "sg:orig_category":"Verenigingen En Stichtingen",
    "sg:phone":"+31 20 641 4333",
    "sg:postcode":"1181 TR",
    "sg:province":"North Holland",
    "wof:name":"Kijkonderzoek, Sticht",
    "wof:placetype":"venue"
},
  "geometry": {"coordinates":[4.856945,52.303444],"type":"Point"}
}