{
  "type": "Feature",
  "properties": {
    "addr:full":"Adm De Ruyterwg 19 Zwyndrecht Zuid-Holland 3333 TD",
    "addr:housenumber":"19",
    "addr:postcode":"3333 td",
    "iso:country":"NL",
    "sg:address":"Adm De Ruyterwg 19",
    "sg:city":"Zwyndrecht",
    "sg:orig_category":"Autorijscholen",
    "sg:phone":"+31 6 14993548",
    "sg:postcode":"3333 TD",
    "sg:province":"Zuid-Holland",
    "wof:name":"Wirin",
    "wof:placetype":"venue"
},
  "geometry": {"coordinates":[4.63394,51.81358],"type":"Point"}
}