{
  "type": "Feature",
  "properties": {
    "iso:country":"NL",
    "sg:address":"Koekoek 18",
    "sg:city":"Rijswijk Nb",
    "sg:orig_category":"Paramedische Behandelingen",
    "sg:phone":"+31 183 442 056",
    "sg:postcode":"4284 XJ",
    "sg:province":"North Brabant",
    "wof:name":"Logopediste M.J. Mars",
    "wof:placetype":"venue"
},
  "geometry": {"coordinates":[5.02155,51.79594],"type":"Point"}
}