{
  "type": "Feature",
  "properties": {
    "addr:full":"Velperplein 8 Arnhem Gelderland 6811 AG",
    "addr:housenumber":"8",
    "addr:postcode":"6811",
    "addr:street":"Velperplein",
    "iso:country":"NL",
    "sg:address":"Velperplein 8",
    "sg:city":"Arnhem",
    "sg:orig_category":"Adviesbureaus Bedrijfsorganisatie",
    "sg:phone":"+31 26 355 1355",
    "sg:postcode":"6811 AG",
    "sg:province":"Gelderland",
    "wof:name":"K+V Organisatie Adviesbureau Bv",
    "wof:placetype":"venue"
},
  "geometry": {"coordinates":[5.911555,51.98365],"type":"Point"}
}