{
  "type": "Feature",
  "properties": {
    "iso:country":"NL",
    "sg:address":"Westhavenweg 117",
    "sg:city":"Amsterdam",
    "sg:orig_category":"Geluidsopnamen",
    "sg:phone":"+31 20 612 4222",
    "sg:postcode":"1042 BB",
    "sg:province":"Noord-Holland",
    "wof:name":"Audio Amsterdam + A Light",
    "wof:placetype":"venue"
},
  "geometry": {"coordinates":[4.822936,52.416149],"type":"Point"}
}