{
  "type": "Feature",
  "properties": {
    "iso:country":"NL",
    "sg:address":"Humcovenderveld 2",
    "sg:city":"Meerssen",
    "sg:orig_category":"Juridische Adviseurs",
    "sg:phone":"+31 43 358 1006",
    "sg:postcode":"6231 HW",
    "sg:province":"Limburg",
    "wof:name":"Tak & Teunissen Bv",
    "wof:placetype":"venue"
},
  "geometry": {"coordinates":[5.75719,50.88979],"type":"Point"}
}