{
  "type": "Feature",
  "properties": {
    "addr:full":"Kavelingen 52 Valthermond Drenthe 7876 TG",
    "addr:housenumber":"52",
    "addr:postcode":"7876 tg",
    "addr:street":"Kavelingen",
    "iso:country":"NL",
    "sg:address":"Kavelingen 52",
    "sg:city":"Valthermond",
    "sg:orig_category":"Bloemen And Planten Gh",
    "sg:phone":"+31 599 412 500",
    "sg:postcode":"7876 TG",
    "sg:province":"Drenthe",
    "wof:name":"Handels- En Transportondern Gebroeders Wever Bv",
    "wof:placetype":"venue"
},
  "geometry": {"coordinates":[7.013634,52.919037],"type":"Point"}
}