{
  "type": "Feature",
  "properties": {
    "addr:full":"Herenwg 298A Wilnis Utrecht 3648 CS",
    "addr:housenumber":"298a",
    "addr:postcode":"3648 cs",
    "iso:country":"NL",
    "sg:address":"Herenwg 298A",
    "sg:city":"Wilnis",
    "sg:orig_category":"Biljarts - Fabrieken",
    "sg:phone":"+31 297 281 604",
    "sg:postcode":"3648 CS",
    "sg:province":"Utrecht",
    "sg:website":"http://www.bocxebiljarts.nl",
    "wof:name":"Bocxe Bv",
    "wof:placetype":"venue"
},
  "geometry": {"coordinates":[4.874472,52.199821],"type":"Point"}
}