{
  "type": "Feature",
  "properties": {
    "addr:full":"2E Lageveldsweg 2 Wierden Overijssel 7641 PC",
    "addr:housenumber":"2",
    "addr:postcode":"7641 pc",
    "addr:street":"2E Lageveldsweg",
    "iso:country":"NL",
    "sg:address":"2E Lageveldsweg 2",
    "sg:city":"Wierden",
    "sg:orig_category":"Bloemen And Planten",
    "sg:phone":"+31 546 576 273",
    "sg:postcode":"7641 PC",
    "sg:province":"Overijssel",
    "wof:name":"Europatuin Wierden",
    "wof:placetype":"venue"
},
  "geometry": {"coordinates":[6.590356,52.367207],"type":"Point"}
}