{
  "type": "Feature",
  "properties": {
    "addr:full":"Postbus 543 Barneveld Gelderland 3770 AM",
    "addr:housenumber":"543",
    "addr:postcode":"3770",
    "addr:street":"Postbus;Gelderland",
    "iso:country":"NL",
    "sg:address":"Postbus 543",
    "sg:city":"Barneveld",
    "sg:orig_category":"Geluidsinstallaties - Verhuur",
    "sg:phone":"+31 342 490 007",
    "sg:postcode":"3770 AM",
    "sg:province":"Gelderland",
    "wof:name":"Crew Vof",
    "wof:placetype":"venue"
},
  "geometry": {"coordinates":[5.588843,52.141216],"type":"Point"}
}