{
  "type": "Feature",
  "properties": {
    "iso:country":"NL",
    "sg:address":"Adrianaln 371",
    "sg:city":"Rotterdam",
    "sg:orig_category":"Offsetdrukkerijen",
    "sg:phone":"+31 10 418 8077",
    "sg:postcode":"3053 JB",
    "sg:province":"Zuid-Holland",
    "wof:name":"Baars En Morel Bv",
    "wof:placetype":"venue"
},
  "geometry": {"coordinates":[4.465578,51.966415],"type":"Point"}
}