{
  "type": "Feature",
  "properties": {
    "addr:full":"Hoefijzerlaan 10 Bunnik Utrecht 3981 GM",
    "addr:housenumber":"10",
    "addr:postcode":"3981 gm",
    "addr:street":"Hoefijzerlaan",
    "iso:country":"NL",
    "sg:address":"Hoefijzerlaan 10",
    "sg:city":"Bunnik",
    "sg:orig_category":"Onderhoud And Reparatie Kantoorapparatuur",
    "sg:phone":"+31 30 656 7843",
    "sg:postcode":"3981 GM",
    "sg:province":"Utrecht",
    "wof:name":"J. Vissers",
    "wof:placetype":"venue"
},
  "geometry": {"coordinates":[5.19416,52.0672],"type":"Point"}
}