{
  "type": "Feature",
  "properties": {
    "addr:full":"Postbus 230 Koog Aan De Zaan North Holland 1540 AE",
    "addr:housenumber":"230",
    "addr:postcode":"1540 ae",
    "addr:street":"Postbus",
    "iso:country":"NL",
    "sg:address":"Postbus 230",
    "sg:city":"Koog Aan De Zaan",
    "sg:orig_category":"Opvangtehuizen",
    "sg:phone":"+31 75 615 9089",
    "sg:postcode":"1540 AE",
    "sg:province":"North Holland",
    "wof:name":"Blijf Van M'N Lijf",
    "wof:placetype":"venue"
},
  "geometry": {"coordinates":[4.7997097969,52.4570007324],"type":"Point"}
}