{
  "type": "Feature",
  "properties": {
    "addr:full":"Bouwery 18-20 Regio Amsterdam Amstelveen Noord-Holland 1185 XX",
    "addr:housenumber":"18-20;amsterdam",
    "addr:postcode":"1185 xx",
    "addr:street":"Regio",
    "iso:country":"NL",
    "sg:address":"Bouwery 18-20 Regio Amsterdam",
    "sg:city":"Amstelveen",
    "sg:orig_category":"Kamers Van Koophandel",
    "sg:phone":"+31 20 531 4000",
    "sg:postcode":"1185 XX",
    "sg:province":"Noord-Holland",
    "wof:name":"Kamer Van Koophdl",
    "wof:placetype":"venue"
},
  "geometry": {"coordinates":[4.8569450378,52.3034439087],"type":"Point"}
}