{
  "type": "Feature",
  "properties": {
    "addr:full":"Noorderkwartier 20 Veendam Groningen 9644 VG",
    "addr:housenumber":"20",
    "addr:postcode":"9644 vg",
    "addr:street":"Noorderkwartier",
    "iso:country":"NL",
    "sg:address":"Noorderkwartier 20",
    "sg:city":"Veendam",
    "sg:orig_category":"Voegwerken",
    "sg:phone":"+31 598 617 092",
    "sg:postcode":"9644 VG",
    "sg:province":"Groningen",
    "wof:name":"Gevor",
    "wof:placetype":"venue"
},
  "geometry": {"coordinates":[6.901606,53.092751],"type":"Point"}
}