{
  "type": "Feature",
  "properties": {
    "iso:country":"NL",
    "sg:address":"Sloetstraat 134",
    "sg:city":"Arnhem",
    "sg:orig_category":"Diverse Grafische Activiteiten",
    "sg:phone":"+31 26 443 1736",
    "sg:postcode":"6821 CZ",
    "sg:province":"Gelderland",
    "wof:name":"De Studio",
    "wof:placetype":"venue"
},
  "geometry": {"coordinates":[5.909957,51.98856],"type":"Point"}
}