{
  "type": "Feature",
  "properties": {
    "addr:full":"Dorpsstraat 48 Zuidlaarderveen Provincie Drenthe 9474 PE",
    "addr:housenumber":"48",
    "addr:postcode":"9474 pe",
    "addr:street":"Dorpsstraat;Provincie Drenthe",
    "iso:country":"NL",
    "sg:address":"Dorpsstraat 48",
    "sg:city":"Zuidlaarderveen",
    "sg:orig_category":"Kampeerterreinen",
    "sg:phone":"+31 598 491 762",
    "sg:postcode":"9474 PE",
    "sg:province":"Provincie Drenthe",
    "wof:name":"De Hofstee",
    "wof:placetype":"venue"
},
  "geometry": {"coordinates":[6.7493309975,53.1030540466],"type":"Point"}
}