{
  "type": "Feature",
  "properties": {
    "iso:country":"NL",
    "sg:address":"Dorpsstr 70",
    "sg:city":"Halsteren",
    "sg:orig_category":"Huishoudelijke Apparaten En Artikelen",
    "sg:phone":"+31 164 682 441",
    "sg:postcode":"4661 HR",
    "sg:province":"Noord-Brabant",
    "wof:name":"Geel, M Van",
    "wof:placetype":"venue"
},
  "geometry": {"coordinates":[4.268547,51.526825],"type":"Point"}
}