{
  "type": "Feature",
  "properties": {
    "addr:full":"Brusselsestr 94 Maastricht Limburg 6211 PH",
    "addr:housenumber":"94",
    "addr:postcode":"6211",
    "addr:street":"Brusselsestr",
    "iso:country":"NL",
    "sg:address":"Brusselsestr 94",
    "sg:city":"Maastricht",
    "sg:orig_category":"Loodgieters",
    "sg:phone":"+31 43 321 2994",
    "sg:postcode":"6211 PH",
    "sg:province":"Limburg",
    "wof:name":"Heuvel Bv, M A Van Den",
    "wof:placetype":"venue"
},
  "geometry": {"coordinates":[5.681259,50.849762],"type":"Point"}
}