{
  "type": "Feature",
  "properties": {
    "iso:country":"NL",
    "sg:address":"Schubertln 6",
    "sg:city":"Enschede",
    "sg:orig_category":"Adviesbureaus Bedrijfsorganisatie",
    "sg:phone":"+31 53 430 1748",
    "sg:postcode":"7522 JR",
    "sg:province":"Overijssel",
    "sg:website":"HTTP://www.dunamisconsultancy.nl",
    "wof:name":"Dunamis",
    "wof:placetype":"venue"
},
  "geometry": {"coordinates":[6.882931,52.240219],"type":"Point"}
}