{
  "type": "Feature",
  "properties": {
    "iso:country":"NL",
    "sg:address":"Infanteriepad 12",
    "sg:city":"Gorinchem",
    "sg:orig_category":"Voetbalverenigingen",
    "sg:phone":"+31 183 602 556",
    "sg:postcode":"4201 ME",
    "sg:province":"Zuid-Holland",
    "wof:name":"Noordeloos Vv",
    "wof:placetype":"venue"
},
  "geometry": {"coordinates":[4.97052,51.82951],"type":"Point"}
}