{
  "type": "Feature",
  "properties": {
    "addr:full":"Postbus 13 Zoetermeer Zuid-Holland 2700 AA",
    "addr:housenumber":"13",
    "addr:postcode":"2700 aa",
    "addr:street":"Postbus",
    "iso:country":"NL",
    "sg:address":"Postbus 13",
    "sg:city":"Zoetermeer",
    "sg:orig_category":"Vakorganisaties",
    "sg:phone":"+31 79 329 3939",
    "sg:postcode":"2700 AA",
    "sg:province":"Zuid-Holland",
    "wof:name":"Abvakabo Fnv",
    "wof:placetype":"venue"
},
  "geometry": {"coordinates":[4.48892,52.06308],"type":"Point"}
}