{
  "type": "Feature",
  "properties": {
    "addr:full":"Hobbel 9 Riethoven North Brabant 5561 TN",
    "addr:housenumber":"9",
    "addr:postcode":"5561",
    "addr:street":"Hobbel",
    "iso:country":"NL",
    "sg:address":"Hobbel 9",
    "sg:city":"Riethoven",
    "sg:orig_category":"Verhuur Audiovisuele Apparatuur",
    "sg:phone":"+31 497 518 452",
    "sg:postcode":"5561 TN",
    "sg:province":"North Brabant",
    "wof:name":"M. Neggers Holland Disco",
    "wof:placetype":"venue"
},
  "geometry": {"coordinates":[5.370012,51.35815],"type":"Point"}
}