{
  "type": "Feature",
  "properties": {
    "iso:country":"NL",
    "sg:address":"M Nyhoffln 2",
    "sg:city":"Delft",
    "sg:orig_category":"Administratie- En Boekhoudkantoren",
    "sg:phone":"+31 15 285 5350",
    "sg:postcode":"2624 ES",
    "sg:province":"Zuid-Holland",
    "wof:name":"Kuijk Administratie- & Belastingadviesbureau, Van",
    "wof:placetype":"venue"
},
  "geometry": {"coordinates":[4.35634,51.995491],"type":"Point"}
}