{
  "type": "Feature",
  "properties": {
    "iso:country":"NL",
    "sg:address":"Dorpsstr 43",
    "sg:city":"Heerde",
    "sg:orig_category":"Opticiens",
    "sg:phone":"+31 578 694 400",
    "sg:postcode":"8181 HN",
    "sg:province":"Gelderland",
    "wof:name":"Boschman, H",
    "wof:placetype":"venue"
},
  "geometry": {"coordinates":[6.0398111343,52.386554718],"type":"Point"}
}