{
  "type": "Feature",
  "properties": {
    "addr:full":"Roothaanstr 23 Eindhoven Noord-Brabant 5643 PW",
    "addr:housenumber":"23",
    "addr:postcode":"5643 pw",
    "addr:street":"Roothaanstr",
    "iso:country":"NL",
    "sg:address":"Roothaanstr 23",
    "sg:city":"Eindhoven",
    "sg:orig_category":"Grafisch Ontwerpers",
    "sg:phone":"+31 40 257 5747",
    "sg:postcode":"5643 PW",
    "sg:province":"Noord-Brabant",
    "wof:name":"Verdonk",
    "wof:placetype":"venue"
},
  "geometry": {"coordinates":[5.50157,51.425236],"type":"Point"}
}