{
  "type": "Feature",
  "properties": {
    "addr:full":"De Tsjasker 2 Witmarsum Provincie Friesland 8748 DW",
    "addr:housenumber":"2",
    "addr:postcode":"8748 dw",
    "addr:street":"De Tsjasker;Provincie Friesland",
    "iso:country":"NL",
    "sg:address":"De Tsjasker 2",
    "sg:city":"Witmarsum",
    "sg:classifiers":[
        {
            "category":"Education",
            "subcategory":"Preschool",
            "type":"Public Place"
        }
    ],
    "sg:phone":"+31 517 531 919",
    "sg:postcode":"8748 DW",
    "sg:province":"Provincie Friesland",
    "sg:tags":[
        "kleuteronderwijs",
        "basis-"
    ],
    "wof:name":"Christelijke Basisschool De Bonkelder",
    "wof:placetype":"venue"
},
  "geometry": {"coordinates":[5.469372,53.101635],"type":"Point"}
}