{
  "type": "Feature",
  "properties": {
    "addr:full":"Hellemanstr 49 Deurne Noord-Brabant 5751 HP",
    "addr:housenumber":"49",
    "addr:postcode":"5751 hp",
    "addr:street":"Hellemanstr",
    "iso:country":"NL",
    "sg:address":"Hellemanstr 49",
    "sg:city":"Deurne",
    "sg:orig_category":"Biljarts - Fabrieken",
    "sg:phone":"+31 493 313 840",
    "sg:postcode":"5751 HP",
    "sg:province":"Noord-Brabant",
    "wof:name":"Berkmortel, H Van Den",
    "wof:placetype":"venue"
},
  "geometry": {"coordinates":[5.786558,51.461445],"type":"Point"}
}