{
  "type": "Feature",
  "properties": {
    "iso:country":"NL",
    "sg:address":"Azaleastraat 2",
    "sg:city":"Steenbergen Nb",
    "sg:orig_category":"Bouwnijverheidsmachines Gh",
    "sg:phone":"+31 167 540 350",
    "sg:postcode":"4651 LB",
    "sg:province":"North Brabant",
    "wof:name":"Euralcoma",
    "wof:placetype":"venue"
},
  "geometry": {"coordinates":[4.319033,51.578842],"type":"Point"}
}