{
  "type": "Feature",
  "properties": {
    "addr:full":"Vyverhofstr 116 Rotterdam Zuid-Holland 3032 SP",
    "addr:housenumber":"116",
    "addr:postcode":"3032 sp",
    "iso:country":"NL",
    "sg:address":"Vyverhofstr 116",
    "sg:city":"Rotterdam",
    "sg:orig_category":"Zalenverhuur",
    "sg:phone":"+31 10 466 4281",
    "sg:postcode":"3032 SP",
    "sg:province":"Zuid-Holland",
    "wof:name":"Jansen",
    "wof:placetype":"venue"
},
  "geometry": {"coordinates":[4.471703,51.93166],"type":"Point"}
}