{
  "type": "Feature",
  "properties": {
    "addr:full":"Wageweg 15 Alkmaar North Holland 1811 MK",
    "addr:housenumber":"15",
    "addr:postcode":"1811",
    "addr:street":"Wageweg",
    "iso:country":"NL",
    "sg:address":"Wageweg 15",
    "sg:city":"Alkmaar",
    "sg:orig_category":"Verhuur Catering-, Feest- En Evenementbenodigdheden",
    "sg:phone":"+31 72 512 3463",
    "sg:postcode":"1811 MK",
    "sg:province":"North Holland",
    "wof:name":"Cab John Selbach Bv",
    "wof:placetype":"venue"
},
  "geometry": {"coordinates":[4.755785,52.629993],"type":"Point"}
}