{
  "type": "Feature",
  "properties": {
    "iso:country":"NL",
    "sg:address":"Julianalaan 35",
    "sg:city":"Bilthoven",
    "sg:orig_category":"Banken And Kredietinstellingen",
    "sg:phone":"+31 30 228 4852",
    "sg:postcode":"3722 GD",
    "sg:province":"Utrecht",
    "wof:name":"Fortis Bank",
    "wof:placetype":"venue"
},
  "geometry": {"coordinates":[5.207691,52.129345],"type":"Point"}
}