{
  "type": "Feature",
  "properties": {
    "addr:full":"Lopikerweg West 100A Lopik Utrecht 3411 AT",
    "addr:housenumber":"100a",
    "addr:postcode":"3411",
    "addr:street":"Lopikerweg West",
    "iso:country":"NL",
    "sg:address":"Lopikerweg West 100A",
    "sg:city":"Lopik",
    "sg:orig_category":"Zuivelproducten",
    "sg:phone":"+31 348 552 181",
    "sg:postcode":"3411 AT",
    "sg:province":"Utrecht",
    "wof:name":"Th. De Vos",
    "wof:placetype":"venue"
},
  "geometry": {"coordinates":[4.87821,51.962807],"type":"Point"}
}