{
  "type": "Feature",
  "properties": {
    "addr:full":"Bar Bentinckstr 67 Ommen NL.08 7731 EK",
    "addr:housenumber":"67;nl.08",
    "addr:postcode":"7731 ek",
    "iso:country":"NL",
    "sg:address":"Bar Bentinckstr 67",
    "sg:city":"Ommen",
    "sg:orig_category":"Artsen - Huisartsen",
    "sg:phone":"+31 529 456 626",
    "sg:postcode":"7731 EK",
    "sg:province":"NL.08",
    "wof:name":"Habets, P C M",
    "wof:placetype":"venue"
},
  "geometry": {"coordinates":[6.420761,52.524155],"type":"Point"}
}