{
  "type": "Feature",
  "properties": {
    "addr:full":"Visbankflat 4 Vlaardingen Zuid-Holland 3131 BW",
    "addr:housenumber":"4",
    "addr:postcode":"3131 bw",
    "addr:street":"Visbankflat",
    "iso:country":"NL",
    "sg:address":"Visbankflat 4",
    "sg:city":"Vlaardingen",
    "sg:orig_category":"Adviesbureaus Bouwkunde",
    "sg:phone":"+31 10 434 1591",
    "sg:postcode":"3131 BW",
    "sg:province":"Zuid-Holland",
    "wof:name":"Boom",
    "wof:placetype":"venue"
},
  "geometry": {"coordinates":[4.343221,51.909466],"type":"Point"}
}