{
  "type": "Feature",
  "properties": {
    "addr:full":"Rijksstraatweg 183 Haren Gn Groningen 9752 BE",
    "addr:housenumber":"183",
    "addr:postcode":"9752",
    "addr:street":"Rijksstraatweg",
    "iso:country":"NL",
    "sg:address":"Rijksstraatweg 183",
    "sg:city":"Haren Gn",
    "sg:orig_category":"Discountwinkels",
    "sg:phone":"+31 50 537 0193",
    "sg:postcode":"9752 BE",
    "sg:province":"Groningen",
    "wof:name":"Wibra Bv",
    "wof:placetype":"venue"
},
  "geometry": {"coordinates":[6.60632,53.170658],"type":"Point"}
}