{
  "type": "Feature",
  "properties": {
    "iso:country":"NL",
    "sg:address":"Slobbeland 4",
    "sg:city":"Volendam",
    "sg:orig_category":"Verenigingen En Stichtingen",
    "sg:phone":"+31 299 361 922",
    "sg:postcode":"1131 AB",
    "sg:province":"Noord-Holland",
    "wof:name":"Werkende Missieteam, Sticht Het",
    "wof:placetype":"venue"
},
  "geometry": {"coordinates":[5.067796,52.490639],"type":"Point"}
}