{
  "type": "Feature",
  "properties": {
    "addr:full":"Stratumsedk 25 Eindhoven North Brabant 5611 NA",
    "addr:housenumber":"25",
    "addr:postcode":"5611 na",
    "addr:street":"Stratumsedk",
    "iso:country":"NL",
    "sg:address":"Stratumsedk 25",
    "sg:city":"Eindhoven",
    "sg:orig_category":"Verenigingen En Stichtingen",
    "sg:phone":"+31 40 212 3569",
    "sg:postcode":"5611 NA",
    "sg:province":"North Brabant",
    "wof:name":"Amicitia, Societeit",
    "wof:placetype":"venue"
},
  "geometry": {"coordinates":[5.484345,51.433727],"type":"Point"}
}