{
  "type": "Feature",
  "properties": {
    "iso:country":"NL",
    "sg:address":"Van De Veldelaan 622",
    "sg:city":"Alkmaar",
    "sg:orig_category":"Artsen And Specialisten",
    "sg:phone":"+31 72 512 5121",
    "sg:postcode":"1816 PR",
    "sg:province":"Noord-Holland",
    "wof:name":"J.G. Van Gulick",
    "wof:placetype":"venue"
},
  "geometry": {"coordinates":[4.72034,52.632339],"type":"Point"}
}