{
  "type": "Feature",
  "properties": {
    "addr:full":"Dokln 22 Rotterdam South Holland 3081 AD",
    "addr:housenumber":"22",
    "addr:postcode":"3081 ad",
    "addr:street":"Dokln",
    "iso:country":"NL",
    "sg:address":"Dokln 22",
    "sg:city":"Rotterdam",
    "sg:orig_category":"Hefwerktuigen",
    "sg:phone":"+31 10 294 6666",
    "sg:postcode":"3081 AD",
    "sg:province":"South Holland",
    "wof:name":"Kelmar Industries Bv",
    "wof:placetype":"venue"
},
  "geometry": {"coordinates":[4.48229,51.893768],"type":"Point"}
}