{
  "type": "Feature",
  "properties": {
    "addr:full":"Lijsterbeswal 5 Drachten Provincie Friesland 9203 LX",
    "addr:housenumber":"5",
    "addr:postcode":"9203 lx",
    "addr:street":"Lijsterbeswal;Provincie Friesland",
    "iso:country":"NL",
    "sg:address":"Lijsterbeswal 5",
    "sg:city":"Drachten",
    "sg:orig_category":"Zonnebanken En Solarium-Installaties",
    "sg:phone":"+31 512 523 926",
    "sg:postcode":"9203 LX",
    "sg:province":"Provincie Friesland",
    "wof:name":"Ellanka",
    "wof:placetype":"venue"
},
  "geometry": {"coordinates":[6.095345,53.093678],"type":"Point"}
}