{
  "type": "Feature",
  "properties": {
    "addr:full":"Spittaalstr 13 Zutphen Gelderland 7201 EA",
    "addr:housenumber":"13",
    "addr:postcode":"7201 ea",
    "addr:street":"Spittaalstr;Gelderland",
    "iso:country":"NL",
    "sg:address":"Spittaalstr 13",
    "sg:city":"Zutphen",
    "sg:orig_category":"Boeken En Tijdschriften",
    "sg:phone":"+31 575 519 662",
    "sg:postcode":"7201 EA",
    "sg:province":"Gelderland",
    "wof:name":"Krantje, 'T",
    "wof:placetype":"venue"
},
  "geometry": {"coordinates":[6.199455,52.138611],"type":"Point"}
}