{
  "type": "Feature",
  "properties": {
    "addr:full":"Steenoven 29 Someren Noord-Brabant 5712 NC",
    "addr:housenumber":"29",
    "addr:postcode":"5712 nc",
    "addr:street":"Steenoven",
    "iso:country":"NL",
    "sg:address":"Steenoven 29",
    "sg:city":"Someren",
    "sg:orig_category":"Boekbinderijen",
    "sg:phone":"+31 493 479 824",
    "sg:postcode":"5712 NC",
    "sg:province":"Noord-Brabant",
    "wof:name":"Wortel, Gijs",
    "wof:placetype":"venue"
},
  "geometry": {"coordinates":[5.732782,51.360661],"type":"Point"}
}