{
  "type": "Feature",
  "properties": {
    "iso:country":"NL",
    "sg:address":"Emmawg 35A",
    "sg:city":"Maarssen",
    "sg:orig_category":"Psychotherapeuten",
    "sg:phone":"+31 346 571 605",
    "sg:postcode":"3603 AL",
    "sg:province":"Utrecht",
    "wof:name":"Rosman-Sonius, Drs Y B",
    "wof:placetype":"venue"
},
  "geometry": {"coordinates":[5.041519,52.13995],"type":"Point"}
}