{
  "type": "Feature",
  "properties": {
    "addr:full":"De Vesting 17 Dalfsen Overijssel 7722 GA",
    "addr:housenumber":"17",
    "addr:postcode":"7722 ga",
    "addr:street":"De Vesting",
    "iso:country":"NL",
    "sg:address":"De Vesting 17",
    "sg:city":"Dalfsen",
    "sg:orig_category":"Etiketten",
    "sg:phone":"+31 529 434 557",
    "sg:postcode":"7722 GA",
    "sg:province":"Overijssel",
    "sg:website":"http://www.omnilabel.nl",
    "wof:name":"Omnilabel Bv",
    "wof:placetype":"venue"
},
  "geometry": {"coordinates":[6.271683,52.512127],"type":"Point"}
}