{
  "type": "Feature",
  "properties": {
    "addr:full":"Reigerstraat 12 Ilpendam North Holland 1452 XR",
    "addr:housenumber":"12",
    "addr:postcode":"1452 xr",
    "addr:street":"Reigerstraat",
    "iso:country":"NL",
    "sg:address":"Reigerstraat 12",
    "sg:city":"Ilpendam",
    "sg:orig_category":"Boekhouders",
    "sg:phone":"+31 20 436 1339",
    "sg:postcode":"1452 XR",
    "sg:province":"North Holland",
    "wof:name":"Adm.- En Belastingadviesburo Van Der Mei",
    "wof:placetype":"venue"
},
  "geometry": {"coordinates":[4.953754,52.465595],"type":"Point"}
}