{
  "type": "Feature",
  "properties": {
    "addr:full":"Balgweg 5 Breezand North Holland 1764 KA",
    "addr:housenumber":"5",
    "addr:postcode":"1764 ka",
    "addr:street":"Balgweg",
    "iso:country":"NL",
    "sg:address":"Balgweg 5",
    "sg:city":"Breezand",
    "sg:orig_category":"Wegen And Sportterreinen",
    "sg:phone":"+31 223 535 790",
    "sg:postcode":"1764 KA",
    "sg:province":"North Holland",
    "wof:name":"Cosja",
    "wof:placetype":"venue"
},
  "geometry": {"coordinates":[4.8663787842,52.8870925903],"type":"Point"}
}