{
  "type": "Feature",
  "properties": {
    "iso:country":"NL",
    "sg:address":"Balgweg 5",
    "sg:city":"Breezand",
    "sg:orig_category":"Wegen And Sportterreinen",
    "sg:phone":"+31 223 535 790",
    "sg:postcode":"1764 KA",
    "sg:province":"North Holland",
    "wof:name":"Cosja",
    "wof:placetype":"venue"
},
  "geometry": {"coordinates":[4.8663787842,52.8870925903],"type":"Point"}
}