{
  "type": "Feature",
  "properties": {
    "addr:full":"Willaertstr 2A Oss Noord-Brabant 5344 AB",
    "addr:housenumber":"2a",
    "addr:postcode":"5344 ab",
    "addr:street":"Willaertstr",
    "iso:country":"NL",
    "sg:address":"Willaertstr 2A",
    "sg:city":"Oss",
    "sg:orig_category":"Graniet-, Granito- En Terrazzowerken",
    "sg:phone":"+31 412 632 552",
    "sg:postcode":"5344 AB",
    "sg:province":"Noord-Brabant",
    "sg:website":"http://www.devriesterrazzo.nl",
    "wof:name":"Vries Oss, De",
    "wof:placetype":"venue"
},
  "geometry": {"coordinates":[-77.235214,38.312599],"type":"Point"}
}