{
  "type": "Feature",
  "properties": {
    "addr:full":"Maaskd 119 Rotterdam Zuid-Holland 3071 NK",
    "addr:housenumber":"119",
    "addr:postcode":"3071 nk",
    "iso:country":"NL",
    "sg:address":"Maaskd 119",
    "sg:city":"Rotterdam",
    "sg:orig_category":"Dtp",
    "sg:phone":"+31 10 412 8344",
    "sg:postcode":"3071 NK",
    "sg:province":"Zuid-Holland",
    "wof:name":"Stoute, Studio",
    "wof:placetype":"venue"
},
  "geometry": {"coordinates":[4.50327,51.910591],"type":"Point"}
}