{
  "type": "Feature",
  "properties": {
    "addr:full":"Kerkstr 64 Abcoude Utrecht 1391 HD",
    "addr:housenumber":"64",
    "addr:postcode":"1391 hd",
    "addr:street":"Kerkstr",
    "iso:country":"NL",
    "sg:address":"Kerkstr 64",
    "sg:city":"Abcoude",
    "sg:orig_category":"Biljarts - Fabrieken",
    "sg:phone":"+31 294 288 022",
    "sg:postcode":"1391 HD",
    "sg:province":"Utrecht",
    "wof:name":"Zoeten & Zn, De",
    "wof:placetype":"venue"
},
  "geometry": {"coordinates":[4.976698,52.272564],"type":"Point"}
}