{
  "type": "Feature",
  "properties": {
    "addr:full":"Postbus 217 Voorschoten South Holland 2250 AE",
    "addr:housenumber":"217",
    "addr:postcode":"2250 ae",
    "addr:street":"Postbus",
    "iso:country":"NL",
    "sg:address":"Postbus 217",
    "sg:city":"Voorschoten",
    "sg:orig_category":"Glas",
    "sg:phone":"+31 71 561 5769",
    "sg:postcode":"2250 AE",
    "sg:province":"South Holland",
    "wof:name":"Accuraat",
    "wof:placetype":"venue"
},
  "geometry": {"coordinates":[4.44429,52.124825],"type":"Point"}
}