{
  "type": "Feature",
  "properties": {
    "addr:full":"Ridderhof 18 Alphen Aan Den Ryn South Holland 2402 EN",
    "addr:housenumber":"18",
    "addr:postcode":"2402 en",
    "addr:street":"Ridderhof;Aan Den Ryn",
    "iso:country":"NL",
    "sg:address":"Ridderhof 18",
    "sg:city":"Alphen Aan Den Ryn",
    "sg:orig_category":"Bloemen En Planten",
    "sg:phone":"+31 172 421 334",
    "sg:postcode":"2402 EN",
    "sg:province":"South Holland",
    "wof:name":"Gils, Henk-Jan Van",
    "wof:placetype":"venue"
},
  "geometry": {"coordinates":[4.674844,52.145409],"type":"Point"}
}