{
  "type": "Feature",
  "properties": {
    "addr:full":"Tweede Van Der Helststr 19Hs Amsterdam Noord-Holland 1073 AE",
    "addr:housenumber":"19hs",
    "addr:postcode":"1073 ae",
    "addr:street":"Tweede Van Der Helststr",
    "iso:country":"NL",
    "sg:address":"Tweede Van Der Helststr 19Hs",
    "sg:city":"Amsterdam",
    "sg:orig_category":"Tandartsen",
    "sg:phone":"+31 20 664 8844",
    "sg:postcode":"1073 AE",
    "sg:province":"Noord-Holland",
    "wof:name":"J.A.M. V.D. Peet",
    "wof:placetype":"venue"
},
  "geometry": {"coordinates":[4.895085,52.352074],"type":"Point"}
}