{
  "type": "Feature",
  "properties": {
    "addr:full":"Nieuwe Rijn 20B Leiden South Holland 2312 JC",
    "addr:housenumber":"20b",
    "addr:postcode":"2312 jc",
    "addr:street":"Nieuwe Rijn",
    "iso:country":"NL",
    "sg:address":"Nieuwe Rijn 20B",
    "sg:city":"Leiden",
    "sg:orig_category":"Kinderopvang Behalve Thuis",
    "sg:phone":"+31 71 512 2441",
    "sg:postcode":"2312 JC",
    "sg:province":"South Holland",
    "wof:name":"Gastouderbureau Leiden Cokl",
    "wof:placetype":"venue"
},
  "geometry": {"coordinates":[4.492106,52.158367],"type":"Point"}
}