{
  "type": "Feature",
  "properties": {
    "addr:full":"Lieshoutseweg 49 Helmond Noord-Brabant 5708 CW",
    "addr:housenumber":"49",
    "addr:postcode":"5708 cw",
    "addr:street":"Lieshoutseweg",
    "iso:country":"NL",
    "sg:address":"Lieshoutseweg 49",
    "sg:city":"Helmond",
    "sg:orig_category":"Schoonheidssalons",
    "sg:phone":"+31 492 526 031",
    "sg:postcode":"5708 CW",
    "sg:province":"Noord-Brabant",
    "wof:name":"Salon Wilma",
    "wof:placetype":"venue"
},
  "geometry": {"coordinates":[5.60977,51.491211],"type":"Point"}
}