{
  "type": "Feature",
  "properties": {
    "addr:full":"Joris Minneepad 1 Rotterdam South Holland 3067 KD",
    "addr:housenumber":"1",
    "addr:postcode":"3067 kd",
    "addr:street":"Joris Minneepad",
    "iso:country":"NL",
    "sg:address":"Joris Minneepad 1",
    "sg:city":"Rotterdam",
    "sg:orig_category":"Medische Apparatuur And Prothesen Fab",
    "sg:phone":"+31 10 420 2806",
    "sg:postcode":"3067 KD",
    "sg:province":"South Holland",
    "wof:name":"Tandtechnisch Laboratorium Ceradent Bv",
    "wof:placetype":"venue"
},
  "geometry": {"coordinates":[4.538738,51.944508],"type":"Point"}
}