{
  "type": "Feature",
  "properties": {
    "iso:country":"NL",
    "sg:address":"Schieweg 60",
    "sg:city":"Delft",
    "sg:orig_category":"Autokeuringen",
    "sg:phone":"+31 15 261 5979",
    "sg:postcode":"2627 AN",
    "sg:province":"Zuid-Holland",
    "wof:name":"Diesel Service West",
    "wof:placetype":"venue"
},
  "geometry": {"coordinates":[4.368095,51.994961],"type":"Point"}
}