{
  "type": "Feature",
  "properties": {
    "addr:full":"Dommelstraat 42 Valkenswaard Noord-Brabant 5551 TA",
    "addr:housenumber":"42",
    "addr:postcode":"5551 ta",
    "addr:street":"Dommelstraat",
    "iso:country":"NL",
    "sg:address":"Dommelstraat 42",
    "sg:city":"Valkenswaard",
    "sg:orig_category":"Bloemen And Planten",
    "sg:phone":"+31 40 204 5239",
    "sg:postcode":"5551 TA",
    "sg:province":"Noord-Brabant",
    "wof:name":"Tuincentrum Dommelhof Theunisse L H M",
    "wof:placetype":"venue"
},
  "geometry": {"coordinates":[5.438548,51.355492],"type":"Point"}
}