{
  "type": "Feature",
  "properties": {
    "addr:full":"Straatwg 55A Rotterdam Zuid-Holland 3051 BD",
    "addr:housenumber":"55a",
    "addr:postcode":"3051 bd",
    "addr:street":"Straatwg",
    "iso:country":"NL",
    "sg:address":"Straatwg 55A",
    "sg:city":"Rotterdam",
    "sg:orig_category":"Kappers",
    "sg:phone":"+31 10 218 4444",
    "sg:postcode":"3051 BD",
    "sg:province":"Zuid-Holland",
    "wof:name":"Salt & Pepper Kappers",
    "wof:placetype":"venue"
},
  "geometry": {"coordinates":[4.482696,51.944981],"type":"Point"}
}