{
  "type": "Feature",
  "properties": {
    "addr:full":"Dorpsstr 16-18 Ouderkerk Ad Yssel South Holland 2935 AC",
    "addr:housenumber":"16-18",
    "addr:postcode":"2935 ac",
    "addr:street":"Yssel",
    "iso:country":"NL",
    "sg:address":"Dorpsstr 16-18",
    "sg:city":"Ouderkerk Ad Yssel",
    "sg:orig_category":"Woninginrichting",
    "sg:phone":"+31 180 681 253",
    "sg:postcode":"2935 AC",
    "sg:province":"South Holland",
    "wof:name":"Weerd, W K De",
    "wof:placetype":"venue"
},
  "geometry": {"coordinates":[4.6348690987,51.9361381531],"type":"Point"}
}