{
  "type": "Feature",
  "properties": {
    "addr:full":"Waterrad 92 Grootebroek North Holland 1613 CR",
    "addr:housenumber":"92",
    "addr:postcode":"1613 cr",
    "addr:street":"Waterrad",
    "iso:country":"NL",
    "sg:address":"Waterrad 92",
    "sg:city":"Grootebroek",
    "sg:orig_category":"Psychotherapeuten",
    "sg:phone":"+31 228 513 630",
    "sg:postcode":"1613 CR",
    "sg:province":"North Holland",
    "wof:name":"Whole-Self",
    "wof:placetype":"venue"
},
  "geometry": {"coordinates":[5.232184,52.688526],"type":"Point"}
}