{
  "type": "Feature",
  "properties": {
    "addr:full":"Lindenlaan 9 Huizen Noord-Holland 1271 AV",
    "addr:housenumber":"9",
    "addr:postcode":"1271 av",
    "addr:street":"Lindenlaan",
    "iso:country":"NL",
    "sg:address":"Lindenlaan 9",
    "sg:city":"Huizen",
    "sg:orig_category":"Makelaars In Onroerend Goed",
    "sg:phone":"+31 35 526 3768",
    "sg:postcode":"1271 AV",
    "sg:province":"Noord-Holland",
    "wof:name":"Makelaarskantoor O.G. De Kleermaeker",
    "wof:placetype":"venue"
},
  "geometry": {"coordinates":[5.235689,52.297012],"type":"Point"}
}