{
  "type": "Feature",
  "properties": {
    "iso:country":"NL",
    "sg:address":"De Reede 55",
    "sg:city":"Veenendaal",
    "sg:orig_category":"Bloemen And Planten",
    "sg:phone":"+31 318 551 577",
    "sg:postcode":"3904 NT",
    "sg:province":"Utrecht",
    "wof:name":"Tuincentrum Boeketterie Jacco Drost",
    "wof:placetype":"venue"
},
  "geometry": {"coordinates":[5.530506,52.025177],"type":"Point"}
}