{
  "type": "Feature",
  "properties": {
    "iso:country":"NL",
    "sg:address":"Brink 13",
    "sg:city":"Dwingeloo",
    "sg:orig_category":"Watersport-, Sport- And Kampeerbenodigdheden Verhuur",
    "sg:phone":"+31 521 591 428",
    "sg:postcode":"7991 CG",
    "sg:province":"Provincie Drenthe",
    "wof:name":"C. Dolsma Vof",
    "wof:placetype":"venue"
},
  "geometry": {"coordinates":[6.3679909706,52.8330726624],"type":"Point"}
}