{
  "type": "Feature",
  "properties": {
    "iso:country":"NL",
    "sg:address":"Dorpsstraat 11",
    "sg:city":"Zoetermeer",
    "sg:orig_category":"Kappers",
    "sg:phone":"+31 79 316 5788",
    "sg:postcode":"2712 AB",
    "sg:province":"South Holland",
    "wof:name":"Enfin Haarmode",
    "wof:placetype":"venue"
},
  "geometry": {"coordinates":[4.4942688942,52.0570869446],"type":"Point"}
}