{
  "type": "Feature",
  "properties": {
    "iso:country":"NL",
    "sg:address":"Tielrodestr 57",
    "sg:city":"Breda",
    "sg:orig_category":"Nagelstudio'S",
    "sg:phone":"+31 76 587 5626",
    "sg:postcode":"4826 CN",
    "sg:province":"Noord-Brabant",
    "wof:name":"Paula",
    "wof:placetype":"venue"
},
  "geometry": {"coordinates":[4.780899,51.612553],"type":"Point"}
}