{
  "type": "Feature",
  "properties": {
    "iso:country":"NL",
    "sg:address":"Gasthuisstraat 15",
    "sg:city":"Heukelum",
    "sg:orig_category":"Muziekinstrumenten Fab",
    "sg:phone":"+31 345 610 358",
    "sg:postcode":"4161 CA",
    "sg:province":"Gelderland",
    "wof:name":"Orgelmaker Gert Van Buuren",
    "wof:placetype":"venue"
},
  "geometry": {"coordinates":[5.077529,51.874168],"type":"Point"}
}