{
  "type": "Feature",
  "properties": {
    "addr:full":"Valksewg 194 Barneveld Gelderland 3771 SJ",
    "addr:housenumber":"194",
    "addr:postcode":"3771",
    "addr:street":"Gelderland",
    "iso:country":"NL",
    "sg:address":"Valksewg 194",
    "sg:city":"Barneveld",
    "sg:orig_category":"Loodgieters",
    "sg:phone":"+31 342 413 508",
    "sg:postcode":"3771 SJ",
    "sg:province":"Gelderland",
    "wof:name":"Blankespoor, J",
    "wof:placetype":"venue"
},
  "geometry": {"coordinates":[5.639873,52.132984],"type":"Point"}
}