{
  "type": "Feature",
  "properties": {
    "addr:full":"Grotestr 76-78-81 Tubbergen Overijssel 7651 CK",
    "addr:housenumber":"76-78-81",
    "addr:postcode":"7651 ck",
    "iso:country":"NL",
    "sg:address":"Grotestr 76-78-81",
    "sg:city":"Tubbergen",
    "sg:orig_category":"Glas, Porselein En Aardewerk",
    "sg:phone":"+31 546 622 551",
    "sg:postcode":"7651 CK",
    "sg:province":"Overijssel",
    "wof:name":"Cuisine Bv, La",
    "wof:placetype":"venue"
},
  "geometry": {"coordinates":[6.782,52.405697],"type":"Point"}
}