{
  "type": "Feature",
  "properties": {
    "addr:full":"Bakkerskampstr 19 Breedenbroek Gelderland 7084 AG",
    "addr:housenumber":"19",
    "addr:postcode":"7084",
    "addr:street":"Bakkerskampstr;Gelderland",
    "iso:country":"NL",
    "sg:address":"Bakkerskampstr 19",
    "sg:city":"Breedenbroek",
    "sg:orig_category":"Verenigingen En Stichtingen",
    "sg:phone":"+31 315 653 104",
    "sg:postcode":"7084 AG",
    "sg:province":"Gelderland",
    "wof:name":"Sportbelangen, Sticht",
    "wof:placetype":"venue"
},
  "geometry": {"coordinates":[6.473229,51.872799],"type":"Point"}
}