{
  "type": "Feature",
  "properties": {
    "addr:full":"Zonstr 59 Hengelo Ov NL.08 7553 DW",
    "addr:housenumber":"59",
    "addr:postcode":"7553 dw",
    "addr:street":"Zonstr;Ov",
    "iso:country":"NL",
    "sg:address":"Zonstr 59",
    "sg:city":"Hengelo Ov",
    "sg:orig_category":"Voegwerken",
    "sg:phone":"+31 74 243 4520",
    "sg:postcode":"7553 DW",
    "sg:province":"NL.08",
    "wof:name":"Huiskes",
    "wof:placetype":"venue"
},
  "geometry": {"coordinates":[6.785039,52.252678],"type":"Point"}
}