{
  "type": "Feature",
  "properties": {
    "iso:country":"NL",
    "sg:address":"Stadionweg 157",
    "sg:city":"Amsterdam",
    "sg:classifiers":[
        {
            "category":"Shopping",
            "subcategory":"Gifts & Souvenirs",
            "type":"Retail Goods"
        }
    ],
    "sg:phone":"+31 20 679 8093",
    "sg:postcode":"1076 NM",
    "sg:province":"Noord-Holland",
    "sg:tags":[
        "geschenken"
    ],
    "wof:name":"Sacha'S Presents",
    "wof:placetype":"venue"
},
  "geometry": {"coordinates":[4.864132,52.345963],"type":"Point"}
}