{
  "type": "Feature",
  "properties": {
    "addr:full":"Galgepad 1 Elst Gld Gelderland 6662 VP",
    "addr:housenumber":"1;6662",
    "addr:street":"Galgepad;Gld Gelderland",
    "iso:country":"NL",
    "sg:address":"Galgepad 1",
    "sg:city":"Elst Gld",
    "sg:orig_category":"Verzekeringen",
    "sg:phone":"+31 481 372 348",
    "sg:postcode":"6662 VP",
    "sg:province":"Gelderland",
    "wof:name":"Henny Willemsen Assurantien",
    "wof:placetype":"venue"
},
  "geometry": {"coordinates":[5.840893,51.912968],"type":"Point"}
}