{
  "type": "Feature",
  "properties": {
    "addr:full":"Bezuidenhoutsewg 106 S Gravenhage South Holland 2594 AZ",
    "addr:housenumber":"106",
    "addr:postcode":"2594 az",
    "addr:street":"S Gravenhage",
    "iso:country":"NL",
    "sg:address":"Bezuidenhoutsewg 106",
    "sg:city":"S Gravenhage",
    "sg:orig_category":"Organisatiebureaus",
    "sg:phone":"+31 70 385 6001",
    "sg:postcode":"2594 AZ",
    "sg:province":"South Holland",
    "wof:name":"Orange Artist Prom",
    "wof:placetype":"venue"
},
  "geometry": {"coordinates":[4.3174152374,52.0839920044],"type":"Point"}
}