{
  "type": "Feature",
  "properties": {
    "addr:full":"Schielandstr 11 Rotterdam South Holland 3043 XH",
    "addr:housenumber":"11",
    "addr:postcode":"3043 xh",
    "addr:street":"Schielandstr",
    "iso:country":"NL",
    "sg:address":"Schielandstr 11",
    "sg:city":"Rotterdam",
    "sg:orig_category":"Hondenscholen",
    "sg:phone":"+31 6 41950187",
    "sg:postcode":"3043 XH",
    "sg:province":"South Holland",
    "wof:name":"Martin Gaus",
    "wof:placetype":"venue"
},
  "geometry": {"coordinates":[4.429201,51.944763],"type":"Point"}
}