{
  "type": "Feature",
  "properties": {
    "addr:full":"D Vd Burgwg 69 Hoek Van Holland Zuid-Holland 3151 XM",
    "addr:housenumber":"69",
    "addr:postcode":"3151 xm",
    "iso:country":"NL",
    "sg:address":"D Vd Burgwg 69",
    "sg:city":"Hoek Van Holland",
    "sg:classifiers":[
        {
            "category":"Travel",
            "subcategory":"Hotels & Motels",
            "type":"Entertainment"
        }
    ],
    "sg:phone":"+31 174 382 273",
    "sg:postcode":"3151 XM",
    "sg:province":"Zuid-Holland",
    "sg:website":"http://www.hotel-noordzee.com",
    "wof:name":"Noordzee",
    "wof:placetype":"venue"
},
  "geometry": {"coordinates":[4.130296,51.986397],"type":"Point"}
}