{
  "type": "Feature",
  "properties": {
    "addr:full":"Hg Miedewg 11 Nes Ameland Provincie Friesland 9163 JS",
    "addr:housenumber":"11",
    "addr:postcode":"9163 js",
    "addr:street":"Friesland",
    "iso:country":"NL",
    "sg:address":"Hg Miedewg 11",
    "sg:city":"Nes Ameland",
    "sg:orig_category":"Fotoreportages",
    "sg:phone":"+31 519 542 879",
    "sg:postcode":"9163 JS",
    "sg:province":"Provincie Friesland",
    "sg:website":"http://www.ameland.org/fotografie",
    "wof:name":"Ameland Fotografie",
    "wof:placetype":"venue"
},
  "geometry": {"coordinates":[5.779911,53.445236],"type":"Point"}
}