{
  "type": "Feature",
  "properties": {
    "iso:country":"NL",
    "sg:address":"Van Bossestraat 27",
    "sg:city":"Amsterdam",
    "sg:orig_category":"Loodgieterswerk, Verwarming And Sanitaire Installaties",
    "sg:phone":"+31 20 682 2898",
    "sg:postcode":"1051 JS",
    "sg:province":"Noord-Holland",
    "wof:name":"W.S.B. Woning Service Bedrijf Van De Ven",
    "wof:placetype":"venue"
},
  "geometry": {"coordinates":[4.868905,52.38121],"type":"Point"}
}