{
  "type": "Feature",
  "properties": {
    "addr:full":"Tilburgseweg 145 Goirle North Brabant 5051 AD",
    "addr:housenumber":"145",
    "addr:postcode":"5051 ad",
    "addr:street":"Tilburgseweg",
    "iso:country":"NL",
    "sg:address":"Tilburgseweg 145",
    "sg:city":"Goirle",
    "sg:orig_category":"Bedrijfs- And Managementsconsultants",
    "sg:phone":"+31 13 534 5293",
    "sg:postcode":"5051 AD",
    "sg:province":"North Brabant",
    "wof:name":"T.F.J.H. Vekemans Management Bv",
    "wof:placetype":"venue"
},
  "geometry": {"coordinates":[5.064057,51.527164],"type":"Point"}
}