{
  "type": "Feature",
  "properties": {
    "addr:full":"Torenstr 172 S Gravenhage South Holland 2513 BW",
    "addr:housenumber":"172",
    "addr:postcode":"2513 bw",
    "addr:street":"S Gravenhage",
    "iso:country":"NL",
    "sg:address":"Torenstr 172",
    "sg:city":"S Gravenhage",
    "sg:orig_category":"Verenigingen En Stichtingen",
    "sg:phone":"+31 70 364 4770",
    "sg:postcode":"2513 BW",
    "sg:province":"South Holland",
    "sg:website":"http://www.anbo.nl",
    "wof:name":"Anbo",
    "wof:placetype":"venue"
},
  "geometry": {"coordinates":[4.30339,52.078442],"type":"Point"}
}