{
  "type": "Feature",
  "properties": {
    "addr:full":"Kamperfoelieln 13 Eindhoven Noord-Brabant 5643 BB",
    "addr:housenumber":"13",
    "addr:postcode":"5643 bb",
    "addr:street":"Kamperfoelieln",
    "iso:country":"NL",
    "sg:address":"Kamperfoelieln 13",
    "sg:city":"Eindhoven",
    "sg:orig_category":"Geluidsinstallaties - Verhuur",
    "sg:phone":"+31 40 213 6454",
    "sg:postcode":"5643 BB",
    "sg:province":"Noord-Brabant",
    "wof:name":"Discovery",
    "wof:placetype":"venue"
},
  "geometry": {"coordinates":[5.498434,51.422974],"type":"Point"}
}