{
  "type": "Feature",
  "properties": {
    "iso:country":"NL",
    "sg:address":"Ootmarsumsestr 407A",
    "sg:city":"Almelo",
    "sg:orig_category":"Kappers",
    "sg:phone":"+31 546 873 515",
    "sg:postcode":"7603 AJ",
    "sg:province":"Overijssel",
    "wof:name":"Barbershop Herensalon",
    "wof:placetype":"venue"
},
  "geometry": {"coordinates":[6.6879329681,52.3716621399],"type":"Point"}
}