{
  "type": "Feature",
  "properties": {
    "iso:country":"NL",
    "sg:address":"V Slingelandtln 71",
    "sg:city":"Woerden",
    "sg:orig_category":"Kunstnijverheidsateliers",
    "sg:phone":"+31 348 502 147",
    "sg:postcode":"3445 EM",
    "sg:province":"Utrecht",
    "wof:name":"Strugarek",
    "wof:placetype":"venue"
},
  "geometry": {"coordinates":[4.906134,52.091278],"type":"Point"}
}