{
  "type": "Feature",
  "properties": {
    "addr:full":"Dorpsweg 68 Hoornaar Zuid-Holland 4223 ND",
    "addr:housenumber":"68",
    "addr:postcode":"4223 nd",
    "addr:street":"Dorpsweg",
    "iso:country":"NL",
    "sg:address":"Dorpsweg 68",
    "sg:city":"Hoornaar",
    "sg:orig_category":"Bedrijfs- And Managementsconsultants",
    "sg:phone":"+31 183 589 192",
    "sg:postcode":"4223 ND",
    "sg:province":"Zuid-Holland",
    "wof:name":"Power Management Systems",
    "wof:placetype":"venue"
},
  "geometry": {"coordinates":[4.947859,51.880245],"type":"Point"}
}