{
  "type": "Feature",
  "properties": {
    "addr:full":"Aartsdijkweg 11 Maasland Zuid-Holland 3155 RR",
    "addr:housenumber":"11",
    "addr:postcode":"3155 rr",
    "addr:street":"Aartsdijkweg",
    "iso:country":"NL",
    "sg:address":"Aartsdijkweg 11",
    "sg:city":"Maasland",
    "sg:orig_category":"Bouwmaterialen Gh",
    "sg:phone":"+31 174 620 511",
    "sg:postcode":"3155 RR",
    "sg:province":"Zuid-Holland",
    "wof:name":"Saint-Gobain Glass Solutions Veromco Maasland",
    "wof:placetype":"venue"
},
  "geometry": {"coordinates":[4.275135,51.936325],"type":"Point"}
}