{
  "type": "Feature",
  "properties": {
    "addr:full":"Cornelis Jolstraat 4 'S Gravenhage Zuid-Holland 2584 ER",
    "addr:housenumber":"4 '",
    "addr:postcode":"2584 er",
    "addr:street":"Cornelis Jolstraat",
    "iso:country":"NL",
    "sg:address":"Cornelis Jolstraat 4",
    "sg:city":"'S Gravenhage",
    "sg:orig_category":"Architecten",
    "sg:phone":"+31 70 354 5275",
    "sg:postcode":"2584 ER",
    "sg:province":"Zuid-Holland",
    "wof:name":"Raamwerk",
    "wof:placetype":"venue"
},
  "geometry": {"coordinates":[4.2856879234,52.1039543152],"type":"Point"}
}