{
  "type": "Feature",
  "properties": {
    "iso:country":"NL",
    "sg:address":"Zinkwerf 21",
    "sg:city":"'S Gravenhage",
    "sg:orig_category":"Schilderwerk",
    "sg:phone":"+31 70 366 3330",
    "sg:postcode":"2544 EC",
    "sg:province":"Zuid-Holland",
    "wof:name":"Verenigde Schildersbedrijven Heko Bv",
    "wof:placetype":"venue"
},
  "geometry": {"coordinates":[4.24787,52.04707],"type":"Point"}
}