{
  "type": "Feature",
  "properties": {
    "addr:full":"Jacob Van Maerlantstraat 21 'S Hertogenbosch North Brabant 5216 JB",
    "addr:housenumber":"21",
    "addr:postcode":"5216 jb",
    "addr:street":"Jacob Van Maerlantstraat;' S Hertogenbosch",
    "iso:country":"NL",
    "sg:address":"Jacob Van Maerlantstraat 21",
    "sg:city":"'S Hertogenbosch",
    "sg:orig_category":"Medische Apparatuur And Prothesen Fab",
    "sg:phone":"+31 73 614 3496",
    "sg:postcode":"5216 JB",
    "sg:province":"North Brabant",
    "wof:name":"Laboratorium Voor Tandtechniek Joost Scheffer",
    "wof:placetype":"venue"
},
  "geometry": {"coordinates":[5.319559,51.685799],"type":"Point"}
}