{
  "type": "Feature",
  "properties": {
    "iso:country":"NL",
    "sg:address":"Lage Haghorst 21",
    "sg:city":"Haghorst",
    "sg:orig_category":"Bedrijfs- And Managementsconsultants",
    "sg:phone":"+31 13 504 1519",
    "sg:postcode":"5089 NC",
    "sg:province":"Noord-Brabant",
    "wof:name":"Systems Transfer",
    "wof:placetype":"venue"
},
  "geometry": {"coordinates":[-80.018333,35.21941],"type":"Point"}
}