{
  "type": "Feature",
  "properties": {
    "iso:country":"NL",
    "sg:address":"Hg Buurlosewg 4",
    "sg:city":"Harskamp",
    "sg:orig_category":"Honden- En Kattentrimsalons",
    "sg:phone":"+31 318 456 840",
    "sg:postcode":"6732 ES",
    "sg:province":"Gelderland",
    "wof:name":"Francis Schotkamp",
    "wof:placetype":"venue"
},
  "geometry": {"coordinates":[-98.924362,20.49721],"type":"Point"}
}