{
  "type": "Feature",
  "properties": {
    "addr:full":"J Mosmansln 47 S Hertogenbosch Noord-Brabant 5237 BB",
    "addr:housenumber":"47",
    "addr:postcode":"5237 bb",
    "addr:street":"S Hertogenbosch",
    "iso:country":"NL",
    "sg:address":"J Mosmansln 47",
    "sg:city":"S Hertogenbosch",
    "sg:orig_category":"Adviesbureaus Bedrijfsorganisatie",
    "sg:phone":"+31 73 611 1330",
    "sg:postcode":"5237 BB",
    "sg:province":"Noord-Brabant",
    "wof:name":"Improned",
    "wof:placetype":"venue"
},
  "geometry": {"coordinates":[5.2993,51.732872],"type":"Point"}
}