{
  "type": "Feature",
  "properties": {
    "addr:full":"P C Hooftln 35B Maassluis Zuid-Holland 3141 AC",
    "addr:housenumber":"35b",
    "addr:postcode":"3141 ac",
    "addr:street":"P C Hooftln",
    "iso:country":"NL",
    "sg:address":"P C Hooftln 35B",
    "sg:city":"Maassluis",
    "sg:orig_category":"Sportverenigingen En Ontspannings- Verenigingen",
    "sg:phone":"+31 6 19436392",
    "sg:postcode":"3141 AC",
    "sg:province":"Zuid-Holland",
    "sg:website":"http://vmz86.voetbalt.nl",
    "wof:name":"Maassluise Zaalvoetbalcompetitie '86, Ver",
    "wof:placetype":"venue"
},
  "geometry": {"coordinates":[4.251202,51.924381],"type":"Point"}
}