{
  "type": "Feature",
  "properties": {
    "addr:full":"Heideburen 53 Heerenveen Friesland 8441 GM",
    "addr:housenumber":"53",
    "addr:postcode":"8441 gm",
    "addr:street":"Heideburen",
    "iso:country":"NL",
    "sg:address":"Heideburen 53",
    "sg:city":"Heerenveen",
    "sg:orig_category":"Elektriciens",
    "sg:phone":"+31 513 623 075",
    "sg:postcode":"8441 GM",
    "sg:province":"Friesland",
    "wof:name":"D.T. Altenburg Elektrotechnisch Bedrijf",
    "wof:placetype":"venue"
},
  "geometry": {"coordinates":[5.927239,52.961349],"type":"Point"}
}