{
  "type": "Feature",
  "properties": {
    "addr:full":"Boeier 158 Barendrecht Zuid-Holland 2991 KH",
    "addr:housenumber":"158",
    "addr:postcode":"2991 kh",
    "addr:street":"Boeier",
    "iso:country":"NL",
    "sg:address":"Boeier 158",
    "sg:city":"Barendrecht",
    "sg:orig_category":"Afslankinstituten",
    "sg:phone":"+31 180 557 002",
    "sg:postcode":"2991 KH",
    "sg:province":"Zuid-Holland",
    "wof:name":"Simons, Anke",
    "wof:placetype":"venue"
},
  "geometry": {"coordinates":[4.547566,51.84441],"type":"Point"}
}