{
  "type": "Feature",
  "properties": {
    "addr:full":"Protonstr 5 Groningen Groningen 9743 AL",
    "addr:housenumber":"5",
    "addr:postcode":"9743 al",
    "addr:street":"Protonstr",
    "iso:country":"NL",
    "sg:address":"Protonstr 5",
    "sg:city":"Groningen",
    "sg:orig_category":"Autorijscholen",
    "sg:phone":"+31 50 318 4000",
    "sg:postcode":"9743 AL",
    "sg:province":"Groningen",
    "wof:name":"Zebra",
    "wof:placetype":"venue"
},
  "geometry": {"coordinates":[6.536441,53.215485],"type":"Point"}
}