{
  "type": "Feature",
  "properties": {
    "iso:country":"NL",
    "sg:address":"Groenhof 163",
    "sg:city":"Amstelveen",
    "sg:orig_category":"Banken And Kredietinstellingen",
    "sg:phone":"+31 20 656 2703",
    "sg:postcode":"1186 EZ",
    "sg:province":"Noord-Holland",
    "wof:name":"Rabobank",
    "wof:placetype":"venue"
},
  "geometry": {"coordinates":[4.869954,52.28923],"type":"Point"}
}