{
  "type": "Feature",
  "properties": {
    "addr:full":"Leidsekd 68Hs Amsterdam North Holland 1016 DA",
    "addr:postcode":"1016 da",
    "iso:country":"NL",
    "sg:address":"Leidsekd 68Hs",
    "sg:city":"Amsterdam",
    "sg:orig_category":"Balletscholen",
    "sg:phone":"+31 20 616 8777",
    "sg:postcode":"1016 DA",
    "sg:province":"North Holland",
    "wof:name":"Marieke Van Der Heijden Balletstudio",
    "wof:placetype":"venue"
},
  "geometry": {"coordinates":[4.893195,52.373119],"type":"Point"}
}