{
  "type": "Feature",
  "properties": {
    "addr:full":"L De Jonghstr 13-19 Rotterdam South Holland 3043 JB",
    "addr:housenumber":"13-19",
    "addr:postcode":"3043 jb",
    "addr:street":"L",
    "iso:country":"NL",
    "sg:address":"L De Jonghstr 13-19",
    "sg:city":"Rotterdam",
    "sg:orig_category":"Lpg-Installaties",
    "sg:phone":"+31 10 462 0261",
    "sg:postcode":"3043 JB",
    "sg:province":"South Holland",
    "wof:name":"Agin Rotterdam Bv",
    "wof:placetype":"venue"
},
  "geometry": {"coordinates":[4.428124,51.941654],"type":"Point"}
}