{
  "type": "Feature",
  "properties": {
    "iso:country":"NL",
    "sg:address":"Erasmusstr 148",
    "sg:city":"Rotterdam",
    "sg:orig_category":"Vertaalbureaus",
    "sg:phone":"+31 6 24542216",
    "sg:postcode":"3035 LJ",
    "sg:province":"Zuid-Holland",
    "wof:name":"Ecdtranslations",
    "wof:placetype":"venue"
},
  "geometry": {"coordinates":[4.480678,51.93148],"type":"Point"}
}