{
  "type": "Feature",
  "properties": {
    "addr:full":"Dijkcentr 45 Roosendaal Noord-Brabant 4706 LB",
    "addr:housenumber":"45",
    "addr:postcode":"4706 lb",
    "addr:street":"Dijkcentr",
    "iso:country":"NL",
    "sg:address":"Dijkcentr 45",
    "sg:city":"Roosendaal",
    "sg:orig_category":"Banken",
    "sg:phone":"+31 165 596 000",
    "sg:postcode":"4706 LB",
    "sg:province":"Noord-Brabant",
    "sg:website":"http://www.rabobank.nl",
    "wof:name":"Rabobank",
    "wof:placetype":"venue"
},
  "geometry": {"coordinates":[4.49167,51.526581],"type":"Point"}
}