{
  "type": "Feature",
  "properties": {
    "addr:full":"Kerkring 21 Fijnaart Noord-Brabant 4793 ES",
    "addr:housenumber":"21",
    "addr:postcode":"4793 es",
    "addr:street":"Kerkring",
    "iso:country":"NL",
    "sg:address":"Kerkring 21",
    "sg:city":"Fijnaart",
    "sg:orig_category":"Bejaarden - Verzorgingstehuizen",
    "sg:phone":"+31 168 462 612",
    "sg:postcode":"4793 ES",
    "sg:province":"Noord-Brabant",
    "wof:name":"Fendertshof",
    "wof:placetype":"venue"
},
  "geometry": {"coordinates":[4.46967,51.636189],"type":"Point"}
}