{
  "type": "Feature",
  "properties": {
    "addr:full":"Oosterdijk 89 Sneek Friesland 8601 BS",
    "addr:housenumber":"89",
    "addr:postcode":"8601 bs",
    "addr:street":"Oosterdijk",
    "iso:country":"NL",
    "sg:address":"Oosterdijk 89",
    "sg:city":"Sneek",
    "sg:orig_category":"Verlichting And Huishoudartikelen",
    "sg:phone":"+31 515 412 874",
    "sg:postcode":"8601 BS",
    "sg:province":"Friesland",
    "wof:name":"De Boer Licht",
    "wof:placetype":"venue"
},
  "geometry": {"coordinates":[5.664994,53.03384],"type":"Point"}
}