{
  "type": "Feature",
  "properties": {
    "iso:country":"NL",
    "sg:address":"Binnensingel 20",
    "sg:city":"Deventer",
    "sg:orig_category":"Boekhouders",
    "sg:phone":"+31 570 611 276",
    "sg:postcode":"7411 PM",
    "sg:province":"Overijssel",
    "wof:name":"F Schuurman",
    "wof:placetype":"venue"
},
  "geometry": {"coordinates":[6.154114,52.256836],"type":"Point"}
}