{
  "type": "Feature",
  "properties": {
    "addr:full":"Boschstr 104 Maastricht Limburg 6211 AZ",
    "addr:housenumber":"104",
    "addr:postcode":"6211 az",
    "iso:country":"NL",
    "sg:address":"Boschstr 104",
    "sg:city":"Maastricht",
    "sg:classifiers":[
        {
            "category":"Travel",
            "subcategory":"Hotels & Motels",
            "type":"Entertainment"
        }
    ],
    "sg:phone":"+31 43 321 3523",
    "sg:postcode":"6211 AZ",
    "sg:province":"Limburg",
    "wof:name":"Du Ch?ne Bv, Maison",
    "wof:placetype":"venue"
},
  "geometry": {"coordinates":[5.68999,50.852402],"type":"Point"}
}