{
  "type": "Feature",
  "properties": {
    "addr:full":"Koninginneln 16 Groningen Groningen 9717 BT",
    "addr:housenumber":"16",
    "addr:postcode":"9717 bt",
    "addr:street":"Koninginneln",
    "iso:country":"NL",
    "sg:address":"Koninginneln 16",
    "sg:city":"Groningen",
    "sg:orig_category":"Logopedisten",
    "sg:phone":"+31 50 318 0260",
    "sg:postcode":"9717 BT",
    "sg:province":"Groningen",
    "wof:name":"Vennema, R",
    "wof:placetype":"venue"
},
  "geometry": {"coordinates":[6.550608,53.221718],"type":"Point"}
}