{
  "type": "Feature",
  "properties": {
    "iso:country":"NL",
    "sg:address":"Winkelwaard 492",
    "sg:city":"Alkmaar",
    "sg:classifiers":[
        {
            "category":"Fast Food",
            "type":"Food & Drink"
        }
    ],
    "sg:phone":"+31 72 561 2229",
    "sg:postcode":"1824 HX",
    "sg:province":"Noord-Holland",
    "sg:tags":[
        "afhaal",
        "restaurant"
    ],
    "wof:name":"Snack-Cafe Smikkelwaard",
    "wof:placetype":"venue"
},
  "geometry": {"coordinates":[4.759981,52.645752],"type":"Point"}
}