{
  "type": "Feature",
  "properties": {
    "addr:full":"Binderseind 50-52 Gemert Noord-Brabant 5421 CJ",
    "addr:housenumber":"50-52",
    "addr:postcode":"5421 cj",
    "addr:street":"Binderseind",
    "iso:country":"NL",
    "sg:address":"Binderseind 50-52",
    "sg:city":"Gemert",
    "sg:orig_category":"Discotheken",
    "sg:phone":"+31 492 361 856",
    "sg:postcode":"5421 CJ",
    "sg:province":"Noord-Brabant",
    "wof:name":"Axis",
    "wof:placetype":"venue"
},
  "geometry": {"coordinates":[5.684716,51.551437],"type":"Point"}
}