{
  "type": "Feature",
  "properties": {
    "addr:full":"Slootwg 4 Schoonhoven South Holland 2871 RP",
    "addr:housenumber":"4",
    "addr:postcode":"2871 rp",
    "addr:street":"Slootwg",
    "iso:country":"NL",
    "sg:address":"Slootwg 4",
    "sg:city":"Schoonhoven",
    "sg:classifiers":[
        {
            "category":"Wholesale",
            "subcategory":"Motor Vehicles",
            "type":"Manufacturing & Wholesale Goods"
        }
    ],
    "sg:phone":"+31 182 387 782",
    "sg:postcode":"2871 RP",
    "sg:province":"South Holland",
    "sg:tags":[
        "scooter",
        "en"
    ],
    "wof:name":"Rovick",
    "wof:placetype":"venue"
},
  "geometry": {"coordinates":[4.862773,51.947605],"type":"Point"}
}