{
  "type": "Feature",
  "properties": {
    "addr:full":"Keizersgr 503 Amsterdam North Holland 1017 DN",
    "addr:housenumber":"503",
    "addr:postcode":"1017 dn",
    "iso:country":"NL",
    "sg:address":"Keizersgr 503",
    "sg:city":"Amsterdam",
    "sg:orig_category":"Antiquiteiten",
    "sg:phone":"+31 20 626 4102",
    "sg:postcode":"1017 DN",
    "sg:province":"North Holland",
    "wof:name":"Meer, A Van Der",
    "wof:placetype":"venue"
},
  "geometry": {"coordinates":[4.888326,52.365299],"type":"Point"}
}