{
  "type": "Feature",
  "properties": {
    "iso:country":"NL",
    "sg:address":"Pereboomwg 117",
    "sg:city":"Almere",
    "sg:orig_category":"Fotojournalisten Freelance",
    "sg:phone":"+31 36 537 8930",
    "sg:postcode":"1326 DX",
    "sg:province":"NL.",
    "wof:name":"Pen, Bertus",
    "wof:placetype":"venue"
},
  "geometry": {"coordinates":[5.2541,52.373631],"type":"Point"}
}