{
  "type": "Feature",
  "properties": {
    "addr:full":"Ryswyksewg 302 S Gravenhage South Holland 2516 ER",
    "addr:housenumber":"302",
    "addr:postcode":"2516 er",
    "addr:street":"S Gravenhage",
    "iso:country":"NL",
    "sg:address":"Ryswyksewg 302",
    "sg:city":"S Gravenhage",
    "sg:orig_category":"Zonnebank- En Solariumcentra",
    "sg:phone":"+31 70 380 1317",
    "sg:postcode":"2516 ER",
    "sg:province":"South Holland",
    "wof:name":"Tropical",
    "wof:placetype":"venue"
},
  "geometry": {"coordinates":[4.33931,52.06786],"type":"Point"}
}