{
  "type": "Feature",
  "properties": {
    "addr:full":"Nansenstr 31 Ryswyk Zh Zuid-Holland 2286 GR",
    "addr:housenumber":"31",
    "addr:postcode":"2286",
    "addr:street":"Nansenstr",
    "iso:country":"NL",
    "sg:address":"Nansenstr 31",
    "sg:city":"Ryswyk Zh",
    "sg:orig_category":"Tegelwerken",
    "sg:phone":"+31 70 393 0277",
    "sg:postcode":"2286 GR",
    "sg:province":"Zuid-Holland",
    "wof:name":"Waasdorp",
    "wof:placetype":"venue"
},
  "geometry": {"coordinates":[4.32436,52.037251],"type":"Point"}
}