{
  "type": "Feature",
  "properties": {
    "addr:full":"Delflandpln 4 Amsterdam Noord-Holland 1062 HR",
    "addr:housenumber":"4",
    "addr:postcode":"1062 hr",
    "addr:street":"Delflandpln",
    "iso:country":"NL",
    "sg:address":"Delflandpln 4",
    "sg:city":"Amsterdam",
    "sg:orig_category":"Kappers",
    "sg:phone":"+31 20 615 4730",
    "sg:postcode":"1062 HR",
    "sg:province":"Noord-Holland",
    "wof:name":"Oosterhuis, Henk",
    "wof:placetype":"venue"
},
  "geometry": {"coordinates":[4.841235,52.349792],"type":"Point"}
}