{
  "type": "Feature",
  "properties": {
    "addr:full":"Beukelswg 10A Rotterdam South Holland 3022 GH",
    "addr:housenumber":"10a",
    "addr:postcode":"3022 gh",
    "addr:street":"Beukelswg",
    "iso:country":"NL",
    "sg:address":"Beukelswg 10A",
    "sg:city":"Rotterdam",
    "sg:orig_category":"Kunstnijverheid",
    "sg:phone":"+31 10 477 2072",
    "sg:postcode":"3022 GH",
    "sg:province":"South Holland",
    "wof:name":"Stickerel",
    "wof:placetype":"venue"
},
  "geometry": {"coordinates":[4.447345,51.91967],"type":"Point"}
}