{
  "type": "Feature",
  "properties": {
    "addr:full":"Populierenln 23 Wieringerwaard Noord-Holland 1766 JD",
    "addr:housenumber":"23",
    "addr:postcode":"1766 jd",
    "addr:street":"Populierenln",
    "iso:country":"NL",
    "sg:address":"Populierenln 23",
    "sg:city":"Wieringerwaard",
    "sg:orig_category":"Onroerende Goederen",
    "sg:phone":"+31 224 223 239",
    "sg:postcode":"1766 JD",
    "sg:province":"Noord-Holland",
    "wof:name":"Ruitenburg",
    "wof:placetype":"venue"
},
  "geometry": {"coordinates":[4.865467,52.835136],"type":"Point"}
}