{
  "type": "Feature",
  "properties": {
    "addr:full":"Benedendorpsstr 15 Zeddam Gelderland 7038 BA",
    "addr:housenumber":"15",
    "addr:postcode":"7038 ba",
    "addr:street":"Benedendorpsstr;Gelderland",
    "iso:country":"NL",
    "sg:address":"Benedendorpsstr 15",
    "sg:city":"Zeddam",
    "sg:classifiers":[
        {
            "category":"Travel",
            "subcategory":"Hotels & Motels",
            "type":"Entertainment"
        }
    ],
    "sg:phone":"+31 314 651 041",
    "sg:postcode":"7038 BA",
    "sg:province":"Gelderland",
    "wof:name":"Moors",
    "wof:placetype":"venue"
},
  "geometry": {"coordinates":[6.259352,51.904011],"type":"Point"}
}