{
  "type": "Feature",
  "properties": {
    "addr:full":"Mortonhof 2 Hoogeveen Drenthe 7908 AP",
    "addr:housenumber":"2",
    "addr:postcode":"7908 ap",
    "addr:street":"Mortonhof",
    "iso:country":"NL",
    "sg:address":"Mortonhof 2",
    "sg:city":"Hoogeveen",
    "sg:orig_category":"Journalisten Freelance",
    "sg:phone":"+31 528 271 500",
    "sg:postcode":"7908 AP",
    "sg:province":"Drenthe",
    "wof:name":"Nijhof, G J",
    "wof:placetype":"venue"
},
  "geometry": {"coordinates":[6.457343,52.720093],"type":"Point"}
}