{
  "type": "Feature",
  "properties": {
    "iso:country":"NL",
    "sg:address":"Past Habetsstr 40",
    "sg:city":"Maastricht",
    "sg:orig_category":"Scholen Voor Basisonderwijs",
    "sg:phone":"+31 43 343 0970",
    "sg:postcode":"6217 KM",
    "sg:province":"Limburg",
    "wof:name":"Oda, St",
    "wof:placetype":"venue"
},
  "geometry": {"coordinates":[5.675869,50.850719],"type":"Point"}
}