{
  "type": "Feature",
  "properties": {
    "addr:full":"Oosterblokker 74 Oosterblokker North Holland 1696 BJ",
    "addr:housenumber":"74",
    "addr:postcode":"1696 bj",
    "addr:street":"Oosterblokker",
    "iso:country":"NL",
    "sg:address":"Oosterblokker 74",
    "sg:city":"Oosterblokker",
    "sg:orig_category":"Verenigingen En Stichtingen",
    "sg:phone":"+31 229 263 431",
    "sg:postcode":"1696 BJ",
    "sg:province":"North Holland",
    "wof:name":"Blindhelp, Sticht",
    "wof:placetype":"venue"
},
  "geometry": {"coordinates":[5.116886,52.668419],"type":"Point"}
}