{
  "type": "Feature",
  "properties": {
    "iso:country":"NL",
    "sg:address":"Remmingweg 37",
    "sg:city":"Almere",
    "sg:orig_category":"Metaalvrije Afvalrecycling",
    "sg:phone":"+31 36 532 3725",
    "sg:postcode":"1332 BD",
    "sg:province":"NL.",
    "wof:name":"Schenk Papier-Recycling Bv",
    "wof:placetype":"venue"
},
  "geometry": {"coordinates":[5.25876,52.408859],"type":"Point"}
}