{
  "type": "Feature",
  "properties": {
    "iso:country":"NL",
    "sg:address":"Rouppe Van Der Voortlaan 1",
    "sg:city":"Vught",
    "sg:classifiers":[
        {
            "category":"Education",
            "subcategory":"Preschool",
            "type":"Public Place"
        }
    ],
    "sg:phone":"+31 73 656 3920",
    "sg:postcode":"5262 HC",
    "sg:province":"North Brabant",
    "sg:tags":[
        "kleuteronderwijs",
        "basis-"
    ],
    "wof:name":"Basisschool De Baarzen",
    "wof:placetype":"venue"
},
  "geometry": {"coordinates":[5.288159,51.640205],"type":"Point"}
}