{
  "type": "Feature",
  "properties": {
    "iso:country":"NL",
    "sg:address":"Marykeln 5",
    "sg:city":"Maurik",
    "sg:orig_category":"Boekhandels",
    "sg:phone":"+31 344 691 735",
    "sg:postcode":"4021 EA",
    "sg:province":"Gelderland",
    "wof:name":"Media Expresse",
    "wof:placetype":"venue"
},
  "geometry": {"coordinates":[5.419951,51.962208],"type":"Point"}
}