{
  "type": "Feature",
  "properties": {
    "iso:country":"NL",
    "sg:address":"C Mohrmannstr 28",
    "sg:city":"Ridderkerk",
    "sg:orig_category":"Fotoreportages",
    "sg:phone":"+31 180 425 692",
    "sg:postcode":"2984 XC",
    "sg:province":"South Holland",
    "sg:website":"http://www.free-foto.nl",
    "wof:name":"Free Foto",
    "wof:placetype":"venue"
},
  "geometry": {"coordinates":[4.618592,51.870201],"type":"Point"}
}