{
  "type": "Feature",
  "properties": {
    "iso:country":"NL",
    "sg:address":"Europalaan 44",
    "sg:city":"Bladel",
    "sg:orig_category":"Levende Dieren Gh",
    "sg:phone":"+31 497 381 450",
    "sg:postcode":"5531 BH",
    "sg:province":"North Brabant",
    "wof:name":"Jos Dijkmans Bv",
    "wof:placetype":"venue"
},
  "geometry": {"coordinates":[5.213852,51.365906],"type":"Point"}
}