{
  "type": "Feature",
  "properties": {
    "addr:full":"Landstr 37 Alkmaar Noord-Holland 1814 BC",
    "addr:housenumber":"37",
    "addr:postcode":"1814 bc",
    "addr:street":"Landstr",
    "iso:country":"NL",
    "sg:address":"Landstr 37",
    "sg:city":"Alkmaar",
    "sg:orig_category":"Vertaalbureaus",
    "sg:phone":"+31 72 511 4096",
    "sg:postcode":"1814 BC",
    "sg:province":"Noord-Holland",
    "wof:name":"Esfinc",
    "wof:placetype":"venue"
},
  "geometry": {"coordinates":[4.746258,52.634361],"type":"Point"}
}