{
  "type": "Feature",
  "properties": {
    "iso:country":"NL",
    "sg:address":"Duivenpad 11",
    "sg:city":"Rotterdam",
    "sg:orig_category":"Sportverenigingen En Ontspannings- Verenigingen",
    "sg:phone":"+31 10 422 4263",
    "sg:postcode":"3055 VE",
    "sg:province":"Zuid-Holland",
    "wof:name":"Duivensteyn",
    "wof:placetype":"venue"
},
  "geometry": {"coordinates":[4.498357,51.964722],"type":"Point"}
}