{
  "type": "Feature",
  "properties": {
    "addr:full":"Munnikendk 18 Kerk Avezaath Gelderland 4012 BH",
    "addr:housenumber":"18",
    "addr:postcode":"4012 bh",
    "addr:street":"Munnikendk",
    "iso:country":"NL",
    "sg:address":"Munnikendk 18",
    "sg:city":"Kerk Avezaath",
    "sg:orig_category":"Schilders",
    "sg:phone":"+31 344 682 390",
    "sg:postcode":"4012 BH",
    "sg:province":"Gelderland",
    "wof:name":"Allround",
    "wof:placetype":"venue"
},
  "geometry": {"coordinates":[5.384368,51.899734],"type":"Point"}
}