{
  "type": "Feature",
  "properties": {
    "addr:full":"Hobbemakd 117 Amsterdam Noord-Holland 1071 XW",
    "addr:housenumber":"117",
    "addr:postcode":"1071 xw",
    "iso:country":"NL",
    "sg:address":"Hobbemakd 117",
    "sg:city":"Amsterdam",
    "sg:orig_category":"Vertalers",
    "sg:phone":"+31 20 671 1981",
    "sg:postcode":"1071 XW",
    "sg:province":"Noord-Holland",
    "wof:name":"Meijers-Butzelaar, Mickey",
    "wof:placetype":"venue"
},
  "geometry": {"coordinates":[4.87701,52.355549],"type":"Point"}
}