{
  "type": "Feature",
  "properties": {
    "addr:full":"Kiosk 12/14 Venray Limburg 5802 NP",
    "addr:housenumber":"14",
    "addr:postcode":"5802 np",
    "iso:country":"NL",
    "sg:address":"Kiosk 12/14",
    "sg:city":"Venray",
    "sg:orig_category":"Bloemen En Planten",
    "sg:phone":"+31 478 510 214",
    "sg:postcode":"5802 NP",
    "sg:province":"Limburg",
    "wof:name":"Bloemenkorf, De",
    "wof:placetype":"venue"
},
  "geometry": {"coordinates":[5.993287,51.521896],"type":"Point"}
}