{
  "type": "Feature",
  "properties": {
    "iso:country":"NL",
    "sg:address":"Dorpskd 98",
    "sg:city":"Wateringen",
    "sg:orig_category":"Grondwerken",
    "sg:phone":"+31 174 297 206",
    "sg:postcode":"2291 HT",
    "sg:province":"South Holland",
    "wof:name":"Kraan Bv, Aannemingsbedrijf Vd",
    "wof:placetype":"venue"
},
  "geometry": {"coordinates":[4.2735,52.023331],"type":"Point"}
}