{
  "type": "Feature",
  "properties": {
    "addr:full":"Oranje Plantage 1 Delft Zuid-Holland 2611 TJ",
    "addr:housenumber":"1",
    "addr:postcode":"2611 tj",
    "addr:street":"Oranje Plantage",
    "iso:country":"NL",
    "sg:address":"Oranje Plantage 1",
    "sg:city":"Delft",
    "sg:orig_category":"Film-, Tv- And Videoproductie",
    "sg:phone":"+31 15 213 7340",
    "sg:postcode":"2611 TJ",
    "sg:province":"Zuid-Holland",
    "wof:name":"Dickmoesker Projectietechniek",
    "wof:placetype":"venue"
},
  "geometry": {"coordinates":[4.3647,52.013519],"type":"Point"}
}