{
  "type": "Feature",
  "properties": {
    "addr:full":"Glacisstr 164 Vlissingen Zeeland 4381 SH",
    "addr:housenumber":"164",
    "addr:postcode":"4381 sh",
    "iso:country":"NL",
    "sg:address":"Glacisstr 164",
    "sg:city":"Vlissingen",
    "sg:orig_category":"Beeldende Kunstenaars",
    "sg:phone":"+31 118 414 407",
    "sg:postcode":"4381 SH",
    "sg:province":"Zeeland",
    "wof:name":"Quelery Maritiem",
    "wof:placetype":"venue"
},
  "geometry": {"coordinates":[3.576968,51.446705],"type":"Point"}
}