{
  "type": "Feature",
  "properties": {
    "addr:full":"Oude Wg 41 Ter Apel Groningen 9561 LB",
    "addr:housenumber":"41",
    "addr:postcode":"9561 lb",
    "addr:street":"Oude Wg",
    "iso:country":"NL",
    "sg:address":"Oude Wg 41",
    "sg:city":"Ter Apel",
    "sg:orig_category":"Scholen Voor Algemeen Voortgezet Onderwijs",
    "sg:phone":"+31 599 581 226",
    "sg:postcode":"9561 LB",
    "sg:province":"Groningen",
    "sg:website":"http://www.rsgterapel.nl",
    "wof:name":"Regionale Scholengem Ter Apel",
    "wof:placetype":"venue"
},
  "geometry": {"coordinates":[7.067239,52.877434],"type":"Point"}
}