{
  "type": "Feature",
  "properties": {
    "addr:full":"Herenstraat 3 Bussum North Holland 1404 HA",
    "addr:housenumber":"3",
    "addr:postcode":"1404 ha",
    "addr:street":"Herenstraat",
    "iso:country":"NL",
    "sg:address":"Herenstraat 3",
    "sg:city":"Bussum",
    "sg:classifiers":[
        {
            "category":"Retail",
            "subcategory":"Photofinishing",
            "type":"Services"
        }
    ],
    "sg:phone":"+31 35 691 0888",
    "sg:postcode":"1404 HA",
    "sg:province":"North Holland",
    "sg:tags":[
        "foto",
        "film"
    ],
    "wof:name":"Autofocus",
    "wof:placetype":"venue"
},
  "geometry": {"coordinates":[5.162174,52.273052],"type":"Point"}
}