{
  "type": "Feature",
  "properties": {
    "addr:full":"Laan Van Verhof 3 Rijnsburg South Holland 2231 BZ",
    "addr:housenumber":"3",
    "addr:postcode":"2231 bz",
    "addr:street":"Laan Van Verhof",
    "iso:country":"NL",
    "sg:address":"Laan Van Verhof 3",
    "sg:city":"Rijnsburg",
    "sg:orig_category":"Werving And Selectie Van Tijdelijk Personeel And Uitzendkantoren",
    "sg:phone":"+31 71 403 1287",
    "sg:postcode":"2231 BZ",
    "sg:province":"South Holland",
    "wof:name":"Luba",
    "wof:placetype":"venue"
},
  "geometry": {"coordinates":[4.450524807,52.1857147217],"type":"Point"}
}