{
  "type": "Feature",
  "properties": {
    "addr:full":"Heiberg 13 Veldhoven North Brabant 5504 PA",
    "addr:housenumber":"13",
    "addr:postcode":"5504 pa",
    "addr:street":"Heiberg",
    "iso:country":"NL",
    "sg:address":"Heiberg 13",
    "sg:city":"Veldhoven",
    "sg:orig_category":"Hogedrukreinigings- Apparatuur",
    "sg:phone":"+31 40 253 1822",
    "sg:postcode":"5504 PA",
    "sg:province":"North Brabant",
    "wof:name":"Interclean Benelux Bv",
    "wof:placetype":"venue"
},
  "geometry": {"coordinates":[5.399285,51.400398],"type":"Point"}
}