{
  "type": "Feature",
  "properties": {
    "iso:country":"NL",
    "sg:address":"Kr Spieringwg 491",
    "sg:city":"Vyfhuizen",
    "sg:orig_category":"Kinderopvang",
    "sg:phone":"+31 23 558 0286",
    "sg:postcode":"2141 AJ",
    "sg:province":"Noord-Holland",
    "wof:name":"Need A Nanny",
    "wof:placetype":"venue"
},
  "geometry": {"coordinates":[4.679655,52.352299],"type":"Point"}
}