{
  "type": "Feature",
  "properties": {
    "addr:full":"De Hoogjens 13 Sleeuwyk Noord-Brabant 4254 XV",
    "addr:housenumber":"13",
    "addr:postcode":"4254 xv",
    "addr:street":"De Hoogjens",
    "iso:country":"NL",
    "sg:address":"De Hoogjens 13",
    "sg:city":"Sleeuwyk",
    "sg:orig_category":"Autoschade- Herstelbedrijven",
    "sg:phone":"+31 183 301 075",
    "sg:postcode":"4254 XV",
    "sg:province":"Noord-Brabant",
    "wof:name":"Csa",
    "wof:placetype":"venue"
},
  "geometry": {"coordinates":[4.957436,51.811214],"type":"Point"}
}