{
  "type": "Feature",
  "properties": {
    "addr:full":"Westwykstr 24 Steenwyk Overijssel 8331 MK",
    "addr:housenumber":"24",
    "addr:postcode":"8331",
    "addr:street":"Westwykstr;Overijssel",
    "iso:country":"NL",
    "sg:address":"Westwykstr 24",
    "sg:city":"Steenwyk",
    "sg:orig_category":"Bloemen En Planten",
    "sg:phone":"+31 521 521 986",
    "sg:postcode":"8331 MK",
    "sg:province":"Overijssel",
    "wof:name":"Nijeveense Bloemenhandel Vof",
    "wof:placetype":"venue"
},
  "geometry": {"coordinates":[21.751289,41.60281],"type":"Point"}
}