{
  "type": "Feature",
  "properties": {
    "iso:country":"NL",
    "sg:address":"Esscheweg 99",
    "sg:city":"Vught",
    "sg:classifiers":[
        {
            "category":"Professional",
            "subcategory":"Accounting & Tax Preparation",
            "type":"Services"
        }
    ],
    "sg:phone":"+31 73 656 2581",
    "sg:postcode":"5262 TV",
    "sg:province":"North Brabant",
    "sg:tags":[
        "accountant"
    ],
    "wof:name":"Accountantskantoor De Jong Bv",
    "wof:placetype":"venue"
},
  "geometry": {"coordinates":[5.281088,51.642929],"type":"Point"}
}