{
  "type": "Feature",
  "properties": {
    "addr:full":"Driebergseweg 9 Zeist Utrecht 3708 JA",
    "addr:housenumber":"9",
    "addr:postcode":"3708 ja",
    "addr:street":"Driebergseweg",
    "iso:country":"NL",
    "sg:address":"Driebergseweg 9",
    "sg:city":"Zeist",
    "sg:orig_category":"Beveiligingsdiensten And Bewakingsbedrijven",
    "sg:phone":"+31 30 692 4281",
    "sg:postcode":"3708 JA",
    "sg:province":"Utrecht",
    "wof:name":"Eerste Zeister Gecombineerde Nachtveilig",
    "wof:placetype":"venue"
},
  "geometry": {"coordinates":[5.252521,52.072334],"type":"Point"}
}