{
  "type": "Feature",
  "properties": {
    "iso:country":"NL",
    "sg:address":"Eikenstr 14",
    "sg:city":"Haarlem",
    "sg:orig_category":"Glazenwasserijen",
    "sg:phone":"+31 23 527 2397",
    "sg:postcode":"2023 TM",
    "sg:province":"Noord-Holland",
    "wof:name":"Westhof",
    "wof:placetype":"venue"
},
  "geometry": {"coordinates":[4.640265,52.400368],"type":"Point"}
}