{
  "type": "Feature",
  "properties": {
    "addr:full":"Ruysdaelstraat 4 Heemskerk Noord-Holland 1964 RN",
    "addr:housenumber":"4",
    "addr:postcode":"1964 rn",
    "addr:street":"Ruysdaelstraat",
    "iso:country":"NL",
    "sg:address":"Ruysdaelstraat 4",
    "sg:city":"Heemskerk",
    "sg:classifiers":[
        {
            "category":"Food & Beverages",
            "subcategory":"Fruits & Vegetables",
            "type":"Retail Goods"
        }
    ],
    "sg:phone":"+31 251 247 835",
    "sg:postcode":"1964 RN",
    "sg:province":"Noord-Holland",
    "sg:tags":[
        "groenten"
    ],
    "wof:name":"De Groentemarkt",
    "wof:placetype":"venue"
},
  "geometry": {"coordinates":[4.668849,52.509876],"type":"Point"}
}