{
  "type": "Feature",
  "properties": {
    "addr:full":"Slotlaan 52 Etten-Leur Noord-Brabant 4873 AG",
    "addr:housenumber":"52",
    "addr:postcode":"4873",
    "addr:street":"Slotlaan",
    "iso:country":"NL",
    "sg:address":"Slotlaan 52",
    "sg:city":"Etten-Leur",
    "sg:orig_category":"Fotostudio'S And Fotografen",
    "sg:phone":"+31 76 501 7091",
    "sg:postcode":"4873 AG",
    "sg:province":"Noord-Brabant",
    "wof:name":"Foto L. Hillemans",
    "wof:placetype":"venue"
},
  "geometry": {"coordinates":[4.640301,51.566849],"type":"Point"}
}