{
  "type": "Feature",
  "properties": {
    "iso:country":"NL",
    "sg:address":"Slotlaan 52",
    "sg:city":"Etten-Leur",
    "sg:orig_category":"Fotostudio'S And Fotografen",
    "sg:phone":"+31 76 501 7091",
    "sg:postcode":"4873 AG",
    "sg:province":"Noord-Brabant",
    "wof:name":"Foto L. Hillemans",
    "wof:placetype":"venue"
},
  "geometry": {"coordinates":[4.640301,51.566849],"type":"Point"}
}