{
  "type": "Feature",
  "properties": {
    "iso:country":"NL",
    "sg:address":"Raadhuisstraat 15",
    "sg:city":"Oud Vossemeer",
    "sg:orig_category":"Fietshandelaren",
    "sg:phone":"+31 166 672 467",
    "sg:postcode":"4698 AJ",
    "sg:province":"Zeeland",
    "wof:name":"Fa. J J Vos En Zonen",
    "wof:placetype":"venue"
},
  "geometry": {"coordinates":[4.198067,51.570248],"type":"Point"}
}