{
  "type": "Feature",
  "properties": {
    "addr:full":"Middelgraafln 47 Arnhem Gelderland 6832 AN",
    "addr:housenumber":"47",
    "addr:postcode":"6832 an",
    "addr:street":"Middelgraafln",
    "iso:country":"NL",
    "sg:address":"Middelgraafln 47",
    "sg:city":"Arnhem",
    "sg:orig_category":"Postkantoren",
    "sg:phone":"+31 26 321 3472",
    "sg:postcode":"6832 AN",
    "sg:province":"Gelderland",
    "sg:website":"http://www.postkantoor.nl",
    "wof:name":"Postkantoor",
    "wof:placetype":"venue"
},
  "geometry": {"coordinates":[5.908069,51.966919],"type":"Point"}
}