{
  "type": "Feature",
  "properties": {
    "addr:full":"Woudhuizerallee 193 Apeldoorn Gelderland 7325 RT",
    "addr:housenumber":"193",
    "addr:postcode":"7325 rt",
    "addr:street":"Woudhuizerallee;Gelderland",
    "iso:country":"NL",
    "sg:address":"Woudhuizerallee 193",
    "sg:city":"Apeldoorn",
    "sg:orig_category":"Adviesbureaus Bedrijfsorganisatie",
    "sg:phone":"+31 55 360 6693",
    "sg:postcode":"7325 RT",
    "sg:province":"Gelderland",
    "sg:website":"http://www.bitall.nl",
    "wof:name":"Bitall Bv",
    "wof:placetype":"venue"
},
  "geometry": {"coordinates":[6.018205,52.213783],"type":"Point"}
}