{
  "type": "Feature",
  "properties": {
    "addr:full":"Goudsesingel 89 Rotterdam South Holland 3031 EE",
    "addr:housenumber":"89",
    "addr:postcode":"3031 ee",
    "addr:street":"Goudsesingel",
    "iso:country":"NL",
    "sg:address":"Goudsesingel 89",
    "sg:city":"Rotterdam",
    "sg:orig_category":"Kappers",
    "sg:phone":"+31 10 433 3200",
    "sg:postcode":"3031 EE",
    "sg:province":"South Holland",
    "wof:name":"Maanurdin Herensalon",
    "wof:placetype":"venue"
},
  "geometry": {"coordinates":[4.49063,51.924541],"type":"Point"}
}