{
  "type": "Feature",
  "properties": {
    "addr:full":"Laagewei 5 Goes Zeeland 4464 AK",
    "addr:housenumber":"5",
    "addr:postcode":"4464 ak",
    "addr:street":"Laagewei",
    "iso:country":"NL",
    "sg:address":"Laagewei 5",
    "sg:city":"Goes",
    "sg:orig_category":"Adviesbureaus Personeel",
    "sg:phone":"+31 113 271 270",
    "sg:postcode":"4464 AK",
    "sg:province":"Zeeland",
    "sg:website":"http://www.personeelsadviesdienst.nl",
    "wof:name":"Hartog, Personeelsdienst Den",
    "wof:placetype":"venue"
},
  "geometry": {"coordinates":[-83.914169,39.768833],"type":"Point"}
}