{
  "type": "Feature",
  "properties": {
    "addr:full":"Rompert Centrum 18 'S Hertogenbosch Noord-Brabant 5233 RE",
    "addr:housenumber":"18",
    "addr:postcode":"5233 re",
    "addr:street":"Rompert Centrum;' S",
    "iso:country":"NL",
    "sg:address":"Rompert Centrum 18",
    "sg:city":"'S Hertogenbosch",
    "sg:orig_category":"Boekhouders",
    "sg:phone":"+31 73 642 2051",
    "sg:postcode":"5233 RE",
    "sg:province":"Noord-Brabant",
    "wof:name":"Administratie- En Belastingkantoor P. Su",
    "wof:placetype":"venue"
},
  "geometry": {"coordinates":[5.312441,51.712185],"type":"Point"}
}