{
  "type": "Feature",
  "properties": {
    "addr:full":"J Vd Heydenstr 14 Hoogerheide Noord-Brabant 4631 NH",
    "addr:housenumber":"14",
    "addr:postcode":"4631 nh",
    "iso:country":"NL",
    "sg:address":"J Vd Heydenstr 14",
    "sg:city":"Hoogerheide",
    "sg:orig_category":"Woningbouw- Verenigingen En -Stichtingen",
    "sg:phone":"+31 164 613 313",
    "sg:postcode":"4631 NH",
    "sg:province":"Noord-Brabant",
    "sg:website":"http://www.wswoensdrecht.nl",
    "wof:name":"Woensdrecht, Woningsticht",
    "wof:placetype":"venue"
},
  "geometry": {"coordinates":[4.3259358406,51.4212875366],"type":"Point"}
}