{
  "type": "Feature",
  "properties": {
    "addr:full":"Markt 18 Wageningen Gelderland 6701 CZ",
    "addr:housenumber":"18;6701",
    "addr:street":"Markt;Gelderland",
    "iso:country":"NL",
    "sg:address":"Markt 18",
    "sg:city":"Wageningen",
    "sg:orig_category":"Kappers",
    "sg:phone":"+31 317 412 231",
    "sg:postcode":"6701 CZ",
    "sg:province":"Gelderland",
    "wof:name":"Kapsalon Bouwman Vof",
    "wof:placetype":"venue"
},
  "geometry": {"coordinates":[5.6624999046,51.9643669128],"type":"Point"}
}