{
  "type": "Feature",
  "properties": {
    "addr:full":"Scheepstimmerm Ln 18 Rotterdam South Holland 3011 BS",
    "addr:housenumber":"18",
    "addr:postcode":"3011 bs",
    "addr:street":"Scheepstimmerm Ln",
    "iso:country":"NL",
    "sg:address":"Scheepstimmerm Ln 18",
    "sg:city":"Rotterdam",
    "sg:orig_category":"Grafisch Ontwerpers",
    "sg:phone":"+31 10 436 1956",
    "sg:postcode":"3011 BS",
    "sg:province":"South Holland",
    "wof:name":"Front-Taal",
    "wof:placetype":"venue"
},
  "geometry": {"coordinates":[4.478312,51.910789],"type":"Point"}
}