{
  "type": "Feature",
  "properties": {
    "addr:full":"Swentiboldweg 100 Geleen Limburg 6167 RK",
    "addr:housenumber":"100",
    "addr:postcode":"6167 rk",
    "addr:street":"Geleen Limburg",
    "iso:country":"NL",
    "sg:address":"Swentiboldweg 100",
    "sg:city":"Geleen",
    "sg:orig_category":"Overheidsdiensten",
    "sg:phone":"+31 46 485 3464",
    "sg:postcode":"6167 RK",
    "sg:province":"Limburg",
    "wof:name":"Atlanta Naturistenvereniging",
    "wof:placetype":"venue"
},
  "geometry": {"coordinates":[5.8018670082,51.0079154968],"type":"Point"}
}