{
  "type": "Feature",
  "properties": {
    "iso:country":"NL",
    "sg:address":"Rozenhof 3",
    "sg:city":"Zwaag",
    "sg:orig_category":"Autorijscholen",
    "sg:phone":"+31 229 239 055",
    "sg:postcode":"1689 GZ",
    "sg:province":"North Holland",
    "wof:name":"Weerd, J Van Der",
    "wof:placetype":"venue"
},
  "geometry": {"coordinates":[5.073885,52.666988],"type":"Point"}
}