{
  "type": "Feature",
  "properties": {
    "addr:full":"Driemanssteewg 186 Rotterdam Zuid-Holland 3084 CB",
    "addr:housenumber":"186",
    "addr:postcode":"3084 cb",
    "iso:country":"NL",
    "sg:address":"Driemanssteewg 186",
    "sg:city":"Rotterdam",
    "sg:orig_category":"Elektrotechnische Apparatuur - Fabrieken En Groothandel",
    "sg:phone":"+31 10 273 2006",
    "sg:postcode":"3084 CB",
    "sg:province":"Zuid-Holland",
    "wof:name":"Id\u00fa Trading",
    "wof:placetype":"venue"
},
  "geometry": {"coordinates":[4.461016,51.864174],"type":"Point"}
}