{
  "type": "Feature",
  "properties": {
    "addr:full":"Zwolsewg 29 Heerde Gelderland 8181 AB",
    "addr:housenumber":"29",
    "addr:postcode":"8181 ab",
    "addr:street":"Zwolsewg;Gelderland",
    "iso:country":"NL",
    "sg:address":"Zwolsewg 29",
    "sg:city":"Heerde",
    "sg:orig_category":"Kinderopvang",
    "sg:phone":"+31 578 611 055",
    "sg:postcode":"8181 AB",
    "sg:province":"Gelderland",
    "wof:name":"Samsam",
    "wof:placetype":"venue"
},
  "geometry": {"coordinates":[6.044263,52.390999],"type":"Point"}
}