{
  "type": "Feature",
  "properties": {
    "addr:full":"P Kiesstr 69 Haarlem Noord-Holland 2013 BG",
    "addr:housenumber":"69",
    "addr:postcode":"2013",
    "iso:country":"NL",
    "sg:address":"P Kiesstr 69",
    "sg:city":"Haarlem",
    "sg:orig_category":"Beeldende Kunstenaars",
    "sg:phone":"+31 23 532 7767",
    "sg:postcode":"2013 BG",
    "sg:province":"Noord-Holland",
    "wof:name":"Hellingman, G",
    "wof:placetype":"venue"
},
  "geometry": {"coordinates":[-82.312515,33.415298],"type":"Point"}
}