{
  "type": "Feature",
  "properties": {
    "iso:country":"NL",
    "sg:address":"Westpln 2",
    "sg:city":"Rotterdam",
    "sg:orig_category":"Arbeidsbureaus",
    "sg:phone":"+31 10 281 0823",
    "sg:postcode":"3016 BL",
    "sg:province":"Zuid-Holland",
    "sg:website":"http://www.job112.nl",
    "wof:name":"112 Bv",
    "wof:placetype":"venue"
},
  "geometry": {"coordinates":[4.478934,51.909023],"type":"Point"}
}