{
  "type": "Feature",
  "properties": {
    "addr:full":"Koningin Julianaweg 16 Maasland Zuid-Holland 3155 XD",
    "addr:housenumber":"16",
    "addr:postcode":"3155 xd",
    "addr:street":"Koningin Julianaweg",
    "iso:country":"NL",
    "sg:address":"Koningin Julianaweg 16",
    "sg:city":"Maasland",
    "sg:orig_category":"Goederenvervoer Over De Weg",
    "sg:phone":"+31 10 592 3964",
    "sg:postcode":"3155 XD",
    "sg:province":"Zuid-Holland",
    "wof:name":"Internationaal Transportbedr Gebr. Vreek",
    "wof:placetype":"venue"
},
  "geometry": {"coordinates":[4.268985,51.929592],"type":"Point"}
}