{
  "type": "Feature",
  "properties": {
    "addr:full":"Voorwg 157 Zoetermeer Zuid-Holland 2716 NJ",
    "addr:housenumber":"157",
    "addr:postcode":"2716 nj",
    "iso:country":"NL",
    "sg:address":"Voorwg 157",
    "sg:city":"Zoetermeer",
    "sg:orig_category":"Adviesbureaus Gezondheidszorg",
    "sg:phone":"+31 79 352 1749",
    "sg:postcode":"2716 NJ",
    "sg:province":"Zuid-Holland",
    "wof:name":"Bun Bv",
    "wof:placetype":"venue"
},
  "geometry": {"coordinates":[4.44573,52.06834],"type":"Point"}
}