{
  "type": "Feature",
  "properties": {
    "iso:country":"NL",
    "sg:address":"Promenade 128",
    "sg:city":"Zoetermeer",
    "sg:orig_category":"Fotoreportages",
    "sg:phone":"+31 79 331 9487",
    "sg:postcode":"2711 AT",
    "sg:province":"Zuid-Holland",
    "sg:website":"http://www.pictures.nl",
    "wof:name":"Koudstaal, Peter",
    "wof:placetype":"venue"
},
  "geometry": {"coordinates":[4.488925,52.06308],"type":"Point"}
}