{
  "type": "Feature",
  "properties": {
    "iso:country":"NL",
    "sg:address":"Ribeslaan 1",
    "sg:city":"Rotterdam",
    "sg:orig_category":"Vertaal- And Tolkenbureaus",
    "sg:phone":"+31 10 422 9689",
    "sg:postcode":"3053 MJ",
    "sg:province":"Zuid-Holland",
    "wof:name":"H M Nieva-Balk",
    "wof:placetype":"venue"
},
  "geometry": {"coordinates":[4.476345,51.960381],"type":"Point"}
}