{
  "type": "Feature",
  "properties": {
    "addr:full":"Boonsweg 7 Heinenoord Zuid-Holland 3274 LH",
    "addr:housenumber":"7",
    "addr:postcode":"3274 lh",
    "addr:street":"Boonsweg",
    "iso:country":"NL",
    "sg:address":"Boonsweg 7",
    "sg:city":"Heinenoord",
    "sg:orig_category":"Meubelzaken, Woning- And Keukeninrichting",
    "sg:phone":"+31 186 601 355",
    "sg:postcode":"3274 LH",
    "sg:province":"Zuid-Holland",
    "wof:name":"H. Kwakernaat Bedding",
    "wof:placetype":"venue"
},
  "geometry": {"coordinates":[4.520326,51.812229],"type":"Point"}
}