{
  "type": "Feature",
  "properties": {
    "addr:full":"Soembastraat 67 Dordrecht South Holland 3312 HT",
    "addr:housenumber":"67",
    "addr:postcode":"3312 ht",
    "addr:street":"Soembastraat",
    "iso:country":"NL",
    "sg:address":"Soembastraat 67",
    "sg:city":"Dordrecht",
    "sg:orig_category":"Diverse Grafische Activiteiten",
    "sg:phone":"+31 78 613 8364",
    "sg:postcode":"3312 HT",
    "sg:province":"South Holland",
    "wof:name":"Duotone",
    "wof:placetype":"venue"
},
  "geometry": {"coordinates":[4.688512,51.806938],"type":"Point"}
}