{
  "type": "Feature",
  "properties": {
    "addr:full":"Tongelresestr 341 Eindhoven Noord-Brabant 5642 NB",
    "addr:housenumber":"341",
    "addr:postcode":"5642 nb",
    "iso:country":"NL",
    "sg:address":"Tongelresestr 341",
    "sg:city":"Eindhoven",
    "sg:orig_category":"Cafetaria'S",
    "sg:phone":"+31 40 281 4556",
    "sg:postcode":"5642 NB",
    "sg:province":"Noord-Brabant",
    "wof:name":"Milaan",
    "wof:placetype":"venue"
},
  "geometry": {"coordinates":[5.508826,51.442177],"type":"Point"}
}