{
  "type": "Feature",
  "properties": {
    "addr:full":"Narcis 18 Krimpen Ad Yssel Zuid-Holland 2925 XC",
    "addr:housenumber":"18;2925",
    "addr:postcode":"xc",
    "addr:street":"Narcis",
    "iso:country":"NL",
    "sg:address":"Narcis 18",
    "sg:city":"Krimpen Ad Yssel",
    "sg:orig_category":"Horloges En Klokken - Reparatie En Onderhoud",
    "sg:phone":"+31 180 520 540",
    "sg:postcode":"2925 XC",
    "sg:province":"Zuid-Holland",
    "wof:name":"Suiker, A",
    "wof:placetype":"venue"
},
  "geometry": {"coordinates":[4.62334,51.921043],"type":"Point"}
}