{
  "type": "Feature",
  "properties": {
    "addr:full":"Dommelsewg 112 Valkenswaard Noord-Brabant 5554 NV",
    "addr:housenumber":"112",
    "addr:postcode":"5554 nv",
    "iso:country":"NL",
    "sg:address":"Dommelsewg 112",
    "sg:city":"Valkenswaard",
    "sg:orig_category":"Muziekinstrumenten En Bladmuziek",
    "sg:phone":"+31 40 201 5318",
    "sg:postcode":"5554 NV",
    "sg:province":"Noord-Brabant",
    "wof:name":"Muziekwinkel, De",
    "wof:placetype":"venue"
},
  "geometry": {"coordinates":[5.447879,51.3512],"type":"Point"}
}