{
  "type": "Feature",
  "properties": {
    "addr:full":"Holendrechtpln 37 Amsterdam Zuidoost Noord-Holland 1106 LP",
    "addr:housenumber":"37",
    "addr:postcode":"zuidoost;1106 lp",
    "addr:street":"Holendrechtpln",
    "iso:country":"NL",
    "sg:address":"Holendrechtpln 37",
    "sg:city":"Amsterdam Zuidoost",
    "sg:orig_category":"Verenigingsgebouwen",
    "sg:phone":"+31 20 696 0737",
    "sg:postcode":"1106 LP",
    "sg:province":"Noord-Holland",
    "wof:name":"Holendrecht, Sticht",
    "wof:placetype":"venue"
},
  "geometry": {"coordinates":[4.964349,52.299805],"type":"Point"}
}