{
  "type": "Feature",
  "properties": {
    "addr:full":"Havenzicht 74 Almere Flevoland 1357 NR",
    "addr:housenumber":"74",
    "addr:postcode":"1357",
    "addr:street":"Havenzicht;Flevoland;Nr",
    "iso:country":"NL",
    "sg:address":"Havenzicht 74",
    "sg:city":"Almere",
    "sg:orig_category":"Hypotheken And Hypotheekbanken",
    "sg:phone":"+31 36 534 9978",
    "sg:postcode":"1357 NR",
    "sg:province":"Flevoland",
    "wof:name":"Hpf Consultants",
    "wof:placetype":"venue"
},
  "geometry": {"coordinates":[5.220457,52.334068],"type":"Point"}
}