{
  "type": "Feature",
  "properties": {
    "addr:full":"De Voormars 12 Ommen Overijssel 7731 DD",
    "addr:housenumber":"12",
    "addr:postcode":"7731 dd",
    "addr:street":"De Voormars",
    "iso:country":"NL",
    "sg:address":"De Voormars 12",
    "sg:city":"Ommen",
    "sg:orig_category":"Artsen And Specialisten",
    "sg:phone":"+31 529 451 465",
    "sg:postcode":"7731 DD",
    "sg:province":"Overijssel",
    "wof:name":"H.J. Bezemer",
    "wof:placetype":"venue"
},
  "geometry": {"coordinates":[6.41719,52.519779],"type":"Point"}
}