{
  "type": "Feature",
  "properties": {
    "addr:full":"Ambergeel 36 Zoetermeer Zuid-Holland 2718 BN",
    "addr:housenumber":"36",
    "addr:postcode":"2718 bn",
    "addr:street":"Ambergeel",
    "iso:country":"NL",
    "sg:address":"Ambergeel 36",
    "sg:city":"Zoetermeer",
    "sg:orig_category":"Metaalwerken",
    "sg:phone":"+31 79 361 0991",
    "sg:postcode":"2718 BN",
    "sg:province":"Zuid-Holland",
    "wof:name":"Zonweringsmontagebedrijf J. & S.",
    "wof:placetype":"venue"
},
  "geometry": {"coordinates":[4.492246,52.043049],"type":"Point"}
}