{
  "type": "Feature",
  "properties": {
    "iso:country":"NL",
    "sg:address":"Regattawg 10",
    "sg:city":"Groningen",
    "sg:orig_category":"Waterbouwkundige Werken",
    "sg:phone":"+31 50 541 2986",
    "sg:postcode":"9731 AJ",
    "sg:province":"Groningen",
    "wof:name":"Dekker Groningen Bv, Gebr",
    "wof:placetype":"venue"
},
  "geometry": {"coordinates":[6.6016302109,53.2238235474],"type":"Point"}
}