{
  "type": "Feature",
  "properties": {
    "iso:country":"NL",
    "sg:address":"Groenling 13",
    "sg:city":"Boxmeer",
    "sg:orig_category":"Schoonheidssalons",
    "sg:phone":"+31 485 572 305",
    "sg:postcode":"5831 MZ",
    "sg:province":"Noord-Brabant",
    "wof:name":"Schoonheidssalon Diny Blom",
    "wof:placetype":"venue"
},
  "geometry": {"coordinates":[5.952104,51.639153],"type":"Point"}
}