{
  "type": "Feature",
  "properties": {
    "addr:full":"Rozenstr 31 Oss Noord-Brabant 5342 BA",
    "addr:housenumber":"31",
    "addr:postcode":"5342 ba",
    "addr:street":"Rozenstr",
    "iso:country":"NL",
    "sg:address":"Rozenstr 31",
    "sg:city":"Oss",
    "sg:orig_category":"Natuurvoeding En Reformartikelen",
    "sg:phone":"+31 412 639 867",
    "sg:postcode":"5342 BA",
    "sg:province":"Noord-Brabant",
    "sg:website":"http://www.bewell.com",
    "wof:name":"Be Well Vof",
    "wof:placetype":"venue"
},
  "geometry": {"coordinates":[-77.235214,38.312599],"type":"Point"}
}