{
  "type": "Feature",
  "properties": {
    "addr:full":"Kanaalstr 47 Heerde Gelderland 8181 HV",
    "addr:housenumber":"47",
    "addr:postcode":"8181 hv",
    "addr:street":"Kanaalstr;Gelderland",
    "iso:country":"NL",
    "sg:address":"Kanaalstr 47",
    "sg:city":"Heerde",
    "sg:classifiers":[
        {
            "category":"Cinema",
            "subcategory":"Drive-in Theater",
            "type":"Entertainment"
        }
    ],
    "sg:phone":"+31 578 696 469",
    "sg:postcode":"8181 HV",
    "sg:province":"Gelderland",
    "sg:tags":[
        "drive-in-shows"
    ],
    "wof:name":"Evor Music Live In",
    "wof:placetype":"venue"
},
  "geometry": {"coordinates":[6.049231,52.387196],"type":"Point"}
}