{
  "type": "Feature",
  "properties": {
    "addr:full":"J Schorerln 131 S Gravenhage Zuid-Holland 2525 ZR",
    "addr:housenumber":"131;gravenhage",
    "addr:postcode":"2525 zr",
    "addr:street":"S",
    "iso:country":"NL",
    "sg:address":"J Schorerln 131",
    "sg:city":"S Gravenhage",
    "sg:orig_category":"Feestverlichting",
    "sg:phone":"+31 6 24684858",
    "sg:postcode":"2525 ZR",
    "sg:province":"Zuid-Holland",
    "wof:name":"Rainville",
    "wof:placetype":"venue"
},
  "geometry": {"coordinates":[4.30248,52.062462],"type":"Point"}
}