{
  "type": "Feature",
  "properties": {
    "addr:full":"Sibbergrubbe 14 Valkenburg Lb Limburg 6301 AA",
    "addr:housenumber":"14",
    "addr:postcode":"lb;6301 aa",
    "addr:street":"Sibbergrubbe",
    "iso:country":"NL",
    "sg:address":"Sibbergrubbe 14",
    "sg:city":"Valkenburg Lb",
    "sg:orig_category":"Hypotheken And Hypotheekbanken",
    "sg:phone":"+31 43 601 4010",
    "sg:postcode":"6301 AA",
    "sg:province":"Limburg",
    "wof:name":"Roks Eurlings Vastgoed",
    "wof:placetype":"venue"
},
  "geometry": {"coordinates":[5.835657,50.856739],"type":"Point"}
}