{
  "type": "Feature",
  "properties": {
    "iso:country":"NL",
    "sg:address":"Hoofdstr 14",
    "sg:city":"Amstenrade",
    "sg:orig_category":"Horloges En Klokken - Reparatie En Onderhoud",
    "sg:phone":"+31 46 442 5807",
    "sg:postcode":"6436 CE",
    "sg:province":"Limburg",
    "wof:name":"Horlogerie Lisette",
    "wof:placetype":"venue"
},
  "geometry": {"coordinates":[5.924058,50.941311],"type":"Point"}
}