{
  "type": "Feature",
  "properties": {
    "addr:full":"J Verhulststr 4 Amsterdam North Holland 1071 NC",
    "addr:housenumber":"4",
    "addr:postcode":"1071 nc",
    "iso:country":"NL",
    "sg:address":"J Verhulststr 4",
    "sg:city":"Amsterdam",
    "sg:orig_category":"Filmstudio'S En -Productie",
    "sg:phone":"+31 20 664 9318",
    "sg:postcode":"1071 NC",
    "sg:province":"North Holland",
    "sg:website":"http://www.deorganisatie.net",
    "wof:name":"Organisatie, De",
    "wof:placetype":"venue"
},
  "geometry": {"coordinates":[4.8771090508,52.3559150696],"type":"Point"}
}