{
  "type": "Feature",
  "properties": {
    "addr:full":"Gasthuisstr 18 Doesburg Gelderland 6981 CS",
    "addr:housenumber":"18",
    "addr:postcode":"6981 cs",
    "addr:street":"Gasthuisstr;Gelderland",
    "iso:country":"NL",
    "sg:address":"Gasthuisstr 18",
    "sg:city":"Doesburg",
    "sg:orig_category":"Kappers",
    "sg:phone":"+31 313 475 445",
    "sg:postcode":"6981 CS",
    "sg:province":"Gelderland",
    "wof:name":"Peter",
    "wof:placetype":"venue"
},
  "geometry": {"coordinates":[6.135443,52.01516],"type":"Point"}
}