{
  "type": "Feature",
  "properties": {
    "addr:full":"Oostsingel 18 Delft Zuid-Holland 2612 HB",
    "addr:housenumber":"18",
    "addr:postcode":"2612 hb",
    "addr:street":"Oostsingel",
    "iso:country":"NL",
    "sg:address":"Oostsingel 18",
    "sg:city":"Delft",
    "sg:orig_category":"Kappers",
    "sg:phone":"+31 15 213 1471",
    "sg:postcode":"2612 HB",
    "sg:province":"Zuid-Holland",
    "wof:name":"Hairstyling Oostpoort",
    "wof:placetype":"venue"
},
  "geometry": {"coordinates":[4.3693261147,52.0115127563],"type":"Point"}
}