{
  "type": "Feature",
  "properties": {
    "addr:full":"Melkpad 42 Rotterdam Zuid-Holland 3075 HP",
    "addr:housenumber":"42",
    "addr:postcode":"3075 hp",
    "addr:street":"Melkpad",
    "iso:country":"NL",
    "sg:address":"Melkpad 42",
    "sg:city":"Rotterdam",
    "sg:orig_category":"Verhuizingen",
    "sg:phone":"+31 10 419 5787",
    "sg:postcode":"3075 HP",
    "sg:province":"Zuid-Holland",
    "wof:name":"Nobelen, R F Van De",
    "wof:placetype":"venue"
},
  "geometry": {"coordinates":[4.511089,51.888817],"type":"Point"}
}