{
  "type": "Feature",
  "properties": {
    "addr:full":"Zeilmakerstraat 8 Assen Drenthe 9403 VA",
    "addr:housenumber":"8",
    "addr:postcode":"9403",
    "addr:street":"Zeilmakerstraat",
    "iso:country":"NL",
    "sg:address":"Zeilmakerstraat 8",
    "sg:city":"Assen",
    "sg:orig_category":"Verlichting And Huishoudartikelen",
    "sg:phone":"+31 592 374 739",
    "sg:postcode":"9403 VA",
    "sg:province":"Drenthe",
    "wof:name":"Trendytexx",
    "wof:placetype":"venue"
},
  "geometry": {"coordinates":[6.583252,53.009598],"type":"Point"}
}