{
  "type": "Feature",
  "properties": {
    "addr:full":"Ribbiusstr 1 Helmond Noord-Brabant 5708 AT",
    "addr:housenumber":"1",
    "addr:postcode":"5708",
    "addr:street":"Ribbiusstr",
    "iso:country":"NL",
    "sg:address":"Ribbiusstr 1",
    "sg:city":"Helmond",
    "sg:orig_category":"Adviesbureaus Bedrijfsorganisatie",
    "sg:phone":"+31 492 590 127",
    "sg:postcode":"5708 AT",
    "sg:province":"Noord-Brabant",
    "wof:name":"Edcar Bv",
    "wof:placetype":"venue"
},
  "geometry": {"coordinates":[5.62252,51.48835],"type":"Point"}
}