{
  "type": "Feature",
  "properties": {
    "iso:country":"NL",
    "sg:address":"Karveel 5975",
    "sg:city":"Lelystad",
    "sg:orig_category":"Boekhouders",
    "sg:phone":"+31 320 242 933",
    "sg:postcode":"8242 WJ",
    "sg:province":"Flevoland",
    "wof:name":"Adm.-Balastingadviesbureau A. Onderwater",
    "wof:placetype":"venue"
},
  "geometry": {"coordinates":[5.454579,52.521095],"type":"Point"}
}