{
  "type": "Feature",
  "properties": {
    "iso:country":"NL",
    "sg:address":"Kloosterstr 62",
    "sg:city":"Venlo",
    "sg:orig_category":"Opticiens",
    "sg:phone":"+31 77 382 8571",
    "sg:postcode":"5921 HD",
    "sg:province":"Limburg",
    "wof:name":"Peeters Bv, Jos",
    "wof:placetype":"venue"
},
  "geometry": {"coordinates":[6.1513829231,51.3670539856],"type":"Point"}
}