{
  "type": "Feature",
  "properties": {
    "addr:full":"Barbizonln 70 Capelle Ad Yssel Zuid-Holland 2908 ME",
    "addr:housenumber":"70",
    "addr:postcode":"2908 me",
    "addr:street":"Barbizonln",
    "iso:country":"NL",
    "sg:address":"Barbizonln 70",
    "sg:city":"Capelle Ad Yssel",
    "sg:orig_category":"Grafische Bedrijven",
    "sg:phone":"+31 10 286 1370",
    "sg:postcode":"2908 ME",
    "sg:province":"Zuid-Holland",
    "wof:name":"Printcare",
    "wof:placetype":"venue"
},
  "geometry": {"coordinates":[4.5846,51.923401],"type":"Point"}
}