{
  "type": "Feature",
  "properties": {
    "addr:full":"Muddegoorn 120 Assen Drenthe 9403 NL",
    "addr:housenumber":"120",
    "addr:postcode":"9403 nl",
    "addr:street":"Muddegoorn",
    "iso:country":"NL",
    "sg:address":"Muddegoorn 120",
    "sg:city":"Assen",
    "sg:orig_category":"Webdesign Bureaus",
    "sg:phone":"+31 6 19302278",
    "sg:postcode":"9403 NL",
    "sg:province":"Drenthe",
    "sg:website":"http://www.4ro.nl",
    "wof:name":"4Ro Design Studio",
    "wof:placetype":"venue"
},
  "geometry": {"coordinates":[6.5854320526,53.0155792236],"type":"Point"}
}