{
  "type": "Feature",
  "properties": {
    "iso:country":"NL",
    "sg:address":"Postbus 129",
    "sg:city":"Haarlem",
    "sg:orig_category":"Organisatiebureaus",
    "sg:phone":"+31 23 512 5555",
    "sg:postcode":"2000 AC",
    "sg:province":"Noord-Holland",
    "sg:website":"http://www.move-now.com",
    "wof:name":"Move The Conceptworkers",
    "wof:placetype":"venue"
},
  "geometry": {"coordinates":[4.6369800568,52.3796081543],"type":"Point"}
}