{
  "type": "Feature",
  "properties": {
    "addr:full":"Grotestr 22 Baarlo Lb Limburg 5991 AW",
    "addr:housenumber":"22",
    "addr:postcode":"lb;5991 aw",
    "addr:street":"Grotestr",
    "iso:country":"NL",
    "sg:address":"Grotestr 22",
    "sg:city":"Baarlo Lb",
    "sg:classifiers":[
        {
            "category":"Food & Beverages",
            "subcategory":"Fruits & Vegetables",
            "type":"Retail Goods"
        }
    ],
    "sg:phone":"+31 77 477 2554",
    "sg:postcode":"5991 AW",
    "sg:province":"Limburg",
    "sg:tags":[
        "en",
        "groenten"
    ],
    "wof:name":"Eppelke, Ut",
    "wof:placetype":"venue"
},
  "geometry": {"coordinates":[6.094294,51.331516],"type":"Point"}
}