{
  "type": "Feature",
  "properties": {
    "iso:country":"NL",
    "sg:address":"Postbus 135 Centr Mag/Kant",
    "sg:city":"Bennebroek",
    "sg:orig_category":"Woninginrichting",
    "sg:phone":"+31 23 584 8412",
    "sg:postcode":"2120 AC",
    "sg:province":"North Holland",
    "wof:name":"Berg & Berg Bv",
    "wof:placetype":"venue"
},
  "geometry": {"coordinates":[4.5932078362,52.32213974],"type":"Point"}
}