{
  "type": "Feature",
  "properties": {
    "addr:full":"Burgemeester Buiskoolweg 9 Sellingen Groningen 9551 TX",
    "addr:housenumber":"9",
    "addr:postcode":"9551 tx",
    "addr:street":"Burgemeester Buiskoolweg",
    "iso:country":"NL",
    "sg:address":"Burgemeester Buiskoolweg 9",
    "sg:city":"Sellingen",
    "sg:orig_category":"Goederenvervoer Over De Weg",
    "sg:phone":"+31 599 322 544",
    "sg:postcode":"9551 TX",
    "sg:province":"Groningen",
    "wof:name":"J. Schoenmaker",
    "wof:placetype":"venue"
},
  "geometry": {"coordinates":[-100.07679,31.168989],"type":"Point"}
}