{
  "type": "Feature",
  "properties": {
    "iso:country":"NL",
    "sg:address":"Oortlaan 110",
    "sg:city":"Veldhoven",
    "sg:orig_category":"Verhuur Audiovisuele Apparatuur",
    "sg:phone":"+31 40 254 1268",
    "sg:postcode":"5505 RG",
    "sg:province":"North Brabant",
    "wof:name":"Barthels P.A. Verhuur",
    "wof:placetype":"venue"
},
  "geometry": {"coordinates":[5.394306,51.412525],"type":"Point"}
}