{
  "type": "Feature",
  "properties": {
    "addr:full":"Dr D Bakkerln 72 Bloemendaal North Holland 2061 EX",
    "addr:housenumber":"72",
    "addr:postcode":"2061 ex",
    "addr:street":"Dr;Bakkerln",
    "iso:country":"NL",
    "sg:address":"Dr D Bakkerln 72",
    "sg:city":"Bloemendaal",
    "sg:orig_category":"Vertalers",
    "sg:phone":"+31 23 526 8070",
    "sg:postcode":"2061 EX",
    "sg:province":"North Holland",
    "wof:name":"Transed",
    "wof:placetype":"venue"
},
  "geometry": {"coordinates":[4.622791,52.405197],"type":"Point"}
}