{
  "type": "Feature",
  "properties": {
    "addr:full":"Kemenawg 36 Aalten Gelderland 7122 XK",
    "addr:housenumber":"36",
    "addr:postcode":"7122 xk",
    "addr:street":"Kemenawg;Gelderland",
    "iso:country":"NL",
    "sg:address":"Kemenawg 36",
    "sg:city":"Aalten",
    "sg:orig_category":"Adviesbureaus Planologie",
    "sg:phone":"+31 543 474 402",
    "sg:postcode":"7122 XK",
    "sg:province":"Gelderland",
    "wof:name":"Joost, A",
    "wof:placetype":"venue"
},
  "geometry": {"coordinates":[6.567264,51.924194],"type":"Point"}
}