{
  "type": "Feature",
  "properties": {
    "iso:country":"NL",
    "sg:address":"Polderwg 102",
    "sg:city":"Amsterdam",
    "sg:orig_category":"Beeldende Kunstenaars",
    "sg:phone":"+31 20 665 2724",
    "sg:postcode":"1093 KP",
    "sg:province":"Noord-Holland",
    "wof:name":"Wouda Buurman-Hondius",
    "wof:placetype":"venue"
},
  "geometry": {"coordinates":[4.930667,52.357864],"type":"Point"}
}