{
  "type": "Feature",
  "properties": {
    "addr:full":"Liendenlaan 5 Tiel Gelderland 4006 CA",
    "addr:housenumber":"5",
    "addr:postcode":"4006 ca",
    "addr:street":"Liendenlaan;Gelderland",
    "iso:country":"NL",
    "sg:address":"Liendenlaan 5",
    "sg:city":"Tiel",
    "sg:orig_category":"Meubelreparatie And -Restauratie",
    "sg:phone":"+31 344 610 959",
    "sg:postcode":"4006 CA",
    "sg:province":"Gelderland",
    "wof:name":"Kulekci",
    "wof:placetype":"venue"
},
  "geometry": {"coordinates":[5.40726,51.879829],"type":"Point"}
}