{
  "type": "Feature",
  "properties": {
    "addr:full":"Stappegoorweg 229 Tilburg Noord-Brabant 5022 DE",
    "addr:housenumber":"229",
    "addr:postcode":"5022 de",
    "addr:street":"Stappegoorweg",
    "iso:country":"NL",
    "sg:address":"Stappegoorweg 229",
    "sg:city":"Tilburg",
    "sg:orig_category":"Bloemen And Planten",
    "sg:phone":"+31 13 535 6991",
    "sg:postcode":"5022 DE",
    "sg:province":"Noord-Brabant",
    "wof:name":"Tuincentrum Tilburg Zuid",
    "wof:placetype":"venue"
},
  "geometry": {"coordinates":[5.08292,51.53788],"type":"Point"}
}