{
  "type": "Feature",
  "properties": {
    "addr:full":"Koningin Wilhelminalaan 34 Gorinchem Zuid-Holland 4205 EX",
    "addr:housenumber":"34",
    "addr:postcode":"4205 ex",
    "addr:street":"Koningin Wilhelminalaan",
    "iso:country":"NL",
    "sg:address":"Koningin Wilhelminalaan 34",
    "sg:city":"Gorinchem",
    "sg:orig_category":"Damesmodezaken",
    "sg:phone":"+31 183 623 993",
    "sg:postcode":"4205 EX",
    "sg:province":"Zuid-Holland",
    "wof:name":"Modehuis De Bruin",
    "wof:placetype":"venue"
},
  "geometry": {"coordinates":[4.967637,51.840611],"type":"Point"}
}