{
  "type": "Feature",
  "properties": {
    "addr:full":"Schoolstraat 2A Zuidwolde Dr Drenthe 7921 AV",
    "addr:housenumber":"2a",
    "addr:postcode":"7921 av",
    "addr:street":"Schoolstraat;Dr",
    "iso:country":"NL",
    "sg:address":"Schoolstraat 2A",
    "sg:city":"Zuidwolde Dr",
    "sg:orig_category":"Banken And Kredietinstellingen",
    "sg:phone":"+31 528 373 080",
    "sg:postcode":"7921 AV",
    "sg:province":"Drenthe",
    "wof:name":"Sns Bank Drenthe",
    "wof:placetype":"venue"
},
  "geometry": {"coordinates":[6.42853,52.67675],"type":"Point"}
}