{
  "type": "Feature",
  "properties": {
    "addr:full":"Z Achterwg 27 Ooltgensplaat Zuid-Holland 3257 BG",
    "addr:housenumber":"27",
    "addr:postcode":"3257",
    "iso:country":"NL",
    "sg:address":"Z Achterwg 27",
    "sg:city":"Ooltgensplaat",
    "sg:orig_category":"Verenigingsgebouwen",
    "sg:phone":"+31 187 632 724",
    "sg:postcode":"3257 BG",
    "sg:province":"Zuid-Holland",
    "wof:name":"Elthato",
    "wof:placetype":"venue"
},
  "geometry": {"coordinates":[4.348876,51.682713],"type":"Point"}
}