{
  "type": "Feature",
  "properties": {
    "addr:full":"Brinkln 5 Bussum Noord-Holland 1404 EP",
    "addr:housenumber":"5",
    "addr:postcode":"1404 ep",
    "addr:street":"Brinkln",
    "iso:country":"NL",
    "sg:address":"Brinkln 5",
    "sg:city":"Bussum",
    "sg:orig_category":"Adviesbureaus Bouwkunde",
    "sg:phone":"+31 35 694 0471",
    "sg:postcode":"1404 EP",
    "sg:province":"Noord-Holland",
    "wof:name":"Bouwpartn Cons",
    "wof:placetype":"venue"
},
  "geometry": {"coordinates":[5.162649,52.282185],"type":"Point"}
}