{
  "type": "Feature",
  "properties": {
    "iso:country":"NL",
    "sg:address":"Huismanstraat 44",
    "sg:city":"Huissen",
    "sg:orig_category":"Granen, Zaden And Diervoeders Gh",
    "sg:phone":"+31 26 325 0935",
    "sg:postcode":"6851 GV",
    "sg:province":"Gelderland",
    "wof:name":"Van Vorselen Bv",
    "wof:placetype":"venue"
},
  "geometry": {"coordinates":[5.93275,51.93211],"type":"Point"}
}