{
  "type": "Feature",
  "properties": {
    "iso:country":"NL",
    "sg:address":"Maliebaan 45",
    "sg:city":"Utrecht",
    "sg:orig_category":"Adviesbureaus Bedrijfsorganisatie",
    "sg:phone":"+31 30 239 4040",
    "sg:postcode":"3581 CD",
    "sg:province":"Utrecht",
    "sg:website":"http://www.kessels-smit.nl",
    "wof:name":"Kessels & Smit The Learning Company",
    "wof:placetype":"venue"
},
  "geometry": {"coordinates":[5.132905,52.09042],"type":"Point"}
}