{
  "type": "Feature",
  "properties": {
    "addr:full":"Wulpendaal 35 Nieuwerkerk Ad Ijssel Zuid-Holland 2914 EP",
    "addr:housenumber":"35",
    "addr:postcode":"ijssel;2914 ep",
    "addr:street":"Wulpendaal",
    "iso:country":"NL",
    "sg:address":"Wulpendaal 35",
    "sg:city":"Nieuwerkerk Ad Ijssel",
    "sg:classifiers":[
        {
            "category":"Education",
            "subcategory":"Preschool",
            "type":"Public Place"
        }
    ],
    "sg:phone":"+31 180 319 536",
    "sg:postcode":"2914 EP",
    "sg:province":"Zuid-Holland",
    "sg:tags":[
        "kleuteronderwijs",
        "basis-"
    ],
    "wof:name":"De Wingerd",
    "wof:placetype":"venue"
},
  "geometry": {"coordinates":[4.615289,51.970982],"type":"Point"}
}