{
  "type": "Feature",
  "properties": {
    "addr:full":"Looiersdreef 688 Apeldoorn Gelderland 7328 HW",
    "addr:housenumber":"688",
    "addr:postcode":"7328 hw",
    "addr:street":"Looiersdreef;Gelderland",
    "iso:country":"NL",
    "sg:address":"Looiersdreef 688",
    "sg:city":"Apeldoorn",
    "sg:orig_category":"Adviesbureaus Bouwkunde",
    "sg:phone":"+31 55 540 1891",
    "sg:postcode":"7328 HW",
    "sg:province":"Gelderland",
    "wof:name":"Visser, Rense",
    "wof:placetype":"venue"
},
  "geometry": {"coordinates":[5.985242,52.201859],"type":"Point"}
}