{
  "type": "Feature",
  "properties": {
    "addr:full":"Zwarteweg 40 Rheden Gelderland 6991 EJ",
    "addr:housenumber":"40",
    "addr:postcode":"6991 ej",
    "addr:street":"Zwarteweg;Gelderland",
    "iso:country":"NL",
    "sg:address":"Zwarteweg 40",
    "sg:city":"Rheden",
    "sg:classifiers":[
        {
            "category":"Fast Food",
            "type":"Food & Drink"
        }
    ],
    "sg:phone":"+31 26 495 9003",
    "sg:postcode":"6991 EJ",
    "sg:province":"Gelderland",
    "sg:tags":[
        "afhaal",
        "restaurant"
    ],
    "wof:name":"Bestaria Hartje Rheden",
    "wof:placetype":"venue"
},
  "geometry": {"coordinates":[6.030268,52.002167],"type":"Point"}
}