{
  "type": "Feature",
  "properties": {
    "addr:full":"Schubertlaan 81 Rotterdam Zuid-Holland 3055 HN",
    "addr:housenumber":"81",
    "addr:postcode":"3055 hn",
    "addr:street":"Schubertlaan",
    "iso:country":"NL",
    "sg:address":"Schubertlaan 81",
    "sg:city":"Rotterdam",
    "sg:orig_category":"Meubelzaken, Woning- And Keukeninrichting",
    "sg:phone":"+31 10 422 4358",
    "sg:postcode":"3055 HN",
    "sg:province":"Zuid-Holland",
    "wof:name":"D'Ananas Bv",
    "wof:placetype":"venue"
},
  "geometry": {"coordinates":[4.505636,51.961678],"type":"Point"}
}