{
  "type": "Feature",
  "properties": {
    "addr:full":"Brouwersgr 212 Amsterdam Noord-Holland 1013 HD",
    "addr:housenumber":"212",
    "addr:postcode":"1013 hd",
    "iso:country":"NL",
    "sg:address":"Brouwersgr 212",
    "sg:city":"Amsterdam",
    "sg:orig_category":"Werving En Selectie",
    "sg:phone":"+31 20 620 1862",
    "sg:postcode":"1013 HD",
    "sg:province":"Noord-Holland",
    "wof:name":"Thiel, Van",
    "wof:placetype":"venue"
},
  "geometry": {"coordinates":[4.8869757652,52.3817481995],"type":"Point"}
}