{
  "type": "Feature",
  "properties": {
    "addr:full":"Economiestr 6 Sittard Limburg 6135 KV",
    "addr:housenumber":"6",
    "addr:postcode":"6135 kv",
    "addr:street":"Economiestr",
    "iso:country":"NL",
    "sg:address":"Economiestr 6",
    "sg:city":"Sittard",
    "sg:orig_category":"Verhuizingen",
    "sg:phone":"+31 46 451 2836",
    "sg:postcode":"6135 KV",
    "sg:province":"Limburg",
    "wof:name":"Boetzkes & Zoon",
    "wof:placetype":"venue"
},
  "geometry": {"coordinates":[5.840668,50.997334],"type":"Point"}
}