{
  "type": "Feature",
  "properties": {
    "addr:full":"Briandstraat 16 Zevenaar Gelderland 6904 NW",
    "addr:housenumber":"16",
    "addr:postcode":"6904 nw",
    "addr:street":"Briandstraat",
    "iso:country":"NL",
    "sg:address":"Briandstraat 16",
    "sg:city":"Zevenaar",
    "sg:orig_category":"Werving And Selectie Van Vast Personeel",
    "sg:phone":"+31 316 528 563",
    "sg:postcode":"6904 NW",
    "sg:province":"Gelderland",
    "wof:name":"Bmo Breuning, Mens En Organisatievraagst",
    "wof:placetype":"venue"
},
  "geometry": {"coordinates":[6.0493359566,51.9307289124],"type":"Point"}
}