{
  "type": "Feature",
  "properties": {
    "iso:country":"NL",
    "sg:address":"Breestraat 38",
    "sg:city":"Leiden",
    "sg:orig_category":"Bloemen And Planten",
    "sg:phone":"+31 71 512 5600",
    "sg:postcode":"2311 CS",
    "sg:province":"Zuid-Holland",
    "wof:name":"Zijdevlinder De",
    "wof:placetype":"venue"
},
  "geometry": {"coordinates":[4.487026,52.160099],"type":"Point"}
}