{
  "type": "Feature",
  "properties": {
    "addr:full":"Joep Nicolasstraat 5 Roermond Limburg 6041 JZ",
    "addr:housenumber":"5",
    "addr:postcode":"6041 jz",
    "addr:street":"Joep Nicolasstraat",
    "iso:country":"NL",
    "sg:address":"Joep Nicolasstraat 5",
    "sg:city":"Roermond",
    "sg:classifiers":[
        {
            "category":"Shopping",
            "subcategory":"Clothing, Apparel, & Fashions",
            "type":"Retail Goods"
        }
    ],
    "sg:phone":"+31 475 334 592",
    "sg:postcode":"6041 JZ",
    "sg:province":"Limburg",
    "sg:tags":[
        "ondergoed",
        "lingerie"
    ],
    "wof:name":"Rob Adriaans Kousen- En Sokkenspeciaalzaak",
    "wof:placetype":"venue"
},
  "geometry": {"coordinates":[5.990542,51.191895],"type":"Point"}
}