{
  "type": "Feature",
  "properties": {
    "iso:country":"NL",
    "sg:address":"Twynstr 49",
    "sg:city":"Utrecht",
    "sg:orig_category":"Elektrotechnische Artikelen",
    "sg:phone":"+31 30 231 5406",
    "sg:postcode":"3511 ZH",
    "sg:province":"Utrecht",
    "wof:name":"Dam, Radio Van",
    "wof:placetype":"venue"
},
  "geometry": {"coordinates":[5.123325,52.08268],"type":"Point"}
}