{
  "type": "Feature",
  "properties": {
    "addr:full":"Weesperzijde 126 Amsterdam Noord-Holland 1091 ER",
    "addr:housenumber":"126",
    "addr:postcode":"1091 er",
    "addr:street":"Weesperzijde",
    "iso:country":"NL",
    "sg:address":"Weesperzijde 126",
    "sg:city":"Amsterdam",
    "sg:orig_category":"Metaalwerken",
    "sg:phone":"+31 20 665 2393",
    "sg:postcode":"1091 ER",
    "sg:province":"Noord-Holland",
    "wof:name":"Louverdrape Nederland Vof",
    "wof:placetype":"venue"
},
  "geometry": {"coordinates":[4.912452,52.350204],"type":"Point"}
}