{
  "type": "Feature",
  "properties": {
    "iso:country":"NL",
    "sg:address":"Weesperzijde 126",
    "sg:city":"Amsterdam",
    "sg:orig_category":"Metaalwerken",
    "sg:phone":"+31 20 665 2393",
    "sg:postcode":"1091 ER",
    "sg:province":"Noord-Holland",
    "wof:name":"Louverdrape Nederland Vof",
    "wof:placetype":"venue"
},
  "geometry": {"coordinates":[4.912452,52.350204],"type":"Point"}
}