{
  "type": "Feature",
  "properties": {
    "iso:country":"NL",
    "sg:address":"Vierlingsbeekseweg 53",
    "sg:city":"Overloon",
    "sg:orig_category":"Bedrijfsinventaris Gh",
    "sg:phone":"+31 6 55801339",
    "sg:postcode":"5825 AT",
    "sg:province":"Noord-Brabant",
    "wof:name":"H & K Overloon",
    "wof:placetype":"venue"
},
  "geometry": {"coordinates":[5.955773,51.574524],"type":"Point"}
}