{
  "type": "Feature",
  "properties": {
    "iso:country":"NL",
    "sg:address":"Wg-Plein 516",
    "sg:city":"Amsterdam",
    "sg:orig_category":"Diverse Grafische Activiteiten",
    "sg:phone":"+31 20 612 1975",
    "sg:postcode":"1054 SJ",
    "sg:province":"North Holland",
    "wof:name":"Koeweiden Postma Associates",
    "wof:placetype":"venue"
},
  "geometry": {"coordinates":[4.87163,52.364368],"type":"Point"}
}