{
  "type": "Feature",
  "properties": {
    "iso:country":"NL",
    "sg:address":"Postbus 408",
    "sg:city":"Almelo",
    "sg:orig_category":"Adviesbureaus Bedrijfsorganisatie",
    "sg:phone":"+31 546 869 132",
    "sg:postcode":"7600 AK",
    "sg:province":"Overijssel",
    "wof:name":"Heijenga'S Bv",
    "wof:placetype":"venue"
},
  "geometry": {"coordinates":[6.664543,52.354954],"type":"Point"}
}