{
  "type": "Feature",
  "properties": {
    "addr:full":"Fluwelen Burgwal 1D Den Haag South Holland 2511 CH",
    "addr:housenumber":"1d",
    "addr:postcode":"2511",
    "addr:street":"Fluwelen Burgwal",
    "iso:country":"NL",
    "sg:address":"Fluwelen Burgwal 1D",
    "sg:city":"Den Haag",
    "sg:orig_category":"Werving And Selectie Van Tijdelijk Personeel And Uitzendkantoren",
    "sg:phone":"+31 70 312 1921",
    "sg:postcode":"2511 CH",
    "sg:province":"South Holland",
    "wof:name":"Content",
    "wof:placetype":"venue"
},
  "geometry": {"coordinates":[4.3181738853,52.0801773071],"type":"Point"}
}