{
  "type": "Feature",
  "properties": {
    "addr:full":"Bergwg 207B Rotterdam South Holland 3037 EJ",
    "addr:housenumber":"207b",
    "addr:postcode":"3037 ej",
    "iso:country":"NL",
    "sg:address":"Bergwg 207B",
    "sg:city":"Rotterdam",
    "sg:orig_category":"Verzekeringen - Verzekeringskantoren",
    "sg:phone":"+31 10 243 0320",
    "sg:postcode":"3037 EJ",
    "sg:province":"South Holland",
    "wof:name":"Flexi International",
    "wof:placetype":"venue"
},
  "geometry": {"coordinates":[4.47688,51.93623],"type":"Point"}
}