{
  "type": "Feature",
  "properties": {
    "iso:country":"NL",
    "sg:address":"Robertaland 225",
    "sg:city":"'S Gravenhage",
    "sg:orig_category":"Loodgieterswerk, Verwarming And Sanitaire Installaties",
    "sg:phone":"+31 70 383 8293",
    "sg:postcode":"2591 HX",
    "sg:province":"Zuid-Holland",
    "wof:name":"J. Lut",
    "wof:placetype":"venue"
},
  "geometry": {"coordinates":[4.364293,52.098602],"type":"Point"}
}