{
  "type": "Feature",
  "properties": {
    "addr:full":"Oud Huizerwg 2 Naarden Noord-Holland 1411 GZ",
    "addr:housenumber":"2",
    "addr:postcode":"1411 gz",
    "addr:street":"Oud Huizerwg",
    "iso:country":"NL",
    "sg:address":"Oud Huizerwg 2",
    "sg:city":"Naarden",
    "sg:orig_category":"Partyservice",
    "sg:phone":"+31 35 694 1140",
    "sg:postcode":"1411 GZ",
    "sg:province":"Noord-Holland",
    "wof:name":"Gasterije, De",
    "wof:placetype":"venue"
},
  "geometry": {"coordinates":[5.192958,52.304436],"type":"Point"}
}