{
  "type": "Feature",
  "properties": {
    "addr:full":"Vleesstr 51 Venlo Limburg 5911 JD",
    "addr:housenumber":"51",
    "addr:postcode":"5911 jd",
    "addr:street":"Vleesstr",
    "iso:country":"NL",
    "sg:address":"Vleesstr 51",
    "sg:city":"Venlo",
    "sg:orig_category":"Warenhuizen",
    "sg:phone":"+31 77 321 0695",
    "sg:postcode":"5911 JD",
    "sg:province":"Limburg",
    "wof:name":"Xenos Bv",
    "wof:placetype":"venue"
},
  "geometry": {"coordinates":[6.168410778,51.3686332703],"type":"Point"}
}