{
  "type": "Feature",
  "properties": {
    "addr:full":"Gooilandwg 223 Huizen Noord-Holland 1271 KW",
    "addr:housenumber":"223",
    "addr:postcode":"1271 kw",
    "iso:country":"NL",
    "sg:address":"Gooilandwg 223",
    "sg:city":"Huizen",
    "sg:orig_category":"Woningstoffeerders",
    "sg:phone":"+31 35 524 2281",
    "sg:postcode":"1271 KW",
    "sg:province":"Noord-Holland",
    "wof:name":"Zeeman",
    "wof:placetype":"venue"
},
  "geometry": {"coordinates":[5.2442598343,52.2893981934],"type":"Point"}
}