{
  "type": "Feature",
  "properties": {
    "addr:full":"Grt Hertoginneln 104 S Gravenhage Zuid-Holland 2517 EL",
    "addr:housenumber":"104;gravenhage;2517",
    "addr:postcode":"el",
    "addr:street":"S",
    "iso:country":"NL",
    "sg:address":"Grt Hertoginneln 104",
    "sg:city":"S Gravenhage",
    "sg:orig_category":"Geschenkartikelen",
    "sg:phone":"+31 70 364 8393",
    "sg:postcode":"2517 EL",
    "sg:province":"Zuid-Holland",
    "wof:name":"Kanna",
    "wof:placetype":"venue"
},
  "geometry": {"coordinates":[4.28708,52.08667],"type":"Point"}
}