{
  "type": "Feature",
  "properties": {
    "iso:country":"NL",
    "sg:address":"Amsterdamstr 14",
    "sg:city":"Haarlem",
    "sg:orig_category":"Veiligheidsuitrusting En -Kleding",
    "sg:phone":"+31 23 533 9325",
    "sg:postcode":"2032 PP",
    "sg:province":"Noord-Holland",
    "wof:name":"Lasschuit, Bedrijfsoptiek",
    "wof:placetype":"venue"
},
  "geometry": {"coordinates":[4.648126,52.380672],"type":"Point"}
}