{
  "type": "Feature",
  "properties": {
    "iso:country":"NL",
    "sg:address":"Regentesselaan 1",
    "sg:city":"Apeldoorn",
    "sg:orig_category":"Banken And Kredietinstellingen",
    "sg:phone":"+31 55 528 8288",
    "sg:postcode":"7316 AA",
    "sg:province":"Gelderland",
    "wof:name":"Ing Bank",
    "wof:placetype":"venue"
},
  "geometry": {"coordinates":[5.964408,52.216526],"type":"Point"}
}