{
  "type": "Feature",
  "properties": {
    "iso:country":"NL",
    "sg:address":"Blauwkapelsewg 57",
    "sg:city":"Utrecht",
    "sg:orig_category":"Adviesbureaus Bedrijfsorganisatie",
    "sg:phone":"+31 30 273 3626",
    "sg:postcode":"3572 KC",
    "sg:province":"Utrecht",
    "wof:name":"Hans Van Der Wielen Bv",
    "wof:placetype":"venue"
},
  "geometry": {"coordinates":[5.129574,52.100891],"type":"Point"}
}