{
  "type": "Feature",
  "properties": {
    "addr:full":"Groenmarktkade 8 Amsterdam Noord-Holland 1016 TA",
    "addr:housenumber":"8",
    "addr:postcode":"1016 ta",
    "addr:street":"Groenmarktkade",
    "iso:country":"NL",
    "sg:address":"Groenmarktkade 8",
    "sg:city":"Amsterdam",
    "sg:orig_category":"Glazenwasserijen",
    "sg:phone":"+31 20 623 2211",
    "sg:postcode":"1016 TA",
    "sg:province":"Noord-Holland",
    "wof:name":"Brouwer, G",
    "wof:placetype":"venue"
},
  "geometry": {"coordinates":[4.875174,52.371269],"type":"Point"}
}