{
  "type": "Feature",
  "properties": {
    "addr:full":"Wisstr 13 Nistelrode North Brabant 5388 KG",
    "addr:housenumber":"13",
    "addr:postcode":"5388 kg",
    "addr:street":"Wisstr",
    "iso:country":"NL",
    "sg:address":"Wisstr 13",
    "sg:city":"Nistelrode",
    "sg:orig_category":"Schoonheidsinstituten",
    "sg:phone":"+31 412 611 609",
    "sg:postcode":"5388 KG",
    "sg:province":"North Brabant",
    "wof:name":"Janine",
    "wof:placetype":"venue"
},
  "geometry": {"coordinates":[5.559204,51.705688],"type":"Point"}
}