{
  "type": "Feature",
  "properties": {
    "addr:full":"Nieuwez Voorburgw 132 Amsterdam Noord-Holland 1012 SH",
    "addr:housenumber":"132",
    "addr:postcode":"1012 sh",
    "iso:country":"NL",
    "sg:address":"Nieuwez Voorburgw 132",
    "sg:city":"Amsterdam",
    "sg:classifiers":[
        {
            "category":"Travel",
            "subcategory":"Hotels & Motels",
            "type":"Entertainment"
        }
    ],
    "sg:phone":"+31 20 626 1295",
    "sg:postcode":"1012 SH",
    "sg:province":"Noord-Holland",
    "sg:website":"http://www.hotelutopia.nl",
    "wof:name":"Utopia",
    "wof:placetype":"venue"
},
  "geometry": {"coordinates":[4.891623,52.375046],"type":"Point"}
}