{
  "type": "Feature",
  "properties": {
    "iso:country":"NL",
    "sg:address":"Dorpsstr 86-88",
    "sg:city":"Harskamp",
    "sg:orig_category":"Bloemen En Planten",
    "sg:phone":"+31 318 456 588",
    "sg:postcode":"6732 AG",
    "sg:province":"Gelderland",
    "wof:name":"Kraak, H",
    "wof:placetype":"venue"
},
  "geometry": {"coordinates":[5.751422,52.131439],"type":"Point"}
}