{
  "type": "Feature",
  "properties": {
    "addr:full":"Oostsngl 81 Bunschoten Spakenb Utrecht 3751 AV",
    "addr:housenumber":"81",
    "addr:street":"Oostsngl;Av",
    "iso:country":"NL",
    "sg:address":"Oostsngl 81",
    "sg:city":"Bunschoten Spakenb",
    "sg:classifiers":[
        {
            "category":"Farming",
            "subcategory":"Fish & Marine Products",
            "type":"Manufacturing & Wholesale Goods"
        }
    ],
    "sg:phone":"+31 33 298 1556",
    "sg:postcode":"3751 AV",
    "sg:province":"Utrecht",
    "sg:tags":[
        "vi"
    ],
    "wof:name":"Alie",
    "wof:placetype":"venue"
},
  "geometry": {"coordinates":[5.37481,52.243553],"type":"Point"}
}