{
  "type": "Feature",
  "properties": {
    "addr:full":"Stobbeweg 18 Ter Aar Zuid-Holland 2461 EX",
    "addr:housenumber":"18",
    "addr:postcode":"aar;2461 ex",
    "addr:street":"Stobbeweg;Ter",
    "iso:country":"NL",
    "sg:address":"Stobbeweg 18",
    "sg:city":"Ter Aar",
    "sg:orig_category":"Schilderwerk",
    "sg:phone":"+31 172 605 643",
    "sg:postcode":"2461 EX",
    "sg:province":"Zuid-Holland",
    "wof:name":"Gs Schilderwerken Bv",
    "wof:placetype":"venue"
},
  "geometry": {"coordinates":[4.709371,52.178047],"type":"Point"}
}