{
  "type": "Feature",
  "properties": {
    "iso:country":"NL",
    "sg:address":"Stobbeweg 18",
    "sg:city":"Ter Aar",
    "sg:orig_category":"Schilderwerk",
    "sg:phone":"+31 172 605 643",
    "sg:postcode":"2461 EX",
    "sg:province":"Zuid-Holland",
    "wof:name":"Gs Schilderwerken Bv",
    "wof:placetype":"venue"
},
  "geometry": {"coordinates":[4.709371,52.178047],"type":"Point"}
}