{
  "type": "Feature",
  "properties": {
    "addr:full":"Kruiskampwg 2 Ermelo Gelderland 3851 GP",
    "addr:housenumber":"2",
    "addr:postcode":"3851 gp",
    "addr:street":"Kruiskampwg;Gelderland",
    "iso:country":"NL",
    "sg:address":"Kruiskampwg 2",
    "sg:city":"Ermelo",
    "sg:orig_category":"Fotostudio'S",
    "sg:phone":"+31 341 559 658",
    "sg:postcode":"3851 GP",
    "sg:province":"Gelderland",
    "wof:name":"Hans Morren",
    "wof:placetype":"venue"
},
  "geometry": {"coordinates":[5.628651,52.294144],"type":"Point"}
}