{
  "type": "Feature",
  "properties": {
    "addr:full":"Bierkaaistraat 2 Hulst Zeeland 4561 BC",
    "addr:housenumber":"2",
    "addr:postcode":"4561 bc",
    "addr:street":"Bierkaaistraat",
    "iso:country":"NL",
    "sg:address":"Bierkaaistraat 2",
    "sg:city":"Hulst",
    "sg:orig_category":"Muziekinstrumenten",
    "sg:phone":"+31 114 315 846",
    "sg:postcode":"4561 BC",
    "sg:province":"Zeeland",
    "wof:name":"Muziekhdl De Polyfoon",
    "wof:placetype":"venue"
},
  "geometry": {"coordinates":[4.051836,51.281963],"type":"Point"}
}