{
  "type": "Feature",
  "properties": {
    "addr:full":"Populierenstr 37 Brunssum Limburg 6444 BP",
    "addr:housenumber":"37",
    "addr:postcode":"6444 bp",
    "addr:street":"Populierenstr",
    "iso:country":"NL",
    "sg:address":"Populierenstr 37",
    "sg:city":"Brunssum",
    "sg:orig_category":"Muziekscholen",
    "sg:phone":"+31 45 532 3082",
    "sg:postcode":"6444 BP",
    "sg:province":"Limburg",
    "wof:name":"Technics",
    "wof:placetype":"venue"
},
  "geometry": {"coordinates":[5.964644,50.943371],"type":"Point"}
}