{
  "type": "Feature",
  "properties": {
    "addr:full":"Hoofdweg 4 Slochteren Groningen 9621 AL",
    "addr:housenumber":"4",
    "addr:postcode":"9621 al",
    "addr:street":"Hoofdweg",
    "iso:country":"NL",
    "sg:address":"Hoofdweg 4",
    "sg:city":"Slochteren",
    "sg:orig_category":"Krantenuitgeverijen",
    "sg:phone":"+31 598 422 070",
    "sg:postcode":"9621 AL",
    "sg:province":"Groningen",
    "wof:name":"T Bokkeblad",
    "wof:placetype":"venue"
},
  "geometry": {"coordinates":[6.80566,53.220657],"type":"Point"}
}