{
  "type": "Feature",
  "properties": {
    "addr:full":"De Zodde 18 Loosdrecht North Holland 1231 MB",
    "addr:housenumber":"18",
    "addr:postcode":"1231 mb",
    "addr:street":"De Zodde",
    "iso:country":"NL",
    "sg:address":"De Zodde 18",
    "sg:city":"Loosdrecht",
    "sg:orig_category":"Autokeuringen",
    "sg:phone":"+31 35 582 5200",
    "sg:postcode":"1231 MB",
    "sg:province":"North Holland",
    "wof:name":"W.F. Molenkamp",
    "wof:placetype":"venue"
},
  "geometry": {"coordinates":[5.113754,52.209705],"type":"Point"}
}