{
  "type": "Feature",
  "properties": {
    "addr:full":"Ceintuurbaan 390 Amsterdam North Holland 1073 EN",
    "addr:housenumber":"390",
    "addr:postcode":"1073 en",
    "addr:street":"Ceintuurbaan",
    "iso:country":"NL",
    "sg:address":"Ceintuurbaan 390",
    "sg:city":"Amsterdam",
    "sg:orig_category":"Bedrijfskleding",
    "sg:phone":"+31 20 676 1333",
    "sg:postcode":"1073 EN",
    "sg:province":"North Holland",
    "wof:name":"Determeijer Beroepskleding-1893",
    "wof:placetype":"venue"
},
  "geometry": {"coordinates":[4.900707,52.354507],"type":"Point"}
}