{
  "type": "Feature",
  "properties": {
    "addr:full":"Ruitenbeekweg 11 Lunteren Gelderland 6741 HA",
    "addr:housenumber":"11",
    "addr:postcode":"6741 ha",
    "addr:street":"Ruitenbeekweg;Gelderland",
    "iso:country":"NL",
    "sg:address":"Ruitenbeekweg 11",
    "sg:city":"Lunteren",
    "sg:orig_category":"Diverse Bedrijfsinstallaties Gh",
    "sg:phone":"+31 318 483 486",
    "sg:postcode":"6741 HA",
    "sg:province":"Gelderland",
    "wof:name":"Pompen- En Installatiebedrijf G. Klomp",
    "wof:placetype":"venue"
},
  "geometry": {"coordinates":[5.627412,52.106865],"type":"Point"}
}