{
  "type": "Feature",
  "properties": {
    "addr:full":"H Dunantwg 4 Alphen Aan Den Ryn Zuid-Holland 2402 NP",
    "addr:housenumber":"4",
    "addr:postcode":"2402 np",
    "addr:street":"Aan Den Ryn",
    "iso:country":"NL",
    "sg:address":"H Dunantwg 4",
    "sg:city":"Alphen Aan Den Ryn",
    "sg:orig_category":"Adviesbureaus Bouwkunde",
    "sg:phone":"+31 172 484 000",
    "sg:postcode":"2402 NP",
    "sg:province":"Zuid-Holland",
    "sg:website":"http://www.alphaplan.nl",
    "wof:name":"Alphaplan Bv",
    "wof:placetype":"venue"
},
  "geometry": {"coordinates":[4.661723,52.144989],"type":"Point"}
}