{
  "type": "Feature",
  "properties": {
    "addr:full":"A Van Bronckhorstlaan 167 Spijkenisse Zuid-Holland 3201 XC",
    "addr:housenumber":"167",
    "addr:postcode":"3201 xc",
    "addr:street":"A Van Bronckhorstlaan",
    "iso:country":"NL",
    "sg:address":"A Van Bronckhorstlaan 167",
    "sg:city":"Spijkenisse",
    "sg:orig_category":"Fotostudio'S And Fotografen",
    "sg:phone":"+31 181 614 094",
    "sg:postcode":"3201 XC",
    "sg:province":"Zuid-Holland",
    "wof:name":"Photo & Computer J.P. Van Iwaarden",
    "wof:placetype":"venue"
},
  "geometry": {"coordinates":[4.329072,51.846313],"type":"Point"}
}