{
  "type": "Feature",
  "properties": {
    "addr:full":"Kiplinglaan 1 Eindhoven Noord-Brabant 5629 MK",
    "addr:housenumber":"1",
    "addr:postcode":"5629",
    "addr:street":"Kiplinglaan",
    "iso:country":"NL",
    "sg:address":"Kiplinglaan 1",
    "sg:city":"Eindhoven",
    "sg:classifiers":[
        {
            "category":"Education",
            "subcategory":"Preschool",
            "type":"Public Place"
        }
    ],
    "sg:phone":"+31 40 242 8917",
    "sg:postcode":"5629 MK",
    "sg:province":"Noord-Brabant",
    "sg:tags":[
        "kleuteronderwijs",
        "basis-"
    ],
    "wof:name":"De Boschuil Ic Basisschool",
    "wof:placetype":"venue"
},
  "geometry": {"coordinates":[5.475385,51.48735],"type":"Point"}
}