{
  "type": "Feature",
  "properties": {
    "addr:full":"Derkinderenstr 24 Amsterdam North Holland 1062 DB",
    "addr:housenumber":"24",
    "addr:postcode":"1062 db",
    "addr:street":"Derkinderenstr",
    "iso:country":"NL",
    "sg:address":"Derkinderenstr 24",
    "sg:city":"Amsterdam",
    "sg:orig_category":"Werving En Selectie",
    "sg:phone":"+31 20 470 9011",
    "sg:postcode":"1062 DB",
    "sg:province":"North Holland",
    "sg:website":"http://www.roberthalf.nl",
    "wof:name":"Robert Half Finance & Accounting",
    "wof:placetype":"venue"
},
  "geometry": {"coordinates":[4.8407201767,52.3586425781],"type":"Point"}
}