{
  "type": "Feature",
  "properties": {
    "iso:country":"NL",
    "sg:address":"Gudsekop 31",
    "sg:city":"Sneek",
    "sg:orig_category":"Beautyfarms And Sauna'S",
    "sg:phone":"+31 515 424 559",
    "sg:postcode":"8604 CV",
    "sg:province":"Friesland",
    "wof:name":"R. Piersma",
    "wof:placetype":"venue"
},
  "geometry": {"coordinates":[5.683095,53.031017],"type":"Point"}
}