{
  "type": "Feature",
  "properties": {
    "addr:full":"K P Vd Mandeleln 90 Rotterdam Zuid-Holland 3062 MB",
    "addr:housenumber":"90",
    "addr:postcode":"3062 mb",
    "addr:street":"K P",
    "iso:country":"NL",
    "sg:address":"K P Vd Mandeleln 90",
    "sg:city":"Rotterdam",
    "sg:orig_category":"Directmail",
    "sg:phone":"+31 800 0484",
    "sg:postcode":"3062 MB",
    "sg:province":"Zuid-Holland",
    "wof:name":"Dmshop",
    "wof:placetype":"venue"
},
  "geometry": {"coordinates":[4.51759,51.931339],"type":"Point"}
}