{
  "type": "Feature",
  "properties": {
    "addr:full":"J De Meesterstr 20 Haarlem Noord-Holland 2024 KX",
    "addr:housenumber":"20",
    "addr:postcode":"2024 kx",
    "addr:street":"J De Meesterstr",
    "iso:country":"NL",
    "sg:address":"J De Meesterstr 20",
    "sg:city":"Haarlem",
    "sg:orig_category":"Peuterspeelzalen",
    "sg:phone":"+31 23 525 1373",
    "sg:postcode":"2024 KX",
    "sg:province":"Noord-Holland",
    "wof:name":"Wickie",
    "wof:placetype":"venue"
},
  "geometry": {"coordinates":[4.64252,52.407673],"type":"Point"}
}