{
  "type": "Feature",
  "properties": {
    "iso:country":"NL",
    "sg:address":"Ammonslaantje 40",
    "sg:city":"Wassenaar",
    "sg:orig_category":"Zuivelproducten",
    "sg:phone":"+31 70 511 2139",
    "sg:postcode":"2241 BR",
    "sg:province":"Zuid-Holland",
    "wof:name":"A.M.M. Den Hollander",
    "wof:placetype":"venue"
},
  "geometry": {"coordinates":[4.422907,52.150909],"type":"Point"}
}