{
  "type": "Feature",
  "properties": {
    "addr:full":"Drossaert Van Bewerstr 1 Stein Lb Limburg 6171 JT",
    "addr:housenumber":"1",
    "addr:postcode":"lb;6171 jt",
    "addr:street":"Drossaert Van Bewerstr",
    "iso:country":"NL",
    "sg:address":"Drossaert Van Bewerstr 1",
    "sg:city":"Stein Lb",
    "sg:orig_category":"Binnenhuisarchitecten",
    "sg:phone":"+31 46 433 6537",
    "sg:postcode":"6171 JT",
    "sg:province":"Limburg",
    "wof:name":"L.G.H. Muris",
    "wof:placetype":"venue"
},
  "geometry": {"coordinates":[-118.11732499999999,33.768589],"type":"Point"}
}