{
  "type": "Feature",
  "properties": {
    "addr:full":"Pleintjes 58 Veldhoven Noord-Brabant 5501 EB",
    "addr:housenumber":"58",
    "addr:postcode":"5501 eb",
    "addr:street":"Pleintjes",
    "iso:country":"NL",
    "sg:address":"Pleintjes 58",
    "sg:city":"Veldhoven",
    "sg:orig_category":"Schoenen",
    "sg:phone":"+31 40 253 8889",
    "sg:postcode":"5501 EB",
    "sg:province":"Noord-Brabant",
    "wof:name":"Louwers Schoenen En Sport",
    "wof:placetype":"venue"
},
  "geometry": {"coordinates":[5.406756,51.419487],"type":"Point"}
}