{
  "type": "Feature",
  "properties": {
    "iso:country":"NL",
    "sg:address":"Weerdingerstraat 251",
    "sg:city":"Emmen",
    "sg:orig_category":"Fotostudio'S And Fotografen",
    "sg:phone":"+31 591 649 746",
    "sg:postcode":"7811 CL",
    "sg:province":"Provincie Drenthe",
    "wof:name":"Foto De Graaf",
    "wof:placetype":"venue"
},
  "geometry": {"coordinates":[6.895142,52.789722],"type":"Point"}
}