{
  "type": "Feature",
  "properties": {
    "addr:full":"Kerkstraat 6 Oude Wetering South Holland 2377 AR",
    "addr:housenumber":"6",
    "addr:postcode":"2377",
    "addr:street":"Kerkstraat",
    "iso:country":"NL",
    "sg:address":"Kerkstraat 6",
    "sg:city":"Oude Wetering",
    "sg:orig_category":"Kantoorartikelen",
    "sg:phone":"+31 71 331 5616",
    "sg:postcode":"2377 AR",
    "sg:province":"South Holland",
    "wof:name":"Kantoor Efficiency Schrama",
    "wof:placetype":"venue"
},
  "geometry": {"coordinates":[4.6464858055,52.2113418579],"type":"Point"}
}