{
  "type": "Feature",
  "properties": {
    "addr:full":"Kruijsakker 4 Drempt Gelderland 6996 DL",
    "addr:housenumber":"4",
    "addr:postcode":"6996 dl",
    "addr:street":"Kruijsakker;Gelderland",
    "iso:country":"NL",
    "sg:address":"Kruijsakker 4",
    "sg:city":"Drempt",
    "sg:orig_category":"Kappers",
    "sg:phone":"+31 313 484 250",
    "sg:postcode":"6996 DL",
    "sg:province":"Gelderland",
    "wof:name":"M.A. Beltman",
    "wof:placetype":"venue"
},
  "geometry": {"coordinates":[6.182937,52.022514],"type":"Point"}
}