{
  "type": "Feature",
  "properties": {
    "iso:country":"NL",
    "sg:address":"Soestdyksewg Z 247",
    "sg:city":"Bilthoven",
    "sg:orig_category":"Pensioenen",
    "sg:phone":"+31 30 225 1459",
    "sg:postcode":"3721 AE",
    "sg:province":"Utrecht",
    "wof:name":"Paardekooper Ass- & Pensioenadv",
    "wof:placetype":"venue"
},
  "geometry": {"coordinates":[5.202339,52.126713],"type":"Point"}
}