{
  "type": "Feature",
  "properties": {
    "iso:country":"NL",
    "sg:address":"Prins Hendrikstraat 20",
    "sg:city":"Oud Beijerland",
    "sg:orig_category":"Begrafenisondernemers",
    "sg:phone":"+31 186 617 078",
    "sg:postcode":"3262 ST",
    "sg:province":"South Holland",
    "wof:name":"Uitvaartverzorging Moree Bv",
    "wof:placetype":"venue"
},
  "geometry": {"coordinates":[4.414311,51.824703],"type":"Point"}
}