{
  "type": "Feature",
  "properties": {
    "addr:full":"Farmsumerwg 103 Appingedam Groningen 9902 BN",
    "addr:housenumber":"103",
    "addr:postcode":"9902 bn",
    "addr:street":"Appingedam",
    "iso:country":"NL",
    "sg:address":"Farmsumerwg 103",
    "sg:city":"Appingedam",
    "sg:orig_category":"Goudsmeden En Zilversmeden",
    "sg:phone":"+31 596 627 013",
    "sg:postcode":"9902 BN",
    "sg:province":"Groningen",
    "wof:name":"Kampinga, B",
    "wof:placetype":"venue"
},
  "geometry": {"coordinates":[6.876961,53.319893],"type":"Point"}
}