{
  "type": "Feature",
  "properties": {
    "addr:full":"Kapt Hatterasstr 48 Tilburg North Brabant 5015 BB",
    "addr:housenumber":"48",
    "addr:postcode":"5015 bb",
    "iso:country":"NL",
    "sg:address":"Kapt Hatterasstr 48",
    "sg:city":"Tilburg",
    "sg:orig_category":"Open Haarden",
    "sg:phone":"+31 13 543 3965",
    "sg:postcode":"5015 BB",
    "sg:province":"North Brabant",
    "sg:website":"http://www.vestiakachels.nl",
    "wof:name":"Vestia",
    "wof:placetype":"venue"
},
  "geometry": {"coordinates":[5.106226,51.569439],"type":"Point"}
}