{
  "type": "Feature",
  "properties": {
    "iso:country":"NL",
    "sg:address":"Industriewg 24",
    "sg:city":"Giessen",
    "sg:classifiers":[
        {
            "category":"Retail",
            "subcategory":"Storage",
            "type":"Services"
        }
    ],
    "sg:phone":"+31 183 443 460",
    "sg:postcode":"4283 GZ",
    "sg:province":"North Brabant",
    "sg:tags":[
        "op-",
        "en",
        "overslagbedrijven"
    ],
    "wof:name":"Giesko Bv",
    "wof:placetype":"venue"
},
  "geometry": {"coordinates":[5.030886,51.779758],"type":"Point"}
}