{
  "type": "Feature",
  "properties": {
    "addr:full":"Buorren 10 Warns Friesland 8721 GP",
    "addr:housenumber":"10",
    "addr:postcode":"8721 gp",
    "addr:street":"Buorren",
    "iso:country":"NL",
    "sg:address":"Buorren 10",
    "sg:city":"Warns",
    "sg:orig_category":"Schilderwerk",
    "sg:phone":"+31 514 681 894",
    "sg:postcode":"8721 GP",
    "sg:province":"Friesland",
    "wof:name":"T.J. De Vries",
    "wof:placetype":"venue"
},
  "geometry": {"coordinates":[-83.884407,34.997856],"type":"Point"}
}