{
  "type": "Feature",
  "properties": {
    "iso:country":"NL",
    "sg:address":"Schootenwg 2A",
    "sg:city":"Den Helder",
    "sg:orig_category":"Verenigingen En Stichtingen",
    "sg:phone":"+31 223 631 340",
    "sg:postcode":"1785 LV",
    "sg:province":"Noord-Holland",
    "wof:name":"Toon Jacobs, Rtv",
    "wof:placetype":"venue"
},
  "geometry": {"coordinates":[4.76665,52.945122],"type":"Point"}
}