{
  "type": "Feature",
  "properties": {
    "addr:full":"Schagchelstraat 40 Haarlem North Holland 2011 HZ",
    "addr:housenumber":"40",
    "addr:postcode":"2011 hz",
    "addr:street":"Schagchelstraat",
    "iso:country":"NL",
    "sg:address":"Schagchelstraat 40",
    "sg:city":"Haarlem",
    "sg:orig_category":"Kappers",
    "sg:phone":"+31 23 532 3869",
    "sg:postcode":"2011 HZ",
    "sg:province":"North Holland",
    "wof:name":"Kapper Hans Smits",
    "wof:placetype":"venue"
},
  "geometry": {"coordinates":[4.6351847649,52.3787765503],"type":"Point"}
}