{
  "type": "Feature",
  "properties": {
    "iso:country":"NL",
    "sg:address":"Dorpsstr 53",
    "sg:city":"Bleiswyk",
    "sg:orig_category":"Huishoudelijke Apparaten En Artikelen",
    "sg:phone":"+31 10 521 2563",
    "sg:postcode":"2665 BH",
    "sg:province":"Zuid-Holland",
    "wof:name":"Spruit",
    "wof:placetype":"venue"
},
  "geometry": {"coordinates":[4.530499,52.010933],"type":"Point"}
}