{
  "type": "Feature",
  "properties": {
    "addr:full":"Burg. Van Royensingel 1 Zwolle NL.08 8011 CS",
    "addr:housenumber":"1",
    "addr:postcode":"8011 cs",
    "addr:street":"Burg.;Royensingel",
    "iso:country":"NL",
    "sg:address":"Burg. Van Royensingel 1",
    "sg:city":"Zwolle",
    "sg:orig_category":"Verzekeringen",
    "sg:phone":"+31 38 426 0800",
    "sg:postcode":"8011 CS",
    "sg:province":"NL.08",
    "wof:name":"Van Calcar B.V. Makelaars In Assurantie",
    "wof:placetype":"venue"
},
  "geometry": {"coordinates":[6.088738,52.512566],"type":"Point"}
}