{
  "type": "Feature",
  "properties": {
    "addr:full":"Carre 46 Tilburg North Brabant 5017 JE",
    "addr:housenumber":"46",
    "addr:postcode":"5017 je",
    "addr:street":"Carre",
    "iso:country":"NL",
    "sg:address":"Carre 46",
    "sg:city":"Tilburg",
    "sg:orig_category":"Bedrijfsmechanisatie En -Automatisering",
    "sg:phone":"+31 13 543 9900",
    "sg:postcode":"5017 JE",
    "sg:province":"North Brabant",
    "wof:name":"Evers",
    "wof:placetype":"venue"
},
  "geometry": {"coordinates":[5.102656,51.558655],"type":"Point"}
}