{
  "type": "Feature",
  "properties": {
    "iso:country":"NL",
    "sg:address":"Pasteurplein 7",
    "sg:city":"'S Gravenhage",
    "sg:orig_category":"Fietshandelaren",
    "sg:phone":"+31 70 399 3824",
    "sg:postcode":"2522 RB",
    "sg:province":"South Holland",
    "wof:name":"Wielershop Rinus",
    "wof:placetype":"venue"
},
  "geometry": {"coordinates":[4.329234,52.062859],"type":"Point"}
}