{
  "type": "Feature",
  "properties": {
    "addr:full":"Kerkwyk 61 Berlicum Nb Noord-Brabant 5258 KB",
    "addr:housenumber":"61",
    "addr:postcode":"5258 kb",
    "addr:street":"Kerkwyk",
    "iso:country":"NL",
    "sg:address":"Kerkwyk 61",
    "sg:city":"Berlicum Nb",
    "sg:orig_category":"Verenigingsgebouwen",
    "sg:phone":"+31 73 503 2016",
    "sg:postcode":"5258 KB",
    "sg:province":"Noord-Brabant",
    "wof:name":"Durpsherd, Den",
    "wof:placetype":"venue"
},
  "geometry": {"coordinates":[5.418169,51.663883],"type":"Point"}
}