{
  "type": "Feature",
  "properties": {
    "addr:full":"Korenlaan 24 Putten Gelderland 3881 DA",
    "addr:housenumber":"24;3881",
    "addr:postcode":"da",
    "addr:street":"Korenlaan;Gelderland",
    "iso:country":"NL",
    "sg:address":"Korenlaan 24",
    "sg:city":"Putten",
    "sg:orig_category":"Autokeuringen",
    "sg:phone":"+31 341 353 480",
    "sg:postcode":"3881 DA",
    "sg:province":"Gelderland",
    "wof:name":"L. Wietsma",
    "wof:placetype":"venue"
},
  "geometry": {"coordinates":[5.616475,52.263443],"type":"Point"}
}