{
  "type": "Feature",
  "properties": {
    "addr:full":"Bredeweg 429 Roermond Limburg 6044 XC",
    "addr:housenumber":"429",
    "addr:postcode":"6044 xc",
    "addr:street":"Bredeweg",
    "iso:country":"NL",
    "sg:address":"Bredeweg 429",
    "sg:city":"Roermond",
    "sg:orig_category":"Autoverhuur",
    "sg:phone":"+31 475 336 300",
    "sg:postcode":"6044 XC",
    "sg:province":"Limburg",
    "wof:name":"Autorent Guus Baggen",
    "wof:placetype":"venue"
},
  "geometry": {"coordinates":[6.001004,51.183826],"type":"Point"}
}