{
  "type": "Feature",
  "properties": {
    "addr:full":"Croeselaan 94 Utrecht Utrecht 3521 CC",
    "addr:housenumber":"94",
    "addr:postcode":"3521 cc",
    "addr:street":"Croeselaan",
    "iso:country":"NL",
    "sg:address":"Croeselaan 94",
    "sg:city":"Utrecht",
    "sg:orig_category":"Huishoudapparatuur, Televisies And Radio'S",
    "sg:phone":"+31 30 297 0088",
    "sg:postcode":"3521 CC",
    "sg:province":"Utrecht",
    "wof:name":"Electro Parts",
    "wof:placetype":"venue"
},
  "geometry": {"coordinates":[5.109931,52.083843],"type":"Point"}
}