{
  "type": "Feature",
  "properties": {
    "addr:full":"De Zwaan 16 Bedum Groningen 9781 JZ",
    "addr:housenumber":"16",
    "addr:postcode":"9781 jz",
    "addr:street":"De Zwaan",
    "iso:country":"NL",
    "sg:address":"De Zwaan 16",
    "sg:city":"Bedum",
    "sg:orig_category":"Goederenvervoer Over De Weg",
    "sg:phone":"+31 50 301 4126",
    "sg:postcode":"9781 JZ",
    "sg:province":"Groningen",
    "wof:name":"Jan Oostinga, Internationaal Transport",
    "wof:placetype":"venue"
},
  "geometry": {"coordinates":[6.600976,53.295166],"type":"Point"}
}