{
  "type": "Feature",
  "properties": {
    "addr:full":"Aploniastraat 1 Rotterdam Zuid-Holland 3084 CC",
    "addr:housenumber":"1",
    "addr:postcode":"3084 cc",
    "addr:street":"Aploniastraat",
    "iso:country":"NL",
    "sg:address":"Aploniastraat 1",
    "sg:city":"Rotterdam",
    "sg:orig_category":"Autokeuringen",
    "sg:phone":"+31 10 240 4848",
    "sg:postcode":"3084 CC",
    "sg:province":"Zuid-Holland",
    "wof:name":"Autoschade Charlois Bv",
    "wof:placetype":"venue"
},
  "geometry": {"coordinates":[4.45281,51.867641],"type":"Point"}
}