{
  "type": "Feature",
  "properties": {
    "addr:full":"Rengersdiep 13 Zwolle NL.08 8032 NJ",
    "addr:housenumber":"13",
    "addr:postcode":"8032 nj",
    "addr:street":"Rengersdiep",
    "iso:country":"NL",
    "sg:address":"Rengersdiep 13",
    "sg:city":"Zwolle",
    "sg:orig_category":"Binnenhuisarchitectuur",
    "sg:phone":"+31 38 454 4423",
    "sg:postcode":"8032 NJ",
    "sg:province":"NL.08",
    "wof:name":"Jong, A F M De",
    "wof:placetype":"venue"
},
  "geometry": {"coordinates":[6.096029,52.540108],"type":"Point"}
}