{
  "type": "Feature",
  "properties": {
    "iso:country":"NL",
    "sg:address":"Voorstr 87",
    "sg:city":"Vianen Zh",
    "sg:orig_category":"Fotoreportages",
    "sg:phone":"+31 347 322 545",
    "sg:postcode":"4132 AP",
    "sg:province":"Utrecht",
    "sg:website":"http://www.fotostudiomarks.nl",
    "wof:name":"Marks",
    "wof:placetype":"venue"
},
  "geometry": {"coordinates":[5.092662,51.993053],"type":"Point"}
}