{
  "type": "Feature",
  "properties": {
    "addr:full":"Van Loghemstraat 25 Haarlem Noord-Holland 2033 XM",
    "addr:housenumber":"25",
    "addr:postcode":"2033 xm",
    "addr:street":"Van Loghemstraat",
    "iso:country":"NL",
    "sg:address":"Van Loghemstraat 25",
    "sg:city":"Haarlem",
    "sg:orig_category":"Binnenhuisarchitecten",
    "sg:phone":"+31 23 536 3930",
    "sg:postcode":"2033 XM",
    "sg:province":"Noord-Holland",
    "wof:name":"D.E. Pot Interieurarchitectuur",
    "wof:placetype":"venue"
},
  "geometry": {"coordinates":[4.66405,52.379108],"type":"Point"}
}