{
  "type": "Feature",
  "properties": {
    "addr:full":"Willemsstreek 5 Noordwolde Gn Groningen 9784 TB",
    "addr:housenumber":"5",
    "addr:postcode":"gn;9784 tb",
    "addr:street":"Willemsstreek",
    "iso:country":"NL",
    "sg:address":"Willemsstreek 5",
    "sg:city":"Noordwolde Gn",
    "sg:orig_category":"Kappers",
    "sg:phone":"+31 50 301 4430",
    "sg:postcode":"9784 TB",
    "sg:province":"Groningen",
    "wof:name":"J Siccama",
    "wof:placetype":"venue"
},
  "geometry": {"coordinates":[6.6009979248,53.2790374756],"type":"Point"}
}