{
  "type": "Feature",
  "properties": {
    "addr:full":"Bergseln 151A Rotterdam Zuid-Holland 3037 BH",
    "addr:housenumber":"151a",
    "addr:postcode":"3037 bh",
    "iso:country":"NL",
    "sg:address":"Bergseln 151A",
    "sg:city":"Rotterdam",
    "sg:orig_category":"Kappers",
    "sg:phone":"+31 10 467 3629",
    "sg:postcode":"3037 BH",
    "sg:province":"Zuid-Holland",
    "wof:name":"Art Hairstudio",
    "wof:placetype":"venue"
},
  "geometry": {"coordinates":[4.4734201431,51.938129425],"type":"Point"}
}