{
  "type": "Feature",
  "properties": {
    "iso:country":"NL",
    "sg:address":"Pr Frederikln 2",
    "sg:city":"Amersfoort",
    "sg:orig_category":"Marketingbureaus",
    "sg:phone":"+31 33 254 0709",
    "sg:postcode":"3818 KC",
    "sg:province":"Utrecht",
    "sg:website":"http://www.senta.com",
    "wof:name":"Senta Multisensory Concepting",
    "wof:placetype":"venue"
},
  "geometry": {"coordinates":[5.37344,52.148651],"type":"Point"}
}