{
  "type": "Feature",
  "properties": {
    "addr:full":"Pr Frederikln 2 Amersfoort Utrecht 3818 KC",
    "addr:housenumber":"2",
    "addr:postcode":"3818 kc",
    "iso:country":"NL",
    "sg:address":"Pr Frederikln 2",
    "sg:city":"Amersfoort",
    "sg:orig_category":"Marketingbureaus",
    "sg:phone":"+31 33 254 0709",
    "sg:postcode":"3818 KC",
    "sg:province":"Utrecht",
    "sg:website":"http://www.senta.com",
    "wof:name":"Senta Multisensory Concepting",
    "wof:placetype":"venue"
},
  "geometry": {"coordinates":[5.37344,52.148651],"type":"Point"}
}