{
  "type": "Feature",
  "properties": {
    "addr:full":"Ryswyksepln 108 S Gravenhage Zuid-Holland 2516 GX",
    "addr:housenumber":"108;gravenhage",
    "addr:postcode":"2516 gx",
    "addr:street":"S",
    "iso:country":"NL",
    "sg:address":"Ryswyksepln 108",
    "sg:city":"S Gravenhage",
    "sg:orig_category":"Vertalers",
    "sg:phone":"+31 70 384 1298",
    "sg:postcode":"2516 GX",
    "sg:province":"Zuid-Holland",
    "wof:name":"Linguatrans",
    "wof:placetype":"venue"
},
  "geometry": {"coordinates":[4.33931,52.06786],"type":"Point"}
}