{
  "type": "Feature",
  "properties": {
    "addr:full":"V Speykln 65 Helmond North Brabant 5703 XE",
    "addr:housenumber":"65",
    "addr:postcode":"5703 xe",
    "iso:country":"NL",
    "sg:address":"V Speykln 65",
    "sg:city":"Helmond",
    "sg:orig_category":"Verenigingen En Stichtingen",
    "sg:phone":"+31 492 474 808",
    "sg:postcode":"5703 XE",
    "sg:province":"North Brabant",
    "wof:name":"Lodar El Molukse Welzijns, Sticht",
    "wof:placetype":"venue"
},
  "geometry": {"coordinates":[5.658284,51.482239],"type":"Point"}
}