{
  "type": "Feature",
  "properties": {
    "addr:full":"De Veste 25 Woerden Utrecht 3443 DZ",
    "addr:housenumber":"25",
    "addr:postcode":"3443 dz",
    "addr:street":"De Veste",
    "iso:country":"NL",
    "sg:address":"De Veste 25",
    "sg:city":"Woerden",
    "sg:orig_category":"Adviesbureaus Bedrijfsorganisatie",
    "sg:phone":"+31 348 422 807",
    "sg:postcode":"3443 DZ",
    "sg:province":"Utrecht",
    "wof:name":"Arnhem, Van",
    "wof:placetype":"venue"
},
  "geometry": {"coordinates":[4.88472,52.093189],"type":"Point"}
}