{
  "type": "Feature",
  "properties": {
    "addr:full":"Lindestr 12 Eersel North Brabant 5521 EK",
    "addr:housenumber":"12",
    "addr:postcode":"5521 ek",
    "addr:street":"Lindestr",
    "iso:country":"NL",
    "sg:address":"Lindestr 12",
    "sg:city":"Eersel",
    "sg:orig_category":"Adviesbureaus Bedrijfsorganisatie",
    "sg:phone":"+31 497 530 540",
    "sg:postcode":"5521 EK",
    "sg:province":"North Brabant",
    "wof:name":"Quak Bv",
    "wof:placetype":"venue"
},
  "geometry": {"coordinates":[5.30905,51.358311],"type":"Point"}
}