{
  "type": "Feature",
  "properties": {
    "addr:full":"Hoeksteen 131 Hoofddorp North Holland 2132 MX",
    "addr:housenumber":"131",
    "addr:postcode":"2132 mx",
    "addr:street":"Hoeksteen",
    "iso:country":"NL",
    "sg:address":"Hoeksteen 131",
    "sg:city":"Hoofddorp",
    "sg:orig_category":"Goederenvervoer Over De Weg",
    "sg:phone":"+31 20 316 2220",
    "sg:postcode":"2132 MX",
    "sg:province":"North Holland",
    "wof:name":"Transportbedrijf R. Nagel Bv",
    "wof:placetype":"venue"
},
  "geometry": {"coordinates":[4.722777,52.292133],"type":"Point"}
}