{
  "type": "Feature",
  "properties": {
    "iso:country":"NL",
    "sg:address":"Lancasterstraat 8",
    "sg:city":"Steenbergen Nb",
    "sg:orig_category":"Diverse Consumentenartikelen Gh",
    "sg:phone":"+31 167 564 916",
    "sg:postcode":"4651 SR",
    "sg:province":"North Brabant",
    "wof:name":"Hoogenboom Diergoed Bv",
    "wof:placetype":"venue"
},
  "geometry": {"coordinates":[4.314555,51.585594],"type":"Point"}
}