{
  "type": "Feature",
  "properties": {
    "addr:full":"Half Elfje 11 Someren Noord-Brabant 5711 ES",
    "addr:housenumber":"11",
    "addr:postcode":"5711 es",
    "addr:street":"Half Elfje",
    "iso:country":"NL",
    "sg:address":"Half Elfje 11",
    "sg:city":"Someren",
    "sg:orig_category":"Goederenvervoer Over De Weg",
    "sg:phone":"+31 493 493 691",
    "sg:postcode":"5711 ES",
    "sg:province":"Noord-Brabant",
    "wof:name":"J. Wijnen",
    "wof:placetype":"venue"
},
  "geometry": {"coordinates":[5.722043,51.393017],"type":"Point"}
}