{
  "type": "Feature",
  "properties": {
    "addr:full":"Assenstraat 5 Arnhem Gelderland 6835 HA",
    "addr:housenumber":"5",
    "addr:postcode":"6835 ha",
    "addr:street":"Assenstraat",
    "iso:country":"NL",
    "sg:address":"Assenstraat 5",
    "sg:city":"Arnhem",
    "sg:orig_category":"Bedrijfs- And Managementsconsultants",
    "sg:phone":"+31 6 20157378",
    "sg:postcode":"6835 HA",
    "sg:province":"Gelderland",
    "wof:name":"Govaert Consulting",
    "wof:placetype":"venue"
},
  "geometry": {"coordinates":[5.903816,51.94915],"type":"Point"}
}