{
  "type": "Feature",
  "properties": {
    "addr:full":"Rysenburgerwg 27 Poeldyk Zuid-Holland 2685 EA",
    "addr:housenumber":"27",
    "addr:postcode":"2685 ea",
    "addr:street":"Rysenburgerwg",
    "iso:country":"NL",
    "sg:address":"Rysenburgerwg 27",
    "sg:city":"Poeldyk",
    "sg:classifiers":[
        {
            "category":"Professional",
            "subcategory":"Accounting & Tax Preparation",
            "type":"Services"
        }
    ],
    "sg:phone":"+31 174 213 587",
    "sg:postcode":"2685 EA",
    "sg:province":"Zuid-Holland",
    "sg:tags":[
        "accountant",
        "en",
        "-kantoren",
        "register-"
    ],
    "wof:name":"Novum Bv",
    "wof:placetype":"venue"
},
  "geometry": {"coordinates":[4.218632,52.021446],"type":"Point"}
}