{
  "type": "Feature",
  "properties": {
    "addr:full":"Javastr 20 S Gravenhage Zuid-Holland 2585 AN",
    "addr:housenumber":"20;gravenhage",
    "addr:postcode":"2585 an",
    "addr:street":"Javastr;S",
    "iso:country":"NL",
    "sg:address":"Javastr 20",
    "sg:city":"S Gravenhage",
    "sg:orig_category":"Ambassades/Consulaten",
    "sg:phone":"+31 70 360 5155",
    "sg:postcode":"2585 AN",
    "sg:province":"Zuid-Holland",
    "wof:name":"Argentini\u00eb Ambassade Van",
    "wof:placetype":"venue"
},
  "geometry": {"coordinates":[4.29777,52.094799],"type":"Point"}
}