{
  "type": "Feature",
  "properties": {
    "addr:full":"Ganzenhorst 30 Grave Louisiana 5361 TM",
    "addr:housenumber":"30",
    "addr:postcode":"5361 tm",
    "addr:street":"Ganzenhorst;Louisiana",
    "iso:country":"NL",
    "sg:address":"Ganzenhorst 30",
    "sg:city":"Grave",
    "sg:orig_category":"Verzekeringen - Verzekeringskantoren",
    "sg:phone":"+31 486 421 456",
    "sg:postcode":"5361 TM",
    "sg:province":"Louisiana",
    "wof:name":"Groot, De",
    "wof:placetype":"venue"
},
  "geometry": {"coordinates":[-92.151741,32.929253],"type":"Point"}
}