{
  "type": "Feature",
  "properties": {
    "iso:country":"NL",
    "sg:address":"Handelsln 16",
    "sg:city":"Uden",
    "sg:orig_category":"Kunstbloemen En -Planten - Fabrieken En Groothandel",
    "sg:phone":"+31 413 241 500",
    "sg:postcode":"5405 AE",
    "sg:province":"Noord-Brabant",
    "sg:website":"http://www.nova-nature.com",
    "wof:name":"Nova Nature Bv",
    "wof:placetype":"venue"
},
  "geometry": {"coordinates":[5.618265,51.657413],"type":"Point"}
}