{
  "type": "Feature",
  "properties": {
    "addr:full":"Ringslang 17 Amersfoort Utrecht 3824 VD",
    "addr:housenumber":"17",
    "addr:postcode":"3824 vd",
    "addr:street":"Ringslang",
    "iso:country":"NL",
    "sg:address":"Ringslang 17",
    "sg:city":"Amersfoort",
    "sg:orig_category":"Begrafenisverzorging",
    "sg:phone":"+31 33 455 5947",
    "sg:postcode":"3824 VD",
    "sg:province":"Utrecht",
    "wof:name":"Peter Henssen, Uitvaartzorg",
    "wof:placetype":"venue"
},
  "geometry": {"coordinates":[5.373133,52.200748],"type":"Point"}
}