{
  "type": "Feature",
  "properties": {
    "addr:full":"Nieuwkerksedk 29 Goirle Noord-Brabant 5051 HS",
    "addr:housenumber":"29",
    "addr:postcode":"5051 hs",
    "addr:street":"Nieuwkerksedk",
    "iso:country":"NL",
    "sg:address":"Nieuwkerksedk 29",
    "sg:city":"Goirle",
    "sg:classifiers":[
        {
            "category":"Sports & Exercise",
            "subcategory":"Stables",
            "type":"Entertainment"
        }
    ],
    "sg:phone":"+31 13 534 1223",
    "sg:postcode":"5051 HS",
    "sg:province":"Noord-Brabant",
    "sg:tags":[
        "maneges"
    ],
    "wof:name":"Heideruiter, De",
    "wof:placetype":"venue"
},
  "geometry": {"coordinates":[5.049133,51.510441],"type":"Point"}
}