{
  "type": "Feature",
  "properties": {
    "addr:full":"Nw Kerkstr 6 Zevenbergen North Brabant 4761 CP",
    "addr:housenumber":"6",
    "addr:postcode":"4761 cp",
    "addr:street":"Kerkstr",
    "iso:country":"NL",
    "sg:address":"Nw Kerkstr 6",
    "sg:city":"Zevenbergen",
    "sg:orig_category":"Juweliers",
    "sg:phone":"+31 168 335 199",
    "sg:postcode":"4761 CP",
    "sg:province":"North Brabant",
    "wof:name":"Loon, Juweliers Van",
    "wof:placetype":"venue"
},
  "geometry": {"coordinates":[4.603908,51.644184],"type":"Point"}
}