{
  "type": "Feature",
  "properties": {
    "iso:country":"NL",
    "sg:address":"Hillenraadwg 2",
    "sg:city":"S Gravenhage",
    "sg:orig_category":"Kinderopvang",
    "sg:phone":"+31 70 367 2692",
    "sg:postcode":"2532 AD",
    "sg:province":"South Holland",
    "wof:name":"Berenboot, De",
    "wof:placetype":"venue"
},
  "geometry": {"coordinates":[4.29807,52.048569],"type":"Point"}
}