{
  "type": "Feature",
  "properties": {
    "addr:full":"Herepoortenmolend 18 Groningen Groningen 9711 DG",
    "addr:housenumber":"18",
    "addr:postcode":"9711 dg",
    "addr:street":"Herepoortenmolend",
    "iso:country":"NL",
    "sg:address":"Herepoortenmolend 18",
    "sg:city":"Groningen",
    "sg:orig_category":"Artiesten/Gezelschappen",
    "sg:phone":"+31 50 312 3503",
    "sg:postcode":"9711 DG",
    "sg:province":"Groningen",
    "sg:website":"http://www.detweedames.nl",
    "wof:name":"Katja En Sonja",
    "wof:placetype":"venue"
},
  "geometry": {"coordinates":[6.567135,53.214127],"type":"Point"}
}