{
  "type": "Feature",
  "properties": {
    "addr:full":"H Dunantwg 2A Zutphen Gelderland 7201 EV",
    "addr:housenumber":"2a",
    "addr:postcode":"7201 ev",
    "addr:street":"Gelderland",
    "iso:country":"NL",
    "sg:address":"H Dunantwg 2A",
    "sg:city":"Zutphen",
    "sg:orig_category":"Autoschade- Herstelbedrijven",
    "sg:phone":"+31 575 555 535",
    "sg:postcode":"7201 EV",
    "sg:province":"Gelderland",
    "wof:name":"A & A",
    "wof:placetype":"venue"
},
  "geometry": {"coordinates":[6.196893,52.136005],"type":"Point"}
}