{
  "type": "Feature",
  "properties": {
    "addr:full":"C Ubaghsln 18 Valkenburg Lb Limburg 6301 LP",
    "addr:housenumber":"18",
    "addr:postcode":"lb;6301 lp",
    "iso:country":"NL",
    "sg:address":"C Ubaghsln 18",
    "sg:city":"Valkenburg Lb",
    "sg:orig_category":"Autorijscholen",
    "sg:phone":"+31 43 601 5164",
    "sg:postcode":"6301 LP",
    "sg:province":"Limburg",
    "wof:name":"Mulders, Bert",
    "wof:placetype":"venue"
},
  "geometry": {"coordinates":[5.83344,50.861328],"type":"Point"}
}