{
  "type": "Feature",
  "properties": {
    "iso:country":"NL",
    "sg:address":"Dorpsstr 46",
    "sg:city":"Oostkapelle",
    "sg:orig_category":"Kunsthandel",
    "sg:phone":"+31 118 583 148",
    "sg:postcode":"4356 AK",
    "sg:province":"Zeeland",
    "wof:name":"Stupa",
    "wof:placetype":"venue"
},
  "geometry": {"coordinates":[3.552798,51.565723],"type":"Point"}
}