{
  "type": "Feature",
  "properties": {
    "addr:full":"Vogelenzang 38 Lieshout North Brabant 5737 PT",
    "addr:housenumber":"38",
    "addr:postcode":"5737 pt",
    "addr:street":"Vogelenzang",
    "iso:country":"NL",
    "sg:address":"Vogelenzang 38",
    "sg:city":"Lieshout",
    "sg:orig_category":"Melktransporten",
    "sg:phone":"+31 499 421 856",
    "sg:postcode":"5737 PT",
    "sg:province":"North Brabant",
    "wof:name":"Heuvel, J Van Den",
    "wof:placetype":"venue"
},
  "geometry": {"coordinates":[5.584912,51.51804],"type":"Point"}
}