{
  "type": "Feature",
  "properties": {
    "addr:full":"Haarlemmerdk 131 Amsterdam North Holland 1013 KG",
    "addr:housenumber":"131",
    "addr:postcode":"1013 kg",
    "iso:country":"NL",
    "sg:address":"Haarlemmerdk 131",
    "sg:city":"Amsterdam",
    "sg:orig_category":"Vertalers",
    "sg:phone":"+31 20 625 6060",
    "sg:postcode":"1013 KG",
    "sg:province":"North Holland",
    "wof:name":"Turks Vertaalburo",
    "wof:placetype":"venue"
},
  "geometry": {"coordinates":[4.885399,52.383507],"type":"Point"}
}