{
  "type": "Feature",
  "properties": {
    "addr:full":"Merodeln 95 Breda Noord-Brabant 4824 BR",
    "addr:housenumber":"95",
    "addr:postcode":"4824 br",
    "addr:street":"Merodeln",
    "iso:country":"NL",
    "sg:address":"Merodeln 95",
    "sg:city":"Breda",
    "sg:orig_category":"Fotoreportages",
    "sg:phone":"+31 76 542 5443",
    "sg:postcode":"4824 BR",
    "sg:province":"Noord-Brabant",
    "wof:name":"Hoof, C E Van",
    "wof:placetype":"venue"
},
  "geometry": {"coordinates":[4.74994,51.612591],"type":"Point"}
}