{
  "type": "Feature",
  "properties": {
    "iso:country":"NL",
    "sg:address":"Dorpsstraat 68",
    "sg:city":"Castricum",
    "sg:orig_category":"Bloemen And Planten",
    "sg:phone":"+31 251 652 389",
    "sg:postcode":"1901 EM",
    "sg:province":"Noord-Holland",
    "wof:name":"Bloemenmagazijn Cools",
    "wof:placetype":"venue"
},
  "geometry": {"coordinates":[4.664368,52.547096],"type":"Point"}
}