{
  "type": "Feature",
  "properties": {
    "addr:full":"Bouwstraat 15 Utrecht Utrecht 3572 SN",
    "addr:housenumber":"15",
    "addr:postcode":"3572 sn",
    "addr:street":"Bouwstraat",
    "iso:country":"NL",
    "sg:address":"Bouwstraat 15",
    "sg:city":"Utrecht",
    "sg:orig_category":"Wasserettes And Stomerijen",
    "sg:phone":"+31 30 271 8692",
    "sg:postcode":"3572 SN",
    "sg:province":"Utrecht",
    "wof:name":"Chemische Wasserij G.J. Uppelschoten",
    "wof:placetype":"venue"
},
  "geometry": {"coordinates":[5.1301269531,52.0971107483],"type":"Point"}
}