{
  "type": "Feature",
  "properties": {
    "addr:full":"Raadhuispln 7 Oostburg Zeeland 4501 BG",
    "addr:housenumber":"7",
    "addr:postcode":"4501",
    "addr:street":"Raadhuispln",
    "iso:country":"NL",
    "sg:address":"Raadhuispln 7",
    "sg:city":"Oostburg",
    "sg:orig_category":"Juweliers",
    "sg:phone":"+31 117 454 479",
    "sg:postcode":"4501 BG",
    "sg:province":"Zeeland",
    "wof:name":"Fliers, Fa",
    "wof:placetype":"venue"
},
  "geometry": {"coordinates":[3.487263,51.326889],"type":"Point"}
}