{
  "type": "Feature",
  "properties": {
    "addr:full":"Paradysvogel 8 Westzaan North Holland 1551 RW",
    "addr:housenumber":"8;1551",
    "addr:postcode":"rw",
    "addr:street":"Paradysvogel",
    "iso:country":"NL",
    "sg:address":"Paradysvogel 8",
    "sg:city":"Westzaan",
    "sg:orig_category":"Schoonheidsinstituten",
    "sg:phone":"+31 75 615 6195",
    "sg:postcode":"1551 RW",
    "sg:province":"North Holland",
    "wof:name":"Witte Roos",
    "wof:placetype":"venue"
},
  "geometry": {"coordinates":[4.77465,52.457294],"type":"Point"}
}