{
  "type": "Feature",
  "properties": {
    "addr:full":"J De Beerstr 25 Tilburg Noord-Brabant 5048 AH",
    "addr:housenumber":"25",
    "addr:postcode":"5048 ah",
    "addr:street":"J De Beerstr",
    "iso:country":"NL",
    "sg:address":"J De Beerstr 25",
    "sg:city":"Tilburg",
    "sg:orig_category":"Oud Papier",
    "sg:phone":"+31 13 467 2727",
    "sg:postcode":"5048 AH",
    "sg:province":"Noord-Brabant",
    "wof:name":"Papierrecycling Brabant",
    "wof:placetype":"venue"
},
  "geometry": {"coordinates":[5.0559668541,51.5837364197],"type":"Point"}
}