{
  "type": "Feature",
  "properties": {
    "addr:full":"Bisonspoor 2012 Maarssen Noord-Holland 3605 LB",
    "addr:housenumber":"2012",
    "addr:postcode":"3605 lb",
    "addr:street":"Bisonspoor",
    "iso:country":"NL",
    "sg:address":"Bisonspoor 2012",
    "sg:city":"Maarssen",
    "sg:orig_category":"Kinderopvang Behalve Thuis",
    "sg:phone":"+31 346 575 529",
    "sg:postcode":"3605 LB",
    "sg:province":"Noord-Holland",
    "wof:name":"T Speelhuis",
    "wof:placetype":"venue"
},
  "geometry": {"coordinates":[5.030538,52.135529],"type":"Point"}
}