{
  "type": "Feature",
  "properties": {
    "iso:country":"NL",
    "sg:address":"Deventerwg 147",
    "sg:city":"Zutphen",
    "sg:orig_category":"Verenigingen En Stichtingen",
    "sg:phone":"+31 575 547 090",
    "sg:postcode":"7203 AG",
    "sg:province":"Gelderland",
    "wof:name":"Medewerkers In Gehoorzaamheid",
    "wof:placetype":"venue"
},
  "geometry": {"coordinates":[6.207936,52.151371],"type":"Point"}
}