{
  "type": "Feature",
  "properties": {
    "addr:full":"Stationsstr 30 Epe Gelderland 8161 CR",
    "addr:housenumber":"30;8161",
    "addr:postcode":"cr",
    "addr:street":"Stationsstr;Gelderland",
    "iso:country":"NL",
    "sg:address":"Stationsstr 30",
    "sg:city":"Epe",
    "sg:orig_category":"Cafetaria'S",
    "sg:phone":"+31 578 628 633",
    "sg:postcode":"8161 CR",
    "sg:province":"Gelderland",
    "wof:name":"Olde Stoof, D'",
    "wof:placetype":"venue"
},
  "geometry": {"coordinates":[5.98865,52.34753],"type":"Point"}
}