{
  "type": "Feature",
  "properties": {
    "iso:country":"NL",
    "sg:address":"Willibrordpad 1",
    "sg:city":"Wyk By Duurstede",
    "sg:orig_category":"Binnenhuisarchitectuur",
    "sg:phone":"+31 343 576 569",
    "sg:postcode":"3962 BS",
    "sg:province":"Utrecht",
    "wof:name":"Wal, O Ter",
    "wof:placetype":"venue"
},
  "geometry": {"coordinates":[5.333224,51.978683],"type":"Point"}
}