{
  "type": "Feature",
  "properties": {
    "addr:full":"Burg V Hooffln 173 Veldhoven Noord-Brabant 5503 BL",
    "addr:housenumber":"173",
    "addr:postcode":"5503 bl",
    "addr:street":"Burg V Hooffln",
    "iso:country":"NL",
    "sg:address":"Burg V Hooffln 173",
    "sg:city":"Veldhoven",
    "sg:orig_category":"Verzekeringen - Verzekeringskantoren",
    "sg:phone":"+31 40 253 6428",
    "sg:postcode":"5503 BL",
    "sg:province":"Noord-Brabant",
    "wof:name":"Veldsink Adviesgroep",
    "wof:placetype":"venue"
},
  "geometry": {"coordinates":[5.404554,51.421745],"type":"Point"}
}