{
  "type": "Feature",
  "properties": {
    "addr:full":"Ryndk 1 Wyk By Duurstede Utrecht 3962 MX",
    "addr:housenumber":"1",
    "addr:postcode":"duurstede;3962 mx",
    "addr:street":"Ryndk",
    "iso:country":"NL",
    "sg:address":"Ryndk 1",
    "sg:city":"Wyk By Duurstede",
    "sg:orig_category":"Wegenbouw",
    "sg:phone":"+31 343 571 641",
    "sg:postcode":"3962 MX",
    "sg:province":"Utrecht",
    "wof:name":"Anker Cv, Van Den",
    "wof:placetype":"venue"
},
  "geometry": {"coordinates":[5.3754000664,51.9853782654],"type":"Point"}
}