{
  "type": "Feature",
  "properties": {
    "iso:country":"NL",
    "sg:address":"Kanaal Noord 152",
    "sg:city":"Apeldoorn",
    "sg:orig_category":"Fietshandelaren",
    "sg:phone":"+31 55 367 1746",
    "sg:postcode":"7322 AC",
    "sg:province":"Gelderland",
    "wof:name":"Bike And Adventure Shop Stappenbelt",
    "wof:placetype":"venue"
},
  "geometry": {"coordinates":[5.972945,52.219666],"type":"Point"}
}