{
  "type": "Feature",
  "properties": {
    "addr:full":"Van Oostsanenstraat 15 Helmond Noord-Brabant 5702 BW",
    "addr:housenumber":"15",
    "addr:postcode":"5702 bw",
    "addr:street":"Van Oostsanenstraat",
    "iso:country":"NL",
    "sg:address":"Van Oostsanenstraat 15",
    "sg:city":"Helmond",
    "sg:orig_category":"Boekhouders",
    "sg:phone":"+31 492 538 229",
    "sg:postcode":"5702 BW",
    "sg:province":"Noord-Brabant",
    "wof:name":"Adm.Kant. B.C. Zoetelief",
    "wof:placetype":"venue"
},
  "geometry": {"coordinates":[5.677228,51.489456],"type":"Point"}
}