{
  "type": "Feature",
  "properties": {
    "addr:full":"Kloosterwg 7 Warffum Groningen 9989 TB",
    "addr:housenumber":"7",
    "addr:postcode":"9989 tb",
    "addr:street":"Kloosterwg",
    "iso:country":"NL",
    "sg:address":"Kloosterwg 7",
    "sg:city":"Warffum",
    "sg:orig_category":"Lasbedrijven",
    "sg:phone":"+31 595 422 538",
    "sg:postcode":"9989 TB",
    "sg:province":"Groningen",
    "wof:name":"Harm'S All In One",
    "wof:placetype":"venue"
},
  "geometry": {"coordinates":[6.573385,53.374119],"type":"Point"}
}