{
  "type": "Feature",
  "properties": {
    "addr:full":"K Onnesln 5 Amsterdam North Holland 1097 DE",
    "addr:housenumber":"5",
    "addr:postcode":"1097 de",
    "addr:street":"Onnesln",
    "iso:country":"NL",
    "sg:address":"K Onnesln 5",
    "sg:city":"Amsterdam",
    "sg:orig_category":"Verenigingen En Stichtingen",
    "sg:phone":"+31 20 668 1610",
    "sg:postcode":"1097 DE",
    "sg:province":"North Holland",
    "wof:name":"Gijsbrecht Van Aemstelgroep, Scouting",
    "wof:placetype":"venue"
},
  "geometry": {"coordinates":[4.89319,52.373119],"type":"Point"}
}