{
  "type": "Feature",
  "properties": {
    "addr:full":"Lindenln 15 Bergen Lb Missouri 5854 AM",
    "addr:housenumber":"15",
    "addr:postcode":"5854",
    "addr:street":"Lindenln",
    "iso:country":"NL",
    "sg:address":"Lindenln 15",
    "sg:city":"Bergen Lb",
    "sg:orig_category":"Gordijnen",
    "sg:phone":"+31 485 341 320",
    "sg:postcode":"5854 AM",
    "sg:province":"Missouri",
    "wof:name":"Briels Wonen",
    "wof:placetype":"venue"
},
  "geometry": {"coordinates":[-93.129936,36.705662],"type":"Point"}
}