{
  "type": "Feature",
  "properties": {
    "addr:full":"Noordzydsewg 225 Polsbroek Utrecht 3415 RE",
    "addr:housenumber":"225",
    "addr:postcode":"3415",
    "addr:street":"Polsbroek",
    "iso:country":"NL",
    "sg:address":"Noordzydsewg 225",
    "sg:city":"Polsbroek",
    "sg:classifiers":[
        {
            "category":"Retail",
            "subcategory":"Auto Repair",
            "type":"Services"
        }
    ],
    "sg:phone":"+31 182 309 384",
    "sg:postcode":"3415 RE",
    "sg:province":"Utrecht",
    "sg:tags":[
        "garage"
    ],
    "wof:name":"Schouten, Garagebedrijf",
    "wof:placetype":"venue"
},
  "geometry": {"coordinates":[4.900154,51.994598],"type":"Point"}
}