{
  "type": "Feature",
  "properties": {
    "addr:full":"Boerhaavepln 9 Oegstgeest South Holland 2343 LT",
    "addr:housenumber":"9",
    "addr:postcode":"2343 lt",
    "addr:street":"Boerhaavepln",
    "iso:country":"NL",
    "sg:address":"Boerhaavepln 9",
    "sg:city":"Oegstgeest",
    "sg:orig_category":"Kappers",
    "sg:phone":"+31 71 517 6067",
    "sg:postcode":"2343 LT",
    "sg:province":"South Holland",
    "wof:name":"Dick Dofferhoff",
    "wof:placetype":"venue"
},
  "geometry": {"coordinates":[4.4749951363,52.191444397],"type":"Point"}
}