{
  "type": "Feature",
  "properties": {
    "addr:full":"Pade 16 Opmeer North Holland 1716 KA",
    "addr:housenumber":"16",
    "addr:postcode":"1716 ka",
    "addr:street":"Pade",
    "iso:country":"NL",
    "sg:address":"Pade 16",
    "sg:city":"Opmeer",
    "sg:orig_category":"Honden- En Kattentrimsalons",
    "sg:phone":"+31 226 353 315",
    "sg:postcode":"1716 KA",
    "sg:province":"North Holland",
    "wof:name":"Wester, Christel",
    "wof:placetype":"venue"
},
  "geometry": {"coordinates":[4.937154,52.704586],"type":"Point"}
}