{
  "type": "Feature",
  "properties": {
    "iso:country":"NL",
    "sg:address":"Tollenburg 15",
    "sg:city":"Ede Gld",
    "sg:classifiers":[
        {
            "category":"Education",
            "subcategory":"Preschool",
            "type":"Public Place"
        }
    ],
    "sg:phone":"+31 318 645 110",
    "sg:postcode":"6714 EJ",
    "sg:province":"Gelderland",
    "sg:tags":[
        "kleuteronderwijs",
        "basis-"
    ],
    "wof:name":"Gereformeerde Basisschool De Triangel",
    "wof:placetype":"venue"
},
  "geometry": {"coordinates":[5.647382,52.046509],"type":"Point"}
}