{
  "type": "Feature",
  "properties": {
    "iso:country":"NL",
    "sg:address":"Zwanenwater 14",
    "sg:city":"Nieuw Vennep",
    "sg:orig_category":"Administratie- En Boekhoudkantoren",
    "sg:phone":"+31 252 674 214",
    "sg:postcode":"2152 BM",
    "sg:province":"Noord-Holland",
    "wof:name":"Overbeek, J",
    "wof:placetype":"venue"
},
  "geometry": {"coordinates":[4.633391,52.268734],"type":"Point"}
}