{
  "type": "Feature",
  "properties": {
    "addr:full":"Ommerweg 67 Den Ham Ov NL.08 7683 AW",
    "addr:housenumber":"67",
    "addr:postcode":"7683 aw",
    "addr:street":"Ommerweg;Ov",
    "iso:country":"NL",
    "sg:address":"Ommerweg 67",
    "sg:city":"Den Ham Ov",
    "sg:orig_category":"Huizensloop And Bouwrijp Maken",
    "sg:phone":"+31 546 671 495",
    "sg:postcode":"7683 AW",
    "sg:province":"NL.08",
    "wof:name":"Wetering Den Ham Bv",
    "wof:placetype":"venue"
},
  "geometry": {"coordinates":[6.496274,52.462387],"type":"Point"}
}