{
  "type": "Feature",
  "properties": {
    "addr:full":"Wassenaarstr 54-56 Bergen Op Zoom North Brabant 4611 BW",
    "addr:housenumber":"54-56",
    "addr:postcode":"4611 bw",
    "iso:country":"NL",
    "sg:address":"Wassenaarstr 54-56",
    "sg:city":"Bergen Op Zoom",
    "sg:orig_category":"Verzekeringen - Verzekeringskantoren",
    "sg:phone":"+31 164 233 094",
    "sg:postcode":"4611 BW",
    "sg:province":"North Brabant",
    "wof:name":"D & G",
    "wof:placetype":"venue"
},
  "geometry": {"coordinates":[4.292233,51.493752],"type":"Point"}
}