{
  "type": "Feature",
  "properties": {
    "iso:country":"NL",
    "sg:address":"Oude Middelhorst 48",
    "sg:city":"Haren Gn",
    "sg:orig_category":"Magazijninrichtingen",
    "sg:phone":"+31 50 534 4261",
    "sg:postcode":"9753 BS",
    "sg:province":"Groningen",
    "wof:name":"Batech",
    "wof:placetype":"venue"
},
  "geometry": {"coordinates":[6.6282310486,53.1752052307],"type":"Point"}
}