{
  "type": "Feature",
  "properties": {
    "addr:full":"Middenwg 456 Heerhugowaard North Holland 1704 BK",
    "addr:housenumber":"456",
    "addr:postcode":"1704 bk",
    "iso:country":"NL",
    "sg:address":"Middenwg 456",
    "sg:city":"Heerhugowaard",
    "sg:orig_category":"Koeriersdiensten",
    "sg:phone":"+31 72 572 5000",
    "sg:postcode":"1704 BK",
    "sg:province":"North Holland",
    "wof:name":"Aa Koeriers Vof",
    "wof:placetype":"venue"
},
  "geometry": {"coordinates":[4.850782,52.692303],"type":"Point"}
}