{
  "type": "Feature",
  "properties": {
    "addr:full":"Bunschotenstraat 23 Almere Flevoland 1324 PC",
    "addr:housenumber":"23",
    "addr:postcode":"1324 pc",
    "addr:street":"Bunschotenstraat;Flevoland",
    "iso:country":"NL",
    "sg:address":"Bunschotenstraat 23",
    "sg:city":"Almere",
    "sg:orig_category":"Diverse Grafische Activiteiten",
    "sg:phone":"+31 36 534 2260",
    "sg:postcode":"1324 PC",
    "sg:province":"Flevoland",
    "wof:name":"Jan H. Van Uden (Spiral Studio)",
    "wof:placetype":"venue"
},
  "geometry": {"coordinates":[5.20386,52.364388],"type":"Point"}
}