{
  "type": "Feature",
  "properties": {
    "iso:country":"NL",
    "sg:address":"Vlierboomstr 600",
    "sg:city":"S Gravenhage",
    "sg:orig_category":"Zonnebank- En Solariumcentra",
    "sg:phone":"+31 70 368 6788",
    "sg:postcode":"2564 JP",
    "sg:province":"South Holland",
    "wof:name":"Pon-Sun",
    "wof:placetype":"venue"
},
  "geometry": {"coordinates":[4.2594599724,52.0680503845],"type":"Point"}
}