{
  "type": "Feature",
  "properties": {
    "addr:full":"Bohrwg 26 Spykenisse Zuid-Holland 3208 KR",
    "addr:housenumber":"26",
    "addr:postcode":"3208 kr",
    "addr:street":"Bohrwg",
    "iso:country":"NL",
    "sg:address":"Bohrwg 26",
    "sg:city":"Spykenisse",
    "sg:orig_category":"Beveiliging",
    "sg:phone":"+31 181 623 111",
    "sg:postcode":"3208 KR",
    "sg:province":"Zuid-Holland",
    "wof:name":"Safe Eye Bv",
    "wof:placetype":"venue"
},
  "geometry": {"coordinates":[4.3029,51.84264],"type":"Point"}
}