{
  "type": "Feature",
  "properties": {
    "addr:full":"Dudokplein 1 Ijmuiden Noord-Holland 1971 EN",
    "addr:housenumber":"1",
    "addr:postcode":"1971 en",
    "addr:street":"Dudokplein",
    "iso:country":"NL",
    "sg:address":"Dudokplein 1",
    "sg:city":"Ijmuiden",
    "sg:orig_category":"Overheidsdiensten",
    "sg:phone":"+31 255 567 200",
    "sg:postcode":"1971 EN",
    "sg:province":"Noord-Holland",
    "wof:name":"Gemeente En Gem Instellingen",
    "wof:placetype":"venue"
},
  "geometry": {"coordinates":[4.6236829758,52.4607315063],"type":"Point"}
}