{
  "type": "Feature",
  "properties": {
    "addr:full":"Nieuwstr 20 Hengelo Ov NL.08 7551 CX",
    "addr:housenumber":"20",
    "addr:postcode":"7551 cx",
    "addr:street":"Nieuwstr;Ov",
    "iso:country":"NL",
    "sg:address":"Nieuwstr 20",
    "sg:city":"Hengelo Ov",
    "sg:orig_category":"Opticiens",
    "sg:phone":"+31 74 291 5769",
    "sg:postcode":"7551 CX",
    "sg:province":"NL.08",
    "wof:name":"Specsavers",
    "wof:placetype":"venue"
},
  "geometry": {"coordinates":[6.7897119522,52.2663612366],"type":"Point"}
}