{
  "type": "Feature",
  "properties": {
    "addr:full":"Eikenlaan 1 Venray Limburg 5802 CS",
    "addr:housenumber":"1",
    "addr:postcode":"5802 cs",
    "addr:street":"Eikenlaan",
    "iso:country":"NL",
    "sg:address":"Eikenlaan 1",
    "sg:city":"Venray",
    "sg:classifiers":[
        {
            "category":"Education",
            "subcategory":"Preschool",
            "type":"Public Place"
        }
    ],
    "sg:phone":"+31 478 569 711",
    "sg:postcode":"5802 CS",
    "sg:province":"Limburg",
    "sg:tags":[
        "kleuteronderwijs",
        "basis-"
    ],
    "wof:name":"Basisschool De Bongerd",
    "wof:placetype":"venue"
},
  "geometry": {"coordinates":[5.979552,51.520508],"type":"Point"}
}