{
  "type": "Feature",
  "properties": {
    "addr:full":"Jutfasewg 1 Utrecht Utrecht 3522 HA",
    "addr:housenumber":"1",
    "addr:postcode":"3522 ha",
    "addr:street":"Jutfasewg",
    "iso:country":"NL",
    "sg:address":"Jutfasewg 1",
    "sg:city":"Utrecht",
    "sg:orig_category":"Hypotheken",
    "sg:phone":"+31 30 289 3434",
    "sg:postcode":"3522 HA",
    "sg:province":"Utrecht",
    "wof:name":"Rijnlandse Hypotheekbank",
    "wof:placetype":"venue"
},
  "geometry": {"coordinates":[5.121314,52.07811],"type":"Point"}
}