{
  "type": "Feature",
  "properties": {
    "addr:full":"Sprongstraat 8 Zutphen Gelderland 7201 KS",
    "addr:housenumber":"8",
    "addr:postcode":"7201 ks",
    "addr:street":"Sprongstraat;Gelderland",
    "iso:country":"NL",
    "sg:address":"Sprongstraat 8",
    "sg:city":"Zutphen",
    "sg:orig_category":"Herenmodezaken",
    "sg:phone":"+31 575 543 992",
    "sg:postcode":"7201 KS",
    "sg:province":"Gelderland",
    "wof:name":"Ferry'S Fashion",
    "wof:placetype":"venue"
},
  "geometry": {"coordinates":[6.197247,52.140911],"type":"Point"}
}