{
  "type": "Feature",
  "properties": {
    "iso:country":"NL",
    "sg:address":"Westerhaven 5",
    "sg:city":"Groningen",
    "sg:orig_category":"Automaterialen En Gereedschappen",
    "sg:phone":"+31 50 313 9017",
    "sg:postcode":"9718 AT",
    "sg:province":"Groningen",
    "sg:website":"http://www.ava.nl",
    "wof:name":"Ava",
    "wof:placetype":"venue"
},
  "geometry": {"coordinates":[6.558124,53.216347],"type":"Point"}
}