{
  "type": "Feature",
  "properties": {
    "addr:full":"Lange Hofstraat 22 Zutphen Gelderland 7201 HV",
    "addr:housenumber":"22",
    "addr:postcode":"7201 hv",
    "addr:street":"Lange Hofstraat;Gelderland",
    "iso:country":"NL",
    "sg:address":"Lange Hofstraat 22",
    "sg:city":"Zutphen",
    "sg:classifiers":[
        {
            "category":"Bakery",
            "type":"Food & Drink"
        }
    ],
    "sg:phone":"+31 575 513 269",
    "sg:postcode":"7201 HV",
    "sg:province":"Gelderland",
    "sg:tags":[
        "brood",
        "banket"
    ],
    "wof:name":"Van Rooyens Bakkerij",
    "wof:placetype":"venue"
},
  "geometry": {"coordinates":[6.195295,52.140827],"type":"Point"}
}