{
  "type": "Feature",
  "properties": {
    "addr:full":"Meervalstraat 27 Aalsmeer North Holland 1431 WE",
    "addr:housenumber":"27",
    "addr:postcode":"1431 we",
    "addr:street":"Meervalstraat",
    "iso:country":"NL",
    "sg:address":"Meervalstraat 27",
    "sg:city":"Aalsmeer",
    "sg:orig_category":"Kinderopvang Behalve Thuis",
    "sg:phone":"+31 297 344 613",
    "sg:postcode":"1431 WE",
    "sg:province":"North Holland",
    "wof:name":"Kinderdagverblijf Kiekeboe",
    "wof:placetype":"venue"
},
  "geometry": {"coordinates":[4.76477,52.254646],"type":"Point"}
}