{
  "type": "Feature",
  "properties": {
    "addr:full":"Blekerstr 20 Almere Flevoland 1315 AH",
    "addr:housenumber":"20",
    "addr:postcode":"1315 ah",
    "addr:street":"Blekerstr;Flevoland",
    "iso:country":"NL",
    "sg:address":"Blekerstr 20",
    "sg:city":"Almere",
    "sg:orig_category":"Verenigingen En Stichtingen",
    "sg:phone":"+31 36 533 1500",
    "sg:postcode":"1315 AH",
    "sg:province":"Flevoland",
    "wof:name":"Openb Onderwijs, Ver Voor",
    "wof:placetype":"venue"
},
  "geometry": {"coordinates":[5.215557,52.368999],"type":"Point"}
}