{
  "type": "Feature",
  "properties": {
    "addr:full":"Eurowerft 16 Denekamp Overijssel 7591 DG",
    "addr:housenumber":"16",
    "addr:postcode":"7591 dg",
    "addr:street":"Eurowerft",
    "iso:country":"NL",
    "sg:address":"Eurowerft 16",
    "sg:city":"Denekamp",
    "sg:orig_category":"Drogisterijen",
    "sg:phone":"+31 541 351 775",
    "sg:postcode":"7591 DG",
    "sg:province":"Overijssel",
    "wof:name":"Firma J.H. Benneker En Zonen",
    "wof:placetype":"venue"
},
  "geometry": {"coordinates":[7.006879,52.375439],"type":"Point"}
}