{
  "type": "Feature",
  "properties": {
    "addr:full":"Van Arkelstraat 19 Asperen Gelderland 4147 EL",
    "addr:housenumber":"19",
    "addr:postcode":"4147 el",
    "addr:street":"Van Arkelstraat;Gelderland",
    "iso:country":"NL",
    "sg:address":"Van Arkelstraat 19",
    "sg:city":"Asperen",
    "sg:orig_category":"Verlichting And Huishoudartikelen",
    "sg:phone":"+31 345 615 019",
    "sg:postcode":"4147 EL",
    "sg:province":"Gelderland",
    "wof:name":"Ij.Th. Jansen",
    "wof:placetype":"venue"
},
  "geometry": {"coordinates":[5.107814,51.881649],"type":"Point"}
}