{
  "type": "Feature",
  "properties": {
    "addr:full":"Schoolstr 1 Vrouwenpolder Zeeland 4354 AJ",
    "addr:housenumber":"1",
    "addr:postcode":"4354 aj",
    "addr:street":"Schoolstr",
    "iso:country":"NL",
    "sg:address":"Schoolstr 1",
    "sg:city":"Vrouwenpolder",
    "sg:classifiers":[
        {
            "category":"Restaurant",
            "type":"Food & Drink"
        }
    ],
    "sg:phone":"+31 118 593 507",
    "sg:postcode":"4354 AJ",
    "sg:province":"Zeeland",
    "sg:website":"http://www.vietnam.zeelandnet.nl",
    "wof:name":"Vietnam",
    "wof:placetype":"venue"
},
  "geometry": {"coordinates":[3.617652,51.575893],"type":"Point"}
}