{
  "type": "Feature",
  "properties": {
    "addr:full":"Lange Jansstraat 20 Utrecht Utrecht 3512 BB",
    "addr:housenumber":"20",
    "addr:postcode":"3512 bb",
    "addr:street":"Lange Jansstraat",
    "iso:country":"NL",
    "sg:address":"Lange Jansstraat 20",
    "sg:city":"Utrecht",
    "sg:orig_category":"Drukkerijen And Copyshops",
    "sg:phone":"+31 30 231 4213",
    "sg:postcode":"3512 BB",
    "sg:province":"Utrecht",
    "wof:name":"Drukkerij Van Nieuwenhuijsen Bv",
    "wof:placetype":"venue"
},
  "geometry": {"coordinates":[5.120083,52.093624],"type":"Point"}
}