{
  "type": "Feature",
  "properties": {
    "iso:country":"NL",
    "sg:address":"Handelswg 2",
    "sg:city":"Zeist",
    "sg:orig_category":"Verzekerings- Maatschappijen",
    "sg:phone":"+31 30 693 7000",
    "sg:postcode":"3707 NH",
    "sg:province":"Utrecht",
    "wof:name":"Achmea",
    "wof:placetype":"venue"
},
  "geometry": {"coordinates":[5.259882,52.105293],"type":"Point"}
}