{
  "type": "Feature",
  "properties": {
    "addr:full":"Postbus 12651 S Gravenhage South Holland 2500 DP",
    "addr:housenumber":"12651",
    "addr:postcode":"2500 dp",
    "addr:street":"Postbus;S Gravenhage",
    "iso:country":"NL",
    "sg:address":"Postbus 12651",
    "sg:city":"S Gravenhage",
    "sg:orig_category":"Milieu",
    "sg:phone":"+31 70 353 6666",
    "sg:postcode":"2500 DP",
    "sg:province":"South Holland",
    "sg:website":"http://www.denhaag.nl",
    "wof:name":"Dienst Stadsbeheer",
    "wof:placetype":"venue"
},
  "geometry": {"coordinates":[4.31741,52.083988],"type":"Point"}
}