{
  "type": "Feature",
  "properties": {
    "addr:full":"Schouwwg 30 Wassenaar Zuid-Holland 2243 BC",
    "addr:housenumber":"30",
    "addr:postcode":"2243 bc",
    "addr:street":"Schouwwg",
    "iso:country":"NL",
    "sg:address":"Schouwwg 30",
    "sg:city":"Wassenaar",
    "sg:orig_category":"Tekstschrijversters",
    "sg:phone":"+31 70 511 4705",
    "sg:postcode":"2243 BC",
    "sg:province":"Zuid-Holland",
    "wof:name":"M@Rtje.Nl",
    "wof:placetype":"venue"
},
  "geometry": {"coordinates":[4.387468,52.135788],"type":"Point"}
}