{
  "type": "Feature",
  "properties": {
    "iso:country":"NL",
    "sg:address":"Schuitendiep 51",
    "sg:city":"Groningen",
    "sg:orig_category":"Architecten En Architectenbureaus",
    "sg:phone":"+31 50 313 7035",
    "sg:postcode":"9711 RB",
    "sg:province":"Groningen",
    "wof:name":"Beukman, W",
    "wof:placetype":"venue"
},
  "geometry": {"coordinates":[6.57329,53.217171],"type":"Point"}
}