{
  "type": "Feature",
  "properties": {
    "addr:full":"Dissel 10 Nuland Noord-Brabant 5391 CM",
    "addr:housenumber":"10",
    "addr:postcode":"5391 cm",
    "addr:street":"Dissel",
    "iso:country":"NL",
    "sg:address":"Dissel 10",
    "sg:city":"Nuland",
    "sg:classifiers":[
        {
            "category":"Personal",
            "subcategory":"Nail Salon",
            "type":"Services"
        }
    ],
    "sg:phone":"+31 73 532 2668",
    "sg:postcode":"5391 CM",
    "sg:province":"Noord-Brabant",
    "sg:tags":[
        "pedicure"
    ],
    "wof:name":"Quinten-Verkuijlen, J",
    "wof:placetype":"venue"
},
  "geometry": {"coordinates":[5.43745,51.724819],"type":"Point"}
}