{
  "type": "Feature",
  "properties": {
    "addr:full":"Rynhaven 11 Wageningen Gelderland 6702 DT",
    "addr:housenumber":"11",
    "addr:postcode":"6702 dt",
    "addr:street":"Rynhaven;Gelderland",
    "iso:country":"NL",
    "sg:address":"Rynhaven 11",
    "sg:city":"Wageningen",
    "sg:orig_category":"Begrafenisverzorging",
    "sg:phone":"+31 317 417 426",
    "sg:postcode":"6702 DT",
    "sg:province":"Gelderland",
    "wof:name":"Dijk-Rituele Vormgeving, Trudy Van",
    "wof:placetype":"venue"
},
  "geometry": {"coordinates":[5.660976,51.964355],"type":"Point"}
}