{
  "type": "Feature",
  "properties": {
    "addr:full":"Kerkplein 1 Dalfsen NL.08 7721 AC",
    "addr:housenumber":"1;nl.08",
    "addr:postcode":"7721 ac",
    "addr:street":"Kerkplein",
    "iso:country":"NL",
    "sg:address":"Kerkplein 1",
    "sg:city":"Dalfsen",
    "sg:orig_category":"Bloemen And Planten",
    "sg:phone":"+31 529 435 013",
    "sg:postcode":"7721 AC",
    "sg:province":"NL.08",
    "wof:name":"Hertsenberg Bloemenshop Vof",
    "wof:placetype":"venue"
},
  "geometry": {"coordinates":[6.26187,52.50462],"type":"Point"}
}