{
  "type": "Feature",
  "properties": {
    "addr:full":"Jan Van Vlissingenhof 16 Helmond Noord-Brabant 5709 AP",
    "addr:housenumber":"16",
    "addr:postcode":"5709 ap",
    "addr:street":"Jan Van Vlissingenhof",
    "iso:country":"NL",
    "sg:address":"Jan Van Vlissingenhof 16",
    "sg:city":"Helmond",
    "sg:orig_category":"Verlichting And Huishoudartikelen",
    "sg:phone":"+31 492 511 450",
    "sg:postcode":"5709 AP",
    "sg:province":"Noord-Brabant",
    "wof:name":"Riky Van Der Ven",
    "wof:placetype":"venue"
},
  "geometry": {"coordinates":[5.711064,51.47435],"type":"Point"}
}