{
  "type": "Feature",
  "properties": {
    "iso:country":"NL",
    "sg:address":"Merelstraat 135",
    "sg:city":"Haaksbergen",
    "sg:orig_category":"Kappers",
    "sg:phone":"+31 53 572 6049",
    "sg:postcode":"7481 AM",
    "sg:province":"Overijssel",
    "wof:name":"E.J. Horck",
    "wof:placetype":"venue"
},
  "geometry": {"coordinates":[6.7511210442,52.1644172668],"type":"Point"}
}