{
  "type": "Feature",
  "properties": {
    "addr:full":"Graaf Gustaaflaan 3 Nieuwegein Utrecht 3434 DX",
    "addr:housenumber":"3",
    "addr:postcode":"3434 dx",
    "addr:street":"Graaf Gustaaflaan",
    "iso:country":"NL",
    "sg:address":"Graaf Gustaaflaan 3",
    "sg:city":"Nieuwegein",
    "sg:orig_category":"Makelaars In Onroerend Goed",
    "sg:phone":"+31 30 601 8020",
    "sg:postcode":"3434 DX",
    "sg:province":"Utrecht",
    "wof:name":"Arverni Vastgoed",
    "wof:placetype":"venue"
},
  "geometry": {"coordinates":[5.091382,52.015007],"type":"Point"}
}