{
  "type": "Feature",
  "properties": {
    "iso:country":"NL",
    "sg:address":"Zandwg 2",
    "sg:city":"Domburg",
    "sg:orig_category":"Loonbedrijven",
    "sg:phone":"+31 118 583 261",
    "sg:postcode":"4357 RL",
    "sg:province":"Zeeland",
    "wof:name":"Visser, De",
    "wof:placetype":"venue"
},
  "geometry": {"coordinates":[3.508683,51.558727],"type":"Point"}
}