{
  "type": "Feature",
  "properties": {
    "addr:full":"Eiland 62 Leerdam South Holland 4143 ER",
    "addr:housenumber":"62",
    "addr:postcode":"4143 er",
    "addr:street":"Eiland",
    "iso:country":"NL",
    "sg:address":"Eiland 62",
    "sg:city":"Leerdam",
    "sg:classifiers":[
        {
            "category":"Education",
            "subcategory":"Preschool",
            "type":"Public Place"
        }
    ],
    "sg:phone":"+31 345 632 361",
    "sg:postcode":"4143 ER",
    "sg:province":"South Holland",
    "sg:tags":[
        "kleuteronderwijs",
        "basis-"
    ],
    "wof:name":"Chr. Basisschool Koningin Wilhelmina",
    "wof:placetype":"venue"
},
  "geometry": {"coordinates":[5.090389,51.898254],"type":"Point"}
}