{
  "type": "Feature",
  "properties": {
    "iso:country":"NL",
    "sg:address":"Broeksewg 3",
    "sg:city":"Ameide",
    "sg:orig_category":"Schilders",
    "sg:phone":"+31 183 601 725",
    "sg:postcode":"4233 CS",
    "sg:province":"Zuid-Holland",
    "wof:name":"Erkelens-Langerak",
    "wof:placetype":"venue"
},
  "geometry": {"coordinates":[4.963216,51.954178],"type":"Point"}
}