{
  "type": "Feature",
  "properties": {
    "iso:country":"NL",
    "sg:address":"Pieter Maritzstraat 25",
    "sg:city":"Wassenaar",
    "sg:orig_category":"Loodgieterswerk, Verwarming And Sanitaire Installaties",
    "sg:phone":"+31 70 511 9803",
    "sg:postcode":"2242 VW",
    "sg:province":"Zuid-Holland",
    "wof:name":"R H Eduard",
    "wof:placetype":"venue"
},
  "geometry": {"coordinates":[4.395748,52.150261],"type":"Point"}
}