{
  "type": "Feature",
  "properties": {
    "iso:country":"NL",
    "sg:address":"Zwartewg 108",
    "sg:city":"Aalsmeer",
    "sg:orig_category":"Begrafenisverzorging",
    "sg:phone":"+31 297 325 865",
    "sg:postcode":"1431 VM",
    "sg:province":"North Holland",
    "wof:name":"Finnema Bv",
    "wof:placetype":"venue"
},
  "geometry": {"coordinates":[4.771594,52.261463],"type":"Point"}
}