{
  "type": "Feature",
  "properties": {
    "addr:full":"Johan Willem Frisostraat 133 Zoetermeer Zuid-Holland 2713 CC",
    "addr:housenumber":"133",
    "addr:postcode":"2713 cc",
    "addr:street":"Johan Willem Frisostraat",
    "iso:country":"NL",
    "sg:address":"Johan Willem Frisostraat 133",
    "sg:city":"Zoetermeer",
    "sg:orig_category":"Hypotheken And Hypotheekbanken",
    "sg:phone":"+31 79 316 4651",
    "sg:postcode":"2713 CC",
    "sg:province":"Zuid-Holland",
    "wof:name":"Rjr Adviesburo Cv",
    "wof:placetype":"venue"
},
  "geometry": {"coordinates":[4.48788,52.051781],"type":"Point"}
}