{
  "type": "Feature",
  "properties": {
    "addr:full":"Bovendijk 39 Kwintsheul Zuid-Holland 2295 RV",
    "addr:housenumber":"39",
    "addr:postcode":"2295 rv",
    "addr:street":"Bovendijk",
    "iso:country":"NL",
    "sg:address":"Bovendijk 39",
    "sg:city":"Kwintsheul",
    "sg:orig_category":"Boekhouders",
    "sg:phone":"+31 174 296 641",
    "sg:postcode":"2295 RV",
    "sg:province":"Zuid-Holland",
    "wof:name":"Admac Bv",
    "wof:placetype":"venue"
},
  "geometry": {"coordinates":[4.262409,52.014004],"type":"Point"}
}