{
  "type": "Feature",
  "properties": {
    "addr:full":"Weimanswg 70 Rotterdam Zuid-Holland 3075 MP",
    "addr:housenumber":"70",
    "addr:postcode":"3075 mp",
    "addr:street":"Weimanswg",
    "iso:country":"NL",
    "sg:address":"Weimanswg 70",
    "sg:city":"Rotterdam",
    "sg:orig_category":"Verenigingen En Stichtingen",
    "sg:phone":"+31 10 215 2855",
    "sg:postcode":"3075 MP",
    "sg:province":"Zuid-Holland",
    "wof:name":"Inloophuis, Rotterdam",
    "wof:placetype":"venue"
},
  "geometry": {"coordinates":[4.501947,51.888885],"type":"Point"}
}