{
  "type": "Feature",
  "properties": {
    "addr:full":"Tijnjedyk 3 Leeuwarden Friesland 8934 BT",
    "addr:housenumber":"3",
    "addr:postcode":"8934 bt",
    "addr:street":"Tijnjedyk",
    "iso:country":"NL",
    "sg:address":"Tijnjedyk 3",
    "sg:city":"Leeuwarden",
    "sg:orig_category":"Bloemen And Planten",
    "sg:phone":"+31 58 288 7744",
    "sg:postcode":"8934 BT",
    "sg:province":"Friesland",
    "wof:name":"Klaver Hydrocultuur Bv",
    "wof:placetype":"venue"
},
  "geometry": {"coordinates":[5.81357,53.192429],"type":"Point"}
}