{
  "type": "Feature",
  "properties": {
    "addr:full":"Dorpsstr 60 Vaassen Gelderland 8171 BS",
    "addr:housenumber":"60",
    "addr:postcode":"8171 bs",
    "addr:street":"Dorpsstr;Gelderland",
    "iso:country":"NL",
    "sg:address":"Dorpsstr 60",
    "sg:city":"Vaassen",
    "sg:orig_category":"Banken",
    "sg:phone":"+31 578 676 100",
    "sg:postcode":"8171 BS",
    "sg:province":"Gelderland",
    "sg:website":"http://www.rabobank.nl",
    "wof:name":"Rabobank",
    "wof:placetype":"venue"
},
  "geometry": {"coordinates":[5.968238,52.288143],"type":"Point"}
}