{
  "type": "Feature",
  "properties": {
    "addr:full":"Stadionplein 41 Maastricht Limburg 6225 XW",
    "addr:housenumber":"41",
    "addr:postcode":"6225 xw",
    "addr:street":"Stadionplein",
    "iso:country":"NL",
    "sg:address":"Stadionplein 41",
    "sg:city":"Maastricht",
    "sg:classifiers":[
        {
            "category":"Professional",
            "subcategory":"Accounting & Tax Preparation",
            "type":"Services"
        }
    ],
    "sg:phone":"+31 43 362 8525",
    "sg:postcode":"6225 XW",
    "sg:province":"Limburg",
    "sg:tags":[
        "accountant"
    ],
    "sg:website":"http://www.deleau.nl",
    "wof:name":"Deleau Adviseurs",
    "wof:placetype":"venue"
},
  "geometry": {"coordinates":[5.716666,50.857185],"type":"Point"}
}