{
  "type": "Feature",
  "properties": {
    "addr:full":"Dennis Leestraat 39 Stampersgat Noord-Brabant 4754 BB",
    "addr:housenumber":"39",
    "addr:postcode":"4754 bb",
    "addr:street":"Dennis Leestraat",
    "iso:country":"NL",
    "sg:address":"Dennis Leestraat 39",
    "sg:city":"Stampersgat",
    "sg:orig_category":"Verhuur Audiovisuele Apparatuur",
    "sg:phone":"+31 165 514 934",
    "sg:postcode":"4754 BB",
    "sg:province":"Noord-Brabant",
    "wof:name":"T & F Sound Systems",
    "wof:placetype":"venue"
},
  "geometry": {"coordinates":[4.446647,51.613224],"type":"Point"}
}