{
  "type": "Feature",
  "properties": {
    "addr:full":"Jansstr 10 Arnhem Gelderland 6811 GJ",
    "addr:housenumber":"10",
    "addr:postcode":"6811 gj",
    "addr:street":"Jansstr",
    "iso:country":"NL",
    "sg:address":"Jansstr 10",
    "sg:city":"Arnhem",
    "sg:classifiers":[
        {
            "category":"Shopping",
            "subcategory":"Adult",
            "type":"Retail Goods"
        }
    ],
    "sg:phone":"+31 26 442 5966",
    "sg:postcode":"6811 GJ",
    "sg:province":"Gelderland",
    "sg:tags":[
        "lingerie",
        "en",
        "tricotage"
    ],
    "wof:name":"Livera",
    "wof:placetype":"venue"
},
  "geometry": {"coordinates":[5.905715,51.982761],"type":"Point"}
}