{
  "type": "Feature",
  "properties": {
    "addr:full":"Heuvel Galerie 146 Eindhoven Noord-Brabant 5611 DK",
    "addr:housenumber":"146",
    "addr:postcode":"5611 dk",
    "addr:street":"Heuvel Galerie",
    "iso:country":"NL",
    "sg:address":"Heuvel Galerie 146",
    "sg:city":"Eindhoven",
    "sg:orig_category":"Bijouterie?n",
    "sg:phone":"+31 40 244 5199",
    "sg:postcode":"5611 DK",
    "sg:province":"Noord-Brabant",
    "wof:name":"Brigitte",
    "wof:placetype":"venue"
},
  "geometry": {"coordinates":[5.47988,51.438873],"type":"Point"}
}