{
  "type": "Feature",
  "properties": {
    "addr:full":"De Fantasie 5 Almere NL. 1324 HZ",
    "addr:housenumber":"5",
    "addr:postcode":"1324 hz",
    "addr:street":"De Fantasie;Nl.",
    "iso:country":"NL",
    "sg:address":"De Fantasie 5",
    "sg:city":"Almere",
    "sg:orig_category":"Beeldende Kunstenaars",
    "sg:phone":"+31 36 534 4575",
    "sg:postcode":"1324 HZ",
    "sg:province":"NL.",
    "wof:name":"Ruben, G J",
    "wof:placetype":"venue"
},
  "geometry": {"coordinates":[5.213381,52.35854],"type":"Point"}
}