{
  "type": "Feature",
  "properties": {
    "iso:country":"NL",
    "sg:address":"Slaperdijkweg 74",
    "sg:city":"Haarlem",
    "sg:orig_category":"Loodgieterswerk, Verwarming And Sanitaire Installaties",
    "sg:phone":"+31 23 538 7622",
    "sg:postcode":"2026 BL",
    "sg:province":"North Holland",
    "wof:name":"Everts Installatie Techniek",
    "wof:placetype":"venue"
},
  "geometry": {"coordinates":[4.652275,52.426418],"type":"Point"}
}