{
  "type": "Feature",
  "properties": {
    "iso:country":"NL",
    "sg:address":"Bromeliastr 3",
    "sg:city":"Almere",
    "sg:orig_category":"Onderhoudswerken",
    "sg:phone":"+31 36 532 7327",
    "sg:postcode":"1338 ZX",
    "sg:province":"Flevoland",
    "wof:name":"Ceka",
    "wof:placetype":"venue"
},
  "geometry": {"coordinates":[5.290609,52.388355],"type":"Point"}
}