{
  "type": "Feature",
  "properties": {
    "iso:country":"NL",
    "sg:address":"Hoge Eng-Oost 11",
    "sg:city":"Putten",
    "sg:orig_category":"Diverse Bedrijfsinstallaties Gh",
    "sg:phone":"+31 341 361 633",
    "sg:postcode":"3882 TM",
    "sg:province":"Gelderland",
    "wof:name":"Techni Fix",
    "wof:placetype":"venue"
},
  "geometry": {"coordinates":[5.605889,52.249046],"type":"Point"}
}