{
  "type": "Feature",
  "properties": {
    "addr:full":"Eindhovensewg 64 Waalre Noord-Brabant 5582 HV",
    "addr:housenumber":"64",
    "addr:postcode":"5582 hv",
    "addr:street":"Eindhovensewg",
    "iso:country":"NL",
    "sg:address":"Eindhovensewg 64",
    "sg:city":"Waalre",
    "sg:orig_category":"Kappers",
    "sg:phone":"+31 40 221 6624",
    "sg:postcode":"5582 HV",
    "sg:province":"Noord-Brabant",
    "wof:name":"Gidy",
    "wof:placetype":"venue"
},
  "geometry": {"coordinates":[5.4767432213,51.395614624],"type":"Point"}
}