{
  "type": "Feature",
  "properties": {
    "iso:country":"NL",
    "sg:address":"Prinsenhil 29",
    "sg:city":"Breda",
    "sg:orig_category":"Bewakingsdiensten",
    "sg:phone":"+31 76 572 9916",
    "sg:postcode":"4825 AX",
    "sg:province":"Noord-Brabant",
    "sg:website":"http://www.omegasecurity.nl",
    "wof:name":"Omega, Security",
    "wof:placetype":"venue"
},
  "geometry": {"coordinates":[4.766889,51.616249],"type":"Point"}
}