{
  "type": "Feature",
  "properties": {
    "addr:full":"Grasklokje 61 Hardenberg Overijssel 7772 NN",
    "addr:housenumber":"61",
    "addr:postcode":"7772 nn",
    "addr:street":"Grasklokje",
    "iso:country":"NL",
    "sg:address":"Grasklokje 61",
    "sg:city":"Hardenberg",
    "sg:orig_category":"Hoefdierhouderijen",
    "sg:phone":"+31 523 261 521",
    "sg:postcode":"7772 NN",
    "sg:province":"Overijssel",
    "wof:name":"A. Datema",
    "wof:placetype":"venue"
},
  "geometry": {"coordinates":[6.644527,52.578514],"type":"Point"}
}