{
  "type": "Feature",
  "properties": {
    "iso:country":"NL",
    "sg:address":"Pyramide 6",
    "sg:city":"Biervliet",
    "sg:orig_category":"Elektronica - Ontwikkeling En Groothandel",
    "sg:phone":"+31 115 400 117",
    "sg:postcode":"4522 NA",
    "sg:province":"\u00cele-de-France",
    "wof:name":"Hoek Bv, W J Van",
    "wof:placetype":"venue"
},
  "geometry": {"coordinates":[2.33585,48.86095],"type":"Point"}
}