{
  "type": "Feature",
  "properties": {
    "addr:full":"Delfgauwsewg 86 Delft Zuid-Holland 2628 EV",
    "addr:housenumber":"86",
    "addr:postcode":"2628 ev",
    "addr:street":"Delfgauwsewg",
    "iso:country":"NL",
    "sg:address":"Delfgauwsewg 86",
    "sg:city":"Delft",
    "sg:orig_category":"Adviesbureaus Bedrijfsorganisatie",
    "sg:phone":"+31 15 215 7324",
    "sg:postcode":"2628 EV",
    "sg:province":"Zuid-Holland",
    "sg:website":"http://www.nijenco.nl",
    "wof:name":"Nijenco",
    "wof:placetype":"venue"
},
  "geometry": {"coordinates":[4.38159,52.007282],"type":"Point"}
}