{
  "type": "Feature",
  "properties": {
    "addr:full":"Kerkln 31 Roermond Limburg 6041 AZ",
    "addr:housenumber":"31",
    "addr:postcode":"6041 az",
    "addr:street":"Kerkln",
    "iso:country":"NL",
    "sg:address":"Kerkln 31",
    "sg:city":"Roermond",
    "sg:orig_category":"Ziekenvervoer",
    "sg:phone":"+31 475 317 344",
    "sg:postcode":"6041 AZ",
    "sg:province":"Limburg",
    "wof:name":"Bremmers Vof, J",
    "wof:placetype":"venue"
},
  "geometry": {"coordinates":[5.991103,51.189888],"type":"Point"}
}