{
  "type": "Feature",
  "properties": {
    "addr:full":"Binnenban 79 Hoogvliet Rt Zuid-Holland 3191 CB",
    "addr:housenumber":"79",
    "addr:postcode":"rt;3191 cb",
    "addr:street":"Binnenban",
    "iso:country":"NL",
    "sg:address":"Binnenban 79",
    "sg:city":"Hoogvliet Rt",
    "sg:classifiers":[
        {
            "category":"Farming",
            "subcategory":"Fish & Marine Products",
            "type":"Manufacturing & Wholesale Goods"
        }
    ],
    "sg:phone":"+31 10 438 7427",
    "sg:postcode":"3191 CB",
    "sg:province":"Zuid-Holland",
    "sg:tags":[
        "vi"
    ],
    "wof:name":"Visspecialist Hoogvliet",
    "wof:placetype":"venue"
},
  "geometry": {"coordinates":[4.354706,51.865265],"type":"Point"}
}