{
  "type": "Feature",
  "properties": {
    "addr:full":"J Luykenstr 92-96 Amsterdam Noord-Holland 1071 CT",
    "addr:housenumber":"92-96",
    "addr:postcode":"1071 ct",
    "iso:country":"NL",
    "sg:address":"J Luykenstr 92-96",
    "sg:city":"Amsterdam",
    "sg:orig_category":"Makelaars En Adviseurs Onroerende Goederen",
    "sg:phone":"+31 20 676 8086",
    "sg:postcode":"1071 CT",
    "sg:province":"Noord-Holland",
    "wof:name":"Roelfzema",
    "wof:placetype":"venue"
},
  "geometry": {"coordinates":[4.87912,52.359337],"type":"Point"}
}