{
  "type": "Feature",
  "properties": {
    "iso:country":"NL",
    "sg:address":"Achterstr 8A",
    "sg:city":"Woerden",
    "sg:orig_category":"Vakorganisaties",
    "sg:phone":"+31 348 421 744",
    "sg:postcode":"3441 EH",
    "sg:province":"Utrecht",
    "sg:website":"http://www.fnv.nl/",
    "wof:name":"Fnv Kunsten Informatie En Media",
    "wof:placetype":"venue"
},
  "geometry": {"coordinates":[4.885397,52.087204],"type":"Point"}
}