{
  "type": "Feature",
  "properties": {
    "addr:full":"Griftstraat 17 Arnhem Gelderland 6826 AM",
    "addr:housenumber":"17",
    "addr:postcode":"6826",
    "addr:street":"Griftstraat",
    "iso:country":"NL",
    "sg:address":"Griftstraat 17",
    "sg:city":"Arnhem",
    "sg:orig_category":"Metaalwerken",
    "sg:phone":"+31 26 361 7213",
    "sg:postcode":"6826 AM",
    "sg:province":"Gelderland",
    "wof:name":"De Wolff Zonweringen Bv",
    "wof:placetype":"venue"
},
  "geometry": {"coordinates":[5.941154,51.984348],"type":"Point"}
}