{
  "type": "Feature",
  "properties": {
    "addr:full":"Muzieklaan 50 Zoetermeer Zuid-Holland 2717 CX",
    "addr:housenumber":"50",
    "addr:postcode":"2717 cx",
    "addr:street":"Muzieklaan",
    "iso:country":"NL",
    "sg:address":"Muzieklaan 50",
    "sg:city":"Zoetermeer",
    "sg:orig_category":"Autokeuringen",
    "sg:phone":"+31 79 351 6712",
    "sg:postcode":"2717 CX",
    "sg:province":"Zuid-Holland",
    "wof:name":"De Limo",
    "wof:placetype":"venue"
},
  "geometry": {"coordinates":[4.471376,52.064522],"type":"Point"}
}