{
  "type": "Feature",
  "properties": {
    "addr:full":"Moleneind 25 Ossendrecht Noord-Brabant 4641 SB",
    "addr:housenumber":"25",
    "addr:postcode":"4641 sb",
    "addr:street":"Moleneind",
    "iso:country":"NL",
    "sg:address":"Moleneind 25",
    "sg:city":"Ossendrecht",
    "sg:orig_category":"Autoverhuur",
    "sg:phone":"+31 164 674 332",
    "sg:postcode":"4641 SB",
    "sg:province":"Noord-Brabant",
    "wof:name":"Brabant Lease Bv",
    "wof:placetype":"venue"
},
  "geometry": {"coordinates":[4.340654,51.391232],"type":"Point"}
}