{
  "type": "Feature",
  "properties": {
    "addr:full":"Sichtermanmarke 13 Zwolle NL.08 8016 MH",
    "addr:housenumber":"13",
    "addr:postcode":"8016 mh",
    "addr:street":"Sichtermanmarke",
    "iso:country":"NL",
    "sg:address":"Sichtermanmarke 13",
    "sg:city":"Zwolle",
    "sg:orig_category":"Kappers",
    "sg:phone":"+31 38 460 2370",
    "sg:postcode":"8016 MH",
    "sg:province":"NL.08",
    "wof:name":"Simone",
    "wof:placetype":"venue"
},
  "geometry": {"coordinates":[6.10841,52.474651],"type":"Point"}
}