{
  "type": "Feature",
  "properties": {
    "iso:country":"NL",
    "sg:address":"Westerweg 138",
    "sg:city":"Alkmaar",
    "sg:orig_category":"Verzekeringen",
    "sg:phone":"+31 72 511 1536",
    "sg:postcode":"1815 DK",
    "sg:province":"Noord-Holland",
    "wof:name":"J.C.J.Bakker",
    "wof:placetype":"venue"
},
  "geometry": {"coordinates":[12.542147,55.672897],"type":"Point"}
}