{
  "type": "Feature",
  "properties": {
    "addr:full":"Rosmolenstr 57 Leusden Utrecht 3833 KB",
    "addr:housenumber":"57",
    "addr:postcode":"3833 kb",
    "addr:street":"Rosmolenstr",
    "iso:country":"NL",
    "sg:address":"Rosmolenstr 57",
    "sg:city":"Leusden",
    "sg:orig_category":"Webdesign Bureaus",
    "sg:phone":"+31 33 434 0730",
    "sg:postcode":"3833 KB",
    "sg:province":"Utrecht",
    "wof:name":"Kalberg",
    "wof:placetype":"venue"
},
  "geometry": {"coordinates":[5.4202070236,52.1235427856],"type":"Point"}
}