{
  "type": "Feature",
  "properties": {
    "addr:full":"Kerkstr 8 Zeeland Noord-Brabant 5411 CL",
    "addr:housenumber":"8",
    "addr:postcode":"5411",
    "addr:street":"Kerkstr",
    "iso:country":"NL",
    "sg:address":"Kerkstr 8",
    "sg:city":"Zeeland",
    "sg:orig_category":"Schilders",
    "sg:phone":"+31 486 451 893",
    "sg:postcode":"5411 CL",
    "sg:province":"Noord-Brabant",
    "wof:name":"Delst Bv, Van",
    "wof:placetype":"venue"
},
  "geometry": {"coordinates":[5.671171,51.693794],"type":"Point"}
}