{
  "type": "Feature",
  "properties": {
    "addr:full":"Oude Kerkwg 1 Hoogmade Zuid-Holland 2355 AT",
    "addr:housenumber":"1",
    "addr:postcode":"2355",
    "addr:street":"Oude Kerkwg",
    "iso:country":"NL",
    "sg:address":"Oude Kerkwg 1",
    "sg:city":"Hoogmade",
    "sg:orig_category":"Onderhoudswerken",
    "sg:phone":"+31 71 501 3562",
    "sg:postcode":"2355 AT",
    "sg:province":"Zuid-Holland",
    "wof:name":"Borst, Carlo",
    "wof:placetype":"venue"
},
  "geometry": {"coordinates":[4.582794,52.171318],"type":"Point"}
}