{
  "type": "Feature",
  "properties": {
    "addr:full":"Wilhelminaplnts 13 Bussum Noord-Holland 1404 JA",
    "addr:housenumber":"13",
    "addr:postcode":"1404 ja",
    "addr:street":"Wilhelminaplnts",
    "iso:country":"NL",
    "sg:address":"Wilhelminaplnts 13",
    "sg:city":"Bussum",
    "sg:orig_category":"Kappers",
    "sg:phone":"+31 35 691 4471",
    "sg:postcode":"1404 JA",
    "sg:province":"Noord-Holland",
    "wof:name":"Kapperij",
    "wof:placetype":"venue"
},
  "geometry": {"coordinates":[5.1626048088,52.2768287659],"type":"Point"}
}