{
  "type": "Feature",
  "properties": {
    "iso:country":"NL",
    "sg:address":"Easterbuorren 86",
    "sg:city":"Boornbergum",
    "sg:orig_category":"Boekhouders",
    "sg:phone":"+31 512 541 585",
    "sg:postcode":"9212 RB",
    "sg:province":"Provincie Friesland",
    "wof:name":"G. De Raad / Administraties",
    "wof:placetype":"venue"
},
  "geometry": {"coordinates":[6.056099,53.08493],"type":"Point"}
}