{
  "type": "Feature",
  "properties": {
    "addr:full":"Enghln 6A Utrecht Utrecht 3543 BD",
    "addr:housenumber":"6a",
    "addr:postcode":"3543 bd",
    "addr:street":"Enghln",
    "iso:country":"NL",
    "sg:address":"Enghln 6A",
    "sg:city":"Utrecht",
    "sg:orig_category":"Kinderopvang",
    "sg:phone":"+31 30 677 6064",
    "sg:postcode":"3543 BD",
    "sg:province":"Utrecht",
    "wof:name":"Boerderij, De",
    "wof:placetype":"venue"
},
  "geometry": {"coordinates":[5.04792,52.107769],"type":"Point"}
}