{
  "type": "Feature",
  "properties": {
    "addr:full":"Hoofdstraat 4 Amstenrade Limburg 6436 CE",
    "addr:housenumber":"4",
    "addr:postcode":"6436 ce",
    "addr:street":"Hoofdstraat",
    "iso:country":"NL",
    "sg:address":"Hoofdstraat 4",
    "sg:city":"Amstenrade",
    "sg:classifiers":[
        {
            "category":"Shopping",
            "subcategory":"Clothing, Apparel, & Fashions",
            "type":"Retail Goods"
        }
    ],
    "sg:phone":"+31 46 442 8578",
    "sg:postcode":"6436 CE",
    "sg:province":"Limburg",
    "sg:tags":[
        "ondergoed",
        "lingerie"
    ],
    "wof:name":"Tri Colore",
    "wof:placetype":"venue"
},
  "geometry": {"coordinates":[5.924292,50.941013],"type":"Point"}
}