{
  "type": "Feature",
  "properties": {
    "iso:country":"NL",
    "sg:address":"Kon Wilhelminapln 1",
    "sg:city":"Amsterdam",
    "sg:orig_category":"Binnenhuisarchitectuur",
    "sg:phone":"+31 20 617 9087",
    "sg:postcode":"1062 HG",
    "sg:province":"North Holland",
    "wof:name":"Impulsief Decoration",
    "wof:placetype":"venue"
},
  "geometry": {"coordinates":[4.8409948349,52.355758667],"type":"Point"}
}