{
  "type": "Feature",
  "properties": {
    "addr:full":"Oelenboom 9 Gieten Drenthe 9461 VA",
    "addr:housenumber":"9",
    "addr:postcode":"9461",
    "addr:street":"Oelenboom",
    "iso:country":"NL",
    "sg:address":"Oelenboom 9",
    "sg:city":"Gieten",
    "sg:orig_category":"Bakkerijbenodigdheden En -Grondstoffen",
    "sg:phone":"+31 592 261 199",
    "sg:postcode":"9461 VA",
    "sg:province":"Drenthe",
    "wof:name":"Sadena",
    "wof:placetype":"venue"
},
  "geometry": {"coordinates":[6.761714,52.999134],"type":"Point"}
}