{
  "type": "Feature",
  "properties": {
    "addr:full":"St Jacobsstr 11G Leeuwarden Friesland 8911 HR",
    "addr:housenumber":"11g",
    "addr:postcode":"8911 hr",
    "addr:street":"Jacobsstr",
    "iso:country":"NL",
    "sg:address":"St Jacobsstr 11G",
    "sg:city":"Leeuwarden",
    "sg:orig_category":"Webdesign Bureaus",
    "sg:phone":"+31 58 299 1712",
    "sg:postcode":"8911 HR",
    "sg:province":"Friesland",
    "sg:website":"http://www.prosolution.nl",
    "wof:name":"Prosolution",
    "wof:placetype":"venue"
},
  "geometry": {"coordinates":[5.7964401245,53.2014312744],"type":"Point"}
}