{
  "type": "Feature",
  "properties": {
    "addr:full":"Dorpsstraat 54 Nieuwerkerk Ad Ijssel South Holland 2912 CB",
    "addr:housenumber":"54",
    "addr:postcode":"2912 cb",
    "addr:street":"Dorpsstraat;Ijssel",
    "iso:country":"NL",
    "sg:address":"Dorpsstraat 54",
    "sg:city":"Nieuwerkerk Ad Ijssel",
    "sg:orig_category":"Juweliers",
    "sg:phone":"+31 180 313 815",
    "sg:postcode":"2912 CB",
    "sg:province":"South Holland",
    "wof:name":"Juwelier J Van Someren Bv",
    "wof:placetype":"venue"
},
  "geometry": {"coordinates":[4.605656,51.970142],"type":"Point"}
}