{
  "type": "Feature",
  "properties": {
    "addr:full":"Z Oosterstr 23/F Tilburg Noord-Brabant 5014 BB",
    "addr:housenumber":"23 / f",
    "addr:postcode":"5014 bb",
    "iso:country":"NL",
    "sg:address":"Z Oosterstr 23/F",
    "sg:city":"Tilburg",
    "sg:classifiers":[
        {
            "category":"Retail",
            "subcategory":"Auto Repair",
            "type":"Services"
        }
    ],
    "sg:phone":"+31 13 543 0014",
    "sg:postcode":"5014 BB",
    "sg:province":"Noord-Brabant",
    "sg:tags":[
        "garage"
    ],
    "wof:name":"Huijgevoort, Van",
    "wof:placetype":"venue"
},
  "geometry": {"coordinates":[5.106271,51.554928],"type":"Point"}
}