{
  "type": "Feature",
  "properties": {
    "addr:full":"Trompenburgstraat 8A Amsterdam Noord-Holland 1079 TX",
    "addr:housenumber":"8a",
    "addr:postcode":"1079 tx",
    "addr:street":"Trompenburgstraat",
    "iso:country":"NL",
    "sg:address":"Trompenburgstraat 8A",
    "sg:city":"Amsterdam",
    "sg:orig_category":"Elektronische Bedrijfsinstallaties",
    "sg:phone":"+31 20 404 0919",
    "sg:postcode":"1079 TX",
    "sg:province":"Noord-Holland",
    "wof:name":"Clifford Electronics Benelux",
    "wof:placetype":"venue"
},
  "geometry": {"coordinates":[4.91051,52.344185],"type":"Point"}
}