{
  "type": "Feature",
  "properties": {
    "addr:full":"St Winfridusstr 53 Utrecht Utrecht 3553 SB",
    "addr:housenumber":"53",
    "addr:postcode":"3553 sb",
    "iso:country":"NL",
    "sg:address":"St Winfridusstr 53",
    "sg:city":"Utrecht",
    "sg:orig_category":"Onderhoudswerken",
    "sg:phone":"+31 30 244 3977",
    "sg:postcode":"3553 SB",
    "sg:province":"Utrecht",
    "wof:name":"Goes, A M J",
    "wof:placetype":"venue"
},
  "geometry": {"coordinates":[5.088938,52.109406],"type":"Point"}
}