{
  "type": "Feature",
  "properties": {
    "iso:country":"NL",
    "sg:address":"Bloemistendam 3",
    "sg:city":"Warmond",
    "sg:classifiers":[
        {
            "category":"Professional",
            "subcategory":"Accounting & Tax Preparation",
            "type":"Services"
        }
    ],
    "sg:phone":"+31 71 301 1472",
    "sg:postcode":"2361 GG",
    "sg:province":"South Holland",
    "sg:tags":[
        "accountant"
    ],
    "wof:name":"M.H.P. Van Winsen",
    "wof:placetype":"venue"
},
  "geometry": {"coordinates":[4.505705,52.198589],"type":"Point"}
}