{
  "type": "Feature",
  "properties": {
    "addr:full":"Kerkstraat 282 Brunssum Limburg 6441 BL",
    "addr:housenumber":"282",
    "addr:postcode":"6441 bl",
    "addr:street":"Kerkstraat",
    "iso:country":"NL",
    "sg:address":"Kerkstraat 282",
    "sg:city":"Brunssum",
    "sg:orig_category":"Meubelzaken, Woning- And Keukeninrichting",
    "sg:phone":"+31 45 525 2581",
    "sg:postcode":"6441 BL",
    "sg:province":"Limburg",
    "wof:name":"W. Ekhart",
    "wof:placetype":"venue"
},
  "geometry": {"coordinates":[5.972463,50.9478],"type":"Point"}
}