{
  "type": "Feature",
  "properties": {
    "addr:full":"Wagenaarstr 370 Amsterdam Noord-Holland 1093 CX",
    "addr:housenumber":"370",
    "addr:postcode":"1093 cx",
    "iso:country":"NL",
    "sg:address":"Wagenaarstr 370",
    "sg:city":"Amsterdam",
    "sg:orig_category":"Webdesign Bureaus",
    "sg:phone":"+31 20 694 3541",
    "sg:postcode":"1093 CX",
    "sg:province":"Noord-Holland",
    "sg:website":"http://www.studiomaup.nl",
    "wof:name":"Maup, Studio",
    "wof:placetype":"venue"
},
  "geometry": {"coordinates":[4.9283571243,52.3633575439],"type":"Point"}
}