{
  "type": "Feature",
  "properties": {
    "addr:full":"Van Eeghenstraat 129 Amsterdam Noord-Holland 1071 GA",
    "addr:housenumber":"129",
    "addr:postcode":"1071 ga",
    "addr:street":"Van Eeghenstraat",
    "iso:country":"NL",
    "sg:address":"Van Eeghenstraat 129",
    "sg:city":"Amsterdam",
    "sg:orig_category":"Antiekzaken",
    "sg:phone":"+31 20 676 3185",
    "sg:postcode":"1071 GA",
    "sg:province":"Noord-Holland",
    "wof:name":"Antiquariaat Junk Bv",
    "wof:placetype":"venue"
},
  "geometry": {"coordinates":[-74.279404,42.866795],"type":"Point"}
}