{
  "type": "Feature",
  "properties": {
    "addr:full":"Anjelierenstraat 45 Rijnsburg Zuid-Holland 2231 GT",
    "addr:housenumber":"45",
    "addr:postcode":"2231 gt",
    "addr:street":"Anjelierenstraat",
    "iso:country":"NL",
    "sg:address":"Anjelierenstraat 45",
    "sg:city":"Rijnsburg",
    "sg:classifiers":[
        {
            "category":"Food & Beverages",
            "subcategory":"Fruits & Vegetables",
            "type":"Retail Goods"
        }
    ],
    "sg:phone":"+31 71 402 0759",
    "sg:postcode":"2231 GT",
    "sg:province":"Zuid-Holland",
    "sg:tags":[
        "groenten"
    ],
    "wof:name":"J P Wetselaar Groenten En Fruit",
    "wof:placetype":"venue"
},
  "geometry": {"coordinates":[4.443285,52.1884],"type":"Point"}
}