{
  "type": "Feature",
  "properties": {
    "addr:full":"Provincialeweg Zuid 107 Oirsbeek Limburg 6438 BC",
    "addr:housenumber":"107",
    "addr:postcode":"6438 bc",
    "addr:street":"Provincialeweg Zuid",
    "iso:country":"NL",
    "sg:address":"Provincialeweg Zuid 107",
    "sg:city":"Oirsbeek",
    "sg:orig_category":"Kappers",
    "sg:phone":"+31 46 442 5366",
    "sg:postcode":"6438 BC",
    "sg:province":"Limburg",
    "wof:name":"Kapper Smeets",
    "wof:placetype":"venue"
},
  "geometry": {"coordinates":[5.9161448479,50.9497070312],"type":"Point"}
}