{
  "type": "Feature",
  "properties": {
    "iso:country":"NL",
    "sg:address":"Spinhuisstg 5",
    "sg:city":"Amsterdam",
    "sg:orig_category":"Webdesign Bureaus",
    "sg:phone":"+31 20 420 6773",
    "sg:postcode":"1012 CJ",
    "sg:province":"North Holland",
    "sg:website":"http://www.mattmo.nl",
    "wof:name":"Mattmo",
    "wof:placetype":"venue"
},
  "geometry": {"coordinates":[4.8970789909,52.3704605103],"type":"Point"}
}