{
  "type": "Feature",
  "properties": {
    "iso:country":"NL",
    "sg:address":"Richterdael 4",
    "sg:city":"Roermond",
    "sg:orig_category":"Fotostudio'S And Fotografen",
    "sg:phone":"+31 475 334 274",
    "sg:postcode":"6045 DG",
    "sg:province":"Limburg",
    "wof:name":"Fotostudio John Bercx",
    "wof:placetype":"venue"
},
  "geometry": {"coordinates":[5.994304,51.181522],"type":"Point"}
}