{
  "type": "Feature",
  "properties": {
    "addr:full":"F Eliasln 5 Baarn Utrecht 3742 AR",
    "addr:housenumber":"5",
    "addr:postcode":"3742",
    "addr:street":"Eliasln",
    "iso:country":"NL",
    "sg:address":"F Eliasln 5",
    "sg:city":"Baarn",
    "sg:orig_category":"Verzekeringen - Verzekeringskantoren",
    "sg:phone":"+31 35 548 8040",
    "sg:postcode":"3742 AR",
    "sg:province":"Utrecht",
    "sg:website":"http://www.geytenbeek.nl",
    "wof:name":"Geytenbeek",
    "wof:placetype":"venue"
},
  "geometry": {"coordinates":[5.292121,52.21101],"type":"Point"}
}