{
  "type": "Feature",
  "properties": {
    "addr:full":"Albrechtpln 43 Sliedrecht South Holland 3361 VE",
    "addr:housenumber":"43",
    "addr:postcode":"3361",
    "addr:street":"Albrechtpln;Ve",
    "iso:country":"NL",
    "sg:address":"Albrechtpln 43",
    "sg:city":"Sliedrecht",
    "sg:orig_category":"Accountants - Administratie- Consulenten En -Kantoren",
    "sg:phone":"+31 184 499 010",
    "sg:postcode":"3361 VE",
    "sg:province":"South Holland",
    "wof:name":"Quirinus",
    "wof:placetype":"venue"
},
  "geometry": {"coordinates":[4.775806,51.816921],"type":"Point"}
}