{
  "type": "Feature",
  "properties": {
    "addr:full":"M H Trompstr 20 Amsterdam North Holland 1056 JA",
    "addr:housenumber":"20",
    "addr:postcode":"1056 ja",
    "addr:street":"M",
    "iso:country":"NL",
    "sg:address":"M H Trompstr 20",
    "sg:city":"Amsterdam",
    "sg:orig_category":"Webdesign Bureaus",
    "sg:phone":"+31 20 616 0257",
    "sg:postcode":"1056 JA",
    "sg:province":"North Holland",
    "sg:website":"http://www.webmonument.nl",
    "wof:name":"Webmonument",
    "wof:placetype":"venue"
},
  "geometry": {"coordinates":[4.8547801971,52.3736991882],"type":"Point"}
}