{
  "type": "Feature",
  "properties": {
    "addr:full":"Grootschoterwg 119 Budel Schoot Noord-Brabant 6023 AR",
    "addr:housenumber":"119",
    "addr:postcode":"6023",
    "iso:country":"NL",
    "sg:address":"Grootschoterwg 119",
    "sg:city":"Budel Schoot",
    "sg:orig_category":"Verenigingsgebouwen",
    "sg:phone":"+31 495 493 867",
    "sg:postcode":"6023 AR",
    "sg:province":"Noord-Brabant",
    "wof:name":"Reinder, De",
    "wof:placetype":"venue"
},
  "geometry": {"coordinates":[5.566162,51.251202],"type":"Point"}
}