{
  "type": "Feature",
  "properties": {
    "addr:full":"W Wissesstr 18 Gorredyk Friesland 8401 RD",
    "addr:housenumber":"18",
    "addr:postcode":"8401",
    "addr:street":"W;Gorredyk Friesland;Rd",
    "iso:country":"NL",
    "sg:address":"W Wissesstr 18",
    "sg:city":"Gorredyk",
    "sg:classifiers":[
        {
            "category":"Personal",
            "subcategory":"Nail Salon",
            "type":"Services"
        }
    ],
    "sg:phone":"+31 513 463 597",
    "sg:postcode":"8401 RD",
    "sg:province":"Friesland",
    "sg:tags":[
        "pedicure"
    ],
    "wof:name":"Bultsma, S E",
    "wof:placetype":"venue"
},
  "geometry": {"coordinates":[6.06447,53.00478],"type":"Point"}
}