{
  "type": "Feature",
  "properties": {
    "addr:full":"Kobaltweg 17 'S Hertogenbosch Noord-Brabant 5234 GN",
    "addr:housenumber":"17",
    "addr:postcode":"5234 gn",
    "addr:street":"Kobaltweg;' S",
    "iso:country":"NL",
    "sg:address":"Kobaltweg 17",
    "sg:city":"'S Hertogenbosch",
    "sg:orig_category":"Diverse Consumentenartikelen Gh",
    "sg:phone":"+31 73 646 1561",
    "sg:postcode":"5234 GN",
    "sg:province":"Noord-Brabant",
    "wof:name":"Pet'S Place",
    "wof:placetype":"venue"
},
  "geometry": {"coordinates":[5.290102,51.719074],"type":"Point"}
}