{
  "type": "Feature",
  "properties": {
    "addr:full":"Treubstr 17 Almelo NL.08 7604 TL",
    "addr:housenumber":"17;nl.08",
    "addr:postcode":"7604 tl",
    "addr:street":"Treubstr",
    "iso:country":"NL",
    "sg:address":"Treubstr 17",
    "sg:city":"Almelo",
    "sg:orig_category":"Cafetaria'S",
    "sg:phone":"+31 546 818 241",
    "sg:postcode":"7604 TL",
    "sg:province":"NL.08",
    "wof:name":"Eiland, Het",
    "wof:placetype":"venue"
},
  "geometry": {"coordinates":[6.647421,52.360489],"type":"Point"}
}