{
  "type": "Feature",
  "properties": {
    "iso:country":"NL",
    "sg:address":"Treubstr 17",
    "sg:city":"Almelo",
    "sg:orig_category":"Cafetaria'S",
    "sg:phone":"+31 546 818 241",
    "sg:postcode":"7604 TL",
    "sg:province":"NL.08",
    "wof:name":"Eiland, Het",
    "wof:placetype":"venue"
},
  "geometry": {"coordinates":[6.647421,52.360489],"type":"Point"}
}