{
  "type": "Feature",
  "properties": {
    "addr:full":"Van Egmondkade 6 Utrecht Utrecht 3553 JE",
    "addr:housenumber":"6",
    "addr:postcode":"3553 je",
    "addr:street":"Van Egmondkade",
    "iso:country":"NL",
    "sg:address":"Van Egmondkade 6",
    "sg:city":"Utrecht",
    "sg:orig_category":"Meubelzaken, Woning- And Keukeninrichting",
    "sg:phone":"+31 30 244 4876",
    "sg:postcode":"3553 JE",
    "sg:province":"Utrecht",
    "wof:name":"Vof Kaptijn En Zn",
    "wof:placetype":"venue"
},
  "geometry": {"coordinates":[5.093603,52.106728],"type":"Point"}
}