{
  "type": "Feature",
  "properties": {
    "iso:country":"NL",
    "sg:address":"Aalsvoort 51L",
    "sg:city":"Lochem",
    "sg:orig_category":"Verlichting And Huishoudartikelen",
    "sg:phone":"+31 573 257 225",
    "sg:postcode":"7241 MA",
    "sg:province":"Gelderland",
    "wof:name":"Verlichting Rouweler",
    "wof:placetype":"venue"
},
  "geometry": {"coordinates":[6.385772,52.167858],"type":"Point"}
}