{
  "type": "Feature",
  "properties": {
    "iso:country":"NL",
    "sg:address":"Boezemkd 1",
    "sg:city":"Spaarndam West",
    "sg:orig_category":"Kinderopvang",
    "sg:phone":"+31 23 538 0588",
    "sg:postcode":"2063 JH",
    "sg:province":"North Holland",
    "wof:name":"Boeg, De",
    "wof:placetype":"venue"
},
  "geometry": {"coordinates":[4.67751,52.414516],"type":"Point"}
}