{
  "type": "Feature",
  "properties": {
    "addr:full":"Postbus 26 Wezep Gelderland 8090 AA",
    "addr:housenumber":"26",
    "addr:postcode":"8090 aa",
    "addr:street":"Postbus",
    "iso:country":"NL",
    "sg:address":"Postbus 26",
    "sg:city":"Wezep",
    "sg:orig_category":"Luchtbehandelings- Apparaten",
    "sg:phone":"+31 38 375 6010",
    "sg:postcode":"8090 AA",
    "sg:province":"Gelderland",
    "wof:name":"Check & Care",
    "wof:placetype":"venue"
},
  "geometry": {"coordinates":[5.99815,52.460609],"type":"Point"}
}