{
  "type": "Feature",
  "properties": {
    "addr:full":"Janswg 42H Haarlem Noord-Holland 2011 KN",
    "addr:postcode":"2011 kn",
    "iso:country":"NL",
    "sg:address":"Janswg 42H",
    "sg:city":"Haarlem",
    "sg:orig_category":"Verzekeringen - Verzekeringskantoren",
    "sg:phone":"+31 23 534 2636",
    "sg:postcode":"2011 KN",
    "sg:province":"Noord-Holland",
    "wof:name":"Hillebrand",
    "wof:placetype":"venue"
},
  "geometry": {"coordinates":[4.63886,52.385494],"type":"Point"}
}