{
  "type": "Feature",
  "properties": {
    "iso:country":"NL",
    "sg:address":"Rynhaven Zz 14",
    "sg:city":"Rotterdam",
    "sg:orig_category":"Wijnkoperijen En -Groothandel",
    "sg:phone":"+31 10 485 6900",
    "sg:postcode":"3072 AJ",
    "sg:province":"Zuid-Holland",
    "wof:name":"Wijnhaven Wijnimport Bv",
    "wof:placetype":"venue"
},
  "geometry": {"coordinates":[4.4930920601,51.902759552],"type":"Point"}
}