{
  "type": "Feature",
  "properties": {
    "addr:full":"Rivierdijk 747 Sliedrecht Zuid-Holland 3361 BV",
    "addr:housenumber":"747",
    "addr:postcode":"3361 bv",
    "addr:street":"Rivierdijk",
    "iso:country":"NL",
    "sg:address":"Rivierdijk 747",
    "sg:city":"Sliedrecht",
    "sg:orig_category":"Woningbouwverenigingen",
    "sg:phone":"+31 184 415 000",
    "sg:postcode":"3361 BV",
    "sg:province":"Zuid-Holland",
    "wof:name":"Bouwvereniging De Waert",
    "wof:placetype":"venue"
},
  "geometry": {"coordinates":[4.7783989906,51.8179473877],"type":"Point"}
}