{
  "type": "Feature",
  "properties": {
    "addr:full":"Zuidhaven 121 Zevenbergen Noord-Brabant 4761 CV",
    "addr:housenumber":"121",
    "addr:postcode":"4761 cv",
    "addr:street":"Zuidhaven",
    "iso:country":"NL",
    "sg:address":"Zuidhaven 121",
    "sg:city":"Zevenbergen",
    "sg:orig_category":"Verlichting And Huishoudartikelen",
    "sg:phone":"+31 168 370 245",
    "sg:postcode":"4761 CV",
    "sg:province":"Noord-Brabant",
    "wof:name":"Marskramer Bv",
    "wof:placetype":"venue"
},
  "geometry": {"coordinates":[4.60346,51.643997],"type":"Point"}
}