{
  "type": "Feature",
  "properties": {
    "iso:country":"NL",
    "sg:address":"Cornelis Drebbelstraat 14",
    "sg:city":"Wijchen",
    "sg:orig_category":"Koeltechniek",
    "sg:phone":"+31 24 641 1771",
    "sg:postcode":"6603 BH",
    "sg:province":"Gelderland",
    "wof:name":"Romijnders Koudetechniek Bv",
    "wof:placetype":"venue"
},
  "geometry": {"coordinates":[5.761118,51.813938],"type":"Point"}
}