{
  "type": "Feature",
  "properties": {
    "addr:full":"Driehuizerkerkweg 123 Driehuis Nh Noord-Holland 1985 HB",
    "addr:housenumber":"123",
    "addr:postcode":"1985 hb",
    "addr:street":"Driehuizerkerkweg",
    "iso:country":"NL",
    "sg:address":"Driehuizerkerkweg 123",
    "sg:city":"Driehuis Nh",
    "sg:orig_category":"Fitnesscentra",
    "sg:phone":"+31 255 561 222",
    "sg:postcode":"1985 HB",
    "sg:province":"Noord-Holland",
    "wof:name":"Sociaal Medische Dienst Buro Sport",
    "wof:placetype":"venue"
},
  "geometry": {"coordinates":[4.633414,52.443974],"type":"Point"}
}