{
  "type": "Feature",
  "properties": {
    "addr:full":"Gildenburg 78 Gouda Zuid-Holland 2804 VK",
    "addr:housenumber":"78",
    "addr:postcode":"2804 vk",
    "addr:street":"Gildenburg",
    "iso:country":"NL",
    "sg:address":"Gildenburg 78",
    "sg:city":"Gouda",
    "sg:classifiers":[
        {
            "category":"Food & Beverages",
            "subcategory":"Fruits & Vegetables",
            "type":"Retail Goods"
        }
    ],
    "sg:phone":"+31 182 532 112",
    "sg:postcode":"2804 VK",
    "sg:province":"Zuid-Holland",
    "sg:tags":[
        "groenten"
    ],
    "wof:name":"Firma C.A. Grootveld En Zoon",
    "wof:placetype":"venue"
},
  "geometry": {"coordinates":[4.702801,52.031933],"type":"Point"}
}