{
  "type": "Feature",
  "properties": {
    "iso:country":"NL",
    "sg:address":"Rooijsestraat 66",
    "sg:city":"Dreumel",
    "sg:orig_category":"Autokeuringen",
    "sg:phone":"+31 487 571 271",
    "sg:postcode":"6621 AP",
    "sg:province":"Gelderland",
    "wof:name":"P C J Smits",
    "wof:placetype":"venue"
},
  "geometry": {"coordinates":[5.431785,51.84922],"type":"Point"}
}