{
  "type": "Feature",
  "properties": {
    "iso:country":"NL",
    "sg:address":"Straatweg 94",
    "sg:city":"Rotterdam",
    "sg:orig_category":"Hypotheken And Hypotheekbanken",
    "sg:phone":"+31 10 422 6144",
    "sg:postcode":"3051 BL",
    "sg:province":"South Holland",
    "wof:name":"Kolpa Makelaars Bv",
    "wof:placetype":"venue"
},
  "geometry": {"coordinates":[4.483905,51.946083],"type":"Point"}
}