{
  "type": "Feature",
  "properties": {
    "iso:country":"NL",
    "sg:address":"Koolmeesstr 26",
    "sg:city":"Zwaagwesteinde",
    "sg:classifiers":[
        {
            "category":"Personal",
            "subcategory":"Nail Salon",
            "type":"Services"
        }
    ],
    "sg:phone":"+31 511 442 681",
    "sg:postcode":"9271 EC",
    "sg:province":"Friesland",
    "sg:tags":[
        "pedicure"
    ],
    "wof:name":"Veenstra-Kooistra, G",
    "wof:placetype":"venue"
},
  "geometry": {"coordinates":[6.035454,53.252022],"type":"Point"}
}