{
  "type": "Feature",
  "properties": {
    "addr:full":"Boschstr 56 Zaltbommel Gelderland 5301 AG",
    "addr:housenumber":"56",
    "addr:postcode":"5301",
    "addr:street":"Boschstr;Gelderland",
    "iso:country":"NL",
    "sg:address":"Boschstr 56",
    "sg:city":"Zaltbommel",
    "sg:orig_category":"Woninginrichting",
    "sg:phone":"+31 418 512 537",
    "sg:postcode":"5301 AG",
    "sg:province":"Gelderland",
    "wof:name":"Bragt & Zoon",
    "wof:placetype":"venue"
},
  "geometry": {"coordinates":[5.2492690086,51.8119277954],"type":"Point"}
}