{
  "type": "Feature",
  "properties": {
    "addr:full":"Ringbaan Noord 154 Tilburg North Brabant 5046 AC",
    "addr:housenumber":"154",
    "addr:postcode":"5046 ac",
    "addr:street":"Ringbaan Noord",
    "iso:country":"NL",
    "sg:address":"Ringbaan Noord 154",
    "sg:city":"Tilburg",
    "sg:orig_category":"Diverse Consumentenartikelen Gh",
    "sg:phone":"+31 13 542 2644",
    "sg:postcode":"5046 AC",
    "sg:province":"North Brabant",
    "wof:name":"Handelsonderneming Arno Hersmus",
    "wof:placetype":"venue"
},
  "geometry": {"coordinates":[5.082576,51.576488],"type":"Point"}
}