{
  "type": "Feature",
  "properties": {
    "addr:full":"Het Cappelryeland 7 Rynsburg South Holland 2231 ZD",
    "addr:housenumber":"7",
    "addr:postcode":"2231 zd",
    "addr:street":"Cappelryeland",
    "iso:country":"NL",
    "sg:address":"Het Cappelryeland 7",
    "sg:city":"Rynsburg",
    "sg:orig_category":"Bloemen En Planten - Groothandel",
    "sg:phone":"+31 71 402 0279",
    "sg:postcode":"2231 ZD",
    "sg:province":"South Holland",
    "wof:name":"Best, A W De",
    "wof:placetype":"venue"
},
  "geometry": {"coordinates":[4.442744,52.183617],"type":"Point"}
}