{
  "type": "Feature",
  "properties": {
    "addr:full":"Adenauerstraat 7 Brunssum Limburg 6441 JV",
    "addr:housenumber":"7",
    "addr:postcode":"6441 jv",
    "addr:street":"Adenauerstraat",
    "iso:country":"NL",
    "sg:address":"Adenauerstraat 7",
    "sg:city":"Brunssum",
    "sg:orig_category":"Boekhouders",
    "sg:phone":"+31 45 525 2031",
    "sg:postcode":"6441 JV",
    "sg:province":"Limburg",
    "wof:name":"J H G Zinken",
    "wof:placetype":"venue"
},
  "geometry": {"coordinates":[5.962388,50.952267],"type":"Point"}
}