{
  "type": "Feature",
  "properties": {
    "addr:full":"Koningsln 60 Utrecht Utrecht 3583 GN",
    "addr:housenumber":"60",
    "addr:postcode":"3583 gn",
    "addr:street":"Koningsln",
    "iso:country":"NL",
    "sg:address":"Koningsln 60",
    "sg:city":"Utrecht",
    "sg:orig_category":"Milieu",
    "sg:phone":"+31 30 254 5840",
    "sg:postcode":"3583 GN",
    "sg:province":"Utrecht",
    "wof:name":"Ameco",
    "wof:placetype":"venue"
},
  "geometry": {"coordinates":[5.14269,52.087463],"type":"Point"}
}