{
  "type": "Feature",
  "properties": {
    "addr:full":"Bilderdykstr 31A Schiedam South Holland 3117 PB",
    "addr:housenumber":"31a",
    "addr:postcode":"3117 pb",
    "addr:street":"Bilderdykstr",
    "iso:country":"NL",
    "sg:address":"Bilderdykstr 31A",
    "sg:city":"Schiedam",
    "sg:orig_category":"Banket",
    "sg:phone":"+31 10 426 9621",
    "sg:postcode":"3117 PB",
    "sg:province":"South Holland",
    "wof:name":"Scholtes, A J M",
    "wof:placetype":"venue"
},
  "geometry": {"coordinates":[4.39816,51.918472],"type":"Point"}
}