{
  "type": "Feature",
  "properties": {
    "iso:country":"NL",
    "sg:address":"Nobelstr 85A",
    "sg:city":"Rotterdam",
    "sg:orig_category":"Psychologen",
    "sg:phone":"+31 10 466 7992",
    "sg:postcode":"3039 SJ",
    "sg:province":"South Holland",
    "wof:name":"Hagenbeek, Drs H P",
    "wof:placetype":"venue"
},
  "geometry": {"coordinates":[4.458813,51.932407],"type":"Point"}
}