{
  "type": "Feature",
  "properties": {
    "addr:full":"Straatwg 1B Maarssen Utrecht 3604 BA",
    "addr:housenumber":"1b",
    "addr:postcode":"3604 ba",
    "addr:street":"Straatwg",
    "iso:country":"NL",
    "sg:address":"Straatwg 1B",
    "sg:city":"Maarssen",
    "sg:orig_category":"Keukenspeciaalzaken",
    "sg:phone":"+31 346 551 514",
    "sg:postcode":"3604 BA",
    "sg:province":"Utrecht",
    "wof:name":"Kaandorp Maarssen, Simon",
    "wof:placetype":"venue"
},
  "geometry": {"coordinates":[5.048011,52.131031],"type":"Point"}
}