{
  "type": "Feature",
  "properties": {
    "addr:full":"Dierenriemstr 196 Groningen Groningen 9742 AM",
    "addr:housenumber":"196",
    "addr:postcode":"9742",
    "iso:country":"NL",
    "sg:address":"Dierenriemstr 196",
    "sg:city":"Groningen",
    "sg:orig_category":"Opticiens",
    "sg:phone":"+31 50 573 6734",
    "sg:postcode":"9742 AM",
    "sg:province":"Groningen",
    "sg:website":"http://www.hansanders.nl",
    "wof:name":"Hans Anders",
    "wof:placetype":"venue"
},
  "geometry": {"coordinates":[6.5444631577,53.2303619385],"type":"Point"}
}