{
  "type": "Feature",
  "properties": {
    "addr:full":"Herenwg 30 Aardenburg Zeeland 4527 PR",
    "addr:housenumber":"30",
    "addr:postcode":"4527 pr",
    "addr:street":"Herenwg",
    "iso:country":"NL",
    "sg:address":"Herenwg 30",
    "sg:city":"Aardenburg",
    "sg:orig_category":"Autorijscholen",
    "sg:phone":"+31 117 492 467",
    "sg:postcode":"4527 PR",
    "sg:province":"Zeeland",
    "sg:website":"http://www.keesfoks.nl",
    "wof:name":"Foks Verkeersschool, Kees",
    "wof:placetype":"venue"
},
  "geometry": {"coordinates":[3.459361,51.280605],"type":"Point"}
}