{
  "type": "Feature",
  "properties": {
    "addr:full":"M Harpertsz Trompwg 382 Dordrecht Zuid-Holland 3317 NV",
    "addr:housenumber":"382",
    "addr:postcode":"3317 nv",
    "addr:street":"M Harpertsz Trompwg",
    "iso:country":"NL",
    "sg:address":"M Harpertsz Trompwg 382",
    "sg:city":"Dordrecht",
    "sg:orig_category":"Woningbouwverenigingen",
    "sg:phone":"+31 78 618 5878",
    "sg:postcode":"3317 NV",
    "sg:province":"Zuid-Holland",
    "wof:name":"Wooncentrum Watersteyn",
    "wof:placetype":"venue"
},
  "geometry": {"coordinates":[4.6530361176,51.7877311707],"type":"Point"}
}