{
  "type": "Feature",
  "properties": {
    "addr:full":"Lievensbergstr 8 Almere Flevoland 1333 ZR",
    "addr:housenumber":"8;1333",
    "addr:street":"Lievensbergstr;Flevoland",
    "iso:country":"NL",
    "sg:address":"Lievensbergstr 8",
    "sg:city":"Almere",
    "sg:orig_category":"Bijouterie?n",
    "sg:phone":"+31 36 546 8845",
    "sg:postcode":"1333 ZR",
    "sg:province":"Flevoland",
    "wof:name":"Kreuger-Spies",
    "wof:placetype":"venue"
},
  "geometry": {"coordinates":[5.265031,52.38591],"type":"Point"}
}