{
  "type": "Feature",
  "properties": {
    "addr:full":"Stryensestr 61 Rotterdam Zuid-Holland 3074 GG",
    "addr:housenumber":"61",
    "addr:postcode":"3074 gg",
    "addr:street":"Stryensestr",
    "iso:country":"NL",
    "sg:address":"Stryensestr 61",
    "sg:city":"Rotterdam",
    "sg:orig_category":"Warenhuizen",
    "sg:phone":"+31 10 290 9696",
    "sg:postcode":"3074 GG",
    "sg:province":"Zuid-Holland",
    "wof:name":"Hema",
    "wof:placetype":"venue"
},
  "geometry": {"coordinates":[4.5114898682,51.8960800171],"type":"Point"}
}