{
  "type": "Feature",
  "properties": {
    "addr:full":"Hallenweg 6 Leiden Zuid-Holland 2316 JW",
    "addr:housenumber":"6",
    "addr:postcode":"2316 jw",
    "addr:street":"Hallenweg",
    "iso:country":"NL",
    "sg:address":"Hallenweg 6",
    "sg:city":"Leiden",
    "sg:orig_category":"Autokeuringen",
    "sg:phone":"+31 71 522 6541",
    "sg:postcode":"2316 JW",
    "sg:province":"Zuid-Holland",
    "wof:name":"Schadenet Leiden",
    "wof:placetype":"venue"
},
  "geometry": {"coordinates":[4.496207,52.171471],"type":"Point"}
}