{
  "type": "Feature",
  "properties": {
    "addr:full":"Bijdorp 85 Amstelveen North Holland 1181 MZ",
    "addr:housenumber":"85",
    "addr:postcode":"1181 mz",
    "addr:street":"Bijdorp",
    "iso:country":"NL",
    "sg:address":"Bijdorp 85",
    "sg:city":"Amstelveen",
    "sg:orig_category":"Boekhouders",
    "sg:phone":"+31 20 643 0612",
    "sg:postcode":"1181 MZ",
    "sg:province":"North Holland",
    "wof:name":"Administratiekantoor Whe Services",
    "wof:placetype":"venue"
},
  "geometry": {"coordinates":[4.868782,52.307961],"type":"Point"}
}