{
  "type": "Feature",
  "properties": {
    "addr:full":"Stationsplein 6 Nijmegen Gelderland 6512 AB",
    "addr:housenumber":"6",
    "addr:postcode":"6512 ab",
    "addr:street":"Stationsplein;Gelderland",
    "iso:country":"NL",
    "sg:address":"Stationsplein 6",
    "sg:city":"Nijmegen",
    "sg:orig_category":"Reisbureaus",
    "sg:phone":"+31 24 322 2430",
    "sg:postcode":"6512 AB",
    "sg:province":"Gelderland",
    "wof:name":"Nv Nederlandse Spoorwegen",
    "wof:placetype":"venue"
},
  "geometry": {"coordinates":[5.853601,51.843433],"type":"Point"}
}