{
  "type": "Feature",
  "properties": {
    "iso:country":"NL",
    "sg:address":"Statenweg 83",
    "sg:city":"Venhorst",
    "sg:orig_category":"Autokeuringen",
    "sg:phone":"+31 492 351 569",
    "sg:postcode":"5428 NL",
    "sg:province":"North Brabant",
    "wof:name":"M P J Althuizen",
    "wof:placetype":"venue"
},
  "geometry": {"coordinates":[5.73992,51.607464],"type":"Point"}
}