{
  "type": "Feature",
  "properties": {
    "addr:full":"Noorderstraat 119 Sappemeer Groningen 9611 AC",
    "addr:housenumber":"119",
    "addr:postcode":"9611 ac",
    "addr:street":"Noorderstraat",
    "iso:country":"NL",
    "sg:address":"Noorderstraat 119",
    "sg:city":"Sappemeer",
    "sg:orig_category":"Herenmodezaken",
    "sg:phone":"+31 598 392 991",
    "sg:postcode":"9611 AC",
    "sg:province":"Groningen",
    "wof:name":"Fa J.G.A. Londeman En Zn",
    "wof:placetype":"venue"
},
  "geometry": {"coordinates":[6.788143,53.16423],"type":"Point"}
}