{
  "type": "Feature",
  "properties": {
    "addr:full":"Seringenhof 47 Schagen Noord-Holland 1741 WC",
    "addr:housenumber":"47",
    "addr:postcode":"1741 wc",
    "addr:street":"Seringenhof",
    "iso:country":"NL",
    "sg:address":"Seringenhof 47",
    "sg:city":"Schagen",
    "sg:orig_category":"Sportverenigingen En Ontspannings- Verenigingen",
    "sg:phone":"+31 224 215 881",
    "sg:postcode":"1741 WC",
    "sg:province":"Noord-Holland",
    "wof:name":"Fietscrossver Schagen",
    "wof:placetype":"venue"
},
  "geometry": {"coordinates":[4.802439,52.799526],"type":"Point"}
}