{
  "type": "Feature",
  "properties": {
    "addr:full":"Doctor Koekkoeklaan 20 'S Gravenmoer North Brabant 5109 TW",
    "addr:housenumber":"20",
    "addr:postcode":"5109 tw",
    "addr:street":"Doctor Koekkoeklaan;S",
    "iso:country":"NL",
    "sg:address":"Doctor Koekkoeklaan 20",
    "sg:city":"'S Gravenmoer",
    "sg:orig_category":"Boekenuitgeverijen",
    "sg:phone":"+31 162 315 387",
    "sg:postcode":"5109 TW",
    "sg:province":"North Brabant",
    "wof:name":"Create-A-Book Molendijk",
    "wof:placetype":"venue"
},
  "geometry": {"coordinates":[4.938608,51.658932],"type":"Point"}
}