{
  "type": "Feature",
  "properties": {
    "addr:full":"Beneden Oosterdiep 48 Veendam Groningen 9641 JE",
    "addr:housenumber":"48",
    "addr:postcode":"9641 je",
    "addr:street":"Beneden Oosterdiep",
    "iso:country":"NL",
    "sg:address":"Beneden Oosterdiep 48",
    "sg:city":"Veendam",
    "sg:orig_category":"Diverse Grafische Activiteiten",
    "sg:phone":"+31 598 618 953",
    "sg:postcode":"9641 JE",
    "sg:province":"Groningen",
    "wof:name":"Koos Vierkant",
    "wof:placetype":"venue"
},
  "geometry": {"coordinates":[6.882649,53.106197],"type":"Point"}
}