{
  "type": "Feature",
  "properties": {
    "addr:full":"De Parelvisserslaan 1 Amstelveen Noord-Holland 1183 RH",
    "addr:housenumber":"1",
    "addr:postcode":"1183 rh",
    "addr:street":"De Parelvisserslaan",
    "iso:country":"NL",
    "sg:address":"De Parelvisserslaan 1",
    "sg:city":"Amstelveen",
    "sg:orig_category":"Public Relationbureaus",
    "sg:phone":"+31 20 656 0111",
    "sg:postcode":"1183 RH",
    "sg:province":"Noord-Holland",
    "wof:name":"Initiative Media Bv",
    "wof:placetype":"venue"
},
  "geometry": {"coordinates":[4.873533,52.302509],"type":"Point"}
}