{
  "type": "Feature",
  "properties": {
    "iso:country":"NL",
    "sg:address":"Rijksstraatweg 127",
    "sg:city":"Sleeuwijk",
    "sg:orig_category":"Huishoudapparatuur, Televisies And Radio'S",
    "sg:phone":"+31 183 301 992",
    "sg:postcode":"4254 XD",
    "sg:province":"North Brabant",
    "wof:name":"A.W. Verhoeven",
    "wof:placetype":"venue"
},
  "geometry": {"coordinates":[4.944877,51.807674],"type":"Point"}
}