{
  "type": "Feature",
  "properties": {
    "addr:full":"Broekestr 6A Sprundel Noord-Brabant 4714 SX",
    "addr:housenumber":"6a",
    "addr:postcode":"4714 sx",
    "addr:street":"Broekestr",
    "iso:country":"NL",
    "sg:address":"Broekestr 6A",
    "sg:city":"Sprundel",
    "sg:orig_category":"Verpakkingsmachines",
    "sg:phone":"+31 165 385 673",
    "sg:postcode":"4714 SX",
    "sg:province":"Noord-Brabant",
    "wof:name":"Hitec",
    "wof:placetype":"venue"
},
  "geometry": {"coordinates":[4.616691,51.55204],"type":"Point"}
}