{
  "type": "Feature",
  "properties": {
    "addr:full":"Vrinssenstraat 36 Stramproy BE.05 6039 GW",
    "addr:housenumber":"36;be.05",
    "addr:postcode":"6039 gw",
    "addr:street":"Vrinssenstraat",
    "iso:country":"NL",
    "sg:address":"Vrinssenstraat 36",
    "sg:city":"Stramproy",
    "sg:orig_category":"Wegen And Sportterreinen",
    "sg:phone":"+31 495 562 688",
    "sg:postcode":"6039 GW",
    "sg:province":"BE.05",
    "wof:name":"Coolen Bestratingen",
    "wof:placetype":"venue"
},
  "geometry": {"coordinates":[5.7089557648,51.1936912537],"type":"Point"}
}