{
  "type": "Feature",
  "properties": {
    "iso:country":"NL",
    "sg:address":"Aardvletterweg 10",
    "sg:city":"Montfoort",
    "sg:orig_category":"Farmaceutische Producten Gh",
    "sg:phone":"+31 348 472 914",
    "sg:postcode":"3417 XL",
    "sg:province":"Utrecht",
    "wof:name":"Kneipp Nederland Bv",
    "wof:placetype":"venue"
},
  "geometry": {"coordinates":[4.940436,52.043655],"type":"Point"}
}