{
  "type": "Feature",
  "properties": {
    "addr:full":"Wannepad 94 Amsterdam Noord-Holland 1066 HZ",
    "addr:housenumber":"94",
    "addr:postcode":"1066 hz",
    "addr:street":"Wannepad",
    "iso:country":"NL",
    "sg:address":"Wannepad 94",
    "sg:city":"Amsterdam",
    "sg:orig_category":"Boekhouders",
    "sg:phone":"+31 20 669 9414",
    "sg:postcode":"1066 HZ",
    "sg:province":"Noord-Holland",
    "wof:name":"Qi-Account-Financial Services-",
    "wof:placetype":"venue"
},
  "geometry": {"coordinates":[4.819308,52.344566],"type":"Point"}
}