{
  "type": "Feature",
  "properties": {
    "addr:full":"Operettewg 3F Almere NL. 1323 VJ",
    "addr:housenumber":"3f",
    "addr:postcode":"1323 vj",
    "addr:street":"Nl.",
    "iso:country":"NL",
    "sg:address":"Operettewg 3F",
    "sg:city":"Almere",
    "sg:orig_category":"Open Haarden",
    "sg:phone":"+31 36 529 5491",
    "sg:postcode":"1323 VJ",
    "sg:province":"NL.",
    "sg:website":"http://www.wela.nl",
    "wof:name":"Wela Open Haarden En Schouwen",
    "wof:placetype":"venue"
},
  "geometry": {"coordinates":[5.189260006,52.3633499146],"type":"Point"}
}