{
  "type": "Feature",
  "properties": {
    "addr:full":"Burgemeester Van Esstr 45 Pernis Rt South Holland 3195 AB",
    "addr:housenumber":"45",
    "addr:postcode":"rt;3195 ab",
    "addr:street":"Burgemeester Van Esstr",
    "iso:country":"NL",
    "sg:address":"Burgemeester Van Esstr 45",
    "sg:city":"Pernis Rt",
    "sg:orig_category":"Boekenuitgeverijen",
    "sg:phone":"+31 10 416 2942",
    "sg:postcode":"3195 AB",
    "sg:province":"South Holland",
    "wof:name":"De Pernisser",
    "wof:placetype":"venue"
},
  "geometry": {"coordinates":[4.386774,51.891117],"type":"Point"}
}