{
  "type": "Feature",
  "properties": {
    "iso:country":"NL",
    "sg:address":"Vlietskant 24A",
    "sg:city":"Leerdam",
    "sg:orig_category":"Fotoreportages",
    "sg:phone":"+31 345 611 200",
    "sg:postcode":"4141 CL",
    "sg:province":"Zuid-Holland",
    "sg:website":"http://www.vdcfotovideo.nl",
    "wof:name":"Vdc",
    "wof:placetype":"venue"
},
  "geometry": {"coordinates":[5.095812,51.892109],"type":"Point"}
}