{
  "type": "Feature",
  "properties": {
    "addr:full":"Achter De Hoven 2B Leeuwarden Provincie Friesland 8933 AJ",
    "addr:housenumber":"2b",
    "addr:postcode":"8933 aj",
    "addr:street":"Achter De Hoven;Provincie Friesland",
    "iso:country":"NL",
    "sg:address":"Achter De Hoven 2B",
    "sg:city":"Leeuwarden",
    "sg:orig_category":"Plafonds",
    "sg:phone":"+31 58 213 8328",
    "sg:postcode":"8933 AJ",
    "sg:province":"Provincie Friesland",
    "wof:name":"Lautenbach",
    "wof:placetype":"venue"
},
  "geometry": {"coordinates":[5.800223,53.198845],"type":"Point"}
}