{
  "type": "Feature",
  "properties": {
    "addr:full":"Latherusstr 86 Amsterdam Noord-Holland 1032 EE",
    "addr:housenumber":"86",
    "addr:postcode":"1032 ee",
    "addr:street":"Latherusstr",
    "iso:country":"NL",
    "sg:address":"Latherusstr 86",
    "sg:city":"Amsterdam",
    "sg:orig_category":"Onderhoudswerken",
    "sg:phone":"+31 20 632 5476",
    "sg:postcode":"1032 EE",
    "sg:province":"Noord-Holland",
    "wof:name":"Ronald Van Welij",
    "wof:placetype":"venue"
},
  "geometry": {"coordinates":[4.91543,52.394802],"type":"Point"}
}