{
  "type": "Feature",
  "properties": {
    "addr:full":"Hoofdstr 52 Terborg Gelderland 7061 CL",
    "addr:housenumber":"52",
    "addr:postcode":"7061",
    "addr:street":"Hoofdstr;Gelderland",
    "iso:country":"NL",
    "sg:address":"Hoofdstr 52",
    "sg:city":"Terborg",
    "sg:orig_category":"Verzekeringen - Verzekeringskantoren",
    "sg:phone":"+31 315 341 122",
    "sg:postcode":"7061 CL",
    "sg:province":"Gelderland",
    "wof:name":"Havegoed",
    "wof:placetype":"venue"
},
  "geometry": {"coordinates":[6.358594,51.919453],"type":"Point"}
}