{
  "type": "Feature",
  "properties": {
    "addr:full":"Klatering 23 Beilen Provincie Drenthe 9411 XG",
    "addr:housenumber":"23",
    "addr:postcode":"9411 xg",
    "addr:street":"Klatering;Provincie Drenthe",
    "iso:country":"NL",
    "sg:address":"Klatering 23",
    "sg:city":"Beilen",
    "sg:orig_category":"Verbouwingen",
    "sg:phone":"+31 593 524 091",
    "sg:postcode":"9411 XG",
    "sg:province":"Provincie Drenthe",
    "wof:name":"Hoogendoorn",
    "wof:placetype":"venue"
},
  "geometry": {"coordinates":[6.533547,52.880157],"type":"Point"}
}