{
  "type": "Feature",
  "properties": {
    "addr:full":"Frankenstr 110 Maastricht Limburg 6224 GS",
    "addr:housenumber":"110",
    "addr:postcode":"6224 gs",
    "iso:country":"NL",
    "sg:address":"Frankenstr 110",
    "sg:city":"Maastricht",
    "sg:orig_category":"Verenigingen En Stichtingen",
    "sg:phone":"+31 43 363 5567",
    "sg:postcode":"6224 GS",
    "sg:province":"Limburg",
    "sg:website":"http://www.homepages.hetnet.nl/~rpv1983",
    "wof:name":"Retina Nederland",
    "wof:placetype":"venue"
},
  "geometry": {"coordinates":[5.715455,50.851265],"type":"Point"}
}