{
  "type": "Feature",
  "properties": {
    "addr:full":"Wildzoom 27 Barneveld Gelderland 3772 SL",
    "addr:housenumber":"27",
    "addr:postcode":"3772 sl",
    "addr:street":"Wildzoom;Gelderland",
    "iso:country":"NL",
    "sg:address":"Wildzoom 27",
    "sg:city":"Barneveld",
    "sg:orig_category":"Honden- En Kattentrimsalons",
    "sg:phone":"+31 342 413 678",
    "sg:postcode":"3772 SL",
    "sg:province":"Gelderland",
    "wof:name":"Rexanne Hondentrimsalon",
    "wof:placetype":"venue"
},
  "geometry": {"coordinates":[5.594863,52.133011],"type":"Point"}
}