{
  "type": "Feature",
  "properties": {
    "addr:full":"Veerstr 66 Oud Vossemeer Zeeland 4698 RM",
    "addr:housenumber":"66",
    "addr:postcode":"4698 rm",
    "addr:street":"Veerstr",
    "iso:country":"NL",
    "sg:address":"Veerstr 66",
    "sg:city":"Oud Vossemeer",
    "sg:orig_category":"Vertaalbureaus",
    "sg:phone":"+31 166 672 219",
    "sg:postcode":"4698 RM",
    "sg:province":"Zeeland",
    "wof:name":"Lucynka",
    "wof:placetype":"venue"
},
  "geometry": {"coordinates":[4.209409,51.575668],"type":"Point"}
}