{
  "type": "Feature",
  "properties": {
    "iso:country":"NL",
    "sg:address":"Kerkstraat 12",
    "sg:city":"Nieuwveen",
    "sg:orig_category":"Bloemen And Planten",
    "sg:phone":"+31 172 538 195",
    "sg:postcode":"2441 CD",
    "sg:province":"Zuid-Holland",
    "wof:name":"Vof Bloemsierkunst Ton De Jong",
    "wof:placetype":"venue"
},
  "geometry": {"coordinates":[4.756785,52.196735],"type":"Point"}
}