{
  "type": "Feature",
  "properties": {
    "addr:full":"Hof Van Den Houte 89 Etten-Leur Noord-Brabant 4873 AZ",
    "addr:housenumber":"89",
    "addr:postcode":"4873 az",
    "addr:street":"Hof Van Den Houte",
    "iso:country":"NL",
    "sg:address":"Hof Van Den Houte 89",
    "sg:city":"Etten-Leur",
    "sg:orig_category":"Opticiens",
    "sg:phone":"+31 76 503 4700",
    "sg:postcode":"4873 AZ",
    "sg:province":"Noord-Brabant",
    "wof:name":"Pearle Opticiens",
    "wof:placetype":"venue"
},
  "geometry": {"coordinates":[4.6382241249,51.5682907104],"type":"Point"}
}