{
  "type": "Feature",
  "properties": {
    "addr:full":"M A De Ruyterstr 137 Spykenisse South Holland 3201 CK",
    "addr:housenumber":"137",
    "addr:postcode":"3201 ck",
    "addr:street":"Spykenisse South",
    "iso:country":"NL",
    "sg:address":"M A De Ruyterstr 137",
    "sg:city":"Spykenisse",
    "sg:orig_category":"Verenigingen En Stichtingen",
    "sg:phone":"+31 181 626 887",
    "sg:postcode":"3201 CK",
    "sg:province":"South Holland",
    "wof:name":"Bewonersver De Samenwerking",
    "wof:placetype":"venue"
},
  "geometry": {"coordinates":[4.325045,51.849525],"type":"Point"}
}