{
  "type": "Feature",
  "properties": {
    "addr:full":"Oudewg 6 Drachten Friesland 9203 AG",
    "addr:housenumber":"6",
    "addr:postcode":"9203",
    "addr:street":"Oudewg",
    "iso:country":"NL",
    "sg:address":"Oudewg 6",
    "sg:city":"Drachten",
    "sg:orig_category":"Kappers",
    "sg:phone":"+31 512 513 821",
    "sg:postcode":"9203 AG",
    "sg:province":"Friesland",
    "wof:name":"Geertje'S",
    "wof:placetype":"venue"
},
  "geometry": {"coordinates":[6.0975208282,53.1075935364],"type":"Point"}
}