{
  "type": "Feature",
  "properties": {
    "addr:full":"Bunderstraat 154 Meerssen Limburg 6231 EM",
    "addr:housenumber":"154",
    "addr:postcode":"6231 em",
    "addr:street":"Bunderstraat",
    "iso:country":"NL",
    "sg:address":"Bunderstraat 154",
    "sg:city":"Meerssen",
    "sg:orig_category":"Kappers",
    "sg:phone":"+31 43 364 2993",
    "sg:postcode":"6231 EM",
    "sg:province":"Limburg",
    "wof:name":"Maison Lady",
    "wof:placetype":"venue"
},
  "geometry": {"coordinates":[5.745713,50.886642],"type":"Point"}
}