{
  "type": "Feature",
  "properties": {
    "iso:country":"NL",
    "sg:address":"Plantsoenstr 12",
    "sg:city":"Deventer",
    "sg:orig_category":"Manueel Therapeuten",
    "sg:phone":"+31 570 636 488",
    "sg:postcode":"7411 HT",
    "sg:province":"Overijssel",
    "wof:name":"Janssen Manuele Therapie (E S), F J L",
    "wof:placetype":"venue"
},
  "geometry": {"coordinates":[6.158693,52.256397],"type":"Point"}
}