{
  "type": "Feature",
  "properties": {
    "addr:full":"Zevenwouden 254 Utrecht Utrecht 3524 CX",
    "addr:housenumber":"254",
    "addr:postcode":"3524 cx",
    "addr:street":"Zevenwouden",
    "iso:country":"NL",
    "sg:address":"Zevenwouden 254",
    "sg:city":"Utrecht",
    "sg:classifiers":[
        {
            "category":"Communications",
            "subcategory":"Television Station",
            "type":"Services"
        }
    ],
    "sg:phone":"+31 30 280 0954",
    "sg:postcode":"3524 CX",
    "sg:province":"Utrecht",
    "sg:tags":[
        "video",
        "audio",
        "verhuur"
    ],
    "wof:name":"Ster Lunetten",
    "wof:placetype":"venue"
},
  "geometry": {"coordinates":[5.136424,52.065105],"type":"Point"}
}