{
  "type": "Feature",
  "properties": {
    "addr:full":"De Kempenaerstraat 67 Amsterdam North Holland 1051 CL",
    "addr:housenumber":"67",
    "addr:postcode":"1051",
    "addr:street":"De Kempenaerstraat",
    "iso:country":"NL",
    "sg:address":"De Kempenaerstraat 67",
    "sg:city":"Amsterdam",
    "sg:orig_category":"Metalen And Ertsen Gh",
    "sg:phone":"+31 20 686 3052",
    "sg:postcode":"1051 CL",
    "sg:province":"North Holland",
    "wof:name":"Daudet Bv",
    "wof:placetype":"venue"
},
  "geometry": {"coordinates":[4.8697,52.380589],"type":"Point"}
}