{
  "type": "Feature",
  "properties": {
    "addr:full":"Queridoln 5 Groningen Groningen 9721 SZ",
    "addr:housenumber":"5",
    "addr:postcode":"9721 sz",
    "addr:street":"Queridoln",
    "iso:country":"NL",
    "sg:address":"Queridoln 5",
    "sg:city":"Groningen",
    "sg:orig_category":"Verzekeringen - Verzekeringskantoren",
    "sg:phone":"+31 50 521 8333",
    "sg:postcode":"9721 SZ",
    "sg:province":"Groningen",
    "sg:website":"HTTP://www.adviescompagnie.nl",
    "wof:name":"Advies Compagnie Bv",
    "wof:placetype":"venue"
},
  "geometry": {"coordinates":[6.57473,53.194111],"type":"Point"}
}