{
  "type": "Feature",
  "properties": {
    "iso:country":"NL",
    "sg:address":"Kreilerstraat 20",
    "sg:city":"Hindeloopen",
    "sg:classifiers":[
        {
            "category":"Education",
            "subcategory":"Preschool",
            "type":"Public Place"
        }
    ],
    "sg:phone":"+31 514 521 510",
    "sg:postcode":"8713 JB",
    "sg:province":"Friesland",
    "sg:tags":[
        "kleuteronderwijs",
        "basis-"
    ],
    "wof:name":"De Skulpe Basisschool",
    "wof:placetype":"venue"
},
  "geometry": {"coordinates":[5.404657,52.938885],"type":"Point"}
}