{
  "type": "Feature",
  "properties": {
    "addr:full":"Appeldk 9 Gorinchem South Holland 4201 AE",
    "addr:housenumber":"9",
    "addr:postcode":"4201 ae",
    "addr:street":"Appeldk",
    "iso:country":"NL",
    "sg:address":"Appeldk 9",
    "sg:city":"Gorinchem",
    "sg:orig_category":"Woninginrichting",
    "sg:phone":"+31 183 630 790",
    "sg:postcode":"4201 AE",
    "sg:province":"South Holland",
    "wof:name":"Plank Bv, Van Der",
    "wof:placetype":"venue"
},
  "geometry": {"coordinates":[4.9770178795,51.8295783997],"type":"Point"}
}