{
  "type": "Feature",
  "properties": {
    "addr:full":"Eise Eisingastraat 16 Franeker Friesland 8801 KG",
    "addr:housenumber":"16",
    "addr:postcode":"8801 kg",
    "addr:street":"Eise Eisingastraat",
    "iso:country":"NL",
    "sg:address":"Eise Eisingastraat 16",
    "sg:city":"Franeker",
    "sg:orig_category":"Advocaten And Juridische Adviseurs",
    "sg:phone":"+31 517 397 470",
    "sg:postcode":"8801 KG",
    "sg:province":"Friesland",
    "wof:name":"Advokatenkantoor Mr. J. Algera",
    "wof:placetype":"venue"
},
  "geometry": {"coordinates":[5.545052,53.18745],"type":"Point"}
}