{
  "type": "Feature",
  "properties": {
    "addr:full":"Kerkln 20 Akersloot North Holland 1921 BL",
    "addr:housenumber":"20",
    "addr:postcode":"1921 bl",
    "addr:street":"Kerkln",
    "iso:country":"NL",
    "sg:address":"Kerkln 20",
    "sg:city":"Akersloot",
    "sg:orig_category":"Zalenverhuur",
    "sg:phone":"+31 251 312 120",
    "sg:postcode":"1921 BL",
    "sg:province":"North Holland",
    "sg:website":"http://www.hoorntje.nl",
    "wof:name":"Hoorntje Horeca En Recr Bedrijf, 'T",
    "wof:placetype":"venue"
},
  "geometry": {"coordinates":[4.734425,52.56197],"type":"Point"}
}