{
  "type": "Feature",
  "properties": {
    "iso:country":"NL",
    "sg:address":"Lingsesdk 82",
    "sg:city":"Gorinchem",
    "sg:orig_category":"Wasmachines En Wasdrogers - Onderhoud En Reparatie",
    "sg:phone":"+31 183 634 848",
    "sg:postcode":"4207 AG",
    "sg:province":"South Holland",
    "wof:name":"Twenty Four Hour Service",
    "wof:placetype":"venue"
},
  "geometry": {"coordinates":[4.9890642166,51.8327560425],"type":"Point"}
}