{
  "type": "Feature",
  "properties": {
    "addr:full":"Hofln 1 Arnhem Gelderland 6824 BN",
    "addr:housenumber":"1",
    "addr:postcode":"6824 bn",
    "addr:street":"Hofln",
    "iso:country":"NL",
    "sg:address":"Hofln 1",
    "sg:city":"Arnhem",
    "sg:orig_category":"Advocaten En Advocatenkantoren",
    "sg:phone":"+31 26 442 7428",
    "sg:postcode":"6824 BN",
    "sg:province":"Gelderland",
    "wof:name":"Hanssen Hermsen & Heerink",
    "wof:placetype":"venue"
},
  "geometry": {"coordinates":[5.93741,51.993671],"type":"Point"}
}