{
  "type": "Feature",
  "properties": {
    "addr:full":"Rondweg-West 33A Dokkum Friesland 9101 BE",
    "addr:housenumber":"33a",
    "addr:postcode":"9101",
    "addr:street":"Rondweg-West",
    "iso:country":"NL",
    "sg:address":"Rondweg-West 33A",
    "sg:city":"Dokkum",
    "sg:orig_category":"Goederenvervoer Over De Weg",
    "sg:phone":"+31 519 293 336",
    "sg:postcode":"9101 BE",
    "sg:province":"Friesland",
    "wof:name":"Dok",
    "wof:placetype":"venue"
},
  "geometry": {"coordinates":[5.986711,53.325226],"type":"Point"}
}