{
  "type": "Feature",
  "properties": {
    "addr:full":"Schoutenhof 11 Ede Gld Gelderland 6715 LT",
    "addr:housenumber":"11",
    "addr:postcode":"6715 lt",
    "addr:street":"Schoutenhof;Gld Gelderland",
    "iso:country":"NL",
    "sg:address":"Schoutenhof 11",
    "sg:city":"Ede Gld",
    "sg:classifiers":[
        {
            "category":"Personal",
            "subcategory":"Nail Salon",
            "type":"Services"
        }
    ],
    "sg:phone":"+31 318 622 837",
    "sg:postcode":"6715 LT",
    "sg:province":"Gelderland",
    "sg:tags":[
        "pedicure"
    ],
    "wof:name":"Hoedt, Ans Ten",
    "wof:placetype":"venue"
},
  "geometry": {"coordinates":[5.630351,52.041958],"type":"Point"}
}