{
  "type": "Feature",
  "properties": {
    "iso:country":"NL",
    "sg:address":"Neringpassage 123",
    "sg:city":"Lelystad",
    "sg:orig_category":"Hulpverlening Sociaal",
    "sg:phone":"+31 320 290 055",
    "sg:postcode":"8224 JB",
    "sg:province":"Flevoland",
    "wof:name":"Nidos, Sticht",
    "wof:placetype":"venue"
},
  "geometry": {"coordinates":[5.477197,52.508987],"type":"Point"}
}