{
  "type": "Feature",
  "properties": {
    "addr:full":"Paalwg 1 Urmond Limburg 6129 EZ",
    "addr:housenumber":"1",
    "addr:postcode":"6129 ez",
    "addr:street":"Paalwg",
    "iso:country":"NL",
    "sg:address":"Paalwg 1",
    "sg:city":"Urmond",
    "sg:classifiers":[
        {
            "category":"Retail",
            "subcategory":"Auto Repair",
            "type":"Services"
        }
    ],
    "sg:phone":"+31 46 433 2010",
    "sg:postcode":"6129 EZ",
    "sg:province":"Limburg",
    "sg:tags":[
        "garage"
    ],
    "wof:name":"Paal, De",
    "wof:placetype":"venue"
},
  "geometry": {"coordinates":[5.767035,50.986919],"type":"Point"}
}