{
  "type": "Feature",
  "properties": {
    "addr:full":"Zilkerduinwg 394 Vogelenzang Noord-Holland 2114 AM",
    "addr:housenumber":"394",
    "addr:postcode":"2114",
    "iso:country":"NL",
    "sg:address":"Zilkerduinwg 394",
    "sg:city":"Vogelenzang",
    "sg:orig_category":"Bloembollen - Groothandel",
    "sg:phone":"+31 252 517 282",
    "sg:postcode":"2114 AM",
    "sg:province":"Noord-Holland",
    "wof:name":"Haaster & Zn, Fa Nic Van",
    "wof:placetype":"venue"
},
  "geometry": {"coordinates":[4.561002,52.312443],"type":"Point"}
}