{
  "type": "Feature",
  "properties": {
    "addr:full":"Kaap Hoorndreef 64 Utrecht Utrecht 3563 AV",
    "addr:housenumber":"64",
    "addr:postcode":"3563 av",
    "addr:street":"Kaap Hoorndreef",
    "iso:country":"NL",
    "sg:address":"Kaap Hoorndreef 64",
    "sg:city":"Utrecht",
    "sg:orig_category":"Artsen - Huisartsen",
    "sg:phone":"+31 30 254 1850",
    "sg:postcode":"3563 AV",
    "sg:province":"Utrecht",
    "wof:name":"Forensisch Medische Maatschap Utrecht",
    "wof:placetype":"venue"
},
  "geometry": {"coordinates":[5.106047,52.114899],"type":"Point"}
}