{
  "type": "Feature",
  "properties": {
    "iso:country":"NL",
    "sg:address":"Schoterlandseweg 40",
    "sg:city":"Nieuwehorne",
    "sg:orig_category":"Huishoudapparatuur, Televisies And Radio'S",
    "sg:phone":"+31 513 541 270",
    "sg:postcode":"8414 LX",
    "sg:province":"Friesland",
    "wof:name":"Vof Pewe",
    "wof:placetype":"venue"
},
  "geometry": {"coordinates":[6.057433,52.950756],"type":"Point"}
}