{
  "type": "Feature",
  "properties": {
    "addr:full":"Eekhoornstraat 35 Hilversum Noord-Holland 1216 AP",
    "addr:housenumber":"35",
    "addr:postcode":"1216 ap",
    "addr:street":"Eekhoornstraat",
    "iso:country":"NL",
    "sg:address":"Eekhoornstraat 35",
    "sg:city":"Hilversum",
    "sg:orig_category":"Bloemen And Planten",
    "sg:phone":"+31 35 621 8018",
    "sg:postcode":"1216 AP",
    "sg:province":"Noord-Holland",
    "wof:name":"Fleuriche",
    "wof:placetype":"venue"
},
  "geometry": {"coordinates":[5.152932,52.222057],"type":"Point"}
}