{
  "type": "Feature",
  "properties": {
    "addr:full":"Zijdstraat 43 Aalsmeer North Holland 1431 EA",
    "addr:housenumber":"43",
    "addr:postcode":"1431 ea",
    "addr:street":"Zijdstraat",
    "iso:country":"NL",
    "sg:address":"Zijdstraat 43",
    "sg:city":"Aalsmeer",
    "sg:orig_category":"Fotostudio'S And Fotografen",
    "sg:phone":"+31 297 324 263",
    "sg:postcode":"1431 EA",
    "sg:province":"North Holland",
    "wof:name":"Combi De Boer",
    "wof:placetype":"venue"
},
  "geometry": {"coordinates":[4.747339,52.268658],"type":"Point"}
}