{
  "type": "Feature",
  "properties": {
    "iso:country":"NL",
    "sg:address":"Christoffel Plantijnstr 3",
    "sg:city":"'S Gravenhage",
    "sg:orig_category":"Bejaardeninstellingen And Serviceflats",
    "sg:phone":"+31 70 344 6100",
    "sg:postcode":"2515 TZ",
    "sg:province":"Zuid-Holland",
    "wof:name":"Verzorgingshuis Rivierenbuurt",
    "wof:placetype":"venue"
},
  "geometry": {"coordinates":[4.323275,52.07626],"type":"Point"}
}