{
  "type": "Feature",
  "properties": {
    "addr:full":"Benedictynenhove 12 Leusden Utrecht 3834 ZE",
    "addr:housenumber":"12",
    "addr:postcode":"3834 ze",
    "addr:street":"Benedictynenhove",
    "iso:country":"NL",
    "sg:address":"Benedictynenhove 12",
    "sg:city":"Leusden",
    "sg:orig_category":"Product-Promotie",
    "sg:phone":"+31 33 494 4383",
    "sg:postcode":"3834 ZE",
    "sg:province":"Utrecht",
    "wof:name":"Breemen, Tonnie Van",
    "wof:placetype":"venue"
},
  "geometry": {"coordinates":[5.43554,52.127586],"type":"Point"}
}