{
  "type": "Feature",
  "properties": {
    "addr:full":"Betterwird 16 Dokkum Friesland 9101 PB",
    "addr:housenumber":"16",
    "addr:postcode":"9101 pb",
    "addr:street":"Betterwird",
    "iso:country":"NL",
    "sg:address":"Betterwird 16",
    "sg:city":"Dokkum",
    "sg:orig_category":"Bloemen En Planten - Groothandel",
    "sg:phone":"+31 6 51278863",
    "sg:postcode":"9101 PB",
    "sg:province":"Friesland",
    "wof:name":"Bote S Dijk",
    "wof:placetype":"venue"
},
  "geometry": {"coordinates":[5.984034,53.326977],"type":"Point"}
}