{
  "type": "Feature",
  "properties": {
    "iso:country":"NL",
    "sg:address":"Havikstr 34",
    "sg:city":"Badhoevedorp",
    "sg:orig_category":"Schilders",
    "sg:phone":"+31 20 659 7646",
    "sg:postcode":"1171 DX",
    "sg:province":"Noord-Holland",
    "wof:name":"Beekman",
    "wof:placetype":"venue"
},
  "geometry": {"coordinates":[4.782321,52.339706],"type":"Point"}
}