{
  "type": "Feature",
  "properties": {
    "iso:country":"NL",
    "sg:address":"P C Hooftstraat 43",
    "sg:city":"Zevenaar",
    "sg:orig_category":"Binnenhuisarchitecten",
    "sg:phone":"+31 316 524 933",
    "sg:postcode":"6901 KL",
    "sg:province":"Gelderland",
    "wof:name":"J.A. Dumon-Tak",
    "wof:placetype":"venue"
},
  "geometry": {"coordinates":[6.085841,51.93195],"type":"Point"}
}