{
  "type": "Feature",
  "properties": {
    "iso:country":"NL",
    "sg:address":"Cuyperswg 52",
    "sg:city":"Groningen",
    "sg:orig_category":"Kappers",
    "sg:phone":"+31 50 541 0855",
    "sg:postcode":"9731 LA",
    "sg:province":"Groningen",
    "wof:name":"Vanessa",
    "wof:placetype":"venue"
},
  "geometry": {"coordinates":[6.578356,53.245483],"type":"Point"}
}