{
  "type": "Feature",
  "properties": {
    "iso:country":"NL",
    "sg:address":"Esdonk 15",
    "sg:city":"Deurne",
    "sg:orig_category":"Administratie- En Boekhoudkantoren",
    "sg:phone":"+31 493 316 288",
    "sg:postcode":"5753 PH",
    "sg:province":"Noord-Brabant",
    "wof:name":"Nymphaea",
    "wof:placetype":"venue"
},
  "geometry": {"coordinates":[5.784312,51.449425],"type":"Point"}
}