{
  "type": "Feature",
  "properties": {
    "addr:full":"Postbus 34 Westerbork Provincie Drenthe 9430 AA",
    "addr:housenumber":"34",
    "addr:postcode":"9430 aa",
    "addr:street":"Postbus;Provincie Drenthe",
    "iso:country":"NL",
    "sg:address":"Postbus 34",
    "sg:city":"Westerbork",
    "sg:orig_category":"Juweliers",
    "sg:phone":"+31 593 346 475",
    "sg:postcode":"9430 AA",
    "sg:province":"Provincie Drenthe",
    "sg:website":"http://www.rewdesign.nl",
    "wof:name":"Rew Design",
    "wof:placetype":"venue"
},
  "geometry": {"coordinates":[6.61104,52.85041],"type":"Point"}
}