{
  "type": "Feature",
  "properties": {
    "addr:full":"Vicariestr 2B Elburg Gelderland 8081 XK",
    "addr:housenumber":"2b",
    "addr:postcode":"8081 xk",
    "addr:street":"Vicariestr;Gelderland",
    "iso:country":"NL",
    "sg:address":"Vicariestr 2B",
    "sg:city":"Elburg",
    "sg:orig_category":"Administratie- En Boekhoudkantoren",
    "sg:phone":"+31 525 680 130",
    "sg:postcode":"8081 XK",
    "sg:province":"Gelderland",
    "wof:name":"Allema",
    "wof:placetype":"venue"
},
  "geometry": {"coordinates":[5.845472,52.449139],"type":"Point"}
}