{
  "type": "Feature",
  "properties": {
    "iso:country":"NL",
    "sg:address":"Duke Ellingtonstraat 34",
    "sg:city":"Amsterdam",
    "sg:orig_category":"Meubels And Huishoudapparatuur Gh",
    "sg:phone":"+31 20 615 7029",
    "sg:postcode":"1066 GE",
    "sg:province":"Noord-Holland",
    "wof:name":"Beatus",
    "wof:placetype":"venue"
},
  "geometry": {"coordinates":[4.826816,52.343906],"type":"Point"}
}