{
  "type": "Feature",
  "properties": {
    "iso:country":"NL",
    "sg:address":"Rubensstr 91",
    "sg:city":"Amsterdam",
    "sg:orig_category":"Adviesbureaus Bedrijfsorganisatie",
    "sg:phone":"+31 20 662 1260",
    "sg:postcode":"1077 MN",
    "sg:province":"North Holland",
    "wof:name":"Coomans, Gwen",
    "wof:placetype":"venue"
},
  "geometry": {"coordinates":[4.874155,52.345234],"type":"Point"}
}