{
  "type": "Feature",
  "properties": {
    "addr:full":"Fluitekruid 21 Nijkerk Gld Gelderland 3863 DZ",
    "addr:housenumber":"21",
    "addr:postcode":"3863 dz",
    "addr:street":"Fluitekruid;Gld Gelderland",
    "iso:country":"NL",
    "sg:address":"Fluitekruid 21",
    "sg:city":"Nijkerk Gld",
    "sg:orig_category":"Meubelreparatie And -Restauratie",
    "sg:phone":"+31 33 245 3806",
    "sg:postcode":"3863 DZ",
    "sg:province":"Gelderland",
    "wof:name":"Woninginrichtersbedrijf Klaarenbeek 'T Olde Huus",
    "wof:placetype":"venue"
},
  "geometry": {"coordinates":[5.458577,52.220295],"type":"Point"}
}