{
  "type": "Feature",
  "properties": {
    "iso:country":"NL",
    "sg:address":"Pr Willem-Alexanderprk 504",
    "sg:city":"Veenendaal",
    "sg:orig_category":"Bibliotheken And Openbare Archieven",
    "sg:phone":"+31 318 511 150",
    "sg:postcode":"3905 DN",
    "sg:province":"Utrecht",
    "wof:name":"Firma F.A. Romijn",
    "wof:placetype":"venue"
},
  "geometry": {"coordinates":[5.544146,52.028378],"type":"Point"}
}