{
  "type": "Feature",
  "properties": {
    "addr:full":"Odijkseweg 48 Houten Utrecht 3994 AT",
    "addr:housenumber":"48",
    "addr:postcode":"3994",
    "addr:street":"Odijkseweg",
    "iso:country":"NL",
    "sg:address":"Odijkseweg 48",
    "sg:city":"Houten",
    "sg:orig_category":"Verzekeringen",
    "sg:phone":"+31 30 637 1274",
    "sg:postcode":"3994 AT",
    "sg:province":"Utrecht",
    "wof:name":"Heiligenberg Assurantien",
    "wof:placetype":"venue"
},
  "geometry": {"coordinates":[5.179042,52.032543],"type":"Point"}
}