{
  "type": "Feature",
  "properties": {
    "addr:full":"Tweede Kostverlorenkade 132-135 Amsterdam North Holland 1053 SE",
    "addr:housenumber":"132-135",
    "addr:postcode":"1053 se",
    "addr:street":"Tweede Kostverlorenkade",
    "iso:country":"NL",
    "sg:address":"Tweede Kostverlorenkade 132-135",
    "sg:city":"Amsterdam",
    "sg:orig_category":"Fitnesscentra",
    "sg:phone":"+31 20 683 1954",
    "sg:postcode":"1053 SE",
    "sg:province":"North Holland",
    "wof:name":"The Family Gym",
    "wof:placetype":"venue"
},
  "geometry": {"coordinates":[4.860108,52.364025],"type":"Point"}
}