{
  "type": "Feature",
  "properties": {
    "addr:full":"Steynstr 3 Wormerveer Noord-Holland 1521 GA",
    "addr:housenumber":"3",
    "addr:postcode":"1521 ga",
    "addr:street":"Steynstr",
    "iso:country":"NL",
    "sg:address":"Steynstr 3",
    "sg:city":"Wormerveer",
    "sg:orig_category":"Maquettes",
    "sg:phone":"+31 75 628 0142",
    "sg:postcode":"1521 GA",
    "sg:province":"Noord-Holland",
    "wof:name":"Corduwener Maquettes",
    "wof:placetype":"venue"
},
  "geometry": {"coordinates":[4.789787,52.492664],"type":"Point"}
}