{
  "type": "Feature",
  "properties": {
    "addr:full":"Molenstraat 77 Tilburg Noord-Brabant 5014 NC",
    "addr:housenumber":"77",
    "addr:postcode":"5014 nc",
    "addr:street":"Molenstraat",
    "iso:country":"NL",
    "sg:address":"Molenstraat 77",
    "sg:city":"Tilburg",
    "sg:orig_category":"Kappers",
    "sg:phone":"+31 13 544 6554",
    "sg:postcode":"5014 NC",
    "sg:province":"Noord-Brabant",
    "wof:name":"Helene Haarmode",
    "wof:placetype":"venue"
},
  "geometry": {"coordinates":[5.1062707901,51.5549278259],"type":"Point"}
}