{
  "type": "Feature",
  "properties": {
    "iso:country":"NL",
    "sg:address":"A Paulownaln 15",
    "sg:city":"Breda",
    "sg:orig_category":"Adviesbureaus Bedrijfsorganisatie",
    "sg:phone":"+31 76 565 0025",
    "sg:postcode":"4835 LA",
    "sg:province":"Noord-Brabant",
    "wof:name":"Hoeven, Van",
    "wof:placetype":"venue"
},
  "geometry": {"coordinates":[4.78069,51.571514],"type":"Point"}
}