{
  "type": "Feature",
  "properties": {
    "addr:full":"Polderwg 3 Oterleek Noord-Holland 1842 EH",
    "addr:housenumber":"3",
    "addr:postcode":"1842 eh",
    "addr:street":"Polderwg",
    "iso:country":"NL",
    "sg:address":"Polderwg 3",
    "sg:city":"Oterleek",
    "sg:orig_category":"Psychotherapeuten",
    "sg:phone":"+31 72 571 9408",
    "sg:postcode":"1842 EH",
    "sg:province":"Noord-Holland",
    "sg:website":"http://www.kinder-psychotherapie.nl",
    "wof:name":"Integratief Kinder-Psychotherapie",
    "wof:placetype":"venue"
},
  "geometry": {"coordinates":[4.838964,52.639057],"type":"Point"}
}