{
  "type": "Feature",
  "properties": {
    "addr:full":"De Schelp 13 Leek Groningen 9351 NV",
    "addr:housenumber":"13",
    "addr:postcode":"9351 nv",
    "addr:street":"De Schelp",
    "iso:country":"NL",
    "sg:address":"De Schelp 13",
    "sg:city":"Leek",
    "sg:orig_category":"Kaasgroothandel",
    "sg:phone":"+31 594 516 443",
    "sg:postcode":"9351 NV",
    "sg:province":"Groningen",
    "wof:name":"Bgnn, Co\u00f7P Ver",
    "wof:placetype":"venue"
},
  "geometry": {"coordinates":[6.3684258461,53.1547431946],"type":"Point"}
}