{
  "type": "Feature",
  "properties": {
    "iso:country":"NL",
    "sg:address":"Westwykpln 76-78",
    "sg:city":"Amstelveen",
    "sg:orig_category":"Postkantoren",
    "sg:phone":"+31 20 647 4153",
    "sg:postcode":"1187 LV",
    "sg:province":"North Holland",
    "sg:website":"http://www.postkantoor.nl",
    "wof:name":"Postkantoor",
    "wof:placetype":"venue"
},
  "geometry": {"coordinates":[4.825977,52.281601],"type":"Point"}
}