{
  "type": "Feature",
  "properties": {
    "iso:country":"NL",
    "sg:address":"Sportln 44A",
    "sg:city":"Emmeloord",
    "sg:orig_category":"Verenigingen En Stichtingen",
    "sg:phone":"+31 527 699 397",
    "sg:postcode":"8302 AZ",
    "sg:province":"Flevoland",
    "wof:name":"Scouting Emmeloord",
    "wof:placetype":"venue"
},
  "geometry": {"coordinates":[5.750635,52.709873],"type":"Point"}
}