{
  "type": "Feature",
  "properties": {
    "iso:country":"NL",
    "sg:address":"H V Vossstr 20",
    "sg:city":"Roosendaal",
    "sg:orig_category":"Wasmachines En Wasdrogers - Onderhoud En Reparatie",
    "sg:phone":"+31 165 558 069",
    "sg:postcode":"4708 AX",
    "sg:province":"North Brabant",
    "wof:name":"Zwart, De",
    "wof:placetype":"venue"
},
  "geometry": {"coordinates":[4.4576702118,51.5314025879],"type":"Point"}
}