{
  "type": "Feature",
  "properties": {
    "iso:country":"NL",
    "sg:address":"N V Hichtumwei 13",
    "sg:city":"Leeuwarden",
    "sg:orig_category":"Verzekeringen - Verzekeringskantoren",
    "sg:phone":"+31 58 213 4350",
    "sg:postcode":"8915 JE",
    "sg:province":"Friesland",
    "sg:website":"http://www.ysiderius.nl",
    "wof:name":"Siderius Assuranti\u00ebn",
    "wof:placetype":"venue"
},
  "geometry": {"coordinates":[5.79257,53.197319],"type":"Point"}
}