{
  "type": "Feature",
  "properties": {
    "iso:country":"NL",
    "sg:address":"Hoofdwg 226",
    "sg:city":"Amsterdam",
    "sg:orig_category":"Koffie- En Theehuizen",
    "sg:phone":"+31 20 685 4995",
    "sg:postcode":"1057 DG",
    "sg:province":"North Holland",
    "wof:name":"Sinbad",
    "wof:placetype":"venue"
},
  "geometry": {"coordinates":[4.852788,52.366901],"type":"Point"}
}