{
  "type": "Feature",
  "properties": {
    "addr:full":"Borniastraat 2 Leeuwarden Provincie Friesland 8932 PE",
    "addr:housenumber":"2",
    "addr:postcode":"8932 pe",
    "addr:street":"Borniastraat;Provincie Friesland",
    "iso:country":"NL",
    "sg:address":"Borniastraat 2",
    "sg:city":"Leeuwarden",
    "sg:orig_category":"Banken And Kredietinstellingen",
    "sg:phone":"+31 58 288 6809",
    "sg:postcode":"8932 PE",
    "sg:province":"Provincie Friesland",
    "wof:name":"Friesland Bank",
    "wof:placetype":"venue"
},
  "geometry": {"coordinates":[5.7981,53.190815],"type":"Point"}
}