{
  "type": "Feature",
  "properties": {
    "addr:full":"Dr P Rinsemastr 7 Vlagtwedde Groningen 9541 AL",
    "addr:housenumber":"7",
    "addr:postcode":"9541 al",
    "addr:street":"Rinsemastr",
    "iso:country":"NL",
    "sg:address":"Dr P Rinsemastr 7",
    "sg:city":"Vlagtwedde",
    "sg:orig_category":"Bibliotheken En Leeszalen Openbare",
    "sg:phone":"+31 599 313 022",
    "sg:postcode":"9541 AL",
    "sg:province":"Groningen",
    "wof:name":"Openb Bibliotheek",
    "wof:placetype":"venue"
},
  "geometry": {"coordinates":[7.107348,53.026279],"type":"Point"}
}