{
  "type": "Feature",
  "properties": {
    "addr:full":"Oosterln 17 Heemstede North Holland 2101 ZP",
    "addr:housenumber":"17",
    "addr:postcode":"2101 zp",
    "addr:street":"Oosterln",
    "iso:country":"NL",
    "sg:address":"Oosterln 17",
    "sg:city":"Heemstede",
    "sg:orig_category":"Onroerende Goederen",
    "sg:phone":"+31 23 547 1944",
    "sg:postcode":"2101 ZP",
    "sg:province":"North Holland",
    "wof:name":"Nieuwe Aanpak, De",
    "wof:placetype":"venue"
},
  "geometry": {"coordinates":[4.621248,52.345287],"type":"Point"}
}