{
  "type": "Feature",
  "properties": {
    "iso:country":"NL",
    "sg:address":"Lange Noordstraat 24",
    "sg:city":"Middelburg",
    "sg:orig_category":"Werving And Selectie Van Tijdelijk Personeel And Uitzendkantoren",
    "sg:phone":"+31 118 651 505",
    "sg:postcode":"4331 CD",
    "sg:province":"Zeeland",
    "wof:name":"Content",
    "wof:placetype":"venue"
},
  "geometry": {"coordinates":[3.6108601093,51.4997444153],"type":"Point"}
}