{
  "type": "Feature",
  "properties": {
    "addr:full":"Gruttostr 29 S Hertogenbosch North Brabant 5212 VM",
    "addr:housenumber":"29",
    "addr:postcode":"5212 vm",
    "addr:street":"Gruttostr;S Hertogenbosch",
    "iso:country":"NL",
    "sg:address":"Gruttostr 29",
    "sg:city":"S Hertogenbosch",
    "sg:orig_category":"Verlichting",
    "sg:phone":"+31 73 612 1815",
    "sg:postcode":"5212 VM",
    "sg:province":"North Brabant",
    "sg:website":"http://www.lampidee.nl",
    "wof:name":"Lampidee",
    "wof:placetype":"venue"
},
  "geometry": {"coordinates":[5.301736,51.701218],"type":"Point"}
}