{
  "type": "Feature",
  "properties": {
    "iso:country":"NL",
    "sg:address":"Laarderwg 7",
    "sg:city":"Eemnes",
    "sg:orig_category":"Verzekeringen - Verzekeringskantoren",
    "sg:phone":"+31 35 531 4361",
    "sg:postcode":"3755 AK",
    "sg:province":"Utrecht",
    "wof:name":"Klooster, D J Van 'T",
    "wof:placetype":"venue"
},
  "geometry": {"coordinates":[5.264029,52.252762],"type":"Point"}
}