{
  "type": "Feature",
  "properties": {
    "addr:full":"S. Bikoplein 12 Amsterdam Noord-Holland 1092 GN",
    "addr:housenumber":"12",
    "addr:postcode":"1092 gn",
    "addr:street":"S. Bikoplein",
    "iso:country":"NL",
    "sg:address":"S. Bikoplein 12",
    "sg:city":"Amsterdam",
    "sg:classifiers":[
        {
            "category":"Fast Food",
            "type":"Food & Drink"
        }
    ],
    "sg:phone":"+31 20 665 3532",
    "sg:postcode":"1092 GN",
    "sg:province":"Noord-Holland",
    "sg:tags":[
        "afhaal",
        "restaurant"
    ],
    "wof:name":"Masada",
    "wof:placetype":"venue"
},
  "geometry": {"coordinates":[4.922933,52.355236],"type":"Point"}
}