{
  "type": "Feature",
  "properties": {
    "iso:country":"NL",
    "sg:address":"Park Berkenoord 9",
    "sg:city":"Pijnacker",
    "sg:orig_category":"Drukkerijen And Copyshops",
    "sg:phone":"+31 15 361 0163",
    "sg:postcode":"2641 CW",
    "sg:province":"Zuid-Holland",
    "wof:name":"Druktiek Aaa",
    "wof:placetype":"venue"
},
  "geometry": {"coordinates":[4.430673,52.022259],"type":"Point"}
}