{
  "type": "Feature",
  "properties": {
    "addr:full":"Gageldk 69 Maarssen Utrecht 3602 AH",
    "addr:housenumber":"69",
    "addr:postcode":"3602 ah",
    "addr:street":"Gageldk",
    "iso:country":"NL",
    "sg:address":"Gageldk 69",
    "sg:city":"Maarssen",
    "sg:classifiers":[
        {
            "category":"Retail",
            "subcategory":"Auto Repair",
            "type":"Services"
        }
    ],
    "sg:phone":"+31 30 262 2602",
    "sg:postcode":"3602 AH",
    "sg:province":"Utrecht",
    "sg:tags":[
        "garage"
    ],
    "wof:name":"Geran",
    "wof:placetype":"venue"
},
  "geometry": {"coordinates":[5.085684,52.136505],"type":"Point"}
}