{
  "type": "Feature",
  "properties": {
    "addr:full":"Zuideind 17 Emmen Drenthe 7812 NH",
    "addr:housenumber":"17",
    "addr:postcode":"7812 nh",
    "addr:street":"Zuideind",
    "iso:country":"NL",
    "sg:address":"Zuideind 17",
    "sg:city":"Emmen",
    "sg:classifiers":[
        {
            "category":"Travel",
            "subcategory":"Hotels & Motels",
            "type":"Entertainment"
        }
    ],
    "sg:phone":"+31 591 617 401",
    "sg:postcode":"7812 NH",
    "sg:province":"Drenthe",
    "wof:name":"Anneke'S Bed & Ontbijt",
    "wof:placetype":"venue"
},
  "geometry": {"coordinates":[6.876375,52.768337],"type":"Point"}
}