{
  "type": "Feature",
  "properties": {
    "addr:full":"Sri Lankapad 1 Delft South Holland 2622 LZ",
    "addr:housenumber":"1",
    "addr:postcode":"2622 lz",
    "iso:country":"NL",
    "sg:address":"Sri Lankapad 1",
    "sg:city":"Delft",
    "sg:orig_category":"Peuterspeelzalen",
    "sg:phone":"+31 15 261 5345",
    "sg:postcode":"2622 LZ",
    "sg:province":"South Holland",
    "wof:name":"Dikkertje Dap",
    "wof:placetype":"venue"
},
  "geometry": {"coordinates":[4.349168,51.98074],"type":"Point"}
}