{
  "type": "Feature",
  "properties": {
    "iso:country":"NL",
    "sg:address":"Laan Van Nieuw Oosteinde 206",
    "sg:city":"Voorburg",
    "sg:orig_category":"Paramedische Behandelingen",
    "sg:phone":"+31 6 54994559",
    "sg:postcode":"2274 EN",
    "sg:province":"Zuid-Holland",
    "wof:name":"Adem En Stem Logopediepraktijk",
    "wof:placetype":"venue"
},
  "geometry": {"coordinates":[4.351197,52.073071],"type":"Point"}
}