{
  "type": "Feature",
  "properties": {
    "addr:full":"Bellinipark 15 Drunen Noord-Brabant 5151 LL",
    "addr:housenumber":"15",
    "addr:postcode":"5151 ll",
    "addr:street":"Bellinipark",
    "iso:country":"NL",
    "sg:address":"Bellinipark 15",
    "sg:city":"Drunen",
    "sg:orig_category":"Boekhouders",
    "sg:phone":"+31 416 374 713",
    "sg:postcode":"5151 LL",
    "sg:province":"Noord-Brabant",
    "wof:name":"Hedru Administratiekantoor",
    "wof:placetype":"venue"
},
  "geometry": {"coordinates":[5.144214,51.678268],"type":"Point"}
}