{
  "type": "Feature",
  "properties": {
    "addr:full":"Nicolaas Beetslaan 328 Voorburg South Holland 2273 RL",
    "addr:housenumber":"328",
    "addr:postcode":"2273 rl",
    "addr:street":"Nicolaas Beetslaan",
    "iso:country":"NL",
    "sg:address":"Nicolaas Beetslaan 328",
    "sg:city":"Voorburg",
    "sg:orig_category":"Begrafenisondernemers",
    "sg:phone":"+31 70 386 9460",
    "sg:postcode":"2273 RL",
    "sg:province":"South Holland",
    "wof:name":"G S Pengel Uitvaartverzorging",
    "wof:placetype":"venue"
},
  "geometry": {"coordinates":[4.353002,52.082451],"type":"Point"}
}