{
  "type": "Feature",
  "properties": {
    "iso:country":"NL",
    "sg:address":"Nijverheidstraat 61",
    "sg:city":"Lemelerveld",
    "sg:orig_category":"Verhuur Audiovisuele Apparatuur",
    "sg:phone":"+31 572 371 237",
    "sg:postcode":"8152 AG",
    "sg:province":"Overijssel",
    "wof:name":"Star Music",
    "wof:placetype":"venue"
},
  "geometry": {"coordinates":[6.337403,52.446117],"type":"Point"}
}