{
  "type": "Feature",
  "properties": {
    "addr:full":"Van Breestraat 116 Amsterdam North Holland 1071 ZV",
    "addr:housenumber":"116",
    "addr:postcode":"1071 zv",
    "addr:street":"Van Breestraat",
    "iso:country":"NL",
    "sg:address":"Van Breestraat 116",
    "sg:city":"Amsterdam",
    "sg:orig_category":"Kantoorapparatuur Gh",
    "sg:phone":"+31 20 679 8799",
    "sg:postcode":"1071 ZV",
    "sg:province":"North Holland",
    "wof:name":"W. Van Bemmel Handelsonderneming",
    "wof:placetype":"venue"
},
  "geometry": {"coordinates":[4.8725790977,52.3559799194],"type":"Point"}
}