{
  "type": "Feature",
  "properties": {
    "addr:full":"De Luther 4 Hooge Mierde Noord-Brabant 5095 AC",
    "addr:housenumber":"4",
    "addr:postcode":"5095 ac",
    "addr:street":"De Luther",
    "iso:country":"NL",
    "sg:address":"De Luther 4",
    "sg:city":"Hooge Mierde",
    "sg:orig_category":"Huizensloop And Bouwrijp Maken",
    "sg:phone":"+31 13 509 1361",
    "sg:postcode":"5095 AC",
    "sg:province":"Noord-Brabant",
    "wof:name":"Loonbedrijf Van Raak Bv",
    "wof:placetype":"venue"
},
  "geometry": {"coordinates":[5.123514,51.381397],"type":"Point"}
}