{
  "type": "Feature",
  "properties": {
    "addr:full":"Merelstraat 21 Utrecht Utrecht 3514 CM",
    "addr:housenumber":"21",
    "addr:postcode":"3514 cm",
    "addr:street":"Merelstraat",
    "iso:country":"NL",
    "sg:address":"Merelstraat 21",
    "sg:city":"Utrecht",
    "sg:orig_category":"Alternatieve Geneeskunde",
    "sg:phone":"+31 30 271 4500",
    "sg:postcode":"3514 CM",
    "sg:province":"Utrecht",
    "wof:name":"Fysiotherapie Wolters",
    "wof:placetype":"venue"
},
  "geometry": {"coordinates":[5.115509,52.100624],"type":"Point"}
}