{
  "type": "Feature",
  "properties": {
    "addr:full":"Nikadel 7A De Koog Noord-Holland 1796 BP",
    "addr:housenumber":"7a",
    "addr:postcode":"1796 bp",
    "addr:street":"Nikadel",
    "iso:country":"NL",
    "sg:address":"Nikadel 7A",
    "sg:city":"De Koog",
    "sg:classifiers":[
        {
            "category":"Travel",
            "subcategory":"Hotels & Motels",
            "type":"Entertainment"
        }
    ],
    "sg:phone":"+31 222 317 906",
    "sg:postcode":"1796 BP",
    "sg:province":"Noord-Holland",
    "wof:name":"Koog, De",
    "wof:placetype":"venue"
},
  "geometry": {"coordinates":[4.763697,53.099857],"type":"Point"}
}