{
  "type": "Feature",
  "properties": {
    "addr:full":"Rijstgras 11 Rotterdam Zuid-Holland 3068 CL",
    "addr:housenumber":"11",
    "addr:postcode":"3068",
    "addr:street":"Rijstgras",
    "iso:country":"NL",
    "sg:address":"Rijstgras 11",
    "sg:city":"Rotterdam",
    "sg:orig_category":"Wasserettes, Stomerijen And Reiniging",
    "sg:phone":"+31 10 286 7646",
    "sg:postcode":"3068 CL",
    "sg:province":"Zuid-Holland",
    "wof:name":"Azs Nederland Regio West",
    "wof:placetype":"venue"
},
  "geometry": {"coordinates":[4.5446028709,51.9552993774],"type":"Point"}
}