{
  "type": "Feature",
  "properties": {
    "addr:full":"Vryenbansestr 9 Nootdorp Zuid-Holland 2631 BD",
    "addr:housenumber":"9",
    "addr:postcode":"2631 bd",
    "addr:street":"Vryenbansestr",
    "iso:country":"NL",
    "sg:address":"Vryenbansestr 9",
    "sg:city":"Nootdorp",
    "sg:orig_category":"Onderhoudswerken",
    "sg:phone":"+31 15 310 5435",
    "sg:postcode":"2631 BD",
    "sg:province":"Zuid-Holland",
    "wof:name":"Burgy, J P",
    "wof:placetype":"venue"
},
  "geometry": {"coordinates":[4.392025,52.042702],"type":"Point"}
}