{
  "type": "Feature",
  "properties": {
    "addr:full":"Wildwg 2 Huizen Noord-Holland 1272 AK",
    "addr:housenumber":"2",
    "addr:postcode":"1272 ak",
    "addr:street":"Wildwg",
    "iso:country":"NL",
    "sg:address":"Wildwg 2",
    "sg:city":"Huizen",
    "sg:orig_category":"Psychotherapeuten",
    "sg:phone":"+31 35 524 7722",
    "sg:postcode":"1272 AK",
    "sg:province":"Noord-Holland",
    "wof:name":"Ringrose, I",
    "wof:placetype":"venue"
},
  "geometry": {"coordinates":[5.218752,52.29768],"type":"Point"}
}