{
  "type": "Feature",
  "properties": {
    "addr:full":"Scheldestr 58 Vlissingen Zeeland 4381 RV",
    "addr:housenumber":"58",
    "addr:postcode":"4381 rv",
    "addr:street":"Scheldestr",
    "iso:country":"NL",
    "sg:address":"Scheldestr 58",
    "sg:city":"Vlissingen",
    "sg:classifiers":[
        {
            "category":"Food & Beverages",
            "subcategory":"Bakery",
            "type":"Retail Goods"
        }
    ],
    "sg:phone":"+31 118 412 473",
    "sg:postcode":"4381 RV",
    "sg:province":"Zeeland",
    "sg:tags":[
        "brood",
        "en",
        "banket"
    ],
    "wof:name":"Kop, J B Van De",
    "wof:placetype":"venue"
},
  "geometry": {"coordinates":[3.573361,51.448017],"type":"Point"}
}