{
  "type": "Feature",
  "properties": {
    "addr:full":"Beulakerwg 129 Giethoorn NL.08 8355 AE",
    "addr:housenumber":"129;nl.08",
    "addr:postcode":"8355 ae",
    "iso:country":"NL",
    "sg:address":"Beulakerwg 129",
    "sg:city":"Giethoorn",
    "sg:orig_category":"Montagebedrijven",
    "sg:phone":"+31 521 361 786",
    "sg:postcode":"8355 AE",
    "sg:province":"NL.08",
    "wof:name":"Moes",
    "wof:placetype":"venue"
},
  "geometry": {"coordinates":[6.077595,52.73391],"type":"Point"}
}