{
  "type": "Feature",
  "properties": {
    "addr:full":"Zonnebloem 9 Krimpen A/D Ijssel South Holland 2925 EZ",
    "addr:housenumber":"9;a / d",
    "addr:postcode":"2925 ez",
    "addr:street":"Zonnebloem;Ijssel South",
    "iso:country":"NL",
    "sg:address":"Zonnebloem 9",
    "sg:city":"Krimpen A/D Ijssel",
    "sg:orig_category":"Verhuur Diversen",
    "sg:phone":"+31 180 522 529",
    "sg:postcode":"2925 EZ",
    "sg:province":"South Holland",
    "wof:name":"Vof W.F. Van Kralingen",
    "wof:placetype":"venue"
},
  "geometry": {"coordinates":[4.623388,51.922729],"type":"Point"}
}