{
  "type": "Feature",
  "properties": {
    "addr:full":"Groenhovenstr 5 Leiden South Holland 2311 BT",
    "addr:housenumber":"5",
    "addr:postcode":"2311 bt",
    "addr:street":"Groenhovenstr",
    "iso:country":"NL",
    "sg:address":"Groenhovenstr 5",
    "sg:city":"Leiden",
    "sg:orig_category":"Adviesbureaus Bouwkunde",
    "sg:phone":"+31 71 566 0040",
    "sg:postcode":"2311 BT",
    "sg:province":"South Holland",
    "wof:name":"Bb",
    "wof:placetype":"venue"
},
  "geometry": {"coordinates":[4.481434,52.1562],"type":"Point"}
}