{
  "type": "Feature",
  "properties": {
    "iso:country":"NL",
    "sg:address":"C Ritsemastr 53",
    "sg:city":"Pynacker",
    "sg:orig_category":"Onroerende Goederen",
    "sg:phone":"+31 15 361 0547",
    "sg:postcode":"2642 CE",
    "sg:province":"Zuid-Holland",
    "wof:name":"Global Invest Og",
    "wof:placetype":"venue"
},
  "geometry": {"coordinates":[4.445986,52.010113],"type":"Point"}
}