{
  "type": "Feature",
  "properties": {
    "iso:country":"NL",
    "sg:address":"Bovenweg 61",
    "sg:city":"Nunspeet",
    "sg:orig_category":"Farmaceutische Producten Gh",
    "sg:phone":"+31 341 256 306",
    "sg:postcode":"8072 PG",
    "sg:province":"Gelderland",
    "wof:name":"H. Vinke",
    "wof:placetype":"venue"
},
  "geometry": {"coordinates":[5.800611,52.394005],"type":"Point"}
}