{
  "type": "Feature",
  "properties": {
    "addr:full":"Postbus 52 Geldrop North Brabant 5660 AB",
    "addr:housenumber":"52",
    "addr:postcode":"5660 ab",
    "addr:street":"Postbus",
    "iso:country":"NL",
    "sg:address":"Postbus 52",
    "sg:city":"Geldrop",
    "sg:orig_category":"Projectinrichting",
    "sg:phone":"+31 40 226 0428",
    "sg:postcode":"5660 AB",
    "sg:province":"North Brabant",
    "wof:name":"Spaan Projectstoffering",
    "wof:placetype":"venue"
},
  "geometry": {"coordinates":[5.55945,51.423519],"type":"Point"}
}