{
  "type": "Feature",
  "properties": {
    "iso:country":"NL",
    "sg:address":"Zuiderpln 31",
    "sg:city":"Leeuwarden",
    "sg:orig_category":"Makelaars En Adviseurs Onroerende Goederen",
    "sg:phone":"+31 58 216 0500",
    "sg:postcode":"8911 AN",
    "sg:province":"Provincie Friesland",
    "sg:website":"http://www.bosmadewitte.nl",
    "wof:name":"Bosma De Witte",
    "wof:placetype":"venue"
},
  "geometry": {"coordinates":[5.796899,53.197815],"type":"Point"}
}