{
  "type": "Feature",
  "properties": {
    "addr:full":"Beekstr 28 Meerssen Limburg 6231 LG",
    "addr:housenumber":"28",
    "addr:postcode":"6231 lg",
    "addr:street":"Beekstr",
    "iso:country":"NL",
    "sg:address":"Beekstr 28",
    "sg:city":"Meerssen",
    "sg:orig_category":"Meubelen",
    "sg:phone":"+31 43 364 3595",
    "sg:postcode":"6231 LG",
    "sg:province":"Limburg",
    "wof:name":"Farfalla, Interieur",
    "wof:placetype":"venue"
},
  "geometry": {"coordinates":[5.755373,50.884995],"type":"Point"}
}