{
  "type": "Feature",
  "properties": {
    "addr:full":"C J Conynstr 6A Volendam Noord-Holland 1131 DZ",
    "addr:housenumber":"6a",
    "addr:postcode":"1131 dz",
    "addr:street":"C;Conynstr",
    "iso:country":"NL",
    "sg:address":"C J Conynstr 6A",
    "sg:city":"Volendam",
    "sg:orig_category":"Verenigingen En Stichtingen",
    "sg:phone":"+31 299 367 471",
    "sg:postcode":"1131 DZ",
    "sg:province":"Noord-Holland",
    "wof:name":"Steun Rk Begrafenisfonds, Sticht",
    "wof:placetype":"venue"
},
  "geometry": {"coordinates":[5.071785,52.496269],"type":"Point"}
}