{
  "type": "Feature",
  "properties": {
    "addr:full":"Omnium 1 Krimpen Ad Yssel Zuid-Holland 2924 XJ",
    "addr:housenumber":"1",
    "addr:postcode":"2924 xj",
    "addr:street":"Omnium",
    "iso:country":"NL",
    "sg:address":"Omnium 1",
    "sg:city":"Krimpen Ad Yssel",
    "sg:orig_category":"Apotheken",
    "sg:phone":"+31 180 517 833",
    "sg:postcode":"2924 XJ",
    "sg:province":"Zuid-Holland",
    "wof:name":"Geurts Bv",
    "wof:placetype":"venue"
},
  "geometry": {"coordinates":[4.611803,51.921425],"type":"Point"}
}