{
  "type": "Feature",
  "properties": {
    "iso:country":"NL",
    "sg:address":"Koopliedenweg 5",
    "sg:city":"Barendrecht",
    "sg:orig_category":"Fruit And Groenten Gh",
    "sg:phone":"+31 180 614 766",
    "sg:postcode":"2991 LN",
    "sg:province":"South Holland",
    "wof:name":"Van Dijk Barendrecht",
    "wof:placetype":"venue"
},
  "geometry": {"coordinates":[4.559117,51.857021],"type":"Point"}
}