{
  "type": "Feature",
  "properties": {
    "addr:full":"Nyverheidsln 28 Veldhoven North Brabant 5506 EE",
    "addr:housenumber":"28",
    "addr:postcode":"5506 ee",
    "addr:street":"Nyverheidsln",
    "iso:country":"NL",
    "sg:address":"Nyverheidsln 28",
    "sg:city":"Veldhoven",
    "sg:orig_category":"Voetbalverenigingen",
    "sg:phone":"+31 40 253 0322",
    "sg:postcode":"5506 EE",
    "sg:province":"North Brabant",
    "wof:name":"Fc Elisa",
    "wof:placetype":"venue"
},
  "geometry": {"coordinates":[5.404554,51.421745],"type":"Point"}
}