{
  "type": "Feature",
  "properties": {
    "iso:country":"NL",
    "sg:address":"Maansteen 12",
    "sg:city":"Eindhoven",
    "sg:orig_category":"Adviesbureaus Gezondheidszorg",
    "sg:phone":"+31 40 292 6495",
    "sg:postcode":"5629 HN",
    "sg:province":"Noord-Brabant",
    "sg:website":"http://www.ejjgmeulenbergadvies.com",
    "wof:name":"Meulenbrug Bv, E J J G",
    "wof:placetype":"venue"
},
  "geometry": {"coordinates":[5.467494,51.484699],"type":"Point"}
}