{
  "type": "Feature",
  "properties": {
    "addr:full":"Gemeent 1 Delwynen Gelderland 5316 NG",
    "addr:housenumber":"1",
    "addr:postcode":"5316 ng",
    "addr:street":"Gemeent;Gelderland",
    "iso:country":"NL",
    "sg:address":"Gemeent 1",
    "sg:city":"Delwynen",
    "sg:orig_category":"Administratie- En Boekhoudkantoren",
    "sg:phone":"+31 418 552 656",
    "sg:postcode":"5316 NG",
    "sg:province":"Gelderland",
    "wof:name":"Eck, Van",
    "wof:placetype":"venue"
},
  "geometry": {"coordinates":[5.187073,51.77124],"type":"Point"}
}