{
  "type": "Feature",
  "properties": {
    "addr:full":"Zandkamp 6 Alphen Gld Gelderland 6626 KV",
    "addr:housenumber":"6",
    "addr:postcode":"6626 kv",
    "addr:street":"Zandkamp;Gld Gelderland",
    "iso:country":"NL",
    "sg:address":"Zandkamp 6",
    "sg:city":"Alphen Gld",
    "sg:orig_category":"Geluidsinstallaties - Verhuur",
    "sg:phone":"+31 487 561 314",
    "sg:postcode":"6626 KV",
    "sg:province":"Gelderland",
    "sg:website":"http://www.storysound.nl",
    "wof:name":"Story Sound",
    "wof:placetype":"venue"
},
  "geometry": {"coordinates":[5.47184,51.82579],"type":"Point"}
}