{
  "type": "Feature",
  "properties": {
    "addr:full":"Thorbeckestr 20 Huizen North Holland 1272 HC",
    "addr:housenumber":"20",
    "addr:postcode":"1272 hc",
    "addr:street":"Thorbeckestr",
    "iso:country":"NL",
    "sg:address":"Thorbeckestr 20",
    "sg:city":"Huizen",
    "sg:orig_category":"Accountants - Administratie- Consulenten En -Kantoren",
    "sg:phone":"+31 35 525 8711",
    "sg:postcode":"1272 HC",
    "sg:province":"North Holland",
    "wof:name":"Adcount",
    "wof:placetype":"venue"
},
  "geometry": {"coordinates":[5.231722,52.291447],"type":"Point"}
}