{
  "type": "Feature",
  "properties": {
    "addr:full":"Wold 1573 Lelystad Flevoland 8225 AG",
    "addr:postcode":"1573;8225",
    "addr:street":"Wold;Flevoland",
    "iso:country":"NL",
    "sg:address":"Wold 1573",
    "sg:city":"Lelystad",
    "sg:orig_category":"Scholen Voor Basisonderwijs",
    "sg:phone":"+31 320 243 434",
    "sg:postcode":"8225 AG",
    "sg:province":"Flevoland",
    "wof:name":"Driemaster Openb, De",
    "wof:placetype":"venue"
},
  "geometry": {"coordinates":[5.491515,52.507164],"type":"Point"}
}