{
  "type": "Feature",
  "properties": {
    "iso:country":"NL",
    "sg:address":"Noorderstr 29",
    "sg:city":"Emmen",
    "sg:orig_category":"Warenhuizen",
    "sg:phone":"+31 591 659 356",
    "sg:postcode":"7811 AK",
    "sg:province":"Drenthe",
    "wof:name":"Blokker",
    "wof:placetype":"venue"
},
  "geometry": {"coordinates":[6.8930501938,52.7875137329],"type":"Point"}
}