{
  "type": "Feature",
  "properties": {
    "addr:full":"Herfterlaan 50 Zwolle NL.08 8026 RB",
    "addr:housenumber":"50",
    "addr:postcode":"8026 rb",
    "addr:street":"Herfterlaan",
    "iso:country":"NL",
    "sg:address":"Herfterlaan 50",
    "sg:city":"Zwolle",
    "sg:orig_category":"Goederenvervoer Over De Weg",
    "sg:phone":"+31 529 401 447",
    "sg:postcode":"8026 RB",
    "sg:province":"NL.08",
    "wof:name":"Transportbedrijf Firma A. Van Krevel En",
    "wof:placetype":"venue"
},
  "geometry": {"coordinates":[6.164089,52.49868],"type":"Point"}
}