{
  "type": "Feature",
  "properties": {
    "addr:full":"De Waag 5 Almelo Overijssel 7607 HP",
    "addr:housenumber":"5",
    "addr:postcode":"7607 hp",
    "addr:street":"De Waag",
    "iso:country":"NL",
    "sg:address":"De Waag 5",
    "sg:city":"Almelo",
    "sg:orig_category":"Watersport-, Sport- And Kampeerbenodigdheden Verhuur",
    "sg:phone":"+31 546 822 110",
    "sg:postcode":"7607 HP",
    "sg:province":"Overijssel",
    "wof:name":"Rijwielstalling De Markt",
    "wof:placetype":"venue"
},
  "geometry": {"coordinates":[6.6639461517,52.3548812866],"type":"Point"}
}