{
  "type": "Feature",
  "properties": {
    "addr:full":"Y Schuitmakerstr 15 Franeker Friesland 8802 ZR",
    "addr:housenumber":"15",
    "addr:postcode":"8802 zr",
    "iso:country":"NL",
    "sg:address":"Y Schuitmakerstr 15",
    "sg:city":"Franeker",
    "sg:orig_category":"Satellietontvangst- En Antenne-Installaties",
    "sg:phone":"+31 517 390 720",
    "sg:postcode":"8802 ZR",
    "sg:province":"Friesland",
    "wof:name":"Waard, De",
    "wof:placetype":"venue"
},
  "geometry": {"coordinates":[5.558854,53.19268],"type":"Point"}
}