{
  "type": "Feature",
  "properties": {
    "addr:full":"Postbus 37133 Rotterdam 3005 LC",
    "addr:housenumber":"37133",
    "addr:postcode":"3005 lc",
    "addr:street":"Postbus",
    "iso:country":"NL",
    "sg:address":"Postbus 37133",
    "sg:city":"Rotterdam",
    "sg:orig_category":"Postorderbedrijven",
    "sg:phone":"+31 10 465 7861",
    "sg:postcode":"3005 LC",
    "wof:name":"Wisbrun, R",
    "wof:placetype":"venue"
},
  "geometry": {"coordinates":[4.47075,51.922619],"type":"Point"}
}