{
  "type": "Feature",
  "properties": {
    "iso:country":"NL",
    "sg:address":"Ruiterswg 35",
    "sg:city":"Hilversum",
    "sg:orig_category":"Webdesign Bureaus",
    "sg:phone":"+31 35 672 0322",
    "sg:postcode":"1211 KT",
    "sg:province":"North Holland",
    "wof:name":"Zeezicht",
    "wof:placetype":"venue"
},
  "geometry": {"coordinates":[5.1726341248,52.2216300964],"type":"Point"}
}