{
  "type": "Feature",
  "properties": {
    "addr:full":"De Weiert 40A Emmen Provincie Drenthe 7811 BL",
    "addr:housenumber":"40a;7811 bl",
    "addr:street":"De Weiert;Provincie Drenthe",
    "iso:country":"NL",
    "sg:address":"De Weiert 40A",
    "sg:city":"Emmen",
    "sg:orig_category":"Boeken En Tijdschriften",
    "sg:phone":"+31 591 612 255",
    "sg:postcode":"7811 BL",
    "sg:province":"Provincie Drenthe",
    "sg:website":"http://www.bruna.nl",
    "wof:name":"Bruna",
    "wof:placetype":"venue"
},
  "geometry": {"coordinates":[6.89298,52.782429],"type":"Point"}
}