{
  "type": "Feature",
  "properties": {
    "addr:full":"Dorpsdk 155 Rhoon South Holland 3161 CB",
    "addr:housenumber":"155",
    "addr:postcode":"3161 cb",
    "iso:country":"NL",
    "sg:address":"Dorpsdk 155",
    "sg:city":"Rhoon",
    "sg:orig_category":"Banken",
    "sg:phone":"+31 180 696 100",
    "sg:postcode":"3161 CB",
    "sg:province":"South Holland",
    "sg:website":"http://www.rabobank.nl",
    "wof:name":"Rabobank",
    "wof:placetype":"venue"
},
  "geometry": {"coordinates":[4.420211,51.855591],"type":"Point"}
}