{
  "type": "Feature",
  "properties": {
    "addr:full":"Keulsebaan 34 Neerkant Noord-Brabant 5758 RW",
    "addr:housenumber":"34",
    "addr:postcode":"5758 rw",
    "addr:street":"Keulsebaan",
    "iso:country":"NL",
    "sg:address":"Keulsebaan 34",
    "sg:city":"Neerkant",
    "sg:orig_category":"Loodgieterswerk, Verwarming And Sanitaire Installaties",
    "sg:phone":"+31 77 466 2278",
    "sg:postcode":"5758 RW",
    "sg:province":"Noord-Brabant",
    "wof:name":"Wim Hoefnagels Bv",
    "wof:placetype":"venue"
},
  "geometry": {"coordinates":[5.865622,51.361675],"type":"Point"}
}