{
  "type": "Feature",
  "properties": {
    "addr:full":"Molenwg 25 Haarle Gem Hellend Overijssel 7448 RC",
    "addr:housenumber":"25",
    "addr:postcode":"7448 rc",
    "addr:street":"Molenwg;Overijssel",
    "iso:country":"NL",
    "sg:address":"Molenwg 25",
    "sg:city":"Haarle Gem Hellend",
    "sg:orig_category":"Verenigingen En Stichtingen",
    "sg:phone":"+31 548 595 348",
    "sg:postcode":"7448 RC",
    "sg:province":"Overijssel",
    "wof:name":"Dorpshuis Haarle, Sticht",
    "wof:placetype":"venue"
},
  "geometry": {"coordinates":[6.383715,52.358818],"type":"Point"}
}