{
  "type": "Feature",
  "properties": {
    "addr:full":"Herbenusstr 136 Maastricht Limburg 6211 RH",
    "addr:housenumber":"136",
    "addr:postcode":"6211 rh",
    "iso:country":"NL",
    "sg:address":"Herbenusstr 136",
    "sg:city":"Maastricht",
    "sg:orig_category":"Beeldende Kunstenaars",
    "sg:phone":"+31 43 321 2416",
    "sg:postcode":"6211 RH",
    "sg:province":"Limburg",
    "wof:name":"Vos-Duffhaus, M",
    "wof:placetype":"venue"
},
  "geometry": {"coordinates":[5.680538,50.851051],"type":"Point"}
}