{
  "type": "Feature",
  "properties": {
    "addr:full":"W De Withln 1 Bennebroek North Holland 2121 XE",
    "addr:housenumber":"1",
    "addr:postcode":"2121 xe",
    "addr:street":"W De Withln",
    "iso:country":"NL",
    "sg:address":"W De Withln 1",
    "sg:city":"Bennebroek",
    "sg:orig_category":"Bejaarden - Verzorgingstehuizen",
    "sg:phone":"+31 23 584 6047",
    "sg:postcode":"2121 XE",
    "sg:province":"North Holland",
    "wof:name":"Zorgcontact, Sticht",
    "wof:placetype":"venue"
},
  "geometry": {"coordinates":[4.593208,52.32214],"type":"Point"}
}