{
  "type": "Feature",
  "properties": {
    "addr:full":"Binnenban 168 Hoogvliet Rt South Holland 3191 CL",
    "addr:housenumber":"168",
    "addr:postcode":"3191",
    "addr:street":"Binnenban;Rt South",
    "iso:country":"NL",
    "sg:address":"Binnenban 168",
    "sg:city":"Hoogvliet Rt",
    "sg:orig_category":"Opticiens",
    "sg:phone":"+31 10 416 7104",
    "sg:postcode":"3191 CL",
    "sg:province":"South Holland",
    "wof:name":"Langstraat Optiek Bv",
    "wof:placetype":"venue"
},
  "geometry": {"coordinates":[4.3564271927,51.8652572632],"type":"Point"}
}