{
  "type": "Feature",
  "properties": {
    "addr:full":"Koninginneweg 72 Kortenhoef Noord-Holland 1241 CW",
    "addr:housenumber":"72",
    "addr:postcode":"1241 cw",
    "addr:street":"Koninginneweg",
    "iso:country":"NL",
    "sg:address":"Koninginneweg 72",
    "sg:city":"Kortenhoef",
    "sg:classifiers":[
        {
            "category":"Bakery",
            "type":"Food & Drink"
        }
    ],
    "sg:phone":"+31 35 656 3958",
    "sg:postcode":"1241 CW",
    "sg:province":"Noord-Holland",
    "sg:tags":[
        "brood",
        "banket"
    ],
    "wof:name":"Jolanda",
    "wof:placetype":"venue"
},
  "geometry": {"coordinates":[5.1205,52.247013],"type":"Point"}
}