{
  "type": "Feature",
  "properties": {
    "addr:full":"Nicolaas Beetsstraat 26 Almelo Overijssel 7606 BE",
    "addr:housenumber":"26",
    "addr:postcode":"7606",
    "addr:street":"Nicolaas Beetsstraat",
    "iso:country":"NL",
    "sg:address":"Nicolaas Beetsstraat 26",
    "sg:city":"Almelo",
    "sg:orig_category":"Meubelzaken, Woning- And Keukeninrichting",
    "sg:phone":"+31 546 819 717",
    "sg:postcode":"7606 BE",
    "sg:province":"Overijssel",
    "wof:name":"Antiekhandel Drenth",
    "wof:placetype":"venue"
},
  "geometry": {"coordinates":[6.65914,52.342587],"type":"Point"}
}