{
  "type": "Feature",
  "properties": {
    "iso:country":"NL",
    "sg:address":"Noordkd 17",
    "sg:city":"Spykenisse",
    "sg:orig_category":"Discotheken",
    "sg:phone":"+31 181 613 109",
    "sg:postcode":"3201 AZ",
    "sg:province":"Zuid-Holland",
    "sg:website":"http://www.y-land.nl",
    "wof:name":"Beach Club Y-Land",
    "wof:placetype":"venue"
},
  "geometry": {"coordinates":[4.325045,51.849525],"type":"Point"}
}