{
  "type": "Feature",
  "properties": {
    "addr:full":"Haatlanderdk 18 Kampen Overijssel 8263 AR",
    "addr:housenumber":"18",
    "addr:postcode":"8263",
    "addr:street":"Haatlanderdk",
    "iso:country":"NL",
    "sg:address":"Haatlanderdk 18",
    "sg:city":"Kampen",
    "sg:orig_category":"Banden",
    "sg:phone":"+31 38 331 5455",
    "sg:postcode":"8263 AR",
    "sg:province":"Overijssel",
    "sg:website":"http://www.euromaster.com",
    "wof:name":"Euromaster",
    "wof:placetype":"venue"
},
  "geometry": {"coordinates":[-92.131348,34.751888],"type":"Point"}
}