{
  "type": "Feature",
  "properties": {
    "addr:full":"Gruizenstraat 32 Sittard Limburg 6131 EH",
    "addr:housenumber":"32",
    "addr:postcode":"6131 eh",
    "addr:street":"Gruizenstraat",
    "iso:country":"NL",
    "sg:address":"Gruizenstraat 32",
    "sg:city":"Sittard",
    "sg:orig_category":"Zuivelproducten",
    "sg:phone":"+31 46 451 8075",
    "sg:postcode":"6131 EH",
    "sg:province":"Limburg",
    "wof:name":"Kps Bude Bv",
    "wof:placetype":"venue"
},
  "geometry": {"coordinates":[5.869324,50.996727],"type":"Point"}
}