{
  "type": "Feature",
  "properties": {
    "addr:full":"Stikkelwaard 2 Alkmaar Noord-Holland 1824 VK",
    "addr:housenumber":"2",
    "addr:postcode":"1824 vk",
    "addr:street":"Stikkelwaard",
    "iso:country":"NL",
    "sg:address":"Stikkelwaard 2",
    "sg:city":"Alkmaar",
    "sg:orig_category":"Gespecialiseerde Bouw",
    "sg:phone":"+31 72 562 2957",
    "sg:postcode":"1824 VK",
    "sg:province":"Noord-Holland",
    "wof:name":"Ben Peereboom",
    "wof:placetype":"venue"
},
  "geometry": {"coordinates":[4.752706,52.64357],"type":"Point"}
}