{
  "type": "Feature",
  "properties": {
    "addr:full":"Luxemburgstraat 7 'S Gravenhage South Holland 2552 RA",
    "addr:housenumber":"7 '",
    "addr:postcode":"2552 ra",
    "addr:street":"Luxemburgstraat",
    "iso:country":"NL",
    "sg:address":"Luxemburgstraat 7",
    "sg:city":"'S Gravenhage",
    "sg:classifiers":[
        {
            "category":"Education",
            "subcategory":"Preschool",
            "type":"Public Place"
        }
    ],
    "sg:phone":"+31 70 397 2259",
    "sg:postcode":"2552 RA",
    "sg:province":"South Holland",
    "sg:tags":[
        "kleuteronderwijs",
        "basis-"
    ],
    "wof:name":"Peuterspeelzaal 'T Peenbuikertje",
    "wof:placetype":"venue"
},
  "geometry": {"coordinates":[4.23807,52.0536],"type":"Point"}
}