{
  "type": "Feature",
  "properties": {
    "addr:full":"St Janstr 32 Oosterhout Nb Noord-Brabant 4901 LT",
    "addr:housenumber":"32",
    "addr:postcode":"4901 lt",
    "iso:country":"NL",
    "sg:address":"St Janstr 32",
    "sg:city":"Oosterhout Nb",
    "sg:orig_category":"Beeldende Kunstenaars",
    "sg:phone":"+31 162 452 885",
    "sg:postcode":"4901 LT",
    "sg:province":"Noord-Brabant",
    "wof:name":"Clema Van Bekhoven",
    "wof:placetype":"venue"
},
  "geometry": {"coordinates":[4.857942,51.645771],"type":"Point"}
}