{
  "type": "Feature",
  "properties": {
    "iso:country":"NL",
    "sg:address":"Boulev Bankert 284",
    "sg:city":"Vlissingen",
    "sg:orig_category":"Kappers",
    "sg:phone":"+31 118 411 472",
    "sg:postcode":"4382 AC",
    "sg:province":"Zeeland",
    "wof:name":"Jacco",
    "wof:placetype":"venue"
},
  "geometry": {"coordinates":[3.5639150143,51.4462203979],"type":"Point"}
}