{
  "type": "Feature",
  "properties": {
    "iso:country":"NL",
    "sg:address":"Havenplein 2",
    "sg:city":"Zierikzee",
    "sg:classifiers":[
        {
            "category":"Food & Beverages",
            "subcategory":"Fruits & Vegetables",
            "type":"Retail Goods"
        }
    ],
    "sg:phone":"+31 111 412 884",
    "sg:postcode":"4301 CB",
    "sg:province":"Zeeland",
    "sg:tags":[
        "groenten"
    ],
    "wof:name":"Groente- En Fruithandel Legemaate",
    "wof:placetype":"venue"
},
  "geometry": {"coordinates":[3.921595,51.649303],"type":"Point"}
}