{
  "type": "Feature",
  "properties": {
    "addr:full":"Hoofdweg 523 Hoofddorp Noord-Holland 2131 MT",
    "addr:housenumber":"523;2131",
    "addr:street":"Hoofdweg;Mt",
    "iso:country":"NL",
    "sg:address":"Hoofdweg 523",
    "sg:city":"Hoofddorp",
    "sg:orig_category":"Granen, Zaden And Diervoeders Gh",
    "sg:phone":"+31 23 561 2600",
    "sg:postcode":"2131 MT",
    "sg:province":"Noord-Holland",
    "wof:name":"Zas International Agriculture Bv",
    "wof:placetype":"venue"
},
  "geometry": {"coordinates":[4.707423,52.316277],"type":"Point"}
}