{
  "type": "Feature",
  "properties": {
    "addr:full":"Kerkwg 9 Zeist Utrecht 3701 HD",
    "addr:housenumber":"9",
    "addr:postcode":"3701 hd",
    "addr:street":"Kerkwg",
    "iso:country":"NL",
    "sg:address":"Kerkwg 9",
    "sg:city":"Zeist",
    "sg:orig_category":"Huishoudelijke Apparaten En Artikelen",
    "sg:phone":"+31 30 691 9400",
    "sg:postcode":"3701 HD",
    "sg:province":"Utrecht",
    "wof:name":"Au Bain Marie",
    "wof:placetype":"venue"
},
  "geometry": {"coordinates":[5.24387,52.08548],"type":"Point"}
}