{
  "type": "Feature",
  "properties": {
    "iso:country":"NL",
    "sg:address":"Vlielandln 12",
    "sg:city":"Son",
    "sg:orig_category":"Sportverenigingen En Ontspannings- Verenigingen",
    "sg:phone":"+31 499 471 097",
    "sg:postcode":"5691 ZK",
    "sg:province":"Noord-Brabant",
    "wof:name":"Htc Son",
    "wof:placetype":"venue"
},
  "geometry": {"coordinates":[-101.937622,35.189621],"type":"Point"}
}