{
  "type": "Feature",
  "properties": {
    "addr:full":"Poststraat 15 Tilburg Noord-Brabant 5038 DG",
    "addr:housenumber":"15",
    "addr:postcode":"5038 dg",
    "addr:street":"Poststraat",
    "iso:country":"NL",
    "sg:address":"Poststraat 15",
    "sg:city":"Tilburg",
    "sg:orig_category":"Loodgieterswerk, Verwarming And Sanitaire Installaties",
    "sg:phone":"+31 13 543 0829",
    "sg:postcode":"5038 DG",
    "sg:province":"Noord-Brabant",
    "wof:name":"Peer",
    "wof:placetype":"venue"
},
  "geometry": {"coordinates":[5.085525,51.558987],"type":"Point"}
}