{
  "type": "Feature",
  "properties": {
    "iso:country":"NL",
    "sg:address":"Poststraat 15",
    "sg:city":"Tilburg",
    "sg:orig_category":"Loodgieterswerk, Verwarming And Sanitaire Installaties",
    "sg:phone":"+31 13 543 0829",
    "sg:postcode":"5038 DG",
    "sg:province":"Noord-Brabant",
    "wof:name":"Peer",
    "wof:placetype":"venue"
},
  "geometry": {"coordinates":[5.085525,51.558987],"type":"Point"}
}