{
  "type": "Feature",
  "properties": {
    "addr:full":"Rivium 1E Str 61 Capelle Ad Yssel Zuid-Holland 2909 LE",
    "addr:housenumber":"61;2909",
    "addr:postcode":"le",
    "addr:street":"Rivium 1E Str",
    "iso:country":"NL",
    "sg:address":"Rivium 1E Str 61",
    "sg:city":"Capelle Ad Yssel",
    "sg:orig_category":"Projectontwikkeling",
    "sg:phone":"+31 10 288 0170",
    "sg:postcode":"2909 LE",
    "sg:province":"Zuid-Holland",
    "wof:name":"Baas En Groen Bv",
    "wof:placetype":"venue"
},
  "geometry": {"coordinates":[4.543547,51.91256],"type":"Point"}
}