{
  "type": "Feature",
  "properties": {
    "iso:country":"NL",
    "sg:address":"Riek Kuiperssingel 9",
    "sg:city":"Pijnacker",
    "sg:orig_category":"Goederenvervoer Over De Weg",
    "sg:phone":"+31 15 369 6888",
    "sg:postcode":"2642 DA",
    "sg:province":"Zuid-Holland",
    "wof:name":"A.J. Notenboom Transport",
    "wof:placetype":"venue"
},
  "geometry": {"coordinates":[4.444474,52.016132],"type":"Point"}
}