{
  "type": "Feature",
  "properties": {
    "iso:country":"NL",
    "sg:address":"Wieldrechtsezeedk 87",
    "sg:city":"Dordrecht",
    "sg:orig_category":"Oud Metaal",
    "sg:phone":"+31 78 618 3311",
    "sg:postcode":"3316 EN",
    "sg:province":"Zuid-Holland",
    "wof:name":"Kirchyunger, A V",
    "wof:placetype":"venue"
},
  "geometry": {"coordinates":[4.6350941658,51.7612533569],"type":"Point"}
}