{
  "type": "Feature",
  "properties": {
    "addr:full":"Venwg 5 Brunssum Limburg 6445 XS",
    "addr:housenumber":"5",
    "addr:postcode":"6445 xs",
    "addr:street":"Venwg",
    "iso:country":"NL",
    "sg:address":"Venwg 5",
    "sg:city":"Brunssum",
    "sg:orig_category":"Horloges En Klokken",
    "sg:phone":"+31 45 527 4048",
    "sg:postcode":"6445 XS",
    "sg:province":"Limburg",
    "wof:name":"Euro Clocks",
    "wof:placetype":"venue"
},
  "geometry": {"coordinates":[5.979764,50.93681],"type":"Point"}
}