{
  "type": "Feature",
  "properties": {
    "addr:full":"Ypemaheerd 4 Groningen Groningen 9736 MA",
    "addr:housenumber":"4",
    "addr:postcode":"9736 ma",
    "addr:street":"Ypemaheerd",
    "iso:country":"NL",
    "sg:address":"Ypemaheerd 4",
    "sg:city":"Groningen",
    "sg:orig_category":"Cafetaria'S",
    "sg:phone":"+31 50 541 8519",
    "sg:postcode":"9736 MA",
    "sg:province":"Groningen",
    "wof:name":"Smullemaheerd",
    "wof:placetype":"venue"
},
  "geometry": {"coordinates":[6.600161,53.248688],"type":"Point"}
}