{
  "type": "Feature",
  "properties": {
    "addr:full":"Willem Fenengastraat 2 Amsterdam North Holland 1096 BN",
    "addr:housenumber":"2",
    "addr:postcode":"1096 bn",
    "addr:street":"Willem Fenengastraat",
    "iso:country":"NL",
    "sg:address":"Willem Fenengastraat 2",
    "sg:city":"Amsterdam",
    "sg:orig_category":"Kantoorartikelen",
    "sg:phone":"+31 20 561 2600",
    "sg:postcode":"1096 BN",
    "sg:province":"North Holland",
    "wof:name":"Office Centre",
    "wof:placetype":"venue"
},
  "geometry": {"coordinates":[4.9195132256,52.3348731995],"type":"Point"}
}