{
  "type": "Feature",
  "properties": {
    "addr:full":"J Obrechtln 38 Hoofddorp Noord-Holland 2132 KV",
    "addr:housenumber":"38",
    "addr:postcode":"2132 kv",
    "iso:country":"NL",
    "sg:address":"J Obrechtln 38",
    "sg:city":"Hoofddorp",
    "sg:orig_category":"Verhuur",
    "sg:phone":"+31 23 562 1022",
    "sg:postcode":"2132 KV",
    "sg:province":"Noord-Holland",
    "wof:name":"Koker Bv, J H De",
    "wof:placetype":"venue"
},
  "geometry": {"coordinates":[4.708549,52.306202],"type":"Point"}
}