{
  "type": "Feature",
  "properties": {
    "addr:full":"Brandersmolenstr 29 Almere Flevoland 1333 BX",
    "addr:housenumber":"29",
    "addr:postcode":"1333 bx",
    "addr:street":"Brandersmolenstr;Flevoland",
    "iso:country":"NL",
    "sg:address":"Brandersmolenstr 29",
    "sg:city":"Almere",
    "sg:orig_category":"Acupunctuur",
    "sg:phone":"+31 36 538 4211",
    "sg:postcode":"1333 BX",
    "sg:province":"Flevoland",
    "wof:name":"Barbara Jorritsma",
    "wof:placetype":"venue"
},
  "geometry": {"coordinates":[5.264979,52.398918],"type":"Point"}
}