{
  "type": "Feature",
  "properties": {
    "addr:full":"Diamantplein 63 Leiden South Holland 2332 HV",
    "addr:housenumber":"63",
    "addr:postcode":"2332 hv",
    "addr:street":"Diamantplein",
    "iso:country":"NL",
    "sg:address":"Diamantplein 63",
    "sg:city":"Leiden",
    "sg:orig_category":"Bloemen And Planten",
    "sg:phone":"+31 71 576 3735",
    "sg:postcode":"2332 HV",
    "sg:province":"South Holland",
    "wof:name":"Decora Bloembinders Vof",
    "wof:placetype":"venue"
},
  "geometry": {"coordinates":[4.465371,52.156448],"type":"Point"}
}