{
  "type": "Feature",
  "properties": {
    "addr:full":"Korvetweg 14 Maastricht Limburg 6222 NE",
    "addr:housenumber":"14",
    "addr:postcode":"6222 ne",
    "addr:street":"Korvetweg",
    "iso:country":"NL",
    "sg:address":"Korvetweg 14",
    "sg:city":"Maastricht",
    "sg:orig_category":"Pleziervaartuigen And Reparatie",
    "sg:phone":"+31 43 363 3034",
    "sg:postcode":"6222 NE",
    "sg:province":"Limburg",
    "wof:name":"Jachtwerf Snijders",
    "wof:placetype":"venue"
},
  "geometry": {"coordinates":[5.71409,50.870548],"type":"Point"}
}