{
  "type": "Feature",
  "properties": {
    "addr:full":"Woudenbergsewg 48 Zeist Utrecht 3707 HX",
    "addr:housenumber":"48",
    "addr:postcode":"3707 hx",
    "addr:street":"Woudenbergsewg",
    "iso:country":"NL",
    "sg:address":"Woudenbergsewg 48",
    "sg:city":"Zeist",
    "sg:orig_category":"Begraafplaatsen",
    "sg:phone":"+31 30 691 8727",
    "sg:postcode":"3707 HX",
    "sg:province":"Utrecht",
    "wof:name":"Alg Begraafplaats Zeist",
    "wof:placetype":"venue"
},
  "geometry": {"coordinates":[5.276723,52.090359],"type":"Point"}
}