{
  "type": "Feature",
  "properties": {
    "addr:full":"Boomstr 27C Amsterdam North Holland 1015 LA",
    "addr:housenumber":"27c",
    "addr:postcode":"1015 la",
    "addr:street":"Boomstr",
    "iso:country":"NL",
    "sg:address":"Boomstr 27C",
    "sg:city":"Amsterdam",
    "sg:orig_category":"Marktonderzoekbureaus",
    "sg:phone":"+31 20 489 2339",
    "sg:postcode":"1015 LA",
    "sg:province":"North Holland",
    "wof:name":"Trendz, M M",
    "wof:placetype":"venue"
},
  "geometry": {"coordinates":[4.885274,52.37915],"type":"Point"}
}