{
  "type": "Feature",
  "properties": {
    "addr:full":"Rockanjeln 11 S Gravenhage Zuid-Holland 2554 BP",
    "addr:housenumber":"11;gravenhage",
    "addr:postcode":"2554 bp",
    "addr:street":"Rockanjeln;S",
    "iso:country":"NL",
    "sg:address":"Rockanjeln 11",
    "sg:city":"S Gravenhage",
    "sg:orig_category":"Adviesbureaus",
    "sg:phone":"+31 70 368 8608",
    "sg:postcode":"2554 BP",
    "sg:province":"Zuid-Holland",
    "wof:name":"Strooker & Zwalf",
    "wof:placetype":"venue"
},
  "geometry": {"coordinates":[4.22476,52.067989],"type":"Point"}
}