{
  "type": "Feature",
  "properties": {
    "iso:country":"NL",
    "sg:address":"Heideln 46",
    "sg:city":"Bennekom",
    "sg:orig_category":"Verf En Lak",
    "sg:phone":"+31 318 430 115",
    "sg:postcode":"6721 CL",
    "sg:province":"Gelderland",
    "wof:name":"Cezet Int",
    "wof:placetype":"venue"
},
  "geometry": {"coordinates":[5.675792,52.000942],"type":"Point"}
}