{
  "type": "Feature",
  "properties": {
    "addr:full":"Steenstr 28 Oldenzaal Overijssel 7571 BK",
    "addr:housenumber":"28",
    "addr:postcode":"7571 bk",
    "addr:street":"Steenstr",
    "iso:country":"NL",
    "sg:address":"Steenstr 28",
    "sg:city":"Oldenzaal",
    "sg:orig_category":"Goudsmeden En Zilversmeden",
    "sg:phone":"+31 541 533 686",
    "sg:postcode":"7571 BK",
    "sg:province":"Overijssel",
    "sg:website":"http://www.goudkado.nl",
    "wof:name":"Tanke-Visser Vof",
    "wof:placetype":"venue"
},
  "geometry": {"coordinates":[6.9274330139,52.3108100891],"type":"Point"}
}