{
  "type": "Feature",
  "properties": {
    "iso:country":"NL",
    "sg:address":"Herenstraat 26",
    "sg:city":"Voorburg",
    "sg:orig_category":"Verlichting And Huishoudartikelen",
    "sg:phone":"+31 70 386 6403",
    "sg:postcode":"2271 CH",
    "sg:province":"Zuid-Holland",
    "wof:name":"J M R Tiessens",
    "wof:placetype":"venue"
},
  "geometry": {"coordinates":[4.365805,52.068424],"type":"Point"}
}