{
  "type": "Feature",
  "properties": {
    "addr:full":"Groen V Prinstererstraat 29 Papendrecht Zuid-Holland 3354 BA",
    "addr:housenumber":"29",
    "addr:postcode":"3354 ba",
    "addr:street":"Prinstererstraat",
    "iso:country":"NL",
    "sg:address":"Groen V Prinstererstraat 29",
    "sg:city":"Papendrecht",
    "sg:orig_category":"Juridische Dienstverlening",
    "sg:phone":"+31 78 615 1070",
    "sg:postcode":"3354 BA",
    "sg:province":"Zuid-Holland",
    "wof:name":"R.J.A. Erkelens",
    "wof:placetype":"venue"
},
  "geometry": {"coordinates":[4.698065,51.828556],"type":"Point"}
}