{
  "type": "Feature",
  "properties": {
    "addr:full":"Vierlinghstr 2 Werkendam North Brabant 4251 LC",
    "addr:housenumber":"2",
    "addr:postcode":"4251 lc",
    "addr:street":"Vierlinghstr",
    "iso:country":"NL",
    "sg:address":"Vierlinghstr 2",
    "sg:city":"Werkendam",
    "sg:orig_category":"Postzegels",
    "sg:phone":"+31 183 502 970",
    "sg:postcode":"4251 LC",
    "sg:province":"North Brabant",
    "wof:name":"Postorder Service Totaal",
    "wof:placetype":"venue"
},
  "geometry": {"coordinates":[4.882092,51.802895],"type":"Point"}
}