{
  "type": "Feature",
  "properties": {
    "addr:full":"Teugelaan 9A Schoorl Noord-Holland 1871 AJ",
    "addr:housenumber":"9a",
    "addr:postcode":"1871 aj",
    "addr:street":"Teugelaan",
    "iso:country":"NL",
    "sg:address":"Teugelaan 9A",
    "sg:city":"Schoorl",
    "sg:orig_category":"Artsen And Specialisten",
    "sg:phone":"+31 72 509 2024",
    "sg:postcode":"1871 AJ",
    "sg:province":"Noord-Holland",
    "wof:name":"I.K. Pronk-Udvarhelyi",
    "wof:placetype":"venue"
},
  "geometry": {"coordinates":[4.706094,52.689575],"type":"Point"}
}