{
  "type": "Feature",
  "properties": {
    "addr:full":"Oude Rijksweg 421 Rouveen Overijssel 7954 GH",
    "addr:housenumber":"421",
    "addr:postcode":"7954 gh",
    "addr:street":"Oude Rijksweg",
    "iso:country":"NL",
    "sg:address":"Oude Rijksweg 421",
    "sg:city":"Rouveen",
    "sg:orig_category":"Levende Dieren Gh",
    "sg:phone":"+31 522 291 348",
    "sg:postcode":"7954 GH",
    "sg:province":"Overijssel",
    "wof:name":"J. Knoll",
    "wof:placetype":"venue"
},
  "geometry": {"coordinates":[6.18578,52.617115],"type":"Point"}
}