{
  "type": "Feature",
  "properties": {
    "iso:country":"NL",
    "sg:address":"Boekweit 10",
    "sg:city":"Eersel",
    "sg:orig_category":"Plafonds",
    "sg:phone":"+31 497 530 056",
    "sg:postcode":"5521 MZ",
    "sg:province":"North Brabant",
    "wof:name":"Plafondexpert Vof, De",
    "wof:placetype":"venue"
},
  "geometry": {"coordinates":[5.308578,51.351357],"type":"Point"}
}