{
  "type": "Feature",
  "properties": {
    "addr:full":"Dokweg 4 Ijmuiden California 1976 CA",
    "addr:housenumber":"4",
    "addr:postcode":"1976 ca",
    "addr:street":"Dokweg",
    "iso:country":"NL",
    "sg:address":"Dokweg 4",
    "sg:city":"Ijmuiden",
    "sg:orig_category":"Technische Studies And Onderzoek",
    "sg:phone":"+31 255 521 450",
    "sg:postcode":"1976 CA",
    "sg:province":"California",
    "wof:name":"Projectie Engineering Bv",
    "wof:placetype":"venue"
},
  "geometry": {"coordinates":[-119.27020263670001,37.2718315125],"type":"Point"}
}