{
  "type": "Feature",
  "properties": {
    "addr:full":"Armhoefstr 44 Tilburg Noord-Brabant 5018 EK",
    "addr:housenumber":"44",
    "addr:postcode":"5018 ek",
    "addr:street":"Armhoefstr",
    "iso:country":"NL",
    "sg:address":"Armhoefstr 44",
    "sg:city":"Tilburg",
    "sg:orig_category":"Bloemen En Planten",
    "sg:phone":"+31 13 544 1731",
    "sg:postcode":"5018 EK",
    "sg:province":"Noord-Brabant",
    "wof:name":"Blossom",
    "wof:placetype":"venue"
},
  "geometry": {"coordinates":[5.108099,51.559383],"type":"Point"}
}