{
  "type": "Feature",
  "properties": {
    "iso:country":"NL",
    "sg:address":"Ruysdaelstraat 106/1",
    "sg:city":"Amsterdam",
    "sg:orig_category":"Architecten",
    "sg:phone":"+31 20 679 5069",
    "sg:postcode":"1071 XH",
    "sg:province":"Noord-Holland",
    "wof:name":"Joh.J. Koch",
    "wof:placetype":"venue"
},
  "geometry": {"coordinates":[4.880233,52.353561],"type":"Point"}
}