{
  "type": "Feature",
  "properties": {
    "addr:full":"Koksedk 1 Gemert Noord-Brabant 5421 ZB",
    "addr:housenumber":"1",
    "addr:postcode":"5421 zb",
    "addr:street":"Koksedk",
    "iso:country":"NL",
    "sg:address":"Koksedk 1",
    "sg:city":"Gemert",
    "sg:orig_category":"Afslankinstituten",
    "sg:phone":"+31 492 368 382",
    "sg:postcode":"5421 ZB",
    "sg:province":"Noord-Brabant",
    "sg:website":"http://www.welcome.to/slenderyougemert.com",
    "wof:name":"Slender You Gemert",
    "wof:placetype":"venue"
},
  "geometry": {"coordinates":[5.667918,51.568016],"type":"Point"}
}