{
  "type": "Feature",
  "properties": {
    "addr:full":"Laan Van Meerdervoort 79 'S Gravenhage Zuid-Holland 2517 AH",
    "addr:housenumber":"79",
    "addr:postcode":"2517 ah",
    "addr:street":"Laan Van Meerdervoort;' S",
    "iso:country":"NL",
    "sg:address":"Laan Van Meerdervoort 79",
    "sg:city":"'S Gravenhage",
    "sg:orig_category":"Artiesten",
    "sg:phone":"+31 70 345 5636",
    "sg:postcode":"2517 AH",
    "sg:province":"Zuid-Holland",
    "wof:name":"Wiegel Art Promotion Vof",
    "wof:placetype":"venue"
},
  "geometry": {"coordinates":[4.290649,52.083298],"type":"Point"}
}