{
  "type": "Feature",
  "properties": {
    "addr:full":"Muntpassage 21 Weert Limburg 6001 GL",
    "addr:housenumber":"21",
    "addr:postcode":"6001 gl",
    "addr:street":"Muntpassage",
    "iso:country":"NL",
    "sg:address":"Muntpassage 21",
    "sg:city":"Weert",
    "sg:orig_category":"Opticiens",
    "sg:phone":"+31 495 537 365",
    "sg:postcode":"6001 GL",
    "sg:province":"Limburg",
    "wof:name":"Huis Havelaer, Het",
    "wof:placetype":"venue"
},
  "geometry": {"coordinates":[5.7046179771,51.2538986206],"type":"Point"}
}