{
  "type": "Feature",
  "properties": {
    "addr:full":"Jansplaats 24 Arnhem Gelderland 6811 GB",
    "addr:housenumber":"24",
    "addr:postcode":"6811 gb",
    "addr:street":"Jansplaats",
    "iso:country":"NL",
    "sg:address":"Jansplaats 24",
    "sg:city":"Arnhem",
    "sg:orig_category":"Biljartzalen",
    "sg:phone":"+31 26 442 9345",
    "sg:postcode":"6811 GB",
    "sg:province":"Gelderland",
    "wof:name":"House Of Billiards",
    "wof:placetype":"venue"
},
  "geometry": {"coordinates":[5.906778,51.982273],"type":"Point"}
}