{
  "type": "Feature",
  "properties": {
    "iso:country":"NL",
    "sg:address":"Hulsdonksestr 37",
    "sg:city":"Roosendaal",
    "sg:classifiers":[
        {
            "category":"Wholesale",
            "subcategory":"Meat",
            "type":"Manufacturing & Wholesale Goods"
        }
    ],
    "sg:phone":"+31 165 538 625",
    "sg:postcode":"4703 AP",
    "sg:province":"Noord-Brabant",
    "sg:tags":[
        "regeltechniek",
        "en",
        "meet-"
    ],
    "wof:name":"Whon Techniek",
    "wof:placetype":"venue"
},
  "geometry": {"coordinates":[4.447346,51.53154],"type":"Point"}
}