{
  "type": "Feature",
  "properties": {
    "addr:full":"Stadhoudersln 43 Utrecht Utrecht 3583 JC",
    "addr:housenumber":"43",
    "addr:postcode":"3583 jc",
    "addr:street":"Stadhoudersln",
    "iso:country":"NL",
    "sg:address":"Stadhoudersln 43",
    "sg:city":"Utrecht",
    "sg:orig_category":"Poliklinieken",
    "sg:phone":"+31 30 254 2233",
    "sg:postcode":"3583 JC",
    "sg:province":"Utrecht",
    "wof:name":"Epilepsie, Ploikliniek Voor",
    "wof:placetype":"venue"
},
  "geometry": {"coordinates":[5.14371,52.086601],"type":"Point"}
}