{
  "type": "Feature",
  "properties": {
    "addr:full":"Franciscuswg 14 Hilversum North Holland 1216 SK",
    "addr:housenumber":"14",
    "addr:street":"Franciscuswg;1216",
    "iso:country":"NL",
    "sg:address":"Franciscuswg 14",
    "sg:city":"Hilversum",
    "sg:orig_category":"Omroep",
    "sg:phone":"+31 35 678 5000",
    "sg:postcode":"1216 SK",
    "sg:province":"North Holland",
    "wof:name":"Holland Media House",
    "wof:placetype":"venue"
},
  "geometry": {"coordinates":[5.144468,52.213448],"type":"Point"}
}