{
  "type": "Feature",
  "properties": {
    "addr:full":"Albregt-Engelmanstraat 34 Rotterdam Zuid-Holland 3025 BH",
    "addr:housenumber":"34",
    "addr:postcode":"3025 bh",
    "addr:street":"Albregt-Engelmanstraat",
    "iso:country":"NL",
    "sg:address":"Albregt-Engelmanstraat 34",
    "sg:city":"Rotterdam",
    "sg:classifiers":[
        {
            "category":"Education",
            "subcategory":"Preschool",
            "type":"Public Place"
        }
    ],
    "sg:phone":"+31 10 476 5521",
    "sg:postcode":"3025 BH",
    "sg:province":"Zuid-Holland",
    "sg:tags":[
        "kleuteronderwijs",
        "basis-"
    ],
    "wof:name":"Dr J. Woltjerschool",
    "wof:placetype":"venue"
},
  "geometry": {"coordinates":[4.444506,51.906277],"type":"Point"}
}