{
  "type": "Feature",
  "properties": {
    "iso:country":"NL",
    "sg:address":"Hoofdstr 376",
    "sg:city":"Hoensbroek",
    "sg:orig_category":"Huishoudelijke Apparaten En Artikelen",
    "sg:phone":"+31 45 528 5389",
    "sg:postcode":"6432 GN",
    "sg:province":"Limburg",
    "wof:name":"Witgoedwinkel, De",
    "wof:placetype":"venue"
},
  "geometry": {"coordinates":[5.917042,50.919994],"type":"Point"}
}