{
  "type": "Feature",
  "properties": {
    "iso:country":"NL",
    "sg:address":"Kerkstr 31",
    "sg:city":"Geldermalsen",
    "sg:orig_category":"Antiquiteiten",
    "sg:phone":"+31 345 577 119",
    "sg:postcode":"4191 AA",
    "sg:province":"Gelderland",
    "wof:name":"Hardy'S & Rose",
    "wof:placetype":"venue"
},
  "geometry": {"coordinates":[5.286999,51.883022],"type":"Point"}
}