{
  "type": "Feature",
  "properties": {
    "iso:country":"NL",
    "sg:address":"Heugemer Molenstraat 3",
    "sg:city":"Maastricht",
    "sg:orig_category":"Hoger Onderwijs",
    "sg:phone":"+31 43 361 6038",
    "sg:postcode":"6229 AK",
    "sg:province":"Limburg",
    "wof:name":"Bert Jongen",
    "wof:placetype":"venue"
},
  "geometry": {"coordinates":[5.705595,50.828114],"type":"Point"}
}