{
  "type": "Feature",
  "properties": {
    "addr:full":"K De Haanstr 22 Sappemeer Groningen 9611 HT",
    "addr:housenumber":"22",
    "addr:postcode":"9611 ht",
    "addr:street":"K De Haanstr",
    "iso:country":"NL",
    "sg:address":"K De Haanstr 22",
    "sg:city":"Sappemeer",
    "sg:orig_category":"Kappers",
    "sg:phone":"+31 598 390 727",
    "sg:postcode":"9611 HT",
    "sg:province":"Groningen",
    "wof:name":"Headline",
    "wof:placetype":"venue"
},
  "geometry": {"coordinates":[6.7740831375,53.1623077393],"type":"Point"}
}