{
  "type": "Feature",
  "properties": {
    "addr:full":"Zandbergenln 14 Amersfoort Utrecht 3817 GN",
    "addr:housenumber":"14",
    "addr:postcode":"3817 gn",
    "addr:street":"Zandbergenln",
    "iso:country":"NL",
    "sg:address":"Zandbergenln 14",
    "sg:city":"Amersfoort",
    "sg:orig_category":"Haptotherapeuten",
    "sg:phone":"+31 33 465 5985",
    "sg:postcode":"3817 GN",
    "sg:province":"Utrecht",
    "wof:name":"Nunspeet, Jos? Van",
    "wof:placetype":"venue"
},
  "geometry": {"coordinates":[5.392721,52.140549],"type":"Point"}
}