{
  "type": "Feature",
  "properties": {
    "addr:full":"Postbus 295 Brielle New Jersey 3230 AG",
    "addr:housenumber":"295",
    "addr:postcode":"3230",
    "addr:street":"Postbus",
    "iso:country":"NL",
    "sg:address":"Postbus 295",
    "sg:city":"Brielle",
    "sg:orig_category":"Miniaturen",
    "sg:phone":"+31 181 410 359",
    "sg:postcode":"3230 AG",
    "sg:province":"New Jersey",
    "wof:name":"Lang",
    "wof:placetype":"venue"
},
  "geometry": {"coordinates":[-74.057137,40.112309],"type":"Point"}
}