{
  "type": "Feature",
  "properties": {
    "addr:full":"Hoogstr 148B Rotterdam Zuid-Holland 3011 PV",
    "addr:housenumber":"148b",
    "addr:postcode":"3011 pv",
    "iso:country":"NL",
    "sg:address":"Hoogstr 148B",
    "sg:city":"Rotterdam",
    "sg:orig_category":"Bedden En Matrassen",
    "sg:phone":"+31 10 214 2459",
    "sg:postcode":"3011 PV",
    "sg:province":"Zuid-Holland",
    "wof:name":"Droomwereld",
    "wof:placetype":"venue"
},
  "geometry": {"coordinates":[4.486052,51.920883],"type":"Point"}
}