{
  "type": "Feature",
  "properties": {
    "addr:full":"Strawinskipln 17 Rhoon South Holland 3161 WG",
    "addr:housenumber":"17",
    "addr:postcode":"3161 wg",
    "addr:street":"Strawinskipln",
    "iso:country":"NL",
    "sg:address":"Strawinskipln 17",
    "sg:city":"Rhoon",
    "sg:orig_category":"Opticiens",
    "sg:phone":"+31 10 501 2530",
    "sg:postcode":"3161 WG",
    "sg:province":"South Holland",
    "sg:website":"http://www.janlucasoptiek.nl",
    "wof:name":"Jan Lucas Optiek",
    "wof:placetype":"venue"
},
  "geometry": {"coordinates":[4.4198799133,51.8565711975],"type":"Point"}
}