{
  "type": "Feature",
  "properties": {
    "iso:country":"NL",
    "sg:address":"Benedenwg 255",
    "sg:city":"St Pancras",
    "sg:orig_category":"Muziekinstrumenten En Bladmuziek",
    "sg:phone":"+31 72 561 9749",
    "sg:postcode":"1834 BB",
    "sg:province":"North Holland",
    "wof:name":"Ruys, Sander",
    "wof:placetype":"venue"
},
  "geometry": {"coordinates":[4.779027,52.655102],"type":"Point"}
}