{
  "type": "Feature",
  "properties": {
    "addr:full":"Dorpsstr 30 Heerjansdam Zuid-Holland 2995 XH",
    "addr:housenumber":"30",
    "addr:postcode":"2995 xh",
    "addr:street":"Dorpsstr",
    "iso:country":"NL",
    "sg:address":"Dorpsstr 30",
    "sg:city":"Heerjansdam",
    "sg:orig_category":"Verzekeringen - Verzekeringskantoren",
    "sg:phone":"+31 78 677 3265",
    "sg:postcode":"2995 XH",
    "sg:province":"Zuid-Holland",
    "wof:name":"Omnido",
    "wof:placetype":"venue"
},
  "geometry": {"coordinates":[4.560496,51.835907],"type":"Point"}
}