{
  "type": "Feature",
  "properties": {
    "addr:full":"Sparrenstraat 2 Kerkdriel Gelderland 5331 GR",
    "addr:housenumber":"2",
    "addr:postcode":"5331",
    "addr:street":"Sparrenstraat;Gelderland",
    "iso:country":"NL",
    "sg:address":"Sparrenstraat 2",
    "sg:city":"Kerkdriel",
    "sg:orig_category":"Vertaal- And Tolkenbureaus",
    "sg:phone":"+31 24 344 2357",
    "sg:postcode":"5331 GR",
    "sg:province":"Gelderland",
    "wof:name":"Kappa Translation Services",
    "wof:placetype":"venue"
},
  "geometry": {"coordinates":[5.329103,51.767693],"type":"Point"}
}