{
  "type": "Feature",
  "properties": {
    "addr:full":"Energiewg 3B Hapert North Brabant 5527 AH",
    "addr:housenumber":"3b",
    "addr:postcode":"5527 ah",
    "addr:street":"Energiewg",
    "iso:country":"NL",
    "sg:address":"Energiewg 3B",
    "sg:city":"Hapert",
    "sg:orig_category":"Lasbedrijven",
    "sg:phone":"+31 497 360 032",
    "sg:postcode":"5527 AH",
    "sg:province":"North Brabant",
    "wof:name":"Bemacom-Vencomatic Bv",
    "wof:placetype":"venue"
},
  "geometry": {"coordinates":[5.270579,51.372364],"type":"Point"}
}