{
  "type": "Feature",
  "properties": {
    "addr:full":"Lizzy Ansinghstraat 80 Amsterdam North Holland 1072 RD",
    "addr:housenumber":"80",
    "addr:postcode":"1072 rd",
    "addr:street":"Lizzy Ansinghstraat",
    "iso:country":"NL",
    "sg:address":"Lizzy Ansinghstraat 80",
    "sg:city":"Amsterdam",
    "sg:orig_category":"Paramedische Behandelingen",
    "sg:phone":"+31 20 676 5532",
    "sg:postcode":"1072 RD",
    "sg:province":"North Holland",
    "wof:name":"Logopedie Beeldspraak Praktijk Voor",
    "wof:placetype":"venue"
},
  "geometry": {"coordinates":[4.89323,52.349766],"type":"Point"}
}