{
  "type": "Feature",
  "properties": {
    "addr:full":"Kentgenspln 24 Zoetermeer Zuid-Holland 2717 HS",
    "addr:housenumber":"24",
    "addr:postcode":"2717 hs",
    "addr:street":"Kentgenspln",
    "iso:country":"NL",
    "sg:address":"Kentgenspln 24",
    "sg:city":"Zoetermeer",
    "sg:orig_category":"Schoenen - Reparaties",
    "sg:phone":"+31 79 351 7538",
    "sg:postcode":"2717 HS",
    "sg:province":"Zuid-Holland",
    "wof:name":"Sebastiaans' Original",
    "wof:placetype":"venue"
},
  "geometry": {"coordinates":[4.478125,52.066067],"type":"Point"}
}