{
  "type": "Feature",
  "properties": {
    "iso:country":"NL",
    "sg:address":"D Curtiusstr 12A",
    "sg:city":"Rotterdam",
    "sg:orig_category":"Grafisch Ontwerpers",
    "sg:phone":"+31 10 265 0399",
    "sg:postcode":"3038 SB",
    "sg:province":"Zuid-Holland",
    "sg:website":"http://www.somethingfishy.nl",
    "wof:name":"Something Fishy",
    "wof:placetype":"venue"
},
  "geometry": {"coordinates":[4.465314,51.937893],"type":"Point"}
}