{
  "type": "Feature",
  "properties": {
    "addr:full":"Moerbeigaarde 58 Zoetermeer Zuid-Holland 2723 AG",
    "addr:housenumber":"58",
    "addr:postcode":"2723",
    "addr:street":"Moerbeigaarde",
    "iso:country":"NL",
    "sg:address":"Moerbeigaarde 58",
    "sg:city":"Zoetermeer",
    "sg:orig_category":"Scholen Voor Basisonderwijs",
    "sg:phone":"+31 79 331 3043",
    "sg:postcode":"2723 AG",
    "sg:province":"Zuid-Holland",
    "wof:name":"Verwers Montessorisch, Mr",
    "wof:placetype":"venue"
},
  "geometry": {"coordinates":[4.51266,52.060646],"type":"Point"}
}