{
  "type": "Feature",
  "properties": {
    "addr:full":"Hekendorpse Buurt 47 Hekendorp Utrecht 3467 PB",
    "addr:housenumber":"47",
    "addr:postcode":"3467 pb",
    "addr:street":"Hekendorpse Buurt",
    "iso:country":"NL",
    "sg:address":"Hekendorpse Buurt 47",
    "sg:city":"Hekendorp",
    "sg:orig_category":"Goudsmeden En Zilversmeden",
    "sg:phone":"+31 348 563 166",
    "sg:postcode":"3467 PB",
    "sg:province":"Utrecht",
    "wof:name":"Stratosfeer",
    "wof:placetype":"venue"
},
  "geometry": {"coordinates":[4.833081,52.01741],"type":"Point"}
}