{
  "type": "Feature",
  "properties": {
    "addr:full":"Haven 32- 34 Kloosterburen Groningen 9977 RZ",
    "addr:housenumber":"32 34",
    "addr:postcode":"9977 rz",
    "addr:street":"Haven",
    "iso:country":"NL",
    "sg:address":"Haven 32- 34",
    "sg:city":"Kloosterburen",
    "sg:orig_category":"Binnenvaart",
    "sg:phone":"+31 595 481 980",
    "sg:postcode":"9977 RZ",
    "sg:province":"Groningen",
    "wof:name":"Recreatiebedrijf Horizon",
    "wof:placetype":"venue"
},
  "geometry": {"coordinates":[6.404063,53.385723],"type":"Point"}
}