{
  "type": "Feature",
  "properties": {
    "addr:full":"Burg D Kievietstr 7 Diemen Noord-Holland 1111 GJ",
    "addr:housenumber":"7",
    "addr:postcode":"1111 gj",
    "addr:street":"Burg;Kievietstr",
    "iso:country":"NL",
    "sg:address":"Burg D Kievietstr 7",
    "sg:city":"Diemen",
    "sg:orig_category":"Voeding, Dranken And Tabak Gh",
    "sg:phone":"+31 20 699 8229",
    "sg:postcode":"1111 GJ",
    "sg:province":"Noord-Holland",
    "wof:name":"Tigris Import/Export Van Levensmiddelen",
    "wof:placetype":"venue"
},
  "geometry": {"coordinates":[4.962633,52.338936],"type":"Point"}
}