{
  "type": "Feature",
  "properties": {
    "iso:country":"NL",
    "sg:address":"Linie 624",
    "sg:city":"Apeldoorn",
    "sg:orig_category":"Logopedisten",
    "sg:phone":"+31 55 366 9805",
    "sg:postcode":"7325 DZ",
    "sg:province":"Gelderland",
    "wof:name":"Woudhuis En Osseveld",
    "wof:placetype":"venue"
},
  "geometry": {"coordinates":[6.005764,52.216259],"type":"Point"}
}