{
  "type": "Feature",
  "properties": {
    "addr:full":"Sint Radboudstraat 4 Amersfoort Utrecht 3817 BN",
    "addr:housenumber":"4",
    "addr:postcode":"3817 bn",
    "addr:street":"Sint Radboudstraat",
    "iso:country":"NL",
    "sg:address":"Sint Radboudstraat 4",
    "sg:city":"Amersfoort",
    "sg:orig_category":"Bedrijfs- And Managementsconsultants",
    "sg:phone":"+31 33 465 1260",
    "sg:postcode":"3817 BN",
    "sg:province":"Utrecht",
    "wof:name":"Color Me Beautiful - Kies Je Kleur",
    "wof:placetype":"venue"
},
  "geometry": {"coordinates":[5.394328,52.15237],"type":"Point"}
}