{
  "type": "Feature",
  "properties": {
    "addr:full":"Meerweg 11 Allingawier Friesland 8758 LC",
    "addr:housenumber":"11",
    "addr:postcode":"8758 lc",
    "addr:street":"Meerweg",
    "iso:country":"NL",
    "sg:address":"Meerweg 11",
    "sg:city":"Allingawier",
    "sg:orig_category":"Autokeuringen",
    "sg:phone":"+31 515 232 710",
    "sg:postcode":"8758 LC",
    "sg:province":"Friesland",
    "wof:name":"Y. Hempenius",
    "wof:placetype":"venue"
},
  "geometry": {"coordinates":[5.454145,53.038471],"type":"Point"}
}