{
  "type": "Feature",
  "properties": {
    "addr:full":"Amersfoortsestraat 123 Soesterberg Utrecht 3769 AJ",
    "addr:housenumber":"123",
    "addr:postcode":"3769 aj",
    "addr:street":"Amersfoortsestraat",
    "iso:country":"NL",
    "sg:address":"Amersfoortsestraat 123",
    "sg:city":"Soesterberg",
    "sg:classifiers":[
        {
            "category":"Professional",
            "subcategory":"Accounting & Tax Preparation",
            "type":"Services"
        }
    ],
    "sg:phone":"+31 33 445 3000",
    "sg:postcode":"3769 AJ",
    "sg:province":"Utrecht",
    "sg:tags":[
        "accountant"
    ],
    "wof:name":"Pricewaterhousecoopers Nv",
    "wof:placetype":"venue"
},
  "geometry": {"coordinates":[5.332042,52.133785],"type":"Point"}
}