{
  "type": "Feature",
  "properties": {
    "addr:full":"Salvator Allendelaan 8 'S Hertogenbosch Noord-Brabant 5231 BZ",
    "addr:housenumber":"8 ' s",
    "addr:postcode":"5231 bz",
    "addr:street":"Salvator Allendelaan",
    "iso:country":"NL",
    "sg:address":"Salvator Allendelaan 8",
    "sg:city":"'S Hertogenbosch",
    "sg:orig_category":"Kinderopvang Behalve Thuis",
    "sg:phone":"+31 73 641 3910",
    "sg:postcode":"5231 BZ",
    "sg:province":"Noord-Brabant",
    "wof:name":"Kinderdagcentrum De Elzengaard",
    "wof:placetype":"venue"
},
  "geometry": {"coordinates":[5.303543,51.711224],"type":"Point"}
}