{
  "type": "Feature",
  "properties": {
    "addr:full":"Merelstr 24 Leiden South Holland 2333 XM",
    "addr:housenumber":"24",
    "addr:postcode":"2333 xm",
    "addr:street":"Merelstr",
    "iso:country":"NL",
    "sg:address":"Merelstr 24",
    "sg:city":"Leiden",
    "sg:orig_category":"Woningstoffeerders",
    "sg:phone":"+31 71 515 6786",
    "sg:postcode":"2333 XM",
    "sg:province":"South Holland",
    "wof:name":"Bey, J F",
    "wof:placetype":"venue"
},
  "geometry": {"coordinates":[4.471862793,52.172996521],"type":"Point"}
}