{
  "type": "Feature",
  "properties": {
    "addr:full":"Klinkerstr 13 Oostwold Scheemda Groningen 9682 RB",
    "addr:housenumber":"13",
    "addr:postcode":"9682 rb",
    "addr:street":"Klinkerstr",
    "iso:country":"NL",
    "sg:address":"Klinkerstr 13",
    "sg:city":"Oostwold Scheemda",
    "sg:orig_category":"Koeriersdiensten",
    "sg:phone":"+31 6 50523487",
    "sg:postcode":"9682 RB",
    "sg:province":"Groningen",
    "wof:name":"Buining",
    "wof:placetype":"venue"
},
  "geometry": {"coordinates":[7.046006,53.201893],"type":"Point"}
}