{
  "type": "Feature",
  "properties": {
    "addr:full":"Lansinkeswg 75 Hengelo Ov NL.08 7553 AE",
    "addr:housenumber":"75",
    "addr:postcode":"7553 ae",
    "addr:street":"Lansinkeswg;Ov",
    "iso:country":"NL",
    "sg:address":"Lansinkeswg 75",
    "sg:city":"Hengelo Ov",
    "sg:orig_category":"Machinefabrieken",
    "sg:phone":"+31 74 240 8200",
    "sg:postcode":"7553 AE",
    "sg:province":"NL.08",
    "wof:name":"Stork",
    "wof:placetype":"venue"
},
  "geometry": {"coordinates":[6.787403,52.26136],"type":"Point"}
}