{
  "type": "Feature",
  "properties": {
    "addr:full":"Kesselsegraaf 5 Maren Kessel Noord-Brabant 5398 CH",
    "addr:housenumber":"5",
    "addr:postcode":"5398",
    "addr:street":"Kesselsegraaf;Maren Kessel",
    "iso:country":"NL",
    "sg:address":"Kesselsegraaf 5",
    "sg:city":"Maren Kessel",
    "sg:orig_category":"Land- En Tuinbouw - Loonbedrijven",
    "sg:phone":"+31 412 479 534",
    "sg:postcode":"5398 CH",
    "sg:province":"Noord-Brabant",
    "wof:name":"Lith, K J G M Van",
    "wof:placetype":"venue"
},
  "geometry": {"coordinates":[5.412748,51.801762],"type":"Point"}
}