{
  "type": "Feature",
  "properties": {
    "iso:country":"NL",
    "sg:address":"Puntenburgerlaan 102",
    "sg:city":"Amersfoort",
    "sg:orig_category":"Kappers",
    "sg:phone":"+31 33 465 6490",
    "sg:postcode":"3812 CG",
    "sg:province":"Utrecht",
    "wof:name":"Kapsalon Puntenburg",
    "wof:placetype":"venue"
},
  "geometry": {"coordinates":[5.3751368523,52.1583938599],"type":"Point"}
}