{
  "type": "Feature",
  "properties": {
    "addr:full":"Ln V Nw Blankenb 260 Rozenburg Zh Zuid-Holland 3181 AL",
    "addr:housenumber":"260",
    "addr:postcode":"zh;3181 al",
    "addr:street":"Ln V Nw Blankenb",
    "iso:country":"NL",
    "sg:address":"Ln V Nw Blankenb 260",
    "sg:city":"Rozenburg Zh",
    "sg:orig_category":"Cafetaria'S",
    "sg:phone":"+31 181 213 605",
    "sg:postcode":"3181 AL",
    "sg:province":"Zuid-Holland",
    "wof:name":"Driesprong, De",
    "wof:placetype":"venue"
},
  "geometry": {"coordinates":[4.249615,51.904446],"type":"Point"}
}