{
  "type": "Feature",
  "properties": {
    "addr:full":"Industriewg 135 Rotterdam Zuid-Holland 3044 AS",
    "addr:housenumber":"135",
    "addr:postcode":"3044 as",
    "iso:country":"NL",
    "sg:address":"Industriewg 135",
    "sg:city":"Rotterdam",
    "sg:classifiers":[
        {
            "category":"Retail",
            "subcategory":"Auto Repair",
            "type":"Services"
        }
    ],
    "sg:phone":"+31 10 462 7647",
    "sg:postcode":"3044 AS",
    "sg:province":"Zuid-Holland",
    "sg:tags":[
        "garage"
    ],
    "wof:name":"Olympia Bv",
    "wof:placetype":"venue"
},
  "geometry": {"coordinates":[4.421576,51.927197],"type":"Point"}
}