{
  "type": "Feature",
  "properties": {
    "iso:country":"NL",
    "sg:address":"Utrechtsewg 28B",
    "sg:city":"Renswoude",
    "sg:orig_category":"Bestratingen",
    "sg:phone":"+31 318 575 370",
    "sg:postcode":"3927 AV",
    "sg:province":"Utrecht",
    "wof:name":"Mastenbroek, B J",
    "wof:placetype":"venue"
},
  "geometry": {"coordinates":[5.524487,52.076244],"type":"Point"}
}