{
  "type": "Feature",
  "properties": {
    "addr:full":"Hoofdstr 31 Zeyen Drenthe 9491 AD",
    "addr:housenumber":"31",
    "addr:postcode":"9491 ad",
    "addr:street":"Hoofdstr",
    "iso:country":"NL",
    "sg:address":"Hoofdstr 31",
    "sg:city":"Zeyen",
    "sg:orig_category":"Kinderopvang",
    "sg:phone":"+31 592 291 962",
    "sg:postcode":"9491 AD",
    "sg:province":"Drenthe",
    "sg:website":"http://www.villa-kakelbont.net",
    "wof:name":"Villa Kakelbont",
    "wof:placetype":"venue"
},
  "geometry": {"coordinates":[6.54743,53.047131],"type":"Point"}
}