{
  "type": "Feature",
  "properties": {
    "addr:full":"Vergiliushof 5 B Maastricht Limburg 6215 GH",
    "addr:housenumber":"5 b",
    "addr:postcode":"6215 gh",
    "addr:street":"Vergiliushof",
    "iso:country":"NL",
    "sg:address":"Vergiliushof 5 B",
    "sg:city":"Maastricht",
    "sg:orig_category":"Zonweringen",
    "sg:phone":"+31 43 347 6238",
    "sg:postcode":"6215 GH",
    "sg:province":"Limburg",
    "wof:name":"Franssen, Jos",
    "wof:placetype":"venue"
},
  "geometry": {"coordinates":[5.647904,50.843521],"type":"Point"}
}