{
  "type": "Feature",
  "properties": {
    "iso:country":"NL",
    "sg:address":"Jarmuiden 56B",
    "sg:city":"Amsterdam",
    "sg:orig_category":"Webdesign Bureaus",
    "sg:phone":"+31 20 624 9940",
    "sg:postcode":"1046 AE",
    "sg:province":"Noord-Holland",
    "wof:name":"Web Business Creations Bv",
    "wof:placetype":"venue"
},
  "geometry": {"coordinates":[4.7908320427,52.3912734985],"type":"Point"}
}