{
  "type": "Feature",
  "properties": {
    "iso:country":"NL",
    "sg:address":"Schipholwg 905C",
    "sg:city":"Boesingheliede",
    "sg:orig_category":"Parketvloeren - Onderhoud En Reparatie",
    "sg:phone":"+31 6 27034391",
    "sg:postcode":"2143 CD",
    "sg:province":"Noord-Holland",
    "wof:name":"Ruud Van Weelden",
    "wof:placetype":"venue"
},
  "geometry": {"coordinates":[4.72394,52.361313],"type":"Point"}
}