{
  "type": "Feature",
  "properties": {
    "addr:full":"De Krim 4 Hoenderloo Gelderland 7351 BL",
    "addr:housenumber":"4",
    "addr:postcode":"7351 bl",
    "addr:street":"De Krim;Gelderland",
    "iso:country":"NL",
    "sg:address":"De Krim 4",
    "sg:city":"Hoenderloo",
    "sg:orig_category":"Bedrijfsamusement",
    "sg:phone":"+31 55 378 1348",
    "sg:postcode":"7351 BL",
    "sg:province":"Gelderland",
    "wof:name":"Midgetgolfbaan Restaurant De Krim",
    "wof:placetype":"venue"
},
  "geometry": {"coordinates":[5.8911452293,52.1207809448],"type":"Point"}
}