{
  "type": "Feature",
  "properties": {
    "iso:country":"NL",
    "sg:address":"K Doormanstr 10",
    "sg:city":"Rotterdam",
    "sg:orig_category":"Discotheken",
    "sg:phone":"+31 10 213 1180",
    "sg:postcode":"3012 GJ",
    "sg:province":"Zuid-Holland",
    "sg:website":"http://www.baja.nl",
    "wof:name":"Baja",
    "wof:placetype":"venue"
},
  "geometry": {"coordinates":[4.473643,51.922737],"type":"Point"}
}