{
  "type": "Feature",
  "properties": {
    "iso:country":"NL",
    "sg:address":"Westfriesedijk 15",
    "sg:city":"Aartswoud",
    "sg:orig_category":"Metaalbekleding And -Behandeling",
    "sg:phone":"+31 229 581 370",
    "sg:postcode":"1719 NK",
    "sg:province":"Noord-Holland",
    "wof:name":"Las- En Montagebedrijf Rob Ruig",
    "wof:placetype":"venue"
},
  "geometry": {"coordinates":[4.988577,52.751823],"type":"Point"}
}