{
  "type": "Feature",
  "properties": {
    "addr:full":"Hoofdwg 94 Blyham Groningen 9697 NN",
    "addr:housenumber":"94",
    "addr:postcode":"9697 nn",
    "addr:street":"Hoofdwg",
    "iso:country":"NL",
    "sg:address":"Hoofdwg 94",
    "sg:city":"Blyham",
    "sg:orig_category":"Fietsen En Bromfietsen",
    "sg:phone":"+31 597 561 292",
    "sg:postcode":"9697 NN",
    "sg:province":"Groningen",
    "wof:name":"Ab De Groot",
    "wof:placetype":"venue"
},
  "geometry": {"coordinates":[7.075358,53.104942],"type":"Point"}
}