{
  "type": "Feature",
  "properties": {
    "addr:full":"Oeverkruid 13 Raamsdonksveer North Brabant 4941 VV",
    "addr:housenumber":"13",
    "addr:postcode":"4941 vv",
    "addr:street":"Oeverkruid",
    "iso:country":"NL",
    "sg:address":"Oeverkruid 13",
    "sg:city":"Raamsdonksveer",
    "sg:orig_category":"Werving And Selectie Van Vast Personeel",
    "sg:phone":"+31 162 515 220",
    "sg:postcode":"4941 VV",
    "sg:province":"North Brabant",
    "wof:name":"Interselling Search Bv",
    "wof:placetype":"venue"
},
  "geometry": {"coordinates":[4.8825187683,51.7098121643],"type":"Point"}
}