{
  "type": "Feature",
  "properties": {
    "addr:full":"Middelstraat 11 Someren Noord-Brabant 5712 LL",
    "addr:housenumber":"11",
    "addr:postcode":"5712 ll",
    "addr:street":"Middelstraat",
    "iso:country":"NL",
    "sg:address":"Middelstraat 11",
    "sg:city":"Someren",
    "sg:orig_category":"Loodgieterswerk, Verwarming And Sanitaire Installaties",
    "sg:phone":"+31 493 490 110",
    "sg:postcode":"5712 LL",
    "sg:province":"Noord-Brabant",
    "wof:name":"W.F.J.M. Boerenkamp",
    "wof:placetype":"venue"
},
  "geometry": {"coordinates":[5.700856,51.382446],"type":"Point"}
}