{
  "type": "Feature",
  "properties": {
    "iso:country":"NL",
    "sg:address":"J A Wentelstr 27",
    "sg:city":"Den Helder",
    "sg:orig_category":"Parketvloeren",
    "sg:phone":"+31 223 630 008",
    "sg:postcode":"1785 HG",
    "sg:province":"Noord-Holland",
    "wof:name":"Bourgondi\u00eb",
    "wof:placetype":"venue"
},
  "geometry": {"coordinates":[4.768445,52.930904],"type":"Point"}
}