{
  "type": "Feature",
  "properties": {
    "iso:country":"NL",
    "sg:address":"Kerkstr 13",
    "sg:city":"Harreveld",
    "sg:orig_category":"Fitnesscentra",
    "sg:phone":"+31 544 375 289",
    "sg:postcode":"7135 JJ",
    "sg:province":"Gelderland",
    "wof:name":"Aquafit",
    "wof:placetype":"venue"
},
  "geometry": {"coordinates":[6.518919,51.976311],"type":"Point"}
}