{
  "type": "Feature",
  "properties": {
    "addr:full":"Heerbaan 73 Millingen A/D Rijn Gelderland 6566 EE",
    "addr:housenumber":"73;a / d",
    "addr:postcode":"6566 ee",
    "addr:street":"Heerbaan;Rijn Gelderland",
    "iso:country":"NL",
    "sg:address":"Heerbaan 73",
    "sg:city":"Millingen A/D Rijn",
    "sg:orig_category":"Beeldende Kunstenaars",
    "sg:phone":"+31 481 431 694",
    "sg:postcode":"6566 EE",
    "sg:province":"Gelderland",
    "wof:name":"Bogaard, P Van Den",
    "wof:placetype":"venue"
},
  "geometry": {"coordinates":[6.048919,51.86116],"type":"Point"}
}