{
  "type": "Feature",
  "properties": {
    "addr:full":"Rykswg Z 148 Geleen Limburg 6161 BT",
    "addr:housenumber":"148",
    "addr:postcode":"6161 bt",
    "addr:street":"Geleen Limburg",
    "iso:country":"NL",
    "sg:address":"Rykswg Z 148",
    "sg:city":"Geleen",
    "sg:orig_category":"Kappers",
    "sg:phone":"+31 46 474 9258",
    "sg:postcode":"6161 BT",
    "sg:province":"Limburg",
    "wof:name":"Dordo Coiffure & Visagie",
    "wof:placetype":"venue"
},
  "geometry": {"coordinates":[5.8232421875,50.9639358521],"type":"Point"}
}