{
  "type": "Feature",
  "properties": {
    "addr:full":"Richtersweg 104 Enschede NL.08 7521 BZ",
    "addr:housenumber":"104",
    "addr:postcode":"7521 bz",
    "addr:street":"Richtersweg",
    "iso:country":"NL",
    "sg:address":"Richtersweg 104",
    "sg:city":"Enschede",
    "sg:orig_category":"Kappers",
    "sg:phone":"+31 53 435 8979",
    "sg:postcode":"7521 BZ",
    "sg:province":"NL.08",
    "wof:name":"Dameskappersbedrijf Keuters",
    "wof:placetype":"venue"
},
  "geometry": {"coordinates":[6.8748168945,52.2238578796],"type":"Point"}
}