{
  "type": "Feature",
  "properties": {
    "addr:full":"Rosegracht 2 Terneuzen Zeeland 4531 HC",
    "addr:housenumber":"2",
    "addr:postcode":"4531 hc",
    "addr:street":"Rosegracht",
    "iso:country":"NL",
    "sg:address":"Rosegracht 2",
    "sg:city":"Terneuzen",
    "sg:orig_category":"Werving And Selectie Van Tijdelijk Personeel And Uitzendkantoren",
    "sg:phone":"+31 115 614 240",
    "sg:postcode":"4531 HC",
    "sg:province":"Zeeland",
    "wof:name":"Uitzendbureau Start",
    "wof:placetype":"venue"
},
  "geometry": {"coordinates":[3.8290851116,51.3349189758],"type":"Point"}
}