{
  "type": "Feature",
  "properties": {
    "addr:full":"Postbus 99 Almelo NL.08 7600 AB",
    "addr:housenumber":"99;nl.08",
    "addr:postcode":"7600 ab",
    "addr:street":"Postbus",
    "iso:country":"NL",
    "sg:address":"Postbus 99",
    "sg:city":"Almelo",
    "sg:orig_category":"Filters - Fabrieken En Groothandel",
    "sg:phone":"+31 546 871 555",
    "sg:postcode":"7600 AB",
    "sg:province":"NL.08",
    "wof:name":"Kiekens Products Bv",
    "wof:placetype":"venue"
},
  "geometry": {"coordinates":[6.664543,52.354954],"type":"Point"}
}