{
  "type": "Feature",
  "properties": {
    "addr:full":"Vermolenweg 25 Geesteren Ov Overijssel 7678 TK",
    "addr:housenumber":"25",
    "addr:postcode":"7678 tk",
    "addr:street":"Vermolenweg;Ov",
    "iso:country":"NL",
    "sg:address":"Vermolenweg 25",
    "sg:city":"Geesteren Ov",
    "sg:orig_category":"Verhuur Bouwmachines",
    "sg:phone":"+31 546 631 570",
    "sg:postcode":"7678 TK",
    "sg:province":"Overijssel",
    "wof:name":"Metselbedrijf Sterlink Bv",
    "wof:placetype":"venue"
},
  "geometry": {"coordinates":[6.715823,52.433922],"type":"Point"}
}