{
  "type": "Feature",
  "properties": {
    "addr:full":"Zuidsngl 70A Amersfoort Utrecht 3811 HD",
    "addr:housenumber":"70a",
    "addr:postcode":"3811 hd",
    "addr:street":"Zuidsngl",
    "iso:country":"NL",
    "sg:address":"Zuidsngl 70A",
    "sg:city":"Amersfoort",
    "sg:orig_category":"Parketvloeren",
    "sg:phone":"+31 33 472 1078",
    "sg:postcode":"3811 HD",
    "sg:province":"Utrecht",
    "sg:website":"http://www.kernparket.nl",
    "wof:name":"Kern Parket",
    "wof:placetype":"venue"
},
  "geometry": {"coordinates":[5.386085,52.152325],"type":"Point"}
}