{
  "type": "Feature",
  "properties": {
    "addr:full":"Bovenboerseweg 45 Wanneperveen NL.08 7946 AL",
    "addr:housenumber":"45;nl.08",
    "addr:postcode":"7946 al",
    "addr:street":"Bovenboerseweg",
    "iso:country":"NL",
    "sg:address":"Bovenboerseweg 45",
    "sg:city":"Wanneperveen",
    "sg:orig_category":"Kansspelen",
    "sg:phone":"+31 522 281 055",
    "sg:postcode":"7946 AL",
    "sg:province":"NL.08",
    "wof:name":"K. Scheer",
    "wof:placetype":"venue"
},
  "geometry": {"coordinates":[6.1212630272,52.7060432434],"type":"Point"}
}