{
  "type": "Feature",
  "properties": {
    "addr:full":"Hoogstr 36 Nieuwpoort Zuid-Holland 2965 AL",
    "addr:housenumber":"36",
    "addr:postcode":"2965 al",
    "addr:street":"Hoogstr",
    "iso:country":"NL",
    "sg:address":"Hoogstr 36",
    "sg:city":"Nieuwpoort",
    "sg:orig_category":"Boekhandels",
    "sg:phone":"+31 184 602 012",
    "sg:postcode":"2965 AL",
    "sg:province":"Zuid-Holland",
    "wof:name":"Wal, P Van Der",
    "wof:placetype":"venue"
},
  "geometry": {"coordinates":[4.869114,51.935394],"type":"Point"}
}