{
  "type": "Feature",
  "properties": {
    "addr:full":"Fultonstraat 8 Ede Gld Gelderland 6716 AX",
    "addr:housenumber":"8",
    "addr:postcode":"6716 ax",
    "addr:street":"Fultonstraat;Gld Gelderland",
    "iso:country":"NL",
    "sg:address":"Fultonstraat 8",
    "sg:city":"Ede Gld",
    "sg:orig_category":"Metaalafval, Schrootrecycling And Sloperijen",
    "sg:phone":"+31 318 639 737",
    "sg:postcode":"6716 AX",
    "sg:province":"Gelderland",
    "wof:name":"Autosloper Van Dooren",
    "wof:placetype":"venue"
},
  "geometry": {"coordinates":[5.62922,52.035389],"type":"Point"}
}