{
  "type": "Feature",
  "properties": {
    "addr:full":"Gasthuisstraat 1 Kaatsheuvel Noord-Brabant 5171 GC",
    "addr:housenumber":"1",
    "addr:postcode":"5171 gc",
    "addr:street":"Gasthuisstraat",
    "iso:country":"NL",
    "sg:address":"Gasthuisstraat 1",
    "sg:city":"Kaatsheuvel",
    "sg:classifiers":[
        {
            "category":"Fast Food",
            "type":"Food & Drink"
        }
    ],
    "sg:phone":"+31 416 280 796",
    "sg:postcode":"5171 GC",
    "sg:province":"Noord-Brabant",
    "sg:tags":[
        "afhaal",
        "restaurant"
    ],
    "wof:name":"Cafetaria De Markt",
    "wof:placetype":"venue"
},
  "geometry": {"coordinates":[5.033903,51.659801],"type":"Point"}
}