{
  "type": "Feature",
  "properties": {
    "iso:country":"NL",
    "sg:address":"Strandweg 6",
    "sg:city":"Ter Heijde",
    "sg:orig_category":"Metaalwerken",
    "sg:phone":"+31 174 212 870",
    "sg:postcode":"2684 VS",
    "sg:province":"Zuid-Holland",
    "wof:name":"C.M. Hoogenraad Kassenbouw",
    "wof:placetype":"venue"
},
  "geometry": {"coordinates":[4.167445,52.028797],"type":"Point"}
}