{
  "type": "Feature",
  "properties": {
    "iso:country":"NL",
    "sg:address":"Bommelsestraat 19",
    "sg:city":"Ophemert",
    "sg:orig_category":"Goederenvervoer Over De Weg",
    "sg:phone":"+31 344 651 221",
    "sg:postcode":"4061 RG",
    "sg:province":"Gelderland",
    "wof:name":"C A Scheurwater",
    "wof:placetype":"venue"
},
  "geometry": {"coordinates":[5.35367,51.83989],"type":"Point"}
}