{
  "type": "Feature",
  "properties": {
    "addr:full":"Postbus 322 Coevorden Drenthe 7740 AH",
    "addr:housenumber":"322",
    "addr:postcode":"7740 ah",
    "addr:street":"Postbus",
    "iso:country":"NL",
    "sg:address":"Postbus 322",
    "sg:city":"Coevorden",
    "sg:orig_category":"Wasserijen",
    "sg:phone":"+31 524 599 699",
    "sg:postcode":"7740 AH",
    "sg:province":"Drenthe",
    "wof:name":"Ens Bv",
    "wof:placetype":"venue"
},
  "geometry": {"coordinates":[6.7389101982,52.6641998291],"type":"Point"}
}