{
  "type": "Feature",
  "properties": {
    "addr:full":"Wim Kanplein 1 Almere Flevoland 1311 LH",
    "addr:housenumber":"1",
    "addr:postcode":"1311 lh",
    "addr:street":"Wim Kanplein;Flevoland",
    "iso:country":"NL",
    "sg:address":"Wim Kanplein 1",
    "sg:city":"Almere",
    "sg:orig_category":"Apothekers",
    "sg:phone":"+31 36 536 3011",
    "sg:postcode":"1311 LH",
    "sg:province":"Flevoland",
    "wof:name":"Apotheker De Notekraker",
    "wof:placetype":"venue"
},
  "geometry": {"coordinates":[5.17968,52.370308],"type":"Point"}
}