{
  "type": "Feature",
  "properties": {
    "iso:country":"NL",
    "sg:address":"Van De Wateringelaan 169",
    "sg:city":"Voorburg",
    "sg:classifiers":[
        {
            "category":"Fast Food",
            "type":"Food & Drink"
        }
    ],
    "sg:phone":"+31 70 385 8340",
    "sg:postcode":"2274 CE",
    "sg:province":"South Holland",
    "sg:tags":[
        "afhaal",
        "restaurant"
    ],
    "wof:name":"Fleuren",
    "wof:placetype":"venue"
},
  "geometry": {"coordinates":[4.345098,52.077709],"type":"Point"}
}