{
  "type": "Feature",
  "properties": {
    "addr:full":"Gentiaan 49 Haaksbergen NL.08 7483 AN",
    "addr:housenumber":"49;nl.08",
    "addr:postcode":"7483 an",
    "addr:street":"Gentiaan",
    "iso:country":"NL",
    "sg:address":"Gentiaan 49",
    "sg:city":"Haaksbergen",
    "sg:orig_category":"Autopoetsbedrijven",
    "sg:phone":"+31 6 22866157",
    "sg:postcode":"7483 AN",
    "sg:province":"NL.08",
    "wof:name":"La Brize",
    "wof:placetype":"venue"
},
  "geometry": {"coordinates":[6.732341,52.165176],"type":"Point"}
}