{
  "type": "Feature",
  "properties": {
    "iso:country":"NL",
    "sg:address":"Gentiaan 49",
    "sg:city":"Haaksbergen",
    "sg:orig_category":"Autopoetsbedrijven",
    "sg:phone":"+31 6 22866157",
    "sg:postcode":"7483 AN",
    "sg:province":"NL.08",
    "wof:name":"La Brize",
    "wof:placetype":"venue"
},
  "geometry": {"coordinates":[6.732341,52.165176],"type":"Point"}
}