{
  "type": "Feature",
  "properties": {
    "addr:full":"Broekakkerwg 16 Gilze Noord-Brabant 5126 BD",
    "addr:housenumber":"16",
    "addr:postcode":"5126 bd",
    "addr:street":"Broekakkerwg",
    "iso:country":"NL",
    "sg:address":"Broekakkerwg 16",
    "sg:city":"Gilze",
    "sg:orig_category":"Houtbewerking",
    "sg:phone":"+31 161 456 248",
    "sg:postcode":"5126 BD",
    "sg:province":"Noord-Brabant",
    "wof:name":"Kroos Bv",
    "wof:placetype":"venue"
},
  "geometry": {"coordinates":[4.946915,51.54847],"type":"Point"}
}