{
  "type": "Feature",
  "properties": {
    "addr:full":"Ln V Nw O Indie 300 S Gravenhage South Holland 2593 CE",
    "addr:housenumber":"300",
    "addr:postcode":"2593 ce",
    "addr:street":"Ln V Nw O Indie;S Gravenhage",
    "iso:country":"NL",
    "sg:address":"Ln V Nw O Indie 300",
    "sg:city":"S Gravenhage",
    "sg:orig_category":"Onderzoekbureaus",
    "sg:phone":"+31 70 344 0640",
    "sg:postcode":"2593 CE",
    "sg:province":"South Holland",
    "sg:website":"http://www.nwo.nl",
    "wof:name":"Ned Org V Wetenschappelijk Onderzoek",
    "wof:placetype":"venue"
},
  "geometry": {"coordinates":[4.34266,52.086121],"type":"Point"}
}