{
  "type": "Feature",
  "properties": {
    "addr:full":"Ribesstr 6 Vaassen Gelderland 8171 XZ",
    "addr:housenumber":"6",
    "addr:postcode":"8171 xz",
    "addr:street":"Ribesstr;Gelderland",
    "iso:country":"NL",
    "sg:address":"Ribesstr 6",
    "sg:city":"Vaassen",
    "sg:orig_category":"Voetbalverenigingen",
    "sg:phone":"+31 578 575 560",
    "sg:postcode":"8171 XZ",
    "sg:province":"Gelderland",
    "wof:name":"Fc Eiland",
    "wof:placetype":"venue"
},
  "geometry": {"coordinates":[5.972218,52.294514],"type":"Point"}
}