{
  "type": "Feature",
  "properties": {
    "addr:full":"Zeestr 97 Beverwyk Noord-Holland 1942 AL",
    "addr:housenumber":"97",
    "addr:postcode":"1942 al",
    "addr:street":"Zeestr",
    "iso:country":"NL",
    "sg:address":"Zeestr 97",
    "sg:city":"Beverwyk",
    "sg:orig_category":"Adviesbureaus Bouwkunde",
    "sg:phone":"+31 251 223 631",
    "sg:postcode":"1942 AL",
    "sg:province":"Noord-Holland",
    "wof:name":"Meijran Partners Bv",
    "wof:placetype":"venue"
},
  "geometry": {"coordinates":[4.649782,52.482586],"type":"Point"}
}