{
  "type": "Feature",
  "properties": {
    "addr:full":"Prof V Bemmelenln 16 Utrecht Utrecht 3571 EM",
    "addr:housenumber":"16",
    "addr:postcode":"3571 em",
    "addr:street":"Prof;Bemmelenln",
    "iso:country":"NL",
    "sg:address":"Prof V Bemmelenln 16",
    "sg:city":"Utrecht",
    "sg:orig_category":"Psychologen",
    "sg:phone":"+31 30 272 2037",
    "sg:postcode":"3571 EM",
    "sg:province":"Utrecht",
    "wof:name":"Psychologische & Orthopedag Prakt",
    "wof:placetype":"venue"
},
  "geometry": {"coordinates":[5.130943,52.109287],"type":"Point"}
}