{
  "type": "Feature",
  "properties": {
    "addr:full":"Marskant 85 Hengelo Ov Overijssel 7551 BT",
    "addr:housenumber":"85",
    "addr:postcode":"7551 bt",
    "addr:street":"Marskant;Ov",
    "iso:country":"NL",
    "sg:address":"Marskant 85",
    "sg:city":"Hengelo Ov",
    "sg:classifiers":[
        {
            "category":"Education",
            "subcategory":"Preschool",
            "type":"Public Place"
        }
    ],
    "sg:phone":"+31 74 291 3764",
    "sg:postcode":"7551 BT",
    "sg:province":"Overijssel",
    "sg:tags":[
        "kleuteronderwijs",
        "basis-"
    ],
    "wof:name":"Openbare Basisschool Willem",
    "wof:placetype":"venue"
},
  "geometry": {"coordinates":[6.788704,52.264969],"type":"Point"}
}