{
  "type": "Feature",
  "properties": {
    "addr:full":"Nibbelinkstraat 22 Hendrik Ido Ambacht Zuid-Holland 3342 VC",
    "addr:housenumber":"22",
    "addr:postcode":"ido ambacht;3342 vc",
    "addr:street":"Nibbelinkstraat",
    "iso:country":"NL",
    "sg:address":"Nibbelinkstraat 22",
    "sg:city":"Hendrik Ido Ambacht",
    "sg:orig_category":"Goederenvervoer Over De Weg",
    "sg:phone":"+31 78 681 3579",
    "sg:postcode":"3342 VC",
    "sg:province":"Zuid-Holland",
    "wof:name":"G. Stolk",
    "wof:placetype":"venue"
},
  "geometry": {"coordinates":[4.628305,51.847893],"type":"Point"}
}