{
  "type": "Feature",
  "properties": {
    "addr:full":"Bossinkkamp 2A Den Ham Ov Overijssel 7683 SL",
    "addr:housenumber":"2a",
    "addr:postcode":"ov;7683 sl",
    "addr:street":"Bossinkkamp",
    "iso:country":"NL",
    "sg:address":"Bossinkkamp 2A",
    "sg:city":"Den Ham Ov",
    "sg:orig_category":"Meubelmakerijen",
    "sg:phone":"+31 546 671 601",
    "sg:postcode":"7683 SL",
    "sg:province":"Overijssel",
    "sg:website":"http://www.meubelmakerijzwiers.nl",
    "wof:name":"Zwiers & Zn Meubelmakerij",
    "wof:placetype":"venue"
},
  "geometry": {"coordinates":[6.496274,52.462387],"type":"Point"}
}