{
  "type": "Feature",
  "properties": {
    "addr:full":"Zoetelaarpassage 36 Almere Flevoland 1315 AZ",
    "addr:housenumber":"36",
    "addr:postcode":"1315",
    "addr:street":"Zoetelaarpassage;Flevoland",
    "iso:country":"NL",
    "sg:address":"Zoetelaarpassage 36",
    "sg:city":"Almere",
    "sg:orig_category":"Verlichting",
    "sg:phone":"+31 36 533 2998",
    "sg:postcode":"1315 AZ",
    "sg:province":"Flevoland",
    "wof:name":"Homelight",
    "wof:placetype":"venue"
},
  "geometry": {"coordinates":[5.215721,52.369198],"type":"Point"}
}