{
  "type": "Feature",
  "properties": {
    "addr:full":"Stationsweg 41 Leiden Zuid-Holland 2312 AT",
    "addr:housenumber":"41",
    "addr:postcode":"2312",
    "addr:street":"Stationsweg",
    "iso:country":"NL",
    "sg:address":"Stationsweg 41",
    "sg:city":"Leiden",
    "sg:orig_category":"Bedrijfs- And Werkgeversorganisaties",
    "sg:phone":"+31 71 525 0500",
    "sg:postcode":"2312 AT",
    "sg:province":"Zuid-Holland",
    "wof:name":"Kamer Van Koophandel En Fabrieken Voor Rijnland",
    "wof:placetype":"venue"
},
  "geometry": {"coordinates":[4.483645,52.165733],"type":"Point"}
}