{
  "type": "Feature",
  "properties": {
    "iso:country":"NL",
    "sg:address":"Volderstr 19",
    "sg:city":"Meerssen",
    "sg:orig_category":"Geluidsinstallaties - Verhuur",
    "sg:phone":"+31 43 364 9458",
    "sg:postcode":"6231 LA",
    "sg:province":"Limburg",
    "wof:name":"Square Sound",
    "wof:placetype":"venue"
},
  "geometry": {"coordinates":[5.757443,50.884716],"type":"Point"}
}