{
  "type": "Feature",
  "properties": {
    "addr:full":"Grt Buren 13 Pingjum Friesland 8749 GD",
    "addr:housenumber":"13",
    "addr:postcode":"8749 gd",
    "addr:street":"Grt Buren",
    "iso:country":"NL",
    "sg:address":"Grt Buren 13",
    "sg:city":"Pingjum",
    "sg:orig_category":"Beeldende Kunstenaars",
    "sg:phone":"+31 517 579 642",
    "sg:postcode":"8749 GD",
    "sg:province":"Friesland",
    "wof:name":"Kingma, Paul",
    "wof:placetype":"venue"
},
  "geometry": {"coordinates":[5.440231,53.115105],"type":"Point"}
}