{
  "type": "Feature",
  "properties": {
    "iso:country":"NL",
    "sg:address":"Pr Hendrikkd 20A",
    "sg:city":"Amsterdam",
    "sg:orig_category":"Parkeergarages",
    "sg:phone":"+31 20 638 5330",
    "sg:postcode":"1012 TL",
    "sg:province":"Noord-Holland",
    "sg:website":"http://www.pmn.nl",
    "wof:name":"Anwb Parking Amsterdam Centraal",
    "wof:placetype":"venue"
},
  "geometry": {"coordinates":[4.896716,52.378853],"type":"Point"}
}