{
  "type": "Feature",
  "properties": {
    "addr:full":"Hoefbladstraat 35 Emmeloord NL. 8302 VM",
    "addr:housenumber":"35",
    "addr:postcode":"8302 vm",
    "addr:street":"Hoefbladstraat;Nl.",
    "iso:country":"NL",
    "sg:address":"Hoefbladstraat 35",
    "sg:city":"Emmeloord",
    "sg:orig_category":"Metaalafval, Schrootrecycling And Sloperijen",
    "sg:phone":"+31 527 699 197",
    "sg:postcode":"8302 VM",
    "sg:province":"NL.",
    "wof:name":"A.P. Van Schoten",
    "wof:placetype":"venue"
},
  "geometry": {"coordinates":[5.743667,52.714401],"type":"Point"}
}