{
  "type": "Feature",
  "properties": {
    "addr:full":"Kosterswg 33 Loenen Gld Gelderland 7371 ES",
    "addr:housenumber":"33",
    "addr:postcode":"7371 es",
    "addr:street":"Kosterswg;Gld Gelderland",
    "iso:country":"NL",
    "sg:address":"Kosterswg 33",
    "sg:city":"Loenen Gld",
    "sg:orig_category":"Pluimveebedrijven En -Handelaren",
    "sg:phone":"+31 55 505 1571",
    "sg:postcode":"7371 ES",
    "sg:province":"Gelderland",
    "wof:name":"Kuiper, W",
    "wof:placetype":"venue"
},
  "geometry": {"coordinates":[6.052318,52.147675],"type":"Point"}
}