{
  "type": "Feature",
  "properties": {
    "addr:full":"Gerberalaan 2 Naaldwijk South Holland 2671 KD",
    "addr:housenumber":"2",
    "addr:postcode":"2671 kd",
    "addr:street":"Gerberalaan",
    "iso:country":"NL",
    "sg:address":"Gerberalaan 2",
    "sg:city":"Naaldwijk",
    "sg:orig_category":"Peuterspeelzalen",
    "sg:phone":"+31 174 628 899",
    "sg:postcode":"2671 KD",
    "sg:province":"South Holland",
    "sg:website":"http://www.samsam.nl",
    "wof:name":"Naaldwijkse Peuterspeelzalen, Sticht",
    "wof:placetype":"venue"
},
  "geometry": {"coordinates":[4.210446,51.990513],"type":"Point"}
}