{
  "type": "Feature",
  "properties": {
    "addr:full":"Bosuillaan 305 Bilthoven Utrecht 3722 XM",
    "addr:housenumber":"305",
    "addr:postcode":"3722 xm",
    "addr:street":"Bosuillaan",
    "iso:country":"NL",
    "sg:address":"Bosuillaan 305",
    "sg:city":"Bilthoven",
    "sg:orig_category":"Boekhouders",
    "sg:phone":"+31 30 225 2581",
    "sg:postcode":"3722 XM",
    "sg:province":"Utrecht",
    "wof:name":"Alliance Francaise Utrecht",
    "wof:placetype":"venue"
},
  "geometry": {"coordinates":[5.216271,52.127117],"type":"Point"}
}