{
  "type": "Feature",
  "properties": {
    "addr:full":"Hoogstraat 22 Gouda South Holland 2801 HH",
    "addr:housenumber":"22",
    "addr:postcode":"2801 hh",
    "addr:street":"Hoogstraat",
    "iso:country":"NL",
    "sg:address":"Hoogstraat 22",
    "sg:city":"Gouda",
    "sg:orig_category":"Opticiens",
    "sg:phone":"+31 182 512 391",
    "sg:postcode":"2801 HH",
    "sg:province":"South Holland",
    "wof:name":"Kempkes-Optiek",
    "wof:placetype":"venue"
},
  "geometry": {"coordinates":[4.7099151611,52.0126686096],"type":"Point"}
}