{
  "type": "Feature",
  "properties": {
    "addr:full":"Lemoen 16 Huissen Gelderland 6852 DS",
    "addr:housenumber":"16",
    "addr:postcode":"6852 ds",
    "addr:street":"Lemoen;Gelderland",
    "iso:country":"NL",
    "sg:address":"Lemoen 16",
    "sg:city":"Huissen",
    "sg:orig_category":"Meubelzaken, Woning- And Keukeninrichting",
    "sg:phone":"+31 26 325 6172",
    "sg:postcode":"6852 DS",
    "sg:province":"Gelderland",
    "wof:name":"Buhr Agenturen",
    "wof:placetype":"venue"
},
  "geometry": {"coordinates":[5.92745,51.942444],"type":"Point"}
}