{
  "type": "Feature",
  "properties": {
    "iso:country":"NL",
    "sg:address":"Nirrewortel 92",
    "sg:city":"De Meern",
    "sg:orig_category":"Binnenhuisarchitectuur",
    "sg:phone":"+31 30 223 2053",
    "sg:postcode":"3453 VZ",
    "sg:province":"Utrecht",
    "sg:website":"http://www.markantdesign.com",
    "wof:name":"Markant",
    "wof:placetype":"venue"
},
  "geometry": {"coordinates":[5.019066,52.079128],"type":"Point"}
}