{
  "type": "Feature",
  "properties": {
    "addr:full":"Dokter P.A. Cornethof 1 Dodewaard Pennsylvania 6669 AZ",
    "addr:housenumber":"1",
    "addr:postcode":"6669 az",
    "addr:street":"Dokter P.A. Cornethof",
    "iso:country":"NL",
    "sg:address":"Dokter P.A. Cornethof 1",
    "sg:city":"Dodewaard",
    "sg:orig_category":"Public Relationbureaus",
    "sg:phone":"+31 488 411 026",
    "sg:postcode":"6669 AZ",
    "sg:province":"Pennsylvania",
    "wof:name":"Top Results",
    "wof:placetype":"venue"
},
  "geometry": {"coordinates":[-77.604507,40.99464],"type":"Point"}
}