{
  "type": "Feature",
  "properties": {
    "addr:full":"Van De Veldelaan 183 Alkmaar Noord-Holland 1816 PD",
    "addr:housenumber":"183",
    "addr:postcode":"1816 pd",
    "addr:street":"Van De Veldelaan",
    "iso:country":"NL",
    "sg:address":"Van De Veldelaan 183",
    "sg:city":"Alkmaar",
    "sg:orig_category":"Boekenuitgeverijen",
    "sg:phone":"+31 72 515 6095",
    "sg:postcode":"1816 PD",
    "sg:province":"Noord-Holland",
    "wof:name":"Kieft Muziekuitgeverij",
    "wof:placetype":"venue"
},
  "geometry": {"coordinates":[4.717056,52.628887],"type":"Point"}
}