{
  "type": "Feature",
  "properties": {
    "iso:country":"NL",
    "sg:address":"Prins Hendriklaan 314",
    "sg:city":"Brunssum",
    "sg:classifiers":[
        {
            "category":"Retail",
            "subcategory":"Photofinishing",
            "type":"Services"
        }
    ],
    "sg:phone":"+31 45 525 6364",
    "sg:postcode":"6443 AE",
    "sg:province":"Limburg",
    "sg:tags":[
        "foto",
        "film"
    ],
    "wof:name":"Fotografie Ber Rijssemus",
    "wof:placetype":"venue"
},
  "geometry": {"coordinates":[5.97872,50.942108],"type":"Point"}
}