{
  "type": "Feature",
  "properties": {
    "iso:country":"NL",
    "sg:address":"Zonnebloemstr 7",
    "sg:city":"Beneden Leeuwen",
    "sg:orig_category":"Peuterspeelzalen",
    "sg:phone":"+31 487 591 840",
    "sg:postcode":"6658 XK",
    "sg:province":"Gelderland",
    "wof:name":"Zonnepit, De",
    "wof:placetype":"venue"
},
  "geometry": {"coordinates":[5.515068,51.877769],"type":"Point"}
}