{
  "type": "Feature",
  "properties": {
    "addr:full":"Kleine Berg 45 Eindhoven Noord-Brabant 5611 JS",
    "addr:housenumber":"45",
    "addr:postcode":"5611 js",
    "addr:street":"Kleine Berg",
    "iso:country":"NL",
    "sg:address":"Kleine Berg 45",
    "sg:city":"Eindhoven",
    "sg:orig_category":"Herenmodezaken",
    "sg:phone":"+31 40 246 4347",
    "sg:postcode":"5611 JS",
    "sg:province":"Noord-Brabant",
    "wof:name":"Jurc Kleding",
    "wof:placetype":"venue"
},
  "geometry": {"coordinates":[5.484105,51.434471],"type":"Point"}
}