{
  "type": "Feature",
  "properties": {
    "addr:full":"Van Berumstraat 2B Zuidwolde Gn Groningen 9785 BG",
    "addr:housenumber":"2b",
    "addr:postcode":"gn;9785",
    "addr:street":"Van Berumstraat",
    "iso:country":"NL",
    "sg:address":"Van Berumstraat 2B",
    "sg:city":"Zuidwolde Gn",
    "sg:orig_category":"Bibliotheken And Openbare Archieven",
    "sg:phone":"+31 50 301 3078",
    "sg:postcode":"9785 BG",
    "sg:province":"Groningen",
    "wof:name":"Openbare Bibliotheek",
    "wof:placetype":"venue"
},
  "geometry": {"coordinates":[6.591138,53.263981],"type":"Point"}
}