{
  "type": "Feature",
  "properties": {
    "addr:full":"Industriewg 66B Wormerveer Noord-Holland 1521 NE",
    "addr:housenumber":"66b;1521",
    "addr:postcode":"ne",
    "addr:street":"Industriewg",
    "iso:country":"NL",
    "sg:address":"Industriewg 66B",
    "sg:city":"Wormerveer",
    "sg:orig_category":"Metaalbewerking",
    "sg:phone":"+31 75 621 9622",
    "sg:postcode":"1521 NE",
    "sg:province":"Noord-Holland",
    "wof:name":"Meerro",
    "wof:placetype":"venue"
},
  "geometry": {"coordinates":[4.78154,52.51759],"type":"Point"}
}