{
  "type": "Feature",
  "properties": {
    "iso:country":"NL",
    "sg:address":"Steenwykerwg 6",
    "sg:city":"Wittelte",
    "sg:classifiers":[
        {
            "category":"Sports & Exercise",
            "subcategory":"Stables",
            "type":"Entertainment"
        }
    ],
    "sg:phone":"+31 521 598 333",
    "sg:postcode":"7986 PP",
    "sg:province":"Drenthe",
    "sg:tags":[
        "maneges"
    ],
    "sg:website":"http://www.inislot.nl",
    "wof:name":"Slot, Ruitersportcentrum Ini",
    "wof:placetype":"venue"
},
  "geometry": {"coordinates":[6.295533,52.833233],"type":"Point"}
}