{
  "type": "Feature",
  "properties": {
    "addr:full":"N Beetspln 101 Hoogeveen Provincie Drenthe 7901 KK",
    "addr:housenumber":"101",
    "addr:postcode":"7901 kk",
    "addr:street":"N;Provincie",
    "iso:country":"NL",
    "sg:address":"N Beetspln 101",
    "sg:city":"Hoogeveen",
    "sg:orig_category":"Kappers",
    "sg:phone":"+31 528 230 578",
    "sg:postcode":"7901 KK",
    "sg:province":"Provincie Drenthe",
    "wof:name":"Jeannette",
    "wof:placetype":"venue"
},
  "geometry": {"coordinates":[6.4765901566,52.7225761414],"type":"Point"}
}