{
  "type": "Feature",
  "properties": {
    "addr:full":"Monierwg 1416 Coevorden Drenthe 7741 KT",
    "addr:housenumber":"1416",
    "addr:postcode":"coevorden;7741 kt",
    "iso:country":"NL",
    "sg:address":"Monierwg 1416",
    "sg:city":"Coevorden",
    "sg:orig_category":"Betonwaren - Fabrieken",
    "sg:phone":"+31 524 515 851",
    "sg:postcode":"7741 KT",
    "sg:province":"Drenthe",
    "wof:name":"Omnia Bv",
    "wof:placetype":"venue"
},
  "geometry": {"coordinates":[6.73501,52.655491],"type":"Point"}
}