{
  "type": "Feature",
  "properties": {
    "addr:full":"Rolderstr 44 Assen Drenthe 9401 AT",
    "addr:housenumber":"44",
    "addr:postcode":"9401",
    "addr:street":"Rolderstr",
    "iso:country":"NL",
    "sg:address":"Rolderstr 44",
    "sg:city":"Assen",
    "sg:orig_category":"Autorijscholen",
    "sg:phone":"+31 592 313 122",
    "sg:postcode":"9401 AT",
    "sg:province":"Drenthe",
    "wof:name":"Braker Autorijschool",
    "wof:placetype":"venue"
},
  "geometry": {"coordinates":[6.565999,52.995899],"type":"Point"}
}