{
  "type": "Feature",
  "properties": {
    "iso:country":"NL",
    "sg:address":"Plaats 15",
    "sg:city":"Bleiswyk",
    "sg:classifiers":[
        {
            "category":"Food & Beverages",
            "subcategory":"Candy",
            "type":"Retail Goods"
        }
    ],
    "sg:phone":"+31 10 521 5280",
    "sg:postcode":"2665 CM",
    "sg:province":"Zuid-Holland",
    "sg:tags":[
        "sport-",
        "en",
        "spelartikelen"
    ],
    "wof:name":"Wooning Sporthuis",
    "wof:placetype":"venue"
},
  "geometry": {"coordinates":[4.530604,52.009918],"type":"Point"}
}