{
  "type": "Feature",
  "properties": {
    "addr:full":"Carrouselweg 72 Apeldoorn Gelderland 7335 PP",
    "addr:housenumber":"72",
    "addr:postcode":"7335 pp",
    "addr:street":"Carrouselweg;Gelderland",
    "iso:country":"NL",
    "sg:address":"Carrouselweg 72",
    "sg:city":"Apeldoorn",
    "sg:orig_category":"Alternatieve Geneeskunde",
    "sg:phone":"+31 55 542 2973",
    "sg:postcode":"7335 PP",
    "sg:province":"Gelderland",
    "wof:name":"H. Spijker",
    "wof:placetype":"venue"
},
  "geometry": {"coordinates":[5.950566,52.193211],"type":"Point"}
}