{
  "type": "Feature",
  "properties": {
    "iso:country":"NL",
    "sg:address":"Sarphatipk 24",
    "sg:city":"Amsterdam",
    "sg:orig_category":"Woninginrichting",
    "sg:phone":"+31 20 676 6683",
    "sg:postcode":"1072 PB",
    "sg:province":"North Holland",
    "wof:name":"Abracadabra Vof",
    "wof:placetype":"venue"
},
  "geometry": {"coordinates":[4.8939990997,52.3536949158],"type":"Point"}
}