{
  "type": "Feature",
  "properties": {
    "addr:full":"De Wulp 8 Vroomshoop NL.08 7681 LV",
    "addr:housenumber":"8;nl.08",
    "addr:postcode":"7681",
    "addr:street":"De Wulp",
    "iso:country":"NL",
    "sg:address":"De Wulp 8",
    "sg:city":"Vroomshoop",
    "sg:orig_category":"Fietsen En Bromfietsen",
    "sg:phone":"+31 546 643 549",
    "sg:postcode":"7681 LV",
    "sg:province":"NL.08",
    "wof:name":"Boes",
    "wof:placetype":"venue"
},
  "geometry": {"coordinates":[6.560683,52.466995],"type":"Point"}
}