{
  "type": "Feature",
  "properties": {
    "addr:full":"Brink 1 Norg Provincie Drenthe 9331 AA",
    "addr:housenumber":"1",
    "addr:postcode":"9331 aa",
    "addr:street":"Brink;Provincie Drenthe",
    "iso:country":"NL",
    "sg:address":"Brink 1",
    "sg:city":"Norg",
    "sg:orig_category":"Verenigingsgebouwen",
    "sg:phone":"+31 592 675 555",
    "sg:postcode":"9331 AA",
    "sg:province":"Provincie Drenthe",
    "wof:name":"Brinkhof, De",
    "wof:placetype":"venue"
},
  "geometry": {"coordinates":[6.461724,53.067257],"type":"Point"}
}