{
  "type": "Feature",
  "properties": {
    "addr:full":"C Lenigestr 22 Makkum Fr Provincie Friesland 8754 CD",
    "addr:housenumber":"22",
    "addr:postcode":"8754 cd",
    "addr:street":"Friesland",
    "iso:country":"NL",
    "sg:address":"C Lenigestr 22",
    "sg:city":"Makkum Fr",
    "sg:orig_category":"Politie",
    "sg:phone":"+31 900 8844",
    "sg:postcode":"8754 CD",
    "sg:province":"Provincie Friesland",
    "wof:name":"Politie",
    "wof:placetype":"venue"
},
  "geometry": {"coordinates":[5.40506,53.057228],"type":"Point"}
}