{
  "type": "Feature",
  "properties": {
    "addr:full":"Eindhovenseweg 67 Waalre Noord-Brabant 5582 HR",
    "addr:housenumber":"67",
    "addr:postcode":"5582 hr",
    "addr:street":"Eindhovenseweg",
    "iso:country":"NL",
    "sg:address":"Eindhovenseweg 67",
    "sg:city":"Waalre",
    "sg:orig_category":"Film-, Tv- And Videoproductie",
    "sg:phone":"+31 40 223 0995",
    "sg:postcode":"5582 HR",
    "sg:province":"Noord-Brabant",
    "wof:name":"Van Otterdijke Sound Design",
    "wof:placetype":"venue"
},
  "geometry": {"coordinates":[5.47748,51.397602],"type":"Point"}
}