{
  "type": "Feature",
  "properties": {
    "iso:country":"NL",
    "sg:address":"Koenestr 16",
    "sg:city":"Amerongen",
    "sg:orig_category":"Administratie- En Boekhoudkantoren",
    "sg:phone":"+31 343 451 244",
    "sg:postcode":"3958 XG",
    "sg:province":"Utrecht",
    "wof:name":"Barneveld, D J Van",
    "wof:placetype":"venue"
},
  "geometry": {"coordinates":[5.460622,52.001423],"type":"Point"}
}