{
  "type": "Feature",
  "properties": {
    "addr:full":"Plantsoen 12 Lage Zwaluwe Noord-Brabant 4926 RB",
    "addr:housenumber":"12",
    "addr:postcode":"zwaluwe;4926 rb",
    "addr:street":"Plantsoen",
    "iso:country":"NL",
    "sg:address":"Plantsoen 12",
    "sg:city":"Lage Zwaluwe",
    "sg:orig_category":"Bibliotheken And Openbare Archieven",
    "sg:phone":"+31 168 486 010",
    "sg:postcode":"4926 RB",
    "sg:province":"Noord-Brabant",
    "wof:name":"Openbare Bibliotheek",
    "wof:placetype":"venue"
},
  "geometry": {"coordinates":[4.709119,51.704674],"type":"Point"}
}