{
  "type": "Feature",
  "properties": {
    "iso:country":"NL",
    "sg:address":"Horsterwg 228",
    "sg:city":"Ermelo",
    "sg:orig_category":"Sauna'S",
    "sg:phone":"+31 341 553 305",
    "sg:postcode":"3853 JH",
    "sg:province":"Gelderland",
    "wof:name":"Palmbosch Sauna",
    "wof:placetype":"venue"
},
  "geometry": {"coordinates":[5.592939,52.310585],"type":"Point"}
}