{
  "type": "Feature",
  "properties": {
    "addr:full":"Buitenpln 76 Amstelveen North Holland 1181 ZE",
    "addr:housenumber":"76",
    "addr:postcode":"1181 ze",
    "addr:street":"Buitenpln",
    "iso:country":"NL",
    "sg:address":"Buitenpln 76",
    "sg:city":"Amstelveen",
    "sg:orig_category":"Bloemen En Planten",
    "sg:phone":"+31 20 441 0327",
    "sg:postcode":"1181 ZE",
    "sg:province":"North Holland",
    "wof:name":"Smit En Zoon, S",
    "wof:placetype":"venue"
},
  "geometry": {"coordinates":[4.863512,52.302158],"type":"Point"}
}