{
  "type": "Feature",
  "properties": {
    "addr:full":"Stationspk 500 Sliedrecht Zuid-Holland 3364 DA",
    "addr:housenumber":"500",
    "addr:postcode":"3364 da",
    "iso:country":"NL",
    "sg:address":"Stationspk 500",
    "sg:city":"Sliedrecht",
    "sg:orig_category":"Elektronische Betaalsystemen",
    "sg:phone":"+31 184 421 818",
    "sg:postcode":"3364 DA",
    "sg:province":"Zuid-Holland",
    "wof:name":"Verklizan Bv",
    "wof:placetype":"venue"
},
  "geometry": {"coordinates":[4.777531,51.828468],"type":"Point"}
}