{
  "type": "Feature",
  "properties": {
    "addr:full":"Djeroekstraat 23 Rotterdam Zuid-Holland 3034 JB",
    "addr:housenumber":"23",
    "addr:postcode":"3034 jb",
    "addr:street":"Djeroekstraat",
    "iso:country":"NL",
    "sg:address":"Djeroekstraat 23",
    "sg:city":"Rotterdam",
    "sg:orig_category":"Loodgieterswerk, Verwarming And Sanitaire Installaties",
    "sg:phone":"+31 10 412 8766",
    "sg:postcode":"3034 JB",
    "sg:province":"Zuid-Holland",
    "wof:name":"Ejas Onderhoudsbedrijf",
    "wof:placetype":"venue"
},
  "geometry": {"coordinates":[4.494923,51.931557],"type":"Point"}
}