{
  "type": "Feature",
  "properties": {
    "addr:full":"Vlinderveen 274 Spijkenisse Zuid-Holland 3205 EK",
    "addr:housenumber":"274",
    "addr:postcode":"3205 ek",
    "addr:street":"Vlinderveen",
    "iso:country":"NL",
    "sg:address":"Vlinderveen 274",
    "sg:city":"Spijkenisse",
    "sg:orig_category":"Paramedische Behandelingen",
    "sg:phone":"+31 181 642 066",
    "sg:postcode":"3205 EK",
    "sg:province":"Zuid-Holland",
    "wof:name":"Samenwerkende Logopedisten",
    "wof:placetype":"venue"
},
  "geometry": {"coordinates":[4.342724,51.83429],"type":"Point"}
}