{
  "type": "Feature",
  "properties": {
    "addr:full":"Lyzy 15 Huizen North Holland 1276 GH",
    "addr:housenumber":"15",
    "addr:postcode":"1276 gh",
    "addr:street":"Lyzy",
    "iso:country":"NL",
    "sg:address":"Lyzy 15",
    "sg:city":"Huizen",
    "sg:orig_category":"Modevakscholen",
    "sg:phone":"+31 35 525 4184",
    "sg:postcode":"1276 GH",
    "sg:province":"North Holland",
    "wof:name":"Ensaid",
    "wof:placetype":"venue"
},
  "geometry": {"coordinates":[5.23421,52.29504],"type":"Point"}
}