{
  "type": "Feature",
  "properties": {
    "iso:country":"NL",
    "sg:address":"Havercampln 18",
    "sg:city":"Heiloo",
    "sg:orig_category":"Kunstnijverheid",
    "sg:phone":"+31 72 533 7841",
    "sg:postcode":"1851 XD",
    "sg:province":"Noord-Holland",
    "wof:name":"Sarana",
    "wof:placetype":"venue"
},
  "geometry": {"coordinates":[4.700367,52.595333],"type":"Point"}
}