{
  "type": "Feature",
  "properties": {
    "addr:full":"Havercampln 18 Heiloo Noord-Holland 1851 XD",
    "addr:housenumber":"18",
    "addr:postcode":"1851 xd",
    "addr:street":"Havercampln",
    "iso:country":"NL",
    "sg:address":"Havercampln 18",
    "sg:city":"Heiloo",
    "sg:orig_category":"Kunstnijverheid",
    "sg:phone":"+31 72 533 7841",
    "sg:postcode":"1851 XD",
    "sg:province":"Noord-Holland",
    "wof:name":"Sarana",
    "wof:placetype":"venue"
},
  "geometry": {"coordinates":[4.700367,52.595333],"type":"Point"}
}