{
  "type": "Feature",
  "properties": {
    "iso:country":"NL",
    "sg:address":"Lombokwg 2",
    "sg:city":"Noordwolde Fr",
    "sg:orig_category":"Stukadoorsbedrijven",
    "sg:phone":"+31 561 433 343",
    "sg:postcode":"8391 KG",
    "sg:province":"Friesland",
    "wof:name":"Ge-Be Schilderservice",
    "wof:placetype":"venue"
},
  "geometry": {"coordinates":[6.14738,52.873951],"type":"Point"}
}