{
  "type": "Feature",
  "properties": {
    "addr:full":"Lotweg 36 Anna Paulowna Noord-Holland 1761 JG",
    "addr:housenumber":"36",
    "addr:postcode":"1761 jg",
    "addr:street":"Lotweg",
    "iso:country":"NL",
    "sg:address":"Lotweg 36",
    "sg:city":"Anna Paulowna",
    "sg:orig_category":"Technische Studies And Onderzoek",
    "sg:phone":"+31 223 531 277",
    "sg:postcode":"1761 JG",
    "sg:province":"Noord-Holland",
    "wof:name":"Kaan Ontwerpen",
    "wof:placetype":"venue"
},
  "geometry": {"coordinates":[4.897541,52.867798],"type":"Point"}
}