{
  "type": "Feature",
  "properties": {
    "addr:full":"Nieuwe Spiegelstraat 60 Amsterdam Noord-Holland 1017 DH",
    "addr:housenumber":"60",
    "addr:postcode":"1017 dh",
    "addr:street":"Nieuwe Spiegelstraat",
    "iso:country":"NL",
    "sg:address":"Nieuwe Spiegelstraat 60",
    "sg:city":"Amsterdam",
    "sg:orig_category":"Kunst And Kunstenaarsbenodigdheden",
    "sg:phone":"+31 20 638 2674",
    "sg:postcode":"1017 DH",
    "sg:province":"Noord-Holland",
    "wof:name":"Studio 2000 Art Gallery",
    "wof:placetype":"venue"
},
  "geometry": {"coordinates":[4.888292,52.363266],"type":"Point"}
}