{
  "type": "Feature",
  "properties": {
    "addr:full":"Kievit 12 Baarle Nassau Noord-Brabant 5111 HD",
    "addr:housenumber":"12",
    "addr:postcode":"5111 hd",
    "addr:street":"Kievit",
    "iso:country":"NL",
    "sg:address":"Kievit 12",
    "sg:city":"Baarle Nassau",
    "sg:orig_category":"Administratie- En Boekhoudkantoren",
    "sg:phone":"+31 13 507 6232",
    "sg:postcode":"5111 HD",
    "sg:province":"Noord-Brabant",
    "wof:name":"Leijte Bv, W",
    "wof:placetype":"venue"
},
  "geometry": {"coordinates":[4.961214,51.427097],"type":"Point"}
}