{
  "type": "Feature",
  "properties": {
    "addr:full":"Johan Wagenaarlaan 2 Leidschendam Zuid-Holland 2264 VZ",
    "addr:housenumber":"2",
    "addr:postcode":"2264 vz",
    "addr:street":"Johan Wagenaarlaan",
    "iso:country":"NL",
    "sg:address":"Johan Wagenaarlaan 2",
    "sg:city":"Leidschendam",
    "sg:orig_category":"Boekhouders",
    "sg:phone":"+31 70 327 4868",
    "sg:postcode":"2264 VZ",
    "sg:province":"Zuid-Holland",
    "wof:name":"Admin & Ass Kant J A Vd Linden",
    "wof:placetype":"venue"
},
  "geometry": {"coordinates":[4.395285,52.089859],"type":"Point"}
}