{
  "type": "Feature",
  "properties": {
    "addr:full":"De Kempen 9 Veghel North Brabant 5461 HL",
    "addr:housenumber":"9",
    "addr:postcode":"5461 hl",
    "addr:street":"De Kempen",
    "iso:country":"NL",
    "sg:address":"De Kempen 9",
    "sg:city":"Veghel",
    "sg:orig_category":"Schoenen",
    "sg:phone":"+31 413 310 289",
    "sg:postcode":"5461 HL",
    "sg:province":"North Brabant",
    "sg:website":"http://www.scapino.nl",
    "wof:name":"Scapino",
    "wof:placetype":"venue"
},
  "geometry": {"coordinates":[5.54658,51.616692],"type":"Point"}
}