{
  "type": "Feature",
  "properties": {
    "addr:full":"Molenveld 11 Hippolytushoef North Holland 1777 HN",
    "addr:housenumber":"11",
    "addr:postcode":"1777 hn",
    "addr:street":"Molenveld",
    "iso:country":"NL",
    "sg:address":"Molenveld 11",
    "sg:city":"Hippolytushoef",
    "sg:orig_category":"Autokeuringen",
    "sg:phone":"+31 227 593 131",
    "sg:postcode":"1777 HN",
    "sg:province":"North Holland",
    "wof:name":"Schadenet Klink",
    "wof:placetype":"venue"
},
  "geometry": {"coordinates":[4.950174,52.902786],"type":"Point"}
}