{
  "type": "Feature",
  "properties": {
    "addr:full":"Slotenmakerstr 17 Zwolle NL.08 8043 DJ",
    "addr:housenumber":"17",
    "addr:postcode":"8043 dj",
    "addr:street":"Slotenmakerstr",
    "iso:country":"NL",
    "sg:address":"Slotenmakerstr 17",
    "sg:city":"Zwolle",
    "sg:orig_category":"Verzekeringen - Verzekeringskantoren",
    "sg:phone":"+31 38 420 1849",
    "sg:postcode":"8043 DJ",
    "sg:province":"NL.08",
    "wof:name":"Gyzen, G",
    "wof:placetype":"venue"
},
  "geometry": {"coordinates":[6.067038,52.530357],"type":"Point"}
}