{
  "type": "Feature",
  "properties": {
    "addr:full":"Pr Bernhardln 1 De Enk Enkhuizen Noord-Holland 1601 LT",
    "addr:housenumber":"1",
    "addr:postcode":"1601 lt",
    "addr:street":"De Enk",
    "iso:country":"NL",
    "sg:address":"Pr Bernhardln 1 De Enk",
    "sg:city":"Enkhuizen",
    "sg:orig_category":"Tehuizen",
    "sg:phone":"+31 228 316 800",
    "sg:postcode":"1601 LT",
    "sg:province":"Noord-Holland",
    "wof:name":"Philadelphia Voorzieningen, Sticht",
    "wof:placetype":"venue"
},
  "geometry": {"coordinates":[5.290085,52.703674],"type":"Point"}
}