{
  "type": "Feature",
  "properties": {
    "addr:full":"Bankastr 10 S Gravenhage Zuid-Holland 2585 EN",
    "addr:housenumber":"10 s",
    "addr:postcode":"2585 en",
    "addr:street":"Bankastr",
    "iso:country":"NL",
    "sg:address":"Bankastr 10",
    "sg:city":"S Gravenhage",
    "sg:orig_category":"Woninginrichting",
    "sg:phone":"+31 70 351 4657",
    "sg:postcode":"2585 EN",
    "sg:province":"Zuid-Holland",
    "wof:name":"Anna Home",
    "wof:placetype":"venue"
},
  "geometry": {"coordinates":[4.2977700233,52.0947990417],"type":"Point"}
}