{
  "type": "Feature",
  "properties": {
    "iso:country":"NL",
    "sg:address":"Herenwg 101",
    "sg:city":"Vinkeveen",
    "sg:orig_category":"Fietsen En Bromfietsen",
    "sg:phone":"+31 297 262 099",
    "sg:postcode":"3645 DG",
    "sg:province":"Utrecht",
    "wof:name":"Slingerland, Piet",
    "wof:placetype":"venue"
},
  "geometry": {"coordinates":[4.93451,52.216648],"type":"Point"}
}