{
  "type": "Feature",
  "properties": {
    "iso:country":"NL",
    "sg:address":"Kobaltwg 27",
    "sg:city":"Utrecht",
    "sg:orig_category":"Pompen",
    "sg:phone":"+31 30 242 5678",
    "sg:postcode":"3542 CE",
    "sg:province":"Utrecht",
    "sg:website":"http://www.abspumps.com",
    "wof:name":"Abs Pompen Bv",
    "wof:placetype":"venue"
},
  "geometry": {"coordinates":[5.049606,52.115219],"type":"Point"}
}