{
  "type": "Feature",
  "properties": {
    "iso:country":"NL",
    "sg:address":"Jaromirgaarde 425",
    "sg:city":"Apeldoorn",
    "sg:orig_category":"Psychologen",
    "sg:phone":"+31 55 542 8564",
    "sg:postcode":"7329 CS",
    "sg:province":"Gelderland",
    "wof:name":"Scheer, Van Der",
    "wof:placetype":"venue"
},
  "geometry": {"coordinates":[5.997802,52.200645],"type":"Point"}
}