{
  "type": "Feature",
  "properties": {
    "addr:full":"Brugpln 1 Lelystad Flevoland 8223 AK",
    "addr:housenumber":"1",
    "addr:postcode":"8223 ak",
    "addr:street":"Brugpln;Flevoland",
    "iso:country":"NL",
    "sg:address":"Brugpln 1",
    "sg:city":"Lelystad",
    "sg:orig_category":"Exploitatie- Maatschappijen",
    "sg:phone":"+31 320 221 711",
    "sg:postcode":"8223 AK",
    "sg:province":"Flevoland",
    "wof:name":"Emwo Ii Bv",
    "wof:placetype":"venue"
},
  "geometry": {"coordinates":[5.484404,52.520504],"type":"Point"}
}