{
  "type": "Feature",
  "properties": {
    "addr:full":"Vliegveldwg 32 Maastricht Airport Limburg 6199 AD",
    "addr:housenumber":"32",
    "addr:postcode":"6199 ad",
    "addr:street":"Vliegveldwg",
    "iso:country":"NL",
    "sg:address":"Vliegveldwg 32",
    "sg:city":"Maastricht Airport",
    "sg:orig_category":"Luchtvrachtexpediteurs",
    "sg:phone":"+31 43 308 8000",
    "sg:postcode":"6199 AD",
    "sg:province":"Limburg",
    "sg:website":"http://www.panalpina.com",
    "wof:name":"Panalpina Bv",
    "wof:placetype":"venue"
},
  "geometry": {"coordinates":[5.778855,50.924934],"type":"Point"}
}