{
  "type": "Feature",
  "properties": {
    "addr:full":"Veldzoom 24 Reeuwyk South Holland 2811 BL",
    "addr:housenumber":"24",
    "addr:postcode":"2811 bl",
    "addr:street":"Veldzoom",
    "iso:country":"NL",
    "sg:address":"Veldzoom 24",
    "sg:city":"Reeuwyk",
    "sg:orig_category":"Schilders",
    "sg:phone":"+31 182 399 660",
    "sg:postcode":"2811 BL",
    "sg:province":"South Holland",
    "wof:name":"Gerritsen Schildersbedrijf",
    "wof:placetype":"venue"
},
  "geometry": {"coordinates":[4.722182,52.050518],"type":"Point"}
}