{
  "type": "Feature",
  "properties": {
    "addr:full":"Hoofdstr 24 Bergambacht Zuid-Holland 2861 AP",
    "addr:housenumber":"24",
    "addr:postcode":"2861 ap",
    "addr:street":"Hoofdstr",
    "iso:country":"NL",
    "sg:address":"Hoofdstr 24",
    "sg:city":"Bergambacht",
    "sg:classifiers":[
        {
            "category":"Food & Beverages",
            "subcategory":"Bakery",
            "type":"Retail Goods"
        }
    ],
    "sg:phone":"+31 182 350 747",
    "sg:postcode":"2861 AP",
    "sg:province":"Zuid-Holland",
    "sg:tags":[
        "brood",
        "en",
        "banket"
    ],
    "wof:name":"Eijk, Jan Van Der",
    "wof:placetype":"venue"
},
  "geometry": {"coordinates":[4.782795,51.93306],"type":"Point"}
}