{
  "type": "Feature",
  "properties": {
    "addr:full":"Poldermolen 21 Maassluis Zuid-Holland 3146 SH",
    "addr:housenumber":"21;3146",
    "addr:postcode":"sh",
    "addr:street":"Poldermolen",
    "iso:country":"NL",
    "sg:address":"Poldermolen 21",
    "sg:city":"Maassluis",
    "sg:orig_category":"Sportverenigingen En Ontspannings- Verenigingen",
    "sg:phone":"+31 10 592 1684",
    "sg:postcode":"3146 SH",
    "sg:province":"Zuid-Holland",
    "wof:name":"Gophers Honk- En Softbalver",
    "wof:placetype":"venue"
},
  "geometry": {"coordinates":[4.227811,51.941746],"type":"Point"}
}