{
  "type": "Feature",
  "properties": {
    "addr:full":"Postbus 15368 Amsterdam Noord-Brabant 1001 MJ",
    "addr:postcode":"15368;1001 mj",
    "addr:street":"Postbus",
    "iso:country":"NL",
    "sg:address":"Postbus 15368",
    "sg:city":"Amsterdam",
    "sg:orig_category":"Modellenbureaus En Modellen Freelance",
    "sg:phone":"+31 20 600 7303",
    "sg:postcode":"1001 MJ",
    "sg:province":"Noord-Brabant",
    "wof:name":"Agency For Make-Up & Hair",
    "wof:placetype":"venue"
},
  "geometry": {"coordinates":[4.89319,52.373119],"type":"Point"}
}