{
  "type": "Feature",
  "properties": {
    "iso:country":"NL",
    "sg:address":"St Jorisstg 25",
    "sg:city":"Leiden",
    "sg:orig_category":"Boekhandels",
    "sg:phone":"+31 71 516 0592",
    "sg:postcode":"2311 JA",
    "sg:province":"Zuid-Holland",
    "wof:name":"Kooyker",
    "wof:placetype":"venue"
},
  "geometry": {"coordinates":[4.494434,52.155067],"type":"Point"}
}