{
  "type": "Feature",
  "properties": {
    "addr:full":"Breestr 28 Amersfoort Utrecht 3811 BJ",
    "addr:housenumber":"28",
    "addr:postcode":"3811 bj",
    "addr:street":"Breestr",
    "iso:country":"NL",
    "sg:address":"Breestr 28",
    "sg:city":"Amersfoort",
    "sg:orig_category":"Administratie- En Boekhoudkantoren",
    "sg:phone":"+31 33 461 3810",
    "sg:postcode":"3811 BJ",
    "sg:province":"Utrecht",
    "wof:name":"Hogenboom, A J M",
    "wof:placetype":"venue"
},
  "geometry": {"coordinates":[5.3865599632,52.1559257507],"type":"Point"}
}