{
  "type": "Feature",
  "properties": {
    "addr:full":"Oosterstr 71 Leiden South Holland 2315 LE",
    "addr:housenumber":"71",
    "addr:postcode":"2315 le",
    "addr:street":"Oosterstr",
    "iso:country":"NL",
    "sg:address":"Oosterstr 71",
    "sg:city":"Leiden",
    "sg:orig_category":"Verbouwingen",
    "sg:phone":"+31 71 521 6647",
    "sg:postcode":"2315 LE",
    "sg:province":"South Holland",
    "wof:name":"Vos, H J C De",
    "wof:placetype":"venue"
},
  "geometry": {"coordinates":[4.507538,52.159019],"type":"Point"}
}