{
  "type": "Feature",
  "properties": {
    "iso:country":"NL",
    "sg:address":"Hoogstr 324",
    "sg:city":"Eindhoven",
    "sg:orig_category":"Fietsen En Bromfietsen",
    "sg:phone":"+31 40 257 1931",
    "sg:postcode":"5654 NJ",
    "sg:province":"Noord-Brabant",
    "sg:website":"http://www.rijwielcentrale.com",
    "wof:name":"Rijwielcentrale, De",
    "wof:placetype":"venue"
},
  "geometry": {"coordinates":[5.45901,51.420891],"type":"Point"}
}