{
  "type": "Feature",
  "properties": {
    "addr:full":"Raamwg 17 S Gravenhage Zuid-Holland 2596 HL",
    "addr:housenumber":"17;gravenhage",
    "addr:postcode":"2596 hl",
    "addr:street":"Raamwg;S",
    "iso:country":"NL",
    "sg:address":"Raamwg 17",
    "sg:city":"S Gravenhage",
    "sg:orig_category":"Psychologen",
    "sg:phone":"+31 70 338 8279",
    "sg:postcode":"2596 HL",
    "sg:province":"Zuid-Holland",
    "wof:name":"Esp\u00e9rance, L'",
    "wof:placetype":"venue"
},
  "geometry": {"coordinates":[4.31846,52.093311],"type":"Point"}
}