{
  "type": "Feature",
  "properties": {
    "addr:full":"Van Voorschotenlaan 27 'S Gravenhage Zuid-Holland 2597 PA",
    "addr:housenumber":"27",
    "addr:postcode":"2597 pa",
    "addr:street":"Van Voorschotenlaan;' S",
    "iso:country":"NL",
    "sg:address":"Van Voorschotenlaan 27",
    "sg:city":"'S Gravenhage",
    "sg:orig_category":"Verzekeringen",
    "sg:phone":"+31 70 328 2467",
    "sg:postcode":"2597 PA",
    "sg:province":"Zuid-Holland",
    "wof:name":"Hogenbirk-Feller Ass",
    "wof:placetype":"venue"
},
  "geometry": {"coordinates":[4.312763,52.101849],"type":"Point"}
}