{
  "type": "Feature",
  "properties": {
    "addr:full":"Piazza Center 44 Gorinchem Zuid-Holland 4204 BR",
    "addr:housenumber":"44",
    "addr:postcode":"4204 br",
    "addr:street":"Piazza Center",
    "iso:country":"NL",
    "sg:address":"Piazza Center 44",
    "sg:city":"Gorinchem",
    "sg:orig_category":"Verlichting And Huishoudartikelen",
    "sg:phone":"+31 183 631 941",
    "sg:postcode":"4204 BR",
    "sg:province":"Zuid-Holland",
    "wof:name":"Vof Electrobert",
    "wof:placetype":"venue"
},
  "geometry": {"coordinates":[4.962753,51.837112],"type":"Point"}
}