{
  "type": "Feature",
  "properties": {
    "addr:full":"Wouwermanstr 13-15 S Gravenhage Zuid-Holland 2525 KM",
    "addr:housenumber":"13-15;gravenhage",
    "addr:street":"S;2525 Km",
    "iso:country":"NL",
    "sg:address":"Wouwermanstr 13-15",
    "sg:city":"S Gravenhage",
    "sg:classifiers":[
        {
            "category":"Retail",
            "subcategory":"Auto Repair",
            "type":"Services"
        }
    ],
    "sg:phone":"+31 70 380 8589",
    "sg:postcode":"2525 KM",
    "sg:province":"Zuid-Holland",
    "sg:tags":[
        "garage"
    ],
    "wof:name":"Euro",
    "wof:placetype":"venue"
},
  "geometry": {"coordinates":[4.30248,52.062462],"type":"Point"}
}