{
  "type": "Feature",
  "properties": {
    "addr:full":"Avenbeeck 59 Hillegom Zuid-Holland 2182 RT",
    "addr:housenumber":"59",
    "addr:postcode":"2182 rt",
    "addr:street":"Avenbeeck",
    "iso:country":"NL",
    "sg:address":"Avenbeeck 59",
    "sg:city":"Hillegom",
    "sg:orig_category":"Bloemen And Planten Gh",
    "sg:phone":"+31 252 520 312",
    "sg:postcode":"2182 RT",
    "sg:province":"Zuid-Holland",
    "wof:name":"F.J.E. De Kort Bv",
    "wof:placetype":"venue"
},
  "geometry": {"coordinates":[4.584854,52.286072],"type":"Point"}
}