{
  "type": "Feature",
  "properties": {
    "addr:full":"Panhuizerweg 14 Kesteren Gelderland 4041 CN",
    "addr:housenumber":"14",
    "addr:postcode":"4041 cn",
    "addr:street":"Panhuizerweg;Gelderland",
    "iso:country":"NL",
    "sg:address":"Panhuizerweg 14",
    "sg:city":"Kesteren",
    "sg:orig_category":"Autokeuringen",
    "sg:phone":"+31 488 482 999",
    "sg:postcode":"4041 CN",
    "sg:province":"Gelderland",
    "wof:name":"A.M.E. Engineering",
    "wof:placetype":"venue"
},
  "geometry": {"coordinates":[5.587855,51.935787],"type":"Point"}
}