{
  "type": "Feature",
  "properties": {
    "iso:country":"NL",
    "sg:address":"Eikenlaan 235",
    "sg:city":"Alphen Aan Den Rijn",
    "sg:orig_category":"Airconditioning And Ventilatie",
    "sg:phone":"+31 172 432 661",
    "sg:postcode":"2404 BP",
    "sg:province":"Zuid-Holland",
    "wof:name":"Ponsioen Installatietechniek Bv",
    "wof:placetype":"venue"
},
  "geometry": {"coordinates":[4.641372,52.133194],"type":"Point"}
}