{
  "type": "Feature",
  "properties": {
    "addr:full":"Voltahof 1 Joure Friesland 8501 XP",
    "addr:housenumber":"1",
    "addr:postcode":"8501 xp",
    "addr:street":"Voltahof",
    "iso:country":"NL",
    "sg:address":"Voltahof 1",
    "sg:city":"Joure",
    "sg:orig_category":"Loopbaanbegeleiding",
    "sg:phone":"+31 513 626 830",
    "sg:postcode":"8501 XP",
    "sg:province":"Friesland",
    "wof:name":"Ap & B",
    "wof:placetype":"venue"
},
  "geometry": {"coordinates":[5.78727,52.956802],"type":"Point"}
}