{
  "type": "Feature",
  "properties": {
    "addr:full":"Lutkeberg 23 Geesteren Ov Overijssel 7678 AJ",
    "addr:housenumber":"23",
    "addr:postcode":"7678 aj",
    "addr:street":"Lutkeberg;Ov",
    "iso:country":"NL",
    "sg:address":"Lutkeberg 23",
    "sg:city":"Geesteren Ov",
    "sg:orig_category":"Verzekeringen - Verzekeringskantoren",
    "sg:phone":"+31 546 631 629",
    "sg:postcode":"7678 AJ",
    "sg:province":"Overijssel",
    "wof:name":"Schr\u00f6der",
    "wof:placetype":"venue"
},
  "geometry": {"coordinates":[6.730465,52.418552],"type":"Point"}
}