{
  "type": "Feature",
  "properties": {
    "iso:country":"NL",
    "sg:address":"Dorpsstr 185",
    "sg:city":"Zuid Beyerland",
    "sg:classifiers":[
        {
            "category":"Retail",
            "subcategory":"Auto Repair",
            "type":"Services"
        }
    ],
    "sg:phone":"+31 186 661 310",
    "sg:postcode":"3284 AG",
    "sg:province":"Zuid-Holland",
    "sg:tags":[
        "garage"
    ],
    "wof:name":"Maasdam & Zn, P",
    "wof:placetype":"venue"
},
  "geometry": {"coordinates":[4.366671,51.749878],"type":"Point"}
}