{
  "type": "Feature",
  "properties": {
    "addr:full":"Merkesstr 8 Utrecht Utrecht 3584 BG",
    "addr:housenumber":"8",
    "addr:postcode":"3584",
    "addr:street":"Merkesstr",
    "iso:country":"NL",
    "sg:address":"Merkesstr 8",
    "sg:city":"Utrecht",
    "sg:orig_category":"Video - Faciliteiten En Producties",
    "sg:phone":"+31 30 276 0279",
    "sg:postcode":"3584 BG",
    "sg:province":"Utrecht",
    "sg:website":"http://www.radicalfilm.nl",
    "wof:name":"Radical",
    "wof:placetype":"venue"
},
  "geometry": {"coordinates":[5.146063,52.09597],"type":"Point"}
}