{
  "type": "Feature",
  "properties": {
    "addr:full":"Bisschopsmolenstr 85 Etten Leur Noord-Brabant 4876 AJ",
    "addr:housenumber":"85",
    "addr:postcode":"4876 aj",
    "addr:street":"Bisschopsmolenstr",
    "iso:country":"NL",
    "sg:address":"Bisschopsmolenstr 85",
    "sg:city":"Etten Leur",
    "sg:orig_category":"Kantoor- En Interieurbeplanting",
    "sg:phone":"+31 76 503 5855",
    "sg:postcode":"4876 AJ",
    "sg:province":"Noord-Brabant",
    "wof:name":"Fleur 85",
    "wof:placetype":"venue"
},
  "geometry": {"coordinates":[4.6362171173,51.5665931702],"type":"Point"}
}