{
  "type": "Feature",
  "properties": {
    "addr:full":"Den Elding 81 Gemert Noord-Brabant 5421 MB",
    "addr:housenumber":"81",
    "addr:postcode":"5421 mb",
    "addr:street":"Den Elding",
    "iso:country":"NL",
    "sg:address":"Den Elding 81",
    "sg:city":"Gemert",
    "sg:orig_category":"Schilders",
    "sg:phone":"+31 492 365 345",
    "sg:postcode":"5421 MB",
    "sg:province":"Noord-Brabant",
    "wof:name":"Bievo",
    "wof:placetype":"venue"
},
  "geometry": {"coordinates":[5.677017,51.563622],"type":"Point"}
}