{
  "type": "Feature",
  "properties": {
    "addr:full":"Osdorppln 712 Amsterdam Noord-Holland 1068 TC",
    "addr:housenumber":"712",
    "addr:postcode":"1068 tc",
    "iso:country":"NL",
    "sg:address":"Osdorppln 712",
    "sg:city":"Amsterdam",
    "sg:orig_category":"Natuurvoeding En Reformartikelen",
    "sg:phone":"+31 20 619 1272",
    "sg:postcode":"1068 TC",
    "sg:province":"Noord-Holland",
    "sg:website":"http://www.vitaminstore.nl",
    "wof:name":"Vitamin Store",
    "wof:placetype":"venue"
},
  "geometry": {"coordinates":[4.805169,52.358967],"type":"Point"}
}