{
  "type": "Feature",
  "properties": {
    "iso:country":"NL",
    "sg:address":"D Laanwg 28",
    "sg:city":"Almere",
    "sg:orig_category":"Koeriersdiensten",
    "sg:phone":"+31 36 546 5414",
    "sg:postcode":"1321 KE",
    "sg:province":"Flevoland",
    "sg:website":"http://www.impact-st.nl",
    "wof:name":"Impact Sneltransport",
    "wof:placetype":"venue"
},
  "geometry": {"coordinates":[5.189186,52.356258],"type":"Point"}
}