{
  "type": "Feature",
  "properties": {
    "iso:country":"NL",
    "sg:address":"W Bontekoestr 34",
    "sg:city":"Hilversum",
    "sg:orig_category":"Scholen Voor Basisonderwijs",
    "sg:phone":"+31 35 685 8266",
    "sg:postcode":"1212 CB",
    "sg:province":"North Holland",
    "wof:name":"Trimaran, De",
    "wof:placetype":"venue"
},
  "geometry": {"coordinates":[5.1951708794,52.2168464661],"type":"Point"}
}