{
  "type": "Feature",
  "properties": {
    "addr:full":"Handelswg 7 Bladel Noord-Brabant 5531 AE",
    "addr:housenumber":"7",
    "addr:postcode":"5531 ae",
    "addr:street":"Handelswg",
    "iso:country":"NL",
    "sg:address":"Handelswg 7",
    "sg:city":"Bladel",
    "sg:orig_category":"Duiven En Duivensport - Artikelen",
    "sg:phone":"+31 411 674 635",
    "sg:postcode":"5531 AE",
    "sg:province":"Noord-Brabant",
    "sg:website":"http://www.npo.nl",
    "wof:name":"Oost-Brabant Postduivenver, Afd",
    "wof:placetype":"venue"
},
  "geometry": {"coordinates":[5.203126,51.357052],"type":"Point"}
}