{
  "type": "Feature",
  "properties": {
    "addr:full":"M J V Olmstr 54 Winschoten Groningen 9672 AE",
    "addr:housenumber":"54",
    "addr:postcode":"9672 ae",
    "addr:street":"M J V Olmstr",
    "iso:country":"NL",
    "sg:address":"M J V Olmstr 54",
    "sg:city":"Winschoten",
    "sg:classifiers":[
        {
            "category":"Shopping",
            "subcategory":"News",
            "type":"Retail Goods"
        }
    ],
    "sg:phone":"+31 597 431 120",
    "sg:postcode":"9672 AE",
    "sg:province":"Groningen",
    "sg:tags":[
        "maandbladen",
        "en",
        "week-"
    ],
    "sg:website":"http://www.waarnaartoe.nl",
    "wof:name":"Vakantie & Vrije Tijd Vof",
    "wof:placetype":"venue"
},
  "geometry": {"coordinates":[7.0451450348,53.1465797424],"type":"Point"}
}