{
  "type": "Feature",
  "properties": {
    "addr:full":"Paramasievaan 10 Ameide Zuid-Holland 4233 EX",
    "addr:housenumber":"10",
    "addr:postcode":"4233 ex",
    "addr:street":"Paramasievaan",
    "iso:country":"NL",
    "sg:address":"Paramasievaan 10",
    "sg:city":"Ameide",
    "sg:orig_category":"Meubelzaken, Woning- And Keukeninrichting",
    "sg:phone":"+31 183 601 373",
    "sg:postcode":"4233 EX",
    "sg:province":"Zuid-Holland",
    "wof:name":"Gebr Van Zouwen Bv",
    "wof:placetype":"venue"
},
  "geometry": {"coordinates":[4.962455,51.954475],"type":"Point"}
}