{
  "type": "Feature",
  "properties": {
    "iso:country":"NL",
    "sg:address":"Spoorlaan 420",
    "sg:city":"Tilburg",
    "sg:orig_category":"Banken And Kredietinstellingen",
    "sg:phone":"+31 13 539 5395",
    "sg:postcode":"5038 CG",
    "sg:province":"North Brabant",
    "wof:name":"Ing Bank",
    "wof:placetype":"venue"
},
  "geometry": {"coordinates":[5.083333,51.560108],"type":"Point"}
}