{
  "type": "Feature",
  "properties": {
    "addr:full":"Brouwersstraat 3 Beneden Leeuwen Gelderland 6658 AD",
    "addr:housenumber":"3",
    "addr:postcode":"6658 ad",
    "addr:street":"Brouwersstraat",
    "iso:country":"NL",
    "sg:address":"Brouwersstraat 3",
    "sg:city":"Beneden Leeuwen",
    "sg:orig_category":"Fruitteelt",
    "sg:phone":"+31 487 591 010",
    "sg:postcode":"6658 AD",
    "sg:province":"Gelderland",
    "wof:name":"Fruithandel J. Van Gelder Bv",
    "wof:placetype":"venue"
},
  "geometry": {"coordinates":[5.52807,51.883743],"type":"Point"}
}