{
  "type": "Feature",
  "properties": {
    "addr:full":"Stationsstr 80 Koog Aan De Zaan North Holland 1541 LJ",
    "addr:housenumber":"80",
    "addr:postcode":"1541 lj",
    "addr:street":"Stationsstr",
    "iso:country":"NL",
    "sg:address":"Stationsstr 80",
    "sg:city":"Koog Aan De Zaan",
    "sg:orig_category":"Postkantoren",
    "sg:phone":"+31 75 621 0011",
    "sg:postcode":"1541 LJ",
    "sg:province":"North Holland",
    "sg:website":"http://www.postkantoor.nl",
    "wof:name":"Postkantoor",
    "wof:placetype":"venue"
},
  "geometry": {"coordinates":[4.806723,52.469288],"type":"Point"}
}