{
  "type": "Feature",
  "properties": {
    "addr:full":"Bronsinkln 82 Deventer Overijssel 7421 ER",
    "addr:housenumber":"82",
    "addr:postcode":"7421 er",
    "addr:street":"Bronsinkln",
    "iso:country":"NL",
    "sg:address":"Bronsinkln 82",
    "sg:city":"Deventer",
    "sg:orig_category":"Gehandicapteninformatie",
    "sg:phone":"+31 570 655 791",
    "sg:postcode":"7421 ER",
    "sg:province":"Overijssel",
    "wof:name":"Woonvorm Voor Doven Deventer",
    "wof:placetype":"venue"
},
  "geometry": {"coordinates":[6.221008,52.243549],"type":"Point"}
}