{
  "type": "Feature",
  "properties": {
    "addr:full":"Jupiterwg 17 Dronten NL. 8251 AW",
    "addr:housenumber":"17",
    "addr:postcode":"8251 aw",
    "addr:street":"Jupiterwg;Nl.",
    "iso:country":"NL",
    "sg:address":"Jupiterwg 17",
    "sg:city":"Dronten",
    "sg:orig_category":"Vakantieverblijven",
    "sg:phone":"+31 321 314 047",
    "sg:postcode":"8251 AW",
    "sg:province":"NL.",
    "wof:name":"Schonewille, K",
    "wof:placetype":"venue"
},
  "geometry": {"coordinates":[5.712238,52.522015],"type":"Point"}
}