{
  "type": "Feature",
  "properties": {
    "addr:full":"Voorstr 17-19 Fynaart Noord-Brabant 4793 ET",
    "addr:housenumber":"17-19",
    "addr:postcode":"4793 et",
    "addr:street":"Fynaart",
    "iso:country":"NL",
    "sg:address":"Voorstr 17-19",
    "sg:city":"Fynaart",
    "sg:orig_category":"Banken",
    "sg:phone":"+31 168 372 222",
    "sg:postcode":"4793 ET",
    "sg:province":"Noord-Brabant",
    "sg:website":"http://www.rabobank.nl",
    "wof:name":"Rabobank",
    "wof:placetype":"venue"
},
  "geometry": {"coordinates":[4.466852,51.635162],"type":"Point"}
}