{
  "type": "Feature",
  "properties": {
    "addr:full":"Zuidkd 206 Waddinxveen Zuid-Holland 2741 JT",
    "addr:housenumber":"206",
    "addr:postcode":"waddinxveen;2741 jt",
    "iso:country":"NL",
    "sg:address":"Zuidkd 206",
    "sg:city":"Waddinxveen",
    "sg:orig_category":"Broodjeszaken",
    "sg:phone":"+31 182 612 804",
    "sg:postcode":"2741 JT",
    "sg:province":"Zuid-Holland",
    "wof:name":"Bruin, A De",
    "wof:placetype":"venue"
},
  "geometry": {"coordinates":[4.65772,52.039589],"type":"Point"}
}