{
  "type": "Feature",
  "properties": {
    "addr:full":"W Vlisterdk 43 Vlist South Holland 2855 AJ",
    "addr:housenumber":"43",
    "addr:postcode":"2855 aj",
    "addr:street":"W",
    "iso:country":"NL",
    "sg:address":"W Vlisterdk 43",
    "sg:city":"Vlist",
    "sg:orig_category":"Loonbedrijven",
    "sg:phone":"+31 182 501 576",
    "sg:postcode":"2855 AJ",
    "sg:province":"South Holland",
    "wof:name":"Vliet, A Van",
    "wof:placetype":"venue"
},
  "geometry": {"coordinates":[4.824113,51.972927],"type":"Point"}
}