{
  "type": "Feature",
  "properties": {
    "addr:full":"Kneuterdk 1 S Gravenhage Zuid-Holland 2514 EM",
    "addr:housenumber":"1;gravenhage",
    "addr:postcode":"2514 em",
    "addr:street":"Kneuterdk;S",
    "iso:country":"NL",
    "sg:address":"Kneuterdk 1",
    "sg:city":"S Gravenhage",
    "sg:orig_category":"Onroerende Goederen",
    "sg:phone":"+31 70 381 6491",
    "sg:postcode":"2514 EM",
    "sg:province":"Zuid-Holland",
    "wof:name":"Bzb",
    "wof:placetype":"venue"
},
  "geometry": {"coordinates":[4.30935,52.084148],"type":"Point"}
}