{
  "type": "Feature",
  "properties": {
    "addr:full":"Passage 211 Sassenheim South Holland 2171 BZ",
    "addr:housenumber":"211",
    "addr:postcode":"2171 bz",
    "addr:street":"Passage",
    "iso:country":"NL",
    "sg:address":"Passage 211",
    "sg:city":"Sassenheim",
    "sg:orig_category":"Pleziervaartuigen And Reparatie",
    "sg:phone":"+31 252 223 370",
    "sg:postcode":"2171 BZ",
    "sg:province":"South Holland",
    "wof:name":"W Van Den Dool",
    "wof:placetype":"venue"
},
  "geometry": {"coordinates":[4.52364,52.226841],"type":"Point"}
}