{
  "type": "Feature",
  "properties": {
    "addr:full":"Zwanenburgerdk 503 Zwanenburg Noord-Holland 1161 NX",
    "addr:housenumber":"503",
    "addr:postcode":"1161 nx",
    "addr:street":"Zwanenburg",
    "iso:country":"NL",
    "sg:address":"Zwanenburgerdk 503",
    "sg:city":"Zwanenburg",
    "sg:classifiers":[
        {
            "category":"Retail",
            "subcategory":"Auto Repair",
            "type":"Services"
        }
    ],
    "sg:phone":"+31 20 497 6572",
    "sg:postcode":"1161 NX",
    "sg:province":"Noord-Holland",
    "sg:tags":[
        "garage"
    ],
    "wof:name":"Yentl",
    "wof:placetype":"venue"
},
  "geometry": {"coordinates":[4.754621,52.378868],"type":"Point"}
}