{
  "type": "Feature",
  "properties": {
    "addr:full":"Leenderweg 189 Eindhoven North Brabant 5643 AG",
    "addr:housenumber":"189",
    "addr:postcode":"5643",
    "addr:street":"Leenderweg",
    "iso:country":"NL",
    "sg:address":"Leenderweg 189",
    "sg:city":"Eindhoven",
    "sg:classifiers":[
        {
            "category":"Professional",
            "subcategory":"Accounting & Tax Preparation",
            "type":"Services"
        }
    ],
    "sg:phone":"+31 40 212 9432",
    "sg:postcode":"5643 AG",
    "sg:province":"North Brabant",
    "sg:tags":[
        "accountant"
    ],
    "wof:name":"Van Camp & Partners",
    "wof:placetype":"venue"
},
  "geometry": {"coordinates":[5.493483,51.423504],"type":"Point"}
}