{
  "type": "Feature",
  "properties": {
    "addr:full":"Karnemelksloot 50 Gouda Zuid-Holland 2806 BH",
    "addr:housenumber":"50",
    "addr:postcode":"2806 bh",
    "addr:street":"Karnemelksloot",
    "iso:country":"NL",
    "sg:address":"Karnemelksloot 50",
    "sg:city":"Gouda",
    "sg:orig_category":"Partyservice",
    "sg:phone":"+31 182 583 875",
    "sg:postcode":"2806 BH",
    "sg:province":"Zuid-Holland",
    "sg:website":"http://www.grandcanyon.nl",
    "wof:name":"Grand Canyon",
    "wof:placetype":"venue"
},
  "geometry": {"coordinates":[4.718347,52.0135],"type":"Point"}
}