{
  "type": "Feature",
  "properties": {
    "iso:country":"NL",
    "sg:address":"Schipholwg 821",
    "sg:city":"Boesingheliede",
    "sg:classifiers":[
        {
            "category":"Retail",
            "subcategory":"Auto Repair",
            "type":"Services"
        }
    ],
    "sg:phone":"+31 23 555 1500",
    "sg:postcode":"2143 CA",
    "sg:province":"Noord-Holland",
    "sg:tags":[
        "garage"
    ],
    "wof:name":"Vugt Haarlemmermeer, Van",
    "wof:placetype":"venue"
},
  "geometry": {"coordinates":[4.727456,52.359436],"type":"Point"}
}