{
  "type": "Feature",
  "properties": {
    "addr:full":"Hoogstr 14 S Gravenhage South Holland 2513 AR",
    "addr:housenumber":"14",
    "addr:postcode":"2513",
    "addr:street":"Hoogstr;S Gravenhage",
    "iso:country":"NL",
    "sg:address":"Hoogstr 14",
    "sg:city":"S Gravenhage",
    "sg:orig_category":"Herenkleding",
    "sg:phone":"+31 70 364 8081",
    "sg:postcode":"2513 AR",
    "sg:province":"South Holland",
    "sg:website":"http://www.societyshop.com/shop.html",
    "wof:name":"The Society Shop Bv",
    "wof:placetype":"venue"
},
  "geometry": {"coordinates":[4.30339,52.078442],"type":"Point"}
}