{
  "type": "Feature",
  "properties": {
    "iso:country":"NL",
    "sg:address":"Minderbroedersb 6",
    "sg:city":"Maastricht",
    "sg:orig_category":"Bibliotheken Weten- Schappelijke",
    "sg:phone":"+31 43 325 8383",
    "sg:postcode":"6211 LK",
    "sg:province":"Limburg",
    "sg:website":"http://www.ihol.nl",
    "wof:name":"Ihol",
    "wof:placetype":"venue"
},
  "geometry": {"coordinates":[5.686595,50.846786],"type":"Point"}
}