{
  "type": "Feature",
  "properties": {
    "addr:full":"Mommersteeg 46 A Haarsteeg Noord-Brabant 5254 VM",
    "addr:housenumber":"46 a",
    "addr:postcode":"5254 vm",
    "addr:street":"Mommersteeg",
    "iso:country":"NL",
    "sg:address":"Mommersteeg 46 A",
    "sg:city":"Haarsteeg",
    "sg:orig_category":"Geluidsopnamen",
    "sg:phone":"+31 73 511 7859",
    "sg:postcode":"5254 VM",
    "sg:province":"Noord-Brabant",
    "wof:name":"Van Den Berk Stage Services Inc.",
    "wof:placetype":"venue"
},
  "geometry": {"coordinates":[5.205979,51.706863],"type":"Point"}
}