{
  "type": "Feature",
  "properties": {
    "addr:full":"Schubertln 20 Apeldoorn Gelderland 7333 CV",
    "addr:housenumber":"20",
    "addr:postcode":"7333 cv",
    "addr:street":"Schubertln;Gelderland",
    "iso:country":"NL",
    "sg:address":"Schubertln 20",
    "sg:city":"Apeldoorn",
    "sg:orig_category":"Bloemen En Planten",
    "sg:phone":"+31 55 533 2655",
    "sg:postcode":"7333 CV",
    "sg:province":"Gelderland",
    "sg:website":"http://www.flowerserviceapeldoorn.com",
    "wof:name":"Margriet Bloemenmagazijn",
    "wof:placetype":"venue"
},
  "geometry": {"coordinates":[5.965097,52.189732],"type":"Point"}
}