{
  "type": "Feature",
  "properties": {
    "addr:full":"Gr Janln 6 Zeist Utrecht 3708 GM",
    "addr:housenumber":"6",
    "addr:postcode":"3708 gm",
    "iso:country":"NL",
    "sg:address":"Gr Janln 6",
    "sg:city":"Zeist",
    "sg:orig_category":"Adviesbureaus Bedrijfsorganisatie",
    "sg:phone":"+31 30 691 2257",
    "sg:postcode":"3708 GM",
    "sg:province":"Utrecht",
    "wof:name":"Brian Goedtz Bv",
    "wof:placetype":"venue"
},
  "geometry": {"coordinates":[5.24387,52.08548],"type":"Point"}
}