{
  "type": "Feature",
  "properties": {
    "addr:full":"Van Boshuizenstraat 439 Amsterdam Missouri 1082 AR",
    "addr:housenumber":"439",
    "addr:postcode":"1082",
    "addr:street":"Van Boshuizenstraat",
    "iso:country":"NL",
    "sg:address":"Van Boshuizenstraat 439",
    "sg:city":"Amsterdam",
    "sg:orig_category":"Verzekeringen",
    "sg:phone":"+31 20 422 1270",
    "sg:postcode":"1082 AR",
    "sg:province":"Missouri",
    "wof:name":"Van Biljouw De Waart & Jurrema",
    "wof:placetype":"venue"
},
  "geometry": {"coordinates":[-94.58503,38.350479],"type":"Point"}
}