{
  "type": "Feature",
  "properties": {
    "iso:country":"NL",
    "sg:address":"De Genestetstraat 27",
    "sg:city":"Etten-Leur",
    "sg:orig_category":"Paramedische Behandelingen",
    "sg:phone":"+31 76 503 8673",
    "sg:postcode":"4873 CP",
    "sg:province":"North Brabant",
    "wof:name":"Aqua-Baby Vof",
    "wof:placetype":"venue"
},
  "geometry": {"coordinates":[4.647338,51.565098],"type":"Point"}
}