{
  "type": "Feature",
  "properties": {
    "iso:country":"NL",
    "sg:address":"Graanstr 64",
    "sg:city":"Purmerend",
    "sg:orig_category":"Webdesign Bureaus",
    "sg:phone":"+31 299 465 751",
    "sg:postcode":"1446 CZ",
    "sg:province":"Noord-Holland",
    "wof:name":"Carota Design",
    "wof:placetype":"venue"
},
  "geometry": {"coordinates":[4.9918961525,52.5056915283],"type":"Point"}
}