{
  "type": "Feature",
  "properties": {
    "addr:full":"Sweelinckstr 87 Drunen Noord-Brabant 5151 PC",
    "addr:housenumber":"87",
    "addr:postcode":"5151 pc",
    "addr:street":"Sweelinckstr",
    "iso:country":"NL",
    "sg:address":"Sweelinckstr 87",
    "sg:city":"Drunen",
    "sg:orig_category":"Machineonderhoud En -Reparatie",
    "sg:phone":"+31 416 379 972",
    "sg:postcode":"5151 PC",
    "sg:province":"Noord-Brabant",
    "wof:name":"Amd",
    "wof:placetype":"venue"
},
  "geometry": {"coordinates":[5.132849,51.679131],"type":"Point"}
}