{
  "type": "Feature",
  "properties": {
    "addr:full":"Papenkamp 10 Arnhem Gelderland 6836 BD",
    "addr:housenumber":"10",
    "addr:postcode":"6836 bd",
    "addr:street":"Papenkamp",
    "iso:country":"NL",
    "sg:address":"Papenkamp 10",
    "sg:city":"Arnhem",
    "sg:orig_category":"Autokeuringen",
    "sg:phone":"+31 26 323 4444",
    "sg:postcode":"6836 BD",
    "sg:province":"Gelderland",
    "wof:name":"Autocenter Van Zijll Zuid Bv",
    "wof:placetype":"venue"
},
  "geometry": {"coordinates":[5.8836,51.948147],"type":"Point"}
}