{
  "type": "Feature",
  "properties": {
    "addr:full":"Nieuwe Steen 2B 101 Hoorn 1625 HV",
    "addr:housenumber":"2b 101",
    "addr:postcode":"1625 hv",
    "addr:street":"Nieuwe Steen;Hoorn",
    "iso:country":"NL",
    "sg:address":"Nieuwe Steen 2B 101",
    "sg:city":"Hoorn",
    "sg:classifiers":[
        {
            "category":"Professional",
            "subcategory":"Computer Services",
            "type":"Services"
        }
    ],
    "sg:postcode":"1625 HV",
    "sg:tags":[
        "sms",
        "premium-messaging",
        "chat",
        "voting",
        "mobile-content",
        "itv"
    ],
    "sg:website":"http://www.mobilebridges.com",
    "wof:name":"Mobile Bridges International",
    "wof:placetype":"venue"
},
  "geometry": {"coordinates":[5.0631877,52.6550182],"type":"Point"}
}