{
  "type": "Feature",
  "properties": {
    "addr:full":"Burgemeester Warnaarsstr 5 Wierden Overijssel 7642 CT",
    "addr:housenumber":"5",
    "addr:postcode":"7642 ct",
    "addr:street":"Burgemeester Warnaarsstr",
    "iso:country":"NL",
    "sg:address":"Burgemeester Warnaarsstr 5",
    "sg:city":"Wierden",
    "sg:orig_category":"Architecten",
    "sg:phone":"+31 546 573 826",
    "sg:postcode":"7642 CT",
    "sg:province":"Overijssel",
    "wof:name":"Orbita Architecten & Partners Johannes Dollen Arch",
    "wof:placetype":"venue"
},
  "geometry": {"coordinates":[6.59144,52.357151],"type":"Point"}
}