{
  "type": "Feature",
  "properties": {
    "addr:full":"Vierzinnen 1 Scherpenzeel Gld Gelderland 3925 EC",
    "addr:housenumber":"1",
    "addr:postcode":"3925 ec",
    "addr:street":"Vierzinnen;Gld Gelderland",
    "iso:country":"NL",
    "sg:address":"Vierzinnen 1",
    "sg:city":"Scherpenzeel Gld",
    "sg:orig_category":"Bloemen En Planten - Decoratie",
    "sg:phone":"+31 33 277 3830",
    "sg:postcode":"3925 EC",
    "sg:province":"Gelderland",
    "sg:website":"http://www.kwekerij-stuivenberg.com",
    "wof:name":"Hobbystation, Het",
    "wof:placetype":"venue"
},
  "geometry": {"coordinates":[5.480395,52.07568],"type":"Point"}
}