{
  "type": "Feature",
  "properties": {
    "addr:full":"Kerkstraat 32 Hattem Gelderland 8051 GM",
    "addr:housenumber":"32",
    "addr:postcode":"8051 gm",
    "addr:street":"Kerkstraat;Gelderland",
    "iso:country":"NL",
    "sg:address":"Kerkstraat 32",
    "sg:city":"Hattem",
    "sg:orig_category":"Baby- And Kinderkleding",
    "sg:phone":"+31 38 444 7457",
    "sg:postcode":"8051 GM",
    "sg:province":"Gelderland",
    "wof:name":"De Junior Boetiek",
    "wof:placetype":"venue"
},
  "geometry": {"coordinates":[6.06756,52.474957],"type":"Point"}
}