{
  "type": "Feature",
  "properties": {
    "addr:full":"Dorpsstraat 56 Benthuizen Zuid-Holland 2731 AR",
    "addr:housenumber":"56",
    "addr:postcode":"2731",
    "addr:street":"Dorpsstraat",
    "iso:country":"NL",
    "sg:address":"Dorpsstraat 56",
    "sg:city":"Benthuizen",
    "sg:orig_category":"Kappers",
    "sg:phone":"+31 79 341 2527",
    "sg:postcode":"2731 AR",
    "sg:province":"Zuid-Holland",
    "wof:name":"Kapsalon Your Line",
    "wof:placetype":"venue"
},
  "geometry": {"coordinates":[4.541162014,52.0772209167],"type":"Point"}
}