{
  "type": "Feature",
  "properties": {
    "addr:full":"Hoofdweg 75 Emst Gelderland 8166 AD",
    "addr:housenumber":"75",
    "addr:postcode":"8166 ad",
    "addr:street":"Hoofdweg;Gelderland",
    "iso:country":"NL",
    "sg:address":"Hoofdweg 75",
    "sg:city":"Emst",
    "sg:orig_category":"Kappers",
    "sg:phone":"+31 578 662 997",
    "sg:postcode":"8166 AD",
    "sg:province":"Gelderland",
    "wof:name":"Kapsalon Driesje'S Haarstudio",
    "wof:placetype":"venue"
},
  "geometry": {"coordinates":[5.9768891335,52.3203315735],"type":"Point"}
}