{
  "type": "Feature",
  "properties": {
    "iso:country":"NL",
    "sg:address":"Lommerbaan 104",
    "sg:city":"Zoetermeer",
    "sg:orig_category":"Technische Studies And Onderzoek",
    "sg:phone":"+31 79 343 6224",
    "sg:postcode":"2728 JH",
    "sg:province":"Zuid-Holland",
    "wof:name":"Miroden Bv",
    "wof:placetype":"venue"
},
  "geometry": {"coordinates":[4.518007,52.073353],"type":"Point"}
}