{
  "type": "Feature",
  "properties": {
    "addr:full":"Ranonkelstr 17 Eindhoven Noord-Brabant 5644 LA",
    "addr:housenumber":"17",
    "addr:postcode":"5644 la",
    "addr:street":"Ranonkelstr",
    "iso:country":"NL",
    "sg:address":"Ranonkelstr 17",
    "sg:city":"Eindhoven",
    "sg:orig_category":"Sportverenigingen En Ontspannings- Verenigingen",
    "sg:phone":"+31 40 212 7203",
    "sg:postcode":"5644 LA",
    "sg:province":"Noord-Brabant",
    "wof:name":"Eindhoven Korfbalver",
    "wof:placetype":"venue"
},
  "geometry": {"coordinates":[5.489816,51.419247],"type":"Point"}
}