{
  "type": "Feature",
  "properties": {
    "iso:country":"NL",
    "sg:address":"Dorpstraat 72",
    "sg:city":"Waddinxveen",
    "sg:orig_category":"Autokeuringen",
    "sg:phone":"+31 182 612 792",
    "sg:postcode":"2742 AK",
    "sg:province":"Zuid-Holland",
    "wof:name":"Autobedrijf Kool",
    "wof:placetype":"venue"
},
  "geometry": {"coordinates":[4.641303,52.046974],"type":"Point"}
}