{
  "type": "Feature",
  "properties": {
    "addr:full":"Dorpsstr 43 Koudekerk Ad Ryn Zuid-Holland 2396 HC",
    "addr:housenumber":"43",
    "addr:postcode":"2396 hc",
    "addr:street":"Dorpsstr",
    "iso:country":"NL",
    "sg:address":"Dorpsstr 43",
    "sg:city":"Koudekerk Ad Ryn",
    "sg:orig_category":"Adviesbureaus Bouwkunde",
    "sg:phone":"+31 71 341 3824",
    "sg:postcode":"2396 HC",
    "sg:province":"Zuid-Holland",
    "wof:name":"Driel, H Van",
    "wof:placetype":"venue"
},
  "geometry": {"coordinates":[4.589622,52.131573],"type":"Point"}
}