{
  "type": "Feature",
  "properties": {
    "addr:full":"Spanjaardstr 108B Rotterdam Zuid-Holland 3025 TW",
    "addr:housenumber":"108b",
    "addr:postcode":"3025 tw",
    "iso:country":"NL",
    "sg:address":"Spanjaardstr 108B",
    "sg:city":"Rotterdam",
    "sg:orig_category":"Beeldende Kunstenaars",
    "sg:phone":"+31 6 23286422",
    "sg:postcode":"3025 TW",
    "sg:province":"Zuid-Holland",
    "sg:website":"http://www.chon.nl",
    "wof:name":"Chon",
    "wof:placetype":"venue"
},
  "geometry": {"coordinates":[4.445911,51.906788],"type":"Point"}
}