{
  "type": "Feature",
  "properties": {
    "addr:full":"David Ben Goerionstraat 30 Utrecht Utrecht 3573 XN",
    "addr:housenumber":"30",
    "addr:postcode":"3573 xn",
    "addr:street":"David Ben Goerionstraat",
    "iso:country":"NL",
    "sg:address":"David Ben Goerionstraat 30",
    "sg:city":"Utrecht",
    "sg:orig_category":"Boekhouders",
    "sg:phone":"+31 30 271 0514",
    "sg:postcode":"3573 XN",
    "sg:province":"Utrecht",
    "wof:name":"H.H.H. De Jong",
    "wof:placetype":"venue"
},
  "geometry": {"coordinates":[5.146094,52.113506],"type":"Point"}
}