{
  "type": "Feature",
  "properties": {
    "addr:full":"De Genestetln 35 Bussum North Holland 1401 EJ",
    "addr:housenumber":"35",
    "addr:postcode":"1401 ej",
    "iso:country":"NL",
    "sg:address":"De Genestetln 35",
    "sg:city":"Bussum",
    "sg:orig_category":"Poppen En Poppenhuismaterialen",
    "sg:phone":"+31 35 691 3660",
    "sg:postcode":"1401 EJ",
    "sg:province":"North Holland",
    "wof:name":"Diewertje",
    "wof:placetype":"venue"
},
  "geometry": {"coordinates":[5.166338,52.277092],"type":"Point"}
}