{
  "type": "Feature",
  "properties": {
    "addr:full":"Eikenln 255 Groningen Groningen 9741 EZ",
    "addr:housenumber":"255",
    "addr:postcode":"9741 ez",
    "iso:country":"NL",
    "sg:address":"Eikenln 255",
    "sg:city":"Groningen",
    "sg:orig_category":"Verenigingsgebouwen",
    "sg:phone":"+31 50 573 1188",
    "sg:postcode":"9741 EZ",
    "sg:province":"Groningen",
    "wof:name":"Fontein Sov, De",
    "wof:placetype":"venue"
},
  "geometry": {"coordinates":[6.546159,53.231697],"type":"Point"}
}