{
  "type": "Feature",
  "properties": {
    "addr:full":"V Beukelaarwg 30 Bleskensgraaf Ca South Holland 2971 VL",
    "addr:housenumber":"30",
    "addr:postcode":"ca;2971 vl",
    "iso:country":"NL",
    "sg:address":"V Beukelaarwg 30",
    "sg:city":"Bleskensgraaf Ca",
    "sg:classifiers":[
        {
            "category":"Home & Garden",
            "subcategory":"Hardware",
            "type":"Retail Goods"
        }
    ],
    "sg:phone":"+31 184 694 624",
    "sg:postcode":"2971 VL",
    "sg:province":"South Holland",
    "sg:tags":[
        "machine",
        "houtbewerking",
        "-"
    ],
    "wof:name":"Baas Service Bv",
    "wof:placetype":"venue"
},
  "geometry": {"coordinates":[4.784609,51.870838],"type":"Point"}
}