{
  "type": "Feature",
  "properties": {
    "iso:country":"NL",
    "sg:address":"Postbus 303",
    "sg:city":"Wageningen",
    "sg:orig_category":"Verenigingen En Stichtingen",
    "sg:phone":"+31 317 416 762",
    "sg:postcode":"6700 AH",
    "sg:province":"Gelderland",
    "wof:name":"Bbga",
    "wof:placetype":"venue"
},
  "geometry": {"coordinates":[5.660976,51.964355],"type":"Point"}
}