{
  "type": "Feature",
  "properties": {
    "addr:full":"Hoefkd 820 S Gravenhage Zuid-Holland 2526 CV",
    "addr:housenumber":"820;gravenhage",
    "addr:postcode":"2526 cv",
    "addr:street":"S",
    "iso:country":"NL",
    "sg:address":"Hoefkd 820",
    "sg:city":"S Gravenhage",
    "sg:orig_category":"Juweliers",
    "sg:phone":"+31 70 380 9880",
    "sg:postcode":"2526 CV",
    "sg:province":"Zuid-Holland",
    "wof:name":"Parbo",
    "wof:placetype":"venue"
},
  "geometry": {"coordinates":[4.30555,52.0681],"type":"Point"}
}