{
  "type": "Feature",
  "properties": {
    "addr:full":"Krijtstr 8 Vroenhoven B377 0",
    "addr:housenumber":"8;b377 0",
    "addr:street":"Krijtstr",
    "iso:country":"NL",
    "sg:address":"Krijtstr 8",
    "sg:city":"Vroenhoven",
    "sg:orig_category":"Homeopathie",
    "sg:phone":"+31 12453918",
    "sg:postcode":"B377 0",
    "wof:name":"Moonen, R",
    "wof:placetype":"venue"
},
  "geometry": {"coordinates":[5.63877,50.827606],"type":"Point"}
}