{
  "type": "Feature",
  "properties": {
    "addr:full":"Engelsbergenstraat 4 Eindhoven North Brabant 5616 JC",
    "addr:housenumber":"4",
    "addr:postcode":"5616 jc",
    "addr:street":"Engelsbergenstraat",
    "iso:country":"NL",
    "sg:address":"Engelsbergenstraat 4",
    "sg:city":"Eindhoven",
    "sg:orig_category":"Autokeuringen",
    "sg:phone":"+31 40 252 8706",
    "sg:postcode":"5616 JC",
    "sg:province":"North Brabant",
    "wof:name":"Van Dommelen",
    "wof:placetype":"venue"
},
  "geometry": {"coordinates":[5.460989,51.438271],"type":"Point"}
}