{
  "type": "Feature",
  "properties": {
    "addr:full":"Bakkersveld 11 Tuk Washington 8334 NE",
    "addr:housenumber":"11;8334",
    "addr:postcode":"ne",
    "addr:street":"Bakkersveld",
    "iso:country":"NL",
    "sg:address":"Bakkersveld 11",
    "sg:city":"Tuk",
    "sg:orig_category":"Goederenvervoer Over De Weg",
    "sg:phone":"+31 521 512 457",
    "sg:postcode":"8334 NE",
    "sg:province":"Washington",
    "wof:name":"Flobbe Steenwijk Bv",
    "wof:placetype":"venue"
},
  "geometry": {"coordinates":[-122.841599,48.057613],"type":"Point"}
}