{
  "type": "Feature",
  "properties": {
    "addr:full":"Molenkap 15 St Nicolaasga Provincie Friesland 8521 MH",
    "addr:housenumber":"15",
    "addr:postcode":"8521 mh",
    "addr:street":"Molenkap;Friesland",
    "iso:country":"NL",
    "sg:address":"Molenkap 15",
    "sg:city":"St Nicolaasga",
    "sg:orig_category":"Verpleegartikelen",
    "sg:phone":"+31 513 467 200",
    "sg:postcode":"8521 MH",
    "sg:province":"Provincie Friesland",
    "wof:name":"Hulpmiddelenentrum Friesland Bv",
    "wof:placetype":"venue"
},
  "geometry": {"coordinates":[5.743319,52.917789],"type":"Point"}
}