{
  "type": "Feature",
  "properties": {
    "addr:full":"Kampersngl 64 Haarlem Noord-Holland 2012 DM",
    "addr:housenumber":"64",
    "addr:postcode":"2012 dm",
    "addr:street":"Kampersngl",
    "iso:country":"NL",
    "sg:address":"Kampersngl 64",
    "sg:city":"Haarlem",
    "sg:orig_category":"Antiquiteiten",
    "sg:phone":"+31 23 531 4223",
    "sg:postcode":"2012 DM",
    "sg:province":"Noord-Holland",
    "wof:name":"Meridienne, La",
    "wof:placetype":"venue"
},
  "geometry": {"coordinates":[4.642253,52.380562],"type":"Point"}
}