{
  "type": "Feature",
  "properties": {
    "iso:country":"NL",
    "sg:address":"Terschellingkade 6",
    "sg:city":"Woerden",
    "sg:orig_category":"Paramedische Behandelingen",
    "sg:phone":"+31 348 434 831",
    "sg:postcode":"3446 BK",
    "sg:province":"Utrecht",
    "wof:name":"Thuiszorgwinkel Meditheek",
    "wof:placetype":"venue"
},
  "geometry": {"coordinates":[4.90359,52.084518],"type":"Point"}
}