{
  "type": "Feature",
  "properties": {
    "addr:full":"Buitendijk 3 Helmond Noord-Brabant 5705 CD",
    "addr:housenumber":"3",
    "addr:postcode":"5705 cd",
    "addr:street":"Buitendijk",
    "iso:country":"NL",
    "sg:address":"Buitendijk 3",
    "sg:city":"Helmond",
    "sg:orig_category":"Chemische Producten Gh",
    "sg:phone":"+31 492 590 755",
    "sg:postcode":"5705 CD",
    "sg:province":"Noord-Brabant",
    "wof:name":"Loctite Nederland Bv Pre Applied Centre",
    "wof:placetype":"venue"
},
  "geometry": {"coordinates":[5.68297,51.469219],"type":"Point"}
}