{
  "type": "Feature",
  "properties": {
    "addr:full":"Singel 512 Amsterdam North Holland 1017 AX",
    "addr:housenumber":"512",
    "addr:postcode":"1017 ax",
    "addr:street":"Singel",
    "iso:country":"NL",
    "sg:address":"Singel 512",
    "sg:city":"Amsterdam",
    "sg:orig_category":"Grafisch Ontwerpers",
    "sg:phone":"+31 20 638 5942",
    "sg:postcode":"1017 AX",
    "sg:province":"North Holland",
    "wof:name":"Gerritse, M",
    "wof:placetype":"venue"
},
  "geometry": {"coordinates":[4.89095,52.366947],"type":"Point"}
}