{
  "type": "Feature",
  "properties": {
    "iso:country":"NL",
    "sg:address":"Spikkerwg 161B",
    "sg:city":"Roermond",
    "sg:orig_category":"Voetbalverenigingen",
    "sg:phone":"+31 475 321 005",
    "sg:postcode":"6042 KS",
    "sg:province":"Limburg",
    "wof:name":"Rkavc",
    "wof:placetype":"venue"
},
  "geometry": {"coordinates":[6.040495,51.196583],"type":"Point"}
}