{
  "type": "Feature",
  "properties": {
    "iso:country":"NL",
    "sg:address":"Wilhelminalaan 41",
    "sg:city":"Beuningen Gld",
    "sg:classifiers":[
        {
            "category":"Professional",
            "subcategory":"Accounting & Tax Preparation",
            "type":"Services"
        }
    ],
    "sg:phone":"+31 24 677 2749",
    "sg:postcode":"6641 DE",
    "sg:province":"Gelderland",
    "sg:tags":[
        "accountant"
    ],
    "wof:name":"Van Haalen Bv Registeraccountants",
    "wof:placetype":"venue"
},
  "geometry": {"coordinates":[5.769137,51.860569],"type":"Point"}
}