{
  "type": "Feature",
  "properties": {
    "addr:full":"Industrieweg 24 Bergeyk Noord-Brabant 5571 LJ",
    "addr:housenumber":"24",
    "addr:postcode":"5571 lj",
    "addr:street":"Industrieweg",
    "iso:country":"NL",
    "sg:address":"Industrieweg 24",
    "sg:city":"Bergeyk",
    "sg:orig_category":"Metaalbekleding And -Behandeling",
    "sg:phone":"+31 497 573 106",
    "sg:postcode":"5571 LJ",
    "sg:province":"Noord-Brabant",
    "wof:name":"Brans Metaalbewerking Bv",
    "wof:placetype":"venue"
},
  "geometry": {"coordinates":[5.350599,51.3144],"type":"Point"}
}