{
  "type": "Feature",
  "properties": {
    "addr:full":"Kalkovenwg 34 Alphen Aan Den Ryn Zuid-Holland 2401 LK",
    "addr:housenumber":"34",
    "addr:postcode":"2401 lk",
    "addr:street":"Kalkovenwg;Aan Den Ryn",
    "iso:country":"NL",
    "sg:address":"Kalkovenwg 34",
    "sg:city":"Alphen Aan Den Ryn",
    "sg:orig_category":"Horeca-Inrichtingen En -Uitrustingen",
    "sg:phone":"+31 172 445 924",
    "sg:postcode":"2401 LK",
    "sg:province":"Zuid-Holland",
    "wof:name":"Nisters Bv",
    "wof:placetype":"venue"
},
  "geometry": {"coordinates":[4.649987,52.148796],"type":"Point"}
}