{
  "type": "Feature",
  "properties": {
    "iso:country":"NL",
    "sg:address":"Frankenslag 402",
    "sg:city":"Den Haag",
    "sg:classifiers":[
        {
            "category":"Banks & Credit Unions",
            "subcategory":"Investment Brokerage",
            "type":"Services"
        }
    ],
    "sg:phone":"+31 70 355 9425",
    "sg:postcode":"2582 JC",
    "sg:province":"South Holland",
    "sg:tags":[
        "pension"
    ],
    "wof:name":"Benjamins-Oey, J C N",
    "wof:placetype":"venue"
},
  "geometry": {"coordinates":[4.271912,52.09148],"type":"Point"}
}