{
  "type": "Feature",
  "properties": {
    "addr:full":"V Hamelstr 13 Heemskerk North Holland 1964 EA",
    "addr:housenumber":"13",
    "addr:postcode":"1964 ea",
    "iso:country":"NL",
    "sg:address":"V Hamelstr 13",
    "sg:city":"Heemskerk",
    "sg:orig_category":"Adviesbureaus Personeel",
    "sg:phone":"+31 251 247 648",
    "sg:postcode":"1964 EA",
    "sg:province":"North Holland",
    "sg:website":"http://www.pabpersoneel.nl",
    "wof:name":"Busman P & O",
    "wof:placetype":"venue"
},
  "geometry": {"coordinates":[4.66983,52.513546],"type":"Point"}
}