{
  "type": "Feature",
  "properties": {
    "addr:full":"Dorpsstr 141 Zwaag Noord-Holland 1689 GA",
    "addr:housenumber":"141",
    "addr:postcode":"1689 ga",
    "iso:country":"NL",
    "sg:address":"Dorpsstr 141",
    "sg:city":"Zwaag",
    "sg:orig_category":"Makelaars En Adviseurs Onroerende Goederen",
    "sg:phone":"+31 229 214 333",
    "sg:postcode":"1689 GA",
    "sg:province":"Noord-Holland",
    "sg:website":"http://www.smitvastgoed.nl",
    "wof:name":"Smit, Vastgoed",
    "wof:placetype":"venue"
},
  "geometry": {"coordinates":[5.070276,52.66721],"type":"Point"}
}