{
  "type": "Feature",
  "properties": {
    "addr:full":"Koningswerf 22 S Gravenzande Zuid-Holland 2691 BJ",
    "addr:housenumber":"22;gravenzande",
    "addr:postcode":"2691 bj",
    "addr:street":"Koningswerf;S",
    "iso:country":"NL",
    "sg:address":"Koningswerf 22",
    "sg:city":"S Gravenzande",
    "sg:orig_category":"Zonweringen",
    "sg:phone":"+31 174 418 822",
    "sg:postcode":"2691 BJ",
    "sg:province":"Zuid-Holland",
    "wof:name":"Kok, Peter",
    "wof:placetype":"venue"
},
  "geometry": {"coordinates":[4.161858,52.002659],"type":"Point"}
}