{
  "type": "Feature",
  "properties": {
    "addr:full":"Kerkewyk 65 Veenendaal Utrecht 3901 EC",
    "addr:housenumber":"65",
    "addr:postcode":"3901 ec",
    "addr:street":"Kerkewyk",
    "iso:country":"NL",
    "sg:address":"Kerkewyk 65",
    "sg:city":"Veenendaal",
    "sg:orig_category":"Architecten En Architectenbureaus",
    "sg:phone":"+31 318 522 324",
    "sg:postcode":"3901 EC",
    "sg:province":"Utrecht",
    "wof:name":"Huibers & Jarring Architecten Bna",
    "wof:placetype":"venue"
},
  "geometry": {"coordinates":[5.552278,52.02219],"type":"Point"}
}