{
  "type": "Feature",
  "properties": {
    "addr:full":"Burmaniastraat 4 Leeuwarden Friesland 8911 DJ",
    "addr:housenumber":"4",
    "addr:postcode":"8911 dj",
    "addr:street":"Burmaniastraat",
    "iso:country":"NL",
    "sg:address":"Burmaniastraat 4",
    "sg:city":"Leeuwarden",
    "sg:orig_category":"Binnenhuisarchitecten",
    "sg:phone":"+31 58 213 6252",
    "sg:postcode":"8911 DJ",
    "sg:province":"Friesland",
    "wof:name":"W Steenhuizen Interieur Adviezen",
    "wof:placetype":"venue"
},
  "geometry": {"coordinates":[5.791371,53.201904],"type":"Point"}
}