{
  "type": "Feature",
  "properties": {
    "addr:full":"Gerrit Bolkade 43 Zaandam Noord-Holland 1507 BR",
    "addr:housenumber":"43",
    "addr:postcode":"1507 br",
    "addr:street":"Gerrit Bolkade",
    "iso:country":"NL",
    "sg:address":"Gerrit Bolkade 43",
    "sg:city":"Zaandam",
    "sg:classifiers":[
        {
            "category":"Retail",
            "subcategory":"Storage",
            "type":"Services"
        }
    ],
    "sg:phone":"+31 75 631 3778",
    "sg:postcode":"1507 BR",
    "sg:province":"Noord-Holland",
    "sg:tags":[
        "opslag",
        "bewaring"
    ],
    "wof:name":"Bruins Veem Bv",
    "wof:placetype":"venue"
},
  "geometry": {"coordinates":[4.8154211044,52.427230835],"type":"Point"}
}