{
  "type": "Feature",
  "properties": {
    "addr:full":"B Wolffpln 98 Hoorn Nh North Holland 1628 NE",
    "addr:housenumber":"98;1628",
    "addr:postcode":"ne",
    "addr:street":"Nh North",
    "iso:country":"NL",
    "sg:address":"B Wolffpln 98",
    "sg:city":"Hoorn Nh",
    "sg:orig_category":"Fotoreportages",
    "sg:phone":"+31 229 296 274",
    "sg:postcode":"1628 NE",
    "sg:province":"North Holland",
    "wof:name":"Fotografika",
    "wof:placetype":"venue"
},
  "geometry": {"coordinates":[5.05207,52.642399],"type":"Point"}
}