{
  "type": "Feature",
  "properties": {
    "addr:full":"Vissersdk 39 Dordrecht Zuid-Holland 3319 GT",
    "addr:housenumber":"39",
    "addr:postcode":"3319 gt",
    "addr:street":"Vissersdk",
    "iso:country":"NL",
    "sg:address":"Vissersdk 39",
    "sg:city":"Dordrecht",
    "sg:orig_category":"Artiesten/Gezelschappen",
    "sg:phone":"+31 78 616 6517",
    "sg:postcode":"3319 GT",
    "sg:province":"Zuid-Holland",
    "wof:name":"Kameleon",
    "wof:placetype":"venue"
},
  "geometry": {"coordinates":[4.711194,51.799751],"type":"Point"}
}