{
  "type": "Feature",
  "properties": {
    "addr:full":"Brucknerplein 7 Eindhoven North Brabant 5653 ER",
    "addr:housenumber":"7",
    "addr:postcode":"5653 er",
    "addr:street":"Brucknerplein",
    "iso:country":"NL",
    "sg:address":"Brucknerplein 7",
    "sg:city":"Eindhoven",
    "sg:orig_category":"Fietshandelaren",
    "sg:phone":"+31 40 251 6069",
    "sg:postcode":"5653 ER",
    "sg:province":"North Brabant",
    "wof:name":"Rijwielhandel 'T Fietske",
    "wof:placetype":"venue"
},
  "geometry": {"coordinates":[5.452004,51.423683],"type":"Point"}
}