{
  "type": "Feature",
  "properties": {
    "addr:full":"Sikko Sjaerdemalaan 44 Ijlst Friesland 8651 BC",
    "addr:housenumber":"44",
    "addr:postcode":"8651 bc",
    "addr:street":"Sikko Sjaerdemalaan",
    "iso:country":"NL",
    "sg:address":"Sikko Sjaerdemalaan 44",
    "sg:city":"Ijlst",
    "sg:classifiers":[
        {
            "category":"Fast Food",
            "type":"Food & Drink"
        }
    ],
    "sg:phone":"+31 515 532 515",
    "sg:postcode":"8651 BC",
    "sg:province":"Friesland",
    "sg:tags":[
        "afhaal",
        "restaurant"
    ],
    "wof:name":"Snackservice Klaver Ijlst",
    "wof:placetype":"venue"
},
  "geometry": {"coordinates":[5.612502,53.010616],"type":"Point"}
}