{
  "type": "Feature",
  "properties": {
    "addr:full":"Wauderickweg 3 Nijmegen Gelderland 6545 CK",
    "addr:housenumber":"3",
    "addr:postcode":"6545 ck",
    "addr:street":"Wauderickweg;Gelderland",
    "iso:country":"NL",
    "sg:address":"Wauderickweg 3",
    "sg:city":"Nijmegen",
    "sg:orig_category":"Metaalafval, Schrootrecycling And Sloperijen",
    "sg:phone":"+31 24 378 0696",
    "sg:postcode":"6545 CK",
    "sg:province":"Gelderland",
    "wof:name":"Metaalhandel Autosloperij P Kilkens",
    "wof:placetype":"venue"
},
  "geometry": {"coordinates":[5.810147,51.850487],"type":"Point"}
}