{
  "type": "Feature",
  "properties": {
    "addr:full":"S Abrahamsestr 93 Meteren Gelderland 4194 RD",
    "addr:housenumber":"93",
    "addr:postcode":"4194",
    "addr:street":"Gelderland;Rd",
    "iso:country":"NL",
    "sg:address":"S Abrahamsestr 93",
    "sg:city":"Meteren",
    "sg:orig_category":"Organisatiebureaus",
    "sg:phone":"+31 345 571 100",
    "sg:postcode":"4194 RD",
    "sg:province":"Gelderland",
    "wof:name":"Vermeulen",
    "wof:placetype":"venue"
},
  "geometry": {"coordinates":[5.2834968567,51.8719367981],"type":"Point"}
}