{
  "type": "Feature",
  "properties": {
    "addr:full":"Egelslag 46 Assen Drenthe 9403 XV",
    "addr:housenumber":"46",
    "addr:postcode":"9403 xv",
    "addr:street":"Egelslag",
    "iso:country":"NL",
    "sg:address":"Egelslag 46",
    "sg:city":"Assen",
    "sg:classifiers":[
        {
            "category":"Shopping",
            "subcategory":"Gifts & Souvenirs",
            "type":"Retail Goods"
        }
    ],
    "sg:phone":"+31 592 373 679",
    "sg:postcode":"9403 XV",
    "sg:province":"Drenthe",
    "sg:tags":[
        "geschenken"
    ],
    "wof:name":"R. Bakker",
    "wof:placetype":"venue"
},
  "geometry": {"coordinates":[6.593299,53.021046],"type":"Point"}
}