{
  "type": "Feature",
  "properties": {
    "iso:country":"NL",
    "sg:address":"Pegasusstraat 90",
    "sg:city":"Haarlem",
    "sg:orig_category":"Autokeuringen",
    "sg:phone":"+31 23 525 4856",
    "sg:postcode":"2024 VS",
    "sg:province":"Noord-Holland",
    "wof:name":"Garagebedrijf Van Laar Bv",
    "wof:placetype":"venue"
},
  "geometry": {"coordinates":[4.640161,52.405605],"type":"Point"}
}