{
  "type": "Feature",
  "properties": {
    "addr:full":"Rijndijk 208 Leiden Zuid-Holland 2331 AL",
    "addr:housenumber":"208",
    "addr:postcode":"2331 al",
    "addr:street":"Rijndijk",
    "iso:country":"NL",
    "sg:address":"Rijndijk 208",
    "sg:city":"Leiden",
    "sg:classifiers":[
        {
            "category":"Fast Food",
            "type":"Food & Drink"
        }
    ],
    "sg:phone":"+31 71 576 4059",
    "sg:postcode":"2331 AL",
    "sg:province":"Zuid-Holland",
    "sg:tags":[
        "afhaal",
        "restaurant"
    ],
    "wof:name":"Vishandel L. Polane",
    "wof:placetype":"venue"
},
  "geometry": {"coordinates":[4.454194,52.155876],"type":"Point"}
}