{
  "type": "Feature",
  "properties": {
    "addr:full":"Zwanenln 2 Kamperland Zeeland 4493 SG",
    "addr:housenumber":"2",
    "addr:postcode":"4493 sg",
    "addr:street":"Zwanenln",
    "iso:country":"NL",
    "sg:address":"Zwanenln 2",
    "sg:city":"Kamperland",
    "sg:orig_category":"Vakantieverblijven",
    "sg:phone":"+31 113 372 237",
    "sg:postcode":"4493 SG",
    "sg:province":"Zeeland",
    "wof:name":"Kaokel De",
    "wof:placetype":"venue"
},
  "geometry": {"coordinates":[3.684829,51.558594],"type":"Point"}
}