{
  "type": "Feature",
  "properties": {
    "iso:country":"NL",
    "sg:address":"Keucheniusstraat 20",
    "sg:city":"Huizen",
    "sg:orig_category":"Loodgieterswerk, Verwarming And Sanitaire Installaties",
    "sg:phone":"+31 35 525 1488",
    "sg:postcode":"1271 BN",
    "sg:province":"Noord-Holland",
    "wof:name":"W.Schram",
    "wof:placetype":"venue"
},
  "geometry": {"coordinates":[5.23418,52.296612],"type":"Point"}
}