{
  "type": "Feature",
  "properties": {
    "addr:full":"Loswal 14 Drachten Provincie Friesland 9206 AH",
    "addr:housenumber":"14",
    "addr:postcode":"9206 ah",
    "addr:street":"Loswal;Provincie Friesland",
    "iso:country":"NL",
    "sg:address":"Loswal 14",
    "sg:city":"Drachten",
    "sg:orig_category":"Bouwnijverheidsmachines Gh",
    "sg:phone":"+31 512 540 344",
    "sg:postcode":"9206 AH",
    "sg:province":"Provincie Friesland",
    "wof:name":"Bo-Rent",
    "wof:placetype":"venue"
},
  "geometry": {"coordinates":[6.075926,53.109779],"type":"Point"}
}