{
  "type": "Feature",
  "properties": {
    "addr:full":"Hazepad 51 Zaandyk Noord-Holland 1544 PW",
    "addr:housenumber":"51",
    "addr:postcode":"1544 pw",
    "addr:street":"Hazepad",
    "iso:country":"NL",
    "sg:address":"Hazepad 51",
    "sg:city":"Zaandyk",
    "sg:orig_category":"Verenigingen En Stichtingen",
    "sg:phone":"+31 75 622 6666",
    "sg:postcode":"1544 PW",
    "sg:province":"Noord-Holland",
    "wof:name":"Bos, Sticht",
    "wof:placetype":"venue"
},
  "geometry": {"coordinates":[4.807042,52.476219],"type":"Point"}
}