{
  "type": "Feature",
  "properties": {
    "addr:full":"Noorderkade 150 Alkmaar North Holland 1823 CJ",
    "addr:housenumber":"150",
    "addr:postcode":"1823 cj",
    "addr:street":"Noorderkade",
    "iso:country":"NL",
    "sg:address":"Noorderkade 150",
    "sg:city":"Alkmaar",
    "sg:orig_category":"Zuivelproducten",
    "sg:phone":"+31 72 520 0460",
    "sg:postcode":"1823 CJ",
    "sg:province":"North Holland",
    "wof:name":"Noordhollandse Kaashandel",
    "wof:placetype":"venue"
},
  "geometry": {"coordinates":[4.76043,52.638321],"type":"Point"}
}