{
  "type": "Feature",
  "properties": {
    "addr:full":"Abel Tasmanstraat 21 Emmen Provincie Drenthe 7825 VA",
    "addr:housenumber":"21",
    "addr:postcode":"7825",
    "addr:street":"Abel Tasmanstraat;Provincie Drenthe",
    "iso:country":"NL",
    "sg:address":"Abel Tasmanstraat 21",
    "sg:city":"Emmen",
    "sg:orig_category":"Kantoorartikelen",
    "sg:phone":"+31 591 619 683",
    "sg:postcode":"7825 VA",
    "sg:province":"Provincie Drenthe",
    "wof:name":"Bert Zomer Kantoorspecialisten",
    "wof:placetype":"venue"
},
  "geometry": {"coordinates":[6.9162797928,52.7526893616],"type":"Point"}
}