{
  "type": "Feature",
  "properties": {
    "addr:full":"T Perron 2 De Lier Zuid-Holland 2678 DB",
    "addr:housenumber":"2",
    "addr:postcode":"2678 db",
    "addr:street":"T Perron",
    "iso:country":"NL",
    "sg:address":"T Perron 2",
    "sg:city":"De Lier",
    "sg:orig_category":"Politie",
    "sg:phone":"+31 900 8844",
    "sg:postcode":"2678 DB",
    "sg:province":"Zuid-Holland",
    "wof:name":"Politie",
    "wof:placetype":"venue"
},
  "geometry": {"coordinates":[4.248107,51.973282],"type":"Point"}
}