{
  "type": "Feature",
  "properties": {
    "addr:full":"Blokdijk 14 Wijdenes Noord-Holland 1608 HG",
    "addr:housenumber":"14",
    "addr:postcode":"1608 hg",
    "addr:street":"Blokdijk",
    "iso:country":"NL",
    "sg:address":"Blokdijk 14",
    "sg:city":"Wijdenes",
    "sg:orig_category":"Adviesbureaus Bouwkosten",
    "sg:phone":"+31 229 501 160",
    "sg:postcode":"1608 HG",
    "sg:province":"Noord-Holland",
    "wof:name":"Hunting Hilversum Bv",
    "wof:placetype":"venue"
},
  "geometry": {"coordinates":[5.151477,52.659393],"type":"Point"}
}