{
  "type": "Feature",
  "properties": {
    "addr:full":"Rentmeestersstr 27 Raamsdonk Noord-Brabant 4944 WB",
    "addr:housenumber":"27",
    "addr:postcode":"4944 wb",
    "addr:street":"Rentmeestersstr",
    "iso:country":"NL",
    "sg:address":"Rentmeestersstr 27",
    "sg:city":"Raamsdonk",
    "sg:classifiers":[
        {
            "category":"Personal",
            "subcategory":"Nail Salon",
            "type":"Services"
        }
    ],
    "sg:phone":"+31 162 520 170",
    "sg:postcode":"4944 WB",
    "sg:province":"Noord-Brabant",
    "sg:tags":[
        "pedicure"
    ],
    "wof:name":"Duivestein, M",
    "wof:placetype":"venue"
},
  "geometry": {"coordinates":[4.904827,51.691441],"type":"Point"}
}