{
  "type": "Feature",
  "properties": {
    "addr:full":"Walstr 88 Vlissingen Zeeland 4381 GE",
    "addr:housenumber":"88",
    "addr:postcode":"4381",
    "addr:street":"Walstr",
    "iso:country":"NL",
    "sg:address":"Walstr 88",
    "sg:city":"Vlissingen",
    "sg:orig_category":"Juweliers",
    "sg:phone":"+31 118 416 400",
    "sg:postcode":"4381 GE",
    "sg:province":"Zeeland",
    "wof:name":"Witsel",
    "wof:placetype":"venue"
},
  "geometry": {"coordinates":[3.573732,51.444408],"type":"Point"}
}