{
  "type": "Feature",
  "properties": {
    "addr:full":"Langsstr 7A Ryswyk Gld Gelderland 4023 AE",
    "addr:housenumber":"7a",
    "addr:postcode":"4023 ae",
    "addr:street":"Langsstr;Gld Gelderland",
    "iso:country":"NL",
    "sg:address":"Langsstr 7A",
    "sg:city":"Ryswyk Gld",
    "sg:orig_category":"Ovenbouw",
    "sg:phone":"+31 345 558 335",
    "sg:postcode":"4023 AE",
    "sg:province":"Gelderland",
    "wof:name":"Maurik Bv",
    "wof:placetype":"venue"
},
  "geometry": {"coordinates":[5.3583521843,51.9585151672],"type":"Point"}
}