{
  "type": "Feature",
  "properties": {
    "addr:full":"Schelpenkd 33 Leiden Zuid-Holland 2313 ZV",
    "addr:housenumber":"33",
    "addr:postcode":"2313 zv",
    "addr:street":"Schelpenkd",
    "iso:country":"NL",
    "sg:address":"Schelpenkd 33",
    "sg:city":"Leiden",
    "sg:orig_category":"Adviesbureaus Bedrijfsorganisatie",
    "sg:phone":"+31 71 512 6914",
    "sg:postcode":"2313 ZV",
    "sg:province":"Zuid-Holland",
    "wof:name":"Vandenbergh",
    "wof:placetype":"venue"
},
  "geometry": {"coordinates":[4.486545,52.152061],"type":"Point"}
}