{
  "type": "Feature",
  "properties": {
    "addr:full":"Tijm 23 Huizen Noord-Holland 1273 EB",
    "addr:housenumber":"23",
    "addr:postcode":"1273 eb",
    "addr:street":"Tijm",
    "iso:country":"NL",
    "sg:address":"Tijm 23",
    "sg:city":"Huizen",
    "sg:orig_category":"Begrafenisondernemers",
    "sg:phone":"+31 35 525 8010",
    "sg:postcode":"1273 EB",
    "sg:province":"Noord-Holland",
    "wof:name":"Grafruimingsbedrijf Jongen",
    "wof:placetype":"venue"
},
  "geometry": {"coordinates":[5.253415,52.301327],"type":"Point"}
}