{
  "type": "Feature",
  "properties": {
    "addr:full":"Blauwstr 15 Gouda Zuid-Holland 2801 HE",
    "addr:housenumber":"15",
    "addr:postcode":"2801 he",
    "addr:street":"Blauwstr",
    "iso:country":"NL",
    "sg:address":"Blauwstr 15",
    "sg:city":"Gouda",
    "sg:orig_category":"Horloges En Klokken - Reparatie En Onderhoud",
    "sg:phone":"+31 182 512 506",
    "sg:postcode":"2801 HE",
    "sg:province":"Zuid-Holland",
    "wof:name":"Mol, W A De",
    "wof:placetype":"venue"
},
  "geometry": {"coordinates":[4.709306,52.012344],"type":"Point"}
}