{
  "type": "Feature",
  "properties": {
    "addr:full":"Magdalenalaan 14 Hengelo Ov Overijssel 7555 TA",
    "addr:housenumber":"14",
    "addr:postcode":"7555 ta",
    "addr:street":"Magdalenalaan;Ov",
    "iso:country":"NL",
    "sg:address":"Magdalenalaan 14",
    "sg:city":"Hengelo Ov",
    "sg:orig_category":"Daken And Skeletbouw",
    "sg:phone":"+31 74 291 3605",
    "sg:postcode":"7555 TA",
    "sg:province":"Overijssel",
    "wof:name":"C. Ermen",
    "wof:placetype":"venue"
},
  "geometry": {"coordinates":[6.773223,52.261375],"type":"Point"}
}