{
  "type": "Feature",
  "properties": {
    "addr:full":"Eemhof 8 Eemnes Utrecht 3755 JA",
    "addr:housenumber":"8",
    "addr:postcode":"3755 ja",
    "addr:street":"Eemhof",
    "iso:country":"NL",
    "sg:address":"Eemhof 8",
    "sg:city":"Eemnes",
    "sg:orig_category":"Bloemen And Planten",
    "sg:phone":"+31 35 531 1665",
    "sg:postcode":"3755 JA",
    "sg:province":"Utrecht",
    "wof:name":"Sonia Bloemen",
    "wof:placetype":"venue"
},
  "geometry": {"coordinates":[5.258074,52.258488],"type":"Point"}
}