{
  "type": "Feature",
  "properties": {
    "iso:country":"NL",
    "sg:address":"Hazeldonk 6405",
    "sg:city":"Breda",
    "sg:orig_category":"Elektrotechnische Apparatuur - Fabrieken En Groothandel",
    "sg:phone":"+31 76 596 4509",
    "sg:postcode":"4836 LH",
    "sg:province":"Noord-Brabant",
    "wof:name":"Turbotronic Bv",
    "wof:placetype":"venue"
},
  "geometry": {"coordinates":[4.744876,51.492256],"type":"Point"}
}