{
  "type": "Feature",
  "properties": {
    "addr:full":"Postbus 474 Etten Leur North Brabant 4870 AL",
    "addr:housenumber":"474",
    "addr:postcode":"4870 al",
    "addr:street":"Postbus",
    "iso:country":"NL",
    "sg:address":"Postbus 474",
    "sg:city":"Etten Leur",
    "sg:orig_category":"Hogedrukreinigings- Apparatuur",
    "sg:phone":"+31 499 375 445",
    "sg:postcode":"4870 AL",
    "sg:province":"North Brabant",
    "sg:website":"http://www.karcher.nl",
    "wof:name":"K?rcher Bv",
    "wof:placetype":"venue"
},
  "geometry": {"coordinates":[4.639522,51.570694],"type":"Point"}
}