{
  "type": "Feature",
  "properties": {
    "addr:full":"Hoekeindsewg 49 Bleiswyk Zuid-Holland 2665 KA",
    "addr:housenumber":"49",
    "addr:postcode":"2665 ka",
    "addr:street":"Hoekeindsewg",
    "iso:country":"NL",
    "sg:address":"Hoekeindsewg 49",
    "sg:city":"Bleiswyk",
    "sg:orig_category":"Verzekeringen - Verzekeringskantoren",
    "sg:phone":"+31 10 521 7560",
    "sg:postcode":"2665 KA",
    "sg:province":"Zuid-Holland",
    "wof:name":"Driel Bv, Van",
    "wof:placetype":"venue"
},
  "geometry": {"coordinates":[4.527115,52.004635],"type":"Point"}
}