{
  "type": "Feature",
  "properties": {
    "addr:full":"Ossendamweg 6 Soest Utrecht 3768 CX",
    "addr:housenumber":"6",
    "addr:postcode":"3768 cx",
    "addr:street":"Ossendamweg",
    "iso:country":"NL",
    "sg:address":"Ossendamweg 6",
    "sg:city":"Soest",
    "sg:orig_category":"Verzekeringen - Verzekeringskantoren",
    "sg:phone":"+31 35 647 1658",
    "sg:postcode":"3768 CX",
    "sg:province":"Utrecht",
    "wof:name":"Vakadi Bv",
    "wof:placetype":"venue"
},
  "geometry": {"coordinates":[5.30297,52.16449],"type":"Point"}
}