{
  "type": "Feature",
  "properties": {
    "addr:full":"Kilderseweg 8 Zeddam Gelderland 7038 BW",
    "addr:housenumber":"8",
    "addr:postcode":"7038 bw",
    "addr:street":"Kilderseweg;Gelderland",
    "iso:country":"NL",
    "sg:address":"Kilderseweg 8",
    "sg:city":"Zeddam",
    "sg:orig_category":"Verzekeringen",
    "sg:phone":"+31 314 651 291",
    "sg:postcode":"7038 BW",
    "sg:province":"Gelderland",
    "wof:name":"Assurantiekantoor Bekker",
    "wof:placetype":"venue"
},
  "geometry": {"coordinates":[6.257264,51.904869],"type":"Point"}
}