{
  "type": "Feature",
  "properties": {
    "addr:full":"Vinkstr 10 Breda Noord-Brabant 4815 AV",
    "addr:housenumber":"10",
    "addr:postcode":"4815 av",
    "addr:street":"Vinkstr",
    "iso:country":"NL",
    "sg:address":"Vinkstr 10",
    "sg:city":"Breda",
    "sg:orig_category":"Administratie- En Boekhoudkantoren",
    "sg:phone":"+31 76 587 5268",
    "sg:postcode":"4815 AV",
    "sg:province":"Noord-Brabant",
    "wof:name":"Houtman, M J",
    "wof:placetype":"venue"
},
  "geometry": {"coordinates":[4.775582,51.598217],"type":"Point"}
}