{
  "type": "Feature",
  "properties": {
    "addr:full":"S-Gravendijckseweg 9 Noordwijk Zh Zuid-Holland 2201 CZ",
    "addr:housenumber":"9;2201",
    "addr:street":"S-Gravendijckseweg",
    "iso:country":"NL",
    "sg:address":"S-Gravendijckseweg 9",
    "sg:city":"Noordwijk Zh",
    "sg:orig_category":"Drukkerijen And Copyshops",
    "sg:phone":"+31 71 407 3197",
    "sg:postcode":"2201 CZ",
    "sg:province":"Zuid-Holland",
    "wof:name":"Dupli Job Vof",
    "wof:placetype":"venue"
},
  "geometry": {"coordinates":[4.432589,52.216995],"type":"Point"}
}