{
  "type": "Feature",
  "properties": {
    "addr:full":"Pracanaln 84 Amsterdam North Holland 1060 RC",
    "addr:housenumber":"84",
    "addr:postcode":"1060 rc",
    "addr:street":"Pracanaln",
    "iso:country":"NL",
    "sg:address":"Pracanaln 84",
    "sg:city":"Amsterdam",
    "sg:orig_category":"Fietsen - Fabrieken En Groothandel",
    "sg:phone":"+31 20 619 5346",
    "sg:postcode":"1060 RC",
    "sg:province":"North Holland",
    "sg:website":"http://www.tweeplustwee.nl",
    "wof:name":"Tweeplustwee",
    "wof:placetype":"venue"
},
  "geometry": {"coordinates":[4.780747,52.346973],"type":"Point"}
}