{
  "type": "Feature",
  "properties": {
    "iso:country":"NL",
    "sg:address":"Ginnekenweg 51",
    "sg:city":"Breda",
    "sg:orig_category":"Bloemen And Planten",
    "sg:phone":"+31 76 521 6759",
    "sg:postcode":"4818 JB",
    "sg:province":"North Brabant",
    "wof:name":"V & V Bloemisten",
    "wof:placetype":"venue"
},
  "geometry": {"coordinates":[4.780576,51.577396],"type":"Point"}
}