{
  "type": "Feature",
  "properties": {
    "addr:full":"Huisbergerstraat 5 Heerlen Limburg 6413 VK",
    "addr:housenumber":"5",
    "addr:postcode":"6413 vk",
    "addr:street":"Huisbergerstraat",
    "iso:country":"NL",
    "sg:address":"Huisbergerstraat 5",
    "sg:city":"Heerlen",
    "sg:orig_category":"Meubelzaken, Woning- And Keukeninrichting",
    "sg:phone":"+31 45 570 8526",
    "sg:postcode":"6413 VK",
    "sg:province":"Limburg",
    "wof:name":"De Rijk Interieurs Bv",
    "wof:placetype":"venue"
},
  "geometry": {"coordinates":[5.963397,50.909454],"type":"Point"}
}