{
  "type": "Feature",
  "properties": {
    "addr:full":"Dobben 6 Roden Drenthe 9301 ZB",
    "addr:housenumber":"6",
    "addr:postcode":"9301 zb",
    "addr:street":"Dobben",
    "iso:country":"NL",
    "sg:address":"Dobben 6",
    "sg:city":"Roden",
    "sg:orig_category":"Metaalbekleding And -Behandeling",
    "sg:phone":"+31 50 501 7707",
    "sg:postcode":"9301 ZB",
    "sg:province":"Drenthe",
    "wof:name":"Leitz Service Bv",
    "wof:placetype":"venue"
},
  "geometry": {"coordinates":[6.434202,53.147095],"type":"Point"}
}