{
  "type": "Feature",
  "properties": {
    "iso:country":"NL",
    "sg:address":"Dobben 6",
    "sg:city":"Roden",
    "sg:orig_category":"Metaalbekleding And -Behandeling",
    "sg:phone":"+31 50 501 7707",
    "sg:postcode":"9301 ZB",
    "sg:province":"Drenthe",
    "wof:name":"Leitz Service Bv",
    "wof:placetype":"venue"
},
  "geometry": {"coordinates":[6.434202,53.147095],"type":"Point"}
}