{
  "type": "Feature",
  "properties": {
    "addr:full":"Groenvinkstraat 24 Maastricht Limburg 6229 VH",
    "addr:housenumber":"24",
    "addr:postcode":"6229 vh",
    "addr:street":"Groenvinkstraat",
    "iso:country":"NL",
    "sg:address":"Groenvinkstraat 24",
    "sg:city":"Maastricht",
    "sg:orig_category":"Autokeuringen",
    "sg:phone":"+31 43 408 1996",
    "sg:postcode":"6229 VH",
    "sg:province":"Limburg",
    "wof:name":"Frans Wolters",
    "wof:placetype":"venue"
},
  "geometry": {"coordinates":[5.718187,50.817883],"type":"Point"}
}