{
  "type": "Feature",
  "properties": {
    "iso:country":"NL",
    "sg:address":"Roodhemsterweg 16",
    "sg:city":"Ijlst",
    "sg:orig_category":"Werving And Selectie Van Tijdelijk Personeel And Uitzendkantoren",
    "sg:phone":"+31 515 532 645",
    "sg:postcode":"8651 CV",
    "sg:province":"Provincie Friesland",
    "wof:name":"Ab Service",
    "wof:placetype":"venue"
},
  "geometry": {"coordinates":[5.6201500893,53.015586853],"type":"Point"}
}