{
  "type": "Feature",
  "properties": {
    "iso:country":"NL",
    "sg:address":"Jonkerhof 5",
    "sg:city":"Rhoon",
    "sg:orig_category":"Honden- En Kattentrimsalons",
    "sg:phone":"+31 10 501 3484",
    "sg:postcode":"3161 LH",
    "sg:province":"South Holland",
    "wof:name":"Pebbles",
    "wof:placetype":"venue"
},
  "geometry": {"coordinates":[4.41303,51.860374],"type":"Point"}
}