{
  "type": "Feature",
  "properties": {
    "addr:full":"Jonkerhof 5 Rhoon South Holland 3161 LH",
    "addr:housenumber":"5",
    "addr:postcode":"3161 lh",
    "addr:street":"Jonkerhof",
    "iso:country":"NL",
    "sg:address":"Jonkerhof 5",
    "sg:city":"Rhoon",
    "sg:orig_category":"Honden- En Kattentrimsalons",
    "sg:phone":"+31 10 501 3484",
    "sg:postcode":"3161 LH",
    "sg:province":"South Holland",
    "wof:name":"Pebbles",
    "wof:placetype":"venue"
},
  "geometry": {"coordinates":[4.41303,51.860374],"type":"Point"}
}