{
  "type": "Feature",
  "properties": {
    "addr:full":"Cicerolaan 9 Utrecht Utrecht 3584 AJ",
    "addr:housenumber":"9",
    "addr:postcode":"3584 aj",
    "addr:street":"Cicerolaan",
    "iso:country":"NL",
    "sg:address":"Cicerolaan 9",
    "sg:city":"Utrecht",
    "sg:orig_category":"Juridische Dienstverlening",
    "sg:phone":"+31 30 251 2043",
    "sg:postcode":"3584 AJ",
    "sg:province":"Utrecht",
    "wof:name":"C. Van Buren",
    "wof:placetype":"venue"
},
  "geometry": {"coordinates":[5.156687,52.083729],"type":"Point"}
}