{
  "type": "Feature",
  "properties": {
    "addr:full":"Kasteelln 33 Raamsdonksveer Noord-Brabant 4941 XM",
    "addr:housenumber":"33",
    "addr:postcode":"4941 xm",
    "addr:street":"Kasteelln",
    "iso:country":"NL",
    "sg:address":"Kasteelln 33",
    "sg:city":"Raamsdonksveer",
    "sg:orig_category":"Schilders",
    "sg:phone":"+31 162 519 143",
    "sg:postcode":"4941 XM",
    "sg:province":"Noord-Brabant",
    "wof:name":"Jens",
    "wof:placetype":"venue"
},
  "geometry": {"coordinates":[4.87459,51.695774],"type":"Point"}
}