{
  "type": "Feature",
  "properties": {
    "addr:full":"Linze 11 Geldrop Noord-Brabant 5667 AH",
    "addr:housenumber":"11",
    "addr:postcode":"5667 ah",
    "addr:street":"Linze",
    "iso:country":"NL",
    "sg:address":"Linze 11",
    "sg:city":"Geldrop",
    "sg:orig_category":"Sportverenigingen En Ontspannings- Verenigingen",
    "sg:phone":"+31 40 285 6786",
    "sg:postcode":"5667 AH",
    "sg:province":"Noord-Brabant",
    "wof:name":"Dle Jeu De Boulesver",
    "wof:placetype":"venue"
},
  "geometry": {"coordinates":[5.559541,51.430016],"type":"Point"}
}