{
  "type": "Feature",
  "properties": {
    "addr:full":"Bovenmaatwg 301 Huizen North Holland 1274 RJ",
    "addr:housenumber":"301",
    "addr:postcode":"1274 rj",
    "iso:country":"NL",
    "sg:address":"Bovenmaatwg 301",
    "sg:city":"Huizen",
    "sg:orig_category":"Perzische En Oosterse Tapijten",
    "sg:phone":"+31 35 525 5622",
    "sg:postcode":"1274 RJ",
    "sg:province":"North Holland",
    "wof:name":"David'S Carpets International",
    "wof:placetype":"venue"
},
  "geometry": {"coordinates":[5.269882,52.299492],"type":"Point"}
}