{
  "type": "Feature",
  "properties": {
    "addr:full":"Molenweg 8 Stramproy Limburg 6039 RH",
    "addr:housenumber":"8",
    "addr:postcode":"6039 rh",
    "addr:street":"Molenweg",
    "iso:country":"NL",
    "sg:address":"Molenweg 8",
    "sg:city":"Stramproy",
    "sg:orig_category":"Schoenen",
    "sg:phone":"+31 495 561 471",
    "sg:postcode":"6039 RH",
    "sg:province":"Limburg",
    "wof:name":"C Hermans",
    "wof:placetype":"venue"
},
  "geometry": {"coordinates":[5.726394,51.193954],"type":"Point"}
}