{
  "type": "Feature",
  "properties": {
    "iso:country":"NL",
    "sg:address":"Wykstr 25",
    "sg:city":"Appingedam",
    "sg:orig_category":"Musea",
    "sg:phone":"+31 596 680 168",
    "sg:postcode":"9901 AE",
    "sg:province":"Groningen",
    "wof:name":"Museum Stad Appingedam",
    "wof:placetype":"venue"
},
  "geometry": {"coordinates":[6.8578882217,53.322593689],"type":"Point"}
}