{
  "type": "Feature",
  "properties": {
    "iso:country":"NL",
    "sg:address":"Skagerrak 1",
    "sg:city":"Emmeloord",
    "sg:classifiers":[
        {
            "category":"Education",
            "subcategory":"Preschool",
            "type":"Public Place"
        }
    ],
    "sg:phone":"+31 527 612 321",
    "sg:postcode":"8303 VA",
    "sg:province":"Flevoland",
    "sg:tags":[
        "kleuteronderwijs",
        "basis-"
    ],
    "wof:name":"Openbare Basisschool Roderik Van Voorst",
    "wof:placetype":"venue"
},
  "geometry": {"coordinates":[5.735553,52.712299],"type":"Point"}
}