{
  "type": "Feature",
  "properties": {
    "addr:full":"Kerkstraat 71 Nieuw Vennep Noord-Holland 2153 BE",
    "addr:housenumber":"71",
    "addr:postcode":"2153",
    "addr:street":"Kerkstraat;Nieuw Vennep",
    "iso:country":"NL",
    "sg:address":"Kerkstraat 71",
    "sg:city":"Nieuw Vennep",
    "sg:orig_category":"Metaalwerken",
    "sg:phone":"+31 252 686 801",
    "sg:postcode":"2153 BE",
    "sg:province":"Noord-Holland",
    "wof:name":"A.C. Verhoeve Plafonds",
    "wof:placetype":"venue"
},
  "geometry": {"coordinates":[4.636385,52.261299],"type":"Point"}
}