{
  "type": "Feature",
  "properties": {
    "addr:full":"Velstrawg 2 Leeuwarden Provincie Friesland 8917 DC",
    "addr:housenumber":"2",
    "addr:postcode":"8917",
    "addr:street":"Velstrawg;Provincie Friesland",
    "iso:country":"NL",
    "sg:address":"Velstrawg 2",
    "sg:city":"Leeuwarden",
    "sg:classifiers":[
        {
            "category":"Sports & Exercise",
            "subcategory":"Stables",
            "type":"Entertainment"
        }
    ],
    "sg:phone":"+31 58 213 8877",
    "sg:postcode":"8917 DC",
    "sg:province":"Provincie Friesland",
    "sg:tags":[
        "maneges"
    ],
    "wof:name":"Leeuwarder Manege",
    "wof:placetype":"venue"
},
  "geometry": {"coordinates":[5.79257,53.197319],"type":"Point"}
}