{
  "type": "Feature",
  "properties": {
    "iso:country":"NL",
    "sg:address":"Ruyschstraat 39",
    "sg:city":"Amsterdam",
    "sg:orig_category":"Fotostudio'S And Fotografen",
    "sg:phone":"+31 20 665 2332",
    "sg:postcode":"1091 BS",
    "sg:province":"Noord-Holland",
    "wof:name":"Fotostudio Govaers",
    "wof:placetype":"venue"
},
  "geometry": {"coordinates":[4.909508,52.35746],"type":"Point"}
}