{
  "type": "Feature",
  "properties": {
    "addr:full":"Leeuwerikstraat 3 Eys Limburg 6287 BD",
    "addr:housenumber":"3",
    "addr:postcode":"6287 bd",
    "addr:street":"Leeuwerikstraat",
    "iso:country":"NL",
    "sg:address":"Leeuwerikstraat 3",
    "sg:city":"Eys",
    "sg:orig_category":"Medische Apparatuur And Prothesen Fab",
    "sg:phone":"+31 43 451 2336",
    "sg:postcode":"6287 BD",
    "sg:province":"Limburg",
    "wof:name":"Dentalab Eys",
    "wof:placetype":"venue"
},
  "geometry": {"coordinates":[5.940708,50.824383],"type":"Point"}
}