{
  "type": "Feature",
  "properties": {
    "addr:full":"Laar 72 Nistelrode North Brabant 5388 HK",
    "addr:housenumber":"72",
    "addr:postcode":"5388 hk",
    "addr:street":"Laar",
    "iso:country":"NL",
    "sg:address":"Laar 72",
    "sg:city":"Nistelrode",
    "sg:orig_category":"Geluidsinstallaties - Verhuur",
    "sg:phone":"+31 412 613 216",
    "sg:postcode":"5388 HK",
    "sg:province":"North Brabant",
    "wof:name":"Regionale Facilitaire Omroep",
    "wof:placetype":"venue"
},
  "geometry": {"coordinates":[5.565484,51.700016],"type":"Point"}
}