{
  "type": "Feature",
  "properties": {
    "iso:country":"NL",
    "sg:address":"Binnenban 75",
    "sg:city":"Hoogvliet Rt",
    "sg:orig_category":"Poeliers",
    "sg:phone":"+31 10 472 2251",
    "sg:postcode":"3191 CB",
    "sg:province":"Zuid-Holland",
    "wof:name":"Broesterhuizen, M",
    "wof:placetype":"venue"
},
  "geometry": {"coordinates":[4.354661,51.865334],"type":"Point"}
}