{
  "type": "Feature",
  "properties": {
    "addr:full":"Rooseveltlaan 266 Amsterdam Noord-Holland 1078 PA",
    "addr:housenumber":"266",
    "addr:postcode":"1078 pa",
    "addr:street":"Rooseveltlaan",
    "iso:country":"NL",
    "sg:address":"Rooseveltlaan 266",
    "sg:city":"Amsterdam",
    "sg:orig_category":"Boekhouders",
    "sg:phone":"+31 20 679 3180",
    "sg:postcode":"1078 PA",
    "sg:province":"Noord-Holland",
    "wof:name":"R.L. Sandbrink Belastingadviseur",
    "wof:placetype":"venue"
},
  "geometry": {"coordinates":[-94.58503,38.350479],"type":"Point"}
}