{
  "type": "Feature",
  "properties": {
    "addr:full":"Badweg 3 Vlieland Provincie Friesland 8899 BV",
    "addr:housenumber":"3",
    "addr:postcode":"8899 bv",
    "addr:street":"Badweg;Friesland",
    "iso:country":"NL",
    "sg:address":"Badweg 3",
    "sg:city":"Vlieland",
    "sg:orig_category":"Granen, Zaden And Diervoeders Gh",
    "sg:phone":"+31 562 451 962",
    "sg:postcode":"8899 BV",
    "sg:province":"Provincie Friesland",
    "wof:name":"Manege De Seeruyter Vof",
    "wof:placetype":"venue"
},
  "geometry": {"coordinates":[5.052836,53.303017],"type":"Point"}
}