{
  "type": "Feature",
  "properties": {
    "addr:full":"Benedictynenborch 29 Rosmalen Noord-Brabant 5241 KR",
    "addr:housenumber":"29",
    "addr:postcode":"5241 kr",
    "addr:street":"Benedictynenborch",
    "iso:country":"NL",
    "sg:address":"Benedictynenborch 29",
    "sg:city":"Rosmalen",
    "sg:orig_category":"Adviesbureaus Bedrijfsorganisatie",
    "sg:phone":"+31 73 523 6123",
    "sg:postcode":"5241 KR",
    "sg:province":"Noord-Brabant",
    "sg:website":"http://www.H2M-Advies.nl",
    "wof:name":"H2M-Milieuadvies",
    "wof:placetype":"venue"
},
  "geometry": {"coordinates":[5.359815,51.72353],"type":"Point"}
}