{
  "type": "Feature",
  "properties": {
    "iso:country":"NL",
    "sg:address":"Rypelberg 3",
    "sg:city":"Helmond",
    "sg:orig_category":"Loonbedrijven",
    "sg:phone":"+31 492 512 789",
    "sg:postcode":"5703 KD",
    "sg:province":"Noord-Brabant",
    "wof:name":"Boxmeer Vof, Van",
    "wof:placetype":"venue"
},
  "geometry": {"coordinates":[5.692642,51.478199],"type":"Point"}
}