{
  "type": "Feature",
  "properties": {
    "addr:full":"Smidsweg 49 Ermelo Gelderland 3852 XA",
    "addr:housenumber":"49",
    "addr:postcode":"3852 xa",
    "addr:street":"Smidsweg;Gelderland",
    "iso:country":"NL",
    "sg:address":"Smidsweg 49",
    "sg:city":"Ermelo",
    "sg:classifiers":[
        {
            "category":"Education",
            "subcategory":"Preschool",
            "type":"Public Place"
        }
    ],
    "sg:phone":"+31 341 554 186",
    "sg:postcode":"3852 XA",
    "sg:province":"Gelderland",
    "sg:tags":[
        "kleuteronderwijs",
        "basis-"
    ],
    "wof:name":"Beatrixschool",
    "wof:placetype":"venue"
},
  "geometry": {"coordinates":[5.63268,52.297562],"type":"Point"}
}