{
  "type": "Feature",
  "properties": {
    "addr:full":"O L Vrouwe Ter Duinenln 45 Ossendrecht Noord-Brabant 4641 HB",
    "addr:housenumber":"45",
    "addr:postcode":"4641 hb",
    "addr:street":"O;Vrouwe",
    "iso:country":"NL",
    "sg:address":"O L Vrouwe Ter Duinenln 45",
    "sg:city":"Ossendrecht",
    "sg:orig_category":"Diverse Consumentenartikelen Gh",
    "sg:phone":"+31 164 674 401",
    "sg:postcode":"4641 HB",
    "sg:province":"Noord-Brabant",
    "wof:name":"G. Veraart",
    "wof:placetype":"venue"
},
  "geometry": {"coordinates":[4.327878,51.396736],"type":"Point"}
}