{
  "type": "Feature",
  "properties": {
    "iso:country":"NL",
    "sg:address":"Krodde 10",
    "sg:city":"Uithoorn",
    "sg:orig_category":"Medische Apparatuur And Prothesen Fab",
    "sg:phone":"+31 297 534 766",
    "sg:postcode":"1422 KJ",
    "sg:province":"Noord-Holland",
    "wof:name":"F M De Vries",
    "wof:placetype":"venue"
},
  "geometry": {"coordinates":[4.821986,52.251709],"type":"Point"}
}