{
  "type": "Feature",
  "properties": {
    "addr:full":"Meilanden 86 Barneveld Gelderland 3773 ZN",
    "addr:housenumber":"86",
    "addr:postcode":"3773 zn",
    "addr:street":"Meilanden;Gelderland",
    "iso:country":"NL",
    "sg:address":"Meilanden 86",
    "sg:city":"Barneveld",
    "sg:orig_category":"Verbouwingen",
    "sg:phone":"+31 342 424 313",
    "sg:postcode":"3773 ZN",
    "sg:province":"Gelderland",
    "wof:name":"Vliet, G Van",
    "wof:placetype":"venue"
},
  "geometry": {"coordinates":[5.609402,52.135941],"type":"Point"}
}