{
  "type": "Feature",
  "properties": {
    "addr:full":"Ir Vd Sluysplnts 19 S Gravenhage Zuid-Holland 2591 CW",
    "addr:housenumber":"19;gravenhage",
    "addr:postcode":"2591 cw",
    "addr:street":"Ir;S",
    "iso:country":"NL",
    "sg:address":"Ir Vd Sluysplnts 19",
    "sg:city":"S Gravenhage",
    "sg:orig_category":"Adviesbureaus Bedrijfsorganisatie",
    "sg:phone":"+31 6 54277273",
    "sg:postcode":"2591 CW",
    "sg:province":"Zuid-Holland",
    "wof:name":"Delta 2000",
    "wof:placetype":"venue"
},
  "geometry": {"coordinates":[4.3639001846,52.0935096741],"type":"Point"}
}