{
  "type": "Feature",
  "properties": {
    "iso:country":"NL",
    "sg:address":"Groene Hilledijk 183",
    "sg:city":"Rotterdam",
    "sg:orig_category":"Huishoudapparatuur, Televisies And Radio'S",
    "sg:phone":"+31 10 423 0005",
    "sg:postcode":"3073 AC",
    "sg:province":"South Holland",
    "wof:name":"Handyman",
    "wof:placetype":"venue"
},
  "geometry": {"coordinates":[4.508746,51.892471],"type":"Point"}
}