{
  "type": "Feature",
  "properties": {
    "addr:full":"Sonoystr 29A Rotterdam Zuid-Holland 3039 ZS",
    "addr:housenumber":"29a",
    "addr:postcode":"3039 zs",
    "addr:street":"Sonoystr",
    "iso:country":"NL",
    "sg:address":"Sonoystr 29A",
    "sg:city":"Rotterdam",
    "sg:orig_category":"Fotoreportages",
    "sg:phone":"+31 10 265 3840",
    "sg:postcode":"3039 ZS",
    "sg:province":"Zuid-Holland",
    "wof:name":"Vane, John",
    "wof:placetype":"venue"
},
  "geometry": {"coordinates":[4.461803,51.927586],"type":"Point"}
}