{
  "type": "Feature",
  "properties": {
    "addr:full":"Heerewg 95 Schoorl Noord-Holland 1871 ED",
    "addr:housenumber":"95",
    "addr:postcode":"1871 ed",
    "addr:street":"Heerewg",
    "iso:country":"NL",
    "sg:address":"Heerewg 95",
    "sg:city":"Schoorl",
    "sg:orig_category":"Adviesbureaus Bedrijfsorganisatie",
    "sg:phone":"+31 72 509 3697",
    "sg:postcode":"1871 ED",
    "sg:province":"Noord-Holland",
    "wof:name":"Proma",
    "wof:placetype":"venue"
},
  "geometry": {"coordinates":[4.690351,52.708412],"type":"Point"}
}