{
  "type": "Feature",
  "properties": {
    "addr:full":"Papenw 16 Mheer Limburg 6261 NE",
    "addr:housenumber":"16",
    "addr:postcode":"6261 ne",
    "addr:street":"Papenw",
    "iso:country":"NL",
    "sg:address":"Papenw 16",
    "sg:city":"Mheer",
    "sg:orig_category":"Beeldende Kunstenaars",
    "sg:phone":"+31 43 457 1978",
    "sg:postcode":"6261 NE",
    "sg:province":"Limburg",
    "wof:name":"Hameleers, J J F",
    "wof:placetype":"venue"
},
  "geometry": {"coordinates":[5.796517,50.777287],"type":"Point"}
}