{
  "type": "Feature",
  "properties": {
    "addr:full":"Het Hoekstuk 9 Heiloo Noord-Holland 1852 KX",
    "addr:housenumber":"9",
    "addr:postcode":"1852 kx",
    "addr:street":"Het Hoekstuk",
    "iso:country":"NL",
    "sg:address":"Het Hoekstuk 9",
    "sg:city":"Heiloo",
    "sg:classifiers":[
        {
            "category":"Farming",
            "subcategory":"Fish & Marine Products",
            "type":"Manufacturing & Wholesale Goods"
        }
    ],
    "sg:phone":"+31 72 534 1014",
    "sg:postcode":"1852 KX",
    "sg:province":"Noord-Holland",
    "sg:tags":[
        "vi"
    ],
    "wof:name":"Michel",
    "wof:placetype":"venue"
},
  "geometry": {"coordinates":[4.687475,52.603928],"type":"Point"}
}