{
  "type": "Feature",
  "properties": {
    "addr:full":"De Hoogstraat 23 Vlijmen Noord-Brabant 5251 PN",
    "addr:housenumber":"23",
    "addr:postcode":"5251 pn",
    "addr:street":"De Hoogstraat",
    "iso:country":"NL",
    "sg:address":"De Hoogstraat 23",
    "sg:city":"Vlijmen",
    "sg:classifiers":[
        {
            "category":"Fast Food",
            "type":"Food & Drink"
        }
    ],
    "sg:phone":"+31 73 511 7550",
    "sg:postcode":"5251 PN",
    "sg:province":"Noord-Brabant",
    "sg:tags":[
        "afhaal",
        "restaurant"
    ],
    "wof:name":"H.L. Koks",
    "wof:placetype":"venue"
},
  "geometry": {"coordinates":[5.196097,51.690231],"type":"Point"}
}