{
  "type": "Feature",
  "properties": {
    "addr:full":"Tarwestr 8 Hengelo Ov NL.08 7552 DT",
    "addr:housenumber":"8",
    "addr:postcode":"7552 dt",
    "addr:street":"Tarwestr;Ov",
    "iso:country":"NL",
    "sg:address":"Tarwestr 8",
    "sg:city":"Hengelo Ov",
    "sg:orig_category":"Elektronica - Ontwikkeling En Groothandel",
    "sg:phone":"+31 74 256 6002",
    "sg:postcode":"7552 DT",
    "sg:province":"NL.08",
    "wof:name":"Microflex",
    "wof:placetype":"venue"
},
  "geometry": {"coordinates":[6.810468,52.25922],"type":"Point"}
}