{
  "type": "Feature",
  "properties": {
    "addr:full":"Emmasngl 5 Weert Limburg 6001 BA",
    "addr:housenumber":"5",
    "addr:postcode":"6001 ba",
    "addr:street":"Emmasngl",
    "iso:country":"NL",
    "sg:address":"Emmasngl 5",
    "sg:city":"Weert",
    "sg:orig_category":"Makelaars En Adviseurs Onroerende Goederen",
    "sg:phone":"+31 495 537 599",
    "sg:postcode":"6001 BA",
    "sg:province":"Limburg",
    "sg:website":"http://www.renedwars.nl",
    "wof:name":"Dwars Bv, Rene",
    "wof:placetype":"venue"
},
  "geometry": {"coordinates":[5.703781,51.255016],"type":"Point"}
}