{
  "type": "Feature",
  "properties": {
    "addr:full":"Lhee 76 Dwingeloo Drenthe 7991 PJ",
    "addr:housenumber":"76",
    "addr:postcode":"7991 pj",
    "addr:street":"Lhee",
    "iso:country":"NL",
    "sg:address":"Lhee 76",
    "sg:city":"Dwingeloo",
    "sg:classifiers":[
        {
            "category":"Travel",
            "subcategory":"Hotels & Motels",
            "type":"Entertainment"
        }
    ],
    "sg:phone":"+31 521 597 200",
    "sg:postcode":"7991 PJ",
    "sg:province":"Drenthe",
    "wof:name":"B\u00f7Rken, De",
    "wof:placetype":"venue"
},
  "geometry": {"coordinates":[6.395942,52.825146],"type":"Point"}
}