{
  "type": "Feature",
  "properties": {
    "addr:full":"Wijchenseweg 20 Nijmegen Gelderland 6537 TL",
    "addr:housenumber":"20",
    "addr:postcode":"6537 tl",
    "addr:street":"Wijchenseweg;Gelderland",
    "iso:country":"NL",
    "sg:address":"Wijchenseweg 20",
    "sg:city":"Nijmegen",
    "sg:orig_category":"Verzekeringen",
    "sg:phone":"+31 24 343 6666",
    "sg:postcode":"6537 TL",
    "sg:province":"Gelderland",
    "wof:name":"Zorgverzekeraar Vgz",
    "wof:placetype":"venue"
},
  "geometry": {"coordinates":[5.789859,51.824406],"type":"Point"}
}