{
  "type": "Feature",
  "properties": {
    "addr:full":"Noord 28 Schagen North Holland 1741 BD",
    "addr:housenumber":"28",
    "addr:postcode":"1741 bd",
    "addr:street":"Noord",
    "iso:country":"NL",
    "sg:address":"Noord 28",
    "sg:city":"Schagen",
    "sg:orig_category":"Boekhouders",
    "sg:phone":"+31 224 212 984",
    "sg:postcode":"1741 BD",
    "sg:province":"North Holland",
    "wof:name":"Adm Kantoor A C Schippers & N J M Rietke",
    "wof:placetype":"venue"
},
  "geometry": {"coordinates":[4.795655,52.787502],"type":"Point"}
}