{
  "type": "Feature",
  "properties": {
    "iso:country":"NL",
    "sg:address":"M J Kosterstr 6",
    "sg:city":"Amsterdam",
    "sg:orig_category":"Modellenbureaus En Modellen Freelance",
    "sg:phone":"+31 20 489 3844",
    "sg:postcode":"1017 VX",
    "sg:province":"North Holland",
    "wof:name":"Us Entertainment Group",
    "wof:placetype":"venue"
},
  "geometry": {"coordinates":[4.901547,52.360561],"type":"Point"}
}