{
  "type": "Feature",
  "properties": {
    "iso:country":"NL",
    "sg:address":"Van Eeghenstraat 93",
    "sg:city":"Amsterdam",
    "sg:orig_category":"Marketingbureaus",
    "sg:phone":"+31 20 679 1471",
    "sg:postcode":"1071 EX",
    "sg:province":"North Holland",
    "wof:name":"De Schepper Campagnes",
    "wof:placetype":"venue"
},
  "geometry": {"coordinates":[4.872404,52.357155],"type":"Point"}
}