{
  "type": "Feature",
  "properties": {
    "addr:full":"Hannie Schaftstraat 150 Haarlem Noord-Holland 2033 PS",
    "addr:housenumber":"150",
    "addr:postcode":"2033 ps",
    "addr:street":"Hannie Schaftstraat",
    "iso:country":"NL",
    "sg:address":"Hannie Schaftstraat 150",
    "sg:city":"Haarlem",
    "sg:orig_category":"Fitnesscentra",
    "sg:phone":"+31 23 536 2914",
    "sg:postcode":"2033 PS",
    "sg:province":"Noord-Holland",
    "wof:name":"Everybody",
    "wof:placetype":"venue"
},
  "geometry": {"coordinates":[4.652615,52.371052],"type":"Point"}
}