{
  "type": "Feature",
  "properties": {
    "iso:country":"NL",
    "sg:address":"Bergeijksedijk 10",
    "sg:city":"Eersel",
    "sg:orig_category":"Fietshandelaren",
    "sg:phone":"+31 497 518 864",
    "sg:postcode":"5521 NA",
    "sg:province":"North Brabant",
    "wof:name":"Joybike!",
    "wof:placetype":"venue"
},
  "geometry": {"coordinates":[5.322118,51.356674],"type":"Point"}
}