{
  "type": "Feature",
  "properties": {
    "iso:country":"NL",
    "sg:address":"Molendk 38",
    "sg:city":"Oud Beyerland",
    "sg:orig_category":"Woninginrichting",
    "sg:phone":"+31 186 612 031",
    "sg:postcode":"3262 AK",
    "sg:province":"Zuid-Holland",
    "sg:website":"http://www.donkersloot-woondecoratie.nl",
    "wof:name":"Donkersloot, Woondecoratie",
    "wof:placetype":"venue"
},
  "geometry": {"coordinates":[4.4094948769,51.8270187378],"type":"Point"}
}