{
  "type": "Feature",
  "properties": {
    "addr:full":"Clarissenstr 2 Wamel Gelderland 6659 BN",
    "addr:housenumber":"2",
    "addr:postcode":"6659 bn",
    "addr:street":"Clarissenstr;Gelderland",
    "iso:country":"NL",
    "sg:address":"Clarissenstr 2",
    "sg:city":"Wamel",
    "sg:orig_category":"Verenigingen En Stichtingen",
    "sg:phone":"+31 487 501 467",
    "sg:postcode":"6659 BN",
    "sg:province":"Gelderland",
    "sg:website":"http://www.federatie-dorpshuizen-gelderland.nl",
    "wof:name":"Federatie Van Dorpshuizen",
    "wof:placetype":"venue"
},
  "geometry": {"coordinates":[5.469036,51.880901],"type":"Point"}
}