{
  "type": "Feature",
  "properties": {
    "addr:full":"Boezemwg 2B Pynacker South Holland 2641 KH",
    "addr:housenumber":"2b",
    "addr:postcode":"pynacker;2641 kh",
    "addr:street":"Boezemwg",
    "iso:country":"NL",
    "sg:address":"Boezemwg 2B",
    "sg:city":"Pynacker",
    "sg:classifiers":[
        {
            "category":"Food & Beverages",
            "subcategory":"Bakery",
            "type":"Retail Goods"
        }
    ],
    "sg:phone":"+31 15 364 0364",
    "sg:postcode":"2641 KH",
    "sg:province":"South Holland",
    "sg:tags":[
        "pizza"
    ],
    "wof:name":"Atlantic",
    "wof:placetype":"venue"
},
  "geometry": {"coordinates":[4.425071,51.987968],"type":"Point"}
}