{
  "type": "Feature",
  "properties": {
    "addr:full":"Waverdijk 15 Waverveen North Holland 3646 AS",
    "addr:housenumber":"15",
    "addr:postcode":"3646 as",
    "addr:street":"Waverdijk",
    "iso:country":"NL",
    "sg:address":"Waverdijk 15",
    "sg:city":"Waverveen",
    "sg:orig_category":"Partycatering And -Organisatie",
    "sg:phone":"+31 297 582 473",
    "sg:postcode":"3646 AS",
    "sg:province":"North Holland",
    "wof:name":"Het Kraamfeestburo",
    "wof:placetype":"venue"
},
  "geometry": {"coordinates":[4.870629,52.250713],"type":"Point"}
}