{
  "type": "Feature",
  "properties": {
    "addr:full":"Hoenderkamp 14 Emmen Provincie Drenthe 7812 VZ",
    "addr:housenumber":"14;7812",
    "addr:postcode":"vz",
    "addr:street":"Hoenderkamp;Provincie Drenthe",
    "iso:country":"NL",
    "sg:address":"Hoenderkamp 14",
    "sg:city":"Emmen",
    "sg:orig_category":"Adviesbureaus Bouwkunde",
    "sg:phone":"+31 591 647 858",
    "sg:postcode":"7812 VZ",
    "sg:province":"Provincie Drenthe",
    "sg:website":"http://www.tms-holland.nl",
    "wof:name":"Tms Holland Bv",
    "wof:placetype":"venue"
},
  "geometry": {"coordinates":[6.897925,52.770935],"type":"Point"}
}