{
  "type": "Feature",
  "properties": {
    "iso:country":"NL",
    "sg:address":"Kralingsewg 120",
    "sg:city":"Rotterdam",
    "sg:classifiers":[
        {
            "category":"Sports & Exercise",
            "subcategory":"Stables",
            "type":"Entertainment"
        }
    ],
    "sg:phone":"+31 10 452 6838",
    "sg:postcode":"3062 CG",
    "sg:province":"Zuid-Holland",
    "sg:tags":[
        "maneges"
    ],
    "wof:name":"Rotterdamsche Manege, De",
    "wof:placetype":"venue"
},
  "geometry": {"coordinates":[4.526677,51.926479],"type":"Point"}
}