{
  "type": "Feature",
  "properties": {
    "addr:full":"De Schans 76 Hoornaar Zuid-Holland 4223 NW",
    "addr:housenumber":"76",
    "addr:postcode":"4223 nw",
    "addr:street":"De Schans",
    "iso:country":"NL",
    "sg:address":"De Schans 76",
    "sg:city":"Hoornaar",
    "sg:orig_category":"Paramedische Behandelingen",
    "sg:phone":"+31 183 582 132",
    "sg:postcode":"4223 NW",
    "sg:province":"Zuid-Holland",
    "wof:name":"Logopedische Dienst Kring Sliedrecht",
    "wof:placetype":"venue"
},
  "geometry": {"coordinates":[4.949539,51.876637],"type":"Point"}
}