{
  "type": "Feature",
  "properties": {
    "addr:full":"Leembaan 31 Deurne Noord-Brabant 5753 CW",
    "addr:housenumber":"31",
    "addr:postcode":"5753 cw",
    "addr:street":"Leembaan",
    "iso:country":"NL",
    "sg:address":"Leembaan 31",
    "sg:city":"Deurne",
    "sg:orig_category":"Metselwerken",
    "sg:phone":"+31 493 316 373",
    "sg:postcode":"5753 CW",
    "sg:province":"Noord-Brabant",
    "wof:name":"Bankers Metselwerken Bv",
    "wof:placetype":"venue"
},
  "geometry": {"coordinates":[5.793773,51.450146],"type":"Point"}
}