{
  "type": "Feature",
  "properties": {
    "addr:full":"Johan Wagenaarstraat 51 Purmerend North Holland 1443 LR",
    "addr:housenumber":"51",
    "addr:postcode":"1443 lr",
    "addr:street":"Johan Wagenaarstraat",
    "iso:country":"NL",
    "sg:address":"Johan Wagenaarstraat 51",
    "sg:city":"Purmerend",
    "sg:orig_category":"Loodgieterswerk, Verwarming And Sanitaire Installaties",
    "sg:phone":"+31 299 421 010",
    "sg:postcode":"1443 LR",
    "sg:province":"North Holland",
    "wof:name":"J. Ter Haak",
    "wof:placetype":"venue"
},
  "geometry": {"coordinates":[4.970816,52.504784],"type":"Point"}
}