{
  "type": "Feature",
  "properties": {
    "addr:full":"Jupiterweg 18 Leeuwarden Friesland 8938 AE",
    "addr:housenumber":"18",
    "addr:postcode":"8938 ae",
    "addr:street":"Jupiterweg",
    "iso:country":"NL",
    "sg:address":"Jupiterweg 18",
    "sg:city":"Leeuwarden",
    "sg:orig_category":"Glaszetten",
    "sg:phone":"+31 58 288 6854",
    "sg:postcode":"8938 AE",
    "sg:province":"Friesland",
    "wof:name":"De Noordhoek Schilderwerken",
    "wof:placetype":"venue"
},
  "geometry": {"coordinates":[5.843118,53.196384],"type":"Point"}
}