{
  "type": "Feature",
  "properties": {
    "iso:country":"NL",
    "sg:address":"Vyverhofstr 30-32",
    "sg:city":"Rotterdam",
    "sg:orig_category":"Fotografie Reclame En Mode",
    "sg:phone":"+31 6 16480487",
    "sg:postcode":"3032 SN",
    "sg:province":"South Holland",
    "wof:name":"Visser, Guido De",
    "wof:placetype":"venue"
},
  "geometry": {"coordinates":[4.476799,51.929085],"type":"Point"}
}