{
  "type": "Feature",
  "properties": {
    "addr:full":"Provincialewg 9 Limbricht Limburg 6141 AA",
    "addr:housenumber":"9",
    "addr:postcode":"6141 aa",
    "addr:street":"Provincialewg",
    "iso:country":"NL",
    "sg:address":"Provincialewg 9",
    "sg:city":"Limbricht",
    "sg:classifiers":[
        {
            "category":"Food & Beverages",
            "subcategory":"Bakery",
            "type":"Retail Goods"
        }
    ],
    "sg:phone":"+31 46 451 0315",
    "sg:postcode":"6141 AA",
    "sg:province":"Limburg",
    "sg:tags":[
        "pizza"
    ],
    "wof:name":"Arbil",
    "wof:placetype":"venue"
},
  "geometry": {"coordinates":[5.839016,51.011467],"type":"Point"}
}