{
  "type": "Feature",
  "properties": {
    "addr:full":"Skutsje 7 Woerden Utrecht 3448 KW",
    "addr:housenumber":"7",
    "addr:postcode":"3448 kw",
    "addr:street":"Skutsje",
    "iso:country":"NL",
    "sg:address":"Skutsje 7",
    "sg:city":"Woerden",
    "sg:orig_category":"Diverse Grafische Activiteiten",
    "sg:phone":"+31 348 423 492",
    "sg:postcode":"3448 KW",
    "sg:province":"Utrecht",
    "wof:name":"Fred Rietveld",
    "wof:placetype":"venue"
},
  "geometry": {"coordinates":[4.854755,52.081802],"type":"Point"}
}