{
  "type": "Feature",
  "properties": {
    "addr:full":"Ridderhof 19 Alphen A/D Rijn Zuid-Holland 2402 EM",
    "addr:housenumber":"19",
    "addr:postcode":"2402 em",
    "addr:street":"Ridderhof",
    "iso:country":"NL",
    "sg:address":"Ridderhof 19",
    "sg:city":"Alphen A/D Rijn",
    "sg:orig_category":"Banken And Kredietinstellingen",
    "sg:phone":"+31 172 421 710",
    "sg:postcode":"2402 EM",
    "sg:province":"Zuid-Holland",
    "wof:name":"Abn Amro",
    "wof:placetype":"venue"
},
  "geometry": {"coordinates":[4.67484,52.145401],"type":"Point"}
}