{
  "type": "Feature",
  "properties": {
    "addr:full":"Abdystr 39 Heeswyk Dinther Noord-Brabant 5473 AC",
    "addr:housenumber":"39;dinther",
    "addr:postcode":"5473 ac",
    "addr:street":"Abdystr",
    "iso:country":"NL",
    "sg:address":"Abdystr 39",
    "sg:city":"Heeswyk Dinther",
    "sg:orig_category":"Zalenverhuur",
    "sg:phone":"+31 413 291 682",
    "sg:postcode":"5473 AC",
    "sg:province":"Noord-Brabant",
    "wof:name":"Speelman Herberg, De",
    "wof:placetype":"venue"
},
  "geometry": {"coordinates":[5.46889,51.650845],"type":"Point"}
}