{
  "type": "Feature",
  "properties": {
    "iso:country":"NL",
    "sg:address":"Pelikaanhof 3",
    "sg:city":"Deurne",
    "sg:orig_category":"Schilders",
    "sg:phone":"+31 493 312 389",
    "sg:postcode":"5751 GV",
    "sg:province":"Noord-Brabant",
    "wof:name":"Goossens, W T G",
    "wof:placetype":"venue"
},
  "geometry": {"coordinates":[5.790517,51.463848],"type":"Point"}
}