{
  "type": "Feature",
  "properties": {
    "addr:full":"Olieslagwg 128 Enschede Overijssel 7521 JG",
    "addr:housenumber":"128",
    "addr:postcode":"7521 jg",
    "iso:country":"NL",
    "sg:address":"Olieslagwg 128",
    "sg:city":"Enschede",
    "sg:orig_category":"Onderhoudswerken",
    "sg:phone":"+31 53 569 6563",
    "sg:postcode":"7521 JG",
    "sg:province":"Overijssel",
    "wof:name":"Kremer",
    "wof:placetype":"venue"
},
  "geometry": {"coordinates":[6.855401,52.231071],"type":"Point"}
}