{
  "type": "Feature",
  "properties": {
    "addr:full":"Kastelenring 116 Leidschendam South Holland 2261 HD",
    "addr:housenumber":"116",
    "addr:postcode":"2261 hd",
    "addr:street":"Kastelenring",
    "iso:country":"NL",
    "sg:address":"Kastelenring 116",
    "sg:city":"Leidschendam",
    "sg:orig_category":"Bloemen En Planten",
    "sg:phone":"+31 70 320 4397",
    "sg:postcode":"2261 HD",
    "sg:province":"South Holland",
    "wof:name":"Potpourri",
    "wof:placetype":"venue"
},
  "geometry": {"coordinates":[4.394142,52.097759],"type":"Point"}
}