{
  "type": "Feature",
  "properties": {
    "addr:full":"T A Kempisstr 14 Zwolle Overijssel 8021 BB",
    "addr:housenumber":"14",
    "addr:postcode":"8021 bb",
    "iso:country":"NL",
    "sg:address":"T A Kempisstr 14",
    "sg:city":"Zwolle",
    "sg:orig_category":"Videotheken",
    "sg:phone":"+31 38 455 0445",
    "sg:postcode":"8021 BB",
    "sg:province":"Overijssel",
    "sg:website":"http://www.videoland.nl",
    "wof:name":"Videoland",
    "wof:placetype":"venue"
},
  "geometry": {"coordinates":[6.103184,52.515388],"type":"Point"}
}