{
  "type": "Feature",
  "properties": {
    "addr:full":"Hofln 6 Groesbeek Gelderland 6561 BA",
    "addr:housenumber":"6",
    "addr:postcode":"6561 ba",
    "addr:street":"Hofln;Gelderland",
    "iso:country":"NL",
    "sg:address":"Hofln 6",
    "sg:city":"Groesbeek",
    "sg:classifiers":[
        {
            "category":"Personal",
            "subcategory":"Nail Salon",
            "type":"Services"
        }
    ],
    "sg:phone":"+31 24 399 9744",
    "sg:postcode":"6561 BA",
    "sg:province":"Gelderland",
    "sg:tags":[
        "pedicure"
    ],
    "wof:name":"Broekman, Rita",
    "wof:placetype":"venue"
},
  "geometry": {"coordinates":[5.93249,51.776745],"type":"Point"}
}