{
  "type": "Feature",
  "properties": {
    "addr:full":"Fuchsiastr 15 Enschede Overijssel 7531 CM",
    "addr:housenumber":"15",
    "addr:postcode":"7531 cm",
    "addr:street":"Fuchsiastr",
    "iso:country":"NL",
    "sg:address":"Fuchsiastr 15",
    "sg:city":"Enschede",
    "sg:orig_category":"Schilders",
    "sg:phone":"+31 53 435 5429",
    "sg:postcode":"7531 CM",
    "sg:province":"Overijssel",
    "wof:name":"Stijckel",
    "wof:placetype":"venue"
},
  "geometry": {"coordinates":[6.914904,52.226669],"type":"Point"}
}