{
  "type": "Feature",
  "properties": {
    "addr:full":"Asschatterwg 199 Leusden Utrecht 3831 JN",
    "addr:housenumber":"199",
    "addr:postcode":"3831 jn",
    "iso:country":"NL",
    "sg:address":"Asschatterwg 199",
    "sg:city":"Leusden",
    "sg:orig_category":"Sportverenigingen En Ontspannings- Verenigingen",
    "sg:phone":"+31 33 494 1501",
    "sg:postcode":"3831 JN",
    "sg:province":"Utrecht",
    "wof:name":"Hockeyclub",
    "wof:placetype":"venue"
},
  "geometry": {"coordinates":[5.45665,52.131462],"type":"Point"}
}