{
  "type": "Feature",
  "properties": {
    "addr:full":"Stilleweersterweg 1 Appingedam Groningen 9902 BX",
    "addr:housenumber":"1",
    "addr:postcode":"9902 bx",
    "addr:street":"Stilleweersterweg",
    "iso:country":"NL",
    "sg:address":"Stilleweersterweg 1",
    "sg:city":"Appingedam",
    "sg:orig_category":"Begrafenisondernemers",
    "sg:phone":"+31 596 680 676",
    "sg:postcode":"9902 BX",
    "sg:province":"Groningen",
    "wof:name":"Stilleweer",
    "wof:placetype":"venue"
},
  "geometry": {"coordinates":[6.857637,53.30954],"type":"Point"}
}