{
  "type": "Feature",
  "properties": {
    "iso:country":"NL",
    "sg:address":"Houtstr 98",
    "sg:city":"Tilburg",
    "sg:classifiers":[
        {
            "category":"Wholesale",
            "subcategory":"Motor Vehicles",
            "type":"Manufacturing & Wholesale Goods"
        }
    ],
    "sg:phone":"+31 6 53491790",
    "sg:postcode":"5046 DL",
    "sg:province":"North Brabant",
    "sg:tags":[
        "scooter",
        "en"
    ],
    "wof:name":"Appy'S Cross Shop",
    "wof:placetype":"venue"
},
  "geometry": {"coordinates":[5.07823,51.57272],"type":"Point"}
}