{
  "type": "Feature",
  "properties": {
    "addr:full":"Parallelweg 16 Geldrop Noord-Brabant 5664 AC",
    "addr:housenumber":"16",
    "addr:postcode":"5664 ac",
    "addr:street":"Parallelweg",
    "iso:country":"NL",
    "sg:address":"Parallelweg 16",
    "sg:city":"Geldrop",
    "sg:orig_category":"Loodgieterswerk, Verwarming And Sanitaire Installaties",
    "sg:phone":"+31 40 286 3258",
    "sg:postcode":"5664 AC",
    "sg:province":"Noord-Brabant",
    "wof:name":"Gramy Bv",
    "wof:placetype":"venue"
},
  "geometry": {"coordinates":[5.551945,51.419918],"type":"Point"}
}