{
  "type": "Feature",
  "properties": {
    "addr:full":"Poeyersstr 118 Eindhoven North Brabant 5642 GE",
    "addr:housenumber":"118",
    "addr:postcode":"5642",
    "iso:country":"NL",
    "sg:address":"Poeyersstr 118",
    "sg:city":"Eindhoven",
    "sg:orig_category":"Journalisten Freelance",
    "sg:phone":"+31 40 296 1109",
    "sg:postcode":"5642 GE",
    "sg:province":"North Brabant",
    "wof:name":"Twende",
    "wof:placetype":"venue"
},
  "geometry": {"coordinates":[5.51811,51.438419],"type":"Point"}
}