{
  "type": "Feature",
  "properties": {
    "iso:country":"NL",
    "sg:address":"Varkensmarkt 15",
    "sg:city":"Culemborg",
    "sg:orig_category":"Opticiens",
    "sg:phone":"+31 345 520 000",
    "sg:postcode":"4101 CK",
    "sg:province":"Gelderland",
    "wof:name":"Merkx",
    "wof:placetype":"venue"
},
  "geometry": {"coordinates":[5.2260828018,51.9553451538],"type":"Point"}
}