{
  "type": "Feature",
  "properties": {
    "addr:full":"Kerkplein 2 Denekamp Overijssel 7591 DD",
    "addr:housenumber":"2",
    "addr:postcode":"7591 dd",
    "addr:street":"Kerkplein",
    "iso:country":"NL",
    "sg:address":"Kerkplein 2",
    "sg:city":"Denekamp",
    "sg:orig_category":"Musea And Historische Gebouwen",
    "sg:phone":"+31 541 351 003",
    "sg:postcode":"7591 DD",
    "sg:province":"Overijssel",
    "wof:name":"Museum Huize Keizer",
    "wof:placetype":"venue"
},
  "geometry": {"coordinates":[7.005499,52.374435],"type":"Point"}
}