{
  "type": "Feature",
  "properties": {
    "addr:full":"Het Jebbink 37 Vorden Gelderland 7251 BJ",
    "addr:housenumber":"37",
    "addr:postcode":"7251 bj",
    "addr:street":"Het Jebbink;Gelderland",
    "iso:country":"NL",
    "sg:address":"Het Jebbink 37",
    "sg:city":"Vorden",
    "sg:orig_category":"Chemische Producten Gh",
    "sg:phone":"+31 575 553 444",
    "sg:postcode":"7251 BJ",
    "sg:province":"Gelderland",
    "wof:name":"J. Vos",
    "wof:placetype":"venue"
},
  "geometry": {"coordinates":[6.305792,52.108231],"type":"Point"}
}