{
  "type": "Feature",
  "properties": {
    "addr:full":"Clinckenburgh 8 Oegstgeest Zuid-Holland 2343 JH",
    "addr:housenumber":"8",
    "addr:postcode":"2343 jh",
    "addr:street":"Clinckenburgh",
    "iso:country":"NL",
    "sg:address":"Clinckenburgh 8",
    "sg:city":"Oegstgeest",
    "sg:orig_category":"Juwelen - Groothandel",
    "sg:phone":"+31 71 301 1893",
    "sg:postcode":"2343 JH",
    "sg:province":"Zuid-Holland",
    "wof:name":"Beseco",
    "wof:placetype":"venue"
},
  "geometry": {"coordinates":[4.486788,52.192692],"type":"Point"}
}