{
  "type": "Feature",
  "properties": {
    "addr:full":"Burg Vd Lelystr 99 Woudrichem Noord-Brabant 4285 BK",
    "addr:housenumber":"99",
    "addr:postcode":"4285 bk",
    "addr:street":"Burg",
    "iso:country":"NL",
    "sg:address":"Burg Vd Lelystr 99",
    "sg:city":"Woudrichem",
    "sg:orig_category":"Jachten - Schilderwerken En Onderhoud",
    "sg:phone":"+31 183 303 715",
    "sg:postcode":"4285 BK",
    "sg:province":"Noord-Brabant",
    "wof:name":"Viveen, Wout",
    "wof:placetype":"venue"
},
  "geometry": {"coordinates":[4.991527,51.814922],"type":"Point"}
}