{
  "type": "Feature",
  "properties": {
    "iso:country":"NL",
    "sg:address":"N Brabantln 267",
    "sg:city":"Eindhoven",
    "sg:orig_category":"Schoenen",
    "sg:phone":"+31 40 252 7009",
    "sg:postcode":"5652 LD",
    "sg:province":"Noord-Brabant",
    "wof:name":"Bristol",
    "wof:placetype":"venue"
},
  "geometry": {"coordinates":[5.428199,51.43708],"type":"Point"}
}