{
  "type": "Feature",
  "properties": {
    "addr:full":"Cazenderstr 3 Meerssen Limburg 6231 HZ",
    "addr:housenumber":"3",
    "addr:postcode":"6231 hz",
    "addr:street":"Cazenderstr",
    "iso:country":"NL",
    "sg:address":"Cazenderstr 3",
    "sg:city":"Meerssen",
    "sg:classifiers":[
        {
            "category":"Sports & Exercise",
            "subcategory":"Stables",
            "type":"Entertainment"
        }
    ],
    "sg:phone":"+31 43 364 7939",
    "sg:postcode":"6231 HZ",
    "sg:province":"Limburg",
    "sg:tags":[
        "maneges"
    ],
    "wof:name":"Hwagveld, 'T",
    "wof:placetype":"venue"
},
  "geometry": {"coordinates":[5.751552,50.890648],"type":"Point"}
}