{
  "type": "Feature",
  "properties": {
    "addr:full":"Parlevinker 5 Amstelveen Noord-Holland 1186 ZA",
    "addr:housenumber":"5",
    "addr:postcode":"1186",
    "addr:street":"Parlevinker",
    "iso:country":"NL",
    "sg:address":"Parlevinker 5",
    "sg:city":"Amstelveen",
    "sg:orig_category":"Adviesbureaus",
    "sg:phone":"+31 20 645 0383",
    "sg:postcode":"1186 ZA",
    "sg:province":"Noord-Holland",
    "sg:website":"http://www.hetgoedegevoel.nl",
    "wof:name":"Goede Gevoel, Het",
    "wof:placetype":"venue"
},
  "geometry": {"coordinates":[4.862867,52.279457],"type":"Point"}
}