{
  "type": "Feature",
  "properties": {
    "iso:country":"NL",
    "sg:address":"Dam 46",
    "sg:city":"Middelburg",
    "sg:orig_category":"Kunstgebitten",
    "sg:phone":"+31 118 613 582",
    "sg:postcode":"4331 GK",
    "sg:province":"Zeeland",
    "wof:name":"Ancodent",
    "wof:placetype":"venue"
},
  "geometry": {"coordinates":[3.61938,51.500687],"type":"Point"}
}