{
  "type": "Feature",
  "properties": {
    "addr:full":"Haaksbergerstraat 508 Enschede Overijssel 7545 GC",
    "addr:housenumber":"508",
    "addr:postcode":"7545 gc",
    "addr:street":"Haaksbergerstraat",
    "iso:country":"NL",
    "sg:address":"Haaksbergerstraat 508",
    "sg:city":"Enschede",
    "sg:classifiers":[
        {
            "category":"Fast Food",
            "type":"Food & Drink"
        }
    ],
    "sg:phone":"+31 53 431 0793",
    "sg:postcode":"7545 GC",
    "sg:province":"Overijssel",
    "sg:tags":[
        "afhaal",
        "restaurant"
    ],
    "wof:name":"Hennie'S Snackbar",
    "wof:placetype":"venue"
},
  "geometry": {"coordinates":[6.872775,52.208473],"type":"Point"}
}