{
  "type": "Feature",
  "properties": {
    "addr:full":"Voorstr 170A Lekkerkerk South Holland 2941 EX",
    "addr:housenumber":"170a",
    "addr:postcode":"2941 ex",
    "iso:country":"NL",
    "sg:address":"Voorstr 170A",
    "sg:city":"Lekkerkerk",
    "sg:classifiers":[
        {
            "category":"Personal",
            "subcategory":"Nail Salon",
            "type":"Services"
        }
    ],
    "sg:phone":"+31 180 662 895",
    "sg:postcode":"2941 EX",
    "sg:province":"South Holland",
    "sg:tags":[
        "pedicure"
    ],
    "wof:name":"Korput-Apon, C L Van Der",
    "wof:placetype":"venue"
},
  "geometry": {"coordinates":[4.681494,51.894924],"type":"Point"}
}