{
  "type": "Feature",
  "properties": {
    "addr:full":"Servaasbolwerk 9 Utrecht Utrecht 3512 NK",
    "addr:housenumber":"9",
    "addr:postcode":"3512 nk",
    "addr:street":"Servaasbolwerk",
    "iso:country":"NL",
    "sg:address":"Servaasbolwerk 9",
    "sg:city":"Utrecht",
    "sg:orig_category":"Artsen - Huisartsen",
    "sg:phone":"+31 30 231 3381",
    "sg:postcode":"3512 NK",
    "sg:province":"Utrecht",
    "wof:name":"Hertog, P B Den",
    "wof:placetype":"venue"
},
  "geometry": {"coordinates":[5.128074,52.087273],"type":"Point"}
}