{
  "type": "Feature",
  "properties": {
    "addr:full":"Wieselse Enkwg 35 Wenum Wiesel Gelderland 7345 CM",
    "addr:housenumber":"35",
    "addr:postcode":"7345 cm",
    "iso:country":"NL",
    "sg:address":"Wieselse Enkwg 35",
    "sg:city":"Wenum Wiesel",
    "sg:orig_category":"Zalenverhuur",
    "sg:phone":"+31 55 312 1325",
    "sg:postcode":"7345 CM",
    "sg:province":"Gelderland",
    "wof:name":"Sprengenhorst",
    "wof:placetype":"venue"
},
  "geometry": {"coordinates":[5.939374,52.253979],"type":"Point"}
}