{
  "type": "Feature",
  "properties": {
    "addr:full":"Eikenlaan 23 Koewacht Zeeland 4576 BJ",
    "addr:housenumber":"23",
    "addr:postcode":"4576 bj",
    "addr:street":"Eikenlaan",
    "iso:country":"NL",
    "sg:address":"Eikenlaan 23",
    "sg:city":"Koewacht",
    "sg:orig_category":"Verzekeringen",
    "sg:phone":"+31 114 361 595",
    "sg:postcode":"4576 BJ",
    "sg:province":"Zeeland",
    "wof:name":"Assurantie Advieskantoor Koewacht",
    "wof:placetype":"venue"
},
  "geometry": {"coordinates":[3.965457,51.230534],"type":"Point"}
}