{
  "type": "Feature",
  "properties": {
    "addr:full":"J V Eyckpln 2 Roosendaal Noord-Brabant 4703 GV",
    "addr:housenumber":"2",
    "addr:postcode":"4703 gv",
    "addr:street":"J;Eyckpln",
    "iso:country":"NL",
    "sg:address":"J V Eyckpln 2",
    "sg:city":"Roosendaal",
    "sg:classifiers":[
        {
            "category":"Professional",
            "subcategory":"Accounting & Tax Preparation",
            "type":"Services"
        }
    ],
    "sg:phone":"+31 165 598 700",
    "sg:postcode":"4703 GV",
    "sg:province":"Noord-Brabant",
    "sg:tags":[
        "accountant",
        "en",
        "-kantoren",
        "register-"
    ],
    "sg:website":"http://www.bdo.nl",
    "wof:name":"Bdo",
    "wof:placetype":"venue"
},
  "geometry": {"coordinates":[4.45767,51.531403],"type":"Point"}
}