{
  "type": "Feature",
  "properties": {
    "addr:full":"Zeevangstraat 3 Purmerend North Holland 1441 WZ",
    "addr:housenumber":"3",
    "addr:postcode":"1441 wz",
    "addr:street":"Zeevangstraat",
    "iso:country":"NL",
    "sg:address":"Zeevangstraat 3",
    "sg:city":"Purmerend",
    "sg:orig_category":"Werving And Selectie Van Vast Personeel",
    "sg:phone":"+31 299 473 998",
    "sg:postcode":"1441 WZ",
    "sg:province":"North Holland",
    "wof:name":"J En J Personeelsmanagement Bv",
    "wof:placetype":"venue"
},
  "geometry": {"coordinates":[4.9588828087,52.5050392151],"type":"Point"}
}