{
  "type": "Feature",
  "properties": {
    "iso:country":"NL",
    "sg:address":"Hoofdstraat 43",
    "sg:city":"Koudum",
    "sg:orig_category":"Muziekinstrumenten",
    "sg:phone":"+31 514 522 253",
    "sg:postcode":"8723 BG",
    "sg:province":"Friesland",
    "wof:name":"Music Inn",
    "wof:placetype":"venue"
},
  "geometry": {"coordinates":[26.91976,42.150398],"type":"Point"}
}