{
  "type": "Feature",
  "properties": {
    "iso:country":"NL",
    "sg:address":"Oosteinde 13",
    "sg:city":"Gasteren",
    "sg:orig_category":"Hoefdierhouderijen",
    "sg:phone":"+31 592 231 260",
    "sg:postcode":"9466 PA",
    "sg:province":"Drenthe",
    "wof:name":"G. Weggemans",
    "wof:placetype":"venue"
},
  "geometry": {"coordinates":[6.669369,53.037163],"type":"Point"}
}