{
  "type": "Feature",
  "properties": {
    "addr:full":"H De Grootstr 32 Arnhem Gelderland 6828 TR",
    "addr:housenumber":"32",
    "addr:postcode":"6828 tr",
    "iso:country":"NL",
    "sg:address":"H De Grootstr 32",
    "sg:city":"Arnhem",
    "sg:orig_category":"Schilders",
    "sg:phone":"+31 26 443 2622",
    "sg:postcode":"6828 TR",
    "sg:province":"Gelderland",
    "sg:website":"http://www.budgetschilders.nl",
    "wof:name":"Budget",
    "wof:placetype":"venue"
},
  "geometry": {"coordinates":[5.930933,51.980511],"type":"Point"}
}