{
  "type": "Feature",
  "properties": {
    "addr:full":"Fregatwg 64 Maastricht Limburg 6222 NZ",
    "addr:housenumber":"64",
    "addr:postcode":"6222 nz",
    "addr:street":"Fregatwg",
    "iso:country":"NL",
    "sg:address":"Fregatwg 64",
    "sg:city":"Maastricht",
    "sg:orig_category":"Verf En Lak - Fabrieken En Groothandel",
    "sg:phone":"+31 43 604 0222",
    "sg:postcode":"6222 NZ",
    "sg:province":"Limburg",
    "wof:name":"Beissel, Fa F D",
    "wof:placetype":"venue"
},
  "geometry": {"coordinates":[5.713917,50.873959],"type":"Point"}
}