{
  "type": "Feature",
  "properties": {
    "addr:full":"Postbus 386 Castricum North Holland 1900 AJ",
    "addr:housenumber":"386",
    "addr:postcode":"1900 aj",
    "addr:street":"Postbus",
    "iso:country":"NL",
    "sg:address":"Postbus 386",
    "sg:city":"Castricum",
    "sg:orig_category":"Verpakkingen En Verpakkingsmaterialen",
    "sg:phone":"+31 75 640 6029",
    "sg:postcode":"1900 AJ",
    "sg:province":"North Holland",
    "sg:website":"http://www.dupack.nl",
    "wof:name":"Dupack",
    "wof:placetype":"venue"
},
  "geometry": {"coordinates":[4.663725,52.546844],"type":"Point"}
}