{
  "type": "Feature",
  "properties": {
    "addr:full":"Paulusweg 6 Hendrik Ido Ambacht Zuid-Holland 3341 CX",
    "addr:housenumber":"6",
    "addr:postcode":"3341 cx",
    "addr:street":"Paulusweg",
    "iso:country":"NL",
    "sg:address":"Paulusweg 6",
    "sg:city":"Hendrik Ido Ambacht",
    "sg:orig_category":"Kunststof Ramen",
    "sg:phone":"+31 78 682 4646",
    "sg:postcode":"3341 CX",
    "sg:province":"Zuid-Holland",
    "sg:website":"http://www.gevel-elementen.nl",
    "wof:name":"Schiebaan",
    "wof:placetype":"venue"
},
  "geometry": {"coordinates":[4.648009,51.84914],"type":"Point"}
}