{
  "type": "Feature",
  "properties": {
    "addr:full":"Zwarteweg 64 Gouda Zuid-Holland 2805 JJ",
    "addr:housenumber":"64",
    "addr:postcode":"2805 jj",
    "addr:street":"Zwarteweg",
    "iso:country":"NL",
    "sg:address":"Zwarteweg 64",
    "sg:city":"Gouda",
    "sg:orig_category":"Fietshandelaren",
    "sg:phone":"+31 182 512 093",
    "sg:postcode":"2805 JJ",
    "sg:province":"Zuid-Holland",
    "wof:name":"S.A. Straver",
    "wof:placetype":"venue"
},
  "geometry": {"coordinates":[4.722637,52.018356],"type":"Point"}
}