{
  "type": "Feature",
  "properties": {
    "iso:country":"NL",
    "sg:address":"Tilburgsewg 74",
    "sg:city":"Goirle",
    "sg:orig_category":"Kappers",
    "sg:phone":"+31 13 534 2855",
    "sg:postcode":"5051 AJ",
    "sg:province":"Noord-Brabant",
    "wof:name":"Merkx, A",
    "wof:placetype":"venue"
},
  "geometry": {"coordinates":[5.066485,51.522366],"type":"Point"}
}