{
  "type": "Feature",
  "properties": {
    "addr:full":"Dorpsstraat 4 Heinkenszand Zeeland 4451 BC",
    "addr:housenumber":"4",
    "addr:postcode":"4451 bc",
    "addr:street":"Dorpsstraat",
    "iso:country":"NL",
    "sg:address":"Dorpsstraat 4",
    "sg:city":"Heinkenszand",
    "sg:classifiers":[
        {
            "category":"Shopping",
            "subcategory":"Gifts & Souvenirs",
            "type":"Retail Goods"
        }
    ],
    "sg:phone":"+31 113 563 774",
    "sg:postcode":"4451 BC",
    "sg:province":"Zeeland",
    "sg:tags":[
        "geschenken"
    ],
    "wof:name":"Potpourri",
    "wof:placetype":"venue"
},
  "geometry": {"coordinates":[-126.555511,54.485668],"type":"Point"}
}