{
  "type": "Feature",
  "properties": {
    "addr:full":"Nieuwe Ebbingestraat 111 Groningen Groningen 9712 NJ",
    "addr:housenumber":"111",
    "addr:postcode":"9712 nj",
    "addr:street":"Nieuwe Ebbingestraat",
    "iso:country":"NL",
    "sg:address":"Nieuwe Ebbingestraat 111",
    "sg:city":"Groningen",
    "sg:classifiers":[
        {
            "category":"Fast Food",
            "type":"Food & Drink"
        }
    ],
    "sg:phone":"+31 50 314 3366",
    "sg:postcode":"9712 NJ",
    "sg:province":"Groningen",
    "sg:tags":[
        "afhaal",
        "restaurant"
    ],
    "wof:name":"De Blauwe Lotus",
    "wof:placetype":"venue"
},
  "geometry": {"coordinates":[6.561557,53.225857],"type":"Point"}
}