{
  "type": "Feature",
  "properties": {
    "addr:full":"Hantert 6 St Agatha North Brabant 5435 XB",
    "addr:housenumber":"6",
    "addr:postcode":"5435 xb",
    "addr:street":"Hantert",
    "iso:country":"NL",
    "sg:address":"Hantert 6",
    "sg:city":"St Agatha",
    "sg:orig_category":"Verkoopautomaten",
    "sg:phone":"+31 485 321 223",
    "sg:postcode":"5435 XB",
    "sg:province":"North Brabant",
    "wof:name":"Peelparel, De",
    "wof:placetype":"venue"
},
  "geometry": {"coordinates":[5.898313,51.712765],"type":"Point"}
}