{
  "type": "Feature",
  "properties": {
    "addr:full":"Grotestr 202 Waalwyk North Brabant 5141 HD",
    "addr:housenumber":"202",
    "addr:postcode":"5141 hd",
    "addr:street":"Waalwyk North",
    "iso:country":"NL",
    "sg:address":"Grotestr 202",
    "sg:city":"Waalwyk",
    "sg:orig_category":"Verlichting",
    "sg:phone":"+31 416 560 456",
    "sg:postcode":"5141 HD",
    "sg:province":"North Brabant",
    "wof:name":"Lampenier",
    "wof:placetype":"venue"
},
  "geometry": {"coordinates":[5.065765,51.690292],"type":"Point"}
}