{
  "type": "Feature",
  "properties": {
    "iso:country":"NL",
    "sg:address":"Prinsegracht 49",
    "sg:city":"'S Gravenhage",
    "sg:orig_category":"Verzekeringen",
    "sg:phone":"+31 70 389 3334",
    "sg:postcode":"2512 EX",
    "sg:province":"South Holland",
    "wof:name":"Assurantiekantoor Veronica",
    "wof:placetype":"venue"
},
  "geometry": {"coordinates":[4.304538,52.074108],"type":"Point"}
}