{
  "type": "Feature",
  "properties": {
    "addr:full":"Uiverln 14 Eindhoven North Brabant 5613 AC",
    "addr:housenumber":"14",
    "addr:postcode":"5613 ac",
    "addr:street":"Uiverln",
    "iso:country":"NL",
    "sg:address":"Uiverln 14",
    "sg:city":"Eindhoven",
    "sg:classifiers":[
        {
            "category":"Professional",
            "subcategory":"Accounting & Tax Preparation",
            "type":"Services"
        }
    ],
    "sg:phone":"+31 40 244 7124",
    "sg:postcode":"5613 AC",
    "sg:province":"North Brabant",
    "sg:tags":[
        "accountant",
        "en",
        "-kantoren",
        "register-"
    ],
    "sg:website":"http://www.ottevangeraccountancy.nl",
    "wof:name":"Ottevanger Accountancy Bv",
    "wof:placetype":"venue"
},
  "geometry": {"coordinates":[5.484105,51.434471],"type":"Point"}
}