{
  "type": "Feature",
  "properties": {
    "addr:full":"Naaldhof 7 Nunspeet Gelderland 8071 AX",
    "addr:housenumber":"7",
    "addr:postcode":"8071 ax",
    "addr:street":"Naaldhof;Gelderland",
    "iso:country":"NL",
    "sg:address":"Naaldhof 7",
    "sg:city":"Nunspeet",
    "sg:orig_category":"Autorijscholen",
    "sg:phone":"+31 341 258 032",
    "sg:postcode":"8071 AX",
    "sg:province":"Gelderland",
    "wof:name":"Frens Autorijschool",
    "wof:placetype":"venue"
},
  "geometry": {"coordinates":[5.793059,52.378044],"type":"Point"}
}