{
  "type": "Feature",
  "properties": {
    "addr:full":"Emmawg 2 Maarssen Utrecht 3603 AM",
    "addr:housenumber":"2",
    "addr:postcode":"3603",
    "addr:street":"Emmawg",
    "iso:country":"NL",
    "sg:address":"Emmawg 2",
    "sg:city":"Maarssen",
    "sg:orig_category":"Bedrijfsmechanisatie En -Automatisering",
    "sg:phone":"+31 346 569 043",
    "sg:postcode":"3603 AM",
    "sg:province":"Utrecht",
    "wof:name":"Xt Bv",
    "wof:placetype":"venue"
},
  "geometry": {"coordinates":[5.041744,52.138363],"type":"Point"}
}