{
  "type": "Feature",
  "properties": {
    "iso:country":"NL",
    "sg:address":"Huls 101",
    "sg:city":"Simpelveld",
    "sg:orig_category":"Verzekeringen",
    "sg:phone":"+31 45 544 3232",
    "sg:postcode":"6369 EV",
    "sg:province":"Limburg",
    "wof:name":"Algemeen Assurantiekantoor E Meyers",
    "wof:placetype":"venue"
},
  "geometry": {"coordinates":[5.97411,50.842789],"type":"Point"}
}