{
  "type": "Feature",
  "properties": {
    "addr:full":"Margrietln 72 T Veld North Holland 1735 HG",
    "addr:housenumber":"72",
    "addr:postcode":"1735 hg",
    "addr:street":"Margrietln;T Veld North",
    "iso:country":"NL",
    "sg:address":"Margrietln 72",
    "sg:city":"T Veld",
    "sg:orig_category":"Offsetdrukkerijen",
    "sg:phone":"+31 226 422 199",
    "sg:postcode":"1735 HG",
    "sg:province":"North Holland",
    "wof:name":"2003",
    "wof:placetype":"venue"
},
  "geometry": {"coordinates":[4.853666,52.738853],"type":"Point"}
}