{
  "type": "Feature",
  "properties": {
    "iso:country":"NL",
    "sg:address":"Le Fevre D Montignyln 101",
    "sg:city":"Rotterdam",
    "sg:orig_category":"Fruit And Groenten Gh",
    "sg:phone":"+31 10 461 0192",
    "sg:postcode":"3055 NA",
    "sg:province":"South Holland",
    "wof:name":"Fl Primeurs Rotterdam",
    "wof:placetype":"venue"
},
  "geometry": {"coordinates":[4.503284,51.957108],"type":"Point"}
}