{
  "type": "Feature",
  "properties": {
    "addr:full":"Ln D Mensenrecht 102 Beverwyk North Holland 1945 EV",
    "addr:housenumber":"102",
    "addr:street":"Ln;Beverwyk North",
    "iso:country":"NL",
    "sg:address":"Ln D Mensenrecht 102",
    "sg:city":"Beverwyk",
    "sg:orig_category":"Kappers",
    "sg:phone":"+31 251 234 850",
    "sg:postcode":"1945 EV",
    "sg:province":"North Holland",
    "wof:name":"Nouveau",
    "wof:placetype":"venue"
},
  "geometry": {"coordinates":[4.654589,52.49662],"type":"Point"}
}