{
  "type": "Feature",
  "properties": {
    "addr:full":"Kaagstr 6 Raalte NL.08 8102 GZ",
    "addr:housenumber":"6;nl.08",
    "addr:postcode":"8102 gz",
    "addr:street":"Kaagstr",
    "iso:country":"NL",
    "sg:address":"Kaagstr 6",
    "sg:city":"Raalte",
    "sg:orig_category":"Boomverzorging",
    "sg:phone":"+31 572 360 557",
    "sg:postcode":"8102 GZ",
    "sg:province":"NL.08",
    "wof:name":"Seko Vof",
    "wof:placetype":"venue"
},
  "geometry": {"coordinates":[6.28819,52.379383],"type":"Point"}
}