{
  "type": "Feature",
  "properties": {
    "addr:full":"Stenen Brug 23 Landgraaf Limburg 6372 AP",
    "addr:housenumber":"23",
    "addr:postcode":"6372 ap",
    "addr:street":"Stenen Brug",
    "iso:country":"NL",
    "sg:address":"Stenen Brug 23",
    "sg:city":"Landgraaf",
    "sg:orig_category":"Verzekeringen",
    "sg:phone":"+31 45 531 6666",
    "sg:postcode":"6372 AP",
    "sg:province":"Limburg",
    "wof:name":"Assurantiekantoor Gulpers",
    "wof:placetype":"venue"
},
  "geometry": {"coordinates":[6.021331,50.891911],"type":"Point"}
}