{
  "type": "Feature",
  "properties": {
    "addr:full":"De Giesel 6 Haelen Limburg 6081 PH",
    "addr:housenumber":"6",
    "addr:postcode":"6081",
    "addr:street":"De Giesel",
    "iso:country":"NL",
    "sg:address":"De Giesel 6",
    "sg:city":"Haelen",
    "sg:orig_category":"Projectontwikkeling",
    "sg:phone":"+31 475 592 222",
    "sg:postcode":"6081 PH",
    "sg:province":"Limburg",
    "wof:name":"Leudal",
    "wof:placetype":"venue"
},
  "geometry": {"coordinates":[5.962562,51.226746],"type":"Point"}
}