{
  "type": "Feature",
  "properties": {
    "iso:country":"NL",
    "sg:address":"Lichtenhorst 1",
    "sg:city":"Borculo",
    "sg:orig_category":"Banken And Kredietinstellingen",
    "sg:phone":"+31 545 274 672",
    "sg:postcode":"7271 AE",
    "sg:province":"Gelderland",
    "wof:name":"Postkantoor",
    "wof:placetype":"venue"
},
  "geometry": {"coordinates":[6.525421,52.117653],"type":"Point"}
}