{
  "type": "Feature",
  "properties": {
    "addr:full":"Bredestraat 11 Huissen Gelderland 6851 JL",
    "addr:housenumber":"11",
    "addr:postcode":"6851 jl",
    "addr:street":"Bredestraat;Gelderland",
    "iso:country":"NL",
    "sg:address":"Bredestraat 11",
    "sg:city":"Huissen",
    "sg:orig_category":"Glaszetten",
    "sg:phone":"+31 26 443 1734",
    "sg:postcode":"6851 JL",
    "sg:province":"Gelderland",
    "wof:name":"Algemene Arnhemse Glasinzetterij Vof",
    "wof:placetype":"venue"
},
  "geometry": {"coordinates":[5.933532,51.938869],"type":"Point"}
}