{
  "type": "Feature",
  "properties": {
    "addr:full":"Dampstr 39 Maastricht Limburg 6226 GH",
    "addr:housenumber":"39",
    "addr:postcode":"6226 gh",
    "addr:street":"Dampstr",
    "iso:country":"NL",
    "sg:address":"Dampstr 39",
    "sg:city":"Maastricht",
    "sg:orig_category":"Voegwerken",
    "sg:phone":"+31 43 362 4151",
    "sg:postcode":"6226 GH",
    "sg:province":"Limburg",
    "wof:name":"Dassen, F",
    "wof:placetype":"venue"
},
  "geometry": {"coordinates":[5.725275,50.844837],"type":"Point"}
}