{
  "type": "Feature",
  "properties": {
    "iso:country":"NL",
    "sg:address":"Verlengde Broekstraat 8",
    "sg:city":"Klarenbeek",
    "sg:orig_category":"Bedrijfs- And Managementsconsultants",
    "sg:phone":"+31 55 301 2620",
    "sg:postcode":"7382 AG",
    "sg:province":"Gelderland",
    "wof:name":"Inforcom Business Services",
    "wof:placetype":"venue"
},
  "geometry": {"coordinates":[6.052392,52.18327],"type":"Point"}
}