{
  "type": "Feature",
  "properties": {
    "addr:full":"V Haersmasngl 2A Drachten Friesland 9201 KP",
    "addr:housenumber":"2a",
    "addr:postcode":"9201 kp",
    "addr:street":"Haersmasngl",
    "iso:country":"NL",
    "sg:address":"V Haersmasngl 2A",
    "sg:city":"Drachten",
    "sg:orig_category":"Adviesbureaus Beroeps- En Schoolkeuze",
    "sg:phone":"+31 512 519 383",
    "sg:postcode":"9201 KP",
    "sg:province":"Friesland",
    "wof:name":"Buro Leerlingbegeleiding Vo",
    "wof:placetype":"venue"
},
  "geometry": {"coordinates":[6.0943,53.115231],"type":"Point"}
}