{
  "type": "Feature",
  "properties": {
    "addr:full":"Glinkastr 255 Almere NL. 1323 RJ",
    "addr:housenumber":"255",
    "addr:postcode":"1323 rj",
    "addr:street":"Nl.",
    "iso:country":"NL",
    "sg:address":"Glinkastr 255",
    "sg:city":"Almere",
    "sg:orig_category":"Kinderopvang",
    "sg:phone":"+31 36 536 0797",
    "sg:postcode":"1323 RJ",
    "sg:province":"NL.",
    "wof:name":"Dikkertje Dap",
    "wof:placetype":"venue"
},
  "geometry": {"coordinates":[5.191906,52.367428],"type":"Point"}
}