{
  "type": "Feature",
  "properties": {
    "addr:full":"Europaweg 43 Zwijndrecht Zuid-Holland 3332 SG",
    "addr:housenumber":"43",
    "addr:postcode":"3332 sg",
    "addr:street":"Europaweg",
    "iso:country":"NL",
    "sg:address":"Europaweg 43",
    "sg:city":"Zwijndrecht",
    "sg:orig_category":"Kinderopvang Behalve Thuis",
    "sg:phone":"+31 78 612 1011",
    "sg:postcode":"3332 SG",
    "sg:province":"Zuid-Holland",
    "wof:name":"Ons Blije Honck Kinderdagcentrum",
    "wof:placetype":"venue"
},
  "geometry": {"coordinates":[4.657109,51.825405],"type":"Point"}
}