{
  "type": "Feature",
  "properties": {
    "addr:full":"Windmolenwg 1 Saasveld Overijssel 7597 LX",
    "addr:housenumber":"1",
    "addr:postcode":"7597 lx",
    "addr:street":"Windmolenwg",
    "iso:country":"NL",
    "sg:address":"Windmolenwg 1",
    "sg:city":"Saasveld",
    "sg:classifiers":[
        {
            "category":"Retail",
            "subcategory":"Auto Repair",
            "type":"Services"
        }
    ],
    "sg:phone":"+31 74 349 4249",
    "sg:postcode":"7597 LX",
    "sg:province":"Overijssel",
    "sg:tags":[
        "garage"
    ],
    "wof:name":"Spijker Vof",
    "wof:placetype":"venue"
},
  "geometry": {"coordinates":[6.789134,52.331329],"type":"Point"}
}