{
  "type": "Feature",
  "properties": {
    "iso:country":"NL",
    "sg:address":"Albrandswaardsewg 5",
    "sg:city":"Poortugaal",
    "sg:orig_category":"Postkantoren",
    "sg:phone":"+31 10 501 7285",
    "sg:postcode":"3171 AD",
    "sg:province":"Zuid-Holland",
    "sg:website":"http://www.postkantoor.nl",
    "wof:name":"Postkantoor",
    "wof:placetype":"venue"
},
  "geometry": {"coordinates":[4.394424,51.857586],"type":"Point"}
}