{
  "type": "Feature",
  "properties": {
    "addr:full":"Bakkerstraat 3 Roermond Limburg 6041 JP",
    "addr:housenumber":"3",
    "addr:postcode":"6041 jp",
    "addr:street":"Bakkerstraat",
    "iso:country":"NL",
    "sg:address":"Bakkerstraat 3",
    "sg:city":"Roermond",
    "sg:classifiers":[
        {
            "category":"Shopping",
            "subcategory":"Gifts & Souvenirs",
            "type":"Retail Goods"
        }
    ],
    "sg:phone":"+31 475 333 346",
    "sg:postcode":"6041 JP",
    "sg:province":"Limburg",
    "sg:tags":[
        "geschenken"
    ],
    "wof:name":"Jungle Fever",
    "wof:placetype":"venue"
},
  "geometry": {"coordinates":[5.986912,51.19149],"type":"Point"}
}