{
  "type": "Feature",
  "properties": {
    "addr:full":"Molenstr 43 Etten Gld Gelderland 7075 BB",
    "addr:housenumber":"43",
    "addr:postcode":"7075 bb",
    "addr:street":"Molenstr;Gld Gelderland",
    "iso:country":"NL",
    "sg:address":"Molenstr 43",
    "sg:city":"Etten Gld",
    "sg:orig_category":"Bloemen En Planten",
    "sg:phone":"+31 315 340 676",
    "sg:postcode":"7075 BB",
    "sg:province":"Gelderland",
    "wof:name":"Kappers, Monique",
    "wof:placetype":"venue"
},
  "geometry": {"coordinates":[6.335795,51.917381],"type":"Point"}
}