{
  "type": "Feature",
  "properties": {
    "addr:full":"Keizerstraat 29 Gorinchem South Holland 4201 XM",
    "addr:housenumber":"29",
    "addr:postcode":"4201 xm",
    "addr:street":"Keizerstraat",
    "iso:country":"NL",
    "sg:address":"Keizerstraat 29",
    "sg:city":"Gorinchem",
    "sg:orig_category":"Fitnesscentra",
    "sg:phone":"+31 183 631 685",
    "sg:postcode":"4201 XM",
    "sg:province":"South Holland",
    "wof:name":"Sportschool Breedveld",
    "wof:placetype":"venue"
},
  "geometry": {"coordinates":[4.978498,51.830811],"type":"Point"}
}