{
  "type": "Feature",
  "properties": {
    "addr:full":"Ledastraat 21 Rotterdam Zuid-Holland 3054 WC",
    "addr:housenumber":"21",
    "addr:postcode":"3054 wc",
    "addr:street":"Ledastraat",
    "iso:country":"NL",
    "sg:address":"Ledastraat 21",
    "sg:city":"Rotterdam",
    "sg:orig_category":"Goederenvervoer Over De Weg",
    "sg:phone":"+31 10 218 1160",
    "sg:postcode":"3054 WC",
    "sg:province":"Zuid-Holland",
    "wof:name":"Ed Van Rooijen",
    "wof:placetype":"venue"
},
  "geometry": {"coordinates":[4.490041,51.965164],"type":"Point"}
}