{
  "type": "Feature",
  "properties": {
    "addr:full":"S Gravenweg 32 Nieuwerkerk Ad Ijssel Zuid-Holland 2911 CG",
    "addr:housenumber":"32",
    "addr:postcode":"ijssel;2911 cg",
    "addr:street":"S Gravenweg",
    "iso:country":"NL",
    "sg:address":"S Gravenweg 32",
    "sg:city":"Nieuwerkerk Ad Ijssel",
    "sg:orig_category":"Autokeuringen",
    "sg:phone":"+31 180 313 082",
    "sg:postcode":"2911 CG",
    "sg:province":"Zuid-Holland",
    "wof:name":"Garage- En Transportbedrijf Neleman Bv",
    "wof:placetype":"venue"
},
  "geometry": {"coordinates":[4.609959,51.949699],"type":"Point"}
}