{
  "type": "Feature",
  "properties": {
    "addr:full":"Overtoom 556 Amsterdam North Holland 1054 LM",
    "addr:housenumber":"556",
    "addr:postcode":"1054 lm",
    "addr:street":"Overtoom",
    "iso:country":"NL",
    "sg:address":"Overtoom 556",
    "sg:city":"Amsterdam",
    "sg:orig_category":"Verzekeringen",
    "sg:phone":"+31 20 683 3951",
    "sg:postcode":"1054 LM",
    "sg:province":"North Holland",
    "wof:name":"Wolf Verzekeringen Bv",
    "wof:placetype":"venue"
},
  "geometry": {"coordinates":[4.857274,52.358395],"type":"Point"}
}