{
  "type": "Feature",
  "properties": {
    "addr:full":"P Gyzenbrugstr 18 2Hg Amsterdam North Holland 1059 XH",
    "addr:housenumber":"18",
    "addr:postcode":"1059 xh",
    "addr:street":"P;2Hg",
    "iso:country":"NL",
    "sg:address":"P Gyzenbrugstr 18 2Hg",
    "sg:city":"Amsterdam",
    "sg:orig_category":"Beeldende Kunstenaars",
    "sg:phone":"+31 20 615 3566",
    "sg:postcode":"1059 XH",
    "sg:province":"North Holland",
    "wof:name":"Hoog, H Van 'T",
    "wof:placetype":"venue"
},
  "geometry": {"coordinates":[4.846685,52.350449],"type":"Point"}
}