{
  "type": "Feature",
  "properties": {
    "iso:country":"NL",
    "sg:address":"Donker Curtiusstraat 7/131",
    "sg:city":"Amsterdam",
    "sg:classifiers":[
        {
            "category":"Food & Beverages",
            "subcategory":"Fruits & Vegetables",
            "type":"Retail Goods"
        }
    ],
    "sg:phone":"+31 20 488 4171",
    "sg:postcode":"1051 JL",
    "sg:province":"Noord-Holland",
    "sg:tags":[
        "groenten"
    ],
    "wof:name":"Tropical Fruit Int Associaton",
    "wof:placetype":"venue"
},
  "geometry": {"coordinates":[4.871745,52.379089],"type":"Point"}
}