{
  "type": "Feature",
  "properties": {
    "addr:full":"Francois Haverschmidtln 1 Schiedam Zuid-Holland 3116 JJ",
    "addr:housenumber":"1",
    "addr:postcode":"3116 jj",
    "iso:country":"NL",
    "sg:address":"Francois Haverschmidtln 1",
    "sg:city":"Schiedam",
    "sg:orig_category":"Begrafenisondernemers",
    "sg:phone":"+31 10 273 2424",
    "sg:postcode":"3116 JJ",
    "sg:province":"Zuid-Holland",
    "wof:name":"Matrice Uitvaartbegeleiding",
    "wof:placetype":"venue"
},
  "geometry": {"coordinates":[4.387575,51.910149],"type":"Point"}
}