{
  "type": "Feature",
  "properties": {
    "addr:full":"Dorpsring 29 Noordwelle Zeeland 4326 AC",
    "addr:housenumber":"29",
    "addr:postcode":"4326 ac",
    "addr:street":"Dorpsring",
    "iso:country":"NL",
    "sg:address":"Dorpsring 29",
    "sg:city":"Noordwelle",
    "sg:classifiers":[
        {
            "category":"Banks & Credit Unions",
            "subcategory":"Investment Brokerage",
            "type":"Services"
        }
    ],
    "sg:phone":"+31 111 461 435",
    "sg:postcode":"4326 AC",
    "sg:province":"Zeeland",
    "sg:tags":[
        "pension"
    ],
    "wof:name":"Arianne, Huize",
    "wof:placetype":"venue"
},
  "geometry": {"coordinates":[3.792423,51.717968],"type":"Point"}
}