{
  "type": "Feature",
  "properties": {
    "addr:full":"Woenselse Markt 41A Eindhoven Noord-Brabant 5612 CS",
    "addr:housenumber":"41a",
    "addr:postcode":"5612 cs",
    "addr:street":"Woenselse Markt",
    "iso:country":"NL",
    "sg:address":"Woenselse Markt 41A",
    "sg:city":"Eindhoven",
    "sg:orig_category":"Verenigingen En Stichtingen",
    "sg:phone":"+31 40 245 8366",
    "sg:postcode":"5612 CS",
    "sg:province":"Noord-Brabant",
    "wof:name":"Sras",
    "wof:placetype":"venue"
},
  "geometry": {"coordinates":[5.471648,51.450748],"type":"Point"}
}