{
  "type": "Feature",
  "properties": {
    "addr:full":"Drebbelstr 328 S Gravenhage South Holland 2522 DJ",
    "addr:housenumber":"328",
    "addr:postcode":"2522 dj",
    "addr:street":"S Gravenhage",
    "iso:country":"NL",
    "sg:address":"Drebbelstr 328",
    "sg:city":"S Gravenhage",
    "sg:orig_category":"Verf En Lak",
    "sg:phone":"+31 70 399 0837",
    "sg:postcode":"2522 DJ",
    "sg:province":"South Holland",
    "wof:name":"Boerman & Zoon",
    "wof:placetype":"venue"
},
  "geometry": {"coordinates":[4.32729,52.060848],"type":"Point"}
}