{
  "type": "Feature",
  "properties": {
    "iso:country":"NL",
    "sg:address":"Bosschestr 2",
    "sg:city":"S Gravenhage",
    "sg:orig_category":"Mobiele- En Autotelefoons",
    "sg:phone":"+31 70 352 0925",
    "sg:postcode":"2587 HE",
    "sg:province":"South Holland",
    "wof:name":"Alpina",
    "wof:placetype":"venue"
},
  "geometry": {"coordinates":[4.29118,52.112942],"type":"Point"}
}