{
  "type": "Feature",
  "properties": {
    "iso:country":"NL",
    "sg:address":"Haarlemmerdk 53",
    "sg:city":"Amsterdam",
    "sg:orig_category":"Poeliers",
    "sg:phone":"+31 20 624 8454",
    "sg:postcode":"1013 KB",
    "sg:province":"Noord-Holland",
    "wof:name":"Jonk Specialiteiten-Poelier",
    "wof:placetype":"venue"
},
  "geometry": {"coordinates":[4.887645,52.382256],"type":"Point"}
}