{
  "type": "Feature",
  "properties": {
    "addr:full":"Gutenbergwg 3 Culemborg Gelderland 4104 BA",
    "addr:housenumber":"3",
    "addr:postcode":"4104 ba",
    "addr:street":"Gutenbergwg;Gelderland",
    "iso:country":"NL",
    "sg:address":"Gutenbergwg 3",
    "sg:city":"Culemborg",
    "sg:orig_category":"Autoschade- Herstelbedrijven",
    "sg:phone":"+31 345 518 723",
    "sg:postcode":"4104 BA",
    "sg:province":"Gelderland",
    "wof:name":"Stolker",
    "wof:placetype":"venue"
},
  "geometry": {"coordinates":[5.208222,51.942764],"type":"Point"}
}