{
  "type": "Feature",
  "properties": {
    "addr:full":"Willemstr 51 Eindhoven Noord-Brabant 5611 HC",
    "addr:housenumber":"51",
    "addr:postcode":"5611 hc",
    "addr:street":"Willemstr",
    "iso:country":"NL",
    "sg:address":"Willemstr 51",
    "sg:city":"Eindhoven",
    "sg:orig_category":"Fotoreportages",
    "sg:phone":"+31 40 844 3691",
    "sg:postcode":"5611 HC",
    "sg:province":"Noord-Brabant",
    "sg:website":"http://www.mauritsvanhout.com",
    "wof:name":"Hout Fotograaf, Maurits Van",
    "wof:placetype":"venue"
},
  "geometry": {"coordinates":[5.484105,51.434471],"type":"Point"}
}