{
  "type": "Feature",
  "properties": {
    "addr:full":"Noord Esmarkerrondweg 372 Enschede Overijssel 7533 BH",
    "addr:housenumber":"372",
    "addr:postcode":"7533 bh",
    "addr:street":"Noord Esmarkerrondweg",
    "iso:country":"NL",
    "sg:address":"Noord Esmarkerrondweg 372",
    "sg:city":"Enschede",
    "sg:orig_category":"Begrafenisondernemers",
    "sg:phone":"+31 53 432 0529",
    "sg:postcode":"7533 BH",
    "sg:province":"Overijssel",
    "wof:name":"Monuta",
    "wof:placetype":"venue"
},
  "geometry": {"coordinates":[6.928403,52.223423],"type":"Point"}
}