{
  "type": "Feature",
  "properties": {
    "addr:full":"Riethorsterstraat 14 Arnhem Gelderland 6828 GE",
    "addr:housenumber":"14",
    "addr:postcode":"6828",
    "addr:street":"Riethorsterstraat",
    "iso:country":"NL",
    "sg:address":"Riethorsterstraat 14",
    "sg:city":"Arnhem",
    "sg:orig_category":"Public Relationbureaus",
    "sg:phone":"+31 26 389 3218",
    "sg:postcode":"6828 GE",
    "sg:province":"Gelderland",
    "wof:name":"Eric Klaverstijn",
    "wof:placetype":"venue"
},
  "geometry": {"coordinates":[5.917625,51.981503],"type":"Point"}
}