{
  "type": "Feature",
  "properties": {
    "addr:full":"Da Costastr 4 Tilburg Noord-Brabant 5025 TE",
    "addr:housenumber":"4",
    "addr:postcode":"5025 te",
    "iso:country":"NL",
    "sg:address":"Da Costastr 4",
    "sg:city":"Tilburg",
    "sg:orig_category":"Wasmachines En Wasdrogers - Onderhoud En Reparatie",
    "sg:phone":"+31 13 467 7615",
    "sg:postcode":"5025 TE",
    "sg:province":"Noord-Brabant",
    "wof:name":"Heijden, Leo Van Der",
    "wof:placetype":"venue"
},
  "geometry": {"coordinates":[5.0627551079,51.5512962341],"type":"Point"}
}