{
  "type": "Feature",
  "properties": {
    "addr:full":"Allemawei 6 Oudwoude Provincie Friesland 9294 KT",
    "addr:housenumber":"6",
    "addr:postcode":"9294 kt",
    "addr:street":"Allemawei;Provincie Friesland",
    "iso:country":"NL",
    "sg:address":"Allemawei 6",
    "sg:city":"Oudwoude",
    "sg:classifiers":[
        {
            "category":"Food & Beverages",
            "subcategory":"Fruits & Vegetables",
            "type":"Retail Goods"
        }
    ],
    "sg:phone":"+31 511 453 911",
    "sg:postcode":"9294 KT",
    "sg:province":"Provincie Friesland",
    "sg:tags":[
        "en",
        "groenten"
    ],
    "wof:name":"Dijkstra, F",
    "wof:placetype":"venue"
},
  "geometry": {"coordinates":[6.122601,53.287251],"type":"Point"}
}