{
  "type": "Feature",
  "properties": {
    "addr:full":"Pr Florisstr 9 Dinteloord North Brabant 4671 GP",
    "addr:housenumber":"9",
    "addr:postcode":"4671 gp",
    "iso:country":"NL",
    "sg:address":"Pr Florisstr 9",
    "sg:city":"Dinteloord",
    "sg:orig_category":"Verlichting",
    "sg:phone":"+31 167 524 936",
    "sg:postcode":"4671 GP",
    "sg:province":"North Brabant",
    "wof:name":"Astra Bv",
    "wof:placetype":"venue"
},
  "geometry": {"coordinates":[4.361805,51.633705],"type":"Point"}
}