{
  "type": "Feature",
  "properties": {
    "addr:full":"Orionstr 143 Eindhoven North Brabant 5632 DC",
    "addr:housenumber":"143",
    "addr:postcode":"5632",
    "iso:country":"NL",
    "sg:address":"Orionstr 143",
    "sg:city":"Eindhoven",
    "sg:orig_category":"Kappers",
    "sg:phone":"+31 40 242 6443",
    "sg:postcode":"5632 DC",
    "sg:province":"North Brabant",
    "wof:name":"Sadia'S Haarmode",
    "wof:placetype":"venue"
},
  "geometry": {"coordinates":[5.493806,51.470348],"type":"Point"}
}