{
  "type": "Feature",
  "properties": {
    "addr:full":"Moriaansdreef 100 Putte Noord-Brabant 4645 GK",
    "addr:housenumber":"100",
    "addr:postcode":"4645 gk",
    "addr:street":"Moriaansdreef",
    "iso:country":"NL",
    "sg:address":"Moriaansdreef 100",
    "sg:city":"Putte",
    "sg:orig_category":"Meubelzaken, Woning- And Keukeninrichting",
    "sg:phone":"+31 164 602 996",
    "sg:postcode":"4645 GK",
    "sg:province":"Noord-Brabant",
    "wof:name":"Wipala",
    "wof:placetype":"venue"
},
  "geometry": {"coordinates":[4.400044,51.364262],"type":"Point"}
}