{
  "type": "Feature",
  "properties": {
    "iso:country":"NL",
    "sg:address":"Vriesestr 38",
    "sg:city":"Dordrecht",
    "sg:orig_category":"Houtgroothandel",
    "sg:phone":"+31 78 613 7604",
    "sg:postcode":"3311 NR",
    "sg:province":"Zuid-Holland",
    "wof:name":"Dielessen, G",
    "wof:placetype":"venue"
},
  "geometry": {"coordinates":[4.667804,51.813759],"type":"Point"}
}