{
  "type": "Feature",
  "properties": {
    "addr:full":"Bloemersmastr 64 Niekerk Grootegast Groningen 9822 AD",
    "addr:housenumber":"64",
    "addr:postcode":"9822 ad",
    "addr:street":"Bloemersmastr",
    "iso:country":"NL",
    "sg:address":"Bloemersmastr 64",
    "sg:city":"Niekerk Grootegast",
    "sg:orig_category":"Fietsen En Bromfietsen",
    "sg:phone":"+31 594 505 757",
    "sg:postcode":"9822 AD",
    "sg:province":"Groningen",
    "wof:name":"Hoiting",
    "wof:placetype":"venue"
},
  "geometry": {"coordinates":[6.356064,53.228455],"type":"Point"}
}