{
  "type": "Feature",
  "properties": {
    "addr:full":"Havenpark 42 Zierikzee Zeeland 4301 CE",
    "addr:housenumber":"42",
    "addr:postcode":"4301 ce",
    "addr:street":"Havenpark",
    "iso:country":"NL",
    "sg:address":"Havenpark 42",
    "sg:city":"Zierikzee",
    "sg:classifiers":[
        {
            "category":"Shopping",
            "subcategory":"Gifts & Souvenirs",
            "type":"Retail Goods"
        }
    ],
    "sg:phone":"+31 111 412 273",
    "sg:postcode":"4301 CE",
    "sg:province":"Zeeland",
    "sg:tags":[
        "geschenken"
    ],
    "wof:name":"Kado- En Rookshop Viergever",
    "wof:placetype":"venue"
},
  "geometry": {"coordinates":[3.922411,51.649014],"type":"Point"}
}