{
  "type": "Feature",
  "properties": {
    "addr:full":"Hyacinthstr 14 Oldenzaal NL.08 7572 BC",
    "addr:housenumber":"14;nl.08",
    "addr:postcode":"7572 bc",
    "addr:street":"Hyacinthstr",
    "iso:country":"NL",
    "sg:address":"Hyacinthstr 14",
    "sg:city":"Oldenzaal",
    "sg:orig_category":"Horecabenodigdheden",
    "sg:phone":"+31 541 512 676",
    "sg:postcode":"7572 BC",
    "sg:province":"NL.08",
    "wof:name":"Echte Bakker",
    "wof:placetype":"venue"
},
  "geometry": {"coordinates":[6.923001,52.312183],"type":"Point"}
}