{
  "type": "Feature",
  "properties": {
    "addr:full":"Maasstr 105 Amsterdam Noord-Holland 1078 HH",
    "addr:housenumber":"105",
    "addr:postcode":"1078 hh",
    "iso:country":"NL",
    "sg:address":"Maasstr 105",
    "sg:city":"Amsterdam",
    "sg:orig_category":"Woningbureaus",
    "sg:phone":"+31 20 679 1100",
    "sg:postcode":"1078 HH",
    "sg:province":"Noord-Holland",
    "wof:name":"World Wide Rentals",
    "wof:placetype":"venue"
},
  "geometry": {"coordinates":[4.8958702087,52.3439483643],"type":"Point"}
}