{
  "type": "Feature",
  "properties": {
    "addr:full":"Wenckebachwg 107 Amsterdam Noord-Holland 1096 AL",
    "addr:housenumber":"107",
    "addr:postcode":"1096 al",
    "iso:country":"NL",
    "sg:address":"Wenckebachwg 107",
    "sg:city":"Amsterdam",
    "sg:orig_category":"Autolakken",
    "sg:phone":"+31 20 460 4210",
    "sg:postcode":"1096 AL",
    "sg:province":"Noord-Holland",
    "wof:name":"Spectrum Bv",
    "wof:placetype":"venue"
},
  "geometry": {"coordinates":[4.928192,52.33794],"type":"Point"}
}