{
  "type": "Feature",
  "properties": {
    "iso:country":"NL",
    "sg:address":"Comm De Quayln 13",
    "sg:city":"S Hertogenbosch",
    "sg:orig_category":"Adviesbureaus Bedrijfsorganisatie",
    "sg:phone":"+31 73 621 4646",
    "sg:postcode":"5224 CR",
    "sg:province":"Noord-Brabant",
    "wof:name":"Miltenburg",
    "wof:placetype":"venue"
},
  "geometry": {"coordinates":[5.25958,51.698631],"type":"Point"}
}