{
  "type": "Feature",
  "properties": {
    "addr:full":"Pannekoekstraat 49 Rotterdam Zuid-Holland 3011 LC",
    "addr:housenumber":"49",
    "addr:postcode":"3011 lc",
    "addr:street":"Pannekoekstraat",
    "iso:country":"NL",
    "sg:address":"Pannekoekstraat 49",
    "sg:city":"Rotterdam",
    "sg:orig_category":"Kunst And Kunstenaarsbenodigdheden",
    "sg:phone":"+31 10 413 9759",
    "sg:postcode":"3011 LC",
    "sg:province":"Zuid-Holland",
    "wof:name":"Kunsthandel Cor Jutte",
    "wof:placetype":"venue"
},
  "geometry": {"coordinates":[4.487443,51.923508],"type":"Point"}
}