{
  "type": "Feature",
  "properties": {
    "iso:country":"NL",
    "sg:address":"C Houtmanstr 7",
    "sg:city":"Emmen",
    "sg:orig_category":"Elektrotechnische Installatiebureaus",
    "sg:phone":"+31 591 632 462",
    "sg:postcode":"7825 VH",
    "sg:province":"Drenthe",
    "wof:name":"Goeree Bv",
    "wof:placetype":"venue"
},
  "geometry": {"coordinates":[6.93044,52.756145],"type":"Point"}
}