{
  "type": "Feature",
  "properties": {
    "addr:full":"Dekemawei 7 Baard New Mexico 8834 XA",
    "addr:housenumber":"7",
    "addr:postcode":"8834 xa",
    "addr:street":"Dekemawei",
    "iso:country":"NL",
    "sg:address":"Dekemawei 7",
    "sg:city":"Baard",
    "sg:orig_category":"Artsen And Specialisten",
    "sg:phone":"+31 517 341 272",
    "sg:postcode":"8834 XA",
    "sg:province":"New Mexico",
    "wof:name":"Apotheekh. Huisartsenprakt. H.B. Bergwer",
    "wof:placetype":"venue"
},
  "geometry": {"coordinates":[-103.243301,35.138901],"type":"Point"}
}