{
  "type": "Feature",
  "properties": {
    "addr:full":"Romeinenstraat 2 Sittard Limburg 6132 GN",
    "addr:housenumber":"2",
    "addr:postcode":"6132 gn",
    "addr:street":"Romeinenstraat",
    "iso:country":"NL",
    "sg:address":"Romeinenstraat 2",
    "sg:city":"Sittard",
    "sg:orig_category":"Supermarkten",
    "sg:phone":"+31 46 451 7087",
    "sg:postcode":"6132 GN",
    "sg:province":"Limburg",
    "wof:name":"Edah",
    "wof:placetype":"venue"
},
  "geometry": {"coordinates":[5.894712,50.996094],"type":"Point"}
}