{
  "type": "Feature",
  "properties": {
    "addr:full":"Hogewoerd 21 Leiden Zuid-Holland 2311 HE",
    "addr:housenumber":"21",
    "addr:postcode":"2311 he",
    "addr:street":"Hogewoerd",
    "iso:country":"NL",
    "sg:address":"Hogewoerd 21",
    "sg:city":"Leiden",
    "sg:orig_category":"Glas, Porselein En Aardewerk",
    "sg:phone":"+31 71 513 9666",
    "sg:postcode":"2311 HE",
    "sg:province":"Zuid-Holland",
    "sg:website":"http://www.vanmanenaantafel.nl",
    "wof:name":"Manen Aan Tafel, Van",
    "wof:placetype":"venue"
},
  "geometry": {"coordinates":[4.494049,52.156113],"type":"Point"}
}