{
  "type": "Feature",
  "properties": {
    "addr:full":"Hogestraat 12 Loppersum Groningen 9919 AM",
    "addr:housenumber":"12",
    "addr:postcode":"9919",
    "addr:street":"Hogestraat",
    "iso:country":"NL",
    "sg:address":"Hogestraat 12",
    "sg:city":"Loppersum",
    "sg:classifiers":[
        {
            "category":"Communications",
            "subcategory":"Television Station",
            "type":"Services"
        }
    ],
    "sg:phone":"+31 596 572 764",
    "sg:postcode":"9919 AM",
    "sg:province":"Groningen",
    "sg:tags":[
        "video",
        "audio",
        "verhuur"
    ],
    "wof:name":"Videotheek Loppersum",
    "wof:placetype":"venue"
},
  "geometry": {"coordinates":[6.743985,53.33276],"type":"Point"}
}