{
  "type": "Feature",
  "properties": {
    "iso:country":"NL",
    "sg:address":"Buterikkers 41",
    "sg:city":"Workum",
    "sg:orig_category":"Artiestenbureaus",
    "sg:phone":"+31 515 541 703",
    "sg:postcode":"8711 GT",
    "sg:province":"Friesland",
    "wof:name":"De Vries",
    "wof:placetype":"venue"
},
  "geometry": {"coordinates":[5.442956,52.972912],"type":"Point"}
}