{
  "type": "Feature",
  "properties": {
    "iso:country":"NL",
    "sg:address":"Bolstr 14",
    "sg:city":"Utrecht",
    "sg:orig_category":"Journalisten Freelance",
    "sg:phone":"+31 30 251 3178",
    "sg:postcode":"3581 WX",
    "sg:province":"Utrecht",
    "wof:name":"Boonman, C",
    "wof:placetype":"venue"
},
  "geometry": {"coordinates":[5.133657,52.088684],"type":"Point"}
}