{
  "type": "Feature",
  "properties": {
    "addr:full":"Zuidendijk 343 Dordrecht Zuid-Holland 3317 NR",
    "addr:housenumber":"343",
    "addr:postcode":"3317 nr",
    "addr:street":"Zuidendijk",
    "iso:country":"NL",
    "sg:address":"Zuidendijk 343",
    "sg:city":"Dordrecht",
    "sg:orig_category":"Goederenvervoer Over De Weg",
    "sg:phone":"+31 78 618 4762",
    "sg:postcode":"3317 NR",
    "sg:province":"Zuid-Holland",
    "wof:name":"W.G. De Bruin",
    "wof:placetype":"venue"
},
  "geometry": {"coordinates":[4.658307,51.788822],"type":"Point"}
}