{
  "type": "Feature",
  "properties": {
    "addr:full":"Geelkruid 79 Rotterdam Zuid-Holland 3068 DT",
    "addr:housenumber":"79",
    "addr:postcode":"3068 dt",
    "addr:street":"Geelkruid",
    "iso:country":"NL",
    "sg:address":"Geelkruid 79",
    "sg:city":"Rotterdam",
    "sg:orig_category":"Artiestenbureaus",
    "sg:phone":"+31 10 420 3712",
    "sg:postcode":"3068 DT",
    "sg:province":"Zuid-Holland",
    "wof:name":"Mister Mopes Goochelkomiek",
    "wof:placetype":"venue"
},
  "geometry": {"coordinates":[4.55136,51.958282],"type":"Point"}
}