{
  "type": "Feature",
  "properties": {
    "iso:country":"NL",
    "sg:address":"Leeuweriklaan 3",
    "sg:city":"Bilthoven",
    "sg:classifiers":[
        {
            "category":"Education",
            "subcategory":"Preschool",
            "type":"Public Place"
        }
    ],
    "sg:phone":"+31 30 228 0003",
    "sg:postcode":"3722 CT",
    "sg:province":"Utrecht",
    "sg:tags":[
        "kleuteronderwijs",
        "basis-"
    ],
    "wof:name":"Dr. W. Van Everdingenschool",
    "wof:placetype":"venue"
},
  "geometry": {"coordinates":[5.216938,52.12542],"type":"Point"}
}