{
  "type": "Feature",
  "properties": {
    "addr:full":"Heerenwg 61A Barsingerhorn North Holland 1768 BH",
    "addr:housenumber":"61a",
    "addr:postcode":"1768 bh",
    "addr:street":"Heerenwg",
    "iso:country":"NL",
    "sg:address":"Heerenwg 61A",
    "sg:city":"Barsingerhorn",
    "sg:classifiers":[
        {
            "category":"Sports & Exercise",
            "subcategory":"Stables",
            "type":"Entertainment"
        }
    ],
    "sg:phone":"+31 224 531 621",
    "sg:postcode":"1768 BH",
    "sg:province":"North Holland",
    "sg:tags":[
        "maneges"
    ],
    "wof:name":"Airborne",
    "wof:placetype":"venue"
},
  "geometry": {"coordinates":[4.85386,52.785015],"type":"Point"}
}