{
  "type": "Feature",
  "properties": {
    "addr:full":"Churchillln 23 Voorhout Zuid-Holland 2215 PE",
    "addr:housenumber":"23",
    "addr:postcode":"2215 pe",
    "addr:street":"Churchillln",
    "iso:country":"NL",
    "sg:address":"Churchillln 23",
    "sg:city":"Voorhout",
    "sg:orig_category":"Etalagefiguren En -Materialen",
    "sg:phone":"+31 252 219 178",
    "sg:postcode":"2215 PE",
    "sg:province":"Zuid-Holland",
    "wof:name":"Raaphorst",
    "wof:placetype":"venue"
},
  "geometry": {"coordinates":[4.48252,52.221874],"type":"Point"}
}