{
  "type": "Feature",
  "properties": {
    "addr:full":"Van Maerlantpark 51 Capelle A/D Ijssel South Holland 2902 BR",
    "addr:housenumber":"51;a / d",
    "addr:postcode":"2902 br",
    "addr:street":"Van Maerlantpark;Ijssel South",
    "iso:country":"NL",
    "sg:address":"Van Maerlantpark 51",
    "sg:city":"Capelle A/D Ijssel",
    "sg:orig_category":"Kinderopvang Behalve Thuis",
    "sg:phone":"+31 10 451 8913",
    "sg:postcode":"2902 BR",
    "sg:province":"South Holland",
    "wof:name":"Buro Het Werkt",
    "wof:placetype":"venue"
},
  "geometry": {"coordinates":[4.575649,51.925659],"type":"Point"}
}