{
  "type": "Feature",
  "properties": {
    "addr:full":"Parallel Boulev 176 Noordwyk Zh Zuid-Holland 2202 HS",
    "addr:housenumber":"176",
    "addr:postcode":"2202 hs",
    "addr:street":"Noordwyk",
    "iso:country":"NL",
    "sg:address":"Parallel Boulev 176",
    "sg:city":"Noordwyk Zh",
    "sg:orig_category":"Wijnkoperijen En -Groothandel",
    "sg:phone":"+31 71 364 9923",
    "sg:postcode":"2202 HS",
    "sg:province":"Zuid-Holland",
    "wof:name":"Casa Prima",
    "wof:placetype":"venue"
},
  "geometry": {"coordinates":[4.4320979118,52.2449798584],"type":"Point"}
}