{
  "type": "Feature",
  "properties": {
    "addr:full":"Julianastraat 17 Leerdam South Holland 4141 AH",
    "addr:housenumber":"17",
    "addr:postcode":"4141 ah",
    "addr:street":"Julianastraat",
    "iso:country":"NL",
    "sg:address":"Julianastraat 17",
    "sg:city":"Leerdam",
    "sg:orig_category":"Wegen And Sportterreinen",
    "sg:phone":"+31 345 615 325",
    "sg:postcode":"4141 AH",
    "sg:province":"South Holland",
    "wof:name":"J. Van Steenis",
    "wof:placetype":"venue"
},
  "geometry": {"coordinates":[5.091378212,51.8933639526],"type":"Point"}
}