{
  "type": "Feature",
  "properties": {
    "addr:full":"Ridderspoor 30 Hoogvliet Rt Zuid-Holland 3191 PD",
    "addr:housenumber":"30",
    "addr:postcode":"rt;3191 pd",
    "addr:street":"Ridderspoor",
    "iso:country":"NL",
    "sg:address":"Ridderspoor 30",
    "sg:city":"Hoogvliet Rt",
    "sg:orig_category":"Verloskundigen",
    "sg:phone":"+31 10 501 9711",
    "sg:postcode":"3191 PD",
    "sg:province":"Zuid-Holland",
    "wof:name":"Gerritsen, I",
    "wof:placetype":"venue"
},
  "geometry": {"coordinates":[4.373136,51.858536],"type":"Point"}
}