{
  "type": "Feature",
  "properties": {
    "addr:full":"Groenestg 107 Leiden Zuid-Holland 2312 SP",
    "addr:housenumber":"107",
    "addr:postcode":"2312 sp",
    "iso:country":"NL",
    "sg:address":"Groenestg 107",
    "sg:city":"Leiden",
    "sg:orig_category":"Verenigingsgebouwen",
    "sg:phone":"+31 71 514 9102",
    "sg:postcode":"2312 SP",
    "sg:province":"Zuid-Holland",
    "wof:name":"Noordrijnevest",
    "wof:placetype":"venue"
},
  "geometry": {"coordinates":[4.502498,52.157295],"type":"Point"}
}