{
  "type": "Feature",
  "properties": {
    "addr:full":"Postbus 80070 Utrecht Utrecht 3508 TB",
    "addr:postcode":"80070;3508 tb",
    "addr:street":"Postbus",
    "iso:country":"NL",
    "sg:address":"Postbus 80070",
    "sg:city":"Utrecht",
    "sg:orig_category":"Milieu",
    "sg:phone":"+31 30 253 6985",
    "sg:postcode":"3508 TB",
    "sg:province":"Utrecht",
    "sg:website":"http://www.chem.uu.nl/cw",
    "wof:name":"Chemiewinkel Utrecht",
    "wof:placetype":"venue"
},
  "geometry": {"coordinates":[5.1228899956,52.0909996033],"type":"Point"}
}