{
  "type": "Feature",
  "properties": {
    "addr:full":"Bunderstr 246 Meerssen Limburg 6231 EP",
    "addr:housenumber":"246",
    "addr:postcode":"6231 ep",
    "iso:country":"NL",
    "sg:address":"Bunderstr 246",
    "sg:city":"Meerssen",
    "sg:orig_category":"Loodgieters",
    "sg:phone":"+31 43 364 7817",
    "sg:postcode":"6231 EP",
    "sg:province":"Limburg",
    "wof:name":"Bruno Loi",
    "wof:placetype":"venue"
},
  "geometry": {"coordinates":[5.743368,50.888802],"type":"Point"}
}