{
  "type": "Feature",
  "properties": {
    "iso:country":"NL",
    "sg:address":"Franciscushof 110",
    "sg:city":"Vianen Zh",
    "sg:classifiers":[
        {
            "category":"Utilities",
            "subcategory":"Cable",
            "type":"Services"
        }
    ],
    "sg:phone":"+31 347 377 742",
    "sg:postcode":"4133 BJ",
    "sg:province":"South Holland",
    "sg:tags":[
        "masseur",
        "en",
        "heilgymnasten"
    ],
    "sg:website":"http://www.rustpuntstoelmassage.nl",
    "wof:name":"Rustpunt",
    "wof:placetype":"venue"
},
  "geometry": {"coordinates":[5.083343,51.979687],"type":"Point"}
}