{
  "type": "Feature",
  "properties": {
    "addr:full":"Winkelerzand 29 Winkel Nh Noord-Holland 1731 LR",
    "addr:housenumber":"29",
    "addr:postcode":"1731 lr",
    "addr:street":"Winkelerzand",
    "iso:country":"NL",
    "sg:address":"Winkelerzand 29",
    "sg:city":"Winkel Nh",
    "sg:orig_category":"Chemische Producten Gh",
    "sg:phone":"+31 224 541 987",
    "sg:postcode":"1731 LR",
    "sg:province":"Noord-Holland",
    "wof:name":"Gramij Bv",
    "wof:placetype":"venue"
},
  "geometry": {"coordinates":[4.89307,52.757111],"type":"Point"}
}