{
  "type": "Feature",
  "properties": {
    "addr:full":"Keienbergwg 3 Amsterdam Zuidoost North Holland 1101 EZ",
    "addr:housenumber":"3",
    "addr:postcode":"1101 ez",
    "addr:street":"Keienbergwg",
    "iso:country":"NL",
    "sg:address":"Keienbergwg 3",
    "sg:city":"Amsterdam Zuidoost",
    "sg:orig_category":"Veilingen En Venduhuizen",
    "sg:phone":"+31 20 452 4712",
    "sg:postcode":"1101 EZ",
    "sg:province":"North Holland",
    "sg:website":"http://www.start-end.nl",
    "wof:name":"Start-End",
    "wof:placetype":"venue"
},
  "geometry": {"coordinates":[4.937006,52.307926],"type":"Point"}
}