{
  "type": "Feature",
  "properties": {
    "addr:full":"Myndensedk 1 Loenen Ad Vecht Utrecht 3632 NT",
    "addr:housenumber":"1",
    "addr:postcode":"3632 nt",
    "addr:street":"Myndensedk;Vecht",
    "iso:country":"NL",
    "sg:address":"Myndensedk 1",
    "sg:city":"Loenen Ad Vecht",
    "sg:classifiers":[
        {
            "category":"Travel",
            "subcategory":"Hotels & Motels",
            "type":"Entertainment"
        }
    ],
    "sg:phone":"+31 294 232 475",
    "sg:postcode":"3632 NT",
    "sg:province":"Utrecht",
    "sg:website":"http://www.motelloenen.nl",
    "wof:name":"Motel Loenen",
    "wof:placetype":"venue"
},
  "geometry": {"coordinates":[5.021896,52.209732],"type":"Point"}
}