{
  "type": "Feature",
  "properties": {
    "addr:full":"Onder De Bomen 2 Thorn Limburg 6017 AL",
    "addr:housenumber":"2",
    "addr:postcode":"6017 al",
    "addr:street":"Onder De Bomen",
    "iso:country":"NL",
    "sg:address":"Onder De Bomen 2",
    "sg:city":"Thorn",
    "sg:orig_category":"Verenigingen En Stichtingen",
    "sg:phone":"+31 475 562 770",
    "sg:postcode":"6017 AL",
    "sg:province":"Limburg",
    "wof:name":"Marthe Robin Foy\u00e9r De Charit\u00e9",
    "wof:placetype":"venue"
},
  "geometry": {"coordinates":[5.841287,51.159187],"type":"Point"}
}