{
  "type": "Feature",
  "properties": {
    "addr:full":"Helper Oostsingel 20 Groningen Groningen 9722 AT",
    "addr:housenumber":"20",
    "addr:postcode":"9722",
    "addr:street":"Helper Oostsingel",
    "iso:country":"NL",
    "sg:address":"Helper Oostsingel 20",
    "sg:city":"Groningen",
    "sg:orig_category":"Diverse Grafische Activiteiten",
    "sg:phone":"+31 50 526 4821",
    "sg:postcode":"9722 AT",
    "sg:province":"Groningen",
    "wof:name":"Fotozetterij Baptist",
    "wof:placetype":"venue"
},
  "geometry": {"coordinates":[6.579469,53.200722],"type":"Point"}
}