{
  "type": "Feature",
  "properties": {
    "addr:full":"Waardeel 10 Borger Provincie Drenthe 9531 EC",
    "addr:housenumber":"10",
    "addr:postcode":"9531 ec",
    "addr:street":"Waardeel;Provincie",
    "iso:country":"NL",
    "sg:address":"Waardeel 10",
    "sg:city":"Borger",
    "sg:orig_category":"Begrafenisverzorging",
    "sg:phone":"+31 599 236 448",
    "sg:postcode":"9531 EC",
    "sg:province":"Provincie Drenthe",
    "wof:name":"Borger Eo",
    "wof:placetype":"venue"
},
  "geometry": {"coordinates":[6.798773,52.916798],"type":"Point"}
}