{
  "type": "Feature",
  "properties": {
    "addr:full":"Noordbolwerk 33 F Middelburg Schleswig-Holstein 4331 SH",
    "addr:housenumber":"33 f",
    "addr:postcode":"4331 sh",
    "addr:street":"Noordbolwerk",
    "iso:country":"NL",
    "sg:address":"Noordbolwerk 33 F",
    "sg:city":"Middelburg",
    "sg:orig_category":"Psychologen",
    "sg:phone":"+31 118 638 162",
    "sg:postcode":"4331 SH",
    "sg:province":"Schleswig-Holstein",
    "wof:name":"Holwerda, Drs J",
    "wof:placetype":"venue"
},
  "geometry": {"coordinates":[10.68287,54.082329],"type":"Point"}
}