{
  "type": "Feature",
  "properties": {
    "addr:full":"Rijksstraatweg 186 Dordrecht Zuid-Holland 3316 EJ",
    "addr:housenumber":"186",
    "addr:postcode":"3316 ej",
    "addr:street":"Rijksstraatweg",
    "iso:country":"NL",
    "sg:address":"Rijksstraatweg 186",
    "sg:city":"Dordrecht",
    "sg:classifiers":[
        {
            "category":"Fast Food",
            "type":"Food & Drink"
        }
    ],
    "sg:phone":"+31 78 618 0017",
    "sg:postcode":"3316 EJ",
    "sg:province":"Zuid-Holland",
    "sg:tags":[
        "afhaal",
        "restaurant"
    ],
    "wof:name":"Cafetaria Bruggehof",
    "wof:placetype":"venue"
},
  "geometry": {"coordinates":[4.630613,51.731205],"type":"Point"}
}