{
  "type": "Feature",
  "properties": {
    "iso:country":"NL",
    "sg:address":"Withuisveld 30",
    "sg:city":"Maastricht",
    "sg:orig_category":"Geluidsisolatie",
    "sg:phone":"+31 43 362 7273",
    "sg:postcode":"6226 NV",
    "sg:province":"Limburg",
    "wof:name":"Makura Bv",
    "wof:placetype":"venue"
},
  "geometry": {"coordinates":[5.732712,50.85342],"type":"Point"}
}