{
  "type": "Feature",
  "properties": {
    "addr:full":"Z Koninginnewal 36 Helmond Noord-Brabant 5701 NT",
    "addr:housenumber":"36",
    "addr:postcode":"5701 nt",
    "addr:street":"Koninginnewal",
    "iso:country":"NL",
    "sg:address":"Z Koninginnewal 36",
    "sg:city":"Helmond",
    "sg:orig_category":"Opticiens",
    "sg:phone":"+31 492 523 666",
    "sg:postcode":"5701 NT",
    "sg:province":"Noord-Brabant",
    "wof:name":"Bogaerts",
    "wof:placetype":"venue"
},
  "geometry": {"coordinates":[5.6576981544,51.4785194397],"type":"Point"}
}