{
  "type": "Feature",
  "properties": {
    "addr:full":"Veemarkt 1 Tiel Gelderland 4001 AE",
    "addr:housenumber":"1",
    "addr:postcode":"4001 ae",
    "addr:street":"Veemarkt;Gelderland",
    "iso:country":"NL",
    "sg:address":"Veemarkt 1",
    "sg:city":"Tiel",
    "sg:orig_category":"Benzine En Olie - Groothandel",
    "sg:phone":"+31 344 614 734",
    "sg:postcode":"4001 AE",
    "sg:province":"Gelderland",
    "wof:name":"Dijkhuizen Bv, H Van",
    "wof:placetype":"venue"
},
  "geometry": {"coordinates":[5.429115,51.887482],"type":"Point"}
}