{
  "type": "Feature",
  "properties": {
    "iso:country":"NL",
    "sg:address":"Textielweg 22",
    "sg:city":"Amersfoort",
    "sg:orig_category":"Loodgieters- And Verwarmingsmateriaal Gh",
    "sg:phone":"+31 33 461 6744",
    "sg:postcode":"3812 RV",
    "sg:province":"Utrecht",
    "wof:name":"Rensa Servicebalie",
    "wof:placetype":"venue"
},
  "geometry": {"coordinates":[5.367597,52.165241],"type":"Point"}
}