{
  "type": "Feature",
  "properties": {
    "addr:full":"De Busser 3 Nuenen Noord-Brabant 5674 PM",
    "addr:housenumber":"3",
    "addr:postcode":"5674 pm",
    "addr:street":"De Busser",
    "iso:country":"NL",
    "sg:address":"De Busser 3",
    "sg:city":"Nuenen",
    "sg:orig_category":"Webdesign Bureaus",
    "sg:phone":"+31 6 44296002",
    "sg:postcode":"5674 PM",
    "sg:province":"Noord-Brabant",
    "sg:website":"http://www.symbolix.nl",
    "wof:name":"Symbolix",
    "wof:placetype":"venue"
},
  "geometry": {"coordinates":[5.5601677895,51.4907226562],"type":"Point"}
}