{
  "type": "Feature",
  "properties": {
    "addr:full":"Dorpsstraat 205 Zwaag Noord-Holland 1689 GC",
    "addr:housenumber":"205",
    "addr:postcode":"1689 gc",
    "addr:street":"Dorpsstraat",
    "iso:country":"NL",
    "sg:address":"Dorpsstraat 205",
    "sg:city":"Zwaag",
    "sg:orig_category":"Auto'S And Voertuigen",
    "sg:phone":"+31 229 261 985",
    "sg:postcode":"1689 GC",
    "sg:province":"Noord-Holland",
    "wof:name":"A. Stroet",
    "wof:placetype":"venue"
},
  "geometry": {"coordinates":[5.079214,52.670002],"type":"Point"}
}