{
  "type": "Feature",
  "properties": {
    "addr:full":"Europaweg 174 Schoonebeek Provincie Drenthe 7761 AM",
    "addr:housenumber":"174",
    "addr:postcode":"7761",
    "addr:street":"Europaweg;Provincie Drenthe",
    "iso:country":"NL",
    "sg:address":"Europaweg 174",
    "sg:city":"Schoonebeek",
    "sg:orig_category":"Loodgieterswerk, Verwarming And Sanitaire Installaties",
    "sg:phone":"+31 524 531 871",
    "sg:postcode":"7761 AM",
    "sg:province":"Provincie Drenthe",
    "wof:name":"Onderhouds Timmerman Albert",
    "wof:placetype":"venue"
},
  "geometry": {"coordinates":[6.8741,52.664772],"type":"Point"}
}