{
  "type": "Feature",
  "properties": {
    "iso:country":"NL",
    "sg:address":"Jan Pieter Heijestraat 168",
    "sg:city":"Amsterdam",
    "sg:classifiers":[
        {
            "category":"Communications",
            "subcategory":"Television Station",
            "type":"Services"
        }
    ],
    "sg:phone":"+31 20 683 1788",
    "sg:postcode":"1054 ML",
    "sg:province":"Noord-Holland",
    "sg:tags":[
        "video",
        "audio",
        "verhuur"
    ],
    "wof:name":"Videotheek Starworld",
    "wof:placetype":"venue"
},
  "geometry": {"coordinates":[4.864765,52.361115],"type":"Point"}
}