{
  "type": "Feature",
  "properties": {
    "addr:full":"Koeweide 16 Aalten Gelderland 7121 EJ",
    "addr:housenumber":"16",
    "addr:postcode":"7121 ej",
    "addr:street":"Koeweide;Gelderland",
    "iso:country":"NL",
    "sg:address":"Koeweide 16",
    "sg:city":"Aalten",
    "sg:orig_category":"Artsen - Huisartsen",
    "sg:phone":"+31 543 473 710",
    "sg:postcode":"7121 EJ",
    "sg:province":"Gelderland",
    "wof:name":"Huisartsenprakt Koeweide",
    "wof:placetype":"venue"
},
  "geometry": {"coordinates":[6.581619,51.921696],"type":"Point"}
}