{
  "type": "Feature",
  "properties": {
    "iso:country":"NL",
    "sg:address":"Hoofdweg 1240",
    "sg:city":"Nieuw Vennep",
    "sg:orig_category":"Bedrijfsinventaris Gh",
    "sg:phone":"+31 252 620 886",
    "sg:postcode":"2153 LR",
    "sg:province":"Noord-Holland",
    "wof:name":"Serco Koeltechniek Bv",
    "wof:placetype":"venue"
},
  "geometry": {"coordinates":[4.638867,52.267551],"type":"Point"}
}