{
  "type": "Feature",
  "properties": {
    "addr:full":"Herenstr 36 Culemborg Gelderland 4101 BV",
    "addr:housenumber":"36",
    "addr:postcode":"4101 bv",
    "addr:street":"Herenstr;Gelderland",
    "iso:country":"NL",
    "sg:address":"Herenstr 36",
    "sg:city":"Culemborg",
    "sg:orig_category":"Adviesbureaus Bedrijfsorganisatie",
    "sg:phone":"+31 345 534 074",
    "sg:postcode":"4101 BV",
    "sg:province":"Gelderland",
    "wof:name":"Hansum",
    "wof:placetype":"venue"
},
  "geometry": {"coordinates":[5.224363,51.957111],"type":"Point"}
}