{
  "type": "Feature",
  "properties": {
    "addr:full":"Goirkestraat 12 Tilburg North Brabant 5046 GK",
    "addr:housenumber":"12",
    "addr:postcode":"5046 gk",
    "addr:street":"Goirkestraat",
    "iso:country":"NL",
    "sg:address":"Goirkestraat 12",
    "sg:city":"Tilburg",
    "sg:orig_category":"Verzekeringen",
    "sg:phone":"+31 13 536 0636",
    "sg:postcode":"5046 GK",
    "sg:province":"North Brabant",
    "wof:name":"Assurantiekantoor A. De Werk Bv",
    "wof:placetype":"venue"
},
  "geometry": {"coordinates":[5.082438,51.575054],"type":"Point"}
}