{
  "type": "Feature",
  "properties": {
    "addr:full":"Naxosdreef 45 Utrecht Utrecht 3562 JB",
    "addr:housenumber":"45",
    "addr:postcode":"3562 jb",
    "addr:street":"Naxosdreef",
    "iso:country":"NL",
    "sg:address":"Naxosdreef 45",
    "sg:city":"Utrecht",
    "sg:orig_category":"Fotografie Reclame En Mode",
    "sg:phone":"+31 30 262 2327",
    "sg:postcode":"3562 JB",
    "sg:province":"Utrecht",
    "wof:name":"Bosch Fotografie, Marc",
    "wof:placetype":"venue"
},
  "geometry": {"coordinates":[5.113951,52.115417],"type":"Point"}
}