{
  "type": "Feature",
  "properties": {
    "addr:full":"Oudedijk 82 Odiliapeel North Brabant 5409 SC",
    "addr:housenumber":"82",
    "addr:postcode":"5409 sc",
    "addr:street":"Oudedijk",
    "iso:country":"NL",
    "sg:address":"Oudedijk 82",
    "sg:city":"Odiliapeel",
    "sg:orig_category":"Loodgieterswerk, Verwarming And Sanitaire Installaties",
    "sg:phone":"+31 413 274 590",
    "sg:postcode":"5409 SC",
    "sg:province":"North Brabant",
    "wof:name":"Van Den Elzen Montage",
    "wof:placetype":"venue"
},
  "geometry": {"coordinates":[5.719926,51.640774],"type":"Point"}
}