{
  "type": "Feature",
  "properties": {
    "addr:full":"St Catharinadal 16 Willemstad Nb Noord-Brabant 4797 BT",
    "addr:housenumber":"16",
    "addr:postcode":"4797 bt",
    "addr:street":"St Catharinadal",
    "iso:country":"NL",
    "sg:address":"St Catharinadal 16",
    "sg:city":"Willemstad Nb",
    "sg:orig_category":"Fietsen - Fabrieken En Groothandel",
    "sg:phone":"+31 168 476 110",
    "sg:postcode":"4797 BT",
    "sg:province":"Noord-Brabant",
    "sg:website":"http://www.mp-products.nl",
    "wof:name":"Mp Products",
    "wof:placetype":"venue"
},
  "geometry": {"coordinates":[4.446309,51.688],"type":"Point"}
}