{
  "type": "Feature",
  "properties": {
    "iso:country":"NL",
    "sg:address":"Heuvelpoort 308A",
    "sg:city":"Tilburg",
    "sg:orig_category":"Verhuur",
    "sg:phone":"+31 13 535 3275",
    "sg:postcode":"5038 DT",
    "sg:province":"North Brabant",
    "wof:name":"Heuvelpoort",
    "wof:placetype":"venue"
},
  "geometry": {"coordinates":[5.090747,51.556881],"type":"Point"}
}