{
  "type": "Feature",
  "properties": {
    "addr:full":"Grotestraat 21 Goor Overijssel 7471 BK",
    "addr:housenumber":"21",
    "addr:postcode":"7471 bk",
    "addr:street":"Grotestraat",
    "iso:country":"NL",
    "sg:address":"Grotestraat 21",
    "sg:city":"Goor",
    "sg:orig_category":"Banken And Kredietinstellingen",
    "sg:phone":"+31 547 286 767",
    "sg:postcode":"7471 BK",
    "sg:province":"Overijssel",
    "wof:name":"Sns Bank Overijssel Nv",
    "wof:placetype":"venue"
},
  "geometry": {"coordinates":[6.587288,52.235176],"type":"Point"}
}