{
  "type": "Feature",
  "properties": {
    "iso:country":"NL",
    "sg:address":"Wooldereswg 82",
    "sg:city":"Hengelo Ov",
    "sg:orig_category":"Verzekeringen - Verzekeringskantoren",
    "sg:phone":"+31 74 242 0014",
    "sg:postcode":"7555 LB",
    "sg:province":"NL.08",
    "wof:name":"Nieuwboer, Van Den",
    "wof:placetype":"venue"
},
  "geometry": {"coordinates":[6.775875,52.2687],"type":"Point"}
}