{
  "type": "Feature",
  "properties": {
    "iso:country":"NL",
    "sg:address":"Mijnbouwstraat 106",
    "sg:city":"Delft",
    "sg:orig_category":"Technische Studies And Onderzoek",
    "sg:phone":"+31 15 261 4341",
    "sg:postcode":"2628 RX",
    "sg:province":"Zuid-Holland",
    "wof:name":"Ketel Raadgevende Ingenieurs Bv",
    "wof:placetype":"venue"
},
  "geometry": {"coordinates":[4.366368,52.006302],"type":"Point"}
}