{
  "type": "Feature",
  "properties": {
    "addr:full":"Morra 30 Zwolle Overijssel 8032 ZN",
    "addr:housenumber":"30",
    "addr:postcode":"8032 zn",
    "addr:street":"Morra",
    "iso:country":"NL",
    "sg:address":"Morra 30",
    "sg:city":"Zwolle",
    "sg:orig_category":"Film-, Tv- And Videoproductie",
    "sg:phone":"+31 38 452 7531",
    "sg:postcode":"8032 ZN",
    "sg:province":"Overijssel",
    "wof:name":"Van Der Wouden",
    "wof:placetype":"venue"
},
  "geometry": {"coordinates":[6.097465,52.535149],"type":"Point"}
}