{
  "type": "Feature",
  "properties": {
    "addr:full":"Floresstraat 9 Groningen Groningen 9715 HM",
    "addr:housenumber":"9",
    "addr:postcode":"9715 hm",
    "addr:street":"Floresstraat",
    "iso:country":"NL",
    "sg:address":"Floresstraat 9",
    "sg:city":"Groningen",
    "sg:orig_category":"Kappers",
    "sg:phone":"+31 50 571 7643",
    "sg:postcode":"9715 HM",
    "sg:province":"Groningen",
    "wof:name":"Salon Eskandar",
    "wof:placetype":"venue"
},
  "geometry": {"coordinates":[6.567752,53.23241],"type":"Point"}
}