{
  "type": "Feature",
  "properties": {
    "addr:full":"Boulevard Antverpia 9 Roosendaal North Brabant 4703 AV",
    "addr:housenumber":"9",
    "addr:postcode":"4703 av",
    "addr:street":"Boulevard Antverpia",
    "iso:country":"NL",
    "sg:address":"Boulevard Antverpia 9",
    "sg:city":"Roosendaal",
    "sg:classifiers":[
        {
            "category":"Education",
            "subcategory":"Preschool",
            "type":"Public Place"
        }
    ],
    "sg:phone":"+31 165 540 845",
    "sg:postcode":"4703 AV",
    "sg:province":"North Brabant",
    "sg:tags":[
        "kleuteronderwijs",
        "basis-"
    ],
    "wof:name":"Basisschool De Blokwei",
    "wof:placetype":"venue"
},
  "geometry": {"coordinates":[4.448595,51.5299],"type":"Point"}
}