{
  "type": "Feature",
  "properties": {
    "addr:full":"Kon Wilhelminawg 50/A Amerongen Utrecht 3958 CP",
    "addr:housenumber":"50 / a",
    "addr:postcode":"3958 cp",
    "addr:street":"Kon",
    "iso:country":"NL",
    "sg:address":"Kon Wilhelminawg 50/A",
    "sg:city":"Amerongen",
    "sg:orig_category":"Landmeetkundige Bureaus",
    "sg:phone":"+31 343 461 484",
    "sg:postcode":"3958 CP",
    "sg:province":"Utrecht",
    "wof:name":"Ned Bedrijven Geodesie, Ver",
    "wof:placetype":"venue"
},
  "geometry": {"coordinates":[5.457508,52.000618],"type":"Point"}
}