{
  "type": "Feature",
  "properties": {
    "addr:full":"Jonkhof 12 'S Hertogenbosch Noord-Brabant 5237 PE",
    "addr:housenumber":"12",
    "addr:postcode":"5237 pe",
    "addr:street":"Jonkhof;' S",
    "iso:country":"NL",
    "sg:address":"Jonkhof 12",
    "sg:city":"'S Hertogenbosch",
    "sg:orig_category":"Boekhouders",
    "sg:phone":"+31 73 641 2842",
    "sg:postcode":"5237 PE",
    "sg:province":"Noord-Brabant",
    "wof:name":"Admiwise",
    "wof:placetype":"venue"
},
  "geometry": {"coordinates":[5.287687,51.728779],"type":"Point"}
}