{
  "type": "Feature",
  "properties": {
    "addr:full":"Fabriekstr 12 Goirle Noord-Brabant 5051 HP",
    "addr:housenumber":"12",
    "addr:postcode":"5051 hp",
    "addr:street":"Fabriekstr",
    "iso:country":"NL",
    "sg:address":"Fabriekstr 12",
    "sg:city":"Goirle",
    "sg:orig_category":"Autorijscholen",
    "sg:phone":"+31 13 534 2440",
    "sg:postcode":"5051 HP",
    "sg:province":"Noord-Brabant",
    "wof:name":"Piet En Annie Van De Pol",
    "wof:placetype":"venue"
},
  "geometry": {"coordinates":[5.060568,51.516129],"type":"Point"}
}