{
  "type": "Feature",
  "properties": {
    "iso:country":"NL",
    "sg:address":"Industrieweg 13",
    "sg:city":"Mijdrecht",
    "sg:orig_category":"Verzekeringen",
    "sg:phone":"+31 297 288 816",
    "sg:postcode":"3641 RK",
    "sg:province":"Utrecht",
    "wof:name":"Ascol Verzekeringen Bv",
    "wof:placetype":"venue"
},
  "geometry": {"coordinates":[4.87121,52.206589],"type":"Point"}
}