{
  "type": "Feature",
  "properties": {
    "addr:full":"Industrieweg 13 Mijdrecht Utrecht 3641 RK",
    "addr:housenumber":"13",
    "addr:postcode":"3641 rk",
    "addr:street":"Industrieweg",
    "iso:country":"NL",
    "sg:address":"Industrieweg 13",
    "sg:city":"Mijdrecht",
    "sg:orig_category":"Verzekeringen",
    "sg:phone":"+31 297 288 816",
    "sg:postcode":"3641 RK",
    "sg:province":"Utrecht",
    "wof:name":"Ascol Verzekeringen Bv",
    "wof:placetype":"venue"
},
  "geometry": {"coordinates":[4.87121,52.206589],"type":"Point"}
}