{
  "type": "Feature",
  "properties": {
    "addr:full":"Grt Houtstr 187 Haarlem Noord-Holland 2011 SM",
    "addr:housenumber":"187",
    "addr:postcode":"2011 sm",
    "iso:country":"NL",
    "sg:address":"Grt Houtstr 187",
    "sg:city":"Haarlem",
    "sg:classifiers":[
        {
            "category":"Food & Beverages",
            "subcategory":"Bakery",
            "type":"Retail Goods"
        }
    ],
    "sg:phone":"+31 23 542 6161",
    "sg:postcode":"2011 SM",
    "sg:province":"Noord-Holland",
    "sg:tags":[
        "brood",
        "en",
        "banket"
    ],
    "wof:name":"Vessem & Le Patichou, Van",
    "wof:placetype":"venue"
},
  "geometry": {"coordinates":[4.631221,52.376247],"type":"Point"}
}