{
  "type": "Feature",
  "properties": {
    "addr:full":"Fruiteniersstr 14 Zwyndrecht Zuid-Holland 3334 KA",
    "addr:housenumber":"14",
    "addr:postcode":"3334 ka",
    "addr:street":"Fruiteniersstr",
    "iso:country":"NL",
    "sg:address":"Fruiteniersstr 14",
    "sg:city":"Zwyndrecht",
    "sg:orig_category":"Schilders",
    "sg:phone":"+31 78 610 5199",
    "sg:postcode":"3334 KA",
    "sg:province":"Zuid-Holland",
    "wof:name":"Bouman Arkel Bv, G",
    "wof:placetype":"venue"
},
  "geometry": {"coordinates":[4.601157,51.812019],"type":"Point"}
}