{
  "type": "Feature",
  "properties": {
    "addr:full":"Keizersgracht 112 Den Helder Noord-Holland 1781 BC",
    "addr:housenumber":"112",
    "addr:postcode":"1781 bc",
    "addr:street":"Keizersgracht",
    "iso:country":"NL",
    "sg:address":"Keizersgracht 112",
    "sg:city":"Den Helder",
    "sg:orig_category":"Granen, Zaden And Diervoeders Gh",
    "sg:phone":"+31 223 612 980",
    "sg:postcode":"1781 BC",
    "sg:province":"Noord-Holland",
    "wof:name":"J.J. Jimmink",
    "wof:placetype":"venue"
},
  "geometry": {"coordinates":[4.768215,52.957237],"type":"Point"}
}