{
  "type": "Feature",
  "properties": {
    "addr:full":"Neringpassage 105 Lelystad NL. 8224 JB",
    "addr:housenumber":"105",
    "addr:postcode":"8224 jb",
    "addr:street":"Neringpassage;Nl.",
    "iso:country":"NL",
    "sg:address":"Neringpassage 105",
    "sg:city":"Lelystad",
    "sg:orig_category":"Hypotheken",
    "sg:phone":"+31 320 242 954",
    "sg:postcode":"8224 JB",
    "sg:province":"NL.",
    "sg:website":"http://www.hypomatch.com",
    "wof:name":"Hypomatch",
    "wof:placetype":"venue"
},
  "geometry": {"coordinates":[5.476831,52.509735],"type":"Point"}
}