{
  "type": "Feature",
  "properties": {
    "addr:full":"Sacharovstraat 4 Oldenzaal Overijssel 7575 EA",
    "addr:housenumber":"4",
    "addr:postcode":"7575 ea",
    "addr:street":"Sacharovstraat",
    "iso:country":"NL",
    "sg:address":"Sacharovstraat 4",
    "sg:city":"Oldenzaal",
    "sg:orig_category":"Gespecialiseerde Bouw",
    "sg:phone":"+31 541 573 030",
    "sg:postcode":"7575 EA",
    "sg:province":"Overijssel",
    "wof:name":"Novicon Staalbouw Bv",
    "wof:placetype":"venue"
},
  "geometry": {"coordinates":[6.915921,52.294601],"type":"Point"}
}