{
  "type": "Feature",
  "properties": {
    "addr:full":"Borszeestraat 17 Borssele Zeeland 4454 BR",
    "addr:housenumber":"17",
    "addr:postcode":"4454 br",
    "addr:street":"Borszeestraat",
    "iso:country":"NL",
    "sg:address":"Borszeestraat 17",
    "sg:city":"Borssele",
    "sg:orig_category":"Boekenuitgeverijen",
    "sg:phone":"+31 113 352 188",
    "sg:postcode":"4454 BR",
    "sg:province":"Zeeland",
    "wof:name":"C. Witte-Moeleker",
    "wof:placetype":"venue"
},
  "geometry": {"coordinates":[3.735733,51.420509],"type":"Point"}
}