{
  "type": "Feature",
  "properties": {
    "addr:full":"Voorstad 2 Tiel Gelderland 4001 LT",
    "addr:housenumber":"2",
    "addr:postcode":"4001 lt",
    "addr:street":"Voorstad;Gelderland",
    "iso:country":"NL",
    "sg:address":"Voorstad 2",
    "sg:city":"Tiel",
    "sg:orig_category":"Herenkleding",
    "sg:phone":"+31 344 613 679",
    "sg:postcode":"4001 LT",
    "sg:province":"Gelderland",
    "wof:name":"Meijers",
    "wof:placetype":"venue"
},
  "geometry": {"coordinates":[5.437707,51.887959],"type":"Point"}
}