{
  "type": "Feature",
  "properties": {
    "addr:full":"Kleine Berg 53 Eindhoven North Brabant 5611 JT",
    "addr:housenumber":"53",
    "addr:postcode":"5611 jt",
    "addr:street":"Kleine Berg",
    "iso:country":"NL",
    "sg:address":"Kleine Berg 53",
    "sg:city":"Eindhoven",
    "sg:classifiers":[
        {
            "category":"Communications",
            "subcategory":"Television Station",
            "type":"Services"
        }
    ],
    "sg:phone":"+31 40 244 8816",
    "sg:postcode":"5611 JT",
    "sg:province":"North Brabant",
    "sg:tags":[
        "video",
        "audio",
        "verhuur"
    ],
    "wof:name":"Cinematheek",
    "wof:placetype":"venue"
},
  "geometry": {"coordinates":[5.484105,51.434471],"type":"Point"}
}