{
  "type": "Feature",
  "properties": {
    "addr:full":"Molenstraat 3 Deurne Noord-Brabant 5751 LA",
    "addr:housenumber":"3",
    "addr:postcode":"5751 la",
    "addr:street":"Molenstraat",
    "iso:country":"NL",
    "sg:address":"Molenstraat 3",
    "sg:city":"Deurne",
    "sg:classifiers":[
        {
            "category":"Retail",
            "subcategory":"Photofinishing",
            "type":"Services"
        }
    ],
    "sg:phone":"+31 493 312 583",
    "sg:postcode":"5751 LA",
    "sg:province":"Noord-Brabant",
    "sg:tags":[
        "foto",
        "film"
    ],
    "wof:name":"Multi Foto Deurne",
    "wof:placetype":"venue"
},
  "geometry": {"coordinates":[5.795486,51.463837],"type":"Point"}
}