{
  "type": "Feature",
  "properties": {
    "addr:full":"Dikkersbos 14 Enschede Overijssel 7543 GR",
    "addr:housenumber":"14",
    "addr:postcode":"7543",
    "addr:street":"Dikkersbos",
    "iso:country":"NL",
    "sg:address":"Dikkersbos 14",
    "sg:city":"Enschede",
    "sg:orig_category":"Metselwerken",
    "sg:phone":"+31 6 20003237",
    "sg:postcode":"7543 GR",
    "sg:province":"Overijssel",
    "wof:name":"Oygur, S",
    "wof:placetype":"venue"
},
  "geometry": {"coordinates":[6.86245,52.204739],"type":"Point"}
}