{
  "type": "Feature",
  "properties": {
    "addr:full":"Knsm Laan 127 Amsterdam North Holland 1019 LB",
    "addr:housenumber":"127",
    "addr:postcode":"1019 lb",
    "addr:street":"Laan",
    "iso:country":"NL",
    "sg:address":"Knsm Laan 127",
    "sg:city":"Amsterdam",
    "sg:orig_category":"Kantoorartikelen",
    "sg:phone":"+31 20 419 5751",
    "sg:postcode":"1019 LB",
    "sg:province":"North Holland",
    "wof:name":"Modular Systems",
    "wof:placetype":"venue"
},
  "geometry": {"coordinates":[4.938811779,52.3772392273],"type":"Point"}
}