{
  "type": "Feature",
  "properties": {
    "addr:full":"De Maalsteen 5 Valkenswaard Noord-Brabant 5554 KC",
    "addr:housenumber":"5",
    "addr:postcode":"5554 kc",
    "addr:street":"De Maalsteen",
    "iso:country":"NL",
    "sg:address":"De Maalsteen 5",
    "sg:city":"Valkenswaard",
    "sg:orig_category":"Video - Faciliteiten En Producties",
    "sg:phone":"+31 40 204 2451",
    "sg:postcode":"5554 KC",
    "sg:province":"Noord-Brabant",
    "wof:name":"Hoof, Frits Van",
    "wof:placetype":"venue"
},
  "geometry": {"coordinates":[5.46336,51.350418],"type":"Point"}
}