{
  "type": "Feature",
  "properties": {
    "addr:full":"Kiel 7 Groningen Groningen 9733 EB",
    "addr:housenumber":"7",
    "addr:postcode":"9733 eb",
    "addr:street":"Kiel",
    "iso:country":"NL",
    "sg:address":"Kiel 7",
    "sg:city":"Groningen",
    "sg:classifiers":[
        {
            "category":"Education",
            "subcategory":"Preschool",
            "type":"Public Place"
        }
    ],
    "sg:phone":"+31 50 549 4118",
    "sg:postcode":"9733 EB",
    "sg:province":"Groningen",
    "sg:tags":[
        "kleuteronderwijs",
        "basis-"
    ],
    "wof:name":"De Swoaistee",
    "wof:placetype":"venue"
},
  "geometry": {"coordinates":[6.616291,53.236271],"type":"Point"}
}