{
  "type": "Feature",
  "properties": {
    "iso:country":"NL",
    "sg:address":"Verdronkenoord 60",
    "sg:city":"Alkmaar",
    "sg:orig_category":"Boekhandels",
    "sg:phone":"+31 72 512 6041",
    "sg:postcode":"1811 BG",
    "sg:province":"Noord-Holland",
    "wof:name":"Stripwinkel Paulus",
    "wof:placetype":"venue"
},
  "geometry": {"coordinates":[4.75213,52.629417],"type":"Point"}
}