{
  "type": "Feature",
  "properties": {
    "addr:full":"Meeuwenlaan 63 Sneek Friesland 8601 XR",
    "addr:housenumber":"63",
    "addr:postcode":"8601 xr",
    "addr:street":"Meeuwenlaan",
    "iso:country":"NL",
    "sg:address":"Meeuwenlaan 63",
    "sg:city":"Sneek",
    "sg:orig_category":"Paramedische Behandelingen",
    "sg:phone":"+31 515 414 983",
    "sg:postcode":"8601 XR",
    "sg:province":"Friesland",
    "wof:name":"T.W. V.D. Werf",
    "wof:placetype":"venue"
},
  "geometry": {"coordinates":[5.648995,53.033218],"type":"Point"}
}