{
  "type": "Feature",
  "properties": {
    "addr:full":"J M Houwenstr 8 Drachten Friesland 9203 SK",
    "addr:housenumber":"8",
    "addr:street":"J M Houwenstr;9203",
    "iso:country":"NL",
    "sg:address":"J M Houwenstr 8",
    "sg:city":"Drachten",
    "sg:orig_category":"Autorijscholen",
    "sg:phone":"+31 512 513 793",
    "sg:postcode":"9203 SK",
    "sg:province":"Friesland",
    "wof:name":"Wierda, J",
    "wof:placetype":"venue"
},
  "geometry": {"coordinates":[6.092918,53.105995],"type":"Point"}
}