{
  "type": "Feature",
  "properties": {
    "iso:country":"NL",
    "sg:address":"Wiebachstr 79",
    "sg:city":"Kerkrade",
    "sg:orig_category":"Opslag Inboedels",
    "sg:phone":"+31 45 546 8440",
    "sg:postcode":"6466 NG",
    "sg:province":"Limburg",
    "sg:website":"http://www.shurgard.nl",
    "wof:name":"Shurgard Kerkrade",
    "wof:placetype":"venue"
},
  "geometry": {"coordinates":[6.007516861,50.8510780334],"type":"Point"}
}