{
  "type": "Feature",
  "properties": {
    "addr:full":"Plantage Middenln 17 Amsterdam Noord-Holland 1018 DA",
    "addr:housenumber":"17",
    "addr:postcode":"1018 da",
    "addr:street":"Plantage Middenln",
    "iso:country":"NL",
    "sg:address":"Plantage Middenln 17",
    "sg:city":"Amsterdam",
    "sg:classifiers":[
        {
            "category":"Travel",
            "subcategory":"Hotels & Motels",
            "type":"Entertainment"
        }
    ],
    "sg:phone":"+31 20 627 2714",
    "sg:postcode":"1018 DA",
    "sg:province":"Noord-Holland",
    "wof:name":"Rembrandt",
    "wof:placetype":"venue"
},
  "geometry": {"coordinates":[4.910527,52.367046],"type":"Point"}
}