{
  "type": "Feature",
  "properties": {
    "addr:full":"Echtenstraat 59 Assen Drenthe 9402 JB",
    "addr:housenumber":"59",
    "addr:postcode":"9402 jb",
    "addr:street":"Echtenstraat",
    "iso:country":"NL",
    "sg:address":"Echtenstraat 59",
    "sg:city":"Assen",
    "sg:orig_category":"Metaalwerken",
    "sg:phone":"+31 592 343 000",
    "sg:postcode":"9402 JB",
    "sg:province":"Drenthe",
    "wof:name":"H. Zagers",
    "wof:placetype":"venue"
},
  "geometry": {"coordinates":[6.550259,53.003483],"type":"Point"}
}