{
  "type": "Feature",
  "properties": {
    "addr:full":"Aureliavlinder 3 Zwolle NL.08 8016 HD",
    "addr:housenumber":"3",
    "addr:postcode":"8016",
    "addr:street":"Aureliavlinder;Hd",
    "iso:country":"NL",
    "sg:address":"Aureliavlinder 3",
    "sg:city":"Zwolle",
    "sg:orig_category":"Verzekeringen",
    "sg:phone":"+31 38 465 2186",
    "sg:postcode":"8016 HD",
    "sg:province":"NL.08",
    "wof:name":"J. Geut",
    "wof:placetype":"venue"
},
  "geometry": {"coordinates":[6.103954,52.491348],"type":"Point"}
}