{
  "type": "Feature",
  "properties": {
    "iso:country":"NL",
    "sg:address":"Zuidvliet 118",
    "sg:city":"Leeuwarden",
    "sg:orig_category":"Onderhoudswerken",
    "sg:phone":"+31 6 51281942",
    "sg:postcode":"8921 BM",
    "sg:province":"Provincie Friesland",
    "wof:name":"Siebe'S Klussenbedrijf",
    "wof:placetype":"venue"
},
  "geometry": {"coordinates":[5.81099,53.205589],"type":"Point"}
}