{
  "type": "Feature",
  "properties": {
    "addr:full":"Scalmeyerpad 20 Soest Utrecht 3766 CE",
    "addr:housenumber":"20",
    "addr:postcode":"3766 ce",
    "addr:street":"Scalmeyerpad",
    "iso:country":"NL",
    "sg:address":"Scalmeyerpad 20",
    "sg:city":"Soest",
    "sg:orig_category":"Facilitaire Dienstverlening",
    "sg:phone":"+31 35 672 0760",
    "sg:postcode":"3766 CE",
    "sg:province":"Utrecht",
    "sg:website":"http://www.extrahands.nl/tgooi",
    "wof:name":"Extra Hands 'T Gooi",
    "wof:placetype":"venue"
},
  "geometry": {"coordinates":[5.300385,52.184044],"type":"Point"}
}