{
  "type": "Feature",
  "properties": {
    "addr:full":"Buitenwg 1 Enschede Overijssel 7545 SN",
    "addr:housenumber":"1",
    "addr:postcode":"7545 sn",
    "addr:street":"Buitenwg",
    "iso:country":"NL",
    "sg:address":"Buitenwg 1",
    "sg:city":"Enschede",
    "sg:orig_category":"Verenigingen En Stichtingen",
    "sg:phone":"+31 53 430 5367",
    "sg:postcode":"7545 SN",
    "sg:province":"Overijssel",
    "wof:name":"Prima Project West",
    "wof:placetype":"venue"
},
  "geometry": {"coordinates":[6.875362,52.215305],"type":"Point"}
}