{
  "type": "Feature",
  "properties": {
    "addr:full":"Lepelstraat 1 Kloosterzande Zeeland 4587 DA",
    "addr:housenumber":"1",
    "addr:postcode":"4587 da",
    "addr:street":"Lepelstraat",
    "iso:country":"NL",
    "sg:address":"Lepelstraat 1",
    "sg:city":"Kloosterzande",
    "sg:orig_category":"Metaalafval, Schrootrecycling And Sloperijen",
    "sg:phone":"+31 114 681 932",
    "sg:postcode":"4587 DA",
    "sg:province":"Zeeland",
    "wof:name":"D. V.D. Ven",
    "wof:placetype":"venue"
},
  "geometry": {"coordinates":[4.025276,51.365009],"type":"Point"}
}