{
  "type": "Feature",
  "properties": {
    "addr:full":"Oudegr 309 Utrecht Utrecht 3511 PB",
    "addr:housenumber":"309",
    "addr:postcode":"3511 pb",
    "iso:country":"NL",
    "sg:address":"Oudegr 309",
    "sg:city":"Utrecht",
    "sg:classifiers":[
        {
            "category":"Professional",
            "subcategory":"Management & Consulting",
            "type":"Services"
        }
    ],
    "sg:phone":"+31 30 666 8853",
    "sg:postcode":"3511 PB",
    "sg:province":"Utrecht",
    "sg:tags":[
        "relation",
        "adviesbureaus",
        "public"
    ],
    "wof:name":"Poco Mas Vof",
    "wof:placetype":"venue"
},
  "geometry": {"coordinates":[5.115405,52.088932],"type":"Point"}
}