{
  "type": "Feature",
  "properties": {
    "addr:full":"De Staat 15 St Anthonis Noord-Brabant 5845 GD",
    "addr:housenumber":"15",
    "addr:postcode":"5845 gd",
    "addr:street":"De Staat;St",
    "iso:country":"NL",
    "sg:address":"De Staat 15",
    "sg:city":"St Anthonis",
    "sg:orig_category":"Schoonheidsinstituten",
    "sg:phone":"+31 485 382 610",
    "sg:postcode":"5845 GD",
    "sg:province":"Noord-Brabant",
    "wof:name":"Rongen-Dortmans, L",
    "wof:placetype":"venue"
},
  "geometry": {"coordinates":[5.87123,51.625473],"type":"Point"}
}