{
  "type": "Feature",
  "properties": {
    "addr:full":"Waarbekenweg 19 Hengelo Ov Overijssel 7553 KH",
    "addr:housenumber":"19",
    "addr:postcode":"7553 kh",
    "addr:street":"Waarbekenweg;Ov",
    "iso:country":"NL",
    "sg:address":"Waarbekenweg 19",
    "sg:city":"Hengelo Ov",
    "sg:orig_category":"Voeding, Dranken And Tabak Gh",
    "sg:phone":"+31 74 242 7821",
    "sg:postcode":"7553 KH",
    "sg:province":"Overijssel",
    "wof:name":"Ipek International",
    "wof:placetype":"venue"
},
  "geometry": {"coordinates":[6.797618,52.254086],"type":"Point"}
}