{
  "type": "Feature",
  "properties": {
    "addr:full":"Jericholn 85 Rotterdam Zuid-Holland 3061 HC",
    "addr:housenumber":"85",
    "addr:postcode":"3061 hc",
    "addr:street":"Jericholn",
    "iso:country":"NL",
    "sg:address":"Jericholn 85",
    "sg:city":"Rotterdam",
    "sg:orig_category":"Artsen - Huisartsen",
    "sg:phone":"+31 10 452 0330",
    "sg:postcode":"3061 HC",
    "sg:province":"Zuid-Holland",
    "wof:name":"Poelstra, F",
    "wof:placetype":"venue"
},
  "geometry": {"coordinates":[4.50434,51.927422],"type":"Point"}
}