{
  "type": "Feature",
  "properties": {
    "iso:country":"NL",
    "sg:address":"Zeelantln 51",
    "sg:city":"Utrecht",
    "sg:orig_category":"Meubelen",
    "sg:phone":"+31 30 267 1395",
    "sg:postcode":"3526 AK",
    "sg:province":"Utrecht",
    "wof:name":"Kastenstudio Utrecht Bv",
    "wof:placetype":"venue"
},
  "geometry": {"coordinates":[5.101557,52.062515],"type":"Point"}
}