{
  "type": "Feature",
  "properties": {
    "addr:full":"Zeelantln 51 Utrecht Utrecht 3526 AK",
    "addr:housenumber":"51",
    "addr:postcode":"3526 ak",
    "addr:street":"Zeelantln",
    "iso:country":"NL",
    "sg:address":"Zeelantln 51",
    "sg:city":"Utrecht",
    "sg:orig_category":"Meubelen",
    "sg:phone":"+31 30 267 1395",
    "sg:postcode":"3526 AK",
    "sg:province":"Utrecht",
    "wof:name":"Kastenstudio Utrecht Bv",
    "wof:placetype":"venue"
},
  "geometry": {"coordinates":[5.101557,52.062515],"type":"Point"}
}