{
  "type": "Feature",
  "properties": {
    "iso:country":"NL",
    "sg:address":"Kruisweg 44",
    "sg:city":"Marum",
    "sg:classifiers":[
        {
            "category":"Fast Food",
            "type":"Food & Drink"
        }
    ],
    "sg:phone":"+31 594 643 292",
    "sg:postcode":"9363 AE",
    "sg:province":"Groningen",
    "sg:tags":[
        "afhaal",
        "restaurant"
    ],
    "wof:name":"Msu",
    "wof:placetype":"venue"
},
  "geometry": {"coordinates":[6.280722,53.148739],"type":"Point"}
}