{
  "type": "Feature",
  "properties": {
    "addr:full":"Bierstraat 54 Deventer Overijssel 7416 AM",
    "addr:housenumber":"54",
    "addr:postcode":"7416",
    "addr:street":"Bierstraat",
    "iso:country":"NL",
    "sg:address":"Bierstraat 54",
    "sg:city":"Deventer",
    "sg:classifiers":[
        {
            "category":"Education",
            "subcategory":"Preschool",
            "type":"Public Place"
        }
    ],
    "sg:phone":"+31 570 624 634",
    "sg:postcode":"7416 AM",
    "sg:province":"Overijssel",
    "sg:tags":[
        "kleuteronderwijs",
        "basis-"
    ],
    "wof:name":"Interconfessionele Basisschool De Windroos",
    "wof:placetype":"venue"
},
  "geometry": {"coordinates":[6.168934,52.258457],"type":"Point"}
}