{
  "type": "Feature",
  "properties": {
    "addr:full":"Louis Armstrongweg 100 Almere NL. 1311 RL",
    "addr:housenumber":"100",
    "addr:postcode":"1311 rl",
    "addr:street":"Louis Armstrongweg;Nl.",
    "iso:country":"NL",
    "sg:address":"Louis Armstrongweg 100",
    "sg:city":"Almere",
    "sg:orig_category":"Beroepsorganisaties",
    "sg:phone":"+31 36 535 8500",
    "sg:postcode":"1311 RL",
    "sg:province":"NL.",
    "wof:name":"Fnv Horecabond",
    "wof:placetype":"venue"
},
  "geometry": {"coordinates":[5.187209,52.366798],"type":"Point"}
}