{
  "type": "Feature",
  "properties": {
    "addr:full":"Wilhelminastr 55 Vlagtwedde Groningen 9541 AN",
    "addr:housenumber":"55",
    "addr:postcode":"9541 an",
    "addr:street":"Wilhelminastr",
    "iso:country":"NL",
    "sg:address":"Wilhelminastr 55",
    "sg:city":"Vlagtwedde",
    "sg:orig_category":"Zonnebank- En Solariumcentra",
    "sg:phone":"+31 599 313 693",
    "sg:postcode":"9541 AN",
    "sg:province":"Groningen",
    "wof:name":"Marieanne Zonnehemelverhuur",
    "wof:placetype":"venue"
},
  "geometry": {"coordinates":[7.11348,53.025806],"type":"Point"}
}