{
  "type": "Feature",
  "properties": {
    "addr:full":"Dalsteindreef 50-52 Diemen Noord-Holland 1112 XC",
    "addr:housenumber":"50-52",
    "addr:postcode":"1112 xc",
    "addr:street":"Dalsteindreef",
    "iso:country":"NL",
    "sg:address":"Dalsteindreef 50-52",
    "sg:city":"Diemen",
    "sg:orig_category":"Actuarissen",
    "sg:phone":"+31 20 695 3031",
    "sg:postcode":"1112 XC",
    "sg:province":"Noord-Holland",
    "sg:website":"http://www.hewitt.com",
    "wof:name":"Heynis & Koelman Bv",
    "wof:placetype":"venue"
},
  "geometry": {"coordinates":[4.95469,52.329006],"type":"Point"}
}