{
  "type": "Feature",
  "properties": {
    "addr:full":"Bergweg Zuid 159 Bergschenhoek South Holland 2661 CT",
    "addr:housenumber":"159",
    "addr:postcode":"2661 ct",
    "addr:street":"Bergweg Zuid",
    "iso:country":"NL",
    "sg:address":"Bergweg Zuid 159",
    "sg:city":"Bergschenhoek",
    "sg:orig_category":"Hout Gh",
    "sg:phone":"+31 6 53121699",
    "sg:postcode":"2661 CT",
    "sg:province":"South Holland",
    "wof:name":"Doornbos Bergschenhoek Handels- En Transportbedr B",
    "wof:placetype":"venue"
},
  "geometry": {"coordinates":[4.497749,51.976006],"type":"Point"}
}