{
  "type": "Feature",
  "properties": {
    "addr:full":"Laurierstr 50 Haarlem Noord-Holland 2023 ND",
    "addr:housenumber":"50",
    "addr:postcode":"2023 nd",
    "addr:street":"Laurierstr",
    "iso:country":"NL",
    "sg:address":"Laurierstr 50",
    "sg:city":"Haarlem",
    "sg:orig_category":"Onderhoudswerken",
    "sg:phone":"+31 23 527 7193",
    "sg:postcode":"2023 ND",
    "sg:province":"Noord-Holland",
    "wof:name":"Mulder, A D",
    "wof:placetype":"venue"
},
  "geometry": {"coordinates":[4.632681,52.402843],"type":"Point"}
}