{
  "type": "Feature",
  "properties": {
    "iso:country":"NL",
    "sg:address":"Butselaar 6",
    "sg:city":"Oosterhout Nb",
    "sg:orig_category":"Goederenvervoer Over De Weg",
    "sg:phone":"+31 162 431 262",
    "sg:postcode":"4907 KM",
    "sg:province":"North Brabant",
    "wof:name":"Frank Van Aanhout",
    "wof:placetype":"venue"
},
  "geometry": {"coordinates":[4.8645,51.660522],"type":"Point"}
}