{
  "type": "Feature",
  "properties": {
    "addr:full":"Butselaar 6 Oosterhout Nb North Brabant 4907 KM",
    "addr:housenumber":"6;nb",
    "addr:postcode":"4907 km",
    "addr:street":"Butselaar",
    "iso:country":"NL",
    "sg:address":"Butselaar 6",
    "sg:city":"Oosterhout Nb",
    "sg:orig_category":"Goederenvervoer Over De Weg",
    "sg:phone":"+31 162 431 262",
    "sg:postcode":"4907 KM",
    "sg:province":"North Brabant",
    "wof:name":"Frank Van Aanhout",
    "wof:placetype":"venue"
},
  "geometry": {"coordinates":[4.8645,51.660522],"type":"Point"}
}