{
  "type": "Feature",
  "properties": {
    "addr:full":"Donkse Dreef 16-18 S Hertogenbosch North Brabant 5233 HE",
    "addr:housenumber":"16-18",
    "addr:postcode":"5233 he",
    "addr:street":"Donkse Dreef;S Hertogenbosch",
    "iso:country":"NL",
    "sg:address":"Donkse Dreef 16-18",
    "sg:city":"S Hertogenbosch",
    "sg:orig_category":"Scholen Voor Basisonderwijs",
    "sg:phone":"+31 73 645 0747",
    "sg:postcode":"5233 HE",
    "sg:province":"North Brabant",
    "wof:name":"Haren Rk, De",
    "wof:placetype":"venue"
},
  "geometry": {"coordinates":[5.321448,51.716351],"type":"Point"}
}