{
  "type": "Feature",
  "properties": {
    "addr:full":"Wethouder Nijhuisstraat 222 Enschede Overijssel 7545 NP",
    "addr:housenumber":"222",
    "addr:postcode":"7545 np",
    "addr:street":"Wethouder Nijhuisstraat",
    "iso:country":"NL",
    "sg:address":"Wethouder Nijhuisstraat 222",
    "sg:city":"Enschede",
    "sg:classifiers":[
        {
            "category":"Fast Food",
            "type":"Food & Drink"
        }
    ],
    "sg:phone":"+31 53 431 7636",
    "sg:postcode":"7545 NP",
    "sg:province":"Overijssel",
    "sg:tags":[
        "afhaal",
        "restaurant"
    ],
    "wof:name":"Snackbar Snackie",
    "wof:placetype":"venue"
},
  "geometry": {"coordinates":[6.863171,52.211544],"type":"Point"}
}