{
  "type": "Feature",
  "properties": {
    "addr:full":"Loostraat 63 Huissen Gelderland 6852 BC",
    "addr:housenumber":"63",
    "addr:postcode":"6852 bc",
    "addr:street":"Loostraat;Gelderland",
    "iso:country":"NL",
    "sg:address":"Loostraat 63",
    "sg:city":"Huissen",
    "sg:orig_category":"Bloemen And Planten Gh",
    "sg:phone":"+31 26 325 7696",
    "sg:postcode":"6852 BC",
    "sg:province":"Gelderland",
    "wof:name":"H.P. Lights Bv",
    "wof:placetype":"venue"
},
  "geometry": {"coordinates":[5.924803,51.942101],"type":"Point"}
}