{
  "type": "Feature",
  "properties": {
    "addr:full":"Verdamstraat 6 Leiden Zuid-Holland 2313 PN",
    "addr:housenumber":"6",
    "addr:postcode":"2313 pn",
    "addr:street":"Verdamstraat",
    "iso:country":"NL",
    "sg:address":"Verdamstraat 6",
    "sg:city":"Leiden",
    "sg:orig_category":"Meubelzaken, Woning- And Keukeninrichting",
    "sg:phone":"+31 71 514 2421",
    "sg:postcode":"2313 PN",
    "sg:province":"Zuid-Holland",
    "wof:name":"Colijn Meubelen Vof",
    "wof:placetype":"venue"
},
  "geometry": {"coordinates":[4.509471,52.155006],"type":"Point"}
}