{
  "type": "Feature",
  "properties": {
    "addr:full":"De Overtoom 4 Papendrecht Zuid-Holland 3353 HC",
    "addr:housenumber":"4",
    "addr:postcode":"3353 hc",
    "addr:street":"De Overtoom",
    "iso:country":"NL",
    "sg:address":"De Overtoom 4",
    "sg:city":"Papendrecht",
    "sg:orig_category":"Meel - Fabrieken En Groothandel",
    "sg:phone":"+31 78 641 4330",
    "sg:postcode":"3353 HC",
    "sg:province":"Zuid-Holland",
    "wof:name":"Plange, Georg",
    "wof:placetype":"venue"
},
  "geometry": {"coordinates":[4.685729,51.82613],"type":"Point"}
}