{
  "type": "Feature",
  "properties": {
    "addr:full":"G V Amstelstr 226 Hilversum Noord-Holland 1214 BE",
    "addr:housenumber":"226",
    "addr:postcode":"1214",
    "addr:street":"V Amstelstr",
    "iso:country":"NL",
    "sg:address":"G V Amstelstr 226",
    "sg:city":"Hilversum",
    "sg:orig_category":"Evenementenverzorging",
    "sg:phone":"+31 35 628 4840",
    "sg:postcode":"1214 BE",
    "sg:province":"Noord-Holland",
    "wof:name":"Delta",
    "wof:placetype":"venue"
},
  "geometry": {"coordinates":[5.1695,52.228565],"type":"Point"}
}