{
  "type": "Feature",
  "properties": {
    "addr:full":"Westdk 25 Middelharnis South Holland 3241 GT",
    "addr:housenumber":"25",
    "addr:postcode":"3241 gt",
    "addr:street":"Westdk",
    "iso:country":"NL",
    "sg:address":"Westdk 25",
    "sg:city":"Middelharnis",
    "sg:orig_category":"Kappers",
    "sg:phone":"+31 187 482 990",
    "sg:postcode":"3241 GT",
    "sg:province":"South Holland",
    "wof:name":"Jongejan",
    "wof:placetype":"venue"
},
  "geometry": {"coordinates":[4.1640539169,51.7597618103],"type":"Point"}
}