{
  "type": "Feature",
  "properties": {
    "addr:full":"Nieuwe Fellenoord 7 Eindhoven Noord-Brabant 5612 KB",
    "addr:housenumber":"7",
    "addr:postcode":"5612 kb",
    "addr:street":"Nieuwe Fellenoord",
    "iso:country":"NL",
    "sg:address":"Nieuwe Fellenoord 7",
    "sg:city":"Eindhoven",
    "sg:orig_category":"Overheidsdiensten",
    "sg:phone":"+31 40 243 5495",
    "sg:postcode":"5612 KB",
    "sg:province":"Noord-Brabant",
    "wof:name":"Woensel-Zuid Wijkcentrum",
    "wof:placetype":"venue"
},
  "geometry": {"coordinates":[5.4750552177,51.4475059509],"type":"Point"}
}