{
  "type": "Feature",
  "properties": {
    "addr:full":"O.L. Vrouwedijk 11A Waalre North Brabant 5581 BN",
    "addr:housenumber":"11a",
    "addr:postcode":"5581 bn",
    "addr:street":"O.L. Vrouwedijk",
    "iso:country":"NL",
    "sg:address":"O.L. Vrouwedijk 11A",
    "sg:city":"Waalre",
    "sg:orig_category":"Kantoorartikelen",
    "sg:phone":"+31 40 223 0708",
    "sg:postcode":"5581 BN",
    "sg:province":"North Brabant",
    "wof:name":"2-Show Bv",
    "wof:placetype":"venue"
},
  "geometry": {"coordinates":[5.4441127777,51.3906822205],"type":"Point"}
}