{
  "type": "Feature",
  "properties": {
    "addr:full":"Putterweg 17 Ermelo Gelderland 3851 GA",
    "addr:housenumber":"17",
    "addr:postcode":"3851 ga",
    "addr:street":"Putterweg;Gelderland",
    "iso:country":"NL",
    "sg:address":"Putterweg 17",
    "sg:city":"Ermelo",
    "sg:orig_category":"Hypotheken And Hypotheekbanken",
    "sg:phone":"+31 341 567 815",
    "sg:postcode":"3851 GA",
    "sg:province":"Gelderland",
    "wof:name":"De Hypotheekshop",
    "wof:placetype":"venue"
},
  "geometry": {"coordinates":[5.631777,52.299786],"type":"Point"}
}