{
  "type": "Feature",
  "properties": {
    "iso:country":"NL",
    "sg:address":"Prinsengracht 909",
    "sg:city":"Amsterdam",
    "sg:orig_category":"Vertaal- And Tolkenbureaus",
    "sg:phone":"+31 20 624 7635",
    "sg:postcode":"1017 KD",
    "sg:province":"Noord-Holland",
    "wof:name":"Jenny Spits Vertaalbureau",
    "wof:placetype":"venue"
},
  "geometry": {"coordinates":[4.890986,52.362568],"type":"Point"}
}