{
  "type": "Feature",
  "properties": {
    "iso:country":"NL",
    "sg:address":"F H G V Itersonln 12",
    "sg:city":"Oostvoorne",
    "sg:orig_category":"Verenigingen En Stichtingen",
    "sg:phone":"+31 181 484 067",
    "sg:postcode":"3233 EK",
    "sg:province":"Zuid-Holland",
    "wof:name":"Ehbo Oostvoorne/Tinte, Kon Ned Ver",
    "wof:placetype":"venue"
},
  "geometry": {"coordinates":[4.103859,51.913956],"type":"Point"}
}