{
  "type": "Feature",
  "properties": {
    "addr:full":"Broekhem 50 Valkenburg Lb Limburg 6301 HJ",
    "addr:housenumber":"50",
    "addr:postcode":"lb;6301 hj",
    "addr:street":"Broekhem",
    "iso:country":"NL",
    "sg:address":"Broekhem 50",
    "sg:city":"Valkenburg Lb",
    "sg:orig_category":"Verzekeringen - Verzekeringskantoren",
    "sg:phone":"+31 43 601 4837",
    "sg:postcode":"6301 HJ",
    "sg:province":"Limburg",
    "wof:name":"Haze, Bas",
    "wof:placetype":"venue"
},
  "geometry": {"coordinates":[5.82546,50.870495],"type":"Point"}
}