{
  "type": "Feature",
  "properties": {
    "addr:full":"Marguerite Yourcenarstr 7 Amsterdam Zuidoost Noord-Holland 1102 AJ",
    "addr:housenumber":"7",
    "addr:postcode":"zuidoost;1102 aj",
    "addr:street":"Marguerite Yourcenarstr",
    "iso:country":"NL",
    "sg:address":"Marguerite Yourcenarstr 7",
    "sg:city":"Amsterdam Zuidoost",
    "sg:orig_category":"Werk- And Beschermkleding Fab",
    "sg:phone":"+31 20 690 1804",
    "sg:postcode":"1102 AJ",
    "sg:province":"Noord-Holland",
    "wof:name":"Ban'S",
    "wof:placetype":"venue"
},
  "geometry": {"coordinates":[4.9507188797,52.3234596252],"type":"Point"}
}