{
  "type": "Feature",
  "properties": {
    "iso:country":"NL",
    "sg:address":"De Cuserstraat 83",
    "sg:city":"Amsterdam",
    "sg:classifiers":[
        {
            "category":"Shopping",
            "subcategory":"Gifts & Souvenirs",
            "type":"Retail Goods"
        }
    ],
    "sg:phone":"+31 20 661 1021",
    "sg:postcode":"1081 CN",
    "sg:province":"North Holland",
    "sg:tags":[
        "geschenken"
    ],
    "wof:name":"De Koloniaal",
    "wof:placetype":"venue"
},
  "geometry": {"coordinates":[4.859256,52.323708],"type":"Point"}
}