{
  "type": "Feature",
  "properties": {
    "addr:full":"Produktieweg 119 Wormerveer Noord-Holland 1521 NJ",
    "addr:housenumber":"119",
    "addr:postcode":"1521 nj",
    "addr:street":"Produktieweg",
    "iso:country":"NL",
    "sg:address":"Produktieweg 119",
    "sg:city":"Wormerveer",
    "sg:classifiers":[
        {
            "category":"Professional",
            "subcategory":"Accounting & Tax Preparation",
            "type":"Services"
        }
    ],
    "sg:phone":"+31 75 621 3111",
    "sg:postcode":"1521 NJ",
    "sg:province":"Noord-Holland",
    "sg:tags":[
        "accountant"
    ],
    "wof:name":"Grafiad Bv",
    "wof:placetype":"venue"
},
  "geometry": {"coordinates":[4.777627,52.506886],"type":"Point"}
}