{
  "type": "Feature",
  "properties": {
    "addr:full":"Zuidplein Hoog 537 Rotterdam Zuid-Holland 3083 BG",
    "addr:housenumber":"537",
    "addr:postcode":"3083",
    "addr:street":"Zuidplein Hoog",
    "iso:country":"NL",
    "sg:address":"Zuidplein Hoog 537",
    "sg:city":"Rotterdam",
    "sg:orig_category":"Herenmodezaken",
    "sg:phone":"+31 10 293 0051",
    "sg:postcode":"3083 BG",
    "sg:province":"Zuid-Holland",
    "wof:name":"Gebr. Coster Bv",
    "wof:placetype":"venue"
},
  "geometry": {"coordinates":[4.490093,51.887062],"type":"Point"}
}