{
  "type": "Feature",
  "properties": {
    "addr:full":"Aquamarynstraat 211 Hengelo Ov Overijssel 7554 NR",
    "addr:housenumber":"211",
    "addr:postcode":"7554 nr",
    "addr:street":"Aquamarynstraat;Ov",
    "iso:country":"NL",
    "sg:address":"Aquamarynstraat 211",
    "sg:city":"Hengelo Ov",
    "sg:orig_category":"Metaalwerken",
    "sg:phone":"+31 74 243 4383",
    "sg:postcode":"7554 NR",
    "sg:province":"Overijssel",
    "wof:name":"Plafond- En Wandsystemen Eissink Bv",
    "wof:placetype":"venue"
},
  "geometry": {"coordinates":[6.76553,52.238659],"type":"Point"}
}