{
  "type": "Feature",
  "properties": {
    "addr:full":"Heerlerbaan 127 Heerlen Limburg 6418 CC",
    "addr:housenumber":"127",
    "addr:postcode":"6418 cc",
    "addr:street":"Heerlerbaan",
    "iso:country":"NL",
    "sg:address":"Heerlerbaan 127",
    "sg:city":"Heerlen",
    "sg:orig_category":"Non-Classified Establishments",
    "sg:phone":"+31 45 560 0550",
    "sg:postcode":"6418 CC",
    "sg:province":"Limburg",
    "wof:name":"Santron Int Bv",
    "wof:placetype":"venue"
},
  "geometry": {"coordinates":[5.998089,50.869221],"type":"Point"}
}