{
  "type": "Feature",
  "properties": {
    "addr:full":"Stokery 28 Gorredyk Provincie Friesland 8401 EH",
    "addr:housenumber":"28",
    "addr:postcode":"8401 eh",
    "addr:street":"Stokery;Provincie Friesland",
    "iso:country":"NL",
    "sg:address":"Stokery 28",
    "sg:city":"Gorredyk",
    "sg:orig_category":"Organisatiebureaus",
    "sg:phone":"+31 513 466 890",
    "sg:postcode":"8401 EH",
    "sg:province":"Provincie Friesland",
    "wof:name":"Danza",
    "wof:placetype":"venue"
},
  "geometry": {"coordinates":[6.0663881302,53.0112304688],"type":"Point"}
}