{
  "type": "Feature",
  "properties": {
    "iso:country":"NL",
    "sg:address":"Parallelweg West 54",
    "sg:city":"Vlijmen",
    "sg:orig_category":"Boekhouders",
    "sg:phone":"+31 73 511 8951",
    "sg:postcode":"5251 JG",
    "sg:province":"Noord-Brabant",
    "wof:name":"Administratiekantoor De Rietvelden",
    "wof:placetype":"venue"
},
  "geometry": {"coordinates":[5.198661,51.693645],"type":"Point"}
}