{
  "type": "Feature",
  "properties": {
    "addr:full":"De Rede 1 Dronten NL. 8251 ER",
    "addr:housenumber":"1",
    "addr:postcode":"8251 er",
    "addr:street":"De Rede;Nl.",
    "iso:country":"NL",
    "sg:address":"De Rede 1",
    "sg:city":"Dronten",
    "sg:orig_category":"Overheidsdiensten",
    "sg:phone":"+31 321 388 911",
    "sg:postcode":"8251 ER",
    "sg:province":"NL.",
    "wof:name":"Gemeente Dronten",
    "wof:placetype":"venue"
},
  "geometry": {"coordinates":[5.7161607742,52.5245780945],"type":"Point"}
}