{
  "type": "Feature",
  "properties": {
    "addr:full":"Fatimaplein 6 Breda North Brabant 4835 BJ",
    "addr:housenumber":"6",
    "addr:postcode":"4835 bj",
    "addr:street":"Fatimaplein",
    "iso:country":"NL",
    "sg:address":"Fatimaplein 6",
    "sg:city":"Breda",
    "sg:orig_category":"Etaleurs And Showroominrichters",
    "sg:phone":"+31 76 565 7378",
    "sg:postcode":"4835 BJ",
    "sg:province":"North Brabant",
    "wof:name":"Vue Promoties",
    "wof:placetype":"venue"
},
  "geometry": {"coordinates":[4.791506,51.576004],"type":"Point"}
}