{
  "type": "Feature",
  "properties": {
    "addr:full":"Pasteurstraat 66 'S Gravenhage South Holland 2522 RM",
    "addr:housenumber":"66",
    "addr:postcode":"2522 rm",
    "addr:street":"Pasteurstraat;' S Gravenhage",
    "iso:country":"NL",
    "sg:address":"Pasteurstraat 66",
    "sg:city":"'S Gravenhage",
    "sg:orig_category":"Loodgieterswerk, Verwarming And Sanitaire Installaties",
    "sg:phone":"+31 70 395 1200",
    "sg:postcode":"2522 RM",
    "sg:province":"South Holland",
    "wof:name":"Jim Matla",
    "wof:placetype":"venue"
},
  "geometry": {"coordinates":[4.329801,52.062222],"type":"Point"}
}