{
  "type": "Feature",
  "properties": {
    "addr:full":"Dommelstr 37 Oss Noord-Brabant 5347 JK",
    "addr:housenumber":"37",
    "addr:postcode":"5347 jk",
    "addr:street":"Dommelstr",
    "iso:country":"NL",
    "sg:address":"Dommelstr 37",
    "sg:city":"Oss",
    "sg:orig_category":"Meubelen",
    "sg:phone":"+31 412 632 588",
    "sg:postcode":"5347 JK",
    "sg:province":"Noord-Brabant",
    "wof:name":"Pelser",
    "wof:placetype":"venue"
},
  "geometry": {"coordinates":[-77.235214,38.312599],"type":"Point"}
}