{
  "type": "Feature",
  "properties": {
    "addr:full":"Briklaan 32 Leek Groningen 9351 PM",
    "addr:housenumber":"32",
    "addr:postcode":"9351 pm",
    "addr:street":"Briklaan",
    "iso:country":"NL",
    "sg:address":"Briklaan 32",
    "sg:city":"Leek",
    "sg:orig_category":"Vertaal- And Tolkenbureaus",
    "sg:phone":"+31 594 515 184",
    "sg:postcode":"9351 PM",
    "sg:province":"Groningen",
    "wof:name":"I M Goeken-Ulriis",
    "wof:placetype":"venue"
},
  "geometry": {"coordinates":[6.375474,53.173561],"type":"Point"}
}