{
  "type": "Feature",
  "properties": {
    "addr:full":"Klokjeslaan 47 Maarssen Utrecht 3601 HC",
    "addr:housenumber":"47",
    "addr:postcode":"3601 hc",
    "addr:street":"Klokjeslaan",
    "iso:country":"NL",
    "sg:address":"Klokjeslaan 47",
    "sg:city":"Maarssen",
    "sg:orig_category":"Fruit And Groenten Gh",
    "sg:phone":"+31 346 562 689",
    "sg:postcode":"3601 HC",
    "sg:province":"Utrecht",
    "wof:name":"Oostveen'S Fruithandel",
    "wof:placetype":"venue"
},
  "geometry": {"coordinates":[5.039183,52.146927],"type":"Point"}
}