{
  "type": "Feature",
  "properties": {
    "addr:full":"W Barentszwg 22 Venlo Limburg 5928 LM",
    "addr:housenumber":"22",
    "addr:postcode":"5928 lm",
    "addr:street":"W",
    "iso:country":"NL",
    "sg:address":"W Barentszwg 22",
    "sg:city":"Venlo",
    "sg:orig_category":"Zoetwaren - Fabrieken En Groothandel",
    "sg:phone":"+31 77 323 2200",
    "sg:postcode":"5928 LM",
    "sg:province":"Limburg",
    "wof:name":"Zuid Nederland Bv",
    "wof:placetype":"venue"
},
  "geometry": {"coordinates":[6.088486,51.390327],"type":"Point"}
}