{
  "type": "Feature",
  "properties": {
    "addr:full":"De Lithse Ham 3K14 Lith Noord-Brabant 5397 GL",
    "addr:housenumber":"3k14",
    "addr:postcode":"5397 gl",
    "addr:street":"De Lithse Ham",
    "iso:country":"NL",
    "sg:address":"De Lithse Ham 3K14",
    "sg:city":"Lith",
    "sg:orig_category":"Kermisexploitatie",
    "sg:phone":"+31 6 53460538",
    "sg:postcode":"5397 GL",
    "sg:province":"Noord-Brabant",
    "wof:name":"Gerry Van Lith",
    "wof:placetype":"venue"
},
  "geometry": {"coordinates":[-82.170288,27.862659],"type":"Point"}
}