{
  "type": "Feature",
  "properties": {
    "addr:full":"De Mieden 19 Oenkerk Friesland 9062 HK",
    "addr:housenumber":"19",
    "addr:postcode":"9062 hk",
    "addr:street":"De Mieden",
    "iso:country":"NL",
    "sg:address":"De Mieden 19",
    "sg:city":"Oenkerk",
    "sg:orig_category":"Geluidsopnamen",
    "sg:phone":"+31 58 256 3697",
    "sg:postcode":"9062 HK",
    "sg:province":"Friesland",
    "wof:name":"Ace",
    "wof:placetype":"venue"
},
  "geometry": {"coordinates":[5.904298,53.248615],"type":"Point"}
}