{
  "type": "Feature",
  "properties": {
    "addr:full":"Melisselaar 1 Veghel Noord-Brabant 5467 BM",
    "addr:housenumber":"1",
    "addr:postcode":"5467 bm",
    "addr:street":"Melisselaar",
    "iso:country":"NL",
    "sg:address":"Melisselaar 1",
    "sg:city":"Veghel",
    "sg:orig_category":"Peuterspeelzalen",
    "sg:phone":"+31 413 343 468",
    "sg:postcode":"5467 BM",
    "sg:province":"Noord-Brabant",
    "wof:name":"Nijntje Pluis",
    "wof:placetype":"venue"
},
  "geometry": {"coordinates":[5.556102,51.620373],"type":"Point"}
}