{
  "type": "Feature",
  "properties": {
    "addr:full":"Industriewg 5 Meppel Provincie Drenthe 7944 HT",
    "addr:housenumber":"5",
    "addr:postcode":"7944 ht",
    "addr:street":"Industriewg;Provincie Drenthe",
    "iso:country":"NL",
    "sg:address":"Industriewg 5",
    "sg:city":"Meppel",
    "sg:orig_category":"Facilitaire Dienstverlening",
    "sg:phone":"+31 522 236 910",
    "sg:postcode":"7944 HT",
    "sg:province":"Provincie Drenthe",
    "wof:name":"Woonzorg Centrale",
    "wof:placetype":"venue"
},
  "geometry": {"coordinates":[6.181302,52.693268],"type":"Point"}
}