{
  "type": "Feature",
  "properties": {
    "iso:country":"NL",
    "sg:address":"Pr Ireneln 79",
    "sg:city":"Voorburg",
    "sg:orig_category":"Elektronica - Ontwikkeling En Groothandel",
    "sg:phone":"+31 70 386 0635",
    "sg:postcode":"2273 DH",
    "sg:province":"Zuid-Holland",
    "wof:name":"Made To Measure Electronics Bv",
    "wof:placetype":"venue"
},
  "geometry": {"coordinates":[4.357922,52.083782],"type":"Point"}
}