{
  "type": "Feature",
  "properties": {
    "addr:full":"Kloosterstr 31 Achthuizen South Holland 3256 AH",
    "addr:housenumber":"31",
    "addr:postcode":"3256 ah",
    "addr:street":"Kloosterstr",
    "iso:country":"NL",
    "sg:address":"Kloosterstr 31",
    "sg:city":"Achthuizen",
    "sg:orig_category":"Scholen Voor Basisonderwijs",
    "sg:phone":"+31 187 631 246",
    "sg:postcode":"3256 AH",
    "sg:province":"South Holland",
    "wof:name":"Achtsprong Rk Basisschool, De",
    "wof:placetype":"venue"
},
  "geometry": {"coordinates":[4.283143,51.686615],"type":"Point"}
}