{
  "type": "Feature",
  "properties": {
    "addr:full":"Molenveld 2 Hippolytushoef Noord-Holland 1777 HP",
    "addr:housenumber":"2",
    "addr:postcode":"1777 hp",
    "addr:street":"Molenveld",
    "iso:country":"NL",
    "sg:address":"Molenveld 2",
    "sg:city":"Hippolytushoef",
    "sg:orig_category":"Kinderopvang",
    "sg:phone":"+31 227 595 420",
    "sg:postcode":"1777 HP",
    "sg:province":"Noord-Holland",
    "sg:website":"http://www.catalpa.nl",
    "wof:name":"Landrotten, De",
    "wof:placetype":"venue"
},
  "geometry": {"coordinates":[4.951937,52.901585],"type":"Point"}
}