{
  "type": "Feature",
  "properties": {
    "addr:full":"Handelswg 7A Emmen Drenthe 7826 TC",
    "addr:housenumber":"7a",
    "addr:postcode":"7826 tc",
    "addr:street":"Handelswg",
    "iso:country":"NL",
    "sg:address":"Handelswg 7A",
    "sg:city":"Emmen",
    "sg:orig_category":"Koeriersdiensten",
    "sg:phone":"+31 591 624 682",
    "sg:postcode":"7826 TC",
    "sg:province":"Drenthe",
    "wof:name":"Quidel",
    "wof:placetype":"venue"
},
  "geometry": {"coordinates":[6.951637,52.775063],"type":"Point"}
}