{
  "type": "Feature",
  "properties": {
    "addr:full":"Overtoom 163D Amsterdam Noord-Holland 1054 HG",
    "addr:housenumber":"163d",
    "addr:postcode":"1054 hg",
    "addr:street":"Overtoom",
    "iso:country":"NL",
    "sg:address":"Overtoom 163D",
    "sg:city":"Amsterdam",
    "sg:orig_category":"Werving And Selectie Van Vast Personeel",
    "sg:phone":"+31 20 685 4223",
    "sg:postcode":"1054 HG",
    "sg:province":"Noord-Holland",
    "wof:name":"Drs. W. Bloemers",
    "wof:placetype":"venue"
},
  "geometry": {"coordinates":[4.8716578484,52.3616218567],"type":"Point"}
}