{
  "type": "Feature",
  "properties": {
    "addr:full":"Houtweg 4 Ter Aar Zuid-Holland 2461 GR",
    "addr:housenumber":"4",
    "addr:postcode":"aar;2461",
    "addr:street":"Houtweg;Ter",
    "iso:country":"NL",
    "sg:address":"Houtweg 4",
    "sg:city":"Ter Aar",
    "sg:orig_category":"Metaalbekleding And -Behandeling",
    "sg:phone":"+31 172 609 269",
    "sg:postcode":"2461 GR",
    "sg:province":"Zuid-Holland",
    "wof:name":"De Groot Vof",
    "wof:placetype":"venue"
},
  "geometry": {"coordinates":[4.712922,52.177288],"type":"Point"}
}