{
  "type": "Feature",
  "properties": {
    "addr:full":"Postbus 111 Beek Ubbergen Gelderland 6573 ZK",
    "addr:housenumber":"111",
    "addr:postcode":"6573",
    "addr:street":"Postbus;Zk",
    "iso:country":"NL",
    "sg:address":"Postbus 111",
    "sg:city":"Beek Ubbergen",
    "sg:orig_category":"Omroep",
    "sg:phone":"+31 481 434 343",
    "sg:postcode":"6573 ZK",
    "sg:province":"Gelderland",
    "sg:website":"http://www.wfmradio.nl",
    "wof:name":"Wfm Streekradio",
    "wof:placetype":"venue"
},
  "geometry": {"coordinates":[5.92779,51.831219],"type":"Point"}
}