{
  "type": "Feature",
  "properties": {
    "addr:full":"Middelwg 130 Uitgeest Noord-Holland 1911 EK",
    "addr:housenumber":"130",
    "addr:postcode":"1911 ek",
    "iso:country":"NL",
    "sg:address":"Middelwg 130",
    "sg:city":"Uitgeest",
    "sg:orig_category":"Bloemen En Planten",
    "sg:phone":"+31 251 312 608",
    "sg:postcode":"1911 EK",
    "sg:province":"Noord-Holland",
    "wof:name":"Middelpunt, 'T",
    "wof:placetype":"venue"
},
  "geometry": {"coordinates":[4.708628,52.522663],"type":"Point"}
}