{
  "type": "Feature",
  "properties": {
    "iso:country":"NL",
    "sg:address":"Viltmakersdonk 113",
    "sg:city":"Apeldoorn",
    "sg:orig_category":"Video - Faciliteiten En Producties",
    "sg:phone":"+31 55 533 6693",
    "sg:postcode":"7326 LJ",
    "sg:province":"Gelderland",
    "wof:name":"Always Productions",
    "wof:placetype":"venue"
},
  "geometry": {"coordinates":[6.008543,52.197189],"type":"Point"}
}