{
  "type": "Feature",
  "properties": {
    "iso:country":"NL",
    "sg:address":"De Beente 15",
    "sg:city":"Maastricht",
    "sg:orig_category":"Scholen Voor Basisonderwijs",
    "sg:phone":"+31 43 361 2916",
    "sg:postcode":"6229 AV",
    "sg:province":"Limburg",
    "wof:name":"Anne Frank School",
    "wof:placetype":"venue"
},
  "geometry": {"coordinates":[5.706393,50.831593],"type":"Point"}
}