{
  "type": "Feature",
  "properties": {
    "addr:full":"Heksenwaag 43 Breda North Brabant 4823 JT",
    "addr:housenumber":"43",
    "addr:postcode":"4823 jt",
    "addr:street":"Heksenwaag",
    "iso:country":"NL",
    "sg:address":"Heksenwaag 43",
    "sg:city":"Breda",
    "sg:orig_category":"Opticiens",
    "sg:phone":"+31 76 541 7138",
    "sg:postcode":"4823 JT",
    "sg:province":"North Brabant",
    "wof:name":"Hans Anders",
    "wof:placetype":"venue"
},
  "geometry": {"coordinates":[4.7444009781,51.6230010986],"type":"Point"}
}