{
  "type": "Feature",
  "properties": {
    "addr:full":"Wickenburgstr 162 Rotterdam Zuid-Holland 3077 TL",
    "addr:housenumber":"162",
    "addr:postcode":"3077 tl",
    "iso:country":"NL",
    "sg:address":"Wickenburgstr 162",
    "sg:city":"Rotterdam",
    "sg:orig_category":"Onderhoudswerken",
    "sg:phone":"+31 10 483 2488",
    "sg:postcode":"3077 TL",
    "sg:province":"Zuid-Holland",
    "wof:name":"Dam, J A Van",
    "wof:placetype":"venue"
},
  "geometry": {"coordinates":[4.563358,51.895672],"type":"Point"}
}