{
  "type": "Feature",
  "properties": {
    "addr:full":"De Stelling 1459 Lelystad NL. 8232 EM",
    "addr:postcode":"1459;8232 em",
    "addr:street":"De Stelling;Nl.",
    "iso:country":"NL",
    "sg:address":"De Stelling 1459",
    "sg:city":"Lelystad",
    "sg:orig_category":"Webdesign Bureaus",
    "sg:phone":"+31 320 249 089",
    "sg:postcode":"8232 EM",
    "sg:province":"NL.",
    "wof:name":"Artiststudio",
    "wof:placetype":"venue"
},
  "geometry": {"coordinates":[5.475315094,52.5128440857],"type":"Point"}
}