{
  "type": "Feature",
  "properties": {
    "addr:full":"Haarlemmerweg 8-10 Amsterdam Noord-Holland 1014 BE",
    "addr:housenumber":"8-10",
    "addr:postcode":"1014",
    "addr:street":"Haarlemmerweg",
    "iso:country":"NL",
    "sg:address":"Haarlemmerweg 8-10",
    "sg:city":"Amsterdam",
    "sg:orig_category":"Diverse Zakelijke Dienstverlening",
    "sg:phone":"+31 20 682 1753",
    "sg:postcode":"1014 BE",
    "sg:province":"Noord-Holland",
    "wof:name":"Setsupport Nederland",
    "wof:placetype":"venue"
},
  "geometry": {"coordinates":[4.874951,52.386051],"type":"Point"}
}