{
  "type": "Feature",
  "properties": {
    "addr:full":"Stationsstr 1 Scheemda Groningen 9679 EA",
    "addr:housenumber":"1",
    "addr:postcode":"9679 ea",
    "addr:street":"Stationsstr",
    "iso:country":"NL",
    "sg:address":"Stationsstr 1",
    "sg:city":"Scheemda",
    "sg:orig_category":"Artsen - Huisartsen",
    "sg:phone":"+31 597 591 250",
    "sg:postcode":"9679 EA",
    "sg:province":"Groningen",
    "wof:name":"Sobel En I M E Sobel-De Boer, J S",
    "wof:placetype":"venue"
},
  "geometry": {"coordinates":[6.971022,53.175117],"type":"Point"}
}