{
  "type": "Feature",
  "properties": {
    "addr:full":"De Veldoven 45 Hendrik Ido Ambacht South Holland 3342 GR",
    "addr:housenumber":"45",
    "addr:postcode":"3342",
    "addr:street":"De Veldoven",
    "iso:country":"NL",
    "sg:address":"De Veldoven 45",
    "sg:city":"Hendrik Ido Ambacht",
    "sg:orig_category":"Kantoorapparatuur Gh",
    "sg:phone":"+31 78 681 2934",
    "sg:postcode":"3342 GR",
    "sg:province":"South Holland",
    "wof:name":"Montec",
    "wof:placetype":"venue"
},
  "geometry": {"coordinates":[4.6212649345,51.8395652771],"type":"Point"}
}