{
  "type": "Feature",
  "properties": {
    "addr:full":"Roosmarynhof 41 Duivendrecht Noord-Holland 1115 DX",
    "addr:housenumber":"41",
    "addr:postcode":"1115 dx",
    "addr:street":"Roosmarynhof",
    "iso:country":"NL",
    "sg:address":"Roosmarynhof 41",
    "sg:city":"Duivendrecht",
    "sg:orig_category":"Video - Faciliteiten En Producties",
    "sg:phone":"+31 20 699 3262",
    "sg:postcode":"1115 DX",
    "sg:province":"Noord-Holland",
    "wof:name":"Holland Video Produkties",
    "wof:placetype":"venue"
},
  "geometry": {"coordinates":[4.934548,52.328754],"type":"Point"}
}