{
  "type": "Feature",
  "properties": {
    "iso:country":"NL",
    "sg:address":"Wouter Smitstraat 16",
    "sg:city":"Venhuizen",
    "sg:orig_category":"Juweliers",
    "sg:phone":"+31 228 541 500",
    "sg:postcode":"1606 XJ",
    "sg:province":"Noord-Holland",
    "wof:name":"J. Kaptijn",
    "wof:placetype":"venue"
},
  "geometry": {"coordinates":[5.217862,52.669037],"type":"Point"}
}