{
  "type": "Feature",
  "properties": {
    "addr:full":"Maasstr 2 Weert Limburg 6001 EC",
    "addr:housenumber":"2",
    "addr:postcode":"6001 ec",
    "addr:street":"Maasstr",
    "iso:country":"NL",
    "sg:address":"Maasstr 2",
    "sg:city":"Weert",
    "sg:orig_category":"Juweliers",
    "sg:phone":"+31 495 531 067",
    "sg:postcode":"6001 EC",
    "sg:province":"Limburg",
    "wof:name":"Siebel",
    "wof:placetype":"venue"
},
  "geometry": {"coordinates":[5.706568,51.253132],"type":"Point"}
}