{
  "type": "Feature",
  "properties": {
    "addr:full":"Schermerweg 95Ab Alkmaar Noord-Holland 1821 BG",
    "addr:housenumber":"95ab",
    "addr:postcode":"1821",
    "addr:street":"Schermerweg",
    "iso:country":"NL",
    "sg:address":"Schermerweg 95Ab",
    "sg:city":"Alkmaar",
    "sg:orig_category":"Schilderwerk",
    "sg:phone":"+31 72 515 2920",
    "sg:postcode":"1821 BG",
    "sg:province":"Noord-Holland",
    "wof:name":"T. Stoop",
    "wof:placetype":"venue"
},
  "geometry": {"coordinates":[4.766129,52.624058],"type":"Point"}
}