{
  "type": "Feature",
  "properties": {
    "addr:full":"De Donk 85 Zevenbergen Noord-Brabant 4761 JJ",
    "addr:housenumber":"85",
    "addr:postcode":"4761 jj",
    "addr:street":"De Donk",
    "iso:country":"NL",
    "sg:address":"De Donk 85",
    "sg:city":"Zevenbergen",
    "sg:orig_category":"Autorijscholen",
    "sg:phone":"+31 168 327 845",
    "sg:postcode":"4761 JJ",
    "sg:province":"Noord-Brabant",
    "wof:name":"Snijders",
    "wof:placetype":"venue"
},
  "geometry": {"coordinates":[4.601273,51.649803],"type":"Point"}
}