{
  "type": "Feature",
  "properties": {
    "addr:full":"Smaragdplein 226 Utrecht Utrecht 3523 EH",
    "addr:housenumber":"226",
    "addr:postcode":"3523 eh",
    "addr:street":"Smaragdplein",
    "iso:country":"NL",
    "sg:address":"Smaragdplein 226",
    "sg:city":"Utrecht",
    "sg:orig_category":"Zuivelproducten",
    "sg:phone":"+31 30 289 1002",
    "sg:postcode":"3523 EH",
    "sg:province":"Utrecht",
    "wof:name":"Den Besten Kaas",
    "wof:placetype":"venue"
},
  "geometry": {"coordinates":[5.12585,52.072708],"type":"Point"}
}