{
  "type": "Feature",
  "properties": {
    "addr:full":"Kapelstraat 68 Heeze Noord-Brabant 5591 HG",
    "addr:housenumber":"68",
    "addr:postcode":"5591 hg",
    "addr:street":"Kapelstraat",
    "iso:country":"NL",
    "sg:address":"Kapelstraat 68",
    "sg:city":"Heeze",
    "sg:classifiers":[
        {
            "category":"Fast Food",
            "type":"Food & Drink"
        }
    ],
    "sg:phone":"+31 40 226 4159",
    "sg:postcode":"5591 HG",
    "sg:province":"Noord-Brabant",
    "sg:tags":[
        "afhaal",
        "restaurant"
    ],
    "wof:name":"Chinees Indisch Restaurant De Chinese Muur",
    "wof:placetype":"venue"
},
  "geometry": {"coordinates":[5.580012,51.382164],"type":"Point"}
}