{
  "type": "Feature",
  "properties": {
    "addr:full":"F D Rooseveltstr 26 Groningen Groningen 9728 RT",
    "addr:housenumber":"26",
    "addr:postcode":"9728 rt",
    "addr:street":"F;Rooseveltstr",
    "iso:country":"NL",
    "sg:address":"F D Rooseveltstr 26",
    "sg:city":"Groningen",
    "sg:orig_category":"Vertalers",
    "sg:phone":"+31 50 525 6813",
    "sg:postcode":"9728 RT",
    "sg:province":"Groningen",
    "wof:name":"Vloedgraven-Volkel, K E",
    "wof:placetype":"venue"
},
  "geometry": {"coordinates":[6.55799,53.189995],"type":"Point"}
}