{
  "type": "Feature",
  "properties": {
    "addr:full":"Kerkplein 2 Stramproy Limburg 6039 GH",
    "addr:housenumber":"2",
    "addr:postcode":"6039 gh",
    "addr:street":"Kerkplein",
    "iso:country":"NL",
    "sg:address":"Kerkplein 2",
    "sg:city":"Stramproy",
    "sg:orig_category":"Banken And Kredietinstellingen",
    "sg:phone":"+31 495 561 924",
    "sg:postcode":"6039 GH",
    "sg:province":"Limburg",
    "wof:name":"Postkantoor",
    "wof:placetype":"venue"
},
  "geometry": {"coordinates":[5.72319,51.193096],"type":"Point"}
}