{
  "type": "Feature",
  "properties": {
    "iso:country":"NL",
    "sg:address":"Landauerln 26",
    "sg:city":"Leek",
    "sg:orig_category":"Adviesbureaus Bedrijfsorganisatie",
    "sg:phone":"+31 594 517 008",
    "sg:postcode":"9351 PP",
    "sg:province":"Groningen",
    "wof:name":"Oosterveld, Henny",
    "wof:placetype":"venue"
},
  "geometry": {"coordinates":[6.377481,53.175205],"type":"Point"}
}