{
  "type": "Feature",
  "properties": {
    "addr:full":"Onderlangs 2A Barendrecht Zuid-Holland 2991 EM",
    "addr:housenumber":"2a",
    "addr:postcode":"2991 em",
    "addr:street":"Onderlangs",
    "iso:country":"NL",
    "sg:address":"Onderlangs 2A",
    "sg:city":"Barendrecht",
    "sg:orig_category":"Advocaten And Juridische Adviseurs",
    "sg:phone":"+31 180 695 115",
    "sg:postcode":"2991 EM",
    "sg:province":"Zuid-Holland",
    "wof:name":"Vos Advocaten",
    "wof:placetype":"venue"
},
  "geometry": {"coordinates":[4.538064,51.855762],"type":"Point"}
}