{
  "type": "Feature",
  "properties": {
    "addr:full":"Klokwg 14 Rotterdam Zuid-Holland 3034 KK",
    "addr:housenumber":"14",
    "addr:postcode":"3034 kk",
    "addr:street":"Klokwg",
    "iso:country":"NL",
    "sg:address":"Klokwg 14",
    "sg:city":"Rotterdam",
    "sg:orig_category":"Luchtbehandelings- Apparaten",
    "sg:phone":"+31 10 413 3717",
    "sg:postcode":"3034 KK",
    "sg:province":"Zuid-Holland",
    "wof:name":"Pelgrim, K H",
    "wof:placetype":"venue"
},
  "geometry": {"coordinates":[4.497231,51.943802],"type":"Point"}
}