{
  "type": "Feature",
  "properties": {
    "iso:country":"NL",
    "sg:address":"Klokwg 14",
    "sg:city":"Rotterdam",
    "sg:orig_category":"Luchtbehandelings- Apparaten",
    "sg:phone":"+31 10 413 3717",
    "sg:postcode":"3034 KK",
    "sg:province":"Zuid-Holland",
    "wof:name":"Pelgrim, K H",
    "wof:placetype":"venue"
},
  "geometry": {"coordinates":[4.497231,51.943802],"type":"Point"}
}