{
  "type": "Feature",
  "properties": {
    "addr:full":"Willinkbeek 4 Zaandam Noord-Holland 1509 HV",
    "addr:housenumber":"4",
    "addr:postcode":"1509 hv",
    "addr:street":"Willinkbeek",
    "iso:country":"NL",
    "sg:address":"Willinkbeek 4",
    "sg:city":"Zaandam",
    "sg:orig_category":"Hypotheken And Hypotheekbanken",
    "sg:phone":"+31 75 617 8297",
    "sg:postcode":"1509 HV",
    "sg:province":"Noord-Holland",
    "wof:name":"Verzekeringsadvieskantoor B. Visser",
    "wof:placetype":"venue"
},
  "geometry": {"coordinates":[4.846834,52.468945],"type":"Point"}
}