{
  "type": "Feature",
  "properties": {
    "addr:full":"A Tasmanstr 61 Rotterdam Albrands Zuid-Holland 3165 AM",
    "addr:housenumber":"61;albrands",
    "addr:postcode":"3165",
    "addr:street":"Rotterdam",
    "iso:country":"NL",
    "sg:address":"A Tasmanstr 61",
    "sg:city":"Rotterdam Albrands",
    "sg:orig_category":"Adviesbureaus",
    "sg:phone":"+31 10 283 0259",
    "sg:postcode":"3165 AM",
    "sg:province":"Zuid-Holland",
    "wof:name":"Manfort Bv",
    "wof:placetype":"venue"
},
  "geometry": {"coordinates":[4.422494,51.869381],"type":"Point"}
}