{
  "type": "Feature",
  "properties": {
    "addr:full":"Osdorppln 256 Amsterdam Noord-Holland 1068 ER",
    "addr:housenumber":"256",
    "addr:postcode":"1068 er",
    "iso:country":"NL",
    "sg:address":"Osdorppln 256",
    "sg:city":"Amsterdam",
    "sg:orig_category":"Accountants - Administratie- Consulenten En -Kantoren",
    "sg:phone":"+31 20 410 8888",
    "sg:postcode":"1068 ER",
    "sg:province":"Noord-Holland",
    "sg:website":"http://www.deloitte.nl",
    "wof:name":"Deloitte & Touche",
    "wof:placetype":"venue"
},
  "geometry": {"coordinates":[4.805263,52.359352],"type":"Point"}
}