{
  "type": "Feature",
  "properties": {
    "iso:country":"NL",
    "sg:address":"Bremhorst 6",
    "sg:city":"St Oedenrode",
    "sg:classifiers":[
        {
            "category":"Sports & Exercise",
            "subcategory":"Stables",
            "type":"Entertainment"
        }
    ],
    "sg:phone":"+31 413 490 753",
    "sg:postcode":"5491 LR",
    "sg:province":"Noord-Brabant",
    "sg:tags":[
        "maneges"
    ],
    "wof:name":"Pijnhorst, De",
    "wof:placetype":"venue"
},
  "geometry": {"coordinates":[5.452391,51.580173],"type":"Point"}
}