{
  "type": "Feature",
  "properties": {
    "addr:full":"Verdistraat 70 'S Hertogenbosch Noord-Brabant 5216 XJ",
    "addr:housenumber":"70",
    "addr:postcode":"5216 xj",
    "addr:street":"Verdistraat;' S",
    "iso:country":"NL",
    "sg:address":"Verdistraat 70",
    "sg:city":"'S Hertogenbosch",
    "sg:orig_category":"Public Relationbureaus",
    "sg:phone":"+31 73 614 6137",
    "sg:postcode":"5216 XJ",
    "sg:province":"Noord-Brabant",
    "wof:name":"E.M.A.S. V.D. Bergh",
    "wof:placetype":"venue"
},
  "geometry": {"coordinates":[5.326463,51.68071],"type":"Point"}
}