{
  "type": "Feature",
  "properties": {
    "iso:country":"NL",
    "sg:address":"Lindeboomlaan 15",
    "sg:city":"Wolfheze",
    "sg:orig_category":"Technische Studies And Onderzoek",
    "sg:phone":"+31 26 482 1389",
    "sg:postcode":"6874 BN",
    "sg:province":"Gelderland",
    "wof:name":"Van Rij En Van Toledo",
    "wof:placetype":"venue"
},
  "geometry": {"coordinates":[5.788639,52.007626],"type":"Point"}
}