{
  "type": "Feature",
  "properties": {
    "addr:full":"Sloterweg 447 Badhoevedorp North Holland 1171 VE",
    "addr:housenumber":"447",
    "addr:postcode":"1171",
    "addr:street":"Sloterweg;Ve",
    "iso:country":"NL",
    "sg:address":"Sloterweg 447",
    "sg:city":"Badhoevedorp",
    "sg:orig_category":"Meubels And Huishoudapparatuur Gh",
    "sg:phone":"+31 20 659 8998",
    "sg:postcode":"1171 VE",
    "sg:province":"North Holland",
    "wof:name":"Rimas Trade International Bv",
    "wof:placetype":"venue"
},
  "geometry": {"coordinates":[4.761297,52.325741],"type":"Point"}
}