{
  "type": "Feature",
  "properties": {
    "addr:full":"Bedryfswg 12 Vriezenveen NL.08 7671 EG",
    "addr:housenumber":"12;nl.08",
    "addr:postcode":"7671 eg",
    "addr:street":"Bedryfswg",
    "iso:country":"NL",
    "sg:address":"Bedryfswg 12",
    "sg:city":"Vriezenveen",
    "sg:classifiers":[
        {
            "category":"Home & Garden",
            "subcategory":"Hardware",
            "type":"Retail Goods"
        }
    ],
    "sg:phone":"+31 546 562 270",
    "sg:postcode":"7671 EG",
    "sg:province":"NL.08",
    "sg:tags":[
        "machine",
        "-",
        "metaalbewerking"
    ],
    "wof:name":"Almi Bv",
    "wof:placetype":"venue"
},
  "geometry": {"coordinates":[6.602079,52.408829],"type":"Point"}
}