{
  "type": "Feature",
  "properties": {
    "addr:full":"Lysterbesoord 31 Diemen Noord-Holland 1112 EG",
    "addr:housenumber":"31",
    "addr:postcode":"1112 eg",
    "addr:street":"Lysterbesoord",
    "iso:country":"NL",
    "sg:address":"Lysterbesoord 31",
    "sg:city":"Diemen",
    "sg:orig_category":"Verenigingen En Stichtingen",
    "sg:phone":"+31 20 698 1888",
    "sg:postcode":"1112 EG",
    "sg:province":"Noord-Holland",
    "wof:name":"Suzuki Coup\u00e9 Gx Fanclub",
    "wof:placetype":"venue"
},
  "geometry": {"coordinates":[4.95393,52.337215],"type":"Point"}
}