{
  "type": "Feature",
  "properties": {
    "iso:country":"NL",
    "sg:address":"Bergstr 10",
    "sg:city":"Amsterdam",
    "sg:orig_category":"Fotoreportages",
    "sg:phone":"+31 20 622 0627",
    "sg:postcode":"1015 AV",
    "sg:province":"Noord-Holland",
    "wof:name":"Haaff, Maarten Van",
    "wof:placetype":"venue"
},
  "geometry": {"coordinates":[4.889548,52.375603],"type":"Point"}
}