{
  "type": "Feature",
  "properties": {
    "addr:full":"Wieksloterweg Oostzijde 41 Soest Utrecht 3766 LS",
    "addr:housenumber":"41",
    "addr:postcode":"3766 ls",
    "addr:street":"Wieksloterweg Oostzijde",
    "iso:country":"NL",
    "sg:address":"Wieksloterweg Oostzijde 41",
    "sg:city":"Soest",
    "sg:orig_category":"Loodgieterswerk, Verwarming And Sanitaire Installaties",
    "sg:phone":"+31 6 22360623",
    "sg:postcode":"3766 LS",
    "sg:province":"Utrecht",
    "wof:name":"R. Koppen",
    "wof:placetype":"venue"
},
  "geometry": {"coordinates":[5.269314,52.164524],"type":"Point"}
}