{
  "type": "Feature",
  "properties": {
    "addr:full":"Elegaststr 8 Oosterhout Nb North Brabant 4906 HJ",
    "addr:housenumber":"8;nb",
    "addr:postcode":"4906 hj",
    "addr:street":"Elegaststr",
    "iso:country":"NL",
    "sg:address":"Elegaststr 8",
    "sg:city":"Oosterhout Nb",
    "sg:orig_category":"Waterkoelers En Drinkwaterinstallaties",
    "sg:phone":"+31 162 430 111",
    "sg:postcode":"4906 HJ",
    "sg:province":"North Brabant",
    "sg:website":"http://www.homespring.nl",
    "wof:name":"Homespring Vof",
    "wof:placetype":"venue"
},
  "geometry": {"coordinates":[4.8396859169,51.652141571],"type":"Point"}
}