{
  "type": "Feature",
  "properties": {
    "addr:full":"Van Speijkstraat 2/135 Zandvoort Noord-Holland 2041 KL",
    "addr:housenumber":"2 / 135",
    "addr:postcode":"2041 kl",
    "addr:street":"Van Speijkstraat;Zandvoort",
    "iso:country":"NL",
    "sg:address":"Van Speijkstraat 2/135",
    "sg:city":"Zandvoort",
    "sg:orig_category":"Schilders",
    "sg:phone":"+31 6 21854336",
    "sg:postcode":"2041 KL",
    "sg:province":"Noord-Holland",
    "wof:name":"Geusebroek, Tom",
    "wof:placetype":"venue"
},
  "geometry": {"coordinates":[4.53121,52.377251],"type":"Point"}
}