{
  "type": "Feature",
  "properties": {
    "addr:full":"Wethouder Bankenstraat 8 Batenburg Gelderland 6634 KC",
    "addr:housenumber":"8",
    "addr:postcode":"6634 kc",
    "addr:street":"Wethouder Bankenstraat;Gelderland",
    "iso:country":"NL",
    "sg:address":"Wethouder Bankenstraat 8",
    "sg:city":"Batenburg",
    "sg:orig_category":"Levende Dieren Gh",
    "sg:phone":"+31 487 541 394",
    "sg:postcode":"6634 KC",
    "sg:province":"Gelderland",
    "wof:name":"Vof Van Haren",
    "wof:placetype":"venue"
},
  "geometry": {"coordinates":[5.618404,51.832535],"type":"Point"}
}