{
  "type": "Feature",
  "properties": {
    "addr:full":"Prinses Beatrixstraat 20 Zegveld Utrecht 3474 JW",
    "addr:housenumber":"20",
    "addr:postcode":"3474 jw",
    "addr:street":"Prinses Beatrixstraat",
    "iso:country":"NL",
    "sg:address":"Prinses Beatrixstraat 20",
    "sg:city":"Zegveld",
    "sg:orig_category":"Zuivelproducten",
    "sg:phone":"+31 348 692 027",
    "sg:postcode":"3474 JW",
    "sg:province":"Utrecht",
    "wof:name":"Vof W.P. Van Bemmel",
    "wof:placetype":"venue"
},
  "geometry": {"coordinates":[4.834149,52.115379],"type":"Point"}
}