{
  "type": "Feature",
  "properties": {
    "iso:country":"NL",
    "sg:address":"Braillestraat 29",
    "sg:city":"'S Gravenzande",
    "sg:orig_category":"Loodgieterswerk, Verwarming And Sanitaire Installaties",
    "sg:phone":"+31 174 440 675",
    "sg:postcode":"2691 HX",
    "sg:province":"South Holland",
    "wof:name":"Technisch Installatie Team",
    "wof:placetype":"venue"
},
  "geometry": {"coordinates":[4.180414,51.998459],"type":"Point"}
}