{
  "type": "Feature",
  "properties": {
    "addr:full":"Dorpsstr 12 St Willebrord Noord-Brabant 4711 NG",
    "addr:housenumber":"12",
    "addr:postcode":"4711 ng",
    "addr:street":"Dorpsstr",
    "iso:country":"NL",
    "sg:address":"Dorpsstr 12",
    "sg:city":"St Willebrord",
    "sg:orig_category":"Plafonds",
    "sg:phone":"+31 6 14489601",
    "sg:postcode":"4711 NG",
    "sg:province":"Noord-Brabant",
    "wof:name":"Wbr",
    "wof:placetype":"venue"
},
  "geometry": {"coordinates":[4.592243,51.545425],"type":"Point"}
}