{
  "type": "Feature",
  "properties": {
    "addr:full":"Goudenheuvel 15 'S Hertogenbosch Noord-Brabant 5234 GA",
    "addr:housenumber":"15",
    "addr:postcode":"5234 ga",
    "addr:street":"Goudenheuvel;' S",
    "iso:country":"NL",
    "sg:address":"Goudenheuvel 15",
    "sg:city":"'S Hertogenbosch",
    "sg:orig_category":"Loodgieterswerk, Verwarming And Sanitaire Installaties",
    "sg:phone":"+31 73 642 7555",
    "sg:postcode":"5234 GA",
    "sg:province":"Noord-Brabant",
    "wof:name":"Meweco Zuid Nederland",
    "wof:placetype":"venue"
},
  "geometry": {"coordinates":[5.284964,51.724354],"type":"Point"}
}