{
  "type": "Feature",
  "properties": {
    "addr:full":"Haagdk 4A Breda Noord-Brabant 4811 TT",
    "addr:housenumber":"4a",
    "addr:postcode":"4811 tt",
    "addr:street":"Haagdk",
    "iso:country":"NL",
    "sg:address":"Haagdk 4A",
    "sg:city":"Breda",
    "sg:orig_category":"Beeldende Kunstenaars",
    "sg:phone":"+31 76 514 1295",
    "sg:postcode":"4811 TT",
    "sg:province":"Noord-Brabant",
    "wof:name":"Mostart",
    "wof:placetype":"venue"
},
  "geometry": {"coordinates":[4.771088,51.588501],"type":"Point"}
}