{
  "type": "Feature",
  "properties": {
    "iso:country":"NL",
    "sg:address":"Ibisln 3",
    "sg:city":"Andyk",
    "sg:orig_category":"Begrafenisverzorging",
    "sg:phone":"+31 228 592 254",
    "sg:postcode":"1619 VP",
    "sg:province":"Noord-Holland",
    "wof:name":"Laatste Eer, De",
    "wof:placetype":"venue"
},
  "geometry": {"coordinates":[5.222525,52.744362],"type":"Point"}
}