{
  "type": "Feature",
  "properties": {
    "addr:full":"Halsterseweg 229 Bergen Op Zoom North Brabant 4613 AN",
    "addr:housenumber":"229",
    "addr:postcode":"4613 an",
    "addr:street":"Halsterseweg",
    "iso:country":"NL",
    "sg:address":"Halsterseweg 229",
    "sg:city":"Bergen Op Zoom",
    "sg:orig_category":"Verzekeringen",
    "sg:phone":"+31 164 235 063",
    "sg:postcode":"4613 AN",
    "sg:province":"North Brabant",
    "wof:name":"Assurantiekantoor M C P Matthee",
    "wof:placetype":"venue"
},
  "geometry": {"coordinates":[4.279736,51.503586],"type":"Point"}
}