{
  "type": "Feature",
  "properties": {
    "addr:full":"Brabantpln 28 Breda Noord-Brabant 4817 LR",
    "addr:housenumber":"28",
    "addr:postcode":"4817 lr",
    "addr:street":"Brabantpln",
    "iso:country":"NL",
    "sg:address":"Brabantpln 28",
    "sg:city":"Breda",
    "sg:orig_category":"Postkantoren",
    "sg:phone":"+31 76 521 4343",
    "sg:postcode":"4817 LR",
    "sg:province":"Noord-Brabant",
    "sg:website":"http://www.postkantoor.nl",
    "wof:name":"Postkantoor",
    "wof:placetype":"venue"
},
  "geometry": {"coordinates":[4.799347,51.590534],"type":"Point"}
}