{
  "type": "Feature",
  "properties": {
    "addr:full":"Stationspln 7 Heerhugowaard Noord-Holland 1703 WD",
    "addr:housenumber":"7",
    "addr:postcode":"1703 wd",
    "addr:street":"Stationspln",
    "iso:country":"NL",
    "sg:address":"Stationspln 7",
    "sg:city":"Heerhugowaard",
    "sg:orig_category":"Bloemen En Planten",
    "sg:phone":"+31 72 571 6285",
    "sg:postcode":"1703 WD",
    "sg:province":"Noord-Holland",
    "wof:name":"Stations Bloemen- En Koffieshop",
    "wof:placetype":"venue"
},
  "geometry": {"coordinates":[4.827522,52.665195],"type":"Point"}
}