{
  "type": "Feature",
  "properties": {
    "addr:full":"Schoolstr 152 Voorschoten Zuid-Holland 2251 BK",
    "addr:housenumber":"152",
    "addr:postcode":"2251 bk",
    "iso:country":"NL",
    "sg:address":"Schoolstr 152",
    "sg:city":"Voorschoten",
    "sg:orig_category":"Drogisterijen",
    "sg:phone":"+31 71 561 4685",
    "sg:postcode":"2251 BK",
    "sg:province":"Zuid-Holland",
    "wof:name":"K?hn",
    "wof:placetype":"venue"
},
  "geometry": {"coordinates":[4.445647,52.124905],"type":"Point"}
}