{
  "type": "Feature",
  "properties": {
    "addr:full":"Hallehuis 15 Delfzyl Groningen 9932 CC",
    "addr:housenumber":"15",
    "addr:postcode":"9932 cc",
    "addr:street":"Hallehuis",
    "iso:country":"NL",
    "sg:address":"Hallehuis 15",
    "sg:city":"Delfzyl",
    "sg:orig_category":"Persbureaus",
    "sg:phone":"+31 596 623 190",
    "sg:postcode":"9932 CC",
    "sg:province":"Groningen",
    "wof:name":"Wals, Yolanda",
    "wof:placetype":"venue"
},
  "geometry": {"coordinates":[6.892127,53.320023],"type":"Point"}
}