{
  "type": "Feature",
  "properties": {
    "addr:full":"Gronausestraat 1299 Enschede NL.08 7534 AK",
    "addr:housenumber":"1299",
    "addr:postcode":"7534 ak",
    "addr:street":"Gronausestraat",
    "iso:country":"NL",
    "sg:address":"Gronausestraat 1299",
    "sg:city":"Enschede",
    "sg:orig_category":"Bloemen And Planten",
    "sg:phone":"+31 53 461 1215",
    "sg:postcode":"7534 AK",
    "sg:province":"NL.08",
    "wof:name":"Bloemenhuis De Ruiter",
    "wof:placetype":"venue"
},
  "geometry": {"coordinates":[6.95548,52.21645],"type":"Point"}
}