{
  "type": "Feature",
  "properties": {
    "addr:full":"Roerdompstraat 26 Velden Limburg 5941 JL",
    "addr:housenumber":"26",
    "addr:postcode":"5941 jl",
    "addr:street":"Roerdompstraat",
    "iso:country":"NL",
    "sg:address":"Roerdompstraat 26",
    "sg:city":"Velden",
    "sg:orig_category":"Chemische Producten Gh",
    "sg:phone":"+31 77 472 1995",
    "sg:postcode":"5941 JL",
    "sg:province":"Limburg",
    "wof:name":"J. Beeks",
    "wof:placetype":"venue"
},
  "geometry": {"coordinates":[6.167303,51.408993],"type":"Point"}
}