{
  "type": "Feature",
  "properties": {
    "iso:country":"NL",
    "sg:address":"Jonker Fransstr 73",
    "sg:city":"Rotterdam",
    "sg:orig_category":"Verf En Lak",
    "sg:phone":"+31 10 412 7246",
    "sg:postcode":"3031 AN",
    "sg:province":"Zuid-Holland",
    "wof:name":"Kern Parket",
    "wof:placetype":"venue"
},
  "geometry": {"coordinates":[4.486458,51.926682],"type":"Point"}
}