{
  "type": "Feature",
  "properties": {
    "iso:country":"NL",
    "sg:address":"Oude Wand 31-33",
    "sg:city":"Zutphen",
    "sg:orig_category":"Verenigingen En Stichtingen",
    "sg:phone":"+31 575 511 826",
    "sg:postcode":"7201 LJ",
    "sg:province":"Gelderland",
    "wof:name":"Gelders Oudheidkundig Contact",
    "wof:placetype":"venue"
},
  "geometry": {"coordinates":[6.191525,52.140202],"type":"Point"}
}