{
  "type": "Feature",
  "properties": {
    "addr:full":"Het Witte Hek 2 Scherpenzeel Gld Gelderland 3925 BH",
    "addr:housenumber":"2",
    "addr:postcode":"3925 bh",
    "addr:street":"Het Witte Hek;Gld Gelderland",
    "iso:country":"NL",
    "sg:address":"Het Witte Hek 2",
    "sg:city":"Scherpenzeel Gld",
    "sg:orig_category":"Vaarscholen",
    "sg:phone":"+31 33 277 4868",
    "sg:postcode":"3925 BH",
    "sg:province":"Gelderland",
    "wof:name":"Maurik",
    "wof:placetype":"venue"
},
  "geometry": {"coordinates":[5.473869,52.078102],"type":"Point"}
}