{
  "type": "Feature",
  "properties": {
    "iso:country":"NL",
    "sg:address":"Loodswg 35",
    "sg:city":"Westknollendam",
    "sg:orig_category":"Drukkerijen",
    "sg:phone":"+31 75 622 3788",
    "sg:postcode":"1525 RH",
    "sg:province":"Noord-Holland",
    "wof:name":"Oza Vof",
    "wof:placetype":"venue"
},
  "geometry": {"coordinates":[4.77674,52.517303],"type":"Point"}
}