{
  "type": "Feature",
  "properties": {
    "iso:country":"NL",
    "sg:address":"Berenhoeksestraat 59",
    "sg:city":"Wijk En Aalburg",
    "sg:orig_category":"Opticiens",
    "sg:phone":"+31 416 692 069",
    "sg:postcode":"4261 KB",
    "sg:province":"Gelderland",
    "wof:name":"Kroon Optiek",
    "wof:placetype":"venue"
},
  "geometry": {"coordinates":[5.1248102188,51.7555770874],"type":"Point"}
}