{
  "type": "Feature",
  "properties": {
    "addr:full":"Ten Eysden 1 Geleen Limburg 6164 JL",
    "addr:housenumber":"1",
    "addr:postcode":"6164 jl",
    "addr:street":"Ten Eysden",
    "iso:country":"NL",
    "sg:address":"Ten Eysden 1",
    "sg:city":"Geleen",
    "sg:classifiers":[
        {
            "category":"Sports & Exercise",
            "subcategory":"Stables",
            "type":"Entertainment"
        }
    ],
    "sg:phone":"+31 46 474 3210",
    "sg:postcode":"6164 JL",
    "sg:province":"Limburg",
    "sg:tags":[
        "maneges"
    ],
    "wof:name":"Eijsden, Ten",
    "wof:placetype":"venue"
},
  "geometry": {"coordinates":[5.841052,50.960232],"type":"Point"}
}