{
  "type": "Feature",
  "properties": {
    "addr:full":"Okeghemlaan 31 Breda North Brabant 4837 AS",
    "addr:housenumber":"31",
    "addr:postcode":"4837 as",
    "addr:street":"Okeghemlaan",
    "iso:country":"NL",
    "sg:address":"Okeghemlaan 31",
    "sg:city":"Breda",
    "sg:orig_category":"Kappers",
    "sg:phone":"+31 76 565 7795",
    "sg:postcode":"4837 AS",
    "sg:province":"North Brabant",
    "wof:name":"Kapsalon Van Oeffelen",
    "wof:placetype":"venue"
},
  "geometry": {"coordinates":[4.7747159004,51.5704498291],"type":"Point"}
}