{
  "type": "Feature",
  "properties": {
    "addr:full":"Kerkstr 4 Schoonhoven Zuid-Holland 2871 EG",
    "addr:housenumber":"4",
    "addr:postcode":"2871 eg",
    "addr:street":"Kerkstr",
    "iso:country":"NL",
    "sg:address":"Kerkstr 4",
    "sg:city":"Schoonhoven",
    "sg:orig_category":"Hypotheken",
    "sg:phone":"+31 182 382 697",
    "sg:postcode":"2871 EG",
    "sg:province":"Zuid-Holland",
    "wof:name":"Optima",
    "wof:placetype":"venue"
},
  "geometry": {"coordinates":[4.849632,51.946339],"type":"Point"}
}