{
  "type": "Feature",
  "properties": {
    "addr:full":"Oude Kruisweg 168 Cruquius Noord-Holland 2142 EJ",
    "addr:housenumber":"168",
    "addr:postcode":"2142 ej",
    "addr:street":"Oude Kruisweg",
    "iso:country":"NL",
    "sg:address":"Oude Kruisweg 168",
    "sg:city":"Cruquius",
    "sg:orig_category":"Loodgieterswerk, Verwarming And Sanitaire Installaties",
    "sg:phone":"+31 23 528 5818",
    "sg:postcode":"2142 EJ",
    "sg:province":"Noord-Holland",
    "wof:name":"Johan Van Son",
    "wof:placetype":"venue"
},
  "geometry": {"coordinates":[4.639238,52.333931],"type":"Point"}
}