{
  "type": "Feature",
  "properties": {
    "addr:full":"Spetsebrugwg 4 Veelerveen Groningen 9566 TK",
    "addr:housenumber":"4",
    "addr:postcode":"9566 tk",
    "addr:street":"Spetsebrugwg",
    "iso:country":"NL",
    "sg:address":"Spetsebrugwg 4",
    "sg:city":"Veelerveen",
    "sg:orig_category":"Verenigingen En Stichtingen",
    "sg:phone":"+31 597 541 341",
    "sg:postcode":"9566 TK",
    "sg:province":"Groningen",
    "wof:name":"Teen Challenge De Spetsehoeve",
    "wof:placetype":"venue"
},
  "geometry": {"coordinates":[7.131042,53.042599],"type":"Point"}
}