{
  "type": "Feature",
  "properties": {
    "addr:full":"Midstr 126 Joure Friesland 8501 AV",
    "addr:housenumber":"126",
    "addr:postcode":"8501 av",
    "iso:country":"NL",
    "sg:address":"Midstr 126",
    "sg:city":"Joure",
    "sg:orig_category":"Zonweringen",
    "sg:phone":"+31 513 414 195",
    "sg:postcode":"8501 AV",
    "sg:province":"Friesland",
    "wof:name":"Brattinga",
    "wof:placetype":"venue"
},
  "geometry": {"coordinates":[5.798115,52.965977],"type":"Point"}
}