{
  "type": "Feature",
  "properties": {
    "addr:full":"Loerikseweg 6 Houten Utrecht 3991 AD",
    "addr:housenumber":"6",
    "addr:postcode":"3991 ad",
    "addr:street":"Loerikseweg",
    "iso:country":"NL",
    "sg:address":"Loerikseweg 6",
    "sg:city":"Houten",
    "sg:classifiers":[
        {
            "category":"Bakery",
            "type":"Food & Drink"
        }
    ],
    "sg:phone":"+31 30 637 1302",
    "sg:postcode":"3991 AD",
    "sg:province":"Utrecht",
    "sg:tags":[
        "brood",
        "banket"
    ],
    "wof:name":"Van Der Wielen Cv",
    "wof:placetype":"venue"
},
  "geometry": {"coordinates":[5.163017,52.027],"type":"Point"}
}