{
  "type": "Feature",
  "properties": {
    "addr:full":"Middenstraat 22 Beesd Gelderland 4153 AD",
    "addr:housenumber":"22",
    "addr:postcode":"4153 ad",
    "addr:street":"Middenstraat;Gelderland",
    "iso:country":"NL",
    "sg:address":"Middenstraat 22",
    "sg:city":"Beesd",
    "sg:classifiers":[
        {
            "category":"Fast Food",
            "type":"Food & Drink"
        }
    ],
    "sg:phone":"+31 345 681 432",
    "sg:postcode":"4153 AD",
    "sg:province":"Gelderland",
    "sg:tags":[
        "afhaal",
        "restaurant"
    ],
    "wof:name":"Cafetaria Het Plein",
    "wof:placetype":"venue"
},
  "geometry": {"coordinates":[5.194509,51.885368],"type":"Point"}
}