{
  "type": "Feature",
  "properties": {
    "addr:full":"Noordkade 82 Waddinxveen South Holland 2741 EZ",
    "addr:housenumber":"82",
    "addr:postcode":"2741 ez",
    "addr:street":"Noordkade",
    "iso:country":"NL",
    "sg:address":"Noordkade 82",
    "sg:city":"Waddinxveen",
    "sg:orig_category":"Kantoorartikelen",
    "sg:phone":"+31 182 612 516",
    "sg:postcode":"2741 EZ",
    "sg:province":"South Holland",
    "wof:name":"Meubelfabriek Vink Vof",
    "wof:placetype":"venue"
},
  "geometry": {"coordinates":[4.6614918709,52.0541343689],"type":"Point"}
}