{
  "type": "Feature",
  "properties": {
    "addr:full":"Koninginnew 6A Noordwijkerhout South Holland 2211 TA",
    "addr:housenumber":"6a",
    "addr:postcode":"2211 ta",
    "addr:street":"Koninginnew",
    "iso:country":"NL",
    "sg:address":"Koninginnew 6A",
    "sg:city":"Noordwijkerhout",
    "sg:orig_category":"Woningbouw- Verenigingen En -Stichtingen",
    "sg:phone":"+31 252 343 100",
    "sg:postcode":"2211 TA",
    "sg:province":"South Holland",
    "wof:name":"Antonius Van Padua, Sint",
    "wof:placetype":"venue"
},
  "geometry": {"coordinates":[4.4988040924,52.2640800476],"type":"Point"}
}