{
  "type": "Feature",
  "properties": {
    "addr:full":"Htg V Brabantln 98 Maastricht Limburg 6223 CK",
    "addr:housenumber":"98",
    "addr:postcode":"6223 ck",
    "addr:street":"Brabantln",
    "iso:country":"NL",
    "sg:address":"Htg V Brabantln 98",
    "sg:city":"Maastricht",
    "sg:orig_category":"Autorijscholen",
    "sg:phone":"+31 43 363 2425",
    "sg:postcode":"6223 CK",
    "sg:province":"Limburg",
    "wof:name":"Jeurissen, Willy",
    "wof:placetype":"venue"
},
  "geometry": {"coordinates":[5.68851,50.877769],"type":"Point"}
}