{
  "type": "Feature",
  "properties": {
    "addr:full":"Venneperstr 16 Nieuw Vennep Noord-Holland 2151 AR",
    "addr:housenumber":"16",
    "addr:postcode":"2151",
    "addr:street":"Venneperstr;Nieuw Vennep",
    "iso:country":"NL",
    "sg:address":"Venneperstr 16",
    "sg:city":"Nieuw Vennep",
    "sg:orig_category":"Kaas",
    "sg:phone":"+31 252 674 225",
    "sg:postcode":"2151 AR",
    "sg:province":"Noord-Holland",
    "wof:name":"Kad?",
    "wof:placetype":"venue"
},
  "geometry": {"coordinates":[4.6311559677,52.2646102905],"type":"Point"}
}