{
  "type": "Feature",
  "properties": {
    "addr:full":"Deeling 8 Roden Drenthe 9301 ZT",
    "addr:housenumber":"8",
    "addr:postcode":"9301 zt",
    "addr:street":"Deeling",
    "iso:country":"NL",
    "sg:address":"Deeling 8",
    "sg:city":"Roden",
    "sg:orig_category":"Kantoorartikelen",
    "sg:phone":"+31 50 501 4854",
    "sg:postcode":"9301 ZT",
    "sg:province":"Drenthe",
    "wof:name":"T.P.S",
    "wof:placetype":"venue"
},
  "geometry": {"coordinates":[6.4329447746,53.1370010376],"type":"Point"}
}