{
  "type": "Feature",
  "properties": {
    "addr:full":"Passage 17 Nieuwegein Utrecht 3431 LM",
    "addr:housenumber":"17",
    "addr:postcode":"3431 lm",
    "addr:street":"Passage",
    "iso:country":"NL",
    "sg:address":"Passage 17",
    "sg:city":"Nieuwegein",
    "sg:orig_category":"Huishoudapparatuur, Televisies And Radio'S",
    "sg:phone":"+31 30 604 8694",
    "sg:postcode":"3431 LM",
    "sg:province":"Utrecht",
    "wof:name":"Modern Electronics",
    "wof:placetype":"venue"
},
  "geometry": {"coordinates":[5.083553,52.02882],"type":"Point"}
}