{
  "type": "Feature",
  "properties": {
    "addr:full":"Sieverdingwg 5 Vragender Gelderland 7134 NH",
    "addr:housenumber":"5",
    "addr:postcode":"7134 nh",
    "addr:street":"Sieverdingwg;Gelderland",
    "iso:country":"NL",
    "sg:address":"Sieverdingwg 5",
    "sg:city":"Vragender",
    "sg:classifiers":[
        {
            "category":"Shopping",
            "subcategory":"Adult",
            "type":"Retail Goods"
        }
    ],
    "sg:phone":"+31 544 371 025",
    "sg:postcode":"7134 NH",
    "sg:province":"Gelderland",
    "sg:tags":[
        "lingerie",
        "en",
        "tricotage"
    ],
    "wof:name":"Tricot Koning",
    "wof:placetype":"venue"
},
  "geometry": {"coordinates":[6.612135,51.987198],"type":"Point"}
}