{
  "type": "Feature",
  "properties": {
    "iso:country":"NL",
    "sg:address":"West-Kruiskade 54",
    "sg:city":"Rotterdam",
    "sg:orig_category":"Bejaardeninstellingen And Serviceflats",
    "sg:phone":"+31 10 436 1488",
    "sg:postcode":"3014 AW",
    "sg:province":"South Holland",
    "wof:name":"Humanitas Centrum De Leeuwenhoek",
    "wof:placetype":"venue"
},
  "geometry": {"coordinates":[4.468266,51.920219],"type":"Point"}
}