{
  "type": "Feature",
  "properties": {
    "addr:full":"Utrechtsestr 10+12 S Gravenhage Zuid-Holland 2587 RC",
    "addr:housenumber":"10 + 12;gravenhage",
    "addr:postcode":"2587 rc",
    "addr:street":"Utrechtsestr;S",
    "iso:country":"NL",
    "sg:address":"Utrechtsestr 10+12",
    "sg:city":"S Gravenhage",
    "sg:classifiers":[
        {
            "category":"Travel",
            "subcategory":"Hotels & Motels",
            "type":"Entertainment"
        }
    ],
    "sg:phone":"+31 70 350 4359",
    "sg:postcode":"2587 RC",
    "sg:province":"Zuid-Holland",
    "wof:name":"Wilhelmina",
    "wof:placetype":"venue"
},
  "geometry": {"coordinates":[4.29118,52.112942],"type":"Point"}
}