{
  "type": "Feature",
  "properties": {
    "addr:full":"Lamadreef 2 Utrecht Utrecht 3563 EW",
    "addr:housenumber":"2",
    "addr:postcode":"3563 ew",
    "addr:street":"Lamadreef",
    "iso:country":"NL",
    "sg:address":"Lamadreef 2",
    "sg:city":"Utrecht",
    "sg:orig_category":"Onderhoudswerken",
    "sg:phone":"+31 30 261 0065",
    "sg:postcode":"3563 EW",
    "sg:province":"Utrecht",
    "wof:name":"Geest, R Van De",
    "wof:placetype":"venue"
},
  "geometry": {"coordinates":[5.100095,52.119522],"type":"Point"}
}