{
  "type": "Feature",
  "properties": {
    "iso:country":"NL",
    "sg:address":"Noorderstationsstraat 32",
    "sg:city":"Zwaagwesteinde",
    "sg:orig_category":"Glaszetten",
    "sg:phone":"+31 511 445 647",
    "sg:postcode":"9271 CK",
    "sg:province":"Friesland",
    "wof:name":"Reitsma'S Glaszetters Bedrijf",
    "wof:placetype":"venue"
},
  "geometry": {"coordinates":[6.037347,53.251644],"type":"Point"}
}