{
  "type": "Feature",
  "properties": {
    "addr:full":"Dalem 10 Hapert Noord-Brabant 5527 JG",
    "addr:housenumber":"10",
    "addr:postcode":"5527 jg",
    "addr:street":"Dalem",
    "iso:country":"NL",
    "sg:address":"Dalem 10",
    "sg:city":"Hapert",
    "sg:orig_category":"Boekhouders",
    "sg:phone":"+31 497 383 137",
    "sg:postcode":"5527 JG",
    "sg:province":"Noord-Brabant",
    "wof:name":"Blox International Bv/B.M.C. Blox Man. C",
    "wof:placetype":"venue"
},
  "geometry": {"coordinates":[5.257965,51.351967],"type":"Point"}
}