{
  "type": "Feature",
  "properties": {
    "iso:country":"NL",
    "sg:address":"Kast Erensteinstr 49",
    "sg:city":"Maastricht",
    "sg:orig_category":"Artsen - Huisartsen",
    "sg:phone":"+31 43 363 4964",
    "sg:postcode":"6222 VH",
    "sg:province":"Limburg",
    "wof:name":"Hendriks, R A J",
    "wof:placetype":"venue"
},
  "geometry": {"coordinates":[5.714712,50.863331],"type":"Point"}
}