{
  "type": "Feature",
  "properties": {
    "addr:full":"Melanendreef 121 Bergen Op Zoom Noord-Brabant 4614 GK",
    "addr:housenumber":"121",
    "addr:postcode":"4614 gk",
    "addr:street":"Melanendreef",
    "iso:country":"NL",
    "sg:address":"Melanendreef 121",
    "sg:city":"Bergen Op Zoom",
    "sg:orig_category":"Behangers",
    "sg:phone":"+31 164 235 492",
    "sg:postcode":"4614 GK",
    "sg:province":"Noord-Brabant",
    "wof:name":"Wouts, J M",
    "wof:placetype":"venue"
},
  "geometry": {"coordinates":[4.287726,51.511097],"type":"Point"}
}