{
  "type": "Feature",
  "properties": {
    "addr:full":"Schiedamsesngl 137139 Rotterdam South Holland 3012 BA",
    "addr:housenumber":"137139",
    "addr:postcode":"3012 ba",
    "iso:country":"NL",
    "sg:address":"Schiedamsesngl 137139",
    "sg:city":"Rotterdam",
    "sg:orig_category":"Discotheken",
    "sg:phone":"+31 10 414 1486",
    "sg:postcode":"3012 BA",
    "sg:province":"South Holland",
    "wof:name":"Gay-Palace",
    "wof:placetype":"venue"
},
  "geometry": {"coordinates":[4.4798,51.914951],"type":"Point"}
}