{
  "type": "Feature",
  "properties": {
    "iso:country":"NL",
    "sg:address":"De Korenaar 15",
    "sg:city":"Oirschot",
    "sg:orig_category":"Goederenvervoer Over De Weg",
    "sg:phone":"+31 499 571 151",
    "sg:postcode":"5688 TS",
    "sg:province":"Noord-Brabant",
    "wof:name":"Van Hooff",
    "wof:placetype":"venue"
},
  "geometry": {"coordinates":[5.315351,51.509136],"type":"Point"}
}