{
  "type": "Feature",
  "properties": {
    "iso:country":"NL",
    "sg:address":"Sleutelbloemstraat 42",
    "sg:city":"Apeldoorn",
    "sg:orig_category":"Autokeuringen",
    "sg:phone":"+31 55 366 1562",
    "sg:postcode":"7322 AK",
    "sg:province":"Gelderland",
    "wof:name":"Transure Mobility Assistance Bv",
    "wof:placetype":"venue"
},
  "geometry": {"coordinates":[5.976395,52.227562],"type":"Point"}
}