{
  "type": "Feature",
  "properties": {
    "iso:country":"NL",
    "sg:address":"Oosterpark 3",
    "sg:city":"Amsterdam",
    "sg:orig_category":"Boekhouders",
    "sg:phone":"+31 20 692 1413",
    "sg:postcode":"1091 AC",
    "sg:province":"Noord-Holland",
    "wof:name":"Koop.Ver. Veilig Vervoer Ua",
    "wof:placetype":"venue"
},
  "geometry": {"coordinates":[4.915736,52.360222],"type":"Point"}
}