{
  "type": "Feature",
  "properties": {
    "addr:full":"Achterstraat 19 Hattem Gelderland 8051 GA",
    "addr:housenumber":"19",
    "addr:postcode":"8051 ga",
    "addr:street":"Achterstraat;Gelderland",
    "iso:country":"NL",
    "sg:address":"Achterstraat 19",
    "sg:city":"Hattem",
    "sg:orig_category":"Kappers",
    "sg:phone":"+31 38 444 3098",
    "sg:postcode":"8051 GA",
    "sg:province":"Gelderland",
    "wof:name":"Dames-/Herenkapsalon Young Style",
    "wof:placetype":"venue"
},
  "geometry": {"coordinates":[6.0680060387,52.4749794006],"type":"Point"}
}