{
  "type": "Feature",
  "properties": {
    "addr:full":"Lange Bunder 99 Bavel North Brabant 4854 MB",
    "addr:housenumber":"99",
    "addr:postcode":"4854 mb",
    "addr:street":"Lange Bunder",
    "iso:country":"NL",
    "sg:address":"Lange Bunder 99",
    "sg:city":"Bavel",
    "sg:orig_category":"Boekhouders",
    "sg:phone":"+31 161 431 845",
    "sg:postcode":"4854 MB",
    "sg:province":"North Brabant",
    "wof:name":"Swolfs Administraties & Belastingzaken",
    "wof:placetype":"venue"
},
  "geometry": {"coordinates":[4.831632,51.571285],"type":"Point"}
}