{
  "type": "Feature",
  "properties": {
    "addr:full":"Rietbaan 8 Capelle Aan Den Ijssel Zuid-Holland 2908 LP",
    "addr:housenumber":"8",
    "addr:postcode":"aan den ijssel;2908 lp",
    "addr:street":"Rietbaan",
    "iso:country":"NL",
    "sg:address":"Rietbaan 8",
    "sg:city":"Capelle Aan Den Ijssel",
    "sg:orig_category":"Werving And Selectie Van Vast Personeel",
    "sg:phone":"+31 10 264 0320",
    "sg:postcode":"2908 LP",
    "sg:province":"Zuid-Holland",
    "wof:name":"Ktg Diensten Bv",
    "wof:placetype":"venue"
},
  "geometry": {"coordinates":[4.5773282051,51.958240509],"type":"Point"}
}