{
  "type": "Feature",
  "properties": {
    "addr:full":"Swadenburgerdam 19 Zwammerdam Zuid-Holland 2471 AR",
    "addr:housenumber":"19",
    "addr:postcode":"2471",
    "addr:street":"Swadenburgerdam",
    "iso:country":"NL",
    "sg:address":"Swadenburgerdam 19",
    "sg:city":"Zwammerdam",
    "sg:orig_category":"Meubelstoffering",
    "sg:phone":"+31 172 615 630",
    "sg:postcode":"2471 AR",
    "sg:province":"Zuid-Holland",
    "wof:name":"Karin",
    "wof:placetype":"venue"
},
  "geometry": {"coordinates":[4.726967,52.106323],"type":"Point"}
}