{
  "type": "Feature",
  "properties": {
    "addr:full":"Veerman 70 Beuningen Gld Gelderland 6641 GJ",
    "addr:housenumber":"70",
    "addr:postcode":"6641 gj",
    "addr:street":"Veerman",
    "iso:country":"NL",
    "sg:address":"Veerman 70",
    "sg:city":"Beuningen Gld",
    "sg:classifiers":[
        {
            "category":"Education",
            "subcategory":"Preschool",
            "type":"Public Place"
        }
    ],
    "sg:phone":"+31 24 677 2086",
    "sg:postcode":"6641 GJ",
    "sg:province":"Gelderland",
    "sg:tags":[
        "kleuteronderwijs",
        "basis-"
    ],
    "wof:name":"Openbare Basisschool Achtsprong",
    "wof:placetype":"venue"
},
  "geometry": {"coordinates":[5.76362,51.860043],"type":"Point"}
}