{
  "type": "Feature",
  "properties": {
    "addr:full":"J Kluitstr 2 Spykenisse Zuid-Holland 3201 KW",
    "addr:housenumber":"2",
    "addr:postcode":"spykenisse;3201 kw",
    "iso:country":"NL",
    "sg:address":"J Kluitstr 2",
    "sg:city":"Spykenisse",
    "sg:orig_category":"Fotoreportages",
    "sg:phone":"+31 181 633 315",
    "sg:postcode":"3201 KW",
    "sg:province":"Zuid-Holland",
    "wof:name":"Jan F\u00e4hmel",
    "wof:placetype":"venue"
},
  "geometry": {"coordinates":[4.313188,51.848576],"type":"Point"}
}