{
  "type": "Feature",
  "properties": {
    "iso:country":"NL",
    "sg:address":"Industriewg 15A",
    "sg:city":"Groesbeek",
    "sg:classifiers":[
        {
            "category":"Retail",
            "subcategory":"Auto Repair",
            "type":"Services"
        }
    ],
    "sg:phone":"+31 24 397 7478",
    "sg:postcode":"6562 AP",
    "sg:province":"Gelderland",
    "sg:tags":[
        "garage"
    ],
    "wof:name":"Douwe",
    "wof:placetype":"venue"
},
  "geometry": {"coordinates":[5.941882,51.776817],"type":"Point"}
}