{
  "type": "Feature",
  "properties": {
    "addr:full":"Schapenkamp 188 Hilversum Noord-Holland 1211 PB",
    "addr:housenumber":"188",
    "addr:postcode":"1211 pb",
    "addr:street":"Schapenkamp",
    "iso:country":"NL",
    "sg:address":"Schapenkamp 188",
    "sg:city":"Hilversum",
    "sg:orig_category":"Loodgieters- And Verwarmingsmateriaal Gh",
    "sg:phone":"+31 35 628 0654",
    "sg:postcode":"1211 PB",
    "sg:province":"Noord-Holland",
    "wof:name":"Warmteservice Hilversum Bv",
    "wof:placetype":"venue"
},
  "geometry": {"coordinates":[5.180792,52.224697],"type":"Point"}
}