{
  "type": "Feature",
  "properties": {
    "iso:country":"NL",
    "sg:address":"Doorzwin 2462",
    "sg:city":"Den Helder",
    "sg:orig_category":"Adviesbureaus Bedrijfsorganisatie",
    "sg:phone":"+31 223 644 694",
    "sg:postcode":"1788 KP",
    "sg:province":"Noord-Holland",
    "wof:name":"Eikelenboom, W",
    "wof:placetype":"venue"
},
  "geometry": {"coordinates":[4.749692,52.890263],"type":"Point"}
}