{
  "type": "Feature",
  "properties": {
    "addr:full":"De Laagt 6 Maarn Utrecht 3951 KC",
    "addr:housenumber":"6",
    "addr:postcode":"3951 kc",
    "addr:street":"De Laagt",
    "iso:country":"NL",
    "sg:address":"De Laagt 6",
    "sg:city":"Maarn",
    "sg:orig_category":"Beeldende Kunstenaars",
    "sg:phone":"+31 343 442 898",
    "sg:postcode":"3951 KC",
    "sg:province":"Utrecht",
    "wof:name":"Haas, J De",
    "wof:placetype":"venue"
},
  "geometry": {"coordinates":[5.344834,52.082458],"type":"Point"}
}