{
  "type": "Feature",
  "properties": {
    "iso:country":"NL",
    "sg:address":"Schoutenstraatje 16",
    "sg:city":"Venray",
    "sg:orig_category":"Damesmodezaken",
    "sg:phone":"+31 478 583 422",
    "sg:postcode":"5801 BS",
    "sg:province":"Limburg",
    "wof:name":"Oda Mode",
    "wof:placetype":"venue"
},
  "geometry": {"coordinates":[5.975385,51.526371],"type":"Point"}
}