{
  "type": "Feature",
  "properties": {
    "addr:full":"Schoutenstraatje 16 Venray Limburg 5801 BS",
    "addr:housenumber":"16",
    "addr:postcode":"5801 bs",
    "addr:street":"Schoutenstraatje",
    "iso:country":"NL",
    "sg:address":"Schoutenstraatje 16",
    "sg:city":"Venray",
    "sg:orig_category":"Damesmodezaken",
    "sg:phone":"+31 478 583 422",
    "sg:postcode":"5801 BS",
    "sg:province":"Limburg",
    "wof:name":"Oda Mode",
    "wof:placetype":"venue"
},
  "geometry": {"coordinates":[5.975385,51.526371],"type":"Point"}
}