{
  "type": "Feature",
  "properties": {
    "addr:full":"Wijngaardplein 13 Eindhoven Noord-Brabant 5632 MA",
    "addr:housenumber":"13",
    "addr:postcode":"5632 ma",
    "addr:street":"Wijngaardplein",
    "iso:country":"NL",
    "sg:address":"Wijngaardplein 13",
    "sg:city":"Eindhoven",
    "sg:orig_category":"Discountwinkels",
    "sg:phone":"+31 40 242 9864",
    "sg:postcode":"5632 MA",
    "sg:province":"Noord-Brabant",
    "wof:name":"Wilgers Textiel",
    "wof:placetype":"venue"
},
  "geometry": {"coordinates":[5.49314,51.477036],"type":"Point"}
}