{
  "type": "Feature",
  "properties": {
    "addr:full":"Oranjestraat 8 Ijzendijke Zeeland 4515 CA",
    "addr:housenumber":"8",
    "addr:postcode":"4515 ca",
    "addr:street":"Oranjestraat",
    "iso:country":"NL",
    "sg:address":"Oranjestraat 8",
    "sg:city":"Ijzendijke",
    "sg:orig_category":"Hypotheken And Hypotheekbanken",
    "sg:phone":"+31 117 301 159",
    "sg:postcode":"4515 CA",
    "sg:province":"Zeeland",
    "wof:name":"Regiobank",
    "wof:placetype":"venue"
},
  "geometry": {"coordinates":[3.613686,51.320175],"type":"Point"}
}