{
  "type": "Feature",
  "properties": {
    "addr:full":"Postbus 9048 Utrecht Utrecht 3506 GA",
    "addr:housenumber":"9048",
    "addr:postcode":"3506 ga",
    "addr:street":"Postbus",
    "iso:country":"NL",
    "sg:address":"Postbus 9048",
    "sg:city":"Utrecht",
    "sg:orig_category":"Adviesbureaus",
    "sg:phone":"+31 30 276 1582",
    "sg:postcode":"3506 GA",
    "sg:province":"Utrecht",
    "wof:name":"Aev",
    "wof:placetype":"venue"
},
  "geometry": {"coordinates":[5.12289,52.091],"type":"Point"}
}