{
  "type": "Feature",
  "properties": {
    "addr:full":"Rochussenstraat 327 Rotterdam Zuid-Holland 3023 DG",
    "addr:housenumber":"327",
    "addr:postcode":"3023 dg",
    "addr:street":"Rochussenstraat",
    "iso:country":"NL",
    "sg:address":"Rochussenstraat 327",
    "sg:city":"Rotterdam",
    "sg:orig_category":"Boekhouders",
    "sg:phone":"+31 10 425 4588",
    "sg:postcode":"3023 DG",
    "sg:province":"Zuid-Holland",
    "wof:name":"Administratiekantoor K.M. Van Tuyl Bv",
    "wof:placetype":"venue"
},
  "geometry": {"coordinates":[4.454266,51.909111],"type":"Point"}
}