{
  "type": "Feature",
  "properties": {
    "addr:full":"Dorsvloer 10 Wierden NL.08 7641 DZ",
    "addr:housenumber":"10;nl.08",
    "addr:postcode":"7641 dz",
    "addr:street":"Dorsvloer",
    "iso:country":"NL",
    "sg:address":"Dorsvloer 10",
    "sg:city":"Wierden",
    "sg:orig_category":"Kinderopvang",
    "sg:phone":"+31 546 577 649",
    "sg:postcode":"7641 DZ",
    "sg:province":"NL.08",
    "wof:name":"Blauwe Walrus, De",
    "wof:placetype":"venue"
},
  "geometry": {"coordinates":[6.60222,52.364552],"type":"Point"}
}