{
  "type": "Feature",
  "properties": {
    "addr:full":"Hennepstr 6A Riethoven Noord-Brabant 5561 AC",
    "addr:housenumber":"6a",
    "addr:postcode":"5561 ac",
    "addr:street":"Hennepstr",
    "iso:country":"NL",
    "sg:address":"Hennepstr 6A",
    "sg:city":"Riethoven",
    "sg:orig_category":"Verenigingsgebouwen",
    "sg:phone":"+31 40 201 9330",
    "sg:postcode":"5561 AC",
    "sg:province":"Noord-Brabant",
    "wof:name":"Rietstek, De",
    "wof:placetype":"venue"
},
  "geometry": {"coordinates":[5.387761,51.354237],"type":"Point"}
}