{
  "type": "Feature",
  "properties": {
    "addr:full":"Brinkstraat 10 Denekamp NL.08 7591 DP",
    "addr:housenumber":"10;nl.08",
    "addr:postcode":"7591 dp",
    "addr:street":"Brinkstraat",
    "iso:country":"NL",
    "sg:address":"Brinkstraat 10",
    "sg:city":"Denekamp",
    "sg:orig_category":"Huishoudapparatuur, Televisies And Radio'S",
    "sg:phone":"+31 541 351 257",
    "sg:postcode":"7591 DP",
    "sg:province":"NL.08",
    "wof:name":"Firma Groothuis",
    "wof:placetype":"venue"
},
  "geometry": {"coordinates":[7.00446,52.376137],"type":"Point"}
}