{
  "type": "Feature",
  "properties": {
    "addr:full":"Linnaeusdwstr 23B Amsterdam North Holland 1098 AW",
    "addr:housenumber":"23b",
    "addr:postcode":"1098 aw",
    "addr:street":"Linnaeusdwstr",
    "iso:country":"NL",
    "sg:address":"Linnaeusdwstr 23B",
    "sg:city":"Amsterdam",
    "sg:orig_category":"Webdesign Bureaus",
    "sg:phone":"+31 6 54744906",
    "sg:postcode":"1098 AW",
    "sg:province":"North Holland",
    "sg:website":"http://www.4ddesign.nl",
    "wof:name":"4D Design",
    "wof:placetype":"venue"
},
  "geometry": {"coordinates":[4.9321718216,52.3535995483],"type":"Point"}
}