{
  "type": "Feature",
  "properties": {
    "iso:country":"NL",
    "sg:address":"Stationsstraat 18",
    "sg:city":"Heythuysen",
    "sg:orig_category":"Verlichting And Huishoudartikelen",
    "sg:phone":"+31 475 495 230",
    "sg:postcode":"6093 BK",
    "sg:province":"Limburg",
    "wof:name":"De Guirlande",
    "wof:placetype":"venue"
},
  "geometry": {"coordinates":[5.89361,51.248665],"type":"Point"}
}