{
  "type": "Feature",
  "properties": {
    "addr:full":"Kerkhoekstr 13 Yerseke Zeeland 4401 GB",
    "addr:housenumber":"13",
    "addr:postcode":"4401 gb",
    "addr:street":"Kerkhoekstr",
    "iso:country":"NL",
    "sg:address":"Kerkhoekstr 13",
    "sg:city":"Yerseke",
    "sg:orig_category":"Kappers",
    "sg:phone":"+31 113 572 254",
    "sg:postcode":"4401 GB",
    "sg:province":"Zeeland",
    "wof:name":"Ther\u00e8se",
    "wof:placetype":"venue"
},
  "geometry": {"coordinates":[4.048797,51.490822],"type":"Point"}
}