{
  "type": "Feature",
  "properties": {
    "iso:country":"NL",
    "sg:address":"Johan De Wittstraat 45",
    "sg:city":"Wassenaar",
    "sg:orig_category":"Overheidsdiensten",
    "sg:phone":"+31 70 512 2222",
    "sg:postcode":"2242 LV",
    "sg:province":"South Holland",
    "wof:name":"Gemeente Wassenaar",
    "wof:placetype":"venue"
},
  "geometry": {"coordinates":[4.3995227814,52.1463279724],"type":"Point"}
}