{
  "type": "Feature",
  "properties": {
    "addr:full":"Bovenweg 13 'T Harde Gelderland 8084 PB",
    "addr:housenumber":"13",
    "addr:postcode":"8084 pb",
    "addr:street":"Bovenweg",
    "iso:country":"NL",
    "sg:address":"Bovenweg 13",
    "sg:city":"'T Harde",
    "sg:orig_category":"Wegen And Sportterreinen",
    "sg:phone":"+31 525 653 935",
    "sg:postcode":"8084 PB",
    "sg:province":"Gelderland",
    "wof:name":"Altena Weg- En Waterbouw Bv",
    "wof:placetype":"venue"
},
  "geometry": {"coordinates":[5.8742370605,52.4215278625],"type":"Point"}
}