{
  "type": "Feature",
  "properties": {
    "iso:country":"NL",
    "sg:address":"Genneperwg 44",
    "sg:city":"Eindhoven",
    "sg:orig_category":"Schoonheidsinstituten",
    "sg:phone":"+31 40 252 8620",
    "sg:postcode":"5654 AH",
    "sg:province":"North Brabant",
    "wof:name":"Wetzels, Janine",
    "wof:placetype":"venue"
},
  "geometry": {"coordinates":[5.464541,51.42411],"type":"Point"}
}