{
  "type": "Feature",
  "properties": {
    "addr:full":"Norbertynenstr 13A Geleen Limburg 6166 AE",
    "addr:housenumber":"13a",
    "addr:postcode":"6166 ae",
    "addr:street":"Norbertynenstr",
    "iso:country":"NL",
    "sg:address":"Norbertynenstr 13A",
    "sg:city":"Geleen",
    "sg:orig_category":"Yoga-Instituten",
    "sg:phone":"+31 46 475 9577",
    "sg:postcode":"6166 AE",
    "sg:province":"Limburg",
    "wof:name":"Betty Driessen",
    "wof:placetype":"venue"
},
  "geometry": {"coordinates":[5.84191,50.97448],"type":"Point"}
}