{
  "type": "Feature",
  "properties": {
    "addr:full":"Newtonln 61 Utrecht Utrecht 3584 BP",
    "addr:housenumber":"61",
    "addr:postcode":"3584 bp",
    "addr:street":"Newtonln",
    "iso:country":"NL",
    "sg:address":"Newtonln 61",
    "sg:city":"Utrecht",
    "sg:orig_category":"Werving En Selectie",
    "sg:phone":"+31 30 212 2055",
    "sg:postcode":"3584 BP",
    "sg:province":"Utrecht",
    "sg:website":"http://www.batenborch.com",
    "wof:name":"Batenborch International",
    "wof:placetype":"venue"
},
  "geometry": {"coordinates":[5.1492848396,52.0907325745],"type":"Point"}
}