{
  "type": "Feature",
  "properties": {
    "iso:country":"NL",
    "sg:address":"Overschiesewg 54",
    "sg:city":"Rotterdam",
    "sg:orig_category":"Bedrijfshuisvesting",
    "sg:phone":"+31 10 415 0476",
    "sg:postcode":"3044 EG",
    "sg:province":"Zuid-Holland",
    "wof:name":"Mbc",
    "wof:placetype":"venue"
},
  "geometry": {"coordinates":[4.410185,51.936275],"type":"Point"}
}