{
  "type": "Feature",
  "properties": {
    "addr:full":"Nieuwestraat 61 Strijen Zuid-Holland 3291 AP",
    "addr:housenumber":"61",
    "addr:postcode":"3291 ap",
    "addr:street":"Nieuwestraat",
    "iso:country":"NL",
    "sg:address":"Nieuwestraat 61",
    "sg:city":"Strijen",
    "sg:orig_category":"Verhuur Audiovisuele Apparatuur",
    "sg:phone":"+31 78 674 2919",
    "sg:postcode":"3291 AP",
    "sg:province":"Zuid-Holland",
    "wof:name":"Rider Audio En Lights",
    "wof:placetype":"venue"
},
  "geometry": {"coordinates":[4.553145,51.742794],"type":"Point"}
}