{
  "type": "Feature",
  "properties": {
    "addr:full":"Vijverstraat 24 Ter Apel Groningen 9561 KR",
    "addr:housenumber":"24",
    "addr:postcode":"9561 kr",
    "addr:street":"Vijverstraat",
    "iso:country":"NL",
    "sg:address":"Vijverstraat 24",
    "sg:city":"Ter Apel",
    "sg:classifiers":[
        {
            "category":"Education",
            "subcategory":"Preschool",
            "type":"Public Place"
        }
    ],
    "sg:phone":"+31 599 581 137",
    "sg:postcode":"9561 KR",
    "sg:province":"Groningen",
    "sg:tags":[
        "kleuteronderwijs",
        "basis-"
    ],
    "wof:name":"Jan Westerschool",
    "wof:placetype":"venue"
},
  "geometry": {"coordinates":[7.059953,52.877743],"type":"Point"}
}