{
  "type": "Feature",
  "properties": {
    "addr:full":"Beusichemseweg 46 'T Goy Utrecht 3997 MJ",
    "addr:housenumber":"46",
    "addr:postcode":"3997 mj",
    "addr:street":"Beusichemseweg;T",
    "iso:country":"NL",
    "sg:address":"Beusichemseweg 46",
    "sg:city":"'T Goy",
    "sg:orig_category":"Landbouwmachines Gh",
    "sg:phone":"+31 30 601 1749",
    "sg:postcode":"3997 MJ",
    "sg:province":"Utrecht",
    "wof:name":"Gerard Huiden Bv",
    "wof:placetype":"venue"
},
  "geometry": {"coordinates":[5.211162,52.00761],"type":"Point"}
}