{
  "type": "Feature",
  "properties": {
    "addr:full":"Kon Beatrixstr 2 Bergambacht Zuid-Holland 2861 XK",
    "addr:housenumber":"2",
    "addr:postcode":"2861 xk",
    "addr:street":"Kon Beatrixstr",
    "iso:country":"NL",
    "sg:address":"Kon Beatrixstr 2",
    "sg:city":"Bergambacht",
    "sg:orig_category":"Administratie- En Boekhoudkantoren",
    "sg:phone":"+31 182 352 214",
    "sg:postcode":"2861 XK",
    "sg:province":"Zuid-Holland",
    "wof:name":"Actievo",
    "wof:placetype":"venue"
},
  "geometry": {"coordinates":[4.784389,51.93483],"type":"Point"}
}