{
  "type": "Feature",
  "properties": {
    "iso:country":"NL",
    "sg:address":"Utrechtsestraat 80",
    "sg:city":"Amsterdam",
    "sg:orig_category":"Huishoudapparatuur, Televisies And Radio'S",
    "sg:phone":"+31 20 624 5082",
    "sg:postcode":"1017 VR",
    "sg:province":"Noord-Holland",
    "wof:name":"Expert Mons Electro Bv",
    "wof:placetype":"venue"
},
  "geometry": {"coordinates":[4.899714,52.361454],"type":"Point"}
}