{
  "type": "Feature",
  "properties": {
    "addr:full":"Ceramstr 40 Dordrecht Zuid-Holland 3312 SH",
    "addr:housenumber":"40",
    "addr:postcode":"3312 sh",
    "addr:street":"Ceramstr",
    "iso:country":"NL",
    "sg:address":"Ceramstr 40",
    "sg:city":"Dordrecht",
    "sg:orig_category":"Webdesign Bureaus",
    "sg:phone":"+31 78 631 2545",
    "sg:postcode":"3312 SH",
    "sg:province":"Zuid-Holland",
    "sg:website":"http://www.thinco.nl",
    "wof:name":"Thinco",
    "wof:placetype":"venue"
},
  "geometry": {"coordinates":[4.6877608299,51.8086433411],"type":"Point"}
}