{
  "type": "Feature",
  "properties": {
    "addr:full":"Molendwstr 25A Apeldoorn Gelderland 7311 MX",
    "addr:housenumber":"25a",
    "addr:postcode":"7311 mx",
    "addr:street":"Molendwstr;Gelderland",
    "iso:country":"NL",
    "sg:address":"Molendwstr 25A",
    "sg:city":"Apeldoorn",
    "sg:orig_category":"Meubelstoffering",
    "sg:phone":"+31 55 521 9031",
    "sg:postcode":"7311 MX",
    "sg:province":"Gelderland",
    "sg:website":"http://www.paulleuven.com",
    "wof:name":"Leuven, P H",
    "wof:placetype":"venue"
},
  "geometry": {"coordinates":[5.969973,52.21244],"type":"Point"}
}