{
  "type": "Feature",
  "properties": {
    "addr:full":"Koningshoek 93054 Maassluis South Holland 3144 BA",
    "addr:housenumber":"93054",
    "addr:postcode":"3144 ba",
    "addr:street":"Koningshoek",
    "iso:country":"NL",
    "sg:address":"Koningshoek 93054",
    "sg:city":"Maassluis",
    "sg:orig_category":"Visspeciaalzaken",
    "sg:phone":"+31 10 591 6049",
    "sg:postcode":"3144 BA",
    "sg:province":"South Holland",
    "wof:name":"M. Groen",
    "wof:placetype":"venue"
},
  "geometry": {"coordinates":[4.239773,51.928005],"type":"Point"}
}