{
  "type": "Feature",
  "properties": {
    "addr:full":"Eekhorstwg 35 Meppel Provincie Drenthe 7942 KC",
    "addr:housenumber":"35",
    "addr:postcode":"7942 kc",
    "addr:street":"Eekhorstwg;Provincie Drenthe",
    "iso:country":"NL",
    "sg:address":"Eekhorstwg 35",
    "sg:city":"Meppel",
    "sg:orig_category":"Kantoormachines - Fabrieken En Groothandel",
    "sg:phone":"+31 522 292 498",
    "sg:postcode":"7942 KC",
    "sg:province":"Provincie Drenthe",
    "sg:website":"http://www.papierklem.nl",
    "wof:name":"Papierklem Bv, De",
    "wof:placetype":"venue"
},
  "geometry": {"coordinates":[6.1955242157,52.7135848999],"type":"Point"}
}