{
  "type": "Feature",
  "properties": {
    "addr:full":"Rozenkransstr 69 St Willebrord Noord-Brabant 4711 CW",
    "addr:housenumber":"69",
    "addr:postcode":"4711 cw",
    "addr:street":"Rozenkransstr",
    "iso:country":"NL",
    "sg:address":"Rozenkransstr 69",
    "sg:city":"St Willebrord",
    "sg:orig_category":"Montagebedrijven",
    "sg:phone":"+31 165 383 485",
    "sg:postcode":"4711 CW",
    "sg:province":"Noord-Brabant",
    "wof:name":"Ren\u00e9",
    "wof:placetype":"venue"
},
  "geometry": {"coordinates":[4.584432,51.552464],"type":"Point"}
}