{
  "type": "Feature",
  "properties": {
    "addr:full":"Boudewynln 4 Dronten Flevoland 8251 RT",
    "addr:housenumber":"4",
    "addr:postcode":"8251 rt",
    "addr:street":"Boudewynln;Flevoland",
    "iso:country":"NL",
    "sg:address":"Boudewynln 4",
    "sg:city":"Dronten",
    "sg:classifiers":[
        {
            "category":"Food & Beverages",
            "subcategory":"Fruits & Vegetables",
            "type":"Retail Goods"
        }
    ],
    "sg:phone":"+31 321 312 193",
    "sg:postcode":"8251 RT",
    "sg:province":"Flevoland",
    "sg:tags":[
        "en",
        "groenten"
    ],
    "wof:name":"Topper, L",
    "wof:placetype":"venue"
},
  "geometry": {"coordinates":[5.750099,52.526733],"type":"Point"}
}