{
  "type": "Feature",
  "properties": {
    "addr:full":"Idenburglaan 24 Rijswijk Zh South Holland 2283 JT",
    "addr:housenumber":"24",
    "addr:postcode":"2283 jt",
    "addr:street":"Idenburglaan",
    "iso:country":"NL",
    "sg:address":"Idenburglaan 24",
    "sg:city":"Rijswijk Zh",
    "sg:orig_category":"Wasserettes And Stomerijen",
    "sg:phone":"+31 70 393 7208",
    "sg:postcode":"2283 JT",
    "sg:province":"South Holland",
    "wof:name":"Vof De Haan",
    "wof:placetype":"venue"
},
  "geometry": {"coordinates":[4.3302559853,52.0455665588],"type":"Point"}
}