{
  "type": "Feature",
  "properties": {
    "addr:full":"Wattstraat 5 Barneveld Gelderland 3771 AG",
    "addr:housenumber":"5",
    "addr:postcode":"3771",
    "addr:street":"Wattstraat;Gelderland",
    "iso:country":"NL",
    "sg:address":"Wattstraat 5",
    "sg:city":"Barneveld",
    "sg:orig_category":"Zuivelproducten And Spijsoli?n Gh",
    "sg:phone":"+31 342 415 374",
    "sg:postcode":"3771 AG",
    "sg:province":"Gelderland",
    "wof:name":"H. Zeggelaar'S Eierhandel Barnevelds Roe",
    "wof:placetype":"venue"
},
  "geometry": {"coordinates":[5.598053,52.136173],"type":"Point"}
}