{
  "type": "Feature",
  "properties": {
    "addr:full":"Postbus 776 Alphen Aan Den Ryn 2400 AT",
    "addr:housenumber":"776",
    "addr:postcode":"2400",
    "addr:street":"Postbus;Aan Den Ryn",
    "iso:country":"NL",
    "sg:address":"Postbus 776",
    "sg:city":"Alphen Aan Den Ryn",
    "sg:orig_category":"Psychologen",
    "sg:phone":"+31 172 424 919",
    "sg:postcode":"2400 AT",
    "wof:name":"Fbe",
    "wof:placetype":"venue"
},
  "geometry": {"coordinates":[4.68895,52.131088],"type":"Point"}
}