{
  "type": "Feature",
  "properties": {
    "iso:country":"NL",
    "sg:address":"Verl Lagewg 3",
    "sg:city":"Hoorn Nh",
    "sg:orig_category":"Keukens",
    "sg:phone":"+31 229 271 187",
    "sg:postcode":"1628 PM",
    "sg:province":"Noord-Holland",
    "sg:website":"http://www.idkeukens.nl",
    "wof:name":"Id",
    "wof:placetype":"venue"
},
  "geometry": {"coordinates":[5.05207,52.642399],"type":"Point"}
}