{
  "type": "Feature",
  "properties": {
    "addr:full":"Gijsbrecht V Aemstelstr 118 Haarlem Noord-Holland 2026 VJ",
    "addr:housenumber":"118",
    "addr:postcode":"2026 vj",
    "addr:street":"Gijsbrecht V Aemstelstr",
    "iso:country":"NL",
    "sg:address":"Gijsbrecht V Aemstelstr 118",
    "sg:city":"Haarlem",
    "sg:classifiers":[
        {
            "category":"Education",
            "subcategory":"Preschool",
            "type":"Public Place"
        }
    ],
    "sg:phone":"+31 23 537 4787",
    "sg:postcode":"2026 VJ",
    "sg:province":"Noord-Holland",
    "sg:tags":[
        "kleuteronderwijs",
        "basis-"
    ],
    "wof:name":"Openbare Basisschool De Schoterkring",
    "wof:placetype":"venue"
},
  "geometry": {"coordinates":[4.653184,52.417873],"type":"Point"}
}