{
  "type": "Feature",
  "properties": {
    "iso:country":"NL",
    "sg:address":"Hoofdwg 620",
    "sg:city":"Hoofddorp",
    "sg:orig_category":"Farmaceutische Industrie En Groothandel",
    "sg:phone":"+31 23 554 0120",
    "sg:postcode":"2132 MJ",
    "sg:province":"Noord-Holland",
    "wof:name":"Speywood",
    "wof:placetype":"venue"
},
  "geometry": {"coordinates":[4.698533,52.309193],"type":"Point"}
}