{
  "type": "Feature",
  "properties": {
    "addr:full":"Kofschip 5 Lelystad Flevoland 8223 EZ",
    "addr:housenumber":"5",
    "addr:postcode":"8223 ez",
    "addr:street":"Kofschip;Flevoland",
    "iso:country":"NL",
    "sg:address":"Kofschip 5",
    "sg:city":"Lelystad",
    "sg:orig_category":"Kinderopvang",
    "sg:phone":"+31 36 535 2592",
    "sg:postcode":"8223 EZ",
    "sg:province":"Flevoland",
    "sg:website":"http://www.hetsprookjesland.nl",
    "wof:name":"Sprookjesland Kindercentrum, 'T",
    "wof:placetype":"venue"
},
  "geometry": {"coordinates":[5.47465,52.523563],"type":"Point"}
}