{
  "type": "Feature",
  "properties": {
    "iso:country":"NL",
    "sg:address":"Vondellaan 86",
    "sg:city":"Veenendaal",
    "sg:orig_category":"Boekhouders",
    "sg:phone":"+31 318 527 354",
    "sg:postcode":"3906 EA",
    "sg:province":"Utrecht",
    "wof:name":"Boekhoudservice Eelink",
    "wof:placetype":"venue"
},
  "geometry": {"coordinates":[5.525275,52.02412],"type":"Point"}
}