{
  "type": "Feature",
  "properties": {
    "addr:full":"Middenweg 9 Heerhugowaard Noord-Holland 1703 RA",
    "addr:housenumber":"9",
    "addr:postcode":"1703 ra",
    "addr:street":"Middenweg",
    "iso:country":"NL",
    "sg:address":"Middenweg 9",
    "sg:city":"Heerhugowaard",
    "sg:orig_category":"Verzekeringen",
    "sg:phone":"+31 72 571 0622",
    "sg:postcode":"1703 RA",
    "sg:province":"Noord-Holland",
    "wof:name":"My Way Bemiddelings- En Servicebureau Bv",
    "wof:placetype":"venue"
},
  "geometry": {"coordinates":[4.827522,52.665195],"type":"Point"}
}