{
  "type": "Feature",
  "properties": {
    "addr:full":"Langendk 5 Eindhoven North Brabant 5652 AX",
    "addr:housenumber":"5",
    "addr:postcode":"5652 ax",
    "addr:street":"Langendk",
    "iso:country":"NL",
    "sg:address":"Langendk 5",
    "sg:city":"Eindhoven",
    "sg:orig_category":"Wegenbouw",
    "sg:phone":"+31 40 257 0571",
    "sg:postcode":"5652 AX",
    "sg:province":"North Brabant",
    "wof:name":"Rasenberg Bv",
    "wof:placetype":"venue"
},
  "geometry": {"coordinates":[5.4322972298,51.4273071289],"type":"Point"}
}