{
  "type": "Feature",
  "properties": {
    "addr:full":"Haarlemmermeerstr 136-I Amsterdam North Holland 1058 KH",
    "addr:housenumber":"136-i",
    "addr:postcode":"1058 kh",
    "addr:street":"Haarlemmermeerstr",
    "iso:country":"NL",
    "sg:address":"Haarlemmermeerstr 136-I",
    "sg:city":"Amsterdam",
    "sg:orig_category":"Product-Promotie",
    "sg:phone":"+31 20 669 8560",
    "sg:postcode":"1058 KH",
    "sg:province":"North Holland",
    "sg:website":"http://www.pppromotions.nl",
    "wof:name":"Promotions",
    "wof:placetype":"venue"
},
  "geometry": {"coordinates":[4.85094,52.357658],"type":"Point"}
}