{
  "type": "Feature",
  "properties": {
    "addr:full":"Maasln 21 Bergen Op Zoom North Brabant 4615 BM",
    "addr:housenumber":"21",
    "addr:postcode":"4615 bm",
    "addr:street":"Maasln",
    "iso:country":"NL",
    "sg:address":"Maasln 21",
    "sg:city":"Bergen Op Zoom",
    "sg:orig_category":"Autorijscholen",
    "sg:phone":"+31 164 266 460",
    "sg:postcode":"4615 BM",
    "sg:province":"North Brabant",
    "wof:name":"Savo",
    "wof:placetype":"venue"
},
  "geometry": {"coordinates":[4.281987,51.495953],"type":"Point"}
}