{
  "type": "Feature",
  "properties": {
    "addr:full":"Het Ham 17 Warnsveld Gelderland 7232 GL",
    "addr:housenumber":"17",
    "addr:postcode":"7232 gl",
    "addr:street":"Het Ham;Gelderland",
    "iso:country":"NL",
    "sg:address":"Het Ham 17",
    "sg:city":"Warnsveld",
    "sg:orig_category":"Bedrijfs- And Managementsconsultants",
    "sg:phone":"+31 575 521 285",
    "sg:postcode":"7232 GL",
    "sg:province":"Gelderland",
    "wof:name":"Seegers Advies",
    "wof:placetype":"venue"
},
  "geometry": {"coordinates":[6.23583,52.128101],"type":"Point"}
}