{
  "type": "Feature",
  "properties": {
    "addr:full":"Dahliastr 55 Culemborg Gelderland 4101 HB",
    "addr:housenumber":"55",
    "addr:postcode":"4101 hb",
    "addr:street":"Dahliastr;Gelderland",
    "iso:country":"NL",
    "sg:address":"Dahliastr 55",
    "sg:city":"Culemborg",
    "sg:orig_category":"Fitnesscentra",
    "sg:phone":"+31 345 521 308",
    "sg:postcode":"4101 HB",
    "sg:province":"Gelderland",
    "wof:name":"Master Gym",
    "wof:placetype":"venue"
},
  "geometry": {"coordinates":[5.23272,51.955978],"type":"Point"}
}