{
  "type": "Feature",
  "properties": {
    "iso:country":"NL",
    "sg:address":"Sydneystr 10",
    "sg:city":"Rotterdam",
    "sg:orig_category":"Kantoorbenodigdheden - Fabrieken En Groothandel",
    "sg:phone":"+31 10 462 7783",
    "sg:postcode":"3047 BP",
    "sg:province":"Zuid-Holland",
    "sg:website":"http://www.officecentre.nl",
    "wof:name":"Office Centre",
    "wof:placetype":"venue"
},
  "geometry": {"coordinates":[4.4085788727,51.9412574768],"type":"Point"}
}