{
  "type": "Feature",
  "properties": {
    "addr:full":"Molenstr 15 Hilvarenbeek North Brabant 5081 ZM",
    "addr:housenumber":"15",
    "addr:postcode":"5081 zm",
    "addr:street":"Molenstr",
    "iso:country":"NL",
    "sg:address":"Molenstr 15",
    "sg:city":"Hilvarenbeek",
    "sg:orig_category":"Dierenvoeder - Fabrieken",
    "sg:phone":"+31 13 505 1420",
    "sg:postcode":"5081 ZM",
    "sg:province":"North Brabant",
    "wof:name":"Renco",
    "wof:placetype":"venue"
},
  "geometry": {"coordinates":[5.17814,51.474358],"type":"Point"}
}