{
  "type": "Feature",
  "properties": {
    "addr:full":"Akkerdistel 8 Bergschenhoek Zuid-Holland 2661 HT",
    "addr:housenumber":"8",
    "addr:postcode":"2661 ht",
    "addr:street":"Akkerdistel",
    "iso:country":"NL",
    "sg:address":"Akkerdistel 8",
    "sg:city":"Bergschenhoek",
    "sg:orig_category":"Loodgieters",
    "sg:phone":"+31 10 521 2746",
    "sg:postcode":"2661 HT",
    "sg:province":"Zuid-Holland",
    "wof:name":"Moes, H M",
    "wof:placetype":"venue"
},
  "geometry": {"coordinates":[4.503226,51.985668],"type":"Point"}
}