{
  "type": "Feature",
  "properties": {
    "iso:country":"NL",
    "sg:address":"Ten Eiken 7",
    "sg:city":"Hoogeloon",
    "sg:orig_category":"Verpakkingsbedrijven",
    "sg:phone":"+31 497 682 882",
    "sg:postcode":"5528 BK",
    "sg:province":"Noord-Brabant",
    "wof:name":"Ropro Produktiemontage",
    "wof:placetype":"venue"
},
  "geometry": {"coordinates":[5.268586,51.397945],"type":"Point"}
}