{
  "type": "Feature",
  "properties": {
    "addr:full":"Gr Florispln 58 S Gravenzande Zuid-Holland 2691 ZX",
    "addr:housenumber":"58;gravenzande",
    "addr:postcode":"2691 zx",
    "addr:street":"S",
    "iso:country":"NL",
    "sg:address":"Gr Florispln 58",
    "sg:city":"S Gravenzande",
    "sg:orig_category":"Adviesbureaus Bedrijfsorganisatie",
    "sg:phone":"+31 174 422 655",
    "sg:postcode":"2691 ZX",
    "sg:province":"Zuid-Holland",
    "wof:name":"Graaff, De",
    "wof:placetype":"venue"
},
  "geometry": {"coordinates":[4.164261,52.003143],"type":"Point"}
}