{
  "type": "Feature",
  "properties": {
    "addr:full":"H De Lintwg 12 Spykenisse South Holland 3201 EK",
    "addr:housenumber":"12",
    "addr:postcode":"3201 ek",
    "addr:street":"Spykenisse South",
    "iso:country":"NL",
    "sg:address":"H De Lintwg 12",
    "sg:city":"Spykenisse",
    "sg:orig_category":"Artsen - Huisartsen",
    "sg:phone":"+31 181 613 931",
    "sg:postcode":"3201 EK",
    "sg:province":"South Holland",
    "wof:name":"Ottema Bv",
    "wof:placetype":"venue"
},
  "geometry": {"coordinates":[4.329865,51.848835],"type":"Point"}
}