{
  "type": "Feature",
  "properties": {
    "addr:full":"Plaats 25 'S Gravenhage Zuid-Holland 2513 AD",
    "addr:housenumber":"25",
    "addr:postcode":"2513 ad",
    "addr:street":"Plaats;' S",
    "iso:country":"NL",
    "sg:address":"Plaats 25",
    "sg:city":"'S Gravenhage",
    "sg:orig_category":"Huishoudapparatuur, Televisies And Radio'S",
    "sg:phone":"+31 70 360 9900",
    "sg:postcode":"2513 AD",
    "sg:province":"Zuid-Holland",
    "wof:name":"Ton Kuylenburg",
    "wof:placetype":"venue"
},
  "geometry": {"coordinates":[4.310181,52.079613],"type":"Point"}
}