{
  "type": "Feature",
  "properties": {
    "iso:country":"NL",
    "sg:address":"Distelveld 24",
    "sg:city":"Bavel",
    "sg:orig_category":"Koeriersdiensten",
    "sg:phone":"+31 6 53730514",
    "sg:postcode":"4854 MC",
    "sg:province":"Noord-Brabant",
    "wof:name":"Avs",
    "wof:placetype":"venue"
},
  "geometry": {"coordinates":[4.831396,51.572071],"type":"Point"}
}