{
  "type": "Feature",
  "properties": {
    "addr:full":"Herestr 9-11 Groningen Groningen 9711 LA",
    "addr:housenumber":"9-11",
    "addr:postcode":"9711 la",
    "iso:country":"NL",
    "sg:address":"Herestr 9-11",
    "sg:city":"Groningen",
    "sg:orig_category":"Opticiens",
    "sg:phone":"+31 50 318 4135",
    "sg:postcode":"9711 LA",
    "sg:province":"Groningen",
    "sg:website":"http://www.eyewish.nl",
    "wof:name":"Becker",
    "wof:placetype":"venue"
},
  "geometry": {"coordinates":[6.5666780472,53.2176094055],"type":"Point"}
}