{
  "type": "Feature",
  "properties": {
    "addr:full":"Lonnekerbrugstr 87A Enschede Overijssel 7547 AJ",
    "addr:housenumber":"87a",
    "addr:postcode":"7547 aj",
    "addr:street":"Lonnekerbrugstr",
    "iso:country":"NL",
    "sg:address":"Lonnekerbrugstr 87A",
    "sg:city":"Enschede",
    "sg:orig_category":"Meubellakkerijen En -Spuiterijen",
    "sg:phone":"+31 53 436 0711",
    "sg:postcode":"7547 AJ",
    "sg:province":"Overijssel",
    "wof:name":"Wolma'S Meubelonderhoud",
    "wof:placetype":"venue"
},
  "geometry": {"coordinates":[6.855148,52.226585],"type":"Point"}
}