{
  "type": "Feature",
  "properties": {
    "iso:country":"NL",
    "sg:address":"Persijnlaan 93",
    "sg:city":"Purmerend",
    "sg:orig_category":"Apothekers",
    "sg:phone":"+31 299 469 090",
    "sg:postcode":"1447 EG",
    "sg:province":"Noord-Holland",
    "wof:name":"Apotheek Molentocht",
    "wof:placetype":"venue"
},
  "geometry": {"coordinates":[4.964838,52.48975],"type":"Point"}
}