{
  "type": "Feature",
  "properties": {
    "addr:full":"Zuiderweg Oost 1 Twisk Noord-Holland 1676 GN",
    "addr:housenumber":"1",
    "addr:postcode":"1676 gn",
    "addr:street":"Zuiderweg Oost",
    "iso:country":"NL",
    "sg:address":"Zuiderweg Oost 1",
    "sg:city":"Twisk",
    "sg:orig_category":"Vertaal- And Tolkenbureaus",
    "sg:phone":"+31 227 547 575",
    "sg:postcode":"1676 GN",
    "sg:province":"Noord-Holland",
    "wof:name":"Monika M. Jongert-Frenzel",
    "wof:placetype":"venue"
},
  "geometry": {"coordinates":[5.071298,52.736725],"type":"Point"}
}