{
  "type": "Feature",
  "properties": {
    "addr:full":"Poststraat 33 Stadskanaal Groningen 9501 ER",
    "addr:housenumber":"33",
    "addr:postcode":"9501 er",
    "addr:street":"Poststraat",
    "iso:country":"NL",
    "sg:address":"Poststraat 33",
    "sg:city":"Stadskanaal",
    "sg:orig_category":"Meubelzaken, Woning- And Keukeninrichting",
    "sg:phone":"+31 599 622 441",
    "sg:postcode":"9501 ER",
    "sg:province":"Groningen",
    "wof:name":"Prummel Meubelen",
    "wof:placetype":"venue"
},
  "geometry": {"coordinates":[6.942923,52.993504],"type":"Point"}
}