{
  "type": "Feature",
  "properties": {
    "addr:full":"Molenwg 80 Wydenes Noord-Holland 1608 EG",
    "addr:housenumber":"80",
    "addr:postcode":"1608 eg",
    "addr:street":"Molenwg",
    "iso:country":"NL",
    "sg:address":"Molenwg 80",
    "sg:city":"Wydenes",
    "sg:orig_category":"Filmstudio'S En -Productie",
    "sg:phone":"+31 229 501 477",
    "sg:postcode":"1608 EG",
    "sg:province":"Noord-Holland",
    "wof:name":"Molenweg Vof, De",
    "wof:placetype":"venue"
},
  "geometry": {"coordinates":[5.160853,52.642563],"type":"Point"}
}