{
  "type": "Feature",
  "properties": {
    "addr:full":"Legmeerdijk 313 Aalsmeer North Holland 1431 GB",
    "addr:housenumber":"313",
    "addr:postcode":"1431 gb",
    "addr:street":"Legmeerdijk",
    "iso:country":"NL",
    "sg:address":"Legmeerdijk 313",
    "sg:city":"Aalsmeer",
    "sg:orig_category":"Bloemen And Planten Gh",
    "sg:phone":"+31 297 353 353",
    "sg:postcode":"1431 GB",
    "sg:province":"North Holland",
    "wof:name":"M.J. Weerman Bloemengroothandel Bv",
    "wof:placetype":"venue"
},
  "geometry": {"coordinates":[4.786656,52.257832],"type":"Point"}
}