{
  "type": "Feature",
  "properties": {
    "iso:country":"NL",
    "sg:address":"Achterstr 33",
    "sg:city":"Asperen",
    "sg:orig_category":"Horloges En Klokken - Reparatie En Onderhoud",
    "sg:phone":"+31 345 618 862",
    "sg:postcode":"4147 AA",
    "sg:province":"Gelderland",
    "wof:name":"Stift, H C",
    "wof:placetype":"venue"
},
  "geometry": {"coordinates":[5.115704,51.881973],"type":"Point"}
}