{
  "type": "Feature",
  "properties": {
    "iso:country":"NL",
    "sg:address":"Handelstr 65-69",
    "sg:city":"Utrecht",
    "sg:orig_category":"Ventilatoren",
    "sg:phone":"+31 30 294 0094",
    "sg:postcode":"3533 GJ",
    "sg:province":"Utrecht",
    "sg:website":"http://www.hermeselectronics.nl",
    "wof:name":"Hermes",
    "wof:placetype":"venue"
},
  "geometry": {"coordinates":[5.085549,52.086735],"type":"Point"}
}