{
  "type": "Feature",
  "properties": {
    "addr:full":"Parkstr 83 S Gravenhage Zuid-Holland 2514 JG",
    "addr:housenumber":"83;gravenhage",
    "addr:postcode":"2514 jg",
    "addr:street":"Parkstr;S",
    "iso:country":"NL",
    "sg:address":"Parkstr 83",
    "sg:city":"S Gravenhage",
    "sg:orig_category":"Werving En Selectie",
    "sg:phone":"+31 70 311 0974",
    "sg:postcode":"2514 JG",
    "sg:province":"Zuid-Holland",
    "wof:name":"Careercompany",
    "wof:placetype":"venue"
},
  "geometry": {"coordinates":[4.3093500137,52.084148407],"type":"Point"}
}