{
  "type": "Feature",
  "properties": {
    "addr:full":"Dorpsstraat 253 Harmelen Utrecht 3481 EJ",
    "addr:housenumber":"253",
    "addr:postcode":"3481 ej",
    "addr:street":"Dorpsstraat",
    "iso:country":"NL",
    "sg:address":"Dorpsstraat 253",
    "sg:city":"Harmelen",
    "sg:orig_category":"Elektriciens",
    "sg:phone":"+31 348 441 808",
    "sg:postcode":"3481 EJ",
    "sg:province":"Utrecht",
    "wof:name":"Van Beusekom Harmelen Bv",
    "wof:placetype":"venue"
},
  "geometry": {"coordinates":[4.952397,52.091801],"type":"Point"}
}