{
  "type": "Feature",
  "properties": {
    "addr:full":"Markt 21C Panningen Limburg 5981 AN",
    "addr:housenumber":"21c",
    "addr:postcode":"5981 an",
    "addr:street":"Markt",
    "iso:country":"NL",
    "sg:address":"Markt 21C",
    "sg:city":"Panningen",
    "sg:orig_category":"Schoenen",
    "sg:phone":"+31 77 306 0585",
    "sg:postcode":"5981 AN",
    "sg:province":"Limburg",
    "wof:name":"Schoenenreus",
    "wof:placetype":"venue"
},
  "geometry": {"coordinates":[5.98067,51.328865],"type":"Point"}
}