{
  "type": "Feature",
  "properties": {
    "iso:country":"NL",
    "sg:address":"Korte Poten 10",
    "sg:city":"'S Gravenhage",
    "sg:classifiers":[
        {
            "category":"Fast Food",
            "type":"Food & Drink"
        }
    ],
    "sg:phone":"+31 70 346 4646",
    "sg:postcode":"2511 ED",
    "sg:province":"Zuid-Holland",
    "sg:tags":[
        "afhaal",
        "restaurant"
    ],
    "wof:name":"Cafetaria Flying Enterprise",
    "wof:placetype":"venue"
},
  "geometry": {"coordinates":[4.316949,52.079903],"type":"Point"}
}