{
  "type": "Feature",
  "properties": {
    "addr:full":"Parelstr 24 Hengelo Ov NL.08 7554 TM",
    "addr:housenumber":"24",
    "addr:postcode":"7554 tm",
    "addr:street":"Parelstr;Ov",
    "iso:country":"NL",
    "sg:address":"Parelstr 24",
    "sg:city":"Hengelo Ov",
    "sg:orig_category":"Waterbehandeling En Waterzuiverings- Systemen",
    "sg:phone":"+31 74 242 5255",
    "sg:postcode":"7554 TM",
    "sg:province":"NL.08",
    "wof:name":"Jotem Bv",
    "wof:placetype":"venue"
},
  "geometry": {"coordinates":[6.7800378799,52.238243103],"type":"Point"}
}