{
  "type": "Feature",
  "properties": {
    "addr:full":"Bornsestr 47 Almelo Overijssel 7607 KJ",
    "addr:housenumber":"47",
    "addr:postcode":"7607 kj",
    "addr:street":"Bornsestr",
    "iso:country":"NL",
    "sg:address":"Bornsestr 47",
    "sg:city":"Almelo",
    "sg:orig_category":"Schilders",
    "sg:phone":"+31 546 813 592",
    "sg:postcode":"7607 KJ",
    "sg:province":"Overijssel",
    "wof:name":"Lochem'S, Schildersbedrijf Van",
    "wof:placetype":"venue"
},
  "geometry": {"coordinates":[6.666712,52.350983],"type":"Point"}
}