{
  "type": "Feature",
  "properties": {
    "iso:country":"NL",
    "sg:address":"D Ellingtonstr 2",
    "sg:city":"Almere",
    "sg:orig_category":"Beeldende Kunstenaars",
    "sg:phone":"+31 6 53764939",
    "sg:postcode":"1311 SE",
    "sg:province":"Flevoland",
    "wof:name":"Tzatzalos, Eleni",
    "wof:placetype":"venue"
},
  "geometry": {"coordinates":[5.185332,52.367519],"type":"Point"}
}