{
  "type": "Feature",
  "properties": {
    "addr:full":"Meanderhof 11 Giessenburg Zuid-Holland 3381 JN",
    "addr:housenumber":"11",
    "addr:postcode":"3381 jn",
    "addr:street":"Meanderhof",
    "iso:country":"NL",
    "sg:address":"Meanderhof 11",
    "sg:city":"Giessenburg",
    "sg:orig_category":"Adviesbureaus Bedrijfsorganisatie",
    "sg:phone":"+31 184 659 913",
    "sg:postcode":"3381 JN",
    "sg:province":"Zuid-Holland",
    "wof:name":"Ladage Bv, J A",
    "wof:placetype":"venue"
},
  "geometry": {"coordinates":[4.890527,51.852509],"type":"Point"}
}