{
  "type": "Feature",
  "properties": {
    "addr:full":"Eperwg 61 Heerde Gelderland 8181 EV",
    "addr:housenumber":"61",
    "addr:postcode":"8181 ev",
    "addr:street":"Eperwg;Gelderland",
    "iso:country":"NL",
    "sg:address":"Eperwg 61",
    "sg:city":"Heerde",
    "sg:classifiers":[
        {
            "category":"Restaurant",
            "type":"Food & Drink"
        }
    ],
    "sg:phone":"+31 578 691 864",
    "sg:postcode":"8181 EV",
    "sg:province":"Gelderland",
    "wof:name":"Vierwinden",
    "wof:placetype":"venue"
},
  "geometry": {"coordinates":[6.019823,52.371021],"type":"Point"}
}