{
  "type": "Feature",
  "properties": {
    "addr:full":"Savannahwg 11 Utrecht Utrecht 3542 AW",
    "addr:housenumber":"11",
    "addr:postcode":"3542 aw",
    "addr:street":"Savannahwg",
    "iso:country":"NL",
    "sg:address":"Savannahwg 11",
    "sg:city":"Utrecht",
    "sg:orig_category":"Cafetaria'S",
    "sg:phone":"+31 30 241 0361",
    "sg:postcode":"3542 AW",
    "sg:province":"Utrecht",
    "wof:name":"Savannah Corner",
    "wof:placetype":"venue"
},
  "geometry": {"coordinates":[5.04331,52.117329],"type":"Point"}
}