{
  "type": "Feature",
  "properties": {
    "iso:country":"NL",
    "sg:address":"Aalboswg 23",
    "sg:city":"Vaassen",
    "sg:orig_category":"Drukkerijen",
    "sg:phone":"+31 578 573 615",
    "sg:postcode":"8171 MA",
    "sg:province":"Gelderland",
    "wof:name":"Manuel",
    "wof:placetype":"venue"
},
  "geometry": {"coordinates":[5.987474,52.300568],"type":"Point"}
}