{
  "type": "Feature",
  "properties": {
    "addr:full":"Kalverstraat 19 Made Noord-Brabant 4921 AA",
    "addr:housenumber":"19",
    "addr:postcode":"4921 aa",
    "addr:street":"Kalverstraat",
    "iso:country":"NL",
    "sg:address":"Kalverstraat 19",
    "sg:city":"Made",
    "sg:orig_category":"Goederenvervoer Over De Weg",
    "sg:phone":"+31 162 670 301",
    "sg:postcode":"4921 AA",
    "sg:province":"Noord-Brabant",
    "wof:name":"Visser Transportgroep Bv",
    "wof:placetype":"venue"
},
  "geometry": {"coordinates":[-120.197731,37.032848],"type":"Point"}
}