{
  "type": "Feature",
  "properties": {
    "addr:full":"De Weegschaal 8 'S Hertogenbosch Noord-Brabant 5215 MN",
    "addr:housenumber":"8 ' s",
    "addr:postcode":"5215 mn",
    "addr:street":"De Weegschaal",
    "iso:country":"NL",
    "sg:address":"De Weegschaal 8",
    "sg:city":"'S Hertogenbosch",
    "sg:orig_category":"Opticiens",
    "sg:phone":"+31 73 548 2020",
    "sg:postcode":"5215 MN",
    "sg:province":"Noord-Brabant",
    "wof:name":"Lunelle Bv",
    "wof:placetype":"venue"
},
  "geometry": {"coordinates":[5.3541750908,51.6884346008],"type":"Point"}
}