{
  "type": "Feature",
  "properties": {
    "addr:full":"Kerkstr 47 Hapert North Brabant 5527 EE",
    "addr:housenumber":"47",
    "addr:postcode":"5527 ee",
    "addr:street":"Kerkstr",
    "iso:country":"NL",
    "sg:address":"Kerkstr 47",
    "sg:city":"Hapert",
    "sg:orig_category":"Woninginrichting",
    "sg:phone":"+31 497 387 744",
    "sg:postcode":"5527 EE",
    "sg:province":"North Brabant",
    "wof:name":"Tapijt- & Gordijnland Hapert",
    "wof:placetype":"venue"
},
  "geometry": {"coordinates":[5.2488899231,51.3703117371],"type":"Point"}
}