{
  "type": "Feature",
  "properties": {
    "addr:full":"Dwangmolenstr 57 Almere Flevoland 1333 GX",
    "addr:housenumber":"57",
    "addr:postcode":"1333 gx",
    "addr:street":"Dwangmolenstr;Flevoland",
    "iso:country":"NL",
    "sg:address":"Dwangmolenstr 57",
    "sg:city":"Almere",
    "sg:orig_category":"Kinderopvang",
    "sg:phone":"+31 36 532 0198",
    "sg:postcode":"1333 GX",
    "sg:province":"Flevoland",
    "wof:name":"Speel-Mere",
    "wof:placetype":"venue"
},
  "geometry": {"coordinates":[5.270979,52.396587],"type":"Point"}
}