{
  "type": "Feature",
  "properties": {
    "addr:full":"Denekamperstraat 15 Ootmarsum NL.08 7631 AA",
    "addr:housenumber":"15;nl.08",
    "addr:postcode":"7631 aa",
    "addr:street":"Denekamperstraat",
    "iso:country":"NL",
    "sg:address":"Denekamperstraat 15",
    "sg:city":"Ootmarsum",
    "sg:classifiers":[
        {
            "category":"Travel",
            "subcategory":"Hotels & Motels",
            "type":"Entertainment"
        }
    ],
    "sg:phone":"+31 541 292 321",
    "sg:postcode":"7631 AA",
    "sg:province":"NL.08",
    "wof:name":"Hotel Pension De Rozenstruik",
    "wof:placetype":"venue"
},
  "geometry": {"coordinates":[6.899826,52.409904],"type":"Point"}
}