{
  "type": "Feature",
  "properties": {
    "iso:country":"NL",
    "sg:address":"Markt 27",
    "sg:city":"Valkenswaard",
    "sg:orig_category":"Banken And Kredietinstellingen",
    "sg:phone":"+31 40 207 1111",
    "sg:postcode":"5554 CA",
    "sg:province":"Noord-Brabant",
    "wof:name":"Ing Bank",
    "wof:placetype":"venue"
},
  "geometry": {"coordinates":[5.459314,51.350353],"type":"Point"}
}