{
  "type": "Feature",
  "properties": {
    "addr:full":"J V Beierenwg 148 Voorhout Zuid-Holland 2215 KX",
    "addr:housenumber":"148",
    "addr:postcode":"2215 kx",
    "addr:street":"J;Beierenwg",
    "iso:country":"NL",
    "sg:address":"J V Beierenwg 148",
    "sg:city":"Voorhout",
    "sg:orig_category":"Non-Classified Establishments",
    "sg:phone":"+31 252 215 920",
    "sg:postcode":"2215 KX",
    "sg:province":"Zuid-Holland",
    "wof:name":"Dijk, J Van",
    "wof:placetype":"venue"
},
  "geometry": {"coordinates":[4.48252,52.221874],"type":"Point"}
}