{
  "type": "Feature",
  "properties": {
    "addr:full":"Postbus 37176 Amsterdam Noord-Holland 1030 AD",
    "addr:postcode":"37176;1030 ad",
    "addr:street":"Postbus",
    "iso:country":"NL",
    "sg:address":"Postbus 37176",
    "sg:city":"Amsterdam",
    "sg:orig_category":"Postorderbedrijven",
    "sg:phone":"+31 20 636 2790",
    "sg:postcode":"1030 AD",
    "sg:province":"Noord-Holland",
    "sg:website":"http://www.satis-factory.nl",
    "wof:name":"Satisfactory",
    "wof:placetype":"venue"
},
  "geometry": {"coordinates":[4.89205,52.37355],"type":"Point"}
}