{
  "type": "Feature",
  "properties": {
    "iso:country":"NL",
    "sg:address":"Beerseweg 29",
    "sg:city":"Mill",
    "sg:orig_category":"Meubelreparatie And -Restauratie",
    "sg:phone":"+31 485 451 521",
    "sg:postcode":"5451 NR",
    "sg:province":"West Virginia",
    "wof:name":"W. Willems",
    "wof:placetype":"venue"
},
  "geometry": {"coordinates":[-80.290665,38.154221],"type":"Point"}
}