{
  "type": "Feature",
  "properties": {
    "addr:full":"Bisschopstraat 1 Creil Flevoland 8312 AK",
    "addr:housenumber":"1",
    "addr:postcode":"8312 ak",
    "addr:street":"Bisschopstraat;Flevoland",
    "iso:country":"NL",
    "sg:address":"Bisschopstraat 1",
    "sg:city":"Creil",
    "sg:classifiers":[
        {
            "category":"Education",
            "subcategory":"Preschool",
            "type":"Public Place"
        }
    ],
    "sg:phone":"+31 527 274 423",
    "sg:postcode":"8312 AK",
    "sg:province":"Flevoland",
    "sg:tags":[
        "kleuteronderwijs",
        "basis-"
    ],
    "wof:name":"Prot Chr Basisschool De Regenboog",
    "wof:placetype":"venue"
},
  "geometry": {"coordinates":[5.661074,52.764961],"type":"Point"}
}