{
  "type": "Feature",
  "properties": {
    "addr:full":"Sint-Jacobstraat 88 Rotterdam Zuid-Holland 3011 DE",
    "addr:housenumber":"88",
    "addr:postcode":"3011 de",
    "addr:street":"Sint-Jacobstraat",
    "iso:country":"NL",
    "sg:address":"Sint-Jacobstraat 88",
    "sg:city":"Rotterdam",
    "sg:orig_category":"Kappers",
    "sg:phone":"+31 10 414 2520",
    "sg:postcode":"3011 DE",
    "sg:province":"Zuid-Holland",
    "wof:name":"Kapsalon Joyce",
    "wof:placetype":"venue"
},
  "geometry": {"coordinates":[4.4826102257,51.9233283997],"type":"Point"}
}