{
  "type": "Feature",
  "properties": {
    "iso:country":"NL",
    "sg:address":"Hei Grindelwg 82",
    "sg:city":"Heerlen",
    "sg:orig_category":"Verenigingsgebouwen",
    "sg:phone":"+31 45 528 5081",
    "sg:postcode":"6414 BT",
    "sg:province":"Limburg",
    "wof:name":"Heksenberg/Bronsebroek, Wijkraad",
    "wof:placetype":"venue"
},
  "geometry": {"coordinates":[5.971151,50.912834],"type":"Point"}
}