{
  "type": "Feature",
  "properties": {
    "iso:country":"NL",
    "sg:address":"Het Hoge 26",
    "sg:city":"Vorden",
    "sg:orig_category":"Adviesbureaus Bouwkunde",
    "sg:phone":"+31 575 551 787",
    "sg:postcode":"7251 XW",
    "sg:province":"Gelderland",
    "wof:name":"Vaags, G H",
    "wof:placetype":"venue"
},
  "geometry": {"coordinates":[6.30913,52.10321],"type":"Point"}
}