{
  "type": "Feature",
  "properties": {
    "addr:full":"Bellamystr 63 Amsterdam Noord-Holland 1053 BH",
    "addr:housenumber":"63",
    "addr:postcode":"1053 bh",
    "addr:street":"Bellamystr",
    "iso:country":"NL",
    "sg:address":"Bellamystr 63",
    "sg:city":"Amsterdam",
    "sg:orig_category":"Onderhoudswerken",
    "sg:phone":"+31 6 20377166",
    "sg:postcode":"1053 BH",
    "sg:province":"Noord-Holland",
    "wof:name":"Stravers, Peter",
    "wof:placetype":"venue"
},
  "geometry": {"coordinates":[4.864729,52.366707],"type":"Point"}
}