{
  "type": "Feature",
  "properties": {
    "addr:full":"Grotestraat 156 Nijverdal NL.08 7443 BP",
    "addr:housenumber":"156;nl.08",
    "addr:postcode":"7443 bp",
    "addr:street":"Grotestraat",
    "iso:country":"NL",
    "sg:address":"Grotestraat 156",
    "sg:city":"Nijverdal",
    "sg:orig_category":"Verlichting And Huishoudartikelen",
    "sg:phone":"+31 548 619 333",
    "sg:postcode":"7443 BP",
    "sg:province":"NL.08",
    "wof:name":"Freie Verlichting Bv",
    "wof:placetype":"venue"
},
  "geometry": {"coordinates":[6.46816,52.36488],"type":"Point"}
}