{
  "type": "Feature",
  "properties": {
    "addr:full":"Pryssewg 65 Culemborg Gelderland 4105 LE",
    "addr:housenumber":"65",
    "addr:postcode":"4105 le",
    "addr:street":"Pryssewg;Gelderland",
    "iso:country":"NL",
    "sg:address":"Pryssewg 65",
    "sg:city":"Culemborg",
    "sg:orig_category":"Werving En Selectie",
    "sg:phone":"+31 345 519 846",
    "sg:postcode":"4105 LE",
    "sg:province":"Gelderland",
    "wof:name":"3Xs",
    "wof:placetype":"venue"
},
  "geometry": {"coordinates":[5.2075967789,51.9498710632],"type":"Point"}
}