{
  "type": "Feature",
  "properties": {
    "iso:country":"NL",
    "sg:address":"Kommisjewei 105",
    "sg:city":"Opeinde",
    "sg:orig_category":"Watersportartikelen",
    "sg:phone":"+31 512 371 360",
    "sg:postcode":"9218 PD",
    "sg:province":"Provincie Friesland",
    "wof:name":"Paradiso Watersport",
    "wof:placetype":"venue"
},
  "geometry": {"coordinates":[6.0587329865,53.1343727112],"type":"Point"}
}