{
  "type": "Feature",
  "properties": {
    "addr:full":"Hastelwg 264 Eindhoven North Brabant 5652 CN",
    "addr:housenumber":"264",
    "addr:postcode":"5652 cn",
    "iso:country":"NL",
    "sg:address":"Hastelwg 264",
    "sg:city":"Eindhoven",
    "sg:orig_category":"Verf En Lak - Fabrieken En Groothandel",
    "sg:phone":"+31 40 255 0550",
    "sg:postcode":"5652 CN",
    "sg:province":"North Brabant",
    "wof:name":"Putten Bv, S V Van Der",
    "wof:placetype":"venue"
},
  "geometry": {"coordinates":[5.433649,51.437275],"type":"Point"}
}