{
  "type": "Feature",
  "properties": {
    "iso:country":"NL",
    "sg:address":"Berghem 11",
    "sg:city":"Gulpen",
    "sg:orig_category":"Huizensloop And Bouwrijp Maken",
    "sg:phone":"+31 43 450 1159",
    "sg:postcode":"6271 NP",
    "sg:province":"Limburg",
    "wof:name":"Kaelen En Zn Loonbedrijven",
    "wof:placetype":"venue"
},
  "geometry": {"coordinates":[5.894651,50.806488],"type":"Point"}
}