{
  "type": "Feature",
  "properties": {
    "iso:country":"NL",
    "sg:address":"Toneellaan 1",
    "sg:city":"Zoetermeer",
    "sg:orig_category":"Opticiens",
    "sg:phone":"+31 180 551 004",
    "sg:postcode":"2725 NA",
    "sg:province":"South Holland",
    "wof:name":"Van Nes Contactlenzen",
    "wof:placetype":"venue"
},
  "geometry": {"coordinates":[4.4997200966,52.0691337585],"type":"Point"}
}