{
  "type": "Feature",
  "properties": {
    "addr:full":"Cronesteinkade 18 Leiden Zuid-Holland 2313 GX",
    "addr:housenumber":"18",
    "addr:postcode":"2313 gx",
    "addr:street":"Cronesteinkade",
    "iso:country":"NL",
    "sg:address":"Cronesteinkade 18",
    "sg:city":"Leiden",
    "sg:orig_category":"Architecten",
    "sg:phone":"+31 71 512 1714",
    "sg:postcode":"2313 GX",
    "sg:province":"Zuid-Holland",
    "wof:name":"Bruins Soedjono Architekten Bv",
    "wof:placetype":"venue"
},
  "geometry": {"coordinates":[4.498413,52.151779],"type":"Point"}
}