{
  "type": "Feature",
  "properties": {
    "addr:full":"Textielweg 16 Amersfoort Utrecht 3812 RV",
    "addr:housenumber":"16",
    "addr:postcode":"3812 rv",
    "addr:street":"Textielweg",
    "iso:country":"NL",
    "sg:address":"Textielweg 16",
    "sg:city":"Amersfoort",
    "sg:orig_category":"Diverse Grafische Activiteiten",
    "sg:phone":"+31 33 461 5251",
    "sg:postcode":"3812 RV",
    "sg:province":"Utrecht",
    "wof:name":"Litho Service Combinatie Bv",
    "wof:placetype":"venue"
},
  "geometry": {"coordinates":[5.368529,52.164883],"type":"Point"}
}