{
  "type": "Feature",
  "properties": {
    "addr:full":"Schoolstraat 13 Nijkerkerveen Gelderland 3864 MA",
    "addr:housenumber":"13",
    "addr:postcode":"3864 ma",
    "addr:street":"Schoolstraat;Gelderland",
    "iso:country":"NL",
    "sg:address":"Schoolstraat 13",
    "sg:city":"Nijkerkerveen",
    "sg:orig_category":"Binnenhuisarchitecten",
    "sg:phone":"+31 33 257 1393",
    "sg:postcode":"3864 MA",
    "sg:province":"Gelderland",
    "wof:name":"Ton Oeben Woonservice",
    "wof:placetype":"venue"
},
  "geometry": {"coordinates":[5.468125,52.192158],"type":"Point"}
}