{
  "type": "Feature",
  "properties": {
    "addr:full":"Veldhovenring 57 Tilburg North Brabant 5041 BB",
    "addr:housenumber":"57",
    "addr:postcode":"5041 bb",
    "addr:street":"Veldhovenring",
    "iso:country":"NL",
    "sg:address":"Veldhovenring 57",
    "sg:city":"Tilburg",
    "sg:orig_category":"Fitnesscentra",
    "sg:phone":"+31 13 536 3156",
    "sg:postcode":"5041 BB",
    "sg:province":"North Brabant",
    "wof:name":"Quality Sport Centre",
    "wof:placetype":"venue"
},
  "geometry": {"coordinates":[5.08483,51.56789],"type":"Point"}
}