{
  "type": "Feature",
  "properties": {
    "addr:full":"Schaepmanlaan 91 Oss British Columbia 5344 BC",
    "addr:housenumber":"91",
    "addr:postcode":"5344 bc",
    "addr:street":"Schaepmanlaan",
    "iso:country":"NL",
    "sg:address":"Schaepmanlaan 91",
    "sg:city":"Oss",
    "sg:orig_category":"Kappers",
    "sg:phone":"+31 412 652 223",
    "sg:postcode":"5344 BC",
    "sg:province":"British Columbia",
    "wof:name":"Wingens Haarmode Oss Bv",
    "wof:placetype":"venue"
},
  "geometry": {"coordinates":[-126.555511,54.485668],"type":"Point"}
}