{
  "type": "Feature",
  "properties": {
    "addr:full":"Waalreseweg 1 Valkenswaard Noord-Brabant 5554 HA",
    "addr:housenumber":"1",
    "addr:postcode":"5554 ha",
    "addr:street":"Waalreseweg",
    "iso:country":"NL",
    "sg:address":"Waalreseweg 1",
    "sg:city":"Valkenswaard",
    "sg:orig_category":"Werving And Selectie Van Tijdelijk Personeel And Uitzendkantoren",
    "sg:phone":"+31 40 204 6846",
    "sg:postcode":"5554 HA",
    "sg:province":"Noord-Brabant",
    "wof:name":"Adecco",
    "wof:placetype":"venue"
},
  "geometry": {"coordinates":[5.4580001831,51.3511962891],"type":"Point"}
}