{
  "type": "Feature",
  "properties": {
    "addr:full":"Zwartelaan 22 Voorburg South Holland 2271 BR",
    "addr:housenumber":"22",
    "addr:postcode":"2271 br",
    "addr:street":"Zwartelaan",
    "iso:country":"NL",
    "sg:address":"Zwartelaan 22",
    "sg:city":"Voorburg",
    "sg:classifiers":[
        {
            "category":"Professional",
            "subcategory":"Accounting & Tax Preparation",
            "type":"Services"
        }
    ],
    "sg:phone":"+31 70 386 7363",
    "sg:postcode":"2271 BR",
    "sg:province":"South Holland",
    "sg:tags":[
        "accountant"
    ],
    "wof:name":"Accountants- En Belastingadv Posthumus & De Winter",
    "wof:placetype":"venue"
},
  "geometry": {"coordinates":[4.360647,52.066826],"type":"Point"}
}