{
  "type": "Feature",
  "properties": {
    "addr:full":"De Bark 6 Baarn Utrecht 3742 HC",
    "addr:housenumber":"6",
    "addr:postcode":"3742 hc",
    "addr:street":"De Bark",
    "iso:country":"NL",
    "sg:address":"De Bark 6",
    "sg:city":"Baarn",
    "sg:orig_category":"Bedrijfsopleidingen",
    "sg:phone":"+31 35 542 6910",
    "sg:postcode":"3742 HC",
    "sg:province":"Utrecht",
    "wof:name":"Hofman, Henk",
    "wof:placetype":"venue"
},
  "geometry": {"coordinates":[5.303716,52.206886],"type":"Point"}
}