{
  "type": "Feature",
  "properties": {
    "addr:full":"Norholm 33 Hoofddorp Noord-Holland 2133 HJ",
    "addr:housenumber":"33",
    "addr:postcode":"2133 hj",
    "addr:street":"Norholm",
    "iso:country":"NL",
    "sg:address":"Norholm 33",
    "sg:city":"Hoofddorp",
    "sg:classifiers":[
        {
            "category":"Professional",
            "subcategory":"Management & Consulting",
            "type":"Services"
        }
    ],
    "sg:phone":"+31 23 555 3706",
    "sg:postcode":"2133 HJ",
    "sg:province":"Noord-Holland",
    "sg:tags":[
        "relation",
        "adviesbureaus",
        "public"
    ],
    "sg:website":"http://www.peterzwetsloot.com",
    "wof:name":"Zwetsloot, Peter",
    "wof:placetype":"venue"
},
  "geometry": {"coordinates":[4.670098,52.313171],"type":"Point"}
}