{
  "type": "Feature",
  "properties": {
    "addr:full":"Van Broekhuisenstraat 11 Ammerzoden Gelderland 5324 CZ",
    "addr:housenumber":"11",
    "addr:postcode":"5324",
    "addr:street":"Van Broekhuisenstraat;Gelderland",
    "iso:country":"NL",
    "sg:address":"Van Broekhuisenstraat 11",
    "sg:city":"Ammerzoden",
    "sg:orig_category":"Bedrijfsinventaris Gh",
    "sg:phone":"+31 73 599 1730",
    "sg:postcode":"5324 CZ",
    "sg:province":"Gelderland",
    "wof:name":"Mb Koeltechniek Bv",
    "wof:placetype":"venue"
},
  "geometry": {"coordinates":[5.212946,51.747299],"type":"Point"}
}