{
  "type": "Feature",
  "properties": {
    "addr:full":"Zonnewijzer 25 Amersfoort Utrecht 3824 EE",
    "addr:housenumber":"25",
    "addr:postcode":"3824 ee",
    "addr:street":"Zonnewijzer",
    "iso:country":"NL",
    "sg:address":"Zonnewijzer 25",
    "sg:city":"Amersfoort",
    "sg:orig_category":"Wasserettes And Stomerijen",
    "sg:phone":"+31 33 455 2727",
    "sg:postcode":"3824 EE",
    "sg:province":"Utrecht",
    "wof:name":"Stomerij Van Soest",
    "wof:placetype":"venue"
},
  "geometry": {"coordinates":[5.3758077621,52.1992950439],"type":"Point"}
}