{
  "type": "Feature",
  "properties": {
    "addr:full":"Rivium 1E Straat 199 Capelle A/D Ijssel Zuid-Holland 2909 LE",
    "addr:housenumber":"199;a / d",
    "addr:postcode":"2909 le",
    "addr:street":"Rivium 1E Straat",
    "iso:country":"NL",
    "sg:address":"Rivium 1E Straat 199",
    "sg:city":"Capelle A/D Ijssel",
    "sg:orig_category":"Elektronische Bedrijfsinstallaties",
    "sg:phone":"+31 10 266 7555",
    "sg:postcode":"2909 LE",
    "sg:province":"Zuid-Holland",
    "wof:name":"Geldnet Bv",
    "wof:placetype":"venue"
},
  "geometry": {"coordinates":[4.54627,51.912369],"type":"Point"}
}