{
  "type": "Feature",
  "properties": {
    "iso:country":"NL",
    "sg:address":"Woestduinln 73 A",
    "sg:city":"Doorn",
    "sg:orig_category":"Sportverenigingen En Ontspannings- Verenigingen",
    "sg:phone":"+31 343 421 266",
    "sg:postcode":"3941 XC",
    "sg:province":"Utrecht",
    "wof:name":"Ludenti Doorn Tennisver",
    "wof:placetype":"venue"
},
  "geometry": {"coordinates":[5.332069,52.043365],"type":"Point"}
}