{
  "type": "Feature",
  "properties": {
    "addr:full":"Sweerssenkamp 18 Zwolle Overijssel 8014 GP",
    "addr:housenumber":"18",
    "addr:postcode":"8014 gp",
    "addr:street":"Sweerssenkamp",
    "iso:country":"NL",
    "sg:address":"Sweerssenkamp 18",
    "sg:city":"Zwolle",
    "sg:orig_category":"Zonnebank- En Solariumcentra",
    "sg:phone":"+31 38 466 2480",
    "sg:postcode":"8014 GP",
    "sg:province":"Overijssel",
    "wof:name":"Sunline",
    "wof:placetype":"venue"
},
  "geometry": {"coordinates":[6.119265,52.48745],"type":"Point"}
}