{
  "type": "Feature",
  "properties": {
    "iso:country":"NL",
    "sg:address":"Winkelhof 54",
    "sg:city":"Leiderdorp",
    "sg:orig_category":"Bloemen And Planten",
    "sg:phone":"+31 71 541 6193",
    "sg:postcode":"2353 TV",
    "sg:province":"Zuid-Holland",
    "wof:name":"Voila",
    "wof:placetype":"venue"
},
  "geometry": {"coordinates":[4.531946,52.162731],"type":"Point"}
}