{
  "type": "Feature",
  "properties": {
    "addr:full":"Zandumerweg 74 Oldekerk Groningen 9821 TH",
    "addr:housenumber":"74",
    "addr:postcode":"9821 th",
    "addr:street":"Zandumerweg",
    "iso:country":"NL",
    "sg:address":"Zandumerweg 74",
    "sg:city":"Oldekerk",
    "sg:classifiers":[
        {
            "category":"Retail",
            "subcategory":"Storage",
            "type":"Services"
        }
    ],
    "sg:phone":"+31 594 504 941",
    "sg:postcode":"9821 TH",
    "sg:province":"Groningen",
    "sg:tags":[
        "opslag",
        "bewaring"
    ],
    "wof:name":"R Bos",
    "wof:placetype":"venue"
},
  "geometry": {"coordinates":[6.3150148392,53.2350769043],"type":"Point"}
}