{
  "type": "Feature",
  "properties": {
    "iso:country":"NL",
    "sg:address":"V Oldenbarnev Str 152B",
    "sg:city":"Rotterdam",
    "sg:orig_category":"Kappers",
    "sg:phone":"+31 10 412 2752",
    "sg:postcode":"3012 GX",
    "sg:province":"South Holland",
    "wof:name":"Fong Ka",
    "wof:placetype":"venue"
},
  "geometry": {"coordinates":[4.4784550667,51.9228363037],"type":"Point"}
}