{
  "type": "Feature",
  "properties": {
    "iso:country":"NL",
    "sg:address":"Demkaweg 11",
    "sg:city":"Utrecht",
    "sg:orig_category":"Architecten",
    "sg:phone":"+31 30 242 8345",
    "sg:postcode":"3555 HW",
    "sg:province":"Utrecht",
    "wof:name":"Econsult Environmental Management",
    "wof:placetype":"venue"
},
  "geometry": {"coordinates":[5.080136,52.111073],"type":"Point"}
}