{
  "type": "Feature",
  "properties": {
    "addr:full":"Koorstr 14 Alkmaar Noord-Holland 1811 GP",
    "addr:housenumber":"14",
    "addr:postcode":"1811 gp",
    "addr:street":"Koorstr",
    "iso:country":"NL",
    "sg:address":"Koorstr 14",
    "sg:city":"Alkmaar",
    "sg:orig_category":"Postzegels",
    "sg:phone":"+31 72 511 9982",
    "sg:postcode":"1811 GP",
    "sg:province":"Noord-Holland",
    "wof:name":"Alexander",
    "wof:placetype":"venue"
},
  "geometry": {"coordinates":[4.743909,52.631924],"type":"Point"}
}