{
  "type": "Feature",
  "properties": {
    "addr:full":"Eykmanstraat 18 Wageningen Gelderland 6706 JX",
    "addr:housenumber":"18",
    "addr:postcode":"6706 jx",
    "addr:street":"Eykmanstraat;Gelderland",
    "iso:country":"NL",
    "sg:address":"Eykmanstraat 18",
    "sg:city":"Wageningen",
    "sg:orig_category":"Vertaal- And Tolkenbureaus",
    "sg:phone":"+31 317 423 369",
    "sg:postcode":"6706 JX",
    "sg:province":"Gelderland",
    "wof:name":"B.J. Tolkamp",
    "wof:placetype":"venue"
},
  "geometry": {"coordinates":[5.67425,51.978321],"type":"Point"}
}