{
  "type": "Feature",
  "properties": {
    "addr:full":"J V Vessemsngl 39 Rotterdam Zuid-Holland 3065 NH",
    "addr:housenumber":"39",
    "addr:postcode":"3065 nh",
    "addr:street":"J;Vessemsngl",
    "iso:country":"NL",
    "sg:address":"J V Vessemsngl 39",
    "sg:city":"Rotterdam",
    "sg:orig_category":"Adviesbureaus Bedrijfsorganisatie",
    "sg:phone":"+31 10 202 5929",
    "sg:postcode":"3065 NH",
    "sg:province":"Zuid-Holland",
    "wof:name":"Muller",
    "wof:placetype":"venue"
},
  "geometry": {"coordinates":[4.55056,51.923611],"type":"Point"}
}