{
  "type": "Feature",
  "properties": {
    "iso:country":"NL",
    "sg:address":"Business Pk Stein 205A",
    "sg:city":"Elsloo Lb",
    "sg:orig_category":"Verzekeringen - Verzekeringskantoren",
    "sg:phone":"+31 46 477 5171",
    "sg:postcode":"6181 MB",
    "sg:province":"BE.05",
    "wof:name":"Schumacher",
    "wof:placetype":"venue"
},
  "geometry": {"coordinates":[5.738695,50.960476],"type":"Point"}
}