{
  "type": "Feature",
  "properties": {
    "addr:full":"Het Heem 79 Breskens Zeeland 4511 PP",
    "addr:housenumber":"79",
    "addr:postcode":"4511 pp",
    "addr:street":"Het Heem",
    "iso:country":"NL",
    "sg:address":"Het Heem 79",
    "sg:city":"Breskens",
    "sg:orig_category":"Visserijbedrijven",
    "sg:phone":"+31 117 381 785",
    "sg:postcode":"4511 PP",
    "sg:province":"Zeeland",
    "wof:name":"Fenijn Van Hanegem, H J",
    "wof:placetype":"venue"
},
  "geometry": {"coordinates":[3.53862,51.397282],"type":"Point"}
}