{
  "type": "Feature",
  "properties": {
    "addr:full":"Galglaan 11 Rijnsburg Zuid-Holland 2231 ND",
    "addr:housenumber":"11",
    "addr:postcode":"2231 nd",
    "addr:street":"Galglaan",
    "iso:country":"NL",
    "sg:address":"Galglaan 11",
    "sg:city":"Rijnsburg",
    "sg:orig_category":"Bedrijfsinventaris Gh",
    "sg:phone":"+31 71 402 2621",
    "sg:postcode":"2231 ND",
    "sg:province":"Zuid-Holland",
    "wof:name":"Installatieburo Eval Bv",
    "wof:placetype":"venue"
},
  "geometry": {"coordinates":[4.452678,52.204113],"type":"Point"}
}