{
  "type": "Feature",
  "properties": {
    "addr:full":"Tulpenpad 27 Stellendam Zuid-Holland 3251 CW",
    "addr:housenumber":"27",
    "addr:postcode":"3251 cw",
    "addr:street":"Tulpenpad",
    "iso:country":"NL",
    "sg:address":"Tulpenpad 27",
    "sg:city":"Stellendam",
    "sg:orig_category":"Sportverenigingen En Ontspannings- Verenigingen",
    "sg:phone":"+31 187 492 849",
    "sg:postcode":"3251 CW",
    "sg:province":"Zuid-Holland",
    "sg:website":"http://home.wxs.nl/~jobreur",
    "wof:name":"Fanfare Orkest",
    "wof:placetype":"venue"
},
  "geometry": {"coordinates":[4.021163,51.806271],"type":"Point"}
}