{
  "type": "Feature",
  "properties": {
    "addr:full":"Christinastr 52 Rayon Eygelshoven Eygelshoven Limburg 6471 EW",
    "addr:housenumber":"52",
    "addr:postcode":"6471 ew",
    "addr:street":"Christinastr",
    "iso:country":"NL",
    "sg:address":"Christinastr 52 Rayon Eygelshoven",
    "sg:city":"Eygelshoven",
    "sg:orig_category":"Woningbouw- Verenigingen En -Stichtingen",
    "sg:phone":"+31 45 535 1245",
    "sg:postcode":"6471 EW",
    "sg:province":"Limburg",
    "wof:name":"Vastgoed Roer En Maas",
    "wof:placetype":"venue"
},
  "geometry": {"coordinates":[6.0597100258,50.8941268921],"type":"Point"}
}