{
  "type": "Feature",
  "properties": {
    "addr:full":"Wierbalg 1721 Den Helder Noord-Holland 1788 TW",
    "addr:housenumber":"1721",
    "addr:postcode":"1788 tw",
    "addr:street":"Wierbalg",
    "iso:country":"NL",
    "sg:address":"Wierbalg 1721",
    "sg:city":"Den Helder",
    "sg:orig_category":"Webdesign Bureaus",
    "sg:phone":"+31 223 690 211",
    "sg:postcode":"1788 TW",
    "sg:province":"Noord-Holland",
    "sg:website":"http://www.webdesign2000.nl",
    "wof:name":"Webdesign 2000 Nl",
    "wof:placetype":"venue"
},
  "geometry": {"coordinates":[4.7334189415,52.8891792297],"type":"Point"}
}