{
  "type": "Feature",
  "properties": {
    "addr:full":"Baan 14-20 Rotterdam Zuid-Holland 3011 CB",
    "addr:housenumber":"14-20",
    "addr:postcode":"3011 cb",
    "addr:street":"Baan",
    "iso:country":"NL",
    "sg:address":"Baan 14-20",
    "sg:city":"Rotterdam",
    "sg:classifiers":[
        {
            "category":"Travel",
            "subcategory":"Hotels & Motels",
            "type":"Entertainment"
        }
    ],
    "sg:phone":"+31 10 214 1922",
    "sg:postcode":"3011 CB",
    "sg:province":"Zuid-Holland",
    "sg:website":"http://www.eurohotelcentrum.nl",
    "wof:name":"Eurohotel-Centrum",
    "wof:placetype":"venue"
},
  "geometry": {"coordinates":[4.480695,51.915257],"type":"Point"}
}