{
  "type": "Feature",
  "properties": {
    "iso:country":"NL",
    "sg:address":"Oude Molenstr 6",
    "sg:city":"Simpelveld",
    "sg:orig_category":"Begrafenisverzorging",
    "sg:phone":"+31 45 544 2476",
    "sg:postcode":"6369 XP",
    "sg:province":"Limburg",
    "wof:name":"Helpt Elkander",
    "wof:placetype":"venue"
},
  "geometry": {"coordinates":[5.972752,50.832706],"type":"Point"}
}