{
  "type": "Feature",
  "properties": {
    "addr:full":"Jupiterweg 8 Leeuwarden Provincie Friesland 8938 AE",
    "addr:housenumber":"8",
    "addr:postcode":"8938 ae",
    "addr:street":"Jupiterweg;Provincie Friesland",
    "iso:country":"NL",
    "sg:address":"Jupiterweg 8",
    "sg:city":"Leeuwarden",
    "sg:orig_category":"Verhuur Catering-, Feest- En Evenementbenodigdheden",
    "sg:phone":"+31 58 280 0041",
    "sg:postcode":"8938 AE",
    "sg:province":"Provincie Friesland",
    "wof:name":"Reserv 4",
    "wof:placetype":"venue"
},
  "geometry": {"coordinates":[5.845484,53.196785],"type":"Point"}
}