{
  "type": "Feature",
  "properties": {
    "addr:full":"De Netelhorst 7 Hattem Gelderland 8051 KE",
    "addr:housenumber":"7",
    "addr:postcode":"8051 ke",
    "addr:street":"De Netelhorst;Gelderland",
    "iso:country":"NL",
    "sg:address":"De Netelhorst 7",
    "sg:city":"Hattem",
    "sg:orig_category":"Verbouwingen",
    "sg:phone":"+31 38 444 7607",
    "sg:postcode":"8051 KE",
    "sg:province":"Gelderland",
    "wof:name":"Dieren, Van",
    "wof:placetype":"venue"
},
  "geometry": {"coordinates":[6.042663,52.485516],"type":"Point"}
}