{
  "type": "Feature",
  "properties": {
    "addr:full":"R. Feithlaan 56 Harderwijk Gelderland 8072 GT",
    "addr:housenumber":"56",
    "addr:postcode":"8072 gt",
    "addr:street":"Feithlaan;Gelderland",
    "iso:country":"NL",
    "sg:address":"R. Feithlaan 56",
    "sg:city":"Harderwijk",
    "sg:orig_category":"Paramedische Behandelingen",
    "sg:phone":"+31 341 426 600",
    "sg:postcode":"8072 GT",
    "sg:province":"Gelderland",
    "wof:name":"Mevr. P.G. Van Der Schans",
    "wof:placetype":"venue"
},
  "geometry": {"coordinates":[5.61719,52.347038],"type":"Point"}
}