{
  "type": "Feature",
  "properties": {
    "addr:full":"Het Oude Diep 9 Zwartsluis NL.08 8064 PN",
    "addr:housenumber":"9;nl.08",
    "addr:postcode":"8064 pn",
    "addr:street":"Het Oude Diep",
    "iso:country":"NL",
    "sg:address":"Het Oude Diep 9",
    "sg:city":"Zwartsluis",
    "sg:orig_category":"Vers Brood And Banket Fab",
    "sg:phone":"+31 38 386 6833",
    "sg:postcode":"8064 PN",
    "sg:province":"NL.08",
    "wof:name":"Van Dijk Banket Bv",
    "wof:placetype":"venue"
},
  "geometry": {"coordinates":[6.088625,52.646198],"type":"Point"}
}