{
  "type": "Feature",
  "properties": {
    "iso:country":"NL",
    "sg:address":"Jacob Van Lennepkade 24",
    "sg:city":"Amsterdam",
    "sg:orig_category":"Diverse Bedrijfsinstallaties Gh",
    "sg:phone":"+31 20 683 2903",
    "sg:postcode":"1053 MK",
    "sg:province":"Noord-Holland",
    "wof:name":"Mylos Waterprodukten Amsterdam Bv",
    "wof:placetype":"venue"
},
  "geometry": {"coordinates":[4.875476,52.366489],"type":"Point"}
}