{
  "type": "Feature",
  "properties": {
    "addr:full":"Kerkweg 20 Haarle Gem Hellend Overijssel 7448 AD",
    "addr:housenumber":"20",
    "addr:postcode":"7448 ad",
    "addr:street":"Kerkweg;Overijssel",
    "iso:country":"NL",
    "sg:address":"Kerkweg 20",
    "sg:city":"Haarle Gem Hellend",
    "sg:orig_category":"Verlichting And Huishoudartikelen",
    "sg:phone":"+31 548 595 214",
    "sg:postcode":"7448 AD",
    "sg:province":"Overijssel",
    "wof:name":"A.Th. Wagenmans-Hoonhorst",
    "wof:placetype":"venue"
},
  "geometry": {"coordinates":[6.381125,52.359623],"type":"Point"}
}