{
  "type": "Feature",
  "properties": {
    "addr:full":"Zwanenkamp 931 Maarssen Utrecht 3607 PZ",
    "addr:housenumber":"931",
    "addr:postcode":"3607 pz",
    "addr:street":"Zwanenkamp",
    "iso:country":"NL",
    "sg:address":"Zwanenkamp 931",
    "sg:city":"Maarssen",
    "sg:orig_category":"Loodgieterswerk, Verwarming And Sanitaire Installaties",
    "sg:phone":"+31 6 51547822",
    "sg:postcode":"3607 PZ",
    "sg:province":"Utrecht",
    "wof:name":"Jack Van Haren",
    "wof:placetype":"venue"
},
  "geometry": {"coordinates":[5.010319,52.143589],"type":"Point"}
}