{
  "type": "Feature",
  "properties": {
    "addr:full":"Touwslagersbaan 17 Wijchen Gelderland 6602 AH",
    "addr:housenumber":"17",
    "addr:postcode":"6602 ah",
    "addr:street":"Touwslagersbaan;Gelderland",
    "iso:country":"NL",
    "sg:address":"Touwslagersbaan 17",
    "sg:city":"Wijchen",
    "sg:orig_category":"Opticiens",
    "sg:phone":"+31 24 641 7295",
    "sg:postcode":"6602 AH",
    "sg:province":"Gelderland",
    "wof:name":"Pearle Opticiens",
    "wof:placetype":"venue"
},
  "geometry": {"coordinates":[5.7247219086,51.8070487976],"type":"Point"}
}