{
  "type": "Feature",
  "properties": {
    "addr:full":"R Holstln 980 Delft South Holland 2624 JM",
    "addr:housenumber":"980",
    "addr:postcode":"2624 jm",
    "iso:country":"NL",
    "sg:address":"R Holstln 980",
    "sg:city":"Delft",
    "sg:orig_category":"Onderhoudswerken",
    "sg:phone":"+31 6 53369260",
    "sg:postcode":"2624 JM",
    "sg:province":"South Holland",
    "wof:name":"Guldemundt Totaal Onderhoud",
    "wof:placetype":"venue"
},
  "geometry": {"coordinates":[4.35634,51.995491],"type":"Point"}
}