{
  "type": "Feature",
  "properties": {
    "iso:country":"NL",
    "sg:address":"Amersfoortsewg 47A",
    "sg:city":"Doorn",
    "sg:orig_category":"Verzekeringen - Verzekeringskantoren",
    "sg:phone":"+31 343 511 411",
    "sg:postcode":"3941 EK",
    "sg:province":"Utrecht",
    "wof:name":"Bakker & Stegenga",
    "wof:placetype":"venue"
},
  "geometry": {"coordinates":[5.345128,52.036442],"type":"Point"}
}