{
  "type": "Feature",
  "properties": {
    "iso:country":"NL",
    "sg:address":"Topaasstraat 49",
    "sg:city":"Nijmegen",
    "sg:orig_category":"Paramedische Behandelingen",
    "sg:phone":"+31 24 355 9989",
    "sg:postcode":"6534 ZJ",
    "sg:province":"Gelderland",
    "wof:name":"E.J.M. Hoefnagel",
    "wof:placetype":"venue"
},
  "geometry": {"coordinates":[5.82796,51.810722],"type":"Point"}
}