{
  "type": "Feature",
  "properties": {
    "addr:full":"Zonnebloemstraat 1 Veenendaal Utrecht 3905 ZC",
    "addr:housenumber":"1",
    "addr:postcode":"3905 zc",
    "addr:street":"Zonnebloemstraat",
    "iso:country":"NL",
    "sg:address":"Zonnebloemstraat 1",
    "sg:city":"Veenendaal",
    "sg:orig_category":"Overheidsdiensten",
    "sg:phone":"+31 318 520 523",
    "sg:postcode":"3905 ZC",
    "sg:province":"Utrecht",
    "wof:name":"Het Turfke",
    "wof:placetype":"venue"
},
  "geometry": {"coordinates":[5.5458011627,52.0326347351],"type":"Point"}
}