{
  "type": "Feature",
  "properties": {
    "addr:full":"Transportstr 6 Bergambacht Zuid-Holland 2861 DZ",
    "addr:housenumber":"6",
    "addr:postcode":"2861 dz",
    "addr:street":"Transportstr",
    "iso:country":"NL",
    "sg:address":"Transportstr 6",
    "sg:city":"Bergambacht",
    "sg:classifiers":[
        {
            "category":"Retail",
            "subcategory":"Auto Repair",
            "type":"Services"
        }
    ],
    "sg:phone":"+31 182 351 249",
    "sg:postcode":"2861 DZ",
    "sg:province":"Zuid-Holland",
    "sg:tags":[
        "garage"
    ],
    "wof:name":"Both",
    "wof:placetype":"venue"
},
  "geometry": {"coordinates":[4.789672,51.929886],"type":"Point"}
}