{
  "type": "Feature",
  "properties": {
    "iso:country":"NL",
    "sg:address":"Kerkdijk 23",
    "sg:city":"Made",
    "sg:orig_category":"Bouwmaterialen Gh",
    "sg:phone":"+31 162 684 384",
    "sg:postcode":"4921 XC",
    "sg:province":"Noord-Brabant",
    "wof:name":"Segeren Stallenbouw",
    "wof:placetype":"venue"
},
  "geometry": {"coordinates":[-120.11932400000001,36.956474],"type":"Point"}
}