{
  "type": "Feature",
  "properties": {
    "iso:country":"NL",
    "sg:address":"Europaweg-Noord 150",
    "sg:city":"Landgraaf",
    "sg:orig_category":"Wegen And Sportterreinen",
    "sg:phone":"+31 45 569 6120",
    "sg:postcode":"6374 CL",
    "sg:province":"Limburg",
    "wof:name":"Bv Aannemingsmaatschappij Janssen & De Jong",
    "wof:placetype":"venue"
},
  "geometry": {"coordinates":[6.030687809,50.9277648926],"type":"Point"}
}