{
  "type": "Feature",
  "properties": {
    "iso:country":"NL",
    "sg:address":"Raadhuisplein 2",
    "sg:city":"Rijen",
    "sg:orig_category":"Boekenuitgeverijen",
    "sg:phone":"+31 161 223 964",
    "sg:postcode":"5121  J",
    "sg:province":"Noord-Brabant",
    "wof:name":"Bruna",
    "wof:placetype":"venue"
},
  "geometry": {"coordinates":[4.912418,51.589642],"type":"Point"}
}