{
  "type": "Feature",
  "properties": {
    "addr:full":"Brouwerstr 30 Ridderkerk South Holland 2984 AR",
    "addr:housenumber":"30",
    "addr:postcode":"2984",
    "addr:street":"Brouwerstr",
    "iso:country":"NL",
    "sg:address":"Brouwerstr 30",
    "sg:city":"Ridderkerk",
    "sg:orig_category":"Verpakkingen En Verpakkingsmaterialen",
    "sg:phone":"+31 180 462 855",
    "sg:postcode":"2984 AR",
    "sg:province":"South Holland",
    "sg:website":"http://www.ligtermoet.nl",
    "wof:name":"Ligtermoet Bv",
    "wof:placetype":"venue"
},
  "geometry": {"coordinates":[4.615653,51.876869],"type":"Point"}
}