{
  "type": "Feature",
  "properties": {
    "addr:full":"Borgmanhof 15 Nijkerk Gld Gelderland 3861 GE",
    "addr:housenumber":"15",
    "addr:postcode":"3861",
    "addr:street":"Borgmanhof;Gld Gelderland",
    "iso:country":"NL",
    "sg:address":"Borgmanhof 15",
    "sg:city":"Nijkerk Gld",
    "sg:orig_category":"Kantoorapparatuur Gh",
    "sg:phone":"+31 33 247 5100",
    "sg:postcode":"3861 GE",
    "sg:province":"Gelderland",
    "wof:name":"Boekhandel Roodbeen En Van Hartskamp",
    "wof:placetype":"venue"
},
  "geometry": {"coordinates":[5.4750499725,52.2227096558],"type":"Point"}
}