{
  "type": "Feature",
  "properties": {
    "addr:full":"Kissel 46A Heerlen Limburg 6416 AC",
    "addr:housenumber":"46a",
    "addr:postcode":"6416 ac",
    "addr:street":"Kissel",
    "iso:country":"NL",
    "sg:address":"Kissel 46A",
    "sg:city":"Heerlen",
    "sg:orig_category":"Kantoorartikelen",
    "sg:phone":"+31 45 572 3142",
    "sg:postcode":"6416 AC",
    "sg:province":"Limburg",
    "wof:name":"Rockmart Ltd Kantoormeubelen",
    "wof:placetype":"venue"
},
  "geometry": {"coordinates":[6.0007958412,50.8895645142],"type":"Point"}
}