{
  "type": "Feature",
  "properties": {
    "iso:country":"NL",
    "sg:address":"Kermisland 110",
    "sg:city":"Arnhem",
    "sg:orig_category":"Ingenieursbureaus",
    "sg:phone":"+31 26 369 8444",
    "sg:postcode":"6825 JC",
    "sg:province":"Gelderland",
    "wof:name":"Fugro Bv",
    "wof:placetype":"venue"
},
  "geometry": {"coordinates":[5.958078,51.982647],"type":"Point"}
}