{
  "type": "Feature",
  "properties": {
    "addr:full":"Hallseweg 12 Hall Gelderland 6964 AM",
    "addr:housenumber":"12",
    "addr:postcode":"6964",
    "addr:street":"Hallseweg;Gelderland",
    "iso:country":"NL",
    "sg:address":"Hallseweg 12",
    "sg:city":"Hall",
    "sg:orig_category":"Kampeerterreinen",
    "sg:phone":"+31 313 651 350",
    "sg:postcode":"6964 AM",
    "sg:province":"Gelderland",
    "wof:name":"Nivon Natuurterrein Hallse Hull",
    "wof:placetype":"venue"
},
  "geometry": {"coordinates":[-113.1963882446,46.5890541077],"type":"Point"}
}