{
  "type": "Feature",
  "properties": {
    "addr:full":"Benthuizerstraat 50 Rotterdam Zuid-Holland 3036 CJ",
    "addr:housenumber":"50",
    "addr:postcode":"3036 cj",
    "addr:street":"Benthuizerstraat",
    "iso:country":"NL",
    "sg:address":"Benthuizerstraat 50",
    "sg:city":"Rotterdam",
    "sg:classifiers":[
        {
            "category":"Communications",
            "subcategory":"Television Station",
            "type":"Services"
        }
    ],
    "sg:phone":"+31 10 467 0573",
    "sg:postcode":"3036 CJ",
    "sg:province":"Zuid-Holland",
    "sg:tags":[
        "video",
        "audio",
        "verhuur"
    ],
    "wof:name":"Videoland",
    "wof:placetype":"venue"
},
  "geometry": {"coordinates":[4.47984,51.936508],"type":"Point"}
}