{
  "type": "Feature",
  "properties": {
    "addr:full":"Bernhardln 11 Margraten Limburg 6269 CW",
    "addr:housenumber":"11",
    "addr:postcode":"6269 cw",
    "addr:street":"Bernhardln",
    "iso:country":"NL",
    "sg:address":"Bernhardln 11",
    "sg:city":"Margraten",
    "sg:orig_category":"Kantoor- En Secretariaatsservice",
    "sg:phone":"+31 43 458 2191",
    "sg:postcode":"6269 CW",
    "sg:province":"Limburg",
    "wof:name":"Franssen",
    "wof:placetype":"venue"
},
  "geometry": {"coordinates":[5.8212161064,50.8199081421],"type":"Point"}
}