{
  "type": "Feature",
  "properties": {
    "addr:full":"Zuidplein Zuiderterras 162 Rotterdam Zuid-Holland 3083 BZ",
    "addr:housenumber":"162",
    "addr:postcode":"3083 bz",
    "addr:street":"Zuidplein Zuiderterras",
    "iso:country":"NL",
    "sg:address":"Zuidplein Zuiderterras 162",
    "sg:city":"Rotterdam",
    "sg:orig_category":"Huishoudapparatuur, Televisies And Radio'S",
    "sg:phone":"+31 10 480 5333",
    "sg:postcode":"3083 BZ",
    "sg:province":"Zuid-Holland",
    "wof:name":"It`S",
    "wof:placetype":"venue"
},
  "geometry": {"coordinates":[4.48876,51.885029],"type":"Point"}
}