{
  "type": "Feature",
  "properties": {
    "addr:full":"De Oude Veiling 109 Zwaag Noord-Holland 1689 AD",
    "addr:housenumber":"109",
    "addr:postcode":"1689 ad",
    "addr:street":"De Oude Veiling",
    "iso:country":"NL",
    "sg:address":"De Oude Veiling 109",
    "sg:city":"Zwaag",
    "sg:orig_category":"Metaalbekleding And -Behandeling",
    "sg:phone":"+31 229 234 601",
    "sg:postcode":"1689 AD",
    "sg:province":"Noord-Holland",
    "wof:name":"Weinzierl Fijnmetaal",
    "wof:placetype":"venue"
},
  "geometry": {"coordinates":[5.062934,52.662022],"type":"Point"}
}