{
  "type": "Feature",
  "properties": {
    "addr:full":"Wedderwg 25 Vriescheloo Groningen 9699 RA",
    "addr:housenumber":"25",
    "addr:postcode":"9699 ra",
    "addr:street":"Wedderwg",
    "iso:country":"NL",
    "sg:address":"Wedderwg 25",
    "sg:city":"Vriescheloo",
    "sg:classifiers":[
        {
            "category":"Banks & Credit Unions",
            "subcategory":"Investment Brokerage",
            "type":"Services"
        }
    ],
    "sg:phone":"+31 597 541 860",
    "sg:postcode":"9699 RA",
    "sg:province":"Groningen",
    "sg:tags":[
        "pension"
    ],
    "wof:name":"Stee En Stoetje Pension",
    "wof:placetype":"venue"
},
  "geometry": {"coordinates":[7.112157,53.068047],"type":"Point"}
}