{
  "type": "Feature",
  "properties": {
    "addr:full":"Weerdsngl Wz 18Bis Utrecht Utrecht 3513 BB",
    "addr:housenumber":"18bis",
    "addr:postcode":"3513 bb",
    "addr:street":"Weerdsngl Wz",
    "iso:country":"NL",
    "sg:address":"Weerdsngl Wz 18Bis",
    "sg:city":"Utrecht",
    "sg:classifiers":[
        {
            "category":"Utilities",
            "subcategory":"Cable",
            "type":"Services"
        }
    ],
    "sg:phone":"+31 30 234 0272",
    "sg:postcode":"3513 BB",
    "sg:province":"Utrecht",
    "sg:tags":[
        "masseur",
        "en",
        "heilgymnasten"
    ],
    "sg:website":"http://www.esoterra.nl",
    "wof:name":"Esoterra",
    "wof:placetype":"venue"
},
  "geometry": {"coordinates":[5.110962,52.096157],"type":"Point"}
}