{
  "type": "Feature",
  "properties": {
    "iso:country":"NL",
    "sg:address":"Groenenborgh 21",
    "sg:city":"Oisterwijk",
    "sg:orig_category":"Chemische Producten Gh",
    "sg:phone":"+31 13 523 4777",
    "sg:postcode":"5062 DC",
    "sg:province":"Noord-Brabant",
    "wof:name":"Klaas J De Vries Bv",
    "wof:placetype":"venue"
},
  "geometry": {"coordinates":[5.206389,51.576458],"type":"Point"}
}