{
  "type": "Feature",
  "properties": {
    "iso:country":"NL",
    "sg:address":"Wilhelminasingel 250",
    "sg:city":"Weert",
    "sg:orig_category":"Bibliotheken And Openbare Archieven",
    "sg:phone":"+31 495 532 757",
    "sg:postcode":"6001 GV",
    "sg:province":"Limburg",
    "wof:name":"Openbare Bibliotheek Weert",
    "wof:placetype":"venue"
},
  "geometry": {"coordinates":[5.704064,51.25518],"type":"Point"}
}