{
  "type": "Feature",
  "properties": {
    "addr:full":"Bokstr 57 Heerlen Limburg 6413 AS",
    "addr:housenumber":"57",
    "addr:postcode":"6413 as",
    "addr:street":"Bokstr",
    "iso:country":"NL",
    "sg:address":"Bokstr 57",
    "sg:city":"Heerlen",
    "sg:classifiers":[
        {
            "category":"Food & Beverages",
            "subcategory":"Bakery",
            "type":"Retail Goods"
        }
    ],
    "sg:phone":"+31 45 523 2021",
    "sg:postcode":"6413 AS",
    "sg:province":"Limburg",
    "sg:tags":[
        "pizza"
    ],
    "wof:name":"Minaret",
    "wof:placetype":"venue"
},
  "geometry": {"coordinates":[5.960374,50.913563],"type":"Point"}
}