{
  "type": "Feature",
  "properties": {
    "addr:full":"Madioenstr 21 Enschede Overijssel 7541 ZN",
    "addr:housenumber":"21",
    "addr:postcode":"7541 zn",
    "addr:street":"Madioenstr",
    "iso:country":"NL",
    "sg:address":"Madioenstr 21",
    "sg:city":"Enschede",
    "sg:orig_category":"Administratie- En Boekhoudkantoren",
    "sg:phone":"+31 53 431 5328",
    "sg:postcode":"7541 ZN",
    "sg:province":"Overijssel",
    "sg:website":"http://www.mf-administratie.nl",
    "wof:name":"Mf Administratiekantoor",
    "wof:placetype":"venue"
},
  "geometry": {"coordinates":[6.903182,52.21077],"type":"Point"}
}