{
  "type": "Feature",
  "properties": {
    "addr:full":"Haantje 15 Rijswijk Zh Zuid-Holland 2288 CV",
    "addr:housenumber":"15",
    "addr:postcode":"zh;2288 cv",
    "addr:street":"Haantje",
    "iso:country":"NL",
    "sg:address":"Haantje 15",
    "sg:city":"Rijswijk Zh",
    "sg:orig_category":"Bloemen And Planten",
    "sg:phone":"+31 15 213 1830",
    "sg:postcode":"2288 CV",
    "sg:province":"Zuid-Holland",
    "wof:name":"Firma W. Van Veen & Zoon",
    "wof:placetype":"venue"
},
  "geometry": {"coordinates":[4.345086,52.021503],"type":"Point"}
}