{
  "type": "Feature",
  "properties": {
    "addr:full":"Hoefstraat 13 Sint Anthonis Noord-Brabant 5845 BB",
    "addr:housenumber":"13",
    "addr:postcode":"anthonis;5845 bb",
    "addr:street":"Hoefstraat",
    "iso:country":"NL",
    "sg:address":"Hoefstraat 13",
    "sg:city":"Sint Anthonis",
    "sg:orig_category":"Overheidsdiensten",
    "sg:phone":"+31 485 382 494",
    "sg:postcode":"5845 BB",
    "sg:province":"Noord-Brabant",
    "wof:name":"De Hoefslag",
    "wof:placetype":"venue"
},
  "geometry": {"coordinates":[5.8767762184,51.6278839111],"type":"Point"}
}