{
  "type": "Feature",
  "properties": {
    "addr:full":"Mercatorpln 10 Apeldoorn Gelderland 7316 HL",
    "addr:housenumber":"10",
    "addr:postcode":"7316 hl",
    "addr:street":"Mercatorpln;Gelderland",
    "iso:country":"NL",
    "sg:address":"Mercatorpln 10",
    "sg:city":"Apeldoorn",
    "sg:orig_category":"Postkantoren",
    "sg:phone":"+31 55 521 1453",
    "sg:postcode":"7316 HL",
    "sg:province":"Gelderland",
    "sg:website":"http://www.postkantoor.nl",
    "wof:name":"Postkantoor",
    "wof:placetype":"venue"
},
  "geometry": {"coordinates":[5.960199,52.229733],"type":"Point"}
}