{
  "type": "Feature",
  "properties": {
    "addr:full":"Venlosewg 17 Ospel Limburg 6035 RX",
    "addr:housenumber":"17",
    "addr:postcode":"6035 rx",
    "addr:street":"Venlosewg",
    "iso:country":"NL",
    "sg:address":"Venlosewg 17",
    "sg:city":"Ospel",
    "sg:orig_category":"Administratie- En Boekhoudkantoren",
    "sg:phone":"+31 495 641 667",
    "sg:postcode":"6035 RX",
    "sg:province":"Limburg",
    "wof:name":"Goor, W H E Van",
    "wof:placetype":"venue"
},
  "geometry": {"coordinates":[-86.165451,34.620892],"type":"Point"}
}