{
  "type": "Feature",
  "properties": {
    "addr:full":"Steenstr 90 Boxmeer North Brabant 5831 JJ",
    "addr:housenumber":"90",
    "addr:postcode":"5831 jj",
    "addr:street":"Steenstr",
    "iso:country":"NL",
    "sg:address":"Steenstr 90",
    "sg:city":"Boxmeer",
    "sg:orig_category":"Schoenen",
    "sg:phone":"+31 485 571 461",
    "sg:postcode":"5831 JJ",
    "sg:province":"North Brabant",
    "wof:name":"Goossens-De Vlam",
    "wof:placetype":"venue"
},
  "geometry": {"coordinates":[5.950172,51.647522],"type":"Point"}
}