{
  "type": "Feature",
  "properties": {
    "addr:full":"Polderweg 6 Ouderkerk A/D Amstel Noord-Holland 1191 JR",
    "addr:housenumber":"6;a / d;1191",
    "addr:postcode":"jr",
    "addr:street":"Polderweg",
    "iso:country":"NL",
    "sg:address":"Polderweg 6",
    "sg:city":"Ouderkerk A/D Amstel",
    "sg:orig_category":"Schilderwerk",
    "sg:phone":"+31 20 496 3904",
    "sg:postcode":"1191 JR",
    "sg:province":"Noord-Holland",
    "wof:name":"Firma Gebroeders Te Beek",
    "wof:placetype":"venue"
},
  "geometry": {"coordinates":[4.899897,52.294117],"type":"Point"}
}