{
  "type": "Feature",
  "properties": {
    "addr:full":"Vinkenln 32 Malden Gelderland 6581 CL",
    "addr:housenumber":"32",
    "addr:postcode":"6581",
    "addr:street":"Vinkenln;Gelderland",
    "iso:country":"NL",
    "sg:address":"Vinkenln 32",
    "sg:city":"Malden",
    "sg:orig_category":"Adviesbureaus Bedrijfsorganisatie",
    "sg:phone":"+31 24 356 7587",
    "sg:postcode":"6581 CL",
    "sg:province":"Gelderland",
    "wof:name":"Kms",
    "wof:placetype":"venue"
},
  "geometry": {"coordinates":[5.86027,51.785965],"type":"Point"}
}