{
  "type": "Feature",
  "properties": {
    "addr:full":"Rijksweg 48 Wittem Limburg 6286 AH",
    "addr:housenumber":"48",
    "addr:postcode":"6286 ah",
    "addr:street":"Rijksweg",
    "iso:country":"NL",
    "sg:address":"Rijksweg 48",
    "sg:city":"Wittem",
    "sg:orig_category":"Daken And Skeletbouw",
    "sg:phone":"+31 43 451 1999",
    "sg:postcode":"6286 AH",
    "sg:province":"Limburg",
    "wof:name":"Crombach Dakafwerking Bv",
    "wof:placetype":"venue"
},
  "geometry": {"coordinates":[5.940041,50.809128],"type":"Point"}
}