{
  "type": "Feature",
  "properties": {
    "addr:full":"Abstederdijk 28 Utrecht Utrecht 3582 BM",
    "addr:housenumber":"28",
    "addr:postcode":"3582 bm",
    "addr:street":"Abstederdijk",
    "iso:country":"NL",
    "sg:address":"Abstederdijk 28",
    "sg:city":"Utrecht",
    "sg:orig_category":"Fotostudio'S And Fotografen",
    "sg:phone":"+31 30 251 1808",
    "sg:postcode":"3582 BM",
    "sg:province":"Utrecht",
    "wof:name":"Patrick Van Der Sande Publiciteitsfotogr",
    "wof:placetype":"venue"
},
  "geometry": {"coordinates":[5.127854,52.082378],"type":"Point"}
}