{
  "type": "Feature",
  "properties": {
    "addr:full":"Dorpswg 40 Hoornaar Zuid-Holland 4223 NC",
    "addr:housenumber":"40",
    "addr:postcode":"4223 nc",
    "addr:street":"Dorpswg",
    "iso:country":"NL",
    "sg:address":"Dorpswg 40",
    "sg:city":"Hoornaar",
    "sg:orig_category":"Wijnkoperijen En -Groothandel",
    "sg:phone":"+31 184 449 177",
    "sg:postcode":"4223 NC",
    "sg:province":"Zuid-Holland",
    "sg:website":"http://www.vinnum.nl",
    "wof:name":"Vinnum Vof",
    "wof:placetype":"venue"
},
  "geometry": {"coordinates":[4.9434289932,51.8838882446],"type":"Point"}
}