{
  "type": "Feature",
  "properties": {
    "addr:full":"Ged Kattendiep 150 Groningen Groningen 9711 PV",
    "addr:housenumber":"150",
    "addr:postcode":"9711 pv",
    "addr:street":"Kattendiep",
    "iso:country":"NL",
    "sg:address":"Ged Kattendiep 150",
    "sg:city":"Groningen",
    "sg:orig_category":"Zalenverhuur",
    "sg:phone":"+31 50 317 2100",
    "sg:postcode":"9711 PV",
    "sg:province":"Groningen",
    "sg:website":"http://www.hollandcasino.nl",
    "wof:name":"Holland Casino",
    "wof:placetype":"venue"
},
  "geometry": {"coordinates":[6.572601,53.217506],"type":"Point"}
}