{
  "type": "Feature",
  "properties": {
    "iso:country":"NL",
    "sg:address":"Prinsengr 496Sous",
    "sg:city":"Amsterdam",
    "sg:orig_category":"Juridische Adviseurs",
    "sg:phone":"+31 20 528 9021",
    "sg:postcode":"1017 KH",
    "sg:province":"Noord-Holland",
    "sg:website":"http://www.baslegal.nl",
    "wof:name":"Bas & Partners Bv",
    "wof:placetype":"venue"
},
  "geometry": {"coordinates":[4.885315,52.364021],"type":"Point"}
}