{
  "type": "Feature",
  "properties": {
    "addr:full":"St Josephstr 20 S Hertogenbosch North Brabant 5211 NJ",
    "addr:housenumber":"20",
    "addr:postcode":"5211 nj",
    "addr:street":"S Hertogenbosch",
    "iso:country":"NL",
    "sg:address":"St Josephstr 20",
    "sg:city":"S Hertogenbosch",
    "sg:orig_category":"Beeldende Kunstenaars",
    "sg:phone":"+31 73 621 5022",
    "sg:postcode":"5211 NJ",
    "sg:province":"North Brabant",
    "sg:website":"http://www.horizon.nl/NovaZembla",
    "wof:name":"Nova Zembla",
    "wof:placetype":"venue"
},
  "geometry": {"coordinates":[5.307805,51.689869],"type":"Point"}
}