{
  "type": "Feature",
  "properties": {
    "iso:country":"NL",
    "sg:address":"De Flank 20",
    "sg:city":"Klundert",
    "sg:orig_category":"Kantoorartikelen",
    "sg:phone":"+31 168 404 741",
    "sg:postcode":"4791 KP",
    "sg:province":"North Brabant",
    "wof:name":"Kantoormeubelhal",
    "wof:placetype":"venue"
},
  "geometry": {"coordinates":[4.5249972343,51.6647758484],"type":"Point"}
}