{
  "type": "Feature",
  "properties": {
    "iso:country":"NL",
    "sg:address":"Hofstraat 6",
    "sg:city":"Den Oever",
    "sg:orig_category":"Film-, Tv- And Videoproductie",
    "sg:phone":"+31 227 511 825",
    "sg:postcode":"1779 CD",
    "sg:province":"North Holland",
    "wof:name":"Maarten J.W. Weel A.V. Design Bv",
    "wof:placetype":"venue"
},
  "geometry": {"coordinates":[5.024869,52.934551],"type":"Point"}
}