{
  "type": "Feature",
  "properties": {
    "addr:full":"Vlietlaan 37 Rotterdam Zuid-Holland 3061 DT",
    "addr:housenumber":"37",
    "addr:postcode":"3061 dt",
    "addr:street":"Vlietlaan",
    "iso:country":"NL",
    "sg:address":"Vlietlaan 37",
    "sg:city":"Rotterdam",
    "sg:orig_category":"Verlichting And Huishoudartikelen",
    "sg:phone":"+31 10 452 1809",
    "sg:postcode":"3061 DT",
    "sg:province":"Zuid-Holland",
    "wof:name":"Magazijn Van Leeuwen",
    "wof:placetype":"venue"
},
  "geometry": {"coordinates":[4.501921,51.929462],"type":"Point"}
}