{
  "type": "Feature",
  "properties": {
    "addr:full":"Hoofdstr 86 Noordwyk Zh Zuid-Holland 2202 GA",
    "addr:housenumber":"86",
    "addr:postcode":"2202 ga",
    "addr:street":"Hoofdstr",
    "iso:country":"NL",
    "sg:address":"Hoofdstr 86",
    "sg:city":"Noordwyk Zh",
    "sg:orig_category":"Schoenen",
    "sg:phone":"+31 71 361 2705",
    "sg:postcode":"2202 GA",
    "sg:province":"Zuid-Holland",
    "sg:website":"http://www.aadvandenberg.nl",
    "wof:name":"Aad V/D Berg, Modeschoenen",
    "wof:placetype":"venue"
},
  "geometry": {"coordinates":[4.430531,52.243195],"type":"Point"}
}