{
  "type": "Feature",
  "properties": {
    "addr:full":"Wipmolen 1 Amsterdam Noord-Holland 1035 CV",
    "addr:housenumber":"1",
    "addr:postcode":"1035 cv",
    "addr:street":"Wipmolen",
    "iso:country":"NL",
    "sg:address":"Wipmolen 1",
    "sg:city":"Amsterdam",
    "sg:orig_category":"Huidtherapeuten",
    "sg:phone":"+31 20 631 0652",
    "sg:postcode":"1035 CV",
    "sg:province":"Noord-Holland",
    "wof:name":"Jeannette Spelt",
    "wof:placetype":"venue"
},
  "geometry": {"coordinates":[4.889336,52.416965],"type":"Point"}
}