{
  "type": "Feature",
  "properties": {
    "addr:full":"Dorpstr 6A Veldhoven Noord-Brabant 5504 HH",
    "addr:housenumber":"6a",
    "addr:postcode":"5504 hh",
    "addr:street":"Dorpstr",
    "iso:country":"NL",
    "sg:address":"Dorpstr 6A",
    "sg:city":"Veldhoven",
    "sg:orig_category":"Beeldende Kunstenaars",
    "sg:phone":"+31 40 254 1097",
    "sg:postcode":"5504 HH",
    "sg:province":"Noord-Brabant",
    "sg:website":"http://www.dekunstpraktijk.nl",
    "wof:name":"Kunstpraktijk, De",
    "wof:placetype":"venue"
},
  "geometry": {"coordinates":[5.397423,51.402561],"type":"Point"}
}