{
  "type": "Feature",
  "properties": {
    "addr:full":"Jan Pieter Sweelinckstr 3 Amersfoort Utrecht 3816 PA",
    "addr:housenumber":"3",
    "addr:postcode":"3816",
    "addr:street":"Jan Pieter Sweelinckstr",
    "iso:country":"NL",
    "sg:address":"Jan Pieter Sweelinckstr 3",
    "sg:city":"Amersfoort",
    "sg:orig_category":"Boekenuitgeverijen",
    "sg:phone":"+31 33 472 3696",
    "sg:postcode":"3816 PA",
    "sg:province":"Utrecht",
    "wof:name":"F.M. Van Den Hoven Filatelie/Topografie",
    "wof:placetype":"venue"
},
  "geometry": {"coordinates":[5.403733,52.153278],"type":"Point"}
}