{
  "type": "Feature",
  "properties": {
    "addr:full":"Jan Deugtstraat 17 Herkingen Zuid-Holland 3249 AH",
    "addr:housenumber":"17",
    "addr:postcode":"3249 ah",
    "addr:street":"Jan Deugtstraat",
    "iso:country":"NL",
    "sg:address":"Jan Deugtstraat 17",
    "sg:city":"Herkingen",
    "sg:orig_category":"Goederenvervoer Over De Weg",
    "sg:phone":"+31 187 669 383",
    "sg:postcode":"3249 AH",
    "sg:province":"Zuid-Holland",
    "wof:name":"Melissant Transport",
    "wof:placetype":"venue"
},
  "geometry": {"coordinates":[4.092326,51.712383],"type":"Point"}
}