{
  "type": "Feature",
  "properties": {
    "iso:country":"NL",
    "sg:address":"Bosschewg 36",
    "sg:city":"Beek En Donk",
    "sg:orig_category":"Ventilatiesystemen",
    "sg:phone":"+31 492 451 500",
    "sg:postcode":"5741 SX",
    "sg:province":"Noord-Brabant",
    "sg:website":"http://www.slsbv.nl",
    "wof:name":"Sls Bv Luchtkanalen",
    "wof:placetype":"venue"
},
  "geometry": {"coordinates":[5.628042,51.542774],"type":"Point"}
}