{
  "type": "Feature",
  "properties": {
    "addr:full":"Nieuwe Deventerweg 96 Zwolle Overijssel 8014 AK",
    "addr:housenumber":"96",
    "addr:postcode":"8014 ak",
    "addr:street":"Nieuwe Deventerweg",
    "iso:country":"NL",
    "sg:address":"Nieuwe Deventerweg 96",
    "sg:city":"Zwolle",
    "sg:orig_category":"Banken And Kredietinstellingen",
    "sg:phone":"+31 38 465 1822",
    "sg:postcode":"8014 AK",
    "sg:province":"Overijssel",
    "wof:name":"Abn Amro",
    "wof:placetype":"venue"
},
  "geometry": {"coordinates":[6.111146,52.48769],"type":"Point"}
}