{
  "type": "Feature",
  "properties": {
    "addr:full":"Preludestr 36 Enschede NL.08 7534 XJ",
    "addr:housenumber":"36",
    "addr:postcode":"7534 xj",
    "addr:street":"Preludestr",
    "iso:country":"NL",
    "sg:address":"Preludestr 36",
    "sg:city":"Enschede",
    "sg:orig_category":"Beeldende Kunstenaars",
    "sg:phone":"+31 53 461 1502",
    "sg:postcode":"7534 XJ",
    "sg:province":"NL.08",
    "wof:name":"Mooy, R",
    "wof:placetype":"venue"
},
  "geometry": {"coordinates":[6.976315,52.211777],"type":"Point"}
}