{
  "type": "Feature",
  "properties": {
    "addr:full":"Kampenslaan 8 Schildwolde Groningen 9626 TE",
    "addr:housenumber":"8",
    "addr:postcode":"9626 te",
    "addr:street":"Kampenslaan",
    "iso:country":"NL",
    "sg:address":"Kampenslaan 8",
    "sg:city":"Schildwolde",
    "sg:orig_category":"Diverse Dierenfokkers",
    "sg:phone":"+31 598 421 455",
    "sg:postcode":"9626 TE",
    "sg:province":"Groningen",
    "wof:name":"Imkerij De Woldstreek",
    "wof:placetype":"venue"
},
  "geometry": {"coordinates":[6.803367,53.22456],"type":"Point"}
}