{
  "type": "Feature",
  "properties": {
    "addr:full":"Strevelswg 700App 210 Rotterdam South Holland 3083 AS",
    "addr:housenumber":"210",
    "addr:postcode":"3083 as",
    "iso:country":"NL",
    "sg:address":"Strevelswg 700App 210",
    "sg:city":"Rotterdam",
    "sg:orig_category":"Loopbaanbegeleiding",
    "sg:phone":"+31 10 240 4000",
    "sg:postcode":"3083 AS",
    "sg:province":"South Holland",
    "sg:website":"http://www.gaga-education.nl",
    "wof:name":"Gaga Education",
    "wof:placetype":"venue"
},
  "geometry": {"coordinates":[4.49325,51.887348],"type":"Point"}
}