{
  "type": "Feature",
  "properties": {
    "addr:full":"Rooysestr 103A Dreumel Gelderland 6621 AL",
    "addr:housenumber":"103a",
    "addr:postcode":"6621",
    "addr:street":"Gelderland",
    "iso:country":"NL",
    "sg:address":"Rooysestr 103A",
    "sg:city":"Dreumel",
    "sg:orig_category":"Kappers",
    "sg:phone":"+31 487 571 355",
    "sg:postcode":"6621 AL",
    "sg:province":"Gelderland",
    "wof:name":"Dammers, C E",
    "wof:placetype":"venue"
},
  "geometry": {"coordinates":[5.4322972298,51.8508224487],"type":"Point"}
}