{
  "type": "Feature",
  "properties": {
    "addr:full":"Willibrordusln 70 Waalre Noord-Brabant 5581 GH",
    "addr:housenumber":"70",
    "addr:postcode":"5581 gh",
    "addr:street":"Willibrordusln",
    "iso:country":"NL",
    "sg:address":"Willibrordusln 70",
    "sg:city":"Waalre",
    "sg:orig_category":"Open Haarden",
    "sg:phone":"+31 40 221 5044",
    "sg:postcode":"5581 GH",
    "sg:province":"Noord-Brabant",
    "wof:name":"Hartjes, H",
    "wof:placetype":"venue"
},
  "geometry": {"coordinates":[5.452059,51.388779],"type":"Point"}
}