{
  "type": "Feature",
  "properties": {
    "iso:country":"NL",
    "sg:address":"Postbus 3059",
    "sg:city":"Venlo",
    "sg:orig_category":"Hang- En Sluitwerk - Fabrieken En Groothandel",
    "sg:phone":"+31 77 324 4200",
    "sg:postcode":"5902 RB",
    "sg:province":"Zuid-Holland",
    "wof:name":"Uver Bv",
    "wof:placetype":"venue"
},
  "geometry": {"coordinates":[6.17784,51.370201],"type":"Point"}
}