{
  "type": "Feature",
  "properties": {
    "addr:full":"Hanendorperwg 11 Emst Gelderland 8166 JG",
    "addr:housenumber":"11",
    "addr:postcode":"8166 jg",
    "addr:street":"Hanendorperwg;Gelderland",
    "iso:country":"NL",
    "sg:address":"Hanendorperwg 11",
    "sg:city":"Emst",
    "sg:orig_category":"Adviesbureaus Bedrijfsorganisatie",
    "sg:phone":"+31 578 662 493",
    "sg:postcode":"8166 JG",
    "sg:province":"Gelderland",
    "wof:name":"Buurman Bv, A F",
    "wof:placetype":"venue"
},
  "geometry": {"coordinates":[5.973048,52.314117],"type":"Point"}
}