{
  "type": "Feature",
  "properties": {
    "addr:full":"Loeff Berchmakerstraat 9 Utrecht Utrecht 3512 TC",
    "addr:housenumber":"9",
    "addr:postcode":"3512 tc",
    "addr:street":"Loeff Berchmakerstraat",
    "iso:country":"NL",
    "sg:address":"Loeff Berchmakerstraat 9",
    "sg:city":"Utrecht",
    "sg:orig_category":"Kappers",
    "sg:phone":"+31 30 241 6134",
    "sg:postcode":"3512 TC",
    "sg:province":"Utrecht",
    "wof:name":"Jam Hair & Make-Up",
    "wof:placetype":"venue"
},
  "geometry": {"coordinates":[5.1183280945,52.0942420959],"type":"Point"}
}