{
  "type": "Feature",
  "properties": {
    "addr:full":"Goudenregenln 22 Castricum North Holland 1901 SP",
    "addr:housenumber":"22",
    "addr:postcode":"1901 sp",
    "addr:street":"Goudenregenln",
    "iso:country":"NL",
    "sg:address":"Goudenregenln 22",
    "sg:city":"Castricum",
    "sg:orig_category":"Goudsmeden En Zilversmeden",
    "sg:phone":"+31 251 671 114",
    "sg:postcode":"1901 SP",
    "sg:province":"North Holland",
    "sg:website":"http://www.artofjoyce",
    "wof:name":"Art Of Joyce",
    "wof:placetype":"venue"
},
  "geometry": {"coordinates":[4.663352,52.554405],"type":"Point"}
}