{
  "type": "Feature",
  "properties": {
    "iso:country":"NL",
    "sg:address":"Boekel 39",
    "sg:city":"Akersloot",
    "sg:orig_category":"Verlichtingsartikelen - Groothandel",
    "sg:phone":"+31 72 533 6931",
    "sg:postcode":"1921 CE",
    "sg:province":"Noord-Holland",
    "wof:name":"Bakker",
    "wof:placetype":"venue"
},
  "geometry": {"coordinates":[4.753224,52.587116],"type":"Point"}
}