{
  "type": "Feature",
  "properties": {
    "addr:full":"Ammandreef 1 Utrecht Utrecht 3564 GT",
    "addr:housenumber":"1",
    "addr:postcode":"3564 gt",
    "addr:street":"Ammandreef",
    "iso:country":"NL",
    "sg:address":"Ammandreef 1",
    "sg:city":"Utrecht",
    "sg:orig_category":"Fitnesscentra",
    "sg:phone":"+31 30 266 1737",
    "sg:postcode":"3564 GT",
    "sg:province":"Utrecht",
    "sg:website":"http://www.bodyconditioning.nl",
    "wof:name":"Body Conditioning",
    "wof:placetype":"venue"
},
  "geometry": {"coordinates":[5.101018,52.124023],"type":"Point"}
}