{
  "type": "Feature",
  "properties": {
    "addr:full":"N.A.M. Weg 23 Dalerveen Provincie Drenthe 7755 PT",
    "addr:housenumber":"23",
    "addr:postcode":"7755",
    "addr:street":"N.A.M. Weg;Provincie Drenthe;Pt",
    "iso:country":"NL",
    "sg:address":"N.A.M. Weg 23",
    "sg:city":"Dalerveen",
    "sg:orig_category":"Zalenexploitatie",
    "sg:phone":"+31 524 221 374",
    "sg:postcode":"7755 PT",
    "sg:province":"Provincie Drenthe",
    "wof:name":"De Sprong",
    "wof:placetype":"venue"
},
  "geometry": {"coordinates":[6.819655,52.684029],"type":"Point"}
}