{
  "type": "Feature",
  "properties": {
    "addr:full":"Commelinstr 6 Amsterdam Noord-Holland 1093 TR",
    "addr:housenumber":"6",
    "addr:postcode":"1093 tr",
    "addr:street":"Commelinstr",
    "iso:country":"NL",
    "sg:address":"Commelinstr 6",
    "sg:city":"Amsterdam",
    "sg:classifiers":[
        {
            "category":"Utilities",
            "subcategory":"Cable",
            "type":"Services"
        }
    ],
    "sg:phone":"+31 20 463 0692",
    "sg:postcode":"1093 TR",
    "sg:province":"Noord-Holland",
    "sg:tags":[
        "masseur",
        "en",
        "heilgymnasten"
    ],
    "wof:name":"Manonshi Studio",
    "wof:placetype":"venue"
},
  "geometry": {"coordinates":[4.923925,52.363087],"type":"Point"}
}