{
  "type": "Feature",
  "properties": {
    "addr:full":"Bloedkoraalstr 18 , (Mobiele Telefoon) Groningen Groningen 9743 KC",
    "addr:housenumber":"18",
    "addr:postcode":"9743 kc",
    "addr:street":"Bloedkoraalstr",
    "iso:country":"NL",
    "sg:address":"Bloedkoraalstr 18 , (Mobiele Telefoon)",
    "sg:city":"Groningen",
    "sg:orig_category":"Onderhoudswerken",
    "sg:phone":"+31 6 55728290",
    "sg:postcode":"9743 KC",
    "sg:province":"Groningen",
    "wof:name":"Dijkstra, J",
    "wof:placetype":"venue"
},
  "geometry": {"coordinates":[6.524205,53.226883],"type":"Point"}
}