{
  "type": "Feature",
  "properties": {
    "addr:full":"Oosterdijk 44 Sneek Friesland 8601 BV",
    "addr:housenumber":"44",
    "addr:postcode":"8601 bv",
    "addr:street":"Oosterdijk",
    "iso:country":"NL",
    "sg:address":"Oosterdijk 44",
    "sg:city":"Sneek",
    "sg:orig_category":"Opticiens",
    "sg:phone":"+31 515 412 582",
    "sg:postcode":"8601 BV",
    "sg:province":"Friesland",
    "wof:name":"Pearle Opticiens",
    "wof:placetype":"venue"
},
  "geometry": {"coordinates":[5.6619701385,53.0334587097],"type":"Point"}
}