{
  "type": "Feature",
  "properties": {
    "addr:full":"Stadhouderspln 36 Rotterdam Zuid-Holland 3039 ER",
    "addr:housenumber":"36",
    "addr:postcode":"3039 er",
    "addr:street":"Stadhouderspln",
    "iso:country":"NL",
    "sg:address":"Stadhouderspln 36",
    "sg:city":"Rotterdam",
    "sg:orig_category":"Kinderopvang",
    "sg:phone":"+31 10 265 0844",
    "sg:postcode":"3039 ER",
    "sg:province":"Zuid-Holland",
    "wof:name":"Basisbende, De",
    "wof:placetype":"venue"
},
  "geometry": {"coordinates":[4.465402,51.931347],"type":"Point"}
}