{
  "type": "Feature",
  "properties": {
    "addr:full":"Dorpsstr 94A Bunschoten Spakenb Utrecht 3751 ES",
    "addr:housenumber":"94a",
    "addr:postcode":"3751 es",
    "addr:street":"Dorpsstr",
    "iso:country":"NL",
    "sg:address":"Dorpsstr 94A",
    "sg:city":"Bunschoten Spakenb",
    "sg:orig_category":"Kaas",
    "sg:phone":"+31 33 298 3350",
    "sg:postcode":"3751 ES",
    "sg:province":"Utrecht",
    "wof:name":"Gooische Boer, De",
    "wof:placetype":"venue"
},
  "geometry": {"coordinates":[5.3736710548,52.2398757935],"type":"Point"}
}