{
  "type": "Feature",
  "properties": {
    "addr:full":"Peperstr 9 Leeuwarden Friesland 8911 HZ",
    "addr:housenumber":"9",
    "addr:postcode":"8911 hz",
    "addr:street":"Peperstr",
    "iso:country":"NL",
    "sg:address":"Peperstr 9",
    "sg:city":"Leeuwarden",
    "sg:orig_category":"Fotozaken",
    "sg:phone":"+31 58 212 4258",
    "sg:postcode":"8911 HZ",
    "sg:province":"Friesland",
    "wof:name":"Bleeker, Foto/Video",
    "wof:placetype":"venue"
},
  "geometry": {"coordinates":[5.797542,53.200981],"type":"Point"}
}