{
  "type": "Feature",
  "properties": {
    "addr:full":"P Baststr 31 Amsterdam Noord-Holland 1071 TV",
    "addr:housenumber":"31",
    "addr:postcode":"1071 tv",
    "addr:street":"P",
    "iso:country":"NL",
    "sg:address":"P Baststr 31",
    "sg:city":"Amsterdam",
    "sg:orig_category":"Schoenen - Reparaties",
    "sg:phone":"+31 20 671 7713",
    "sg:postcode":"1071 TV",
    "sg:province":"Noord-Holland",
    "wof:name":"Glasenap G.H., Van",
    "wof:placetype":"venue"
},
  "geometry": {"coordinates":[4.885278,52.352634],"type":"Point"}
}