{
  "type": "Feature",
  "properties": {
    "addr:full":"Bredeweg 6 Echt Limburg 6102 GD",
    "addr:housenumber":"6",
    "addr:postcode":"6102 gd",
    "addr:street":"Bredeweg",
    "iso:country":"NL",
    "sg:address":"Bredeweg 6",
    "sg:city":"Echt",
    "sg:orig_category":"Landbouwmachines Gh",
    "sg:phone":"+31 475 485 125",
    "sg:postcode":"6102 GD",
    "sg:province":"Limburg",
    "wof:name":"P.H.M. De Boer",
    "wof:placetype":"venue"
},
  "geometry": {"coordinates":[5.912834,51.102936],"type":"Point"}
}