{
  "type": "Feature",
  "properties": {
    "addr:full":"Rode Klif 212 Lelystad Flevoland 8223 CK",
    "addr:housenumber":"212",
    "addr:postcode":"8223 ck",
    "addr:street":"Rode Klif;Flevoland",
    "iso:country":"NL",
    "sg:address":"Rode Klif 212",
    "sg:city":"Lelystad",
    "sg:orig_category":"Fotostudio'S And Fotografen",
    "sg:phone":"+31 320 281 121",
    "sg:postcode":"8223 CK",
    "sg:province":"Flevoland",
    "wof:name":"Peter Mastenbroek/ Optima Foto",
    "wof:placetype":"venue"
},
  "geometry": {"coordinates":[5.485484,52.52285],"type":"Point"}
}