{
  "type": "Feature",
  "properties": {
    "addr:full":"Harnas 120 Oss Noord-Brabant 5346 WR",
    "addr:housenumber":"120",
    "addr:postcode":"5346 wr",
    "addr:street":"Harnas",
    "iso:country":"NL",
    "sg:address":"Harnas 120",
    "sg:city":"Oss",
    "sg:orig_category":"Huishoudapparatuur, Televisies And Radio'S",
    "sg:phone":"+31 412 638 650",
    "sg:postcode":"5346 WR",
    "sg:province":"Noord-Brabant",
    "wof:name":"G.L. Brands",
    "wof:placetype":"venue"
},
  "geometry": {"coordinates":[-77.235214,38.312599],"type":"Point"}
}