{
  "type": "Feature",
  "properties": {
    "iso:country":"NL",
    "sg:address":"Plasweg 30",
    "sg:city":"Waddinxveen",
    "sg:orig_category":"Bloemen And Planten",
    "sg:phone":"+31 182 615 589",
    "sg:postcode":"2742 KD",
    "sg:province":"Zuid-Holland",
    "wof:name":"Plantenkwekerij A.J. Sonneveld Plasweg Bv",
    "wof:placetype":"venue"
},
  "geometry": {"coordinates":[4.616289,52.029358],"type":"Point"}
}