{
  "type": "Feature",
  "properties": {
    "addr:full":"Plasweg 30 Waddinxveen Zuid-Holland 2742 KD",
    "addr:housenumber":"30",
    "addr:postcode":"2742 kd",
    "addr:street":"Plasweg",
    "iso:country":"NL",
    "sg:address":"Plasweg 30",
    "sg:city":"Waddinxveen",
    "sg:orig_category":"Bloemen And Planten",
    "sg:phone":"+31 182 615 589",
    "sg:postcode":"2742 KD",
    "sg:province":"Zuid-Holland",
    "wof:name":"Plantenkwekerij A.J. Sonneveld Plasweg Bv",
    "wof:placetype":"venue"
},
  "geometry": {"coordinates":[4.616289,52.029358],"type":"Point"}
}