{
  "type": "Feature",
  "properties": {
    "addr:full":"Zeestr 214 Wyk Aan Zee Noord-Holland 1949 AG",
    "addr:housenumber":"214",
    "addr:postcode":"1949",
    "addr:street":"Wyk Aan Zee",
    "iso:country":"NL",
    "sg:address":"Zeestr 214",
    "sg:city":"Wyk Aan Zee",
    "sg:orig_category":"Honden- En Kattentrimsalons",
    "sg:phone":"+31 6 51735042",
    "sg:postcode":"1949 AG",
    "sg:province":"Noord-Holland",
    "wof:name":"Charmed Hondentrimsalon",
    "wof:placetype":"venue"
},
  "geometry": {"coordinates":[4.594696,52.491993],"type":"Point"}
}