{
  "type": "Feature",
  "properties": {
    "addr:full":"Proosthof 17 Berg En Terblyt Limburg 6325 EW",
    "addr:housenumber":"17",
    "addr:postcode":"6325 ew",
    "addr:street":"Proosthof;Limburg",
    "iso:country":"NL",
    "sg:address":"Proosthof 17",
    "sg:city":"Berg En Terblyt",
    "sg:orig_category":"Voetbalverenigingen",
    "sg:phone":"+31 43 604 1174",
    "sg:postcode":"6325 EW",
    "sg:province":"Limburg",
    "wof:name":"Berg 28",
    "wof:placetype":"venue"
},
  "geometry": {"coordinates":[5.773464,50.862106],"type":"Point"}
}