{
  "type": "Feature",
  "properties": {
    "addr:full":"Saerdam 91 Lelystad North Holland 8242 JC",
    "addr:housenumber":"91",
    "addr:postcode":"8242 jc",
    "addr:street":"Saerdam",
    "iso:country":"NL",
    "sg:address":"Saerdam 91",
    "sg:city":"Lelystad",
    "sg:orig_category":"Sportverenigingen En Ontspannings- Verenigingen",
    "sg:phone":"+31 320 234 096",
    "sg:postcode":"8242 JC",
    "sg:province":"North Holland",
    "sg:website":"http://www.access2golf.nl",
    "wof:name":"Access 2 Golf",
    "wof:placetype":"venue"
},
  "geometry": {"coordinates":[5.439511,52.515388],"type":"Point"}
}