{
  "type": "Feature",
  "properties": {
    "iso:country":"NL",
    "sg:address":"Bannenbergstr 54",
    "sg:city":"St Michielsgestel",
    "sg:orig_category":"Biljarts - Fabrieken",
    "sg:phone":"+31 73 551 3410",
    "sg:postcode":"5272 BR",
    "sg:province":"Noord-Brabant",
    "wof:name":"Wordragen, H A Van",
    "wof:placetype":"venue"
},
  "geometry": {"coordinates":[5.35867,51.640408],"type":"Point"}
}