{
  "type": "Feature",
  "properties": {
    "addr:full":"Hoogstedelaan 4 Arnhem Gelderland 6812 DN",
    "addr:housenumber":"4",
    "addr:postcode":"6812 dn",
    "addr:street":"Hoogstedelaan",
    "iso:country":"NL",
    "sg:address":"Hoogstedelaan 4",
    "sg:city":"Arnhem",
    "sg:orig_category":"Fotolaboratoria",
    "sg:phone":"+31 26 445 0710",
    "sg:postcode":"6812 DN",
    "sg:province":"Gelderland",
    "wof:name":"Foto Joi Ochsendorf",
    "wof:placetype":"venue"
},
  "geometry": {"coordinates":[5.873011,51.982738],"type":"Point"}
}