{
  "type": "Feature",
  "properties": {
    "addr:full":"Oranjeplein 8 Waalwijk Noord-Brabant 5142 SL",
    "addr:housenumber":"8",
    "addr:postcode":"5142 sl",
    "addr:street":"Oranjeplein",
    "iso:country":"NL",
    "sg:address":"Oranjeplein 8",
    "sg:city":"Waalwijk",
    "sg:orig_category":"Metaalbekleding And -Behandeling",
    "sg:phone":"+31 416 332 533",
    "sg:postcode":"5142 SL",
    "sg:province":"Noord-Brabant",
    "wof:name":"Harry Van Der Mee Bv",
    "wof:placetype":"venue"
},
  "geometry": {"coordinates":[5.078122,51.68816],"type":"Point"}
}