{
  "type": "Feature",
  "properties": {
    "addr:full":"Zuiderzeestraatweg 21 Hattem Gelderland 8051 SL",
    "addr:housenumber":"21",
    "addr:postcode":"8051 sl",
    "addr:street":"Zuiderzeestraatweg;Gelderland",
    "iso:country":"NL",
    "sg:address":"Zuiderzeestraatweg 21",
    "sg:city":"Hattem",
    "sg:orig_category":"Bloemen And Planten",
    "sg:phone":"+31 38 444 3748",
    "sg:postcode":"8051 SL",
    "sg:province":"Gelderland",
    "wof:name":"Groenrijk Hattem",
    "wof:placetype":"venue"
},
  "geometry": {"coordinates":[6.031995,52.482307],"type":"Point"}
}