{
  "type": "Feature",
  "properties": {
    "addr:full":"W De Clercqstr 35 A+B Hengelo Ov NL.08 7553 VA",
    "addr:housenumber":"35 a+b",
    "addr:postcode":"7553",
    "addr:street":"W De Clercqstr;Ov",
    "iso:country":"NL",
    "sg:address":"W De Clercqstr 35 A+B",
    "sg:city":"Hengelo Ov",
    "sg:orig_category":"Kunststof Ramen",
    "sg:phone":"+31 74 250 1328",
    "sg:postcode":"7553 VA",
    "sg:province":"NL.08",
    "sg:website":"http://www.plankozijn.nl",
    "wof:name":"Plankozijn",
    "wof:placetype":"venue"
},
  "geometry": {"coordinates":[6.78971,52.266331],"type":"Point"}
}