{
  "type": "Feature",
  "properties": {
    "addr:full":"Zandweg 4 Sirjansland Zeeland 4308 AB",
    "addr:housenumber":"4",
    "addr:postcode":"4308 ab",
    "addr:street":"Zandweg",
    "iso:country":"NL",
    "sg:address":"Zandweg 4",
    "sg:city":"Sirjansland",
    "sg:orig_category":"Kampeerterreinen",
    "sg:phone":"+31 111 641 989",
    "sg:postcode":"4308 AB",
    "sg:province":"Zeeland",
    "wof:name":"Camping 'T Hoge Zand",
    "wof:placetype":"venue"
},
  "geometry": {"coordinates":[4.0323371887,51.6725273132],"type":"Point"}
}