{
  "type": "Feature",
  "properties": {
    "addr:full":"J Persynstr 15 Ouderkerk Amstel North Holland 1191 JX",
    "addr:housenumber":"15",
    "addr:postcode":"1191 jx",
    "addr:street":"Ouderkerk Amstel",
    "iso:country":"NL",
    "sg:address":"J Persynstr 15",
    "sg:city":"Ouderkerk Amstel",
    "sg:orig_category":"Onderhoudswerken",
    "sg:phone":"+31 20 496 4443",
    "sg:postcode":"1191 JX",
    "sg:province":"North Holland",
    "wof:name":"A Tot Z, Van",
    "wof:placetype":"venue"
},
  "geometry": {"coordinates":[4.904776,52.296631],"type":"Point"}
}