{
  "type": "Feature",
  "properties": {
    "iso:country":"NL",
    "sg:address":"Prinses Marijkeweg 18",
    "sg:city":"Geldermalsen",
    "sg:orig_category":"Kappers",
    "sg:phone":"+31 345 573 305",
    "sg:postcode":"4191 XL",
    "sg:province":"Gelderland",
    "wof:name":"Kapsalon E Van Zoelen",
    "wof:placetype":"venue"
},
  "geometry": {"coordinates":[5.3014278412,51.8823623657],"type":"Point"}
}