{
  "type": "Feature",
  "properties": {
    "iso:country":"NL",
    "sg:address":"Lindestraat 66",
    "sg:city":"Kerkdriel",
    "sg:orig_category":"Paramedische Behandelingen",
    "sg:phone":"+31 418 634 499",
    "sg:postcode":"5331 GW",
    "sg:province":"Gelderland",
    "wof:name":"Prakt Oost-Bommelerwaard",
    "wof:placetype":"venue"
},
  "geometry": {"coordinates":[5.325239,51.767593],"type":"Point"}
}