{
  "type": "Feature",
  "properties": {
    "addr:full":"Kerkwg 3 Anna Paulowna Noord-Holland 1761 JD",
    "addr:housenumber":"3",
    "addr:postcode":"1761 jd",
    "addr:street":"Kerkwg",
    "iso:country":"NL",
    "sg:address":"Kerkwg 3",
    "sg:city":"Anna Paulowna",
    "sg:orig_category":"Honden- En Kattentrimsalons",
    "sg:phone":"+31 223 535 838",
    "sg:postcode":"1761 JD",
    "sg:province":"Noord-Holland",
    "wof:name":"? La Professionnelle",
    "wof:placetype":"venue"
},
  "geometry": {"coordinates":[4.8328199387,52.8625602722],"type":"Point"}
}