{
  "type": "Feature",
  "properties": {
    "addr:full":"Geldelozewg 66 Hoorn Nh Noord-Holland 1625 NX",
    "addr:housenumber":"66",
    "addr:postcode":"1625 nx",
    "addr:street":"Geldelozewg",
    "iso:country":"NL",
    "sg:address":"Geldelozewg 66",
    "sg:city":"Hoorn Nh",
    "sg:orig_category":"Bejaarden - Verzorgingstehuizen",
    "sg:phone":"+31 229 231 344",
    "sg:postcode":"1625 NX",
    "sg:province":"Noord-Holland",
    "wof:name":"Avondlicht",
    "wof:placetype":"venue"
},
  "geometry": {"coordinates":[5.046017,52.65023],"type":"Point"}
}