{
  "type": "Feature",
  "properties": {
    "addr:full":"Badstr 3 Musselkanaal Groningen 9581 BB",
    "addr:housenumber":"3",
    "addr:postcode":"9581 bb",
    "addr:street":"Badstr",
    "iso:country":"NL",
    "sg:address":"Badstr 3",
    "sg:city":"Musselkanaal",
    "sg:orig_category":"Schoonheidsinstituten",
    "sg:phone":"+31 599 413 397",
    "sg:postcode":"9581 BB",
    "sg:province":"Groningen",
    "wof:name":"Jamilla",
    "wof:placetype":"venue"
},
  "geometry": {"coordinates":[7.013438,52.933582],"type":"Point"}
}