{
  "type": "Feature",
  "properties": {
    "addr:full":"Schout V Eykln 29 Leidschendam Zuid-Holland 2262 XK",
    "addr:housenumber":"29",
    "addr:postcode":"2262 xk",
    "addr:street":"Schout V Eykln",
    "iso:country":"NL",
    "sg:address":"Schout V Eykln 29",
    "sg:city":"Leidschendam",
    "sg:orig_category":"Organisatiebureaus",
    "sg:phone":"+31 70 301 8188",
    "sg:postcode":"2262 XK",
    "sg:province":"Zuid-Holland",
    "wof:name":"Berg, Van Den",
    "wof:placetype":"venue"
},
  "geometry": {"coordinates":[4.3875198364,52.0913887024],"type":"Point"}
}