{
  "type": "Feature",
  "properties": {
    "addr:full":"Huizerwg 27A Bussum North Holland 1401 GG",
    "addr:housenumber":"27a",
    "addr:postcode":"1401 gg",
    "addr:street":"Huizerwg",
    "iso:country":"NL",
    "sg:address":"Huizerwg 27A",
    "sg:city":"Bussum",
    "sg:classifiers":[
        {
            "category":"Shopping",
            "subcategory":"Adult",
            "type":"Retail Goods"
        }
    ],
    "sg:phone":"+31 35 691 2848",
    "sg:postcode":"1401 GG",
    "sg:province":"North Holland",
    "sg:tags":[
        "lingerie",
        "en",
        "tricotage"
    ],
    "wof:name":"La Nouvelle Lingerie",
    "wof:placetype":"venue"
},
  "geometry": {"coordinates":[5.170721,52.27454],"type":"Point"}
}