{
  "type": "Feature",
  "properties": {
    "addr:full":"Heimansweg 21 Amsterdam Noord-Holland 1031 TX",
    "addr:housenumber":"21;1031",
    "addr:street":"Heimansweg",
    "iso:country":"NL",
    "sg:address":"Heimansweg 21",
    "sg:city":"Amsterdam",
    "sg:orig_category":"Artsen And Specialisten",
    "sg:phone":"+31 20 636 0101",
    "sg:postcode":"1031 TX",
    "sg:province":"Noord-Holland",
    "wof:name":"I. Hidayat",
    "wof:placetype":"venue"
},
  "geometry": {"coordinates":[4.911757,52.388424],"type":"Point"}
}