{
  "type": "Feature",
  "properties": {
    "addr:full":"Meeuwenln 1 Enkhuizen North Holland 1602 NA",
    "addr:housenumber":"1",
    "addr:postcode":"1602 na",
    "addr:street":"Meeuwenln",
    "iso:country":"NL",
    "sg:address":"Meeuwenln 1",
    "sg:city":"Enkhuizen",
    "sg:orig_category":"Verenigingsgebouwen",
    "sg:phone":"+31 228 317 568",
    "sg:postcode":"1602 NA",
    "sg:province":"North Holland",
    "wof:name":"Witte Duif, De",
    "wof:placetype":"venue"
},
  "geometry": {"coordinates":[5.276957,52.712158],"type":"Point"}
}