{
  "type": "Feature",
  "properties": {
    "addr:full":"Gysbrechtgaarde 30 Apeldoorn Gelderland 7329 CB",
    "addr:housenumber":"30",
    "addr:postcode":"7329 cb",
    "addr:street":"Gysbrechtgaarde;Gelderland",
    "iso:country":"NL",
    "sg:address":"Gysbrechtgaarde 30",
    "sg:city":"Apeldoorn",
    "sg:orig_category":"Logopedisten",
    "sg:phone":"+31 55 542 7605",
    "sg:postcode":"7329 CB",
    "sg:province":"Gelderland",
    "wof:name":"Werf, P M Van Der",
    "wof:placetype":"venue"
},
  "geometry": {"coordinates":[5.992603,52.201542],"type":"Point"}
}