{
  "type": "Feature",
  "properties": {
    "iso:country":"NL",
    "sg:address":"Mechelaarstraat 40",
    "sg:city":"Oosterhout Nb",
    "sg:orig_category":"Metaalbekleding And -Behandeling",
    "sg:phone":"+31 162 437 378",
    "sg:postcode":"4903 RE",
    "sg:province":"Noord-Brabant",
    "wof:name":"L & R Handelsonderneming Bv",
    "wof:placetype":"venue"
},
  "geometry": {"coordinates":[4.879631,51.624969],"type":"Point"}
}