{
  "type": "Feature",
  "properties": {
    "addr:full":"Doolhofje 6 Huizen Noord-Holland 1271 SB",
    "addr:housenumber":"6",
    "addr:postcode":"1271 sb",
    "addr:street":"Doolhofje",
    "iso:country":"NL",
    "sg:address":"Doolhofje 6",
    "sg:city":"Huizen",
    "sg:orig_category":"Levensmiddelen - Fabrieken En Groothandel",
    "sg:phone":"+31 35 525 3299",
    "sg:postcode":"1271 SB",
    "sg:province":"Noord-Holland",
    "wof:name":"Visser Bv, Jaap",
    "wof:placetype":"venue"
},
  "geometry": {"coordinates":[5.232129,52.300964],"type":"Point"}
}