{
  "type": "Feature",
  "properties": {
    "addr:full":"Verlengde J A Feithstr 18 Groningen Groningen 9725 AT",
    "addr:housenumber":"18",
    "addr:postcode":"9725",
    "addr:street":"Verlengde J A Feithstr",
    "iso:country":"NL",
    "sg:address":"Verlengde J A Feithstr 18",
    "sg:city":"Groningen",
    "sg:orig_category":"Boekenuitgeverijen",
    "sg:phone":"+31 50 525 3730",
    "sg:postcode":"9725 AT",
    "sg:province":"Groningen",
    "wof:name":"Banga Book Productions",
    "wof:placetype":"venue"
},
  "geometry": {"coordinates":[6.576381,53.208706],"type":"Point"}
}