{
  "type": "Feature",
  "properties": {
    "addr:full":"J Zoetemelkstr 31 Oldenzaal NL.08 7572 EK",
    "addr:housenumber":"31;nl.08",
    "addr:postcode":"7572 ek",
    "iso:country":"NL",
    "sg:address":"J Zoetemelkstr 31",
    "sg:city":"Oldenzaal",
    "sg:orig_category":"Vertalers",
    "sg:phone":"+31 541 510 708",
    "sg:postcode":"7572 EK",
    "sg:province":"NL.08",
    "wof:name":"Wientjes-M\u00fcnkten",
    "wof:placetype":"venue"
},
  "geometry": {"coordinates":[6.913271,52.308952],"type":"Point"}
}