{
  "type": "Feature",
  "properties": {
    "iso:country":"NL",
    "sg:address":"Dalweg 14",
    "sg:city":"Rotterdam",
    "sg:orig_category":"Goederenvervoer Over De Weg",
    "sg:phone":"+31 10 210 2768",
    "sg:postcode":"3075 LR",
    "sg:province":"Zuid-Holland",
    "wof:name":"Vdn",
    "wof:placetype":"venue"
},
  "geometry": {"coordinates":[4.517135,51.889687],"type":"Point"}
}