{
  "type": "Feature",
  "properties": {
    "addr:full":"J Romenwg 1 Roermond Limburg 6042 EZ",
    "addr:housenumber":"1",
    "addr:postcode":"6042 ez",
    "iso:country":"NL",
    "sg:address":"J Romenwg 1",
    "sg:city":"Roermond",
    "sg:classifiers":[
        {
            "category":"Retail",
            "subcategory":"Auto Repair",
            "type":"Services"
        }
    ],
    "sg:phone":"+31 475 322 333",
    "sg:postcode":"6042 EZ",
    "sg:province":"Limburg",
    "sg:tags":[
        "garage"
    ],
    "sg:website":"http://www.nizet.nl",
    "wof:name":"Nizet Roermond Bv Autobedrijf",
    "wof:placetype":"venue"
},
  "geometry": {"coordinates":[6.015448,51.210545],"type":"Point"}
}