{
  "type": "Feature",
  "properties": {
    "addr:full":"J De Wittstr 11 Drunen North Brabant 5151 CK",
    "addr:housenumber":"11",
    "addr:postcode":"5151 ck",
    "addr:street":"J De Wittstr",
    "iso:country":"NL",
    "sg:address":"J De Wittstr 11",
    "sg:city":"Drunen",
    "sg:orig_category":"Scholen Voor Basisonderwijs",
    "sg:phone":"+31 416 373 376",
    "sg:postcode":"5151 CK",
    "sg:province":"North Brabant",
    "wof:name":"Albert Schweitzer Prot Chr",
    "wof:placetype":"venue"
},
  "geometry": {"coordinates":[5.140105,51.686749],"type":"Point"}
}