{
  "type": "Feature",
  "properties": {
    "addr:full":"Schiedamseweg 89 Vlaardingen Zuid-Holland 3134 BD",
    "addr:housenumber":"89",
    "addr:postcode":"3134 bd",
    "addr:street":"Schiedamseweg",
    "iso:country":"NL",
    "sg:address":"Schiedamseweg 89",
    "sg:city":"Vlaardingen",
    "sg:orig_category":"Artsen And Specialisten",
    "sg:phone":"+31 10 434 2013",
    "sg:postcode":"3134 BD",
    "sg:province":"Zuid-Holland",
    "wof:name":"A.P. Scheek",
    "wof:placetype":"venue"
},
  "geometry": {"coordinates":[4.350141,51.9095],"type":"Point"}
}