{
  "type": "Feature",
  "properties": {
    "addr:full":"Burg V Rynsngl 41 Venlo Limburg 5913 AP",
    "addr:housenumber":"41",
    "addr:postcode":"5913 ap",
    "addr:street":"Burg V Rynsngl",
    "iso:country":"NL",
    "sg:address":"Burg V Rynsngl 41",
    "sg:city":"Venlo",
    "sg:orig_category":"Beleggingen",
    "sg:phone":"+31 77 354 0351",
    "sg:postcode":"5913 AP",
    "sg:province":"Limburg",
    "wof:name":"Baxxlogic Cv",
    "wof:placetype":"venue"
},
  "geometry": {"coordinates":[6.17286,51.372421],"type":"Point"}
}