{
  "type": "Feature",
  "properties": {
    "addr:full":"Rijksstraatweg 14 Wilp Gld Gelderland 7384 AA",
    "addr:housenumber":"14",
    "addr:postcode":"7384 aa",
    "addr:street":"Rijksstraatweg;Gld Gelderland",
    "iso:country":"NL",
    "sg:address":"Rijksstraatweg 14",
    "sg:city":"Wilp Gld",
    "sg:orig_category":"Glaszetten",
    "sg:phone":"+31 571 261 046",
    "sg:postcode":"7384 AA",
    "sg:province":"Gelderland",
    "wof:name":"G J Vd Pol Glaszettersbedrijf",
    "wof:placetype":"venue"
},
  "geometry": {"coordinates":[6.146285,52.223152],"type":"Point"}
}