{
  "type": "Feature",
  "properties": {
    "iso:country":"NL",
    "sg:address":"Protonweg 28",
    "sg:city":"Hoorn Nh",
    "sg:orig_category":"Schilderwerk",
    "sg:phone":"+31 229 219 040",
    "sg:postcode":"1627 LD",
    "sg:province":"North Holland",
    "wof:name":"Schildersbedrijf Wurth En Zn",
    "wof:placetype":"venue"
},
  "geometry": {"coordinates":[5.094694,52.64222],"type":"Point"}
}