{
  "type": "Feature",
  "properties": {
    "iso:country":"NL",
    "sg:address":"Hynstewaed 3",
    "sg:city":"Stiens",
    "sg:orig_category":"Verzekeringen",
    "sg:phone":"+31 58 257 1468",
    "sg:postcode":"9051 CV",
    "sg:province":"Friesland",
    "wof:name":"Assurantien Bij De Leij Sinds 1953",
    "wof:placetype":"venue"
},
  "geometry": {"coordinates":[5.76141,53.257992],"type":"Point"}
}