{
  "type": "Feature",
  "properties": {
    "addr:full":"Oosthavenkd 30 Vlaardingen South Holland 3134 NW",
    "addr:housenumber":"30",
    "addr:postcode":"3134 nw",
    "addr:street":"Oosthavenkd",
    "iso:country":"NL",
    "sg:address":"Oosthavenkd 30",
    "sg:city":"Vlaardingen",
    "sg:orig_category":"Administratie- En Boekhoudkantoren",
    "sg:phone":"+31 10 435 9011",
    "sg:postcode":"3134 NW",
    "sg:province":"South Holland",
    "wof:name":"Hydra",
    "wof:placetype":"venue"
},
  "geometry": {"coordinates":[4.345551,51.907646],"type":"Point"}
}