{
  "type": "Feature",
  "properties": {
    "iso:country":"NL",
    "sg:address":"Elektrawg 6",
    "sg:city":"Maassluis",
    "sg:orig_category":"Verenigingen En Stichtingen",
    "sg:phone":"+31 10 592 5505",
    "sg:postcode":"3144 CB",
    "sg:province":"Zuid-Holland",
    "wof:name":"Islam Ver Van Turken",
    "wof:placetype":"venue"
},
  "geometry": {"coordinates":[4.246256,51.925995],"type":"Point"}
}