{
  "type": "Feature",
  "properties": {
    "iso:country":"NL",
    "sg:address":"Brucknerlaan 12",
    "sg:city":"Tilburg",
    "sg:orig_category":"Kappers",
    "sg:phone":"+31 13 455 0880",
    "sg:postcode":"5011 DM",
    "sg:province":"Noord-Brabant",
    "wof:name":"Louvet - Coiffures",
    "wof:placetype":"venue"
},
  "geometry": {"coordinates":[5.087839,51.584225],"type":"Point"}
}