{
  "type": "Feature",
  "properties": {
    "addr:full":"Tamboerpassage 16 Hoogeveen Drenthe 7902 GM",
    "addr:housenumber":"16",
    "addr:postcode":"7902 gm",
    "addr:street":"Tamboerpassage",
    "iso:country":"NL",
    "sg:address":"Tamboerpassage 16",
    "sg:city":"Hoogeveen",
    "sg:orig_category":"Discountwinkels",
    "sg:phone":"+31 528 231 494",
    "sg:postcode":"7902 GM",
    "sg:province":"Drenthe",
    "wof:name":"Zeeman Textielsupers",
    "wof:placetype":"venue"
},
  "geometry": {"coordinates":[6.477995,52.726723],"type":"Point"}
}