{
  "type": "Feature",
  "properties": {
    "addr:full":"Holtermanstraat 4 Nijmegen Gelderland 6512 DB",
    "addr:housenumber":"4",
    "addr:postcode":"6512 db",
    "addr:street":"Holtermanstraat;Gelderland",
    "iso:country":"NL",
    "sg:address":"Holtermanstraat 4",
    "sg:city":"Nijmegen",
    "sg:orig_category":"Krantenuitgeverijen",
    "sg:phone":"+31 24 388 8452",
    "sg:postcode":"6512 DB",
    "sg:province":"Gelderland",
    "wof:name":"Uitgeverij Entheon",
    "wof:placetype":"venue"
},
  "geometry": {"coordinates":[5.858208,51.839741],"type":"Point"}
}