{
  "type": "Feature",
  "properties": {
    "addr:full":"Dorpsstraat 28 Meteren Gelderland 4194 TD",
    "addr:housenumber":"28",
    "addr:postcode":"4194 td",
    "addr:street":"Dorpsstraat;Gelderland",
    "iso:country":"NL",
    "sg:address":"Dorpsstraat 28",
    "sg:city":"Meteren",
    "sg:orig_category":"Verlichting And Huishoudartikelen",
    "sg:phone":"+31 345 569 223",
    "sg:postcode":"4194 TD",
    "sg:province":"Gelderland",
    "wof:name":"H De Jongh",
    "wof:placetype":"venue"
},
  "geometry": {"coordinates":[5.282178,51.864964],"type":"Point"}
}