{
  "type": "Feature",
  "properties": {
    "addr:full":"Tegelerwg 7 Enschede NL.08 7535 CJ",
    "addr:housenumber":"7",
    "addr:postcode":"7535",
    "addr:street":"Tegelerwg;Cj",
    "iso:country":"NL",
    "sg:address":"Tegelerwg 7",
    "sg:city":"Enschede",
    "sg:orig_category":"Peuterspeelzalen",
    "sg:phone":"+31 53 430 8361",
    "sg:postcode":"7535 CJ",
    "sg:province":"NL.08",
    "wof:name":"Bruintje Beer Mickey Mouse",
    "wof:placetype":"venue"
},
  "geometry": {"coordinates":[6.913702,52.214695],"type":"Point"}
}