{
  "type": "Feature",
  "properties": {
    "addr:full":"Postbus 1068 Nykerk Gld Gelderland 3860 BB",
    "addr:housenumber":"1068",
    "addr:postcode":"3860 bb",
    "addr:street":"Postbus;Gld Gelderland",
    "iso:country":"NL",
    "sg:address":"Postbus 1068",
    "sg:city":"Nykerk Gld",
    "sg:orig_category":"Automaterialen En Gereedschappen",
    "sg:phone":"+31 33 246 2754",
    "sg:postcode":"3860 BB",
    "sg:province":"Gelderland",
    "wof:name":"Wesko Bv",
    "wof:placetype":"venue"
},
  "geometry": {"coordinates":[5.51415,52.21376],"type":"Point"}
}