{
  "type": "Feature",
  "properties": {
    "addr:full":"Kamilleln 81A Arnhem Gelderland 6833 GH",
    "addr:housenumber":"81a",
    "addr:postcode":"6833 gh",
    "addr:street":"Kamilleln",
    "iso:country":"NL",
    "sg:address":"Kamilleln 81A",
    "sg:city":"Arnhem",
    "sg:orig_category":"Sportverenigingen En Ontspannings- Verenigingen",
    "sg:phone":"+31 26 321 5897",
    "sg:postcode":"6833 GH",
    "sg:province":"Gelderland",
    "wof:name":"Budover",
    "wof:placetype":"venue"
},
  "geometry": {"coordinates":[5.92045,51.965302],"type":"Point"}
}