{
  "type": "Feature",
  "properties": {
    "addr:full":"Wilgenlaan 21 Leusden Utrecht 3831 XT",
    "addr:housenumber":"21",
    "addr:postcode":"3831 xt",
    "addr:street":"Wilgenlaan",
    "iso:country":"NL",
    "sg:address":"Wilgenlaan 21",
    "sg:city":"Leusden",
    "sg:orig_category":"Schilderwerk",
    "sg:phone":"+31 33 494 1251",
    "sg:postcode":"3831 XT",
    "sg:province":"Utrecht",
    "wof:name":"Schildersbedrijf J Blok",
    "wof:placetype":"venue"
},
  "geometry": {"coordinates":[5.434802,52.138157],"type":"Point"}
}