{
  "type": "Feature",
  "properties": {
    "addr:full":"Dorpsstr 367 Assendelft Noord-Holland 1566 BD",
    "addr:housenumber":"367",
    "addr:postcode":"1566 bd",
    "iso:country":"NL",
    "sg:address":"Dorpsstr 367",
    "sg:city":"Assendelft",
    "sg:orig_category":"Fietsen En Bromfietsen",
    "sg:phone":"+31 75 687 1202",
    "sg:postcode":"1566 BD",
    "sg:province":"Noord-Holland",
    "wof:name":"Metz, Tweewielerspec",
    "wof:placetype":"venue"
},
  "geometry": {"coordinates":[4.739804,52.465401],"type":"Point"}
}