{
  "type": "Feature",
  "properties": {
    "iso:country":"NL",
    "sg:address":"Groenstr 51",
    "sg:city":"Roosendaal",
    "sg:orig_category":"Beveiliging",
    "sg:phone":"+31 165 529 902",
    "sg:postcode":"4702 VE",
    "sg:province":"Noord-Brabant",
    "wof:name":"Dam",
    "wof:placetype":"venue"
},
  "geometry": {"coordinates":[4.468083,51.544067],"type":"Point"}
}