{
  "type": "Feature",
  "properties": {
    "iso:country":"NL",
    "sg:address":"Kzr Ottoln 11",
    "sg:city":"Loenen Ad Vecht",
    "sg:orig_category":"Bibliotheken En Leeszalen Openbare",
    "sg:phone":"+31 294 234 285",
    "sg:postcode":"3632 BV",
    "sg:province":"Utrecht",
    "wof:name":"Openb Bibliotheek",
    "wof:placetype":"venue"
},
  "geometry": {"coordinates":[5.021896,52.209732],"type":"Point"}
}