{
  "type": "Feature",
  "properties": {
    "addr:full":"Nymeegsewg 90 Venlo Limburg 5916 PT",
    "addr:housenumber":"90",
    "addr:postcode":"5916 pt",
    "addr:street":"Nymeegsewg",
    "iso:country":"NL",
    "sg:address":"Nymeegsewg 90",
    "sg:city":"Venlo",
    "sg:classifiers":[
        {
            "category":"Travel",
            "subcategory":"Hotels & Motels",
            "type":"Entertainment"
        }
    ],
    "sg:phone":"+31 77 354 4141",
    "sg:postcode":"5916 PT",
    "sg:province":"Limburg",
    "sg:website":"http://www.hotelvenlo.nl",
    "wof:name":"Valk Hotel Venlo, Van Der",
    "wof:placetype":"venue"
},
  "geometry": {"coordinates":[6.172744,51.39505],"type":"Point"}
}