{
  "type": "Feature",
  "properties": {
    "addr:full":"Oude Watering 374 Rotterdam South Holland 3077 RE",
    "addr:housenumber":"374",
    "addr:postcode":"3077 re",
    "addr:street":"Oude Watering",
    "iso:country":"NL",
    "sg:address":"Oude Watering 374",
    "sg:city":"Rotterdam",
    "sg:orig_category":"Pleziervaartuigen And Reparatie",
    "sg:phone":"+31 10 483 5805",
    "sg:postcode":"3077 RE",
    "sg:province":"South Holland",
    "wof:name":"K. De Jong Opblaasboten Specialist",
    "wof:placetype":"venue"
},
  "geometry": {"coordinates":[4.56432,51.89217],"type":"Point"}
}