{
  "type": "Feature",
  "properties": {
    "iso:country":"NL",
    "sg:address":"De Els 76",
    "sg:city":"Waalwyk",
    "sg:orig_category":"Juweliers",
    "sg:phone":"+31 416 650 046",
    "sg:postcode":"5141 HN",
    "sg:province":"Noord-Brabant",
    "wof:name":"Lucardi",
    "wof:placetype":"venue"
},
  "geometry": {"coordinates":[5.066678,51.689629],"type":"Point"}
}