{
  "type": "Feature",
  "properties": {
    "addr:full":"Nieuwe Karselaan 67 Amstelveen North Holland 1182 BP",
    "addr:housenumber":"67",
    "addr:postcode":"1182 bp",
    "addr:street":"Nieuwe Karselaan",
    "iso:country":"NL",
    "sg:address":"Nieuwe Karselaan 67",
    "sg:city":"Amstelveen",
    "sg:orig_category":"Autokeuringen",
    "sg:phone":"+31 20 645 2769",
    "sg:postcode":"1182 BP",
    "sg:province":"North Holland",
    "wof:name":"Firma J J Leijen & Zoon",
    "wof:placetype":"venue"
},
  "geometry": {"coordinates":[4.84987,52.310963],"type":"Point"}
}