{
  "type": "Feature",
  "properties": {
    "iso:country":"NL",
    "sg:address":"Vouerweg 19",
    "sg:city":"Sittard",
    "sg:orig_category":"Kappers",
    "sg:phone":"+31 46 411 0853",
    "sg:postcode":"6136 AK",
    "sg:province":"Limburg",
    "wof:name":"Kapsalon Marcel",
    "wof:placetype":"venue"
},
  "geometry": {"coordinates":[5.8650741577,51.0055885315],"type":"Point"}
}