{
  "type": "Feature",
  "properties": {
    "addr:full":"Akker 113 De Bilt Utrecht 3732 XC",
    "addr:housenumber":"113",
    "addr:postcode":"3732 xc",
    "addr:street":"Akker",
    "iso:country":"NL",
    "sg:address":"Akker 113",
    "sg:city":"De Bilt",
    "sg:orig_category":"Vertaalbureaus",
    "sg:phone":"+31 30 220 1273",
    "sg:postcode":"3732 XC",
    "sg:province":"Utrecht",
    "wof:name":"Swinging Wings",
    "wof:placetype":"venue"
},
  "geometry": {"coordinates":[5.187513,52.109928],"type":"Point"}
}