{
  "type": "Feature",
  "properties": {
    "addr:full":"Grotestr 6B Raalte NL.08 8102 CE",
    "addr:housenumber":"6b;nl.08",
    "addr:postcode":"8102 ce",
    "addr:street":"Grotestr",
    "iso:country":"NL",
    "sg:address":"Grotestr 6B",
    "sg:city":"Raalte",
    "sg:orig_category":"Kaas",
    "sg:phone":"+31 572 358 311",
    "sg:postcode":"8102 CE",
    "sg:province":"NL.08",
    "wof:name":"Sallands Kaashuus, 'T",
    "wof:placetype":"venue"
},
  "geometry": {"coordinates":[6.275001049,52.3852386475],"type":"Point"}
}