{
  "type": "Feature",
  "properties": {
    "addr:full":"Pade 14 Opmeer Noord-Holland 1716 KA",
    "addr:housenumber":"14",
    "addr:postcode":"1716 ka",
    "addr:street":"Pade",
    "iso:country":"NL",
    "sg:address":"Pade 14",
    "sg:city":"Opmeer",
    "sg:orig_category":"Papier- And Kartonverpakkingen Fab",
    "sg:phone":"+31 226 355 396",
    "sg:postcode":"1716 KA",
    "sg:province":"Noord-Holland",
    "wof:name":"Welling Verpakkingsspecialist",
    "wof:placetype":"venue"
},
  "geometry": {"coordinates":[4.936335,52.70557],"type":"Point"}
}