{
  "type": "Feature",
  "properties": {
    "addr:full":"Grote Kerkstraat 36 Hoogeveen Drenthe 7902 CJ",
    "addr:housenumber":"36",
    "addr:postcode":"7902 cj",
    "addr:street":"Grote Kerkstraat",
    "iso:country":"NL",
    "sg:address":"Grote Kerkstraat 36",
    "sg:city":"Hoogeveen",
    "sg:classifiers":[
        {
            "category":"Shopping",
            "subcategory":"Gifts & Souvenirs",
            "type":"Retail Goods"
        }
    ],
    "sg:phone":"+31 528 231 226",
    "sg:postcode":"7902 CJ",
    "sg:province":"Drenthe",
    "sg:tags":[
        "geschenken"
    ],
    "wof:name":"Wereldwinkel",
    "wof:placetype":"venue"
},
  "geometry": {"coordinates":[6.479852,52.72599],"type":"Point"}
}