{
  "type": "Feature",
  "properties": {
    "addr:full":"C Tooropstr 48 Doetinchem Gelderland 7004 AS",
    "addr:housenumber":"48",
    "addr:postcode":"7004 as",
    "addr:street":"Gelderland",
    "iso:country":"NL",
    "sg:address":"C Tooropstr 48",
    "sg:city":"Doetinchem",
    "sg:orig_category":"Psychologen",
    "sg:phone":"+31 314 330 563",
    "sg:postcode":"7004 AS",
    "sg:province":"Gelderland",
    "wof:name":"Kuijper, Drs J W",
    "wof:placetype":"venue"
},
  "geometry": {"coordinates":[6.299713,51.957939],"type":"Point"}
}