{
  "type": "Feature",
  "properties": {
    "iso:country":"NL",
    "sg:address":"W. M. Dudokweg 27",
    "sg:city":"Heerhugowaard",
    "sg:orig_category":"Krantenuitgeverijen",
    "sg:phone":"+31 72 574 1339",
    "sg:postcode":"1703 DA",
    "sg:province":"Noord-Holland",
    "wof:name":"Dutch Connection Group",
    "wof:placetype":"venue"
},
  "geometry": {"coordinates":[4.819443,52.667213],"type":"Point"}
}