{
  "type": "Feature",
  "properties": {
    "addr:full":"Dorcamp 1 Castricum Noord-Holland 1902 AV",
    "addr:housenumber":"1;1902",
    "addr:postcode":"av",
    "addr:street":"Dorcamp",
    "iso:country":"NL",
    "sg:address":"Dorcamp 1",
    "sg:city":"Castricum",
    "sg:orig_category":"Artsen - Huisartsen",
    "sg:phone":"+31 251 654 540",
    "sg:postcode":"1902 AV",
    "sg:province":"Noord-Holland",
    "wof:name":"Leemhuis, A",
    "wof:placetype":"venue"
},
  "geometry": {"coordinates":[4.67881,52.545601],"type":"Point"}
}