{
  "type": "Feature",
  "properties": {
    "addr:full":"Bergstraat 33 Amersfoort Utrecht 3811 NG",
    "addr:housenumber":"33",
    "addr:postcode":"3811 ng",
    "addr:street":"Bergstraat",
    "iso:country":"NL",
    "sg:address":"Bergstraat 33",
    "sg:city":"Amersfoort",
    "sg:orig_category":"Verzekeringen",
    "sg:phone":"+31 33 462 7195",
    "sg:postcode":"3811 NG",
    "sg:province":"Utrecht",
    "wof:name":"D & R Group Bv",
    "wof:placetype":"venue"
},
  "geometry": {"coordinates":[5.386085,52.152325],"type":"Point"}
}