{
  "type": "Feature",
  "properties": {
    "addr:full":"Kattensingel 62 Gouda Zuid-Holland 2801 CC",
    "addr:housenumber":"62",
    "addr:postcode":"2801 cc",
    "addr:street":"Kattensingel",
    "iso:country":"NL",
    "sg:address":"Kattensingel 62",
    "sg:city":"Gouda",
    "sg:orig_category":"Zuivelproducten And Spijsoli?n Gh",
    "sg:phone":"+31 182 513 944",
    "sg:postcode":"2801 CC",
    "sg:province":"Zuid-Holland",
    "wof:name":"Kaashandel Paul Bv",
    "wof:placetype":"venue"
},
  "geometry": {"coordinates":[4.706673,52.014404],"type":"Point"}
}