{
  "type": "Feature",
  "properties": {
    "iso:country":"NL",
    "sg:address":"Barndestg 25",
    "sg:city":"Amsterdam",
    "sg:orig_category":"Hulpverlening Sociaal",
    "sg:phone":"+31 20 622 6897",
    "sg:postcode":"1012 BV",
    "sg:province":"Noord-Holland",
    "sg:website":"http://www.scharlakenkoord.nl",
    "wof:name":"Scharlaken Koord",
    "wof:placetype":"venue"
},
  "geometry": {"coordinates":[4.8991,52.37244],"type":"Point"}
}