{
  "type": "Feature",
  "properties": {
    "addr:full":"Weg Op Den Heuvel 55 Helmond North Brabant 5701 NV",
    "addr:housenumber":"55",
    "addr:postcode":"5701 nv",
    "addr:street":"Weg Op Den Heuvel",
    "iso:country":"NL",
    "sg:address":"Weg Op Den Heuvel 55",
    "sg:city":"Helmond",
    "sg:orig_category":"Boekhouders",
    "sg:phone":"+31 492 526 111",
    "sg:postcode":"5701 NV",
    "sg:province":"North Brabant",
    "wof:name":"Administratiekantoor H.F. Van De Meulenh",
    "wof:placetype":"venue"
},
  "geometry": {"coordinates":[5.658568,51.476475],"type":"Point"}
}