{
  "type": "Feature",
  "properties": {
    "addr:full":"Sportln 7 Dongen Noord-Brabant 5101 TA",
    "addr:housenumber":"7",
    "addr:postcode":"5101 ta",
    "addr:street":"Sportln",
    "iso:country":"NL",
    "sg:address":"Sportln 7",
    "sg:city":"Dongen",
    "sg:orig_category":"Administratie- En Boekhoudkantoren",
    "sg:phone":"+31 162 313 837",
    "sg:postcode":"5101 TA",
    "sg:province":"Noord-Brabant",
    "wof:name":"Houdt Bv, N C M Van Den",
    "wof:placetype":"venue"
},
  "geometry": {"coordinates":[4.93777,51.629677],"type":"Point"}
}