{
  "type": "Feature",
  "properties": {
    "addr:full":"Postbus 1 Castricum North Holland 1900 AA",
    "addr:housenumber":"1",
    "addr:postcode":"1900 aa",
    "addr:street":"Postbus",
    "iso:country":"NL",
    "sg:address":"Postbus 1",
    "sg:city":"Castricum",
    "sg:orig_category":"Fotolitho- En Reprografie - Inrichtingen",
    "sg:phone":"+31 251 200 679",
    "sg:postcode":"1900 AA",
    "sg:province":"North Holland",
    "wof:name":"Koot, Kees",
    "wof:placetype":"venue"
},
  "geometry": {"coordinates":[4.663725,52.546844],"type":"Point"}
}