{
  "type": "Feature",
  "properties": {
    "addr:full":"Scheepjeshof 94 Veenendaal Utrecht 3901 CW",
    "addr:housenumber":"94",
    "addr:postcode":"3901 cw",
    "addr:street":"Scheepjeshof",
    "iso:country":"NL",
    "sg:address":"Scheepjeshof 94",
    "sg:city":"Veenendaal",
    "sg:orig_category":"Juweliers",
    "sg:phone":"+31 318 550 440",
    "sg:postcode":"3901 CW",
    "sg:province":"Utrecht",
    "wof:name":"Facet Juweliers",
    "wof:placetype":"venue"
},
  "geometry": {"coordinates":[5.555177,52.029182],"type":"Point"}
}