{
  "type": "Feature",
  "properties": {
    "iso:country":"NL",
    "sg:address":"Vrugteveensweg 5A",
    "sg:city":"Hellendoorn",
    "sg:orig_category":"Bloemen And Planten",
    "sg:phone":"+31 548 655 335",
    "sg:postcode":"7447 AL",
    "sg:province":"Overijssel",
    "wof:name":"Gvn Vijverplanten Bv",
    "wof:placetype":"venue"
},
  "geometry": {"coordinates":[6.45366,52.380039],"type":"Point"}
}