{
  "type": "Feature",
  "properties": {
    "addr:full":"De Vierde Hoeve 9 Maasdyk Zuid-Holland 2676 CP",
    "addr:housenumber":"9",
    "addr:postcode":"2676 cp",
    "addr:street":"De Vierde Hoeve",
    "iso:country":"NL",
    "sg:address":"De Vierde Hoeve 9",
    "sg:city":"Maasdyk",
    "sg:orig_category":"Verenigingen En Stichtingen",
    "sg:phone":"+31 174 670 014",
    "sg:postcode":"2676 CP",
    "sg:province":"Zuid-Holland",
    "wof:name":"On Wheels, Sticht",
    "wof:placetype":"venue"
},
  "geometry": {"coordinates":[4.208726,51.959526],"type":"Point"}
}