{
  "type": "Feature",
  "properties": {
    "addr:full":"Gr Jansdk A 135 Westdorpe Zeeland 4554 AK",
    "addr:housenumber":"135",
    "addr:postcode":"4554 ak",
    "addr:street":"A",
    "iso:country":"NL",
    "sg:address":"Gr Jansdk A 135",
    "sg:city":"Westdorpe",
    "sg:orig_category":"Sportverenigingen En Ontspannings- Verenigingen",
    "sg:phone":"+31 115 452 852",
    "sg:postcode":"4554 AK",
    "sg:province":"Zeeland",
    "wof:name":"Grutmoole Volksdansver, De",
    "wof:placetype":"venue"
},
  "geometry": {"coordinates":[3.82829,51.233471],"type":"Point"}
}