{
  "type": "Feature",
  "properties": {
    "addr:full":"Nieuwendijk 11 Heeze Noord-Brabant 5591 JJ",
    "addr:housenumber":"11",
    "addr:postcode":"5591 jj",
    "addr:street":"Nieuwendijk",
    "iso:country":"NL",
    "sg:address":"Nieuwendijk 11",
    "sg:city":"Heeze",
    "sg:orig_category":"Meubelzaken, Woning- And Keukeninrichting",
    "sg:phone":"+31 40 226 0665",
    "sg:postcode":"5591 JJ",
    "sg:province":"Noord-Brabant",
    "wof:name":"Glass Design",
    "wof:placetype":"venue"
},
  "geometry": {"coordinates":[5.57865,51.376129],"type":"Point"}
}