{
  "type": "Feature",
  "properties": {
    "addr:full":"Grote Houtstraat 63 Haarlem Noord-Holland 2011 SE",
    "addr:housenumber":"63",
    "addr:postcode":"2011 se",
    "addr:street":"Grote Houtstraat",
    "iso:country":"NL",
    "sg:address":"Grote Houtstraat 63",
    "sg:city":"Haarlem",
    "sg:orig_category":"Juweliers",
    "sg:phone":"+31 23 532 1711",
    "sg:postcode":"2011 SE",
    "sg:province":"Noord-Holland",
    "wof:name":"Siebel Juweliers Bv",
    "wof:placetype":"venue"
},
  "geometry": {"coordinates":[4.634074,52.379543],"type":"Point"}
}