{
  "type": "Feature",
  "properties": {
    "addr:full":"Herengracht 416 Amsterdam Noord-Holland 1017 BZ",
    "addr:housenumber":"416",
    "addr:postcode":"1017 bz",
    "addr:street":"Herengracht",
    "iso:country":"NL",
    "sg:address":"Herengracht 416",
    "sg:city":"Amsterdam",
    "sg:orig_category":"Diverse Grafische Activiteiten",
    "sg:phone":"+31 20 626 6775",
    "sg:postcode":"1017 BZ",
    "sg:province":"Noord-Holland",
    "wof:name":"De Elementen",
    "wof:placetype":"venue"
},
  "geometry": {"coordinates":[4.887439,52.366856],"type":"Point"}
}