{
  "type": "Feature",
  "properties": {
    "iso:country":"NL",
    "sg:address":"Keurwg 8B",
    "sg:city":"Waalwyk",
    "sg:orig_category":"Kunststoffen- Verwerkende Industrie",
    "sg:phone":"+31 416 319 013",
    "sg:postcode":"5145 NX",
    "sg:province":"North Brabant",
    "wof:name":"Bbb",
    "wof:placetype":"venue"
},
  "geometry": {"coordinates":[5.039955,51.698166],"type":"Point"}
}