{
  "type": "Feature",
  "properties": {
    "addr:full":"Groenendaal 23-25 Rotterdam South Holland 3011 SK",
    "addr:housenumber":"23-25",
    "addr:street":"Groenendaal;3011",
    "iso:country":"NL",
    "sg:address":"Groenendaal 23-25",
    "sg:city":"Rotterdam",
    "sg:orig_category":"Verzekeringen - Verzekeringskantoren",
    "sg:phone":"+31 10 411 0228",
    "sg:postcode":"3011 SK",
    "sg:province":"South Holland",
    "wof:name":"Veld Assurantiebedrijf, A C In 'T",
    "wof:placetype":"venue"
},
  "geometry": {"coordinates":[4.495414,51.922619],"type":"Point"}
}