{
  "type": "Feature",
  "properties": {
    "addr:full":"Korsjespoortsteeg 13 Amsterdam 1015AP",
    "addr:housenumber":"13",
    "addr:postcode":"1015ap",
    "addr:street":"Korsjespoortsteeg",
    "iso:country":"NL",
    "sg:address":"Korsjespoortsteeg 13",
    "sg:city":"Amsterdam",
    "sg:classifiers":[
        {
            "category":"Professional",
            "subcategory":"Computer Services",
            "type":"Services"
        }
    ],
    "sg:postcode":"1015AP",
    "sg:tags":[
        "contacts",
        "mobile",
        "sync",
        "synchronization",
        "address-book"
    ],
    "sg:website":"http://www.soocial.com",
    "wof:name":"Soocial",
    "wof:placetype":"venue"
},
  "geometry": {"coordinates":[4.92319,52.3768747],"type":"Point"}
}