{
  "type": "Feature",
  "properties": {
    "addr:full":"Fideliohof 72 Alphen A/D Rijn Zuid-Holland 2402 ET",
    "addr:housenumber":"72",
    "addr:postcode":"2402 et",
    "addr:street":"Fideliohof",
    "iso:country":"NL",
    "sg:address":"Fideliohof 72",
    "sg:city":"Alphen A/D Rijn",
    "sg:orig_category":"Baby- And Kinderkleding",
    "sg:phone":"+31 172 439 056",
    "sg:postcode":"2402 ET",
    "sg:province":"Zuid-Holland",
    "wof:name":"Bo Bo'Tjes",
    "wof:placetype":"venue"
},
  "geometry": {"coordinates":[4.674664,52.145901],"type":"Point"}
}