{
  "type": "Feature",
  "properties": {
    "addr:full":"Korenmolenln 1E Woerden Utrecht 3447 GG",
    "addr:housenumber":"1e",
    "addr:postcode":"3447 gg",
    "addr:street":"Korenmolenln",
    "iso:country":"NL",
    "sg:address":"Korenmolenln 1E",
    "sg:city":"Woerden",
    "sg:orig_category":"Projectontwikkeling",
    "sg:phone":"+31 348 488 020",
    "sg:postcode":"3447 GG",
    "sg:province":"Utrecht",
    "wof:name":"Ibc Bv",
    "wof:placetype":"venue"
},
  "geometry": {"coordinates":[4.894928,52.078339],"type":"Point"}
}