{
  "type": "Feature",
  "properties": {
    "iso:country":"NL",
    "sg:address":"De Genestetln 33A",
    "sg:city":"Bussum",
    "sg:orig_category":"Fietsen En Bromfietsen",
    "sg:phone":"+31 35 691 3138",
    "sg:postcode":"1401 EJ",
    "sg:province":"North Holland",
    "wof:name":"Fraiture, Annelies De",
    "wof:placetype":"venue"
},
  "geometry": {"coordinates":[5.166181,52.277138],"type":"Point"}
}