{
  "type": "Feature",
  "properties": {
    "iso:country":"NL",
    "sg:address":"Molenweg 3",
    "sg:city":"Oostvoorne",
    "sg:orig_category":"Verzekeringen",
    "sg:phone":"+31 181 483 318",
    "sg:postcode":"3233 AT",
    "sg:province":"Zuid-Holland",
    "wof:name":"Braber & Slabbekoorn",
    "wof:placetype":"venue"
},
  "geometry": {"coordinates":[4.110461,51.913731],"type":"Point"}
}