{
  "type": "Feature",
  "properties": {
    "addr:full":"Vrijstraat 10 Eindhoven North Brabant 5611 AV",
    "addr:housenumber":"10",
    "addr:postcode":"5611 av",
    "addr:street":"Vrijstraat",
    "iso:country":"NL",
    "sg:address":"Vrijstraat 10",
    "sg:city":"Eindhoven",
    "sg:orig_category":"Gespecialiseerde Voeding",
    "sg:phone":"+31 40 244 8954",
    "sg:postcode":"5611 AV",
    "sg:province":"North Brabant",
    "wof:name":"Bloem'S Vinotheek Unique Holland Bv",
    "wof:placetype":"venue"
},
  "geometry": {"coordinates":[5.476905,51.439198],"type":"Point"}
}