{
  "type": "Feature",
  "properties": {
    "iso:country":"NL",
    "sg:address":"Watermanwg 313",
    "sg:city":"Rotterdam",
    "sg:orig_category":"Warenhuizen",
    "sg:phone":"+31 10 286 0469",
    "sg:postcode":"3067 GA",
    "sg:province":"Zuid-Holland",
    "wof:name":"Xenos Bv",
    "wof:placetype":"venue"
},
  "geometry": {"coordinates":[4.5581259727,51.951133728],"type":"Point"}
}