{
  "type": "Feature",
  "properties": {
    "iso:country":"NL",
    "sg:address":"Kerkstr 35",
    "sg:city":"Hattem",
    "sg:orig_category":"Boeken En Tijdschriften",
    "sg:phone":"+31 38 444 1292",
    "sg:postcode":"8051 GK",
    "sg:province":"Gelderland",
    "sg:website":"http://www.bruna.nl",
    "wof:name":"Bruna",
    "wof:placetype":"venue"
},
  "geometry": {"coordinates":[6.067643,52.474663],"type":"Point"}
}