{
  "type": "Feature",
  "properties": {
    "iso:country":"NL",
    "sg:address":"V Almondestr 41",
    "sg:city":"Goudswaard",
    "sg:orig_category":"Kappers",
    "sg:phone":"+31 186 694 588",
    "sg:postcode":"3267 AV",
    "sg:province":"Zuid-Holland",
    "wof:name":"Engel, Den",
    "wof:placetype":"venue"
},
  "geometry": {"coordinates":[4.2745847702,51.7960090637],"type":"Point"}
}