{
  "type": "Feature",
  "properties": {
    "iso:country":"NL",
    "sg:address":"K Havenstr 6",
    "sg:city":"Oudewater",
    "sg:classifiers":[
        {
            "category":"Food & Beverages",
            "subcategory":"Bakery",
            "type":"Retail Goods"
        }
    ],
    "sg:phone":"+31 348 561 279",
    "sg:postcode":"3421 AG",
    "sg:province":"Utrecht",
    "sg:tags":[
        "brood",
        "en",
        "banket"
    ],
    "wof:name":"Stijnman",
    "wof:placetype":"venue"
},
  "geometry": {"coordinates":[4.872141,52.021896],"type":"Point"}
}