{
  "type": "Feature",
  "properties": {
    "addr:full":"Kaapseplein 43 'S Gravenhage South Holland 2572 NE",
    "addr:housenumber":"43",
    "addr:postcode":"2572 ne",
    "addr:street":"Kaapseplein;' S Gravenhage",
    "iso:country":"NL",
    "sg:address":"Kaapseplein 43",
    "sg:city":"'S Gravenhage",
    "sg:orig_category":"Werving And Selectie Van Tijdelijk Personeel And Uitzendkantoren",
    "sg:phone":"+31 70 388 3662",
    "sg:postcode":"2572 NE",
    "sg:province":"South Holland",
    "wof:name":"Alkan Uitzendbureau Bv",
    "wof:placetype":"venue"
},
  "geometry": {"coordinates":[4.2966527939,52.0612297058],"type":"Point"}
}