{
  "type": "Feature",
  "properties": {
    "iso:country":"NL",
    "sg:address":"Kaapseplein 43",
    "sg:city":"'S Gravenhage",
    "sg:orig_category":"Werving And Selectie Van Tijdelijk Personeel And Uitzendkantoren",
    "sg:phone":"+31 70 388 3662",
    "sg:postcode":"2572 NE",
    "sg:province":"South Holland",
    "wof:name":"Alkan Uitzendbureau Bv",
    "wof:placetype":"venue"
},
  "geometry": {"coordinates":[4.2966527939,52.0612297058],"type":"Point"}
}