{
  "type": "Feature",
  "properties": {
    "iso:country":"NL",
    "sg:address":"Rochussenstr 67 C",
    "sg:city":"Rotterdam",
    "sg:orig_category":"Artsen - Huisartsen",
    "sg:phone":"+31 10 436 0141",
    "sg:postcode":"3015 ED",
    "sg:province":"Zuid-Holland",
    "wof:name":"Oemrawsingh, R P",
    "wof:placetype":"venue"
},
  "geometry": {"coordinates":[4.468174,51.913708],"type":"Point"}
}