{
  "type": "Feature",
  "properties": {
    "addr:full":"Herenstraat 60 Voorburg Zuid-Holland 2271 CJ",
    "addr:housenumber":"60",
    "addr:postcode":"2271 cj",
    "addr:street":"Herenstraat",
    "iso:country":"NL",
    "sg:address":"Herenstraat 60",
    "sg:city":"Voorburg",
    "sg:orig_category":"Visspeciaalzaken",
    "sg:phone":"+31 70 386 1728",
    "sg:postcode":"2271 CJ",
    "sg:province":"Zuid-Holland",
    "wof:name":"Atlantis Vis & Visspecialiteiten",
    "wof:placetype":"venue"
},
  "geometry": {"coordinates":[4.364727,52.067699],"type":"Point"}
}