{
  "type": "Feature",
  "properties": {
    "addr:full":"K Kruiswg 48 Maasdyk South Holland 2676 BS",
    "addr:housenumber":"48",
    "addr:postcode":"2676 bs",
    "addr:street":"Kruiswg",
    "iso:country":"NL",
    "sg:address":"K Kruiswg 48",
    "sg:city":"Maasdyk",
    "sg:orig_category":"Banken",
    "sg:phone":"+31 174 527 800",
    "sg:postcode":"2676 BS",
    "sg:province":"South Holland",
    "sg:website":"http://www.rabobank.nl",
    "wof:name":"Rabobank",
    "wof:placetype":"venue"
},
  "geometry": {"coordinates":[4.21651,51.95908],"type":"Point"}
}