{
  "type": "Feature",
  "properties": {
    "addr:full":"E Dorsstr 23 Grubbenvorst Limburg 5971 VE",
    "addr:housenumber":"23",
    "addr:postcode":"5971",
    "addr:street":"E;Ve",
    "iso:country":"NL",
    "sg:address":"E Dorsstr 23",
    "sg:city":"Grubbenvorst",
    "sg:orig_category":"Sportverenigingen En Ontspannings- Verenigingen",
    "sg:phone":"+31 77 366 2875",
    "sg:postcode":"5971 VE",
    "sg:province":"Limburg",
    "wof:name":"Grubbenvorst Badmintoncl",
    "wof:placetype":"venue"
},
  "geometry": {"coordinates":[6.148142,51.419395],"type":"Point"}
}