{
  "type": "Feature",
  "properties": {
    "iso:country":"NL",
    "sg:address":"Lekkenburg 25",
    "sg:city":"Gouda",
    "sg:orig_category":"Boeken En Tijdschriften",
    "sg:phone":"+31 182 532 058",
    "sg:postcode":"2804 XA",
    "sg:province":"Zuid-Holland",
    "wof:name":"Read Shop, The",
    "wof:placetype":"venue"
},
  "geometry": {"coordinates":[4.705287,52.03204],"type":"Point"}
}