{
  "type": "Feature",
  "properties": {
    "addr:full":"Ganzeweide 58A Heerlen Limburg 6413 GG",
    "addr:housenumber":"58a",
    "addr:postcode":"6413 gg",
    "addr:street":"Ganzeweide",
    "iso:country":"NL",
    "sg:address":"Ganzeweide 58A",
    "sg:city":"Heerlen",
    "sg:orig_category":"Banken",
    "sg:phone":"+31 45 563 0000",
    "sg:postcode":"6413 GG",
    "sg:province":"Limburg",
    "sg:website":"http://www.sns.nl",
    "wof:name":"Sns",
    "wof:placetype":"venue"
},
  "geometry": {"coordinates":[5.954658,50.915215],"type":"Point"}
}