{
  "type": "Feature",
  "properties": {
    "addr:full":"Koppelstr 10 Roggel Limburg 6088 EP",
    "addr:housenumber":"10",
    "addr:postcode":"6088 ep",
    "addr:street":"Koppelstr",
    "iso:country":"NL",
    "sg:address":"Koppelstr 10",
    "sg:city":"Roggel",
    "sg:orig_category":"Postkantoren",
    "sg:phone":"+31 475 491 310",
    "sg:postcode":"6088 EP",
    "sg:province":"Limburg",
    "sg:website":"http://www.postkantoor.nl",
    "wof:name":"Postkantoor",
    "wof:placetype":"venue"
},
  "geometry": {"coordinates":[5.925519,51.264576],"type":"Point"}
}