{
  "type": "Feature",
  "properties": {
    "addr:full":"Dorpsstr 34 Bergschenhoek Zuid-Holland 2661 CG",
    "addr:housenumber":"34",
    "addr:postcode":"2661 cg",
    "addr:street":"Dorpsstr",
    "iso:country":"NL",
    "sg:address":"Dorpsstr 34",
    "sg:city":"Bergschenhoek",
    "sg:orig_category":"Herenkleding",
    "sg:phone":"+31 10 521 6571",
    "sg:postcode":"2661 CG",
    "sg:province":"Zuid-Holland",
    "wof:name":"Evert",
    "wof:placetype":"venue"
},
  "geometry": {"coordinates":[4.500449,51.988987],"type":"Point"}
}