{
  "type": "Feature",
  "properties": {
    "addr:full":"Zuidkade 21 Waddinxveen Zuid-Holland 2741 JB",
    "addr:housenumber":"21",
    "addr:postcode":"2741 jb",
    "addr:street":"Zuidkade",
    "iso:country":"NL",
    "sg:address":"Zuidkade 21",
    "sg:city":"Waddinxveen",
    "sg:classifiers":[
        {
            "category":"Fast Food",
            "type":"Food & Drink"
        }
    ],
    "sg:phone":"+31 182 611 199",
    "sg:postcode":"2741 JB",
    "sg:province":"Zuid-Holland",
    "sg:tags":[
        "afhaal",
        "restaurant"
    ],
    "wof:name":"Pizza Spidi",
    "wof:placetype":"venue"
},
  "geometry": {"coordinates":[4.658916,52.04221],"type":"Point"}
}