{
  "type": "Feature",
  "properties": {
    "addr:full":"Postbus 53481 'S-Gravenhage Noord-Brabant 2505 AL",
    "addr:housenumber":"53481;2505",
    "addr:postcode":"s-gravenhage;al",
    "addr:street":"Postbus",
    "iso:country":"NL",
    "sg:address":"Postbus 53481",
    "sg:city":"'S-Gravenhage",
    "sg:orig_category":"Bedrijfsmechanisatie En -Automatisering",
    "sg:phone":"+31 70 352 0354",
    "sg:postcode":"2505 AL",
    "sg:province":"Noord-Brabant",
    "wof:name":"Use Autonomic Trainbrain",
    "wof:placetype":"venue"
},
  "geometry": {"coordinates":[4.31361,52.07832],"type":"Point"}
}