{
  "type": "Feature",
  "properties": {
    "iso:country":"NL",
    "sg:address":"Buitenwg 26",
    "sg:city":"Maarssen",
    "sg:orig_category":"Kappers",
    "sg:phone":"+31 346 553 030",
    "sg:postcode":"3602 PS",
    "sg:province":"Utrecht",
    "wof:name":"Kenzo",
    "wof:placetype":"venue"
},
  "geometry": {"coordinates":[5.0549578667,52.1364059448],"type":"Point"}
}