{
  "type": "Feature",
  "properties": {
    "addr:full":"Klaverbeemd 19 Terheijden North Brabant 4844 RH",
    "addr:housenumber":"19",
    "addr:postcode":"4844 rh",
    "addr:street":"Klaverbeemd",
    "iso:country":"NL",
    "sg:address":"Klaverbeemd 19",
    "sg:city":"Terheijden",
    "sg:orig_category":"Autokeuringen",
    "sg:phone":"+31 76 593 2325",
    "sg:postcode":"4844 RH",
    "sg:province":"North Brabant",
    "wof:name":"Yildirim Auto'S",
    "wof:placetype":"venue"
},
  "geometry": {"coordinates":[4.756276,51.644302],"type":"Point"}
}