{
  "type": "Feature",
  "properties": {
    "addr:full":"Kerklaan 2 Langeveen Overijssel 7679 VG",
    "addr:housenumber":"2",
    "addr:postcode":"7679 vg",
    "addr:street":"Kerklaan",
    "iso:country":"NL",
    "sg:address":"Kerklaan 2",
    "sg:city":"Langeveen",
    "sg:classifiers":[
        {
            "category":"Education",
            "subcategory":"Preschool",
            "type":"Public Place"
        }
    ],
    "sg:phone":"+31 546 681 358",
    "sg:postcode":"7679 VG",
    "sg:province":"Overijssel",
    "sg:tags":[
        "kleuteronderwijs",
        "basis-"
    ],
    "wof:name":"Mariaschool",
    "wof:placetype":"venue"
},
  "geometry": {"coordinates":[6.71358,52.46896],"type":"Point"}
}