{
  "type": "Feature",
  "properties": {
    "addr:full":"Visstr 18 Zierikzee Zeeland 4301 CC",
    "addr:housenumber":"18",
    "addr:postcode":"4301 cc",
    "addr:street":"Visstr",
    "iso:country":"NL",
    "sg:address":"Visstr 18",
    "sg:city":"Zierikzee",
    "sg:orig_category":"Wintersportkleding En -Artikelen",
    "sg:phone":"+31 111 413 774",
    "sg:postcode":"4301 CC",
    "sg:province":"Zeeland",
    "wof:name":"Sporthuis Zierikzee",
    "wof:placetype":"venue"
},
  "geometry": {"coordinates":[3.9205880165,51.6488380432],"type":"Point"}
}