{
  "type": "Feature",
  "properties": {
    "addr:full":"Westerpk 74 Tilburg Noord-Brabant 5042 MH",
    "addr:housenumber":"74",
    "addr:postcode":"5042 mh",
    "addr:street":"Westerpk",
    "iso:country":"NL",
    "sg:address":"Westerpk 74",
    "sg:city":"Tilburg",
    "sg:orig_category":"Afslankinstituten",
    "sg:phone":"+31 13 463 3104",
    "sg:postcode":"5042 MH",
    "sg:province":"Noord-Brabant",
    "wof:name":"Slank-Klup",
    "wof:placetype":"venue"
},
  "geometry": {"coordinates":[5.049786,51.571232],"type":"Point"}
}