{
  "type": "Feature",
  "properties": {
    "addr:full":"St Maartenstr 14 Oosterhout Nb Noord-Brabant 4902 XN",
    "addr:housenumber":"14",
    "addr:postcode":"4902 xn",
    "iso:country":"NL",
    "sg:address":"St Maartenstr 14",
    "sg:city":"Oosterhout Nb",
    "sg:classifiers":[
        {
            "category":"Utilities",
            "subcategory":"Cable",
            "type":"Services"
        }
    ],
    "sg:phone":"+31 162 430 001",
    "sg:postcode":"4902 XN",
    "sg:province":"Noord-Brabant",
    "sg:tags":[
        "masseur",
        "en",
        "heilgymnasten"
    ],
    "wof:name":"Africa-Bambou",
    "wof:placetype":"venue"
},
  "geometry": {"coordinates":[4.860828,51.63599],"type":"Point"}
}