{
  "type": "Feature",
  "properties": {
    "addr:full":"Burgemeesterpk 9 Driebergen Rysenb Utrecht 3971 CT",
    "addr:housenumber":"9",
    "addr:postcode":"3971 ct",
    "addr:street":"Burgemeesterpk;Rysenb",
    "iso:country":"NL",
    "sg:address":"Burgemeesterpk 9",
    "sg:city":"Driebergen Rysenb",
    "sg:orig_category":"Kantoor- En Secretariaatsservice",
    "sg:phone":"+31 343 513 330",
    "sg:postcode":"3971 CT",
    "sg:province":"Utrecht",
    "wof:name":"Fmo",
    "wof:placetype":"venue"
},
  "geometry": {"coordinates":[5.2895097733,52.0577392578],"type":"Point"}
}