{
  "type": "Feature",
  "properties": {
    "iso:country":"NL",
    "sg:address":"Zwaagdijk 396",
    "sg:city":"Zwaagdijk",
    "sg:orig_category":"Fruitteelt",
    "sg:phone":"+31 229 573 255",
    "sg:postcode":"1686 PH",
    "sg:province":"Noord-Holland",
    "wof:name":"Firma Sjaak Jong",
    "wof:placetype":"venue"
},
  "geometry": {"coordinates":[5.13598,52.705639],"type":"Point"}
}