{
  "type": "Feature",
  "properties": {
    "addr:full":"Kloosterstr 11 Beverwyk Noord-Holland 1941 BN",
    "addr:housenumber":"11",
    "addr:postcode":"1941 bn",
    "addr:street":"Kloosterstr",
    "iso:country":"NL",
    "sg:address":"Kloosterstr 11",
    "sg:city":"Beverwyk",
    "sg:orig_category":"Administratie- En Boekhoudkantoren",
    "sg:phone":"+31 251 274 274",
    "sg:postcode":"1941 BN",
    "sg:province":"Noord-Holland",
    "wof:name":"Eckhard",
    "wof:placetype":"venue"
},
  "geometry": {"coordinates":[4.656259,52.483028],"type":"Point"}
}