{
  "type": "Feature",
  "properties": {
    "iso:country":"NL",
    "sg:address":"Van Goghstraat 10",
    "sg:city":"Horst",
    "sg:orig_category":"Boekhouders",
    "sg:phone":"+31 77 398 2902",
    "sg:postcode":"5961 AR",
    "sg:province":"Limburg",
    "wof:name":"Jabelad",
    "wof:placetype":"venue"
},
  "geometry": {"coordinates":[-63.666481,-31.56329],"type":"Point"}
}