{
  "type": "Feature",
  "properties": {
    "addr:full":"Haspelwyk 17 Zevenhuizen Gn Groningen 9354 VT",
    "addr:housenumber":"17;gn",
    "addr:postcode":"9354",
    "addr:street":"Haspelwyk",
    "iso:country":"NL",
    "sg:address":"Haspelwyk 17",
    "sg:city":"Zevenhuizen Gn",
    "sg:orig_category":"Adviesbureaus Economie",
    "sg:phone":"+31 594 631 630",
    "sg:postcode":"9354 VT",
    "sg:province":"Groningen",
    "wof:name":"Laan, Vd",
    "wof:placetype":"venue"
},
  "geometry": {"coordinates":[6.348505,53.124569],"type":"Point"}
}