{
  "type": "Feature",
  "properties": {
    "addr:full":"Steynlaan 81 Zeist Utrecht 3701 ED",
    "addr:housenumber":"81",
    "addr:postcode":"3701 ed",
    "addr:street":"Steynlaan",
    "iso:country":"NL",
    "sg:address":"Steynlaan 81",
    "sg:city":"Zeist",
    "sg:orig_category":"Kappers",
    "sg:phone":"+31 30 692 0432",
    "sg:postcode":"3701 ED",
    "sg:province":"Utrecht",
    "wof:name":"Berty'S Hairstyling",
    "wof:placetype":"venue"
},
  "geometry": {"coordinates":[5.2434129715,52.0911026001],"type":"Point"}
}