{
  "type": "Feature",
  "properties": {
    "addr:full":"Statensingel 176 Maastricht Limburg 6217 KJ",
    "addr:housenumber":"176",
    "addr:postcode":"6217 kj",
    "addr:street":"Statensingel",
    "iso:country":"NL",
    "sg:address":"Statensingel 176",
    "sg:city":"Maastricht",
    "sg:orig_category":"Meubelzaken, Woning- And Keukeninrichting",
    "sg:phone":"+31 43 321 8698",
    "sg:postcode":"6217 KJ",
    "sg:province":"Limburg",
    "wof:name":"Marni'S Trading Company",
    "wof:placetype":"venue"
},
  "geometry": {"coordinates":[5.678093,50.850422],"type":"Point"}
}