{
  "type": "Feature",
  "properties": {
    "iso:country":"NL",
    "sg:address":"Hoendiepstr 20",
    "sg:city":"Utrecht",
    "sg:orig_category":"Onderhoudswerken",
    "sg:phone":"+31 30 288 8202",
    "sg:postcode":"3522 GD",
    "sg:province":"Utrecht",
    "wof:name":"Teunissen",
    "wof:placetype":"venue"
},
  "geometry": {"coordinates":[5.115038,52.068459],"type":"Point"}
}