{
  "type": "Feature",
  "properties": {
    "addr:full":"Schoolstr 12A Vroomshoop Overijssel 7681 CK",
    "addr:housenumber":"12a",
    "addr:postcode":"7681 ck",
    "addr:street":"Schoolstr",
    "iso:country":"NL",
    "sg:address":"Schoolstr 12A",
    "sg:city":"Vroomshoop",
    "sg:orig_category":"Meubelmakerijen",
    "sg:phone":"+31 6 20621847",
    "sg:postcode":"7681 CK",
    "sg:province":"Overijssel",
    "wof:name":"Zandbergen Meubelmakerij",
    "wof:placetype":"venue"
},
  "geometry": {"coordinates":[6.573225,52.464355],"type":"Point"}
}