{
  "type": "Feature",
  "properties": {
    "iso:country":"NL",
    "sg:address":"Koninginneln 63",
    "sg:city":"Apeldoorn",
    "sg:orig_category":"Juweliers",
    "sg:phone":"+31 55 522 1963",
    "sg:postcode":"7315 BM",
    "sg:province":"Gelderland",
    "wof:name":"Mulderij, W",
    "wof:placetype":"venue"
},
  "geometry": {"coordinates":[5.956408,52.22485],"type":"Point"}
}