{
  "type": "Feature",
  "properties": {
    "iso:country":"NL",
    "sg:address":"Esscheweg 74",
    "sg:city":"Sint Michielsgestel",
    "sg:orig_category":"Hypotheken And Hypotheekbanken",
    "sg:phone":"+31 73 551 4241",
    "sg:postcode":"5271 NA",
    "sg:province":"Noord-Brabant",
    "wof:name":"Romeijnders Partners Bv",
    "wof:placetype":"venue"
},
  "geometry": {"coordinates":[5.3415608406,51.6331863403],"type":"Point"}
}