{
  "type": "Feature",
  "properties": {
    "iso:country":"NL",
    "sg:address":"Bremstr 10",
    "sg:city":"Enschede",
    "sg:orig_category":"Bestratingen",
    "sg:phone":"+31 53 430 1923",
    "sg:postcode":"7531 CJ",
    "sg:province":"Overijssel",
    "wof:name":"Dusschoten, Van",
    "wof:placetype":"venue"
},
  "geometry": {"coordinates":[6.913906,52.226089],"type":"Point"}
}