{
  "type": "Feature",
  "properties": {
    "iso:country":"NL",
    "sg:address":"Havenpk 3",
    "sg:city":"Zierikzee",
    "sg:orig_category":"Makelaars En Adviseurs Onroerende Goederen",
    "sg:phone":"+31 111 451 500",
    "sg:postcode":"4301 JG",
    "sg:province":"Zeeland",
    "sg:website":"http://www.sinke.nl",
    "wof:name":"Sinke Komejan Bv",
    "wof:placetype":"venue"
},
  "geometry": {"coordinates":[3.921941,51.649654],"type":"Point"}
}