{
  "type": "Feature",
  "properties": {
    "addr:full":"Nw Ryn 33 Leiden South Holland 2312 JE",
    "addr:housenumber":"33",
    "addr:postcode":"2312 je",
    "addr:street":"Nw Ryn",
    "iso:country":"NL",
    "sg:address":"Nw Ryn 33",
    "sg:city":"Leiden",
    "sg:orig_category":"Kappers",
    "sg:phone":"+31 71 514 4753",
    "sg:postcode":"2312 JE",
    "sg:province":"South Holland",
    "wof:name":"Ziggy",
    "wof:placetype":"venue"
},
  "geometry": {"coordinates":[4.49463,52.154572],"type":"Point"}
}