{
  "type": "Feature",
  "properties": {
    "addr:full":"Eikenln 37 Groningen Groningen 9741 EH",
    "addr:housenumber":"37",
    "addr:postcode":"9741 eh",
    "addr:street":"Eikenln",
    "iso:country":"NL",
    "sg:address":"Eikenln 37",
    "sg:city":"Groningen",
    "sg:orig_category":"Bloemen En Planten",
    "sg:phone":"+31 50 577 1031",
    "sg:postcode":"9741 EH",
    "sg:province":"Groningen",
    "wof:name":"Abutilon",
    "wof:placetype":"venue"
},
  "geometry": {"coordinates":[6.55351,53.233047],"type":"Point"}
}