{
  "type": "Feature",
  "properties": {
    "addr:full":"Postbus 2330 Leeuwarden Provincie Friesland 8901 JH",
    "addr:postcode":"2330;8901 jh",
    "addr:street":"Postbus;Friesland",
    "iso:country":"NL",
    "sg:address":"Postbus 2330",
    "sg:city":"Leeuwarden",
    "sg:orig_category":"Accountants - Administratie- Consulenten En -Kantoren",
    "sg:phone":"+31 58 288 7887",
    "sg:postcode":"8901 JH",
    "sg:province":"Provincie Friesland",
    "sg:website":"http://www.avm.nl/subsidies",
    "wof:name":"Avm",
    "wof:placetype":"venue"
},
  "geometry": {"coordinates":[5.79143,53.203049],"type":"Point"}
}