{
  "type": "Feature",
  "properties": {
    "iso:country":"NL",
    "sg:address":"Lieuwenburg 186",
    "sg:city":"Leeuwarden",
    "sg:orig_category":"Fietshandelaren",
    "sg:phone":"+31 58 266 3330",
    "sg:postcode":"8925 CL",
    "sg:province":"Provincie Friesland",
    "wof:name":"De Fietswinkel Mient De Vries",
    "wof:placetype":"venue"
},
  "geometry": {"coordinates":[5.838572,53.211246],"type":"Point"}
}