{
  "type": "Feature",
  "properties": {
    "addr:full":"3E Industriewg 5A Lopik Utrecht 3411 MD",
    "addr:housenumber":"5a",
    "addr:postcode":"3411",
    "addr:street":"3E Industriewg",
    "iso:country":"NL",
    "sg:address":"3E Industriewg 5A",
    "sg:city":"Lopik",
    "sg:orig_category":"Kaasgroothandel",
    "sg:phone":"+31 348 743 052",
    "sg:postcode":"3411 MD",
    "sg:province":"Utrecht",
    "wof:name":"Kvl",
    "wof:placetype":"venue"
},
  "geometry": {"coordinates":[4.9704108238,51.9859924316],"type":"Point"}
}