{
  "type": "Feature",
  "properties": {
    "iso:country":"NL",
    "sg:address":"V Ittersumstr 112",
    "sg:city":"Zwolle",
    "sg:classifiers":[
        {
            "category":"Food & Beverages",
            "subcategory":"Bakery",
            "type":"Retail Goods"
        }
    ],
    "sg:phone":"+31 38 423 0026",
    "sg:postcode":"8012 TM",
    "sg:province":"NL.08",
    "sg:tags":[
        "pizza"
    ],
    "wof:name":"Pizza 8660",
    "wof:placetype":"venue"
},
  "geometry": {"coordinates":[6.088738,52.512566],"type":"Point"}
}