{
  "type": "Feature",
  "properties": {
    "iso:country":"NL",
    "sg:address":"Hartenstr 18",
    "sg:city":"Amsterdam",
    "sg:orig_category":"Verenigingen En Stichtingen",
    "sg:phone":"+31 20 625 4450",
    "sg:postcode":"1016 CB",
    "sg:province":"Noord-Holland",
    "wof:name":"Gilde Amsterdam",
    "wof:placetype":"venue"
},
  "geometry": {"coordinates":[4.886052,52.372448],"type":"Point"}
}