{
  "type": "Feature",
  "properties": {
    "iso:country":"NL",
    "sg:address":"Zuidelijke Burgvlietkade 16",
    "sg:city":"Gouda",
    "sg:orig_category":"Architecten",
    "sg:phone":"+31 182 682 382",
    "sg:postcode":"2806 BK",
    "sg:province":"Zuid-Holland",
    "wof:name":"2M Architektuur Bv",
    "wof:placetype":"venue"
},
  "geometry": {"coordinates":[4.7217011452,52.0157203674],"type":"Point"}
}