{
  "type": "Feature",
  "properties": {
    "addr:full":"De Gronckelstr 1 Limbricht Limburg 6141 AG",
    "addr:housenumber":"1",
    "addr:postcode":"6141",
    "iso:country":"NL",
    "sg:address":"De Gronckelstr 1",
    "sg:city":"Limbricht",
    "sg:orig_category":"Verenigingsgebouwen",
    "sg:phone":"+31 46 452 5473",
    "sg:postcode":"6141 AG",
    "sg:province":"Limburg",
    "wof:name":"Waope Van L\u00f6mmerich, 'T",
    "wof:placetype":"venue"
},
  "geometry": {"coordinates":[5.840044,51.011845],"type":"Point"}
}