{
  "type": "Feature",
  "properties": {
    "iso:country":"NL",
    "sg:address":"Suikerpot 2",
    "sg:city":"Kortenhoef",
    "sg:orig_category":"Agenturen En Commissiehandel",
    "sg:phone":"+31 35 656 2191",
    "sg:postcode":"1241 HK",
    "sg:province":"Noord-Holland",
    "wof:name":"Verhagen",
    "wof:placetype":"venue"
},
  "geometry": {"coordinates":[5.110416,52.237873],"type":"Point"}
}