{
  "type": "Feature",
  "properties": {
    "iso:country":"NL",
    "sg:address":"Monnickendammerijweg 18 A",
    "sg:city":"Ilpendam",
    "sg:orig_category":"Partycatering And -Organisatie",
    "sg:phone":"+31 20 436 1247",
    "sg:postcode":"1452 PL",
    "sg:province":"North Holland",
    "wof:name":"Rinders Catering",
    "wof:placetype":"venue"
},
  "geometry": {"coordinates":[4.954189,52.460434],"type":"Point"}
}