{
  "type": "Feature",
  "properties": {
    "addr:full":"Monnickendammerijweg 18 A Ilpendam North Holland 1452 PL",
    "addr:housenumber":"18 a",
    "addr:postcode":"1452 pl",
    "addr:street":"Monnickendammerijweg",
    "iso:country":"NL",
    "sg:address":"Monnickendammerijweg 18 A",
    "sg:city":"Ilpendam",
    "sg:orig_category":"Partycatering And -Organisatie",
    "sg:phone":"+31 20 436 1247",
    "sg:postcode":"1452 PL",
    "sg:province":"North Holland",
    "wof:name":"Rinders Catering",
    "wof:placetype":"venue"
},
  "geometry": {"coordinates":[4.954189,52.460434],"type":"Point"}
}