{
  "type": "Feature",
  "properties": {
    "addr:full":"De Houtakker 4 Bemmel Gelderland 6681 CW",
    "addr:housenumber":"4",
    "addr:postcode":"6681 cw",
    "addr:street":"De Houtakker;Gelderland",
    "iso:country":"NL",
    "sg:address":"De Houtakker 4",
    "sg:city":"Bemmel",
    "sg:orig_category":"Meubelzaken, Woning- And Keukeninrichting",
    "sg:phone":"+31 481 462 586",
    "sg:postcode":"6681 CW",
    "sg:province":"Gelderland",
    "wof:name":"Jac Van Roosmalen Interieurs",
    "wof:placetype":"venue"
},
  "geometry": {"coordinates":[5.910307,51.895813],"type":"Point"}
}