{
  "type": "Feature",
  "properties": {
    "iso:country":"NL",
    "sg:address":"De Houtakker 4",
    "sg:city":"Bemmel",
    "sg:orig_category":"Meubelzaken, Woning- And Keukeninrichting",
    "sg:phone":"+31 481 462 586",
    "sg:postcode":"6681 CW",
    "sg:province":"Gelderland",
    "wof:name":"Jac Van Roosmalen Interieurs",
    "wof:placetype":"venue"
},
  "geometry": {"coordinates":[5.910307,51.895813],"type":"Point"}
}