{
  "type": "Feature",
  "properties": {
    "addr:full":"Jachthuisstr 2 Kloetinge Zeeland 4481 AL",
    "addr:housenumber":"2",
    "addr:postcode":"4481 al",
    "addr:street":"Jachthuisstr",
    "iso:country":"NL",
    "sg:address":"Jachthuisstr 2",
    "sg:city":"Kloetinge",
    "sg:orig_category":"Fietsen En Bromfietsen",
    "sg:phone":"+31 113 216 613",
    "sg:postcode":"4481 AL",
    "sg:province":"Zeeland",
    "wof:name":"Verstelle, M",
    "wof:placetype":"venue"
},
  "geometry": {"coordinates":[3.916668,51.497948],"type":"Point"}
}