{
  "type": "Feature",
  "properties": {
    "addr:full":"Platengastr 1 Hoogerheide North Brabant 4631 KZ",
    "addr:housenumber":"1",
    "addr:postcode":"4631 kz",
    "addr:street":"Platengastr",
    "iso:country":"NL",
    "sg:address":"Platengastr 1",
    "sg:city":"Hoogerheide",
    "sg:orig_category":"Verzekeringen - Verzekeringskantoren",
    "sg:phone":"+31 164 612 494",
    "sg:postcode":"4631 KZ",
    "sg:province":"North Brabant",
    "wof:name":"Goossens",
    "wof:placetype":"venue"
},
  "geometry": {"coordinates":[4.325936,51.421288],"type":"Point"}
}