{
  "type": "Feature",
  "properties": {
    "addr:full":"Smidsweg 97 Nijverdal Overijssel 7441 EL",
    "addr:housenumber":"97",
    "addr:postcode":"7441 el",
    "addr:street":"Smidsweg",
    "iso:country":"NL",
    "sg:address":"Smidsweg 97",
    "sg:city":"Nijverdal",
    "sg:orig_category":"Werving And Selectie Van Tijdelijk Personeel And Uitzendkantoren",
    "sg:phone":"+31 548 616 609",
    "sg:postcode":"7441 EL",
    "sg:province":"Overijssel",
    "wof:name":"Uitzendburo Oost-Nederland",
    "wof:placetype":"venue"
},
  "geometry": {"coordinates":[6.4591431618,52.3615531921],"type":"Point"}
}