{
  "type": "Feature",
  "properties": {
    "addr:full":"Frits Ruysstraat 40 Rotterdam Zuid-Holland 3061 MG",
    "addr:housenumber":"40",
    "addr:postcode":"3061 mg",
    "addr:street":"Frits Ruysstraat",
    "iso:country":"NL",
    "sg:address":"Frits Ruysstraat 40",
    "sg:city":"Rotterdam",
    "sg:orig_category":"Juweliers",
    "sg:phone":"+31 10 212 2990",
    "sg:postcode":"3061 MG",
    "sg:province":"Zuid-Holland",
    "wof:name":"Goudsmederij Domeni",
    "wof:placetype":"venue"
},
  "geometry": {"coordinates":[4.502112,51.926926],"type":"Point"}
}