{
  "type": "Feature",
  "properties": {
    "iso:country":"NL",
    "sg:address":"Kruisstraat 18",
    "sg:city":"Hattem",
    "sg:orig_category":"Kappers",
    "sg:phone":"+31 38 444 7600",
    "sg:postcode":"8051 GE",
    "sg:province":"Gelderland",
    "wof:name":"Woldberg Hairstyling",
    "wof:placetype":"venue"
},
  "geometry": {"coordinates":[6.070066,52.475368],"type":"Point"}
}