{
  "type": "Feature",
  "properties": {
    "addr:full":"Kloosterpln 6 Breda Noord-Brabant 4811 GN",
    "addr:housenumber":"6",
    "addr:postcode":"4811 gn",
    "addr:street":"Kloosterpln",
    "iso:country":"NL",
    "sg:address":"Kloosterpln 6",
    "sg:city":"Breda",
    "sg:orig_category":"Verenigingen En Stichtingen",
    "sg:phone":"+31 76 521 2046",
    "sg:postcode":"4811 GN",
    "sg:province":"Noord-Brabant",
    "wof:name":"Dagbehandelingscentrum",
    "wof:placetype":"venue"
},
  "geometry": {"coordinates":[4.780486,51.587852],"type":"Point"}
}