{
  "type": "Feature",
  "properties": {
    "addr:full":"Rechtestraat 13 Eindhoven Noord-Brabant 5611 GL",
    "addr:housenumber":"13",
    "addr:postcode":"5611 gl",
    "addr:street":"Rechtestraat",
    "iso:country":"NL",
    "sg:address":"Rechtestraat 13",
    "sg:city":"Eindhoven",
    "sg:orig_category":"Discountwinkels",
    "sg:phone":"+31 40 244 2825",
    "sg:postcode":"5611 GL",
    "sg:province":"Noord-Brabant",
    "wof:name":"Men At Work",
    "wof:placetype":"venue"
},
  "geometry": {"coordinates":[5.477973,51.439007],"type":"Point"}
}