{
  "type": "Feature",
  "properties": {
    "iso:country":"NL",
    "sg:address":"De Koppel 5",
    "sg:city":"Nuenen",
    "sg:classifiers":[
        {
            "category":"Education",
            "subcategory":"Preschool",
            "type":"Public Place"
        }
    ],
    "sg:phone":"+31 40 283 1207",
    "sg:postcode":"5674 NW",
    "sg:province":"Noord-Brabant",
    "sg:tags":[
        "kleuteronderwijs",
        "basis-"
    ],
    "wof:name":"Basisschool St. Jozef",
    "wof:placetype":"venue"
},
  "geometry": {"coordinates":[5.521568,51.492298],"type":"Point"}
}