{
  "type": "Feature",
  "properties": {
    "addr:full":"Gen Cronjestr 45 Haarlem Noord-Holland 2021 JB",
    "addr:housenumber":"45",
    "addr:postcode":"2021 jb",
    "iso:country":"NL",
    "sg:address":"Gen Cronjestr 45",
    "sg:city":"Haarlem",
    "sg:classifiers":[
        {
            "category":"Food & Beverages",
            "subcategory":"Bakery",
            "type":"Retail Goods"
        }
    ],
    "sg:phone":"+31 23 526 0928",
    "sg:postcode":"2021 JB",
    "sg:province":"Noord-Holland",
    "sg:tags":[
        "brood",
        "en",
        "banket"
    ],
    "wof:name":"Vink Bv",
    "wof:placetype":"venue"
},
  "geometry": {"coordinates":[4.641229,52.393684],"type":"Point"}
}