{
  "type": "Feature",
  "properties": {
    "addr:full":"J Dobbelsteenstr 18 Loosbroek Noord-Brabant 5472 PK",
    "addr:housenumber":"18",
    "addr:postcode":"5472 pk",
    "iso:country":"NL",
    "sg:address":"J Dobbelsteenstr 18",
    "sg:city":"Loosbroek",
    "sg:orig_category":"Onderhoudswerken",
    "sg:phone":"+31 413 229 831",
    "sg:postcode":"5472 PK",
    "sg:province":"Noord-Brabant",
    "wof:name":"Bernhezer",
    "wof:placetype":"venue"
},
  "geometry": {"coordinates":[5.505653,51.678429],"type":"Point"}
}