{
  "type": "Feature",
  "properties": {
    "iso:country":"NL",
    "sg:address":"Warmoesstr 13-13A",
    "sg:city":"Groningen",
    "sg:orig_category":"Loodgieters",
    "sg:phone":"+31 50 313 7914",
    "sg:postcode":"9724 JH",
    "sg:province":"Groningen",
    "wof:name":"Sienot, Loodgietersbedrijf",
    "wof:placetype":"venue"
},
  "geometry": {"coordinates":[6.576569,53.211132],"type":"Point"}
}