{
  "type": "Feature",
  "properties": {
    "iso:country":"NL",
    "sg:address":"Kapitein Grantstraat 19",
    "sg:city":"Tilburg",
    "sg:orig_category":"Loodgieterswerk, Verwarming And Sanitaire Installaties",
    "sg:phone":"+31 13 542 4529",
    "sg:postcode":"5015 BA",
    "sg:province":"North Brabant",
    "wof:name":"Feenstra Tilburg Regio Zuid",
    "wof:placetype":"venue"
},
  "geometry": {"coordinates":[5.114583,51.566895],"type":"Point"}
}