{
  "type": "Feature",
  "properties": {
    "addr:full":"Boerenkamplaan 34 Someren North Brabant 5712 AE",
    "addr:housenumber":"34",
    "addr:postcode":"5712 ae",
    "addr:street":"Boerenkamplaan",
    "iso:country":"NL",
    "sg:address":"Boerenkamplaan 34",
    "sg:city":"Someren",
    "sg:orig_category":"Pluimveehouderijen",
    "sg:phone":"+31 493 493 381",
    "sg:postcode":"5712 AE",
    "sg:province":"North Brabant",
    "wof:name":"P.J. Hurkmans-Van Oosterhout",
    "wof:placetype":"venue"
},
  "geometry": {"coordinates":[5.724424,51.374001],"type":"Point"}
}