{
  "type": "Feature",
  "properties": {
    "iso:country":"NL",
    "sg:address":"Steenweg 16",
    "sg:city":"Sittard",
    "sg:orig_category":"Meubelzaken, Woning- And Keukeninrichting",
    "sg:phone":"+31 46 452 3779",
    "sg:postcode":"6131 BE",
    "sg:province":"Limburg",
    "wof:name":"Knibbeler Meubel Bv",
    "wof:placetype":"venue"
},
  "geometry": {"coordinates":[5.863058,50.999565],"type":"Point"}
}