{
  "type": "Feature",
  "properties": {
    "addr:full":"A V Scharnln 170 Maastricht Limburg 6224 JX",
    "addr:housenumber":"170",
    "addr:postcode":"6224 jx",
    "addr:street":"A;Scharnln",
    "iso:country":"NL",
    "sg:address":"A V Scharnln 170",
    "sg:city":"Maastricht",
    "sg:orig_category":"Verenigingen En Stichtingen",
    "sg:phone":"+31 43 352 3900",
    "sg:postcode":"6224 JX",
    "sg:province":"Limburg",
    "wof:name":"Phoenix, Sticht",
    "wof:placetype":"venue"
},
  "geometry": {"coordinates":[5.71167,50.850868],"type":"Point"}
}