{
  "type": "Feature",
  "properties": {
    "iso:country":"NL",
    "sg:address":"De Hondert Margen 23",
    "sg:city":"De Lier",
    "sg:orig_category":"Pompen",
    "sg:phone":"+31 174 518 410",
    "sg:postcode":"2678 AC",
    "sg:province":"Zuid-Holland",
    "sg:website":"http://www.johnson-pump.com",
    "wof:name":"Johnson Pump Bv",
    "wof:placetype":"venue"
},
  "geometry": {"coordinates":[4.236393,51.974445],"type":"Point"}
}