{
  "type": "Feature",
  "properties": {
    "addr:full":"Hummelosewg 74 Zelhem Gelderland 7021 KM",
    "addr:housenumber":"74",
    "addr:postcode":"7021",
    "addr:street":"Hummelosewg;Gelderland;Km",
    "iso:country":"NL",
    "sg:address":"Hummelosewg 74",
    "sg:city":"Zelhem",
    "sg:orig_category":"Hondenscholen",
    "sg:phone":"+31 314 362 813",
    "sg:postcode":"7021 KM",
    "sg:province":"Gelderland",
    "sg:website":"http://www.hondenschool.nl",
    "wof:name":"Hondenleven Hondenschool",
    "wof:placetype":"venue"
},
  "geometry": {"coordinates":[6.298948,52.002541],"type":"Point"}
}