{
  "type": "Feature",
  "properties": {
    "addr:full":"Nijverheidsstraat 1 Haaksbergen Overijssel 7482 GZ",
    "addr:housenumber":"1",
    "addr:postcode":"7482 gz",
    "addr:street":"Nijverheidsstraat",
    "iso:country":"NL",
    "sg:address":"Nijverheidsstraat 1",
    "sg:city":"Haaksbergen",
    "sg:orig_category":"Hout Gh",
    "sg:phone":"+31 53 573 5735",
    "sg:postcode":"7482 GZ",
    "sg:province":"Overijssel",
    "wof:name":"Reinaerdt Deuren Bv",
    "wof:placetype":"venue"
},
  "geometry": {"coordinates":[6.720511,52.154358],"type":"Point"}
}