{
  "type": "Feature",
  "properties": {
    "addr:full":"Vleeshouwersdreef 15 Maastricht Limburg 6216 PT",
    "addr:housenumber":"15",
    "addr:postcode":"6216 pt",
    "addr:street":"Vleeshouwersdreef",
    "iso:country":"NL",
    "sg:address":"Vleeshouwersdreef 15",
    "sg:city":"Maastricht",
    "sg:orig_category":"Schilders",
    "sg:phone":"+31 43 343 2442",
    "sg:postcode":"6216 PT",
    "sg:province":"Limburg",
    "wof:name":"Candel, M J C",
    "wof:placetype":"venue"
},
  "geometry": {"coordinates":[5.664366,50.84462],"type":"Point"}
}