{
  "type": "Feature",
  "properties": {
    "addr:full":"Fromawg 2 Wirdum Gn Groningen 9917 PK",
    "addr:housenumber":"2",
    "addr:postcode":"gn;9917 pk",
    "addr:street":"Fromawg",
    "iso:country":"NL",
    "sg:address":"Fromawg 2",
    "sg:city":"Wirdum Gn",
    "sg:orig_category":"Verenigingsgebouwen",
    "sg:phone":"+31 596 571 916",
    "sg:postcode":"9917 PK",
    "sg:province":"Groningen",
    "wof:name":"Dorpshuis",
    "wof:placetype":"venue"
},
  "geometry": {"coordinates":[6.785348,53.323452],"type":"Point"}
}