{
  "type": "Feature",
  "properties": {
    "addr:full":"A Tasmanstr 41 Enschede Overijssel 7534 BS",
    "addr:housenumber":"41",
    "addr:postcode":"7534 bs",
    "iso:country":"NL",
    "sg:address":"A Tasmanstr 41",
    "sg:city":"Enschede",
    "sg:orig_category":"Schilders",
    "sg:phone":"+31 53 461 5280",
    "sg:postcode":"7534 BS",
    "sg:province":"Overijssel",
    "wof:name":"Middelhoff",
    "wof:placetype":"venue"
},
  "geometry": {"coordinates":[6.96773,52.214115],"type":"Point"}
}