{
  "type": "Feature",
  "properties": {
    "iso:country":"NL",
    "sg:address":"Keilewg 26",
    "sg:city":"Rotterdam",
    "sg:orig_category":"Beeldende Kunstenaars",
    "sg:phone":"+31 10 425 9321",
    "sg:postcode":"3029 BT",
    "sg:province":"Zuid-Holland",
    "wof:name":"Mooij, O",
    "wof:placetype":"venue"
},
  "geometry": {"coordinates":[4.430211,51.908878],"type":"Point"}
}