{
  "type": "Feature",
  "properties": {
    "addr:full":"Wolga 16 S Gravenhage 2491 BJ",
    "addr:housenumber":"16",
    "addr:postcode":"2491 bj",
    "addr:street":"Wolga;S Gravenhage",
    "iso:country":"NL",
    "sg:address":"Wolga 16",
    "sg:city":"S Gravenhage",
    "sg:orig_category":"Meubelen",
    "sg:phone":"+31 70 301 4040",
    "sg:postcode":"2491 BJ",
    "sg:website":"http://www.luckyleder.nl",
    "wof:name":"Lucky Leder",
    "wof:placetype":"venue"
},
  "geometry": {"coordinates":[4.38382,52.065289],"type":"Point"}
}