{
  "type": "Feature",
  "properties": {
    "addr:full":"Rijksweg Centrum 65 Geleen Limburg 6161 EC",
    "addr:housenumber":"65",
    "addr:postcode":"6161 ec",
    "addr:street":"Rijksweg Centrum",
    "iso:country":"NL",
    "sg:address":"Rijksweg Centrum 65",
    "sg:city":"Geleen",
    "sg:orig_category":"Werving And Selectie Van Tijdelijk Personeel And Uitzendkantoren",
    "sg:phone":"+31 46 474 0980",
    "sg:postcode":"6161 EC",
    "sg:province":"Limburg",
    "wof:name":"Flair Bv",
    "wof:placetype":"venue"
},
  "geometry": {"coordinates":[5.8294968605,50.9684753418],"type":"Point"}
}