{
  "type": "Feature",
  "properties": {
    "addr:full":"Hoogzwanenstr 134 Maastricht Limburg 6211 BZ",
    "addr:housenumber":"134",
    "addr:postcode":"6211 bz",
    "iso:country":"NL",
    "sg:address":"Hoogzwanenstr 134",
    "sg:city":"Maastricht",
    "sg:orig_category":"Verzekeringen - Verzekeringskantoren",
    "sg:phone":"+31 43 364 0339",
    "sg:postcode":"6211 BZ",
    "sg:province":"Limburg",
    "wof:name":"Boves, J J L",
    "wof:placetype":"venue"
},
  "geometry": {"coordinates":[5.690995,50.853371],"type":"Point"}
}