{
  "type": "Feature",
  "properties": {
    "iso:country":"NL",
    "sg:address":"Wattstr 56",
    "sg:city":"Sassenheim",
    "sg:orig_category":"Bloemen En Planten",
    "sg:phone":"+31 252 213 668",
    "sg:postcode":"2171 TR",
    "sg:province":"Zuid-Holland",
    "sg:website":"http://www.meifleur.nl",
    "wof:name":"Meifleur Zijdenbloemsierkunst",
    "wof:placetype":"venue"
},
  "geometry": {"coordinates":[4.495096,52.21056],"type":"Point"}
}