{
  "type": "Feature",
  "properties": {
    "iso:country":"NL",
    "sg:address":"De Sillestraat 181",
    "sg:city":"'S Gravenhage",
    "sg:orig_category":"Glaszetten",
    "sg:phone":"+31 70 347 3349",
    "sg:postcode":"2593 TX",
    "sg:province":"South Holland",
    "wof:name":"Glashandel Van Dijk",
    "wof:placetype":"venue"
},
  "geometry": {"coordinates":[4.344764,52.086559],"type":"Point"}
}