{
  "type": "Feature",
  "properties": {
    "iso:country":"NL",
    "sg:address":"Hoofdweg 3",
    "sg:city":"Boerakker",
    "sg:orig_category":"Kappers",
    "sg:phone":"+31 594 549 902",
    "sg:postcode":"9361 PA",
    "sg:province":"Groningen",
    "wof:name":"Haarstudio Boerakker",
    "wof:placetype":"venue"
},
  "geometry": {"coordinates":[6.330411911,53.1808395386],"type":"Point"}
}