{
  "type": "Feature",
  "properties": {
    "iso:country":"NL",
    "sg:address":"Raalterwg 36",
    "sg:city":"Holten",
    "sg:orig_category":"Zuivel - Groothandel",
    "sg:phone":"+31 548 367 271",
    "sg:postcode":"7451 KX",
    "sg:province":"NL.08",
    "sg:website":"http://www.triscom.nl",
    "wof:name":"Triscom Bv",
    "wof:placetype":"venue"
},
  "geometry": {"coordinates":[6.397871,52.295361],"type":"Point"}
}