{
  "type": "Feature",
  "properties": {
    "addr:full":"Industrieweg 8B Heusden Gem Heusden Noord-Brabant 5256 PN",
    "addr:housenumber":"8b",
    "addr:postcode":"5256 pn",
    "addr:street":"Industrieweg",
    "iso:country":"NL",
    "sg:address":"Industrieweg 8B",
    "sg:city":"Heusden Gem Heusden",
    "sg:orig_category":"Jachthavens - Jachtwerven",
    "sg:phone":"+31 416 660 206",
    "sg:postcode":"5256 PN",
    "sg:province":"Noord-Brabant",
    "sg:website":"http://www.doomernik.nl",
    "wof:name":"Doomernik Bv",
    "wof:placetype":"venue"
},
  "geometry": {"coordinates":[5.12532,51.733559],"type":"Point"}
}