{
  "type": "Feature",
  "properties": {
    "addr:full":"De Herkulis 12 Wormer North Holland 1531 PR",
    "addr:housenumber":"12",
    "addr:postcode":"1531 pr",
    "addr:street":"De Herkulis",
    "iso:country":"NL",
    "sg:address":"De Herkulis 12",
    "sg:city":"Wormer",
    "sg:orig_category":"Kantoor- En Interieurbeplanting",
    "sg:phone":"+31 75 642 5450",
    "sg:postcode":"1531 PR",
    "sg:province":"North Holland",
    "wof:name":"Green Design",
    "wof:placetype":"venue"
},
  "geometry": {"coordinates":[4.8112850189,52.4980545044],"type":"Point"}
}