{
  "type": "Feature",
  "properties": {
    "iso:country":"NL",
    "sg:address":"Handelswg 21",
    "sg:city":"Bladel",
    "sg:orig_category":"Wegenbouw",
    "sg:phone":"+31 497 386 890",
    "sg:postcode":"5531 AE",
    "sg:province":"Noord-Brabant",
    "sg:website":"http://www.roosgroep.nl",
    "wof:name":"Roos Bv, P E",
    "wof:placetype":"venue"
},
  "geometry": {"coordinates":[5.198843956,51.3569450378],"type":"Point"}
}