{
  "type": "Feature",
  "properties": {
    "addr:full":"Lutmastraat 29 Amsterdam Noord-Holland 1072 JM",
    "addr:housenumber":"29",
    "addr:postcode":"1072 jm",
    "addr:street":"Lutmastraat",
    "iso:country":"NL",
    "sg:address":"Lutmastraat 29",
    "sg:city":"Amsterdam",
    "sg:orig_category":"Fotostudio'S And Fotografen",
    "sg:phone":"+31 20 679 5772",
    "sg:postcode":"1072 JM",
    "sg:province":"Noord-Holland",
    "wof:name":"Peter Van Breugel",
    "wof:placetype":"venue"
},
  "geometry": {"coordinates":[4.89338,52.350666],"type":"Point"}
}