{
  "type": "Feature",
  "properties": {
    "addr:full":"Berg En Dalseweg 63 Nijmegen Gelderland 6522 BB",
    "addr:housenumber":"63",
    "addr:postcode":"6522 bb",
    "addr:street":"Berg En Dalseweg;Gelderland",
    "iso:country":"NL",
    "sg:address":"Berg En Dalseweg 63",
    "sg:city":"Nijmegen",
    "sg:orig_category":"Werving And Selectie Van Vast Personeel",
    "sg:phone":"+31 24 322 2551",
    "sg:postcode":"6522 BB",
    "sg:province":"Gelderland",
    "wof:name":"Bhp Groep Loopbaanadvisering",
    "wof:placetype":"venue"
},
  "geometry": {"coordinates":[5.8768458366,51.8412399292],"type":"Point"}
}