{
  "type": "Feature",
  "properties": {
    "addr:full":"Vd Madewg 41 Amsterdam Noord-Holland 1099 BS",
    "addr:housenumber":"41;1099",
    "addr:postcode":"bs",
    "iso:country":"NL",
    "sg:address":"Vd Madewg 41",
    "sg:city":"Amsterdam",
    "sg:orig_category":"Projectinrichting",
    "sg:phone":"+31 20 665 0160",
    "sg:postcode":"1099 BS",
    "sg:province":"Noord-Holland",
    "sg:website":"http://www.vroomendreesmann.nl",
    "wof:name":"V & D",
    "wof:placetype":"venue"
},
  "geometry": {"coordinates":[-80.97189299999999,40.493458],"type":"Point"}
}