{
  "type": "Feature",
  "properties": {
    "addr:full":"1 Februariwg 7 Heyningen North Brabant 4794 SM",
    "addr:housenumber":"1;7",
    "addr:postcode":"4794 sm",
    "addr:street":"Februariwg",
    "iso:country":"NL",
    "sg:address":"1 Februariwg 7",
    "sg:city":"Heyningen",
    "sg:orig_category":"Metaalbewerking",
    "sg:phone":"+31 167 524 348",
    "sg:postcode":"4794 SM",
    "sg:province":"North Brabant",
    "wof:name":"Land, Jaap Van Der",
    "wof:placetype":"venue"
},
  "geometry": {"coordinates":[4.378353,51.65868],"type":"Point"}
}