{
  "type": "Feature",
  "properties": {
    "addr:full":"Breestraat 58 Leiden Zuid-Holland 2311 CS",
    "addr:housenumber":"58",
    "addr:postcode":"2311 cs",
    "addr:street":"Breestraat",
    "iso:country":"NL",
    "sg:address":"Breestraat 58",
    "sg:city":"Leiden",
    "sg:orig_category":"Medische Apparatuur And Prothesen Fab",
    "sg:phone":"+31 71 514 2785",
    "sg:postcode":"2311 CS",
    "sg:province":"Zuid-Holland",
    "wof:name":"Beter Horen",
    "wof:placetype":"venue"
},
  "geometry": {"coordinates":[4.488694,52.159538],"type":"Point"}
}