{
  "type": "Feature",
  "properties": {
    "addr:full":"H Figeewg 13/B Haarlem North Holland 2031 BJ",
    "addr:housenumber":"13 / b",
    "addr:postcode":"2031 bj",
    "iso:country":"NL",
    "sg:address":"H Figeewg 13/B",
    "sg:city":"Haarlem",
    "sg:orig_category":"Metaalbewerking",
    "sg:phone":"+31 23 532 6870",
    "sg:postcode":"2031 BJ",
    "sg:province":"North Holland",
    "wof:name":"D-Metaal",
    "wof:placetype":"venue"
},
  "geometry": {"coordinates":[4.653937,52.390556],"type":"Point"}
}