{
  "type": "Feature",
  "properties": {
    "addr:full":"Huygensweg 10 Veghel Noord-Brabant 5466 AN",
    "addr:housenumber":"10",
    "addr:postcode":"5466 an",
    "addr:street":"Huygensweg",
    "iso:country":"NL",
    "sg:address":"Huygensweg 10",
    "sg:city":"Veghel",
    "sg:orig_category":"Goederenvervoer Over De Weg",
    "sg:phone":"+31 413 347 911",
    "sg:postcode":"5466 AN",
    "sg:province":"Noord-Brabant",
    "wof:name":"Msas Hitec Logistics Bv",
    "wof:placetype":"venue"
},
  "geometry": {"coordinates":[5.51254,51.614113],"type":"Point"}
}