{
  "type": "Feature",
  "properties": {
    "addr:full":"Boerenhoek 18 Angeren Gelderland 6687 LT",
    "addr:housenumber":"18",
    "addr:postcode":"6687 lt",
    "addr:street":"Boerenhoek;Gelderland",
    "iso:country":"NL",
    "sg:address":"Boerenhoek 18",
    "sg:city":"Angeren",
    "sg:orig_category":"Goederenvervoer Over De Weg",
    "sg:phone":"+31 481 424 246",
    "sg:postcode":"6687 LT",
    "sg:province":"Gelderland",
    "wof:name":"Walravens Vrachttax",
    "wof:placetype":"venue"
},
  "geometry": {"coordinates":[5.975475,51.906536],"type":"Point"}
}