{
  "type": "Feature",
  "properties": {
    "addr:full":"Strawinskyln 3051 Amsterdam Noord-Holland 1077 ZX",
    "addr:housenumber":"3051",
    "addr:postcode":"1077 zx",
    "iso:country":"NL",
    "sg:address":"Strawinskyln 3051",
    "sg:city":"Amsterdam",
    "sg:orig_category":"Advocaten En Advocatenkantoren",
    "sg:phone":"+31 20 799 6200",
    "sg:postcode":"1077 ZX",
    "sg:province":"Noord-Holland",
    "sg:website":"http://www.linklaters.com",
    "wof:name":"Linklaters",
    "wof:placetype":"venue"
},
  "geometry": {"coordinates":[4.869424,52.340435],"type":"Point"}
}