{
  "type": "Feature",
  "properties": {
    "addr:full":"Sandtln 62 Katwyk Zh South Holland 2223 GG",
    "addr:housenumber":"62;zh",
    "addr:postcode":"2223 gg",
    "addr:street":"Sandtln",
    "iso:country":"NL",
    "sg:address":"Sandtln 62",
    "sg:city":"Katwyk Zh",
    "sg:orig_category":"Metaalbewerking",
    "sg:phone":"+31 71 401 3496",
    "sg:postcode":"2223 GG",
    "sg:province":"South Holland",
    "wof:name":"Duijn, D Van",
    "wof:placetype":"venue"
},
  "geometry": {"coordinates":[4.42057,52.187599],"type":"Point"}
}