{
  "type": "Feature",
  "properties": {
    "addr:full":"Doktersln 31 Heiloo North Holland 1851 BS",
    "addr:housenumber":"31",
    "addr:postcode":"1851 bs",
    "addr:street":"Doktersln",
    "iso:country":"NL",
    "sg:address":"Doktersln 31",
    "sg:city":"Heiloo",
    "sg:orig_category":"Adviesbureaus Bedrijfsorganisatie",
    "sg:phone":"+31 72 532 2067",
    "sg:postcode":"1851 BS",
    "sg:province":"North Holland",
    "sg:website":"http://www.kuinadvies.nl",
    "wof:name":"Kuin Heiloo",
    "wof:placetype":"venue"
},
  "geometry": {"coordinates":[4.716621,52.602814],"type":"Point"}
}