{
  "type": "Feature",
  "properties": {
    "addr:full":"Pypbloem 1 Rotterdam South Holland 3068 AM",
    "addr:housenumber":"1",
    "addr:postcode":"3068",
    "addr:street":"Pypbloem",
    "iso:country":"NL",
    "sg:address":"Pypbloem 1",
    "sg:city":"Rotterdam",
    "sg:orig_category":"Bloemen En Planten - Groothandel",
    "sg:phone":"+31 10 420 6879",
    "sg:postcode":"3068 AM",
    "sg:province":"South Holland",
    "wof:name":"Houberg Vof, H",
    "wof:placetype":"venue"
},
  "geometry": {"coordinates":[4.55679,51.959869],"type":"Point"}
}