{
  "type": "Feature",
  "properties": {
    "addr:full":"Lijsterbeshof 30 Papendrecht Zuid-Holland 3355 CD",
    "addr:housenumber":"30",
    "addr:postcode":"3355 cd",
    "addr:street":"Lijsterbeshof",
    "iso:country":"NL",
    "sg:address":"Lijsterbeshof 30",
    "sg:city":"Papendrecht",
    "sg:classifiers":[
        {
            "category":"Personal",
            "subcategory":"Nail Salon",
            "type":"Services"
        }
    ],
    "sg:phone":"+31 78 615 8784",
    "sg:postcode":"3355 CD",
    "sg:province":"Zuid-Holland",
    "sg:tags":[
        "pedicure"
    ],
    "wof:name":"Kornet-Slob, A M",
    "wof:placetype":"venue"
},
  "geometry": {"coordinates":[4.698666,51.837528],"type":"Point"}
}