{
  "type": "Feature",
  "properties": {
    "addr:full":"Barten 70 Heerenveen Provincie Friesland 8447 BR",
    "addr:housenumber":"70",
    "addr:postcode":"8447 br",
    "addr:street":"Barten;Provincie Friesland",
    "iso:country":"NL",
    "sg:address":"Barten 70",
    "sg:city":"Heerenveen",
    "sg:orig_category":"Grafologen, Handlezers And Helderzienden",
    "sg:phone":"+31 513 620 333",
    "sg:postcode":"8447 BR",
    "sg:province":"Provincie Friesland",
    "wof:name":"Ruud Hollander",
    "wof:placetype":"venue"
},
  "geometry": {"coordinates":[5.907908,52.961231],"type":"Point"}
}