{
  "type": "Feature",
  "properties": {
    "iso:country":"NL",
    "sg:address":"Berlagestr 1",
    "sg:city":"Rotterdam",
    "sg:orig_category":"Administratie- En Boekhoudkantoren",
    "sg:phone":"+31 10 456 1259",
    "sg:postcode":"3067 CB",
    "sg:province":"Zuid-Holland",
    "wof:name":"Muilwijk & Partn, J",
    "wof:placetype":"venue"
},
  "geometry": {"coordinates":[4.548572,51.945564],"type":"Point"}
}