{
  "type": "Feature",
  "properties": {
    "addr:full":"Kerkstraat 42 Hoogezand Groningen 9603 AL",
    "addr:housenumber":"42",
    "addr:postcode":"9603 al",
    "addr:street":"Kerkstraat",
    "iso:country":"NL",
    "sg:address":"Kerkstraat 42",
    "sg:city":"Hoogezand",
    "sg:orig_category":"Benzinestations And Brandstoffen",
    "sg:phone":"+31 598 390 626",
    "sg:postcode":"9603 AL",
    "sg:province":"Groningen",
    "wof:name":"Bim Tankstation Zeller",
    "wof:placetype":"venue"
},
  "geometry": {"coordinates":[6.75605,53.160332],"type":"Point"}
}