{
  "type": "Feature",
  "properties": {
    "addr:full":"St Maartenshof 4 Puiflyk Gelderland 6655 AZ",
    "addr:housenumber":"4",
    "addr:postcode":"6655",
    "addr:street":"St Maartenshof;Gelderland",
    "iso:country":"NL",
    "sg:address":"St Maartenshof 4",
    "sg:city":"Puiflyk",
    "sg:orig_category":"Fotoreportages",
    "sg:phone":"+31 6 50628532",
    "sg:postcode":"6655 AZ",
    "sg:province":"Gelderland",
    "wof:name":"Neok",
    "wof:placetype":"venue"
},
  "geometry": {"coordinates":[5.589888,51.878838],"type":"Point"}
}