{
  "type": "Feature",
  "properties": {
    "addr:full":"Adriaen Van Ostadelaan 33 Utrecht Utrecht 3583 AA",
    "addr:housenumber":"33",
    "addr:postcode":"3583 aa",
    "addr:street":"Adriaen Van Ostadelaan",
    "iso:country":"NL",
    "sg:address":"Adriaen Van Ostadelaan 33",
    "sg:city":"Utrecht",
    "sg:orig_category":"Apothekers",
    "sg:phone":"+31 30 251 2421",
    "sg:postcode":"3583 AA",
    "sg:province":"Utrecht",
    "wof:name":"Apotheek Van Keule",
    "wof:placetype":"venue"
},
  "geometry": {"coordinates":[5.139451,52.083427],"type":"Point"}
}