{
  "type": "Feature",
  "properties": {
    "iso:country":"NL",
    "sg:address":"Groen Van Prinstererstr 9",
    "sg:city":"Winterswijk",
    "sg:orig_category":"Metaalbekleding And -Behandeling",
    "sg:phone":"+31 543 520 813",
    "sg:postcode":"7103 GK",
    "sg:province":"Gelderland",
    "wof:name":"Technolas",
    "wof:placetype":"venue"
},
  "geometry": {"coordinates":[6.720341,51.982178],"type":"Point"}
}