{
  "type": "Feature",
  "properties": {
    "addr:full":"Amperestraat 22A Zwolle NL.08 8013 PV",
    "addr:housenumber":"22a",
    "addr:postcode":"8013 pv",
    "addr:street":"Amperestraat",
    "iso:country":"NL",
    "sg:address":"Amperestraat 22A",
    "sg:city":"Zwolle",
    "sg:orig_category":"Verpakkingsbedrijven",
    "sg:phone":"+31 38 465 5133",
    "sg:postcode":"8013 PV",
    "sg:province":"NL.08",
    "wof:name":"Klepke Loonverpakkingen",
    "wof:placetype":"venue"
},
  "geometry": {"coordinates":[6.128539,52.492996],"type":"Point"}
}