{
  "type": "Feature",
  "properties": {
    "iso:country":"NL",
    "sg:address":"Willibrordusstr 35",
    "sg:city":"Amersfoort",
    "sg:orig_category":"Psychosociale Therapeuten",
    "sg:phone":"+31 33 461 7921",
    "sg:postcode":"3812 TJ",
    "sg:province":"Utrecht",
    "wof:name":"Stimulans",
    "wof:placetype":"venue"
},
  "geometry": {"coordinates":[5.370654,52.15873],"type":"Point"}
}