{
  "type": "Feature",
  "properties": {
    "addr:full":"Kerkwg 100 Lekkerkerk Zuid-Holland 2941 BP",
    "addr:housenumber":"100",
    "addr:postcode":"2941 bp",
    "iso:country":"NL",
    "sg:address":"Kerkwg 100",
    "sg:city":"Lekkerkerk",
    "sg:orig_category":"Postkantoren",
    "sg:phone":"+31 180 661 285",
    "sg:postcode":"2941 BP",
    "sg:province":"Zuid-Holland",
    "sg:website":"http://www.postkantoor.nl",
    "wof:name":"Postkantoor",
    "wof:placetype":"venue"
},
  "geometry": {"coordinates":[4.683921,51.900284],"type":"Point"}
}