{
  "type": "Feature",
  "properties": {
    "addr:full":"Ijdoornlaan 34 Amsterdam North Holland 1024 KV",
    "addr:housenumber":"34",
    "addr:postcode":"1024 kv",
    "addr:street":"Ijdoornlaan",
    "iso:country":"NL",
    "sg:address":"Ijdoornlaan 34",
    "sg:city":"Amsterdam",
    "sg:orig_category":"Woningbouwverenigingen",
    "sg:phone":"+31 20 435 3444",
    "sg:postcode":"1024 KV",
    "sg:province":"North Holland",
    "wof:name":"Woningstichting Patrimonium",
    "wof:placetype":"venue"
},
  "geometry": {"coordinates":[4.9573488235,52.3917274475],"type":"Point"}
}