{
  "type": "Feature",
  "properties": {
    "addr:full":"Bossenburg 30 Vlissingen Zeeland 4385 EA",
    "addr:housenumber":"30",
    "addr:postcode":"4385 ea",
    "addr:street":"Bossenburg",
    "iso:country":"NL",
    "sg:address":"Bossenburg 30",
    "sg:city":"Vlissingen",
    "sg:orig_category":"Koeriersdiensten",
    "sg:phone":"+31 118 473 678",
    "sg:postcode":"4385 EA",
    "sg:province":"Zeeland",
    "wof:name":"Eurocourier, De",
    "wof:placetype":"venue"
},
  "geometry": {"coordinates":[3.576144,51.462547],"type":"Point"}
}