{
  "type": "Feature",
  "properties": {
    "addr:full":"Stadhoudersweg 181 Rotterdam Zuid-Holland 3039 MC",
    "addr:housenumber":"181",
    "addr:postcode":"3039 mc",
    "addr:street":"Stadhoudersweg",
    "iso:country":"NL",
    "sg:address":"Stadhoudersweg 181",
    "sg:city":"Rotterdam",
    "sg:orig_category":"Sportcentra",
    "sg:phone":"+31 10 465 4977",
    "sg:postcode":"3039 MC",
    "sg:province":"Zuid-Holland",
    "wof:name":"Tenniscentrum Blijdorp Bv",
    "wof:placetype":"venue"
},
  "geometry": {"coordinates":[4.450272,51.929138],"type":"Point"}
}