{
  "type": "Feature",
  "properties": {
    "addr:full":"Gasthuisstraat 7A 'S Hertogenbosch Noord-Brabant 5211 NP",
    "addr:housenumber":"7a ' s",
    "addr:postcode":"5211 np",
    "addr:street":"Gasthuisstraat",
    "iso:country":"NL",
    "sg:address":"Gasthuisstraat 7A",
    "sg:city":"'S Hertogenbosch",
    "sg:orig_category":"Binnenhuisarchitecten",
    "sg:phone":"+31 73 691 0064",
    "sg:postcode":"5211 NP",
    "sg:province":"Noord-Brabant",
    "wof:name":"Anke Vroomen Interieur Architecte",
    "wof:placetype":"venue"
},
  "geometry": {"coordinates":[5.305831,51.689335],"type":"Point"}
}