{
  "type": "Feature",
  "properties": {
    "addr:full":"Rembrandtkade 36 Utrecht Utrecht 3583 TN",
    "addr:housenumber":"36",
    "addr:postcode":"3583",
    "addr:street":"Rembrandtkade",
    "iso:country":"NL",
    "sg:address":"Rembrandtkade 36",
    "sg:city":"Utrecht",
    "sg:orig_category":"Advocaten And Juridische Adviseurs",
    "sg:phone":"+31 30 251 1224",
    "sg:postcode":"3583 TN",
    "sg:province":"Utrecht",
    "wof:name":"Advokatenkantoor Hummels Van De Brug De Jong",
    "wof:placetype":"venue"
},
  "geometry": {"coordinates":[5.142993,52.086277],"type":"Point"}
}