{
  "type": "Feature",
  "properties": {
    "addr:full":"Overtoom 174 Amsterdam Noord-Holland 1054 HR",
    "addr:housenumber":"174",
    "addr:postcode":"1054 hr",
    "addr:street":"Overtoom",
    "iso:country":"NL",
    "sg:address":"Overtoom 174",
    "sg:city":"Amsterdam",
    "sg:orig_category":"Artsen - Huisartsen",
    "sg:phone":"+31 20 618 2056",
    "sg:postcode":"1054 HR",
    "sg:province":"Noord-Holland",
    "wof:name":"Speelman, W P",
    "wof:placetype":"venue"
},
  "geometry": {"coordinates":[4.872556,52.362259],"type":"Point"}
}