{
  "type": "Feature",
  "properties": {
    "iso:country":"NL",
    "sg:address":"Akerstraat 88",
    "sg:city":"Kerkrade",
    "sg:orig_category":"Verlichting And Huishoudartikelen",
    "sg:phone":"+31 45 549 0181",
    "sg:postcode":"6466 HL",
    "sg:province":"Limburg",
    "wof:name":"M & M Glas- En Spiegelboutique Vof",
    "wof:placetype":"venue"
},
  "geometry": {"coordinates":[6.025452,50.858654],"type":"Point"}
}