{
  "type": "Feature",
  "properties": {
    "addr:full":"Singel 457/B6 Amsterdam Noord-Holland 1012 WP",
    "addr:housenumber":"457 / b6",
    "addr:postcode":"1012 wp",
    "addr:street":"Singel",
    "iso:country":"NL",
    "sg:address":"Singel 457/B6",
    "sg:city":"Amsterdam",
    "sg:classifiers":[
        {
            "category":"Shopping",
            "subcategory":"Gifts & Souvenirs",
            "type":"Retail Goods"
        }
    ],
    "sg:phone":"+31 20 420 4410",
    "sg:postcode":"1012 WP",
    "sg:province":"Noord-Holland",
    "sg:tags":[
        "geschenken"
    ],
    "wof:name":"Mediterranee Cadeau Artikelen",
    "wof:placetype":"venue"
},
  "geometry": {"coordinates":[4.893195,52.373119],"type":"Point"}
}