{
  "type": "Feature",
  "properties": {
    "iso:country":"NL",
    "sg:address":"Stationsstraat 24",
    "sg:city":"Gieten",
    "sg:classifiers":[
        {
            "category":"Communications",
            "subcategory":"Television Station",
            "type":"Services"
        }
    ],
    "sg:phone":"+31 592 264 077",
    "sg:postcode":"9461 GT",
    "sg:province":"Drenthe",
    "sg:tags":[
        "video",
        "audio",
        "verhuur"
    ],
    "wof:name":"Videotheek Gieten",
    "wof:placetype":"venue"
},
  "geometry": {"coordinates":[6.764121,53.002216],"type":"Point"}
}