{
  "type": "Feature",
  "properties": {
    "addr:full":"Ommelanderwyk 249A Veendam Groningen 9644 TH",
    "addr:housenumber":"249a",
    "addr:postcode":"9644 th",
    "iso:country":"NL",
    "sg:address":"Ommelanderwyk 249A",
    "sg:city":"Veendam",
    "sg:orig_category":"Adviesbureaus Bouwkunde",
    "sg:phone":"+31 598 690 470",
    "sg:postcode":"9644 TH",
    "sg:province":"Groningen",
    "wof:name":"Hendriksen Bv",
    "wof:placetype":"venue"
},
  "geometry": {"coordinates":[6.910974,53.085308],"type":"Point"}
}