{
  "type": "Feature",
  "properties": {
    "iso:country":"NL",
    "sg:address":"Telefoonweg 70",
    "sg:city":"Ede Gld",
    "sg:orig_category":"Dierenspeciaalzaken",
    "sg:phone":"+31 318 612 735",
    "sg:postcode":"6713 AL",
    "sg:province":"Gelderland",
    "wof:name":"Dierenspeciaalzaak Jumper",
    "wof:placetype":"venue"
},
  "geometry": {"coordinates":[5.667641,52.044758],"type":"Point"}
}