{
  "type": "Feature",
  "properties": {
    "iso:country":"NL",
    "sg:address":"Rijksstraatweg 97",
    "sg:city":"Baambrugge",
    "sg:classifiers":[
        {
            "category":"Shopping",
            "subcategory":"Clothing, Apparel, & Fashions",
            "type":"Retail Goods"
        }
    ],
    "sg:phone":"+31 294 295 088",
    "sg:postcode":"1396 JG",
    "sg:province":"Utrecht",
    "sg:tags":[
        "ondergoed",
        "lingerie"
    ],
    "wof:name":"Stayput Benelux",
    "wof:placetype":"venue"
},
  "geometry": {"coordinates":[4.996032,52.241791],"type":"Point"}
}