{
  "type": "Feature",
  "properties": {
    "addr:full":"Grotestr 8A Markelo Overijssel 7475 AX",
    "addr:housenumber":"8a",
    "addr:postcode":"7475 ax",
    "addr:street":"Grotestr",
    "iso:country":"NL",
    "sg:address":"Grotestr 8A",
    "sg:city":"Markelo",
    "sg:orig_category":"Kantoorbenodigdheden",
    "sg:phone":"+31 547 363 363",
    "sg:postcode":"7475 AX",
    "sg:province":"Overijssel",
    "sg:website":"http://www.suppreme.nl",
    "wof:name":"Suppreme",
    "wof:placetype":"venue"
},
  "geometry": {"coordinates":[6.4922790527,52.2360610962],"type":"Point"}
}