{
  "type": "Feature",
  "properties": {
    "addr:full":"Bovenwg 18A Bennekom Gelderland 6721 HW",
    "addr:housenumber":"18a",
    "addr:postcode":"6721 hw",
    "addr:street":"Bovenwg;Gelderland",
    "iso:country":"NL",
    "sg:address":"Bovenwg 18A",
    "sg:city":"Bennekom",
    "sg:orig_category":"Adviesbureaus Land- En Tuinbouw",
    "sg:phone":"+31 318 430 852",
    "sg:postcode":"6721 HW",
    "sg:province":"Gelderland",
    "wof:name":"Schutte Bv",
    "wof:placetype":"venue"
},
  "geometry": {"coordinates":[5.676905,51.99538],"type":"Point"}
}