{
  "type": "Feature",
  "properties": {
    "iso:country":"NL",
    "sg:address":"Bovenwg 18A",
    "sg:city":"Bennekom",
    "sg:orig_category":"Adviesbureaus Land- En Tuinbouw",
    "sg:phone":"+31 318 430 852",
    "sg:postcode":"6721 HW",
    "sg:province":"Gelderland",
    "wof:name":"Schutte Bv",
    "wof:placetype":"venue"
},
  "geometry": {"coordinates":[5.676905,51.99538],"type":"Point"}
}