{
  "type": "Feature",
  "properties": {
    "iso:country":"NL",
    "sg:address":"Dorpsstraat 151",
    "sg:city":"Sint Willebrord",
    "sg:orig_category":"Verzekeringen",
    "sg:phone":"+31 165 382 555",
    "sg:postcode":"4711 EH",
    "sg:province":"Noord-Brabant",
    "wof:name":"Assurantiekantoor A.A. Schijven Bv",
    "wof:placetype":"venue"
},
  "geometry": {"coordinates":[4.590746,51.554611],"type":"Point"}
}