{
  "type": "Feature",
  "properties": {
    "addr:full":"Karthuizerstr 40 Arnhem Gelderland 6824 KC",
    "addr:housenumber":"40",
    "addr:postcode":"6824 kc",
    "addr:street":"Karthuizerstr",
    "iso:country":"NL",
    "sg:address":"Karthuizerstr 40",
    "sg:city":"Arnhem",
    "sg:orig_category":"Vertalers",
    "sg:phone":"+31 26 389 2926",
    "sg:postcode":"6824 KC",
    "sg:province":"Gelderland",
    "wof:name":"Sloten, Van",
    "wof:placetype":"venue"
},
  "geometry": {"coordinates":[5.935127,51.993359],"type":"Point"}
}