{
  "type": "Feature",
  "properties": {
    "addr:full":"Wj V Erpers Roijaardsstr 3 Montfoort Utrecht 3417 WG",
    "addr:housenumber":"3",
    "addr:postcode":"3417 wg",
    "addr:street":"Roijaardsstr",
    "iso:country":"NL",
    "sg:address":"Wj V Erpers Roijaardsstr 3",
    "sg:city":"Montfoort",
    "sg:orig_category":"Bedrijfs- And Managementsconsultants",
    "sg:phone":"+31 348 472 814",
    "sg:postcode":"3417 WG",
    "sg:province":"Utrecht",
    "wof:name":"Bode",
    "wof:placetype":"venue"
},
  "geometry": {"coordinates":[4.946729,52.044067],"type":"Point"}
}