{
  "type": "Feature",
  "properties": {
    "addr:full":"Arnhemsebovenwg 13 Driebergen Rysenb Utrecht 3971 MA",
    "addr:housenumber":"13",
    "addr:postcode":"3971 ma",
    "addr:street":"Arnhemsebovenwg;Rysenb",
    "iso:country":"NL",
    "sg:address":"Arnhemsebovenwg 13",
    "sg:city":"Driebergen Rysenb",
    "sg:orig_category":"Wijnmakers- Benodigdheden En -Bewaarsystemen",
    "sg:phone":"+31 343 512 706",
    "sg:postcode":"3971 MA",
    "sg:province":"Utrecht",
    "sg:website":"http://www.wijnwereld.nl",
    "wof:name":"Bossenbroek",
    "wof:placetype":"venue"
},
  "geometry": {"coordinates":[5.2707371712,52.066860199],"type":"Point"}
}