{
  "type": "Feature",
  "properties": {
    "addr:full":"Gamba 15 Rotterdam Zuid-Holland 3068 HK",
    "addr:housenumber":"15",
    "addr:postcode":"3068 hk",
    "addr:street":"Gamba",
    "iso:country":"NL",
    "sg:address":"Gamba 15",
    "sg:city":"Rotterdam",
    "sg:orig_category":"Goederenvervoer Over De Weg",
    "sg:phone":"+31 10 455 4969",
    "sg:postcode":"3068 HK",
    "sg:province":"Zuid-Holland",
    "wof:name":"R. Sloof Transport",
    "wof:placetype":"venue"
},
  "geometry": {"coordinates":[4.560178,51.963009],"type":"Point"}
}