{
  "type": "Feature",
  "properties": {
    "addr:full":"Het Kleine Loo 390 'S Gravenhage Zuid-Holland 2592 CK",
    "addr:housenumber":"390 '",
    "addr:postcode":"2592 ck",
    "addr:street":"Het Kleine Loo",
    "iso:country":"NL",
    "sg:address":"Het Kleine Loo 390",
    "sg:city":"'S Gravenhage",
    "sg:orig_category":"Banken And Kredietinstellingen",
    "sg:phone":"+31 70 385 5905",
    "sg:postcode":"2592 CK",
    "sg:province":"Zuid-Holland",
    "wof:name":"Abn Amro",
    "wof:placetype":"venue"
},
  "geometry": {"coordinates":[4.358096,52.092079],"type":"Point"}
}