{
  "type": "Feature",
  "properties": {
    "addr:full":"Graswg 53D Amsterdam Noord-Holland 1031 HX",
    "addr:housenumber":"53d",
    "addr:postcode":"1031 hx",
    "addr:street":"Graswg",
    "iso:country":"NL",
    "sg:address":"Graswg 53D",
    "sg:city":"Amsterdam",
    "sg:orig_category":"Fotografie Reclame En Mode",
    "sg:phone":"+31 20 637 3397",
    "sg:postcode":"1031 HX",
    "sg:province":"Noord-Holland",
    "wof:name":"Jong, Danny De",
    "wof:placetype":"venue"
},
  "geometry": {"coordinates":[4.899849,52.3918],"type":"Point"}
}