{
  "type": "Feature",
  "properties": {
    "addr:full":"Munteltuinen 56 Den Bosch Noord-Brabant 5212 PM",
    "addr:housenumber":"56",
    "addr:postcode":"5212 pm",
    "addr:street":"Munteltuinen",
    "iso:country":"NL",
    "sg:address":"Munteltuinen 56",
    "sg:city":"Den Bosch",
    "sg:classifiers":[
        {
            "category":"Retail",
            "subcategory":"Photofinishing",
            "type":"Services"
        }
    ],
    "sg:phone":"+31 73 690 1708",
    "sg:postcode":"5212 PM",
    "sg:province":"Noord-Brabant",
    "sg:tags":[
        "foto",
        "film"
    ],
    "wof:name":"Fotostudio Ton Vd Vorst",
    "wof:placetype":"venue"
},
  "geometry": {"coordinates":[5.30916,51.696529],"type":"Point"}
}