{
  "type": "Feature",
  "properties": {
    "addr:full":"Schoudermantel 56 Bunnik Utrecht 3981 AH",
    "addr:housenumber":"56",
    "addr:postcode":"3981 ah",
    "addr:street":"Schoudermantel",
    "iso:country":"NL",
    "sg:address":"Schoudermantel 56",
    "sg:city":"Bunnik",
    "sg:orig_category":"Loodgieters",
    "sg:phone":"+31 30 657 2051",
    "sg:postcode":"3981 AH",
    "sg:province":"Utrecht",
    "wof:name":"Veltman, W K",
    "wof:placetype":"venue"
},
  "geometry": {"coordinates":[5.217603,52.059093],"type":"Point"}
}