{
  "type": "Feature",
  "properties": {
    "iso:country":"NL",
    "sg:address":"Jan Van Scorelstraat 37",
    "sg:city":"Zaandam",
    "sg:orig_category":"Boekhouders",
    "sg:phone":"+31 75 616 4485",
    "sg:postcode":"1506 KA",
    "sg:province":"Noord-Holland",
    "wof:name":"J.J. V.D. Bos",
    "wof:placetype":"venue"
},
  "geometry": {"coordinates":[4.815434,52.451157],"type":"Point"}
}