{
  "type": "Feature",
  "properties": {
    "addr:full":"Bronbastion 2 Nieuweschans Groningen 9693 TE",
    "addr:housenumber":"2",
    "addr:postcode":"9693 te",
    "addr:street":"Bronbastion",
    "iso:country":"NL",
    "sg:address":"Bronbastion 2",
    "sg:city":"Nieuweschans",
    "sg:orig_category":"Huidtherapeuten",
    "sg:phone":"+31 597 528 566",
    "sg:postcode":"9693 TE",
    "sg:province":"Groningen",
    "wof:name":"Kuurpoli Groningen Nieuweschans",
    "wof:placetype":"venue"
},
  "geometry": {"coordinates":[7.203849,53.177704],"type":"Point"}
}