{
  "type": "Feature",
  "properties": {
    "iso:country":"NL",
    "sg:address":"Kempenaar 0220",
    "sg:city":"Lelystad",
    "sg:orig_category":"Evenementenverzorging",
    "sg:phone":"+31 320 288 382",
    "sg:postcode":"8242 BC",
    "sg:province":"NL.",
    "sg:website":"http://www.agriflevovisit.nl",
    "wof:name":"Agri-Flevo-Visit Bv",
    "wof:placetype":"venue"
},
  "geometry": {"coordinates":[5.457547,52.519459],"type":"Point"}
}