{
  "type": "Feature",
  "properties": {
    "iso:country":"NL",
    "sg:address":"Sonatestr 44A",
    "sg:city":"Enschede",
    "sg:orig_category":"Scholen Voor Basisonderwijs",
    "sg:phone":"+31 53 461 1691",
    "sg:postcode":"7534 XC",
    "sg:province":"Overijssel",
    "wof:name":"Troubadour Rk, De",
    "wof:placetype":"venue"
},
  "geometry": {"coordinates":[6.97277,52.212193],"type":"Point"}
}