{
  "type": "Feature",
  "properties": {
    "addr:full":"Schaesbergerwg 167 Heerlen Limburg 6415 AG",
    "addr:housenumber":"167",
    "addr:postcode":"6415",
    "iso:country":"NL",
    "sg:address":"Schaesbergerwg 167",
    "sg:city":"Heerlen",
    "sg:orig_category":"Zaden",
    "sg:phone":"+31 45 572 8912",
    "sg:postcode":"6415 AG",
    "sg:province":"Limburg",
    "wof:name":"Horizon, De",
    "wof:placetype":"venue"
},
  "geometry": {"coordinates":[5.994674,50.892262],"type":"Point"}
}