{
  "type": "Feature",
  "properties": {
    "addr:full":"Plantage Middenlaan 2 Amsterdam Noord-Holland 1018 DD",
    "addr:housenumber":"2",
    "addr:postcode":"1018 dd",
    "addr:street":"Plantage Middenlaan",
    "iso:country":"NL",
    "sg:address":"Plantage Middenlaan 2",
    "sg:city":"Amsterdam",
    "sg:orig_category":"Boekenuitgeverijen",
    "sg:phone":"+31 20 330 7200",
    "sg:postcode":"1018 DD",
    "sg:province":"Noord-Holland",
    "wof:name":"Bv Uitgeverij Swp",
    "wof:placetype":"venue"
},
  "geometry": {"coordinates":[4.908393,52.36721],"type":"Point"}
}