{
  "type": "Feature",
  "properties": {
    "addr:full":"Molenakkers 30 Annen South Carolina 9468 BM",
    "addr:housenumber":"30",
    "addr:postcode":"9468 bm",
    "addr:street":"Molenakkers",
    "iso:country":"NL",
    "sg:address":"Molenakkers 30",
    "sg:city":"Annen",
    "sg:orig_category":"Peuterspeelzalen",
    "sg:phone":"+31 592 272 313",
    "sg:postcode":"9468 BM",
    "sg:province":"South Carolina",
    "wof:name":"Krummelhoekje, 'T",
    "wof:placetype":"venue"
},
  "geometry": {"coordinates":[-79.253815,33.471233],"type":"Point"}
}