{
  "type": "Feature",
  "properties": {
    "addr:full":"Capelseweg 214 Capelle A/D Ijssel Zuid-Holland 2907 XE",
    "addr:housenumber":"214;a / d",
    "addr:postcode":"2907 xe",
    "addr:street":"Capelseweg",
    "iso:country":"NL",
    "sg:address":"Capelseweg 214",
    "sg:city":"Capelle A/D Ijssel",
    "sg:orig_category":"Binnenhuisarchitecten",
    "sg:phone":"+31 10 227 1499",
    "sg:postcode":"2907 XE",
    "sg:province":"Zuid-Holland",
    "wof:name":"Bandell",
    "wof:placetype":"venue"
},
  "geometry": {"coordinates":[4.573714,51.942982],"type":"Point"}
}