{
  "type": "Feature",
  "properties": {
    "addr:full":"Van Meelstraat 110 Helmond Noord-Brabant 5703 ET",
    "addr:housenumber":"110",
    "addr:postcode":"5703 et",
    "addr:street":"Van Meelstraat",
    "iso:country":"NL",
    "sg:address":"Van Meelstraat 110",
    "sg:city":"Helmond",
    "sg:classifiers":[
        {
            "category":"Professional",
            "subcategory":"Accounting & Tax Preparation",
            "type":"Services"
        }
    ],
    "sg:phone":"+31 492 525 567",
    "sg:postcode":"5703 ET",
    "sg:province":"Noord-Brabant",
    "sg:tags":[
        "accountant"
    ],
    "wof:name":"Accountantskantoor A.H.L. Aben",
    "wof:placetype":"venue"
},
  "geometry": {"coordinates":[5.683686,51.48177],"type":"Point"}
}