{
  "type": "Feature",
  "properties": {
    "addr:full":"G W Burgerpln 8 Rotterdam Zuid-Holland 3021 AV",
    "addr:housenumber":"8",
    "addr:postcode":"3021 av",
    "addr:street":"G W Burgerpln",
    "iso:country":"NL",
    "sg:address":"G W Burgerpln 8",
    "sg:city":"Rotterdam",
    "sg:orig_category":"Verbouwingen",
    "sg:phone":"+31 6 24577289",
    "sg:postcode":"3021 AV",
    "sg:province":"Zuid-Holland",
    "wof:name":"Dpa",
    "wof:placetype":"venue"
},
  "geometry": {"coordinates":[4.458079,51.922173],"type":"Point"}
}