{
  "type": "Feature",
  "properties": {
    "iso:country":"NL",
    "sg:address":"Groothandelsmarkt 170",
    "sg:city":"Rotterdam",
    "sg:orig_category":"Fruit And Groenten Gh",
    "sg:phone":"+31 10 437 1111",
    "sg:postcode":"3044 HG",
    "sg:province":"Zuid-Holland",
    "wof:name":"J.A. Meeder",
    "wof:placetype":"venue"
},
  "geometry": {"coordinates":[4.415957,51.933151],"type":"Point"}
}