{
  "type": "Feature",
  "properties": {
    "iso:country":"NL",
    "sg:address":"Nw Havenwg 10",
    "sg:city":"Hilversum",
    "sg:orig_category":"Muziekdrukkerijen En -Uitgeverijen",
    "sg:phone":"+31 35 623 7272",
    "sg:postcode":"1216 BS",
    "sg:province":"Noord-Holland",
    "wof:name":"Kunst, De",
    "wof:placetype":"venue"
},
  "geometry": {"coordinates":[5.140077,52.222385],"type":"Point"}
}