{
  "type": "Feature",
  "properties": {
    "addr:full":"Postbus 186 Leeuwarden Friesland 8900 AD",
    "addr:housenumber":"186",
    "addr:postcode":"8900 ad",
    "addr:street":"Postbus",
    "iso:country":"NL",
    "sg:address":"Postbus 186",
    "sg:city":"Leeuwarden",
    "sg:orig_category":"Artiesten/Gezelschappen",
    "sg:phone":"+31 511 475 547",
    "sg:postcode":"8900 AD",
    "sg:province":"Friesland",
    "wof:name":"Kast, De",
    "wof:placetype":"venue"
},
  "geometry": {"coordinates":[5.79143,53.203049],"type":"Point"}
}