{
  "type": "Feature",
  "properties": {
    "addr:full":"Hengelosestr 14 Haaksbergen NL.08 7482 AC",
    "addr:housenumber":"14;nl.08",
    "addr:postcode":"7482 ac",
    "addr:street":"Hengelosestr",
    "iso:country":"NL",
    "sg:address":"Hengelosestr 14",
    "sg:city":"Haaksbergen",
    "sg:orig_category":"Tuingereedschappen En Tuinmachines",
    "sg:phone":"+31 53 572 1792",
    "sg:postcode":"7482 AC",
    "sg:province":"NL.08",
    "wof:name":"Keizers, Firma",
    "wof:placetype":"venue"
},
  "geometry": {"coordinates":[6.734787,52.161591],"type":"Point"}
}