{
  "type": "Feature",
  "properties": {
    "addr:full":"Singel 45 Westdorpe Zeeland 4554 CP",
    "addr:housenumber":"45",
    "addr:postcode":"4554 cp",
    "addr:street":"Singel",
    "iso:country":"NL",
    "sg:address":"Singel 45",
    "sg:city":"Westdorpe",
    "sg:orig_category":"Beeldende Kunstenaars",
    "sg:phone":"+31 115 454 629",
    "sg:postcode":"4554 CP",
    "sg:province":"Zeeland",
    "wof:name":"Atelier 45",
    "wof:placetype":"venue"
},
  "geometry": {"coordinates":[3.8297829628,51.2307357788],"type":"Point"}
}