{
  "type": "Feature",
  "properties": {
    "iso:country":"NL",
    "sg:address":"St.-Janshovenstraat 1",
    "sg:city":"Utrecht",
    "sg:orig_category":"Fotostudio'S And Fotografen",
    "sg:phone":"+31 30 272 4600",
    "sg:postcode":"3572 RA",
    "sg:province":"Utrecht",
    "wof:name":"Studio Voor Fotografie",
    "wof:placetype":"venue"
},
  "geometry": {"coordinates":[5.12753,52.095318],"type":"Point"}
}