{
  "type": "Feature",
  "properties": {
    "addr:full":"Industriewg 16 Wormerveer North Holland 1521 NC",
    "addr:housenumber":"16;1521",
    "addr:postcode":"nc",
    "addr:street":"Industriewg",
    "iso:country":"NL",
    "sg:address":"Industriewg 16",
    "sg:city":"Wormerveer",
    "sg:orig_category":"Bedrijfshuisvesting",
    "sg:phone":"+31 75 621 2721",
    "sg:postcode":"1521 NC",
    "sg:province":"North Holland",
    "wof:name":"Molletjesveer Bv",
    "wof:placetype":"venue"
},
  "geometry": {"coordinates":[4.777204,52.503651],"type":"Point"}
}