{
  "type": "Feature",
  "properties": {
    "addr:full":"De Beukums 37 Boxtel Noord-Brabant 5283 XG",
    "addr:housenumber":"37",
    "addr:postcode":"5283 xg",
    "addr:street":"De Beukums",
    "iso:country":"NL",
    "sg:address":"De Beukums 37",
    "sg:city":"Boxtel",
    "sg:classifiers":[
        {
            "category":"Personal",
            "subcategory":"Nail Salon",
            "type":"Services"
        }
    ],
    "sg:phone":"+31 411 677 596",
    "sg:postcode":"5283 XG",
    "sg:province":"Noord-Brabant",
    "sg:tags":[
        "pedicure"
    ],
    "wof:name":"Horst, Nelly Van De",
    "wof:placetype":"venue"
},
  "geometry": {"coordinates":[5.347927,51.589119],"type":"Point"}
}