{
  "type": "Feature",
  "properties": {
    "iso:country":"NL",
    "sg:address":"Hofwegen 37",
    "sg:city":"Bleskensgraaf Ca",
    "sg:orig_category":"Oldtimers",
    "sg:phone":"+31 184 692 967",
    "sg:postcode":"2971 XB",
    "sg:province":"Zuid-Holland",
    "wof:name":"Blankemeijer Automobielrenovatie",
    "wof:placetype":"venue"
},
  "geometry": {"coordinates":[4.787206,51.870506],"type":"Point"}
}