{
  "type": "Feature",
  "properties": {
    "addr:full":"Anjerdreef 24 Berkel En Rodenrijs Zuid-Holland 2651 XS",
    "addr:housenumber":"24",
    "addr:postcode":"2651 xs",
    "addr:street":"Anjerdreef",
    "iso:country":"NL",
    "sg:address":"Anjerdreef 24",
    "sg:city":"Berkel En Rodenrijs",
    "sg:orig_category":"Technische Studies And Onderzoek",
    "sg:phone":"+31 10 511 4550",
    "sg:postcode":"2651 XS",
    "sg:province":"Zuid-Holland",
    "wof:name":"Kwaliteitszorg Adviesbureau Nv",
    "wof:placetype":"venue"
},
  "geometry": {"coordinates":[4.462181,51.979568],"type":"Point"}
}