{
  "type": "Feature",
  "properties": {
    "iso:country":"NL",
    "sg:address":"Lisbaan 6",
    "sg:city":"Capelle Ad Yssel",
    "sg:orig_category":"Autolakken",
    "sg:phone":"+31 10 458 7355",
    "sg:postcode":"2908 LN",
    "sg:province":"Zuid-Holland",
    "wof:name":"Standox",
    "wof:placetype":"venue"
},
  "geometry": {"coordinates":[4.576488,51.957123],"type":"Point"}
}