{
  "type": "Feature",
  "properties": {
    "addr:full":"Bazuinstraat 1 Nijmegen Gelderland 6544 NK",
    "addr:housenumber":"1",
    "addr:postcode":"6544 nk",
    "addr:street":"Bazuinstraat;Gelderland",
    "iso:country":"NL",
    "sg:address":"Bazuinstraat 1",
    "sg:city":"Nijmegen",
    "sg:orig_category":"Fitnesscentra",
    "sg:phone":"+31 24 378 0332",
    "sg:postcode":"6544 NK",
    "sg:province":"Gelderland",
    "wof:name":"Sportvereniging Atlas",
    "wof:placetype":"venue"
},
  "geometry": {"coordinates":[5.811662,51.832737],"type":"Point"}
}