{
  "type": "Feature",
  "properties": {
    "addr:full":"Oude Brandenb Wg 13 Bilthoven Utrecht 3721 DT",
    "addr:housenumber":"13",
    "addr:postcode":"3721 dt",
    "addr:street":"Oude;Wg",
    "iso:country":"NL",
    "sg:address":"Oude Brandenb Wg 13",
    "sg:city":"Bilthoven",
    "sg:orig_category":"Kappers",
    "sg:phone":"+31 30 228 4199",
    "sg:postcode":"3721 DT",
    "sg:province":"Utrecht",
    "wof:name":"Hairpoint",
    "wof:placetype":"venue"
},
  "geometry": {"coordinates":[5.1881680489,52.1229476929],"type":"Point"}
}