{
  "type": "Feature",
  "properties": {
    "addr:full":"Hoofdstr 107/Ii Apeldoorn Gelderland 7311 JZ",
    "addr:housenumber":"107 / ii",
    "addr:postcode":"7311 jz",
    "addr:street":"Gelderland",
    "iso:country":"NL",
    "sg:address":"Hoofdstr 107/Ii",
    "sg:city":"Apeldoorn",
    "sg:orig_category":"Juweliers",
    "sg:phone":"+31 55 521 1450",
    "sg:postcode":"7311 JZ",
    "sg:province":"Gelderland",
    "wof:name":"Smit",
    "wof:placetype":"venue"
},
  "geometry": {"coordinates":[5.96566,52.216518],"type":"Point"}
}