{
  "type": "Feature",
  "properties": {
    "iso:country":"NL",
    "sg:address":"De Karekiet 32",
    "sg:city":"Vriezenveen",
    "sg:orig_category":"Geluidsinstallaties",
    "sg:phone":"+31 546 564 663",
    "sg:postcode":"7671 LA",
    "sg:province":"Overijssel",
    "sg:website":"http://www.christianfacilities.nl",
    "wof:name":"Christian Facilities",
    "wof:placetype":"venue"
},
  "geometry": {"coordinates":[6.610617,52.40374],"type":"Point"}
}