{
  "type": "Feature",
  "properties": {
    "addr:full":"Tartaud Kleinstr 42 Rotterdam Zuid-Holland 3066 JH",
    "addr:housenumber":"42",
    "addr:postcode":"3066 jh",
    "iso:country":"NL",
    "sg:address":"Tartaud Kleinstr 42",
    "sg:city":"Rotterdam",
    "sg:orig_category":"Behangers",
    "sg:phone":"+31 10 220 5794",
    "sg:postcode":"3066 JH",
    "sg:province":"Zuid-Holland",
    "wof:name":"Kalkan Behang & Stoffeerbedrijf",
    "wof:placetype":"venue"
},
  "geometry": {"coordinates":[4.545226,51.933147],"type":"Point"}
}