{
  "type": "Feature",
  "properties": {
    "addr:full":"M H Trompstr 39 Amsterdam North Holland 1056 HX",
    "addr:housenumber":"39",
    "addr:postcode":"1056 hx",
    "addr:street":"M",
    "iso:country":"NL",
    "sg:address":"M H Trompstr 39",
    "sg:city":"Amsterdam",
    "sg:orig_category":"Belastingconsulenten/ Belastingadviseurs",
    "sg:phone":"+31 20 616 1006",
    "sg:postcode":"1056 HX",
    "sg:province":"North Holland",
    "wof:name":"Stienstra, Accountantskantoor",
    "wof:placetype":"venue"
},
  "geometry": {"coordinates":[4.85478,52.373699],"type":"Point"}
}