{
  "type": "Feature",
  "properties": {
    "iso:country":"NL",
    "sg:address":"Lynbaen 16",
    "sg:city":"Workum",
    "sg:orig_category":"Huizensloop And Bouwrijp Maken",
    "sg:phone":"+31 515 542 840",
    "sg:postcode":"8711 ET",
    "sg:province":"Friesland",
    "wof:name":"N. Boekema",
    "wof:placetype":"venue"
},
  "geometry": {"coordinates":[5.439904,52.974785],"type":"Point"}
}