{
  "type": "Feature",
  "properties": {
    "addr:full":"T Dorp 15 Heesch Noord-Brabant 5384 MA",
    "addr:housenumber":"15",
    "addr:postcode":"5384 ma",
    "addr:street":"T Dorp",
    "iso:country":"NL",
    "sg:address":"T Dorp 15",
    "sg:city":"Heesch",
    "sg:orig_category":"Verlichting And Huishoudartikelen",
    "sg:phone":"+31 412 452 159",
    "sg:postcode":"5384 MA",
    "sg:province":"Noord-Brabant",
    "wof:name":"Eurotapijt Bv",
    "wof:placetype":"venue"
},
  "geometry": {"coordinates":[5.533183,51.735893],"type":"Point"}
}