{
  "type": "Feature",
  "properties": {
    "iso:country":"NL",
    "sg:address":"Juweelstraat 45",
    "sg:city":"Alphen A/D Rijn",
    "sg:classifiers":[
        {
            "category":"Professional",
            "subcategory":"Accounting & Tax Preparation",
            "type":"Services"
        }
    ],
    "sg:phone":"+31 172 431 804",
    "sg:postcode":"2403 BJ",
    "sg:province":"South Holland",
    "sg:tags":[
        "accountant"
    ],
    "wof:name":"Sax V.D. Weijden Administratieve Dienstv",
    "wof:placetype":"venue"
},
  "geometry": {"coordinates":[4.677642,52.139572],"type":"Point"}
}