{
  "type": "Feature",
  "properties": {
    "iso:country":"NL",
    "sg:address":"De Schakel 12",
    "sg:city":"Vught",
    "sg:orig_category":"Banden",
    "sg:phone":"+31 73 684 3322",
    "sg:postcode":"5261 LL",
    "sg:province":"Noord-Brabant",
    "sg:website":"http://www.kwik-fit.nl",
    "wof:name":"Kwik-Fit",
    "wof:placetype":"venue"
},
  "geometry": {"coordinates":[5.294317,51.644756],"type":"Point"}
}