{
  "type": "Feature",
  "properties": {
    "addr:full":"Ten Veldestr 97 De Meern Utrecht 3454 EK",
    "addr:housenumber":"97",
    "addr:postcode":"3454 ek",
    "addr:street":"Ten",
    "iso:country":"NL",
    "sg:address":"Ten Veldestr 97",
    "sg:city":"De Meern",
    "sg:orig_category":"Marktonderzoekbureaus",
    "sg:phone":"+31 30 662 1847",
    "sg:postcode":"3454 EK",
    "sg:province":"Utrecht",
    "wof:name":"Proservice",
    "wof:placetype":"venue"
},
  "geometry": {"coordinates":[5.031757,52.077026],"type":"Point"}
}