{
  "type": "Feature",
  "properties": {
    "addr:full":"Kerklaan 146 Rijswijk Zh Zuid-Holland 2282 CP",
    "addr:housenumber":"146",
    "addr:postcode":"zh;2282 cp",
    "addr:street":"Kerklaan",
    "iso:country":"NL",
    "sg:address":"Kerklaan 146",
    "sg:city":"Rijswijk Zh",
    "sg:orig_category":"Kappers",
    "sg:phone":"+31 70 390 8050",
    "sg:postcode":"2282 CP",
    "sg:province":"Zuid-Holland",
    "wof:name":"Vof Zonneveld Haarverzorging",
    "wof:placetype":"venue"
},
  "geometry": {"coordinates":[4.336928,52.052574],"type":"Point"}
}