{
  "type": "Feature",
  "properties": {
    "addr:full":"Begastr 1 Haarlem North Holland 2023 DW",
    "addr:housenumber":"1",
    "addr:postcode":"2023 dw",
    "addr:street":"Begastr",
    "iso:country":"NL",
    "sg:address":"Begastr 1",
    "sg:city":"Haarlem",
    "sg:orig_category":"Psychologen",
    "sg:phone":"+31 23 527 9444",
    "sg:postcode":"2023 DW",
    "sg:province":"North Holland",
    "wof:name":"Pabb",
    "wof:placetype":"venue"
},
  "geometry": {"coordinates":[4.628165,52.395302],"type":"Point"}
}