{
  "type": "Feature",
  "properties": {
    "iso:country":"NL",
    "sg:address":"Adelln 2B",
    "sg:city":"Made",
    "sg:orig_category":"Autorijscholen",
    "sg:phone":"+31 162 682 347",
    "sg:postcode":"4921 BM",
    "sg:province":"California",
    "wof:name":"Dongen, Verkeersschool Van",
    "wof:placetype":"venue"
},
  "geometry": {"coordinates":[-120.06399500000001,36.962055],"type":"Point"}
}