{
  "type": "Feature",
  "properties": {
    "addr:full":"Hoofdstr 13 Maasbracht Limburg 6051 AJ",
    "addr:housenumber":"13",
    "addr:postcode":"6051 aj",
    "addr:street":"Hoofdstr",
    "iso:country":"NL",
    "sg:address":"Hoofdstr 13",
    "sg:city":"Maasbracht",
    "sg:orig_category":"Artsen - Huisartsen",
    "sg:phone":"+31 475 464 220",
    "sg:postcode":"6051 AJ",
    "sg:province":"Limburg",
    "wof:name":"Engels En C T A M Janssen, R G A",
    "wof:placetype":"venue"
},
  "geometry": {"coordinates":[5.888862,51.149525],"type":"Point"}
}