{
  "type": "Feature",
  "properties": {
    "iso:country":"NL",
    "sg:address":"Berberisstr 36",
    "sg:city":"Amsterdam",
    "sg:orig_category":"Kappers",
    "sg:phone":"+31 20 632 6936",
    "sg:postcode":"1032 EM",
    "sg:province":"Noord-Holland",
    "wof:name":"Judith",
    "wof:placetype":"venue"
},
  "geometry": {"coordinates":[4.9139108658,52.3927345276],"type":"Point"}
}