{
  "type": "Feature",
  "properties": {
    "iso:country":"NL",
    "sg:address":"Eerste Breeuwersstraat 3",
    "sg:city":"Amsterdam",
    "sg:orig_category":"Fotostudio'S And Fotografen",
    "sg:phone":"+31 20 624 5728",
    "sg:postcode":"1013 MA",
    "sg:province":"Noord-Holland",
    "wof:name":"F. Sadaghyany",
    "wof:placetype":"venue"
},
  "geometry": {"coordinates":[4.885225,52.386234],"type":"Point"}
}