{
  "type": "Feature",
  "properties": {
    "addr:full":"Driemarkweg 1A Winterswijk Gelderland 7102 EM",
    "addr:housenumber":"1a",
    "addr:postcode":"7102 em",
    "addr:street":"Driemarkweg;Gelderland",
    "iso:country":"NL",
    "sg:address":"Driemarkweg 1A",
    "sg:city":"Winterswijk",
    "sg:orig_category":"Meubelzaken, Woning- And Keukeninrichting",
    "sg:phone":"+31 543 531 935",
    "sg:postcode":"7102 EM",
    "sg:province":"Gelderland",
    "wof:name":"Wapro Premier Waterbedden",
    "wof:placetype":"venue"
},
  "geometry": {"coordinates":[6.703663,51.962414],"type":"Point"}
}