{
  "type": "Feature",
  "properties": {
    "iso:country":"NL",
    "sg:address":"W Wesselspad 6",
    "sg:city":"Nes Ameland",
    "sg:orig_category":"Loonbedrijven",
    "sg:phone":"+31 519 543 180",
    "sg:postcode":"9163 JE",
    "sg:province":"Friesland",
    "wof:name":"Beekema, W",
    "wof:placetype":"venue"
},
  "geometry": {"coordinates":[5.774644,53.443932],"type":"Point"}
}