{
  "type": "Feature",
  "properties": {
    "addr:full":"Strawinskyln 1225 Amsterdam Noord-Holland 1077 XX",
    "addr:housenumber":"1225",
    "addr:postcode":"1077 xx",
    "iso:country":"NL",
    "sg:address":"Strawinskyln 1225",
    "sg:city":"Amsterdam",
    "sg:orig_category":"Adviesbureaus Bedrijfsorganisatie",
    "sg:phone":"+31 20 305 2780",
    "sg:postcode":"1077 XX",
    "sg:province":"Noord-Holland",
    "sg:website":"http://www.juran.com",
    "wof:name":"Juran Bv",
    "wof:placetype":"venue"
},
  "geometry": {"coordinates":[4.87414,52.340645],"type":"Point"}
}