{
  "type": "Feature",
  "properties": {
    "addr:full":"Toldk 7A Hekelingen Zuid-Holland 3209 BC",
    "addr:housenumber":"7a",
    "addr:postcode":"3209 bc",
    "addr:street":"Toldk",
    "iso:country":"NL",
    "sg:address":"Toldk 7A",
    "sg:city":"Hekelingen",
    "sg:classifiers":[
        {
            "category":"Sports & Exercise",
            "subcategory":"Stables",
            "type":"Entertainment"
        }
    ],
    "sg:phone":"+31 181 687 236",
    "sg:postcode":"3209 BC",
    "sg:province":"Zuid-Holland",
    "sg:tags":[
        "maneges"
    ],
    "wof:name":"Willemshof",
    "wof:placetype":"venue"
},
  "geometry": {"coordinates":[4.349962,51.825745],"type":"Point"}
}