{
  "type": "Feature",
  "properties": {
    "addr:full":"Amstelveld 7 Amsterdam Noord-Holland 1017 JD",
    "addr:housenumber":"7",
    "addr:postcode":"1017 jd",
    "addr:street":"Amstelveld",
    "iso:country":"NL",
    "sg:address":"Amstelveld 7",
    "sg:city":"Amsterdam",
    "sg:orig_category":"Advocaten And Juridische Adviseurs",
    "sg:phone":"+31 20 627 6684",
    "sg:postcode":"1017 JD",
    "sg:province":"Noord-Holland",
    "wof:name":"Van Gessel & Blaauw Advocaten",
    "wof:placetype":"venue"
},
  "geometry": {"coordinates":[4.898248,52.362568],"type":"Point"}
}