{
  "type": "Feature",
  "properties": {
    "addr:full":"Westerdorpsstraat 37 Hoevelaken Gelderland 3871 AT",
    "addr:housenumber":"37",
    "addr:postcode":"3871",
    "addr:street":"Westerdorpsstraat;Gelderland",
    "iso:country":"NL",
    "sg:address":"Westerdorpsstraat 37",
    "sg:city":"Hoevelaken",
    "sg:orig_category":"Bloemen And Planten",
    "sg:phone":"+31 33 253 7020",
    "sg:postcode":"3871 AT",
    "sg:province":"Gelderland",
    "wof:name":"Bloemsierkunst Kiki",
    "wof:placetype":"venue"
},
  "geometry": {"coordinates":[5.454428,52.17514],"type":"Point"}
}