{
  "type": "Feature",
  "properties": {
    "iso:country":"NL",
    "sg:address":"Doornseweg 30",
    "sg:city":"Leusden",
    "sg:orig_category":"Technische Studies And Onderzoek",
    "sg:phone":"+31 33 461 8616",
    "sg:postcode":"3832 RM",
    "sg:province":"Utrecht",
    "wof:name":"Buro Voor Vormgev. En Archit. Vellekoop",
    "wof:placetype":"venue"
},
  "geometry": {"coordinates":[5.361197,52.113262],"type":"Point"}
}