{
  "type": "Feature",
  "properties": {
    "addr:full":"Curiewg 25 Zwolle NL.08 8013 RA",
    "addr:housenumber":"25",
    "addr:postcode":"8013 ra",
    "addr:street":"Curiewg",
    "iso:country":"NL",
    "sg:address":"Curiewg 25",
    "sg:city":"Zwolle",
    "sg:orig_category":"Koffiebranderijen",
    "sg:phone":"+31 38 465 3500",
    "sg:postcode":"8013 RA",
    "sg:province":"NL.08",
    "sg:website":"http://www.algrakoffie.nl",
    "wof:name":"Algra Koffie Branderij & Theehndl",
    "wof:placetype":"venue"
},
  "geometry": {"coordinates":[6.130026,52.50024],"type":"Point"}
}