{
  "type": "Feature",
  "properties": {
    "addr:full":"Herenweg 259 Vinkeveen Utrecht 3645 DM",
    "addr:housenumber":"259",
    "addr:postcode":"3645 dm",
    "addr:street":"Herenweg",
    "iso:country":"NL",
    "sg:address":"Herenweg 259",
    "sg:city":"Vinkeveen",
    "sg:orig_category":"Pleziervaartuigen And Reparatie",
    "sg:phone":"+31 297 261 877",
    "sg:postcode":"3645 DM",
    "sg:province":"Utrecht",
    "wof:name":"Scheepbouw Achterbos Theo Kok",
    "wof:placetype":"venue"
},
  "geometry": {"coordinates":[4.930345,52.221741],"type":"Point"}
}