{
  "type": "Feature",
  "properties": {
    "addr:full":"Staringstraat 22 Schoonoord Gelderland 7204 DG",
    "addr:housenumber":"22",
    "addr:postcode":"7204 dg",
    "addr:street":"Staringstraat;Gelderland",
    "iso:country":"NL",
    "sg:address":"Staringstraat 22",
    "sg:city":"Schoonoord",
    "sg:orig_category":"Huisdierenfokkers",
    "sg:phone":"+31 575 512 843",
    "sg:postcode":"7204 DG",
    "sg:province":"Gelderland",
    "wof:name":"Hondenkennel Chihuahua",
    "wof:placetype":"venue"
},
  "geometry": {"coordinates":[6.75755,52.845219],"type":"Point"}
}