{
  "type": "Feature",
  "properties": {
    "addr:full":"Weissenbruchln 148 Rotterdam Zuid-Holland 3054 LS",
    "addr:housenumber":"148",
    "addr:postcode":"3054 ls",
    "iso:country":"NL",
    "sg:address":"Weissenbruchln 148",
    "sg:city":"Rotterdam",
    "sg:orig_category":"Schoenen",
    "sg:phone":"+31 10 418 9992",
    "sg:postcode":"3054 LS",
    "sg:province":"Zuid-Holland",
    "sg:website":"http://www.dungelmann-schoenen.nl",
    "wof:name":"Dungelmann",
    "wof:placetype":"venue"
},
  "geometry": {"coordinates":[4.495949,51.956608],"type":"Point"}
}