{
  "type": "Feature",
  "properties": {
    "addr:full":"Gasthuisring 54 Tilburg North Brabant 5041 DT",
    "addr:housenumber":"54",
    "addr:postcode":"5041 dt",
    "addr:street":"Gasthuisring",
    "iso:country":"NL",
    "sg:address":"Gasthuisring 54",
    "sg:city":"Tilburg",
    "sg:orig_category":"Architecten",
    "sg:phone":"+31 13 542 5517",
    "sg:postcode":"5041 DT",
    "sg:province":"North Brabant",
    "wof:name":"Vs Building Care",
    "wof:placetype":"venue"
},
  "geometry": {"coordinates":[5.077679,51.562363],"type":"Point"}
}