{
  "type": "Feature",
  "properties": {
    "iso:country":"NL",
    "sg:address":"Oliemolen 98",
    "sg:city":"Roosendaal",
    "sg:orig_category":"Drukkerijen",
    "sg:phone":"+31 165 562 628",
    "sg:postcode":"4701 KM",
    "sg:province":"Noord-Brabant",
    "wof:name":"Pres&Tatie",
    "wof:placetype":"venue"
},
  "geometry": {"coordinates":[4.461916,51.536694],"type":"Point"}
}