{
  "type": "Feature",
  "properties": {
    "addr:full":"Laarstraat 30 Goor Overijssel 7471 DD",
    "addr:housenumber":"30",
    "addr:postcode":"7471 dd",
    "addr:street":"Laarstraat",
    "iso:country":"NL",
    "sg:address":"Laarstraat 30",
    "sg:city":"Goor",
    "sg:orig_category":"Fotostudio'S And Fotografen",
    "sg:phone":"+31 547 276 158",
    "sg:postcode":"7471 DD",
    "sg:province":"Overijssel",
    "wof:name":"Fotografie Ge Pe Fotografie",
    "wof:placetype":"venue"
},
  "geometry": {"coordinates":[6.583211,52.234097],"type":"Point"}
}