{
  "type": "Feature",
  "properties": {
    "addr:full":"Olingermeeden 86 Appingedam Groningen 9903 ET",
    "addr:housenumber":"86",
    "addr:postcode":"9903 et",
    "addr:street":"Olingermeeden",
    "iso:country":"NL",
    "sg:address":"Olingermeeden 86",
    "sg:city":"Appingedam",
    "sg:orig_category":"Machinehandel",
    "sg:phone":"+31 596 624 215",
    "sg:postcode":"9903 ET",
    "sg:province":"Groningen",
    "wof:name":"Snakenborg",
    "wof:placetype":"venue"
},
  "geometry": {"coordinates":[6.84601,53.315533],"type":"Point"}
}