{
  "type": "Feature",
  "properties": {
    "addr:full":"Coenecoop 123D Waddinxveen Zuid-Holland 2741 PJ",
    "addr:housenumber":"123d",
    "addr:postcode":"2741 pj",
    "addr:street":"Coenecoop",
    "iso:country":"NL",
    "sg:address":"Coenecoop 123D",
    "sg:city":"Waddinxveen",
    "sg:classifiers":[
        {
            "category":"Autos & Motor Vehicles",
            "subcategory":"Motorcycle Sales",
            "type":"Retail Goods"
        }
    ],
    "sg:phone":"+31 182 637 258",
    "sg:postcode":"2741 PJ",
    "sg:province":"Zuid-Holland",
    "sg:tags":[
        "groothandel",
        "scooter",
        "en",
        "-"
    ],
    "sg:website":"http://www.koopmanstuning.nl",
    "wof:name":"Koopmans",
    "wof:placetype":"venue"
},
  "geometry": {"coordinates":[4.65624,52.02636],"type":"Point"}
}