{
  "type": "Feature",
  "properties": {
    "addr:full":"Herenwg 64 Maarssen Utrecht 3602 AR",
    "addr:housenumber":"64",
    "addr:postcode":"3602",
    "addr:street":"Herenwg",
    "iso:country":"NL",
    "sg:address":"Herenwg 64",
    "sg:city":"Maarssen",
    "sg:orig_category":"Geluidsinstallaties - Verhuur",
    "sg:phone":"+31 346 550 089",
    "sg:postcode":"3602 AR",
    "sg:province":"Utrecht",
    "sg:website":"http://www.autottaal.net",
    "wof:name":"Av Totaal",
    "wof:placetype":"venue"
},
  "geometry": {"coordinates":[5.072969,52.141514],"type":"Point"}
}