{
  "type": "Feature",
  "properties": {
    "addr:full":"Rijksstraatweg 20 Elst Ut Utrecht 3921 AJ",
    "addr:housenumber":"20",
    "addr:postcode":"ut;3921 aj",
    "addr:street":"Rijksstraatweg",
    "iso:country":"NL",
    "sg:address":"Rijksstraatweg 20",
    "sg:city":"Elst Ut",
    "sg:orig_category":"Zuivelproducten And Spijsoli?n Gh",
    "sg:phone":"+31 318 471 229",
    "sg:postcode":"3921 AJ",
    "sg:province":"Utrecht",
    "wof:name":"Eierhandel G.G. Van De Grift & Zonen Bv",
    "wof:placetype":"venue"
},
  "geometry": {"coordinates":[5.491095,51.985634],"type":"Point"}
}