{
  "type": "Feature",
  "properties": {
    "addr:full":"Weitakkerstr 2 Elburg Gelderland 8081 XX",
    "addr:housenumber":"2",
    "addr:postcode":"8081 xx",
    "addr:street":"Weitakkerstr;Gelderland",
    "iso:country":"NL",
    "sg:address":"Weitakkerstr 2",
    "sg:city":"Elburg",
    "sg:orig_category":"Scholen Voor Basisonderwijs",
    "sg:phone":"+31 525 681 059",
    "sg:postcode":"8081 XX",
    "sg:province":"Gelderland",
    "wof:name":"Octaaf, Het",
    "wof:placetype":"venue"
},
  "geometry": {"coordinates":[5.850052,52.449387],"type":"Point"}
}