{
  "type": "Feature",
  "properties": {
    "addr:full":"Burg Stulemeijerln 14 Bergen Op Zoom Noord-Brabant 4611 EE",
    "addr:housenumber":"14",
    "addr:postcode":"4611 ee",
    "addr:street":"Burg",
    "iso:country":"NL",
    "sg:address":"Burg Stulemeijerln 14",
    "sg:city":"Bergen Op Zoom",
    "sg:orig_category":"Boekhouders",
    "sg:phone":"+31 164 256 200",
    "sg:postcode":"4611 EE",
    "sg:province":"Noord-Brabant",
    "wof:name":"Administratiekantoor V/H J. Zwagemakers",
    "wof:placetype":"venue"
},
  "geometry": {"coordinates":[4.281987,51.495953],"type":"Point"}
}