{
  "type": "Feature",
  "properties": {
    "addr:full":"Waterlandsngl 12A S Gravenhage Zuid-Holland 2548 SR",
    "addr:housenumber":"12a;gravenhage;2548",
    "addr:postcode":"sr",
    "addr:street":"Waterlandsngl;S",
    "iso:country":"NL",
    "sg:address":"Waterlandsngl 12A",
    "sg:city":"S Gravenhage",
    "sg:orig_category":"Schilders",
    "sg:phone":"+31 70 367 0538",
    "sg:postcode":"2548 SR",
    "sg:province":"Zuid-Holland",
    "wof:name":"Schenk, F W",
    "wof:placetype":"venue"
},
  "geometry": {"coordinates":[4.2901,52.029888],"type":"Point"}
}