{
  "type": "Feature",
  "properties": {
    "addr:full":"Hoofdstr 15 Deurningen Overijssel 7561 AB",
    "addr:housenumber":"15",
    "addr:postcode":"7561 ab",
    "addr:street":"Hoofdstr",
    "iso:country":"NL",
    "sg:address":"Hoofdstr 15",
    "sg:city":"Deurningen",
    "sg:orig_category":"Woninginrichting",
    "sg:phone":"+31 74 277 2241",
    "sg:postcode":"7561 AB",
    "sg:province":"Overijssel",
    "wof:name":"Scheffer, Vincent",
    "wof:placetype":"venue"
},
  "geometry": {"coordinates":[6.8346948624,52.3000984192],"type":"Point"}
}