{
  "type": "Feature",
  "properties": {
    "addr:full":"Strevelswg 48B Rotterdam Zuid-Holland 3075 AK",
    "addr:housenumber":"48b",
    "addr:postcode":"3075 ak",
    "addr:street":"Strevelswg",
    "iso:country":"NL",
    "sg:address":"Strevelswg 48B",
    "sg:city":"Rotterdam",
    "sg:orig_category":"Kappers",
    "sg:phone":"+31 10 485 9405",
    "sg:postcode":"3075 AK",
    "sg:province":"Zuid-Holland",
    "wof:name":"Artistique",
    "wof:placetype":"venue"
},
  "geometry": {"coordinates":[4.4999098778,51.8895111084],"type":"Point"}
}