{
  "type": "Feature",
  "properties": {
    "addr:full":"Diefstg 9 Leiden South Holland 2311 TS",
    "addr:housenumber":"9",
    "addr:postcode":"2311 ts",
    "addr:street":"Diefstg",
    "iso:country":"NL",
    "sg:address":"Diefstg 9",
    "sg:city":"Leiden",
    "sg:orig_category":"Juridische Adviseurs",
    "sg:phone":"+31 71 514 1799",
    "sg:postcode":"2311 TS",
    "sg:province":"South Holland",
    "sg:website":"http://www.newlaw.nl",
    "wof:name":"New Law Facilities Bv",
    "wof:placetype":"venue"
},
  "geometry": {"coordinates":[4.488662,52.158875],"type":"Point"}
}