{
  "type": "Feature",
  "properties": {
    "iso:country":"NL",
    "sg:address":"Voorschoterlaan 103",
    "sg:city":"Rotterdam",
    "sg:orig_category":"Papier- And Kartonverpakkingen Fab",
    "sg:phone":"+31 10 412 3701",
    "sg:postcode":"3062 KK",
    "sg:province":"South Holland",
    "wof:name":"R Hollaar",
    "wof:placetype":"venue"
},
  "geometry": {"coordinates":[4.511181,51.922436],"type":"Point"}
}