{
  "type": "Feature",
  "properties": {
    "addr:full":"Voorschoterlaan 103 Rotterdam South Holland 3062 KK",
    "addr:housenumber":"103",
    "addr:postcode":"3062 kk",
    "addr:street":"Voorschoterlaan",
    "iso:country":"NL",
    "sg:address":"Voorschoterlaan 103",
    "sg:city":"Rotterdam",
    "sg:orig_category":"Papier- And Kartonverpakkingen Fab",
    "sg:phone":"+31 10 412 3701",
    "sg:postcode":"3062 KK",
    "sg:province":"South Holland",
    "wof:name":"R Hollaar",
    "wof:placetype":"venue"
},
  "geometry": {"coordinates":[4.511181,51.922436],"type":"Point"}
}