{
  "type": "Feature",
  "properties": {
    "addr:full":"Aalsmeerweg 55 Amsterdam North Holland 1059 AC",
    "addr:housenumber":"55",
    "addr:postcode":"1059 ac",
    "addr:street":"Aalsmeerweg",
    "iso:country":"NL",
    "sg:address":"Aalsmeerweg 55",
    "sg:city":"Amsterdam",
    "sg:classifiers":[
        {
            "category":"Food & Beverages",
            "subcategory":"Fruits & Vegetables",
            "type":"Retail Goods"
        }
    ],
    "sg:phone":"+31 20 615 7352",
    "sg:postcode":"1059 AC",
    "sg:province":"North Holland",
    "sg:tags":[
        "groenten"
    ],
    "wof:name":"Hiba",
    "wof:placetype":"venue"
},
  "geometry": {"coordinates":[4.849322,52.349457],"type":"Point"}
}