{
  "type": "Feature",
  "properties": {
    "addr:full":"Zwinstraat 6 Den Oever Noord-Holland 1779 BG",
    "addr:housenumber":"6",
    "addr:postcode":"1779",
    "addr:street":"Zwinstraat",
    "iso:country":"NL",
    "sg:address":"Zwinstraat 6",
    "sg:city":"Den Oever",
    "sg:orig_category":"Recreatie",
    "sg:phone":"+31 227 511 689",
    "sg:postcode":"1779 BG",
    "sg:province":"Noord-Holland",
    "wof:name":"Zomerdijk & Zn.",
    "wof:placetype":"venue"
},
  "geometry": {"coordinates":[5.02882,52.934517],"type":"Point"}
}