{
  "type": "Feature",
  "properties": {
    "addr:full":"De Schokker 36 Egmond Aan Zee Noord-Holland 1931 DC",
    "addr:housenumber":"36",
    "addr:postcode":"1931",
    "addr:street":"De Schokker",
    "iso:country":"NL",
    "sg:address":"De Schokker 36",
    "sg:city":"Egmond Aan Zee",
    "sg:orig_category":"Begrafenisondernemers",
    "sg:phone":"+31 72 506 2687",
    "sg:postcode":"1931 DC",
    "sg:province":"Noord-Holland",
    "wof:name":"Begrafenisvereniging Memento Mori",
    "wof:placetype":"venue"
},
  "geometry": {"coordinates":[-91.34150699999999,30.753977],"type":"Point"}
}