{
  "type": "Feature",
  "properties": {
    "addr:full":"Slotlaan 89 Doetinchem Gelderland 7006 HC",
    "addr:housenumber":"89",
    "addr:postcode":"7006 hc",
    "addr:street":"Slotlaan;Gelderland",
    "iso:country":"NL",
    "sg:address":"Slotlaan 89",
    "sg:city":"Doetinchem",
    "sg:orig_category":"Goederenvervoer Over De Weg",
    "sg:phone":"+31 314 325 145",
    "sg:postcode":"7006 HC",
    "sg:province":"Gelderland",
    "wof:name":"Internationaal Transportbedrijf V. Ooij",
    "wof:placetype":"venue"
},
  "geometry": {"coordinates":[6.260516,51.965942],"type":"Point"}
}