{
  "type": "Feature",
  "properties": {
    "addr:full":"Bossenwaard 3 Zoetermeer Zuid-Holland 2716 DM",
    "addr:housenumber":"3",
    "addr:postcode":"2716 dm",
    "addr:street":"Bossenwaard",
    "iso:country":"NL",
    "sg:address":"Bossenwaard 3",
    "sg:city":"Zoetermeer",
    "sg:classifiers":[
        {
            "category":"Fast Food",
            "type":"Food & Drink"
        }
    ],
    "sg:phone":"+31 79 321 0626",
    "sg:postcode":"2716 DM",
    "sg:province":"Zuid-Holland",
    "sg:tags":[
        "afhaal",
        "restaurant"
    ],
    "wof:name":"The Corner",
    "wof:placetype":"venue"
},
  "geometry": {"coordinates":[4.467662,52.055656],"type":"Point"}
}