{
  "type": "Feature",
  "properties": {
    "addr:full":"Haanderik 56 Ijsselstein Ut Utrecht 3401 ES",
    "addr:housenumber":"56",
    "addr:postcode":"3401 es",
    "addr:street":"Haanderik",
    "iso:country":"NL",
    "sg:address":"Haanderik 56",
    "sg:city":"Ijsselstein Ut",
    "sg:orig_category":"Meubels And Huishoudapparatuur Gh",
    "sg:phone":"+31 30 687 4914",
    "sg:postcode":"3401 ES",
    "sg:province":"Utrecht",
    "wof:name":"Frans Brand Meubelen",
    "wof:placetype":"venue"
},
  "geometry": {"coordinates":[5.03833,52.026085],"type":"Point"}
}