{
  "type": "Feature",
  "properties": {
    "addr:full":"Grebbedk 39 Wageningen Gelderland 6702 DS",
    "addr:housenumber":"39",
    "addr:postcode":"6702 ds",
    "addr:street":"Grebbedk;Gelderland",
    "iso:country":"NL",
    "sg:address":"Grebbedk 39",
    "sg:city":"Wageningen",
    "sg:classifiers":[
        {
            "category":"Retail",
            "subcategory":"Storage",
            "type":"Services"
        }
    ],
    "sg:phone":"+31 317 414 594",
    "sg:postcode":"6702 DS",
    "sg:province":"Gelderland",
    "sg:tags":[
        "op-",
        "en",
        "overslagbedrijven"
    ],
    "wof:name":"Silo Wageningen Bv",
    "wof:placetype":"venue"
},
  "geometry": {"coordinates":[5.649884,51.957439],"type":"Point"}
}