{
  "type": "Feature",
  "properties": {
    "addr:full":"Groene Streep 6 Afferden Lb Limburg 5851 ED",
    "addr:housenumber":"6",
    "addr:postcode":"lb;5851 ed",
    "addr:street":"Groene Streep",
    "iso:country":"NL",
    "sg:address":"Groene Streep 6",
    "sg:city":"Afferden Lb",
    "sg:orig_category":"Adviesbureaus Bedrijfsorganisatie",
    "sg:phone":"+31 485 531 807",
    "sg:postcode":"5851 ED",
    "sg:province":"Limburg",
    "wof:name":"Diva",
    "wof:placetype":"venue"
},
  "geometry": {"coordinates":[-93.129936,36.705662],"type":"Point"}
}