{
  "type": "Feature",
  "properties": {
    "iso:country":"NL",
    "sg:address":"Nieuweweg 84",
    "sg:city":"Zwartemeer",
    "sg:orig_category":"Metaalwerken",
    "sg:phone":"+31 591 316 085",
    "sg:postcode":"7894 AT",
    "sg:province":"Drenthe",
    "wof:name":"G. Harms",
    "wof:placetype":"venue"
},
  "geometry": {"coordinates":[7.043434,52.710293],"type":"Point"}
}