{
  "type": "Feature",
  "properties": {
    "addr:full":"Langendijk 1 Gorinchem Zuid-Holland 4201 CE",
    "addr:housenumber":"1",
    "addr:postcode":"4201 ce",
    "addr:street":"Langendijk",
    "iso:country":"NL",
    "sg:address":"Langendijk 1",
    "sg:city":"Gorinchem",
    "sg:orig_category":"Baby- And Kinderkleding",
    "sg:phone":"+31 183 635 310",
    "sg:postcode":"4201 CE",
    "sg:province":"Zuid-Holland",
    "wof:name":"Prenatal Het Linnenhuis",
    "wof:placetype":"venue"
},
  "geometry": {"coordinates":[4.976468,51.830051],"type":"Point"}
}