{
  "type": "Feature",
  "properties": {
    "addr:full":"Mekelwg 4 Delft Zuid-Holland 2628 CD",
    "addr:housenumber":"4",
    "addr:postcode":"2628 cd",
    "addr:street":"Mekelwg",
    "iso:country":"NL",
    "sg:address":"Mekelwg 4",
    "sg:city":"Delft",
    "sg:orig_category":"Verenigingen En Stichtingen",
    "sg:phone":"+31 15 278 2870",
    "sg:postcode":"2628 CD",
    "sg:province":"Zuid-Holland",
    "wof:name":"Hidde Nijland, Sticht Dr Ir H A",
    "wof:placetype":"venue"
},
  "geometry": {"coordinates":[4.373978,51.998997],"type":"Point"}
}