{
  "type": "Feature",
  "properties": {
    "addr:full":"V Vredenburchwg 26 Ryswyk Zh Zuid-Holland 2282 SH",
    "addr:housenumber":"26",
    "addr:postcode":"2282 sh",
    "addr:street":"Ryswyk",
    "iso:country":"NL",
    "sg:address":"V Vredenburchwg 26",
    "sg:city":"Ryswyk Zh",
    "sg:orig_category":"Bejaarden - Verzorgingstehuizen",
    "sg:phone":"+31 70 413 8200",
    "sg:postcode":"2282 SH",
    "sg:province":"Zuid-Holland",
    "wof:name":"Onderwatershof",
    "wof:placetype":"venue"
},
  "geometry": {"coordinates":[4.33694,52.056503],"type":"Point"}
}