{
  "type": "Feature",
  "properties": {
    "addr:full":"Raam 67 Gouda Zuid-Holland 2801 VJ",
    "addr:housenumber":"67",
    "addr:postcode":"2801 vj",
    "addr:street":"Raam",
    "iso:country":"NL",
    "sg:address":"Raam 67",
    "sg:city":"Gouda",
    "sg:classifiers":[
        {
            "category":"Communications",
            "subcategory":"Television Station",
            "type":"Services"
        }
    ],
    "sg:phone":"+31 182 585 963",
    "sg:postcode":"2801 VJ",
    "sg:province":"Zuid-Holland",
    "sg:tags":[
        "video",
        "audio",
        "verhuur"
    ],
    "wof:name":"Filmclub Gouda",
    "wof:placetype":"venue"
},
  "geometry": {"coordinates":[4.706338,52.009483],"type":"Point"}
}