{
  "type": "Feature",
  "properties": {
    "addr:full":"Molenweg 49 Rozenburg Zh South Holland 3181 AT",
    "addr:housenumber":"49",
    "addr:postcode":"zh;3181",
    "addr:street":"Molenweg",
    "iso:country":"NL",
    "sg:address":"Molenweg 49",
    "sg:city":"Rozenburg Zh",
    "sg:orig_category":"Kappers",
    "sg:phone":"+31 181 219 017",
    "sg:postcode":"3181 AT",
    "sg:province":"South Holland",
    "wof:name":"Fedina Haarmode",
    "wof:placetype":"venue"
},
  "geometry": {"coordinates":[4.2483911514,51.9048576355],"type":"Point"}
}