{
  "type": "Feature",
  "properties": {
    "addr:full":"Democratenlaan 88 Zwolle NL.08 8014 VC",
    "addr:housenumber":"88",
    "addr:postcode":"8014 vc",
    "addr:street":"Democratenlaan",
    "iso:country":"NL",
    "sg:address":"Democratenlaan 88",
    "sg:city":"Zwolle",
    "sg:orig_category":"Paramedische Behandelingen",
    "sg:phone":"+31 38 465 2601",
    "sg:postcode":"8014 VC",
    "sg:province":"NL.08",
    "wof:name":"Logopediepraktijk Zwolle Zuid",
    "wof:placetype":"venue"
},
  "geometry": {"coordinates":[6.115096,52.482471],"type":"Point"}
}