{
  "type": "Feature",
  "properties": {
    "addr:full":"Z Oosterstr 22B Tilburg Noord-Brabant 5014 BB",
    "addr:housenumber":"22b",
    "addr:postcode":"5014 bb",
    "iso:country":"NL",
    "sg:address":"Z Oosterstr 22B",
    "sg:city":"Tilburg",
    "sg:classifiers":[
        {
            "category":"Retail",
            "subcategory":"Auto Repair",
            "type":"Services"
        }
    ],
    "sg:phone":"+31 13 535 3467",
    "sg:postcode":"5014 BB",
    "sg:province":"Noord-Brabant",
    "sg:tags":[
        "garage"
    ],
    "wof:name":"Ron Garage",
    "wof:placetype":"venue"
},
  "geometry": {"coordinates":[5.097307,51.560371],"type":"Point"}
}