{
  "type": "Feature",
  "properties": {
    "addr:full":"Beukerstr 11 Fil Zutphen Gelderland 7201 LA",
    "addr:housenumber":"11;7201",
    "addr:street":"Beukerstr;Fil;Gelderland",
    "iso:country":"NL",
    "sg:address":"Beukerstr 11 Fil",
    "sg:city":"Zutphen",
    "sg:orig_category":"Herenkleding",
    "sg:phone":"+31 575 510 970",
    "sg:postcode":"7201 LA",
    "sg:province":"Gelderland",
    "sg:website":"http://www.wefashion.com",
    "wof:name":"We",
    "wof:placetype":"venue"
},
  "geometry": {"coordinates":[6.191525,52.140202],"type":"Point"}
}