{
  "type": "Feature",
  "properties": {
    "iso:country":"NL",
    "sg:address":"Eikendreef 55",
    "sg:city":"Helmond",
    "sg:orig_category":"Adviesbureaus Financieel",
    "sg:phone":"+31 492 546 637",
    "sg:postcode":"5707 BP",
    "sg:province":"Noord-Brabant",
    "wof:name":"Verhees & Partners Bv",
    "wof:placetype":"venue"
},
  "geometry": {"coordinates":[5.645271,51.477772],"type":"Point"}
}