{
  "type": "Feature",
  "properties": {
    "addr:full":"G Gezelleln 28 Zeist Utrecht 3705 AT",
    "addr:housenumber":"28",
    "addr:postcode":"3705",
    "iso:country":"NL",
    "sg:address":"G Gezelleln 28",
    "sg:city":"Zeist",
    "sg:classifiers":[
        {
            "category":"Professional",
            "subcategory":"Accounting & Tax Preparation",
            "type":"Services"
        }
    ],
    "sg:phone":"+31 30 696 1591",
    "sg:postcode":"3705 AT",
    "sg:province":"Utrecht",
    "sg:tags":[
        "accountant",
        "en",
        "-kantoren",
        "register-"
    ],
    "wof:name":"Rijnja Bv",
    "wof:placetype":"venue"
},
  "geometry": {"coordinates":[5.24387,52.08548],"type":"Point"}
}