{
  "type": "Feature",
  "properties": {
    "addr:full":"Stationsplein 294 Schiphol Noord-Holland 1117 CJ",
    "addr:housenumber":"294",
    "addr:postcode":"1117 cj",
    "addr:street":"Stationsplein",
    "iso:country":"NL",
    "sg:address":"Stationsplein 294",
    "sg:city":"Schiphol",
    "sg:orig_category":"Public Relationbureaus",
    "sg:phone":"+31 20 316 1551",
    "sg:postcode":"1117 CJ",
    "sg:province":"Noord-Holland",
    "wof:name":"Andriesse Public Relations",
    "wof:placetype":"venue"
},
  "geometry": {"coordinates":[4.812667,52.311737],"type":"Point"}
}