{
  "type": "Feature",
  "properties": {
    "iso:country":"NL",
    "sg:address":"Langestr 82",
    "sg:city":"S Gravenzande",
    "sg:orig_category":"Poeliers",
    "sg:phone":"+31 174 417 669",
    "sg:postcode":"2691 BJ",
    "sg:province":"Zuid-Holland",
    "wof:name":"Joh Lieffering, Gilde Poelier",
    "wof:placetype":"venue"
},
  "geometry": {"coordinates":[4.162,52.002037],"type":"Point"}
}