{
  "type": "Feature",
  "properties": {
    "addr:full":"Dubbelebuurt 29 Wormerveer North Holland 1521 DB",
    "addr:housenumber":"29",
    "addr:postcode":"1521 db",
    "addr:street":"Dubbelebuurt",
    "iso:country":"NL",
    "sg:address":"Dubbelebuurt 29",
    "sg:city":"Wormerveer",
    "sg:orig_category":"Autokeuringen",
    "sg:phone":"+31 75 621 6467",
    "sg:postcode":"1521 DB",
    "sg:province":"North Holland",
    "wof:name":"Guus Gobel Autoreparatie",
    "wof:placetype":"venue"
},
  "geometry": {"coordinates":[4.803879,52.488297],"type":"Point"}
}