{
  "type": "Feature",
  "properties": {
    "addr:full":"Molenstr 51 Oss Noord-Brabant 5341 GB",
    "addr:housenumber":"51",
    "addr:postcode":"5341 gb",
    "addr:street":"Molenstr",
    "iso:country":"NL",
    "sg:address":"Molenstr 51",
    "sg:city":"Oss",
    "sg:orig_category":"Verzekeringen - Verzekeringskantoren",
    "sg:phone":"+31 412 695 005",
    "sg:postcode":"5341 GB",
    "sg:province":"Noord-Brabant",
    "sg:website":"http://www.blommersgreve.nl",
    "wof:name":"Blommers & Greve Bv",
    "wof:placetype":"venue"
},
  "geometry": {"coordinates":[-77.235214,38.312599],"type":"Point"}
}