{
  "type": "Feature",
  "properties": {
    "iso:country":"NL",
    "sg:address":"Langewg 80",
    "sg:city":"Apeldoorn",
    "sg:orig_category":"Binnenhuisarchitectuur",
    "sg:phone":"+31 55 378 2393",
    "sg:postcode":"7315 CZ",
    "sg:province":"Gelderland",
    "sg:website":"http://www.nemesys-interieur.nl",
    "wof:name":"Nemesys Binnenhuisarchitektuur",
    "wof:placetype":"venue"
},
  "geometry": {"coordinates":[5.955759,52.227646],"type":"Point"}
}