{
  "type": "Feature",
  "properties": {
    "addr:full":"V Osingawg 17 Schettens Friesland 8744 EV",
    "addr:housenumber":"17",
    "iso:country":"NL",
    "sg:address":"V Osingawg 17",
    "sg:city":"Schettens",
    "sg:orig_category":"Beeldende Kunstenaars",
    "sg:phone":"+31 517 531 013",
    "sg:postcode":"8744 EV",
    "sg:province":"Friesland",
    "wof:name":"Ykje/Durk",
    "wof:placetype":"venue"
},
  "geometry": {"coordinates":[5.483232,53.082283],"type":"Point"}
}