{
  "type": "Feature",
  "properties": {
    "addr:full":"Heerlenstr 9 Almere Flevoland 1324 MC",
    "addr:housenumber":"9;1324",
    "addr:street":"Heerlenstr;Flevoland;Mc",
    "iso:country":"NL",
    "sg:address":"Heerlenstr 9",
    "sg:city":"Almere",
    "sg:orig_category":"Grafisch Ontwerpers",
    "sg:phone":"+31 36 548 9302",
    "sg:postcode":"1324 MC",
    "sg:province":"Flevoland",
    "wof:name":"Aha",
    "wof:placetype":"venue"
},
  "geometry": {"coordinates":[5.210234,52.358849],"type":"Point"}
}