{
  "type": "Feature",
  "properties": {
    "iso:country":"NL",
    "sg:address":"Kwikstaart 5",
    "sg:city":"Nieuwegein",
    "sg:orig_category":"Adviesbureaus Bedrijfsorganisatie",
    "sg:phone":"+31 30 605 1482",
    "sg:postcode":"3435 RL",
    "sg:province":"Utrecht",
    "wof:name":"Kuiper & Van De Kieft",
    "wof:placetype":"venue"
},
  "geometry": {"coordinates":[5.072765,52.027164],"type":"Point"}
}