{
  "type": "Feature",
  "properties": {
    "addr:full":"V Hallstr 41 Wassenaar Zuid-Holland 2241 KT",
    "addr:housenumber":"41",
    "addr:postcode":"2241 kt",
    "iso:country":"NL",
    "sg:address":"V Hallstr 41",
    "sg:city":"Wassenaar",
    "sg:orig_category":"Loodgieters",
    "sg:phone":"+31 70 511 0106",
    "sg:postcode":"2241 KT",
    "sg:province":"Zuid-Holland",
    "wof:name":"Dijksterhuis Bv, A",
    "wof:placetype":"venue"
},
  "geometry": {"coordinates":[4.393863,52.14307],"type":"Point"}
}