{
  "type": "Feature",
  "properties": {
    "iso:country":"NL",
    "sg:address":"Beemsterboerweg 7",
    "sg:city":"Waarland",
    "sg:orig_category":"Bloemen And Planten",
    "sg:phone":"+31 226 421 466",
    "sg:postcode":"1738 JX",
    "sg:province":"Noord-Holland",
    "wof:name":"P.J. Smit",
    "wof:placetype":"venue"
},
  "geometry": {"coordinates":[4.839913,52.726402],"type":"Point"}
}