{
  "type": "Feature",
  "properties": {
    "addr:full":"Dorpsstraat 89 Bunschoten Spakenburg Utrecht 3751 EN",
    "addr:housenumber":"89",
    "addr:postcode":"3751 en",
    "addr:street":"Dorpsstraat",
    "iso:country":"NL",
    "sg:address":"Dorpsstraat 89",
    "sg:city":"Bunschoten Spakenburg",
    "sg:orig_category":"Boekhouders",
    "sg:phone":"+31 33 298 6444",
    "sg:postcode":"3751 EN",
    "sg:province":"Utrecht",
    "wof:name":"H. Van Renselaar",
    "wof:placetype":"venue"
},
  "geometry": {"coordinates":[5.373918,52.239799],"type":"Point"}
}