{
  "type": "Feature",
  "properties": {
    "iso:country":"NL",
    "sg:address":"Heerbaan 248A",
    "sg:city":"Breda",
    "sg:orig_category":"Administratie- En Boekhoudkantoren",
    "sg:phone":"+31 76 514 1114",
    "sg:postcode":"4817 NL",
    "sg:province":"Noord-Brabant",
    "wof:name":"Fidessa Services",
    "wof:placetype":"venue"
},
  "geometry": {"coordinates":[4.82116,51.5928],"type":"Point"}
}