{
  "type": "Feature",
  "properties": {
    "addr:full":"St Hubertusplaats 8 Tollebeek NL. 8309 AB",
    "addr:housenumber":"8",
    "addr:postcode":"8309 ab",
    "addr:street":"St Hubertusplaats;Nl.",
    "iso:country":"NL",
    "sg:address":"St Hubertusplaats 8",
    "sg:city":"Tollebeek",
    "sg:orig_category":"Partyservice",
    "sg:phone":"+31 527 651 333",
    "sg:postcode":"8309 AB",
    "sg:province":"NL.",
    "sg:website":"http://www.degoedeaanloop.nl",
    "wof:name":"Goede Aanloop, De",
    "wof:placetype":"venue"
},
  "geometry": {"coordinates":[5.680215,52.677723],"type":"Point"}
}