{
  "type": "Feature",
  "properties": {
    "addr:full":"Turbinestr 21A Veenendaal Utrecht 3903 LV",
    "addr:housenumber":"21a",
    "addr:postcode":"3903",
    "addr:street":"Turbinestr",
    "iso:country":"NL",
    "sg:address":"Turbinestr 21A",
    "sg:city":"Veenendaal",
    "sg:orig_category":"Wolgroothandel",
    "sg:phone":"+31 318 514 752",
    "sg:postcode":"3903 LV",
    "sg:province":"Utrecht",
    "wof:name":"Slot",
    "wof:placetype":"venue"
},
  "geometry": {"coordinates":[5.5696549416,52.0071258545],"type":"Point"}
}