{
  "type": "Feature",
  "properties": {
    "addr:full":"Gouwe 35 Hoogwoud North Holland 1718 LK",
    "addr:housenumber":"35",
    "addr:postcode":"1718 lk",
    "addr:street":"Gouwe",
    "iso:country":"NL",
    "sg:address":"Gouwe 35",
    "sg:city":"Hoogwoud",
    "sg:orig_category":"Boeken Antiquarische En Gebruikte",
    "sg:phone":"+31 229 582 472",
    "sg:postcode":"1718 LK",
    "sg:province":"North Holland",
    "wof:name":"Pallieter",
    "wof:placetype":"venue"
},
  "geometry": {"coordinates":[4.959836,52.731689],"type":"Point"}
}