{
  "type": "Feature",
  "properties": {
    "addr:full":"Beukelaar 28 Someren Noord-Brabant 5711 BL",
    "addr:housenumber":"28",
    "addr:postcode":"5711 bl",
    "addr:street":"Beukelaar",
    "iso:country":"NL",
    "sg:address":"Beukelaar 28",
    "sg:city":"Someren",
    "sg:orig_category":"Binnenhuisarchitecten",
    "sg:phone":"+31 493 496 230",
    "sg:postcode":"5711 BL",
    "sg:province":"Noord-Brabant",
    "wof:name":"Aki Interieurbouw",
    "wof:placetype":"venue"
},
  "geometry": {"coordinates":[5.718469,51.391144],"type":"Point"}
}