{
  "type": "Feature",
  "properties": {
    "addr:full":"M L Kingstr 3 Limbricht Limburg 6141 DA",
    "addr:housenumber":"3",
    "addr:postcode":"6141 da",
    "addr:street":"M;Kingstr",
    "iso:country":"NL",
    "sg:address":"M L Kingstr 3",
    "sg:city":"Limbricht",
    "sg:orig_category":"Verzekeringen - Verzekeringskantoren",
    "sg:phone":"+31 46 452 0294",
    "sg:postcode":"6141 DA",
    "sg:province":"Limburg",
    "wof:name":"Stoffels, P L M",
    "wof:placetype":"venue"
},
  "geometry": {"coordinates":[5.837232,51.011879],"type":"Point"}
}