{
  "type": "Feature",
  "properties": {
    "addr:full":"Bloemendalstr 5 Zwolle Overijssel 8011 PJ",
    "addr:housenumber":"5",
    "addr:postcode":"8011 pj",
    "addr:street":"Bloemendalstr",
    "iso:country":"NL",
    "sg:address":"Bloemendalstr 5",
    "sg:city":"Zwolle",
    "sg:orig_category":"Psychologen",
    "sg:phone":"+31 38 423 5885",
    "sg:postcode":"8011 PJ",
    "sg:province":"Overijssel",
    "wof:name":"Elf",
    "wof:placetype":"venue"
},
  "geometry": {"coordinates":[6.094001,52.510586],"type":"Point"}
}