{
  "type": "Feature",
  "properties": {
    "addr:full":"Kevelaerstraat 24 Weert Limburg 6002 BM",
    "addr:housenumber":"24",
    "addr:postcode":"6002 bm",
    "addr:street":"Kevelaerstraat",
    "iso:country":"NL",
    "sg:address":"Kevelaerstraat 24",
    "sg:city":"Weert",
    "sg:orig_category":"Naai- And Breimachines",
    "sg:phone":"+31 495 538 538",
    "sg:postcode":"6002 BM",
    "sg:province":"Limburg",
    "wof:name":"J.H.M. Broens",
    "wof:placetype":"venue"
},
  "geometry": {"coordinates":[5.686826,51.257874],"type":"Point"}
}