{
  "type": "Feature",
  "properties": {
    "addr:full":"Kerkstr 2B Landgraaf Limburg 6374 HK",
    "addr:housenumber":"2b",
    "addr:postcode":"6374 hk",
    "addr:street":"Kerkstr",
    "iso:country":"NL",
    "sg:address":"Kerkstr 2B",
    "sg:city":"Landgraaf",
    "sg:classifiers":[
        {
            "category":"Shopping",
            "subcategory":"Adult",
            "type":"Retail Goods"
        }
    ],
    "sg:phone":"+31 45 531 6065",
    "sg:postcode":"6374 HK",
    "sg:province":"Limburg",
    "sg:tags":[
        "lingerie",
        "en",
        "tricotage"
    ],
    "sg:website":"http://www.barbara.nl",
    "wof:name":"Barbara",
    "wof:placetype":"venue"
},
  "geometry": {"coordinates":[6.051468,50.916996],"type":"Point"}
}