{
  "type": "Feature",
  "properties": {
    "addr:full":"Chopinplein 1 Culemborg Gelderland 4102 CP",
    "addr:housenumber":"1",
    "addr:postcode":"4102 cp",
    "addr:street":"Chopinplein;Gelderland",
    "iso:country":"NL",
    "sg:address":"Chopinplein 1",
    "sg:city":"Culemborg",
    "sg:classifiers":[
        {
            "category":"Fast Food",
            "type":"Food & Drink"
        }
    ],
    "sg:phone":"+31 345 519 890",
    "sg:postcode":"4102 CP",
    "sg:province":"Gelderland",
    "sg:tags":[
        "afhaal",
        "restaurant"
    ],
    "wof:name":"Cafetaria De Vluchtheuvel",
    "wof:placetype":"venue"
},
  "geometry": {"coordinates":[5.237777,51.952549],"type":"Point"}
}