{
  "type": "Feature",
  "properties": {
    "iso:country":"NL",
    "sg:address":"Vossenpelssestr 39",
    "sg:city":"Lent",
    "sg:orig_category":"Psychotherapeuten",
    "sg:phone":"+31 24 323 7432",
    "sg:postcode":"6663 KE",
    "sg:province":"Gelderland",
    "wof:name":"Hofwegen-Hoppenbrouwers, J Van",
    "wof:placetype":"venue"
},
  "geometry": {"coordinates":[-77.241432,38.151344],"type":"Point"}
}