{
  "type": "Feature",
  "properties": {
    "addr:full":"Raadhuispln 47 Drachten Friesland 9203 CZ",
    "addr:housenumber":"47",
    "addr:postcode":"9203",
    "addr:street":"Raadhuispln",
    "iso:country":"NL",
    "sg:address":"Raadhuispln 47",
    "sg:city":"Drachten",
    "sg:orig_category":"Babyartikelen",
    "sg:phone":"+31 512 531 797",
    "sg:postcode":"9203 CZ",
    "sg:province":"Friesland",
    "wof:name":"Pr?natal",
    "wof:placetype":"venue"
},
  "geometry": {"coordinates":[6.098565,53.102871],"type":"Point"}
}