{
  "type": "Feature",
  "properties": {
    "addr:full":"Pancratiusstraat 22 Tubbergen NL.08 7651 BD",
    "addr:housenumber":"22;nl.08",
    "addr:postcode":"7651 bd",
    "addr:street":"Pancratiusstraat",
    "iso:country":"NL",
    "sg:address":"Pancratiusstraat 22",
    "sg:city":"Tubbergen",
    "sg:orig_category":"Artiestenbureaus",
    "sg:phone":"+31 546 622 238",
    "sg:postcode":"7651 BD",
    "sg:province":"NL.08",
    "wof:name":"Mardi Le Vingt",
    "wof:placetype":"venue"
},
  "geometry": {"coordinates":[6.787122,52.409264],"type":"Point"}
}