{
  "type": "Feature",
  "properties": {
    "addr:full":"De Pallert 6 Schoonebeek Drenthe 7761 BT",
    "addr:housenumber":"6",
    "addr:postcode":"7761 bt",
    "addr:street":"De Pallert",
    "iso:country":"NL",
    "sg:address":"De Pallert 6",
    "sg:city":"Schoonebeek",
    "sg:orig_category":"Postkantoren",
    "sg:phone":"+31 524 531 209",
    "sg:postcode":"7761 BT",
    "sg:province":"Drenthe",
    "sg:website":"http://www.postkantoor.nl",
    "wof:name":"Postkantoor",
    "wof:placetype":"venue"
},
  "geometry": {"coordinates":[6.882491,52.662228],"type":"Point"}
}