{
  "type": "Feature",
  "properties": {
    "addr:full":"Urkhovenseweg 108 Eindhoven Noord-Brabant 5641 KJ",
    "addr:housenumber":"108",
    "addr:postcode":"5641 kj",
    "addr:street":"Urkhovenseweg",
    "iso:country":"NL",
    "sg:address":"Urkhovenseweg 108",
    "sg:city":"Eindhoven",
    "sg:orig_category":"Artiesten",
    "sg:phone":"+31 40 281 2756",
    "sg:postcode":"5641 KJ",
    "sg:province":"Noord-Brabant",
    "wof:name":"Nel Verhoeven",
    "wof:placetype":"venue"
},
  "geometry": {"coordinates":[5.523801,51.445248],"type":"Point"}
}