{
  "type": "Feature",
  "properties": {
    "addr:full":"Spinolaberg 8 Halsteren Noord-Brabant 4661 RT",
    "addr:housenumber":"8",
    "addr:postcode":"4661 rt",
    "addr:street":"Spinolaberg",
    "iso:country":"NL",
    "sg:address":"Spinolaberg 8",
    "sg:city":"Halsteren",
    "sg:orig_category":"Verenigingen En Stichtingen",
    "sg:phone":"+31 164 688 068",
    "sg:postcode":"4661 RT",
    "sg:province":"Noord-Brabant",
    "wof:name":"Day By Day, Sticht",
    "wof:placetype":"venue"
},
  "geometry": {"coordinates":[4.268442,51.513855],"type":"Point"}
}