{
  "type": "Feature",
  "properties": {
    "addr:full":"Tulpstr 13 Hattem Gelderland 8051 CV",
    "addr:housenumber":"13",
    "addr:postcode":"8051 cv",
    "addr:street":"Tulpstr;Gelderland",
    "iso:country":"NL",
    "sg:address":"Tulpstr 13",
    "sg:city":"Hattem",
    "sg:orig_category":"Verenigingen En Stichtingen",
    "sg:phone":"+31 38 444 5746",
    "sg:postcode":"8051 CV",
    "sg:province":"Gelderland",
    "wof:name":"Dierenbescherming Afd Hattem",
    "wof:placetype":"venue"
},
  "geometry": {"coordinates":[6.073409,52.464104],"type":"Point"}
}