{
  "type": "Feature",
  "properties": {
    "iso:country":"NL",
    "sg:address":"Lenculenstr 11",
    "sg:city":"Maastricht",
    "sg:classifiers":[
        {
            "category":"Travel",
            "subcategory":"Hotels & Motels",
            "type":"Entertainment"
        }
    ],
    "sg:phone":"+31 6 53446341",
    "sg:postcode":"6211 KP",
    "sg:province":"Limburg",
    "wof:name":"Esperanto Domo",
    "wof:placetype":"venue"
},
  "geometry": {"coordinates":[5.689565,50.846695],"type":"Point"}
}