{
  "type": "Feature",
  "properties": {
    "addr:full":"Drouwenerstraat 1A Borger Drenthe 9531 JZ",
    "addr:housenumber":"1a",
    "addr:postcode":"9531 jz",
    "addr:street":"Drouwenerstraat",
    "iso:country":"NL",
    "sg:address":"Drouwenerstraat 1A",
    "sg:city":"Borger",
    "sg:orig_category":"Kappers",
    "sg:phone":"+31 599 238 103",
    "sg:postcode":"9531 JZ",
    "sg:province":"Drenthe",
    "wof:name":"J. Hovenkamp",
    "wof:placetype":"venue"
},
  "geometry": {"coordinates":[6.7894968987,52.9279556274],"type":"Point"}
}