{
  "type": "Feature",
  "properties": {
    "iso:country":"NL",
    "sg:address":"Kruisweg 19",
    "sg:city":"Thorn",
    "sg:orig_category":"Loodgieterswerk, Verwarming And Sanitaire Installaties",
    "sg:phone":"+31 475 563 037",
    "sg:postcode":"6017 CD",
    "sg:province":"Limburg",
    "wof:name":"Winkelmolen Serv. Onderhoud",
    "wof:placetype":"venue"
},
  "geometry": {"coordinates":[5.837974,51.165424],"type":"Point"}
}