{
  "type": "Feature",
  "properties": {
    "addr:full":"Ringdk Bov Polder 25 Amstelveen Noord-Holland 1188 WC",
    "addr:housenumber":"25",
    "addr:postcode":"1188 wc",
    "addr:street":"Bov Polder",
    "iso:country":"NL",
    "sg:address":"Ringdk Bov Polder 25",
    "sg:city":"Amstelveen",
    "sg:orig_category":"Verhuur",
    "sg:phone":"+31 297 582 346",
    "sg:postcode":"1188 WC",
    "sg:province":"Noord-Holland",
    "wof:name":"Schip, Van 'T",
    "wof:placetype":"venue"
},
  "geometry": {"coordinates":[4.874239,52.263988],"type":"Point"}
}