{
  "type": "Feature",
  "properties": {
    "iso:country":"NL",
    "sg:address":"F Vd Heydenstr 2",
    "sg:city":"Netersel",
    "sg:orig_category":"Wolartikelen En Breiwol",
    "sg:phone":"+31 497 682 309",
    "sg:postcode":"5534 AV",
    "sg:province":"Noord-Brabant",
    "wof:name":"Luffelen, Van",
    "wof:placetype":"venue"
},
  "geometry": {"coordinates":[6.657720089,46.5615501404],"type":"Point"}
}