{
  "type": "Feature",
  "properties": {
    "addr:full":"Nyverheidswg 30-36 Zeewolde NL. 3899 AJ",
    "addr:housenumber":"30-36",
    "addr:postcode":"3899 aj",
    "addr:street":"Nl.",
    "iso:country":"NL",
    "sg:address":"Nyverheidswg 30-36",
    "sg:city":"Zeewolde",
    "sg:orig_category":"Verhuur",
    "sg:phone":"+31 36 522 5666",
    "sg:postcode":"3899 AJ",
    "sg:province":"NL.",
    "wof:name":"All Two Twenty Bv",
    "wof:placetype":"venue"
},
  "geometry": {"coordinates":[5.50467,52.357269],"type":"Point"}
}