{
  "type": "Feature",
  "properties": {
    "addr:full":"Emmaberg 10 Valkenburg Lb Limburg 6301 ER",
    "addr:housenumber":"10",
    "addr:postcode":"lb;6301 er",
    "addr:street":"Emmaberg",
    "iso:country":"NL",
    "sg:address":"Emmaberg 10",
    "sg:city":"Valkenburg Lb",
    "sg:orig_category":"Medische Installaties En Instrumenten",
    "sg:phone":"+31 43 601 6445",
    "sg:postcode":"6301 ER",
    "sg:province":"Limburg",
    "wof:name":"Hueber",
    "wof:placetype":"venue"
},
  "geometry": {"coordinates":[5.843868,50.873383],"type":"Point"}
}