{
  "type": "Feature",
  "properties": {
    "addr:full":"J Vermeerstr 18 Amsterdam North Holland 1071 DR",
    "addr:housenumber":"18",
    "addr:postcode":"1071 dr",
    "iso:country":"NL",
    "sg:address":"J Vermeerstr 18",
    "sg:city":"Amsterdam",
    "sg:orig_category":"Marktonderzoekbureaus",
    "sg:phone":"+31 20 671 5536",
    "sg:postcode":"1071 DR",
    "sg:province":"North Holland",
    "wof:name":"Wolking Bv",
    "wof:placetype":"venue"
},
  "geometry": {"coordinates":[4.883602,52.356312],"type":"Point"}
}