{
  "type": "Feature",
  "properties": {
    "iso:country":"NL",
    "sg:address":"Korte Singel 4",
    "sg:city":"Bussum",
    "sg:orig_category":"Meubelreparatie And -Restauratie",
    "sg:phone":"+31 35 693 8020",
    "sg:postcode":"1402 SJ",
    "sg:province":"Noord-Holland",
    "wof:name":"R. Groenhuyzen",
    "wof:placetype":"venue"
},
  "geometry": {"coordinates":[5.170563,52.274132],"type":"Point"}
}