{
  "type": "Feature",
  "properties": {
    "iso:country":"NL",
    "sg:address":"Duitslandlaan 3",
    "sg:city":"Haarlem",
    "sg:classifiers":[
        {
            "category":"Education",
            "subcategory":"Preschool",
            "type":"Public Place"
        }
    ],
    "sg:phone":"+31 23 533 6358",
    "sg:postcode":"2034 BC",
    "sg:province":"North Holland",
    "sg:tags":[
        "kleuteronderwijs",
        "basis-"
    ],
    "wof:name":"T Peuterpandje",
    "wof:placetype":"venue"
},
  "geometry": {"coordinates":[4.644892,52.363773],"type":"Point"}
}