{
  "type": "Feature",
  "properties": {
    "addr:full":"Nieuwlandstr 8 Tilburg North Brabant 5038 SN",
    "addr:housenumber":"8",
    "addr:postcode":"5038 sn",
    "addr:street":"Nieuwlandstr",
    "iso:country":"NL",
    "sg:address":"Nieuwlandstr 8",
    "sg:city":"Tilburg",
    "sg:orig_category":"Kappers",
    "sg:phone":"+31 13 543 1555",
    "sg:postcode":"5038 SN",
    "sg:province":"North Brabant",
    "wof:name":"Faz",
    "wof:placetype":"venue"
},
  "geometry": {"coordinates":[5.0818748474,51.5570983887],"type":"Point"}
}