{
  "type": "Feature",
  "properties": {
    "iso:country":"NL",
    "sg:address":"Bevelandselaan 69",
    "sg:city":"Amstelveen",
    "sg:orig_category":"Werving And Selectie Van Vast Personeel",
    "sg:phone":"+31 6 51172951",
    "sg:postcode":"1181 JM",
    "sg:province":"Noord-Holland",
    "wof:name":"Interlock",
    "wof:placetype":"venue"
},
  "geometry": {"coordinates":[4.8670549393,52.3146057129],"type":"Point"}
}