{
  "type": "Feature",
  "properties": {
    "addr:full":"Strevelswg 7274 Rotterdam South Holland 3075 AM",
    "addr:housenumber":"7274",
    "addr:postcode":"3075",
    "iso:country":"NL",
    "sg:address":"Strevelswg 7274",
    "sg:city":"Rotterdam",
    "sg:orig_category":"Fietsen En Bromfietsen",
    "sg:phone":"+31 10 485 6486",
    "sg:postcode":"3075 AM",
    "sg:province":"South Holland",
    "wof:name":"Jonkers, C",
    "wof:placetype":"venue"
},
  "geometry": {"coordinates":[4.49568,51.88937],"type":"Point"}
}