{
  "type": "Feature",
  "properties": {
    "addr:full":"Apolloweg 15 Moerdijk North Brabant 4782 SB",
    "addr:housenumber":"15",
    "addr:postcode":"4782 sb",
    "addr:street":"Apolloweg",
    "iso:country":"NL",
    "sg:address":"Apolloweg 15",
    "sg:city":"Moerdijk",
    "sg:classifiers":[
        {
            "category":"Parking",
            "subcategory":"Lot",
            "type":"Transportation"
        }
    ],
    "sg:phone":"+31 168 384 110",
    "sg:postcode":"4782 SB",
    "sg:province":"North Brabant",
    "sg:tags":[
        "fab",
        "metalen",
        "tank"
    ],
    "wof:name":"Fabricom Piping Bv",
    "wof:placetype":"venue"
},
  "geometry": {"coordinates":[4.605904,51.689396],"type":"Point"}
}