{
  "type": "Feature",
  "properties": {
    "addr:full":"Scheepswerf 19 Leidschendam Zuid-Holland 2265 BE",
    "addr:housenumber":"19",
    "addr:postcode":"2265",
    "addr:street":"Scheepswerf",
    "iso:country":"NL",
    "sg:address":"Scheepswerf 19",
    "sg:city":"Leidschendam",
    "sg:orig_category":"Verenigingen En Stichtingen",
    "sg:phone":"+31 70 320 0115",
    "sg:postcode":"2265 BE",
    "sg:province":"Zuid-Holland",
    "wof:name":"Swl Servicebur Welzijn Leidschendam, Sticht",
    "wof:placetype":"venue"
},
  "geometry": {"coordinates":[4.395367,52.080143],"type":"Point"}
}