{
  "type": "Feature",
  "properties": {
    "iso:country":"NL",
    "sg:address":"Vredebestlaan 7A",
    "sg:city":"Poeldijk",
    "sg:orig_category":"Begrafenisondernemers",
    "sg:phone":"+31 174 247 749",
    "sg:postcode":"2685 AJ",
    "sg:province":"Zuid-Holland",
    "wof:name":"Uitvaartverzorging Poeldijk",
    "wof:placetype":"venue"
},
  "geometry": {"coordinates":[4.210842,52.023842],"type":"Point"}
}