{
  "type": "Feature",
  "properties": {
    "addr:full":"Zadelmakersstraat 7 Sneek Friesland 8601 WH",
    "addr:housenumber":"7",
    "addr:postcode":"8601 wh",
    "addr:street":"Zadelmakersstraat",
    "iso:country":"NL",
    "sg:address":"Zadelmakersstraat 7",
    "sg:city":"Sneek",
    "sg:orig_category":"Zuivelproducten And Spijsoli?n Gh",
    "sg:phone":"+31 515 412 748",
    "sg:postcode":"8601 WH",
    "sg:province":"Friesland",
    "wof:name":"Firma W. Bakker & Zonen",
    "wof:placetype":"venue"
},
  "geometry": {"coordinates":[5.632574,53.03001],"type":"Point"}
}