{
  "type": "Feature",
  "properties": {
    "addr:full":"Albinonistraat 75 Boxtel Noord-Brabant 5283 KL",
    "addr:housenumber":"75",
    "addr:postcode":"5283 kl",
    "addr:street":"Albinonistraat",
    "iso:country":"NL",
    "sg:address":"Albinonistraat 75",
    "sg:city":"Boxtel",
    "sg:orig_category":"Paramedische Behandelingen",
    "sg:phone":"+31 411 682 199",
    "sg:postcode":"5283 KL",
    "sg:province":"Noord-Brabant",
    "wof:name":"J C A Mestrum - Stamps",
    "wof:placetype":"venue"
},
  "geometry": {"coordinates":[5.343081,51.584202],"type":"Point"}
}