{
  "type": "Feature",
  "properties": {
    "addr:full":"Pluto 11 Hapert Noord-Brabant 5527 CE",
    "addr:housenumber":"11",
    "addr:postcode":"5527 ce",
    "addr:street":"Pluto",
    "iso:country":"NL",
    "sg:address":"Pluto 11",
    "sg:city":"Hapert",
    "sg:orig_category":"Technische Studies And Onderzoek",
    "sg:phone":"+31 497 382 871",
    "sg:postcode":"5527 CE",
    "sg:province":"Noord-Brabant",
    "wof:name":"J. Van Stam Advies",
    "wof:placetype":"venue"
},
  "geometry": {"coordinates":[5.260587,51.365742],"type":"Point"}
}