{
  "type": "Feature",
  "properties": {
    "addr:full":"Ltm Wg 123 Heerlen Limburg 6412 BS",
    "addr:housenumber":"123",
    "addr:postcode":"6412 bs",
    "addr:street":"Wg",
    "iso:country":"NL",
    "sg:address":"Ltm Wg 123",
    "sg:city":"Heerlen",
    "sg:orig_category":"Scholen Voor Basisonderwijs",
    "sg:phone":"+31 45 561 0145",
    "sg:postcode":"6412 BS",
    "sg:province":"Limburg",
    "wof:name":"Arsschool Sbo, Pastoor Van",
    "wof:placetype":"venue"
},
  "geometry": {"coordinates":[5.977281,50.89526],"type":"Point"}
}