{
  "type": "Feature",
  "properties": {
    "iso:country":"NL",
    "sg:address":"Nw Boschstr 40",
    "sg:city":"Breda",
    "sg:orig_category":"Verzekeringen - Verzekeringskantoren",
    "sg:phone":"+31 76 541 9009",
    "sg:postcode":"4811 CZ",
    "sg:province":"North Brabant",
    "wof:name":"Westen, Van Der",
    "wof:placetype":"venue"
},
  "geometry": {"coordinates":[4.787639,51.592529],"type":"Point"}
}