{
  "type": "Feature",
  "properties": {
    "iso:country":"NL",
    "sg:address":"Baarderbuorren 18",
    "sg:city":"Arum",
    "sg:orig_category":"Loonbedrijven",
    "sg:phone":"+31 517 641 550",
    "sg:postcode":"8822 WR",
    "sg:province":"Provincie Friesland",
    "wof:name":"Westra Bv, M",
    "wof:placetype":"venue"
},
  "geometry": {"coordinates":[5.48776,53.12603],"type":"Point"}
}