{
  "type": "Feature",
  "properties": {
    "iso:country":"NL",
    "sg:address":"Javastraat 56",
    "sg:city":"Hengelo Ov",
    "sg:orig_category":"Makelaars In Onroerend Goed",
    "sg:phone":"+31 74 291 1365",
    "sg:postcode":"7556 SH",
    "sg:province":"NL.08",
    "wof:name":"G.M. Slosser",
    "wof:placetype":"venue"
},
  "geometry": {"coordinates":[6.783526,52.266872],"type":"Point"}
}