{
  "type": "Feature",
  "properties": {
    "addr:full":"Briljant 43 Eindhoven North Brabant 5629 HE",
    "addr:housenumber":"43",
    "addr:postcode":"5629 he",
    "addr:street":"Briljant",
    "iso:country":"NL",
    "sg:address":"Briljant 43",
    "sg:city":"Eindhoven",
    "sg:orig_category":"Meubelen - Fabrieken En Groothandel",
    "sg:phone":"+31 40 241 4959",
    "sg:postcode":"5629 HE",
    "sg:province":"North Brabant",
    "wof:name":"Smulders, P H M",
    "wof:placetype":"venue"
},
  "geometry": {"coordinates":[5.464124,51.488056],"type":"Point"}
}