{
  "type": "Feature",
  "properties": {
    "iso:country":"NL",
    "sg:address":"Verl Bladderswijk Wz 4",
    "sg:city":"Klazienaveen",
    "sg:orig_category":"Autokeuringen",
    "sg:phone":"+31 591 316 060",
    "sg:postcode":"7891 AM",
    "sg:province":"Drenthe",
    "wof:name":"Autohandel M. De Hoog",
    "wof:placetype":"venue"
},
  "geometry": {"coordinates":[6.968661,52.723366],"type":"Point"}
}