{
  "type": "Feature",
  "properties": {
    "addr:full":"Papenvoort 1 Geldrop Noord-Brabant 5663 AC",
    "addr:housenumber":"1",
    "addr:postcode":"5663 ac",
    "addr:street":"Papenvoort",
    "iso:country":"NL",
    "sg:address":"Papenvoort 1",
    "sg:city":"Geldrop",
    "sg:orig_category":"Overheidsdiensten",
    "sg:phone":"+31 40 285 8778",
    "sg:postcode":"5663 AC",
    "sg:province":"Noord-Brabant",
    "wof:name":"Stichting Gemeenschapshuis Zesgehuchten",
    "wof:placetype":"venue"
},
  "geometry": {"coordinates":[5.5418720245,51.4183578491],"type":"Point"}
}