{
  "type": "Feature",
  "properties": {
    "iso:country":"NL",
    "sg:address":"Hollanderstraat 8",
    "sg:city":"'S Gravenhage",
    "sg:orig_category":"Schilderwerk",
    "sg:phone":"+31 70 345 0280",
    "sg:postcode":"2517 HK",
    "sg:province":"Zuid-Holland",
    "wof:name":"Schildersbedrijf J. Van Loenen",
    "wof:placetype":"venue"
},
  "geometry": {"coordinates":[4.283194,52.084396],"type":"Point"}
}