{
  "type": "Feature",
  "properties": {
    "iso:country":"NL",
    "sg:address":"H Tollensdreef 32",
    "sg:city":"Goirle",
    "sg:orig_category":"Directmail",
    "sg:phone":"+31 13 534 8401",
    "sg:postcode":"5051 MX",
    "sg:province":"Noord-Brabant",
    "wof:name":"Teletrain Consult",
    "wof:placetype":"venue"
},
  "geometry": {"coordinates":[5.078048,51.530159],"type":"Point"}
}