{
  "type": "Feature",
  "properties": {
    "iso:country":"NL",
    "sg:address":"Vuurdoornlaan 18",
    "sg:city":"Ridderkerk",
    "sg:classifiers":[
        {
            "category":"Professional",
            "subcategory":"Accounting & Tax Preparation",
            "type":"Services"
        }
    ],
    "sg:phone":"+31 180 414 051",
    "sg:postcode":"2982 BZ",
    "sg:province":"South Holland",
    "sg:tags":[
        "accountant"
    ],
    "wof:name":"Accountantskantoor Hordijk",
    "wof:placetype":"venue"
},
  "geometry": {"coordinates":[4.587912,51.871887],"type":"Point"}
}