{
  "type": "Feature",
  "properties": {
    "addr:full":"De Plataan 79 Didam Gelderland 6942 TX",
    "addr:housenumber":"79",
    "addr:postcode":"6942",
    "addr:street":"De Plataan;Gelderland",
    "iso:country":"NL",
    "sg:address":"De Plataan 79",
    "sg:city":"Didam",
    "sg:orig_category":"Verenigingen En Stichtingen",
    "sg:phone":"+31 316 227 987",
    "sg:postcode":"6942 TX",
    "sg:province":"Gelderland",
    "wof:name":"Pelita",
    "wof:placetype":"venue"
},
  "geometry": {"coordinates":[6.133926,51.946957],"type":"Point"}
}