{
  "type": "Feature",
  "properties": {
    "iso:country":"NL",
    "sg:address":"Hamarpln 2",
    "sg:city":"Belfeld",
    "sg:orig_category":"Verenigingsgebouwen",
    "sg:phone":"+31 77 475 1960",
    "sg:postcode":"5951 CD",
    "sg:province":"Limburg",
    "wof:name":"Hamar, De",
    "wof:placetype":"venue"
},
  "geometry": {"coordinates":[6.114772,51.310501],"type":"Point"}
}