{
  "type": "Feature",
  "properties": {
    "addr:full":"Tuinstr 79 Veenendaal Utrecht 3901 RA",
    "addr:housenumber":"79",
    "addr:postcode":"3901 ra",
    "addr:street":"Tuinstr",
    "iso:country":"NL",
    "sg:address":"Tuinstr 79",
    "sg:city":"Veenendaal",
    "sg:orig_category":"Fotoreportages",
    "sg:phone":"+31 318 553 221",
    "sg:postcode":"3901 RA",
    "sg:province":"Utrecht",
    "sg:website":"http://www.abfoto.nl",
    "wof:name":"Annemarie Bakker, Fotografie",
    "wof:placetype":"venue"
},
  "geometry": {"coordinates":[5.556413,52.026375],"type":"Point"}
}