{
  "type": "Feature",
  "properties": {
    "iso:country":"NL",
    "sg:address":"Eschwg 1",
    "sg:city":"Bentelo",
    "sg:orig_category":"Pluimveebedrijven En -Handelaren",
    "sg:phone":"+31 547 292 313",
    "sg:postcode":"7497 NJ",
    "sg:province":"Overijssel",
    "wof:name":"Broekkamp, H G M",
    "wof:placetype":"venue"
},
  "geometry": {"coordinates":[6.67261,52.212879],"type":"Point"}
}