{
  "type": "Feature",
  "properties": {
    "addr:full":"Weesperzijde 80/Hs A Amsterdam North Holland 1091 EJ",
    "addr:housenumber":"80 / hs a",
    "addr:postcode":"1091 ej",
    "addr:street":"Weesperzijde",
    "iso:country":"NL",
    "sg:address":"Weesperzijde 80/Hs A",
    "sg:city":"Amsterdam",
    "sg:orig_category":"Fotostudio'S And Fotografen",
    "sg:phone":"+31 20 663 2025",
    "sg:postcode":"1091 EJ",
    "sg:province":"North Holland",
    "wof:name":"M. Ferron",
    "wof:placetype":"venue"
},
  "geometry": {"coordinates":[4.91306,52.35487],"type":"Point"}
}