{
  "type": "Feature",
  "properties": {
    "addr:full":"Knapheidewg 12 Groesbeek Gelderland 6562 DT",
    "addr:housenumber":"12",
    "addr:postcode":"6562 dt",
    "addr:street":"Knapheidewg;Gelderland",
    "iso:country":"NL",
    "sg:address":"Knapheidewg 12",
    "sg:city":"Groesbeek",
    "sg:orig_category":"Adviesbureaus Bouwkunde",
    "sg:phone":"+31 24 397 0965",
    "sg:postcode":"6562 DT",
    "sg:province":"Gelderland",
    "wof:name":"Wb Bouwk Teken- & Adviesbureau",
    "wof:placetype":"venue"
},
  "geometry": {"coordinates":[5.930462,51.765865],"type":"Point"}
}