{
  "type": "Feature",
  "properties": {
    "iso:country":"NL",
    "sg:address":"Hoofdstr 6",
    "sg:city":"Schimmert",
    "sg:orig_category":"Banken",
    "sg:phone":"+31 45 560 1727",
    "sg:postcode":"6333 BJ",
    "sg:province":"Limburg",
    "sg:website":"http://www.rabobank.nl",
    "wof:name":"Rabobank",
    "wof:placetype":"venue"
},
  "geometry": {"coordinates":[5.823024,50.900494],"type":"Point"}
}