{
  "type": "Feature",
  "properties": {
    "addr:full":"Broek 4 Holthees Noord-Brabant 5824 AC",
    "addr:housenumber":"4",
    "addr:postcode":"5824 ac",
    "addr:street":"Broek",
    "iso:country":"NL",
    "sg:address":"Broek 4",
    "sg:city":"Holthees",
    "sg:orig_category":"Administratie- En Boekhoudkantoren",
    "sg:phone":"+31 478 639 000",
    "sg:postcode":"5824 AC",
    "sg:province":"Noord-Brabant",
    "wof:name":"Datax Bv",
    "wof:placetype":"venue"
},
  "geometry": {"coordinates":[6.006589,51.572067],"type":"Point"}
}