{
  "type": "Feature",
  "properties": {
    "addr:full":"Gen Dibbetsln 69 Eindhoven Noord-Brabant 5623 JM",
    "addr:housenumber":"69",
    "addr:postcode":"5623 jm",
    "iso:country":"NL",
    "sg:address":"Gen Dibbetsln 69",
    "sg:city":"Eindhoven",
    "sg:orig_category":"Wijnkoperijen En -Groothandel",
    "sg:phone":"+31 6 51361593",
    "sg:postcode":"5623 JM",
    "sg:province":"Noord-Brabant",
    "sg:website":"http://www.wijnpost.nl",
    "wof:name":"Wijnpost",
    "wof:placetype":"venue"
},
  "geometry": {"coordinates":[5.4770798683,51.4600410461],"type":"Point"}
}