{
  "type": "Feature",
  "properties": {
    "iso:country":"NL",
    "sg:address":"Nieuwlandstraat 2",
    "sg:city":"Tilburg",
    "sg:orig_category":"Damesmodezaken",
    "sg:phone":"+31 13 542 1186",
    "sg:postcode":"5038 SN",
    "sg:province":"Noord-Brabant",
    "wof:name":"Modehuis Kollau Bv",
    "wof:placetype":"venue"
},
  "geometry": {"coordinates":[5.081713,51.557274],"type":"Point"}
}