{
  "type": "Feature",
  "properties": {
    "addr:full":"Nieuwlandstraat 2 Tilburg Noord-Brabant 5038 SN",
    "addr:housenumber":"2",
    "addr:postcode":"5038 sn",
    "addr:street":"Nieuwlandstraat",
    "iso:country":"NL",
    "sg:address":"Nieuwlandstraat 2",
    "sg:city":"Tilburg",
    "sg:orig_category":"Damesmodezaken",
    "sg:phone":"+31 13 542 1186",
    "sg:postcode":"5038 SN",
    "sg:province":"Noord-Brabant",
    "wof:name":"Modehuis Kollau Bv",
    "wof:placetype":"venue"
},
  "geometry": {"coordinates":[5.081713,51.557274],"type":"Point"}
}