{
  "type": "Feature",
  "properties": {
    "addr:full":"De Ibis 12A Almelo NL.08 7609 ES",
    "addr:housenumber":"12a;nl.08",
    "addr:postcode":"7609 es",
    "addr:street":"De Ibis",
    "iso:country":"NL",
    "sg:address":"De Ibis 12A",
    "sg:city":"Almelo",
    "sg:orig_category":"Metaalwerken",
    "sg:phone":"+31 546 825 131",
    "sg:postcode":"7609 ES",
    "sg:province":"NL.08",
    "wof:name":"H.D. Bekke",
    "wof:placetype":"venue"
},
  "geometry": {"coordinates":[6.628005,52.333168],"type":"Point"}
}