{
  "type": "Feature",
  "properties": {
    "addr:full":"Echterstraat 44 Echt Limburg 6102 ET",
    "addr:housenumber":"44",
    "addr:postcode":"6102 et",
    "addr:street":"Echterstraat",
    "iso:country":"NL",
    "sg:address":"Echterstraat 44",
    "sg:city":"Echt",
    "sg:orig_category":"Vloer- And Wandbedekkingen",
    "sg:phone":"+31 475 484 292",
    "sg:postcode":"6102 ET",
    "sg:province":"Limburg",
    "wof:name":"Bestratingsbedrijf Maurice Renet",
    "wof:placetype":"venue"
},
  "geometry": {"coordinates":[5.892796,51.103806],"type":"Point"}
}