{
  "type": "Feature",
  "properties": {
    "addr:full":"Eindhovenseweg 64 Waalre Noord-Brabant 5582 HV",
    "addr:housenumber":"64",
    "addr:postcode":"5582 hv",
    "addr:street":"Eindhovenseweg",
    "iso:country":"NL",
    "sg:address":"Eindhovenseweg 64",
    "sg:city":"Waalre",
    "sg:orig_category":"Kappers",
    "sg:phone":"+31 40 221 6624",
    "sg:postcode":"5582 HV",
    "sg:province":"Noord-Brabant",
    "wof:name":"Marijke Van Melis",
    "wof:placetype":"venue"
},
  "geometry": {"coordinates":[5.476743,51.395615],"type":"Point"}
}