{
  "type": "Feature",
  "properties": {
    "addr:full":"Achter Sint Pieter 9 Utrecht Utrecht 3512 HP",
    "addr:housenumber":"9",
    "addr:postcode":"3512 hp",
    "addr:street":"Achter Sint Pieter",
    "iso:country":"NL",
    "sg:address":"Achter Sint Pieter 9",
    "sg:city":"Utrecht",
    "sg:orig_category":"Bedrijfs- And Managementsconsultants",
    "sg:phone":"+31 30 230 0699",
    "sg:postcode":"3512 HP",
    "sg:province":"Utrecht",
    "wof:name":"Bpi Advies",
    "wof:placetype":"venue"
},
  "geometry": {"coordinates":[5.12301,52.091686],"type":"Point"}
}