{
  "type": "Feature",
  "properties": {
    "addr:full":"Grt Hond Ring 20 Dordrecht South Holland 3328 HH",
    "addr:housenumber":"20",
    "addr:postcode":"3328 hh",
    "addr:street":"Hond Ring",
    "iso:country":"NL",
    "sg:address":"Grt Hond Ring 20",
    "sg:city":"Dordrecht",
    "sg:orig_category":"Scholen Voor Basisonderwijs",
    "sg:phone":"+31 78 617 2065",
    "sg:postcode":"3328 HH",
    "sg:province":"South Holland",
    "wof:name":"Driehoek, De",
    "wof:placetype":"venue"
},
  "geometry": {"coordinates":[4.684603,51.779751],"type":"Point"}
}