{
  "type": "Feature",
  "properties": {
    "iso:country":"NL",
    "sg:address":"Grootgenhouterstraat 122",
    "sg:city":"Beek Lb",
    "sg:orig_category":"Boekhouders",
    "sg:phone":"+31 46 436 0820",
    "sg:postcode":"6191 NW",
    "sg:province":"Limburg",
    "wof:name":"Admi Octopus",
    "wof:placetype":"venue"
},
  "geometry": {"coordinates":[6.18361,51.222759],"type":"Point"}
}