{
  "type": "Feature",
  "properties": {
    "iso:country":"NL",
    "sg:address":"Stompekamperweg 19",
    "sg:city":"Ede Gld",
    "sg:orig_category":"Kappers",
    "sg:phone":"+31 318 615 881",
    "sg:postcode":"6711 BJ",
    "sg:province":"Gelderland",
    "wof:name":"J De Kruyff",
    "wof:placetype":"venue"
},
  "geometry": {"coordinates":[5.6686310768,52.0501213074],"type":"Point"}
}