{
  "type": "Feature",
  "properties": {
    "addr:full":"Voordk 61 Vlijmen North Brabant 5251 VE",
    "addr:housenumber":"61",
    "addr:postcode":"5251",
    "addr:street":"Voordk;Ve",
    "iso:country":"NL",
    "sg:address":"Voordk 61",
    "sg:city":"Vlijmen",
    "sg:orig_category":"Organisatiebureaus",
    "sg:phone":"+31 73 511 5967",
    "sg:postcode":"5251 VE",
    "sg:province":"North Brabant",
    "wof:name":"Walco",
    "wof:placetype":"venue"
},
  "geometry": {"coordinates":[5.2232117653,51.7093200684],"type":"Point"}
}