{
  "type": "Feature",
  "properties": {
    "addr:full":"Beetsstr 200 S Gravenhage South Holland 2524 RE",
    "addr:housenumber":"200",
    "addr:postcode":"2524 re",
    "addr:street":"S Gravenhage",
    "iso:country":"NL",
    "sg:address":"Beetsstr 200",
    "sg:city":"S Gravenhage",
    "sg:orig_category":"Verenigingsgebouwen",
    "sg:phone":"+31 70 394 8958",
    "sg:postcode":"2524 RE",
    "sg:province":"South Holland",
    "wof:name":"Framboos Buurtcentr, De",
    "wof:placetype":"venue"
},
  "geometry": {"coordinates":[4.31538,52.052422],"type":"Point"}
}