{
  "type": "Feature",
  "properties": {
    "addr:full":"Past Elsenstr 53 Helmond Noord-Brabant 5706 VM",
    "addr:housenumber":"53",
    "addr:postcode":"5706 vm",
    "iso:country":"NL",
    "sg:address":"Past Elsenstr 53",
    "sg:city":"Helmond",
    "sg:orig_category":"Voegwerken",
    "sg:phone":"+31 492 533 063",
    "sg:postcode":"5706 VM",
    "sg:province":"Noord-Brabant",
    "wof:name":"Laar, M L Van De",
    "wof:placetype":"venue"
},
  "geometry": {"coordinates":[5.639363,51.467506],"type":"Point"}
}