{
  "type": "Feature",
  "properties": {
    "iso:country":"NL",
    "sg:address":"Burg Molenaarhoeven 115",
    "sg:city":"Rosmalen",
    "sg:classifiers":[
        {
            "category":"Communications",
            "subcategory":"Television Station",
            "type":"Services"
        }
    ],
    "sg:phone":"+31 73 521 4101",
    "sg:postcode":"5244 JL",
    "sg:province":"Noord-Brabant",
    "sg:tags":[
        "video",
        "audio",
        "verhuur"
    ],
    "wof:name":"Videotheek Maasland",
    "wof:placetype":"venue"
},
  "geometry": {"coordinates":[5.383299,51.715466],"type":"Point"}
}