{
  "type": "Feature",
  "properties": {
    "addr:full":"Burg Molenaarhoeven 115 Rosmalen Noord-Brabant 5244 JL",
    "addr:housenumber":"115",
    "addr:postcode":"5244 jl",
    "addr:street":"Burg Molenaarhoeven",
    "iso:country":"NL",
    "sg:address":"Burg Molenaarhoeven 115",
    "sg:city":"Rosmalen",
    "sg:classifiers":[
        {
            "category":"Communications",
            "subcategory":"Television Station",
            "type":"Services"
        }
    ],
    "sg:phone":"+31 73 521 4101",
    "sg:postcode":"5244 JL",
    "sg:province":"Noord-Brabant",
    "sg:tags":[
        "video",
        "audio",
        "verhuur"
    ],
    "wof:name":"Videotheek Maasland",
    "wof:placetype":"venue"
},
  "geometry": {"coordinates":[5.383299,51.715466],"type":"Point"}
}