{
  "type": "Feature",
  "properties": {
    "addr:full":"Oude Naarderwg 21 Laren Nh North Holland 1251 BJ",
    "addr:housenumber":"21",
    "addr:postcode":"1251 bj",
    "addr:street":"Oude Naarderwg;Nh North",
    "iso:country":"NL",
    "sg:address":"Oude Naarderwg 21",
    "sg:city":"Laren Nh",
    "sg:orig_category":"Onderhoudswerken",
    "sg:phone":"+31 35 538 9041",
    "sg:postcode":"1251 BJ",
    "sg:province":"North Holland",
    "wof:name":"Schrijver",
    "wof:placetype":"venue"
},
  "geometry": {"coordinates":[5.222036,52.261185],"type":"Point"}
}