{
  "type": "Feature",
  "properties": {
    "addr:full":"Kardinaal De Jongsingel 15 'S Hertogenbosch Noord-Brabant 5224 HR",
    "addr:housenumber":"15",
    "addr:postcode":"5224 hr",
    "addr:street":"Kardinaal De Jongsingel;' S",
    "iso:country":"NL",
    "sg:address":"Kardinaal De Jongsingel 15",
    "sg:city":"'S Hertogenbosch",
    "sg:orig_category":"Verzekeringen",
    "sg:phone":"+31 73 621 5952",
    "sg:postcode":"5224 HR",
    "sg:province":"Noord-Brabant",
    "wof:name":"Assurantiekantoor Frerichs",
    "wof:placetype":"venue"
},
  "geometry": {"coordinates":[5.25819,51.698048],"type":"Point"}
}