{
  "type": "Feature",
  "properties": {
    "iso:country":"NL",
    "sg:address":"Postbus 29",
    "sg:city":"Beltrum",
    "sg:orig_category":"Scholen Voor Basisonderwijs",
    "sg:phone":"+31 544 481 517",
    "sg:postcode":"7156 ZG",
    "sg:province":"Gelderland",
    "wof:name":"Tweespan Rk Jenaplan, Het",
    "wof:placetype":"venue"
},
  "geometry": {"coordinates":[6.563325,52.067696],"type":"Point"}
}