{
  "type": "Feature",
  "properties": {
    "addr:full":"Bilderdykstr 11 Amsterdam North Holland 1052 NA",
    "addr:housenumber":"11",
    "addr:postcode":"1052 na",
    "addr:street":"Bilderdykstr",
    "iso:country":"NL",
    "sg:address":"Bilderdykstr 11",
    "sg:city":"Amsterdam",
    "sg:orig_category":"Vertaalbureaus",
    "sg:phone":"+31 20 685 5704",
    "sg:postcode":"1052 NA",
    "sg:province":"North Holland",
    "wof:name":"Midas",
    "wof:placetype":"venue"
},
  "geometry": {"coordinates":[4.87124,52.372078],"type":"Point"}
}