{
  "type": "Feature",
  "properties": {
    "iso:country":"NL",
    "sg:address":"Vondelweg 14",
    "sg:city":"Haarlem",
    "sg:orig_category":"Diverse Bedrijfsinstallaties Gh",
    "sg:phone":"+31 23 531 6813",
    "sg:postcode":"2025 AA",
    "sg:province":"Noord-Holland",
    "wof:name":"Calcon Trading",
    "wof:placetype":"venue"
},
  "geometry": {"coordinates":[4.656419,52.406231],"type":"Point"}
}