{
  "type": "Feature",
  "properties": {
    "addr:full":"Krimwg 63 Hoenderloo Gelderland 7351 AV",
    "addr:housenumber":"63;7351",
    "addr:postcode":"av",
    "addr:street":"Krimwg;Gelderland",
    "iso:country":"NL",
    "sg:address":"Krimwg 63",
    "sg:city":"Hoenderloo",
    "sg:orig_category":"Onderhoudswerken",
    "sg:phone":"+31 55 378 1155",
    "sg:postcode":"7351 AV",
    "sg:province":"Gelderland",
    "wof:name":"Ekas, Edwin",
    "wof:placetype":"venue"
},
  "geometry": {"coordinates":[5.88726,52.11935],"type":"Point"}
}