{
  "type": "Feature",
  "properties": {
    "addr:full":"Lagoenstraat 1 Almere Flevoland 1317 BM",
    "addr:housenumber":"1",
    "addr:postcode":"1317 bm",
    "addr:street":"Lagoenstraat;Flevoland",
    "iso:country":"NL",
    "sg:address":"Lagoenstraat 1",
    "sg:city":"Almere",
    "sg:orig_category":"Architecten",
    "sg:phone":"+31 36 533 2540",
    "sg:postcode":"1317 BM",
    "sg:province":"Flevoland",
    "wof:name":"Bouwtechnisch Adviesburo Arthur E De Gro",
    "wof:placetype":"venue"
},
  "geometry": {"coordinates":[5.229897,52.389023],"type":"Point"}
}