{
  "type": "Feature",
  "properties": {
    "iso:country":"NL",
    "sg:address":"Roland Holststraat 16",
    "sg:city":"Breda",
    "sg:classifiers":[
        {
            "category":"Education",
            "subcategory":"Preschool",
            "type":"Public Place"
        }
    ],
    "sg:phone":"+31 76 530 0006",
    "sg:postcode":"4819 HR",
    "sg:province":"Noord-Brabant",
    "sg:tags":[
        "kleuteronderwijs",
        "basis-"
    ],
    "wof:name":"Basisschool Petrus En Paulus",
    "wof:placetype":"venue"
},
  "geometry": {"coordinates":[4.767493,51.576218],"type":"Point"}
}