{
  "type": "Feature",
  "properties": {
    "addr:full":"Ohmstr 8 Ede Gld Gelderland 6716 BB",
    "addr:housenumber":"8",
    "addr:postcode":"6716 bb",
    "addr:street":"Ohmstr;Gld Gelderland",
    "iso:country":"NL",
    "sg:address":"Ohmstr 8",
    "sg:city":"Ede Gld",
    "sg:orig_category":"Heftrucks",
    "sg:phone":"+31 318 624 499",
    "sg:postcode":"6716 BB",
    "sg:province":"Gelderland",
    "sg:website":"http://www.staalheftrucks.nl",
    "wof:name":"Staal Heftruck Service",
    "wof:placetype":"venue"
},
  "geometry": {"coordinates":[5.629227,52.031624],"type":"Point"}
}