{
  "type": "Feature",
  "properties": {
    "iso:country":"NL",
    "sg:address":"K De Groteln 345",
    "sg:city":"Eindhoven",
    "sg:orig_category":"Verenigingen En Stichtingen",
    "sg:phone":"+31 40 293 2327",
    "sg:postcode":"5654 NN",
    "sg:province":"North Brabant",
    "sg:website":"http://www.indian-dylan.nl",
    "wof:name":"Indian Dylan",
    "wof:placetype":"venue"
},
  "geometry": {"coordinates":[5.45901,51.420891],"type":"Point"}
}