{
  "type": "Feature",
  "properties": {
    "addr:full":"Zonnedauw 107 Tiel Gelderland 4007 VD",
    "addr:housenumber":"107",
    "addr:postcode":"4007 vd",
    "addr:street":"Zonnedauw;Gelderland",
    "iso:country":"NL",
    "sg:address":"Zonnedauw 107",
    "sg:city":"Tiel",
    "sg:orig_category":"Video - Faciliteiten En Producties",
    "sg:phone":"+31 344 682 097",
    "sg:postcode":"4007 VD",
    "sg:province":"Gelderland",
    "wof:name":"Dick Van Empel Media",
    "wof:placetype":"venue"
},
  "geometry": {"coordinates":[5.404379,51.870628],"type":"Point"}
}