{
  "type": "Feature",
  "properties": {
    "addr:full":"J Smit Erf 134 Dordrecht Zuid-Holland 3315 VE",
    "addr:housenumber":"134",
    "addr:postcode":"3315",
    "addr:street":"Erf;Ve",
    "iso:country":"NL",
    "sg:address":"J Smit Erf 134",
    "sg:city":"Dordrecht",
    "sg:orig_category":"Fotopersbureaus",
    "sg:phone":"+31 78 630 0714",
    "sg:postcode":"3315 VE",
    "sg:province":"Zuid-Holland",
    "wof:name":"Dirk Hol",
    "wof:placetype":"venue"
},
  "geometry": {"coordinates":[4.722325,51.797482],"type":"Point"}
}