{
  "type": "Feature",
  "properties": {
    "addr:full":"J De Vosln 8 Terschelling West Friesland 8881 EN",
    "addr:housenumber":"8",
    "addr:postcode":"8881 en",
    "addr:street":"J De Vosln",
    "iso:country":"NL",
    "sg:address":"J De Vosln 8",
    "sg:city":"Terschelling West",
    "sg:orig_category":"Artsen - Huisartsen",
    "sg:phone":"+31 562 442 181",
    "sg:postcode":"8881 EN",
    "sg:province":"Friesland",
    "wof:name":"Smit En K J Mellema, P S",
    "wof:placetype":"venue"
},
  "geometry": {"coordinates":[5.214094,53.360294],"type":"Point"}
}