{
  "type": "Feature",
  "properties": {
    "iso:country":"NL",
    "sg:address":"Keppelseweg 11",
    "sg:city":"Doetinchem",
    "sg:orig_category":"Elektronische Bedrijfsinstallaties",
    "sg:phone":"+31 314 363 311",
    "sg:postcode":"7001 CE",
    "sg:province":"Gelderland",
    "wof:name":"Seceurtronics Security Systems",
    "wof:placetype":"venue"
},
  "geometry": {"coordinates":[6.285219,51.967682],"type":"Point"}
}