{
  "type": "Feature",
  "properties": {
    "addr:full":"Jan Van Galenstraat 19 Maassluis South Holland 3143 KC",
    "addr:housenumber":"19",
    "addr:postcode":"3143 kc",
    "addr:street":"Jan Van Galenstraat",
    "iso:country":"NL",
    "sg:address":"Jan Van Galenstraat 19",
    "sg:city":"Maassluis",
    "sg:orig_category":"Onderhoud And Reparatie Kantoorapparatuur",
    "sg:phone":"+31 10 592 6038",
    "sg:postcode":"3143 KC",
    "sg:province":"South Holland",
    "wof:name":"Aldebaran",
    "wof:placetype":"venue"
},
  "geometry": {"coordinates":[4.254751,51.918175],"type":"Point"}
}