{
  "type": "Feature",
  "properties": {
    "addr:full":"Lideweysngl 22B Maasland Zuid-Holland 3155 VW",
    "addr:housenumber":"22b",
    "addr:postcode":"3155 vw",
    "addr:street":"Lideweysngl",
    "iso:country":"NL",
    "sg:address":"Lideweysngl 22B",
    "sg:city":"Maasland",
    "sg:orig_category":"Juridische Adviseurs",
    "sg:phone":"+31 10 591 5276",
    "sg:postcode":"3155 VW",
    "sg:province":"Zuid-Holland",
    "wof:name":"Contractpoint Juristen",
    "wof:placetype":"venue"
},
  "geometry": {"coordinates":[4.275135,51.936325],"type":"Point"}
}