{
  "type": "Feature",
  "properties": {
    "addr:full":"Jadelaan 137 Hoofddorp North Holland 2132 XZ",
    "addr:housenumber":"137",
    "addr:postcode":"2132 xz",
    "addr:street":"Jadelaan",
    "iso:country":"NL",
    "sg:address":"Jadelaan 137",
    "sg:city":"Hoofddorp",
    "sg:orig_category":"Boekhouders",
    "sg:phone":"+31 23 531 2997",
    "sg:postcode":"2132 XZ",
    "sg:province":"North Holland",
    "wof:name":"Administratiekantoor Van De Berg",
    "wof:placetype":"venue"
},
  "geometry": {"coordinates":[4.680437,52.291988],"type":"Point"}
}