{
  "type": "Feature",
  "properties": {
    "iso:country":"NL",
    "sg:address":"Polanerbaan 13N",
    "sg:city":"Woerden",
    "sg:orig_category":"Public Relationbureaus",
    "sg:phone":"+31 348 431 666",
    "sg:postcode":"3447 GN",
    "sg:province":"Utrecht",
    "wof:name":"Droes & Wijdooge Communicatie Adviseurs Vof",
    "wof:placetype":"venue"
},
  "geometry": {"coordinates":[4.894265,52.079994],"type":"Point"}
}