{
  "type": "Feature",
  "properties": {
    "addr:full":"W Prinzenstraat 16A Helmond Noord-Brabant 5701 BH",
    "addr:housenumber":"16a",
    "addr:postcode":"5701 bh",
    "addr:street":"W Prinzenstraat",
    "iso:country":"NL",
    "sg:address":"W Prinzenstraat 16A",
    "sg:city":"Helmond",
    "sg:orig_category":"Verhuisdiensten",
    "sg:phone":"+31 492 525 988",
    "sg:postcode":"5701 BH",
    "sg:province":"Noord-Brabant",
    "wof:name":"Keijsers & De Klijn Verhuisservice",
    "wof:placetype":"venue"
},
  "geometry": {"coordinates":[5.672607,51.483955],"type":"Point"}
}