{
  "type": "Feature",
  "properties": {
    "addr:full":"Spoorstr 48 Schoonhoven Zuid-Holland 2871 TP",
    "addr:housenumber":"48",
    "addr:postcode":"2871 tp",
    "addr:street":"Spoorstr",
    "iso:country":"NL",
    "sg:address":"Spoorstr 48",
    "sg:city":"Schoonhoven",
    "sg:orig_category":"Grafisch Ontwerpers",
    "sg:phone":"+31 182 385 902",
    "sg:postcode":"2871 TP",
    "sg:province":"Zuid-Holland",
    "wof:name":"Schoovers, J A",
    "wof:placetype":"venue"
},
  "geometry": {"coordinates":[4.847969,51.947739],"type":"Point"}
}