{
  "type": "Feature",
  "properties": {
    "iso:country":"NL",
    "sg:address":"De Wielewaal 3",
    "sg:city":"Delden",
    "sg:orig_category":"Adviesbureaus Elektronica",
    "sg:phone":"+31 74 376 1422",
    "sg:postcode":"7491 HE",
    "sg:province":"Overijssel",
    "wof:name":"Pemco",
    "wof:placetype":"venue"
},
  "geometry": {"coordinates":[6.721331,52.256783],"type":"Point"}
}