{
  "type": "Feature",
  "properties": {
    "iso:country":"NL",
    "sg:address":"Robynstr 64-68",
    "sg:city":"Alkmaar",
    "sg:orig_category":"Makelaars En Adviseurs Onroerende Goederen",
    "sg:phone":"+31 72 515 6564",
    "sg:postcode":"1812 RB",
    "sg:province":"North Holland",
    "sg:website":"http://www.bregman.nl",
    "wof:name":"Bregman, Makelaardij Og",
    "wof:placetype":"venue"
},
  "geometry": {"coordinates":[4.758867,52.611629],"type":"Point"}
}