{
  "type": "Feature",
  "properties": {
    "addr:full":"Oostpln 13 Roosendaal Noord-Brabant 4706 NL",
    "addr:housenumber":"13",
    "addr:postcode":"4706 nl",
    "addr:street":"Oostpln",
    "iso:country":"NL",
    "sg:address":"Oostpln 13",
    "sg:city":"Roosendaal",
    "sg:orig_category":"Keukens",
    "sg:phone":"+31 165 569 852",
    "sg:postcode":"4706 NL",
    "sg:province":"Noord-Brabant",
    "sg:website":"http://www.brugman.nl",
    "wof:name":"Brugman",
    "wof:placetype":"venue"
},
  "geometry": {"coordinates":[4.487159,51.537247],"type":"Point"}
}