{
  "type": "Feature",
  "properties": {
    "addr:full":"Breesaapstraat 29 Ijmuiden Noord-Holland 1975 CA",
    "addr:housenumber":"29",
    "addr:postcode":"1975 ca",
    "addr:street":"Breesaapstraat",
    "iso:country":"NL",
    "sg:address":"Breesaapstraat 29",
    "sg:city":"Ijmuiden",
    "sg:orig_category":"Technische Studies And Onderzoek",
    "sg:phone":"+31 255 537 323",
    "sg:postcode":"1975 CA",
    "sg:province":"Noord-Holland",
    "wof:name":"Van Der Heide Development & Engineering",
    "wof:placetype":"venue"
},
  "geometry": {"coordinates":[-119.270203,37.271832],"type":"Point"}
}