{
  "type": "Feature",
  "properties": {
    "addr:full":"De Hoef Oostzijde 121 De Hoef Utrecht 1426 AJ",
    "addr:housenumber":"121",
    "addr:postcode":"1426 aj",
    "addr:street":"De Hoef Oostzijde",
    "iso:country":"NL",
    "sg:address":"De Hoef Oostzijde 121",
    "sg:city":"De Hoef",
    "sg:orig_category":"Landbouwmachines Gh",
    "sg:phone":"+31 297 281 655",
    "sg:postcode":"1426 AJ",
    "sg:province":"Utrecht",
    "wof:name":"A.A. Van Rossum",
    "wof:placetype":"venue"
},
  "geometry": {"coordinates":[4.839556,52.183155],"type":"Point"}
}