{
  "type": "Feature",
  "properties": {
    "addr:full":"Nw Langendk 110 Delft Zuid-Holland 2611 VM",
    "addr:housenumber":"110",
    "addr:postcode":"delft;2611 vm",
    "iso:country":"NL",
    "sg:address":"Nw Langendk 110",
    "sg:city":"Delft",
    "sg:classifiers":[
        {
            "category":"Food & Beverages",
            "subcategory":"Bakery",
            "type":"Retail Goods"
        }
    ],
    "sg:phone":"+31 15 212 7418",
    "sg:postcode":"2611 VM",
    "sg:province":"Zuid-Holland",
    "sg:tags":[
        "pizza"
    ],
    "sg:website":"http://www.meximan.com",
    "wof:name":"Meximan",
    "wof:placetype":"venue"
},
  "geometry": {"coordinates":[4.364577,52.013653],"type":"Point"}
}