{
  "type": "Feature",
  "properties": {
    "addr:full":"Veldstraat 21 Enschede NL.08 7532 ZE",
    "addr:housenumber":"21",
    "addr:postcode":"7532 ze",
    "addr:street":"Veldstraat",
    "iso:country":"NL",
    "sg:address":"Veldstraat 21",
    "sg:city":"Enschede",
    "sg:orig_category":"Meubelzaken, Woning- And Keukeninrichting",
    "sg:phone":"+31 53 461 1761",
    "sg:postcode":"7532 ZE",
    "sg:province":"NL.08",
    "wof:name":"Interieurverzorging Krabbe Bv",
    "wof:placetype":"venue"
},
  "geometry": {"coordinates":[6.969261,52.216717],"type":"Point"}
}