{
  "type": "Feature",
  "properties": {
    "iso:country":"NL",
    "sg:address":"Boezemsngl 9",
    "sg:city":"Oud Beyerland",
    "sg:orig_category":"Verenigingen En Stichtingen",
    "sg:phone":"+31 186 621 260",
    "sg:postcode":"3261 BC",
    "sg:province":"Zuid-Holland",
    "wof:name":"Scouting",
    "wof:placetype":"venue"
},
  "geometry": {"coordinates":[4.42806,51.807892],"type":"Point"}
}