{
  "type": "Feature",
  "properties": {
    "iso:country":"NL",
    "sg:address":"Kapeldijk 7",
    "sg:city":"Harfsen",
    "sg:orig_category":"Wasserettes And Stomerijen",
    "sg:phone":"+31 573 431 365",
    "sg:postcode":"7217 SH",
    "sg:province":"Gelderland",
    "wof:name":"A. Plekkenpol",
    "wof:placetype":"venue"
},
  "geometry": {"coordinates":[6.2912120819,52.1854248047],"type":"Point"}
}