{
  "type": "Feature",
  "properties": {
    "addr:full":"Vlietenburg 31 Gouda Zuid-Holland 2804 WR",
    "addr:housenumber":"31",
    "addr:postcode":"2804 wr",
    "addr:street":"Vlietenburg",
    "iso:country":"NL",
    "sg:address":"Vlietenburg 31",
    "sg:city":"Gouda",
    "sg:orig_category":"Verslagbureaus",
    "sg:phone":"+31 182 553 428",
    "sg:postcode":"2804 WR",
    "sg:province":"Zuid-Holland",
    "sg:website":"http://www.verslagbureaudejager.nl",
    "wof:name":"Jager, De",
    "wof:placetype":"venue"
},
  "geometry": {"coordinates":[4.706727,52.033321],"type":"Point"}
}