{
  "type": "Feature",
  "properties": {
    "addr:full":"Oude Bredaseweg 59 Etten-Leur North Brabant 4872 AC",
    "addr:housenumber":"59",
    "addr:postcode":"4872 ac",
    "addr:street":"Oude Bredaseweg",
    "iso:country":"NL",
    "sg:address":"Oude Bredaseweg 59",
    "sg:city":"Etten-Leur",
    "sg:orig_category":"Autokeuringen",
    "sg:phone":"+31 76 501 2023",
    "sg:postcode":"4872 AC",
    "sg:province":"North Brabant",
    "wof:name":"J M Vd Luitgaarden",
    "wof:placetype":"venue"
},
  "geometry": {"coordinates":[4.641921,51.570477],"type":"Point"}
}