{
  "type": "Feature",
  "properties": {
    "addr:full":"Industriewg 4 Terneuzen Zeeland 4538 AH",
    "addr:housenumber":"4",
    "addr:postcode":"4538 ah",
    "addr:street":"Industriewg",
    "iso:country":"NL",
    "sg:address":"Industriewg 4",
    "sg:city":"Terneuzen",
    "sg:orig_category":"Scheepsbouw En -Reparatie",
    "sg:phone":"+31 115 630 148",
    "sg:postcode":"4538 AH",
    "sg:province":"Zeeland",
    "wof:name":"Terneuzen Port Service",
    "wof:placetype":"venue"
},
  "geometry": {"coordinates":[3.827461,51.328873],"type":"Point"}
}