{
  "type": "Feature",
  "properties": {
    "iso:country":"NL",
    "sg:address":"Techniekwg 1",
    "sg:city":"Emmeloord",
    "sg:orig_category":"Autopoetsbedrijven",
    "sg:phone":"+31 527 619 868",
    "sg:postcode":"8304 AW",
    "sg:province":"Flevoland",
    "sg:website":"http://www.steenslagreparatie.nl",
    "wof:name":"Ace",
    "wof:placetype":"venue"
},
  "geometry": {"coordinates":[5.755723,52.698624],"type":"Point"}
}