{
  "type": "Feature",
  "properties": {
    "addr:full":"Techniekwg 1 Emmeloord Flevoland 8304 AW",
    "addr:housenumber":"1",
    "addr:postcode":"8304 aw",
    "addr:street":"Techniekwg;Flevoland",
    "iso:country":"NL",
    "sg:address":"Techniekwg 1",
    "sg:city":"Emmeloord",
    "sg:orig_category":"Autopoetsbedrijven",
    "sg:phone":"+31 527 619 868",
    "sg:postcode":"8304 AW",
    "sg:province":"Flevoland",
    "sg:website":"http://www.steenslagreparatie.nl",
    "wof:name":"Ace",
    "wof:placetype":"venue"
},
  "geometry": {"coordinates":[5.755723,52.698624],"type":"Point"}
}