{
  "type": "Feature",
  "properties": {
    "addr:full":"Elspeterbos 36 Hoofddorp Noord-Holland 2134 LD",
    "addr:housenumber":"36",
    "addr:postcode":"2134 ld",
    "addr:street":"Elspeterbos",
    "iso:country":"NL",
    "sg:address":"Elspeterbos 36",
    "sg:city":"Hoofddorp",
    "sg:orig_category":"Webdesign Bureaus",
    "sg:phone":"+31 23 557 3221",
    "sg:postcode":"2134 LD",
    "sg:province":"Noord-Holland",
    "sg:website":"http://www.creagraphy.nl",
    "wof:name":"Creagraphy",
    "wof:placetype":"venue"
},
  "geometry": {"coordinates":[4.6578211784,52.3132705688],"type":"Point"}
}