{
  "type": "Feature",
  "properties": {
    "addr:full":"Koninginneln 34 Apeldoorn Gelderland 7315 BS",
    "addr:housenumber":"34",
    "addr:postcode":"7315 bs",
    "addr:street":"Koninginneln;Gelderland",
    "iso:country":"NL",
    "sg:address":"Koninginneln 34",
    "sg:city":"Apeldoorn",
    "sg:orig_category":"Administratie- En Boekhoudkantoren",
    "sg:phone":"+31 55 521 4072",
    "sg:postcode":"7315 BS",
    "sg:province":"Gelderland",
    "wof:name":"Polderman Administratiekantoor",
    "wof:placetype":"venue"
},
  "geometry": {"coordinates":[5.956644,52.224449],"type":"Point"}
}