{
  "type": "Feature",
  "properties": {
    "addr:full":"Ceramstraat 2 Tilburg Noord-Brabant 5013 BB",
    "addr:housenumber":"2",
    "addr:postcode":"5013 bb",
    "addr:street":"Ceramstraat",
    "iso:country":"NL",
    "sg:address":"Ceramstraat 2",
    "sg:city":"Tilburg",
    "sg:orig_category":"Meubels And Huishoudapparatuur Gh",
    "sg:phone":"+31 13 543 7673",
    "sg:postcode":"5013 BB",
    "sg:province":"Noord-Brabant",
    "wof:name":"Ceram",
    "wof:placetype":"venue"
},
  "geometry": {"coordinates":[5.105732,51.56546],"type":"Point"}
}