{
  "type": "Feature",
  "properties": {
    "addr:full":"Hellingkd 7 Maassluis Zuid-Holland 3144 EJ",
    "addr:housenumber":"7",
    "addr:postcode":"3144 ej",
    "addr:street":"Hellingkd",
    "iso:country":"NL",
    "sg:address":"Hellingkd 7",
    "sg:city":"Maassluis",
    "sg:orig_category":"Lasbedrijven",
    "sg:phone":"+31 10 591 8470",
    "sg:postcode":"3144 EJ",
    "sg:province":"Zuid-Holland",
    "wof:name":"Aluservice Bv",
    "wof:placetype":"venue"
},
  "geometry": {"coordinates":[4.251202,51.924381],"type":"Point"}
}