{
  "type": "Feature",
  "properties": {
    "addr:full":"Rotterdamseweg 186 Zwijndrecht Zuid-Holland 3332 AM",
    "addr:housenumber":"186",
    "addr:postcode":"3332",
    "addr:street":"Rotterdamseweg",
    "iso:country":"NL",
    "sg:address":"Rotterdamseweg 186",
    "sg:city":"Zwijndrecht",
    "sg:orig_category":"Verzekeringen",
    "sg:phone":"+31 78 612 4357",
    "sg:postcode":"3332 AM",
    "sg:province":"Zuid-Holland",
    "wof:name":"J C Koorneef",
    "wof:placetype":"venue"
},
  "geometry": {"coordinates":[4.642988,51.823143],"type":"Point"}
}