{
  "type": "Feature",
  "properties": {
    "addr:full":"Vlierberg 5 Eemnes Utrecht 3755 BS",
    "addr:housenumber":"5",
    "addr:postcode":"3755 bs",
    "addr:street":"Vlierberg",
    "iso:country":"NL",
    "sg:address":"Vlierberg 5",
    "sg:city":"Eemnes",
    "sg:orig_category":"Gassen Industrieel En Medisch",
    "sg:phone":"+31 35 538 2768",
    "sg:postcode":"3755 BS",
    "sg:province":"Utrecht",
    "wof:name":"Kuiper'S Gassen Eemnes",
    "wof:placetype":"venue"
},
  "geometry": {"coordinates":[5.249544,52.24715],"type":"Point"}
}