{
  "type": "Feature",
  "properties": {
    "addr:full":"Lange Broekweg 72 Naaldwijk Zuid-Holland 2671 DW",
    "addr:housenumber":"72",
    "addr:postcode":"2671 dw",
    "addr:street":"Lange Broekweg",
    "iso:country":"NL",
    "sg:address":"Lange Broekweg 72",
    "sg:city":"Naaldwijk",
    "sg:orig_category":"Verhuur Gereedschapsmachines And Gereedschappen",
    "sg:phone":"+31 174 625 444",
    "sg:postcode":"2671 DW",
    "sg:province":"Zuid-Holland",
    "wof:name":"Firma G. Boekesteijn En Zoon",
    "wof:placetype":"venue"
},
  "geometry": {"coordinates":[4.23923,51.990627],"type":"Point"}
}