{
  "type": "Feature",
  "properties": {
    "addr:full":"Kruburg 9 Eindhoven Noord-Brabant 5632 PG",
    "addr:housenumber":"9",
    "addr:postcode":"5632 pg",
    "addr:street":"Kruburg",
    "iso:country":"NL",
    "sg:address":"Kruburg 9",
    "sg:city":"Eindhoven",
    "sg:orig_category":"Drukkerijen",
    "sg:phone":"+31 40 242 5677",
    "sg:postcode":"5632 PG",
    "sg:province":"Noord-Brabant",
    "wof:name":"Papyrette",
    "wof:placetype":"venue"
},
  "geometry": {"coordinates":[5.49848,51.477058],"type":"Point"}
}