{
  "type": "Feature",
  "properties": {
    "addr:full":"Lodewijk Napoleonlaan 77 Oosterhout Nb North Brabant 4904 LH",
    "addr:housenumber":"77;nb",
    "addr:postcode":"4904 lh",
    "addr:street":"Lodewijk Napoleonlaan",
    "iso:country":"NL",
    "sg:address":"Lodewijk Napoleonlaan 77",
    "sg:city":"Oosterhout Nb",
    "sg:orig_category":"Makelaars In Onroerend Goed",
    "sg:phone":"+31 162 426 348",
    "sg:postcode":"4904 LH",
    "sg:province":"North Brabant",
    "wof:name":"Klijsen Makelaardij Onroerend Goed Bv",
    "wof:placetype":"venue"
},
  "geometry": {"coordinates":[4.855793,51.625568],"type":"Point"}
}