{
  "type": "Feature",
  "properties": {
    "addr:full":"Mauritsstraat 17 Breda North Brabant 4811 EN",
    "addr:housenumber":"17",
    "addr:postcode":"4811 en",
    "addr:street":"Mauritsstraat",
    "iso:country":"NL",
    "sg:address":"Mauritsstraat 17",
    "sg:city":"Breda",
    "sg:orig_category":"Fotostudio'S And Fotografen",
    "sg:phone":"+31 76 520 3397",
    "sg:postcode":"4811 EN",
    "sg:province":"North Brabant",
    "wof:name":"Miles Ladeur Fotografische Vormgeving",
    "wof:placetype":"venue"
},
  "geometry": {"coordinates":[4.784296,51.593151],"type":"Point"}
}