{
  "type": "Feature",
  "properties": {
    "addr:full":"Beetsln 222 Ryswyk Zh Zuid-Holland 2281 TS",
    "addr:housenumber":"222",
    "addr:postcode":"2281 ts",
    "addr:street":"Ryswyk",
    "iso:country":"NL",
    "sg:address":"Beetsln 222",
    "sg:city":"Ryswyk Zh",
    "sg:classifiers":[
        {
            "category":"Retail",
            "subcategory":"Auto Repair",
            "type":"Services"
        }
    ],
    "sg:phone":"+31 70 399 5353",
    "sg:postcode":"2281 TS",
    "sg:province":"Zuid-Holland",
    "sg:tags":[
        "garage"
    ],
    "wof:name":"Premex",
    "wof:placetype":"venue"
},
  "geometry": {"coordinates":[4.341704,52.056934],"type":"Point"}
}