{
  "type": "Feature",
  "properties": {
    "addr:full":"Sandoel 35 Raamsdonksveer Noord-Brabant 4941 DT",
    "addr:housenumber":"35",
    "addr:postcode":"4941 dt",
    "addr:street":"Sandoel",
    "iso:country":"NL",
    "sg:address":"Sandoel 35",
    "sg:city":"Raamsdonksveer",
    "sg:orig_category":"Projectontwikkeling",
    "sg:phone":"+31 162 513 529",
    "sg:postcode":"4941 DT",
    "sg:province":"Noord-Brabant",
    "wof:name":"Logistiek Project Management",
    "wof:placetype":"venue"
},
  "geometry": {"coordinates":[4.863694,51.693668],"type":"Point"}
}