{
  "type": "Feature",
  "properties": {
    "addr:full":"Dr Cuypersln 86 Eindhoven Noord-Brabant 5623 BB",
    "addr:housenumber":"86",
    "addr:postcode":"5623 bb",
    "iso:country":"NL",
    "sg:address":"Dr Cuypersln 86",
    "sg:city":"Eindhoven",
    "sg:orig_category":"Logopedisten",
    "sg:phone":"+31 40 243 3699",
    "sg:postcode":"5623 BB",
    "sg:province":"Noord-Brabant",
    "wof:name":"Brinkmann, Karin",
    "wof:placetype":"venue"
},
  "geometry": {"coordinates":[5.47708,51.460041],"type":"Point"}
}