{
  "type": "Feature",
  "properties": {
    "addr:full":"G Molstr 25 Zaandam Noord-Holland 1507 WN",
    "addr:housenumber":"25",
    "addr:postcode":"1507 wn",
    "iso:country":"NL",
    "sg:address":"G Molstr 25",
    "sg:city":"Zaandam",
    "sg:orig_category":"Kappers",
    "sg:phone":"+31 75 616 6498",
    "sg:postcode":"1507 WN",
    "sg:province":"Noord-Holland",
    "wof:name":"Johnn & Vilja'S",
    "wof:placetype":"venue"
},
  "geometry": {"coordinates":[4.7973542213,52.4504203796],"type":"Point"}
}