{
  "type": "Feature",
  "properties": {
    "addr:full":"Merwedepln 54 Amsterdam North Holland 1078 NG",
    "addr:housenumber":"54",
    "addr:postcode":"1078 ng",
    "addr:street":"Merwedepln",
    "iso:country":"NL",
    "sg:address":"Merwedepln 54",
    "sg:city":"Amsterdam",
    "sg:orig_category":"Makelaars En Adviseurs Onroerende Goederen",
    "sg:phone":"+31 20 675 0451",
    "sg:postcode":"1078 NG",
    "sg:province":"North Holland",
    "sg:website":"http://www.ameo.nl",
    "wof:name":"Ameo",
    "wof:placetype":"venue"
},
  "geometry": {"coordinates":[4.899761,52.345852],"type":"Point"}
}