{
  "type": "Feature",
  "properties": {
    "iso:country":"NL",
    "sg:address":"Sarphatistr 54",
    "sg:city":"Amsterdam",
    "sg:orig_category":"Vakantieverblijven",
    "sg:phone":"+31 20 699 3972",
    "sg:postcode":"1018 GP",
    "sg:province":"North Holland",
    "wof:name":"Casa Italia",
    "wof:placetype":"venue"
},
  "geometry": {"coordinates":[4.908154,52.361115],"type":"Point"}
}