{
  "type": "Feature",
  "properties": {
    "iso:country":"NL",
    "sg:address":"Vriesestr 30",
    "sg:city":"Dordrecht",
    "sg:orig_category":"Gemeentelijke Informatie",
    "sg:phone":"+31 78 613 2645",
    "sg:postcode":"3311 NR",
    "sg:province":"Zuid-Holland",
    "wof:name":"Stadsmarkten",
    "wof:placetype":"venue"
},
  "geometry": {"coordinates":[4.66759,51.813808],"type":"Point"}
}