{
  "type": "Feature",
  "properties": {
    "addr:full":"Stephensonwg 14 Gorinchem Zuid-Holland 4207 HB",
    "addr:housenumber":"14",
    "addr:postcode":"4207 hb",
    "addr:street":"Stephensonwg",
    "iso:country":"NL",
    "sg:address":"Stephensonwg 14",
    "sg:city":"Gorinchem",
    "sg:orig_category":"Bedrijfsopleidingen",
    "sg:phone":"+31 183 648 864",
    "sg:postcode":"4207 HB",
    "sg:province":"Zuid-Holland",
    "sg:website":"http://www.arbode.nl",
    "wof:name":"Arbode Bv",
    "wof:placetype":"venue"
},
  "geometry": {"coordinates":[4.99958,51.842899],"type":"Point"}
}