{
  "type": "Feature",
  "properties": {
    "addr:full":"Rooysestr 56 Dreumel Gelderland 6621 AN",
    "addr:housenumber":"56",
    "addr:postcode":"6621 an",
    "addr:street":"Rooysestr;Gelderland",
    "iso:country":"NL",
    "sg:address":"Rooysestr 56",
    "sg:city":"Dreumel",
    "sg:orig_category":"Banken",
    "sg:phone":"+31 487 572 761",
    "sg:postcode":"6621 AN",
    "sg:province":"Gelderland",
    "wof:name":"Regio Bank",
    "wof:placetype":"venue"
},
  "geometry": {"coordinates":[5.431383,51.848587],"type":"Point"}
}