{
  "type": "Feature",
  "properties": {
    "addr:full":"Nijverheidslaan 49 Musselkanaal Groningen 9581 EJ",
    "addr:housenumber":"49",
    "addr:postcode":"9581 ej",
    "addr:street":"Nijverheidslaan",
    "iso:country":"NL",
    "sg:address":"Nijverheidslaan 49",
    "sg:city":"Musselkanaal",
    "sg:orig_category":"Kantoorartikelen",
    "sg:phone":"+31 599 413 300",
    "sg:postcode":"9581 EJ",
    "sg:province":"Groningen",
    "wof:name":"Compuline Automatisering Bv",
    "wof:placetype":"venue"
},
  "geometry": {"coordinates":[7.0285391808,52.9251861572],"type":"Point"}
}