{
  "type": "Feature",
  "properties": {
    "addr:full":"Eendrachtstr 11 Terschuur Gelderland 3784 KA",
    "addr:housenumber":"11",
    "addr:postcode":"3784 ka",
    "addr:street":"Eendrachtstr;Gelderland",
    "iso:country":"NL",
    "sg:address":"Eendrachtstr 11",
    "sg:city":"Terschuur",
    "sg:orig_category":"Loodgieters",
    "sg:phone":"+31 342 461 737",
    "sg:postcode":"3784 KA",
    "sg:province":"Gelderland",
    "wof:name":"Veldhuizen Bv",
    "wof:placetype":"venue"
},
  "geometry": {"coordinates":[5.519076,52.16581],"type":"Point"}
}