{
  "type": "Feature",
  "properties": {
    "iso:country":"NL",
    "sg:address":"Strickledewg 23",
    "sg:city":"Schiedam",
    "sg:orig_category":"Kantoor- En Bedrijfsmeubelen",
    "sg:phone":"+31 10 437 4791",
    "sg:postcode":"3125 AT",
    "sg:province":"South Holland",
    "wof:name":"Tof Bv",
    "wof:placetype":"venue"
},
  "geometry": {"coordinates":[4.4111409187,51.9280891418],"type":"Point"}
}