{
  "type": "Feature",
  "properties": {
    "addr:full":"Slotermeerlaan 125 Amsterdam North Holland 1063 JN",
    "addr:housenumber":"125",
    "addr:postcode":"1063 jn",
    "addr:street":"Slotermeerlaan",
    "iso:country":"NL",
    "sg:address":"Slotermeerlaan 125",
    "sg:city":"Amsterdam",
    "sg:classifiers":[
        {
            "category":"Retail",
            "subcategory":"Photofinishing",
            "type":"Services"
        }
    ],
    "sg:phone":"+31 20 614 9222",
    "sg:postcode":"1063 JN",
    "sg:province":"North Holland",
    "sg:tags":[
        "foto",
        "film"
    ],
    "wof:name":"Foto Cinecentrum",
    "wof:placetype":"venue"
},
  "geometry": {"coordinates":[4.820897,52.38084],"type":"Point"}
}