{
  "type": "Feature",
  "properties": {
    "iso:country":"NL",
    "sg:address":"Wouwseweg 15",
    "sg:city":"Halsteren",
    "sg:orig_category":"Woningbouwverenigingen",
    "sg:phone":"+31 164 682 983",
    "sg:postcode":"4661 VM",
    "sg:province":"Noord-Brabant",
    "wof:name":"Woningstichting Halsteren",
    "wof:placetype":"venue"
},
  "geometry": {"coordinates":[4.2817549706,51.5270423889],"type":"Point"}
}