{
  "type": "Feature",
  "properties": {
    "addr:full":"Rijnstraat 12 Tolkamer North Rhine-Westphalia 6916 BD",
    "addr:housenumber":"12",
    "addr:postcode":"6916 bd",
    "addr:street":"Rijnstraat",
    "iso:country":"NL",
    "sg:address":"Rijnstraat 12",
    "sg:city":"Tolkamer",
    "sg:classifiers":[
        {
            "category":"Fast Food",
            "type":"Food & Drink"
        }
    ],
    "sg:phone":"+31 316 543 886",
    "sg:postcode":"6916 BD",
    "sg:province":"North Rhine-Westphalia",
    "sg:tags":[
        "afhaal",
        "restaurant"
    ],
    "wof:name":"T Luifeltje",
    "wof:placetype":"venue"
},
  "geometry": {"coordinates":[6.102983,51.851116],"type":"Point"}
}