{
  "type": "Feature",
  "properties": {
    "addr:full":"Arendsstraat 7 Oude-Tonge Zuid-Holland 3255 XA",
    "addr:housenumber":"7",
    "addr:postcode":"3255 xa",
    "addr:street":"Arendsstraat",
    "iso:country":"NL",
    "sg:address":"Arendsstraat 7",
    "sg:city":"Oude-Tonge",
    "sg:orig_category":"Loodgieterswerk, Verwarming And Sanitaire Installaties",
    "sg:phone":"+31 187 641 458",
    "sg:postcode":"3255 XA",
    "sg:province":"Zuid-Holland",
    "wof:name":"Loodgietersbedrijf J. Sprong En Zonen Bv",
    "wof:placetype":"venue"
},
  "geometry": {"coordinates":[4.213857,51.690075],"type":"Point"}
}