{
  "type": "Feature",
  "properties": {
    "addr:full":"Bredasingel 5 Arnhem Gelderland 6843 RA",
    "addr:housenumber":"5",
    "addr:postcode":"6843 ra",
    "addr:street":"Bredasingel",
    "iso:country":"NL",
    "sg:address":"Bredasingel 5",
    "sg:city":"Arnhem",
    "sg:orig_category":"Geluidsopnamen",
    "sg:phone":"+31 26 383 0922",
    "sg:postcode":"6843 RA",
    "sg:province":"Gelderland",
    "wof:name":"Bobo-Sound",
    "wof:placetype":"venue"
},
  "geometry": {"coordinates":[5.859608,51.952694],"type":"Point"}
}