{
  "type": "Feature",
  "properties": {
    "iso:country":"NL",
    "sg:address":"2E Bloemdwstr 24",
    "sg:city":"Amsterdam",
    "sg:orig_category":"Organisatiebureaus",
    "sg:phone":"+31 20 671 0847",
    "sg:postcode":"1016 LM",
    "sg:province":"Noord-Holland",
    "wof:name":"Claassen, Gerard",
    "wof:placetype":"venue"
},
  "geometry": {"coordinates":[4.8795289993,52.3735198975],"type":"Point"}
}