{
  "type": "Feature",
  "properties": {
    "addr:full":"Vismarkt 3 Heusden Gem Heusden North Brabant 5256 BC",
    "addr:housenumber":"3",
    "addr:postcode":"5256 bc",
    "addr:street":"Vismarkt",
    "iso:country":"NL",
    "sg:address":"Vismarkt 3",
    "sg:city":"Heusden Gem Heusden",
    "sg:classifiers":[
        {
            "category":"Fast Food",
            "type":"Food & Drink"
        }
    ],
    "sg:phone":"+31 416 661 213",
    "sg:postcode":"5256 BC",
    "sg:province":"North Brabant",
    "sg:tags":[
        "afhaal",
        "restaurant"
    ],
    "wof:name":"Shoarma Pizzeria De Veste",
    "wof:placetype":"venue"
},
  "geometry": {"coordinates":[5.137639,51.734856],"type":"Point"}
}