{
  "type": "Feature",
  "properties": {
    "addr:full":"Radarstr 10 Capelle Ad Yssel Zuid-Holland 2901 AV",
    "addr:housenumber":"10;2901",
    "addr:postcode":"av",
    "addr:street":"Radarstr",
    "iso:country":"NL",
    "sg:address":"Radarstr 10",
    "sg:city":"Capelle Ad Yssel",
    "sg:orig_category":"Autoschade- Herstelbedrijven",
    "sg:phone":"+31 10 450 6533",
    "sg:postcode":"2901 AV",
    "sg:province":"Zuid-Holland",
    "wof:name":"Asn",
    "wof:placetype":"venue"
},
  "geometry": {"coordinates":[4.563719,51.911057],"type":"Point"}
}