{
  "type": "Feature",
  "properties": {
    "addr:full":"G Van Nijenrodestraat 154 Breukelen Ut Utrecht 3621 GM",
    "addr:housenumber":"154",
    "addr:postcode":"3621 gm",
    "addr:street":"G Van Nijenrodestraat",
    "iso:country":"NL",
    "sg:address":"G Van Nijenrodestraat 154",
    "sg:city":"Breukelen Ut",
    "sg:orig_category":"Verzekeringen",
    "sg:phone":"+31 346 262 317",
    "sg:postcode":"3621 GM",
    "sg:province":"Utrecht",
    "wof:name":"Assurantiekantoor Jan De Bruin",
    "wof:placetype":"venue"
},
  "geometry": {"coordinates":[5.001585,52.172958],"type":"Point"}
}