{
  "type": "Feature",
  "properties": {
    "addr:full":"Mr W M O V Veenwg 40 Bergum Provincie Friesland 9251 GA",
    "addr:housenumber":"40",
    "addr:postcode":"9251 ga",
    "addr:street":"W;Veenwg;Provincie Friesland",
    "iso:country":"NL",
    "sg:address":"Mr W M O V Veenwg 40",
    "sg:city":"Bergum",
    "sg:orig_category":"Verzekerings- Maatschappijen",
    "sg:phone":"+31 900 2358648",
    "sg:postcode":"9251 GA",
    "sg:province":"Provincie Friesland",
    "sg:website":"http://www.unive.nl/105",
    "wof:name":"Univ\u00e9 Friesland",
    "wof:placetype":"venue"
},
  "geometry": {"coordinates":[5.986921,53.19529],"type":"Point"}
}