{
  "type": "Feature",
  "properties": {
    "addr:full":"Gorsdk 7 Moerdyk Noord-Brabant 4782 PH",
    "addr:housenumber":"7",
    "addr:postcode":"4782",
    "addr:street":"Gorsdk",
    "iso:country":"NL",
    "sg:address":"Gorsdk 7",
    "sg:city":"Moerdyk",
    "sg:orig_category":"Hoefsmederijen",
    "sg:phone":"+31 168 412 961",
    "sg:postcode":"4782 PH",
    "sg:province":"Noord-Brabant",
    "wof:name":"Aart, F Van",
    "wof:placetype":"venue"
},
  "geometry": {"coordinates":[4.621449,51.685261],"type":"Point"}
}