{
  "type": "Feature",
  "properties": {
    "iso:country":"NL",
    "sg:address":"Linnaeusweg 98",
    "sg:city":"Boskoop",
    "sg:classifiers":[
        {
            "category":"Retail",
            "subcategory":"Photofinishing",
            "type":"Services"
        }
    ],
    "sg:phone":"+31 172 218 716",
    "sg:postcode":"2771 HH",
    "sg:province":"Zuid-Holland",
    "sg:tags":[
        "foto",
        "film"
    ],
    "wof:name":"Foto Pander & Pander Snel Service",
    "wof:placetype":"venue"
},
  "geometry": {"coordinates":[4.64849,52.064903],"type":"Point"}
}