{
  "type": "Feature",
  "properties": {
    "iso:country":"NL",
    "sg:address":"Schoterlandsewg 3",
    "sg:city":"Katlyk",
    "sg:orig_category":"Bloemisterijartikelen - Fabrieken En Groothandel",
    "sg:phone":"+31 513 682 310",
    "sg:postcode":"8455 JC",
    "sg:province":"Friesland",
    "wof:name":"Afa Bv",
    "wof:placetype":"venue"
},
  "geometry": {"coordinates":[6.012525,52.938545],"type":"Point"}
}