{
  "type": "Feature",
  "properties": {
    "addr:full":"Bongerd 4B Heerlen Limburg 6411 JM",
    "addr:housenumber":"4b",
    "addr:postcode":"6411 jm",
    "addr:street":"Bongerd",
    "iso:country":"NL",
    "sg:address":"Bongerd 4B",
    "sg:city":"Heerlen",
    "sg:orig_category":"Kinderkleding",
    "sg:phone":"+31 45 571 0466",
    "sg:postcode":"6411 JM",
    "sg:province":"Limburg",
    "wof:name":"Villa Happ",
    "wof:placetype":"venue"
},
  "geometry": {"coordinates":[5.978608,50.887936],"type":"Point"}
}