{
  "type": "Feature",
  "properties": {
    "addr:full":"Raamstr 10 Groningen Groningen 9711 CK",
    "addr:housenumber":"10",
    "addr:postcode":"9711 ck",
    "addr:street":"Raamstr",
    "iso:country":"NL",
    "sg:address":"Raamstr 10",
    "sg:city":"Groningen",
    "sg:orig_category":"Psychologen",
    "sg:phone":"+31 50 314 2152",
    "sg:postcode":"9711 CK",
    "sg:province":"Groningen",
    "wof:name":"Psychologengroep Zuiderpark",
    "wof:placetype":"venue"
},
  "geometry": {"coordinates":[6.568128,53.214222],"type":"Point"}
}