{
  "type": "Feature",
  "properties": {
    "addr:full":"Neutronenln 70 Uden Noord-Brabant 5405 NH",
    "addr:housenumber":"70",
    "addr:postcode":"5405 nh",
    "addr:street":"Neutronenln",
    "iso:country":"NL",
    "sg:address":"Neutronenln 70",
    "sg:city":"Uden",
    "sg:orig_category":"Kopieerservice",
    "sg:phone":"+31 413 247 448",
    "sg:postcode":"5405 NH",
    "sg:province":"Noord-Brabant",
    "wof:name":"Kopieerwinkel Uden, De",
    "wof:placetype":"venue"
},
  "geometry": {"coordinates":[-71.632828,44.001301],"type":"Point"}
}