{
  "type": "Feature",
  "properties": {
    "addr:full":"St. Annastraat 13 Breda North Brabant 4811 XK",
    "addr:housenumber":"13",
    "addr:postcode":"4811 xk",
    "addr:street":"St. Annastraat",
    "iso:country":"NL",
    "sg:address":"St. Annastraat 13",
    "sg:city":"Breda",
    "sg:orig_category":"Kunst And Kunstenaarsbenodigdheden",
    "sg:phone":"+31 76 521 3018",
    "sg:postcode":"4811 XK",
    "sg:province":"North Brabant",
    "wof:name":"Kunsthandel M. Jas, Lijstenmakerij",
    "wof:placetype":"venue"
},
  "geometry": {"coordinates":[4.777968,51.588825],"type":"Point"}
}