{
  "type": "Feature",
  "properties": {
    "addr:full":"Koeweg 49 Emst Gelderland 8166 JP",
    "addr:housenumber":"49",
    "addr:postcode":"8166 jp",
    "addr:street":"Koeweg;Gelderland",
    "iso:country":"NL",
    "sg:address":"Koeweg 49",
    "sg:city":"Emst",
    "sg:orig_category":"Bloemen And Planten",
    "sg:phone":"+31 578 661 531",
    "sg:postcode":"8166 JP",
    "sg:province":"Gelderland",
    "wof:name":"Fa. Wagenvoort En Zoon",
    "wof:placetype":"venue"
},
  "geometry": {"coordinates":[5.959096,52.31834],"type":"Point"}
}