{
  "type": "Feature",
  "properties": {
    "addr:full":"Buitendk 16 Stryensas South Holland 3292 LB",
    "addr:housenumber":"16",
    "addr:postcode":"3292 lb",
    "addr:street":"Buitendk",
    "iso:country":"NL",
    "sg:address":"Buitendk 16",
    "sg:city":"Stryensas",
    "sg:orig_category":"Behangers",
    "sg:phone":"+31 78 674 3588",
    "sg:postcode":"3292 LB",
    "sg:province":"South Holland",
    "wof:name":"Leentjes Bv, Ruud",
    "wof:placetype":"venue"
},
  "geometry": {"coordinates":[4.58554,51.714409],"type":"Point"}
}