{
  "type": "Feature",
  "properties": {
    "iso:country":"NL",
    "sg:address":"Buitendk 16",
    "sg:city":"Stryensas",
    "sg:orig_category":"Behangers",
    "sg:phone":"+31 78 674 3588",
    "sg:postcode":"3292 LB",
    "sg:province":"South Holland",
    "wof:name":"Leentjes Bv, Ruud",
    "wof:placetype":"venue"
},
  "geometry": {"coordinates":[4.58554,51.714409],"type":"Point"}
}