{
  "type": "Feature",
  "properties": {
    "addr:full":"Van Deventerlaan 16 Voorburg Zuid-Holland 2271 TX",
    "addr:housenumber":"16",
    "addr:postcode":"2271 tx",
    "addr:street":"Van Deventerlaan",
    "iso:country":"NL",
    "sg:address":"Van Deventerlaan 16",
    "sg:city":"Voorburg",
    "sg:classifiers":[
        {
            "category":"Education",
            "subcategory":"Preschool",
            "type":"Public Place"
        }
    ],
    "sg:phone":"+31 70 386 0177",
    "sg:postcode":"2271 TX",
    "sg:province":"Zuid-Holland",
    "sg:tags":[
        "kleuteronderwijs",
        "basis-"
    ],
    "wof:name":"Prof. Casimirschool",
    "wof:placetype":"venue"
},
  "geometry": {"coordinates":[4.368213,52.074089],"type":"Point"}
}