{
  "type": "Feature",
  "properties": {
    "addr:full":"Gouden Regenlaan 3 Hilversum Noord-Holland 1214 NC",
    "addr:housenumber":"3",
    "addr:postcode":"1214 nc",
    "addr:street":"Gouden Regenlaan",
    "iso:country":"NL",
    "sg:address":"Gouden Regenlaan 3",
    "sg:city":"Hilversum",
    "sg:orig_category":"Kinderopvang Behalve Thuis",
    "sg:phone":"+31 35 623 5815",
    "sg:postcode":"1214 NC",
    "sg:province":"Noord-Holland",
    "wof:name":"Kinderdagverblijf Dribbel",
    "wof:placetype":"venue"
},
  "geometry": {"coordinates":[5.165807,52.208061],"type":"Point"}
}