{
  "type": "Feature",
  "properties": {
    "addr:full":"Spoorstraat 47 Ijsselmuiden Overijssel 8271 RG",
    "addr:housenumber":"47",
    "addr:postcode":"8271 rg",
    "addr:street":"Spoorstraat",
    "iso:country":"NL",
    "sg:address":"Spoorstraat 47",
    "sg:city":"Ijsselmuiden",
    "sg:orig_category":"Fruit And Groenten Gh",
    "sg:phone":"+31 38 337 0099",
    "sg:postcode":"8271 RG",
    "sg:province":"Overijssel",
    "wof:name":"Firma Postuma Kampen",
    "wof:placetype":"venue"
},
  "geometry": {"coordinates":[5.935624,52.554619],"type":"Point"}
}