{
  "type": "Feature",
  "properties": {
    "addr:full":"Bouwerij 81 Amstelveen North Holland 1185 XW",
    "addr:housenumber":"81",
    "addr:postcode":"1185 xw",
    "addr:street":"Bouwerij",
    "iso:country":"NL",
    "sg:address":"Bouwerij 81",
    "sg:city":"Amstelveen",
    "sg:orig_category":"Public Relationbureaus",
    "sg:phone":"+31 20 640 7878",
    "sg:postcode":"1185 XW",
    "sg:province":"North Holland",
    "wof:name":"Vgrp Marketing Communications",
    "wof:placetype":"venue"
},
  "geometry": {"coordinates":[4.837614,52.279835],"type":"Point"}
}