{
  "type": "Feature",
  "properties": {
    "addr:full":"Boterdijk 26 Siebengewald Limburg 5853 BX",
    "addr:housenumber":"26",
    "addr:postcode":"5853 bx",
    "addr:street":"Boterdijk",
    "iso:country":"NL",
    "sg:address":"Boterdijk 26",
    "sg:city":"Siebengewald",
    "sg:orig_category":"Wegen And Sportterreinen",
    "sg:phone":"+31 485 441 926",
    "sg:postcode":"5853 BX",
    "sg:province":"Limburg",
    "wof:name":"Van Der Aa",
    "wof:placetype":"venue"
},
  "geometry": {"coordinates":[6.1020522118,51.6534309387],"type":"Point"}
}