{
  "type": "Feature",
  "properties": {
    "addr:full":"K Hoogstr 23 Vlaardingen Zuid-Holland 3131 BH",
    "addr:housenumber":"23",
    "addr:postcode":"3131 bh",
    "addr:street":"Hoogstr",
    "iso:country":"NL",
    "sg:address":"K Hoogstr 23",
    "sg:city":"Vlaardingen",
    "sg:orig_category":"Opticiens",
    "sg:phone":"+31 10 434 8450",
    "sg:postcode":"3131 BH",
    "sg:province":"Zuid-Holland",
    "wof:name":"Huis Argus, Het",
    "wof:placetype":"venue"
},
  "geometry": {"coordinates":[4.3444480896,51.9124298096],"type":"Point"}
}