{
  "type": "Feature",
  "properties": {
    "addr:full":"Jan Pieterszoon Coenstr 131 Utrecht Utrecht 3531 ES",
    "addr:housenumber":"131",
    "addr:postcode":"3531 es",
    "addr:street":"Jan Pieterszoon Coenstr",
    "iso:country":"NL",
    "sg:address":"Jan Pieterszoon Coenstr 131",
    "sg:city":"Utrecht",
    "sg:orig_category":"Kappers",
    "sg:phone":"+31 30 299 0539",
    "sg:postcode":"3531 ES",
    "sg:province":"Utrecht",
    "wof:name":"Kapsalon Ferid",
    "wof:placetype":"venue"
},
  "geometry": {"coordinates":[5.0969810486,52.0929107666],"type":"Point"}
}