{
  "type": "Feature",
  "properties": {
    "addr:full":"Torenwacht 55 Leiderdorp Zuid-Holland 2353 DB",
    "addr:housenumber":"55",
    "addr:postcode":"2353 db",
    "addr:street":"Torenwacht",
    "iso:country":"NL",
    "sg:address":"Torenwacht 55",
    "sg:city":"Leiderdorp",
    "sg:orig_category":"Vertaal- And Tolkenbureaus",
    "sg:phone":"+31 71 541 6724",
    "sg:postcode":"2353 DB",
    "sg:province":"Zuid-Holland",
    "wof:name":"M H Beem",
    "wof:placetype":"venue"
},
  "geometry": {"coordinates":[4.537235,52.171612],"type":"Point"}
}