{
  "type": "Feature",
  "properties": {
    "iso:country":"NL",
    "sg:address":"Nieuwegr 10",
    "sg:city":"Soest",
    "sg:orig_category":"Video - Faciliteiten En Producties",
    "sg:phone":"+31 35 603 3552",
    "sg:postcode":"3763 LB",
    "sg:province":"Utrecht",
    "wof:name":"Sbt",
    "wof:placetype":"venue"
},
  "geometry": {"coordinates":[5.300385,52.184044],"type":"Point"}
}