{
  "type": "Feature",
  "properties": {
    "iso:country":"NL",
    "sg:address":"Rosmarynstg 8",
    "sg:city":"Amsterdam",
    "sg:orig_category":"Antiquariaten",
    "sg:phone":"+31 20 428 4790",
    "sg:postcode":"1012 RP",
    "sg:province":"Noord-Holland",
    "wof:name":"Straat",
    "wof:placetype":"venue"
},
  "geometry": {"coordinates":[4.889382,52.370502],"type":"Point"}
}