{
  "type": "Feature",
  "properties": {
    "addr:full":"Roderwolderwg 16 Foxwolde Drenthe 9314 TB",
    "addr:housenumber":"16",
    "addr:postcode":"9314 tb",
    "addr:street":"Roderwolderwg",
    "iso:country":"NL",
    "sg:address":"Roderwolderwg 16",
    "sg:city":"Foxwolde",
    "sg:orig_category":"Product-Promotie",
    "sg:phone":"+31 50 503 2678",
    "sg:postcode":"9314 TB",
    "sg:province":"Drenthe",
    "wof:name":"Diemark",
    "wof:placetype":"venue"
},
  "geometry": {"coordinates":[6.458454,53.157146],"type":"Point"}
}