{
  "type": "Feature",
  "properties": {
    "addr:full":"Schrassertstr 23 Nykerk Gld Gelderland 3861 KK",
    "addr:housenumber":"23",
    "addr:postcode":"3861 kk",
    "addr:street":"Schrassertstr;Gld Gelderland",
    "iso:country":"NL",
    "sg:address":"Schrassertstr 23",
    "sg:city":"Nykerk Gld",
    "sg:orig_category":"Kantoor- En Secretariaatsservice",
    "sg:phone":"+31 33 246 0633",
    "sg:postcode":"3861 KK",
    "sg:province":"Gelderland",
    "wof:name":"Schoon, P J",
    "wof:placetype":"venue"
},
  "geometry": {"coordinates":[5.4875330925,52.2271461487],"type":"Point"}
}