{
  "type": "Feature",
  "properties": {
    "addr:full":"Opwettenseweg 74 Nuenen Noord-Brabant 5672 AJ",
    "addr:housenumber":"74",
    "addr:postcode":"5672 aj",
    "addr:street":"Opwettenseweg",
    "iso:country":"NL",
    "sg:address":"Opwettenseweg 74",
    "sg:city":"Nuenen",
    "sg:orig_category":"Kunst And Kunstenaarsbenodigdheden",
    "sg:phone":"+31 40 284 1583",
    "sg:postcode":"5672 AJ",
    "sg:province":"Noord-Brabant",
    "wof:name":"Galerie De Kei Vof",
    "wof:placetype":"venue"
},
  "geometry": {"coordinates":[5.538704,51.466236],"type":"Point"}
}