{
  "type": "Feature",
  "properties": {
    "iso:country":"NL",
    "sg:address":"Stoelmatter 8",
    "sg:city":"Wateringen",
    "sg:orig_category":"Keukens",
    "sg:phone":"+31 174 388 800",
    "sg:postcode":"2292 JL",
    "sg:province":"Zuid-Holland",
    "wof:name":"Kitchen King",
    "wof:placetype":"venue"
},
  "geometry": {"coordinates":[4.293105,52.015148],"type":"Point"}
}