{
  "type": "Feature",
  "properties": {
    "iso:country":"NL",
    "sg:address":"Tudderenderwg 64",
    "sg:city":"Sittard",
    "sg:orig_category":"Verenigingen En Stichtingen",
    "sg:phone":"+31 46 400 0606",
    "sg:postcode":"6137 CG",
    "sg:province":"Limburg",
    "wof:name":"Tuhejo",
    "wof:placetype":"venue"
},
  "geometry": {"coordinates":[5.882369,51.003357],"type":"Point"}
}