{
  "type": "Feature",
  "properties": {
    "addr:full":"Columbusweg 24 Venlo Limburg 5928 LC",
    "addr:housenumber":"24",
    "addr:postcode":"5928 lc",
    "addr:street":"Columbusweg",
    "iso:country":"NL",
    "sg:address":"Columbusweg 24",
    "sg:city":"Venlo",
    "sg:classifiers":[
        {
            "category":"Retail",
            "subcategory":"Storage",
            "type":"Services"
        }
    ],
    "sg:phone":"+31 77 389 4444",
    "sg:postcode":"5928 LC",
    "sg:province":"Limburg",
    "sg:tags":[
        "opslag",
        "bewaring"
    ],
    "wof:name":"Vitesse Logistics Bv",
    "wof:placetype":"venue"
},
  "geometry": {"coordinates":[6.0976519585,51.3979263306],"type":"Point"}
}