{
  "type": "Feature",
  "properties": {
    "addr:full":"Spireastraat 4 Musselkanaal Groningen 9581 CZ",
    "addr:housenumber":"4",
    "addr:postcode":"9581",
    "addr:street":"Spireastraat",
    "iso:country":"NL",
    "sg:address":"Spireastraat 4",
    "sg:city":"Musselkanaal",
    "sg:classifiers":[
        {
            "category":"Education",
            "subcategory":"Preschool",
            "type":"Public Place"
        }
    ],
    "sg:phone":"+31 599 416 236",
    "sg:postcode":"9581 CZ",
    "sg:province":"Groningen",
    "sg:tags":[
        "kleuteronderwijs",
        "basis-"
    ],
    "wof:name":"Openbare Basisschool De Musselhorst",
    "wof:placetype":"venue"
},
  "geometry": {"coordinates":[7.011267,52.937508],"type":"Point"}
}