{
  "type": "Feature",
  "properties": {
    "addr:full":"Kon Julianastr 15 Gulpen Limburg 6271 CB",
    "addr:housenumber":"15",
    "addr:postcode":"6271 cb",
    "addr:street":"Kon;Gulpen Limburg",
    "iso:country":"NL",
    "sg:address":"Kon Julianastr 15",
    "sg:city":"Gulpen",
    "sg:orig_category":"Natuurvoeding En Reformartikelen",
    "sg:phone":"+31 43 450 4361",
    "sg:postcode":"6271 CB",
    "sg:province":"Limburg",
    "wof:name":"Allfit",
    "wof:placetype":"venue"
},
  "geometry": {"coordinates":[5.887173,50.81694],"type":"Point"}
}