{
  "type": "Feature",
  "properties": {
    "addr:full":"Lekdijk 73 Nieuw Lekkerland Zuid-Holland 2957 CD",
    "addr:housenumber":"73",
    "addr:postcode":"lekkerland;2957 cd",
    "addr:street":"Lekdijk",
    "iso:country":"NL",
    "sg:address":"Lekdijk 73",
    "sg:city":"Nieuw Lekkerland",
    "sg:orig_category":"Kaas",
    "sg:phone":"+31 184 684 213",
    "sg:postcode":"2957 CD",
    "sg:province":"Zuid-Holland",
    "wof:name":"Vliet, Van",
    "wof:placetype":"venue"
},
  "geometry": {"coordinates":[4.6970992088,51.8926887512],"type":"Point"}
}