{
  "type": "Feature",
  "properties": {
    "addr:full":"Haanwijk 3 Sint Michielsgestel Noord-Brabant 5271 VG",
    "addr:housenumber":"3;michielsgestel",
    "addr:postcode":"5271 vg",
    "addr:street":"Haanwijk",
    "iso:country":"NL",
    "sg:address":"Haanwijk 3",
    "sg:city":"Sint Michielsgestel",
    "sg:orig_category":"Farmaceutische Producten Gh",
    "sg:phone":"+31 73 551 2359",
    "sg:postcode":"5271 VG",
    "sg:province":"Noord-Brabant",
    "wof:name":"B.N.F. Bink",
    "wof:placetype":"venue"
},
  "geometry": {"coordinates":[5.322634,51.654228],"type":"Point"}
}