{
  "type": "Feature",
  "properties": {
    "addr:full":"Binnenpad 41 Giethoorn Overijssel 8355 BR",
    "addr:housenumber":"41",
    "addr:postcode":"8355 br",
    "addr:street":"Binnenpad",
    "iso:country":"NL",
    "sg:address":"Binnenpad 41",
    "sg:city":"Giethoorn",
    "sg:orig_category":"Keramische Producten Fab",
    "sg:phone":"+31 521 362 040",
    "sg:postcode":"8355 BR",
    "sg:province":"Overijssel",
    "wof:name":"Pottenbakkerij Rhoda",
    "wof:placetype":"venue"
},
  "geometry": {"coordinates":[6.090005,52.724594],"type":"Point"}
}