{
  "type": "Feature",
  "properties": {
    "addr:full":"Raamsteeg 24 Haarlem Noord-Holland 2011 BH",
    "addr:housenumber":"24",
    "addr:postcode":"2011 bh",
    "addr:street":"Raamsteeg",
    "iso:country":"NL",
    "sg:address":"Raamsteeg 24",
    "sg:city":"Haarlem",
    "sg:orig_category":"Onderhoudswerken",
    "sg:phone":"+31 6 21538949",
    "sg:postcode":"2011 BH",
    "sg:province":"Noord-Holland",
    "wof:name":"Kuiper, F",
    "wof:placetype":"venue"
},
  "geometry": {"coordinates":[4.642563,52.377777],"type":"Point"}
}