{
  "type": "Feature",
  "properties": {
    "addr:full":"De Werf 7 Loenen A/D Vecht Utrecht 3632 AE",
    "addr:housenumber":"7;a / d",
    "addr:postcode":"3632 ae",
    "addr:street":"De Werf;Vecht",
    "iso:country":"NL",
    "sg:address":"De Werf 7",
    "sg:city":"Loenen A/D Vecht",
    "sg:orig_category":"Geluidsopnamen",
    "sg:phone":"+31 294 237 557",
    "sg:postcode":"3632 AE",
    "sg:province":"Utrecht",
    "wof:name":"Stu Stu Studio",
    "wof:placetype":"venue"
},
  "geometry": {"coordinates":[5.021896,52.209732],"type":"Point"}
}