{
  "type": "Feature",
  "properties": {
    "addr:full":"Wilhelminakan O 43 Oosterhout Nb Noord-Brabant 4905 AG",
    "addr:housenumber":"43",
    "addr:postcode":"4905",
    "iso:country":"NL",
    "sg:address":"Wilhelminakan O 43",
    "sg:city":"Oosterhout Nb",
    "sg:orig_category":"Wasserijen",
    "sg:phone":"+31 162 453 230",
    "sg:postcode":"4905 AG",
    "sg:province":"Noord-Brabant",
    "wof:name":"Juliana Bv, Wasserij",
    "wof:placetype":"venue"
},
  "geometry": {"coordinates":[4.8462538719,51.6458587646],"type":"Point"}
}