{
  "type": "Feature",
  "properties": {
    "addr:full":"De Hoef Oz 34 De Hoef Utrecht 1426 AE",
    "addr:housenumber":"34",
    "addr:postcode":"1426 ae",
    "addr:street":"De Hoef Oz",
    "iso:country":"NL",
    "sg:address":"De Hoef Oz 34",
    "sg:city":"De Hoef",
    "sg:orig_category":"Architecten En Architectenbureaus",
    "sg:phone":"+31 297 593 283",
    "sg:postcode":"1426 AE",
    "sg:province":"Utrecht",
    "wof:name":"Koeleman, Porton & Van 'T Hul",
    "wof:placetype":"venue"
},
  "geometry": {"coordinates":[4.815453,52.204426],"type":"Point"}
}