{
  "type": "Feature",
  "properties": {
    "addr:full":"Westeinde 141 S Gravenhage Zuid-Holland 2512 GW",
    "addr:housenumber":"141;gravenhage",
    "addr:postcode":"2512 gw",
    "addr:street":"Westeinde;S",
    "iso:country":"NL",
    "sg:address":"Westeinde 141",
    "sg:city":"S Gravenhage",
    "sg:orig_category":"Kappers",
    "sg:phone":"+31 70 365 9289",
    "sg:postcode":"2512 GW",
    "sg:province":"Zuid-Holland",
    "wof:name":"West",
    "wof:placetype":"venue"
},
  "geometry": {"coordinates":[4.30618,52.073212],"type":"Point"}
}