{
  "type": "Feature",
  "properties": {
    "addr:full":"De Berken 8 Nyeveen Drenthe 7948 AX",
    "addr:housenumber":"8",
    "addr:postcode":"7948 ax",
    "addr:street":"De Berken",
    "iso:country":"NL",
    "sg:address":"De Berken 8",
    "sg:city":"Nyeveen",
    "sg:orig_category":"Geluidsinstallaties - Verhuur",
    "sg:phone":"+31 522 490 222",
    "sg:postcode":"7948 AX",
    "sg:province":"Drenthe",
    "wof:name":"Frontstage Geluidstechniek",
    "wof:placetype":"venue"
},
  "geometry": {"coordinates":[6.160105,52.725842],"type":"Point"}
}