{
  "type": "Feature",
  "properties": {
    "addr:full":"Friezenstr 3 Rosmalen Noord-Brabant 5249 JT",
    "addr:housenumber":"3",
    "addr:postcode":"5249 jt",
    "addr:street":"Friezenstr",
    "iso:country":"NL",
    "sg:address":"Friezenstr 3",
    "sg:city":"Rosmalen",
    "sg:classifiers":[
        {
            "category":"Home & Garden",
            "subcategory":"Hardware",
            "type":"Retail Goods"
        }
    ],
    "sg:phone":"+31 73 521 7048",
    "sg:postcode":"5249 JT",
    "sg:province":"Noord-Brabant",
    "sg:tags":[
        "machine",
        "-",
        "metaalbewerking"
    ],
    "wof:name":"Sts Group",
    "wof:placetype":"venue"
},
  "geometry": {"coordinates":[5.40014,51.727051],"type":"Point"}
}