{
  "type": "Feature",
  "properties": {
    "addr:full":"A J Ernststr 601 Amsterdam Noord-Holland 1082 LE",
    "addr:housenumber":"601",
    "addr:postcode":"1082 le",
    "addr:street":"A",
    "iso:country":"NL",
    "sg:address":"A J Ernststr 601",
    "sg:city":"Amsterdam",
    "sg:orig_category":"Positiekleding",
    "sg:phone":"+31 20 644 3344",
    "sg:postcode":"1082 LE",
    "sg:province":"Noord-Holland",
    "sg:website":"http://www.ruimschoots.nl",
    "wof:name":"Ruimschoots Positiemode",
    "wof:placetype":"venue"
},
  "geometry": {"coordinates":[4.87756,52.330521],"type":"Point"}
}