{
  "type": "Feature",
  "properties": {
    "addr:full":"Mezenveld 112 Emmen Drenthe 7827 BX",
    "addr:housenumber":"112",
    "addr:postcode":"7827 bx",
    "addr:street":"Mezenveld",
    "iso:country":"NL",
    "sg:address":"Mezenveld 112",
    "sg:city":"Emmen",
    "sg:orig_category":"Autorijscholen",
    "sg:phone":"+31 591 612 241",
    "sg:postcode":"7827 BX",
    "sg:province":"Drenthe",
    "sg:website":"http://www.rijschool-snijder.nl",
    "wof:name":"Snijder, Richard",
    "wof:placetype":"venue"
},
  "geometry": {"coordinates":[6.900693,52.743877],"type":"Point"}
}