{
  "type": "Feature",
  "properties": {
    "addr:full":"Katwijkerbroek 18 Katwijk Zh South Holland 2223 XP",
    "addr:housenumber":"18",
    "addr:postcode":"zh;2223 xp",
    "addr:street":"Katwijkerbroek",
    "iso:country":"NL",
    "sg:address":"Katwijkerbroek 18",
    "sg:city":"Katwijk Zh",
    "sg:orig_category":"Goederenvervoer Over De Weg",
    "sg:phone":"+31 71 401 3574",
    "sg:postcode":"2223 XP",
    "sg:province":"South Holland",
    "wof:name":"H.A. De Vries & Zn",
    "wof:placetype":"venue"
},
  "geometry": {"coordinates":[4.425501,52.183746],"type":"Point"}
}