{
  "type": "Feature",
  "properties": {
    "addr:full":"Hoogbrugstr 36 Maastricht Limburg 6221 CR",
    "addr:housenumber":"36",
    "addr:postcode":"6221 cr",
    "addr:street":"Hoogbrugstr",
    "iso:country":"NL",
    "sg:address":"Hoogbrugstr 36",
    "sg:city":"Maastricht",
    "sg:orig_category":"Homeopathie",
    "sg:phone":"+31 43 326 1999",
    "sg:postcode":"6221 CR",
    "sg:province":"Limburg",
    "wof:name":"Schr\u00f7Der, P B",
    "wof:placetype":"venue"
},
  "geometry": {"coordinates":[5.700746,50.847515],"type":"Point"}
}