{
  "type": "Feature",
  "properties": {
    "addr:full":"L Couperusstr 25 Amsterdam Noord-Holland 1064 CA",
    "addr:housenumber":"25",
    "addr:postcode":"1064 ca",
    "iso:country":"NL",
    "sg:address":"L Couperusstr 25",
    "sg:city":"Amsterdam",
    "sg:orig_category":"Autorijscholen",
    "sg:phone":"+31 20 447 0866",
    "sg:postcode":"1064 CA",
    "sg:province":"Noord-Holland",
    "sg:website":"http://www.dester.net",
    "wof:name":"Ster, De",
    "wof:placetype":"venue"
},
  "geometry": {"coordinates":[-94.58503,38.350479],"type":"Point"}
}