{
  "type": "Feature",
  "properties": {
    "iso:country":"NL",
    "sg:address":"Exloerkyl N 1",
    "sg:city":"Tweede Exloermond",
    "sg:orig_category":"Veenderijen",
    "sg:phone":"+31 599 662 504",
    "sg:postcode":"9571 AM",
    "sg:province":"Provincie Drenthe",
    "wof:name":"Oosting, J",
    "wof:placetype":"venue"
},
  "geometry": {"coordinates":[6.916471,52.901325],"type":"Point"}
}