{
  "type": "Feature",
  "properties": {
    "addr:full":"Mastbosstr 105 Breda Noord-Brabant 4812 PB",
    "addr:housenumber":"105",
    "addr:postcode":"4812 pb",
    "iso:country":"NL",
    "sg:address":"Mastbosstr 105",
    "sg:city":"Breda",
    "sg:orig_category":"Parketvloeren",
    "sg:phone":"+31 76 514 0610",
    "sg:postcode":"4812 PB",
    "sg:province":"Noord-Brabant",
    "wof:name":"Stadhouders Parket",
    "wof:placetype":"venue"
},
  "geometry": {"coordinates":[4.743321,51.571247],"type":"Point"}
}