{
  "type": "Feature",
  "properties": {
    "iso:country":"NL",
    "sg:address":"Schoterlandsewg 58",
    "sg:city":"Nieuwehorne",
    "sg:orig_category":"Voegwerken",
    "sg:phone":"+31 513 542 191",
    "sg:postcode":"8414 LX",
    "sg:province":"Provincie Friesland",
    "wof:name":"Ijtsma Voegwerken",
    "wof:placetype":"venue"
},
  "geometry": {"coordinates":[6.057968,52.950958],"type":"Point"}
}