{
  "type": "Feature",
  "properties": {
    "addr:full":"Schoterlandsewg 58 Nieuwehorne Provincie Friesland 8414 LX",
    "addr:housenumber":"58",
    "addr:postcode":"8414 lx",
    "addr:street":"Schoterlandsewg;Provincie Friesland",
    "iso:country":"NL",
    "sg:address":"Schoterlandsewg 58",
    "sg:city":"Nieuwehorne",
    "sg:orig_category":"Voegwerken",
    "sg:phone":"+31 513 542 191",
    "sg:postcode":"8414 LX",
    "sg:province":"Provincie Friesland",
    "wof:name":"Ijtsma Voegwerken",
    "wof:placetype":"venue"
},
  "geometry": {"coordinates":[6.057968,52.950958],"type":"Point"}
}