{
  "type": "Feature",
  "properties": {
    "addr:full":"De Mossel 18-20 Noord-Scharwoude Noord-Holland 1723 HZ",
    "addr:housenumber":"18-20",
    "addr:postcode":"noord-scharwoude;1723 hz",
    "addr:street":"De Mossel",
    "iso:country":"NL",
    "sg:address":"De Mossel 18-20",
    "sg:city":"Noord-Scharwoude",
    "sg:orig_category":"Goederenvervoer Over De Weg",
    "sg:phone":"+31 226 313 141",
    "sg:postcode":"1723 HZ",
    "sg:province":"Noord-Holland",
    "wof:name":"De Waard Transport Bv",
    "wof:placetype":"venue"
},
  "geometry": {"coordinates":[4.80248,52.704128],"type":"Point"}
}