{
  "type": "Feature",
  "properties": {
    "iso:country":"NL",
    "sg:address":"Zwitserlandstr 25",
    "sg:city":"Alphen Aan Den Ryn",
    "sg:classifiers":[
        {
            "category":"Personal",
            "subcategory":"Nail Salon",
            "type":"Services"
        }
    ],
    "sg:phone":"+31 172 424 600",
    "sg:postcode":"2408 CN",
    "sg:province":"Zuid-Holland",
    "sg:tags":[
        "pedicure"
    ],
    "wof:name":"Verkerk, A",
    "wof:placetype":"venue"
},
  "geometry": {"coordinates":[4.646362,52.12344],"type":"Point"}
}