{
  "type": "Feature",
  "properties": {
    "iso:country":"NL",
    "sg:address":"Rosendaalseweg 503",
    "sg:city":"Arnhem",
    "sg:orig_category":"Autokeuringen",
    "sg:phone":"+31 26 443 2900",
    "sg:postcode":"6824 KL",
    "sg:province":"Gelderland",
    "wof:name":"Shell",
    "wof:placetype":"venue"
},
  "geometry": {"coordinates":[5.935225,51.996445],"type":"Point"}
}