{
  "type": "Feature",
  "properties": {
    "addr:full":"Noorderwg 59 Slochteren Groningen 9621 BN",
    "addr:housenumber":"59",
    "addr:postcode":"9621 bn",
    "addr:street":"Noorderwg",
    "iso:country":"NL",
    "sg:address":"Noorderwg 59",
    "sg:city":"Slochteren",
    "sg:orig_category":"Geluidsinstallaties",
    "sg:phone":"+31 6 52055831",
    "sg:postcode":"9621 BN",
    "sg:province":"Groningen",
    "wof:name":"Jansen, Rick",
    "wof:placetype":"venue"
},
  "geometry": {"coordinates":[6.79802,53.211872],"type":"Point"}
}