{
  "type": "Feature",
  "properties": {
    "addr:full":"Groenland 7 Edam Noord-Holland 1135 TE",
    "addr:housenumber":"7",
    "addr:postcode":"1135 te",
    "addr:street":"Groenland",
    "iso:country":"NL",
    "sg:address":"Groenland 7",
    "sg:city":"Edam",
    "sg:orig_category":"Architecten En Architectenbureaus",
    "sg:phone":"+31 299 373 483",
    "sg:postcode":"1135 TE",
    "sg:province":"Noord-Holland",
    "wof:name":"Waterland Tekenbureaus",
    "wof:placetype":"venue"
},
  "geometry": {"coordinates":[5.050306,52.514252],"type":"Point"}
}