{
  "type": "Feature",
  "properties": {
    "iso:country":"NL",
    "sg:address":"Pleimuiden 8D",
    "sg:city":"Amsterdam",
    "sg:orig_category":"Autorijscholen",
    "sg:phone":"+31 20 447 0575",
    "sg:postcode":"1046 AG",
    "sg:province":"Noord-Holland",
    "wof:name":"Trilling, Verkeersschool",
    "wof:placetype":"venue"
},
  "geometry": {"coordinates":[4.786623,52.391041],"type":"Point"}
}