{
  "type": "Feature",
  "properties": {
    "addr:full":"Oorsprongpk 1Sout Utrecht Utrecht 3581 ES",
    "addr:housenumber":"1sout",
    "addr:postcode":"3581 es",
    "iso:country":"NL",
    "sg:address":"Oorsprongpk 1Sout",
    "sg:city":"Utrecht",
    "sg:orig_category":"Podotherapeuten",
    "sg:phone":"+31 30 231 2328",
    "sg:postcode":"3581 ES",
    "sg:province":"Utrecht",
    "wof:name":"Podotherapie Wittevrouwen",
    "wof:placetype":"venue"
},
  "geometry": {"coordinates":[5.137087,52.095238],"type":"Point"}
}