{
  "type": "Feature",
  "properties": {
    "addr:full":"Kamperstraat 39 Zwolle NL.08 8011 LK",
    "addr:housenumber":"39",
    "addr:postcode":"8011 lk",
    "addr:street":"Kamperstraat",
    "iso:country":"NL",
    "sg:address":"Kamperstraat 39",
    "sg:city":"Zwolle",
    "sg:classifiers":[
        {
            "category":"Bars & Pubs",
            "type":"Food & Drink"
        }
    ],
    "sg:phone":"+31 38 423 2106",
    "sg:postcode":"8011 LK",
    "sg:province":"NL.08",
    "wof:name":"Zero Zero",
    "wof:placetype":"venue"
},
  "geometry": {"coordinates":[6.088552,52.511795],"type":"Point"}
}