{
  "type": "Feature",
  "properties": {
    "addr:full":"Hoofdstraat 45 Stadskanaal Groningen 9501 CM",
    "addr:housenumber":"45",
    "addr:postcode":"9501 cm",
    "addr:street":"Hoofdstraat",
    "iso:country":"NL",
    "sg:address":"Hoofdstraat 45",
    "sg:city":"Stadskanaal",
    "sg:orig_category":"Beautyfarms And Sauna'S",
    "sg:phone":"+31 599 621 111",
    "sg:postcode":"9501 CM",
    "sg:province":"Groningen",
    "wof:name":"Schoonheidssalon-Zonnestudio Margreet Ku",
    "wof:placetype":"venue"
},
  "geometry": {"coordinates":[6.952575,52.987274],"type":"Point"}
}