{
  "type": "Feature",
  "properties": {
    "addr:full":"Molenbeek 7 Kaatsheuvel North Brabant 5172 CH",
    "addr:housenumber":"7",
    "addr:postcode":"5172",
    "addr:street":"Molenbeek",
    "iso:country":"NL",
    "sg:address":"Molenbeek 7",
    "sg:city":"Kaatsheuvel",
    "sg:orig_category":"Boekhouders",
    "sg:phone":"+31 416 273 852",
    "sg:postcode":"5172 CH",
    "sg:province":"North Brabant",
    "wof:name":"Administratiekantoor A. V. Boxtel",
    "wof:placetype":"venue"
},
  "geometry": {"coordinates":[5.018592,51.652676],"type":"Point"}
}