{
  "type": "Feature",
  "properties": {
    "addr:full":"Vyverhofstr 49E Rotterdam South Holland 3032 SC",
    "addr:housenumber":"49e",
    "addr:postcode":"3032 sc",
    "addr:street":"Vyverhofstr",
    "iso:country":"NL",
    "sg:address":"Vyverhofstr 49E",
    "sg:city":"Rotterdam",
    "sg:orig_category":"Verpleegkundigen - Particulier",
    "sg:phone":"+31 6 52143390",
    "sg:postcode":"3032 SC",
    "sg:province":"South Holland",
    "wof:name":"Huisden, M",
    "wof:placetype":"venue"
},
  "geometry": {"coordinates":[4.476285,51.929615],"type":"Point"}
}