{
  "type": "Feature",
  "properties": {
    "addr:full":"Bornerbroeksewg 2 Enter Overijssel 7468 RM",
    "addr:housenumber":"2",
    "addr:postcode":"7468 rm",
    "addr:street":"Bornerbroeksewg",
    "iso:country":"NL",
    "sg:address":"Bornerbroeksewg 2",
    "sg:city":"Enter",
    "sg:orig_category":"Apotheken",
    "sg:phone":"+31 547 383 366",
    "sg:postcode":"7468 RM",
    "sg:province":"Overijssel",
    "wof:name":"Enter",
    "wof:placetype":"venue"
},
  "geometry": {"coordinates":[-76.841904,40.463078],"type":"Point"}
}