{
  "type": "Feature",
  "properties": {
    "addr:full":"Molenstr 83 Ede Gld Gelderland 6712 CT",
    "addr:housenumber":"83",
    "addr:postcode":"6712 ct",
    "addr:street":"Molenstr;Gld Gelderland",
    "iso:country":"NL",
    "sg:address":"Molenstr 83",
    "sg:city":"Ede Gld",
    "sg:orig_category":"Postzegels",
    "sg:phone":"+31 318 618 074",
    "sg:postcode":"6712 CT",
    "sg:province":"Gelderland",
    "wof:name":"Triest Bv, Van",
    "wof:placetype":"venue"
},
  "geometry": {"coordinates":[5.663557,52.046017],"type":"Point"}
}