{
  "type": "Feature",
  "properties": {
    "addr:full":"Koningin Julianaweg 44 Leidschendam Zuid-Holland 2264 BD",
    "addr:housenumber":"44",
    "addr:postcode":"2264 bd",
    "addr:street":"Koningin Julianaweg",
    "iso:country":"NL",
    "sg:address":"Koningin Julianaweg 44",
    "sg:city":"Leidschendam",
    "sg:orig_category":"Overheidsdiensten",
    "sg:phone":"+31 70 320 0033",
    "sg:postcode":"2264 BD",
    "sg:province":"Zuid-Holland",
    "wof:name":"De Sater",
    "wof:placetype":"venue"
},
  "geometry": {"coordinates":[4.3938040733,52.0835990906],"type":"Point"}
}