{
  "type": "Feature",
  "properties": {
    "addr:full":"Bilderdijklaan 1 Rijswijk Zh Zuid-Holland 2281 SM",
    "addr:housenumber":"1",
    "addr:postcode":"zh;2281 sm",
    "addr:street":"Bilderdijklaan",
    "iso:country":"NL",
    "sg:address":"Bilderdijklaan 1",
    "sg:city":"Rijswijk Zh",
    "sg:orig_category":"Fotolaboratoria",
    "sg:phone":"+31 70 395 0524",
    "sg:postcode":"2281 SM",
    "sg:province":"Zuid-Holland",
    "wof:name":"Super Photo Snelservice",
    "wof:placetype":"venue"
},
  "geometry": {"coordinates":[4.336576,52.058537],"type":"Point"}
}