{
  "type": "Feature",
  "properties": {
    "addr:full":"Populierenlaan 3 Rhenen Utrecht 3911 GR",
    "addr:housenumber":"3",
    "addr:postcode":"3911",
    "addr:street":"Populierenlaan",
    "iso:country":"NL",
    "sg:address":"Populierenlaan 3",
    "sg:city":"Rhenen",
    "sg:orig_category":"Fitnesscentra",
    "sg:phone":"+31 317 616 365",
    "sg:postcode":"3911 GR",
    "sg:province":"Utrecht",
    "wof:name":"Sportschool Van Doorn",
    "wof:placetype":"venue"
},
  "geometry": {"coordinates":[5.569771,51.961781],"type":"Point"}
}