{
  "type": "Feature",
  "properties": {
    "addr:full":"Nassaulaan 18 Baarle Nassau Noord-Brabant 5111 XE",
    "addr:housenumber":"18",
    "addr:postcode":"5111 xe",
    "addr:street":"Nassaulaan",
    "iso:country":"NL",
    "sg:address":"Nassaulaan 18",
    "sg:city":"Baarle Nassau",
    "sg:orig_category":"Juridische Dienstverlening",
    "sg:phone":"+31 13 507 8875",
    "sg:postcode":"5111 XE",
    "sg:province":"Noord-Brabant",
    "wof:name":"Juridisch Adviesburo Krijger",
    "wof:placetype":"venue"
},
  "geometry": {"coordinates":[4.931858,51.450962],"type":"Point"}
}