{
  "type": "Feature",
  "properties": {
    "addr:full":"Meent 44 Veldhoven North Brabant 5501 JK",
    "addr:housenumber":"44",
    "addr:postcode":"5501 jk",
    "addr:street":"Meent",
    "iso:country":"NL",
    "sg:address":"Meent 44",
    "sg:city":"Veldhoven",
    "sg:orig_category":"Herenmodezaken",
    "sg:phone":"+31 40 255 4738",
    "sg:postcode":"5501 JK",
    "sg:province":"North Brabant",
    "wof:name":"Amici Mannenmode",
    "wof:placetype":"venue"
},
  "geometry": {"coordinates":[5.406302,51.419979],"type":"Point"}
}