{
  "type": "Feature",
  "properties": {
    "addr:full":"Graafseweg 151 'S Hertogenbosch Noord-Brabant 5213 AD",
    "addr:housenumber":"151 ' s",
    "addr:postcode":"5213 ad",
    "addr:street":"Graafseweg",
    "iso:country":"NL",
    "sg:address":"Graafseweg 151",
    "sg:city":"'S Hertogenbosch",
    "sg:classifiers":[
        {
            "category":"Communications",
            "subcategory":"Television Station",
            "type":"Services"
        }
    ],
    "sg:phone":"+31 73 614 7893",
    "sg:postcode":"5213 AD",
    "sg:province":"Noord-Brabant",
    "sg:tags":[
        "video",
        "audio",
        "verhuur"
    ],
    "wof:name":"Hollywood",
    "wof:placetype":"venue"
},
  "geometry": {"coordinates":[5.323092,51.694855],"type":"Point"}
}