{
  "type": "Feature",
  "properties": {
    "addr:full":"Zwembadwg 6 Geldrop North Brabant 5663 PL",
    "addr:housenumber":"6",
    "addr:postcode":"5663 pl",
    "addr:street":"Zwembadwg",
    "iso:country":"NL",
    "sg:address":"Zwembadwg 6",
    "sg:city":"Geldrop",
    "sg:orig_category":"Bloemen En Planten",
    "sg:phone":"+31 40 285 6490",
    "sg:postcode":"5663 PL",
    "sg:province":"North Brabant",
    "wof:name":"Groenrijk Geldrop",
    "wof:placetype":"venue"
},
  "geometry": {"coordinates":[5.556284,51.410229],"type":"Point"}
}