{
  "type": "Feature",
  "properties": {
    "addr:full":"Oostdijk 7 Zuidoostbeemster Noord-Holland 1461 DR",
    "addr:housenumber":"7;1461",
    "addr:postcode":"dr",
    "addr:street":"Oostdijk",
    "iso:country":"NL",
    "sg:address":"Oostdijk 7",
    "sg:city":"Zuidoostbeemster",
    "sg:orig_category":"Marktonderzoekbureaus",
    "sg:phone":"+31 299 402 088",
    "sg:postcode":"1461 DR",
    "sg:province":"Noord-Holland",
    "wof:name":"Hiemstra Communications",
    "wof:placetype":"venue"
},
  "geometry": {"coordinates":[4.97641,52.547104],"type":"Point"}
}