{
  "type": "Feature",
  "properties": {
    "iso:country":"NL",
    "sg:address":"Admiraal De Ruyterweg 19",
    "sg:city":"Papendrecht",
    "sg:orig_category":"Bloemen And Planten",
    "sg:phone":"+31 78 615 1142",
    "sg:postcode":"3354 XA",
    "sg:province":"South Holland",
    "wof:name":"G Van Pelt",
    "wof:placetype":"venue"
},
  "geometry": {"coordinates":[4.697287,51.826832],"type":"Point"}
}