{
  "type": "Feature",
  "properties": {
    "addr:full":"Marktplein 130 Hoofddorp Noord-Holland 2132 DD",
    "addr:housenumber":"130",
    "addr:postcode":"2132 dd",
    "addr:street":"Marktplein",
    "iso:country":"NL",
    "sg:address":"Marktplein 130",
    "sg:city":"Hoofddorp",
    "sg:classifiers":[
        {
            "category":"Fast Food",
            "type":"Food & Drink"
        }
    ],
    "sg:phone":"+31 23 561 6333",
    "sg:postcode":"2132 DD",
    "sg:province":"Noord-Holland",
    "sg:tags":[
        "afhaal",
        "restaurant"
    ],
    "wof:name":"Chinees Specialiteiten Restaurant Jasmin",
    "wof:placetype":"venue"
},
  "geometry": {"coordinates":[4.694003,52.303391],"type":"Point"}
}