{
  "type": "Feature",
  "properties": {
    "iso:country":"NL",
    "sg:address":"Sint Luciensteeg 22",
    "sg:city":"Amsterdam",
    "sg:classifiers":[
        {
            "category":"Shopping",
            "subcategory":"Gifts & Souvenirs",
            "type":"Retail Goods"
        }
    ],
    "sg:phone":"+31 20 422 0784",
    "sg:postcode":"1012 PM",
    "sg:province":"Noord-Holland",
    "sg:tags":[
        "geschenken"
    ],
    "wof:name":"The Go Round Trading",
    "wof:placetype":"venue"
},
  "geometry": {"coordinates":[4.890437,52.37064],"type":"Point"}
}