{
  "type": "Feature",
  "properties": {
    "addr:full":"Beatrixstraat 39A Beneden Leeuwen Gelderland 6658 EJ",
    "addr:housenumber":"39a",
    "addr:postcode":"6658 ej",
    "addr:street":"Beatrixstraat",
    "iso:country":"NL",
    "sg:address":"Beatrixstraat 39A",
    "sg:city":"Beneden Leeuwen",
    "sg:orig_category":"Drukkerijen And Copyshops",
    "sg:phone":"+31 487 595 786",
    "sg:postcode":"6658 EJ",
    "sg:province":"Gelderland",
    "wof:name":"Special-T Workwear Bv",
    "wof:placetype":"venue"
},
  "geometry": {"coordinates":[5.520991,51.880016],"type":"Point"}
}