{
  "type": "Feature",
  "properties": {
    "addr:full":"Koestraat 21 Maastricht Limburg 6211 HR",
    "addr:housenumber":"21",
    "addr:postcode":"6211 hr",
    "addr:street":"Koestraat",
    "iso:country":"NL",
    "sg:address":"Koestraat 21",
    "sg:city":"Maastricht",
    "sg:classifiers":[
        {
            "category":"Fast Food",
            "type":"Food & Drink"
        }
    ],
    "sg:phone":"+31 43 321 5155",
    "sg:postcode":"6211 HR",
    "sg:province":"Limburg",
    "sg:tags":[
        "afhaal",
        "restaurant"
    ],
    "wof:name":"Grillroom Alexandra",
    "wof:placetype":"venue"
},
  "geometry": {"coordinates":[5.692741,50.846561],"type":"Point"}
}