{
  "type": "Feature",
  "properties": {
    "addr:full":"Slotjesveld 15 Oosterhout Nb Noord-Brabant 4902 ZP",
    "addr:housenumber":"15",
    "addr:postcode":"4902 zp",
    "addr:street":"Slotjesveld",
    "iso:country":"NL",
    "sg:address":"Slotjesveld 15",
    "sg:city":"Oosterhout Nb",
    "sg:classifiers":[
        {
            "category":"Education",
            "subcategory":"Preschool",
            "type":"Public Place"
        }
    ],
    "sg:phone":"+31 162 454 052",
    "sg:postcode":"4902 ZP",
    "sg:province":"Noord-Brabant",
    "sg:tags":[
        "kleuteronderwijs",
        "basis-"
    ],
    "wof:name":"Buurthuis De Slotjes",
    "wof:placetype":"venue"
},
  "geometry": {"coordinates":[4.861674,51.637718],"type":"Point"}
}