{
  "type": "Feature",
  "properties": {
    "iso:country":"NL",
    "sg:address":"Eerschotsestraat 92",
    "sg:city":"Sint Oedenrode",
    "sg:classifiers":[
        {
            "category":"Fast Food",
            "type":"Food & Drink"
        }
    ],
    "sg:phone":"+31 413 473 142",
    "sg:postcode":"5491 AD",
    "sg:province":"North Brabant",
    "sg:tags":[
        "afhaal",
        "restaurant"
    ],
    "wof:name":"Snackbar Van Den Dungen Vof",
    "wof:placetype":"venue"
},
  "geometry": {"coordinates":[5.473017,51.567551],"type":"Point"}
}