{
  "type": "Feature",
  "properties": {
    "addr:full":"Beugelstraat 51 Valkenswaard North Brabant 5556 WL",
    "addr:housenumber":"51",
    "addr:postcode":"5556 wl",
    "addr:street":"Beugelstraat",
    "iso:country":"NL",
    "sg:address":"Beugelstraat 51",
    "sg:city":"Valkenswaard",
    "sg:orig_category":"Metalen And Ertsen Gh",
    "sg:phone":"+31 40 206 8458",
    "sg:postcode":"5556 WL",
    "sg:province":"North Brabant",
    "wof:name":"C. Pasma",
    "wof:placetype":"venue"
},
  "geometry": {"coordinates":[5.439104,51.296631],"type":"Point"}
}