{
  "type": "Feature",
  "properties": {
    "addr:full":"Handelsstr 29 Stadskanaal Groningen 9501 EV",
    "addr:housenumber":"29",
    "addr:postcode":"9501 ev",
    "addr:street":"Handelsstr",
    "iso:country":"NL",
    "sg:address":"Handelsstr 29",
    "sg:city":"Stadskanaal",
    "sg:orig_category":"Makelaars En Adviseurs Onroerende Goederen",
    "sg:phone":"+31 599 614 835",
    "sg:postcode":"9501 EV",
    "sg:province":"Groningen",
    "wof:name":"Beuving Vof",
    "wof:placetype":"venue"
},
  "geometry": {"coordinates":[6.932313,52.999928],"type":"Point"}
}