{
  "type": "Feature",
  "properties": {
    "iso:country":"NL",
    "sg:address":"Reespoor 6",
    "sg:city":"Soest",
    "sg:orig_category":"Verenigingen En Stichtingen",
    "sg:phone":"+31 118 626 670",
    "sg:postcode":"3766 JX",
    "sg:province":"Utrecht",
    "wof:name":"Osteogenesis Imperfecta",
    "wof:placetype":"venue"
},
  "geometry": {"coordinates":[5.276269,52.166027],"type":"Point"}
}