{
  "type": "Feature",
  "properties": {
    "addr:full":"Heemraad 27 Naarden Noord-Holland 1412 DM",
    "addr:housenumber":"27",
    "addr:postcode":"1412 dm",
    "addr:street":"Heemraad",
    "iso:country":"NL",
    "sg:address":"Heemraad 27",
    "sg:city":"Naarden",
    "sg:orig_category":"Adviesbureaus Bedrijfsorganisatie",
    "sg:phone":"+31 35 694 9743",
    "sg:postcode":"1412 DM",
    "sg:province":"Noord-Holland",
    "sg:website":"http://www.interimmanager.nl",
    "wof:name":"Bic",
    "wof:placetype":"venue"
},
  "geometry": {"coordinates":[5.145078,52.285858],"type":"Point"}
}