{
  "type": "Feature",
  "properties": {
    "addr:full":"Industriestr 72 Hengelo NL.08 7553 CR",
    "addr:housenumber":"72;nl.08",
    "addr:postcode":"7553 cr",
    "addr:street":"Industriestr",
    "iso:country":"NL",
    "sg:address":"Industriestr 72",
    "sg:city":"Hengelo",
    "sg:orig_category":"Kappers",
    "sg:phone":"+31 74 291 7140",
    "sg:postcode":"7553 CR",
    "sg:province":"NL.08",
    "wof:name":"Paul",
    "wof:placetype":"venue"
},
  "geometry": {"coordinates":[6.786743,52.256573],"type":"Point"}
}