{
  "type": "Feature",
  "properties": {
    "addr:full":"Kerkstraat 29Hs Amsterdam North Holland 1017 GB",
    "addr:housenumber":"29hs",
    "addr:postcode":"1017 gb",
    "addr:street":"Kerkstraat",
    "iso:country":"NL",
    "sg:address":"Kerkstraat 29Hs",
    "sg:city":"Amsterdam",
    "sg:orig_category":"Kinderopvang Behalve Thuis",
    "sg:phone":"+31 20 622 2597",
    "sg:postcode":"1017 GB",
    "sg:province":"North Holland",
    "wof:name":"Kinderdagverblijf Baboffel",
    "wof:placetype":"venue"
},
  "geometry": {"coordinates":[4.885035,52.365852],"type":"Point"}
}