{
  "type": "Feature",
  "properties": {
    "iso:country":"NL",
    "sg:address":"Kerkstraat 29Hs",
    "sg:city":"Amsterdam",
    "sg:orig_category":"Kinderopvang Behalve Thuis",
    "sg:phone":"+31 20 622 2597",
    "sg:postcode":"1017 GB",
    "sg:province":"North Holland",
    "wof:name":"Kinderdagverblijf Baboffel",
    "wof:placetype":"venue"
},
  "geometry": {"coordinates":[4.885035,52.365852],"type":"Point"}
}