{
  "type": "Feature",
  "properties": {
    "iso:country":"NL",
    "sg:address":"Engelandln 178",
    "sg:city":"Zoetermeer",
    "sg:orig_category":"Advocaten En Advocatenkantoren",
    "sg:phone":"+31 79 316 0570",
    "sg:postcode":"2711 DW",
    "sg:province":"Zuid-Holland",
    "wof:name":"Goudriaan, Mr A",
    "wof:placetype":"venue"
},
  "geometry": {"coordinates":[4.489352,52.059746],"type":"Point"}
}