{
  "type": "Feature",
  "properties": {
    "iso:country":"NL",
    "sg:address":"Westmallepad 11",
    "sg:city":"Amsterdam",
    "sg:classifiers":[
        {
            "category":"Education",
            "subcategory":"Preschool",
            "type":"Public Place"
        }
    ],
    "sg:phone":"+31 20 669 2488",
    "sg:postcode":"1066 PP",
    "sg:province":"North Holland",
    "sg:tags":[
        "kleuteronderwijs",
        "basis-"
    ],
    "wof:name":"Katholieke Basisschool De Mijlpaal",
    "wof:placetype":"venue"
},
  "geometry": {"coordinates":[4.806622,52.347424],"type":"Point"}
}