{
  "type": "Feature",
  "properties": {
    "addr:full":"Jansbinnensingel 24 Arnhem Gelderland 6811 AL",
    "addr:housenumber":"24",
    "addr:postcode":"6811 al",
    "addr:street":"Jansbinnensingel",
    "iso:country":"NL",
    "sg:address":"Jansbinnensingel 24",
    "sg:city":"Arnhem",
    "sg:orig_category":"Advocaten And Juridische Adviseurs",
    "sg:phone":"+31 26 370 3701",
    "sg:postcode":"6811 AL",
    "sg:province":"Gelderland",
    "wof:name":"Advocatenkantoor Mr A M Van Rossum",
    "wof:placetype":"venue"
},
  "geometry": {"coordinates":[5.910477,51.983944],"type":"Point"}
}