{
  "type": "Feature",
  "properties": {
    "addr:full":"Voske 4 Baarle Nassau North Brabant 5111 PE",
    "addr:housenumber":"4",
    "addr:postcode":"5111 pe",
    "addr:street":"Voske",
    "iso:country":"NL",
    "sg:address":"Voske 4",
    "sg:city":"Baarle Nassau",
    "sg:orig_category":"Onderhoudswerken",
    "sg:phone":"+31 13 507 8521",
    "sg:postcode":"5111 PE",
    "sg:province":"North Brabant",
    "wof:name":"Haagen",
    "wof:placetype":"venue"
},
  "geometry": {"coordinates":[4.974467,51.449165],"type":"Point"}
}