{
  "type": "Feature",
  "properties": {
    "addr:full":"Dorpsstr 25 Koekange Provincie Drenthe 7958 RK",
    "addr:housenumber":"25",
    "addr:postcode":"7958 rk",
    "addr:street":"Dorpsstr;Provincie Drenthe",
    "iso:country":"NL",
    "sg:address":"Dorpsstr 25",
    "sg:city":"Koekange",
    "sg:orig_category":"Banken",
    "sg:phone":"+31 522 458 510",
    "sg:postcode":"7958 RK",
    "sg:province":"Provincie Drenthe",
    "sg:website":"http://www.rabobank.nl",
    "wof:name":"Rabobank",
    "wof:placetype":"venue"
},
  "geometry": {"coordinates":[6.321218,52.697975],"type":"Point"}
}