{
  "type": "Feature",
  "properties": {
    "addr:full":"Hagelkruispln 2 Tilburg Noord-Brabant 5038 ME",
    "addr:housenumber":"2",
    "addr:postcode":"5038 me",
    "addr:street":"Hagelkruispln",
    "iso:country":"NL",
    "sg:address":"Hagelkruispln 2",
    "sg:city":"Tilburg",
    "sg:orig_category":"Adviesbureaus",
    "sg:phone":"+31 13 468 0104",
    "sg:postcode":"5038 ME",
    "sg:province":"Noord-Brabant",
    "wof:name":"Geurts, L",
    "wof:placetype":"venue"
},
  "geometry": {"coordinates":[5.069132,51.558289],"type":"Point"}
}