{
  "type": "Feature",
  "properties": {
    "addr:full":"Kapelstr 14 Bussum Noord-Holland 1404 HX",
    "addr:housenumber":"14",
    "addr:postcode":"1404 hx",
    "addr:street":"Kapelstr",
    "iso:country":"NL",
    "sg:address":"Kapelstr 14",
    "sg:city":"Bussum",
    "sg:orig_category":"Herenkleding",
    "sg:phone":"+31 6 29434757",
    "sg:postcode":"1404 HX",
    "sg:province":"Noord-Holland",
    "wof:name":"Nr 14",
    "wof:placetype":"venue"
},
  "geometry": {"coordinates":[5.164384,52.274677],"type":"Point"}
}