{
  "type": "Feature",
  "properties": {
    "iso:country":"NL",
    "sg:address":"Hoyerstr 19",
    "sg:city":"Brielle",
    "sg:orig_category":"Schoonheidsinstituten",
    "sg:phone":"+31 181 418 381",
    "sg:postcode":"3232 AD",
    "sg:province":"Zuid-Holland",
    "wof:name":"Senang Brielle",
    "wof:placetype":"venue"
},
  "geometry": {"coordinates":[4.155718,51.898556],"type":"Point"}
}