{
  "type": "Feature",
  "properties": {
    "addr:full":"P Brueghelln 7 Roelofarendsveen Zuid-Holland 2371 RV",
    "addr:housenumber":"7",
    "addr:postcode":"2371 rv",
    "addr:street":"P Brueghelln",
    "iso:country":"NL",
    "sg:address":"P Brueghelln 7",
    "sg:city":"Roelofarendsveen",
    "sg:orig_category":"Autorijscholen",
    "sg:phone":"+31 71 331 2650",
    "sg:postcode":"2371 RV",
    "sg:province":"Zuid-Holland",
    "wof:name":"Bakker, Bert",
    "wof:placetype":"venue"
},
  "geometry": {"coordinates":[4.632897,52.204285],"type":"Point"}
}