{
  "type": "Feature",
  "properties": {
    "addr:full":"Wooldstraat 16 Winterswijk Gelderland 7101 NR",
    "addr:housenumber":"16",
    "addr:postcode":"7101",
    "addr:street":"Wooldstraat;Gelderland;Nr",
    "iso:country":"NL",
    "sg:address":"Wooldstraat 16",
    "sg:city":"Winterswijk",
    "sg:classifiers":[
        {
            "category":"Shopping",
            "subcategory":"Clothing, Apparel, & Fashions",
            "type":"Retail Goods"
        }
    ],
    "sg:phone":"+31 543 516 420",
    "sg:postcode":"7101 NR",
    "sg:province":"Gelderland",
    "sg:tags":[
        "ondergoed",
        "lingerie"
    ],
    "wof:name":"Livera",
    "wof:placetype":"venue"
},
  "geometry": {"coordinates":[6.720675,51.970604],"type":"Point"}
}