{
  "type": "Feature",
  "properties": {
    "iso:country":"NL",
    "sg:address":"J Hobergstr 14",
    "sg:city":"Castricum",
    "sg:orig_category":"Verhuur",
    "sg:phone":"+31 251 670 096",
    "sg:postcode":"1901 PL",
    "sg:province":"North Holland",
    "wof:name":"Giling, John",
    "wof:placetype":"venue"
},
  "geometry": {"coordinates":[4.662572,52.545486],"type":"Point"}
}