{
  "type": "Feature",
  "properties": {
    "iso:country":"NL",
    "sg:address":"Cobaltstr 27",
    "sg:city":"Zoetermeer",
    "sg:classifiers":[
        {
            "category":"Wholesale",
            "subcategory":"Meat",
            "type":"Manufacturing & Wholesale Goods"
        }
    ],
    "sg:phone":"+31 79 362 0000",
    "sg:postcode":"2718 RN",
    "sg:province":"Zuid-Holland",
    "sg:tags":[
        "regeltechniek",
        "en",
        "meet-"
    ],
    "wof:name":"Alflex Bv",
    "wof:placetype":"venue"
},
  "geometry": {"coordinates":[4.516112,52.040707],"type":"Point"}
}