{
  "type": "Feature",
  "properties": {
    "iso:country":"NL",
    "sg:address":"Botenln 22",
    "sg:city":"Eindhoven",
    "sg:orig_category":"Schilders",
    "sg:phone":"+31 40 292 8182",
    "sg:postcode":"5652 CA",
    "sg:province":"Noord-Brabant",
    "wof:name":"Weijers",
    "wof:placetype":"venue"
},
  "geometry": {"coordinates":[5.4376,51.435398],"type":"Point"}
}