{
  "type": "Feature",
  "properties": {
    "addr:full":"Speenkruidlaan 27 Baarn Utrecht 3742 ET",
    "addr:housenumber":"27",
    "addr:postcode":"3742 et",
    "addr:street":"Speenkruidlaan",
    "iso:country":"NL",
    "sg:address":"Speenkruidlaan 27",
    "sg:city":"Baarn",
    "sg:orig_category":"Bedrijfs- And Managementsconsultants",
    "sg:phone":"+31 35 541 8494",
    "sg:postcode":"3742 ET",
    "sg:province":"Utrecht",
    "wof:name":"Marbo",
    "wof:placetype":"venue"
},
  "geometry": {"coordinates":[5.301427,52.200359],"type":"Point"}
}