{
  "type": "Feature",
  "properties": {
    "addr:full":"J. Vd Haagenstraat 26 Den Haag Zuid-Holland 2525 TR",
    "addr:housenumber":"26",
    "addr:postcode":"2525 tr",
    "addr:street":"J. Vd Haagenstraat",
    "iso:country":"NL",
    "sg:address":"J. Vd Haagenstraat 26",
    "sg:city":"Den Haag",
    "sg:orig_category":"Werving And Selectie Van Tijdelijk Personeel And Uitzendkantoren",
    "sg:phone":"+31 70 384 0531",
    "sg:postcode":"2525 TR",
    "sg:province":"Zuid-Holland",
    "wof:name":"Starlit",
    "wof:placetype":"venue"
},
  "geometry": {"coordinates":[4.3064417839,52.0636405945],"type":"Point"}
}