{
  "type": "Feature",
  "properties": {
    "addr:full":"Molenstraat 70C Zaandam North Holland 1502 TH",
    "addr:housenumber":"70c",
    "addr:postcode":"1502 th",
    "addr:street":"Molenstraat",
    "iso:country":"NL",
    "sg:address":"Molenstraat 70C",
    "sg:city":"Zaandam",
    "sg:orig_category":"Loodgieterswerk, Verwarming And Sanitaire Installaties",
    "sg:phone":"+31 75 612 1200",
    "sg:postcode":"1502 TH",
    "sg:province":"North Holland",
    "wof:name":"Topcat Afbouw",
    "wof:placetype":"venue"
},
  "geometry": {"coordinates":[4.826051,52.444759],"type":"Point"}
}