{
  "type": "Feature",
  "properties": {
    "addr:full":"Jarmuiden 71 Amsterdam Noord-Holland 1046 AE",
    "addr:housenumber":"71",
    "addr:postcode":"1046 ae",
    "addr:street":"Jarmuiden",
    "iso:country":"NL",
    "sg:address":"Jarmuiden 71",
    "sg:city":"Amsterdam",
    "sg:orig_category":"Fournituren - Fabrieken En Groothandel",
    "sg:phone":"+31 20 448 7222",
    "sg:postcode":"1046 AE",
    "sg:province":"Noord-Holland",
    "sg:website":"http://www.de-streng.nl",
    "wof:name":"Streng Bv, De",
    "wof:placetype":"venue"
},
  "geometry": {"coordinates":[4.79037,52.390186],"type":"Point"}
}