{
  "type": "Feature",
  "properties": {
    "iso:country":"NL",
    "sg:address":"Zwartewater 27",
    "sg:city":"Lelystad",
    "sg:orig_category":"Architecten",
    "sg:phone":"+31 320 226 757",
    "sg:postcode":"8223 DN",
    "sg:province":"Flevoland",
    "wof:name":"Architectenbureau Voorwyk",
    "wof:placetype":"venue"
},
  "geometry": {"coordinates":[5.48613,52.52618],"type":"Point"}
}