{
  "type": "Feature",
  "properties": {
    "addr:full":"Dubbelsteynlaan West 41 Dordrecht Zuid-Holland 3319 EK",
    "addr:housenumber":"41",
    "addr:postcode":"3319 ek",
    "addr:street":"Dubbelsteynlaan West",
    "iso:country":"NL",
    "sg:address":"Dubbelsteynlaan West 41",
    "sg:city":"Dordrecht",
    "sg:orig_category":"Bloemen And Planten",
    "sg:phone":"+31 78 621 5407",
    "sg:postcode":"3319 EK",
    "sg:province":"Zuid-Holland",
    "wof:name":"Bloemkwekerij Leen Valk Bv",
    "wof:placetype":"venue"
},
  "geometry": {"coordinates":[4.695595,51.793987],"type":"Point"}
}