{
  "type": "Feature",
  "properties": {
    "addr:full":"Nude 55A Wageningen Gelderland 6702 DK",
    "addr:housenumber":"55a",
    "addr:postcode":"6702 dk",
    "addr:street":"Nude;Gelderland",
    "iso:country":"NL",
    "sg:address":"Nude 55A",
    "sg:city":"Wageningen",
    "sg:orig_category":"Zeilmakerijen",
    "sg:phone":"+31 317 414 887",
    "sg:postcode":"6702 DK",
    "sg:province":"Gelderland",
    "wof:name":"Albers Tent- En Zeilmakerij, J",
    "wof:placetype":"venue"
},
  "geometry": {"coordinates":[5.647967,51.960579],"type":"Point"}
}