{
  "type": "Feature",
  "properties": {
    "addr:full":"Houtsnijdershorst 9 Apeldoorn Gelderland 7328 VT",
    "addr:housenumber":"9",
    "addr:postcode":"7328",
    "addr:street":"Houtsnijdershorst;Gelderland",
    "iso:country":"NL",
    "sg:address":"Houtsnijdershorst 9",
    "sg:city":"Apeldoorn",
    "sg:orig_category":"Binnenhuisarchitecten",
    "sg:phone":"+31 55 542 9277",
    "sg:postcode":"7328 VT",
    "sg:province":"Gelderland",
    "wof:name":"Split Level",
    "wof:placetype":"venue"
},
  "geometry": {"coordinates":[5.996439,52.203266],"type":"Point"}
}