{
  "type": "Feature",
  "properties": {
    "iso:country":"NL",
    "sg:address":"Nyverheidswg 7",
    "sg:city":"Ysselstein Ut",
    "sg:orig_category":"Meubelen - Fabrieken En Groothandel",
    "sg:phone":"+31 30 688 1941",
    "sg:postcode":"3401 MC",
    "sg:province":"Utrecht",
    "wof:name":"Saba Bv",
    "wof:placetype":"venue"
},
  "geometry": {"coordinates":[5.051955,52.012108],"type":"Point"}
}