{
  "type": "Feature",
  "properties": {
    "addr:full":"Oudkerkhof 11 Utrecht Utrecht 3512 GH",
    "addr:housenumber":"11",
    "addr:postcode":"3512 gh",
    "addr:street":"Oudkerkhof",
    "iso:country":"NL",
    "sg:address":"Oudkerkhof 11",
    "sg:city":"Utrecht",
    "sg:orig_category":"Meubelzaken, Woning- And Keukeninrichting",
    "sg:phone":"+31 30 231 4984",
    "sg:postcode":"3512 GH",
    "sg:province":"Utrecht",
    "wof:name":"Morpheus Slaapvoorlichters",
    "wof:placetype":"venue"
},
  "geometry": {"coordinates":[5.12078,52.09156],"type":"Point"}
}