{
  "type": "Feature",
  "properties": {
    "addr:full":"Amer 15 Zwolle NL.08 8032 GL",
    "addr:housenumber":"15",
    "addr:postcode":"8032 gl",
    "addr:street":"Amer",
    "iso:country":"NL",
    "sg:address":"Amer 15",
    "sg:city":"Zwolle",
    "sg:orig_category":"Psychotherapeuten",
    "sg:phone":"+31 38 455 0313",
    "sg:postcode":"8032 GL",
    "sg:province":"NL.08",
    "wof:name":"Wierenga, P S",
    "wof:placetype":"venue"
},
  "geometry": {"coordinates":[6.098537,52.531174],"type":"Point"}
}