{
  "type": "Feature",
  "properties": {
    "addr:full":"Verbenaln 1 Aerdenhout Noord-Holland 2111 ZL",
    "addr:housenumber":"1",
    "addr:postcode":"2111 zl",
    "addr:street":"Verbenaln",
    "iso:country":"NL",
    "sg:address":"Verbenaln 1",
    "sg:city":"Aerdenhout",
    "sg:orig_category":"Grondverbetering En -Ontginning",
    "sg:phone":"+31 23 544 1993",
    "sg:postcode":"2111 ZL",
    "sg:province":"Noord-Holland",
    "wof:name":"Green Globe",
    "wof:placetype":"venue"
},
  "geometry": {"coordinates":[4.601412,52.357971],"type":"Point"}
}