{
  "type": "Feature",
  "properties": {
    "addr:full":"Burg Knoppersln 32A Meppel Drenthe 7941 KN",
    "addr:housenumber":"32a",
    "addr:postcode":"7941 kn",
    "addr:street":"Burg Knoppersln",
    "iso:country":"NL",
    "sg:address":"Burg Knoppersln 32A",
    "sg:city":"Meppel",
    "sg:orig_category":"Adviesbureaus Bedrijfsorganisatie",
    "sg:phone":"+31 522 255 342",
    "sg:postcode":"7941 KN",
    "sg:province":"Drenthe",
    "sg:website":"http://www.wso-advies.nl",
    "wof:name":"Wso Vof",
    "wof:placetype":"venue"
},
  "geometry": {"coordinates":[6.196295,52.699615],"type":"Point"}
}