{
  "type": "Feature",
  "properties": {
    "addr:full":"Deldenerstr 182 Hengelo Ov NL.08 7555 AJ",
    "addr:housenumber":"182",
    "addr:postcode":"7555 aj",
    "addr:street":"Ov",
    "iso:country":"NL",
    "sg:address":"Deldenerstr 182",
    "sg:city":"Hengelo Ov",
    "sg:orig_category":"Antiquiteiten",
    "sg:phone":"+31 74 242 0462",
    "sg:postcode":"7555 AJ",
    "sg:province":"NL.08",
    "wof:name":"Klokhuis, Het",
    "wof:placetype":"venue"
},
  "geometry": {"coordinates":[6.77736,52.266434],"type":"Point"}
}