{
  "type": "Feature",
  "properties": {
    "addr:full":"Holbeinstraat 5 Amsterdam North Holland 1077 VB",
    "addr:housenumber":"5",
    "addr:postcode":"1077 vb",
    "addr:street":"Holbeinstraat",
    "iso:country":"NL",
    "sg:address":"Holbeinstraat 5",
    "sg:city":"Amsterdam",
    "sg:orig_category":"Marktonderzoekbureaus",
    "sg:phone":"+31 20 671 1558",
    "sg:postcode":"1077 VB",
    "sg:province":"North Holland",
    "wof:name":"Deenik Krebbers Partners",
    "wof:placetype":"venue"
},
  "geometry": {"coordinates":[4.875527,52.346378],"type":"Point"}
}