{
  "type": "Feature",
  "properties": {
    "iso:country":"NL",
    "sg:address":"Franseln 293A",
    "sg:city":"Rotterdam",
    "sg:orig_category":"Bloemen En Planten",
    "sg:phone":"+31 10 410 0075",
    "sg:postcode":"3028 AE",
    "sg:province":"South Holland",
    "wof:name":"Maasflora",
    "wof:placetype":"venue"
},
  "geometry": {"coordinates":[4.41724,51.917728],"type":"Point"}
}