{
  "type": "Feature",
  "properties": {
    "addr:full":"Parkweg 4 Harderwijk Gelderland 3842 AD",
    "addr:housenumber":"4",
    "addr:postcode":"3842 ad",
    "addr:street":"Parkweg;Gelderland",
    "iso:country":"NL",
    "sg:address":"Parkweg 4",
    "sg:city":"Harderwijk",
    "sg:orig_category":"Sportcentra",
    "sg:phone":"+31 341 434 434",
    "sg:postcode":"3842 AD",
    "sg:province":"Gelderland",
    "wof:name":"Sport En Aquacentrum De Sypel",
    "wof:placetype":"venue"
},
  "geometry": {"coordinates":[5.627707,52.34248],"type":"Point"}
}