{
  "type": "Feature",
  "properties": {
    "addr:full":"Kruidenln 18 Tilburg Noord-Brabant 5044 CM",
    "addr:housenumber":"18",
    "addr:postcode":"5044 cm",
    "addr:street":"Kruidenln",
    "iso:country":"NL",
    "sg:address":"Kruidenln 18",
    "sg:city":"Tilburg",
    "sg:orig_category":"Machineonderhoud En -Reparatie",
    "sg:phone":"+31 13 456 1092",
    "sg:postcode":"5044 CM",
    "sg:province":"Noord-Brabant",
    "wof:name":"Hvr-Techniek",
    "wof:placetype":"venue"
},
  "geometry": {"coordinates":[5.042826,51.577015],"type":"Point"}
}