{
  "type": "Feature",
  "properties": {
    "iso:country":"NL",
    "sg:address":"Hermelijnweide 7",
    "sg:city":"Nieuwegein",
    "sg:orig_category":"Verzekeringen - Verzekeringskantoren",
    "sg:phone":"+31 30 630 1466",
    "sg:postcode":"3437 TV",
    "sg:province":"Utrecht",
    "wof:name":"Amstel, H A Van",
    "wof:placetype":"venue"
},
  "geometry": {"coordinates":[5.074289,52.044563],"type":"Point"}
}