{
  "type": "Feature",
  "properties": {
    "addr:full":"W Sidelinge 302A Rotterdam Zuid-Holland 3042 CZ",
    "addr:housenumber":"302a",
    "addr:postcode":"3042",
    "addr:street":"W",
    "iso:country":"NL",
    "sg:address":"W Sidelinge 302A",
    "sg:city":"Rotterdam",
    "sg:orig_category":"Administratie- En Boekhoudkantoren",
    "sg:phone":"+31 10 437 2227",
    "sg:postcode":"3042 CZ",
    "sg:province":"Zuid-Holland",
    "wof:name":"Overschie",
    "wof:placetype":"venue"
},
  "geometry": {"coordinates":[4.43666,51.932205],"type":"Point"}
}