{
  "type": "Feature",
  "properties": {
    "addr:full":"Oranjeweg 67 Emst Gelderland 8166 JA",
    "addr:housenumber":"67",
    "addr:postcode":"8166 ja",
    "addr:street":"Oranjeweg;Gelderland",
    "iso:country":"NL",
    "sg:address":"Oranjeweg 67",
    "sg:city":"Emst",
    "sg:orig_category":"Kampeerterreinen",
    "sg:phone":"+31 578 661 628",
    "sg:postcode":"8166 JA",
    "sg:province":"Gelderland",
    "wof:name":"De Veluwse Wagen Bv",
    "wof:placetype":"venue"
},
  "geometry": {"coordinates":[5.9571537971,52.3225440979],"type":"Point"}
}