{
  "type": "Feature",
  "properties": {
    "iso:country":"NL",
    "sg:address":"Molstraat 6",
    "sg:city":"Dedemsvaart",
    "sg:orig_category":"Beautyfarms And Sauna'S",
    "sg:phone":"+31 523 613 440",
    "sg:postcode":"7701 JC",
    "sg:province":"Overijssel",
    "wof:name":"J. Veerbeek",
    "wof:placetype":"venue"
},
  "geometry": {"coordinates":[6.451502,52.600071],"type":"Point"}
}