{
  "type": "Feature",
  "properties": {
    "addr:full":"P Saenredamstr 7B Utrecht Utrecht 3583 TA",
    "addr:housenumber":"7b",
    "addr:postcode":"3583 ta",
    "addr:street":"P Saenredamstr",
    "iso:country":"NL",
    "sg:address":"P Saenredamstr 7B",
    "sg:city":"Utrecht",
    "sg:orig_category":"Grafisch Ontwerpers",
    "sg:phone":"+31 30 254 4131",
    "sg:postcode":"3583 TA",
    "sg:province":"Utrecht",
    "wof:name":"Sa & R",
    "wof:placetype":"venue"
},
  "geometry": {"coordinates":[5.143991,52.084957],"type":"Point"}
}