{
  "type": "Feature",
  "properties": {
    "addr:full":"Scheringstraat 28 Winterswijk Gelderland 7101 HD",
    "addr:housenumber":"28",
    "addr:postcode":"7101 hd",
    "addr:street":"Scheringstraat;Gelderland",
    "iso:country":"NL",
    "sg:address":"Scheringstraat 28",
    "sg:city":"Winterswijk",
    "sg:orig_category":"Kappers",
    "sg:phone":"+31 543 512 409",
    "sg:postcode":"7101 HD",
    "sg:province":"Gelderland",
    "wof:name":"G J Rauwerdink",
    "wof:placetype":"venue"
},
  "geometry": {"coordinates":[6.7184510231,51.966884613],"type":"Point"}
}