{
  "type": "Feature",
  "properties": {
    "iso:country":"NL",
    "sg:address":"G Reynststr 19",
    "sg:city":"S Gravenhage",
    "sg:orig_category":"Onderzoekbureaus",
    "sg:phone":"+31 6 19638292",
    "sg:postcode":"2593 EA",
    "sg:province":"Zuid-Holland",
    "wof:name":"Boer, Lauri De",
    "wof:placetype":"venue"
},
  "geometry": {"coordinates":[4.34266,52.086121],"type":"Point"}
}