{
  "type": "Feature",
  "properties": {
    "addr:full":"V Slypestr 43 Maastricht Limburg 6225 BK",
    "addr:housenumber":"43",
    "addr:postcode":"6225 bk",
    "iso:country":"NL",
    "sg:address":"V Slypestr 43",
    "sg:city":"Maastricht",
    "sg:orig_category":"Administratie- En Boekhoudkantoren",
    "sg:phone":"+31 43 362 0067",
    "sg:postcode":"6225 BK",
    "sg:province":"Limburg",
    "wof:name":"Bronckers",
    "wof:placetype":"venue"
},
  "geometry": {"coordinates":[5.73794,50.863708],"type":"Point"}
}