{
  "type": "Feature",
  "properties": {
    "addr:full":"Schorwg 13 Breezand North Holland 1764 MA",
    "addr:housenumber":"13",
    "addr:postcode":"1764 ma",
    "addr:street":"Schorwg",
    "iso:country":"NL",
    "sg:address":"Schorwg 13",
    "sg:city":"Breezand",
    "sg:orig_category":"Bloemen En Planten",
    "sg:phone":"+31 223 522 695",
    "sg:postcode":"1764 MA",
    "sg:province":"North Holland",
    "wof:name":"Kreatief",
    "wof:placetype":"venue"
},
  "geometry": {"coordinates":[4.780637,52.883526],"type":"Point"}
}