{
  "type": "Feature",
  "properties": {
    "addr:full":"Ln C Den Hoorn 102-104 Groningen Groningen 9728 JR",
    "addr:postcode":"102-104;9728 jr",
    "addr:street":"Ln C",
    "iso:country":"NL",
    "sg:address":"Ln C Den Hoorn 102-104",
    "sg:city":"Groningen",
    "sg:orig_category":"Adviesbureaus Bedrijfsorganisatie",
    "sg:phone":"+31 50 520 4640",
    "sg:postcode":"9728 JR",
    "sg:province":"Groningen",
    "sg:website":"http://www.bakkenist.nl",
    "wof:name":"Deloitte & Touche Bakkenist",
    "wof:placetype":"venue"
},
  "geometry": {"coordinates":[6.552897,53.194233],"type":"Point"}
}