{
  "type": "Feature",
  "properties": {
    "addr:full":"Raaphorstln 94 S Gravenhage Zuid-Holland 2532 BJ",
    "addr:housenumber":"94;gravenhage",
    "addr:postcode":"2532 bj",
    "addr:street":"Raaphorstln;S",
    "iso:country":"NL",
    "sg:address":"Raaphorstln 94",
    "sg:city":"S Gravenhage",
    "sg:orig_category":"Muziekinstrumenten - Reparatie En Onderhoud",
    "sg:phone":"+31 70 396 0235",
    "sg:postcode":"2532 BJ",
    "sg:province":"Zuid-Holland",
    "wof:name":"Bert Wijnand",
    "wof:placetype":"venue"
},
  "geometry": {"coordinates":[4.29807,52.048569],"type":"Point"}
}