{
  "type": "Feature",
  "properties": {
    "iso:country":"NL",
    "sg:address":"Dedemsvaartwg 245",
    "sg:city":"S Gravenhage",
    "sg:orig_category":"Administratie- En Boekhoudkantoren",
    "sg:phone":"+31 70 309 6590",
    "sg:postcode":"2545 DD",
    "sg:province":"Zuid-Holland",
    "wof:name":"Hatho",
    "wof:placetype":"venue"
},
  "geometry": {"coordinates":[4.27049,52.05093],"type":"Point"}
}