{
  "type": "Feature",
  "properties": {
    "addr:full":"Molenpk 15 Voorthuizen Gelderland 3781 GX",
    "addr:housenumber":"15",
    "addr:postcode":"3781 gx",
    "addr:street":"Molenpk;Gelderland",
    "iso:country":"NL",
    "sg:address":"Molenpk 15",
    "sg:city":"Voorthuizen",
    "sg:orig_category":"Modellenbureaus En Modellen Freelance",
    "sg:phone":"+31 342 441 200",
    "sg:postcode":"3781 GX",
    "sg:province":"Gelderland",
    "wof:name":"Expos",
    "wof:placetype":"venue"
},
  "geometry": {"coordinates":[5.613152,52.186058],"type":"Point"}
}