{
  "type": "Feature",
  "properties": {
    "iso:country":"NL",
    "sg:address":"Beverhof 43",
    "sg:city":"Beverwijk",
    "sg:orig_category":"Verlichting And Huishoudartikelen",
    "sg:phone":"+31 251 226 756",
    "sg:postcode":"1941 EC",
    "sg:province":"Noord-Holland",
    "wof:name":"Lampenier",
    "wof:placetype":"venue"
},
  "geometry": {"coordinates":[4.6604,52.481934],"type":"Point"}
}