{
  "type": "Feature",
  "properties": {
    "addr:full":"Buitenhovelaan 1 Middelburg Zeeland 4337 HJ",
    "addr:housenumber":"1",
    "addr:postcode":"4337 hj",
    "addr:street":"Buitenhovelaan",
    "iso:country":"NL",
    "sg:address":"Buitenhovelaan 1",
    "sg:city":"Middelburg",
    "sg:orig_category":"Begrafenisondernemers",
    "sg:phone":"+31 118 616 261",
    "sg:postcode":"4337 HJ",
    "sg:province":"Zeeland",
    "wof:name":"Rouwcentrum Middelburg",
    "wof:placetype":"venue"
},
  "geometry": {"coordinates":[3.626369,51.490623],"type":"Point"}
}