{
  "type": "Feature",
  "properties": {
    "addr:full":"Winkelcentrum Woensel 121 Eindhoven Noord-Brabant 5625 AG",
    "addr:housenumber":"121",
    "addr:postcode":"5625",
    "addr:street":"Winkelcentrum Woensel",
    "iso:country":"NL",
    "sg:address":"Winkelcentrum Woensel 121",
    "sg:city":"Eindhoven",
    "sg:classifiers":[
        {
            "category":"Shopping",
            "subcategory":"Gifts & Souvenirs",
            "type":"Retail Goods"
        }
    ],
    "sg:phone":"+31 40 241 8272",
    "sg:postcode":"5625 AG",
    "sg:province":"Noord-Brabant",
    "sg:tags":[
        "geschenken"
    ],
    "wof:name":"Kado Van De Kaa",
    "wof:placetype":"venue"
},
  "geometry": {"coordinates":[5.475182,51.46785],"type":"Point"}
}