{
  "type": "Feature",
  "properties": {
    "addr:full":"Mozartstr 6 Brunssum Limburg 6444 AW",
    "addr:housenumber":"6",
    "addr:postcode":"6444 aw",
    "addr:street":"Mozartstr",
    "iso:country":"NL",
    "sg:address":"Mozartstr 6",
    "sg:city":"Brunssum",
    "sg:orig_category":"Acupunctuur",
    "sg:phone":"+31 45 525 1343",
    "sg:postcode":"6444 AW",
    "sg:province":"Limburg",
    "wof:name":"Koselka-Amir, A B",
    "wof:placetype":"venue"
},
  "geometry": {"coordinates":[5.968822,50.942921],"type":"Point"}
}