{
  "type": "Feature",
  "properties": {
    "iso:country":"NL",
    "sg:address":"Pr V Oranjestr 1",
    "sg:city":"Wormer",
    "sg:orig_category":"Bejaarden - Verzorgingstehuizen",
    "sg:phone":"+31 75 642 1390",
    "sg:postcode":"1531 GA",
    "sg:province":"North Holland",
    "wof:name":"Torenerf, Verzorgingstehuis",
    "wof:placetype":"venue"
},
  "geometry": {"coordinates":[4.811285,52.498055],"type":"Point"}
}