{
  "type": "Feature",
  "properties": {
    "addr:full":"Molenpad 9 Ommen Overijssel 7731 GX",
    "addr:housenumber":"9",
    "addr:postcode":"7731 gx",
    "addr:street":"Molenpad",
    "iso:country":"NL",
    "sg:address":"Molenpad 9",
    "sg:city":"Ommen",
    "sg:orig_category":"Sportverenigingen En Ontspannings- Verenigingen",
    "sg:phone":"+31 529 451 052",
    "sg:postcode":"7731 GX",
    "sg:province":"Overijssel",
    "wof:name":"Luchtpost Postduivenver, De",
    "wof:placetype":"venue"
},
  "geometry": {"coordinates":[6.426237,52.521946],"type":"Point"}
}