{
  "type": "Feature",
  "properties": {
    "iso:country":"NL",
    "sg:address":"Zijtak 4",
    "sg:city":"Klijndijk",
    "sg:orig_category":"Diverse Artikelen Fab",
    "sg:phone":"+31 591 513 315",
    "sg:postcode":"7871 TA",
    "sg:province":"Drenthe",
    "wof:name":"Erkend Preparateur Henk Beijering",
    "wof:placetype":"venue"
},
  "geometry": {"coordinates":[6.84523,52.830292],"type":"Point"}
}