{
  "type": "Feature",
  "properties": {
    "addr:full":"Dorpsstr 148 Scherpenzeel Gld Gelderland 3925 KE",
    "addr:housenumber":"148",
    "addr:postcode":"3925 ke",
    "addr:street":"Gld Gelderland",
    "iso:country":"NL",
    "sg:address":"Dorpsstr 148",
    "sg:city":"Scherpenzeel Gld",
    "sg:orig_category":"Wereldwinkels",
    "sg:phone":"+31 33 277 4577",
    "sg:postcode":"3925 KE",
    "sg:province":"Gelderland",
    "wof:name":"Wereldwinkel Scherpenzeel",
    "wof:placetype":"venue"
},
  "geometry": {"coordinates":[5.4917578697,52.0793457031],"type":"Point"}
}