{
  "type": "Feature",
  "properties": {
    "addr:full":"Kerkstr 143 Amsterdam Noord-Holland 1017 GG",
    "addr:housenumber":"143",
    "addr:postcode":"1017 gg",
    "iso:country":"NL",
    "sg:address":"Kerkstr 143",
    "sg:city":"Amsterdam",
    "sg:orig_category":"Kunsthandel",
    "sg:phone":"+31 20 489 5134",
    "sg:postcode":"1017 GG",
    "sg:province":"Noord-Holland",
    "wof:name":"Kawsara Fall",
    "wof:placetype":"venue"
},
  "geometry": {"coordinates":[4.888229,52.363857],"type":"Point"}
}