{
  "type": "Feature",
  "properties": {
    "addr:full":"Dorpstraat 100 Heel North Carolina 6097 AR",
    "addr:housenumber":"100",
    "addr:postcode":"6097",
    "addr:street":"Dorpstraat",
    "iso:country":"NL",
    "sg:address":"Dorpstraat 100",
    "sg:city":"Heel",
    "sg:orig_category":"Schoenen",
    "sg:phone":"+31 475 571 257",
    "sg:postcode":"6097 AR",
    "sg:province":"North Carolina",
    "wof:name":"M.H.M. Claessens",
    "wof:placetype":"venue"
},
  "geometry": {"coordinates":[-78.789642,34.73262],"type":"Point"}
}