{
  "type": "Feature",
  "properties": {
    "addr:full":"Anthonie Van Dijckstraat 7 Amsterdam Noord-Holland 1077 ME",
    "addr:housenumber":"7",
    "addr:postcode":"1077 me",
    "addr:street":"Anthonie Van Dijckstraat",
    "iso:country":"NL",
    "sg:address":"Anthonie Van Dijckstraat 7",
    "sg:city":"Amsterdam",
    "sg:orig_category":"Voeding, Dranken And Tabak Gh",
    "sg:phone":"+31 20 662 1009",
    "sg:postcode":"1077 ME",
    "sg:province":"Noord-Holland",
    "wof:name":"Bv Agentuur & Com Hand V/H Fa A P Boelaa",
    "wof:placetype":"venue"
},
  "geometry": {"coordinates":[4.874414,52.348179],"type":"Point"}
}