{
  "type": "Feature",
  "properties": {
    "addr:full":"Dorpsstraat 93 Zoetermeer Zuid-Holland 2712 AE",
    "addr:housenumber":"93",
    "addr:postcode":"2712 ae",
    "addr:street":"Dorpsstraat",
    "iso:country":"NL",
    "sg:address":"Dorpsstraat 93",
    "sg:city":"Zoetermeer",
    "sg:orig_category":"Opticiens",
    "sg:phone":"+31 79 316 4575",
    "sg:postcode":"2712 AE",
    "sg:province":"Zuid-Holland",
    "wof:name":"Ergra Optiekspec",
    "wof:placetype":"venue"
},
  "geometry": {"coordinates":[4.4974198341,52.0559425354],"type":"Point"}
}