{
  "type": "Feature",
  "properties": {
    "addr:full":"De Haare 6 Zieuwent Gelderland 7136 MJ",
    "addr:housenumber":"6",
    "addr:postcode":"7136 mj",
    "addr:street":"De Haare;Gelderland",
    "iso:country":"NL",
    "sg:address":"De Haare 6",
    "sg:city":"Zieuwent",
    "sg:orig_category":"Metaalwerken",
    "sg:phone":"+31 544 351 956",
    "sg:postcode":"7136 MJ",
    "sg:province":"Gelderland",
    "wof:name":"Rouwhorst Plafonds En Wanden Vof",
    "wof:placetype":"venue"
},
  "geometry": {"coordinates":[6.521026,52.006508],"type":"Point"}
}