{
  "type": "Feature",
  "properties": {
    "addr:full":"Westplein 10 Rotterdam South Holland 3016 BM",
    "addr:housenumber":"10",
    "addr:postcode":"3016 bm",
    "addr:street":"Westplein",
    "iso:country":"NL",
    "sg:address":"Westplein 10",
    "sg:city":"Rotterdam",
    "sg:orig_category":"Werving And Selectie Van Vast Personeel",
    "sg:phone":"+31 10 241 3555",
    "sg:postcode":"3016 BM",
    "sg:province":"South Holland",
    "wof:name":"United Capacity Rotterdam Bv",
    "wof:placetype":"venue"
},
  "geometry": {"coordinates":[4.4779481888,51.9088134766],"type":"Point"}
}