{
  "type": "Feature",
  "properties": {
    "iso:country":"NL",
    "sg:address":"Kildersewg 22",
    "sg:city":"Doetinchem",
    "sg:orig_category":"Autorijscholen",
    "sg:phone":"+31 314 346 103",
    "sg:postcode":"7007 GK",
    "sg:province":"Gelderland",
    "sg:website":"http://www.striekwold.nl",
    "wof:name":"Striekwold, E",
    "wof:placetype":"venue"
},
  "geometry": {"coordinates":[6.268868,51.949718],"type":"Point"}
}