{
  "type": "Feature",
  "properties": {
    "addr:full":"Nieuwenhuyzenstr 12 Rosmalen Noord-Brabant 5241 TC",
    "addr:housenumber":"12",
    "addr:postcode":"5241 tc",
    "addr:street":"Nieuwenhuyzenstr",
    "iso:country":"NL",
    "sg:address":"Nieuwenhuyzenstr 12",
    "sg:city":"Rosmalen",
    "sg:orig_category":"Poeliers",
    "sg:phone":"+31 73 521 4220",
    "sg:postcode":"5241 TC",
    "sg:province":"Noord-Brabant",
    "wof:name":"Kreij",
    "wof:placetype":"venue"
},
  "geometry": {"coordinates":[5.364569,51.718582],"type":"Point"}
}