{
  "type": "Feature",
  "properties": {
    "addr:full":"Ncb Ln 80 Veghel Noord-Brabant 5462 GE",
    "addr:housenumber":"80",
    "addr:postcode":"5462",
    "addr:street":"Ncb Ln",
    "iso:country":"NL",
    "sg:address":"Ncb Ln 80",
    "sg:city":"Veghel",
    "sg:orig_category":"Zuivel - Fabrieken",
    "sg:phone":"+31 413 372 222",
    "sg:postcode":"5462 GE",
    "sg:province":"Noord-Brabant",
    "sg:website":"http://www.dmv-international.com",
    "wof:name":"Dmv Int",
    "wof:placetype":"venue"
},
  "geometry": {"coordinates":[5.54175,51.617222],"type":"Point"}
}