{
  "type": "Feature",
  "properties": {
    "iso:country":"NL",
    "sg:address":"Lindenplein 2",
    "sg:city":"Ter Aar",
    "sg:orig_category":"Fruit And Groenten Gh",
    "sg:phone":"+31 172 602 543",
    "sg:postcode":"2461 JC",
    "sg:province":"Zuid-Holland",
    "wof:name":"Het Fruitpaleis",
    "wof:placetype":"venue"
},
  "geometry": {"coordinates":[4.709777,52.167908],"type":"Point"}
}