{
  "type": "Feature",
  "properties": {
    "addr:full":"Zesstedenweg 211 Grootebroek North Holland 1613 JE",
    "addr:housenumber":"211",
    "addr:postcode":"1613 je",
    "addr:street":"Zesstedenweg",
    "iso:country":"NL",
    "sg:address":"Zesstedenweg 211",
    "sg:city":"Grootebroek",
    "sg:orig_category":"Verzekeringen",
    "sg:phone":"+31 228 520 000",
    "sg:postcode":"1613 JE",
    "sg:province":"North Holland",
    "wof:name":"Enra Verzekeringen Bv",
    "wof:placetype":"venue"
},
  "geometry": {"coordinates":[5.2172,52.697803],"type":"Point"}
}