{
  "type": "Feature",
  "properties": {
    "iso:country":"NL",
    "sg:address":"J De Wittln 411",
    "sg:city":"Arnhem",
    "sg:orig_category":"Adviesbureaus Chemische Techniek",
    "sg:phone":"+31 26 389 2236",
    "sg:postcode":"6828 XS",
    "sg:province":"Gelderland",
    "wof:name":"Dejo",
    "wof:placetype":"venue"
},
  "geometry": {"coordinates":[5.92598,51.98053],"type":"Point"}
}