{
  "type": "Feature",
  "properties": {
    "addr:full":"Rietveldenweg 54 Den Bosch North Brabant 5222 AS",
    "addr:housenumber":"54",
    "addr:postcode":"5222 as",
    "addr:street":"Rietveldenweg",
    "iso:country":"NL",
    "sg:address":"Rietveldenweg 54",
    "sg:city":"Den Bosch",
    "sg:classifiers":[
        {
            "category":"Professional",
            "subcategory":"Accounting & Tax Preparation",
            "type":"Services"
        }
    ],
    "sg:phone":"+31 73 623 0219",
    "sg:postcode":"5222 AS",
    "sg:province":"North Brabant",
    "sg:tags":[
        "accountant"
    ],
    "wof:name":"Millenaar & Partners",
    "wof:placetype":"venue"
},
  "geometry": {"coordinates":[5.2772,51.702991],"type":"Point"}
}