{
  "type": "Feature",
  "properties": {
    "addr:full":"Industriewg 10 Swifterbant Flevoland 8255 PB",
    "addr:housenumber":"10",
    "addr:postcode":"8255 pb",
    "addr:street":"Industriewg;Flevoland",
    "iso:country":"NL",
    "sg:address":"Industriewg 10",
    "sg:city":"Swifterbant",
    "sg:orig_category":"Heftrucks",
    "sg:phone":"+31 321 324 031",
    "sg:postcode":"8255 PB",
    "sg:province":"Flevoland",
    "sg:website":"http://www.all-lift.nl",
    "wof:name":"All-Lift",
    "wof:placetype":"venue"
},
  "geometry": {"coordinates":[5.643619,52.57172],"type":"Point"}
}