{
  "type": "Feature",
  "properties": {
    "addr:full":"Zadelmakerstr 23 Ridderkerk Zuid-Holland 2984 CC",
    "addr:housenumber":"23",
    "addr:postcode":"2984 cc",
    "addr:street":"Zadelmakerstr",
    "iso:country":"NL",
    "sg:address":"Zadelmakerstr 23",
    "sg:city":"Ridderkerk",
    "sg:orig_category":"Drukkerijen",
    "sg:phone":"+31 180 419 711",
    "sg:postcode":"2984 CC",
    "sg:province":"Zuid-Holland",
    "sg:website":"http://www.tricop.nl",
    "wof:name":"Tricop Bv",
    "wof:placetype":"venue"
},
  "geometry": {"coordinates":[4.606518,51.876308],"type":"Point"}
}