{
  "type": "Feature",
  "properties": {
    "addr:full":"Kloosterstraat 48 Doesburg Gelderland 6981 CE",
    "addr:housenumber":"48",
    "addr:postcode":"6981 ce",
    "addr:street":"Kloosterstraat;Gelderland",
    "iso:country":"NL",
    "sg:address":"Kloosterstraat 48",
    "sg:city":"Doesburg",
    "sg:orig_category":"Bloemen And Planten Gh",
    "sg:phone":"+31 313 474 551",
    "sg:postcode":"6981 CE",
    "sg:province":"Gelderland",
    "wof:name":"Bloemen Pelgrim",
    "wof:placetype":"venue"
},
  "geometry": {"coordinates":[-39.34277,-5.32226],"type":"Point"}
}