{
  "type": "Feature",
  "properties": {
    "addr:full":"Holstmeerwg 1 Leeuwarden Provincie Friesland 8936 AS",
    "addr:housenumber":"1",
    "addr:postcode":"8936 as",
    "addr:street":"Holstmeerwg;Provincie Friesland",
    "iso:country":"NL",
    "sg:address":"Holstmeerwg 1",
    "sg:city":"Leeuwarden",
    "sg:orig_category":"Politie",
    "sg:phone":"+31 900 8844",
    "sg:postcode":"8936 AS",
    "sg:province":"Provincie Friesland",
    "wof:name":"Politie",
    "wof:placetype":"venue"
},
  "geometry": {"coordinates":[5.825426,53.192066],"type":"Point"}
}