{
  "type": "Feature",
  "properties": {
    "addr:full":"Grotestraat 24 Tubbergen NL.08 7651 CJ",
    "addr:housenumber":"24;nl.08",
    "addr:postcode":"7651 cj",
    "addr:street":"Grotestraat",
    "iso:country":"NL",
    "sg:address":"Grotestraat 24",
    "sg:city":"Tubbergen",
    "sg:orig_category":"Kappers",
    "sg:phone":"+31 546 623 643",
    "sg:postcode":"7651 CJ",
    "sg:province":"NL.08",
    "wof:name":"Kapsalon Sam - Sam",
    "wof:placetype":"venue"
},
  "geometry": {"coordinates":[6.782242775,52.4056243896],"type":"Point"}
}