{
  "type": "Feature",
  "properties": {
    "iso:country":"NL",
    "sg:address":"Hunzeweg 17",
    "sg:city":"Garnwerd",
    "sg:orig_category":"Bloemen And Planten",
    "sg:phone":"+31 594 621 987",
    "sg:postcode":"9893 PA",
    "sg:province":"Groningen",
    "wof:name":"Fleur De Lys",
    "wof:placetype":"venue"
},
  "geometry": {"coordinates":[6.490525,53.304478],"type":"Point"}
}