{
  "type": "Feature",
  "properties": {
    "addr:full":"Leusdenhof 214 Amsterdam Zuidoost North Holland 1108 DH",
    "addr:housenumber":"214",
    "addr:postcode":"1108 dh",
    "addr:street":"Leusdenhof",
    "iso:country":"NL",
    "sg:address":"Leusdenhof 214",
    "sg:city":"Amsterdam Zuidoost",
    "sg:orig_category":"Administratie- En Boekhoudkantoren",
    "sg:phone":"+31 20 697 1100",
    "sg:postcode":"1108 DH",
    "sg:province":"North Holland",
    "wof:name":"Hardes",
    "wof:placetype":"venue"
},
  "geometry": {"coordinates":[4.979394,52.307957],"type":"Point"}
}