{
  "type": "Feature",
  "properties": {
    "iso:country":"NL",
    "sg:address":"Ridderpoort 39",
    "sg:city":"Ridderkerk",
    "sg:orig_category":"Projectinrichting",
    "sg:phone":"+31 180 330 011",
    "sg:postcode":"2984 BG",
    "sg:province":"Zuid-Holland",
    "wof:name":"Heer, De",
    "wof:placetype":"venue"
},
  "geometry": {"coordinates":[4.627305,51.876915],"type":"Point"}
}