{
  "type": "Feature",
  "properties": {
    "addr:full":"Ridderpoort 39 Ridderkerk Zuid-Holland 2984 BG",
    "addr:housenumber":"39",
    "addr:postcode":"2984",
    "addr:street":"Ridderpoort",
    "iso:country":"NL",
    "sg:address":"Ridderpoort 39",
    "sg:city":"Ridderkerk",
    "sg:orig_category":"Projectinrichting",
    "sg:phone":"+31 180 330 011",
    "sg:postcode":"2984 BG",
    "sg:province":"Zuid-Holland",
    "wof:name":"Heer, De",
    "wof:placetype":"venue"
},
  "geometry": {"coordinates":[4.627305,51.876915],"type":"Point"}
}