{
  "type": "Feature",
  "properties": {
    "addr:full":"Lubeck 22 Barendrecht Zuid-Holland 2993 LK",
    "addr:housenumber":"22",
    "addr:postcode":"2993 lk",
    "addr:street":"Lubeck",
    "iso:country":"NL",
    "sg:address":"Lubeck 22",
    "sg:city":"Barendrecht",
    "sg:orig_category":"Meubelmakerijen",
    "sg:phone":"+31 180 649 573",
    "sg:postcode":"2993 LK",
    "sg:province":"Zuid-Holland",
    "sg:website":"http://www.tact-teak.nl",
    "wof:name":"Tact Teak",
    "wof:placetype":"venue"
},
  "geometry": {"coordinates":[4.48534,51.858334],"type":"Point"}
}