{
  "type": "Feature",
  "properties": {
    "iso:country":"NL",
    "sg:address":"Huntstr 22",
    "sg:city":"Sittard",
    "sg:orig_category":"Vakantieverblijven",
    "sg:phone":"+31 46 451 1512",
    "sg:postcode":"6135 CP",
    "sg:province":"Limburg",
    "sg:website":"http://www.sonnevijver.nl",
    "wof:name":"Sonnevijver E41, De",
    "wof:placetype":"venue"
},
  "geometry": {"coordinates":[5.851302,51.007687],"type":"Point"}
}