{
  "type": "Feature",
  "properties": {
    "addr:full":"C Huygenswg 19B Hellevoetsluis Zuid-Holland 3225 LD",
    "addr:housenumber":"19b",
    "addr:postcode":"3225 ld",
    "iso:country":"NL",
    "sg:address":"C Huygenswg 19B",
    "sg:city":"Hellevoetsluis",
    "sg:orig_category":"Loodgieters",
    "sg:phone":"+31 181 323 758",
    "sg:postcode":"3225 LD",
    "sg:province":"Zuid-Holland",
    "sg:website":"http://www.sijde-wenting.nl",
    "wof:name":"Sijde-Wenting, Van De",
    "wof:placetype":"venue"
},
  "geometry": {"coordinates":[4.171119,51.837322],"type":"Point"}
}