{
  "type": "Feature",
  "properties": {
    "iso:country":"NL",
    "sg:address":"Reggeln 14A",
    "sg:city":"Heemstede",
    "sg:orig_category":"Peuterspeelzalen",
    "sg:phone":"+31 23 529 4132",
    "sg:postcode":"2105 VH",
    "sg:province":"Noord-Holland",
    "wof:name":"Meerlnest, 'T",
    "wof:placetype":"venue"
},
  "geometry": {"coordinates":[4.621248,52.345287],"type":"Point"}
}