{
  "type": "Feature",
  "properties": {
    "addr:full":"Meerstraat 25 Hillegom Zuid-Holland 2181 BH",
    "addr:housenumber":"25",
    "addr:postcode":"2181 bh",
    "addr:street":"Meerstraat",
    "iso:country":"NL",
    "sg:address":"Meerstraat 25",
    "sg:city":"Hillegom",
    "sg:classifiers":[
        {
            "category":"Shopping",
            "subcategory":"Gifts & Souvenirs",
            "type":"Retail Goods"
        }
    ],
    "sg:phone":"+31 252 525 529",
    "sg:postcode":"2181 BH",
    "sg:province":"Zuid-Holland",
    "sg:tags":[
        "geschenken"
    ],
    "wof:name":"La Belle",
    "wof:placetype":"venue"
},
  "geometry": {"coordinates":[4.580977,52.292946],"type":"Point"}
}