{
  "type": "Feature",
  "properties": {
    "addr:full":"Slenerweg 31 Schoonoord Drenthe 7848 AD",
    "addr:housenumber":"31",
    "addr:postcode":"7848 ad",
    "addr:street":"Slenerweg",
    "iso:country":"NL",
    "sg:address":"Slenerweg 31",
    "sg:city":"Schoonoord",
    "sg:orig_category":"Kampeerterreinen",
    "sg:phone":"+31 591 381 605",
    "sg:postcode":"7848 AD",
    "sg:province":"Drenthe",
    "wof:name":"Camping Laweda",
    "wof:placetype":"venue"
},
  "geometry": {"coordinates":[6.757958889,52.8449668884],"type":"Point"}
}