{
  "type": "Feature",
  "properties": {
    "addr:full":"Beethovenstr 7B Amsterdam Noord-Holland 1077 HK",
    "addr:housenumber":"7b",
    "addr:postcode":"1077 hk",
    "addr:street":"Beethovenstr",
    "iso:country":"NL",
    "sg:address":"Beethovenstr 7B",
    "sg:city":"Amsterdam",
    "sg:orig_category":"Herenkleding",
    "sg:phone":"+31 20 675 5660",
    "sg:postcode":"1077 HK",
    "sg:province":"Noord-Holland",
    "wof:name":"Frenkel, Marcel",
    "wof:placetype":"venue"
},
  "geometry": {"coordinates":[4.878304,52.349869],"type":"Point"}
}