{
  "type": "Feature",
  "properties": {
    "iso:country":"NL",
    "sg:address":"Hogeweg 24",
    "sg:city":"Wijhe",
    "sg:orig_category":"Diverse Bedrijfsinstallaties Gh",
    "sg:phone":"+31 572 357 176",
    "sg:postcode":"8131 RK",
    "sg:province":"NL.08",
    "wof:name":"Handelsonderneming B. Van Dartel",
    "wof:placetype":"venue"
},
  "geometry": {"coordinates":[6.227595,52.395283],"type":"Point"}
}