{
  "type": "Feature",
  "properties": {
    "addr:full":"Kraatsweg 9A Ede Gld Gelderland 6712 DA",
    "addr:housenumber":"9a;6712",
    "addr:postcode":"da",
    "addr:street":"Kraatsweg;Gld Gelderland",
    "iso:country":"NL",
    "sg:address":"Kraatsweg 9A",
    "sg:city":"Ede Gld",
    "sg:orig_category":"Kinderopvang Behalve Thuis",
    "sg:phone":"+31 318 651 568",
    "sg:postcode":"6712 DA",
    "sg:province":"Gelderland",
    "wof:name":"Kinderdagverblijf 'T Kalfje",
    "wof:placetype":"venue"
},
  "geometry": {"coordinates":[5.653149,52.049301],"type":"Point"}
}