{
  "type": "Feature",
  "properties": {
    "addr:full":"Oosterhesselerwg 1 Holsloot Provincie Drenthe 7845 TB",
    "addr:housenumber":"1",
    "addr:postcode":"7845 tb",
    "addr:street":"Oosterhesselerwg;Provincie Drenthe",
    "iso:country":"NL",
    "sg:address":"Oosterhesselerwg 1",
    "sg:city":"Holsloot",
    "sg:orig_category":"Paardensport",
    "sg:phone":"+31 591 564 116",
    "sg:postcode":"7845 TB",
    "sg:province":"Provincie Drenthe",
    "wof:name":"Bn Stables",
    "wof:placetype":"venue"
},
  "geometry": {"coordinates":[6.795726,52.732334],"type":"Point"}
}