{
  "type": "Feature",
  "properties": {
    "iso:country":"NL",
    "sg:address":"Centaurusweg 39",
    "sg:city":"Tilburg",
    "sg:orig_category":"Metaalvrije Afvalrecycling",
    "sg:phone":"+31 13 455 5925",
    "sg:postcode":"5015 TC",
    "sg:province":"Noord-Brabant",
    "wof:name":"Heijnen Papierrecycling Bv",
    "wof:placetype":"venue"
},
  "geometry": {"coordinates":[5.105101,51.576195],"type":"Point"}
}