{
  "type": "Feature",
  "properties": {
    "addr:full":"Gedempte Zuiderdiep 12 Groningen Groningen 9711 HG",
    "addr:housenumber":"12",
    "addr:postcode":"9711 hg",
    "addr:street":"Gedempte Zuiderdiep",
    "iso:country":"NL",
    "sg:address":"Gedempte Zuiderdiep 12",
    "sg:city":"Groningen",
    "sg:orig_category":"Werving And Selectie Van Tijdelijk Personeel And Uitzendkantoren",
    "sg:phone":"+31 50 850 5050",
    "sg:postcode":"9711 HG",
    "sg:province":"Groningen",
    "wof:name":"Randstad",
    "wof:placetype":"venue"
},
  "geometry": {"coordinates":[6.5706629753,53.2155075073],"type":"Point"}
}