{
  "type": "Feature",
  "properties": {
    "addr:full":"Middenweg 71 Amsterdam North Holland 1098 AE",
    "addr:housenumber":"71",
    "addr:postcode":"1098 ae",
    "addr:street":"Middenweg",
    "iso:country":"NL",
    "sg:address":"Middenweg 71",
    "sg:city":"Amsterdam",
    "sg:orig_category":"Makelaars In Onroerend Goed",
    "sg:phone":"+31 20 665 4380",
    "sg:postcode":"1098 AE",
    "sg:province":"North Holland",
    "wof:name":"Van Veeren Makelaardij",
    "wof:placetype":"venue"
},
  "geometry": {"coordinates":[4.931525,52.353287],"type":"Point"}
}