{
  "type": "Feature",
  "properties": {
    "addr:full":"Kanaalstr 54 Lisse North Holland 2161 JM",
    "addr:housenumber":"54",
    "addr:postcode":"2161 jm",
    "addr:street":"Kanaalstr",
    "iso:country":"NL",
    "sg:address":"Kanaalstr 54",
    "sg:city":"Lisse",
    "sg:orig_category":"Opticiens",
    "sg:phone":"+31 252 418 160",
    "sg:postcode":"2161 JM",
    "sg:province":"North Holland",
    "sg:website":"http://www.hansanders.nl",
    "wof:name":"Hans Anders",
    "wof:placetype":"venue"
},
  "geometry": {"coordinates":[4.5568399429,52.2597351074],"type":"Point"}
}