{
  "type": "Feature",
  "properties": {
    "addr:full":"Herman Heijermanslaan 21 Bladel Noord-Brabant 5531 TB",
    "addr:housenumber":"21",
    "addr:postcode":"5531 tb",
    "addr:street":"Herman Heijermanslaan",
    "iso:country":"NL",
    "sg:address":"Herman Heijermanslaan 21",
    "sg:city":"Bladel",
    "sg:orig_category":"Bedrijfsinventaris Gh",
    "sg:phone":"+31 497 381 449",
    "sg:postcode":"5531 TB",
    "sg:province":"Noord-Brabant",
    "wof:name":"Symfoni",
    "wof:placetype":"venue"
},
  "geometry": {"coordinates":[5.217136,51.372753],"type":"Point"}
}