{
  "type": "Feature",
  "properties": {
    "iso:country":"NL",
    "sg:address":"Rooseveltstr 1",
    "sg:city":"Egmond Aan Zee",
    "sg:orig_category":"Bejaarden - Verzorgingstehuizen",
    "sg:phone":"+31 72 506 2844",
    "sg:postcode":"1931 VN",
    "sg:province":"Noord-Holland",
    "wof:name":"Agnes",
    "wof:placetype":"venue"
},
  "geometry": {"coordinates":[4.62648,52.613876],"type":"Point"}
}