{
  "type": "Feature",
  "properties": {
    "iso:country":"NL",
    "sg:address":"Nieuwe Rijksweg 49",
    "sg:city":"'S Heer Arendskerke",
    "sg:orig_category":"Bloemen And Planten",
    "sg:phone":"+31 113 270 960",
    "sg:postcode":"4458 SG",
    "sg:province":"Zeeland",
    "wof:name":"Tuincentrum En Bloembinderij Ter Lucht",
    "wof:placetype":"venue"
},
  "geometry": {"coordinates":[3.841892,51.501083],"type":"Point"}
}