{
  "type": "Feature",
  "properties": {
    "addr:full":"Ondersteweg 1 Kessel Lb Limburg 5995 PS",
    "addr:housenumber":"1",
    "addr:postcode":"lb;5995 ps",
    "addr:street":"Ondersteweg",
    "iso:country":"NL",
    "sg:address":"Ondersteweg 1",
    "sg:city":"Kessel Lb",
    "sg:orig_category":"Kampeerterreinen",
    "sg:phone":"+31 77 462 1201",
    "sg:postcode":"5995 PS",
    "sg:province":"Limburg",
    "wof:name":"Watersportcamping Gravenhof",
    "wof:placetype":"venue"
},
  "geometry": {"coordinates":[6.0598292351,51.2922363281],"type":"Point"}
}