{
  "type": "Feature",
  "properties": {
    "addr:full":"Moleneind Nz 98 Drachten Provincie Friesland 9203 ZS",
    "addr:housenumber":"98",
    "addr:postcode":"9203 zs",
    "addr:street":"Moleneind Nz;Provincie Friesland",
    "iso:country":"NL",
    "sg:address":"Moleneind Nz 98",
    "sg:city":"Drachten",
    "sg:orig_category":"Beeldende Kunstenaars",
    "sg:phone":"+31 512 524 054",
    "sg:postcode":"9203 ZS",
    "sg:province":"Provincie Friesland",
    "wof:name":"Woudwijk, A",
    "wof:placetype":"venue"
},
  "geometry": {"coordinates":[6.09016,53.106373],"type":"Point"}
}