{
  "type": "Feature",
  "properties": {
    "addr:full":"Montagewg 1 Nieuwegein Utrecht 3433 NT",
    "addr:housenumber":"1",
    "addr:postcode":"3433 nt",
    "addr:street":"Montagewg",
    "iso:country":"NL",
    "sg:address":"Montagewg 1",
    "sg:city":"Nieuwegein",
    "sg:orig_category":"Woningbouw- Verenigingen En -Stichtingen",
    "sg:phone":"+31 30 608 3131",
    "sg:postcode":"3433 NT",
    "sg:province":"Utrecht",
    "sg:website":"http://www.jutphaas.nl",
    "wof:name":"Jutphaas",
    "wof:placetype":"venue"
},
  "geometry": {"coordinates":[5.1018838882,52.0152244568],"type":"Point"}
}