{
  "type": "Feature",
  "properties": {
    "iso:country":"NL",
    "sg:address":"Nw Keizersgr 58 Sous",
    "sg:city":"Amsterdam",
    "sg:orig_category":"Acupunctuur",
    "sg:phone":"+31 20 427 3769",
    "sg:postcode":"1018 DT",
    "sg:province":"Noord-Holland",
    "sg:website":"http://www.acupunctuuramsterdam.nl",
    "wof:name":"Arno Roelofs, Acupunctuur",
    "wof:placetype":"venue"
},
  "geometry": {"coordinates":[4.893195,52.373119],"type":"Point"}
}