{
  "type": "Feature",
  "properties": {
    "addr:full":"Vierlinghstr 8B Werkendam Noord-Brabant 4251 LC",
    "addr:housenumber":"8b",
    "addr:postcode":"4251 lc",
    "addr:street":"Vierlinghstr",
    "iso:country":"NL",
    "sg:address":"Vierlinghstr 8B",
    "sg:city":"Werkendam",
    "sg:classifiers":[
        {
            "category":"Professional",
            "subcategory":"Accounting & Tax Preparation",
            "type":"Services"
        }
    ],
    "sg:phone":"+31 183 503 699",
    "sg:postcode":"4251 LC",
    "sg:province":"Noord-Brabant",
    "sg:tags":[
        "accountant",
        "en",
        "-kantoren",
        "register-"
    ],
    "wof:name":"Vervloet Senden & Co Bv",
    "wof:placetype":"venue"
},
  "geometry": {"coordinates":[4.883732,51.802921],"type":"Point"}
}