{
  "type": "Feature",
  "properties": {
    "addr:full":"Kernmakerijstraat 2 Gaanderen Gelderland 7011 VL",
    "addr:housenumber":"2",
    "addr:postcode":"7011 vl",
    "addr:street":"Kernmakerijstraat;Gelderland",
    "iso:country":"NL",
    "sg:address":"Kernmakerijstraat 2",
    "sg:city":"Gaanderen",
    "sg:orig_category":"Koeriersdiensten",
    "sg:phone":"+31 315 340 986",
    "sg:postcode":"7011 VL",
    "sg:province":"Gelderland",
    "wof:name":"Vriezen Koerierdienst",
    "wof:placetype":"venue"
},
  "geometry": {"coordinates":[6.342004,51.926498],"type":"Point"}
}