{
  "type": "Feature",
  "properties": {
    "iso:country":"NL",
    "sg:address":"Vd M De Walch Str 1",
    "sg:city":"Lichtenvoorde",
    "sg:orig_category":"Kopieerservice",
    "sg:phone":"+31 544 373 242",
    "sg:postcode":"7131 EN",
    "sg:province":"Vaud",
    "sg:website":"http://www.mcwindos.nl",
    "wof:name":"Mc Windos",
    "wof:placetype":"venue"
},
  "geometry": {"coordinates":[6.65772,46.56155],"type":"Point"}
}