{
  "type": "Feature",
  "properties": {
    "iso:country":"NL",
    "sg:address":"Sluytersln 449",
    "sg:city":"Nieuwegein",
    "sg:orig_category":"Onderhoudswerken",
    "sg:phone":"+31 30 609 0628",
    "sg:postcode":"3431 BK",
    "sg:province":"Utrecht",
    "wof:name":"Nolan",
    "wof:placetype":"venue"
},
  "geometry": {"coordinates":[5.08554,52.031139],"type":"Point"}
}