{
  "type": "Feature",
  "properties": {
    "iso:country":"NL",
    "sg:address":"Dr A Philipsstr 32",
    "sg:city":"Hoogeveen",
    "sg:orig_category":"Maquettes",
    "sg:phone":"+31 528 273 892",
    "sg:postcode":"7903 AM",
    "sg:province":"Drenthe",
    "wof:name":"Jonge Maquettebouw, Ing L De",
    "wof:placetype":"venue"
},
  "geometry": {"coordinates":[6.497054,52.729855],"type":"Point"}
}