{
  "type": "Feature",
  "properties": {
    "addr:full":"M Pololn 111 Utrecht Utrecht 3526 GB",
    "addr:housenumber":"111",
    "addr:postcode":"3526 gb",
    "iso:country":"NL",
    "sg:address":"M Pololn 111",
    "sg:city":"Utrecht",
    "sg:orig_category":"Verloskundigen",
    "sg:phone":"+31 30 288 6666",
    "sg:postcode":"3526 GB",
    "sg:province":"Utrecht",
    "wof:name":"Verloskundigen Praktijk Utrecht West",
    "wof:placetype":"venue"
},
  "geometry": {"coordinates":[5.09982,52.063389],"type":"Point"}
}