{
  "type": "Feature",
  "properties": {
    "iso:country":"NL",
    "sg:address":"Begonialn 11",
    "sg:city":"Ede Gld",
    "sg:orig_category":"Autopoetsbedrijven",
    "sg:phone":"+31 6 50516529",
    "sg:postcode":"6713 GS",
    "sg:province":"Gelderland",
    "wof:name":"Refresh",
    "wof:placetype":"venue"
},
  "geometry": {"coordinates":[5.655159,52.037838],"type":"Point"}
}