{
  "type": "Feature",
  "properties": {
    "iso:country":"NL",
    "sg:address":"Kortenhoefsedijk 52",
    "sg:city":"Kortenhoef",
    "sg:orig_category":"Koffie, Thee And Specerijen Gh",
    "sg:phone":"+31 35 656 0355",
    "sg:postcode":"1241 LP",
    "sg:province":"Noord-Holland",
    "wof:name":"W. Buma",
    "wof:placetype":"venue"
},
  "geometry": {"coordinates":[5.102883,52.235451],"type":"Point"}
}