{
  "type": "Feature",
  "properties": {
    "addr:full":"Grutto 20 Zoeterwoude South Holland 2381 KB",
    "addr:housenumber":"20",
    "addr:postcode":"2381 kb",
    "addr:street":"Grutto",
    "iso:country":"NL",
    "sg:address":"Grutto 20",
    "sg:city":"Zoeterwoude",
    "sg:orig_category":"Poppen En Poppenhuismaterialen",
    "sg:phone":"+31 71 580 3987",
    "sg:postcode":"2381 KB",
    "sg:province":"South Holland",
    "wof:name":"Gb & S-Holland",
    "wof:placetype":"venue"
},
  "geometry": {"coordinates":[4.494341,52.119869],"type":"Point"}
}