{
  "type": "Feature",
  "properties": {
    "addr:full":"Crerarstraat 12 Hoogeveen Drenthe 7901 AE",
    "addr:housenumber":"12",
    "addr:postcode":"7901 ae",
    "addr:street":"Crerarstraat",
    "iso:country":"NL",
    "sg:address":"Crerarstraat 12",
    "sg:city":"Hoogeveen",
    "sg:orig_category":"Werving And Selectie Van Vast Personeel",
    "sg:phone":"+31 528 294 949",
    "sg:postcode":"7901 AE",
    "sg:province":"Drenthe",
    "wof:name":"Arbeidsbureau Hoogeveen",
    "wof:placetype":"venue"
},
  "geometry": {"coordinates":[6.4705228806,52.7308273315],"type":"Point"}
}