{
  "type": "Feature",
  "properties": {
    "addr:full":"Prins Hendrikstraat 190 'S Gravenhage South Holland 2518 HZ",
    "addr:housenumber":"190 '",
    "addr:postcode":"2518 hz",
    "addr:street":"Prins Hendrikstraat",
    "iso:country":"NL",
    "sg:address":"Prins Hendrikstraat 190",
    "sg:city":"'S Gravenhage",
    "sg:classifiers":[
        {
            "category":"Fast Food",
            "type":"Food & Drink"
        }
    ],
    "sg:phone":"+31 70 365 0533",
    "sg:postcode":"2518 HZ",
    "sg:province":"South Holland",
    "sg:tags":[
        "afhaal",
        "restaurant"
    ],
    "wof:name":"Aziatisch Restaurant Asia",
    "wof:placetype":"venue"
},
  "geometry": {"coordinates":[4.29004,52.080334],"type":"Point"}
}