{
  "type": "Feature",
  "properties": {
    "addr:full":"Professor J Bogermanstr 24 Franeker Friesland 8801 HB",
    "addr:housenumber":"24",
    "addr:postcode":"8801 hb",
    "addr:street":"Professor",
    "iso:country":"NL",
    "sg:address":"Professor J Bogermanstr 24",
    "sg:city":"Franeker",
    "sg:orig_category":"Kappers",
    "sg:phone":"+31 517 396 962",
    "sg:postcode":"8801 HB",
    "sg:province":"Friesland",
    "wof:name":"Haarmode Caro-Line",
    "wof:placetype":"venue"
},
  "geometry": {"coordinates":[5.5335359573,53.1872291565],"type":"Point"}
}