{
  "type": "Feature",
  "properties": {
    "addr:full":"Donkereweg 7 Heerhugowaard North Holland 1704 DV",
    "addr:housenumber":"7",
    "addr:postcode":"1704 dv",
    "addr:street":"Donkereweg",
    "iso:country":"NL",
    "sg:address":"Donkereweg 7",
    "sg:city":"Heerhugowaard",
    "sg:orig_category":"Bloemen And Planten",
    "sg:phone":"+31 72 571 5135",
    "sg:postcode":"1704 DV",
    "sg:province":"North Holland",
    "wof:name":"Firma G. Zuurbier En Zonen",
    "wof:placetype":"venue"
},
  "geometry": {"coordinates":[4.862091,52.699459],"type":"Point"}
}