{
  "type": "Feature",
  "properties": {
    "iso:country":"NL",
    "sg:address":"Zesweg 188",
    "sg:city":"Wijchen",
    "sg:orig_category":"Metaalbekleding And -Behandeling",
    "sg:phone":"+31 24 642 2754",
    "sg:postcode":"6604 BP",
    "sg:province":"Gelderland",
    "wof:name":"Metaaldraaierij Peters",
    "wof:placetype":"venue"
},
  "geometry": {"coordinates":[5.73085,51.808395],"type":"Point"}
}