{
  "type": "Feature",
  "properties": {
    "addr:full":"Christinastr 7 Nieuw Beyerland Zuid-Holland 3264 XD",
    "addr:housenumber":"7",
    "addr:postcode":"3264 xd",
    "addr:street":"Christinastr;Nieuw Beyerland",
    "iso:country":"NL",
    "sg:address":"Christinastr 7",
    "sg:city":"Nieuw Beyerland",
    "sg:orig_category":"Honden- En Kattentrimsalons",
    "sg:phone":"+31 186 692 138",
    "sg:postcode":"3264 XD",
    "sg:province":"Zuid-Holland",
    "wof:name":"Faylovesky",
    "wof:placetype":"venue"
},
  "geometry": {"coordinates":[4.340227,51.813251],"type":"Point"}
}