{
  "type": "Feature",
  "properties": {
    "addr:full":"Copernicuspln 6 S Gravenhage South Holland 2561 VN",
    "addr:housenumber":"6",
    "addr:postcode":"2561 vn",
    "addr:street":"Copernicuspln;S Gravenhage",
    "iso:country":"NL",
    "sg:address":"Copernicuspln 6",
    "sg:city":"S Gravenhage",
    "sg:orig_category":"Fietsen En Bromfietsen",
    "sg:phone":"+31 70 360 2710",
    "sg:postcode":"2561 VN",
    "sg:province":"South Holland",
    "wof:name":"Bcn",
    "wof:placetype":"venue"
},
  "geometry": {"coordinates":[4.27581,52.074532],"type":"Point"}
}