{
  "type": "Feature",
  "properties": {
    "addr:full":"Rudi Bloemgartensingel 89 Amsterdam Noord-Holland 1069 PR",
    "addr:housenumber":"89",
    "addr:postcode":"1069 pr",
    "addr:street":"Rudi Bloemgartensingel",
    "iso:country":"NL",
    "sg:address":"Rudi Bloemgartensingel 89",
    "sg:city":"Amsterdam",
    "sg:orig_category":"Elektronische Bedrijfsinstallaties",
    "sg:phone":"+31 20 610 5014",
    "sg:postcode":"1069 PR",
    "sg:province":"Noord-Holland",
    "wof:name":"Bron-Lock",
    "wof:placetype":"venue"
},
  "geometry": {"coordinates":[4.78737,52.352272],"type":"Point"}
}