{
  "type": "Feature",
  "properties": {
    "addr:full":"Overtoom 60 Amsterdam Noord-Holland 1054 HK",
    "addr:housenumber":"60",
    "addr:postcode":"1054 hk",
    "addr:street":"Overtoom",
    "iso:country":"NL",
    "sg:address":"Overtoom 60",
    "sg:city":"Amsterdam",
    "sg:orig_category":"Luchtvaart",
    "sg:phone":"+31 20 589 2989",
    "sg:postcode":"1054 HK",
    "sg:province":"Noord-Holland",
    "wof:name":"Kuwait Airways",
    "wof:placetype":"venue"
},
  "geometry": {"coordinates":[4.876068,52.363106],"type":"Point"}
}