{
  "type": "Feature",
  "properties": {
    "addr:full":"Bredasestraat 6 Bergen Op Zoom Noord-Brabant 4611 CG",
    "addr:housenumber":"6",
    "addr:postcode":"4611 cg",
    "addr:street":"Bredasestraat",
    "iso:country":"NL",
    "sg:address":"Bredasestraat 6",
    "sg:city":"Bergen Op Zoom",
    "sg:classifiers":[
        {
            "category":"Retail",
            "subcategory":"Photofinishing",
            "type":"Services"
        }
    ],
    "sg:phone":"+31 164 234 148",
    "sg:postcode":"4611 CG",
    "sg:province":"Noord-Brabant",
    "sg:tags":[
        "foto",
        "film"
    ],
    "wof:name":"Combi Serri Vof",
    "wof:placetype":"venue"
},
  "geometry": {"coordinates":[4.293825,51.495541],"type":"Point"}
}