{
  "type": "Feature",
  "properties": {
    "addr:full":"Hillegommerdijk 395 Beinsdorp North Holland 2144 KV",
    "addr:housenumber":"395",
    "addr:postcode":"2144 kv",
    "addr:street":"Hillegommerdijk",
    "iso:country":"NL",
    "sg:address":"Hillegommerdijk 395",
    "sg:city":"Beinsdorp",
    "sg:classifiers":[
        {
            "category":"Home & Garden",
            "subcategory":"Garden Supply",
            "type":"Retail Goods"
        }
    ],
    "sg:phone":"+31 6 10282531",
    "sg:postcode":"2144 KV",
    "sg:province":"North Holland",
    "sg:tags":[
        "zand",
        "en",
        "grind"
    ],
    "wof:name":"Terra Supply",
    "wof:placetype":"venue"
},
  "geometry": {"coordinates":[4.596875,52.291466],"type":"Point"}
}