{
  "type": "Feature",
  "properties": {
    "addr:full":"P J Troelstrawg 20 Ymuiden Noord-Holland 1971 HL",
    "addr:housenumber":"20",
    "addr:postcode":"1971 hl",
    "addr:street":"Ymuiden Noord-Holland",
    "iso:country":"NL",
    "sg:address":"P J Troelstrawg 20",
    "sg:city":"Ymuiden",
    "sg:orig_category":"Verenigingen En Stichtingen",
    "sg:phone":"+31 255 515 508",
    "sg:postcode":"1971 HL",
    "sg:province":"Noord-Holland",
    "wof:name":"Velser Gemeenschap, De",
    "wof:placetype":"venue"
},
  "geometry": {"coordinates":[4.617625,52.458279],"type":"Point"}
}