{
  "type": "Feature",
  "properties": {
    "addr:full":"Stationswg 83 Heiloo North Holland 1851 LJ",
    "addr:housenumber":"83",
    "addr:postcode":"1851 lj",
    "addr:street":"Stationswg",
    "iso:country":"NL",
    "sg:address":"Stationswg 83",
    "sg:city":"Heiloo",
    "sg:orig_category":"Kinderkleding",
    "sg:phone":"+31 72 532 5320",
    "sg:postcode":"1851 LJ",
    "sg:province":"North Holland",
    "wof:name":"Dibbes",
    "wof:placetype":"venue"
},
  "geometry": {"coordinates":[4.702495,52.600323],"type":"Point"}
}