{
  "type": "Feature",
  "properties": {
    "addr:full":"Groothandelsmarkt 229 Rotterdam Zuid-Holland 3044 HH",
    "addr:housenumber":"229",
    "addr:postcode":"3044 hh",
    "addr:street":"Groothandelsmarkt",
    "iso:country":"NL",
    "sg:address":"Groothandelsmarkt 229",
    "sg:city":"Rotterdam",
    "sg:orig_category":"Fruit And Groenten Gh",
    "sg:phone":"+31 10 437 4377",
    "sg:postcode":"3044 HH",
    "sg:province":"Zuid-Holland",
    "wof:name":"Van Ooijen Rotterdam Bv",
    "wof:placetype":"venue"
},
  "geometry": {"coordinates":[4.41979,51.934559],"type":"Point"}
}