{
  "type": "Feature",
  "properties": {
    "iso:country":"NL",
    "sg:address":"Nieuwpoortslaan 180",
    "sg:city":"Alkmaar",
    "sg:orig_category":"Schilderwerk",
    "sg:phone":"+31 72 515 4917",
    "sg:postcode":"1815 LS",
    "sg:province":"Noord-Holland",
    "wof:name":"Schildersbedrijf Bijwaard & De Haas",
    "wof:placetype":"venue"
},
  "geometry": {"coordinates":[4.731356,52.619762],"type":"Point"}
}