{
  "type": "Feature",
  "properties": {
    "addr:full":"Folkstonewg 65 Luchth Schiphol Noord-Holland 1118 LN",
    "addr:housenumber":"65",
    "addr:postcode":"1118 ln",
    "addr:street":"Folkstonewg",
    "iso:country":"NL",
    "sg:address":"Folkstonewg 65",
    "sg:city":"Luchth Schiphol",
    "sg:orig_category":"Luchtvrachtexpediteurs",
    "sg:phone":"+31 20 405 3335",
    "sg:postcode":"1118 LN",
    "sg:province":"Noord-Holland",
    "sg:website":"http://www.envirotainer.nl",
    "wof:name":"Envirotainer Bv",
    "wof:placetype":"venue"
},
  "geometry": {"coordinates":[4.75776,52.28928],"type":"Point"}
}