{
  "type": "Feature",
  "properties": {
    "iso:country":"NL",
    "sg:address":"Vestingplein 25",
    "sg:city":"Velserbroek",
    "sg:orig_category":"Drogisterijen",
    "sg:phone":"+31 23 538 8792",
    "sg:postcode":"1991 RK",
    "sg:province":"Noord-Holland",
    "wof:name":"Kruidvat",
    "wof:placetype":"venue"
},
  "geometry": {"coordinates":[4.661248,52.433746],"type":"Point"}
}