{
  "type": "Feature",
  "properties": {
    "addr:full":"Zijlsingel 91 Leiden South Holland 2315 KH",
    "addr:housenumber":"91",
    "addr:postcode":"2315 kh",
    "addr:street":"Zijlsingel",
    "iso:country":"NL",
    "sg:address":"Zijlsingel 91",
    "sg:city":"Leiden",
    "sg:orig_category":"Fietshandelaren",
    "sg:phone":"+31 71 522 4923",
    "sg:postcode":"2315 KH",
    "sg:province":"South Holland",
    "wof:name":"Vof R. Van Den Berg",
    "wof:placetype":"venue"
},
  "geometry": {"coordinates":[4.504129,52.156445],"type":"Point"}
}