{
  "type": "Feature",
  "properties": {
    "addr:full":"Vinkenstraat 86 Zaandam North Holland 1506 CP",
    "addr:housenumber":"86",
    "addr:postcode":"1506 cp",
    "addr:street":"Vinkenstraat",
    "iso:country":"NL",
    "sg:address":"Vinkenstraat 86",
    "sg:city":"Zaandam",
    "sg:orig_category":"Beautyfarms And Sauna'S",
    "sg:phone":"+31 75 635 6519",
    "sg:postcode":"1506 CP",
    "sg:province":"North Holland",
    "wof:name":"Khymo'S Health And Beauty Centre",
    "wof:placetype":"venue"
},
  "geometry": {"coordinates":[4.81883,52.439453],"type":"Point"}
}