{
  "type": "Feature",
  "properties": {
    "addr:full":"Ruiterstr 10 Zaltbommel Gelderland 5301 ED",
    "addr:housenumber":"10",
    "addr:postcode":"5301 ed",
    "addr:street":"Ruiterstr;Gelderland",
    "iso:country":"NL",
    "sg:address":"Ruiterstr 10",
    "sg:city":"Zaltbommel",
    "sg:orig_category":"Artsen - Huisartsen",
    "sg:phone":"+31 418 513 557",
    "sg:postcode":"5301 ED",
    "sg:province":"Gelderland",
    "wof:name":"Dijk, P A Van",
    "wof:placetype":"venue"
},
  "geometry": {"coordinates":[5.249999,51.812477],"type":"Point"}
}