{
  "type": "Feature",
  "properties": {
    "addr:full":"De Groet 17A Waarland North Holland 1738 DV",
    "addr:housenumber":"17a",
    "addr:postcode":"1738 dv",
    "addr:street":"De Groet",
    "iso:country":"NL",
    "sg:address":"De Groet 17A",
    "sg:city":"Waarland",
    "sg:orig_category":"Lijsten - Fabrieken En Groothandel",
    "sg:phone":"+31 226 421 518",
    "sg:postcode":"1738 DV",
    "sg:province":"North Holland",
    "wof:name":"Rojos",
    "wof:placetype":"venue"
},
  "geometry": {"coordinates":[4.829695,52.729218],"type":"Point"}
}