{
  "type": "Feature",
  "properties": {
    "addr:full":"Heerengr 66 Franeker Friesland 8801 MD",
    "addr:housenumber":"66",
    "addr:postcode":"8801",
    "addr:street":"Heerengr",
    "iso:country":"NL",
    "sg:address":"Heerengr 66",
    "sg:city":"Franeker",
    "sg:orig_category":"Kappers",
    "sg:phone":"+31 517 395 000",
    "sg:postcode":"8801 MD",
    "sg:province":"Friesland",
    "wof:name":"Petite Maison, La",
    "wof:placetype":"venue"
},
  "geometry": {"coordinates":[5.545757,53.185326],"type":"Point"}
}