{
  "type": "Feature",
  "properties": {
    "addr:full":"Burensedk 13 Buurmalsen Gelderland 4197 RE",
    "addr:housenumber":"13",
    "addr:postcode":"4197",
    "addr:street":"Burensedk;Gelderland",
    "iso:country":"NL",
    "sg:address":"Burensedk 13",
    "sg:city":"Buurmalsen",
    "sg:orig_category":"Pianostemmen En -Reparatie",
    "sg:phone":"+31 345 574 989",
    "sg:postcode":"4197 RE",
    "sg:province":"Gelderland",
    "wof:name":"Gewestelijk Inst",
    "wof:placetype":"venue"
},
  "geometry": {"coordinates":[5.302828,51.894798],"type":"Point"}
}