{
  "type": "Feature",
  "properties": {
    "addr:full":"Koninginnewg 11-13 Hilversum Noord-Holland 1217 KP",
    "addr:housenumber":"11-13",
    "addr:postcode":"hilversum;1217 kp",
    "iso:country":"NL",
    "sg:address":"Koninginnewg 11-13",
    "sg:city":"Hilversum",
    "sg:orig_category":"Verzekeringen - Verzekeringskantoren",
    "sg:phone":"+31 35 750 1111",
    "sg:postcode":"1217 KP",
    "sg:province":"Noord-Holland",
    "sg:website":"http://www.assicuro.nl",
    "wof:name":"Assicuro Bv",
    "wof:placetype":"venue"
},
  "geometry": {"coordinates":[5.167174,52.229546],"type":"Point"}
}