{
  "type": "Feature",
  "properties": {
    "iso:country":"NL",
    "sg:address":"Twynstr 50",
    "sg:city":"Utrecht",
    "sg:orig_category":"Bloemen En Planten",
    "sg:phone":"+31 30 231 3006",
    "sg:postcode":"3511 ZM",
    "sg:province":"Utrecht",
    "wof:name":"Korenschoof, De",
    "wof:placetype":"venue"
},
  "geometry": {"coordinates":[5.123751,52.082207],"type":"Point"}
}