{
  "type": "Feature",
  "properties": {
    "iso:country":"NL",
    "sg:address":"Zaanwg 95",
    "sg:city":"Wormerveer",
    "sg:orig_category":"Kindermeubelen",
    "sg:phone":"+31 75 622 3144",
    "sg:postcode":"1521 DP",
    "sg:province":"North Holland",
    "wof:name":"Mikamila Kinderspullen",
    "wof:placetype":"venue"
},
  "geometry": {"coordinates":[4.791537,52.49081],"type":"Point"}
}