{
  "type": "Feature",
  "properties": {
    "addr:full":"De Hoeven 62 Heusden Gem Heusden Noord-Brabant 5256 VS",
    "addr:housenumber":"62",
    "addr:postcode":"5256 vs",
    "addr:street":"De Hoeven",
    "iso:country":"NL",
    "sg:address":"De Hoeven 62",
    "sg:city":"Heusden Gem Heusden",
    "sg:classifiers":[
        {
            "category":"Food & Beverages",
            "subcategory":"Fruits & Vegetables",
            "type":"Retail Goods"
        }
    ],
    "sg:phone":"+31 73 511 3095",
    "sg:postcode":"5256 VS",
    "sg:province":"Noord-Brabant",
    "sg:tags":[
        "groenten"
    ],
    "wof:name":"P.J. Van Heeswijk",
    "wof:placetype":"venue"
},
  "geometry": {"coordinates":[5.163196,51.70615],"type":"Point"}
}