{
  "type": "Feature",
  "properties": {
    "addr:full":"Dorpsstr 629 Assendelft North Holland 1566 EB",
    "addr:housenumber":"629",
    "addr:postcode":"1566 eb",
    "iso:country":"NL",
    "sg:address":"Dorpsstr 629",
    "sg:city":"Assendelft",
    "sg:orig_category":"Metselwerken",
    "sg:phone":"+31 6 11003892",
    "sg:postcode":"1566 EB",
    "sg:province":"North Holland",
    "wof:name":"Dijk, J Van",
    "wof:placetype":"venue"
},
  "geometry": {"coordinates":[4.749051,52.477772],"type":"Point"}
}