{
  "type": "Feature",
  "properties": {
    "iso:country":"NL",
    "sg:address":"Nieuwe Havenweg 75",
    "sg:city":"Hilversum",
    "sg:orig_category":"Kantoor- And Schoolbenodigdheden Gh",
    "sg:phone":"+31 35 621 9678",
    "sg:postcode":"1216 BN",
    "sg:province":"Noord-Holland",
    "wof:name":"Hekla Hilversum Bv",
    "wof:placetype":"venue"
},
  "geometry": {"coordinates":[5.1405191422,52.2219429016],"type":"Point"}
}