{
  "type": "Feature",
  "properties": {
    "addr:full":"Druivenstraat 37 'S Gravenhage Zuid-Holland 2564 VE",
    "addr:housenumber":"37",
    "addr:postcode":"2564",
    "addr:street":"Druivenstraat;' S;Ve",
    "iso:country":"NL",
    "sg:address":"Druivenstraat 37",
    "sg:city":"'S Gravenhage",
    "sg:orig_category":"Paramedische Behandelingen",
    "sg:phone":"+31 70 368 2282",
    "sg:postcode":"2564 VE",
    "sg:province":"Zuid-Holland",
    "wof:name":"H.B. Zegwaard-Vos",
    "wof:placetype":"venue"
},
  "geometry": {"coordinates":[4.260778,52.072166],"type":"Point"}
}