{
  "type": "Feature",
  "properties": {
    "addr:full":"Prinsestr 22A Enschede Overijssel 7513 AL",
    "addr:housenumber":"22a",
    "addr:postcode":"7513 al",
    "addr:street":"Prinsestr",
    "iso:country":"NL",
    "sg:address":"Prinsestr 22A",
    "sg:city":"Enschede",
    "sg:orig_category":"Artsen - Huisartsen",
    "sg:phone":"+31 53 432 4473",
    "sg:postcode":"7513 AL",
    "sg:province":"Overijssel",
    "wof:name":"Burgh En N W Fons, M E Vd",
    "wof:placetype":"venue"
},
  "geometry": {"coordinates":[6.886064,52.21764],"type":"Point"}
}