{
  "type": "Feature",
  "properties": {
    "addr:full":"Belgiestr 7 Oisterwyk Noord-Brabant 5061 KG",
    "addr:housenumber":"7",
    "addr:postcode":"5061 kg",
    "addr:street":"Belgiestr",
    "iso:country":"NL",
    "sg:address":"Belgiestr 7",
    "sg:city":"Oisterwyk",
    "sg:orig_category":"Keukens",
    "sg:phone":"+31 13 521 9612",
    "sg:postcode":"5061 KG",
    "sg:province":"Noord-Brabant",
    "wof:name":"Siematic Studio Nuva",
    "wof:placetype":"venue"
},
  "geometry": {"coordinates":[5.195323,51.586166],"type":"Point"}
}