{
  "type": "Feature",
  "properties": {
    "addr:full":"Seinestr 64 Venlo Limburg 5912 LD",
    "addr:housenumber":"64",
    "addr:postcode":"5912 ld",
    "addr:street":"Seinestr",
    "iso:country":"NL",
    "sg:address":"Seinestr 64",
    "sg:city":"Venlo",
    "sg:orig_category":"Levensmiddelen- Grondstoffen - Fabrieken En Groothandel",
    "sg:phone":"+31 6 53918338",
    "sg:postcode":"5912 LD",
    "sg:province":"Limburg",
    "wof:name":"Bosman, Bur",
    "wof:placetype":"venue"
},
  "geometry": {"coordinates":[6.160542,51.365131],"type":"Point"}
}