{
  "type": "Feature",
  "properties": {
    "iso:country":"NL",
    "sg:address":"Prof Zernikestr 1",
    "sg:city":"Sneek",
    "sg:orig_category":"Watersportartikelen",
    "sg:phone":"+31 515 487 575",
    "sg:postcode":"8606 JS",
    "sg:province":"Provincie Friesland",
    "wof:name":"Lankhorst Taselaar",
    "wof:placetype":"venue"
},
  "geometry": {"coordinates":[5.6833968163,53.0195999146],"type":"Point"}
}