{
  "type": "Feature",
  "properties": {
    "addr:full":"Postbus 134 Raalte NL.08 8100 AC",
    "addr:housenumber":"134;nl.08",
    "addr:postcode":"8100 ac",
    "addr:street":"Postbus",
    "iso:country":"NL",
    "sg:address":"Postbus 134",
    "sg:city":"Raalte",
    "sg:orig_category":"Verenigingen En Stichtingen",
    "sg:phone":"+31 572 361 177",
    "sg:postcode":"8100 AC",
    "sg:province":"NL.08",
    "wof:name":"Protestants Chr Ouderen Bond",
    "wof:placetype":"venue"
},
  "geometry": {"coordinates":[6.274628,52.387249],"type":"Point"}
}