{
  "type": "Feature",
  "properties": {
    "addr:full":"De Brink 74 Zutphen Gelderland 7206 KC",
    "addr:housenumber":"74",
    "addr:postcode":"7206 kc",
    "addr:street":"De Brink;Gelderland",
    "iso:country":"NL",
    "sg:address":"De Brink 74",
    "sg:city":"Zutphen",
    "sg:orig_category":"Fietsen En Bromfietsen",
    "sg:phone":"+31 575 526 628",
    "sg:postcode":"7206 KC",
    "sg:province":"Gelderland",
    "wof:name":"Wolters",
    "wof:placetype":"venue"
},
  "geometry": {"coordinates":[6.191525,52.140202],"type":"Point"}
}