{
  "type": "Feature",
  "properties": {
    "addr:full":"Aluminiumstr 12 Groningen Groningen 9743 SE",
    "addr:housenumber":"12",
    "addr:postcode":"9743 se",
    "addr:street":"Aluminiumstr",
    "iso:country":"NL",
    "sg:address":"Aluminiumstr 12",
    "sg:city":"Groningen",
    "sg:orig_category":"Psychologen",
    "sg:phone":"+31 50 571 1434",
    "sg:postcode":"9743 SE",
    "sg:province":"Groningen",
    "wof:name":"Callender, Drs K S",
    "wof:placetype":"venue"
},
  "geometry": {"coordinates":[6.531166,53.221745],"type":"Point"}
}