{
  "type": "Feature",
  "properties": {
    "addr:full":"Schansstr 22B Raamsdonk North Brabant 4944 AH",
    "addr:housenumber":"22b",
    "addr:postcode":"4944 ah",
    "addr:street":"Schansstr",
    "iso:country":"NL",
    "sg:address":"Schansstr 22B",
    "sg:city":"Raamsdonk",
    "sg:orig_category":"Adviesbureaus Bouwkunde",
    "sg:phone":"+31 162 512 423",
    "sg:postcode":"4944 AH",
    "sg:province":"North Brabant",
    "wof:name":"Keijzers",
    "wof:placetype":"venue"
},
  "geometry": {"coordinates":[4.914241,51.688087],"type":"Point"}
}