{
  "type": "Feature",
  "properties": {
    "addr:full":"Appelaar 7 Oosterhout Nb North Brabant 4907 KD",
    "addr:housenumber":"7;nb",
    "addr:postcode":"4907 kd",
    "addr:street":"Appelaar",
    "iso:country":"NL",
    "sg:address":"Appelaar 7",
    "sg:city":"Oosterhout Nb",
    "sg:orig_category":"Glaszetten",
    "sg:phone":"+31 162 470 078",
    "sg:postcode":"4907 KD",
    "sg:province":"North Brabant",
    "wof:name":"Atelier Elders",
    "wof:placetype":"venue"
},
  "geometry": {"coordinates":[4.863495,51.661346],"type":"Point"}
}