{
  "type": "Feature",
  "properties": {
    "addr:full":"Robynstr 7 Hengelo Ov Overijssel 7554 TK",
    "addr:housenumber":"7",
    "addr:postcode":"7554 tk",
    "addr:street":"Robynstr;Ov",
    "iso:country":"NL",
    "sg:address":"Robynstr 7",
    "sg:city":"Hengelo Ov",
    "sg:orig_category":"Automaterialen En Gereedschappen",
    "sg:phone":"+31 74 291 2035",
    "sg:postcode":"7554 TK",
    "sg:province":"Overijssel",
    "wof:name":"Veenstra Hengelo Bv",
    "wof:placetype":"venue"
},
  "geometry": {"coordinates":[6.78971,52.266331],"type":"Point"}
}