{
  "type": "Feature",
  "properties": {
    "iso:country":"NL",
    "sg:address":"Zaanstraat 22",
    "sg:city":"Enschede",
    "sg:classifiers":[
        {
            "category":"Education",
            "subcategory":"Preschool",
            "type":"Public Place"
        }
    ],
    "sg:phone":"+31 53 435 5593",
    "sg:postcode":"7523 HC",
    "sg:province":"Overijssel",
    "sg:tags":[
        "kleuteronderwijs",
        "basis-"
    ],
    "wof:name":"De Noordlinde",
    "wof:placetype":"venue"
},
  "geometry": {"coordinates":[6.88617,52.240162],"type":"Point"}
}