{
  "type": "Feature",
  "properties": {
    "addr:full":"Nijverheidslaan 28 Weesp North Holland 1382 LJ",
    "addr:housenumber":"28",
    "addr:postcode":"1382 lj",
    "addr:street":"Nijverheidslaan",
    "iso:country":"NL",
    "sg:address":"Nijverheidslaan 28",
    "sg:city":"Weesp",
    "sg:orig_category":"Meubelzaken, Woning- And Keukeninrichting",
    "sg:phone":"+31 294 431 967",
    "sg:postcode":"1382 LJ",
    "sg:province":"North Holland",
    "wof:name":"Denpasar",
    "wof:placetype":"venue"
},
  "geometry": {"coordinates":[5.052309,52.31152],"type":"Point"}
}