{
  "type": "Feature",
  "properties": {
    "addr:full":"Piccolopad 34 Amersfoort Utrecht 3822 CR",
    "addr:housenumber":"34",
    "addr:postcode":"3822 cr",
    "addr:street":"Piccolopad",
    "iso:country":"NL",
    "sg:address":"Piccolopad 34",
    "sg:city":"Amersfoort",
    "sg:orig_category":"Autorijscholen",
    "sg:phone":"+31 33 455 5769",
    "sg:postcode":"3822 CR",
    "sg:province":"Utrecht",
    "wof:name":"Achterberg, Ron",
    "wof:placetype":"venue"
},
  "geometry": {"coordinates":[5.404581,52.180622],"type":"Point"}
}