{
  "type": "Feature",
  "properties": {
    "iso:country":"NL",
    "sg:address":"Kerkstr 12",
    "sg:city":"Schoonhoven",
    "sg:orig_category":"Journalisten Freelance",
    "sg:phone":"+31 182 320 547",
    "sg:postcode":"2871 EH",
    "sg:province":"Zuid-Holland",
    "wof:name":"Midden Holland",
    "wof:placetype":"venue"
},
  "geometry": {"coordinates":[4.849398,51.946339],"type":"Point"}
}