{
  "type": "Feature",
  "properties": {
    "addr:full":"Meerndijk 12A De Meern Utrecht 3454 HR",
    "addr:housenumber":"12a",
    "addr:postcode":"3454 hr",
    "addr:street":"Meerndijk",
    "iso:country":"NL",
    "sg:address":"Meerndijk 12A",
    "sg:city":"De Meern",
    "sg:orig_category":"Fotostudio'S And Fotografen",
    "sg:phone":"+31 30 666 1485",
    "sg:postcode":"3454 HR",
    "sg:province":"Utrecht",
    "wof:name":"Paul Van Den Dungen Fotografie",
    "wof:placetype":"venue"
},
  "geometry": {"coordinates":[5.03689,52.082188],"type":"Point"}
}