{
  "type": "Feature",
  "properties": {
    "addr:full":"Wielingenweg 208 Alkmaar Noord-Holland 1826 BT",
    "addr:housenumber":"208",
    "addr:postcode":"1826 bt",
    "addr:street":"Wielingenweg",
    "iso:country":"NL",
    "sg:address":"Wielingenweg 208",
    "sg:city":"Alkmaar",
    "sg:orig_category":"Vertaal- And Tolkenbureaus",
    "sg:phone":"+31 72 560 0150",
    "sg:postcode":"1826 BT",
    "sg:province":"Noord-Holland",
    "wof:name":"Russian Business Consultancy Rbc",
    "wof:placetype":"venue"
},
  "geometry": {"coordinates":[4.765724,52.655891],"type":"Point"}
}