{
  "type": "Feature",
  "properties": {
    "iso:country":"NL",
    "sg:address":"Lichtenvoordsewg 58",
    "sg:city":"Groenlo",
    "sg:orig_category":"Begrafenisverzorging",
    "sg:phone":"+31 544 461 515",
    "sg:postcode":"7141 DZ",
    "sg:province":"Gelderland",
    "sg:website":"http://www.skcc.nl",
    "wof:name":"Uitvaartcentrum Ventura, Rk Begraafplaats",
    "wof:placetype":"venue"
},
  "geometry": {"coordinates":[6.614417,52.035145],"type":"Point"}
}