{
  "type": "Feature",
  "properties": {
    "iso:country":"NL",
    "sg:address":"Almeloseweg 45",
    "sg:city":"Tubbergen",
    "sg:orig_category":"Bloemen And Planten",
    "sg:phone":"+31 546 621 547",
    "sg:postcode":"7651 ND",
    "sg:province":"NL.08",
    "wof:name":"Europatuin Tubbergen",
    "wof:placetype":"venue"
},
  "geometry": {"coordinates":[6.775759,52.404228],"type":"Point"}
}