{
  "type": "Feature",
  "properties": {
    "addr:full":"Almeloseweg 45 Tubbergen NL.08 7651 ND",
    "addr:housenumber":"45;nl.08",
    "addr:postcode":"7651 nd",
    "addr:street":"Almeloseweg",
    "iso:country":"NL",
    "sg:address":"Almeloseweg 45",
    "sg:city":"Tubbergen",
    "sg:orig_category":"Bloemen And Planten",
    "sg:phone":"+31 546 621 547",
    "sg:postcode":"7651 ND",
    "sg:province":"NL.08",
    "wof:name":"Europatuin Tubbergen",
    "wof:placetype":"venue"
},
  "geometry": {"coordinates":[6.775759,52.404228],"type":"Point"}
}