{
  "type": "Feature",
  "properties": {
    "addr:full":"Vierlinghstr 6D Werkendam Noord-Brabant 4251 LC",
    "addr:housenumber":"6d",
    "addr:postcode":"4251 lc",
    "iso:country":"NL",
    "sg:address":"Vierlinghstr 6D",
    "sg:city":"Werkendam",
    "sg:classifiers":[
        {
            "category":"Professional",
            "subcategory":"Accounting & Tax Preparation",
            "type":"Services"
        }
    ],
    "sg:phone":"+31 183 635 377",
    "sg:postcode":"4251 LC",
    "sg:province":"Noord-Brabant",
    "sg:tags":[
        "accountant",
        "en",
        "-kantoren",
        "register-"
    ],
    "wof:name":"Ravesteijn & Leliveld, Van",
    "wof:placetype":"venue"
},
  "geometry": {"coordinates":[4.883185,51.80291],"type":"Point"}
}