{
  "type": "Feature",
  "properties": {
    "addr:full":"Celsiusbaan 6 Nieuwegein Utrecht 3439 NC",
    "addr:housenumber":"6",
    "addr:postcode":"3439 nc",
    "addr:street":"Celsiusbaan",
    "iso:country":"NL",
    "sg:address":"Celsiusbaan 6",
    "sg:city":"Nieuwegein",
    "sg:orig_category":"Verf En Lak - Fabrieken En Groothandel",
    "sg:phone":"+31 30 604 1818",
    "sg:postcode":"3439 NC",
    "sg:province":"Utrecht",
    "wof:name":"Koopman",
    "wof:placetype":"venue"
},
  "geometry": {"coordinates":[5.109658,52.031403],"type":"Point"}
}