{
  "type": "Feature",
  "properties": {
    "addr:full":"Willemstr 47 Delft Zuid-Holland 2613 DS",
    "addr:housenumber":"47",
    "addr:postcode":"2613 ds",
    "addr:street":"Willemstr",
    "iso:country":"NL",
    "sg:address":"Willemstr 47",
    "sg:city":"Delft",
    "sg:orig_category":"Onderhoudswerken",
    "sg:phone":"+31 15 212 5212",
    "sg:postcode":"2613 DS",
    "sg:province":"Zuid-Holland",
    "wof:name":"Verbeek",
    "wof:placetype":"venue"
},
  "geometry": {"coordinates":[4.349172,52.010857],"type":"Point"}
}