{
  "type": "Feature",
  "properties": {
    "addr:full":"Gaardenstr 31 Holten NL.08 7451 CV",
    "addr:housenumber":"31;nl.08",
    "addr:postcode":"7451 cv",
    "addr:street":"Gaardenstr",
    "iso:country":"NL",
    "sg:address":"Gaardenstr 31",
    "sg:city":"Holten",
    "sg:orig_category":"Mensendieck - Oefentherapeuten",
    "sg:phone":"+31 548 362 299",
    "sg:postcode":"7451 CV",
    "sg:province":"NL.08",
    "wof:name":"Tomassen-Hettinga, J J M",
    "wof:placetype":"venue"
},
  "geometry": {"coordinates":[6.418625,52.281601],"type":"Point"}
}