{
  "type": "Feature",
  "properties": {
    "addr:full":"Scherpakkerwg 9 Eindhoven Noord-Brabant 5616 HP",
    "addr:housenumber":"9",
    "addr:postcode":"5616 hp",
    "addr:street":"Scherpakkerwg",
    "iso:country":"NL",
    "sg:address":"Scherpakkerwg 9",
    "sg:city":"Eindhoven",
    "sg:orig_category":"Wasmachines En Wasdrogers - Onderhoud En Reparatie",
    "sg:phone":"+31 40 255 1110",
    "sg:postcode":"5616 HP",
    "sg:province":"Noord-Brabant",
    "wof:name":"Verheijen Onderdelen",
    "wof:placetype":"venue"
},
  "geometry": {"coordinates":[5.4554672241,51.4361724854],"type":"Point"}
}