{
  "type": "Feature",
  "properties": {
    "addr:full":"Harmonieln 41B Zeist Utrecht 3704 HH",
    "addr:housenumber":"41b",
    "addr:postcode":"3704 hh",
    "addr:street":"Harmonieln",
    "iso:country":"NL",
    "sg:address":"Harmonieln 41B",
    "sg:city":"Zeist",
    "sg:orig_category":"Adviesbureaus Bedrijfsorganisatie",
    "sg:phone":"+31 30 699 1691",
    "sg:postcode":"3704 HH",
    "sg:province":"Utrecht",
    "wof:name":"Biztos Bv",
    "wof:placetype":"venue"
},
  "geometry": {"coordinates":[5.24387,52.08548],"type":"Point"}
}