{
  "type": "Feature",
  "properties": {
    "addr:full":"Dkn Zondagln 98 Vogelenzang Noord-Holland 2114 EE",
    "addr:housenumber":"98",
    "addr:postcode":"2114 ee",
    "iso:country":"NL",
    "sg:address":"Dkn Zondagln 98",
    "sg:city":"Vogelenzang",
    "sg:classifiers":[
        {
            "category":"Food & Beverages",
            "subcategory":"Bakery",
            "type":"Retail Goods"
        }
    ],
    "sg:phone":"+31 23 584 9276",
    "sg:postcode":"2114 EE",
    "sg:province":"Noord-Holland",
    "sg:tags":[
        "brood",
        "en",
        "banket"
    ],
    "wof:name":"Caspers",
    "wof:placetype":"venue"
},
  "geometry": {"coordinates":[4.575447,52.319458],"type":"Point"}
}