{
  "type": "Feature",
  "properties": {
    "addr:full":"Meester Troelstralaan 2 Amstelveen North Holland 1181 VE",
    "addr:housenumber":"2",
    "addr:postcode":"1181",
    "addr:street":"Meester Troelstralaan;Ve",
    "iso:country":"NL",
    "sg:address":"Meester Troelstralaan 2",
    "sg:city":"Amstelveen",
    "sg:orig_category":"Kunstbemiddeling",
    "sg:phone":"+31 20 453 2810",
    "sg:postcode":"1181 VE",
    "sg:province":"North Holland",
    "wof:name":"Touch Of Art Bv, The",
    "wof:placetype":"venue"
},
  "geometry": {"coordinates":[4.851028,52.306648],"type":"Point"}
}