{
  "type": "Feature",
  "properties": {
    "addr:full":"V Wassenaerwg 19 Oosterbeek Gelderland 6862 ZC",
    "addr:housenumber":"19",
    "addr:postcode":"6862 zc",
    "addr:street":"Gelderland",
    "iso:country":"NL",
    "sg:address":"V Wassenaerwg 19",
    "sg:city":"Oosterbeek",
    "sg:orig_category":"Psychotherapeuten",
    "sg:phone":"+31 26 370 8022",
    "sg:postcode":"6862 ZC",
    "sg:province":"Gelderland",
    "wof:name":"Christelijke Hulpverlening, Praktijk Voor",
    "wof:placetype":"venue"
},
  "geometry": {"coordinates":[5.84094,51.987579],"type":"Point"}
}