{
  "type": "Feature",
  "properties": {
    "addr:full":"Grt Hertoginneln 52 S Gravenhage Zuid-Holland 2517 EJ",
    "addr:housenumber":"52;gravenhage",
    "addr:postcode":"2517 ej",
    "addr:street":"S",
    "iso:country":"NL",
    "sg:address":"Grt Hertoginneln 52",
    "sg:city":"S Gravenhage",
    "sg:orig_category":"Architecten En Architectenbureaus",
    "sg:phone":"+31 70 346 6367",
    "sg:postcode":"2517 EJ",
    "sg:province":"Zuid-Holland",
    "sg:website":"http://www.terryvanderheide.nl",
    "wof:name":"Terry Van Der Heide Architecten Bv",
    "wof:placetype":"venue"
},
  "geometry": {"coordinates":[4.2870798111,52.0866699219],"type":"Point"}
}