{
  "type": "Feature",
  "properties": {
    "addr:full":"Burg Fockstr 64 Amsterdam Noord-Holland 1063 CV",
    "addr:housenumber":"64",
    "addr:postcode":"1063 cv",
    "addr:street":"Burg",
    "iso:country":"NL",
    "sg:address":"Burg Fockstr 64",
    "sg:city":"Amsterdam",
    "sg:orig_category":"Fietsen En Bromfietsen",
    "sg:phone":"+31 20 613 5522",
    "sg:postcode":"1063 CV",
    "sg:province":"Noord-Holland",
    "wof:name":"Hoogland, Q C M",
    "wof:placetype":"venue"
},
  "geometry": {"coordinates":[4.833029,52.381153],"type":"Point"}
}