{
  "type": "Feature",
  "properties": {
    "addr:full":"Sportln 2 Maarn Utrecht 3951 CG",
    "addr:housenumber":"2",
    "addr:postcode":"3951 cg",
    "addr:street":"Sportln",
    "iso:country":"NL",
    "sg:address":"Sportln 2",
    "sg:city":"Maarn",
    "sg:orig_category":"Adviesbureaus Bedrijfsorganisatie",
    "sg:phone":"+31 343 443 551",
    "sg:postcode":"3951 CG",
    "sg:province":"Utrecht",
    "wof:name":"Copal Bv",
    "wof:placetype":"venue"
},
  "geometry": {"coordinates":[5.374867,52.064064],"type":"Point"}
}