{
  "type": "Feature",
  "properties": {
    "addr:full":"Oostbroekselaan 52 Utrecht Utrecht 3584 BD",
    "addr:housenumber":"52",
    "addr:postcode":"3584 bd",
    "addr:street":"Oostbroekselaan",
    "iso:country":"NL",
    "sg:address":"Oostbroekselaan 52",
    "sg:city":"Utrecht",
    "sg:orig_category":"Beursorganisaties And Standbouw",
    "sg:phone":"+31 30 252 2242",
    "sg:postcode":"3584 BD",
    "sg:province":"Utrecht",
    "wof:name":"Eduard Van Aarle",
    "wof:placetype":"venue"
},
  "geometry": {"coordinates":[5.154483,52.095753],"type":"Point"}
}