{
  "type": "Feature",
  "properties": {
    "addr:full":"Vanadiumweg 22A Amersfoort Utrecht 3812 PZ",
    "addr:housenumber":"22a",
    "addr:postcode":"3812 pz",
    "addr:street":"Vanadiumweg",
    "iso:country":"NL",
    "sg:address":"Vanadiumweg 22A",
    "sg:city":"Amersfoort",
    "sg:orig_category":"Beveiliging",
    "sg:phone":"+31 33 422 4700",
    "sg:postcode":"3812 PZ",
    "sg:province":"Utrecht",
    "sg:website":"http://www.rsgroep.nl",
    "wof:name":"Roest Groep",
    "wof:placetype":"venue"
},
  "geometry": {"coordinates":[5.35401,52.171715],"type":"Point"}
}