{
  "type": "Feature",
  "properties": {
    "addr:full":"Populierstraat 6 Breda Noord-Brabant 4814 HP",
    "addr:housenumber":"6",
    "addr:postcode":"4814 hp",
    "addr:street":"Populierstraat",
    "iso:country":"NL",
    "sg:address":"Populierstraat 6",
    "sg:city":"Breda",
    "sg:orig_category":"Loodgieterswerk, Verwarming And Sanitaire Installaties",
    "sg:phone":"+31 76 520 3989",
    "sg:postcode":"4814 HP",
    "sg:province":"Noord-Brabant",
    "wof:name":"Aad Rioolservice",
    "wof:placetype":"venue"
},
  "geometry": {"coordinates":[4.756201,51.586872],"type":"Point"}
}