{
  "type": "Feature",
  "properties": {
    "addr:full":"Bolswardervaart 1 Harlingen Provincie Friesland 8862 SE",
    "addr:housenumber":"1;8862",
    "addr:street":"Bolswardervaart;Provincie Friesland;Se",
    "iso:country":"NL",
    "sg:address":"Bolswardervaart 1",
    "sg:city":"Harlingen",
    "sg:orig_category":"Woningbouwverenigingen",
    "sg:phone":"+31 517 432 525",
    "sg:postcode":"8862 SE",
    "sg:province":"Provincie Friesland",
    "wof:name":"Stichting Woningbeheer Harlingen",
    "wof:placetype":"venue"
},
  "geometry": {"coordinates":[5.4223327637,53.1697502136],"type":"Point"}
}