{
  "type": "Feature",
  "properties": {
    "addr:full":"Nassaulaan 55 Schiedam South Holland 3116 ET",
    "addr:housenumber":"55",
    "addr:postcode":"3116 et",
    "addr:street":"Nassaulaan",
    "iso:country":"NL",
    "sg:address":"Nassaulaan 55",
    "sg:city":"Schiedam",
    "sg:orig_category":"Boekhouders",
    "sg:phone":"+31 10 426 2525",
    "sg:postcode":"3116 ET",
    "sg:province":"South Holland",
    "wof:name":"Administratiekantoor De Vos Burchart",
    "wof:placetype":"venue"
},
  "geometry": {"coordinates":[4.398197,51.910477],"type":"Point"}
}