{
  "type": "Feature",
  "properties": {
    "addr:full":"Markendaalseweg 2 Breda Noord-Brabant 4811 KC",
    "addr:housenumber":"2",
    "addr:postcode":"4811 kc",
    "addr:street":"Markendaalseweg",
    "iso:country":"NL",
    "sg:address":"Markendaalseweg 2",
    "sg:city":"Breda",
    "sg:orig_category":"Meubelzaken, Woning- And Keukeninrichting",
    "sg:phone":"+31 76 520 5517",
    "sg:postcode":"4811 KC",
    "sg:province":"Noord-Brabant",
    "wof:name":"Lamers & Lamers Cv",
    "wof:placetype":"venue"
},
  "geometry": {"coordinates":[4.771169,51.588272],"type":"Point"}
}