{
  "type": "Feature",
  "properties": {
    "addr:full":"Smitswg 46 Soest Utrecht 3765 CT",
    "addr:housenumber":"46",
    "addr:postcode":"3765 ct",
    "addr:street":"Smitswg",
    "iso:country":"NL",
    "sg:address":"Smitswg 46",
    "sg:city":"Soest",
    "sg:orig_category":"Scholen Voor Basisonderwijs",
    "sg:phone":"+31 35 601 7230",
    "sg:postcode":"3765 CT",
    "sg:province":"Utrecht",
    "wof:name":"Dani?l Reform",
    "wof:placetype":"venue"
},
  "geometry": {"coordinates":[5.287854,52.169945],"type":"Point"}
}