{
  "type": "Feature",
  "properties": {
    "iso:country":"NL",
    "sg:address":"Herderlaan 10",
    "sg:city":"Ermelo",
    "sg:orig_category":"Zuivelproducten",
    "sg:phone":"+31 341 561 874",
    "sg:postcode":"3851 BD",
    "sg:province":"Gelderland",
    "wof:name":"Domburg Kaas En Noten",
    "wof:placetype":"venue"
},
  "geometry": {"coordinates":[5.610311,52.29134],"type":"Point"}
}