{
  "type": "Feature",
  "properties": {
    "addr:full":"Ln V Meerdervoort 522 S Gravenhage Zuid-Holland 2563 BK",
    "addr:housenumber":"522;gravenhage",
    "addr:postcode":"2563 bk",
    "addr:street":"Ln;Meerdervoort;S",
    "iso:country":"NL",
    "sg:address":"Ln V Meerdervoort 522",
    "sg:city":"S Gravenhage",
    "sg:orig_category":"Kappers",
    "sg:phone":"+31 70 345 2260",
    "sg:postcode":"2563 BK",
    "sg:province":"Zuid-Holland",
    "wof:name":"Mady'S Hairstylist'S",
    "wof:placetype":"venue"
},
  "geometry": {"coordinates":[4.270956,52.072578],"type":"Point"}
}