{
  "type": "Feature",
  "properties": {
    "addr:full":"Kerkstr 29 Voorthuizen Gelderland 3781 GA",
    "addr:housenumber":"29",
    "addr:postcode":"3781 ga",
    "addr:street":"Kerkstr;Gelderland",
    "iso:country":"NL",
    "sg:address":"Kerkstr 29",
    "sg:city":"Voorthuizen",
    "sg:orig_category":"Accountants - Administratie- Consulenten En -Kantoren",
    "sg:phone":"+31 342 473 444",
    "sg:postcode":"3781 GA",
    "sg:province":"Gelderland",
    "wof:name":"Schuiteman",
    "wof:placetype":"venue"
},
  "geometry": {"coordinates":[5.606639,52.189289],"type":"Point"}
}