{
  "type": "Feature",
  "properties": {
    "addr:full":"Regentessestr 1 Zoetermeer Zuid-Holland 2713 EM",
    "addr:housenumber":"1",
    "addr:postcode":"2713 em",
    "addr:street":"Regentessestr",
    "iso:country":"NL",
    "sg:address":"Regentessestr 1",
    "sg:city":"Zoetermeer",
    "sg:orig_category":"Loodgieters",
    "sg:phone":"+31 79 316 6774",
    "sg:postcode":"2713 EM",
    "sg:province":"Zuid-Holland",
    "sg:website":"http://www.riodak.nl",
    "wof:name":"Riodak",
    "wof:placetype":"venue"
},
  "geometry": {"coordinates":[4.482955,52.052174],"type":"Point"}
}