{
  "type": "Feature",
  "properties": {
    "addr:full":"Lissenveld 17 Raamsdonksveer Noord-Brabant 4941 VK",
    "addr:housenumber":"17",
    "addr:postcode":"4941 vk",
    "addr:street":"Lissenveld",
    "iso:country":"NL",
    "sg:address":"Lissenveld 17",
    "sg:city":"Raamsdonksveer",
    "sg:orig_category":"Elektronica - Ontwikkeling En Groothandel",
    "sg:phone":"+31 162 521 677",
    "sg:postcode":"4941 VK",
    "sg:province":"Noord-Brabant",
    "wof:name":"W & S Benelux Bv",
    "wof:placetype":"venue"
},
  "geometry": {"coordinates":[4.885305,51.708305],"type":"Point"}
}