{
  "type": "Feature",
  "properties": {
    "iso:country":"NL",
    "sg:address":"Wilgenlaan 8",
    "sg:city":"Oudorp Nh",
    "sg:orig_category":"Hypotheken And Hypotheekbanken",
    "sg:phone":"+31 72 512 1554",
    "sg:postcode":"1829 EC",
    "sg:province":"Noord-Holland",
    "wof:name":"Makelaardij Zelsmann",
    "wof:placetype":"venue"
},
  "geometry": {"coordinates":[4.777971,52.634678],"type":"Point"}
}