{
  "type": "Feature",
  "properties": {
    "addr:full":"Frans Strouxstraat 40 Stramproy BE.05 6039 GK",
    "addr:housenumber":"40;be.05",
    "addr:postcode":"6039 gk",
    "addr:street":"Frans Strouxstraat",
    "iso:country":"NL",
    "sg:address":"Frans Strouxstraat 40",
    "sg:city":"Stramproy",
    "sg:orig_category":"Visspeciaalzaken",
    "sg:phone":"+31 495 562 060",
    "sg:postcode":"6039 GK",
    "sg:province":"BE.05",
    "wof:name":"Vishandel Steijvers M.E.J. Steijvers",
    "wof:placetype":"venue"
},
  "geometry": {"coordinates":[5.724959,51.185516],"type":"Point"}
}