{
  "type": "Feature",
  "properties": {
    "addr:full":"Kedoestr 102 Rotterdam Zuid-Holland 3029 CK",
    "addr:housenumber":"102",
    "addr:postcode":"3029 ck",
    "iso:country":"NL",
    "sg:address":"Kedoestr 102",
    "sg:city":"Rotterdam",
    "sg:orig_category":"Scholen Voor Basisonderwijs",
    "sg:phone":"+31 10 478 0808",
    "sg:postcode":"3029 CK",
    "sg:province":"Zuid-Holland",
    "sg:website":"http://www.obsdeboog.nl",
    "wof:name":"Boog Openbare Basisschool, De",
    "wof:placetype":"venue"
},
  "geometry": {"coordinates":[4.441423,51.903873],"type":"Point"}
}