{
  "type": "Feature",
  "properties": {
    "addr:full":"Gerhard Nijlandstraat 1A Daarlerveen Overijssel 7687 AR",
    "addr:housenumber":"1a",
    "addr:postcode":"7687",
    "addr:street":"Gerhard Nijlandstraat",
    "iso:country":"NL",
    "sg:address":"Gerhard Nijlandstraat 1A",
    "sg:city":"Daarlerveen",
    "sg:orig_category":"Bibliotheken And Openbare Archieven",
    "sg:phone":"+31 546 646 086",
    "sg:postcode":"7687 AR",
    "sg:province":"Overijssel",
    "wof:name":"Openbare Bibliotheek",
    "wof:placetype":"venue"
},
  "geometry": {"coordinates":[-92.131348,34.751888],"type":"Point"}
}