{
  "type": "Feature",
  "properties": {
    "addr:full":"Hoogstr 361A Eindhoven Noord-Brabant 5654 NC",
    "addr:housenumber":"361a",
    "addr:postcode":"5654 nc",
    "iso:country":"NL",
    "sg:address":"Hoogstr 361A",
    "sg:city":"Eindhoven",
    "sg:orig_category":"Cafetaria'S",
    "sg:phone":"+31 40 255 0066",
    "sg:postcode":"5654 NC",
    "sg:province":"Noord-Brabant",
    "wof:name":"Conny",
    "wof:placetype":"venue"
},
  "geometry": {"coordinates":[5.45901,51.420891],"type":"Point"}
}