{
  "type": "Feature",
  "properties": {
    "addr:full":"Dykgraafpln 409 Amsterdam Noord-Holland 1069 EV",
    "addr:housenumber":"409",
    "iso:country":"NL",
    "sg:address":"Dykgraafpln 409",
    "sg:city":"Amsterdam",
    "sg:orig_category":"Bloemen En Planten",
    "sg:phone":"+31 20 610 5129",
    "sg:postcode":"1069 EV",
    "sg:province":"Noord-Holland",
    "wof:name":"Purmerplantenhal",
    "wof:placetype":"venue"
},
  "geometry": {"coordinates":[4.785318,52.355782],"type":"Point"}
}