{
  "type": "Feature",
  "properties": {
    "iso:country":"NL",
    "sg:address":"Zomerdykhof 9",
    "sg:city":"Delft",
    "sg:orig_category":"Belastingconsulenten/ Belastingadviseurs",
    "sg:phone":"+31 15 256 1834",
    "sg:postcode":"2625 LD",
    "sg:province":"Zuid-Holland",
    "wof:name":"Hoogstraaten, J A",
    "wof:placetype":"venue"
},
  "geometry": {"coordinates":[4.340644,51.98682],"type":"Point"}
}