{
  "type": "Feature",
  "properties": {
    "addr:full":"Coornhertstraat 88 Vlaardingen Zuid-Holland 3132 GK",
    "addr:housenumber":"88",
    "addr:postcode":"3132 gk",
    "addr:street":"Coornhertstraat",
    "iso:country":"NL",
    "sg:address":"Coornhertstraat 88",
    "sg:city":"Vlaardingen",
    "sg:orig_category":"Boekhouders",
    "sg:phone":"+31 10 435 8300",
    "sg:postcode":"3132 GK",
    "sg:province":"Zuid-Holland",
    "wof:name":"Administratiekantoor H.J. Van De Heuvel",
    "wof:placetype":"venue"
},
  "geometry": {"coordinates":[4.311226,51.90601],"type":"Point"}
}