{
  "type": "Feature",
  "properties": {
    "iso:country":"NL",
    "sg:address":"Reinkenstraat 48",
    "sg:city":"'S Gravenhage",
    "sg:orig_category":"Kappers",
    "sg:phone":"+31 70 345 8632",
    "sg:postcode":"2517 CW",
    "sg:province":"Zuid-Holland",
    "wof:name":"John Van Bodegom",
    "wof:placetype":"venue"
},
  "geometry": {"coordinates":[4.2828040123,52.0819969177],"type":"Point"}
}