{
  "type": "Feature",
  "properties": {
    "addr:full":"Kerkstraat 1 Giessen North Brabant 4283 GA",
    "addr:housenumber":"1",
    "addr:postcode":"4283 ga",
    "addr:street":"Kerkstraat",
    "iso:country":"NL",
    "sg:address":"Kerkstraat 1",
    "sg:city":"Giessen",
    "sg:orig_category":"Personenvervoer Zonder Dienstregeling",
    "sg:phone":"+31 183 441 369",
    "sg:postcode":"4283 GA",
    "sg:province":"North Brabant",
    "wof:name":"Touringcarbedrijf Zwaluw Reizen Bv",
    "wof:placetype":"venue"
},
  "geometry": {"coordinates":[5.036144,51.792763],"type":"Point"}
}