{
  "type": "Feature",
  "properties": {
    "addr:full":"Grotestraat 51 Diepenheim Overijssel 7478 AB",
    "addr:housenumber":"51",
    "addr:postcode":"7478 ab",
    "addr:street":"Grotestraat",
    "iso:country":"NL",
    "sg:address":"Grotestraat 51",
    "sg:city":"Diepenheim",
    "sg:orig_category":"Kappers",
    "sg:phone":"+31 547 352 172",
    "sg:postcode":"7478 AB",
    "sg:province":"Overijssel",
    "wof:name":"Salon Marisch",
    "wof:placetype":"venue"
},
  "geometry": {"coordinates":[6.553704,52.199722],"type":"Point"}
}