{
  "type": "Feature",
  "properties": {
    "addr:full":"Dorpstr 40 Babberich Gelderland 6909 AL",
    "addr:housenumber":"40",
    "addr:postcode":"6909",
    "addr:street":"Dorpstr;Gelderland",
    "iso:country":"NL",
    "sg:address":"Dorpstr 40",
    "sg:city":"Babberich",
    "sg:orig_category":"Kappers",
    "sg:phone":"+31 316 247 121",
    "sg:postcode":"6909 AL",
    "sg:province":"Gelderland",
    "wof:name":"Capelli",
    "wof:placetype":"venue"
},
  "geometry": {"coordinates":[6.1116452217,51.9070091248],"type":"Point"}
}