{
  "type": "Feature",
  "properties": {
    "addr:full":"Valkenbergstraat 23 Veghel North Brabant 5466 RS",
    "addr:housenumber":"23",
    "addr:postcode":"5466 rs",
    "addr:street":"Valkenbergstraat",
    "iso:country":"NL",
    "sg:address":"Valkenbergstraat 23",
    "sg:city":"Veghel",
    "sg:classifiers":[
        {
            "category":"Education",
            "subcategory":"Preschool",
            "type":"Public Place"
        }
    ],
    "sg:phone":"+31 413 364 674",
    "sg:postcode":"5466 RS",
    "sg:province":"North Brabant",
    "sg:tags":[
        "kleuteronderwijs",
        "basis-"
    ],
    "wof:name":"Basisschool Petrus En Paulus",
    "wof:placetype":"venue"
},
  "geometry": {"coordinates":[5.498686,51.605206],"type":"Point"}
}