{
  "type": "Feature",
  "properties": {
    "iso:country":"NL",
    "sg:address":"Nieuwpoortkade 2A",
    "sg:city":"Amsterdam",
    "sg:orig_category":"Meubelreparatie And -Restauratie",
    "sg:phone":"+31 20 606 0919",
    "sg:postcode":"1055 RX",
    "sg:province":"Noord-Holland",
    "wof:name":"De Hete Naald Meubelstoffeerderij",
    "wof:placetype":"venue"
},
  "geometry": {"coordinates":[4.859365,52.384743],"type":"Point"}
}