{
  "type": "Feature",
  "properties": {
    "addr:full":"Maatmanwg 27 Enschede Overijssel 7522 AN",
    "addr:housenumber":"27",
    "addr:postcode":"7522 an",
    "addr:street":"Maatmanwg",
    "iso:country":"NL",
    "sg:address":"Maatmanwg 27",
    "sg:city":"Enschede",
    "sg:orig_category":"Golfbanen",
    "sg:phone":"+31 53 433 7992",
    "sg:postcode":"7522 AN",
    "sg:province":"Overijssel",
    "wof:name":"Golf Club Prinses Wilhelmina",
    "wof:placetype":"venue"
},
  "geometry": {"coordinates":[6.877396,52.233582],"type":"Point"}
}