{
  "type": "Feature",
  "properties": {
    "addr:full":"De Meent 24 Odyk Utrecht 3984 JJ",
    "addr:housenumber":"24",
    "addr:postcode":"3984 jj",
    "addr:street":"De Meent",
    "iso:country":"NL",
    "sg:address":"De Meent 24",
    "sg:city":"Odyk",
    "sg:orig_category":"Postkantoren",
    "sg:phone":"+31 30 656 1291",
    "sg:postcode":"3984 JJ",
    "sg:province":"Utrecht",
    "sg:website":"http://www.postkantoor.nl",
    "wof:name":"Postkantoor",
    "wof:placetype":"venue"
},
  "geometry": {"coordinates":[5.232595,52.05056],"type":"Point"}
}