{
  "type": "Feature",
  "properties": {
    "addr:full":"Kanaalstraat 19 Son Noord-Brabant 5691 NA",
    "addr:housenumber":"19",
    "addr:postcode":"5691 na",
    "addr:street":"Kanaalstraat",
    "iso:country":"NL",
    "sg:address":"Kanaalstraat 19",
    "sg:city":"Son",
    "sg:orig_category":"Architecten",
    "sg:phone":"+31 499 471 192",
    "sg:postcode":"5691 NA",
    "sg:province":"Noord-Brabant",
    "wof:name":"Bureau Voor Architectuur W A J Lavrijsse",
    "wof:placetype":"venue"
},
  "geometry": {"coordinates":[-101.937622,35.189621],"type":"Point"}
}