{
  "type": "Feature",
  "properties": {
    "iso:country":"NL",
    "sg:address":"Henri Wijnmalenweg 14",
    "sg:city":"Eindhoven",
    "sg:orig_category":"Kantoorartikelen",
    "sg:phone":"+31 40 235 0747",
    "sg:postcode":"5657 EP",
    "sg:province":"Noord-Brabant",
    "wof:name":"Hpi Group",
    "wof:placetype":"venue"
},
  "geometry": {"coordinates":[5.3941168785,51.4550895691],"type":"Point"}
}