{
  "type": "Feature",
  "properties": {
    "iso:country":"NL",
    "sg:address":"Hessepas 10",
    "sg:city":"Westervoort",
    "sg:orig_category":"Projectontwikkeling",
    "sg:phone":"+31 6 22200787",
    "sg:postcode":"6931 HJ",
    "sg:province":"Gelderland",
    "wof:name":"Haveteco",
    "wof:placetype":"venue"
},
  "geometry": {"coordinates":[5.967915,51.952991],"type":"Point"}
}