{
  "type": "Feature",
  "properties": {
    "addr:full":"Scheepsbouwplein 10 Alblasserdam Zuid-Holland 2953 XM",
    "addr:housenumber":"10",
    "addr:postcode":"2953 xm",
    "addr:street":"Scheepsbouwplein",
    "iso:country":"NL",
    "sg:address":"Scheepsbouwplein 10",
    "sg:city":"Alblasserdam",
    "sg:classifiers":[
        {
            "category":"Education",
            "subcategory":"Preschool",
            "type":"Public Place"
        }
    ],
    "sg:phone":"+31 78 691 2669",
    "sg:postcode":"2953 XM",
    "sg:province":"Zuid-Holland",
    "sg:tags":[
        "kleuteronderwijs",
        "basis-"
    ],
    "wof:name":"Christelijke Basisschool Het Kompas",
    "wof:placetype":"venue"
},
  "geometry": {"coordinates":[4.638707,51.872227],"type":"Point"}
}