{
  "type": "Feature",
  "properties": {
    "addr:full":"Sint Agnietenstraat 5 Tiel Gelderland 4001 NB",
    "addr:housenumber":"5",
    "addr:postcode":"4001 nb",
    "addr:street":"Sint Agnietenstraat;Gelderland",
    "iso:country":"NL",
    "sg:address":"Sint Agnietenstraat 5",
    "sg:city":"Tiel",
    "sg:orig_category":"Boekhouders",
    "sg:phone":"+31 344 626 028",
    "sg:postcode":"4001 NB",
    "sg:province":"Gelderland",
    "wof:name":"G.C.D. Blume",
    "wof:placetype":"venue"
},
  "geometry": {"coordinates":[5.435551,51.88612],"type":"Point"}
}