{
  "type": "Feature",
  "properties": {
    "addr:full":"Gotenburgwg 5 Groningen Groningen 9723 TK",
    "addr:housenumber":"5",
    "addr:postcode":"9723 tk",
    "addr:street":"Gotenburgwg",
    "iso:country":"NL",
    "sg:address":"Gotenburgwg 5",
    "sg:city":"Groningen",
    "sg:orig_category":"Lasapparaten En Benodigdheden",
    "sg:phone":"+31 50 542 4030",
    "sg:postcode":"9723 TK",
    "sg:province":"Groningen",
    "sg:website":"http://www.reonlas.nl",
    "wof:name":"Re-On",
    "wof:placetype":"venue"
},
  "geometry": {"coordinates":[6.604795,53.211205],"type":"Point"}
}