{
  "type": "Feature",
  "properties": {
    "addr:full":"Westerblokker 129 Blokker Noord-Holland 1695 AD",
    "addr:housenumber":"129",
    "addr:postcode":"1695 ad",
    "addr:street":"Westerblokker",
    "iso:country":"NL",
    "sg:address":"Westerblokker 129",
    "sg:city":"Blokker",
    "sg:orig_category":"Juweliers",
    "sg:phone":"+31 229 232 846",
    "sg:postcode":"1695 AD",
    "sg:province":"Noord-Holland",
    "wof:name":"Ben De Haan Juwelier",
    "wof:placetype":"venue"
},
  "geometry": {"coordinates":[5.08565,52.660149],"type":"Point"}
}