{
  "type": "Feature",
  "properties": {
    "iso:country":"NL",
    "sg:address":"J V Geelstr 62B",
    "sg:city":"Rotterdam",
    "sg:classifiers":[
        {
            "category":"Retail",
            "subcategory":"Auto Repair",
            "type":"Services"
        }
    ],
    "sg:phone":"+31 10 478 1902",
    "sg:postcode":"3021 VP",
    "sg:province":"Zuid-Holland",
    "sg:tags":[
        "garage"
    ],
    "wof:name":"Altay, A",
    "wof:placetype":"venue"
},
  "geometry": {"coordinates":[4.45925,51.916531],"type":"Point"}
}