{
  "type": "Feature",
  "properties": {
    "addr:full":"De Dyk 6 Gastel Noord-Brabant 6028 RJ",
    "addr:housenumber":"6",
    "addr:postcode":"6028 rj",
    "addr:street":"De Dyk",
    "iso:country":"NL",
    "sg:address":"De Dyk 6",
    "sg:city":"Gastel",
    "sg:orig_category":"Keukens",
    "sg:phone":"+31 495 493 350",
    "sg:postcode":"6028 RJ",
    "sg:province":"Noord-Brabant",
    "wof:name":"Mardy",
    "wof:placetype":"venue"
},
  "geometry": {"coordinates":[5.554681,51.284348],"type":"Point"}
}