{
  "type": "Feature",
  "properties": {
    "addr:full":"Delflandplein 8 Amsterdam Noord-Holland 1062 HR",
    "addr:housenumber":"8",
    "addr:postcode":"1062 hr",
    "addr:street":"Delflandplein",
    "iso:country":"NL",
    "sg:address":"Delflandplein 8",
    "sg:city":"Amsterdam",
    "sg:orig_category":"Werving And Selectie Van Tijdelijk Personeel And Uitzendkantoren",
    "sg:phone":"+31 20 346 3100",
    "sg:postcode":"1062 HR",
    "sg:province":"Noord-Holland",
    "wof:name":"Ats Bv",
    "wof:placetype":"venue"
},
  "geometry": {"coordinates":[4.841176033,52.3497962952],"type":"Point"}
}