{
  "type": "Feature",
  "properties": {
    "addr:full":"Maaskade 105 Rotterdam Zuid-Holland 3071 NH",
    "addr:housenumber":"105",
    "addr:postcode":"3071 nh",
    "addr:street":"Maaskade",
    "iso:country":"NL",
    "sg:address":"Maaskade 105",
    "sg:city":"Rotterdam",
    "sg:orig_category":"Bouwmaterialen Gh",
    "sg:phone":"+31 10 413 8013",
    "sg:postcode":"3071 NH",
    "sg:province":"Zuid-Holland",
    "wof:name":"Cooperatieve Zandschippersbond Ua",
    "wof:placetype":"venue"
},
  "geometry": {"coordinates":[4.493147,51.913239],"type":"Point"}
}