{
  "type": "Feature",
  "properties": {
    "addr:full":"Marktstraat 34 Ravenstein North Brabant 5371 AD",
    "addr:housenumber":"34",
    "addr:postcode":"5371 ad",
    "addr:street":"Marktstraat",
    "iso:country":"NL",
    "sg:address":"Marktstraat 34",
    "sg:city":"Ravenstein",
    "sg:orig_category":"Fotostudio'S And Fotografen",
    "sg:phone":"+31 486 416 641",
    "sg:postcode":"5371 AD",
    "sg:province":"North Brabant",
    "wof:name":"Fotografie Maaspoort",
    "wof:placetype":"venue"
},
  "geometry": {"coordinates":[5.652581,51.797291],"type":"Point"}
}