{
  "type": "Feature",
  "properties": {
    "addr:full":"Utrechtsewg 160 Amersfoort Utrecht 3818 ES",
    "addr:housenumber":"160",
    "addr:postcode":"3818 es",
    "iso:country":"NL",
    "sg:address":"Utrechtsewg 160",
    "sg:city":"Amersfoort",
    "sg:orig_category":"Apotheken",
    "sg:phone":"+31 33 432 8500",
    "sg:postcode":"3818 ES",
    "sg:province":"Utrecht",
    "wof:name":"Dienstapotheek Eemland",
    "wof:placetype":"venue"
},
  "geometry": {"coordinates":[5.369148,52.144279],"type":"Point"}
}