{
  "type": "Feature",
  "properties": {
    "addr:full":"Molenstr 24 Soest Utrecht 3764 TG",
    "addr:housenumber":"24",
    "addr:postcode":"3764 tg",
    "addr:street":"Molenstr",
    "iso:country":"NL",
    "sg:address":"Molenstr 24",
    "sg:city":"Soest",
    "sg:orig_category":"Adviesbureaus",
    "sg:phone":"+31 35 609 0660",
    "sg:postcode":"3764 TG",
    "sg:province":"Utrecht",
    "wof:name":"Draisma & Maille Bv",
    "wof:placetype":"venue"
},
  "geometry": {"coordinates":[5.300385,52.184044],"type":"Point"}
}