{
  "type": "Feature",
  "properties": {
    "iso:country":"NL",
    "sg:address":"Waterrad 72",
    "sg:city":"Grootebroek",
    "sg:orig_category":"Loodgieterswerk, Verwarming And Sanitaire Installaties",
    "sg:phone":"+31 228 513 100",
    "sg:postcode":"1613 CP",
    "sg:province":"Noord-Holland",
    "wof:name":"R De Graaf Montagebedrijf",
    "wof:placetype":"venue"
},
  "geometry": {"coordinates":[5.231243,52.688381],"type":"Point"}
}