{
  "type": "Feature",
  "properties": {
    "addr:full":"Noorderstraat 64 Amsterdam Noord-Holland 1017 TV",
    "addr:housenumber":"64",
    "addr:postcode":"1017 tv",
    "addr:street":"Noorderstraat",
    "iso:country":"NL",
    "sg:address":"Noorderstraat 64",
    "sg:city":"Amsterdam",
    "sg:orig_category":"Diverse Grafische Activiteiten",
    "sg:phone":"+31 20 623 6485",
    "sg:postcode":"1017 TV",
    "sg:province":"Noord-Holland",
    "wof:name":"K. Van Rossum",
    "wof:placetype":"venue"
},
  "geometry": {"coordinates":[4.894458,52.361],"type":"Point"}
}