{
  "type": "Feature",
  "properties": {
    "addr:full":"Sun Pln 24 Landgraaf Limburg 6373 LH",
    "addr:housenumber":"24",
    "addr:postcode":"6373 lh",
    "addr:street":"Pln",
    "iso:country":"NL",
    "sg:address":"Sun Pln 24",
    "sg:city":"Landgraaf",
    "sg:orig_category":"Fietsen En Bromfietsen",
    "sg:phone":"+31 45 533 1931",
    "sg:postcode":"6373 LH",
    "sg:province":"Limburg",
    "wof:name":"Daytona Shop",
    "wof:placetype":"venue"
},
  "geometry": {"coordinates":[6.036256,50.907753],"type":"Point"}
}