{
  "type": "Feature",
  "properties": {
    "addr:full":"Dominee T O Hylkemaweg 43 Giethoorn Overijssel 8355 CE",
    "addr:housenumber":"43",
    "addr:postcode":"8355 ce",
    "addr:street":"Dominee T O Hylkemaweg",
    "iso:country":"NL",
    "sg:address":"Dominee T O Hylkemaweg 43",
    "sg:city":"Giethoorn",
    "sg:orig_category":"Kampeerterreinen",
    "sg:phone":"+31 521 361 674",
    "sg:postcode":"8355 CE",
    "sg:province":"Overijssel",
    "wof:name":"Restaurant 'T Achterhuus",
    "wof:placetype":"venue"
},
  "geometry": {"coordinates":[6.0884418488,52.722530365],"type":"Point"}
}