{
  "type": "Feature",
  "properties": {
    "addr:full":"Overgoo 11 Leidschendam South Holland 2266 JZ",
    "addr:housenumber":"11",
    "addr:postcode":"2266 jz",
    "addr:street":"Overgoo",
    "iso:country":"NL",
    "sg:address":"Overgoo 11",
    "sg:city":"Leidschendam",
    "sg:orig_category":"Kantoor- En Secretariaatsservice",
    "sg:phone":"+31 70 337 6200",
    "sg:postcode":"2266 JZ",
    "sg:province":"South Holland",
    "wof:name":"Pro-Sec Leidschendam Bv",
    "wof:placetype":"venue"
},
  "geometry": {"coordinates":[4.394338131,52.0764160156],"type":"Point"}
}