{
  "type": "Feature",
  "properties": {
    "addr:full":"Spitsbrug 14 Afferden Lb Missouri 5851 AC",
    "addr:housenumber":"14",
    "addr:postcode":"5851 ac",
    "addr:street":"Spitsbrug",
    "iso:country":"NL",
    "sg:address":"Spitsbrug 14",
    "sg:city":"Afferden Lb",
    "sg:orig_category":"Pluimveehouderijen",
    "sg:phone":"+31 485 531 922",
    "sg:postcode":"5851 AC",
    "sg:province":"Missouri",
    "wof:name":"J. Van Berloo",
    "wof:placetype":"venue"
},
  "geometry": {"coordinates":[-93.129936,36.705662],"type":"Point"}
}