{
  "type": "Feature",
  "properties": {
    "addr:full":"Weteringplein 12 Zeewolde NL. 3892 AM",
    "addr:housenumber":"12",
    "addr:postcode":"3892",
    "addr:street":"Weteringplein;Nl.",
    "iso:country":"NL",
    "sg:address":"Weteringplein 12",
    "sg:city":"Zeewolde",
    "sg:orig_category":"Verhuur Audiovisuele Apparatuur",
    "sg:phone":"+31 6 51519093",
    "sg:postcode":"3892 AM",
    "sg:province":"NL.",
    "wof:name":"Peter Buis Audio & Video",
    "wof:placetype":"venue"
},
  "geometry": {"coordinates":[5.542684,52.327328],"type":"Point"}
}