{
  "type": "Feature",
  "properties": {
    "iso:country":"NL",
    "sg:address":"Reinkenstr 85-91",
    "sg:city":"S Gravenhage",
    "sg:orig_category":"Bloemen En Planten",
    "sg:phone":"+31 70 364 6170",
    "sg:postcode":"2517 CS",
    "sg:province":"South Holland",
    "wof:name":"Lofica Bv",
    "wof:placetype":"venue"
},
  "geometry": {"coordinates":[4.28708,52.08667],"type":"Point"}
}