{
  "type": "Feature",
  "properties": {
    "addr:full":"Kalsdonksestr 134/A Roosendaal Noord-Brabant 4702 ZJ",
    "addr:housenumber":"134 / a",
    "addr:postcode":"4702 zj",
    "iso:country":"NL",
    "sg:address":"Kalsdonksestr 134/A",
    "sg:city":"Roosendaal",
    "sg:orig_category":"Bloemen En Planten",
    "sg:phone":"+31 165 535 130",
    "sg:postcode":"4702 ZJ",
    "sg:province":"Noord-Brabant",
    "wof:name":"Overveld, Van",
    "wof:placetype":"venue"
},
  "geometry": {"coordinates":[4.471039,51.540668],"type":"Point"}
}