{
  "type": "Feature",
  "properties": {
    "addr:full":"Morswg 55D Leiden Zuid-Holland 2312 AB",
    "addr:housenumber":"55d",
    "addr:postcode":"2312 ab",
    "addr:street":"Morswg",
    "iso:country":"NL",
    "sg:address":"Morswg 55D",
    "sg:city":"Leiden",
    "sg:classifiers":[
        {
            "category":"Retail",
            "subcategory":"Auto Repair",
            "type":"Services"
        }
    ],
    "sg:phone":"+31 6 21222688",
    "sg:postcode":"2312 AB",
    "sg:province":"Zuid-Holland",
    "sg:tags":[
        "garage"
    ],
    "wof:name":"Danny",
    "wof:placetype":"venue"
},
  "geometry": {"coordinates":[4.477356,52.160851],"type":"Point"}
}