{
  "type": "Feature",
  "properties": {
    "addr:full":"Tunnelweg 109 Wijchen Gelderland 6601 CT",
    "addr:housenumber":"109",
    "addr:postcode":"6601 ct",
    "addr:street":"Tunnelweg;Gelderland",
    "iso:country":"NL",
    "sg:address":"Tunnelweg 109",
    "sg:city":"Wijchen",
    "sg:orig_category":"Bedrijfs- And Managementsconsultants",
    "sg:phone":"+31 24 641 4078",
    "sg:postcode":"6601 CT",
    "sg:province":"Gelderland",
    "wof:name":"Van Teeffelen Training & Advies",
    "wof:placetype":"venue"
},
  "geometry": {"coordinates":[5.726605,51.815334],"type":"Point"}
}