{
  "type": "Feature",
  "properties": {
    "addr:full":"Ruys De Beerenbrouckstr 138 Amsterdam North Holland 1067 BZ",
    "addr:housenumber":"138",
    "addr:postcode":"1067 bz",
    "addr:street":"Ruys De Beerenbrouckstr",
    "iso:country":"NL",
    "sg:address":"Ruys De Beerenbrouckstr 138",
    "sg:city":"Amsterdam",
    "sg:orig_category":"Kleding And Schoenen Gh",
    "sg:phone":"+31 20 611 0010",
    "sg:postcode":"1067 BZ",
    "sg:province":"North Holland",
    "wof:name":"Haga Sportboetiek",
    "wof:placetype":"venue"
},
  "geometry": {"coordinates":[4.800658,52.382439],"type":"Point"}
}