{
  "type": "Feature",
  "properties": {
    "iso:country":"NL",
    "sg:address":"Schubertln 17",
    "sg:city":"Arnhem",
    "sg:orig_category":"Voetbalverenigingen",
    "sg:phone":"+31 26 443 4272",
    "sg:postcode":"6815 HH",
    "sg:province":"Gelderland",
    "wof:name":"Cranevelt",
    "wof:placetype":"venue"
},
  "geometry": {"coordinates":[5.898992,52.005157],"type":"Point"}
}