{
  "type": "Feature",
  "properties": {
    "addr:full":"Sperwerhorst 16 Honselersdijk Zuid-Holland 2675 WT",
    "addr:housenumber":"16",
    "addr:postcode":"2675 wt",
    "addr:street":"Sperwerhorst",
    "iso:country":"NL",
    "sg:address":"Sperwerhorst 16",
    "sg:city":"Honselersdijk",
    "sg:orig_category":"Metaalwerken",
    "sg:phone":"+31 174 622 429",
    "sg:postcode":"2675 WT",
    "sg:province":"Zuid-Holland",
    "wof:name":"R.A.B. Middendorp Montage",
    "wof:placetype":"venue"
},
  "geometry": {"coordinates":[4.230916,52.004131],"type":"Point"}
}