{
  "type": "Feature",
  "properties": {
    "addr:full":"Oude Leedewg 55 Pynacker Zuid-Holland 2641 NM",
    "addr:housenumber":"55",
    "addr:postcode":"2641",
    "addr:street":"Oude Leedewg",
    "iso:country":"NL",
    "sg:address":"Oude Leedewg 55",
    "sg:city":"Pynacker",
    "sg:orig_category":"Loonbedrijven",
    "sg:phone":"+31 6 55332787",
    "sg:postcode":"2641 NM",
    "sg:province":"Zuid-Holland",
    "wof:name":"Dijk, Robert Van",
    "wof:placetype":"venue"
},
  "geometry": {"coordinates":[4.432019,51.990437],"type":"Point"}
}