{
  "type": "Feature",
  "properties": {
    "addr:full":"Anjerstr 42 Steenbergen Nb Noord-Brabant 4651 MJ",
    "addr:housenumber":"42",
    "addr:postcode":"4651 mj",
    "addr:street":"Anjerstr",
    "iso:country":"NL",
    "sg:address":"Anjerstr 42",
    "sg:city":"Steenbergen Nb",
    "sg:orig_category":"Administratie- En Boekhoudkantoren",
    "sg:phone":"+31 167 565 600",
    "sg:postcode":"4651 MJ",
    "sg:province":"Noord-Brabant",
    "wof:name":"Bos",
    "wof:placetype":"venue"
},
  "geometry": {"coordinates":[4.317274,51.578732],"type":"Point"}
}