{
  "type": "Feature",
  "properties": {
    "addr:full":"Lekdk O 5 Lopik Utrecht 3411 MN",
    "addr:housenumber":"5",
    "addr:postcode":"3411 mn",
    "iso:country":"NL",
    "sg:address":"Lekdk O 5",
    "sg:city":"Lopik",
    "sg:orig_category":"Sportverenigingen En Ontspannings- Verenigingen",
    "sg:phone":"+31 348 552 949",
    "sg:postcode":"3411 MN",
    "sg:province":"Utrecht",
    "sg:website":"http://www.desnip.demon.nl/index-nl.html",
    "wof:name":"Snip Schietver, De",
    "wof:placetype":"venue"
},
  "geometry": {"coordinates":[4.944414,51.967083],"type":"Point"}
}