{
  "type": "Feature",
  "properties": {
    "addr:full":"Syltpier 19 Zaandam Noord-Holland 1506 BX",
    "addr:housenumber":"19",
    "addr:postcode":"1506 bx",
    "addr:street":"Syltpier",
    "iso:country":"NL",
    "sg:address":"Syltpier 19",
    "sg:city":"Zaandam",
    "sg:orig_category":"Film-, Tv- And Videoproductie",
    "sg:phone":"+31 75 631 5532",
    "sg:postcode":"1506 BX",
    "sg:province":"Noord-Holland",
    "wof:name":"Mark Bakker",
    "wof:placetype":"venue"
},
  "geometry": {"coordinates":[4.824696,52.433311],"type":"Point"}
}