{
  "type": "Feature",
  "properties": {
    "iso:country":"NL",
    "sg:address":"T Erf 12",
    "sg:city":"Leusden",
    "sg:classifiers":[
        {
            "category":"Fast Food",
            "type":"Food & Drink"
        }
    ],
    "sg:phone":"+31 33 494 7059",
    "sg:postcode":"3831 NB",
    "sg:province":"Utrecht",
    "sg:tags":[
        "afhaal",
        "restaurant"
    ],
    "wof:name":"Pizzeria Ristorante Bella Venezia 2",
    "wof:placetype":"venue"
},
  "geometry": {"coordinates":[5.428602,52.130215],"type":"Point"}
}