{
  "type": "Feature",
  "properties": {
    "addr:full":"Kerkweg 21 Ede Gld Gelderland 6717 EX",
    "addr:housenumber":"21",
    "addr:postcode":"6717 ex",
    "addr:street":"Kerkweg;Gld Gelderland",
    "iso:country":"NL",
    "sg:address":"Kerkweg 21",
    "sg:city":"Ede Gld",
    "sg:orig_category":"Bloemen And Planten",
    "sg:phone":"+31 318 631 779",
    "sg:postcode":"6717 EX",
    "sg:province":"Gelderland",
    "wof:name":"Bloemenhal Gerrit Van Den Born",
    "wof:placetype":"venue"
},
  "geometry": {"coordinates":[5.658758,52.028919],"type":"Point"}
}