{
  "type": "Feature",
  "properties": {
    "addr:full":"C Huygensstr 1A Voorschoten Zuid-Holland 2251 CH",
    "addr:housenumber":"1a",
    "addr:postcode":"2251",
    "iso:country":"NL",
    "sg:address":"C Huygensstr 1A",
    "sg:city":"Voorschoten",
    "sg:orig_category":"Autorijscholen",
    "sg:phone":"+31 71 561 9507",
    "sg:postcode":"2251 CH",
    "sg:province":"Zuid-Holland",
    "wof:name":"Richard",
    "wof:placetype":"venue"
},
  "geometry": {"coordinates":[4.448906,52.124893],"type":"Point"}
}