{
  "type": "Feature",
  "properties": {
    "addr:full":"Zevenkampse Ring 578 Rotterdam South Holland 3068 HG",
    "addr:housenumber":"578",
    "addr:postcode":"3068 hg",
    "addr:street":"Zevenkampse Ring",
    "iso:country":"NL",
    "sg:address":"Zevenkampse Ring 578",
    "sg:city":"Rotterdam",
    "sg:orig_category":"Verlichtingsartikelen - Groothandel",
    "sg:phone":"+31 10 455 3256",
    "sg:postcode":"3068 HG",
    "sg:province":"South Holland",
    "wof:name":"Br",
    "wof:placetype":"venue"
},
  "geometry": {"coordinates":[4.565422,51.961658],"type":"Point"}
}