{
  "type": "Feature",
  "properties": {
    "addr:full":"Raadhuislaan 41 Spijkenisse South Holland 3201 EM",
    "addr:housenumber":"41",
    "addr:postcode":"3201 em",
    "addr:street":"Raadhuislaan",
    "iso:country":"NL",
    "sg:address":"Raadhuislaan 41",
    "sg:city":"Spijkenisse",
    "sg:orig_category":"Werving And Selectie Van Tijdelijk Personeel And Uitzendkantoren",
    "sg:phone":"+31 181 621 355",
    "sg:postcode":"3201 EM",
    "sg:province":"South Holland",
    "wof:name":"Randstad",
    "wof:placetype":"venue"
},
  "geometry": {"coordinates":[4.3300142288,51.8481025696],"type":"Point"}
}