{
  "type": "Feature",
  "properties": {
    "addr:full":"Dorpsstraat 21 Ilpendam North Holland 1452 PE",
    "addr:housenumber":"21",
    "addr:postcode":"1452 pe",
    "addr:street":"Dorpsstraat",
    "iso:country":"NL",
    "sg:address":"Dorpsstraat 21",
    "sg:city":"Ilpendam",
    "sg:orig_category":"Wasserettes, Stomerijen And Reiniging",
    "sg:phone":"+31 20 436 1835",
    "sg:postcode":"1452 PE",
    "sg:province":"North Holland",
    "wof:name":"Clean-O-Clean",
    "wof:placetype":"venue"
},
  "geometry": {"coordinates":[4.9504351616,52.462890625],"type":"Point"}
}