{
  "type": "Feature",
  "properties": {
    "iso:country":"NL",
    "sg:address":"Postbus 555",
    "sg:city":"Enschede",
    "sg:orig_category":"Verenigingen En Stichtingen",
    "sg:phone":"+31 53 430 5486",
    "sg:postcode":"7500 AN",
    "sg:province":"Overijssel",
    "sg:website":"HTTP://www.twentemarathon.nl",
    "wof:name":"Int Twente Marathon",
    "wof:placetype":"venue"
},
  "geometry": {"coordinates":[6.89112,52.220821],"type":"Point"}
}