{
  "type": "Feature",
  "properties": {
    "addr:full":"Rumpenerstraat 92 Brunssum Limburg 6443 CG",
    "addr:housenumber":"92",
    "addr:postcode":"6443 cg",
    "addr:street":"Rumpenerstraat",
    "iso:country":"NL",
    "sg:address":"Rumpenerstraat 92",
    "sg:city":"Brunssum",
    "sg:orig_category":"Kappers",
    "sg:phone":"+31 45 525 2461",
    "sg:postcode":"6443 CG",
    "sg:province":"Limburg",
    "wof:name":"Dameskapsalon Femina",
    "wof:placetype":"venue"
},
  "geometry": {"coordinates":[5.9698262215,50.9387321472],"type":"Point"}
}