{
  "type": "Feature",
  "properties": {
    "addr:full":"St Maartenstr 49 Losser NL.08 7581 AK",
    "addr:housenumber":"49;nl.08",
    "addr:postcode":"7581 ak",
    "iso:country":"NL",
    "sg:address":"St Maartenstr 49",
    "sg:city":"Losser",
    "sg:orig_category":"Juweliers",
    "sg:phone":"+31 53 538 1675",
    "sg:postcode":"7581 AK",
    "sg:province":"NL.08",
    "wof:name":"Vreriks",
    "wof:placetype":"venue"
},
  "geometry": {"coordinates":[7.005728,52.263584],"type":"Point"}
}