{
  "type": "Feature",
  "properties": {
    "iso:country":"NL",
    "sg:address":"Gangboord 1A",
    "sg:city":"Raamsdonksveer",
    "sg:orig_category":"Kunstgebitten",
    "sg:phone":"+31 162 523 888",
    "sg:postcode":"4941 RE",
    "sg:province":"North Brabant",
    "wof:name":"Gebitsprothese, Praktijk",
    "wof:placetype":"venue"
},
  "geometry": {"coordinates":[4.872125,51.695938],"type":"Point"}
}