{
  "type": "Feature",
  "properties": {
    "addr:full":"Vuistbyl 11 Borger Drenthe 9531 PK",
    "addr:housenumber":"11",
    "addr:postcode":"9531 pk",
    "addr:street":"Vuistbyl",
    "iso:country":"NL",
    "sg:address":"Vuistbyl 11",
    "sg:city":"Borger",
    "sg:orig_category":"Administratie- En Boekhoudkantoren",
    "sg:phone":"+31 599 239 000",
    "sg:postcode":"9531 PK",
    "sg:province":"Drenthe",
    "wof:name":"Kamminga",
    "wof:placetype":"venue"
},
  "geometry": {"coordinates":[6.78528,52.917118],"type":"Point"}
}