{
  "type": "Feature",
  "properties": {
    "addr:full":"Irenestr 79 Landgraaf Limburg 6373 NJ",
    "addr:housenumber":"79",
    "addr:postcode":"6373 nj",
    "addr:street":"Irenestr",
    "iso:country":"NL",
    "sg:address":"Irenestr 79",
    "sg:city":"Landgraaf",
    "sg:orig_category":"Verhuur",
    "sg:phone":"+31 6 53782548",
    "sg:postcode":"6373 NJ",
    "sg:province":"Limburg",
    "wof:name":"Bert Gillissen Kinderplezier",
    "wof:placetype":"venue"
},
  "geometry": {"coordinates":[6.036367,50.904995],"type":"Point"}
}