{
  "type": "Feature",
  "properties": {
    "addr:full":"Laat 214 Alkmaar North Holland 1811 EN",
    "addr:housenumber":"214",
    "addr:postcode":"1811 en",
    "addr:street":"Laat",
    "iso:country":"NL",
    "sg:address":"Laat 214",
    "sg:city":"Alkmaar",
    "sg:orig_category":"Meubelzaken, Woning- And Keukeninrichting",
    "sg:phone":"+31 72 511 2726",
    "sg:postcode":"1811 EN",
    "sg:province":"North Holland",
    "wof:name":"Sidonius Slaapvoorlichter",
    "wof:placetype":"venue"
},
  "geometry": {"coordinates":[4.743917,52.631462],"type":"Point"}
}