{
  "type": "Feature",
  "properties": {
    "addr:full":"Batterystr 10 Maastricht Limburg 6211 SH",
    "addr:housenumber":"10",
    "addr:postcode":"6211 sh",
    "addr:street":"Batterystr",
    "iso:country":"NL",
    "sg:address":"Batterystr 10",
    "sg:city":"Maastricht",
    "sg:orig_category":"Bloemen En Planten - Groothandel",
    "sg:phone":"+31 43 321 2402",
    "sg:postcode":"6211 SH",
    "sg:province":"Limburg",
    "wof:name":"Veja",
    "wof:placetype":"venue"
},
  "geometry": {"coordinates":[5.688693,50.853271],"type":"Point"}
}