{
  "type": "Feature",
  "properties": {
    "addr:full":"Damsterdiep 19-25 Groningen Groningen 9711 SG",
    "addr:housenumber":"19-25",
    "addr:postcode":"9711 sg",
    "addr:street":"Damsterdiep",
    "iso:country":"NL",
    "sg:address":"Damsterdiep 19-25",
    "sg:city":"Groningen",
    "sg:orig_category":"Zonnebanken En Solaria - Fabrieken En Groothandel",
    "sg:phone":"+31 50 314 0204",
    "sg:postcode":"9711 SG",
    "sg:province":"Groningen",
    "wof:name":"Helios Prof",
    "wof:placetype":"venue"
},
  "geometry": {"coordinates":[6.575684,53.217049],"type":"Point"}
}