{
  "type": "Feature",
  "properties": {
    "addr:full":"St Janstr 10 Alphen Nb Noord-Brabant 5131 BS",
    "addr:housenumber":"10",
    "addr:postcode":"5131 bs",
    "iso:country":"NL",
    "sg:address":"St Janstr 10",
    "sg:city":"Alphen Nb",
    "sg:orig_category":"Verenigingen En Stichtingen",
    "sg:phone":"+31 13 508 2447",
    "sg:postcode":"5131 BS",
    "sg:province":"Noord-Brabant",
    "wof:name":"Peuterspeelzaal, Sticht",
    "wof:placetype":"venue"
},
  "geometry": {"coordinates":[4.961791,51.477825],"type":"Point"}
}