{
  "type": "Feature",
  "properties": {
    "addr:full":"Lysterbesln 7 Bennekom Gelderland 6721 CW",
    "addr:housenumber":"7",
    "addr:postcode":"6721 cw",
    "addr:street":"Lysterbesln;Gelderland",
    "iso:country":"NL",
    "sg:address":"Lysterbesln 7",
    "sg:city":"Bennekom",
    "sg:orig_category":"Marketingbureaus",
    "sg:phone":"+31 318 430 899",
    "sg:postcode":"6721 CW",
    "sg:province":"Gelderland",
    "wof:name":"Acharya",
    "wof:placetype":"venue"
},
  "geometry": {"coordinates":[5.683242,52.005829],"type":"Point"}
}