{
  "type": "Feature",
  "properties": {
    "addr:full":"Industriewg 5 Moergestel Noord-Brabant 5066 XJ",
    "addr:housenumber":"5",
    "addr:postcode":"5066 xj",
    "addr:street":"Industriewg",
    "iso:country":"NL",
    "sg:address":"Industriewg 5",
    "sg:city":"Moergestel",
    "sg:classifiers":[
        {
            "category":"Wholesale",
            "subcategory":"Motor Vehicles",
            "type":"Manufacturing & Wholesale Goods"
        }
    ],
    "sg:phone":"+31 13 513 2134",
    "sg:postcode":"5066 XJ",
    "sg:province":"Noord-Brabant",
    "sg:tags":[
        "scooter",
        "en"
    ],
    "wof:name":"Bijvelt Van De Ven",
    "wof:placetype":"venue"
},
  "geometry": {"coordinates":[5.177919,51.548645],"type":"Point"}
}