{
  "type": "Feature",
  "properties": {
    "iso:country":"NL",
    "sg:address":"Duiventoren 76",
    "sg:city":"Oudenbosch",
    "sg:orig_category":"Boekhouders",
    "sg:phone":"+31 165 315 665",
    "sg:postcode":"4731 MX",
    "sg:province":"North Brabant",
    "wof:name":"Akm",
    "wof:placetype":"venue"
},
  "geometry": {"coordinates":[4.519514,51.592129],"type":"Point"}
}