{
  "type": "Feature",
  "properties": {
    "addr:full":"Semmekrotswg 2A Bornerbroek NL.08 7627 RE",
    "addr:housenumber":"2a;nl.08",
    "addr:postcode":"7627",
    "addr:street":"Semmekrotswg",
    "iso:country":"NL",
    "sg:address":"Semmekrotswg 2A",
    "sg:city":"Bornerbroek",
    "sg:orig_category":"Keukens",
    "sg:phone":"+31 74 384 1339",
    "sg:postcode":"7627 RE",
    "sg:province":"NL.08",
    "wof:name":"Oude Meijers",
    "wof:placetype":"venue"
},
  "geometry": {"coordinates":[6.634561,52.300602],"type":"Point"}
}