{
  "type": "Feature",
  "properties": {
    "iso:country":"NL",
    "sg:address":"Raadhuispln 101",
    "sg:city":"Krimpen Ad Yssel",
    "sg:orig_category":"Schoenen",
    "sg:phone":"+31 180 599 793",
    "sg:postcode":"2922 AJ",
    "sg:province":"South Holland",
    "wof:name":"Haren Bv, Van",
    "wof:placetype":"venue"
},
  "geometry": {"coordinates":[4.588142,51.914299],"type":"Point"}
}