{
  "type": "Feature",
  "properties": {
    "addr:full":"Duinoordstraat 59 Haarlem North Holland 2023 WC",
    "addr:housenumber":"59",
    "addr:postcode":"2023 wc",
    "addr:street":"Duinoordstraat",
    "iso:country":"NL",
    "sg:address":"Duinoordstraat 59",
    "sg:city":"Haarlem",
    "sg:orig_category":"Kappers",
    "sg:phone":"+31 23 526 5900",
    "sg:postcode":"2023 WC",
    "sg:province":"North Holland",
    "wof:name":"Jean Pierre Coiffures",
    "wof:placetype":"venue"
},
  "geometry": {"coordinates":[4.633111,52.399197],"type":"Point"}
}