{
  "type": "Feature",
  "properties": {
    "addr:full":"De Kreek 19 Barendrecht Zuid-Holland 2991 EG",
    "addr:housenumber":"19",
    "addr:postcode":"2991 eg",
    "addr:street":"De Kreek",
    "iso:country":"NL",
    "sg:address":"De Kreek 19",
    "sg:city":"Barendrecht",
    "sg:orig_category":"Loodgieterswerk, Verwarming And Sanitaire Installaties",
    "sg:phone":"+31 180 613 978",
    "sg:postcode":"2991 EG",
    "sg:province":"Zuid-Holland",
    "wof:name":"Wensa",
    "wof:placetype":"venue"
},
  "geometry": {"coordinates":[4.545468,51.851826],"type":"Point"}
}