{
  "type": "Feature",
  "properties": {
    "addr:full":"Slotpln 26 Capelle A/D Ijssel Zuid-Holland 2902 HP",
    "addr:housenumber":"26;a / d",
    "addr:postcode":"2902 hp",
    "addr:street":"Slotpln",
    "iso:country":"NL",
    "sg:address":"Slotpln 26",
    "sg:city":"Capelle A/D Ijssel",
    "sg:classifiers":[
        {
            "category":"Food & Beverages",
            "subcategory":"Fruits & Vegetables",
            "type":"Retail Goods"
        }
    ],
    "sg:phone":"+31 10 450 5005",
    "sg:postcode":"2902 HP",
    "sg:province":"Zuid-Holland",
    "sg:tags":[
        "en",
        "groenten"
    ],
    "wof:name":"Capelle'S Fruithuis",
    "wof:placetype":"venue"
},
  "geometry": {"coordinates":[4.580807,51.926193],"type":"Point"}
}