{
  "type": "Feature",
  "properties": {
    "iso:country":"NL",
    "sg:address":"De Meenthe 5",
    "sg:city":"Hattem",
    "sg:orig_category":"Goederenvervoer Over De Weg",
    "sg:phone":"+31 38 444 6952",
    "sg:postcode":"8051 KS",
    "sg:province":"Gelderland",
    "wof:name":"G.R. Koers Transport",
    "wof:placetype":"venue"
},
  "geometry": {"coordinates":[6.053769,52.476963],"type":"Point"}
}