{
  "type": "Feature",
  "properties": {
    "iso:country":"NL",
    "sg:address":"De Helle 34",
    "sg:city":"Delden",
    "sg:orig_category":"Kappers",
    "sg:phone":"+31 74 376 3161",
    "sg:postcode":"7491 KW",
    "sg:province":"Overijssel",
    "wof:name":"Baake, C F M",
    "wof:placetype":"venue"
},
  "geometry": {"coordinates":[6.7195391655,52.2547683716],"type":"Point"}
}