{
  "type": "Feature",
  "properties": {
    "iso:country":"NL",
    "sg:address":"Maastrichterln 108",
    "sg:city":"Vaals",
    "sg:orig_category":"Vertalers",
    "sg:phone":"+31 43 306 5909",
    "sg:postcode":"6291 EV",
    "sg:province":"Limburg",
    "wof:name":"Sirtmac",
    "wof:placetype":"venue"
},
  "geometry": {"coordinates":[6.017422,50.772984],"type":"Point"}
}