{
  "type": "Feature",
  "properties": {
    "addr:full":"Zoetevaart 8 Hulst Zeeland 4561 GR",
    "addr:housenumber":"8",
    "addr:postcode":"4561",
    "addr:street":"Zoetevaart",
    "iso:country":"NL",
    "sg:address":"Zoetevaart 8",
    "sg:city":"Hulst",
    "sg:orig_category":"Bloemen And Planten",
    "sg:phone":"+31 114 321 693",
    "sg:postcode":"4561 GR",
    "sg:province":"Zeeland",
    "wof:name":"Geba",
    "wof:placetype":"venue"
},
  "geometry": {"coordinates":[4.05255,51.275524],"type":"Point"}
}