{
  "type": "Feature",
  "properties": {
    "iso:country":"NL",
    "sg:address":"De Liesbosch 12F",
    "sg:city":"Nieuwegein",
    "sg:orig_category":"Ventilatiesystemen",
    "sg:phone":"+31 30 280 1778",
    "sg:postcode":"3439 LC",
    "sg:province":"Utrecht",
    "wof:name":"Bommel, Van",
    "wof:placetype":"venue"
},
  "geometry": {"coordinates":[5.1104,52.051151],"type":"Point"}
}