{
  "type": "Feature",
  "properties": {
    "addr:full":"C A V Beverenpln 10 S Gravenhage Zuid-Holland 2552 HT",
    "addr:housenumber":"10 s",
    "addr:postcode":"2552 ht",
    "addr:street":"Beverenpln",
    "iso:country":"NL",
    "sg:address":"C A V Beverenpln 10",
    "sg:city":"S Gravenhage",
    "sg:orig_category":"Verzekeringen - Verzekeringskantoren",
    "sg:phone":"+31 70 397 2613",
    "sg:postcode":"2552 HT",
    "sg:province":"Zuid-Holland",
    "wof:name":"Houtwijk",
    "wof:placetype":"venue"
},
  "geometry": {"coordinates":[4.2495799065,52.0536308289],"type":"Point"}
}