{
  "type": "Feature",
  "properties": {
    "addr:full":"Ayttawei 27 Roordahuizum Provincie Friesland 9008 SH",
    "addr:housenumber":"27;9008",
    "addr:postcode":"sh",
    "addr:street":"Ayttawei;Provincie Friesland",
    "iso:country":"NL",
    "sg:address":"Ayttawei 27",
    "sg:city":"Roordahuizum",
    "sg:orig_category":"Onderhoudswerken",
    "sg:phone":"+31 566 602 039",
    "sg:postcode":"9008 SH",
    "sg:province":"Provincie Friesland",
    "wof:name":"Jager-Koldijk, De",
    "wof:placetype":"venue"
},
  "geometry": {"coordinates":[5.791873,53.119015],"type":"Point"}
}