{
  "type": "Feature",
  "properties": {
    "addr:full":"K Bergstr 14 Amersfoort Utrecht 3811 ML",
    "addr:housenumber":"14",
    "addr:postcode":"3811 ml",
    "addr:street":"K Bergstr",
    "iso:country":"NL",
    "sg:address":"K Bergstr 14",
    "sg:city":"Amersfoort",
    "sg:orig_category":"Psychologen",
    "sg:phone":"+31 33 461 6196",
    "sg:postcode":"3811 ML",
    "sg:province":"Utrecht",
    "wof:name":"Hit",
    "wof:placetype":"venue"
},
  "geometry": {"coordinates":[5.383651,52.150524],"type":"Point"}
}