{
  "type": "Feature",
  "properties": {
    "iso:country":"NL",
    "sg:address":"Herdersveld 9",
    "sg:city":"Geldrop",
    "sg:orig_category":"Verzekeringen - Verzekeringskantoren",
    "sg:phone":"+31 40 285 2111",
    "sg:postcode":"5665 JK",
    "sg:province":"North Brabant",
    "wof:name":"Mauro",
    "wof:placetype":"venue"
},
  "geometry": {"coordinates":[5.579597,51.420471],"type":"Point"}
}