{
  "type": "Feature",
  "properties": {
    "addr:full":"Elmpterweg 27 Roermond Limburg 6042 KJ",
    "addr:housenumber":"27",
    "addr:postcode":"6042 kj",
    "addr:street":"Elmpterweg",
    "iso:country":"NL",
    "sg:address":"Elmpterweg 27",
    "sg:city":"Roermond",
    "sg:orig_category":"Drukkerijen And Copyshops",
    "sg:phone":"+31 475 322 824",
    "sg:postcode":"6042 KJ",
    "sg:province":"Limburg",
    "wof:name":"Uitgeverij Drukkerij Gilsing Bv",
    "wof:placetype":"venue"
},
  "geometry": {"coordinates":[6.019454,51.201317],"type":"Point"}
}