{
  "type": "Feature",
  "properties": {
    "addr:full":"Engeland 53 Beekbergen Gelderland 7361 CS",
    "addr:housenumber":"53",
    "addr:postcode":"7361 cs",
    "addr:street":"Engeland;Gelderland",
    "iso:country":"NL",
    "sg:address":"Engeland 53",
    "sg:city":"Beekbergen",
    "sg:orig_category":"Homeopathie",
    "sg:phone":"+31 55 506 3032",
    "sg:postcode":"7361 CS",
    "sg:province":"Gelderland",
    "wof:name":"Schiebaan-Weijland, C",
    "wof:placetype":"venue"
},
  "geometry": {"coordinates":[-1.97685,52.883289],"type":"Point"}
}