{
  "type": "Feature",
  "properties": {
    "addr:full":"Loevestein 30 Ede Gld Gelderland 6714 BV",
    "addr:housenumber":"30",
    "addr:postcode":"6714 bv",
    "addr:street":"Loevestein;Gld Gelderland",
    "iso:country":"NL",
    "sg:address":"Loevestein 30",
    "sg:city":"Ede Gld",
    "sg:orig_category":"Verhuur Bouwmachines",
    "sg:phone":"+31 318 632 184",
    "sg:postcode":"6714 BV",
    "sg:province":"Gelderland",
    "wof:name":"Ars Ede",
    "wof:placetype":"venue"
},
  "geometry": {"coordinates":[5.647291,52.041855],"type":"Point"}
}