{
  "type": "Feature",
  "properties": {
    "addr:full":"Voorstr 27 Woerden Utrecht 3441 CC",
    "addr:housenumber":"27",
    "addr:postcode":"3441 cc",
    "addr:street":"Voorstr",
    "iso:country":"NL",
    "sg:address":"Voorstr 27",
    "sg:city":"Woerden",
    "sg:orig_category":"Mode-Artikelen Dames En Heren",
    "sg:phone":"+31 348 417 799",
    "sg:postcode":"3441 CC",
    "sg:province":"Utrecht",
    "wof:name":"Doek Bv",
    "wof:placetype":"venue"
},
  "geometry": {"coordinates":[4.887371,52.085117],"type":"Point"}
}