{
  "type": "Feature",
  "properties": {
    "addr:full":"Achlumerstraat 12 Leeuwarden Provincie Friesland 8913 GM",
    "addr:housenumber":"12",
    "addr:postcode":"8913 gm",
    "addr:street":"Achlumerstraat;Provincie Friesland",
    "iso:country":"NL",
    "sg:address":"Achlumerstraat 12",
    "sg:city":"Leeuwarden",
    "sg:orig_category":"Fotostudio'S And Fotografen",
    "sg:phone":"+31 58 213 6572",
    "sg:postcode":"8913 GM",
    "sg:province":"Provincie Friesland",
    "wof:name":"Haaije Bruinsma Fotografie",
    "wof:placetype":"venue"
},
  "geometry": {"coordinates":[5.778948,53.201931],"type":"Point"}
}