{
  "type": "Feature",
  "properties": {
    "addr:full":"Doctor M Luther King-Hof 15 Lopik Utrecht 3411 CD",
    "addr:housenumber":"15",
    "addr:postcode":"3411 cd",
    "addr:street":"Doctor M Luther King-Hof",
    "iso:country":"NL",
    "sg:address":"Doctor M Luther King-Hof 15",
    "sg:city":"Lopik",
    "sg:orig_category":"Boekhouders",
    "sg:phone":"+31 348 551 522",
    "sg:postcode":"3411 CD",
    "sg:province":"Utrecht",
    "wof:name":"Administratiekantoor Jansen Bv",
    "wof:placetype":"venue"
},
  "geometry": {"coordinates":[4.95464,51.97393],"type":"Point"}
}