{
  "type": "Feature",
  "properties": {
    "addr:full":"Waterland 117 Groningen Groningen 9734 BC",
    "addr:housenumber":"117",
    "addr:postcode":"9734 bc",
    "addr:street":"Waterland",
    "iso:country":"NL",
    "sg:address":"Waterland 117",
    "sg:city":"Groningen",
    "sg:orig_category":"Schoonheidssalons",
    "sg:phone":"+31 50 549 0148",
    "sg:postcode":"9734 BC",
    "sg:province":"Groningen",
    "wof:name":"Ada",
    "wof:placetype":"venue"
},
  "geometry": {"coordinates":[6.615402,53.242455],"type":"Point"}
}