{
  "type": "Feature",
  "properties": {
    "addr:full":"Bosscheweg 7 Den Dungen North Brabant 5275 HD",
    "addr:housenumber":"7",
    "addr:postcode":"5275 hd",
    "addr:street":"Bosscheweg",
    "iso:country":"NL",
    "sg:address":"Bosscheweg 7",
    "sg:city":"Den Dungen",
    "sg:orig_category":"Overheidsdiensten",
    "sg:phone":"+31 73 594 2966",
    "sg:postcode":"5275 HD",
    "sg:province":"North Brabant",
    "wof:name":"De Blauwe Scholk",
    "wof:placetype":"venue"
},
  "geometry": {"coordinates":[5.3678998947,51.6645088196],"type":"Point"}
}