{
  "type": "Feature",
  "properties": {
    "addr:full":"Okapistr 1 Almere Flevoland 1338 JT",
    "addr:housenumber":"1",
    "addr:postcode":"1338 jt",
    "addr:street":"Okapistr;Flevoland",
    "iso:country":"NL",
    "sg:address":"Okapistr 1",
    "sg:city":"Almere",
    "sg:orig_category":"Webdesign Bureaus",
    "sg:phone":"+31 36 537 2215",
    "sg:postcode":"1338 JT",
    "sg:province":"Flevoland",
    "sg:website":"http://www.okapisoft.nl",
    "wof:name":"Okapisoft",
    "wof:placetype":"venue"
},
  "geometry": {"coordinates":[5.2743601799,52.3830299377],"type":"Point"}
}