{
  "type": "Feature",
  "properties": {
    "addr:full":"Swammerdamstraat 78 Utrecht Utrecht 3553 RZ",
    "addr:housenumber":"78",
    "addr:postcode":"3553 rz",
    "addr:street":"Swammerdamstraat",
    "iso:country":"NL",
    "sg:address":"Swammerdamstraat 78",
    "sg:city":"Utrecht",
    "sg:orig_category":"Boekhouders",
    "sg:phone":"+31 30 243 2280",
    "sg:postcode":"3553 RZ",
    "sg:province":"Utrecht",
    "wof:name":"Beleid- Adviesbureau V/D Bruggen",
    "wof:placetype":"venue"
},
  "geometry": {"coordinates":[5.083839,52.112713],"type":"Point"}
}