{
  "type": "Feature",
  "properties": {
    "addr:full":"Hogewoerd 32 Leiden Zuid-Holland 2311 HN",
    "addr:housenumber":"32",
    "addr:postcode":"2311 hn",
    "addr:street":"Hogewoerd",
    "iso:country":"NL",
    "sg:address":"Hogewoerd 32",
    "sg:city":"Leiden",
    "sg:orig_category":"Fotostudio'S And Fotografen",
    "sg:phone":"+31 71 515 6565",
    "sg:postcode":"2311 HN",
    "sg:province":"Zuid-Holland",
    "wof:name":"Fotografie Frits Falkenhagen",
    "wof:placetype":"venue"
},
  "geometry": {"coordinates":[4.495123,52.15609],"type":"Point"}
}