{
  "type": "Feature",
  "properties": {
    "addr:full":"Koningln 14 Helmond Noord-Brabant 5708 ED",
    "addr:housenumber":"14",
    "addr:postcode":"5708 ed",
    "addr:street":"Koningln",
    "iso:country":"NL",
    "sg:address":"Koningln 14",
    "sg:city":"Helmond",
    "sg:orig_category":"Horecabenodigdheden",
    "sg:phone":"+31 492 547 646",
    "sg:postcode":"5708 ED",
    "sg:province":"Noord-Brabant",
    "wof:name":"Panne-Gies Bv",
    "wof:placetype":"venue"
},
  "geometry": {"coordinates":[5.603324,51.48645],"type":"Point"}
}