{
  "type": "Feature",
  "properties": {
    "addr:full":"Rondven 46 Maarheeze Noord-Brabant 6026 PX",
    "addr:housenumber":"46",
    "addr:postcode":"6026 px",
    "addr:street":"Rondven",
    "iso:country":"NL",
    "sg:address":"Rondven 46",
    "sg:city":"Maarheeze",
    "sg:orig_category":"Plaatwerk",
    "sg:phone":"+31 495 599 988",
    "sg:postcode":"6026 PX",
    "sg:province":"Noord-Brabant",
    "sg:website":"http://www.stetec.nl",
    "wof:name":"Stetec Bv",
    "wof:placetype":"venue"
},
  "geometry": {"coordinates":[5.631669,51.309772],"type":"Point"}
}