{
  "type": "Feature",
  "properties": {
    "addr:full":"Hoofdstr 5 Nes Gem Donger Friesland 9143 WS",
    "addr:housenumber":"5",
    "addr:postcode":"donger;9143 ws",
    "addr:street":"Hoofdstr",
    "iso:country":"NL",
    "sg:address":"Hoofdstr 5",
    "sg:city":"Nes Gem Donger",
    "sg:orig_category":"Beeldende Kunstenaars",
    "sg:phone":"+31 519 589 333",
    "sg:postcode":"9143 WS",
    "sg:province":"Friesland",
    "wof:name":"Offringa, G",
    "wof:placetype":"venue"
},
  "geometry": {"coordinates":[6.04631,53.396358],"type":"Point"}
}