{
  "type": "Feature",
  "properties": {
    "addr:full":"Zoutmanlaan 5 Hilversum Noord-Holland 1215 PR",
    "addr:housenumber":"5",
    "addr:postcode":"1215 pr",
    "addr:street":"Zoutmanlaan",
    "iso:country":"NL",
    "sg:address":"Zoutmanlaan 5",
    "sg:city":"Hilversum",
    "sg:orig_category":"Autokeuringen",
    "sg:phone":"+31 35 621 0968",
    "sg:postcode":"1215 PR",
    "sg:province":"Noord-Holland",
    "wof:name":"Zelftankstation J. Iesberts",
    "wof:placetype":"venue"
},
  "geometry": {"coordinates":[5.15246,52.210773],"type":"Point"}
}