{
  "type": "Feature",
  "properties": {
    "addr:full":"Postbus 91632 S Gravenhage Friesland 2509 EE",
    "addr:housenumber":"91632",
    "addr:postcode":"2509 ee",
    "addr:street":"Postbus;S Gravenhage Friesland",
    "iso:country":"NL",
    "sg:address":"Postbus 91632",
    "sg:city":"S Gravenhage",
    "sg:orig_category":"Verenigingsgebouwen",
    "sg:phone":"+31 70 383 4005",
    "sg:postcode":"2509 EE",
    "sg:province":"Friesland",
    "wof:name":"Horst, De",
    "wof:placetype":"venue"
},
  "geometry": {"coordinates":[4.31361,52.07832],"type":"Point"}
}