{
  "type": "Feature",
  "properties": {
    "addr:full":"Veersedijk 145 Hendrik Ido Ambacht South Holland 3341 LL",
    "addr:housenumber":"145",
    "addr:postcode":"3341 ll",
    "addr:street":"Veersedijk",
    "iso:country":"NL",
    "sg:address":"Veersedijk 145",
    "sg:city":"Hendrik Ido Ambacht",
    "sg:orig_category":"Verhuur Gereedschapsmachines And Gereedschappen",
    "sg:phone":"+31 78 681 4030",
    "sg:postcode":"3341 LL",
    "sg:province":"South Holland",
    "wof:name":"Carl Wille Geluidstechniek",
    "wof:placetype":"venue"
},
  "geometry": {"coordinates":[4.655769,51.843933],"type":"Point"}
}