{
  "type": "Feature",
  "properties": {
    "iso:country":"NL",
    "sg:address":"Veersedijk 145",
    "sg:city":"Hendrik Ido Ambacht",
    "sg:orig_category":"Verhuur Gereedschapsmachines And Gereedschappen",
    "sg:phone":"+31 78 681 4030",
    "sg:postcode":"3341 LL",
    "sg:province":"South Holland",
    "wof:name":"Carl Wille Geluidstechniek",
    "wof:placetype":"venue"
},
  "geometry": {"coordinates":[4.655769,51.843933],"type":"Point"}
}