{
  "type": "Feature",
  "properties": {
    "addr:full":"Konenhofstr 11 Weert Limburg 6005 SB",
    "addr:housenumber":"11",
    "addr:postcode":"6005 sb",
    "addr:street":"Konenhofstr",
    "iso:country":"NL",
    "sg:address":"Konenhofstr 11",
    "sg:city":"Weert",
    "sg:orig_category":"Kappers",
    "sg:phone":"+31 495 562 259",
    "sg:postcode":"6005 SB",
    "sg:province":"Limburg",
    "wof:name":"Helen",
    "wof:placetype":"venue"
},
  "geometry": {"coordinates":[5.7343587875,51.211681366],"type":"Point"}
}