{
  "type": "Feature",
  "properties": {
    "iso:country":"NL",
    "sg:address":"Kapelstraat 17",
    "sg:city":"Baarle-Hertog-Nassau Belgie",
    "sg:orig_category":"Meubelzaken, Woning- And Keukeninrichting",
    "sg:phone":"+32 14 69 96 29",
    "sg:postcode":"2387 ",
    "wof:name":"Den Torenburg",
    "wof:placetype":"venue"
},
  "geometry": {"coordinates":[4.9341812134,51.4423103333],"type":"Point"}
}