{
  "type": "Feature",
  "properties": {
    "iso:country":"NL",
    "sg:address":"Weverstr 73",
    "sg:city":"Den Burg",
    "sg:orig_category":"Fotoreportages",
    "sg:phone":"+31 222 314 499",
    "sg:postcode":"1791 AC",
    "sg:province":"Noord-Holland",
    "sg:website":"http://www.simonsmit.nl",
    "wof:name":"Simon Smit Fotografie",
    "wof:placetype":"venue"
},
  "geometry": {"coordinates":[4.799774,53.054565],"type":"Point"}
}