{
  "type": "Feature",
  "properties": {
    "iso:country":"NL",
    "sg:address":"Stolbergstraat 9",
    "sg:city":"Haarlem",
    "sg:orig_category":"Diverse Grafische Activiteiten",
    "sg:phone":"+31 23 540 0554",
    "sg:postcode":"2012 EP",
    "sg:province":"Noord-Holland",
    "wof:name":"Funcke Ontwerpers",
    "wof:placetype":"venue"
},
  "geometry": {"coordinates":[4.625016,52.375107],"type":"Point"}
}