{
  "type": "Feature",
  "properties": {
    "addr:full":"Tholen 25 Utrecht Utrecht 3524 ZN",
    "addr:housenumber":"25",
    "addr:postcode":"3524 zn",
    "addr:street":"Tholen",
    "iso:country":"NL",
    "sg:address":"Tholen 25",
    "sg:city":"Utrecht",
    "sg:orig_category":"Verenigingen En Stichtingen",
    "sg:phone":"+31 30 287 4044",
    "sg:postcode":"3524 ZN",
    "sg:province":"Utrecht",
    "wof:name":"Kajuit, De",
    "wof:placetype":"venue"
},
  "geometry": {"coordinates":[5.136116,52.060841],"type":"Point"}
}