{
  "type": "Feature",
  "properties": {
    "addr:full":"Neutronstr 10 Groningen Groningen 9743 AM",
    "addr:housenumber":"10",
    "addr:postcode":"9743",
    "addr:street":"Neutronstr",
    "iso:country":"NL",
    "sg:address":"Neutronstr 10",
    "sg:city":"Groningen",
    "sg:orig_category":"Fotolitho- En Reprografie - Inrichtingen",
    "sg:phone":"+31 50 313 2268",
    "sg:postcode":"9743 AM",
    "sg:province":"Groningen",
    "sg:website":"HTTP://www.reproform.nl",
    "wof:name":"Reproform Bv",
    "wof:placetype":"venue"
},
  "geometry": {"coordinates":[6.534966,53.216328],"type":"Point"}
}