{
  "type": "Feature",
  "properties": {
    "addr:full":"Zeeanemoon 25 Hoek Van Holland Zuid-Holland 3151 VN",
    "addr:housenumber":"25",
    "addr:postcode":"3151 vn",
    "addr:street":"Zeeanemoon",
    "iso:country":"NL",
    "sg:address":"Zeeanemoon 25",
    "sg:city":"Hoek Van Holland",
    "sg:orig_category":"Webdesign Bureaus",
    "sg:phone":"+31 174 385 798",
    "sg:postcode":"3151 VN",
    "sg:province":"Zuid-Holland",
    "wof:name":"Rdh-Online-Support",
    "wof:placetype":"venue"
},
  "geometry": {"coordinates":[4.1280670166,51.9856109619],"type":"Point"}
}