{
  "type": "Feature",
  "properties": {
    "addr:full":"P Mulierstr 7 Sneek Friesland 8602 CL",
    "addr:housenumber":"7",
    "addr:postcode":"8602",
    "addr:street":"P Mulierstr",
    "iso:country":"NL",
    "sg:address":"P Mulierstr 7",
    "sg:city":"Sneek",
    "sg:classifiers":[
        {
            "category":"Sports & Exercise",
            "subcategory":"Stables",
            "type":"Entertainment"
        }
    ],
    "sg:phone":"+31 515 414 881",
    "sg:postcode":"8602 CL",
    "sg:province":"Friesland",
    "sg:tags":[
        "maneges"
    ],
    "wof:name":"Ruitersportcentrum",
    "wof:placetype":"venue"
},
  "geometry": {"coordinates":[5.651672,53.047104],"type":"Point"}
}