{
  "type": "Feature",
  "properties": {
    "addr:full":"Rosa Luxemburgstraat 1 Almelo Overijssel 7607 SM",
    "addr:housenumber":"1",
    "addr:postcode":"7607 sm",
    "addr:street":"Rosa Luxemburgstraat",
    "iso:country":"NL",
    "sg:address":"Rosa Luxemburgstraat 1",
    "sg:city":"Almelo",
    "sg:orig_category":"Zuivelproducten",
    "sg:phone":"+31 546 826 424",
    "sg:postcode":"7607 SM",
    "sg:province":"Overijssel",
    "wof:name":"Finkers Uw Kaasspecialist",
    "wof:placetype":"venue"
},
  "geometry": {"coordinates":[6.661769,52.356899],"type":"Point"}
}