{
  "type": "Feature",
  "properties": {
    "addr:full":"Einsteinstr 6A Harderwyk Ar Rifa\u2019 and Southern Region 3846 BH",
    "addr:housenumber":"6a harderwyk",
    "addr:postcode":"3846 bh",
    "addr:street":"Einsteinstr",
    "iso:country":"NL",
    "sg:address":"Einsteinstr 6A",
    "sg:city":"Harderwyk",
    "sg:orig_category":"Banden",
    "sg:phone":"+31 341 423 500",
    "sg:postcode":"3846 BH",
    "sg:province":"Ar Rifa\u2019 and Southern Region",
    "wof:name":"Hazeleger Banden Service",
    "wof:placetype":"venue"
},
  "geometry": {"coordinates":[50.5485,26.02475],"type":"Point"}
}