{
  "type": "Feature",
  "properties": {
    "addr:full":"Seattleweg 7 Pernis Rt Zuid-Holland 3195 ND",
    "addr:housenumber":"7",
    "addr:postcode":"rt;3195 nd",
    "addr:street":"Seattleweg",
    "iso:country":"NL",
    "sg:address":"Seattleweg 7",
    "sg:city":"Pernis Rt",
    "sg:orig_category":"Boekhouders",
    "sg:phone":"+31 10 283 4059",
    "sg:postcode":"3195 ND",
    "sg:province":"Zuid-Holland",
    "wof:name":"Ht Datasupport Bv",
    "wof:placetype":"venue"
},
  "geometry": {"coordinates":[4.403384,51.874718],"type":"Point"}
}