{
  "type": "Feature",
  "properties": {
    "addr:full":"Zalmwater 145 Barendrecht Zuid-Holland 2993 DX",
    "addr:housenumber":"145",
    "addr:postcode":"2993 dx",
    "addr:street":"Zalmwater",
    "iso:country":"NL",
    "sg:address":"Zalmwater 145",
    "sg:city":"Barendrecht",
    "sg:orig_category":"Hypotheken",
    "sg:phone":"+31 180 612 160",
    "sg:postcode":"2993 DX",
    "sg:province":"Zuid-Holland",
    "wof:name":"Hades",
    "wof:placetype":"venue"
},
  "geometry": {"coordinates":[4.503314,51.84528],"type":"Point"}
}