{
  "type": "Feature",
  "properties": {
    "addr:full":"Steenwijklaan 432 'S-Gravenhage South Holland 2541 RW",
    "addr:housenumber":"432",
    "addr:postcode":"2541 rw",
    "addr:street":"Steenwijklaan",
    "iso:country":"NL",
    "sg:address":"Steenwijklaan 432",
    "sg:city":"'S-Gravenhage",
    "sg:orig_category":"Fotoreportages",
    "sg:phone":"+31 70 321 0942",
    "sg:postcode":"2541 RW",
    "sg:province":"South Holland",
    "wof:name":"Haan",
    "wof:placetype":"venue"
},
  "geometry": {"coordinates":[4.277967,52.041805],"type":"Point"}
}