{
  "type": "Feature",
  "properties": {
    "iso:country":"NL",
    "sg:address":"Postbus 803",
    "sg:city":"Zoetermeer",
    "sg:orig_category":"Onroerende Goederen",
    "sg:phone":"+31 79 368 5610",
    "sg:postcode":"2700 AV",
    "sg:province":"South Holland",
    "wof:name":"Desenco Group Bv",
    "wof:placetype":"venue"
},
  "geometry": {"coordinates":[4.48892,52.06308],"type":"Point"}
}