{
  "type": "Feature",
  "properties": {
    "addr:full":"Postbus 895 S Gravenhage South Holland 2501 CW",
    "addr:housenumber":"895",
    "addr:postcode":"2501 cw",
    "addr:street":"Postbus;S Gravenhage",
    "iso:country":"NL",
    "sg:address":"Postbus 895",
    "sg:city":"S Gravenhage",
    "sg:orig_category":"Verenigingen En Stichtingen",
    "sg:phone":"+31 70 364 1141",
    "sg:postcode":"2501 CW",
    "sg:province":"South Holland",
    "sg:website":"http://www.fonds1818.nl",
    "wof:name":"Fonds 1818",
    "wof:placetype":"venue"
},
  "geometry": {"coordinates":[4.31361,52.07832],"type":"Point"}
}