{
  "type": "Feature",
  "properties": {
    "addr:full":"Zuideinde 114 Oostzaan North Holland 1511 GJ",
    "addr:housenumber":"114",
    "addr:postcode":"1511 gj",
    "addr:street":"Zuideinde",
    "iso:country":"NL",
    "sg:address":"Zuideinde 114",
    "sg:city":"Oostzaan",
    "sg:orig_category":"Plafonds",
    "sg:phone":"+31 75 684 4748",
    "sg:postcode":"1511 GJ",
    "sg:province":"North Holland",
    "wof:name":"Zaanstad",
    "wof:placetype":"venue"
},
  "geometry": {"coordinates":[4.88039,52.433414],"type":"Point"}
}