{
  "type": "Feature",
  "properties": {
    "addr:full":"Beukenstr 11 Ymuiden North Holland 1971 JL",
    "addr:housenumber":"11",
    "addr:postcode":"1971 jl",
    "addr:street":"Beukenstr;North",
    "iso:country":"NL",
    "sg:address":"Beukenstr 11",
    "sg:city":"Ymuiden",
    "sg:orig_category":"Kinderopvang",
    "sg:phone":"+31 255 533 577",
    "sg:postcode":"1971 JL",
    "sg:province":"North Holland",
    "wof:name":"Pino",
    "wof:placetype":"venue"
},
  "geometry": {"coordinates":[4.626929,52.454136],"type":"Point"}
}