{
  "type": "Feature",
  "properties": {
    "addr:full":"Groenendyksepad 4 Hazerswoude Ryndyk Zuid-Holland 2394 BZ",
    "addr:housenumber":"4;ryndyk",
    "addr:postcode":"2394 bz",
    "addr:street":"Groenendyksepad",
    "iso:country":"NL",
    "sg:address":"Groenendyksepad 4",
    "sg:city":"Hazerswoude Ryndyk",
    "sg:classifiers":[
        {
            "category":"Education",
            "subcategory":"School",
            "type":"Public Place"
        }
    ],
    "sg:phone":"+31 71 341 3392",
    "sg:postcode":"2394 BZ",
    "sg:province":"Zuid-Holland",
    "sg:tags":[
        "studiebegeleiding",
        "en",
        "school-"
    ],
    "wof:name":"Koning, De",
    "wof:placetype":"venue"
},
  "geometry": {"coordinates":[4.595154,52.131054],"type":"Point"}
}