{
  "type": "Feature",
  "properties": {
    "iso:country":"NL",
    "sg:address":"Lottumsewg 45-47",
    "sg:city":"Grubbenvorst",
    "sg:classifiers":[
        {
            "category":"Retail",
            "subcategory":"Auto Repair",
            "type":"Services"
        }
    ],
    "sg:phone":"+31 77 366 2447",
    "sg:postcode":"5971 BV",
    "sg:province":"Limburg",
    "sg:tags":[
        "garage"
    ],
    "wof:name":"Comert, De",
    "wof:placetype":"venue"
},
  "geometry": {"coordinates":[6.147565,51.423756],"type":"Point"}
}