{
  "type": "Feature",
  "properties": {
    "addr:full":"Bergstraat 9 Amersfoort Utrecht 3811 NE",
    "addr:housenumber":"9",
    "addr:postcode":"3811 ne",
    "addr:street":"Bergstraat",
    "iso:country":"NL",
    "sg:address":"Bergstraat 9",
    "sg:city":"Amersfoort",
    "sg:orig_category":"Hypotheken And Hypotheekbanken",
    "sg:phone":"+31 33 464 0700",
    "sg:postcode":"3811 NE",
    "sg:province":"Utrecht",
    "wof:name":"Kamerbeek Assurantie Makelaars Bv",
    "wof:placetype":"venue"
},
  "geometry": {"coordinates":[5.386085,52.152325],"type":"Point"}
}