{
  "type": "Feature",
  "properties": {
    "addr:full":"Leeuwenstr 50 Hilversum Noord-Holland 1211 EW",
    "addr:housenumber":"50",
    "addr:postcode":"1211 ew",
    "addr:street":"Leeuwenstr",
    "iso:country":"NL",
    "sg:address":"Leeuwenstr 50",
    "sg:city":"Hilversum",
    "sg:orig_category":"Broodjeszaken",
    "sg:phone":"+31 35 640 0369",
    "sg:postcode":"1211 EW",
    "sg:province":"Noord-Holland",
    "wof:name":"Broodje D\u00f7Ner Van Hassan",
    "wof:placetype":"venue"
},
  "geometry": {"coordinates":[5.178703,52.226021],"type":"Point"}
}