{
  "type": "Feature",
  "properties": {
    "iso:country":"NL",
    "sg:address":"Schoepenwg 29",
    "sg:city":"Lelystad",
    "sg:orig_category":"Autoschade- Herstelbedrijven",
    "sg:phone":"+31 320 221 976",
    "sg:postcode":"8243 PX",
    "sg:province":"NL.",
    "wof:name":"Care Schadeservice Lelystad Bv",
    "wof:placetype":"venue"
},
  "geometry": {"coordinates":[5.450721,52.503643],"type":"Point"}
}