{
  "type": "Feature",
  "properties": {
    "addr:full":"Kerkstraat 13 Vriezenveen Overijssel 7671 HE",
    "addr:housenumber":"13",
    "addr:postcode":"7671 he",
    "addr:street":"Kerkstraat",
    "iso:country":"NL",
    "sg:address":"Kerkstraat 13",
    "sg:city":"Vriezenveen",
    "sg:orig_category":"Artiesten",
    "sg:phone":"+31 546 562 943",
    "sg:postcode":"7671 HE",
    "sg:province":"Overijssel",
    "wof:name":"J Jansen",
    "wof:placetype":"venue"
},
  "geometry": {"coordinates":[6.627487,52.409698],"type":"Point"}
}