{
  "type": "Feature",
  "properties": {
    "addr:full":"Moeder Teresastraat 41 Purmerend Noord-Holland 1447 XC",
    "addr:housenumber":"41",
    "addr:postcode":"1447 xc",
    "addr:street":"Moeder Teresastraat",
    "iso:country":"NL",
    "sg:address":"Moeder Teresastraat 41",
    "sg:city":"Purmerend",
    "sg:orig_category":"Boekhouders",
    "sg:phone":"+31 299 463 485",
    "sg:postcode":"1447 XC",
    "sg:province":"Noord-Holland",
    "wof:name":"Monique",
    "wof:placetype":"venue"
},
  "geometry": {"coordinates":[4.957475,52.487816],"type":"Point"}
}