{
  "type": "Feature",
  "properties": {
    "iso:country":"NL",
    "sg:address":"Zekkenstraat 48",
    "sg:city":"Hoek Van Holland",
    "sg:orig_category":"Meubeltextiel Fab",
    "sg:phone":"+31 174 415 831",
    "sg:postcode":"3151 XP",
    "sg:province":"Zuid-Holland",
    "wof:name":"Equator Sails",
    "wof:placetype":"venue"
},
  "geometry": {"coordinates":[4.144785,51.97044],"type":"Point"}
}