{
  "type": "Feature",
  "properties": {
    "addr:full":"Z Industriewg 3-7 Franeker Provincie Friesland 8801 JB",
    "addr:housenumber":"3-7",
    "addr:postcode":"8801 jb",
    "addr:street":"Provincie Friesland",
    "iso:country":"NL",
    "sg:address":"Z Industriewg 3-7",
    "sg:city":"Franeker",
    "sg:orig_category":"Verpakkingen En Verpakkingsmaterialen",
    "sg:phone":"+31 517 399 400",
    "sg:postcode":"8801 JB",
    "sg:province":"Provincie Friesland",
    "sg:website":"http://www.huhtamaki.com",
    "wof:name":"Huhtamaki Bv",
    "wof:placetype":"venue"
},
  "geometry": {"coordinates":[5.540528,53.182198],"type":"Point"}
}