{
  "type": "Feature",
  "properties": {
    "addr:full":"Markt 2 Staphorst NL.08 7951 HR",
    "addr:housenumber":"2;nl.08",
    "addr:postcode":"7951 hr",
    "addr:street":"Markt",
    "iso:country":"NL",
    "sg:address":"Markt 2",
    "sg:city":"Staphorst",
    "sg:orig_category":"Boekhandels",
    "sg:phone":"+31 522 464 165",
    "sg:postcode":"7951 HR",
    "sg:province":"NL.08",
    "wof:name":"Frans Nooren Staphorst Bv",
    "wof:placetype":"venue"
},
  "geometry": {"coordinates":[6.209137,52.645393],"type":"Point"}
}