{
  "type": "Feature",
  "properties": {
    "addr:full":"Kade 19A Rucphen Noord-Brabant 4715 AB",
    "addr:housenumber":"19a",
    "addr:postcode":"4715 ab",
    "addr:street":"Kade",
    "iso:country":"NL",
    "sg:address":"Kade 19A",
    "sg:city":"Rucphen",
    "sg:classifiers":[
        {
            "category":"Personal",
            "subcategory":"Nail Salon",
            "type":"Services"
        }
    ],
    "sg:phone":"+31 165 342 325",
    "sg:postcode":"4715 AB",
    "sg:province":"Noord-Brabant",
    "sg:tags":[
        "pedicure"
    ],
    "wof:name":"Sur Un Bon Pied",
    "wof:placetype":"venue"
},
  "geometry": {"coordinates":[4.554171,51.531898],"type":"Point"}
}