{
  "type": "Feature",
  "properties": {
    "iso:country":"NL",
    "sg:address":"Prins Hendrikplein 1",
    "sg:city":"Veendam",
    "sg:orig_category":"Huishoudapparatuur, Televisies And Radio'S",
    "sg:phone":"+31 598 612 082",
    "sg:postcode":"9641 GJ",
    "sg:province":"Groningen",
    "wof:name":"Radio Kip Bv",
    "wof:placetype":"venue"
},
  "geometry": {"coordinates":[6.872957,53.106224],"type":"Point"}
}