{
  "type": "Feature",
  "properties": {
    "addr:full":"Stadswerf 38 Almere Flevoland 1354 CC",
    "addr:housenumber":"38",
    "addr:postcode":"1354 cc",
    "addr:street":"Stadswerf;Flevoland",
    "iso:country":"NL",
    "sg:address":"Stadswerf 38",
    "sg:city":"Almere",
    "sg:orig_category":"Psychologen",
    "sg:phone":"+31 36 531 3164",
    "sg:postcode":"1354 CC",
    "sg:province":"Flevoland",
    "wof:name":"Dagelijkse Praktijk, De",
    "wof:placetype":"venue"
},
  "geometry": {"coordinates":[5.219026,52.33852],"type":"Point"}
}