{
  "type": "Feature",
  "properties": {
    "addr:full":"Sportln 2 Epe Gelderland 8162 BE",
    "addr:housenumber":"2",
    "addr:postcode":"8162",
    "addr:street":"Sportln;Gelderland",
    "iso:country":"NL",
    "sg:address":"Sportln 2",
    "sg:city":"Epe",
    "sg:orig_category":"Verenigingsgebouwen",
    "sg:phone":"+31 578 614 589",
    "sg:postcode":"8162 BE",
    "sg:province":"Gelderland",
    "wof:name":"Buurthoeve, De",
    "wof:placetype":"venue"
},
  "geometry": {"coordinates":[5.986395,52.35199],"type":"Point"}
}