{
  "type": "Feature",
  "properties": {
    "addr:full":"Stationslaan 13 Harderwijk Gelderland 3844 GA",
    "addr:housenumber":"13",
    "addr:postcode":"3844 ga",
    "addr:street":"Stationslaan;Gelderland",
    "iso:country":"NL",
    "sg:address":"Stationslaan 13",
    "sg:city":"Harderwijk",
    "sg:orig_category":"Meubelzaken, Woning- And Keukeninrichting",
    "sg:phone":"+31 341 417 177",
    "sg:postcode":"3844 GA",
    "sg:province":"Gelderland",
    "wof:name":"Wezep Jonkers Beheer",
    "wof:placetype":"venue"
},
  "geometry": {"coordinates":[5.620873,52.339287],"type":"Point"}
}