{
  "type": "Feature",
  "properties": {
    "addr:full":"Dorpeldk 2 Vleuten Utrecht 3451 RD",
    "addr:housenumber":"2",
    "addr:postcode":"3451 rd",
    "addr:street":"Dorpeldk",
    "iso:country":"NL",
    "sg:address":"Dorpeldk 2",
    "sg:city":"Vleuten",
    "sg:orig_category":"Koel- En Vrieshuizen",
    "sg:phone":"+31 30 677 1754",
    "sg:postcode":"3451 RD",
    "sg:province":"Utrecht",
    "wof:name":"Vernooy, C J",
    "wof:placetype":"venue"
},
  "geometry": {"coordinates":[4.97648,52.099964],"type":"Point"}
}