{
  "type": "Feature",
  "properties": {
    "iso:country":"NL",
    "sg:address":"Doktersfiif 22",
    "sg:city":"Oosternykerk",
    "sg:orig_category":"Verenigingsgebouwen",
    "sg:phone":"+31 519 241 486",
    "sg:postcode":"9137 RW",
    "sg:province":"Provincie Friesland",
    "wof:name":"Terp, De",
    "wof:placetype":"venue"
},
  "geometry": {"coordinates":[6.055269,53.379475],"type":"Point"}
}