{
  "type": "Feature",
  "properties": {
    "iso:country":"NL",
    "sg:address":"Grotestr 69",
    "sg:city":"Venray",
    "sg:orig_category":"Drogisterijen",
    "sg:phone":"+31 478 589 021",
    "sg:postcode":"5801 BE",
    "sg:province":"Limburg",
    "wof:name":"Kruidvat",
    "wof:placetype":"venue"
},
  "geometry": {"coordinates":[5.975744,51.525295],"type":"Point"}
}