{
  "type": "Feature",
  "properties": {
    "addr:full":"Meidoornstraat 11 Hellevoetsluis Zuid-Holland 3222 XL",
    "addr:housenumber":"11",
    "addr:postcode":"3222 xl",
    "addr:street":"Meidoornstraat",
    "iso:country":"NL",
    "sg:address":"Meidoornstraat 11",
    "sg:city":"Hellevoetsluis",
    "sg:orig_category":"Kappers",
    "sg:phone":"+31 181 311 020",
    "sg:postcode":"3222 XL",
    "sg:province":"Zuid-Holland",
    "wof:name":"J.C.A. Bosschieter-Broer",
    "wof:placetype":"venue"
},
  "geometry": {"coordinates":[4.1327471733,51.8390388489],"type":"Point"}
}