{
  "type": "Feature",
  "properties": {
    "addr:full":"Maasnielderwg 33 Roermond Limburg 6042 CX",
    "addr:housenumber":"33",
    "addr:postcode":"6042 cx",
    "addr:street":"Maasnielderwg",
    "iso:country":"NL",
    "sg:address":"Maasnielderwg 33",
    "sg:city":"Roermond",
    "sg:orig_category":"Keukens",
    "sg:phone":"+31 475 333 605",
    "sg:postcode":"6042 CX",
    "sg:province":"Limburg",
    "wof:name":"Siematic",
    "wof:placetype":"venue"
},
  "geometry": {"coordinates":[6.004863,51.200397],"type":"Point"}
}