{
  "type": "Feature",
  "properties": {
    "addr:full":"Bevrijdingspln 7 Leiden Zuid-Holland 2321 BV",
    "addr:housenumber":"7",
    "addr:postcode":"2321 bv",
    "addr:street":"Bevrijdingspln",
    "iso:country":"NL",
    "sg:address":"Bevrijdingspln 7",
    "sg:city":"Leiden",
    "sg:orig_category":"Kaas",
    "sg:phone":"+31 71 576 6346",
    "sg:postcode":"2321 BV",
    "sg:province":"Zuid-Holland",
    "wof:name":"Kaas En Notenhuisje",
    "wof:placetype":"venue"
},
  "geometry": {"coordinates":[4.4770731926,52.1465644836],"type":"Point"}
}