{
  "type": "Feature",
  "properties": {
    "addr:full":"Nykerkln 34 S Gravenhage Zuid-Holland 2573 BB",
    "addr:housenumber":"34;gravenhage",
    "addr:postcode":"2573 bb",
    "addr:street":"Nykerkln;S",
    "iso:country":"NL",
    "sg:address":"Nykerkln 34",
    "sg:city":"S Gravenhage",
    "sg:orig_category":"Loonbedrijven",
    "sg:phone":"+31 70 365 8237",
    "sg:postcode":"2573 BB",
    "sg:province":"Zuid-Holland",
    "wof:name":"Cesim, O",
    "wof:placetype":"venue"
},
  "geometry": {"coordinates":[4.2844,52.064911],"type":"Point"}
}