{
  "type": "Feature",
  "properties": {
    "addr:full":"Nachtegaalstraat 8 Krimpen A/D Ijssel Zuid-Holland 2922 VL",
    "addr:housenumber":"8;a / d",
    "addr:postcode":"2922 vl",
    "addr:street":"Nachtegaalstraat",
    "iso:country":"NL",
    "sg:address":"Nachtegaalstraat 8",
    "sg:city":"Krimpen A/D Ijssel",
    "sg:classifiers":[
        {
            "category":"Shopping",
            "subcategory":"Gifts & Souvenirs",
            "type":"Retail Goods"
        }
    ],
    "sg:phone":"+31 180 516 060",
    "sg:postcode":"2922 VL",
    "sg:province":"Zuid-Holland",
    "sg:tags":[
        "geschenken"
    ],
    "wof:name":"Wereldwinkel",
    "wof:placetype":"venue"
},
  "geometry": {"coordinates":[4.590601,51.916245],"type":"Point"}
}