{
  "type": "Feature",
  "properties": {
    "addr:full":"Maasdijk 273 Wijk En Aalburg Noord-Brabant 4261 AL",
    "addr:housenumber":"273",
    "addr:postcode":"4261 al",
    "addr:street":"Maasdijk",
    "iso:country":"NL",
    "sg:address":"Maasdijk 273",
    "sg:city":"Wijk En Aalburg",
    "sg:orig_category":"Bloemen And Planten",
    "sg:phone":"+31 416 691 785",
    "sg:postcode":"4261 AL",
    "sg:province":"Noord-Brabant",
    "wof:name":"A. Vos Colijn",
    "wof:placetype":"venue"
},
  "geometry": {"coordinates":[5.116467,51.775803],"type":"Point"}
}