{
  "type": "Feature",
  "properties": {
    "addr:full":"Stationslaan 75 Nunspeet Gelderland 8071 CL",
    "addr:housenumber":"75",
    "addr:postcode":"8071",
    "addr:street":"Stationslaan;Gelderland",
    "iso:country":"NL",
    "sg:address":"Stationslaan 75",
    "sg:city":"Nunspeet",
    "sg:orig_category":"Kappers",
    "sg:phone":"+31 341 258 379",
    "sg:postcode":"8071 CL",
    "sg:province":"Gelderland",
    "wof:name":"Jose'S Hairshop",
    "wof:placetype":"venue"
},
  "geometry": {"coordinates":[5.7722048759,52.3749809265],"type":"Point"}
}