{
  "type": "Feature",
  "properties": {
    "addr:full":"J Keplerwg 24 Alphen Aan Den Ryn Zuid-Holland 2408 AC",
    "addr:housenumber":"24",
    "addr:postcode":"2408 ac",
    "addr:street":"Aan Den Ryn",
    "iso:country":"NL",
    "sg:address":"J Keplerwg 24",
    "sg:city":"Alphen Aan Den Ryn",
    "sg:orig_category":"Boeken En Tijdschriften - Groothandel",
    "sg:phone":"+31 172 426 027",
    "sg:postcode":"2408 AC",
    "sg:province":"Zuid-Holland",
    "wof:name":"Mercuriwal Bv",
    "wof:placetype":"venue"
},
  "geometry": {"coordinates":[4.635283,52.123585],"type":"Point"}
}