{
  "type": "Feature",
  "properties": {
    "addr:full":"Schoolstraat 9 Zwaagwesteinde Friesland 9271 BT",
    "addr:housenumber":"9",
    "addr:postcode":"9271 bt",
    "addr:street":"Schoolstraat",
    "iso:country":"NL",
    "sg:address":"Schoolstraat 9",
    "sg:city":"Zwaagwesteinde",
    "sg:orig_category":"Wegen And Sportterreinen",
    "sg:phone":"+31 511 442 921",
    "sg:postcode":"9271 BT",
    "sg:province":"Friesland",
    "wof:name":"W. Alma",
    "wof:placetype":"venue"
},
  "geometry": {"coordinates":[6.034072876,53.2565498352],"type":"Point"}
}