{
  "type": "Feature",
  "properties": {
    "addr:full":"Brinklaan 30 Bussum Noord-Holland 1404 EW",
    "addr:housenumber":"30",
    "addr:postcode":"1404 ew",
    "addr:street":"Brinklaan",
    "iso:country":"NL",
    "sg:address":"Brinklaan 30",
    "sg:city":"Bussum",
    "sg:orig_category":"Werving And Selectie Van Vast Personeel",
    "sg:phone":"+31 35 691 7141",
    "sg:postcode":"1404 EW",
    "sg:province":"Noord-Holland",
    "wof:name":"Wynners Bv",
    "wof:placetype":"venue"
},
  "geometry": {"coordinates":[5.1627249718,52.2786102295],"type":"Point"}
}