{
  "type": "Feature",
  "properties": {
    "addr:full":"Langenboomseweg 43 Zeeland Noord-Brabant 5411 AT",
    "addr:housenumber":"43",
    "addr:postcode":"5411",
    "addr:street":"Langenboomseweg",
    "iso:country":"NL",
    "sg:address":"Langenboomseweg 43",
    "sg:city":"Zeeland",
    "sg:orig_category":"Fruit And Groenten Gh",
    "sg:phone":"+31 486 451 425",
    "sg:postcode":"5411 AT",
    "sg:province":"Noord-Brabant",
    "wof:name":"A.A.M. Van Dongen",
    "wof:placetype":"venue"
},
  "geometry": {"coordinates":[5.680879,51.696217],"type":"Point"}
}