{
  "type": "Feature",
  "properties": {
    "addr:full":"Jachthaven 1 Sassenheim Zuid-Holland 2172 JX",
    "addr:housenumber":"1",
    "addr:postcode":"2172 jx",
    "addr:street":"Jachthaven",
    "iso:country":"NL",
    "sg:address":"Jachthaven 1",
    "sg:city":"Sassenheim",
    "sg:orig_category":"Jachthavens - Jachtwerven",
    "sg:phone":"+31 252 211 583",
    "sg:postcode":"2172 JX",
    "sg:province":"Zuid-Holland",
    "wof:name":"Jonkman",
    "wof:placetype":"venue"
},
  "geometry": {"coordinates":[4.544665,52.220776],"type":"Point"}
}