{
  "type": "Feature",
  "properties": {
    "iso:country":"NL",
    "sg:address":"De Brauwwg 38-40",
    "sg:city":"Schiedam",
    "sg:orig_category":"Adviesbureaus Bedrijfsorganisatie",
    "sg:phone":"+31 10 437 9089",
    "sg:postcode":"3125 AE",
    "sg:province":"Zuid-Holland",
    "sg:website":"http://www.orbin.nl",
    "wof:name":"Orbital Technologies Bv",
    "wof:placetype":"venue"
},
  "geometry": {"coordinates":[4.408509,51.928829],"type":"Point"}
}