{
  "type": "Feature",
  "properties": {
    "addr:full":"Lindenhof 66 Weert Limburg 6006 VM",
    "addr:housenumber":"66",
    "addr:postcode":"6006 vm",
    "addr:street":"Lindenhof",
    "iso:country":"NL",
    "sg:address":"Lindenhof 66",
    "sg:city":"Weert",
    "sg:orig_category":"Hypotheken And Hypotheekbanken",
    "sg:phone":"+31 495 542 330",
    "sg:postcode":"6006 VM",
    "sg:province":"Limburg",
    "wof:name":"Hako-Otten",
    "wof:placetype":"venue"
},
  "geometry": {"coordinates":[5.679106,51.222164],"type":"Point"}
}