{
  "type": "Feature",
  "properties": {
    "addr:full":"Grotestraat 31 Sambeek Noord-Brabant 5836 AB",
    "addr:housenumber":"31",
    "addr:postcode":"5836 ab",
    "addr:street":"Grotestraat",
    "iso:country":"NL",
    "sg:address":"Grotestraat 31",
    "sg:city":"Sambeek",
    "sg:orig_category":"Loodgieterswerk, Verwarming And Sanitaire Installaties",
    "sg:phone":"+31 485 571 331",
    "sg:postcode":"5836 AB",
    "sg:province":"Noord-Brabant",
    "wof:name":"Kuenen Installatietechniek",
    "wof:placetype":"venue"
},
  "geometry": {"coordinates":[5.96365,51.638344],"type":"Point"}
}