{
  "type": "Feature",
  "properties": {
    "iso:country":"NL",
    "sg:address":"Torenveen 5",
    "sg:city":"Gieterveen",
    "sg:orig_category":"Oud Metaal",
    "sg:phone":"+31 599 648 577",
    "sg:postcode":"9511 PB",
    "sg:province":"Drenthe",
    "wof:name":"Lubben, H",
    "wof:placetype":"venue"
},
  "geometry": {"coordinates":[6.8320508003,53.0099067688],"type":"Point"}
}