{
  "type": "Feature",
  "properties": {
    "addr:full":"Nicolaas Beetslaan 5 Uithoorn Noord-Holland 1422 AP",
    "addr:housenumber":"5",
    "addr:postcode":"1422 ap",
    "addr:street":"Nicolaas Beetslaan",
    "iso:country":"NL",
    "sg:address":"Nicolaas Beetslaan 5",
    "sg:city":"Uithoorn",
    "sg:orig_category":"Kappers",
    "sg:phone":"+31 297 531 575",
    "sg:postcode":"1422 AP",
    "sg:province":"Noord-Holland",
    "wof:name":"De Alpenkapper",
    "wof:placetype":"venue"
},
  "geometry": {"coordinates":[4.8246908188,52.2427978516],"type":"Point"}
}