{
  "type": "Feature",
  "properties": {
    "addr:full":"Nachtegaalstraat 8 Krimpen A/D Ijssel South Holland 2922 VL",
    "addr:housenumber":"8;a / d",
    "addr:postcode":"2922 vl",
    "addr:street":"Nachtegaalstraat;Ijssel South",
    "iso:country":"NL",
    "sg:address":"Nachtegaalstraat 8",
    "sg:city":"Krimpen A/D Ijssel",
    "sg:orig_category":"Dansscholen",
    "sg:phone":"+31 180 520 162",
    "sg:postcode":"2922 VL",
    "sg:province":"South Holland",
    "wof:name":"Balletstudio 83",
    "wof:placetype":"venue"
},
  "geometry": {"coordinates":[4.590601,51.916245],"type":"Point"}
}