{
  "type": "Feature",
  "properties": {
    "iso:country":"NL",
    "sg:address":"Franse Kampwg 6",
    "sg:city":"Bussum",
    "sg:orig_category":"Adviesbureaus Verzekeringen",
    "sg:phone":"+31 35 692 6092",
    "sg:postcode":"1406 NW",
    "sg:province":"Noord-Holland",
    "wof:name":"Assuradeuren Bv Europees Diensten Centrum",
    "wof:placetype":"venue"
},
  "geometry": {"coordinates":[5.1434,52.260307],"type":"Point"}
}