{
  "type": "Feature",
  "properties": {
    "iso:country":"NL",
    "sg:address":"Penningln 23",
    "sg:city":"Ryswyk Zh",
    "sg:orig_category":"Schilders",
    "sg:phone":"+31 70 399 5471",
    "sg:postcode":"2281 BW",
    "sg:province":"Zuid-Holland",
    "wof:name":"Ijzerloo Rijswijk Schilderwerken Bv, M J Van",
    "wof:placetype":"venue"
},
  "geometry": {"coordinates":[4.341704,52.056934],"type":"Point"}
}