{
  "type": "Feature",
  "properties": {
    "iso:country":"NL",
    "sg:address":"Oranjeln 46",
    "sg:city":"Castricum",
    "sg:orig_category":"Autorijscholen",
    "sg:phone":"+31 6 51172502",
    "sg:postcode":"1901 TZ",
    "sg:province":"Noord-Holland",
    "wof:name":"Aerostar",
    "wof:placetype":"venue"
},
  "geometry": {"coordinates":[4.672643,52.553974],"type":"Point"}
}