{
  "type": "Feature",
  "properties": {
    "iso:country":"NL",
    "sg:address":"Frederikstr 11",
    "sg:city":"Serooskerke Schouw",
    "sg:orig_category":"Product-Promotie",
    "sg:phone":"+31 111 671 798",
    "sg:postcode":"4327 AD",
    "sg:province":"Zeeland",
    "wof:name":"Crazy Kangaroo",
    "wof:placetype":"venue"
},
  "geometry": {"coordinates":[3.813633,51.701061],"type":"Point"}
}