{
  "type": "Feature",
  "properties": {
    "addr:full":"Havendam 12 Oud Beijerland Zuid-Holland 3262 AE",
    "addr:housenumber":"12",
    "addr:postcode":"3262 ae",
    "addr:street":"Havendam;Oud Beijerland",
    "iso:country":"NL",
    "sg:address":"Havendam 12",
    "sg:city":"Oud Beijerland",
    "sg:classifiers":[
        {
            "category":"Fast Food",
            "type":"Food & Drink"
        }
    ],
    "sg:phone":"+31 186 626 828",
    "sg:postcode":"3262 AE",
    "sg:province":"Zuid-Holland",
    "sg:tags":[
        "afhaal",
        "restaurant"
    ],
    "wof:name":"Cheng Chinees Spec Restaurant",
    "wof:placetype":"venue"
},
  "geometry": {"coordinates":[4.411095,51.827415],"type":"Point"}
}