{
  "type": "Feature",
  "properties": {
    "addr:full":"Molendk 24 S Heerenhoek Zeeland 4453 AE",
    "addr:housenumber":"24",
    "addr:postcode":"4453 ae",
    "addr:street":"Molendk;S Heerenhoek Zeeland",
    "iso:country":"NL",
    "sg:address":"Molendk 24",
    "sg:city":"S Heerenhoek",
    "sg:orig_category":"Fietsen En Bromfietsen",
    "sg:phone":"+31 113 351 638",
    "sg:postcode":"4453 AE",
    "sg:province":"Zeeland",
    "wof:name":"Raas, C",
    "wof:placetype":"venue"
},
  "geometry": {"coordinates":[3.768182,51.455006],"type":"Point"}
}