{
  "type": "Feature",
  "properties": {
    "addr:full":"Zekeringstr 9 Amsterdam Noord-Holland 1014 BM",
    "addr:housenumber":"9",
    "addr:postcode":"1014 bm",
    "addr:street":"Zekeringstr",
    "iso:country":"NL",
    "sg:address":"Zekeringstr 9",
    "sg:city":"Amsterdam",
    "sg:orig_category":"Elektrotechnische Artikelen",
    "sg:phone":"+31 20 606 8100",
    "sg:postcode":"1014 BM",
    "sg:province":"Noord-Holland",
    "sg:website":"http://www.sonion.com",
    "wof:name":"Sonionmicrotronic Ned Bv",
    "wof:placetype":"venue"
},
  "geometry": {"coordinates":[4.853996,52.396423],"type":"Point"}
}