{
  "type": "Feature",
  "properties": {
    "addr:full":"Lijnbaan 50 Rotterdam Zuid-Holland 3012 EP",
    "addr:housenumber":"50",
    "addr:postcode":"3012 ep",
    "addr:street":"Lijnbaan",
    "iso:country":"NL",
    "sg:address":"Lijnbaan 50",
    "sg:city":"Rotterdam",
    "sg:orig_category":"Juweliers",
    "sg:phone":"+31 10 433 3633",
    "sg:postcode":"3012 EP",
    "sg:province":"Zuid-Holland",
    "wof:name":"Ierland Bv, L Van",
    "wof:placetype":"venue"
},
  "geometry": {"coordinates":[4.476193,51.922466],"type":"Point"}
}