{
  "type": "Feature",
  "properties": {
    "addr:full":"Geldersekd 80C Amsterdam Noord-Holland 1012 BL",
    "addr:housenumber":"80c",
    "addr:postcode":"1012 bl",
    "addr:street":"Geldersekd",
    "iso:country":"NL",
    "sg:address":"Geldersekd 80C",
    "sg:city":"Amsterdam",
    "sg:orig_category":"Kunstenaars- Benodigdheden",
    "sg:phone":"+31 20 623 7785",
    "sg:postcode":"1012 BL",
    "sg:province":"Noord-Holland",
    "wof:name":"Amsterdams Linnen, St",
    "wof:placetype":"venue"
},
  "geometry": {"coordinates":[4.893195,52.373119],"type":"Point"}
}