{
  "type": "Feature",
  "properties": {
    "iso:country":"NL",
    "sg:address":"Orionln 1",
    "sg:city":"Bilthoven",
    "sg:orig_category":"Kinderopvang",
    "sg:phone":"+31 30 228 3362",
    "sg:postcode":"3721 HD",
    "sg:province":"Utrecht",
    "wof:name":"Steenarend, De",
    "wof:placetype":"venue"
},
  "geometry": {"coordinates":[5.184633,52.122673],"type":"Point"}
}