{
  "type": "Feature",
  "properties": {
    "addr:full":"Anjerstraat 21 Oldenzaal NL.08 7572 VP",
    "addr:housenumber":"21;nl.08",
    "addr:postcode":"7572 vp",
    "addr:street":"Anjerstraat",
    "iso:country":"NL",
    "sg:address":"Anjerstraat 21",
    "sg:city":"Oldenzaal",
    "sg:orig_category":"Loodgieterswerk, Verwarming And Sanitaire Installaties",
    "sg:phone":"+31 541 532 332",
    "sg:postcode":"7572 VP",
    "sg:province":"NL.08",
    "wof:name":"Schoonmaakbedrijf Rkb",
    "wof:placetype":"venue"
},
  "geometry": {"coordinates":[6.921936,52.315128],"type":"Point"}
}