{
  "type": "Feature",
  "properties": {
    "addr:full":"Wynhaven 72 Rotterdam Zuid-Holland 3011 WT",
    "addr:housenumber":"72",
    "addr:postcode":"3011 wt",
    "addr:street":"Wynhaven",
    "iso:country":"NL",
    "sg:address":"Wynhaven 72",
    "sg:city":"Rotterdam",
    "sg:orig_category":"Non-Classified Establishments",
    "sg:phone":"+31 10 436 5755",
    "sg:postcode":"3011 WT",
    "sg:province":"Zuid-Holland",
    "wof:name":"Poortershaven Bv",
    "wof:placetype":"venue"
},
  "geometry": {"coordinates":[4.478455,51.922836],"type":"Point"}
}