{
  "type": "Feature",
  "properties": {
    "iso:country":"NL",
    "sg:address":"Past C M V Everdingenstr 22",
    "sg:city":"Rietmolen",
    "sg:orig_category":"Peuterspeelzalen",
    "sg:phone":"+31 6 12297819",
    "sg:postcode":"7165 AK",
    "sg:province":"Gelderland",
    "wof:name":"Reetm\u00f6lleke 'T",
    "wof:placetype":"venue"
},
  "geometry": {"coordinates":[6.662935,52.141399],"type":"Point"}
}