{
  "type": "Feature",
  "properties": {
    "addr:full":"Brugstraat 17 Gennep Limburg 6591 BA",
    "addr:housenumber":"17",
    "addr:postcode":"6591 ba",
    "addr:street":"Brugstraat",
    "iso:country":"NL",
    "sg:address":"Brugstraat 17",
    "sg:city":"Gennep",
    "sg:orig_category":"Overheidsdiensten",
    "sg:phone":"+31 485 515 382",
    "sg:postcode":"6591 BA",
    "sg:province":"Limburg",
    "wof:name":"Zo Wie Zo",
    "wof:placetype":"venue"
},
  "geometry": {"coordinates":[5.9699440002,51.6987609863],"type":"Point"}
}