{
  "type": "Feature",
  "properties": {
    "iso:country":"NL",
    "sg:address":"Randstad 2177",
    "sg:city":"Almere",
    "sg:orig_category":"Administratie- En Boekhoudkantoren",
    "sg:phone":"+31 36 530 0148",
    "sg:postcode":"1314 BJ",
    "sg:province":"Flevoland",
    "wof:name":"Prins & Partn Bv, J C",
    "wof:placetype":"venue"
},
  "geometry": {"coordinates":[5.223828,52.377541],"type":"Point"}
}