{
  "type": "Feature",
  "properties": {
    "addr:full":"Gersteland 3 Delfzijl Groningen 9932 HZ",
    "addr:housenumber":"3",
    "addr:postcode":"9932 hz",
    "addr:street":"Gersteland",
    "iso:country":"NL",
    "sg:address":"Gersteland 3",
    "sg:city":"Delfzijl",
    "sg:classifiers":[
        {
            "category":"Education",
            "subcategory":"Preschool",
            "type":"Public Place"
        }
    ],
    "sg:phone":"+31 596 626 734",
    "sg:postcode":"9932 HZ",
    "sg:province":"Groningen",
    "sg:tags":[
        "kleuteronderwijs",
        "basis-"
    ],
    "wof:name":"Openbare Basisschool Het Zigt",
    "wof:placetype":"venue"
},
  "geometry": {"coordinates":[6.890884,53.326889],"type":"Point"}
}