{
  "type": "Feature",
  "properties": {
    "addr:full":"Z Haaks 9 Den Hoorn Texel North Holland 1797 SH",
    "addr:housenumber":"9",
    "addr:postcode":"1797 sh",
    "addr:street":"Haaks",
    "iso:country":"NL",
    "sg:address":"Z Haaks 9",
    "sg:city":"Den Hoorn Texel",
    "sg:orig_category":"Koeriersdiensten",
    "sg:phone":"+31 222 319 944",
    "sg:postcode":"1797 SH",
    "sg:province":"North Holland",
    "wof:name":"Kempers",
    "wof:placetype":"venue"
},
  "geometry": {"coordinates":[4.785045,53.005547],"type":"Point"}
}