{
  "type": "Feature",
  "properties": {
    "addr:full":"Tafelstr 22 Maastricht Limburg 6211 JD",
    "addr:housenumber":"22",
    "addr:postcode":"6211 jd",
    "addr:street":"Tafelstr",
    "iso:country":"NL",
    "sg:address":"Tafelstr 22",
    "sg:city":"Maastricht",
    "sg:orig_category":"Galeries",
    "sg:phone":"+31 43 321 1021",
    "sg:postcode":"6211 JD",
    "sg:province":"Limburg",
    "wof:name":"Issues",
    "wof:placetype":"venue"
},
  "geometry": {"coordinates":[5.69086,50.846024],"type":"Point"}
}