{
  "type": "Feature",
  "properties": {
    "addr:full":"Hassinkwg 22A Hengelo Ov Overijssel 7556 BV",
    "addr:housenumber":"22a",
    "addr:postcode":"7556 bv",
    "addr:street":"Hassinkwg;Ov",
    "iso:country":"NL",
    "sg:address":"Hassinkwg 22A",
    "sg:city":"Hengelo Ov",
    "sg:orig_category":"Veiligheidsuitrusting En -Kleding",
    "sg:phone":"+31 74 256 6755",
    "sg:postcode":"7556 BV",
    "sg:province":"Overijssel",
    "wof:name":"Berco En Telva",
    "wof:placetype":"venue"
},
  "geometry": {"coordinates":[6.773017,52.280514],"type":"Point"}
}