{
  "type": "Feature",
  "properties": {
    "addr:full":"Clavecymbelstraat 58 Maastricht Limburg 6217 CV",
    "addr:housenumber":"58",
    "addr:postcode":"6217 cv",
    "addr:street":"Clavecymbelstraat",
    "iso:country":"NL",
    "sg:address":"Clavecymbelstraat 58",
    "sg:city":"Maastricht",
    "sg:orig_category":"Huishoudapparatuur, Televisies And Radio'S",
    "sg:phone":"+31 43 343 2162",
    "sg:postcode":"6217 CV",
    "sg:province":"Limburg",
    "wof:name":"Elektro Weerts Bv",
    "wof:placetype":"venue"
},
  "geometry": {"coordinates":[5.669281,50.860432],"type":"Point"}
}