{
  "type": "Feature",
  "properties": {
    "iso:country":"NL",
    "sg:address":"De Reede 20",
    "sg:city":"Urk",
    "sg:classifiers":[
        {
            "category":"Personal",
            "subcategory":"Nail Salon",
            "type":"Services"
        }
    ],
    "sg:phone":"+31 527 682 910",
    "sg:postcode":"8321 DA",
    "sg:province":"Flevoland",
    "sg:tags":[
        "pedicure"
    ],
    "wof:name":"Pasterkamp-Ras, H",
    "wof:placetype":"venue"
},
  "geometry": {"coordinates":[5.608824,52.661465],"type":"Point"}
}