{
  "type": "Feature",
  "properties": {
    "addr:full":"Kerkstr 66 Oisterwijk Noord-Brabant 5061 EK",
    "addr:housenumber":"66",
    "addr:postcode":"5061 ek",
    "addr:street":"Kerkstr",
    "iso:country":"NL",
    "sg:address":"Kerkstr 66",
    "sg:city":"Oisterwijk",
    "sg:orig_category":"Bloemen En Planten",
    "sg:phone":"+31 13 521 2718",
    "sg:postcode":"5061 EK",
    "sg:province":"Noord-Brabant",
    "wof:name":"Philomena",
    "wof:placetype":"venue"
},
  "geometry": {"coordinates":[5.187513,51.579479],"type":"Point"}
}