{
  "type": "Feature",
  "properties": {
    "addr:full":"Oude Bossche Baan 35 Helvoirt Noord-Brabant 5268 KS",
    "addr:housenumber":"35",
    "addr:postcode":"5268 ks",
    "addr:street":"Oude Bossche Baan",
    "iso:country":"NL",
    "sg:address":"Oude Bossche Baan 35",
    "sg:city":"Helvoirt",
    "sg:orig_category":"Kampeerterreinen",
    "sg:phone":"+31 411 641 880",
    "sg:postcode":"5268 KS",
    "sg:province":"Noord-Brabant",
    "wof:name":"Weideblik",
    "wof:placetype":"venue"
},
  "geometry": {"coordinates":[5.1850399971,51.6405525208],"type":"Point"}
}