{
  "type": "Feature",
  "properties": {
    "addr:full":"Noordeinde 108 Oostzaan Noord-Holland 1511 AG",
    "addr:housenumber":"108",
    "addr:postcode":"1511",
    "addr:street":"Noordeinde",
    "iso:country":"NL",
    "sg:address":"Noordeinde 108",
    "sg:city":"Oostzaan",
    "sg:orig_category":"Gespecialiseerde Bouw",
    "sg:phone":"+31 75 684 1589",
    "sg:postcode":"1511 AG",
    "sg:province":"Noord-Holland",
    "wof:name":"Constructiebedrijf Horstman Bv",
    "wof:placetype":"venue"
},
  "geometry": {"coordinates":[4.8698,52.451817],"type":"Point"}
}