{
  "type": "Feature",
  "properties": {
    "addr:full":"G V Endegeeststr 25 Hoofddorp North Holland 2132 SL",
    "addr:housenumber":"25",
    "addr:postcode":"2132 sl",
    "addr:street":"V Endegeeststr",
    "iso:country":"NL",
    "sg:address":"G V Endegeeststr 25",
    "sg:city":"Hoofddorp",
    "sg:orig_category":"Werving En Selectie",
    "sg:phone":"+31 23 561 2555",
    "sg:postcode":"2132 SL",
    "sg:province":"North Holland",
    "wof:name":"Rommers",
    "wof:placetype":"venue"
},
  "geometry": {"coordinates":[4.6929597855,52.305393219],"type":"Point"}
}