{
  "type": "Feature",
  "properties": {
    "iso:country":"NL",
    "sg:address":"Herenstraat 73",
    "sg:city":"Voorhout",
    "sg:classifiers":[
        {
            "category":"Communications",
            "subcategory":"Television Station",
            "type":"Services"
        }
    ],
    "sg:phone":"+31 252 216 156",
    "sg:postcode":"2215 KG",
    "sg:province":"Zuid-Holland",
    "sg:tags":[
        "video",
        "audio",
        "verhuur"
    ],
    "wof:name":"Flashlight",
    "wof:placetype":"venue"
},
  "geometry": {"coordinates":[4.484013,52.222443],"type":"Point"}
}