{
  "type": "Feature",
  "properties": {
    "addr:full":"Pastoriestr 19 Velp Nb Noord-Brabant 5363 TP",
    "addr:housenumber":"19",
    "addr:postcode":"5363 tp",
    "addr:street":"Pastoriestr",
    "iso:country":"NL",
    "sg:address":"Pastoriestr 19",
    "sg:city":"Velp Nb",
    "sg:orig_category":"Prijs- En Codeerapparatuur",
    "sg:phone":"+31 486 420 980",
    "sg:postcode":"5363 TP",
    "sg:province":"Noord-Brabant",
    "wof:name":"Zomerdam Bv",
    "wof:placetype":"venue"
},
  "geometry": {"coordinates":[5.713701,51.759682],"type":"Point"}
}