{
  "type": "Feature",
  "properties": {
    "addr:full":"Nijverheidsstraat 1 Gorssel Gelderland 7213 DA",
    "addr:housenumber":"1",
    "addr:postcode":"7213 da",
    "addr:street":"Nijverheidsstraat;Gelderland",
    "iso:country":"NL",
    "sg:address":"Nijverheidsstraat 1",
    "sg:city":"Gorssel",
    "sg:orig_category":"Discountwinkels",
    "sg:phone":"+31 575 491 594",
    "sg:postcode":"7213 DA",
    "sg:province":"Gelderland",
    "wof:name":"Kreeftenberg Textiel",
    "wof:placetype":"venue"
},
  "geometry": {"coordinates":[6.201127,52.200497],"type":"Point"}
}