{
  "type": "Feature",
  "properties": {
    "addr:full":"Beethovenln 394 Holtenbroek Zwolle NL.08 8031 BZ",
    "addr:housenumber":"394",
    "addr:postcode":"nl.08 8031 bz",
    "iso:country":"NL",
    "sg:address":"Beethovenln 394 Holtenbroek",
    "sg:city":"Zwolle",
    "sg:orig_category":"Verenigingsgebouwen",
    "sg:phone":"+31 38 422 4933",
    "sg:postcode":"8031 BZ",
    "sg:province":"NL.08",
    "wof:name":"Wijkcentr Holtenbroek",
    "wof:placetype":"venue"
},
  "geometry": {"coordinates":[6.0833,52.533298],"type":"Point"}
}