{
  "type": "Feature",
  "properties": {
    "addr:full":"Pastoor Van Arsplein 19 Eindhoven Noord-Brabant 5622 CJ",
    "addr:housenumber":"19",
    "addr:postcode":"5622 cj",
    "addr:street":"Pastoor Van Arsplein",
    "iso:country":"NL",
    "sg:address":"Pastoor Van Arsplein 19",
    "sg:city":"Eindhoven",
    "sg:orig_category":"Hout Gh",
    "sg:phone":"+31 40 245 2228",
    "sg:postcode":"5622 CJ",
    "sg:province":"Noord-Brabant",
    "wof:name":"Jos Hessing Deurenprogramma",
    "wof:placetype":"venue"
},
  "geometry": {"coordinates":[5.458991,51.458252],"type":"Point"}
}