{
  "type": "Feature",
  "properties": {
    "addr:full":"Brigidastr 49A Bavel Noord-Brabant 4854 CS",
    "addr:housenumber":"49a",
    "addr:postcode":"4854 cs",
    "addr:street":"Brigidastr",
    "iso:country":"NL",
    "sg:address":"Brigidastr 49A",
    "sg:city":"Bavel",
    "sg:orig_category":"Psychologen",
    "sg:phone":"+31 161 431 622",
    "sg:postcode":"4854 CS",
    "sg:province":"Noord-Brabant",
    "wof:name":"Kleij, Drs A H M",
    "wof:placetype":"venue"
},
  "geometry": {"coordinates":[4.834302,51.560436],"type":"Point"}
}