{
  "type": "Feature",
  "properties": {
    "addr:full":"Krugerln 183 Gouda Zuid-Holland 2806 EG",
    "addr:housenumber":"183",
    "addr:postcode":"2806 eg",
    "iso:country":"NL",
    "sg:address":"Krugerln 183",
    "sg:city":"Gouda",
    "sg:orig_category":"Psychotherapeuten",
    "sg:phone":"+31 182 526 260",
    "sg:postcode":"2806 EG",
    "sg:province":"Zuid-Holland",
    "wof:name":"Balans",
    "wof:placetype":"venue"
},
  "geometry": {"coordinates":[4.710714817,52.0100059509],"type":"Point"}
}