{
  "type": "Feature",
  "properties": {
    "addr:full":"Energieweg 85 Zoeterwoude Zuid-Holland 2382 NH",
    "addr:housenumber":"85",
    "addr:postcode":"2382 nh",
    "addr:street":"Energieweg",
    "iso:country":"NL",
    "sg:address":"Energieweg 85",
    "sg:city":"Zoeterwoude",
    "sg:orig_category":"Afvalinzameling And -Verwerking",
    "sg:phone":"+31 71 341 9408",
    "sg:postcode":"2382 NH",
    "sg:province":"Zuid-Holland",
    "wof:name":"C.W. Milieudienst Bv",
    "wof:placetype":"venue"
},
  "geometry": {"coordinates":[4.528284,52.13662],"type":"Point"}
}