{
  "type": "Feature",
  "properties": {
    "addr:full":"Wagenwg 92 Haarlem North Holland 2012 NH",
    "addr:housenumber":"92",
    "addr:postcode":"2012 nh",
    "addr:street":"Wagenwg",
    "iso:country":"NL",
    "sg:address":"Wagenwg 92",
    "sg:city":"Haarlem",
    "sg:orig_category":"Banken",
    "sg:phone":"+31 23 512 0512",
    "sg:postcode":"2012 NH",
    "sg:province":"North Holland",
    "sg:website":"http://www.rabobank.nl",
    "wof:name":"Rabobank",
    "wof:placetype":"venue"
},
  "geometry": {"coordinates":[4.624191,52.371689],"type":"Point"}
}