{
  "type": "Feature",
  "properties": {
    "iso:country":"NL",
    "sg:address":"Westermarwei 42",
    "sg:city":"Joure",
    "sg:orig_category":"Ballonvaarten En -Reclame",
    "sg:phone":"+31 513 414 059",
    "sg:postcode":"8501 TC",
    "sg:province":"Provincie Friesland",
    "sg:website":"http://www.ballonvaren.net",
    "wof:name":"Ballon Team Joure",
    "wof:placetype":"venue"
},
  "geometry": {"coordinates":[5.810154,52.96402],"type":"Point"}
}