{
  "type": "Feature",
  "properties": {
    "iso:country":"NL",
    "sg:address":"Fransestraat 19",
    "sg:city":"Ameide",
    "sg:orig_category":"Zuivelproducten And Spijsoli?n Gh",
    "sg:phone":"+31 183 601 213",
    "sg:postcode":"4233 EC",
    "sg:province":"Zuid-Holland",
    "wof:name":"Lekkerkerkers Zuivelhuis",
    "wof:placetype":"venue"
},
  "geometry": {"coordinates":[4.962639,51.957691],"type":"Point"}
}