{
  "type": "Feature",
  "properties": {
    "addr:full":"H De Grootstr 71 S Gravenhage Zuid-Holland 2518 EC",
    "addr:housenumber":"71;gravenhage",
    "addr:postcode":"2518 ec",
    "addr:street":"S",
    "iso:country":"NL",
    "sg:address":"H De Grootstr 71",
    "sg:city":"S Gravenhage",
    "sg:orig_category":"Fotografie Reclame En Mode",
    "sg:phone":"+31 70 365 0955",
    "sg:postcode":"2518 EC",
    "sg:province":"Zuid-Holland",
    "wof:name":"Bolier, J C",
    "wof:placetype":"venue"
},
  "geometry": {"coordinates":[4.29348,52.080318],"type":"Point"}
}