{
  "type": "Feature",
  "properties": {
    "addr:full":"Meteorenweg 385 Amsterdam North Holland 1033 HD",
    "addr:housenumber":"385",
    "addr:postcode":"1033 hd",
    "addr:street":"Meteorenweg",
    "iso:country":"NL",
    "sg:address":"Meteorenweg 385",
    "sg:city":"Amsterdam",
    "sg:orig_category":"Metaalafval, Schrootrecycling And Sloperijen",
    "sg:phone":"+31 20 631 0038",
    "sg:postcode":"1033 HD",
    "sg:province":"North Holland",
    "wof:name":"Autosloperij Farsi",
    "wof:placetype":"venue"
},
  "geometry": {"coordinates":[4.87601,52.41729],"type":"Point"}
}