{
  "type": "Feature",
  "properties": {
    "addr:full":"Blauwedk 15 Middelburg Zeeland 4331 JC",
    "addr:housenumber":"15",
    "addr:postcode":"4331 jc",
    "addr:street":"Blauwedk",
    "iso:country":"NL",
    "sg:address":"Blauwedk 15",
    "sg:city":"Middelburg",
    "sg:orig_category":"Herenkleding",
    "sg:phone":"+31 118 613 073",
    "sg:postcode":"4331 JC",
    "sg:province":"Zeeland",
    "wof:name":"Peca",
    "wof:placetype":"venue"
},
  "geometry": {"coordinates":[3.613595,51.495087],"type":"Point"}
}