{
  "type": "Feature",
  "properties": {
    "addr:full":"Kalverstr 208 Amsterdam North Holland 1012 XH",
    "addr:housenumber":"208",
    "addr:postcode":"1012 xh",
    "iso:country":"NL",
    "sg:address":"Kalverstr 208",
    "sg:city":"Amsterdam",
    "sg:orig_category":"Fotolaboratoria",
    "sg:phone":"+31 20 626 8720",
    "sg:postcode":"1012 XH",
    "sg:province":"North Holland",
    "wof:name":"Hema",
    "wof:placetype":"venue"
},
  "geometry": {"coordinates":[4.892072,52.367577],"type":"Point"}
}