{
  "type": "Feature",
  "properties": {
    "addr:full":"Ireneplnts 4 Cothen Utrecht 3945 CS",
    "addr:housenumber":"4",
    "addr:postcode":"3945 cs",
    "addr:street":"Ireneplnts",
    "iso:country":"NL",
    "sg:address":"Ireneplnts 4",
    "sg:city":"Cothen",
    "sg:orig_category":"Autorijscholen",
    "sg:phone":"+31 343 563 528",
    "sg:postcode":"3945 CS",
    "sg:province":"Utrecht",
    "wof:name":"Krijgsman, Hans",
    "wof:placetype":"venue"
},
  "geometry": {"coordinates":[5.311961,51.997684],"type":"Point"}
}