{
  "type": "Feature",
  "properties": {
    "iso:country":"NL",
    "sg:address":"Voltastr 92",
    "sg:city":"Doetinchem",
    "sg:orig_category":"Metaalbewerking",
    "sg:phone":"+31 314 391 465",
    "sg:postcode":"7006 RW",
    "sg:province":"Gelderland",
    "wof:name":"De Ce",
    "wof:placetype":"venue"
},
  "geometry": {"coordinates":[6.254828,51.970966],"type":"Point"}
}