{
  "type": "Feature",
  "properties": {
    "addr:full":"Brueghelstraat 287 'S Gravenhage Zuid-Holland 2525 RG",
    "addr:housenumber":"287 '",
    "addr:postcode":"2525 rg",
    "addr:street":"Brueghelstraat",
    "iso:country":"NL",
    "sg:address":"Brueghelstraat 287",
    "sg:city":"'S Gravenhage",
    "sg:orig_category":"Werving And Selectie Van Tijdelijk Personeel And Uitzendkantoren",
    "sg:phone":"+31 70 388 3196",
    "sg:postcode":"2525 RG",
    "sg:province":"Zuid-Holland",
    "wof:name":"Colonnade",
    "wof:placetype":"venue"
},
  "geometry": {"coordinates":[4.3035788536,52.0660438538],"type":"Point"}
}