{
  "type": "Feature",
  "properties": {
    "addr:full":"Bedrijvenstraat 10 Giessen Noord-Brabant 4283 JH",
    "addr:housenumber":"10",
    "addr:postcode":"4283 jh",
    "addr:street":"Bedrijvenstraat",
    "iso:country":"NL",
    "sg:address":"Bedrijvenstraat 10",
    "sg:city":"Giessen",
    "sg:orig_category":"Bloemen And Planten Gh",
    "sg:phone":"+31 183 443 371",
    "sg:postcode":"4283 JH",
    "sg:province":"Noord-Brabant",
    "wof:name":"Plantscape Bv",
    "wof:placetype":"venue"
},
  "geometry": {"coordinates":[5.033767,51.79155],"type":"Point"}
}