{
  "type": "Feature",
  "properties": {
    "addr:full":"Dorpsstr 76A Zoetermeer South Holland 2712 AM",
    "addr:housenumber":"76a",
    "addr:postcode":"2712",
    "addr:street":"Dorpsstr",
    "iso:country":"NL",
    "sg:address":"Dorpsstr 76A",
    "sg:city":"Zoetermeer",
    "sg:orig_category":"Verenigingen En Stichtingen",
    "sg:phone":"+31 79 316 5365",
    "sg:postcode":"2712 AM",
    "sg:province":"South Holland",
    "wof:name":"Wijkver Dorp",
    "wof:placetype":"venue"
},
  "geometry": {"coordinates":[4.497389,52.056301],"type":"Point"}
}