{
  "type": "Feature",
  "properties": {
    "addr:full":"Kompasstraat 30 Capelle Aan Den Ijssel Zuid-Holland 2901 AM",
    "addr:housenumber":"30",
    "addr:postcode":"aan den ijssel;2901",
    "addr:street":"Kompasstraat",
    "iso:country":"NL",
    "sg:address":"Kompasstraat 30",
    "sg:city":"Capelle Aan Den Ijssel",
    "sg:orig_category":"Autokeuringen",
    "sg:phone":"+31 10 540 1718",
    "sg:postcode":"2901 AM",
    "sg:province":"Zuid-Holland",
    "wof:name":"Tymons Autobedrijf Y",
    "wof:placetype":"venue"
},
  "geometry": {"coordinates":[4.562587,51.910282],"type":"Point"}
}