{
  "type": "Feature",
  "properties": {
    "addr:full":"M V Borsselenln 39 Amstelveen Noord-Holland 1181 CZ",
    "addr:housenumber":"39",
    "addr:postcode":"1181",
    "addr:street":"Borsselenln",
    "iso:country":"NL",
    "sg:address":"M V Borsselenln 39",
    "sg:city":"Amstelveen",
    "sg:orig_category":"Verloskundigen",
    "sg:phone":"+31 20 640 5006",
    "sg:postcode":"1181 CZ",
    "sg:province":"Noord-Holland",
    "sg:website":"http://www.cyclusgroep.nl",
    "wof:name":"Cyclusgroep Praktijk Brandenbarg",
    "wof:placetype":"venue"
},
  "geometry": {"coordinates":[4.856945,52.303444],"type":"Point"}
}