{
  "type": "Feature",
  "properties": {
    "addr:full":"Vechtdijk 140 Utrecht Utrecht 3563 MA",
    "addr:housenumber":"140",
    "addr:postcode":"3563 ma",
    "addr:street":"Vechtdijk",
    "iso:country":"NL",
    "sg:address":"Vechtdijk 140",
    "sg:city":"Utrecht",
    "sg:orig_category":"Beeldende Kunstenaars",
    "sg:phone":"+31 30 262 0652",
    "sg:postcode":"3563 MA",
    "sg:province":"Utrecht",
    "wof:name":"Poppel, P A Th Van",
    "wof:placetype":"venue"
},
  "geometry": {"coordinates":[5.094931,52.116901],"type":"Point"}
}