{
  "type": "Feature",
  "properties": {
    "addr:full":"Passage Molenpoort 6 Nijmegen Gelderland 6511 HV",
    "addr:housenumber":"6",
    "addr:postcode":"6511 hv",
    "addr:street":"Passage Molenpoort;Gelderland",
    "iso:country":"NL",
    "sg:address":"Passage Molenpoort 6",
    "sg:city":"Nijmegen",
    "sg:classifiers":[
        {
            "category":"Shopping",
            "subcategory":"Gifts & Souvenirs",
            "type":"Retail Goods"
        }
    ],
    "sg:phone":"+31 24 322 6881",
    "sg:postcode":"6511 HV",
    "sg:province":"Gelderland",
    "sg:tags":[
        "geschenken"
    ],
    "wof:name":"Markant",
    "wof:placetype":"venue"
},
  "geometry": {"coordinates":[5.863856,51.844322],"type":"Point"}
}