{
  "type": "Feature",
  "properties": {
    "addr:full":"Botweg 32 Bussum North Holland 1402 LE",
    "addr:housenumber":"32",
    "addr:postcode":"1402 le",
    "addr:street":"Botweg",
    "iso:country":"NL",
    "sg:address":"Botweg 32",
    "sg:city":"Bussum",
    "sg:orig_category":"Beeldende Kunstenaars",
    "sg:phone":"+31 35 694 0447",
    "sg:postcode":"1402 LE",
    "sg:province":"North Holland",
    "wof:name":"Rood, Van 'T",
    "wof:placetype":"venue"
},
  "geometry": {"coordinates":[5.168458,52.272705],"type":"Point"}
}