{
  "type": "Feature",
  "properties": {
    "addr:full":"Schoolstraat 6 Pannerden Gelderland 6911 AZ",
    "addr:housenumber":"6",
    "addr:postcode":"6911",
    "addr:street":"Schoolstraat;Gelderland",
    "iso:country":"NL",
    "sg:address":"Schoolstraat 6",
    "sg:city":"Pannerden",
    "sg:classifiers":[
        {
            "category":"Fast Food",
            "type":"Food & Drink"
        }
    ],
    "sg:phone":"+31 316 371 770",
    "sg:postcode":"6911 AZ",
    "sg:province":"Gelderland",
    "sg:tags":[
        "afhaal",
        "restaurant"
    ],
    "wof:name":"Vof Janssen",
    "wof:placetype":"venue"
},
  "geometry": {"coordinates":[6.039419,51.888245],"type":"Point"}
}