{
  "type": "Feature",
  "properties": {
    "iso:country":"NL",
    "sg:address":"Patryzenwg 11",
    "sg:city":"Callantsoog",
    "sg:orig_category":"Verhuur",
    "sg:phone":"+31 224 582 949",
    "sg:postcode":"1759 GD",
    "sg:province":"Noord-Holland",
    "wof:name":"Alpaca Bv",
    "wof:placetype":"venue"
},
  "geometry": {"coordinates":[4.698209,52.837795],"type":"Point"}
}