{
  "type": "Feature",
  "properties": {
    "addr:full":"Rigelhof 14 Dordrecht South Holland 3318 CZ",
    "addr:housenumber":"14",
    "addr:postcode":"3318",
    "addr:street":"Rigelhof",
    "iso:country":"NL",
    "sg:address":"Rigelhof 14",
    "sg:city":"Dordrecht",
    "sg:orig_category":"Vertaal- And Tolkenbureaus",
    "sg:phone":"+31 78 618 3998",
    "sg:postcode":"3318 CZ",
    "sg:province":"South Holland",
    "wof:name":"Van Beers & Kooijmans Vof",
    "wof:placetype":"venue"
},
  "geometry": {"coordinates":[4.680258,51.786568],"type":"Point"}
}