{
  "type": "Feature",
  "properties": {
    "iso:country":"NL",
    "sg:address":"Vervul 1A",
    "sg:city":"Rysbergen",
    "sg:orig_category":"Graszoden",
    "sg:phone":"+31 76 596 2736",
    "sg:postcode":"4891 SW",
    "sg:province":"North Brabant",
    "sg:website":"http://www.heidehoeve.com",
    "wof:name":"Heidehoeve Graszodenkwekerij Bv",
    "wof:placetype":"venue"
},
  "geometry": {"coordinates":[4.681196,51.5355],"type":"Point"}
}