{
  "type": "Feature",
  "properties": {
    "iso:country":"NL",
    "sg:address":"Meervalweg 87",
    "sg:city":"Landsmeer",
    "sg:orig_category":"Schilderwerk",
    "sg:phone":"+31 20 482 3558",
    "sg:postcode":"1121 LB",
    "sg:province":"Noord-Holland",
    "wof:name":"Schildersbedrijf Huisman",
    "wof:placetype":"venue"
},
  "geometry": {"coordinates":[4.903133,52.429001],"type":"Point"}
}