{
  "type": "Feature",
  "properties": {
    "addr:full":"Opwg 86 Schoonhoven Zuid-Holland 2871 NG",
    "addr:housenumber":"86",
    "addr:postcode":"2871 ng",
    "addr:street":"Opwg",
    "iso:country":"NL",
    "sg:address":"Opwg 86",
    "sg:city":"Schoonhoven",
    "sg:orig_category":"Administratie- En Boekhoudkantoren",
    "sg:phone":"+31 182 381 010",
    "sg:postcode":"2871 NG",
    "sg:province":"Zuid-Holland",
    "wof:name":"Boom",
    "wof:placetype":"venue"
},
  "geometry": {"coordinates":[4.845359,51.956051],"type":"Point"}
}