{
  "type": "Feature",
  "properties": {
    "iso:country":"NL",
    "sg:address":"Munnikenhof 17",
    "sg:city":"Ede Gld",
    "sg:orig_category":"Verenigingsgebouwen",
    "sg:phone":"+31 318 625 507",
    "sg:postcode":"6715 EC",
    "sg:province":"Gelderland",
    "wof:name":"Velder, Sticht De",
    "wof:placetype":"venue"
},
  "geometry": {"coordinates":[5.633318,52.042068],"type":"Point"}
}