{
  "type": "Feature",
  "properties": {
    "addr:full":"Munnikenhof 17 Ede Gld Gelderland 6715 EC",
    "addr:housenumber":"17",
    "addr:postcode":"6715 ec",
    "addr:street":"Munnikenhof;Gld Gelderland",
    "iso:country":"NL",
    "sg:address":"Munnikenhof 17",
    "sg:city":"Ede Gld",
    "sg:orig_category":"Verenigingsgebouwen",
    "sg:phone":"+31 318 625 507",
    "sg:postcode":"6715 EC",
    "sg:province":"Gelderland",
    "wof:name":"Velder, Sticht De",
    "wof:placetype":"venue"
},
  "geometry": {"coordinates":[5.633318,52.042068],"type":"Point"}
}