{
  "type": "Feature",
  "properties": {
    "iso:country":"NL",
    "sg:address":"Binnenwg 167",
    "sg:city":"Heemstede",
    "sg:orig_category":"Boeken En Tijdschriften",
    "sg:phone":"+31 23 529 2772",
    "sg:postcode":"2101 JH",
    "sg:province":"Noord-Holland",
    "sg:website":"http://www.bruna.nl",
    "wof:name":"Bruna",
    "wof:placetype":"venue"
},
  "geometry": {"coordinates":[4.620865,52.354935],"type":"Point"}
}