{
  "type": "Feature",
  "properties": {
    "iso:country":"NL",
    "sg:address":"Kerkeland 3",
    "sg:city":"Druten",
    "sg:orig_category":"Woningbouwverenigingen",
    "sg:phone":"+31 487 581 820",
    "sg:postcode":"6651 KN",
    "sg:province":"Gelderland",
    "wof:name":"Woningstichting Dr. Alphons Ariens",
    "wof:placetype":"venue"
},
  "geometry": {"coordinates":[5.615114212,51.8880996704],"type":"Point"}
}