{
  "type": "Feature",
  "properties": {
    "addr:full":"Vordensewg 50 Hengelo Gelderland 7255 BX",
    "addr:housenumber":"50",
    "addr:postcode":"7255 bx",
    "addr:street":"Vordensewg;Gelderland",
    "iso:country":"NL",
    "sg:address":"Vordensewg 50",
    "sg:city":"Hengelo",
    "sg:orig_category":"Meubelen - Fabrieken En Groothandel",
    "sg:phone":"+31 575 461 481",
    "sg:postcode":"7255 BX",
    "sg:province":"Gelderland",
    "wof:name":"Lenselink Bv",
    "wof:placetype":"venue"
},
  "geometry": {"coordinates":[6.306012,52.057652],"type":"Point"}
}