{
  "type": "Feature",
  "properties": {
    "addr:full":"Groningerstr 16014 Deventer NL.08 7418 BX",
    "addr:postcode":"16014;nl.08 7418 bx",
    "addr:street":"Groningerstr",
    "iso:country":"NL",
    "sg:address":"Groningerstr 16014",
    "sg:city":"Deventer",
    "sg:orig_category":"Bewakingsdiensten",
    "sg:phone":"+31 570 623 800",
    "sg:postcode":"7418 BX",
    "sg:province":"NL.08",
    "sg:website":"http://www.pereboomteam.nl",
    "wof:name":"Pereboom Beveiliging/Bewaking Bv",
    "wof:placetype":"venue"
},
  "geometry": {"coordinates":[6.174668,52.252373],"type":"Point"}
}