{
  "type": "Feature",
  "properties": {
    "iso:country":"NL",
    "sg:address":"L Brugstr 39",
    "sg:city":"Breda",
    "sg:orig_category":"Verlichting",
    "sg:phone":"+31 76 521 2821",
    "sg:postcode":"4811 WP",
    "sg:province":"Noord-Brabant",
    "wof:name":"Lampenier",
    "wof:placetype":"venue"
},
  "geometry": {"coordinates":[4.773355,51.58799],"type":"Point"}
}