{
  "type": "Feature",
  "properties": {
    "addr:full":"Amersfoortsestr 23 Amersfoort Utrecht 3821 CA",
    "addr:housenumber":"23",
    "addr:postcode":"3821 ca",
    "addr:street":"Amersfoortsestr",
    "iso:country":"NL",
    "sg:address":"Amersfoortsestr 23",
    "sg:city":"Amersfoort",
    "sg:orig_category":"Woninginrichting- Fournituren - Fabrieken En Groothandel",
    "sg:phone":"+31 33 253 7000",
    "sg:postcode":"3821 CA",
    "sg:province":"Utrecht",
    "wof:name":"Suk-7",
    "wof:placetype":"venue"
},
  "geometry": {"coordinates":[5.4351530075,52.1706466675],"type":"Point"}
}