{
  "type": "Feature",
  "properties": {
    "addr:full":"Marswg 3 Zwolle NL.08 8013 PD",
    "addr:housenumber":"3",
    "addr:postcode":"8013 pd",
    "addr:street":"Marswg",
    "iso:country":"NL",
    "sg:address":"Marswg 3",
    "sg:city":"Zwolle",
    "sg:orig_category":"Vaten - Fabrieken En Groothandel",
    "sg:phone":"+31 38 421 8991",
    "sg:postcode":"8013 PD",
    "sg:province":"NL.08",
    "wof:name":"Blagden Packaging Zwolle Bv",
    "wof:placetype":"venue"
},
  "geometry": {"coordinates":[6.12153,52.501232],"type":"Point"}
}