{
  "type": "Feature",
  "properties": {
    "iso:country":"NL",
    "sg:address":"Cranendonckweg 40",
    "sg:city":"Rotterdam",
    "sg:orig_category":"Overheidsdiensten",
    "sg:phone":"+31 10 482 7401",
    "sg:postcode":"3077 LA",
    "sg:province":"South Holland",
    "wof:name":"De Magneet Ijsselmonde",
    "wof:placetype":"venue"
},
  "geometry": {"coordinates":[4.5514569283,51.9002723694],"type":"Point"}
}