{
  "type": "Feature",
  "properties": {
    "addr:full":"Charleroistraat 180 Breda North Brabant 4826 LP",
    "addr:housenumber":"180",
    "addr:postcode":"4826 lp",
    "addr:street":"Charleroistraat",
    "iso:country":"NL",
    "sg:address":"Charleroistraat 180",
    "sg:city":"Breda",
    "sg:classifiers":[
        {
            "category":"Fast Food",
            "type":"Food & Drink"
        }
    ],
    "sg:phone":"+31 76 587 4468",
    "sg:postcode":"4826 LP",
    "sg:province":"North Brabant",
    "sg:tags":[
        "afhaal",
        "restaurant"
    ],
    "wof:name":"Cafetaria Jenny",
    "wof:placetype":"venue"
},
  "geometry": {"coordinates":[4.781636,51.605385],"type":"Point"}
}