{
  "type": "Feature",
  "properties": {
    "addr:full":"Wijksestraat 10 B Wijk En Aalburg Noord-Brabant 4261 TT",
    "addr:housenumber":"10 b",
    "addr:postcode":"4261 tt",
    "addr:street":"Wijksestraat",
    "iso:country":"NL",
    "sg:address":"Wijksestraat 10 B",
    "sg:city":"Wijk En Aalburg",
    "sg:orig_category":"Bloemen And Planten",
    "sg:phone":"+31 416 692 384",
    "sg:postcode":"4261 TT",
    "sg:province":"Noord-Brabant",
    "wof:name":"Tuincentrum A. & P. Smulders",
    "wof:placetype":"venue"
},
  "geometry": {"coordinates":[5.117417,51.764439],"type":"Point"}
}