{
  "type": "Feature",
  "properties": {
    "addr:full":"Drostewg 6 Saasveld Overijssel 7597 MG",
    "addr:housenumber":"6",
    "addr:postcode":"7597 mg",
    "addr:street":"Drostewg",
    "iso:country":"NL",
    "sg:address":"Drostewg 6",
    "sg:city":"Saasveld",
    "sg:orig_category":"Meubelstoffering",
    "sg:phone":"+31 74 349 4551",
    "sg:postcode":"7597 MG",
    "sg:province":"Overijssel",
    "wof:name":"Ruepert Saasveld",
    "wof:placetype":"venue"
},
  "geometry": {"coordinates":[6.807968,52.333771],"type":"Point"}
}