{
  "type": "Feature",
  "properties": {
    "addr:full":"Bijlmerplein 860 Amsterdam Zuidoost Noord-Holland 1102 ME",
    "addr:housenumber":"860",
    "addr:postcode":"zuidoost;1102 me",
    "addr:street":"Bijlmerplein",
    "iso:country":"NL",
    "sg:address":"Bijlmerplein 860",
    "sg:city":"Amsterdam Zuidoost",
    "sg:orig_category":"Kappers",
    "sg:phone":"+31 20 696 1715",
    "sg:postcode":"1102 ME",
    "sg:province":"Noord-Holland",
    "wof:name":"J. Limp",
    "wof:placetype":"venue"
},
  "geometry": {"coordinates":[4.9545311928,52.313621521],"type":"Point"}
}