{
  "type": "Feature",
  "properties": {
    "addr:full":"Herengracht 539 Amsterdam Noord-Holland 1017 BW",
    "addr:housenumber":"539",
    "addr:postcode":"1017 bw",
    "addr:street":"Herengracht",
    "iso:country":"NL",
    "sg:address":"Herengracht 539",
    "sg:city":"Amsterdam",
    "sg:orig_category":"Banken And Kredietinstellingen",
    "sg:phone":"+31 20 520 4911",
    "sg:postcode":"1017 BW",
    "sg:province":"Noord-Holland",
    "wof:name":"Banque Artesia Nederland Nv",
    "wof:placetype":"venue"
},
  "geometry": {"coordinates":[4.894321,52.365273],"type":"Point"}
}