{
  "type": "Feature",
  "properties": {
    "addr:full":"B De Waalstr 55 Utrecht Utrecht 3555 BH",
    "addr:housenumber":"55",
    "addr:postcode":"3555 bh",
    "addr:street":"B",
    "iso:country":"NL",
    "sg:address":"B De Waalstr 55",
    "sg:city":"Utrecht",
    "sg:orig_category":"Voetbalverenigingen",
    "sg:phone":"+31 30 243 7724",
    "sg:postcode":"3555 BH",
    "sg:province":"Utrecht",
    "wof:name":"Dennis Boys",
    "wof:placetype":"venue"
},
  "geometry": {"coordinates":[5.083164,52.114502],"type":"Point"}
}