{
  "type": "Feature",
  "properties": {
    "iso:country":"NL",
    "sg:address":"Stationsstraat",
    "sg:city":"Ermelo",
    "sg:orig_category":"Winkelcentra",
    "sg:phone":"+31 136",
    "sg:postcode":"3851 NB",
    "sg:province":"Gelderland",
    "wof:name":"Ermelo Binnenstad",
    "wof:placetype":"venue"
},
  "geometry": {"coordinates":[5.629609108,52.3008155823],"type":"Point"}
}