{
  "type": "Feature",
  "properties": {
    "iso:country":"NL",
    "sg:address":"Postbus 17120",
    "sg:city":"S Gravenhage",
    "sg:orig_category":"Scholen Voor Basisonderwijs",
    "sg:phone":"+31 70 355 3805",
    "sg:postcode":"2502 CC",
    "wof:name":"Statenkwartier Interconf",
    "wof:placetype":"venue"
},
  "geometry": {"coordinates":[4.31361,52.07832],"type":"Point"}
}