{
  "type": "Feature",
  "properties": {
    "addr:full":"Straatwg 25 Breukelen Ut Utrecht 3621 BG",
    "addr:housenumber":"25",
    "addr:postcode":"3621",
    "addr:street":"Straatwg",
    "iso:country":"NL",
    "sg:address":"Straatwg 25",
    "sg:city":"Breukelen Ut",
    "sg:orig_category":"Onderzoekbureaus",
    "sg:phone":"+31 346 291 290",
    "sg:postcode":"3621 BG",
    "sg:province":"Utrecht",
    "wof:name":"Eibe Inst Of Responsible Business",
    "wof:placetype":"venue"
},
  "geometry": {"coordinates":[5.00913,52.165909],"type":"Point"}
}