{
  "type": "Feature",
  "properties": {
    "addr:full":"Regulierenring 14 Bunnik Utrecht 3981 LB",
    "addr:housenumber":"14",
    "addr:postcode":"3981 lb",
    "addr:street":"Regulierenring",
    "iso:country":"NL",
    "sg:address":"Regulierenring 14",
    "sg:city":"Bunnik",
    "sg:orig_category":"Adviesbureaus",
    "sg:phone":"+31 30 657 2444",
    "sg:postcode":"3981 LB",
    "sg:province":"Utrecht",
    "wof:name":"Happy Service",
    "wof:placetype":"venue"
},
  "geometry": {"coordinates":[5.189015,52.064178],"type":"Point"}
}