{
  "type": "Feature",
  "properties": {
    "addr:full":"Valkstr 14 Sittard Limburg 6135 GC",
    "addr:housenumber":"14",
    "addr:postcode":"6135 gc",
    "addr:street":"Valkstr",
    "iso:country":"NL",
    "sg:address":"Valkstr 14",
    "sg:city":"Sittard",
    "sg:orig_category":"Kabelexploitanten",
    "sg:phone":"+31 43 855 8888",
    "sg:postcode":"6135 GC",
    "sg:province":"Limburg",
    "sg:website":"http://www.essent.nl",
    "wof:name":"Essent Kabelcom Bv",
    "wof:placetype":"venue"
},
  "geometry": {"coordinates":[5.8474640846,51.005191803],"type":"Point"}
}