{
  "type": "Feature",
  "properties": {
    "addr:full":"Salomonszegel 41 Apeldoorn Gelderland 7322 EP",
    "addr:housenumber":"41",
    "addr:postcode":"7322 ep",
    "addr:street":"Salomonszegel;Gelderland",
    "iso:country":"NL",
    "sg:address":"Salomonszegel 41",
    "sg:city":"Apeldoorn",
    "sg:orig_category":"Bedrijfshuisvesting",
    "sg:phone":"+31 55 367 1401",
    "sg:postcode":"7322 EP",
    "sg:province":"Gelderland",
    "wof:name":"Gotz",
    "wof:placetype":"venue"
},
  "geometry": {"coordinates":[5.98562,52.226768],"type":"Point"}
}