{
  "type": "Feature",
  "properties": {
    "iso:country":"NL",
    "sg:address":"De Wieken 13",
    "sg:city":"Limmen",
    "sg:orig_category":"Adviesbureaus Bedrijfsorganisatie",
    "sg:phone":"+31 6 10884938",
    "sg:postcode":"1906 DA",
    "sg:province":"Noord-Holland",
    "wof:name":"Casalou",
    "wof:placetype":"venue"
},
  "geometry": {"coordinates":[4.688774,52.571129],"type":"Point"}
}