{
  "type": "Feature",
  "properties": {
    "addr:full":"Villapk 17 Geldrop Noord-Brabant 5667 HW",
    "addr:housenumber":"17",
    "addr:postcode":"5667 hw",
    "addr:street":"Villapk",
    "iso:country":"NL",
    "sg:address":"Villapk 17",
    "sg:city":"Geldrop",
    "sg:orig_category":"Beeldende Kunstenaars",
    "sg:phone":"+31 40 285 3705",
    "sg:postcode":"5667 HW",
    "sg:province":"Noord-Brabant",
    "wof:name":"Bazelmans, F?",
    "wof:placetype":"venue"
},
  "geometry": {"coordinates":[5.572463,51.432808],"type":"Point"}
}