{
  "type": "Feature",
  "properties": {
    "addr:full":"Aeoluswg 91 De Bilt Utrecht 3731 XD",
    "addr:housenumber":"91",
    "addr:postcode":"3731 xd",
    "addr:street":"Aeoluswg",
    "iso:country":"NL",
    "sg:address":"Aeoluswg 91",
    "sg:city":"De Bilt",
    "sg:orig_category":"Verhuur Audiovisuele Apparatuur",
    "sg:phone":"+31 30 221 3046",
    "sg:postcode":"3731 XD",
    "sg:province":"Utrecht",
    "wof:name":"Miquelangelo",
    "wof:placetype":"venue"
},
  "geometry": {"coordinates":[5.179827,52.111835],"type":"Point"}
}