{
  "type": "Feature",
  "properties": {
    "iso:country":"NL",
    "sg:address":"Sandenburg 155",
    "sg:city":"Haarlem",
    "sg:orig_category":"Parkeersystemen",
    "sg:phone":"+31 23 533 1133",
    "sg:postcode":"2036 PC",
    "sg:province":"Noord-Holland",
    "wof:name":"Parkeren Met Systeem Bv",
    "wof:placetype":"venue"
},
  "geometry": {"coordinates":[4.65204,52.349682],"type":"Point"}
}