{
  "type": "Feature",
  "properties": {
    "addr:full":"Aresstr 13 Tilburg Noord-Brabant 5048 CD",
    "addr:housenumber":"13",
    "addr:postcode":"5048 cd",
    "addr:street":"Aresstr",
    "iso:country":"NL",
    "sg:address":"Aresstr 13",
    "sg:city":"Tilburg",
    "sg:orig_category":"Elektrotechnische Installatiebureaus",
    "sg:phone":"+31 13 572 1878",
    "sg:postcode":"5048 CD",
    "sg:province":"Noord-Brabant",
    "wof:name":"Blankers Bv",
    "wof:placetype":"venue"
},
  "geometry": {"coordinates":[5.027452,51.594883],"type":"Point"}
}