{
  "type": "Feature",
  "properties": {
    "iso:country":"NL",
    "sg:address":"De Compagnie 49",
    "sg:city":"Zwaag",
    "sg:orig_category":"Autoverhuur",
    "sg:phone":"+31 229 244 340",
    "sg:postcode":"1689 AG",
    "sg:province":"Noord-Holland",
    "sg:website":"http://www.bertjonk.nl",
    "wof:name":"Bert Jonk",
    "wof:placetype":"venue"
},
  "geometry": {"coordinates":[5.057372,52.66988],"type":"Point"}
}