{
  "type": "Feature",
  "properties": {
    "iso:country":"NL",
    "sg:address":"J G Sandbrinkstraat 39",
    "sg:city":"Veenendaal",
    "sg:orig_category":"Opticiens",
    "sg:phone":"+31 318 540 288",
    "sg:postcode":"3901 EX",
    "sg:province":"Utrecht",
    "wof:name":"Hans Anders Opticiens",
    "wof:placetype":"venue"
},
  "geometry": {"coordinates":[5.5562901497,52.0238418579],"type":"Point"}
}