{
  "type": "Feature",
  "properties": {
    "addr:full":"Stationsweg 124 'S Gravenhage South Holland 2515 BR",
    "addr:housenumber":"124 '",
    "addr:postcode":"2515 br",
    "addr:street":"Stationsweg",
    "iso:country":"NL",
    "sg:address":"Stationsweg 124",
    "sg:city":"'S Gravenhage",
    "sg:orig_category":"Diverse Bedrijfsinstallaties Gh",
    "sg:phone":"+31 70 384 1061",
    "sg:postcode":"2515 BR",
    "sg:province":"South Holland",
    "wof:name":"Eurosel",
    "wof:placetype":"venue"
},
  "geometry": {"coordinates":[4.320688,52.071812],"type":"Point"}
}