{
  "type": "Feature",
  "properties": {
    "addr:full":"Lindenln 71A Amstelveen Noord-Holland 1185 LC",
    "addr:housenumber":"71a",
    "addr:postcode":"1185 lc",
    "addr:street":"Lindenln",
    "iso:country":"NL",
    "sg:address":"Lindenln 71A",
    "sg:city":"Amstelveen",
    "sg:orig_category":"Bloemen En Planten",
    "sg:phone":"+31 20 641 4857",
    "sg:postcode":"1185 LC",
    "sg:province":"Noord-Holland",
    "wof:name":"Flowers & Dreams",
    "wof:placetype":"venue"
},
  "geometry": {"coordinates":[4.849806,52.293999],"type":"Point"}
}