{
  "type": "Feature",
  "properties": {
    "addr:full":"Buizerdstraat 9 Zwartsluis Overijssel 8064 CN",
    "addr:housenumber":"9",
    "addr:postcode":"8064 cn",
    "addr:street":"Buizerdstraat",
    "iso:country":"NL",
    "sg:address":"Buizerdstraat 9",
    "sg:city":"Zwartsluis",
    "sg:orig_category":"Onderhoud And Reparatie Kantoorapparatuur",
    "sg:phone":"+31 38 386 8506",
    "sg:postcode":"8064 CN",
    "sg:province":"Overijssel",
    "wof:name":"Brouwer Computer Service",
    "wof:placetype":"venue"
},
  "geometry": {"coordinates":[6.070704937,52.6435279846],"type":"Point"}
}