{
  "type": "Feature",
  "properties": {
    "iso:country":"NL",
    "sg:address":"Molenwg 8",
    "sg:city":"Middenmeer",
    "sg:orig_category":"Bloembollen - Groothandel",
    "sg:phone":"+31 227 577 378",
    "sg:postcode":"1775 NX",
    "sg:province":"North Holland",
    "wof:name":"Verbruggen, Fa M N",
    "wof:placetype":"venue"
},
  "geometry": {"coordinates":[4.973841,52.810406],"type":"Point"}
}