{
  "type": "Feature",
  "properties": {
    "addr:full":"Businesspark Friesland-W 35 Nijehaske Friesland 8466 SL",
    "addr:housenumber":"35",
    "addr:postcode":"8466 sl",
    "iso:country":"NL",
    "sg:address":"Businesspark Friesland-W 35",
    "sg:city":"Nijehaske",
    "sg:orig_category":"Beveiliging",
    "sg:phone":"+31 513 645 686",
    "sg:postcode":"8466 SL",
    "sg:province":"Friesland",
    "wof:name":"Quick Security Bv",
    "wof:placetype":"venue"
},
  "geometry": {"coordinates":[5.890971,52.964153],"type":"Point"}
}