{
  "type": "Feature",
  "properties": {
    "addr:full":"Idsingha 12 Veenwouden Provincie Friesland 9269 VJ",
    "addr:housenumber":"12",
    "addr:postcode":"9269 vj",
    "addr:street":"Idsingha;Provincie Friesland",
    "iso:country":"NL",
    "sg:address":"Idsingha 12",
    "sg:city":"Veenwouden",
    "sg:orig_category":"Woningstoffeerders",
    "sg:phone":"+31 511 474 401",
    "sg:postcode":"9269 VJ",
    "sg:province":"Provincie Friesland",
    "wof:name":"Tijsma",
    "wof:placetype":"venue"
},
  "geometry": {"coordinates":[5.9831709862,53.2386436462],"type":"Point"}
}