{
  "type": "Feature",
  "properties": {
    "iso:country":"NL",
    "sg:address":"Ferdinand Bolstraat 168",
    "sg:city":"Amsterdam",
    "sg:orig_category":"Fietshandelaren",
    "sg:phone":"+31 20 673 7026",
    "sg:postcode":"1072 LT",
    "sg:province":"Noord-Holland",
    "wof:name":"Zijwind",
    "wof:placetype":"venue"
},
  "geometry": {"coordinates":[4.89114,52.351768],"type":"Point"}
}