{
  "type": "Feature",
  "properties": {
    "addr:full":"Konynenberg 53 Breda Noord-Brabant 4825 BC",
    "addr:housenumber":"53",
    "addr:postcode":"4825 bc",
    "addr:street":"Konynenberg",
    "iso:country":"NL",
    "sg:address":"Konynenberg 53",
    "sg:city":"Breda",
    "sg:orig_category":"Koeltechniek",
    "sg:phone":"+31 76 572 0220",
    "sg:postcode":"4825 BC",
    "sg:province":"Noord-Brabant",
    "sg:website":"http://www.deltatechnics.nl",
    "wof:name":"Delta Bv",
    "wof:placetype":"venue"
},
  "geometry": {"coordinates":[4.76852,51.611752],"type":"Point"}
}