{
  "type": "Feature",
  "properties": {
    "iso:country":"NL",
    "sg:address":"Laone 20",
    "sg:city":"Renesse",
    "sg:orig_category":"Bloemen And Planten",
    "sg:phone":"+31 111 461 031",
    "sg:postcode":"4325 EL",
    "sg:province":"Zeeland",
    "wof:name":"Europatuin Renesse",
    "wof:placetype":"venue"
},
  "geometry": {"coordinates":[3.784255,51.739559],"type":"Point"}
}