{
  "type": "Feature",
  "properties": {
    "addr:full":"Dwergkonijnstraat 2 Almere Flevoland 1338 AJ",
    "addr:housenumber":"2",
    "addr:postcode":"1338 aj",
    "addr:street":"Dwergkonijnstraat;Flevoland",
    "iso:country":"NL",
    "sg:address":"Dwergkonijnstraat 2",
    "sg:city":"Almere",
    "sg:orig_category":"Kinderopvang Behalve Thuis",
    "sg:phone":"+31 36 537 0245",
    "sg:postcode":"1338 AJ",
    "sg:province":"Flevoland",
    "wof:name":"Kinderdagverblijf De Kleine Reus",
    "wof:placetype":"venue"
},
  "geometry": {"coordinates":[5.275917,52.390663],"type":"Point"}
}