{
  "type": "Feature",
  "properties": {
    "addr:full":"Haaghuishof 19 Leiderdorp Zuid-Holland 2352 SW",
    "addr:housenumber":"19;2352",
    "addr:street":"Haaghuishof;Sw",
    "iso:country":"NL",
    "sg:address":"Haaghuishof 19",
    "sg:city":"Leiderdorp",
    "sg:orig_category":"Elektronische Bedrijfsinstallaties",
    "sg:phone":"+31 71 589 8998",
    "sg:postcode":"2352 SW",
    "sg:province":"Zuid-Holland",
    "wof:name":"Art Control Lifttechniek",
    "wof:placetype":"venue"
},
  "geometry": {"coordinates":[4.521662,52.157227],"type":"Point"}
}