{
  "type": "Feature",
  "properties": {
    "addr:full":"Gabrielstr 70 Ursem Noord-Holland 1645 ST",
    "addr:housenumber":"70;1645",
    "addr:postcode":"st",
    "addr:street":"Gabrielstr",
    "iso:country":"NL",
    "sg:address":"Gabrielstr 70",
    "sg:city":"Ursem",
    "sg:orig_category":"Schilders",
    "sg:phone":"+31 72 502 2053",
    "sg:postcode":"1645 ST",
    "sg:province":"Noord-Holland",
    "wof:name":"Humphrey Mercera",
    "wof:placetype":"venue"
},
  "geometry": {"coordinates":[4.897426,52.630096],"type":"Point"}
}