{
  "type": "Feature",
  "properties": {
    "addr:full":"W V Kesselstr 112 Eindhoven North Brabant 5622 JC",
    "addr:housenumber":"112",
    "addr:postcode":"5622 jc",
    "addr:street":"W V Kesselstr",
    "iso:country":"NL",
    "sg:address":"W V Kesselstr 112",
    "sg:city":"Eindhoven",
    "sg:orig_category":"Koeriersdiensten",
    "sg:phone":"+31 40 245 1473",
    "sg:postcode":"5622 JC",
    "sg:province":"North Brabant",
    "wof:name":"Jsk",
    "wof:placetype":"venue"
},
  "geometry": {"coordinates":[5.46291,51.459381],"type":"Point"}
}