{
  "type": "Feature",
  "properties": {
    "addr:full":"Amstelstr 71A Utrecht Utrecht 3522 CM",
    "addr:housenumber":"71a",
    "addr:postcode":"3522 cm",
    "addr:street":"Amstelstr",
    "iso:country":"NL",
    "sg:address":"Amstelstr 71A",
    "sg:city":"Utrecht",
    "sg:orig_category":"Verenigingen En Stichtingen",
    "sg:phone":"+31 30 271 0354",
    "sg:postcode":"3522 CM",
    "sg:province":"Utrecht",
    "wof:name":"Sbwu Bw Rivierenwijk",
    "wof:placetype":"venue"
},
  "geometry": {"coordinates":[5.114134,52.073051],"type":"Point"}
}