{
  "type": "Feature",
  "properties": {
    "iso:country":"NL",
    "sg:address":"Kolkgriend 99",
    "sg:city":"Almere",
    "sg:orig_category":"Adviesbureaus Bouwkunde",
    "sg:phone":"+31 36 531 5327",
    "sg:postcode":"1356 BH",
    "sg:province":"Flevoland",
    "wof:name":"Doeldesign",
    "wof:placetype":"venue"
},
  "geometry": {"coordinates":[5.236624,52.337044],"type":"Point"}
}