{
  "type": "Feature",
  "properties": {
    "iso:country":"NL",
    "sg:address":"Bekerbaan 33A",
    "sg:city":"Schimmert",
    "sg:orig_category":"Juridische Adviseurs",
    "sg:phone":"+31 45 404 2441",
    "sg:postcode":"6333 EJ",
    "sg:province":"Limburg",
    "wof:name":"Severeyns-Wijenbergh Jur Adv Buro",
    "wof:placetype":"venue"
},
  "geometry": {"coordinates":[5.819766,50.901962],"type":"Point"}
}