{
  "type": "Feature",
  "properties": {
    "addr:full":"Molenwei 2 Best Noord-Brabant 5683 DZ",
    "addr:housenumber":"2",
    "addr:postcode":"5683 dz",
    "addr:street":"Molenwei",
    "iso:country":"NL",
    "sg:address":"Molenwei 2",
    "sg:city":"Best",
    "sg:orig_category":"Woningbouw- Verenigingen En -Stichtingen",
    "sg:phone":"+31 499 397 691",
    "sg:postcode":"5683 DZ",
    "sg:province":"Noord-Brabant",
    "wof:name":"Voorzorg, Woningsticht",
    "wof:placetype":"venue"
},
  "geometry": {"coordinates":[-101.45208740229999,31.1912746429],"type":"Point"}
}