{
  "type": "Feature",
  "properties": {
    "addr:full":"Gerestr 17 Heesselt Gelderland 4063 CN",
    "addr:housenumber":"17",
    "addr:postcode":"4063 cn",
    "addr:street":"Gerestr;Gelderland",
    "iso:country":"NL",
    "sg:address":"Gerestr 17",
    "sg:city":"Heesselt",
    "sg:orig_category":"Kunststof Ramen",
    "sg:phone":"+31 344 652 234",
    "sg:postcode":"4063 CN",
    "sg:province":"Gelderland",
    "wof:name":"Veka Verkoopkantoor Nederland",
    "wof:placetype":"venue"
},
  "geometry": {"coordinates":[5.352247,51.815311],"type":"Point"}
}