{
  "type": "Feature",
  "properties": {
    "addr:full":"Broekheurnerwg 69 Enschede Overijssel 7513 EP",
    "addr:housenumber":"69",
    "addr:postcode":"7513 ep",
    "addr:street":"Broekheurnerwg",
    "iso:country":"NL",
    "sg:address":"Broekheurnerwg 69",
    "sg:city":"Enschede",
    "sg:orig_category":"Verhuizingen",
    "sg:phone":"+31 53 431 5454",
    "sg:postcode":"7513 EP",
    "sg:province":"Overijssel",
    "wof:name":"Centrum Verhuisbedrijf",
    "wof:placetype":"venue"
},
  "geometry": {"coordinates":[6.882952,52.211597],"type":"Point"}
}