{
  "type": "Feature",
  "properties": {
    "iso:country":"NL",
    "sg:address":"Mansel 75",
    "sg:city":"Sneek",
    "sg:orig_category":"Gespecialiseerde Voeding",
    "sg:phone":"+31 515 422 251",
    "sg:postcode":"8603 DX",
    "sg:province":"Friesland",
    "wof:name":"W.J.M. Scheffer",
    "wof:placetype":"venue"
},
  "geometry": {"coordinates":[5.669812,53.045235],"type":"Point"}
}