{
  "type": "Feature",
  "properties": {
    "addr:full":"Guyotte V Ijsselsteinln 25 Egmond A/D Hoef North Holland 1934 GM",
    "addr:housenumber":"25",
    "addr:postcode":"1934 gm",
    "addr:street":"Ijsselsteinln",
    "iso:country":"NL",
    "sg:address":"Guyotte V Ijsselsteinln 25",
    "sg:city":"Egmond A/D Hoef",
    "sg:orig_category":"Autokeuringen",
    "sg:phone":"+31 72 506 1808",
    "sg:postcode":"1934 GM",
    "sg:province":"North Holland",
    "wof:name":"Rs Janssen",
    "wof:placetype":"venue"
},
  "geometry": {"coordinates":[4.650513,52.62249],"type":"Point"}
}