{
  "type": "Feature",
  "properties": {
    "addr:full":"R Claeszenstr 94 Amsterdam Noord-Holland 1056 WS",
    "addr:housenumber":"94",
    "addr:postcode":"1056 ws",
    "iso:country":"NL",
    "sg:address":"R Claeszenstr 94",
    "sg:city":"Amsterdam",
    "sg:orig_category":"Koeriersdiensten",
    "sg:phone":"+31 20 618 2545",
    "sg:postcode":"1056 WS",
    "sg:province":"Noord-Holland",
    "wof:name":"Alanski",
    "wof:placetype":"venue"
},
  "geometry": {"coordinates":[4.862213,52.373947],"type":"Point"}
}