{
  "type": "Feature",
  "properties": {
    "addr:full":"Donkenwg 19 Wouw North Brabant 4724 SN",
    "addr:housenumber":"19",
    "addr:postcode":"4724 sn",
    "addr:street":"Donkenwg",
    "iso:country":"NL",
    "sg:address":"Donkenwg 19",
    "sg:city":"Wouw",
    "sg:orig_category":"Kunststoffen- Verwerkende Industrie",
    "sg:phone":"+31 165 301 275",
    "sg:postcode":"4724 SN",
    "sg:province":"North Brabant",
    "wof:name":"Schuerman Bv",
    "wof:placetype":"venue"
},
  "geometry": {"coordinates":[4.390443,51.526985],"type":"Point"}
}