{
  "type": "Feature",
  "properties": {
    "addr:full":"J V Twickelostr 5 Raalte NL.08 8101 EW",
    "addr:housenumber":"5;nl.08",
    "addr:postcode":"8101 ew",
    "addr:street":"J;Twickelostr",
    "iso:country":"NL",
    "sg:address":"J V Twickelostr 5",
    "sg:city":"Raalte",
    "sg:orig_category":"Onderhoudswerken",
    "sg:phone":"+31 800 1605",
    "sg:postcode":"8101 EW",
    "sg:province":"NL.08",
    "wof:name":"Vakklusser, De",
    "wof:placetype":"venue"
},
  "geometry": {"coordinates":[6.274628,52.387249],"type":"Point"}
}