{
  "type": "Feature",
  "properties": {
    "addr:full":"Fruitweg 268 'S Gravenhage Zuid-Holland 2525 KJ",
    "addr:housenumber":"268 '",
    "addr:postcode":"2525 kj",
    "addr:street":"Fruitweg",
    "iso:country":"NL",
    "sg:address":"Fruitweg 268",
    "sg:city":"'S Gravenhage",
    "sg:orig_category":"Technische Studies And Onderzoek",
    "sg:phone":"+31 70 402 0100",
    "sg:postcode":"2525 KJ",
    "sg:province":"Zuid-Holland",
    "wof:name":"Van Den Berg Transporttechniek",
    "wof:placetype":"venue"
},
  "geometry": {"coordinates":[4.304481,52.057339],"type":"Point"}
}