{
  "type": "Feature",
  "properties": {
    "addr:full":"T Holland 9 Duiven Gelderland 6921 GX",
    "addr:housenumber":"9",
    "addr:postcode":"6921 gx",
    "addr:street":"T Holland;Gelderland",
    "iso:country":"NL",
    "sg:address":"T Holland 9",
    "sg:city":"Duiven",
    "sg:orig_category":"Goederenvervoer Over De Weg",
    "sg:phone":"+31 316 261 425",
    "sg:postcode":"6921 GX",
    "sg:province":"Gelderland",
    "wof:name":"Vof Transportbedrijf Gebr. Steentjes Duiven",
    "wof:placetype":"venue"
},
  "geometry": {"coordinates":[6.025828,51.942432],"type":"Point"}
}