{
  "type": "Feature",
  "properties": {
    "addr:full":"Rechterstr 55 Boxtel Noord-Brabant 5281 BT",
    "addr:housenumber":"55",
    "addr:postcode":"5281 bt",
    "addr:street":"Rechterstr",
    "iso:country":"NL",
    "sg:address":"Rechterstr 55",
    "sg:city":"Boxtel",
    "sg:orig_category":"Natuur- En Milieuorganisaties",
    "sg:phone":"+31 411 614 111",
    "sg:postcode":"5281 BT",
    "sg:province":"Noord-Brabant",
    "wof:name":"Ivn-Consulentschap Brabant",
    "wof:placetype":"venue"
},
  "geometry": {"coordinates":[5.329439,51.587215],"type":"Point"}
}