{
  "type": "Feature",
  "properties": {
    "addr:full":"Kerkstraat 10 Nieuwveen Zuid-Holland 2441 CD",
    "addr:housenumber":"10",
    "addr:postcode":"2441 cd",
    "addr:street":"Kerkstraat",
    "iso:country":"NL",
    "sg:address":"Kerkstraat 10",
    "sg:city":"Nieuwveen",
    "sg:classifiers":[
        {
            "category":"Fast Food",
            "type":"Food & Drink"
        }
    ],
    "sg:phone":"+31 172 537 212",
    "sg:postcode":"2441 CD",
    "sg:province":"Zuid-Holland",
    "sg:tags":[
        "afhaal",
        "restaurant"
    ],
    "wof:name":"Snackbar The Boxx",
    "wof:placetype":"venue"
},
  "geometry": {"coordinates":[4.756752,52.196793],"type":"Point"}
}