{
  "type": "Feature",
  "properties": {
    "iso:country":"NL",
    "sg:address":"Maasdk 23",
    "sg:city":"Nederhemert",
    "sg:orig_category":"Beveiliging",
    "sg:phone":"+31 418 552 682",
    "sg:postcode":"5317 KP",
    "sg:province":"Gelderland",
    "wof:name":"Dommelen Bv, Van",
    "wof:placetype":"venue"
},
  "geometry": {"coordinates":[5.151587,51.763462],"type":"Point"}
}