{
  "type": "Feature",
  "properties": {
    "addr:full":"Z Parallelwg 5 Velp Gld Gelderland 6882 AC",
    "addr:housenumber":"5",
    "addr:postcode":"6882 ac",
    "addr:street":"Gld Gelderland",
    "iso:country":"NL",
    "sg:address":"Z Parallelwg 5",
    "sg:city":"Velp Gld",
    "sg:orig_category":"Onderhoudswerken",
    "sg:phone":"+31 26 363 6196",
    "sg:postcode":"6882 AC",
    "sg:province":"Gelderland",
    "wof:name":"Korendijk",
    "wof:placetype":"venue"
},
  "geometry": {"coordinates":[5.973012,51.993351],"type":"Point"}
}