{
  "type": "Feature",
  "properties": {
    "iso:country":"NL",
    "sg:address":"Looiersweg 3",
    "sg:city":"Alphen Nb",
    "sg:orig_category":"Drukkerijen And Copyshops",
    "sg:phone":"+31 13 508 2245",
    "sg:postcode":"5131 BE",
    "sg:province":"Noord-Brabant",
    "wof:name":"Hdj International Bv",
    "wof:placetype":"venue"
},
  "geometry": {"coordinates":[4.956817,51.477314],"type":"Point"}
}