{
  "type": "Feature",
  "properties": {
    "addr:full":"Stieltjesstraat 2 Rotterdam South Holland 3071 JW",
    "addr:housenumber":"2",
    "addr:postcode":"3071 jw",
    "addr:street":"Stieltjesstraat",
    "iso:country":"NL",
    "sg:address":"Stieltjesstraat 2",
    "sg:city":"Rotterdam",
    "sg:orig_category":"Boekhouders",
    "sg:phone":"+31 10 423 0476",
    "sg:postcode":"3071 JW",
    "sg:province":"South Holland",
    "wof:name":"A & B Consultants",
    "wof:placetype":"venue"
},
  "geometry": {"coordinates":[4.498702,51.911964],"type":"Point"}
}