{
  "type": "Feature",
  "properties": {
    "addr:full":"Touwln 25 Ysselstein Ut Utrecht 3401 CA",
    "addr:housenumber":"25",
    "addr:postcode":"3401 ca",
    "addr:street":"Touwln",
    "iso:country":"NL",
    "sg:address":"Touwln 25",
    "sg:city":"Ysselstein Ut",
    "sg:orig_category":"Podotherapeuten",
    "sg:phone":"+31 30 687 0708",
    "sg:postcode":"3401 CA",
    "sg:province":"Utrecht",
    "wof:name":"Kivits C H J En F Pieksma",
    "wof:placetype":"venue"
},
  "geometry": {"coordinates":[5.04266,52.017044],"type":"Point"}
}