{
  "type": "Feature",
  "properties": {
    "addr:full":"Doortocht 13 Bodegraven South Holland 2411 DS",
    "addr:housenumber":"13",
    "addr:postcode":"2411 ds",
    "addr:street":"Doortocht",
    "iso:country":"NL",
    "sg:address":"Doortocht 13",
    "sg:city":"Bodegraven",
    "sg:orig_category":"Verhuur Bouwmachines",
    "sg:phone":"+31 172 618 687",
    "sg:postcode":"2411 DS",
    "sg:province":"South Holland",
    "wof:name":"T. Agterof Verhuur",
    "wof:placetype":"venue"
},
  "geometry": {"coordinates":[4.742876,52.083298],"type":"Point"}
}