{
  "type": "Feature",
  "properties": {
    "addr:full":"Putterweg 29 Garderen Gelderland 3886 PA",
    "addr:housenumber":"29",
    "addr:postcode":"3886",
    "addr:street":"Putterweg;Gelderland",
    "iso:country":"NL",
    "sg:address":"Putterweg 29",
    "sg:city":"Garderen",
    "sg:orig_category":"Kappers",
    "sg:phone":"+31 577 461 413",
    "sg:postcode":"3886 PA",
    "sg:province":"Gelderland",
    "wof:name":"Dameskapsalon Henriette",
    "wof:placetype":"venue"
},
  "geometry": {"coordinates":[5.7078170776,52.2353744507],"type":"Point"}
}