{
  "type": "Feature",
  "properties": {
    "addr:full":"Rijksweg 18 Schoorl Noord-Holland 1871 PD",
    "addr:housenumber":"18",
    "addr:postcode":"1871 pd",
    "addr:street":"Rijksweg",
    "iso:country":"NL",
    "sg:address":"Rijksweg 18",
    "sg:city":"Schoorl",
    "sg:orig_category":"Notarissen",
    "sg:phone":"+31 72 509 2944",
    "sg:postcode":"1871 PD",
    "sg:province":"Noord-Holland",
    "wof:name":"Notaris Mr. J.E.A. Eijckelhof",
    "wof:placetype":"venue"
},
  "geometry": {"coordinates":[4.715838,52.706341],"type":"Point"}
}