{
  "type": "Feature",
  "properties": {
    "addr:full":"Heerenweg 151 Heiloo Noord-Holland 1851 KN",
    "addr:housenumber":"151",
    "addr:postcode":"1851 kn",
    "addr:street":"Heerenweg",
    "iso:country":"NL",
    "sg:address":"Heerenweg 151",
    "sg:city":"Heiloo",
    "sg:orig_category":"Opticiens",
    "sg:phone":"+31 72 533 1275",
    "sg:postcode":"1851 KN",
    "sg:province":"Noord-Holland",
    "wof:name":"Zonneveld Optiek Bv",
    "wof:placetype":"venue"
},
  "geometry": {"coordinates":[4.7065191269,52.601726532],"type":"Point"}
}