{
  "type": "Feature",
  "properties": {
    "iso:country":"NL",
    "sg:address":"Parmentierpln 1",
    "sg:city":"Rotterdam",
    "sg:orig_category":"Scheepvaartmijen",
    "sg:phone":"+31 10 429 6144",
    "sg:postcode":"3088 GN",
    "sg:province":"Zuid-Holland",
    "wof:name":"Rova Bv",
    "wof:placetype":"venue"
},
  "geometry": {"coordinates":[4.445977,51.87598],"type":"Point"}
}