{
  "type": "Feature",
  "properties": {
    "addr:full":"Omloop 0 Utrecht Utrecht 3552 AX",
    "addr:housenumber":"0",
    "addr:postcode":"3552 ax",
    "addr:street":"Omloop",
    "iso:country":"NL",
    "sg:address":"Omloop 0",
    "sg:city":"Utrecht",
    "sg:orig_category":"Visspeciaalzaken",
    "sg:phone":"+31 30 243 8134",
    "sg:postcode":"3552 AX",
    "sg:province":"Utrecht",
    "wof:name":"Vishandel Thomas",
    "wof:placetype":"venue"
},
  "geometry": {"coordinates":[5.105814,52.10545],"type":"Point"}
}