{
  "type": "Feature",
  "properties": {
    "addr:full":"Teylingerln 82A Voorhout Zuid-Holland 2215 RT",
    "addr:housenumber":"82a",
    "addr:postcode":"2215 rt",
    "addr:street":"Teylingerln",
    "iso:country":"NL",
    "sg:address":"Teylingerln 82A",
    "sg:city":"Voorhout",
    "sg:classifiers":[
        {
            "category":"Retail",
            "subcategory":"Auto Repair",
            "type":"Services"
        }
    ],
    "sg:phone":"+31 252 214 248",
    "sg:postcode":"2215 RT",
    "sg:province":"Zuid-Holland",
    "sg:tags":[
        "garage"
    ],
    "sg:website":"http://www.jtvansteynauto.nl",
    "wof:name":"Steyn, J T Van",
    "wof:placetype":"venue"
},
  "geometry": {"coordinates":[4.51954,52.233051],"type":"Point"}
}