{
  "type": "Feature",
  "properties": {
    "addr:full":"Calandstr 20 Werkendam Noord-Brabant 4251 NZ",
    "addr:housenumber":"20",
    "addr:postcode":"4251 nz",
    "addr:street":"Calandstr",
    "iso:country":"NL",
    "sg:address":"Calandstr 20",
    "sg:city":"Werkendam",
    "sg:orig_category":"Behangselpapier En Wandbekleding - Fabr. En Grooth",
    "sg:phone":"+31 183 504 700",
    "sg:postcode":"4251 NZ",
    "sg:province":"Noord-Brabant",
    "wof:name":"Wandvisie 2000 Bv",
    "wof:placetype":"venue"
},
  "geometry": {"coordinates":[4.868413,51.802494],"type":"Point"}
}