{
  "type": "Feature",
  "properties": {
    "addr:full":"Wilhelminastraat 97 'S Gravenhage Zuid-Holland 2595 EN",
    "addr:housenumber":"97",
    "addr:postcode":"2595 en",
    "addr:street":"Wilhelminastraat;' S",
    "iso:country":"NL",
    "sg:address":"Wilhelminastraat 97",
    "sg:city":"'S Gravenhage",
    "sg:orig_category":"Bedrijfs- And Managementsconsultants",
    "sg:phone":"+31 70 383 6182",
    "sg:postcode":"2595 EN",
    "sg:province":"Zuid-Holland",
    "wof:name":"T. Besancon Management Bv",
    "wof:placetype":"venue"
},
  "geometry": {"coordinates":[4.333405,52.08371],"type":"Point"}
}