{
  "type": "Feature",
  "properties": {
    "addr:full":"Tjalk 77 Schipluiden South Holland 2636 DB",
    "addr:housenumber":"77",
    "addr:postcode":"2636 db",
    "addr:street":"Tjalk",
    "iso:country":"NL",
    "sg:address":"Tjalk 77",
    "sg:city":"Schipluiden",
    "sg:orig_category":"Architecten",
    "sg:phone":"+31 15 380 8661",
    "sg:postcode":"2636 DB",
    "sg:province":"South Holland",
    "wof:name":"Marja Nevalainen",
    "wof:placetype":"venue"
},
  "geometry": {"coordinates":[4.314643,51.978565],"type":"Point"}
}