{
  "type": "Feature",
  "properties": {
    "addr:full":"De Rede 46 Dronten NL. 8251 EW",
    "addr:housenumber":"46",
    "addr:postcode":"8251 ew",
    "addr:street":"De Rede;Nl.",
    "iso:country":"NL",
    "sg:address":"De Rede 46",
    "sg:city":"Dronten",
    "sg:orig_category":"Bloemen And Planten",
    "sg:phone":"+31 321 312 015",
    "sg:postcode":"8251 EW",
    "sg:province":"NL.",
    "wof:name":"Flevo-Flora",
    "wof:placetype":"venue"
},
  "geometry": {"coordinates":[5.716865,52.524029],"type":"Point"}
}