{
  "type": "Feature",
  "properties": {
    "addr:full":"Bunschotenweg 160 Rotterdam Zuid-Holland 3089 KC",
    "addr:housenumber":"160",
    "addr:postcode":"3089 kc",
    "addr:street":"Bunschotenweg",
    "iso:country":"NL",
    "sg:address":"Bunschotenweg 160",
    "sg:city":"Rotterdam",
    "sg:orig_category":"Bedrijfsinventaris Gh",
    "sg:phone":"+31 10 429 7155",
    "sg:postcode":"3089 KC",
    "sg:province":"Zuid-Holland",
    "wof:name":"Reftrade Bv",
    "wof:placetype":"venue"
},
  "geometry": {"coordinates":[4.409459,51.889194],"type":"Point"}
}