{
  "type": "Feature",
  "properties": {
    "addr:full":"Laan Van Insulinde 27 Heemstede Noord-Holland 2103 TA",
    "addr:housenumber":"27",
    "addr:postcode":"2103 ta",
    "addr:street":"Laan Van Insulinde",
    "iso:country":"NL",
    "sg:address":"Laan Van Insulinde 27",
    "sg:city":"Heemstede",
    "sg:orig_category":"Boekhouders",
    "sg:phone":"+31 23 528 5275",
    "sg:postcode":"2103 TA",
    "sg:province":"Noord-Holland",
    "wof:name":"Administratie- En Servicebureau Hamer",
    "wof:placetype":"venue"
},
  "geometry": {"coordinates":[4.626665,52.3437],"type":"Point"}
}