{
  "type": "Feature",
  "properties": {
    "addr:full":"T Weike 12 Gorredyk Friesland 8401 AT",
    "addr:housenumber":"12",
    "addr:postcode":"8401",
    "addr:street":"T Weike",
    "iso:country":"NL",
    "sg:address":"T Weike 12",
    "sg:city":"Gorredyk",
    "sg:classifiers":[
        {
            "category":"Personal",
            "subcategory":"Nail Salon",
            "type":"Services"
        }
    ],
    "sg:phone":"+31 513 465 465",
    "sg:postcode":"8401 AT",
    "sg:province":"Friesland",
    "sg:tags":[
        "pedicure"
    ],
    "wof:name":"Huisman, L",
    "wof:placetype":"venue"
},
  "geometry": {"coordinates":[6.072672,52.998173],"type":"Point"}
}