{
  "type": "Feature",
  "properties": {
    "addr:full":"H A Lorentzstr 6 Zwyndrecht South Holland 3331 EE",
    "addr:housenumber":"6",
    "addr:postcode":"3331 ee",
    "addr:street":"Zwyndrecht South",
    "iso:country":"NL",
    "sg:address":"H A Lorentzstr 6",
    "sg:city":"Zwyndrecht",
    "sg:orig_category":"Machinehandel",
    "sg:phone":"+31 78 619 5681",
    "sg:postcode":"3331 EE",
    "sg:province":"South Holland",
    "wof:name":"Marvel Bv",
    "wof:placetype":"venue"
},
  "geometry": {"coordinates":[4.629498,51.818916],"type":"Point"}
}