{
  "type": "Feature",
  "properties": {
    "addr:full":"Heuvelpoort 321 Tilburg Noord-Brabant 5038 DT",
    "addr:housenumber":"321",
    "addr:postcode":"5038 dt",
    "addr:street":"Heuvelpoort",
    "iso:country":"NL",
    "sg:address":"Heuvelpoort 321",
    "sg:city":"Tilburg",
    "sg:orig_category":"Werving And Selectie Van Tijdelijk Personeel And Uitzendkantoren",
    "sg:phone":"+31 13 536 1695",
    "sg:postcode":"5038 DT",
    "sg:province":"Noord-Brabant",
    "wof:name":"Adecco",
    "wof:placetype":"venue"
},
  "geometry": {"coordinates":[5.0906791687,51.5569190979],"type":"Point"}
}