{
  "type": "Feature",
  "properties": {
    "addr:full":"Kl Beer 467 Rotterdam Zuid-Holland 3067 ZW",
    "addr:housenumber":"467",
    "addr:postcode":"3067 zw",
    "iso:country":"NL",
    "sg:address":"Kl Beer 467",
    "sg:city":"Rotterdam",
    "sg:orig_category":"Journalisten Freelance",
    "sg:phone":"+31 10 220 1063",
    "sg:postcode":"3067 ZW",
    "sg:province":"Zuid-Holland",
    "wof:name":"Funny Pens",
    "wof:placetype":"venue"
},
  "geometry": {"coordinates":[4.555231,51.949841],"type":"Point"}
}