{
  "type": "Feature",
  "properties": {
    "addr:full":"Parkstraat 8 Steenwijk Overijssel 8331 PN",
    "addr:housenumber":"8",
    "addr:postcode":"8331 pn",
    "addr:street":"Parkstraat",
    "iso:country":"NL",
    "sg:address":"Parkstraat 8",
    "sg:city":"Steenwijk",
    "sg:orig_category":"Metaalafval, Schrootrecycling And Sloperijen",
    "sg:phone":"+31 521 513 738",
    "sg:postcode":"8331 PN",
    "sg:province":"Overijssel",
    "wof:name":"F W Spijkerman",
    "wof:placetype":"venue"
},
  "geometry": {"coordinates":[6.10611,52.785168],"type":"Point"}
}