{
  "type": "Feature",
  "properties": {
    "addr:full":"Sterrenln 38 Apeldoorn Gelderland 7314 KK",
    "addr:housenumber":"38",
    "addr:postcode":"7314 kk",
    "addr:street":"Sterrenln;Gelderland",
    "iso:country":"NL",
    "sg:address":"Sterrenln 38",
    "sg:city":"Apeldoorn",
    "sg:orig_category":"Makelaars En Adviseurs Horecabedrijven",
    "sg:phone":"+31 55 355 2752",
    "sg:postcode":"7314 KK",
    "sg:province":"Gelderland",
    "wof:name":"Barmentloo",
    "wof:placetype":"venue"
},
  "geometry": {"coordinates":[5.942706,52.216343],"type":"Point"}
}