{
  "type": "Feature",
  "properties": {
    "addr:full":"Beethovenstraat 22-28 Amsterdam Noord-Holland 1077 JH",
    "addr:housenumber":"22-28",
    "addr:postcode":"1077 jh",
    "addr:street":"Beethovenstraat",
    "iso:country":"NL",
    "sg:address":"Beethovenstraat 22-28",
    "sg:city":"Amsterdam",
    "sg:orig_category":"Verlichting And Huishoudartikelen",
    "sg:phone":"+31 20 671 2407",
    "sg:postcode":"1077 JH",
    "sg:province":"Noord-Holland",
    "wof:name":"De Gezellige Winkel Van Heemskerk",
    "wof:placetype":"venue"
},
  "geometry": {"coordinates":[4.877613,52.349667],"type":"Point"}
}