{
  "type": "Feature",
  "properties": {
    "addr:full":"St Annenstr 24 Amsterdam Noord-Holland 1012 HE",
    "addr:housenumber":"24",
    "addr:postcode":"1012 he",
    "iso:country":"NL",
    "sg:address":"St Annenstr 24",
    "sg:city":"Amsterdam",
    "sg:orig_category":"Verenigingen En Stichtingen",
    "sg:phone":"+31 20 622 0553",
    "sg:postcode":"1012 HE",
    "sg:province":"Noord-Holland",
    "wof:name":"Zwartlaken Ateliers, Ver",
    "wof:placetype":"venue"
},
  "geometry": {"coordinates":[4.897088,52.373596],"type":"Point"}
}