{
  "type": "Feature",
  "properties": {
    "addr:full":"Scholeksterstr 9 Baarn Utrecht 3742 XJ",
    "addr:housenumber":"9",
    "addr:postcode":"3742 xj",
    "addr:street":"Scholeksterstr",
    "iso:country":"NL",
    "sg:address":"Scholeksterstr 9",
    "sg:city":"Baarn",
    "sg:orig_category":"Schilders",
    "sg:phone":"+31 35 542 1364",
    "sg:postcode":"3742 XJ",
    "sg:province":"Utrecht",
    "wof:name":"Putten, Van",
    "wof:placetype":"venue"
},
  "geometry": {"coordinates":[5.29739,52.201618],"type":"Point"}
}