{
  "type": "Feature",
  "properties": {
    "addr:full":"Rijnstraat 61 Amsterdam Noord-Holland 1079 GW",
    "addr:housenumber":"61",
    "addr:postcode":"1079 gw",
    "addr:street":"Rijnstraat",
    "iso:country":"NL",
    "sg:address":"Rijnstraat 61",
    "sg:city":"Amsterdam",
    "sg:orig_category":"Boekenuitgeverijen",
    "sg:phone":"+31 20 644 9386",
    "sg:postcode":"1079 GW",
    "sg:province":"Noord-Holland",
    "wof:name":"Boekhandel Favie Bv",
    "wof:placetype":"venue"
},
  "geometry": {"coordinates":[4.905488,52.346226],"type":"Point"}
}