{
  "type": "Feature",
  "properties": {
    "addr:full":"Boekert 3 Oosterblokker North Holland 1696 AH",
    "addr:housenumber":"3",
    "addr:postcode":"1696 ah",
    "addr:street":"Boekert",
    "iso:country":"NL",
    "sg:address":"Boekert 3",
    "sg:city":"Oosterblokker",
    "sg:orig_category":"Glaszetten",
    "sg:phone":"+31 229 262 531",
    "sg:postcode":"1696 AH",
    "sg:province":"North Holland",
    "wof:name":"Wagenaar",
    "wof:placetype":"venue"
},
  "geometry": {"coordinates":[5.106709,52.664074],"type":"Point"}
}