{
  "type": "Feature",
  "properties": {
    "addr:full":"Aalsmeerderwg 441 Aalsmeer Noord-Holland 1432 EC",
    "addr:housenumber":"441",
    "addr:postcode":"aalsmeer;1432 ec",
    "iso:country":"NL",
    "sg:address":"Aalsmeerderwg 441",
    "sg:city":"Aalsmeer",
    "sg:orig_category":"Bloemen En Planten - Groothandel",
    "sg:phone":"+31 297 326 931",
    "sg:postcode":"1432 EC",
    "sg:province":"Noord-Holland",
    "wof:name":"Helsloot",
    "wof:placetype":"venue"
},
  "geometry": {"coordinates":[4.816964,52.287483],"type":"Point"}
}