{
  "type": "Feature",
  "properties": {
    "addr:full":"Oudeschans 71Bg Amsterdam Noord-Holland 1011 KW",
    "addr:housenumber":"71bg",
    "addr:postcode":"1011 kw",
    "addr:street":"Oudeschans",
    "iso:country":"NL",
    "sg:address":"Oudeschans 71Bg",
    "sg:city":"Amsterdam",
    "sg:orig_category":"Technische Studies And Onderzoek",
    "sg:phone":"+31 20 623 8001",
    "sg:postcode":"1011 KW",
    "sg:province":"Noord-Holland",
    "wof:name":"K. Hamelink",
    "wof:placetype":"venue"
},
  "geometry": {"coordinates":[4.903288,52.370296],"type":"Point"}
}