{
  "type": "Feature",
  "properties": {
    "addr:full":"Stoevenberg 13 Genemuiden NL.08 8281 EL",
    "addr:housenumber":"13;nl.08 8281",
    "addr:street":"Stoevenberg;El",
    "iso:country":"NL",
    "sg:address":"Stoevenberg 13",
    "sg:city":"Genemuiden",
    "sg:orig_category":"Zonnebank- En Solariumcentra",
    "sg:phone":"+31 38 385 5246",
    "sg:postcode":"8281 EL",
    "sg:province":"NL.08",
    "wof:name":"Astrid",
    "wof:placetype":"venue"
},
  "geometry": {"coordinates":[6.04599,52.622475],"type":"Point"}
}