{
  "type": "Feature",
  "properties": {
    "addr:full":"Bettoweg 25 Schiedam Zuid-Holland 3125 AB",
    "addr:housenumber":"25",
    "addr:postcode":"3125 ab",
    "addr:street":"Bettoweg",
    "iso:country":"NL",
    "sg:address":"Bettoweg 25",
    "sg:city":"Schiedam",
    "sg:orig_category":"Autokeuringen",
    "sg:phone":"+31 10 262 1163",
    "sg:postcode":"3125 AB",
    "sg:province":"Zuid-Holland",
    "wof:name":"Mercecars",
    "wof:placetype":"venue"
},
  "geometry": {"coordinates":[4.410084,51.924919],"type":"Point"}
}