{
  "type": "Feature",
  "properties": {
    "addr:full":"Zandberglaan 2 Breda North Brabant 4818 GK",
    "addr:housenumber":"2",
    "addr:postcode":"4818 gk",
    "addr:street":"Zandberglaan",
    "iso:country":"NL",
    "sg:address":"Zandberglaan 2",
    "sg:city":"Breda",
    "sg:orig_category":"Diverse Grafische Activiteiten",
    "sg:phone":"+31 76 520 0316",
    "sg:postcode":"4818 GK",
    "sg:province":"North Brabant",
    "wof:name":"G.A.M. Van Gerwen",
    "wof:placetype":"venue"
},
  "geometry": {"coordinates":[4.78197,51.576385],"type":"Point"}
}