{
  "type": "Feature",
  "properties": {
    "iso:country":"NL",
    "sg:address":"Pinksterbloem 38",
    "sg:city":"Purmerend",
    "sg:orig_category":"Autokeuringen",
    "sg:phone":"+31 299 436 292",
    "sg:postcode":"1441 RK",
    "sg:province":"Noord-Holland",
    "wof:name":"P.O.S.T.",
    "wof:placetype":"venue"
},
  "geometry": {"coordinates":[4.949842,52.496613],"type":"Point"}
}