{
  "type": "Feature",
  "properties": {
    "addr:full":"Schonauwensewg 7 Houten Utrecht 3991 MC",
    "addr:housenumber":"7",
    "addr:postcode":"3991 mc",
    "addr:street":"Schonauwensewg",
    "iso:country":"NL",
    "sg:address":"Schonauwensewg 7",
    "sg:city":"Houten",
    "sg:classifiers":[
        {
            "category":"Home & Garden",
            "subcategory":"Garden Supply",
            "type":"Retail Goods"
        }
    ],
    "sg:phone":"+31 30 635 3355",
    "sg:postcode":"3991 MC",
    "sg:province":"Utrecht",
    "sg:tags":[
        "zand",
        "en",
        "grind"
    ],
    "wof:name":"Loswal Houten",
    "wof:placetype":"venue"
},
  "geometry": {"coordinates":[5.17875,52.008141],"type":"Point"}
}