{
  "type": "Feature",
  "properties": {
    "iso:country":"NL",
    "sg:address":"Molendk 6",
    "sg:city":"Zwartewaal",
    "sg:orig_category":"Automaterialen En Gereedschappen",
    "sg:phone":"+31 181 661 193",
    "sg:postcode":"3238 LD",
    "sg:province":"Zuid-Holland",
    "wof:name":"Reacs Vof",
    "wof:placetype":"venue"
},
  "geometry": {"coordinates":[4.218425,51.879154],"type":"Point"}
}