{
  "type": "Feature",
  "properties": {
    "addr:full":"Menstr 24-28 Deventer Overijssel 7411 EZ",
    "addr:housenumber":"24-28",
    "addr:postcode":"7411 ez",
    "iso:country":"NL",
    "sg:address":"Menstr 24-28",
    "sg:city":"Deventer",
    "sg:orig_category":"Airconditioning",
    "sg:phone":"+31 570 615 100",
    "sg:postcode":"7411 EZ",
    "sg:province":"Overijssel",
    "wof:name":"Bergstr\u00f6m Koeltechniek",
    "wof:placetype":"venue"
},
  "geometry": {"coordinates":[6.161632,52.251434],"type":"Point"}
}