{
  "type": "Feature",
  "properties": {
    "addr:full":"Admiraal De Ruijterweg 135 Amsterdam Noord-Holland 1056 EX",
    "addr:housenumber":"135",
    "addr:postcode":"1056 ex",
    "addr:street":"Admiraal De Ruijterweg",
    "iso:country":"NL",
    "sg:address":"Admiraal De Ruijterweg 135",
    "sg:city":"Amsterdam",
    "sg:orig_category":"Diverse Consumentenartikelen Gh",
    "sg:phone":"+31 20 616 5901",
    "sg:postcode":"1056 EX",
    "sg:province":"Noord-Holland",
    "wof:name":"Arriba Muziek Import",
    "wof:placetype":"venue"
},
  "geometry": {"coordinates":[4.858708,52.373363],"type":"Point"}
}