{
  "type": "Feature",
  "properties": {
    "addr:full":"Markt 38 Dokkum Provincie Friesland 9101 LS",
    "addr:housenumber":"38",
    "addr:postcode":"9101 ls",
    "addr:street":"Markt;Provincie Friesland",
    "iso:country":"NL",
    "sg:address":"Markt 38",
    "sg:city":"Dokkum",
    "sg:orig_category":"Meubelzaken, Woning- And Keukeninrichting",
    "sg:phone":"+31 519 292 719",
    "sg:postcode":"9101 LS",
    "sg:province":"Provincie Friesland",
    "wof:name":"Van Sinderen Klassemeubelen Bv",
    "wof:placetype":"venue"
},
  "geometry": {"coordinates":[5.997873,53.326649],"type":"Point"}
}