{
  "type": "Feature",
  "properties": {
    "addr:full":"Birkstr 40 Soest Utrecht 3768 HH",
    "addr:housenumber":"40",
    "addr:postcode":"3768 hh",
    "addr:street":"Birkstr",
    "iso:country":"NL",
    "sg:address":"Birkstr 40",
    "sg:city":"Soest",
    "sg:classifiers":[
        {
            "category":"Retail",
            "subcategory":"Auto Repair",
            "type":"Services"
        }
    ],
    "sg:phone":"+31 35 601 1764",
    "sg:postcode":"3768 HH",
    "sg:province":"Utrecht",
    "sg:tags":[
        "garage"
    ],
    "wof:name":"Wijnands Garage, N",
    "wof:placetype":"venue"
},
  "geometry": {"coordinates":[5.310917,52.164742],"type":"Point"}
}