{
  "type": "Feature",
  "properties": {
    "addr:full":"Fitisln 37 Zeewolde Flevoland 3893 JA",
    "addr:housenumber":"37",
    "addr:postcode":"3893 ja",
    "addr:street":"Fitisln;Flevoland",
    "iso:country":"NL",
    "sg:address":"Fitisln 37",
    "sg:city":"Zeewolde",
    "sg:orig_category":"Administratie- En Boekhoudkantoren",
    "sg:phone":"+31 36 522 1996",
    "sg:postcode":"3893 JA",
    "sg:province":"Flevoland",
    "wof:name":"Hamaker",
    "wof:placetype":"venue"
},
  "geometry": {"coordinates":[5.54213,52.332512],"type":"Point"}
}