{
  "type": "Feature",
  "properties": {
    "addr:full":"Elburgerweg 53 Nunspeet Gelderland 8071 TA",
    "addr:housenumber":"53",
    "addr:postcode":"8071 ta",
    "addr:street":"Elburgerweg;Gelderland",
    "iso:country":"NL",
    "sg:address":"Elburgerweg 53",
    "sg:city":"Nunspeet",
    "sg:orig_category":"Hout Gh",
    "sg:phone":"+31 341 254 334",
    "sg:postcode":"8071 TA",
    "sg:province":"Gelderland",
    "wof:name":"Beekhuizen-Hoekerd Bv",
    "wof:placetype":"venue"
},
  "geometry": {"coordinates":[5.792183,52.386959],"type":"Point"}
}