{
  "type": "Feature",
  "properties": {
    "iso:country":"NL",
    "sg:address":"Lange Nering 98",
    "sg:city":"Emmeloord",
    "sg:orig_category":"Huishoudapparatuur, Televisies And Radio'S",
    "sg:phone":"+31 527 698 937",
    "sg:postcode":"8302 EG",
    "sg:province":"NL.",
    "wof:name":"S & F Scheer & Foppen",
    "wof:placetype":"venue"
},
  "geometry": {"coordinates":[5.759766,52.71114],"type":"Point"}
}