{
  "type": "Feature",
  "properties": {
    "addr:full":"Lange Nering 98 Emmeloord NL. 8302 EG",
    "addr:housenumber":"98",
    "addr:postcode":"8302 eg",
    "addr:street":"Lange Nering;Nl.",
    "iso:country":"NL",
    "sg:address":"Lange Nering 98",
    "sg:city":"Emmeloord",
    "sg:orig_category":"Huishoudapparatuur, Televisies And Radio'S",
    "sg:phone":"+31 527 698 937",
    "sg:postcode":"8302 EG",
    "sg:province":"NL.",
    "wof:name":"S & F Scheer & Foppen",
    "wof:placetype":"venue"
},
  "geometry": {"coordinates":[5.759766,52.71114],"type":"Point"}
}