{
  "type": "Feature",
  "properties": {
    "addr:full":"Wilhelminaln 2 Raamsdonksveer North Brabant 4941 GK",
    "addr:housenumber":"2",
    "addr:postcode":"4941 gk",
    "addr:street":"Wilhelminaln",
    "iso:country":"NL",
    "sg:address":"Wilhelminaln 2",
    "sg:city":"Raamsdonksveer",
    "sg:orig_category":"Biljartzalen",
    "sg:phone":"+31 162 519 733",
    "sg:postcode":"4941 GK",
    "sg:province":"North Brabant",
    "wof:name":"Posterij, De",
    "wof:placetype":"venue"
},
  "geometry": {"coordinates":[4.87516,51.693649],"type":"Point"}
}