{
  "type": "Feature",
  "properties": {
    "addr:full":"Thorbeckeln 187 Roosendaal Noord-Brabant 4708 MG",
    "addr:housenumber":"187",
    "addr:postcode":"4708 mg",
    "iso:country":"NL",
    "sg:address":"Thorbeckeln 187",
    "sg:city":"Roosendaal",
    "sg:orig_category":"Accountants - Administratie- Consulenten En -Kantoren",
    "sg:phone":"+31 165 550 786",
    "sg:postcode":"4708 MG",
    "sg:province":"Noord-Brabant",
    "wof:name":"Kar Bv, Van De",
    "wof:placetype":"venue"
},
  "geometry": {"coordinates":[4.45767,51.531403],"type":"Point"}
}