{
  "type": "Feature",
  "properties": {
    "addr:full":"Lossersestr 2 De Lutte NL.08 7587 PX",
    "addr:housenumber":"2",
    "addr:postcode":"nl.08 7587 px",
    "addr:street":"Lossersestr",
    "iso:country":"NL",
    "sg:address":"Lossersestr 2",
    "sg:city":"De Lutte",
    "sg:orig_category":"Schoonheidsinstituten",
    "sg:phone":"+31 541 552 272",
    "sg:postcode":"7587 PX",
    "sg:province":"NL.08",
    "wof:name":"Marian, Salon",
    "wof:placetype":"venue"
},
  "geometry": {"coordinates":[6.987698,52.313782],"type":"Point"}
}