{
  "type": "Feature",
  "properties": {
    "addr:full":"Kikkertwg 2 Wormerveer Noord-Holland 1521 RG",
    "addr:housenumber":"2",
    "addr:postcode":"1521 rg",
    "addr:street":"Kikkertwg",
    "iso:country":"NL",
    "sg:address":"Kikkertwg 2",
    "sg:city":"Wormerveer",
    "sg:orig_category":"Verpakkingsbedrijven",
    "sg:phone":"+31 75 647 5510",
    "sg:postcode":"1521 RG",
    "sg:province":"Noord-Holland",
    "wof:name":"Argent Verpakkingen Bv",
    "wof:placetype":"venue"
},
  "geometry": {"coordinates":[4.783841,52.50613],"type":"Point"}
}