{
  "type": "Feature",
  "properties": {
    "iso:country":"NL",
    "sg:address":"Spechtendonk 9",
    "sg:city":"St Willebrord",
    "sg:orig_category":"Montagebedrijven",
    "sg:phone":"+31 165 384 881",
    "sg:postcode":"4711 LN",
    "sg:province":"Noord-Brabant",
    "wof:name":"Gool Vof, Van",
    "wof:placetype":"venue"
},
  "geometry": {"coordinates":[4.584887,51.54129],"type":"Point"}
}