{
  "type": "Feature",
  "properties": {
    "iso:country":"NL",
    "sg:address":"Peperstraat 25",
    "sg:city":"Kaatsheuvel",
    "sg:orig_category":"Bioscopen",
    "sg:phone":"+31 416 279 660",
    "sg:postcode":"5171 EC",
    "sg:province":"Noord-Brabant",
    "wof:name":"Apollotheater",
    "wof:placetype":"venue"
},
  "geometry": {"coordinates":[5.032974,51.660141],"type":"Point"}
}