{
  "type": "Feature",
  "properties": {
    "addr:full":"Koninginnepln 10 Belfeld Limburg 5951 LC",
    "addr:housenumber":"10",
    "addr:postcode":"5951 lc",
    "addr:street":"Koninginnepln",
    "iso:country":"NL",
    "sg:address":"Koninginnepln 10",
    "sg:city":"Belfeld",
    "sg:orig_category":"Fietsen En Bromfietsen",
    "sg:phone":"+31 77 475 3334",
    "sg:postcode":"5951 LC",
    "sg:province":"Limburg",
    "wof:name":"Profile Peter G\u00e4hler",
    "wof:placetype":"venue"
},
  "geometry": {"coordinates":[6.111527,51.311604],"type":"Point"}
}