{
  "type": "Feature",
  "properties": {
    "addr:full":"Koekoekln 5 Hoogeveen Drenthe 7905 HJ",
    "addr:housenumber":"5",
    "addr:postcode":"7905 hj",
    "addr:street":"Koekoekln",
    "iso:country":"NL",
    "sg:address":"Koekoekln 5",
    "sg:city":"Hoogeveen",
    "sg:orig_category":"Verenigingsgebouwen",
    "sg:phone":"+31 528 267 275",
    "sg:postcode":"7905 HJ",
    "sg:province":"Drenthe",
    "wof:name":"Buurtbeheer Wolfsbos Zuid",
    "wof:placetype":"venue"
},
  "geometry": {"coordinates":[6.50454,52.716564],"type":"Point"}
}