{
  "type": "Feature",
  "properties": {
    "addr:full":"Kuipersdk 90 Enschede Overijssel 7512 CK",
    "addr:housenumber":"90",
    "addr:postcode":"7512 ck",
    "addr:street":"Kuipersdk",
    "iso:country":"NL",
    "sg:address":"Kuipersdk 90",
    "sg:city":"Enschede",
    "sg:orig_category":"Wasmachines En Wasdrogers - Onderhoud En Reparatie",
    "sg:phone":"+31 53 432 9325",
    "sg:postcode":"7512 CK",
    "sg:province":"Overijssel",
    "wof:name":"Stuntmarkt",
    "wof:placetype":"venue"
},
  "geometry": {"coordinates":[6.8959960938,52.2137527466],"type":"Point"}
}