{
  "type": "Feature",
  "properties": {
    "addr:full":"Lageweg 6 Burgum Provincie Friesland 9251 JW",
    "addr:housenumber":"6",
    "addr:postcode":"9251 jw",
    "addr:street":"Lageweg;Provincie Friesland",
    "iso:country":"NL",
    "sg:address":"Lageweg 6",
    "sg:city":"Burgum",
    "sg:classifiers":[
        {
            "category":"Fast Food",
            "type":"Food & Drink"
        }
    ],
    "sg:phone":"+31 511 464 168",
    "sg:postcode":"9251 JW",
    "sg:province":"Provincie Friesland",
    "sg:tags":[
        "afhaal",
        "restaurant"
    ],
    "wof:name":"Pyramide",
    "wof:placetype":"venue"
},
  "geometry": {"coordinates":[5.990116,53.1922],"type":"Point"}
}