{
  "type": "Feature",
  "properties": {
    "addr:full":"Paul Krugersdreef 5 Sas Van Gent Zeeland 4551 AJ",
    "addr:housenumber":"5",
    "addr:postcode":"4551 aj",
    "iso:country":"NL",
    "sg:address":"Paul Krugersdreef 5",
    "sg:city":"Sas Van Gent",
    "sg:orig_category":"Autokeuringen",
    "sg:phone":"+31 115 451 292",
    "sg:postcode":"4551 AJ",
    "sg:province":"Zeeland",
    "wof:name":"Garagebedrijf R. Bode",
    "wof:placetype":"venue"
},
  "geometry": {"coordinates":[3.800965,51.229752],"type":"Point"}
}