{
  "type": "Feature",
  "properties": {
    "addr:full":"Niasstr 1 Utrecht Utrecht 3531 WR",
    "addr:housenumber":"1",
    "addr:postcode":"3531 wr",
    "addr:street":"Niasstr",
    "iso:country":"NL",
    "sg:address":"Niasstr 1",
    "sg:city":"Utrecht",
    "sg:orig_category":"Loopbaanbegeleiding",
    "sg:phone":"+31 30 291 9977",
    "sg:postcode":"3531 WR",
    "sg:province":"Utrecht",
    "sg:website":"http://www.loopbaanperspectief.nl",
    "wof:name":"Hordijk Loopbaanperspectief",
    "wof:placetype":"venue"
},
  "geometry": {"coordinates":[5.090556,52.093433],"type":"Point"}
}