{
  "type": "Feature",
  "properties": {
    "addr:full":"Oude Kruiswg 188 Cruquius North Holland 2142 EK",
    "addr:housenumber":"188",
    "addr:postcode":"2142 ek",
    "addr:street":"Oude Kruiswg",
    "iso:country":"NL",
    "sg:address":"Oude Kruiswg 188",
    "sg:city":"Cruquius",
    "sg:orig_category":"Acupunctuur",
    "sg:phone":"+31 23 547 2878",
    "sg:postcode":"2142 EK",
    "sg:province":"North Holland",
    "wof:name":"Overbeeke, E Van",
    "wof:placetype":"venue"
},
  "geometry": {"coordinates":[4.638366,52.3344],"type":"Point"}
}