{
  "type": "Feature",
  "properties": {
    "iso:country":"NL",
    "sg:address":"Olympiawg 252-254",
    "sg:city":"Rotterdam",
    "sg:orig_category":"Dieselmotoren",
    "sg:phone":"+31 10 419 6530",
    "sg:postcode":"3078 HT",
    "sg:province":"Zuid-Holland",
    "wof:name":"Maas Bv, De",
    "wof:placetype":"venue"
},
  "geometry": {"coordinates":[4.522888,51.89119],"type":"Point"}
}