{
  "type": "Feature",
  "properties": {
    "addr:full":"Olympiawg 252-254 Rotterdam Zuid-Holland 3078 HT",
    "addr:housenumber":"252-254",
    "addr:postcode":"3078 ht",
    "iso:country":"NL",
    "sg:address":"Olympiawg 252-254",
    "sg:city":"Rotterdam",
    "sg:orig_category":"Dieselmotoren",
    "sg:phone":"+31 10 419 6530",
    "sg:postcode":"3078 HT",
    "sg:province":"Zuid-Holland",
    "wof:name":"Maas Bv, De",
    "wof:placetype":"venue"
},
  "geometry": {"coordinates":[4.522888,51.89119],"type":"Point"}
}