{
  "type": "Feature",
  "properties": {
    "addr:full":"Weteringdreef 61 Zoetermeer Zuid-Holland 2724 GT",
    "addr:housenumber":"61",
    "addr:postcode":"2724 gt",
    "addr:street":"Weteringdreef",
    "iso:country":"NL",
    "sg:address":"Weteringdreef 61",
    "sg:city":"Zoetermeer",
    "sg:classifiers":[
        {
            "category":"Communications",
            "subcategory":"Television Station",
            "type":"Services"
        }
    ],
    "sg:phone":"+31 79 342 5916",
    "sg:postcode":"2724 GT",
    "sg:province":"Zuid-Holland",
    "sg:tags":[
        "video",
        "audio",
        "verhuur"
    ],
    "wof:name":"Videotheek Avantage",
    "wof:placetype":"venue"
},
  "geometry": {"coordinates":[4.507804,52.067329],"type":"Point"}
}