{
  "type": "Feature",
  "properties": {
    "addr:full":"Eikenlaan 2 Harmelen Utrecht 3481 CN",
    "addr:housenumber":"2",
    "addr:postcode":"3481 cn",
    "addr:street":"Eikenlaan",
    "iso:country":"NL",
    "sg:address":"Eikenlaan 2",
    "sg:city":"Harmelen",
    "sg:orig_category":"Granen, Zaden And Diervoeders Gh",
    "sg:phone":"+31 348 441 920",
    "sg:postcode":"3481 CN",
    "sg:province":"Utrecht",
    "wof:name":"C. Van Schaik Handelsondern En Fourageha",
    "wof:placetype":"venue"
},
  "geometry": {"coordinates":[4.963439,52.089291],"type":"Point"}
}