{
  "type": "Feature",
  "properties": {
    "addr:full":"Croesenstr 51 Haarlem Noord-Holland 2015 JK",
    "addr:housenumber":"51",
    "addr:postcode":"2015 jk",
    "addr:street":"Croesenstr",
    "iso:country":"NL",
    "sg:address":"Croesenstr 51",
    "sg:city":"Haarlem",
    "sg:orig_category":"Kinderopvang",
    "sg:phone":"+31 23 524 3931",
    "sg:postcode":"2015 JK",
    "sg:province":"Noord-Holland",
    "wof:name":"Speeltuin, De",
    "wof:placetype":"venue"
},
  "geometry": {"coordinates":[4.605565,52.381027],"type":"Point"}
}