{
  "type": "Feature",
  "properties": {
    "addr:full":"Vondellaan 7 Schiedam Zuid-Holland 3117 PS",
    "addr:housenumber":"7",
    "addr:postcode":"3117 ps",
    "addr:street":"Vondellaan",
    "iso:country":"NL",
    "sg:address":"Vondellaan 7",
    "sg:city":"Schiedam",
    "sg:orig_category":"Diverse Grafische Activiteiten",
    "sg:phone":"+31 10 426 4274",
    "sg:postcode":"3117 PS",
    "sg:province":"Zuid-Holland",
    "wof:name":"Loonzetterij Schiedam",
    "wof:placetype":"venue"
},
  "geometry": {"coordinates":[4.385932,51.911724],"type":"Point"}
}