{
  "type": "Feature",
  "properties": {
    "addr:full":"Bedrijfsweg 6 Bladel Noord-Brabant 5531 PT",
    "addr:housenumber":"6",
    "addr:postcode":"5531 pt",
    "addr:street":"Bedrijfsweg",
    "iso:country":"NL",
    "sg:address":"Bedrijfsweg 6",
    "sg:city":"Bladel",
    "sg:orig_category":"Metaalafval, Schrootrecycling And Sloperijen",
    "sg:phone":"+31 497 384 680",
    "sg:postcode":"5531 PT",
    "sg:province":"Noord-Brabant",
    "wof:name":"Auto- En Autodemontagebedrijf Van De Hou",
    "wof:placetype":"venue"
},
  "geometry": {"coordinates":[5.196704,51.359608],"type":"Point"}
}