{
  "type": "Feature",
  "properties": {
    "addr:full":"Kruiswg 112 Marum Groningen 9363 AG",
    "addr:housenumber":"112",
    "addr:postcode":"9363",
    "iso:country":"NL",
    "sg:address":"Kruiswg 112",
    "sg:city":"Marum",
    "sg:classifiers":[
        {
            "category":"Sports & Exercise",
            "subcategory":"Stables",
            "type":"Entertainment"
        }
    ],
    "sg:phone":"+31 594 644 558",
    "sg:postcode":"9363 AG",
    "sg:province":"Groningen",
    "sg:tags":[
        "maneges"
    ],
    "wof:name":"Js",
    "wof:placetype":"venue"
},
  "geometry": {"coordinates":[6.28769,53.149933],"type":"Point"}
}