{
  "type": "Feature",
  "properties": {
    "addr:full":"Utrechtsestr 23 Amersfoort Utrecht 3811 LA",
    "addr:housenumber":"23",
    "addr:postcode":"3811 la",
    "addr:street":"Utrechtsestr",
    "iso:country":"NL",
    "sg:address":"Utrechtsestr 23",
    "sg:city":"Amersfoort",
    "sg:orig_category":"Juweliers",
    "sg:phone":"+31 33 463 2834",
    "sg:postcode":"3811 LA",
    "sg:province":"Utrecht",
    "wof:name":"Lucardi",
    "wof:placetype":"venue"
},
  "geometry": {"coordinates":[5.38595,52.154297],"type":"Point"}
}