{
  "type": "Feature",
  "properties": {
    "addr:full":"Bornerbroeksestraat 323 Almelo Overijssel 7606 BN",
    "addr:housenumber":"323",
    "addr:postcode":"7606 bn",
    "addr:street":"Bornerbroeksestraat",
    "iso:country":"NL",
    "sg:address":"Bornerbroeksestraat 323",
    "sg:city":"Almelo",
    "sg:orig_category":"Diverse Consumentenartikelen Gh",
    "sg:phone":"+31 546 828 694",
    "sg:postcode":"7606 BN",
    "sg:province":"Overijssel",
    "wof:name":"P.P.D.A. Klaster",
    "wof:placetype":"venue"
},
  "geometry": {"coordinates":[6.661233,52.341763],"type":"Point"}
}