{
  "type": "Feature",
  "properties": {
    "addr:full":"Bovenweg 87 Sint Pancras Noord-Holland 1834 CC",
    "addr:housenumber":"87",
    "addr:postcode":"1834 cc",
    "addr:street":"Bovenweg",
    "iso:country":"NL",
    "sg:address":"Bovenweg 87",
    "sg:city":"Sint Pancras",
    "sg:orig_category":"Bloemen And Planten",
    "sg:phone":"+31 72 564 2366",
    "sg:postcode":"1834 CC",
    "sg:province":"Noord-Holland",
    "wof:name":"Bloemenmagazijn A. Van Der Velden",
    "wof:placetype":"venue"
},
  "geometry": {"coordinates":[4.783268,52.661026],"type":"Point"}
}