{
  "type": "Feature",
  "properties": {
    "addr:full":"Breed 34 Hoorn Nh North Holland 1621 KC",
    "addr:housenumber":"34",
    "addr:postcode":"1621 kc",
    "addr:street":"Breed;Nh North",
    "iso:country":"NL",
    "sg:address":"Breed 34",
    "sg:city":"Hoorn Nh",
    "sg:orig_category":"Huishoudapparatuur, Televisies And Radio'S",
    "sg:phone":"+31 229 216 266",
    "sg:postcode":"1621 KC",
    "sg:province":"North Holland",
    "wof:name":"Elektro Hahn",
    "wof:placetype":"venue"
},
  "geometry": {"coordinates":[5.053804,52.642178],"type":"Point"}
}