{
  "type": "Feature",
  "properties": {
    "addr:full":"Vaartwijk 7 Axel Colorado 4571 SV",
    "addr:housenumber":"7",
    "addr:postcode":"4571 sv",
    "addr:street":"Vaartwijk;Colorado",
    "iso:country":"NL",
    "sg:address":"Vaartwijk 7",
    "sg:city":"Axel",
    "sg:orig_category":"Bloemen And Planten Gh",
    "sg:phone":"+31 115 561 786",
    "sg:postcode":"4571 SV",
    "sg:province":"Colorado",
    "wof:name":"Kwekerij J. Hollebek",
    "wof:placetype":"venue"
},
  "geometry": {"coordinates":[-107.834,40.048],"type":"Point"}
}