{
  "type": "Feature",
  "properties": {
    "addr:full":"Cyclamenstraat 70 Aalsmeer Noord-Holland 1431 SC",
    "addr:housenumber":"70",
    "addr:postcode":"1431 sc",
    "addr:street":"Cyclamenstraat",
    "iso:country":"NL",
    "sg:address":"Cyclamenstraat 70",
    "sg:city":"Aalsmeer",
    "sg:orig_category":"Overheidsdiensten",
    "sg:phone":"+31 297 326 427",
    "sg:postcode":"1431 SC",
    "sg:province":"Noord-Holland",
    "wof:name":"De Schakel",
    "wof:placetype":"venue"
},
  "geometry": {"coordinates":[4.7599110603,52.2617073059],"type":"Point"}
}