{
  "type": "Feature",
  "properties": {
    "addr:full":"Ruischerwaard 108 Groningen Groningen 9734 CJ",
    "addr:housenumber":"108",
    "addr:postcode":"9734 cj",
    "addr:street":"Ruischerwaard",
    "iso:country":"NL",
    "sg:address":"Ruischerwaard 108",
    "sg:city":"Groningen",
    "sg:orig_category":"Dtp",
    "sg:phone":"+31 50 549 6355",
    "sg:postcode":"9734 CJ",
    "sg:province":"Groningen",
    "wof:name":"Vrolijk",
    "wof:placetype":"venue"
},
  "geometry": {"coordinates":[6.617583,53.228485],"type":"Point"}
}