{
  "type": "Feature",
  "properties": {
    "addr:full":"Kromgouw 77 Almere Flevoland 1352 BD",
    "addr:housenumber":"77",
    "addr:postcode":"1352 bd",
    "addr:street":"Kromgouw;Flevoland",
    "iso:country":"NL",
    "sg:address":"Kromgouw 77",
    "sg:city":"Almere",
    "sg:orig_category":"Krantenuitgeverijen",
    "sg:phone":"+31 36 531 6875",
    "sg:postcode":"1352 BD",
    "sg:province":"Flevoland",
    "wof:name":"Ij. Djah Belinga",
    "wof:placetype":"venue"
},
  "geometry": {"coordinates":[5.216684,52.345451],"type":"Point"}
}