{
  "type": "Feature",
  "properties": {
    "addr:full":"Boerenstr 20 Gorinchem Zuid-Holland 4201 GB",
    "addr:housenumber":"20",
    "addr:postcode":"4201 gb",
    "addr:street":"Boerenstr",
    "iso:country":"NL",
    "sg:address":"Boerenstr 20",
    "sg:city":"Gorinchem",
    "sg:classifiers":[
        {
            "category":"Real Estate",
            "subcategory":"Real Estate Operator",
            "type":"Services"
        }
    ],
    "sg:phone":"+31 183 638 302",
    "sg:postcode":"4201 GB",
    "sg:province":"Zuid-Holland",
    "sg:tags":[
        "appartementen",
        "en",
        "flat"
    ],
    "wof:name":"Home Rent",
    "wof:placetype":"venue"
},
  "geometry": {"coordinates":[4.972266,51.828854],"type":"Point"}
}