{
  "type": "Feature",
  "properties": {
    "addr:full":"Pleinweg 2 Rotterdam South Holland 3083 EB",
    "addr:housenumber":"2",
    "addr:postcode":"3083 eb",
    "addr:street":"Pleinweg",
    "iso:country":"NL",
    "sg:address":"Pleinweg 2",
    "sg:city":"Rotterdam",
    "sg:orig_category":"Werving And Selectie Van Tijdelijk Personeel And Uitzendkantoren",
    "sg:phone":"+31 10 481 1799",
    "sg:postcode":"3083 EB",
    "sg:province":"South Holland",
    "wof:name":"Randstad",
    "wof:placetype":"venue"
},
  "geometry": {"coordinates":[4.4882397652,51.8893623352],"type":"Point"}
}