{
  "type": "Feature",
  "properties": {
    "addr:full":"Ecustr 1 Etten Leur North Brabant 4879 NP",
    "addr:housenumber":"1",
    "addr:postcode":"4879 np",
    "addr:street":"Ecustr",
    "iso:country":"NL",
    "sg:address":"Ecustr 1",
    "sg:city":"Etten Leur",
    "sg:orig_category":"Plafonds",
    "sg:phone":"+31 76 508 8077",
    "sg:postcode":"4879 NP",
    "sg:province":"North Brabant",
    "sg:website":"http://www.comatherm.nl",
    "wof:name":"Gialuxe Bv",
    "wof:placetype":"venue"
},
  "geometry": {"coordinates":[4.610749,51.557434],"type":"Point"}
}