{
  "type": "Feature",
  "properties": {
    "addr:full":"Parallelweg 15 Den Helder North Holland 1781 EA",
    "addr:housenumber":"15",
    "addr:postcode":"1781 ea",
    "addr:street":"Parallelweg",
    "iso:country":"NL",
    "sg:address":"Parallelweg 15",
    "sg:city":"Den Helder",
    "sg:orig_category":"Banken And Kredietinstellingen",
    "sg:phone":"+31 223 540 600",
    "sg:postcode":"1781 EA",
    "sg:province":"North Holland",
    "wof:name":"Ing Bank",
    "wof:placetype":"venue"
},
  "geometry": {"coordinates":[4.761849,52.956375],"type":"Point"}
}