{
  "type": "Feature",
  "properties": {
    "addr:full":"Bosscheweg 255 Tilburg Noord-Brabant 5013 AB",
    "addr:housenumber":"255",
    "addr:postcode":"5013 ab",
    "addr:street":"Bosscheweg",
    "iso:country":"NL",
    "sg:address":"Bosscheweg 255",
    "sg:city":"Tilburg",
    "sg:orig_category":"Metaalwerken",
    "sg:phone":"+31 13 542 5594",
    "sg:postcode":"5013 AB",
    "sg:province":"Noord-Brabant",
    "wof:name":"Carpet-Land",
    "wof:placetype":"venue"
},
  "geometry": {"coordinates":[5.106132,51.562653],"type":"Point"}
}