{
  "type": "Feature",
  "properties": {
    "addr:full":"Voorschoterlaan 50 Rotterdam South Holland 3062 KR",
    "addr:housenumber":"50",
    "addr:postcode":"3062 kr",
    "addr:street":"Voorschoterlaan",
    "iso:country":"NL",
    "sg:address":"Voorschoterlaan 50",
    "sg:city":"Rotterdam",
    "sg:orig_category":"Werving And Selectie Van Vast Personeel",
    "sg:phone":"+31 10 404 5136",
    "sg:postcode":"3062 KR",
    "sg:province":"South Holland",
    "wof:name":"Distichon Management Consultants",
    "wof:placetype":"venue"
},
  "geometry": {"coordinates":[4.5129199028,51.9237442017],"type":"Point"}
}