{
  "type": "Feature",
  "properties": {
    "iso:country":"NL",
    "sg:address":"Byronstr 2",
    "sg:city":"Utrecht",
    "sg:orig_category":"Video - Faciliteiten En Producties",
    "sg:phone":"+31 30 294 3492",
    "sg:postcode":"3533 VX",
    "sg:province":"Utrecht",
    "wof:name":"Byron",
    "wof:placetype":"venue"
},
  "geometry": {"coordinates":[5.086673,52.088634],"type":"Point"}
}