{
  "type": "Feature",
  "properties": {
    "addr:full":"Hessenweg 170 Achterveld Utrecht 3791 PM",
    "addr:housenumber":"170",
    "addr:postcode":"3791 pm",
    "addr:street":"Hessenweg",
    "iso:country":"NL",
    "sg:address":"Hessenweg 170",
    "sg:city":"Achterveld",
    "sg:orig_category":"Verzekeringen",
    "sg:phone":"+31 342 451 879",
    "sg:postcode":"3791 PM",
    "sg:province":"Utrecht",
    "wof:name":"Assurantiekantoor Kerkhof Bv",
    "wof:placetype":"venue"
},
  "geometry": {"coordinates":[5.492022,52.136913],"type":"Point"}
}