{
  "type": "Feature",
  "properties": {
    "addr:full":"Frobenstr 21D Rotterdam Zuid-Holland 3045 RD",
    "addr:housenumber":"21d",
    "addr:postcode":"3045 rd",
    "addr:street":"Frobenstr",
    "iso:country":"NL",
    "sg:address":"Frobenstr 21D",
    "sg:city":"Rotterdam",
    "sg:orig_category":"Verzekeringen - Verzekeringskantoren",
    "sg:phone":"+31 10 461 0377",
    "sg:postcode":"3045 RD",
    "sg:province":"Zuid-Holland",
    "wof:name":"Heinsbroek",
    "wof:placetype":"venue"
},
  "geometry": {"coordinates":[4.46265,51.947491],"type":"Point"}
}