{
  "type": "Feature",
  "properties": {
    "addr:full":"Westerwerf 22 Uitgeest Noord-Holland 1911 JA",
    "addr:housenumber":"22",
    "addr:postcode":"1911 ja",
    "addr:street":"Westerwerf",
    "iso:country":"NL",
    "sg:address":"Westerwerf 22",
    "sg:city":"Uitgeest",
    "sg:orig_category":"Drukkerijen And Copyshops",
    "sg:phone":"+31 251 317 251",
    "sg:postcode":"1911 JA",
    "sg:province":"Noord-Holland",
    "wof:name":"Drukkerij Van Den Boogaard Bv",
    "wof:placetype":"venue"
},
  "geometry": {"coordinates":[4.718559,52.538475],"type":"Point"}
}