{
  "type": "Feature",
  "properties": {
    "addr:full":"Bergsestraat 33 Wouw North Brabant 4724 CA",
    "addr:housenumber":"33",
    "addr:postcode":"4724 ca",
    "addr:street":"Bergsestraat",
    "iso:country":"NL",
    "sg:address":"Bergsestraat 33",
    "sg:city":"Wouw",
    "sg:orig_category":"Kappers",
    "sg:phone":"+31 165 301 277",
    "sg:postcode":"4724 CA",
    "sg:province":"North Brabant",
    "wof:name":"J. Van Wezel",
    "wof:placetype":"venue"
},
  "geometry": {"coordinates":[4.3876338005,51.5203781128],"type":"Point"}
}