{
  "type": "Feature",
  "properties": {
    "addr:full":"Vierde Vogelstraat 19 Amsterdam Noord-Holland 1022 XH",
    "addr:housenumber":"19",
    "addr:postcode":"1022 xh",
    "addr:street":"Vierde Vogelstraat",
    "iso:country":"NL",
    "sg:address":"Vierde Vogelstraat 19",
    "sg:city":"Amsterdam",
    "sg:orig_category":"Elektronische Bedrijfsinstallaties",
    "sg:phone":"+31 20 494 1888",
    "sg:postcode":"1022 XH",
    "sg:province":"Noord-Holland",
    "wof:name":"Safe Klus Amsterdam",
    "wof:placetype":"venue"
},
  "geometry": {"coordinates":[4.928289,52.387638],"type":"Point"}
}