{
  "type": "Feature",
  "properties": {
    "addr:full":"Vryenbansestr 18 Nootdorp South Holland 2631 BD",
    "addr:housenumber":"18",
    "addr:postcode":"2631 bd",
    "addr:street":"Vryenbansestr",
    "iso:country":"NL",
    "sg:address":"Vryenbansestr 18",
    "sg:city":"Nootdorp",
    "sg:orig_category":"Projectinrichting",
    "sg:phone":"+31 15 310 5708",
    "sg:postcode":"2631 BD",
    "sg:province":"South Holland",
    "wof:name":"Hagen, R J P Van",
    "wof:placetype":"venue"
},
  "geometry": {"coordinates":[4.392025,52.042702],"type":"Point"}
}