{
  "type": "Feature",
  "properties": {
    "addr:full":"Derkswg 50 Klazienaveen Drenthe 7891 PL",
    "addr:housenumber":"50",
    "addr:postcode":"7891 pl",
    "addr:street":"Derkswg",
    "iso:country":"NL",
    "sg:address":"Derkswg 50",
    "sg:city":"Klazienaveen",
    "sg:orig_category":"Metaalbewerking",
    "sg:phone":"+31 591 317 909",
    "sg:postcode":"7891 PL",
    "sg:province":"Drenthe",
    "wof:name":"M & I Work",
    "wof:placetype":"venue"
},
  "geometry": {"coordinates":[6.971398,52.720829],"type":"Point"}
}