{
  "type": "Feature",
  "properties": {
    "addr:full":"Walruskoog 10 Alkmaar North Holland 1822 BC",
    "addr:housenumber":"10",
    "addr:postcode":"1822 bc",
    "addr:street":"Walruskoog",
    "iso:country":"NL",
    "sg:address":"Walruskoog 10",
    "sg:city":"Alkmaar",
    "sg:orig_category":"Bouwmaterialen Gh",
    "sg:phone":"+31 72 564 4900",
    "sg:postcode":"1822 BC",
    "sg:province":"North Holland",
    "wof:name":"Kox",
    "wof:placetype":"venue"
},
  "geometry": {"coordinates":[4.786391,52.64732],"type":"Point"}
}