{
  "type": "Feature",
  "properties": {
    "addr:full":"Bagijnestraat 10 Ochten Gelderland 4051 AL",
    "addr:housenumber":"10",
    "addr:postcode":"4051",
    "addr:street":"Bagijnestraat;Gelderland",
    "iso:country":"NL",
    "sg:address":"Bagijnestraat 10",
    "sg:city":"Ochten",
    "sg:orig_category":"Boekhouders",
    "sg:phone":"+31 344 643 580",
    "sg:postcode":"4051 AL",
    "sg:province":"Gelderland",
    "wof:name":"Administratiekantoor Van De Pol",
    "wof:placetype":"venue"
},
  "geometry": {"coordinates":[5.564294,51.907166],"type":"Point"}
}