{
  "type": "Feature",
  "properties": {
    "iso:country":"NL",
    "sg:address":"Singel 1940 1945 157",
    "sg:city":"Oss",
    "sg:orig_category":"Babyartikelen",
    "sg:phone":"+31 412 625 989",
    "sg:postcode":"5348 PK",
    "sg:province":"Virginia",
    "wof:name":"Vereyken Oss, L & M",
    "wof:placetype":"venue"
},
  "geometry": {"coordinates":[-77.235214,38.312599],"type":"Point"}
}