{
  "type": "Feature",
  "properties": {
    "addr:full":"Pieter De Hooghlaan 47 Hilversum Noord-Holland 1213 BR",
    "addr:housenumber":"47",
    "addr:postcode":"1213 br",
    "addr:street":"Pieter De Hooghlaan",
    "iso:country":"NL",
    "sg:address":"Pieter De Hooghlaan 47",
    "sg:city":"Hilversum",
    "sg:orig_category":"Bedrijfs- And Managementsconsultants",
    "sg:phone":"+31 35 640 0975",
    "sg:postcode":"1213 BR",
    "sg:province":"Noord-Holland",
    "wof:name":"E. Scholtes Management Bv",
    "wof:placetype":"venue"
},
  "geometry": {"coordinates":[5.179002,52.214428],"type":"Point"}
}