{
  "type": "Feature",
  "properties": {
    "addr:full":"Morsweg 55 E Leiden Zuid-Holland 2312 AB",
    "addr:housenumber":"55 e",
    "addr:postcode":"2312 ab",
    "addr:street":"Morsweg",
    "iso:country":"NL",
    "sg:address":"Morsweg 55 E",
    "sg:city":"Leiden",
    "sg:orig_category":"Bedrijfs- And Managementsconsultants",
    "sg:phone":"+31 71 514 7375",
    "sg:postcode":"2312 AB",
    "sg:province":"Zuid-Holland",
    "wof:name":"Bfb Communications Bv",
    "wof:placetype":"venue"
},
  "geometry": {"coordinates":[4.49463,52.154572],"type":"Point"}
}