{
  "type": "Feature",
  "properties": {
    "addr:full":"Almystr 14 Oisterwyk Noord-Brabant 5061 PA",
    "addr:housenumber":"14",
    "addr:postcode":"5061 pa",
    "addr:street":"Almystr",
    "iso:country":"NL",
    "sg:address":"Almystr 14",
    "sg:city":"Oisterwyk",
    "sg:orig_category":"Bijouterie?n - Fabrieken En Groothandel",
    "sg:phone":"+31 13 571 9320",
    "sg:postcode":"5061 PA",
    "sg:province":"Noord-Brabant",
    "wof:name":"Hilly'S Bijou Highlights",
    "wof:placetype":"venue"
},
  "geometry": {"coordinates":[5.1821,51.57653],"type":"Point"}
}