{
  "type": "Feature",
  "properties": {
    "addr:full":"Nijverheidsweg 24 Heemstede Noord-Holland 2102 LL",
    "addr:housenumber":"24",
    "addr:postcode":"2102 ll",
    "addr:street":"Nijverheidsweg",
    "iso:country":"NL",
    "sg:address":"Nijverheidsweg 24",
    "sg:city":"Heemstede",
    "sg:orig_category":"Autokeuringen",
    "sg:phone":"+31 23 529 2550",
    "sg:postcode":"2102 LL",
    "sg:province":"Noord-Holland",
    "wof:name":"Merks Autoschade Vof",
    "wof:placetype":"venue"
},
  "geometry": {"coordinates":[4.627272,52.345737],"type":"Point"}
}