{
  "type": "Feature",
  "properties": {
    "addr:full":"Vinkenbroek 16 Etten Leur North Brabant 4871 JD",
    "addr:housenumber":"16",
    "addr:postcode":"4871 jd",
    "addr:street":"Vinkenbroek",
    "iso:country":"NL",
    "sg:address":"Vinkenbroek 16",
    "sg:city":"Etten Leur",
    "sg:orig_category":"Kappers",
    "sg:phone":"+31 6 22811897",
    "sg:postcode":"4871 JD",
    "sg:province":"North Brabant",
    "wof:name":"Kapriolen Hairstyling",
    "wof:placetype":"venue"
},
  "geometry": {"coordinates":[4.6478881836,51.5917549133],"type":"Point"}
}