{
  "type": "Feature",
  "properties": {
    "iso:country":"NL",
    "sg:address":"Ryksstrwg 57",
    "sg:city":"Haarlem",
    "sg:orig_category":"Kappers",
    "sg:phone":"+31 23 526 3679",
    "sg:postcode":"2024 DA",
    "sg:province":"North Holland",
    "wof:name":"Ilse Voor Haar",
    "wof:placetype":"venue"
},
  "geometry": {"coordinates":[4.6376099586,52.4059295654],"type":"Point"}
}