{
  "type": "Feature",
  "properties": {
    "addr:full":"De Hermelyn 40 Driebergen Rysenb Utrecht 3972 TT",
    "addr:housenumber":"40",
    "addr:postcode":"3972 tt",
    "addr:street":"Driebergen Rysenb",
    "iso:country":"NL",
    "sg:address":"De Hermelyn 40",
    "sg:city":"Driebergen Rysenb",
    "sg:orig_category":"Beeldende Kunstenaars",
    "sg:phone":"+31 343 520 976",
    "sg:postcode":"3972 TT",
    "sg:province":"Utrecht",
    "wof:name":"Westerhof",
    "wof:placetype":"venue"
},
  "geometry": {"coordinates":[5.270607,52.045456],"type":"Point"}
}