{
  "type": "Feature",
  "properties": {
    "iso:country":"NL",
    "sg:address":"Bud Abbottstraat 18",
    "sg:city":"Almere",
    "sg:orig_category":"Diverse Consumentenartikelen Gh",
    "sg:phone":"+31 36 537 7263",
    "sg:postcode":"1325 CP",
    "sg:province":"Flevoland",
    "wof:name":"Diva Design",
    "wof:placetype":"venue"
},
  "geometry": {"coordinates":[5.231582,52.375435],"type":"Point"}
}