{
  "type": "Feature",
  "properties": {
    "iso:country":"NL",
    "sg:address":"Ahornstr 25",
    "sg:city":"Kerkrade",
    "sg:orig_category":"Gehandicapteninformatie",
    "sg:phone":"+31 45 546 4890",
    "sg:postcode":"6463 GA",
    "sg:province":"Limburg",
    "sg:website":"http://www.stichting-gips.nl",
    "wof:name":"Gips Zuid-Limburg",
    "wof:placetype":"venue"
},
  "geometry": {"coordinates":[6.069788,50.874172],"type":"Point"}
}