{
  "type": "Feature",
  "properties": {
    "iso:country":"NL",
    "sg:address":"Driesprong 1-3",
    "sg:city":"Zuidland",
    "sg:orig_category":"Kappers",
    "sg:phone":"+31 181 453 154",
    "sg:postcode":"3214 DA",
    "sg:province":"Zuid-Holland",
    "wof:name":"Bernissesteyn",
    "wof:placetype":"venue"
},
  "geometry": {"coordinates":[4.253882885,51.8235092163],"type":"Point"}
}