{
  "type": "Feature",
  "properties": {
    "addr:full":"Wilhelminastraat 47 Sittard Limburg 6131 KM",
    "addr:housenumber":"47",
    "addr:street":"Wilhelminastraat;6131 Km",
    "iso:country":"NL",
    "sg:address":"Wilhelminastraat 47",
    "sg:city":"Sittard",
    "sg:orig_category":"Public Relationbureaus",
    "sg:phone":"+31 46 452 7606",
    "sg:postcode":"6131 KM",
    "sg:province":"Limburg",
    "wof:name":"Van Haalen En Partners",
    "wof:placetype":"venue"
},
  "geometry": {"coordinates":[5.860537,50.999668],"type":"Point"}
}