{
  "type": "Feature",
  "properties": {
    "addr:full":"Burg Baumannln 182 Rotterdam Zuid-Holland 3042 AJ",
    "addr:housenumber":"182",
    "addr:postcode":"3042 aj",
    "addr:street":"Burg",
    "iso:country":"NL",
    "sg:address":"Burg Baumannln 182",
    "sg:city":"Rotterdam",
    "sg:classifiers":[
        {
            "category":"Retail",
            "subcategory":"Auto Repair",
            "type":"Services"
        }
    ],
    "sg:phone":"+31 10 415 7403",
    "sg:postcode":"3042 AJ",
    "sg:province":"Zuid-Holland",
    "sg:tags":[
        "garage"
    ],
    "wof:name":"Willem",
    "wof:placetype":"venue"
},
  "geometry": {"coordinates":[4.428171,51.934364],"type":"Point"}
}