{
  "type": "Feature",
  "properties": {
    "addr:full":"Kesselskade 64 Maastricht Limburg 6211 EN",
    "addr:housenumber":"64",
    "addr:postcode":"6211 en",
    "addr:street":"Kesselskade",
    "iso:country":"NL",
    "sg:address":"Kesselskade 64",
    "sg:city":"Maastricht",
    "sg:orig_category":"Opticiens",
    "sg:phone":"+31 43 321 4732",
    "sg:postcode":"6211 EN",
    "sg:province":"Limburg",
    "wof:name":"Optiek Carl Kramp Bv",
    "wof:placetype":"venue"
},
  "geometry": {"coordinates":[5.6939668655,50.8495140076],"type":"Point"}
}