{
  "type": "Feature",
  "properties": {
    "addr:full":"Postbus 246 Nieuwegein Utrecht 3430 AE",
    "addr:housenumber":"246",
    "addr:postcode":"3430 ae",
    "addr:street":"Postbus",
    "iso:country":"NL",
    "sg:address":"Postbus 246",
    "sg:city":"Nieuwegein",
    "sg:orig_category":"Touringcars",
    "sg:phone":"+31 30 605 2207",
    "sg:postcode":"3430 AE",
    "sg:province":"Utrecht",
    "wof:name":"Starterbus",
    "wof:placetype":"venue"
},
  "geometry": {"coordinates":[5.082197,52.027325],"type":"Point"}
}