{
  "type": "Feature",
  "properties": {
    "addr:full":"Zuidbrink 12 Westerbork Drenthe 9431 AR",
    "addr:housenumber":"12",
    "addr:postcode":"9431",
    "addr:street":"Zuidbrink",
    "iso:country":"NL",
    "sg:address":"Zuidbrink 12",
    "sg:city":"Westerbork",
    "sg:orig_category":"Boekhouders",
    "sg:phone":"+31 593 333 700",
    "sg:postcode":"9431 AR",
    "sg:province":"Drenthe",
    "wof:name":"Raad Midden Drenthe",
    "wof:placetype":"venue"
},
  "geometry": {"coordinates":[6.612489,52.848373],"type":"Point"}
}