{
  "type": "Feature",
  "properties": {
    "addr:full":"Jonge Hagen 28 Mheer Limburg 6261 NL",
    "addr:housenumber":"28",
    "addr:postcode":"6261 nl",
    "addr:street":"Jonge Hagen",
    "iso:country":"NL",
    "sg:address":"Jonge Hagen 28",
    "sg:city":"Mheer",
    "sg:orig_category":"Psychotherapeuten",
    "sg:phone":"+31 43 457 1494",
    "sg:postcode":"6261 NL",
    "sg:province":"Limburg",
    "wof:name":"Meijer Prakt V Psychother, Drs R R De",
    "wof:placetype":"venue"
},
  "geometry": {"coordinates":[5.795053,50.78326],"type":"Point"}
}