{
  "type": "Feature",
  "properties": {
    "iso:country":"NL",
    "sg:address":"Dinteloordstr 68",
    "sg:city":"Rotterdam",
    "sg:orig_category":"Onroerende Goederen",
    "sg:phone":"+31 10 410 2516",
    "sg:postcode":"3086 VV",
    "sg:province":"South Holland",
    "wof:name":"Rasave Bv",
    "wof:placetype":"venue"
},
  "geometry": {"coordinates":[4.469968,51.870895],"type":"Point"}
}