{
  "type": "Feature",
  "properties": {
    "addr:full":"De Zodde 14 Loosdrecht Noord-Holland 1231 MB",
    "addr:housenumber":"14",
    "addr:postcode":"1231 mb",
    "addr:street":"De Zodde",
    "iso:country":"NL",
    "sg:address":"De Zodde 14",
    "sg:city":"Loosdrecht",
    "sg:orig_category":"Geluidsinstallaties",
    "sg:phone":"+31 35 582 5454",
    "sg:postcode":"1231 MB",
    "sg:province":"Noord-Holland",
    "wof:name":"Pie?e",
    "wof:placetype":"venue"
},
  "geometry": {"coordinates":[5.113669,52.209412],"type":"Point"}
}