{
  "type": "Feature",
  "properties": {
    "iso:country":"NL",
    "sg:address":"Australieweg 26",
    "sg:city":"Hulst",
    "sg:orig_category":"Goederenvervoer Over De Weg",
    "sg:phone":"+31 114 370 033",
    "sg:postcode":"4561 PD",
    "sg:province":"Zeeland",
    "wof:name":"Roland De Block",
    "wof:placetype":"venue"
},
  "geometry": {"coordinates":[4.036714,51.269737],"type":"Point"}
}