{
  "type": "Feature",
  "properties": {
    "addr:full":"Klaproosstr 7 Ommen Overijssel 7731 WC",
    "addr:housenumber":"7",
    "addr:postcode":"7731 wc",
    "addr:street":"Klaproosstr",
    "iso:country":"NL",
    "sg:address":"Klaproosstr 7",
    "sg:city":"Ommen",
    "sg:orig_category":"Adviesbureaus Bedrijfsorganisatie",
    "sg:phone":"+31 6 22972559",
    "sg:postcode":"7731 WC",
    "sg:province":"Overijssel",
    "wof:name":"B & J",
    "wof:placetype":"venue"
},
  "geometry": {"coordinates":[6.434345,52.524811],"type":"Point"}
}