{
  "type": "Feature",
  "properties": {
    "addr:full":"Prof. Mr. P.J. Oudlaan 1 Purmerend Noord-Holland 1444 HT",
    "addr:housenumber":"1",
    "addr:postcode":"1444 ht",
    "addr:street":"Mr. P.J. Oudlaan",
    "iso:country":"NL",
    "sg:address":"Prof. Mr. P.J. Oudlaan 1",
    "sg:city":"Purmerend",
    "sg:orig_category":"Bejaardeninstellingen And Serviceflats",
    "sg:phone":"+31 299 427 451",
    "sg:postcode":"1444 HT",
    "sg:province":"Noord-Holland",
    "wof:name":"Zorgcirkel Waterland Locatie Overwere",
    "wof:placetype":"venue"
},
  "geometry": {"coordinates":[4.961423,52.518936],"type":"Point"}
}