{
  "type": "Feature",
  "properties": {
    "addr:full":"Rozenstraat 73 Didam Gelderland 6942 WG",
    "addr:housenumber":"73",
    "addr:postcode":"6942 wg",
    "addr:street":"Rozenstraat;Gelderland",
    "iso:country":"NL",
    "sg:address":"Rozenstraat 73",
    "sg:city":"Didam",
    "sg:orig_category":"Kinderopvang Behalve Thuis",
    "sg:phone":"+31 316 229 145",
    "sg:postcode":"6942 WG",
    "sg:province":"Gelderland",
    "wof:name":"Didam Stichting Kinderopvang",
    "wof:placetype":"venue"
},
  "geometry": {"coordinates":[6.135776,51.944637],"type":"Point"}
}