{
  "type": "Feature",
  "properties": {
    "addr:full":"Coevorderstraatweg 28 Noordscheschut Provincie Drenthe 7914 TM",
    "addr:housenumber":"28",
    "addr:postcode":"7914 tm",
    "addr:street":"Coevorderstraatweg;Provincie Drenthe",
    "iso:country":"NL",
    "sg:address":"Coevorderstraatweg 28",
    "sg:city":"Noordscheschut",
    "sg:orig_category":"Hout Gh",
    "sg:phone":"+31 528 341 407",
    "sg:postcode":"7914 TM",
    "sg:province":"Provincie Drenthe",
    "wof:name":"Houthandel G. Koster En Zn",
    "wof:placetype":"venue"
},
  "geometry": {"coordinates":[6.531148,52.720867],"type":"Point"}
}