{
  "type": "Feature",
  "properties": {
    "iso:country":"NL",
    "sg:address":"De Clomp 3130",
    "sg:city":"Zeist",
    "sg:orig_category":"Kantoorartikelen",
    "sg:phone":"+31 30 695 6565",
    "sg:postcode":"3704 KA",
    "sg:province":"Utrecht",
    "wof:name":"Van Der Sluys, Pauw Vof",
    "wof:placetype":"venue"
},
  "geometry": {"coordinates":[5.2192978859,52.0830574036],"type":"Point"}
}