{
  "type": "Feature",
  "properties": {
    "addr:full":"Kelvinbaan 16 Nieuwegein Utrecht 3439 MT",
    "addr:housenumber":"16",
    "addr:postcode":"3439 mt",
    "addr:street":"Kelvinbaan",
    "iso:country":"NL",
    "sg:address":"Kelvinbaan 16",
    "sg:city":"Nieuwegein",
    "sg:orig_category":"Onderzoekbureaus",
    "sg:phone":"+31 30 607 5957",
    "sg:postcode":"3439 MT",
    "sg:province":"Utrecht",
    "wof:name":"Skf",
    "wof:placetype":"venue"
},
  "geometry": {"coordinates":[5.096895,52.031776],"type":"Point"}
}