{
  "type": "Feature",
  "properties": {
    "addr:full":"St Ignatiusstr 13 Venlo Limburg 5915 VL",
    "addr:housenumber":"13",
    "addr:postcode":"5915 vl",
    "iso:country":"NL",
    "sg:address":"St Ignatiusstr 13",
    "sg:city":"Venlo",
    "sg:classifiers":[
        {
            "category":"Personal",
            "subcategory":"Nail Salon",
            "type":"Services"
        }
    ],
    "sg:phone":"+31 77 354 1996",
    "sg:postcode":"5915 VL",
    "sg:province":"Limburg",
    "sg:tags":[
        "pedicure"
    ],
    "wof:name":"Ulft, Annemiek Van",
    "wof:placetype":"venue"
},
  "geometry": {"coordinates":[6.182988,51.359024],"type":"Point"}
}