{
  "type": "Feature",
  "properties": {
    "addr:full":"Transformatorweg 30 Amsterdam Noord-Holland 1014 AK",
    "addr:housenumber":"30",
    "addr:postcode":"1014 ak",
    "addr:street":"Transformatorweg",
    "iso:country":"NL",
    "sg:address":"Transformatorweg 30",
    "sg:city":"Amsterdam",
    "sg:classifiers":[
        {
            "category":"Fast Food",
            "type":"Food & Drink"
        }
    ],
    "sg:phone":"+31 20 686 2569",
    "sg:postcode":"1014 AK",
    "sg:province":"Noord-Holland",
    "sg:tags":[
        "afhaal",
        "restaurant"
    ],
    "wof:name":"Tiny Snackbar",
    "wof:placetype":"venue"
},
  "geometry": {"coordinates":[4.851355,52.392284],"type":"Point"}
}