{
  "type": "Feature",
  "properties": {
    "addr:full":"J Brunnekreefstr 41 Oisterwyk Noord-Brabant 5063 AE",
    "addr:housenumber":"41",
    "addr:postcode":"5063 ae",
    "addr:street":"Oisterwyk",
    "iso:country":"NL",
    "sg:address":"J Brunnekreefstr 41",
    "sg:city":"Oisterwyk",
    "sg:orig_category":"Plafonds",
    "sg:phone":"+31 13 528 6715",
    "sg:postcode":"5063 AE",
    "sg:province":"Noord-Brabant",
    "wof:name":"Dentho",
    "wof:placetype":"venue"
},
  "geometry": {"coordinates":[5.169902,51.579182],"type":"Point"}
}