{
  "type": "Feature",
  "properties": {
    "iso:country":"NL",
    "sg:address":"J Brunnekreefstr 41",
    "sg:city":"Oisterwyk",
    "sg:orig_category":"Plafonds",
    "sg:phone":"+31 13 528 6715",
    "sg:postcode":"5063 AE",
    "sg:province":"Noord-Brabant",
    "wof:name":"Dentho",
    "wof:placetype":"venue"
},
  "geometry": {"coordinates":[5.169902,51.579182],"type":"Point"}
}