{
  "type": "Feature",
  "properties": {
    "addr:full":"Van Foreestweg 109 Den Helder Noord-Holland 1788 BP",
    "addr:housenumber":"109",
    "addr:postcode":"1788 bp",
    "addr:street":"Van Foreestweg",
    "iso:country":"NL",
    "sg:address":"Van Foreestweg 109",
    "sg:city":"Den Helder",
    "sg:orig_category":"Kappers",
    "sg:phone":"+31 223 646 249",
    "sg:postcode":"1788 BP",
    "sg:province":"Noord-Holland",
    "wof:name":"Kapsalon Head Lines",
    "wof:placetype":"venue"
},
  "geometry": {"coordinates":[4.7504220009,52.8981437683],"type":"Point"}
}