{
  "type": "Feature",
  "properties": {
    "addr:full":"Rykswg 81G Naarden Noord-Holland 1411 GE",
    "addr:housenumber":"81g",
    "addr:postcode":"1411",
    "addr:street":"Rykswg",
    "iso:country":"NL",
    "sg:address":"Rykswg 81G",
    "sg:city":"Naarden",
    "sg:orig_category":"Werving En Selectie",
    "sg:phone":"+31 35 694 8014",
    "sg:postcode":"1411 GE",
    "sg:province":"Noord-Holland",
    "sg:website":"http://www.epc-search.nl",
    "wof:name":"European Personnel Counsellors Bv",
    "wof:placetype":"venue"
},
  "geometry": {"coordinates":[5.1302709579,52.3071365356],"type":"Point"}
}