{
  "type": "Feature",
  "properties": {
    "addr:full":"Zijlweg 46 Haarlem Noord-Holland 2013 DJ",
    "addr:housenumber":"46",
    "addr:postcode":"2013 dj",
    "addr:street":"Zijlweg",
    "iso:country":"NL",
    "sg:address":"Zijlweg 46",
    "sg:city":"Haarlem",
    "sg:orig_category":"Verzekeringen",
    "sg:phone":"+31 23 534 3631",
    "sg:postcode":"2013 DJ",
    "sg:province":"Noord-Holland",
    "wof:name":"Vof Assurantiekantoor Bartelsman",
    "wof:placetype":"venue"
},
  "geometry": {"coordinates":[4.626435,52.384377],"type":"Point"}
}