{
  "type": "Feature",
  "properties": {
    "addr:full":"Mgr Borretwg 10 Grave Noord-Brabant 5361 AR",
    "addr:housenumber":"10",
    "addr:postcode":"5361",
    "addr:street":"Borretwg",
    "iso:country":"NL",
    "sg:address":"Mgr Borretwg 10",
    "sg:city":"Grave",
    "sg:orig_category":"Verenigingen En Stichtingen",
    "sg:phone":"+31 486 476 616",
    "sg:postcode":"5361 AR",
    "sg:province":"Noord-Brabant",
    "wof:name":"Geneste, Scoutinggroep Mgr De",
    "wof:placetype":"venue"
},
  "geometry": {"coordinates":[-67.340683,-29.09403],"type":"Point"}
}