{
  "type": "Feature",
  "properties": {
    "iso:country":"NL",
    "sg:address":"Natriumwg 12",
    "sg:city":"Amersfoort",
    "sg:orig_category":"Loodgieters",
    "sg:phone":"+31 33 463 2153",
    "sg:postcode":"3812 PV",
    "sg:province":"Utrecht",
    "wof:name":"Foppen, J",
    "wof:placetype":"venue"
},
  "geometry": {"coordinates":[5.363873,52.167278],"type":"Point"}
}