{
  "type": "Feature",
  "properties": {
    "addr:full":"T Bosmanln 28 Hoogmade South Holland 2355 DB",
    "addr:housenumber":"28",
    "addr:postcode":"2355 db",
    "iso:country":"NL",
    "sg:address":"T Bosmanln 28",
    "sg:city":"Hoogmade",
    "sg:orig_category":"Bloemen En Planten",
    "sg:phone":"+31 71 501 2612",
    "sg:postcode":"2355 DB",
    "sg:province":"South Holland",
    "wof:name":"Kauffman, A L",
    "wof:placetype":"venue"
},
  "geometry": {"coordinates":[4.577427,52.168674],"type":"Point"}
}