{
  "type": "Feature",
  "properties": {
    "iso:country":"NL",
    "sg:address":"Nieuw Putoor 1",
    "sg:city":"Breda",
    "sg:orig_category":"Boekhouders",
    "sg:phone":"+31 76 543 0080",
    "sg:postcode":"4823 GH",
    "sg:province":"North Brabant",
    "wof:name":"Admicare",
    "wof:placetype":"venue"
},
  "geometry": {"coordinates":[4.75503,51.624001],"type":"Point"}
}