{
  "type": "Feature",
  "properties": {
    "addr:full":"M Veningastr 85 Hoogezand Groningen 9601 KD",
    "addr:housenumber":"85",
    "addr:postcode":"9601 kd",
    "iso:country":"NL",
    "sg:address":"M Veningastr 85",
    "sg:city":"Hoogezand",
    "sg:orig_category":"Helderzienden",
    "sg:phone":"+31 598 393 306",
    "sg:postcode":"9601 KD",
    "sg:province":"Groningen",
    "wof:name":"Lien Massink-Faber",
    "wof:placetype":"venue"
},
  "geometry": {"coordinates":[6.74937,53.163589],"type":"Point"}
}