{
  "type": "Feature",
  "properties": {
    "addr:full":"Vondelln 43 Utrecht Utrecht 3521 GC",
    "addr:housenumber":"43",
    "addr:postcode":"3521 gc",
    "addr:street":"Vondelln",
    "iso:country":"NL",
    "sg:address":"Vondelln 43",
    "sg:city":"Utrecht",
    "sg:orig_category":"Herenkleding",
    "sg:phone":"+31 30 293 0524",
    "sg:postcode":"3521 GC",
    "sg:province":"Utrecht",
    "wof:name":"Ven, Jac Van De",
    "wof:placetype":"venue"
},
  "geometry": {"coordinates":[5.11037,52.084572],"type":"Point"}
}