{
  "type": "Feature",
  "properties": {
    "addr:full":"Eduard Van Beinumstraat 59 Leiden Zuid-Holland 2324 KN",
    "addr:housenumber":"59",
    "addr:postcode":"2324 kn",
    "addr:street":"Eduard Van Beinumstraat",
    "iso:country":"NL",
    "sg:address":"Eduard Van Beinumstraat 59",
    "sg:city":"Leiden",
    "sg:orig_category":"Begrafenisondernemers",
    "sg:phone":"+31 71 532 2071",
    "sg:postcode":"2324 KN",
    "sg:province":"Zuid-Holland",
    "wof:name":"B De Boer Uitvaartzorg Huisdieren",
    "wof:placetype":"venue"
},
  "geometry": {"coordinates":[4.474109,52.145721],"type":"Point"}
}