{
  "type": "Feature",
  "properties": {
    "iso:country":"NL",
    "sg:address":"Rotterd Airp Pln 60",
    "sg:city":"Rotterdam",
    "sg:orig_category":"Luchtvaart- Maatschappijen",
    "sg:phone":"+31 10 415 7777",
    "sg:postcode":"3045 AP",
    "sg:province":"Zuid-Holland",
    "sg:website":"http://www.vlm-airlines.com",
    "wof:name":"Vlm Airlines",
    "wof:placetype":"venue"
},
  "geometry": {"coordinates":[4.43378,51.948936],"type":"Point"}
}