{
  "type": "Feature",
  "properties": {
    "addr:full":"Markt 102 Almere Flevoland 1354 AZ",
    "addr:housenumber":"102",
    "addr:postcode":"1354",
    "addr:street":"Markt;Flevoland",
    "iso:country":"NL",
    "sg:address":"Markt 102",
    "sg:city":"Almere",
    "sg:orig_category":"Opticiens",
    "sg:phone":"+31 36 538 6002",
    "sg:postcode":"1354 AZ",
    "sg:province":"Flevoland",
    "sg:website":"http://www.rijffkompleetoptiek.nl",
    "wof:name":"Rijff",
    "wof:placetype":"venue"
},
  "geometry": {"coordinates":[5.2186331749,52.3365097046],"type":"Point"}
}