{
  "type": "Feature",
  "properties": {
    "addr:full":"Molecaten 46 Barneveld Gelderland 3772 LN",
    "addr:housenumber":"46",
    "addr:postcode":"3772 ln",
    "addr:street":"Molecaten;Gelderland",
    "iso:country":"NL",
    "sg:address":"Molecaten 46",
    "sg:city":"Barneveld",
    "sg:orig_category":"Goederenvervoer Over De Weg",
    "sg:phone":"+31 342 417 288",
    "sg:postcode":"3772 LN",
    "sg:province":"Gelderland",
    "wof:name":"Transportbedrijf Pater & Zn Bv",
    "wof:placetype":"venue"
},
  "geometry": {"coordinates":[5.586828,52.131844],"type":"Point"}
}