{
  "type": "Feature",
  "properties": {
    "addr:full":"Broekheurnerwg 76 Haaksbergen NL.08 7481 PZ",
    "addr:housenumber":"76;nl.08",
    "addr:postcode":"7481 pz",
    "addr:street":"Broekheurnerwg",
    "iso:country":"NL",
    "sg:address":"Broekheurnerwg 76",
    "sg:city":"Haaksbergen",
    "sg:orig_category":"Juridische Adviseurs",
    "sg:phone":"+31 53 569 6423",
    "sg:postcode":"7481 PZ",
    "sg:province":"NL.08",
    "wof:name":"Kamphuis, Mr H A M",
    "wof:placetype":"venue"
},
  "geometry": {"coordinates":[6.82766,52.14785],"type":"Point"}
}