{
  "type": "Feature",
  "properties": {
    "addr:full":"Kastelenwg 1-3 Sittard Limburg 6136 BK",
    "addr:housenumber":"1-3",
    "addr:postcode":"6136 bk",
    "addr:street":"Kastelenwg",
    "iso:country":"NL",
    "sg:address":"Kastelenwg 1-3",
    "sg:city":"Sittard",
    "sg:orig_category":"Verenigingen En Stichtingen",
    "sg:phone":"+31 46 451 8914",
    "sg:postcode":"6136 BK",
    "sg:province":"Limburg",
    "wof:name":"Karwei, Sticht Het",
    "wof:placetype":"venue"
},
  "geometry": {"coordinates":[5.870673,51.010185],"type":"Point"}
}