{
  "type": "Feature",
  "properties": {
    "addr:full":"Mecklenburgstraat 1 Eindhoven Noord-Brabant 5615 PZ",
    "addr:housenumber":"1",
    "addr:postcode":"5615 pz",
    "addr:street":"Mecklenburgstraat",
    "iso:country":"NL",
    "sg:address":"Mecklenburgstraat 1",
    "sg:city":"Eindhoven",
    "sg:orig_category":"Verlichting And Huishoudartikelen",
    "sg:phone":"+31 40 246 3602",
    "sg:postcode":"5615 PZ",
    "sg:province":"Noord-Brabant",
    "wof:name":"Van Dam Woon En Lichtwereld",
    "wof:placetype":"venue"
},
  "geometry": {"coordinates":[5.471381,51.435188],"type":"Point"}
}