{
  "type": "Feature",
  "properties": {
    "addr:full":"Tuchthuisstr 4 Haarlem Noord-Holland 2011 XK",
    "addr:housenumber":"4",
    "addr:postcode":"2011 xk",
    "addr:street":"Tuchthuisstr",
    "iso:country":"NL",
    "sg:address":"Tuchthuisstr 4",
    "sg:city":"Haarlem",
    "sg:orig_category":"Verzekeringen - Verzekeringskantoren",
    "sg:phone":"+31 23 542 7230",
    "sg:postcode":"2011 XK",
    "sg:province":"Noord-Holland",
    "wof:name":"Europays",
    "wof:placetype":"venue"
},
  "geometry": {"coordinates":[4.631007,52.37952],"type":"Point"}
}