{
  "type": "Feature",
  "properties": {
    "addr:full":"Van Foreestlaan 17 Alphen A/D Rijn Zuid-Holland 2404 HC",
    "addr:housenumber":"17",
    "addr:postcode":"2404 hc",
    "addr:street":"Van Foreestlaan",
    "iso:country":"NL",
    "sg:address":"Van Foreestlaan 17",
    "sg:city":"Alphen A/D Rijn",
    "sg:orig_category":"Verzekeringen",
    "sg:phone":"+31 172 422 623",
    "sg:postcode":"2404 HC",
    "sg:province":"Zuid-Holland",
    "wof:name":"Assurantiekantoor Valaska",
    "wof:placetype":"venue"
},
  "geometry": {"coordinates":[4.645632,52.14027],"type":"Point"}
}