{
  "type": "Feature",
  "properties": {
    "iso:country":"NL",
    "sg:address":"Kerkveldweg 1",
    "sg:city":"Landgraaf",
    "sg:orig_category":"Kampeerterreinen",
    "sg:phone":"+31 45 532 1747",
    "sg:postcode":"6374 LE",
    "sg:province":"Limburg",
    "wof:name":"Camping De Watertoren",
    "wof:placetype":"venue"
},
  "geometry": {"coordinates":[6.073428154,50.9103355408],"type":"Point"}
}