{
  "type": "Feature",
  "properties": {
    "addr:full":"Winschoterdiep 19 Groningen Groningen 9724 GH",
    "addr:housenumber":"19",
    "addr:postcode":"9724 gh",
    "addr:street":"Winschoterdiep",
    "iso:country":"NL",
    "sg:address":"Winschoterdiep 19",
    "sg:city":"Groningen",
    "sg:orig_category":"Schilderwerk",
    "sg:phone":"+31 50 312 9226",
    "sg:postcode":"9724 GH",
    "sg:province":"Groningen",
    "wof:name":"Schoonbeek En Groen",
    "wof:placetype":"venue"
},
  "geometry": {"coordinates":[6.579588,53.213772],"type":"Point"}
}