{
  "type": "Feature",
  "properties": {
    "addr:full":"Dirk Kleimanstraat 26 Zaandam Noord-Holland 1502 XG",
    "addr:housenumber":"26",
    "addr:postcode":"1502 xg",
    "addr:street":"Dirk Kleimanstraat",
    "iso:country":"NL",
    "sg:address":"Dirk Kleimanstraat 26",
    "sg:city":"Zaandam",
    "sg:classifiers":[
        {
            "category":"Fast Food",
            "type":"Food & Drink"
        }
    ],
    "sg:phone":"+31 75 612 5325",
    "sg:postcode":"1502 XG",
    "sg:province":"Noord-Holland",
    "sg:tags":[
        "afhaal",
        "restaurant"
    ],
    "wof:name":"Tenca Snacks",
    "wof:placetype":"venue"
},
  "geometry": {"coordinates":[4.833398,52.442795],"type":"Point"}
}