{
  "type": "Feature",
  "properties": {
    "iso:country":"NL",
    "sg:address":"Dr V Noortstr 214",
    "sg:city":"Leidschendam",
    "sg:orig_category":"Zand En Grind - Vervoer",
    "sg:phone":"+31 71 580 3359",
    "sg:postcode":"2266 HC",
    "sg:province":"Zuid-Holland",
    "wof:name":"Cees Luiten",
    "wof:placetype":"venue"
},
  "geometry": {"coordinates":[4.4389,52.096062],"type":"Point"}
}