{
  "type": "Feature",
  "properties": {
    "addr:full":"Prinsengracht 747 Amsterdam Noord-Holland 1017 JX",
    "addr:housenumber":"747",
    "addr:postcode":"1017 jx",
    "addr:street":"Prinsengracht",
    "iso:country":"NL",
    "sg:address":"Prinsengracht 747",
    "sg:city":"Amsterdam",
    "sg:orig_category":"Boekenuitgeverijen",
    "sg:phone":"+31 20 622 6107",
    "sg:postcode":"1017 JX",
    "sg:province":"Noord-Holland",
    "wof:name":"Uitgeverij Boom",
    "wof:placetype":"venue"
},
  "geometry": {"coordinates":[4.886331,52.364212],"type":"Point"}
}