{
  "type": "Feature",
  "properties": {
    "addr:full":"Oude Breestraat 43 Sint Anthonis Noord-Brabant 5845  A",
    "addr:housenumber":"43;5845 a",
    "addr:postcode":"anthonis",
    "addr:street":"Oude Breestraat",
    "iso:country":"NL",
    "sg:address":"Oude Breestraat 43",
    "sg:city":"Sint Anthonis",
    "sg:orig_category":"Vertaal- And Tolkenbureaus",
    "sg:phone":"+31 485 381 686",
    "sg:postcode":"5845  A",
    "sg:province":"Noord-Brabant",
    "wof:name":"Gkz Vertaalwerk",
    "wof:placetype":"venue"
},
  "geometry": {"coordinates":[5.887586,51.628139],"type":"Point"}
}