{
  "type": "Feature",
  "properties": {
    "addr:full":"Halverwege 5 Alphen Aan Den Ryn Zuid-Holland 2402 NK",
    "addr:housenumber":"5",
    "addr:postcode":"2402 nk",
    "addr:street":"Halverwege;Aan Den Ryn",
    "iso:country":"NL",
    "sg:address":"Halverwege 5",
    "sg:city":"Alphen Aan Den Ryn",
    "sg:orig_category":"Accountants - Administratie- Consulenten En -Kantoren",
    "sg:phone":"+31 172 430 774",
    "sg:postcode":"2402 NK",
    "sg:province":"Zuid-Holland",
    "wof:name":"Arenthals Grant Thornton",
    "wof:placetype":"venue"
},
  "geometry": {"coordinates":[4.660378,52.144287],"type":"Point"}
}