{
  "type": "Feature",
  "properties": {
    "addr:full":"Kortland 5 Lopikerkapel Utrecht 3412 KW",
    "addr:housenumber":"5",
    "addr:postcode":"3412 kw",
    "addr:street":"Kortland",
    "iso:country":"NL",
    "sg:address":"Kortland 5",
    "sg:city":"Lopikerkapel",
    "sg:orig_category":"Verhuur Bouwmachines",
    "sg:phone":"+31 348 483 208",
    "sg:postcode":"3412 KW",
    "sg:province":"Utrecht",
    "wof:name":"Hb Vof",
    "wof:placetype":"venue"
},
  "geometry": {"coordinates":[5.004267,51.982925],"type":"Point"}
}