{
  "type": "Feature",
  "properties": {
    "addr:full":"De Hermelyn 49 Driebergen Rysenb Utrecht 3972 TS",
    "addr:housenumber":"49",
    "addr:postcode":"3972 ts",
    "addr:street":"Rysenb",
    "iso:country":"NL",
    "sg:address":"De Hermelyn 49",
    "sg:city":"Driebergen Rysenb",
    "sg:orig_category":"Sportverenigingen En Ontspannings- Verenigingen",
    "sg:phone":"+31 343 516 312",
    "sg:postcode":"3972 TS",
    "sg:province":"Utrecht",
    "wof:name":"Gooise Wandelsport Bond, Sticht",
    "wof:placetype":"venue"
},
  "geometry": {"coordinates":[5.271084,52.04541],"type":"Point"}
}