{
  "type": "Feature",
  "properties": {
    "addr:full":"Constantijn Huygensstr 11 Rijssen Overijssel 7461 ZH",
    "addr:housenumber":"11",
    "addr:postcode":"7461 zh",
    "iso:country":"NL",
    "sg:address":"Constantijn Huygensstr 11",
    "sg:city":"Rijssen",
    "sg:orig_category":"Metaalbekleding And -Behandeling",
    "sg:phone":"+31 548 517 176",
    "sg:postcode":"7461 ZH",
    "sg:province":"Overijssel",
    "wof:name":"G.J. Brinks",
    "wof:placetype":"venue"
},
  "geometry": {"coordinates":[6.525551,52.298512],"type":"Point"}
}