{
  "type": "Feature",
  "properties": {
    "iso:country":"NL",
    "sg:address":"Burgemeester Elkhuizenln 37",
    "sg:city":"Halsteren",
    "sg:orig_category":"Kappers",
    "sg:phone":"+31 164 683 394",
    "sg:postcode":"4661 CH",
    "sg:province":"North Brabant",
    "wof:name":"Haarstudio Miranda",
    "wof:placetype":"venue"
},
  "geometry": {"coordinates":[4.2714080811,51.5341072083],"type":"Point"}
}