{
  "type": "Feature",
  "properties": {
    "addr:full":"Wildehornstersingel 3 Haskerhorne Provincie Friesland 8506 AC",
    "addr:housenumber":"3",
    "addr:postcode":"8506 ac",
    "addr:street":"Wildehornstersingel;Provincie Friesland",
    "iso:country":"NL",
    "sg:address":"Wildehornstersingel 3",
    "sg:city":"Haskerhorne",
    "sg:orig_category":"Levende Dieren Gh",
    "sg:phone":"+31 513 412 239",
    "sg:postcode":"8506 AC",
    "sg:province":"Provincie Friesland",
    "wof:name":"T.A. Crow",
    "wof:placetype":"venue"
},
  "geometry": {"coordinates":[5.823896,52.966267],"type":"Point"}
}