{
  "type": "Feature",
  "properties": {
    "iso:country":"NL",
    "sg:address":"Vleeshouwersstraat 50",
    "sg:city":"Dordrecht",
    "sg:classifiers":[
        {
            "category":"Shopping",
            "subcategory":"Gifts & Souvenirs",
            "type":"Retail Goods"
        }
    ],
    "sg:phone":"+31 78 614 9435",
    "sg:postcode":"3311 CS",
    "sg:province":"Zuid-Holland",
    "sg:tags":[
        "geschenken"
    ],
    "wof:name":"Jettie Ponte",
    "wof:placetype":"venue"
},
  "geometry": {"coordinates":[4.664275,51.814919],"type":"Point"}
}