{
  "type": "Feature",
  "properties": {
    "iso:country":"NL",
    "sg:address":"Park 1",
    "sg:city":"Nuenen",
    "sg:orig_category":"Fotoreportages",
    "sg:phone":"+31 6 41276444",
    "sg:postcode":"5671 GA",
    "sg:province":"North Brabant",
    "sg:website":"http://www.foto-grafisch.com",
    "wof:name":"Foto Grafisch",
    "wof:placetype":"venue"
},
  "geometry": {"coordinates":[5.548101,51.47419],"type":"Point"}
}