{
  "type": "Feature",
  "properties": {
    "addr:full":"Stadionkd 146 Iii Amsterdam Noord-Holland 1076 BV",
    "addr:housenumber":"146",
    "addr:postcode":"1076 bv",
    "iso:country":"NL",
    "sg:address":"Stadionkd 146 Iii",
    "sg:city":"Amsterdam",
    "sg:orig_category":"Modellenbureaus En Modellen Freelance",
    "sg:phone":"+31 20 679 5998",
    "sg:postcode":"1076 BV",
    "sg:province":"Noord-Holland",
    "wof:name":"Show, De",
    "wof:placetype":"venue"
},
  "geometry": {"coordinates":[4.85812,52.344231],"type":"Point"}
}