{
  "type": "Feature",
  "properties": {
    "iso:country":"NL",
    "sg:address":"Steurwg 8",
    "sg:city":"Raamsdonksveer",
    "sg:orig_category":"Musea",
    "sg:phone":"+31 162 585 400",
    "sg:postcode":"4941 VR",
    "sg:province":"North Brabant",
    "wof:name":"Nat Automobielmuseum, Het",
    "wof:placetype":"venue"
},
  "geometry": {"coordinates":[4.886031,51.715477],"type":"Point"}
}