{
  "type": "Feature",
  "properties": {
    "addr:full":"Slinge 185 Rotterdam Zuid-Holland 3085 ER",
    "addr:housenumber":"185",
    "addr:postcode":"3085 er",
    "addr:street":"Slinge",
    "iso:country":"NL",
    "sg:address":"Slinge 185",
    "sg:city":"Rotterdam",
    "sg:orig_category":"Huishoudelijke Apparaten En Artikelen",
    "sg:phone":"+31 10 293 7800",
    "sg:postcode":"3085 ER",
    "sg:province":"Zuid-Holland",
    "wof:name":"Marskramer Bv",
    "wof:placetype":"venue"
},
  "geometry": {"coordinates":[4.491274,51.873756],"type":"Point"}
}