{
  "type": "Feature",
  "properties": {
    "addr:full":"Reinaldstraat 7 Arnhem Gelderland 6824 GN",
    "addr:housenumber":"7",
    "addr:postcode":"6824 gn",
    "addr:street":"Reinaldstraat",
    "iso:country":"NL",
    "sg:address":"Reinaldstraat 7",
    "sg:city":"Arnhem",
    "sg:orig_category":"Diverse Bedrijfsinstallaties Gh",
    "sg:phone":"+31 26 364 5599",
    "sg:postcode":"6824 GN",
    "sg:province":"Gelderland",
    "wof:name":"Asv Stubbe Benelux Bv",
    "wof:placetype":"venue"
},
  "geometry": {"coordinates":[5.941579,51.98888],"type":"Point"}
}