{
  "type": "Feature",
  "properties": {
    "addr:full":"Kruisweg 3 Callantsoog North Holland 1759 JA",
    "addr:housenumber":"3",
    "addr:postcode":"1759 ja",
    "addr:street":"Kruisweg",
    "iso:country":"NL",
    "sg:address":"Kruisweg 3",
    "sg:city":"Callantsoog",
    "sg:orig_category":"Kampeerterreinen",
    "sg:phone":"+31 224 581 224",
    "sg:postcode":"1759 JA",
    "sg:province":"North Holland",
    "wof:name":"Camping Luttikduin",
    "wof:placetype":"venue"
},
  "geometry": {"coordinates":[4.7072548866,52.8416671753],"type":"Point"}
}