{
  "type": "Feature",
  "properties": {
    "iso:country":"NL",
    "sg:address":"Zuidpln Hg 950",
    "sg:city":"Rotterdam",
    "sg:orig_category":"Warenhuizen",
    "sg:phone":"+31 10 481 1644",
    "sg:postcode":"3083 BS",
    "sg:province":"Zuid-Holland",
    "wof:name":"V & D",
    "wof:placetype":"venue"
},
  "geometry": {"coordinates":[4.4906430244,51.8868598938],"type":"Point"}
}