{
  "type": "Feature",
  "properties": {
    "addr:full":"Zwarteweg 10 Aerdenhout Noord-Holland 2111 AJ",
    "addr:housenumber":"10",
    "addr:postcode":"2111 aj",
    "addr:street":"Zwarteweg",
    "iso:country":"NL",
    "sg:address":"Zwarteweg 10",
    "sg:city":"Aerdenhout",
    "sg:orig_category":"Chemische Producten Gh",
    "sg:phone":"+31 23 524 7484",
    "sg:postcode":"2111 AJ",
    "sg:province":"Noord-Holland",
    "wof:name":"Goudsmit Chemical Trading Bv",
    "wof:placetype":"venue"
},
  "geometry": {"coordinates":[4.58612,52.365673],"type":"Point"}
}