{
  "type": "Feature",
  "properties": {
    "addr:full":"In De Bogaard E 19 Ryswyk Zh Zuid-Holland 2284 KE",
    "addr:housenumber":"19",
    "addr:postcode":"2284 ke",
    "addr:street":"In De Bogaard E",
    "iso:country":"NL",
    "sg:address":"In De Bogaard E 19",
    "sg:city":"Ryswyk Zh",
    "sg:orig_category":"Opticiens",
    "sg:phone":"+31 70 394 1791",
    "sg:postcode":"2284 KE",
    "sg:province":"Zuid-Holland",
    "wof:name":"Pearle",
    "wof:placetype":"venue"
},
  "geometry": {"coordinates":[4.3243598938,52.0372505188],"type":"Point"}
}