{
  "type": "Feature",
  "properties": {
    "addr:full":"Broekstraat 26 Bergeyk North Brabant 5571 KK",
    "addr:housenumber":"26",
    "addr:postcode":"5571 kk",
    "addr:street":"Broekstraat",
    "iso:country":"NL",
    "sg:address":"Broekstraat 26",
    "sg:city":"Bergeyk",
    "sg:orig_category":"Diverse Grafische Activiteiten",
    "sg:phone":"+31 497 571 772",
    "sg:postcode":"5571 KK",
    "sg:province":"North Brabant",
    "wof:name":"Boers-Sterken",
    "wof:placetype":"venue"
},
  "geometry": {"coordinates":[5.354991,51.313011],"type":"Point"}
}