{
  "type": "Feature",
  "properties": {
    "addr:full":"Weesperstr 110 Diemen Noord-Holland 1112 AP",
    "addr:housenumber":"110",
    "addr:postcode":"1112 ap",
    "iso:country":"NL",
    "sg:address":"Weesperstr 110",
    "sg:city":"Diemen",
    "sg:orig_category":"Veilingen En Venduhuizen",
    "sg:phone":"+31 20 623 0343",
    "sg:postcode":"1112 AP",
    "sg:province":"Noord-Holland",
    "sg:website":"http://www.veilinghuis-de-eland.nl",
    "wof:name":"Eland De Zon En Loth Gijselman, De",
    "wof:placetype":"venue"
},
  "geometry": {"coordinates":[4.970674,52.333885],"type":"Point"}
}