{
  "type": "Feature",
  "properties": {
    "addr:full":"Hollandseweg 155 Wageningen Gelderland 6705 BC",
    "addr:housenumber":"155",
    "addr:postcode":"6705 bc",
    "addr:street":"Hollandseweg;Gelderland",
    "iso:country":"NL",
    "sg:address":"Hollandseweg 155",
    "sg:city":"Wageningen",
    "sg:orig_category":"Elektriciens",
    "sg:phone":"+31 317 411 124",
    "sg:postcode":"6705 BC",
    "sg:province":"Gelderland",
    "wof:name":"Ing. O. Franse",
    "wof:placetype":"venue"
},
  "geometry": {"coordinates":[5.697226,51.988586],"type":"Point"}
}