{
  "type": "Feature",
  "properties": {
    "addr:full":"Kerkstraat 23 Didam Gelderland 6941 AC",
    "addr:housenumber":"23",
    "addr:postcode":"6941 ac",
    "addr:street":"Kerkstraat;Gelderland",
    "iso:country":"NL",
    "sg:address":"Kerkstraat 23",
    "sg:city":"Didam",
    "sg:orig_category":"Bloemen And Planten",
    "sg:phone":"+31 316 226 004",
    "sg:postcode":"6941 AC",
    "sg:province":"Gelderland",
    "wof:name":"Bloemenhuis G. Duis",
    "wof:placetype":"venue"
},
  "geometry": {"coordinates":[6.128787,51.942123],"type":"Point"}
}