{
  "type": "Feature",
  "properties": {
    "addr:full":"Lothariusln 7 Bussum Noord-Holland 1402 GE",
    "addr:housenumber":"7",
    "addr:postcode":"1402",
    "addr:street":"Lothariusln",
    "iso:country":"NL",
    "sg:address":"Lothariusln 7",
    "sg:city":"Bussum",
    "sg:orig_category":"Adviesbureaus",
    "sg:phone":"+31 35 693 0123",
    "sg:postcode":"1402 GE",
    "sg:province":"Noord-Holland",
    "wof:name":"Hazet Bv",
    "wof:placetype":"venue"
},
  "geometry": {"coordinates":[5.162605,52.276829],"type":"Point"}
}