{
  "type": "Feature",
  "properties": {
    "iso:country":"NL",
    "sg:address":"Nieuwmarkt 9",
    "sg:city":"Amsterdam",
    "sg:orig_category":"Beeldende Kunstenaars",
    "sg:phone":"+31 20 622 6948",
    "sg:postcode":"1011 JR",
    "sg:province":"Noord-Holland",
    "wof:name":"Knaup, Pim",
    "wof:placetype":"venue"
},
  "geometry": {"coordinates":[4.900972,52.372791],"type":"Point"}
}