{
  "type": "Feature",
  "properties": {
    "iso:country":"NL",
    "sg:address":"Den Heuvel 3-13",
    "sg:city":"Oirschot",
    "sg:orig_category":"Glasblazerijen",
    "sg:phone":"+31 499 577 145",
    "sg:postcode":"5688 EM",
    "sg:province":"Noord-Brabant",
    "wof:name":"Martorell Glasblazerij",
    "wof:placetype":"venue"
},
  "geometry": {"coordinates":[5.301641,51.500931],"type":"Point"}
}