{
  "type": "Feature",
  "properties": {
    "addr:full":"Makkum 4 Beilen Drenthe 9411 TJ",
    "addr:housenumber":"4",
    "addr:postcode":"9411 tj",
    "addr:street":"Makkum",
    "iso:country":"NL",
    "sg:address":"Makkum 4",
    "sg:city":"Beilen",
    "sg:orig_category":"Levende Dieren Gh",
    "sg:phone":"+31 593 522 762",
    "sg:postcode":"9411 TJ",
    "sg:province":"Drenthe",
    "wof:name":"G. Moes",
    "wof:placetype":"venue"
},
  "geometry": {"coordinates":[6.531452,52.848785],"type":"Point"}
}