{
  "type": "Feature",
  "properties": {
    "iso:country":"NL",
    "sg:address":"Baselaarshoef 31",
    "sg:city":"Schyndel",
    "sg:orig_category":"Tegelwerken",
    "sg:phone":"+31 73 547 6694",
    "sg:postcode":"5481 NB",
    "sg:province":"Noord-Brabant",
    "wof:name":"Heymans",
    "wof:placetype":"venue"
},
  "geometry": {"coordinates":[5.41239,51.625286],"type":"Point"}
}