{
  "type": "Feature",
  "properties": {
    "addr:full":"Baselaarshoef 31 Schyndel Noord-Brabant 5481 NB",
    "addr:housenumber":"31",
    "addr:postcode":"5481 nb",
    "addr:street":"Baselaarshoef",
    "iso:country":"NL",
    "sg:address":"Baselaarshoef 31",
    "sg:city":"Schyndel",
    "sg:orig_category":"Tegelwerken",
    "sg:phone":"+31 73 547 6694",
    "sg:postcode":"5481 NB",
    "sg:province":"Noord-Brabant",
    "wof:name":"Heymans",
    "wof:placetype":"venue"
},
  "geometry": {"coordinates":[5.41239,51.625286],"type":"Point"}
}