{
  "type": "Feature",
  "properties": {
    "addr:full":"Vyverwg 11 Rotterdam Zuid-Holland 3062 JN",
    "addr:housenumber":"11",
    "addr:postcode":"3062 jn",
    "addr:street":"Vyverwg",
    "iso:country":"NL",
    "sg:address":"Vyverwg 11",
    "sg:city":"Rotterdam",
    "sg:orig_category":"Adviesbureaus Economie",
    "sg:phone":"+31 10 412 3345",
    "sg:postcode":"3062 JN",
    "sg:province":"Zuid-Holland",
    "wof:name":"Class & Genius",
    "wof:placetype":"venue"
},
  "geometry": {"coordinates":[4.515187,51.920418],"type":"Point"}
}