{
  "type": "Feature",
  "properties": {
    "iso:country":"NL",
    "sg:address":"Oranjestraat 6",
    "sg:city":"Noord-Scharwoude",
    "sg:orig_category":"Bedrijfsinventaris Gh",
    "sg:phone":"+31 226 318 044",
    "sg:postcode":"1723 MP",
    "sg:province":"Noord-Holland",
    "wof:name":"Witte Koeltechniek Bv",
    "wof:placetype":"venue"
},
  "geometry": {"coordinates":[4.81024,52.698441],"type":"Point"}
}