{
  "type": "Feature",
  "properties": {
    "addr:full":"Damsport 157 Groningen Groningen 9728 PS",
    "addr:housenumber":"157",
    "addr:postcode":"9728 ps",
    "addr:street":"Damsport",
    "iso:country":"NL",
    "sg:address":"Damsport 157",
    "sg:city":"Groningen",
    "sg:orig_category":"Boekenuitgeverijen",
    "sg:phone":"+31 50 522 6922",
    "sg:postcode":"9728 PS",
    "sg:province":"Groningen",
    "wof:name":"Wolters Noordhoff Bv",
    "wof:placetype":"venue"
},
  "geometry": {"coordinates":[6.556673,53.192032],"type":"Point"}
}