{
  "type": "Feature",
  "properties": {
    "addr:full":"Vrouwenln 97 Zwolle Overijssel 8017 HR",
    "addr:housenumber":"97",
    "addr:postcode":"8017 hr",
    "addr:street":"Vrouwenln",
    "iso:country":"NL",
    "sg:address":"Vrouwenln 97",
    "sg:city":"Zwolle",
    "sg:orig_category":"Autosnelservice",
    "sg:phone":"+31 38 460 5885",
    "sg:postcode":"8017 HR",
    "sg:province":"Overijssel",
    "wof:name":"Harten, Van",
    "wof:placetype":"venue"
},
  "geometry": {"coordinates":[6.104714,52.497467],"type":"Point"}
}