{
  "type": "Feature",
  "properties": {
    "addr:full":"Grietsestraat 27 Zevenaar Gelderland 6901 GR",
    "addr:housenumber":"27",
    "addr:postcode":"6901",
    "addr:street":"Grietsestraat",
    "iso:country":"NL",
    "sg:address":"Grietsestraat 27",
    "sg:city":"Zevenaar",
    "sg:orig_category":"Medische Apparatuur And Prothesen Fab",
    "sg:phone":"+31 316 525 620",
    "sg:postcode":"6901 GR",
    "sg:province":"Gelderland",
    "wof:name":"Faazen Hoortoestellen Bv",
    "wof:placetype":"venue"
},
  "geometry": {"coordinates":[6.076991,51.929676],"type":"Point"}
}