{
  "type": "Feature",
  "properties": {
    "addr:full":"Rembrandtln 72 Voorburg South Holland 2271 GK",
    "addr:housenumber":"72",
    "addr:postcode":"2271 gk",
    "addr:street":"Rembrandtln",
    "iso:country":"NL",
    "sg:address":"Rembrandtln 72",
    "sg:city":"Voorburg",
    "sg:classifiers":[
        {
            "category":"Travel",
            "subcategory":"Hotels & Motels",
            "type":"Entertainment"
        }
    ],
    "sg:phone":"+31 6 20033903",
    "sg:postcode":"2271 GK",
    "sg:province":"South Holland",
    "wof:name":"Rembrandt Gasthouse",
    "wof:placetype":"venue"
},
  "geometry": {"coordinates":[4.373103,52.076313],"type":"Point"}
}