{
  "type": "Feature",
  "properties": {
    "addr:full":"Jane Austenlaan 5 Eindhoven North Brabant 5629 MA",
    "addr:housenumber":"5",
    "addr:postcode":"5629 ma",
    "addr:street":"Jane Austenlaan",
    "iso:country":"NL",
    "sg:address":"Jane Austenlaan 5",
    "sg:city":"Eindhoven",
    "sg:orig_category":"Public Relationbureaus",
    "sg:phone":"+31 40 292 7323",
    "sg:postcode":"5629 MA",
    "sg:province":"North Brabant",
    "wof:name":"Progest Bv",
    "wof:placetype":"venue"
},
  "geometry": {"coordinates":[5.473086,51.487133],"type":"Point"}
}