{
  "type": "Feature",
  "properties": {
    "addr:full":"Insulindewg 7 Middenbeemster Noord-Holland 1462 MJ",
    "addr:housenumber":"7",
    "addr:postcode":"1462 mj",
    "addr:street":"Insulindewg",
    "iso:country":"NL",
    "sg:address":"Insulindewg 7",
    "sg:city":"Middenbeemster",
    "sg:orig_category":"Lasapparaten En Benodigdheden",
    "sg:phone":"+31 299 684 235",
    "sg:postcode":"1462 MJ",
    "sg:province":"Noord-Holland",
    "sg:website":"http://www.emw.nl",
    "wof:name":"Hrc Holland Rectifier Company Bv",
    "wof:placetype":"venue"
},
  "geometry": {"coordinates":[4.903135,52.552826],"type":"Point"}
}