{
  "type": "Feature",
  "properties": {
    "addr:full":"Hoofdstraat 59 Epe Gelderland 8162 AB",
    "addr:housenumber":"59",
    "addr:postcode":"8162 ab",
    "addr:street":"Hoofdstraat;Gelderland",
    "iso:country":"NL",
    "sg:address":"Hoofdstraat 59",
    "sg:city":"Epe",
    "sg:orig_category":"Bloemen And Planten",
    "sg:phone":"+31 578 612 487",
    "sg:postcode":"8162 AB",
    "sg:province":"Gelderland",
    "wof:name":"Konmar",
    "wof:placetype":"venue"
},
  "geometry": {"coordinates":[5.98436,52.349213],"type":"Point"}
}