{
  "type": "Feature",
  "properties": {
    "addr:full":"Hoefstraat 214 Tilburg Noord-Brabant 5014 NP",
    "addr:housenumber":"214",
    "addr:postcode":"5014 np",
    "addr:street":"Hoefstraat",
    "iso:country":"NL",
    "sg:address":"Hoefstraat 214",
    "sg:city":"Tilburg",
    "sg:orig_category":"Artsen And Specialisten",
    "sg:phone":"+31 13 581 2440",
    "sg:postcode":"5014 NP",
    "sg:province":"Noord-Brabant",
    "wof:name":"G J Praktijk Heiremans",
    "wof:placetype":"venue"
},
  "geometry": {"coordinates":[5.091381,51.570496],"type":"Point"}
}