{
  "type": "Feature",
  "properties": {
    "addr:full":"Van Baerlestraat 27 Amsterdam North Holland 1071 AN",
    "addr:housenumber":"27",
    "addr:postcode":"1071 an",
    "addr:street":"Van Baerlestraat",
    "iso:country":"NL",
    "sg:address":"Van Baerlestraat 27",
    "sg:city":"Amsterdam",
    "sg:orig_category":"Hoger Onderwijs",
    "sg:phone":"+31 20 527 7550",
    "sg:postcode":"1071 AN",
    "sg:province":"North Holland",
    "wof:name":"Conservatorium Van Amsterdam",
    "wof:placetype":"venue"
},
  "geometry": {"coordinates":[4.8785,52.358593],"type":"Point"}
}