{
  "type": "Feature",
  "properties": {
    "addr:full":"Oude Vest 27 Breda Noord-Brabant 4811 HS",
    "addr:housenumber":"27",
    "addr:postcode":"4811 hs",
    "addr:street":"Oude Vest",
    "iso:country":"NL",
    "sg:address":"Oude Vest 27",
    "sg:city":"Breda",
    "sg:orig_category":"Fietsen En Bromfietsen Stalling",
    "sg:phone":"+31 76 520 7934",
    "sg:postcode":"4811 HS",
    "sg:province":"Noord-Brabant",
    "wof:name":"Oude Vest",
    "wof:placetype":"venue"
},
  "geometry": {"coordinates":[4.771685,51.591351],"type":"Point"}
}