{
  "type": "Feature",
  "properties": {
    "addr:full":"Assumburg 11 Roden Drenthe 9301 VJ",
    "addr:housenumber":"11",
    "addr:postcode":"9301 vj",
    "addr:street":"Assumburg",
    "iso:country":"NL",
    "sg:address":"Assumburg 11",
    "sg:city":"Roden",
    "sg:orig_category":"Paramedische Behandelingen",
    "sg:phone":"+31 50 501 6712",
    "sg:postcode":"9301 VJ",
    "sg:province":"Drenthe",
    "wof:name":"T. Hofstra",
    "wof:placetype":"venue"
},
  "geometry": {"coordinates":[6.407332,53.133694],"type":"Point"}
}