{
  "type": "Feature",
  "properties": {
    "addr:full":"Schoutenbosje 4 Laren Nh Noord-Holland 1251 LE",
    "addr:housenumber":"4",
    "addr:postcode":"1251 le",
    "addr:street":"Schoutenbosje",
    "iso:country":"NL",
    "sg:address":"Schoutenbosje 4",
    "sg:city":"Laren Nh",
    "sg:classifiers":[
        {
            "category":"Shopping",
            "subcategory":"Adult",
            "type":"Retail Goods"
        }
    ],
    "sg:phone":"+31 35 683 6329",
    "sg:postcode":"1251 LE",
    "sg:province":"Noord-Holland",
    "sg:tags":[
        "lingerie",
        "en",
        "tricotage"
    ],
    "wof:name":"Sottovita Laren",
    "wof:placetype":"venue"
},
  "geometry": {"coordinates":[5.223153,52.255997],"type":"Point"}
}