{
  "type": "Feature",
  "properties": {
    "iso:country":"NL",
    "sg:address":"Kimswerderwg 1",
    "sg:city":"Harlingen",
    "sg:orig_category":"Bevrachting",
    "sg:phone":"+31 517 419 777",
    "sg:postcode":"8862 TR",
    "sg:province":"Provincie Friesland",
    "wof:name":"Water-Land Bv",
    "wof:placetype":"venue"
},
  "geometry": {"coordinates":[5.427816,53.169472],"type":"Point"}
}