{
  "type": "Feature",
  "properties": {
    "addr:full":"Laakwg 22 Nykerkerveen Gelderland 3864 LC",
    "addr:housenumber":"22",
    "addr:postcode":"3864 lc",
    "addr:street":"Laakwg;Gelderland",
    "iso:country":"NL",
    "sg:address":"Laakwg 22",
    "sg:city":"Nykerkerveen",
    "sg:orig_category":"Poeliers",
    "sg:phone":"+31 33 257 1500",
    "sg:postcode":"3864 LC",
    "sg:province":"Gelderland",
    "wof:name":"Brom, Van Den",
    "wof:placetype":"venue"
},
  "geometry": {"coordinates":[5.455997,52.191296],"type":"Point"}
}