{
  "type": "Feature",
  "properties": {
    "addr:full":"Schoolstr 26 Bakel North Brabant 5761 BV",
    "addr:housenumber":"26",
    "addr:postcode":"5761 bv",
    "addr:street":"Schoolstr",
    "iso:country":"NL",
    "sg:address":"Schoolstr 26",
    "sg:city":"Bakel",
    "sg:orig_category":"Kappers",
    "sg:phone":"+31 492 341 628",
    "sg:postcode":"5761 BV",
    "sg:province":"North Brabant",
    "wof:name":"Manders, J G",
    "wof:placetype":"venue"
},
  "geometry": {"coordinates":[5.740359,51.502266],"type":"Point"}
}