{
  "type": "Feature",
  "properties": {
    "addr:full":"Adstg 33 Beek Lb Limburg 6191 PW",
    "addr:housenumber":"33",
    "addr:postcode":"lb;6191 pw",
    "addr:street":"Adstg",
    "iso:country":"NL",
    "sg:address":"Adstg 33",
    "sg:city":"Beek Lb",
    "sg:orig_category":"Psychotherapeuten",
    "sg:phone":"+31 46 428 0370",
    "sg:postcode":"6191 PW",
    "sg:province":"Limburg",
    "wof:name":"Labyrint",
    "wof:placetype":"venue"
},
  "geometry": {"coordinates":[5.80195,50.933601],"type":"Point"}
}