{
  "type": "Feature",
  "properties": {
    "iso:country":"NL",
    "sg:address":"Kl Kerkstr 6",
    "sg:city":"Sneek",
    "sg:orig_category":"Omroep",
    "sg:phone":"+31 515 420 600",
    "sg:postcode":"8601 CN",
    "sg:province":"Friesland",
    "wof:name":"Radio Markant",
    "wof:placetype":"venue"
},
  "geometry": {"coordinates":[5.66197,53.033459],"type":"Point"}
}