{
  "type": "Feature",
  "properties": {
    "addr:full":"Sluiswg 4 Oosthuizen Noord-Holland 1474 HL",
    "addr:housenumber":"4",
    "addr:postcode":"1474 hl",
    "addr:street":"Sluiswg",
    "iso:country":"NL",
    "sg:address":"Sluiswg 4",
    "sg:city":"Oosthuizen",
    "sg:orig_category":"Hypotheken",
    "sg:phone":"+31 299 451 693",
    "sg:postcode":"1474 HL",
    "sg:province":"Noord-Holland",
    "wof:name":"Afd Bv",
    "wof:placetype":"venue"
},
  "geometry": {"coordinates":[4.997738,52.57481],"type":"Point"}
}