{
  "type": "Feature",
  "properties": {
    "iso:country":"NL",
    "sg:address":"Sluiswg 4",
    "sg:city":"Oosthuizen",
    "sg:orig_category":"Hypotheken",
    "sg:phone":"+31 299 451 693",
    "sg:postcode":"1474 HL",
    "sg:province":"Noord-Holland",
    "wof:name":"Afd Bv",
    "wof:placetype":"venue"
},
  "geometry": {"coordinates":[4.997738,52.57481],"type":"Point"}
}