{
  "type": "Feature",
  "properties": {
    "addr:full":"Kanaaldk 193A Koedyk Noord-Holland 1831 BD",
    "addr:housenumber":"193a",
    "addr:postcode":"1831 bd",
    "addr:street":"Koedyk Noord-Holland",
    "iso:country":"NL",
    "sg:address":"Kanaaldk 193A",
    "sg:city":"Koedyk",
    "sg:orig_category":"Binnenhuisarchitectuur",
    "sg:phone":"+31 6 51088286",
    "sg:postcode":"1831 BD",
    "sg:province":"Noord-Holland",
    "wof:name":"M Art",
    "wof:placetype":"venue"
},
  "geometry": {"coordinates":[4.752976,52.671967],"type":"Point"}
}