{
  "type": "Feature",
  "properties": {
    "iso:country":"NL",
    "sg:address":"Conradstr 36",
    "sg:city":"Katwyk Zh",
    "sg:classifiers":[
        {
            "category":"Personal",
            "subcategory":"Nail Salon",
            "type":"Services"
        }
    ],
    "sg:phone":"+31 71 403 0065",
    "sg:postcode":"2221 SH",
    "sg:province":"Zuid-Holland",
    "sg:tags":[
        "pedicure"
    ],
    "wof:name":"Voetje, 'T",
    "wof:placetype":"venue"
},
  "geometry": {"coordinates":[4.421948,52.205204],"type":"Point"}
}