{
  "type": "Feature",
  "properties": {
    "iso:country":"NL",
    "sg:address":"Francina Molen 40",
    "sg:city":"Rotterdam",
    "sg:orig_category":"Diverse Grafische Activiteiten",
    "sg:phone":"+31 10 453 1810",
    "sg:postcode":"3063 PC",
    "sg:province":"Zuid-Holland",
    "wof:name":"Dick Pruis Artworkstudio",
    "wof:placetype":"venue"
},
  "geometry": {"coordinates":[4.508869,51.919376],"type":"Point"}
}