{
  "type": "Feature",
  "properties": {
    "addr:full":"Spuistraat 1 Amsterdam Noord-Holland 1012 SP",
    "addr:housenumber":"1",
    "addr:postcode":"1012 sp",
    "addr:street":"Spuistraat",
    "iso:country":"NL",
    "sg:address":"Spuistraat 1",
    "sg:city":"Amsterdam",
    "sg:classifiers":[
        {
            "category":"Fast Food",
            "type":"Food & Drink"
        }
    ],
    "sg:phone":"+31 20 627 1282",
    "sg:postcode":"1012 SP",
    "sg:province":"Noord-Holland",
    "sg:tags":[
        "afhaal",
        "restaurant"
    ],
    "wof:name":"Ristaurante Savini",
    "wof:placetype":"venue"
},
  "geometry": {"coordinates":[4.894648,52.37738],"type":"Point"}
}