{
  "type": "Feature",
  "properties": {
    "addr:full":"Markerkant 1434 Almere Flevoland 1314 AS",
    "addr:postcode":"1434;1314 as",
    "addr:street":"Markerkant;Flevoland",
    "iso:country":"NL",
    "sg:address":"Markerkant 1434",
    "sg:city":"Almere",
    "sg:classifiers":[
        {
            "category":"Retail",
            "subcategory":"Auto Repair",
            "type":"Services"
        }
    ],
    "sg:phone":"+31 36 534 3445",
    "sg:postcode":"1314 AS",
    "sg:province":"Flevoland",
    "sg:tags":[
        "garage"
    ],
    "wof:name":"Amazigh",
    "wof:placetype":"venue"
},
  "geometry": {"coordinates":[5.21371,52.382378],"type":"Point"}
}