{
  "type": "Feature",
  "properties": {
    "iso:country":"NL",
    "sg:address":"Deeling 3",
    "sg:city":"Roden",
    "sg:orig_category":"Metaalbewerking",
    "sg:phone":"+31 50 501 7601",
    "sg:postcode":"9301 ZT",
    "sg:province":"Provincie Drenthe",
    "wof:name":"Mennes Metaalbewerking",
    "wof:placetype":"venue"
},
  "geometry": {"coordinates":[6.435714,53.148205],"type":"Point"}
}