{
  "type": "Feature",
  "properties": {
    "addr:full":"Varkensmarkt 10 Roermond Limburg 6041 ET",
    "addr:housenumber":"10",
    "addr:postcode":"6041 et",
    "addr:street":"Varkensmarkt",
    "iso:country":"NL",
    "sg:address":"Varkensmarkt 10",
    "sg:city":"Roermond",
    "sg:orig_category":"Boeken En Tijdschriften",
    "sg:phone":"+31 475 337 059",
    "sg:postcode":"6041 ET",
    "sg:province":"Limburg",
    "wof:name":"Boekenvoordeel",
    "wof:placetype":"venue"
},
  "geometry": {"coordinates":[5.985968,51.195038],"type":"Point"}
}