{
  "type": "Feature",
  "properties": {
    "addr:full":"Weidemaad 51 Oosterwolde Fr Friesland 8431 TH",
    "addr:housenumber":"51",
    "addr:postcode":"8431 th",
    "addr:street":"Weidemaad",
    "iso:country":"NL",
    "sg:address":"Weidemaad 51",
    "sg:city":"Oosterwolde Fr",
    "sg:orig_category":"Autorijscholen",
    "sg:phone":"+31 516 520 029",
    "sg:postcode":"8431 TH",
    "sg:province":"Friesland",
    "wof:name":"Radix",
    "wof:placetype":"venue"
},
  "geometry": {"coordinates":[6.284593,52.999229],"type":"Point"}
}