{
  "type": "Feature",
  "properties": {
    "iso:country":"NL",
    "sg:address":"Weidemaad 51",
    "sg:city":"Oosterwolde Fr",
    "sg:orig_category":"Autorijscholen",
    "sg:phone":"+31 516 520 029",
    "sg:postcode":"8431 TH",
    "sg:province":"Friesland",
    "wof:name":"Radix",
    "wof:placetype":"venue"
},
  "geometry": {"coordinates":[6.284593,52.999229],"type":"Point"}
}