{
  "type": "Feature",
  "properties": {
    "addr:full":"Lingebos 14 Purmerend North Holland 1447 TB",
    "addr:housenumber":"14",
    "addr:postcode":"1447 tb",
    "addr:street":"Lingebos",
    "iso:country":"NL",
    "sg:address":"Lingebos 14",
    "sg:city":"Purmerend",
    "sg:orig_category":"Kinderopvang",
    "sg:phone":"+31 299 647 915",
    "sg:postcode":"1447 TB",
    "sg:province":"North Holland",
    "wof:name":"Bijl, Van Der",
    "wof:placetype":"venue"
},
  "geometry": {"coordinates":[4.976287,52.493298],"type":"Point"}
}