{
  "type": "Feature",
  "properties": {
    "addr:full":"Kl Hei 26 Oisterwyk Noord-Brabant 5062 HP",
    "addr:housenumber":"kl;26",
    "addr:postcode":"5062 hp",
    "addr:street":"Hei",
    "iso:country":"NL",
    "sg:address":"Kl Hei 26",
    "sg:city":"Oisterwyk",
    "sg:orig_category":"Veiligheidsuitrusting En -Kleding",
    "sg:phone":"+31 6 54934842",
    "sg:postcode":"5062 HP",
    "sg:province":"Noord-Brabant",
    "wof:name":"Buckler Benelux",
    "wof:placetype":"venue"
},
  "geometry": {"coordinates":[5.20733,51.556389],"type":"Point"}
}