{
  "type": "Feature",
  "properties": {
    "addr:full":"Schweibergerwg 70 Mechelen Limburg 6281 NJ",
    "addr:housenumber":"70",
    "addr:postcode":"6281 nj",
    "addr:street":"Schweibergerwg",
    "iso:country":"NL",
    "sg:address":"Schweibergerwg 70",
    "sg:city":"Mechelen",
    "sg:orig_category":"Vakantieverblijven",
    "sg:phone":"+31 45 544 0519",
    "sg:postcode":"6281 NJ",
    "sg:province":"Limburg",
    "wof:name":"Doubrigh, Hoeve",
    "wof:placetype":"venue"
},
  "geometry": {"coordinates":[5.897741,50.781487],"type":"Point"}
}