{
  "type": "Feature",
  "properties": {
    "addr:full":"Grt Markt 46 Almere Flevoland 1315 JH",
    "addr:housenumber":"46",
    "addr:postcode":"1315 jh",
    "addr:street":"Markt;Flevoland",
    "iso:country":"NL",
    "sg:address":"Grt Markt 46",
    "sg:city":"Almere",
    "sg:orig_category":"Fitnesscentra",
    "sg:phone":"+31 36 530 2381",
    "sg:postcode":"1315 JH",
    "sg:province":"Flevoland",
    "wof:name":"Fitness-Club 46",
    "wof:placetype":"venue"
},
  "geometry": {"coordinates":[5.21998,52.374531],"type":"Point"}
}