{
  "type": "Feature",
  "properties": {
    "iso:country":"NL",
    "sg:address":"Dorpsstraat 29",
    "sg:city":"Holten",
    "sg:classifiers":[
        {
            "category":"Fast Food",
            "type":"Food & Drink"
        }
    ],
    "sg:phone":"+31 548 365 138",
    "sg:postcode":"7451 BR",
    "sg:province":"NL.08",
    "sg:tags":[
        "afhaal",
        "restaurant"
    ],
    "wof:name":"Altamura",
    "wof:placetype":"venue"
},
  "geometry": {"coordinates":[6.421064,52.282471],"type":"Point"}
}