{
  "type": "Feature",
  "properties": {
    "addr:full":"Tolweg 45 Hellevoetsluis Zuid-Holland 3223 CD",
    "addr:housenumber":"45",
    "addr:postcode":"3223 cd",
    "addr:street":"Tolweg",
    "iso:country":"NL",
    "sg:address":"Tolweg 45",
    "sg:city":"Hellevoetsluis",
    "sg:orig_category":"Huizensloop And Bouwrijp Maken",
    "sg:phone":"+31 181 312 819",
    "sg:postcode":"3223 CD",
    "sg:province":"Zuid-Holland",
    "wof:name":"Aann Bedr V Grondw Annex Plaatw H Berkho",
    "wof:placetype":"venue"
},
  "geometry": {"coordinates":[4.147025,51.835419],"type":"Point"}
}