{
  "type": "Feature",
  "properties": {
    "addr:full":"Leidekkerswg 14 Woerden Utrecht 3449 JH",
    "addr:housenumber":"14",
    "addr:postcode":"3449 jh",
    "addr:street":"Leidekkerswg",
    "iso:country":"NL",
    "sg:address":"Leidekkerswg 14",
    "sg:city":"Woerden",
    "sg:orig_category":"Verzekeringen - Verzekeringskantoren",
    "sg:phone":"+31 348 431 370",
    "sg:postcode":"3449 JH",
    "sg:province":"Utrecht",
    "wof:name":"Oostveen, Van",
    "wof:placetype":"venue"
},
  "geometry": {"coordinates":[4.867751,52.083076],"type":"Point"}
}