{
  "type": "Feature",
  "properties": {
    "addr:full":"Walstraat 31 Vlissingen Zeeland 4381 ED",
    "addr:housenumber":"31",
    "addr:postcode":"4381 ed",
    "addr:street":"Walstraat",
    "iso:country":"NL",
    "sg:address":"Walstraat 31",
    "sg:city":"Vlissingen",
    "sg:classifiers":[
        {
            "category":"Shopping",
            "subcategory":"Gifts & Souvenirs",
            "type":"Retail Goods"
        }
    ],
    "sg:phone":"+31 118 413 774",
    "sg:postcode":"4381 ED",
    "sg:province":"Zeeland",
    "sg:tags":[
        "geschenken"
    ],
    "wof:name":"Wereldwinkel",
    "wof:placetype":"venue"
},
  "geometry": {"coordinates":[3.576121,51.443249],"type":"Point"}
}