{
  "type": "Feature",
  "properties": {
    "iso:country":"NL",
    "sg:address":"Klaproos 2",
    "sg:city":"Hoogvliet Rt",
    "sg:orig_category":"Wegen And Sportterreinen",
    "sg:phone":"+31 10 416 7208",
    "sg:postcode":"3191 PA",
    "sg:province":"Zuid-Holland",
    "wof:name":"Civieltechnisch Bureau D. Boer",
    "wof:placetype":"venue"
},
  "geometry": {"coordinates":[4.3722338676,51.8589057922],"type":"Point"}
}