{
  "type": "Feature",
  "properties": {
    "iso:country":"NL",
    "sg:address":"De Compagnie 22C",
    "sg:city":"Zwaag",
    "sg:orig_category":"Elektrotechnische Installatiebureaus",
    "sg:phone":"+31 229 244 500",
    "sg:postcode":"1689 AG",
    "sg:province":"Noord-Holland",
    "wof:name":"Pronk Bv, Elektrotechniek",
    "wof:placetype":"venue"
},
  "geometry": {"coordinates":[5.05934,52.669949],"type":"Point"}
}