{
  "type": "Feature",
  "properties": {
    "addr:full":"Kostverlorenhof 5 Amstelveen North Holland 1183 HE",
    "addr:housenumber":"5",
    "addr:postcode":"1183 he",
    "addr:street":"Kostverlorenhof",
    "iso:country":"NL",
    "sg:address":"Kostverlorenhof 5",
    "sg:city":"Amstelveen",
    "sg:orig_category":"Visspeciaalzaken",
    "sg:phone":"+31 20 647 0340",
    "sg:postcode":"1183 HE",
    "sg:province":"North Holland",
    "wof:name":"De Volendamse Vishandel",
    "wof:placetype":"venue"
},
  "geometry": {"coordinates":[4.874874,52.313072],"type":"Point"}
}