{
  "type": "Feature",
  "properties": {
    "addr:full":"Horstacker 2047 Nijmegen Gelderland 6546 GB",
    "addr:housenumber":"2047",
    "addr:postcode":"6546 gb",
    "addr:street":"Horstacker;Gelderland",
    "iso:country":"NL",
    "sg:address":"Horstacker 2047",
    "sg:city":"Nijmegen",
    "sg:orig_category":"Diverse Opleidingen And Onderwijs",
    "sg:phone":"+31 24 378 6348",
    "sg:postcode":"6546 GB",
    "sg:province":"Gelderland",
    "wof:name":"Deltatrainingen",
    "wof:placetype":"venue"
},
  "geometry": {"coordinates":[5.79459,51.830788],"type":"Point"}
}