{
  "type": "Feature",
  "properties": {
    "addr:full":"Strawinskyln 767 Amsterdam North Holland 1077 XX",
    "addr:housenumber":"767",
    "addr:postcode":"1077 xx",
    "iso:country":"NL",
    "sg:address":"Strawinskyln 767",
    "sg:city":"Amsterdam",
    "sg:orig_category":"Kamers Van Koophandel",
    "sg:phone":"+31 20 673 0555",
    "sg:postcode":"1077 XX",
    "sg:province":"North Holland",
    "wof:name":"Korea Trade Center",
    "wof:placetype":"venue"
},
  "geometry": {"coordinates":[4.873404026,52.3406028748],"type":"Point"}
}