{
  "type": "Feature",
  "properties": {
    "addr:full":"Burg Andriessenstr 7 Ovezande Zeeland 4441 AN",
    "addr:housenumber":"7",
    "addr:postcode":"4441 an",
    "addr:street":"Burg Andriessenstr",
    "iso:country":"NL",
    "sg:address":"Burg Andriessenstr 7",
    "sg:city":"Ovezande",
    "sg:orig_category":"Sportclubs",
    "sg:phone":"+31 113 655 881",
    "sg:postcode":"4441 AN",
    "sg:province":"Zeeland",
    "wof:name":"Voetbalvereniging Volharding",
    "wof:placetype":"venue"
},
  "geometry": {"coordinates":[3.82196,51.429359],"type":"Point"}
}