{
  "type": "Feature",
  "properties": {
    "addr:full":"Bakkerstraat 28 Valkenswaard Noord-Brabant 5554 EE",
    "addr:housenumber":"28",
    "addr:postcode":"5554 ee",
    "addr:street":"Bakkerstraat",
    "iso:country":"NL",
    "sg:address":"Bakkerstraat 28",
    "sg:city":"Valkenswaard",
    "sg:orig_category":"Artistiek Onderwijs",
    "sg:phone":"+31 40 201 3840",
    "sg:postcode":"5554 EE",
    "sg:province":"Noord-Brabant",
    "wof:name":"De Draaikolk Volksuniversiteit",
    "wof:placetype":"venue"
},
  "geometry": {"coordinates":[5.46195,51.349831],"type":"Point"}
}