{
  "type": "Feature",
  "properties": {
    "addr:full":"Baanhoek 161 Sliedrecht Zuid-Holland 3361 GC",
    "addr:housenumber":"161",
    "addr:postcode":"3361 gc",
    "addr:street":"Baanhoek",
    "iso:country":"NL",
    "sg:address":"Baanhoek 161",
    "sg:city":"Sliedrecht",
    "sg:orig_category":"Autokeuringen",
    "sg:phone":"+31 184 414 429",
    "sg:postcode":"3361 GC",
    "sg:province":"Zuid-Holland",
    "wof:name":"Garage Van Der Stel",
    "wof:placetype":"venue"
},
  "geometry": {"coordinates":[4.748771,51.823643],"type":"Point"}
}