{
  "type": "Feature",
  "properties": {
    "addr:full":"Achterdk 14C Purmerend Noord-Holland 1441 DH",
    "addr:housenumber":"14c",
    "addr:postcode":"1441 dh",
    "addr:street":"Achterdk",
    "iso:country":"NL",
    "sg:address":"Achterdk 14C",
    "sg:city":"Purmerend",
    "sg:orig_category":"Administratie- En Boekhoudkantoren",
    "sg:phone":"+31 299 660 520",
    "sg:postcode":"1441 DH",
    "sg:province":"Noord-Holland",
    "sg:website":"http://www.personal-accountancy.nl",
    "wof:name":"Personal Accountancy Vof",
    "wof:placetype":"venue"
},
  "geometry": {"coordinates":[4.949721,52.509335],"type":"Point"}
}