{
  "type": "Feature",
  "properties": {
    "iso:country":"NL",
    "sg:address":"Engelsewg 198",
    "sg:city":"Helmond",
    "sg:orig_category":"Parketvloeren",
    "sg:phone":"+31 492 538 559",
    "sg:postcode":"5705 AJ",
    "sg:province":"North Brabant",
    "wof:name":"Gemar Parket",
    "wof:placetype":"venue"
},
  "geometry": {"coordinates":[5.673866,51.473534],"type":"Point"}
}