{
  "type": "Feature",
  "properties": {
    "iso:country":"NL",
    "sg:address":"G Doustr 60",
    "sg:city":"Amsterdam",
    "sg:orig_category":"Kaas",
    "sg:phone":"+31 20 679 6717",
    "sg:postcode":"1072 VV",
    "sg:province":"North Holland",
    "wof:name":"Kaasboertje, 'T",
    "wof:placetype":"venue"
},
  "geometry": {"coordinates":[4.8908939362,52.3553886414],"type":"Point"}
}