{
  "type": "Feature",
  "properties": {
    "addr:full":"Laaghuissingel 7 Venlo Limburg 5913 EK",
    "addr:housenumber":"7",
    "addr:postcode":"5913 ek",
    "addr:street":"Laaghuissingel",
    "iso:country":"NL",
    "sg:address":"Laaghuissingel 7",
    "sg:city":"Venlo",
    "sg:orig_category":"Verzekeringen",
    "sg:phone":"+31 77 351 6173",
    "sg:postcode":"5913 EK",
    "sg:province":"Limburg",
    "wof:name":"Jos Wolters Bv",
    "wof:placetype":"venue"
},
  "geometry": {"coordinates":[6.184646,51.373344],"type":"Point"}
}