{
  "type": "Feature",
  "properties": {
    "addr:full":"Ooievaarstraat 1 Strijen Zuid-Holland 3291 XK",
    "addr:housenumber":"1",
    "addr:postcode":"3291 xk",
    "addr:street":"Ooievaarstraat",
    "iso:country":"NL",
    "sg:address":"Ooievaarstraat 1",
    "sg:city":"Strijen",
    "sg:classifiers":[
        {
            "category":"Education",
            "subcategory":"Preschool",
            "type":"Public Place"
        }
    ],
    "sg:phone":"+31 78 674 2344",
    "sg:postcode":"3291 XK",
    "sg:province":"Zuid-Holland",
    "sg:tags":[
        "kleuteronderwijs",
        "basis-"
    ],
    "wof:name":"Openbare Basisschool De Patrijspoort",
    "wof:placetype":"venue"
},
  "geometry": {"coordinates":[4.5475,51.741741],"type":"Point"}
}