{
  "type": "Feature",
  "properties": {
    "addr:full":"Carrouselwg 3-5 Hellevoetsluis South Holland 3225 LN",
    "addr:housenumber":"3-5",
    "addr:postcode":"3225 ln",
    "addr:street":"Carrouselwg",
    "iso:country":"NL",
    "sg:address":"Carrouselwg 3-5",
    "sg:city":"Hellevoetsluis",
    "sg:orig_category":"Banden - Fabrieken En Groothandel",
    "sg:phone":"+31 181 311 474",
    "sg:postcode":"3225 LN",
    "sg:province":"South Holland",
    "wof:name":"Pregon Bv",
    "wof:placetype":"venue"
},
  "geometry": {"coordinates":[4.17416,51.841782],"type":"Point"}
}