{
  "type": "Feature",
  "properties": {
    "addr:full":"Planciusstr 34 Hoek Van Holland Zuid-Holland 3151 BT",
    "addr:housenumber":"34",
    "addr:postcode":"3151 bt",
    "addr:street":"Planciusstr",
    "iso:country":"NL",
    "sg:address":"Planciusstr 34",
    "sg:city":"Hoek Van Holland",
    "sg:orig_category":"Scholen Voor Basisonderwijs",
    "sg:phone":"+31 174 382 763",
    "sg:postcode":"3151 BT",
    "sg:province":"Zuid-Holland",
    "wof:name":"Jozefschool Rk",
    "wof:placetype":"venue"
},
  "geometry": {"coordinates":[4.131116,51.979088],"type":"Point"}
}