{
  "type": "Feature",
  "properties": {
    "iso:country":"NL",
    "sg:address":"Weverstr 16",
    "sg:city":"Ophemert",
    "sg:classifiers":[
        {
            "category":"Food & Beverages",
            "subcategory":"Bakery",
            "type":"Retail Goods"
        }
    ],
    "sg:phone":"+31 344 613 207",
    "sg:postcode":"4061 AP",
    "sg:province":"Gelderland",
    "sg:tags":[
        "brood",
        "en",
        "banket"
    ],
    "wof:name":"Rivalin",
    "wof:placetype":"venue"
},
  "geometry": {"coordinates":[5.388977,51.845963],"type":"Point"}
}