{
  "type": "Feature",
  "properties": {
    "addr:full":"St Josephstr 2 St Odilienberg Limburg 6077 NJ",
    "addr:housenumber":"2",
    "addr:postcode":"6077",
    "addr:street":"St Odilienberg Limburg",
    "iso:country":"NL",
    "sg:address":"St Josephstr 2",
    "sg:city":"St Odilienberg",
    "sg:orig_category":"Verenigingsgebouwen",
    "sg:phone":"+31 475 402 855",
    "sg:postcode":"6077 NJ",
    "sg:province":"Limburg",
    "wof:name":"Wiro Fanfare, St",
    "wof:placetype":"venue"
},
  "geometry": {"coordinates":[6.002301,51.129993],"type":"Point"}
}