{
  "type": "Feature",
  "properties": {
    "addr:full":"Albionstraat 60 Tilburg Noord-Brabant 5047 SN",
    "addr:housenumber":"60",
    "addr:postcode":"5047 sn",
    "addr:street":"Albionstraat",
    "iso:country":"NL",
    "sg:address":"Albionstraat 60",
    "sg:city":"Tilburg",
    "sg:orig_category":"Wegen And Sportterreinen",
    "sg:phone":"+31 13 570 0816",
    "sg:postcode":"5047 SN",
    "sg:province":"Noord-Brabant",
    "wof:name":"Aannemingsbedrijf C.J.M. Van Gaal Bv",
    "wof:placetype":"venue"
},
  "geometry": {"coordinates":[5.0365052223,51.5848236084],"type":"Point"}
}