{
  "type": "Feature",
  "properties": {
    "addr:full":"Kooistukken 30 Eelde Provincie Drenthe 9761 JZ",
    "addr:housenumber":"30",
    "addr:postcode":"9761 jz",
    "addr:street":"Kooistukken;Provincie Drenthe",
    "iso:country":"NL",
    "sg:address":"Kooistukken 30",
    "sg:city":"Eelde",
    "sg:classifiers":[
        {
            "category":"Personal",
            "subcategory":"Nail Salon",
            "type":"Services"
        }
    ],
    "sg:phone":"+31 50 309 5912",
    "sg:postcode":"9761 JZ",
    "sg:province":"Provincie Drenthe",
    "sg:tags":[
        "pedicure"
    ],
    "wof:name":"Vijfschaft, Pia",
    "wof:placetype":"venue"
},
  "geometry": {"coordinates":[6.551811,53.136929],"type":"Point"}
}