{
  "type": "Feature",
  "properties": {
    "addr:full":"Dwingelowg 6 Winschoten Groningen 9671 KD",
    "addr:housenumber":"6",
    "addr:postcode":"9671 kd",
    "addr:street":"Dwingelowg",
    "iso:country":"NL",
    "sg:address":"Dwingelowg 6",
    "sg:city":"Winschoten",
    "sg:orig_category":"Zonnebank- En Solariumcentra",
    "sg:phone":"+31 597 422 646",
    "sg:postcode":"9671 KD",
    "sg:province":"Groningen",
    "wof:name":"Mistral",
    "wof:placetype":"venue"
},
  "geometry": {"coordinates":[7.029981,53.145893],"type":"Point"}
}