{
  "type": "Feature",
  "properties": {
    "addr:full":"Overschiesewg 2 Rotterdam South Holland 3044 EE",
    "addr:housenumber":"2",
    "addr:postcode":"3044 ee",
    "addr:street":"Overschiesewg",
    "iso:country":"NL",
    "sg:address":"Overschiesewg 2",
    "sg:city":"Rotterdam",
    "sg:orig_category":"Watersportartikelen",
    "sg:phone":"+31 10 415 9131",
    "sg:postcode":"3044 EE",
    "sg:province":"South Holland",
    "wof:name":"Egmond, Fa F Van",
    "wof:placetype":"venue"
},
  "geometry": {"coordinates":[4.4172739983,51.9378585815],"type":"Point"}
}