{
  "type": "Feature",
  "properties": {
    "iso:country":"NL",
    "sg:address":"Havenkade 31",
    "sg:city":"Venlo",
    "sg:orig_category":"Goederenvervoer Over De Weg",
    "sg:phone":"+31 77 354 6561",
    "sg:postcode":"5911 HP",
    "sg:province":"Limburg",
    "wof:name":"Sintra Venlo Bv",
    "wof:placetype":"venue"
},
  "geometry": {"coordinates":[6.16662,51.370266],"type":"Point"}
}