{
  "type": "Feature",
  "properties": {
    "iso:country":"NL",
    "sg:address":"Hoofdstr 69",
    "sg:city":"Bergambacht",
    "sg:orig_category":"Werving En Selectie",
    "sg:phone":"+31 182 350 238",
    "sg:postcode":"2861 AL",
    "sg:province":"South Holland",
    "wof:name":"Personal Watch Bv",
    "wof:placetype":"venue"
},
  "geometry": {"coordinates":[4.7831997871,51.9341773987],"type":"Point"}
}