{
  "type": "Feature",
  "properties": {
    "addr:full":"2E Oosterstr 21 Hilversum Noord-Holland 1211 LG",
    "addr:housenumber":"21",
    "addr:postcode":"1211 lg",
    "addr:street":"2E Oosterstr",
    "iso:country":"NL",
    "sg:address":"2E Oosterstr 21",
    "sg:city":"Hilversum",
    "sg:orig_category":"Fotojournalisten Freelance",
    "sg:phone":"+31 35 624 8224",
    "sg:postcode":"1211 LG",
    "sg:province":"Noord-Holland",
    "wof:name":"Botma, G",
    "wof:placetype":"venue"
},
  "geometry": {"coordinates":[5.169007,52.220654],"type":"Point"}
}