{
  "type": "Feature",
  "properties": {
    "addr:full":"Albatrosstr B 74 Nieuwe Pekela Groningen 9663 PR",
    "addr:housenumber":"74",
    "addr:postcode":"9663 pr",
    "iso:country":"NL",
    "sg:address":"Albatrosstr B 74",
    "sg:city":"Nieuwe Pekela",
    "sg:orig_category":"Verzekeringen - Verzekeringskantoren",
    "sg:phone":"+31 597 647 980",
    "sg:postcode":"9663 PR",
    "sg:province":"Groningen",
    "sg:website":"http://www.assurantiekantoor-wiegman.nl",
    "wof:name":"Wiegman, Assurantiekantoor",
    "wof:placetype":"venue"
},
  "geometry": {"coordinates":[6.968106,53.078468],"type":"Point"}
}