{
  "type": "Feature",
  "properties": {
    "addr:full":"Stationswg 72 Bedum Groningen 9781 CK",
    "addr:housenumber":"72",
    "addr:postcode":"9781 ck",
    "addr:street":"Stationswg",
    "iso:country":"NL",
    "sg:address":"Stationswg 72",
    "sg:city":"Bedum",
    "sg:orig_category":"Adviesbureaus Bedrijfsorganisatie",
    "sg:phone":"+31 50 301 7032",
    "sg:postcode":"9781 CK",
    "sg:province":"Groningen",
    "sg:website":"http://www.tripleg.myweb.nl",
    "wof:name":"Triple G",
    "wof:placetype":"venue"
},
  "geometry": {"coordinates":[6.59444,53.304993],"type":"Point"}
}