{
  "type": "Feature",
  "properties": {
    "iso:country":"NL",
    "sg:address":"Borghoutspark 58",
    "sg:city":"Veldhoven",
    "sg:orig_category":"Werving And Selectie Van Tijdelijk Personeel And Uitzendkantoren",
    "sg:phone":"+31 40 254 1555",
    "sg:postcode":"5502 JZ",
    "sg:province":"North Brabant",
    "wof:name":"Fixview Bv",
    "wof:placetype":"venue"
},
  "geometry": {"coordinates":[5.4264101982,51.4297103882],"type":"Point"}
}