{
  "type": "Feature",
  "properties": {
    "iso:country":"NL",
    "sg:address":"Bloesemstraat 43",
    "sg:city":"Utrecht",
    "sg:orig_category":"Schilderwerk",
    "sg:phone":"+31 30 251 3139",
    "sg:postcode":"3581 XB",
    "sg:province":"Utrecht",
    "wof:name":"Zeddeman Schildersbedrijf",
    "wof:placetype":"venue"
},
  "geometry": {"coordinates":[5.1328778267,52.0877113342],"type":"Point"}
}