{
  "type": "Feature",
  "properties": {
    "addr:full":"Wethouder Romeijnlaan 4 Barneveld Gelderland 3771 KP",
    "addr:housenumber":"4",
    "addr:postcode":"3771 kp",
    "addr:street":"Wethouder Romeijnlaan;Gelderland",
    "iso:country":"NL",
    "sg:address":"Wethouder Romeijnlaan 4",
    "sg:city":"Barneveld",
    "sg:orig_category":"Loodgieterswerk, Verwarming And Sanitaire Installaties",
    "sg:phone":"+31 342 416 246",
    "sg:postcode":"3771 KP",
    "sg:province":"Gelderland",
    "wof:name":"Wessel Willemsen Service En Onderhoud",
    "wof:placetype":"venue"
},
  "geometry": {"coordinates":[5.582579,52.153362],"type":"Point"}
}