{
  "type": "Feature",
  "properties": {
    "iso:country":"NL",
    "sg:address":"Valeriaanstr 121",
    "sg:city":"Soest",
    "sg:classifiers":[
        {
            "category":"Education",
            "subcategory":"School",
            "type":"Public Place"
        }
    ],
    "sg:phone":"+31 35 603 0195",
    "sg:postcode":"3765 EL",
    "sg:province":"Utrecht",
    "sg:tags":[
        "studiebegeleiding",
        "en",
        "school-"
    ],
    "wof:name":"Leerbegeleiding Soest (Lbs)",
    "wof:placetype":"venue"
},
  "geometry": {"coordinates":[5.292029,52.166878],"type":"Point"}
}