{
  "type": "Feature",
  "properties": {
    "addr:full":"Rontgenwg 6 Bunschoten Spakenb Utrecht 3752 LJ",
    "addr:housenumber":"6;3752 lj",
    "addr:street":"Rontgenwg",
    "iso:country":"NL",
    "sg:address":"Rontgenwg 6",
    "sg:city":"Bunschoten Spakenb",
    "sg:orig_category":"Levensmiddelen- Grondstoffen - Fabrieken En Groothandel",
    "sg:phone":"+31 33 298 2034",
    "sg:postcode":"3752 LJ",
    "sg:province":"Utrecht",
    "wof:name":"Orffa-Pomosin Bv",
    "wof:placetype":"venue"
},
  "geometry": {"coordinates":[5.360064,52.228489],"type":"Point"}
}