{
  "type": "Feature",
  "properties": {
    "addr:full":"Citroenstr 37 S Gravenhage Zuid-Holland 2564 PJ",
    "addr:housenumber":"37;gravenhage",
    "addr:postcode":"2564 pj",
    "addr:street":"Citroenstr;S",
    "iso:country":"NL",
    "sg:address":"Citroenstr 37",
    "sg:city":"S Gravenhage",
    "sg:orig_category":"Webdesign Bureaus",
    "sg:phone":"+31 70 368 2029",
    "sg:postcode":"2564 PJ",
    "sg:province":"Zuid-Holland",
    "sg:website":"http://www.sobczakweb.nl",
    "wof:name":"Sobczak",
    "wof:placetype":"venue"
},
  "geometry": {"coordinates":[4.2594599724,52.0680503845],"type":"Point"}
}