{
  "type": "Feature",
  "properties": {
    "iso:country":"NL",
    "sg:address":"Hosingenhof 5",
    "sg:city":"Eindhoven",
    "sg:orig_category":"Administratie- En Boekhoudkantoren",
    "sg:phone":"+31 40 292 6041",
    "sg:postcode":"5625 NJ",
    "sg:province":"Noord-Brabant",
    "wof:name":"Berendsen",
    "wof:placetype":"venue"
},
  "geometry": {"coordinates":[5.47725,51.473797],"type":"Point"}
}