{
  "type": "Feature",
  "properties": {
    "iso:country":"NL",
    "sg:address":"Tweebaksmarkt 52",
    "sg:city":"Leeuwarden",
    "sg:orig_category":"Overheidsdiensten",
    "sg:phone":"+31 58 292 5925",
    "sg:postcode":"8911 KZ",
    "sg:province":"Friesland",
    "wof:name":"Provinciehuis Fryslan",
    "wof:placetype":"venue"
},
  "geometry": {"coordinates":[5.8003177643,53.2017097473],"type":"Point"}
}