{
  "type": "Feature",
  "properties": {
    "addr:full":"A Kuylstr 15 Rotterdam Zuid-Holland 3066 GS",
    "addr:housenumber":"15",
    "addr:postcode":"3066 gs",
    "iso:country":"NL",
    "sg:address":"A Kuylstr 15",
    "sg:city":"Rotterdam",
    "sg:orig_category":"Danssportbenodigdheden",
    "sg:phone":"+31 10 286 7355",
    "sg:postcode":"3066 GS",
    "sg:province":"Zuid-Holland",
    "sg:website":"http://www.dancelife.nl",
    "wof:name":"Dancelife",
    "wof:placetype":"venue"
},
  "geometry": {"coordinates":[4.55005,51.934711],"type":"Point"}
}