{
  "type": "Feature",
  "properties": {
    "addr:full":"Molenwg 48 Groesbeek Gelderland 6561 AK",
    "addr:housenumber":"48",
    "addr:postcode":"6561 ak",
    "addr:street":"Molenwg;Gelderland",
    "iso:country":"NL",
    "sg:address":"Molenwg 48",
    "sg:city":"Groesbeek",
    "sg:classifiers":[
        {
            "category":"Travel",
            "subcategory":"Hotels & Motels",
            "type":"Entertainment"
        }
    ],
    "sg:phone":"+31 24 397 1478",
    "sg:postcode":"6561 AK",
    "sg:province":"Gelderland",
    "sg:website":"http://www.hoteldeoudemolen.com",
    "wof:name":"Oude Molen, Hotel De",
    "wof:placetype":"venue"
},
  "geometry": {"coordinates":[5.93249,51.776745],"type":"Point"}
}