{
  "type": "Feature",
  "properties": {
    "iso:country":"NL",
    "sg:address":"Boulevard Paulus Loot 1",
    "sg:city":"Zandvoort",
    "sg:classifiers":[
        {
            "category":"Fast Food",
            "type":"Food & Drink"
        }
    ],
    "sg:phone":"+31 23 571 2547",
    "sg:postcode":"2042 AD",
    "sg:province":"North Holland",
    "sg:tags":[
        "afhaal",
        "restaurant"
    ],
    "wof:name":"Tijn Akersloot'S",
    "wof:placetype":"venue"
},
  "geometry": {"coordinates":[4.52444,52.371819],"type":"Point"}
}