{
  "type": "Feature",
  "properties": {
    "addr:full":"Garyp 3 Grypskerke Zeeland 4364 AD",
    "addr:housenumber":"3",
    "addr:postcode":"4364 ad",
    "addr:street":"Garyp;Zeeland",
    "iso:country":"NL",
    "sg:address":"Garyp 3",
    "sg:city":"Grypskerke",
    "sg:orig_category":"Bloemen En Planten",
    "sg:phone":"+31 118 593 460",
    "sg:postcode":"4364 AD",
    "sg:province":"Zeeland",
    "wof:name":"Vanas Export Bv",
    "wof:placetype":"venue"
},
  "geometry": {"coordinates":[3.573785,51.519073],"type":"Point"}
}