{
  "type": "Feature",
  "properties": {
    "iso:country":"NL",
    "sg:address":"Brediuswg 15",
    "sg:city":"Bussum",
    "sg:orig_category":"Elektronische Informatie- Systemen Off-Line",
    "sg:phone":"+31 35 678 0750",
    "sg:postcode":"1401 AA",
    "sg:province":"Noord-Holland",
    "sg:website":"http://www.mariot-multisoft.com",
    "wof:name":"Mms",
    "wof:placetype":"venue"
},
  "geometry": {"coordinates":[5.164339,52.280407],"type":"Point"}
}