{
  "type": "Feature",
  "properties": {
    "addr:full":"Elzenln 16 Loosdrecht North Holland 1231 CD",
    "addr:housenumber":"16",
    "addr:postcode":"1231 cd",
    "addr:street":"Elzenln",
    "iso:country":"NL",
    "sg:address":"Elzenln 16",
    "sg:city":"Loosdrecht",
    "sg:orig_category":"Psychologen",
    "sg:phone":"+31 35 582 1790",
    "sg:postcode":"1231 CD",
    "sg:province":"North Holland",
    "wof:name":"Meester, J L D",
    "wof:placetype":"venue"
},
  "geometry": {"coordinates":[5.136097,52.201569],"type":"Point"}
}