{
  "type": "Feature",
  "properties": {
    "addr:full":"Prinses Beatrixlaan 921 Rijswijk Zh Zuid-Holland 2284 BK",
    "addr:housenumber":"921",
    "addr:postcode":"zh;2284 bk",
    "addr:street":"Prinses Beatrixlaan",
    "iso:country":"NL",
    "sg:address":"Prinses Beatrixlaan 921",
    "sg:city":"Rijswijk Zh",
    "sg:orig_category":"Huishoudapparatuur, Televisies And Radio'S",
    "sg:phone":"+31 70 394 7211",
    "sg:postcode":"2284 BK",
    "sg:province":"Zuid-Holland",
    "wof:name":"Modern Electronics",
    "wof:placetype":"venue"
},
  "geometry": {"coordinates":[4.311519,52.039192],"type":"Point"}
}