{
  "type": "Feature",
  "properties": {
    "addr:full":"Broek 12 Gieterveen Drenthe 9511 PT",
    "addr:housenumber":"12",
    "addr:postcode":"9511 pt",
    "addr:street":"Broek",
    "iso:country":"NL",
    "sg:address":"Broek 12",
    "sg:city":"Gieterveen",
    "sg:orig_category":"Meubelreparatie And -Restauratie",
    "sg:phone":"+31 6 53323744",
    "sg:postcode":"9511 PT",
    "sg:province":"Drenthe",
    "wof:name":"Roelof'S Stoffeerbedrijf",
    "wof:placetype":"venue"
},
  "geometry": {"coordinates":[6.835256,53.025463],"type":"Point"}
}