{
  "type": "Feature",
  "properties": {
    "addr:full":"R Meeuwiszwg 8 Brielle Zuid-Holland 3231 CM",
    "addr:housenumber":"8",
    "addr:postcode":"3231 cm",
    "iso:country":"NL",
    "sg:address":"R Meeuwiszwg 8",
    "sg:city":"Brielle",
    "sg:orig_category":"Jachthavens - Jachtwerven",
    "sg:phone":"+31 181 412 593",
    "sg:postcode":"3231 CM",
    "sg:province":"Zuid-Holland",
    "wof:name":"Tromp Bv, M H",
    "wof:placetype":"venue"
},
  "geometry": {"coordinates":[4.167875,51.90406],"type":"Point"}
}