{
  "type": "Feature",
  "properties": {
    "addr:full":"Zijlstraat 51 Haarlem Noord-Holland 2011 TK",
    "addr:housenumber":"51",
    "addr:postcode":"2011 tk",
    "addr:street":"Zijlstraat",
    "iso:country":"NL",
    "sg:address":"Zijlstraat 51",
    "sg:city":"Haarlem",
    "sg:orig_category":"Werving And Selectie Van Tijdelijk Personeel And Uitzendkantoren",
    "sg:phone":"+31 23 518 3450",
    "sg:postcode":"2011 TK",
    "sg:province":"Noord-Holland",
    "wof:name":"Short Track Uitzendburo",
    "wof:placetype":"venue"
},
  "geometry": {"coordinates":[4.6324548721,52.3824615479],"type":"Point"}
}