{
  "type": "Feature",
  "properties": {
    "addr:full":"Schifferheidestraat 11 Kerkrade Limburg 6466 EN",
    "addr:housenumber":"11",
    "addr:postcode":"6466 en",
    "addr:street":"Schifferheidestraat",
    "iso:country":"NL",
    "sg:address":"Schifferheidestraat 11",
    "sg:city":"Kerkrade",
    "sg:orig_category":"Sportclubs",
    "sg:phone":"+31 45 541 4120",
    "sg:postcode":"6466 EN",
    "sg:province":"Limburg",
    "wof:name":"Voetbalvereniging Heilust",
    "wof:placetype":"venue"
},
  "geometry": {"coordinates":[6.040776,50.859097],"type":"Point"}
}