{
  "type": "Feature",
  "properties": {
    "addr:full":"Wilhelminastraat 1 Venlo Limburg 5911 AZ",
    "addr:housenumber":"1",
    "addr:postcode":"5911 az",
    "addr:street":"Wilhelminastraat",
    "iso:country":"NL",
    "sg:address":"Wilhelminastraat 1",
    "sg:city":"Venlo",
    "sg:orig_category":"Werving And Selectie Van Tijdelijk Personeel And Uitzendkantoren",
    "sg:phone":"+31 77 324 0740",
    "sg:postcode":"5911 AZ",
    "sg:province":"Limburg",
    "wof:name":"Flex Uitzendbureau",
    "wof:placetype":"venue"
},
  "geometry": {"coordinates":[6.1742610931,51.3716430664],"type":"Point"}
}