{
  "type": "Feature",
  "properties": {
    "addr:full":"Kl Rozenstr 14 Groningen Groningen 9712 TM",
    "addr:housenumber":"14",
    "addr:postcode":"9712 tm",
    "iso:country":"NL",
    "sg:address":"Kl Rozenstr 14",
    "sg:city":"Groningen",
    "sg:orig_category":"Artiesten/Gezelschappen",
    "sg:phone":"+31 50 311 8375",
    "sg:postcode":"9712 TM",
    "sg:province":"Groningen",
    "sg:website":"http://www.dickschuur.nl",
    "wof:name":"Dick Schuur All-Round Pianist",
    "wof:placetype":"venue"
},
  "geometry": {"coordinates":[6.560115,53.223038],"type":"Point"}
}