{
  "type": "Feature",
  "properties": {
    "addr:full":"Noordkade 64 Waddinxveen Zuid-Holland 2741 EZ",
    "addr:housenumber":"64",
    "addr:postcode":"2741 ez",
    "addr:street":"Noordkade",
    "iso:country":"NL",
    "sg:address":"Noordkade 64",
    "sg:city":"Waddinxveen",
    "sg:orig_category":"Chemische Producten Gh",
    "sg:phone":"+31 182 631 360",
    "sg:postcode":"2741 EZ",
    "sg:province":"Zuid-Holland",
    "wof:name":"King Industries Inc",
    "wof:placetype":"venue"
},
  "geometry": {"coordinates":[4.661049,52.052486],"type":"Point"}
}