{
  "type": "Feature",
  "properties": {
    "addr:full":"Galgeriet 5E Monnickendam Noord-Holland 1141 GA",
    "addr:housenumber":"5e",
    "addr:postcode":"1141 ga",
    "addr:street":"Galgeriet",
    "iso:country":"NL",
    "sg:address":"Galgeriet 5E",
    "sg:city":"Monnickendam",
    "sg:orig_category":"Watersportartikelen",
    "sg:phone":"+31 299 650 395",
    "sg:postcode":"1141 GA",
    "sg:province":"Noord-Holland",
    "wof:name":"Visser, Yacht Service",
    "wof:placetype":"venue"
},
  "geometry": {"coordinates":[5.0396761894,52.4590339661],"type":"Point"}
}