{
  "type": "Feature",
  "properties": {
    "addr:full":"Pleinweg 125 Rotterdam Zuid-Holland 3081 JJ",
    "addr:housenumber":"125",
    "addr:postcode":"3081 jj",
    "addr:street":"Pleinweg",
    "iso:country":"NL",
    "sg:address":"Pleinweg 125",
    "sg:city":"Rotterdam",
    "sg:orig_category":"Boekhouders",
    "sg:phone":"+31 10 423 2454",
    "sg:postcode":"3081 JJ",
    "sg:province":"Zuid-Holland",
    "wof:name":"Administratiekantoor R.G. Smits",
    "wof:placetype":"venue"
},
  "geometry": {"coordinates":[4.482505,51.89114],"type":"Point"}
}