{
  "type": "Feature",
  "properties": {
    "addr:full":"F Bolstr 28 Amsterdam Noord-Holland 1072 LK",
    "addr:housenumber":"28",
    "addr:postcode":"1072 lk",
    "iso:country":"NL",
    "sg:address":"F Bolstr 28",
    "sg:city":"Amsterdam",
    "sg:orig_category":"Boekhandels",
    "sg:phone":"+31 20 679 4649",
    "sg:postcode":"1072 LK",
    "sg:province":"Noord-Holland",
    "wof:name":"Wanuskewin",
    "wof:placetype":"venue"
},
  "geometry": {"coordinates":[4.89067,52.354012],"type":"Point"}
}