{
  "type": "Feature",
  "properties": {
    "addr:full":"Elft 18 Hippolytushoef North Holland 1777 AD",
    "addr:housenumber":"18",
    "addr:postcode":"1777 ad",
    "addr:street":"Elft",
    "iso:country":"NL",
    "sg:address":"Elft 18",
    "sg:city":"Hippolytushoef",
    "sg:orig_category":"Technische Studies And Onderzoek",
    "sg:phone":"+31 227 592 354",
    "sg:postcode":"1777 AD",
    "sg:province":"North Holland",
    "wof:name":"S J Veenstra Arboburo",
    "wof:placetype":"venue"
},
  "geometry": {"coordinates":[4.966466,52.906963],"type":"Point"}
}