{
  "type": "Feature",
  "properties": {
    "addr:full":"Admiraliteitskade 50 Rotterdam South Holland 3063 ED",
    "addr:housenumber":"50",
    "addr:postcode":"3063 ed",
    "addr:street":"Admiraliteitskade",
    "iso:country":"NL",
    "sg:address":"Admiraliteitskade 50",
    "sg:city":"Rotterdam",
    "sg:classifiers":[
        {
            "category":"Professional",
            "subcategory":"Accounting & Tax Preparation",
            "type":"Services"
        }
    ],
    "sg:phone":"+31 10 272 1500",
    "sg:postcode":"3063 ED",
    "sg:province":"South Holland",
    "sg:tags":[
        "accountant"
    ],
    "wof:name":"Deloitte & Touche",
    "wof:placetype":"venue"
},
  "geometry": {"coordinates":[4.5038528442,51.9214363098],"type":"Point"}
}