{
  "type": "Feature",
  "properties": {
    "addr:full":"Daalmansplnts 42 Boskoop Zuid-Holland 2771 SH",
    "addr:housenumber":"42;2771",
    "addr:postcode":"sh",
    "addr:street":"Daalmansplnts",
    "iso:country":"NL",
    "sg:address":"Daalmansplnts 42",
    "sg:city":"Boskoop",
    "sg:orig_category":"Airconditioning",
    "sg:phone":"+31 172 213 766",
    "sg:postcode":"2771 SH",
    "sg:province":"Zuid-Holland",
    "wof:name":"Airedale Continental Bv",
    "wof:placetype":"venue"
},
  "geometry": {"coordinates":[4.65922,52.074268],"type":"Point"}
}