{
  "type": "Feature",
  "properties": {
    "addr:full":"Wynstr 84C Rotterdam Zuid-Holland 3011 TP",
    "addr:housenumber":"84c",
    "addr:postcode":"3011 tp",
    "addr:street":"Wynstr",
    "iso:country":"NL",
    "sg:address":"Wynstr 84C",
    "sg:city":"Rotterdam",
    "sg:orig_category":"Architecten En Architectenbureaus",
    "sg:phone":"+31 10 280 9050",
    "sg:postcode":"3011 TP",
    "sg:province":"Zuid-Holland",
    "sg:website":"http://www.hulshof-architecten.nl",
    "wof:name":"Hulshof Architecten",
    "wof:placetype":"venue"
},
  "geometry": {"coordinates":[4.478455,51.922836],"type":"Point"}
}