{
  "type": "Feature",
  "properties": {
    "addr:full":"Rieteiland 70 Rijswijk Zh South Holland 2285 JV",
    "addr:housenumber":"70",
    "addr:postcode":"2285 jv",
    "addr:street":"Rieteiland",
    "iso:country":"NL",
    "sg:address":"Rieteiland 70",
    "sg:city":"Rijswijk Zh",
    "sg:orig_category":"Marktonderzoekbureaus",
    "sg:phone":"+31 70 388 6074",
    "sg:postcode":"2285 JV",
    "sg:province":"South Holland",
    "wof:name":"Van Winkelen Marketing Diensten",
    "wof:placetype":"venue"
},
  "geometry": {"coordinates":[4.298961,52.032261],"type":"Point"}
}