{
  "type": "Feature",
  "properties": {
    "addr:full":"Nederlandplein 98 Eindhoven Noord-Brabant 5628 AJ",
    "addr:housenumber":"98",
    "addr:postcode":"5628 aj",
    "addr:street":"Nederlandplein",
    "iso:country":"NL",
    "sg:address":"Nederlandplein 98",
    "sg:city":"Eindhoven",
    "sg:orig_category":"Kappers",
    "sg:phone":"+31 40 241 8968",
    "sg:postcode":"5628 AJ",
    "sg:province":"Noord-Brabant",
    "wof:name":"P.Vissenberg",
    "wof:placetype":"venue"
},
  "geometry": {"coordinates":[5.463189,51.478886],"type":"Point"}
}