{
  "type": "Feature",
  "properties": {
    "addr:full":"Cederstraat 53 Ijmuiden North Holland 1971 KB",
    "addr:housenumber":"53",
    "addr:postcode":"1971 kb",
    "addr:street":"Cederstraat",
    "iso:country":"NL",
    "sg:address":"Cederstraat 53",
    "sg:city":"Ijmuiden",
    "sg:orig_category":"Kappers",
    "sg:phone":"+31 255 510 819",
    "sg:postcode":"1971 KB",
    "sg:province":"North Holland",
    "wof:name":"Kapsalon Frans Neve",
    "wof:placetype":"venue"
},
  "geometry": {"coordinates":[4.6307778358,52.4563789368],"type":"Point"}
}