{
  "type": "Feature",
  "properties": {
    "addr:full":"Klooster Leuterstraat 22 Wijk Bij Duurstede Utrecht 3961 AZ",
    "addr:housenumber":"22",
    "addr:postcode":"3961",
    "addr:street":"Klooster Leuterstraat",
    "iso:country":"NL",
    "sg:address":"Klooster Leuterstraat 22",
    "sg:city":"Wijk Bij Duurstede",
    "sg:orig_category":"Huishoudapparatuur, Televisies And Radio'S",
    "sg:phone":"+31 343 575 143",
    "sg:postcode":"3961 AZ",
    "sg:province":"Utrecht",
    "wof:name":"Ep Electronic Partner",
    "wof:placetype":"venue"
},
  "geometry": {"coordinates":[5.347184,51.972458],"type":"Point"}
}