{
  "type": "Feature",
  "properties": {
    "addr:full":"Scheepersdk 5 Oisterwyk Noord-Brabant 5062 EA",
    "addr:housenumber":"5",
    "addr:postcode":"5062 ea",
    "addr:street":"Scheepersdk",
    "iso:country":"NL",
    "sg:address":"Scheepersdk 5",
    "sg:city":"Oisterwyk",
    "sg:orig_category":"Orthopedisch Schoeisel",
    "sg:phone":"+31 13 521 6559",
    "sg:postcode":"5062 EA",
    "sg:province":"Noord-Brabant",
    "wof:name":"Broeks Steunzolen",
    "wof:placetype":"venue"
},
  "geometry": {"coordinates":[5.202272892,51.5787658691],"type":"Point"}
}