{
  "type": "Feature",
  "properties": {
    "addr:full":"Oostenburgervoorstraat 156/2 Amsterdam Noord-Holland 1018 MR",
    "addr:housenumber":"156 / 2",
    "addr:postcode":"1018 mr",
    "addr:street":"Oostenburgervoorstraat",
    "iso:country":"NL",
    "sg:address":"Oostenburgervoorstraat 156/2",
    "sg:city":"Amsterdam",
    "sg:orig_category":"Geluidsopnamen",
    "sg:phone":"+31 20 420 5706",
    "sg:postcode":"1018 MR",
    "sg:province":"Noord-Holland",
    "wof:name":"H.F. Dijkstal",
    "wof:placetype":"venue"
},
  "geometry": {"coordinates":[4.924455,52.369949],"type":"Point"}
}