{
  "type": "Feature",
  "properties": {
    "addr:full":"Regenwulp 14 Breda Noord-Brabant 4822 RH",
    "addr:housenumber":"14",
    "addr:postcode":"4822 rh",
    "addr:street":"Regenwulp",
    "iso:country":"NL",
    "sg:address":"Regenwulp 14",
    "sg:city":"Breda",
    "sg:classifiers":[
        {
            "category":"Shopping",
            "subcategory":"News",
            "type":"Retail Goods"
        }
    ],
    "sg:phone":"+31 76 520 6905",
    "sg:postcode":"4822 RH",
    "sg:province":"Noord-Brabant",
    "sg:tags":[
        "maandbladen",
        "en",
        "week-"
    ],
    "wof:name":"Riant Wonen",
    "wof:placetype":"venue"
},
  "geometry": {"coordinates":[4.7362790108,51.6179084778],"type":"Point"}
}