{
  "type": "Feature",
  "properties": {
    "addr:full":"Zuiderspoorstr 11-13 Enschede Overijssel 7512 AX",
    "addr:housenumber":"11-13",
    "addr:postcode":"7512 ax",
    "iso:country":"NL",
    "sg:address":"Zuiderspoorstr 11-13",
    "sg:city":"Enschede",
    "sg:orig_category":"Energiebesparing",
    "sg:phone":"+31 53 480 7140",
    "sg:postcode":"7512 AX",
    "sg:province":"Overijssel",
    "sg:website":"http://www.enerdeco.nl",
    "wof:name":"Enerdeco Bv",
    "wof:placetype":"venue"
},
  "geometry": {"coordinates":[6.889281,52.213341],"type":"Point"}
}