{
  "type": "Feature",
  "properties": {
    "addr:full":"Colosseum 25 Enschede Overijssel 7521 PV",
    "addr:housenumber":"25",
    "addr:postcode":"7521 pv",
    "addr:street":"Colosseum",
    "iso:country":"NL",
    "sg:address":"Colosseum 25",
    "sg:city":"Enschede",
    "sg:orig_category":"Medische Installaties En Instrumenten - Fabrieken",
    "sg:phone":"+31 53 480 3700",
    "sg:postcode":"7521 PV",
    "sg:province":"Overijssel",
    "sg:website":"http://www.mmsinternational.com",
    "wof:name":"Mms Bv",
    "wof:placetype":"venue"
},
  "geometry": {"coordinates":[6.840406,52.240265],"type":"Point"}
}