{
  "type": "Feature",
  "properties": {
    "addr:full":"Hurksestraat 1 Eindhoven Noord-Brabant 5652 AH",
    "addr:housenumber":"1",
    "addr:postcode":"5652 ah",
    "addr:street":"Hurksestraat",
    "iso:country":"NL",
    "sg:address":"Hurksestraat 1",
    "sg:city":"Eindhoven",
    "sg:orig_category":"Parfum And Cosmetica Gh",
    "sg:phone":"+31 40 252 3535",
    "sg:postcode":"5652 AH",
    "sg:province":"Noord-Brabant",
    "wof:name":"Treffina International Trading Bv",
    "wof:placetype":"venue"
},
  "geometry": {"coordinates":[5.446011,51.430157],"type":"Point"}
}