{
  "type": "Feature",
  "properties": {
    "addr:full":"Pr W De Zwijgerln 6 Houten Utrecht 3991 BR",
    "addr:housenumber":"6",
    "addr:postcode":"3991 br",
    "addr:street":"W De Zwijgerln",
    "iso:country":"NL",
    "sg:address":"Pr W De Zwijgerln 6",
    "sg:city":"Houten",
    "sg:orig_category":"Beeldende Kunstenaars",
    "sg:phone":"+31 30 637 9454",
    "sg:postcode":"3991 BR",
    "sg:province":"Utrecht",
    "wof:name":"Roffiaen, M L W",
    "wof:placetype":"venue"
},
  "geometry": {"coordinates":[5.169435,52.036541],"type":"Point"}
}