{
  "type": "Feature",
  "properties": {
    "iso:country":"NL",
    "sg:address":"Hendrik Staetslaan 83-85",
    "sg:city":"Eindhoven",
    "sg:classifiers":[
        {
            "category":"Communications",
            "subcategory":"Television Station",
            "type":"Services"
        }
    ],
    "sg:phone":"+31 40 245 7511",
    "sg:postcode":"5622 HM",
    "sg:province":"Noord-Brabant",
    "sg:tags":[
        "video",
        "audio",
        "verhuur"
    ],
    "wof:name":"Number One Videoshop",
    "wof:placetype":"venue"
},
  "geometry": {"coordinates":[5.463794,51.463299],"type":"Point"}
}