{
  "type": "Feature",
  "properties": {
    "addr:full":"Agaatln 327 Leiden South Holland 2332 RA",
    "addr:housenumber":"327",
    "addr:postcode":"2332 ra",
    "iso:country":"NL",
    "sg:address":"Agaatln 327",
    "sg:city":"Leiden",
    "sg:orig_category":"Betonijzervlechten",
    "sg:phone":"+31 71 576 7836",
    "sg:postcode":"2332 RA",
    "sg:province":"South Holland",
    "wof:name":"Hoekstra",
    "wof:placetype":"venue"
},
  "geometry": {"coordinates":[4.46377,52.159088],"type":"Point"}
}