{
  "type": "Feature",
  "properties": {
    "addr:full":"Achter De Hoven 16A Maasbree Limburg 5993 CR",
    "addr:housenumber":"16a",
    "addr:postcode":"5993 cr",
    "addr:street":"Achter De Hoven",
    "iso:country":"NL",
    "sg:address":"Achter De Hoven 16A",
    "sg:city":"Maasbree",
    "sg:classifiers":[
        {
            "category":"Professional",
            "subcategory":"Accounting & Tax Preparation",
            "type":"Services"
        }
    ],
    "sg:phone":"+31 77 465 7010",
    "sg:postcode":"5993 CR",
    "sg:province":"Limburg",
    "sg:tags":[
        "accountant",
        "en",
        "-kantoren",
        "register-"
    ],
    "wof:name":"Thielen, Drs H W",
    "wof:placetype":"venue"
},
  "geometry": {"coordinates":[6.053187,51.359962],"type":"Point"}
}