{
  "type": "Feature",
  "properties": {
    "addr:full":"Lanckhorstln 59 Heemstede Noord-Holland 2101 BA",
    "addr:housenumber":"59",
    "addr:postcode":"2101 ba",
    "addr:street":"Lanckhorstln",
    "iso:country":"NL",
    "sg:address":"Lanckhorstln 59",
    "sg:city":"Heemstede",
    "sg:orig_category":"Hypotheken",
    "sg:phone":"+31 23 528 7150",
    "sg:postcode":"2101 BA",
    "sg:province":"Noord-Holland",
    "sg:website":"http://www.kokmakelaars.nl",
    "wof:name":"Kok Hypotheken",
    "wof:placetype":"venue"
},
  "geometry": {"coordinates":[4.62205,52.357433],"type":"Point"}
}