{
  "type": "Feature",
  "properties": {
    "addr:full":"Koningin Emmaplein 1 Maastricht Limburg 6211 NG",
    "addr:housenumber":"1",
    "addr:postcode":"6211 ng",
    "addr:street":"Koningin Emmaplein",
    "iso:country":"NL",
    "sg:address":"Koningin Emmaplein 1",
    "sg:city":"Maastricht",
    "sg:orig_category":"Verlichting And Huishoudartikelen",
    "sg:phone":"+31 43 326 0403",
    "sg:postcode":"6211 NG",
    "sg:province":"Limburg",
    "wof:name":"Van Wissem Porselein",
    "wof:placetype":"venue"
},
  "geometry": {"coordinates":[5.678087,50.849522],"type":"Point"}
}