{
  "type": "Feature",
  "properties": {
    "iso:country":"NL",
    "sg:address":"Bitterstr 57",
    "sg:city":"Zwolle",
    "sg:orig_category":"Verenigingen En Stichtingen",
    "sg:phone":"+31 38 429 1281",
    "sg:postcode":"8011 XK",
    "sg:province":"Overijssel",
    "wof:name":"Welzijn Ouderen, Sticht",
    "wof:placetype":"venue"
},
  "geometry": {"coordinates":[6.09283,52.513538],"type":"Point"}
}