{
  "type": "Feature",
  "properties": {
    "iso:country":"NL",
    "sg:address":"Winterpad 6",
    "sg:city":"Delft",
    "sg:orig_category":"Psychologen",
    "sg:phone":"+31 15 213 6758",
    "sg:postcode":"2614 WE",
    "sg:province":"Zuid-Holland",
    "wof:name":"Somerwil, Drs C J",
    "wof:placetype":"venue"
},
  "geometry": {"coordinates":[4.338577,52.006493],"type":"Point"}
}