{
  "type": "Feature",
  "properties": {
    "addr:full":"Kerkstr 37 Hoogezand Groningen 9601 AA",
    "addr:housenumber":"37",
    "addr:postcode":"9601 aa",
    "addr:street":"Kerkstr",
    "iso:country":"NL",
    "sg:address":"Kerkstr 37",
    "sg:city":"Hoogezand",
    "sg:orig_category":"Adviesbureaus Elektrotechniek",
    "sg:phone":"+31 598 394 022",
    "sg:postcode":"9601 AA",
    "sg:province":"Groningen",
    "wof:name":"Koops",
    "wof:placetype":"venue"
},
  "geometry": {"coordinates":[6.756176,53.167305],"type":"Point"}
}