{
  "type": "Feature",
  "properties": {
    "addr:full":"Damstr 8 Haarlem Noord-Holland 2011 HA",
    "addr:housenumber":"8",
    "addr:postcode":"2011 ha",
    "addr:street":"Damstr",
    "iso:country":"NL",
    "sg:address":"Damstr 8",
    "sg:city":"Haarlem",
    "sg:orig_category":"Makelaars En Adviseurs Onroerende Goederen",
    "sg:phone":"+31 23 553 0999",
    "sg:postcode":"2011 HA",
    "sg:province":"Noord-Holland",
    "wof:name":"Hahn & Van Engelen",
    "wof:placetype":"venue"
},
  "geometry": {"coordinates":[4.638583,52.380478],"type":"Point"}
}