{
  "type": "Feature",
  "properties": {
    "iso:country":"NL",
    "sg:address":"Marktstr 9",
    "sg:city":"Zevenaar",
    "sg:orig_category":"Bloemen En Planten",
    "sg:phone":"+31 316 344 577",
    "sg:postcode":"6901 AK",
    "sg:province":"Gelderland",
    "wof:name":"Meeuwsen Vof",
    "wof:placetype":"venue"
},
  "geometry": {"coordinates":[6.076501,51.927834],"type":"Point"}
}