{
  "type": "Feature",
  "properties": {
    "addr:full":"Blauw Druifje 2 Papendrecht Zuid-Holland 3353 XL",
    "addr:housenumber":"2",
    "addr:postcode":"3353 xl",
    "addr:street":"Blauw Druifje",
    "iso:country":"NL",
    "sg:address":"Blauw Druifje 2",
    "sg:city":"Papendrecht",
    "sg:orig_category":"Grondwerken",
    "sg:phone":"+31 78 641 5812",
    "sg:postcode":"3353 XL",
    "sg:province":"Zuid-Holland",
    "wof:name":"Korevaar",
    "wof:placetype":"venue"
},
  "geometry": {"coordinates":[4.689731,51.831959],"type":"Point"}
}