{
  "type": "Feature",
  "properties": {
    "iso:country":"NL",
    "sg:address":"Industriestr 11",
    "sg:city":"Naaldwyk",
    "sg:orig_category":"Adviesbureaus Bouwkunde",
    "sg:phone":"+31 174 621 700",
    "sg:postcode":"2671 CT",
    "sg:province":"Zuid-Holland",
    "wof:name":"Aad Bom, Archiplan",
    "wof:placetype":"venue"
},
  "geometry": {"coordinates":[4.212344,51.999657],"type":"Point"}
}