{
  "type": "Feature",
  "properties": {
    "iso:country":"NL",
    "sg:address":"C V Rennesln 6",
    "sg:city":"Almelo",
    "sg:orig_category":"Verenigingen En Stichtingen",
    "sg:phone":"+31 546 850 983",
    "sg:postcode":"7604 KV",
    "sg:province":"Overijssel",
    "wof:name":"Knooppunt, 'T",
    "wof:placetype":"venue"
},
  "geometry": {"coordinates":[6.664543,52.354954],"type":"Point"}
}