{
  "type": "Feature",
  "properties": {
    "addr:full":"Woldstr 47 Meppel Drenthe 7941 LG",
    "addr:housenumber":"47",
    "addr:postcode":"7941 lg",
    "addr:street":"Woldstr",
    "iso:country":"NL",
    "sg:address":"Woldstr 47",
    "sg:city":"Meppel",
    "sg:orig_category":"Woninginrichting",
    "sg:phone":"+31 522 242 353",
    "sg:postcode":"7941 LG",
    "sg:province":"Drenthe",
    "wof:name":"Iets Anders",
    "wof:placetype":"venue"
},
  "geometry": {"coordinates":[6.1926379204,52.6983070374],"type":"Point"}
}