{
  "type": "Feature",
  "properties": {
    "addr:full":"Op De Dries 36 Berg En Terblyt Limburg 6325 HC",
    "addr:housenumber":"36",
    "addr:postcode":"6325 hc",
    "addr:street":"Op De Dries;Limburg",
    "iso:country":"NL",
    "sg:address":"Op De Dries 36",
    "sg:city":"Berg En Terblyt",
    "sg:orig_category":"Makelaars En Adviseurs Onroerende Goederen",
    "sg:phone":"+31 43 604 2065",
    "sg:postcode":"6325 HC",
    "sg:province":"Limburg",
    "wof:name":"Hendriks",
    "wof:placetype":"venue"
},
  "geometry": {"coordinates":[5.794667,50.860645],"type":"Point"}
}