{
  "type": "Feature",
  "properties": {
    "addr:full":"Kralingse Plasln 38 Rotterdam South Holland 3061 BA",
    "addr:housenumber":"38",
    "addr:postcode":"3061 ba",
    "iso:country":"NL",
    "sg:address":"Kralingse Plasln 38",
    "sg:city":"Rotterdam",
    "sg:orig_category":"Verenigingen En Stichtingen",
    "sg:phone":"+31 10 452 0659",
    "sg:postcode":"3061 BA",
    "sg:province":"South Holland",
    "wof:name":"Eendragt Maakt Magt, Soc",
    "wof:placetype":"venue"
},
  "geometry": {"coordinates":[4.512134,51.930439],"type":"Point"}
}