{
  "type": "Feature",
  "properties": {
    "addr:full":"Prinses Beatrixlaan 17 Tiel Gelderland 4001 AG",
    "addr:housenumber":"17",
    "addr:postcode":"4001",
    "addr:street":"Prinses Beatrixlaan;Gelderland",
    "iso:country":"NL",
    "sg:address":"Prinses Beatrixlaan 17",
    "sg:city":"Tiel",
    "sg:orig_category":"Werving And Selectie Van Vast Personeel",
    "sg:phone":"+31 344 626 919",
    "sg:postcode":"4001 AG",
    "sg:province":"Gelderland",
    "wof:name":"Hoogt Huberts & Blok Detachering Bv De",
    "wof:placetype":"venue"
},
  "geometry": {"coordinates":[5.4276828766,51.8871307373],"type":"Point"}
}