{
  "type": "Feature",
  "properties": {
    "iso:country":"NL",
    "sg:address":"Pleinweg 86 A",
    "sg:city":"Rotterdam",
    "sg:orig_category":"Erotische Etablissementen",
    "sg:phone":"+31 10 481 2161",
    "sg:postcode":"3083 EJ",
    "sg:province":"Zuid-Holland",
    "wof:name":"Brizi`S Sm-Studio",
    "wof:placetype":"venue"
},
  "geometry": {"coordinates":[4.483813,51.890244],"type":"Point"}
}