{
  "type": "Feature",
  "properties": {
    "iso:country":"NL",
    "sg:address":"Vredenburg 1",
    "sg:city":"Utrecht",
    "sg:orig_category":"Visspeciaalzaken",
    "sg:phone":"+31 30 231 8628",
    "sg:postcode":"3511 BA",
    "sg:province":"Utrecht",
    "wof:name":"J.H. Van Daalen Vishandel",
    "wof:placetype":"venue"
},
  "geometry": {"coordinates":[5.11506,52.09203],"type":"Point"}
}