{
  "type": "Feature",
  "properties": {
    "addr:full":"Rivierdk 677 Sliedrecht South Holland 3361 BT",
    "addr:housenumber":"677",
    "addr:postcode":"3361 bt",
    "iso:country":"NL",
    "sg:address":"Rivierdk 677",
    "sg:city":"Sliedrecht",
    "sg:orig_category":"Gordijnen",
    "sg:phone":"+31 184 410 611",
    "sg:postcode":"3361 BT",
    "sg:province":"South Holland",
    "wof:name":"Kop Woninginrichting",
    "wof:placetype":"venue"
},
  "geometry": {"coordinates":[4.781718,51.81675],"type":"Point"}
}