{
  "type": "Feature",
  "properties": {
    "iso:country":"NL",
    "sg:address":"Spoorhaag 138",
    "sg:city":"Houten",
    "sg:orig_category":"Huishoudapparatuur, Televisies And Radio'S",
    "sg:phone":"+31 30 636 2400",
    "sg:postcode":"3995 EA",
    "sg:province":"Utrecht",
    "wof:name":"Megapool",
    "wof:placetype":"venue"
},
  "geometry": {"coordinates":[5.168113,52.036327],"type":"Point"}
}