{
  "type": "Feature",
  "properties": {
    "addr:full":"Galjoen 2001 Lelystad North Holland 8243 LP",
    "addr:housenumber":"2001",
    "addr:postcode":"8243 lp",
    "addr:street":"Galjoen",
    "iso:country":"NL",
    "sg:address":"Galjoen 2001",
    "sg:city":"Lelystad",
    "sg:orig_category":"Onderhoudswerken",
    "sg:phone":"+31 320 247 321",
    "sg:postcode":"8243 LP",
    "sg:province":"North Holland",
    "wof:name":"Kesteren, A Van",
    "wof:placetype":"venue"
},
  "geometry": {"coordinates":[5.438573,52.509682],"type":"Point"}
}