{
  "type": "Feature",
  "properties": {
    "addr:full":"Muskuszand 9 Ochten Gelderland 4051 CR",
    "addr:housenumber":"9",
    "addr:postcode":"4051 cr",
    "addr:street":"Muskuszand;Gelderland",
    "iso:country":"NL",
    "sg:address":"Muskuszand 9",
    "sg:city":"Ochten",
    "sg:classifiers":[
        {
            "category":"Wholesale",
            "subcategory":"Meat",
            "type":"Manufacturing & Wholesale Goods"
        }
    ],
    "sg:phone":"+31 344 644 875",
    "sg:postcode":"4051 CR",
    "sg:province":"Gelderland",
    "sg:tags":[
        "regeltechniek",
        "en",
        "meet-"
    ],
    "sg:website":"http://www.thabs.nl",
    "wof:name":"Thabs Nederland",
    "wof:placetype":"venue"
},
  "geometry": {"coordinates":[5.593433,51.914085],"type":"Point"}
}