{
  "type": "Feature",
  "properties": {
    "addr:full":"Landerum 11 Terschelling Landr Provincie Friesland 8893 GX",
    "addr:housenumber":"11",
    "addr:postcode":"8893 gx",
    "addr:street":"Landerum;Friesland",
    "iso:country":"NL",
    "sg:address":"Landerum 11",
    "sg:city":"Terschelling Landr",
    "sg:orig_category":"Vakantieverblijven",
    "sg:phone":"+31 562 448 957",
    "sg:postcode":"8893 GX",
    "sg:province":"Provincie Friesland",
    "wof:name":"Rollekeyn",
    "wof:placetype":"venue"
},
  "geometry": {"coordinates":[5.298768,53.386551],"type":"Point"}
}