{
  "type": "Feature",
  "properties": {
    "addr:full":"Amsterdamsew 168 Amstelveen Noord-Holland 1182 HK",
    "addr:housenumber":"168",
    "addr:postcode":"1182 hk",
    "iso:country":"NL",
    "sg:address":"Amsterdamsew 168",
    "sg:city":"Amstelveen",
    "sg:orig_category":"Verenigingen En Stichtingen",
    "sg:phone":"+31 20 641 1864",
    "sg:postcode":"1182 HK",
    "sg:province":"Noord-Holland",
    "wof:name":"Vrijm Moza\u00efek",
    "wof:placetype":"venue"
},
  "geometry": {"coordinates":[4.847006,52.310925],"type":"Point"}
}