{
  "type": "Feature",
  "properties": {
    "iso:country":"NL",
    "sg:address":"De Iep 11",
    "sg:city":"Hellevoetsluis",
    "sg:orig_category":"Adviesbureaus Bedrijfsorganisatie",
    "sg:phone":"+31 181 311 029",
    "sg:postcode":"3224 TG",
    "sg:province":"South Holland",
    "wof:name":"Wizzers",
    "wof:placetype":"venue"
},
  "geometry": {"coordinates":[4.148882,51.82851],"type":"Point"}
}