{
  "type": "Feature",
  "properties": {
    "iso:country":"NL",
    "sg:address":"De Ruyterln 18",
    "sg:city":"Velp Gld",
    "sg:orig_category":"Adviesbureaus Bedrijfsorganisatie",
    "sg:phone":"+31 26 361 4793",
    "sg:postcode":"6881 GV",
    "sg:province":"Gelderland",
    "wof:name":"Burgers Beheer Bv, E M A",
    "wof:placetype":"venue"
},
  "geometry": {"coordinates":[5.974033,51.996021],"type":"Point"}
}