{
  "type": "Feature",
  "properties": {
    "addr:full":"Herenstr 87 Voorburg South Holland 2271 CC",
    "addr:housenumber":"87",
    "addr:postcode":"2271 cc",
    "addr:street":"Herenstr",
    "iso:country":"NL",
    "sg:address":"Herenstr 87",
    "sg:city":"Voorburg",
    "sg:orig_category":"Woninginrichting",
    "sg:phone":"+31 70 387 5002",
    "sg:postcode":"2271 CC",
    "sg:province":"South Holland",
    "wof:name":"Mi Vida",
    "wof:placetype":"venue"
},
  "geometry": {"coordinates":[4.3638820648,52.0674934387],"type":"Point"}
}