{
  "type": "Feature",
  "properties": {
    "addr:full":"In De Cramer 14 Heerlen Limburg 6411 RS",
    "addr:housenumber":"14",
    "addr:postcode":"6411 rs",
    "addr:street":"In De Cramer",
    "iso:country":"NL",
    "sg:address":"In De Cramer 14",
    "sg:city":"Heerlen",
    "sg:orig_category":"Elektrotechnische Apparatuur - Fabrieken En Groothandel",
    "sg:phone":"+31 45 571 7106",
    "sg:postcode":"6411 RS",
    "sg:province":"Limburg",
    "wof:name":"Bernard Bv",
    "wof:placetype":"venue"
},
  "geometry": {"coordinates":[5.957756,50.894886],"type":"Point"}
}