{
  "type": "Feature",
  "properties": {
    "addr:full":"Groenewegje 161 'S Gravenhage Zuid-Holland 2515 NC",
    "addr:housenumber":"161 ';2515",
    "addr:postcode":"nc",
    "addr:street":"Groenewegje",
    "iso:country":"NL",
    "sg:address":"Groenewegje 161",
    "sg:city":"'S Gravenhage",
    "sg:orig_category":"Diverse Grafische Activiteiten",
    "sg:phone":"+31 70 384 0654",
    "sg:postcode":"2515 NC",
    "sg:province":"Zuid-Holland",
    "wof:name":"J J Andela",
    "wof:placetype":"venue"
},
  "geometry": {"coordinates":[4.318503,52.074062],"type":"Point"}
}