{
  "type": "Feature",
  "properties": {
    "addr:full":"Frans Halsstraat 35I Amsterdam Noord-Holland 1072 BK",
    "addr:housenumber":"35i",
    "addr:postcode":"1072 bk",
    "addr:street":"Frans Halsstraat",
    "iso:country":"NL",
    "sg:address":"Frans Halsstraat 35I",
    "sg:city":"Amsterdam",
    "sg:orig_category":"Vertaal- And Tolkenbureaus",
    "sg:phone":"+31 20 673 7592",
    "sg:postcode":"1072 BK",
    "sg:province":"Noord-Holland",
    "wof:name":"A.I.T. Oliemans",
    "wof:placetype":"venue"
},
  "geometry": {"coordinates":[4.888904,52.356972],"type":"Point"}
}