{
  "type": "Feature",
  "properties": {
    "addr:full":"Vryenbergwg 60 Loenen Gld Gelderland 7371 AB",
    "addr:housenumber":"60",
    "addr:postcode":"7371 ab",
    "addr:street":"Vryenbergwg;Gld Gelderland",
    "iso:country":"NL",
    "sg:address":"Vryenbergwg 60",
    "sg:city":"Loenen Gld",
    "sg:orig_category":"Juweliers",
    "sg:phone":"+31 6 20535627",
    "sg:postcode":"7371 AB",
    "sg:province":"Gelderland",
    "wof:name":"Amba Art Vof",
    "wof:placetype":"venue"
},
  "geometry": {"coordinates":[6.01798,52.11705],"type":"Point"}
}