{
  "type": "Feature",
  "properties": {
    "addr:full":"Hamakerstr 77 Rotterdam South Holland 3052 JA",
    "addr:housenumber":"77",
    "addr:postcode":"3052 ja",
    "addr:street":"Hamakerstr",
    "iso:country":"NL",
    "sg:address":"Hamakerstr 77",
    "sg:city":"Rotterdam",
    "sg:orig_category":"Kinderopvang",
    "sg:phone":"+31 10 285 9696",
    "sg:postcode":"3052 JA",
    "sg:province":"South Holland",
    "wof:name":"Wilgen, De",
    "wof:placetype":"venue"
},
  "geometry": {"coordinates":[4.463888,51.951881],"type":"Point"}
}