{
  "type": "Feature",
  "properties": {
    "iso:country":"NL",
    "sg:address":"Margrietstr 2",
    "sg:city":"Bodegraven",
    "sg:orig_category":"Kaasgroothandel",
    "sg:phone":"+31 172 612 209",
    "sg:postcode":"2411 VT",
    "sg:province":"South Holland",
    "wof:name":"Groot-Verburg, De",
    "wof:placetype":"venue"
},
  "geometry": {"coordinates":[4.7495398521,52.0884628296],"type":"Point"}
}