{
  "type": "Feature",
  "properties": {
    "iso:country":"NL",
    "sg:address":"Nassauln 5A",
    "sg:city":"Haarlem",
    "sg:orig_category":"Bloemen En Planten",
    "sg:phone":"+31 23 542 2296",
    "sg:postcode":"2011 PB",
    "sg:province":"Noord-Holland",
    "wof:name":"House Of Flowers",
    "wof:placetype":"venue"
},
  "geometry": {"coordinates":[4.642253,52.380562],"type":"Point"}
}