{
  "type": "Feature",
  "properties": {
    "addr:full":"Boeier 5 Hoorn Nh North Holland 1625 CG",
    "addr:housenumber":"5",
    "addr:postcode":"1625 cg",
    "addr:street":"Boeier;Nh North",
    "iso:country":"NL",
    "sg:address":"Boeier 5",
    "sg:city":"Hoorn Nh",
    "sg:orig_category":"Autorijscholen",
    "sg:phone":"+31 229 232 288",
    "sg:postcode":"1625 CG",
    "sg:province":"North Holland",
    "wof:name":"Vlotter Bv",
    "wof:placetype":"venue"
},
  "geometry": {"coordinates":[5.059718,52.658947],"type":"Point"}
}