{
  "type": "Feature",
  "properties": {
    "addr:full":"Nieuwe Heikantstraat 34 Vught Noord-Brabant 5263 AE",
    "addr:housenumber":"34",
    "addr:postcode":"5263 ae",
    "addr:street":"Nieuwe Heikantstraat",
    "iso:country":"NL",
    "sg:address":"Nieuwe Heikantstraat 34",
    "sg:city":"Vught",
    "sg:orig_category":"Meubelreparatie And -Restauratie",
    "sg:phone":"+31 73 656 3625",
    "sg:postcode":"5263 AE",
    "sg:province":"Noord-Brabant",
    "wof:name":"Meubelstoffeerderij Dekkers",
    "wof:placetype":"venue"
},
  "geometry": {"coordinates":[5.289574,51.658367],"type":"Point"}
}