{
  "type": "Feature",
  "properties": {
    "addr:full":"Pinaskade 53 Zoetermeer Zuid-Holland 2725 EN",
    "addr:housenumber":"53",
    "addr:postcode":"2725 en",
    "addr:street":"Pinaskade",
    "iso:country":"NL",
    "sg:address":"Pinaskade 53",
    "sg:city":"Zoetermeer",
    "sg:orig_category":"Hypotheken And Hypotheekbanken",
    "sg:phone":"+31 79 341 6182",
    "sg:postcode":"2725 EN",
    "sg:province":"Zuid-Holland",
    "wof:name":"F Rebel Hyp Visie Den Haag",
    "wof:placetype":"venue"
},
  "geometry": {"coordinates":[4.499099,52.073883],"type":"Point"}
}