{
  "type": "Feature",
  "properties": {
    "iso:country":"NL",
    "sg:address":"Pleiadenstr 136",
    "sg:city":"Haarlem",
    "sg:orig_category":"Peuterspeelzalen",
    "sg:phone":"+31 23 527 5968",
    "sg:postcode":"2024 TT",
    "sg:province":"Noord-Holland",
    "wof:name":"Nijntje",
    "wof:placetype":"venue"
},
  "geometry": {"coordinates":[4.635742,52.405582],"type":"Point"}
}