{
  "type": "Feature",
  "properties": {
    "addr:full":"Stationswg 74 Heiloo Noord-Holland 1851 LL",
    "addr:housenumber":"74",
    "addr:postcode":"1851 ll",
    "addr:street":"Stationswg",
    "iso:country":"NL",
    "sg:address":"Stationswg 74",
    "sg:city":"Heiloo",
    "sg:orig_category":"Herenkleding",
    "sg:phone":"+31 72 533 3308",
    "sg:postcode":"1851 LL",
    "sg:province":"Noord-Holland",
    "wof:name":"Blom",
    "wof:placetype":"venue"
},
  "geometry": {"coordinates":[4.70299,52.600098],"type":"Point"}
}