{
  "type": "Feature",
  "properties": {
    "addr:full":"Italieln 135 Heerlen Limburg 6414 TN",
    "addr:housenumber":"135",
    "addr:postcode":"6414",
    "iso:country":"NL",
    "sg:address":"Italieln 135",
    "sg:city":"Heerlen",
    "sg:orig_category":"Schilders",
    "sg:phone":"+31 45 523 2370",
    "sg:postcode":"6414 TN",
    "sg:province":"Limburg",
    "wof:name":"Ess",
    "wof:placetype":"venue"
},
  "geometry": {"coordinates":[5.98098,50.885506],"type":"Point"}
}