{
  "type": "Feature",
  "properties": {
    "addr:full":"Hoogstr 183B Rotterdam Zuid-Holland 3011 PM",
    "addr:housenumber":"183b",
    "addr:postcode":"3011 pm",
    "iso:country":"NL",
    "sg:address":"Hoogstr 183B",
    "sg:city":"Rotterdam",
    "sg:orig_category":"Sportschoenen - Winkels",
    "sg:phone":"+31 10 213 1465",
    "sg:postcode":"3011 PM",
    "sg:province":"Zuid-Holland",
    "sg:website":"http://www.footlocker-europe.com",
    "wof:name":"Foot Locker",
    "wof:placetype":"venue"
},
  "geometry": {"coordinates":[4.483433,51.920544],"type":"Point"}
}