{
  "type": "Feature",
  "properties": {
    "addr:full":"B Vd Brinkstr 20 Utrecht Utrecht 3532 GG",
    "addr:housenumber":"20",
    "addr:postcode":"3532 gg",
    "iso:country":"NL",
    "sg:address":"B Vd Brinkstr 20",
    "sg:city":"Utrecht",
    "sg:orig_category":"Verhuur",
    "sg:phone":"+31 30 293 1127",
    "sg:postcode":"3532 GG",
    "sg:province":"Utrecht",
    "sg:website":"http://www.herko-bus.nl",
    "wof:name":"Herko & Bus",
    "wof:placetype":"venue"
},
  "geometry": {"coordinates":[5.09129,52.095211],"type":"Point"}
}