{
  "type": "Feature",
  "properties": {
    "addr:full":"Tweede Groenelaan 14 Castricum North Holland 1901 HX",
    "addr:housenumber":"14",
    "addr:postcode":"1901 hx",
    "addr:street":"Tweede Groenelaan",
    "iso:country":"NL",
    "sg:address":"Tweede Groenelaan 14",
    "sg:city":"Castricum",
    "sg:orig_category":"Verzekeringen",
    "sg:phone":"+31 251 650 742",
    "sg:postcode":"1901 HX",
    "sg:province":"North Holland",
    "wof:name":"Ch Verstraete",
    "wof:placetype":"venue"
},
  "geometry": {"coordinates":[4.659306,52.55637],"type":"Point"}
}