{
  "type": "Feature",
  "properties": {
    "addr:full":"Laan Van Nieuwoord 5 Woudenberg Utrecht 3931 DD",
    "addr:housenumber":"5",
    "addr:postcode":"3931 dd",
    "addr:street":"Laan Van Nieuwoord",
    "iso:country":"NL",
    "sg:address":"Laan Van Nieuwoord 5",
    "sg:city":"Woudenberg",
    "sg:orig_category":"Loodgieterswerk, Verwarming And Sanitaire Installaties",
    "sg:phone":"+31 33 286 1769",
    "sg:postcode":"3931 DD",
    "sg:province":"Utrecht",
    "wof:name":"G.J. Dunsbergen",
    "wof:placetype":"venue"
},
  "geometry": {"coordinates":[5.409368,52.077995],"type":"Point"}
}