{
  "type": "Feature",
  "properties": {
    "iso:country":"NL",
    "sg:address":"Vinkekampwg 27",
    "sg:city":"Kootwykerbroek",
    "sg:classifiers":[
        {
            "category":"Sports & Exercise",
            "subcategory":"Stables",
            "type":"Entertainment"
        }
    ],
    "sg:phone":"+31 342 490 822",
    "sg:postcode":"3774 PK",
    "sg:province":"Gelderland",
    "sg:tags":[
        "maneges"
    ],
    "wof:name":"Finchcamp",
    "wof:placetype":"venue"
},
  "geometry": {"coordinates":[5.644254,52.138634],"type":"Point"}
}