{
  "type": "Feature",
  "properties": {
    "addr:full":"T Hoogtln 14A Noordwykerhout South Holland 2211 AN",
    "addr:housenumber":"14a",
    "addr:postcode":"2211 an",
    "addr:street":"Noordwykerhout South",
    "iso:country":"NL",
    "sg:address":"T Hoogtln 14A",
    "sg:city":"Noordwykerhout",
    "sg:orig_category":"Babykleding - Fabrieken En Groothandel",
    "sg:phone":"+31 252 341 939",
    "sg:postcode":"2211 AN",
    "sg:province":"South Holland",
    "wof:name":"Idee",
    "wof:placetype":"venue"
},
  "geometry": {"coordinates":[4.491189,52.26347],"type":"Point"}
}