{
  "type": "Feature",
  "properties": {
    "addr:full":"Adelaar 95 Oss Noord-Brabant 5348 EH",
    "addr:housenumber":"95",
    "addr:postcode":"5348 eh",
    "addr:street":"Adelaar",
    "iso:country":"NL",
    "sg:address":"Adelaar 95",
    "sg:city":"Oss",
    "sg:classifiers":[
        {
            "category":"Wholesale",
            "subcategory":"Meat",
            "type":"Manufacturing & Wholesale Goods"
        }
    ],
    "sg:phone":"+31 412 630 527",
    "sg:postcode":"5348 EH",
    "sg:province":"Noord-Brabant",
    "sg:tags":[
        "abattoir"
    ],
    "wof:name":"Heesen",
    "wof:placetype":"venue"
},
  "geometry": {"coordinates":[-77.235214,38.312599],"type":"Point"}
}