{
  "type": "Feature",
  "properties": {
    "addr:full":"Beekstraat 109 Arnhem Gelderland 6811 DZ",
    "addr:housenumber":"109",
    "addr:postcode":"6811 dz",
    "addr:street":"Beekstraat",
    "iso:country":"NL",
    "sg:address":"Beekstraat 109",
    "sg:city":"Arnhem",
    "sg:orig_category":"Schoenen",
    "sg:phone":"+31 26 442 3830",
    "sg:postcode":"6811 DZ",
    "sg:province":"Gelderland",
    "wof:name":"Flipse Schoenen Bv",
    "wof:placetype":"venue"
},
  "geometry": {"coordinates":[5.910427,51.981743],"type":"Point"}
}