{
  "type": "Feature",
  "properties": {
    "addr:full":"V Blanckenburgstr 80 Dordrecht Zuid-Holland 3314 WP",
    "addr:housenumber":"80",
    "addr:postcode":"3314 wp",
    "iso:country":"NL",
    "sg:address":"V Blanckenburgstr 80",
    "sg:city":"Dordrecht",
    "sg:orig_category":"Montagebedrijven",
    "sg:phone":"+31 78 657 9765",
    "sg:postcode":"3314 WP",
    "sg:province":"Zuid-Holland",
    "wof:name":"Rcw Montage & Timmerwerken",
    "wof:placetype":"venue"
},
  "geometry": {"coordinates":[4.653457,51.801723],"type":"Point"}
}