{
  "type": "Feature",
  "properties": {
    "iso:country":"NL",
    "sg:address":"Mignonpad 9",
    "sg:city":"Amersfoort",
    "sg:orig_category":"Homeopathie",
    "sg:phone":"+31 33 475 4534",
    "sg:postcode":"3816 ES",
    "sg:province":"Utrecht",
    "wof:name":"Beer, Judith De",
    "wof:placetype":"venue"
},
  "geometry": {"coordinates":[5.412433,52.154152],"type":"Point"}
}