{
  "type": "Feature",
  "properties": {
    "iso:country":"NL",
    "sg:address":"Westvlietwg 64",
    "sg:city":"S Gravenhage",
    "sg:orig_category":"Automaterialen En Gereedschappen",
    "sg:phone":"+31 70 319 2800",
    "sg:postcode":"2495 AA",
    "wof:name":"Pecar Automaterialen Bv",
    "wof:placetype":"venue"
},
  "geometry": {"coordinates":[4.35834,52.053719],"type":"Point"}
}