{
  "type": "Feature",
  "properties": {
    "addr:full":"Adriaanswg 3 Hengelo Ov Overijssel 7553 KB",
    "addr:housenumber":"3",
    "addr:postcode":"7553 kb",
    "addr:street":"Adriaanswg;Ov",
    "iso:country":"NL",
    "sg:address":"Adriaanswg 3",
    "sg:city":"Hengelo Ov",
    "sg:orig_category":"Verpakkingen En Verpakkingsmaterialen",
    "sg:phone":"+31 74 242 1777",
    "sg:postcode":"7553 KB",
    "sg:province":"Overijssel",
    "wof:name":"Elpack",
    "wof:placetype":"venue"
},
  "geometry": {"coordinates":[6.795536,52.257107],"type":"Point"}
}