{
  "type": "Feature",
  "properties": {
    "addr:full":"Koninginnegracht 72 'S Gravenhage South Holland 2514 AG",
    "addr:housenumber":"72",
    "addr:postcode":"2514",
    "addr:street":"Koninginnegracht;' S Gravenhage",
    "iso:country":"NL",
    "sg:address":"Koninginnegracht 72",
    "sg:city":"'S Gravenhage",
    "sg:orig_category":"Werving And Selectie Van Vast Personeel",
    "sg:phone":"+31 70 363 6010",
    "sg:postcode":"2514 AG",
    "sg:province":"South Holland",
    "wof:name":"Qm Engineering Services Bv",
    "wof:placetype":"venue"
},
  "geometry": {"coordinates":[4.3093500137,52.084148407],"type":"Point"}
}