{
  "type": "Feature",
  "properties": {
    "iso:country":"NL",
    "sg:address":"Kampbrugweg 3",
    "sg:city":"Beuningen Ov",
    "sg:orig_category":"Kampeerterreinen",
    "sg:phone":"+31 541 351 826",
    "sg:postcode":"7588 RK",
    "sg:province":"NL.08",
    "wof:name":"Natuurcamping 'T Olde Kottink",
    "wof:placetype":"venue"
},
  "geometry": {"coordinates":[7.0123119354,52.3543930054],"type":"Point"}
}