{
  "type": "Feature",
  "properties": {
    "addr:full":"Huigsloterdijk 395 Buitenkaag Noord-Holland 2158 LS",
    "addr:housenumber":"395",
    "addr:postcode":"2158 ls",
    "addr:street":"Huigsloterdijk",
    "iso:country":"NL",
    "sg:address":"Huigsloterdijk 395",
    "sg:city":"Buitenkaag",
    "sg:orig_category":"Banken And Kredietinstellingen",
    "sg:phone":"+31 252 544 597",
    "sg:postcode":"2158 LS",
    "sg:province":"Noord-Holland",
    "wof:name":"Rabobank",
    "wof:placetype":"venue"
},
  "geometry": {"coordinates":[4.560602,52.218933],"type":"Point"}
}