{
  "type": "Feature",
  "properties": {
    "iso:country":"NL",
    "sg:address":"De Ganzeboom 115",
    "sg:city":"Schalkhaar",
    "sg:orig_category":"Kunststofcoating",
    "sg:phone":"+31 570 623 543",
    "sg:postcode":"7433 GD",
    "sg:province":"Overijssel",
    "wof:name":"Soldicoat Bv",
    "wof:placetype":"venue"
},
  "geometry": {"coordinates":[6.199951,52.270351],"type":"Point"}
}