{
  "type": "Feature",
  "properties": {
    "addr:full":"Julianalaan 100 Raamsdonksveer Noord-Brabant 4941 JE",
    "addr:housenumber":"100",
    "addr:postcode":"4941 je",
    "addr:street":"Julianalaan",
    "iso:country":"NL",
    "sg:address":"Julianalaan 100",
    "sg:city":"Raamsdonksveer",
    "sg:orig_category":"Metaalwerken",
    "sg:phone":"+31 162 516 449",
    "sg:postcode":"4941 JE",
    "sg:province":"Noord-Brabant",
    "wof:name":"Hvr Hanegraaf - Van Rijn",
    "wof:placetype":"venue"
},
  "geometry": {"coordinates":[4.881248,51.69466],"type":"Point"}
}