{
  "type": "Feature",
  "properties": {
    "addr:full":"Grt Woerdln 36E Naaldwyk Zuid-Holland 2671 CL",
    "addr:housenumber":"36e",
    "addr:postcode":"2671",
    "addr:street":"Woerdln",
    "iso:country":"NL",
    "sg:address":"Grt Woerdln 36E",
    "sg:city":"Naaldwyk",
    "sg:orig_category":"Banden",
    "sg:phone":"+31 174 630 034",
    "sg:postcode":"2671 CL",
    "sg:province":"Zuid-Holland",
    "sg:website":"http://www.euromaster.com",
    "wof:name":"Euromaster",
    "wof:placetype":"venue"
},
  "geometry": {"coordinates":[4.205249,51.991398],"type":"Point"}
}