{
  "type": "Feature",
  "properties": {
    "addr:full":"Grotestraat 62 Cuijk Noord-Brabant 5431 DL",
    "addr:housenumber":"62",
    "addr:postcode":"5431 dl",
    "addr:street":"Grotestraat",
    "iso:country":"NL",
    "sg:address":"Grotestraat 62",
    "sg:city":"Cuijk",
    "sg:orig_category":"Bioscopen",
    "sg:phone":"+31 485 315 107",
    "sg:postcode":"5431 DL",
    "sg:province":"Noord-Brabant",
    "wof:name":"Bios En Filmtheater Cuijk",
    "wof:placetype":"venue"
},
  "geometry": {"coordinates":[5.88184,51.728397],"type":"Point"}
}