{
  "type": "Feature",
  "properties": {
    "addr:full":"F Scholtenstr 10Hs Amsterdam Noord-Holland 1051 EX",
    "addr:postcode":"1051 ex",
    "iso:country":"NL",
    "sg:address":"F Scholtenstr 10Hs",
    "sg:city":"Amsterdam",
    "sg:orig_category":"Fotografie Reclame En Mode",
    "sg:phone":"+31 20 622 6417",
    "sg:postcode":"1051 EX",
    "sg:province":"Noord-Holland",
    "wof:name":"Fotokantoor",
    "wof:placetype":"venue"
},
  "geometry": {"coordinates":[4.873173,52.384933],"type":"Point"}
}