{
  "type": "Feature",
  "properties": {
    "addr:full":"Tulpstr 30 Baarn Utrecht 3742 RP",
    "addr:housenumber":"30",
    "addr:postcode":"3742 rp",
    "addr:street":"Tulpstr",
    "iso:country":"NL",
    "sg:address":"Tulpstr 30",
    "sg:city":"Baarn",
    "sg:orig_category":"Schilders",
    "sg:phone":"+31 6 22288970",
    "sg:postcode":"3742 RP",
    "sg:province":"Utrecht",
    "wof:name":"Bas Ravenhorst Schildersbedrijf",
    "wof:placetype":"venue"
},
  "geometry": {"coordinates":[5.297309,52.205967],"type":"Point"}
}