{
  "type": "Feature",
  "properties": {
    "addr:full":"Rondweg 17 Wezep Gelderland 8091 XA",
    "addr:housenumber":"17",
    "addr:postcode":"8091 xa",
    "addr:street":"Rondweg",
    "iso:country":"NL",
    "sg:address":"Rondweg 17",
    "sg:city":"Wezep",
    "sg:orig_category":"Goederenvervoer Over De Weg",
    "sg:phone":"+31 38 375 9500",
    "sg:postcode":"8091 XA",
    "sg:province":"Gelderland",
    "wof:name":"Nt Nederland Int Transport En Expeditiebedrijf",
    "wof:placetype":"venue"
},
  "geometry": {"coordinates":[6.005641,52.474144],"type":"Point"}
}