{
  "type": "Feature",
  "properties": {
    "addr:full":"Antonetta Hoeve 27 Raamsdonksveer Noord-Brabant 4941 GM",
    "addr:housenumber":"27",
    "addr:postcode":"4941 gm",
    "addr:street":"Hoeve",
    "iso:country":"NL",
    "sg:address":"Antonetta Hoeve 27",
    "sg:city":"Raamsdonksveer",
    "sg:orig_category":"Verzekeringen - Verzekeringskantoren",
    "sg:phone":"+31 162 511 581",
    "sg:postcode":"4941 GM",
    "sg:province":"Noord-Brabant",
    "wof:name":"Heijblom, J A",
    "wof:placetype":"venue"
},
  "geometry": {"coordinates":[4.875972,51.691948],"type":"Point"}
}