{
  "type": "Feature",
  "properties": {
    "addr:full":"S De Beauvoirln 121 Huizen Noord-Holland 1277 BN",
    "addr:housenumber":"121",
    "addr:postcode":"1277 bn",
    "addr:street":"S",
    "iso:country":"NL",
    "sg:address":"S De Beauvoirln 121",
    "sg:city":"Huizen",
    "sg:orig_category":"Onderhoudswerken",
    "sg:phone":"+31 35 524 0362",
    "sg:postcode":"1277 BN",
    "sg:province":"Noord-Holland",
    "wof:name":"Ijdo",
    "wof:placetype":"venue"
},
  "geometry": {"coordinates":[5.279375,52.296528],"type":"Point"}
}