{
  "type": "Feature",
  "properties": {
    "addr:full":"Dommersweg 6 Nieuw Amsterdam Drenthe 7833 KP",
    "addr:housenumber":"6",
    "addr:postcode":"7833 kp",
    "addr:street":"Dommersweg;Nieuw",
    "iso:country":"NL",
    "sg:address":"Dommersweg 6",
    "sg:city":"Nieuw Amsterdam",
    "sg:orig_category":"Afvalinzameling And -Verwerking",
    "sg:phone":"+31 591 551 454",
    "sg:postcode":"7833 KP",
    "sg:province":"Drenthe",
    "wof:name":"A-Tec",
    "wof:placetype":"venue"
},
  "geometry": {"coordinates":[-74.141273,42.937397],"type":"Point"}
}