{
  "type": "Feature",
  "properties": {
    "addr:full":"Eilandpln 126 Duiven Gelderland 6922 EM",
    "addr:housenumber":"126",
    "addr:postcode":"6922 em",
    "addr:street":"Gelderland",
    "iso:country":"NL",
    "sg:address":"Eilandpln 126",
    "sg:city":"Duiven",
    "sg:orig_category":"Verenigingen En Stichtingen",
    "sg:phone":"+31 316 280 458",
    "sg:postcode":"6922 EM",
    "sg:province":"Gelderland",
    "wof:name":"Parade",
    "wof:placetype":"venue"
},
  "geometry": {"coordinates":[6.00797,51.941448],"type":"Point"}
}