{
  "type": "Feature",
  "properties": {
    "addr:full":"Breusterstraat 62 Eijsden Limburg 6245 EK",
    "addr:housenumber":"62",
    "addr:postcode":"6245 ek",
    "addr:street":"Breusterstraat",
    "iso:country":"NL",
    "sg:address":"Breusterstraat 62",
    "sg:city":"Eijsden",
    "sg:orig_category":"Paramedische Behandelingen",
    "sg:phone":"+31 43 409 4734",
    "sg:postcode":"6245 EK",
    "sg:province":"Limburg",
    "wof:name":"Elis Thuiszorgbureau",
    "wof:placetype":"venue"
},
  "geometry": {"coordinates":[5.710801,50.77702],"type":"Point"}
}