{
  "type": "Feature",
  "properties": {
    "iso:country":"NL",
    "sg:address":"Saal 10",
    "sg:city":"Mierlo",
    "sg:orig_category":"Wegen And Sportterreinen",
    "sg:phone":"+31 492 664 859",
    "sg:postcode":"5731 BA",
    "sg:province":"Noord-Brabant",
    "wof:name":"Vd Laak Bestratingen",
    "wof:placetype":"venue"
},
  "geometry": {"coordinates":[5.6146697998,51.4411506653],"type":"Point"}
}