{
  "type": "Feature",
  "properties": {
    "iso:country":"NL",
    "sg:address":"Johan Frisoplein 3",
    "sg:city":"Nunspeet",
    "sg:orig_category":"Apothekers",
    "sg:phone":"+31 341 250 218",
    "sg:postcode":"8071 LX",
    "sg:province":"Gelderland",
    "wof:name":"De Eecken",
    "wof:placetype":"venue"
},
  "geometry": {"coordinates":[5.779619,52.381283],"type":"Point"}
}