{
  "type": "Feature",
  "properties": {
    "iso:country":"NL",
    "sg:address":"Spoorstraat 56",
    "sg:city":"Ruurlo",
    "sg:orig_category":"Wegen And Sportterreinen",
    "sg:phone":"+31 573 451 907",
    "sg:postcode":"7261 AG",
    "sg:province":"Gelderland",
    "wof:name":"Koninklijke Wegenbouw Stevin Gelderland Flevoland",
    "wof:placetype":"venue"
},
  "geometry": {"coordinates":[6.4555101395,52.0795516968],"type":"Point"}
}