{
  "type": "Feature",
  "properties": {
    "iso:country":"NL",
    "sg:address":"Kerkweg 49",
    "sg:city":"Driebruggen",
    "sg:classifiers":[
        {
            "category":"Education",
            "subcategory":"Preschool",
            "type":"Public Place"
        }
    ],
    "sg:phone":"+31 348 501 254",
    "sg:postcode":"3465 JH",
    "sg:province":"South Holland",
    "sg:tags":[
        "kleuteronderwijs",
        "basis-"
    ],
    "wof:name":"De Wegwijzer",
    "wof:placetype":"venue"
},
  "geometry": {"coordinates":[4.80148,52.028252],"type":"Point"}
}