{
  "type": "Feature",
  "properties": {
    "addr:full":"Lindendreef 30 Vlaardingen Zuid-Holland 3137 CM",
    "addr:housenumber":"30",
    "addr:postcode":"3137 cm",
    "addr:street":"Lindendreef",
    "iso:country":"NL",
    "sg:address":"Lindendreef 30",
    "sg:city":"Vlaardingen",
    "sg:orig_category":"Makelaars In Onroerend Goed",
    "sg:phone":"+31 10 474 2408",
    "sg:postcode":"3137 CM",
    "sg:province":"Zuid-Holland",
    "wof:name":"Ammers Vastgoed Vlaardingen",
    "wof:placetype":"venue"
},
  "geometry": {"coordinates":[4.343895,51.938175],"type":"Point"}
}