{
  "type": "Feature",
  "properties": {
    "addr:full":"Venbergsewg 34 Valkenswaard North Brabant 5551 TJ",
    "addr:housenumber":"34",
    "addr:postcode":"5551 tj",
    "addr:street":"Venbergsewg",
    "iso:country":"NL",
    "sg:address":"Venbergsewg 34",
    "sg:city":"Valkenswaard",
    "sg:orig_category":"Grondwerken",
    "sg:phone":"+31 40 204 9285",
    "sg:postcode":"5551 TJ",
    "sg:province":"North Brabant",
    "wof:name":"Wienholts Vof",
    "wof:placetype":"venue"
},
  "geometry": {"coordinates":[5.439213,51.337494],"type":"Point"}
}