{
  "type": "Feature",
  "properties": {
    "addr:full":"Strypenln 24 Teteringen Noord-Brabant 4847 AW",
    "addr:housenumber":"24",
    "addr:postcode":"4847 aw",
    "addr:street":"Strypenln",
    "iso:country":"NL",
    "sg:address":"Strypenln 24",
    "sg:city":"Teteringen",
    "sg:orig_category":"Yoga-Instituten",
    "sg:phone":"+31 76 581 2570",
    "sg:postcode":"4847 AW",
    "sg:province":"Noord-Brabant",
    "wof:name":"Corrie Goossens",
    "wof:placetype":"venue"
},
  "geometry": {"coordinates":[4.82202,51.61412],"type":"Point"}
}