{
  "type": "Feature",
  "properties": {
    "addr:full":"Mol 3 Zierikzee Zeeland 4301 JC",
    "addr:housenumber":"3",
    "addr:postcode":"4301 jc",
    "addr:street":"Mol",
    "iso:country":"NL",
    "sg:address":"Mol 3",
    "sg:city":"Zierikzee",
    "sg:orig_category":"Herenkleding",
    "sg:phone":"+31 111 412 117",
    "sg:postcode":"4301 JC",
    "sg:province":"Zeeland",
    "wof:name":"Dries",
    "wof:placetype":"venue"
},
  "geometry": {"coordinates":[3.92001,51.650551],"type":"Point"}
}