{
  "type": "Feature",
  "properties": {
    "addr:full":"Brederodelaan 5 Bg Papendrecht South Holland 3353 GG",
    "addr:housenumber":"5",
    "addr:postcode":"3353 gg",
    "addr:street":"Brederodelaan",
    "iso:country":"NL",
    "sg:address":"Brederodelaan 5 Bg",
    "sg:city":"Papendrecht",
    "sg:orig_category":"Bloemen And Planten",
    "sg:phone":"+31 78 641 2095",
    "sg:postcode":"3353 GG",
    "sg:province":"South Holland",
    "wof:name":"Florissant Bloemenwinkel",
    "wof:placetype":"venue"
},
  "geometry": {"coordinates":[4.683685,51.826294],"type":"Point"}
}