{
  "type": "Feature",
  "properties": {
    "addr:full":"Steiltjesstr 6 Zierikzee Zeeland 4301 HS",
    "addr:housenumber":"6",
    "addr:postcode":"4301 hs",
    "addr:street":"Steiltjesstr",
    "iso:country":"NL",
    "sg:address":"Steiltjesstr 6",
    "sg:city":"Zierikzee",
    "sg:orig_category":"Vertaalbureaus",
    "sg:phone":"+31 111 420 344",
    "sg:postcode":"4301 HS",
    "sg:province":"Zeeland",
    "wof:name":"Moerland-Romanova, V",
    "wof:placetype":"venue"
},
  "geometry": {"coordinates":[3.919326,51.652847],"type":"Point"}
}