{
  "type": "Feature",
  "properties": {
    "addr:full":"Marskramer 4 Landsmeer Noord-Holland 1121 JW",
    "addr:housenumber":"4",
    "addr:postcode":"1121 jw",
    "addr:street":"Marskramer",
    "iso:country":"NL",
    "sg:address":"Marskramer 4",
    "sg:city":"Landsmeer",
    "sg:orig_category":"Exploitatie- Maatschappijen",
    "sg:phone":"+31 20 482 3338",
    "sg:postcode":"1121 JW",
    "sg:province":"Noord-Holland",
    "wof:name":"Ancha Bv",
    "wof:placetype":"venue"
},
  "geometry": {"coordinates":[4.90571,52.429241],"type":"Point"}
}