{
  "type": "Feature",
  "properties": {
    "addr:full":"Salonikistraat 1 Zoetermeer Zuid-Holland 2711 GV",
    "addr:housenumber":"1",
    "addr:postcode":"2711 gv",
    "addr:street":"Salonikistraat",
    "iso:country":"NL",
    "sg:address":"Salonikistraat 1",
    "sg:city":"Zoetermeer",
    "sg:orig_category":"Werving And Selectie Van Tijdelijk Personeel And Uitzendkantoren",
    "sg:phone":"+31 79 342 8246",
    "sg:postcode":"2711 GV",
    "sg:province":"Zuid-Holland",
    "wof:name":"Farwakhan",
    "wof:placetype":"venue"
},
  "geometry": {"coordinates":[4.4974069595,52.0636787415],"type":"Point"}
}