{
  "type": "Feature",
  "properties": {
    "addr:full":"Orleansstr 36 Maastricht Limburg 6217 LE",
    "addr:housenumber":"36",
    "addr:postcode":"6217 le",
    "addr:street":"Orleansstr",
    "iso:country":"NL",
    "sg:address":"Orleansstr 36",
    "sg:city":"Maastricht",
    "sg:orig_category":"Kappers",
    "sg:phone":"+31 43 347 0260",
    "sg:postcode":"6217 LE",
    "sg:province":"Limburg",
    "wof:name":"Jef'S Haircare",
    "wof:placetype":"venue"
},
  "geometry": {"coordinates":[5.6730871201,50.851020813],"type":"Point"}
}