{
  "type": "Feature",
  "properties": {
    "addr:full":"Roggestraat 31 Arnhem Gelderland 6811 BB",
    "addr:housenumber":"31",
    "addr:postcode":"6811 bb",
    "addr:street":"Roggestraat",
    "iso:country":"NL",
    "sg:address":"Roggestraat 31",
    "sg:city":"Arnhem",
    "sg:classifiers":[
        {
            "category":"Fast Food",
            "type":"Food & Drink"
        }
    ],
    "sg:phone":"+31 26 351 1724",
    "sg:postcode":"6811 BB",
    "sg:province":"Gelderland",
    "sg:tags":[
        "afhaal",
        "restaurant"
    ],
    "wof:name":"Hap Hoek Ratelband Bv",
    "wof:placetype":"venue"
},
  "geometry": {"coordinates":[5.910908,51.982437],"type":"Point"}
}