{
  "type": "Feature",
  "properties": {
    "iso:country":"NL",
    "sg:address":"Kleterstraat 5",
    "sg:city":"Nijkerk Gld",
    "sg:orig_category":"Artsen And Specialisten",
    "sg:phone":"+31 33 245 2827",
    "sg:postcode":"3862 CA",
    "sg:province":"Gelderland",
    "wof:name":"Huisartsenpraktijk",
    "wof:placetype":"venue"
},
  "geometry": {"coordinates":[5.486836,52.222588],"type":"Point"}
}