{
  "type": "Feature",
  "properties": {
    "iso:country":"NL",
    "sg:address":"Pleinwg 211A",
    "sg:city":"Rotterdam",
    "sg:orig_category":"Administratie- En Boekhoudkantoren",
    "sg:phone":"+31 10 215 0645",
    "sg:postcode":"3081 JN",
    "sg:province":"Zuid-Holland",
    "wof:name":"Bluts, Chr De",
    "wof:placetype":"venue"
},
  "geometry": {"coordinates":[4.477675,51.892147],"type":"Point"}
}