{
  "type": "Feature",
  "properties": {
    "addr:full":"Goudsewg 24 Stolwyk Sofiya 2821 BG",
    "addr:housenumber":"24",
    "addr:postcode":"2821",
    "addr:street":"Goudsewg",
    "iso:country":"NL",
    "sg:address":"Goudsewg 24",
    "sg:city":"Stolwyk",
    "sg:orig_category":"Woninginrichting",
    "sg:phone":"+31 182 341 219",
    "sg:postcode":"2821 BG",
    "sg:province":"Sofiya",
    "wof:name":"Berkouwer",
    "wof:placetype":"venue"
},
  "geometry": {"coordinates":[23.3348007202,41.4954490662],"type":"Point"}
}