{
  "type": "Feature",
  "properties": {
    "addr:full":"Herengr 518 Amsterdam North Holland 1017 CC",
    "addr:housenumber":"518",
    "addr:postcode":"1017 cc",
    "iso:country":"NL",
    "sg:address":"Herengr 518",
    "sg:city":"Amsterdam",
    "sg:orig_category":"Ingenieursbureaus",
    "sg:phone":"+31 20 330 6260",
    "sg:postcode":"1017 CC",
    "sg:province":"North Holland",
    "sg:website":"http://www.fdn-engineering.nl",
    "wof:name":"Fdn Engineering",
    "wof:placetype":"venue"
},
  "geometry": {"coordinates":[4.894415,52.364655],"type":"Point"}
}