{
  "type": "Feature",
  "properties": {
    "iso:country":"NL",
    "sg:address":"Oude Neerkantseweg 9",
    "sg:city":"Liessel",
    "sg:orig_category":"Granen, Zaden And Diervoeders Gh",
    "sg:phone":"+31 493 342 822",
    "sg:postcode":"5757 SC",
    "sg:province":"Noord-Brabant",
    "wof:name":"Van Den Eerenbeemt",
    "wof:placetype":"venue"
},
  "geometry": {"coordinates":[5.846451,51.393028],"type":"Point"}
}