{
  "type": "Feature",
  "properties": {
    "addr:full":"Gasthuislaan 42 Delft Zuid-Holland 2611 RB",
    "addr:housenumber":"42",
    "addr:postcode":"2611 rb",
    "addr:street":"Gasthuislaan",
    "iso:country":"NL",
    "sg:address":"Gasthuislaan 42",
    "sg:city":"Delft",
    "sg:orig_category":"Kappers",
    "sg:phone":"+31 15 214 7007",
    "sg:postcode":"2611 RB",
    "sg:province":"Zuid-Holland",
    "wof:name":"Peter Van Boheemen Haarmode",
    "wof:placetype":"venue"
},
  "geometry": {"coordinates":[4.362901,52.009506],"type":"Point"}
}