{
  "type": "Feature",
  "properties": {
    "addr:full":"Witte Paal 241A Schagen Noord-Holland 1742 LB",
    "addr:housenumber":"241a",
    "addr:postcode":"1742 lb",
    "addr:street":"Witte Paal",
    "iso:country":"NL",
    "sg:address":"Witte Paal 241A",
    "sg:city":"Schagen",
    "sg:orig_category":"Bedden En Matrassen",
    "sg:phone":"+31 224 292 737",
    "sg:postcode":"1742 LB",
    "sg:province":"Noord-Holland",
    "sg:website":"http://www.beterbed.nl",
    "wof:name":"Beter Bed",
    "wof:placetype":"venue"
},
  "geometry": {"coordinates":[4.812949,52.780472],"type":"Point"}
}