{
  "type": "Feature",
  "properties": {
    "addr:full":"Benedeneind Noordzijde 316 Benschop Utrecht 3405 CB",
    "addr:housenumber":"316",
    "addr:postcode":"3405 cb",
    "addr:street":"Benedeneind Noordzijde",
    "iso:country":"NL",
    "sg:address":"Benedeneind Noordzijde 316",
    "sg:city":"Benschop",
    "sg:orig_category":"Verhuur Bouwmachines",
    "sg:phone":"+31 348 451 238",
    "sg:postcode":"3405 CB",
    "sg:province":"Utrecht",
    "wof:name":"Verhuurbedrijf Firma Doornenbal",
    "wof:placetype":"venue"
},
  "geometry": {"coordinates":[4.960085,52.005527],"type":"Point"}
}