{
  "type": "Feature",
  "properties": {
    "addr:full":"Repel 79 Hellevoetsluis South Holland 3224 VE",
    "addr:housenumber":"79",
    "addr:postcode":"3224",
    "addr:street":"Repel;Ve",
    "iso:country":"NL",
    "sg:address":"Repel 79",
    "sg:city":"Hellevoetsluis",
    "sg:orig_category":"Meubelzaken, Woning- And Keukeninrichting",
    "sg:phone":"+31 181 316 654",
    "sg:postcode":"3224 VE",
    "sg:province":"South Holland",
    "wof:name":"Ferber'S Meubel- En Kunstnijverheid Atelier",
    "wof:placetype":"venue"
},
  "geometry": {"coordinates":[4.143193,51.824394],"type":"Point"}
}