{
  "type": "Feature",
  "properties": {
    "addr:full":"Zuidpoldersngl 44 Delfgauw Zuid-Holland 2645 KD",
    "addr:housenumber":"44",
    "addr:postcode":"2645 kd",
    "addr:street":"Zuidpoldersngl",
    "iso:country":"NL",
    "sg:address":"Zuidpoldersngl 44",
    "sg:city":"Delfgauw",
    "sg:orig_category":"Kappers",
    "sg:phone":"+31 15 262 1510",
    "sg:postcode":"2645 KD",
    "sg:province":"Zuid-Holland",
    "wof:name":"Marjo",
    "wof:placetype":"venue"
},
  "geometry": {"coordinates":[4.392532,52.002045],"type":"Point"}
}