{
  "type": "Feature",
  "properties": {
    "addr:full":"Basralocushout 10 Zoetermeer Zuid-Holland 2719 MH",
    "addr:housenumber":"10",
    "addr:postcode":"2719 mh",
    "addr:street":"Basralocushout",
    "iso:country":"NL",
    "sg:address":"Basralocushout 10",
    "sg:city":"Zoetermeer",
    "sg:orig_category":"Fotografie Reclame En Mode",
    "sg:phone":"+31 79 361 3680",
    "sg:postcode":"2719 MH",
    "sg:province":"Zuid-Holland",
    "sg:website":"http://www.joelphoto.nl",
    "wof:name":"Wattimena, Jo\u00ebl",
    "wof:placetype":"venue"
},
  "geometry": {"coordinates":[4.461833,52.046432],"type":"Point"}
}