{
  "type": "Feature",
  "properties": {
    "addr:full":"J Catsstr 49 Hengelo Ov Overijssel 7551 BD",
    "addr:housenumber":"49",
    "addr:postcode":"7551 bd",
    "addr:street":"Ov",
    "iso:country":"NL",
    "sg:address":"J Catsstr 49",
    "sg:city":"Hengelo Ov",
    "sg:orig_category":"Verenigingen En Stichtingen",
    "sg:phone":"+31 74 250 0490",
    "sg:postcode":"7551 BD",
    "sg:province":"Overijssel",
    "wof:name":"Zebno",
    "wof:placetype":"venue"
},
  "geometry": {"coordinates":[6.789712,52.266361],"type":"Point"}
}