{
  "type": "Feature",
  "properties": {
    "addr:full":"Nautilusweg 22 Utrecht Utrecht 3542 AV",
    "addr:housenumber":"22",
    "addr:postcode":"3542 av",
    "addr:street":"Nautilusweg",
    "iso:country":"NL",
    "sg:address":"Nautilusweg 22",
    "sg:city":"Utrecht",
    "sg:orig_category":"Autokeuringen",
    "sg:phone":"+31 30 241 0717",
    "sg:postcode":"3542 AV",
    "sg:province":"Utrecht",
    "wof:name":"Hadema Trading Bv",
    "wof:placetype":"venue"
},
  "geometry": {"coordinates":[5.045138,52.116428],"type":"Point"}
}