{
  "type": "Feature",
  "properties": {
    "addr:full":"Nieuwe Markt 50 Weert Limburg 6001 EL",
    "addr:housenumber":"50",
    "addr:postcode":"6001 el",
    "addr:street":"Nieuwe Markt",
    "iso:country":"NL",
    "sg:address":"Nieuwe Markt 50",
    "sg:city":"Weert",
    "sg:orig_category":"Banken And Kredietinstellingen",
    "sg:phone":"+31 495 577 555",
    "sg:postcode":"6001 EL",
    "sg:province":"Limburg",
    "wof:name":"Ing Bank",
    "wof:placetype":"venue"
},
  "geometry": {"coordinates":[5.704456,51.252838],"type":"Point"}
}