{
  "type": "Feature",
  "properties": {
    "addr:full":"Passage 1 Gulpen Limburg 6271 HA",
    "addr:housenumber":"1",
    "addr:postcode":"6271 ha",
    "addr:street":"Passage",
    "iso:country":"NL",
    "sg:address":"Passage 1",
    "sg:city":"Gulpen",
    "sg:orig_category":"Supermarkten",
    "sg:phone":"+31 43 450 4158",
    "sg:postcode":"6271 HA",
    "sg:province":"Limburg",
    "wof:name":"Edah",
    "wof:placetype":"venue"
},
  "geometry": {"coordinates":[5.892172,50.815708],"type":"Point"}
}