{
  "type": "Feature",
  "properties": {
    "addr:full":"Cremerstr 45 Valkenburg Lb Limburg 6301 GD",
    "addr:housenumber":"45",
    "addr:postcode":"lb;6301 gd",
    "addr:street":"Cremerstr",
    "iso:country":"NL",
    "sg:address":"Cremerstr 45",
    "sg:city":"Valkenburg Lb",
    "sg:orig_category":"Hypotheken",
    "sg:phone":"+31 43 601 2555",
    "sg:postcode":"6301 GD",
    "sg:province":"Limburg",
    "wof:name":"Gwb Assuranti?n Bv",
    "wof:placetype":"venue"
},
  "geometry": {"coordinates":[5.826859,50.871181],"type":"Point"}
}