{
  "type": "Feature",
  "properties": {
    "addr:full":"Oude Kerkstr 9 Goirle North Brabant 5051 RN",
    "addr:housenumber":"9",
    "addr:postcode":"5051 rn",
    "addr:street":"Oude Kerkstr",
    "iso:country":"NL",
    "sg:address":"Oude Kerkstr 9",
    "sg:city":"Goirle",
    "sg:orig_category":"Banken",
    "sg:phone":"+31 13 534 7077",
    "sg:postcode":"5051 RN",
    "sg:province":"North Brabant",
    "wof:name":"Regio Bank",
    "wof:placetype":"venue"
},
  "geometry": {"coordinates":[5.063295,51.521141],"type":"Point"}
}