{
  "type": "Feature",
  "properties": {
    "iso:country":"NL",
    "sg:address":"A Goekoopln 5",
    "sg:city":"S Gravenhage",
    "sg:orig_category":"Bedrijfsorganisaties",
    "sg:phone":"+31 70 354 2547",
    "sg:postcode":"2517 JX",
    "sg:province":"South Holland",
    "sg:website":"http://www.smeerolievereniging.nl",
    "wof:name":"Vsn",
    "wof:placetype":"venue"
},
  "geometry": {"coordinates":[4.28708,52.08667],"type":"Point"}
}