{
  "type": "Feature",
  "properties": {
    "iso:country":"NL",
    "sg:address":"Frederik Hendriklaan 22",
    "sg:city":"Woerden",
    "sg:classifiers":[
        {
            "category":"Fast Food",
            "type":"Food & Drink"
        }
    ],
    "sg:phone":"+31 348 418 187",
    "sg:postcode":"3445 XN",
    "sg:province":"Utrecht",
    "sg:tags":[
        "afhaal",
        "restaurant"
    ],
    "wof:name":"De Lekkerbek",
    "wof:placetype":"venue"
},
  "geometry": {"coordinates":[4.901422,52.089886],"type":"Point"}
}