{
  "type": "Feature",
  "properties": {
    "addr:full":"Bellamystr 19 Amsterdam Noord-Holland 1053 BE",
    "addr:housenumber":"19",
    "addr:postcode":"1053",
    "addr:street":"Bellamystr",
    "iso:country":"NL",
    "sg:address":"Bellamystr 19",
    "sg:city":"Amsterdam",
    "sg:orig_category":"Beeldende Kunstenaars",
    "sg:phone":"+31 20 612 7462",
    "sg:postcode":"1053 BE",
    "sg:province":"Noord-Holland",
    "wof:name":"Willebrands, F W",
    "wof:placetype":"venue"
},
  "geometry": {"coordinates":[4.866267,52.367012],"type":"Point"}
}