{
  "type": "Feature",
  "properties": {
    "addr:full":"Kokelestr 89 Kerkrade Limburg 6462 EP",
    "addr:housenumber":"89",
    "addr:postcode":"6462 ep",
    "addr:street":"Kokelestr",
    "iso:country":"NL",
    "sg:address":"Kokelestr 89",
    "sg:city":"Kerkrade",
    "sg:orig_category":"Behangers",
    "sg:phone":"+31 45 546 3313",
    "sg:postcode":"6462 EP",
    "sg:province":"Limburg",
    "wof:name":"Piekaz Bv",
    "wof:placetype":"venue"
},
  "geometry": {"coordinates":[6.071734,50.852562],"type":"Point"}
}