{
  "type": "Feature",
  "properties": {
    "addr:full":"Dreef 1 Breda Noord-Brabant 4813 ED",
    "addr:housenumber":"1",
    "addr:postcode":"4813 ed",
    "addr:street":"Dreef",
    "iso:country":"NL",
    "sg:address":"Dreef 1",
    "sg:city":"Breda",
    "sg:classifiers":[
        {
            "category":"Shopping",
            "subcategory":"Gifts & Souvenirs",
            "type":"Retail Goods"
        }
    ],
    "sg:phone":"+31 76 514 0206",
    "sg:postcode":"4813 ED",
    "sg:province":"Noord-Brabant",
    "sg:tags":[
        "geschenken"
    ],
    "wof:name":"Tabaksspeciaalzaak A. Janssen",
    "wof:placetype":"venue"
},
  "geometry": {"coordinates":[4.739865,51.577084],"type":"Point"}
}