{
  "type": "Feature",
  "properties": {
    "iso:country":"NL",
    "sg:address":"Kerkradersteenwg 17",
    "sg:city":"Kerkrade",
    "sg:orig_category":"Wasmachines En Wasdrogers - Onderhoud En Reparatie",
    "sg:phone":"+31 45 545 3395",
    "sg:postcode":"6466 PA",
    "sg:province":"Limburg",
    "wof:name":"Rinkens, F A M B",
    "wof:placetype":"venue"
},
  "geometry": {"coordinates":[6.0529608727,50.8681716919],"type":"Point"}
}