{
  "type": "Feature",
  "properties": {
    "iso:country":"NL",
    "sg:address":"Kerkpln 22-23",
    "sg:city":"Abcoude",
    "sg:orig_category":"Kappers",
    "sg:phone":"+31 294 283 839",
    "sg:postcode":"1391 GK",
    "sg:province":"North Holland",
    "wof:name":"Cees De Waal Kapsalon",
    "wof:placetype":"venue"
},
  "geometry": {"coordinates":[4.973772049,52.2720947266],"type":"Point"}
}