{
  "type": "Feature",
  "properties": {
    "iso:country":"NL",
    "sg:address":"Haitinkweg 7",
    "sg:city":"Zelhem",
    "sg:orig_category":"Autokeuringen",
    "sg:phone":"+31 314 621 440",
    "sg:postcode":"7021 KB",
    "sg:province":"Gelderland",
    "wof:name":"Fa. Teerink",
    "wof:placetype":"venue"
},
  "geometry": {"coordinates":[6.336537,51.994076],"type":"Point"}
}