{
  "type": "Feature",
  "properties": {
    "addr:full":"Valkenburgerweg 8 Voerendaal Limburg 6367 GV",
    "addr:housenumber":"8",
    "addr:postcode":"6367 gv",
    "addr:street":"Valkenburgerweg",
    "iso:country":"NL",
    "sg:address":"Valkenburgerweg 8",
    "sg:city":"Voerendaal",
    "sg:classifiers":[
        {
            "category":"Communications",
            "subcategory":"Television Station",
            "type":"Services"
        }
    ],
    "sg:phone":"+31 45 575 4333",
    "sg:postcode":"6367 GV",
    "sg:province":"Limburg",
    "sg:tags":[
        "video",
        "audio",
        "verhuur"
    ],
    "wof:name":"Videotheek Premiere",
    "wof:placetype":"venue"
},
  "geometry": {"coordinates":[5.919593,50.876423],"type":"Point"}
}