{
  "type": "Feature",
  "properties": {
    "addr:full":"Raadhuisstr 37B Amsterdam Noord-Holland 1016 DC",
    "addr:housenumber":"37b",
    "addr:postcode":"1016",
    "addr:street":"Raadhuisstr",
    "iso:country":"NL",
    "sg:address":"Raadhuisstr 37B",
    "sg:city":"Amsterdam",
    "sg:classifiers":[
        {
            "category":"Travel",
            "subcategory":"Hotels & Motels",
            "type":"Entertainment"
        }
    ],
    "sg:phone":"+31 20 624 9735",
    "sg:postcode":"1016 DC",
    "sg:province":"Noord-Holland",
    "wof:name":"Pax",
    "wof:placetype":"venue"
},
  "geometry": {"coordinates":[4.885973,52.373505],"type":"Point"}
}