{
  "type": "Feature",
  "properties": {
    "addr:full":"Oudeland 126 Zwijndrecht Zuid-Holland 3335 VJ",
    "addr:housenumber":"126",
    "addr:postcode":"3335 vj",
    "addr:street":"Oudeland",
    "iso:country":"NL",
    "sg:address":"Oudeland 126",
    "sg:city":"Zwijndrecht",
    "sg:orig_category":"Opticiens",
    "sg:phone":"+31 78 610 4741",
    "sg:postcode":"3335 VJ",
    "sg:province":"Zuid-Holland",
    "wof:name":"Brilmode Rob Boon",
    "wof:placetype":"venue"
},
  "geometry": {"coordinates":[4.6564698219,51.8222465515],"type":"Point"}
}