{
  "type": "Feature",
  "properties": {
    "addr:full":"St Peterln 49 Arnhem Gelderland 6821 HD",
    "addr:housenumber":"49",
    "addr:postcode":"6821 hd",
    "iso:country":"NL",
    "sg:address":"St Peterln 49",
    "sg:city":"Arnhem",
    "sg:orig_category":"Vertaalbureaus",
    "sg:phone":"+31 26 442 6515",
    "sg:postcode":"6821 HD",
    "sg:province":"Gelderland",
    "wof:name":"Distinguin",
    "wof:placetype":"venue"
},
  "geometry": {"coordinates":[5.90939,51.989902],"type":"Point"}
}