{
  "type": "Feature",
  "properties": {
    "addr:full":"Zuidwenk 66 Bunschoten Spakenb Utrecht 3751 CE",
    "addr:housenumber":"66",
    "addr:postcode":"3751 ce",
    "addr:street":"Zuidwenk",
    "iso:country":"NL",
    "sg:address":"Zuidwenk 66",
    "sg:city":"Bunschoten Spakenb",
    "sg:orig_category":"Bestratingen",
    "sg:phone":"+31 33 298 2460",
    "sg:postcode":"3751 CE",
    "sg:province":"Utrecht",
    "wof:name":"Hoogen Bestratingsbedrijf, W V/D",
    "wof:placetype":"venue"
},
  "geometry": {"coordinates":[5.382082,52.249092],"type":"Point"}
}