{
  "type": "Feature",
  "properties": {
    "addr:full":"Vullingswg 72 Heerlen Limburg 6418 HV",
    "addr:housenumber":"72",
    "addr:postcode":"6418 hv",
    "addr:street":"Vullingswg",
    "iso:country":"NL",
    "sg:address":"Vullingswg 72",
    "sg:city":"Heerlen",
    "sg:orig_category":"Cafetaria'S",
    "sg:phone":"+31 45 541 4175",
    "sg:postcode":"6418 HV",
    "sg:province":"Limburg",
    "wof:name":"Trefpunt, 'T",
    "wof:placetype":"venue"
},
  "geometry": {"coordinates":[6.006428,50.867893],"type":"Point"}
}