{
  "type": "Feature",
  "properties": {
    "iso:country":"NL",
    "sg:address":"Straatweg 53",
    "sg:city":"Breukelen Ut",
    "sg:orig_category":"Banken And Kredietinstellingen",
    "sg:phone":"+31 346 269 411",
    "sg:postcode":"3621 BH",
    "sg:province":"Utrecht",
    "wof:name":"Rabobank",
    "wof:placetype":"venue"
},
  "geometry": {"coordinates":[5.002286,52.170818],"type":"Point"}
}