{
  "type": "Feature",
  "properties": {
    "addr:full":"Ten Ankerweg 86 Tholen Zeeland 4691 GZ",
    "addr:housenumber":"86",
    "addr:postcode":"4691 gz",
    "addr:street":"Ten Ankerweg",
    "iso:country":"NL",
    "sg:address":"Ten Ankerweg 86",
    "sg:city":"Tholen",
    "sg:orig_category":"Visspeciaalzaken",
    "sg:phone":"+31 166 603 462",
    "sg:postcode":"4691 GZ",
    "sg:province":"Zeeland",
    "wof:name":"Vishandel Schot-Van Dijke",
    "wof:placetype":"venue"
},
  "geometry": {"coordinates":[4.221435,51.535782],"type":"Point"}
}