{
  "type": "Feature",
  "properties": {
    "addr:full":"Grotestraat 47 Heusden Gem Heusden Noord-Brabant 5256 PA",
    "addr:housenumber":"47",
    "addr:postcode":"5256 pa",
    "addr:street":"Grotestraat",
    "iso:country":"NL",
    "sg:address":"Grotestraat 47",
    "sg:city":"Heusden Gem Heusden",
    "sg:orig_category":"Autokeuringen",
    "sg:phone":"+31 416 662 516",
    "sg:postcode":"5256 PA",
    "sg:province":"Noord-Brabant",
    "wof:name":"Vof M.P. Vrijhoeven En Co.",
    "wof:placetype":"venue"
},
  "geometry": {"coordinates":[5.12867,51.734112],"type":"Point"}
}