{
  "type": "Feature",
  "properties": {
    "addr:full":"Wildbaan 112 Etten-Leur North Brabant 4874 KG",
    "addr:housenumber":"112",
    "addr:postcode":"4874 kg",
    "addr:street":"Wildbaan",
    "iso:country":"NL",
    "sg:address":"Wildbaan 112",
    "sg:city":"Etten-Leur",
    "sg:orig_category":"Kansspelen",
    "sg:phone":"+31 76 501 4525",
    "sg:postcode":"4874 KG",
    "sg:province":"North Brabant",
    "wof:name":"Bonky Kiddy-Rides",
    "wof:placetype":"venue"
},
  "geometry": {"coordinates":[4.6226911545,51.57371521],"type":"Point"}
}