{
  "type": "Feature",
  "properties": {
    "addr:full":"Kykakkers 14 Maarheeze Noord-Brabant 6026 ER",
    "addr:housenumber":"14",
    "addr:postcode":"6026 er",
    "addr:street":"Kykakkers",
    "iso:country":"NL",
    "sg:address":"Kykakkers 14",
    "sg:city":"Maarheeze",
    "sg:orig_category":"Webdesign Bureaus",
    "sg:phone":"+31 495 594 718",
    "sg:postcode":"6026 ER",
    "sg:province":"Noord-Brabant",
    "sg:website":"http://www.solidminds.nl",
    "wof:name":"Solidminds",
    "wof:placetype":"venue"
},
  "geometry": {"coordinates":[5.6153650284,51.3121261597],"type":"Point"}
}