{
  "type": "Feature",
  "properties": {
    "addr:full":"Kerkewg 27 Wirdum Gn Groningen 9917 PG",
    "addr:housenumber":"27",
    "addr:postcode":"gn;9917 pg",
    "addr:street":"Kerkewg",
    "iso:country":"NL",
    "sg:address":"Kerkewg 27",
    "sg:city":"Wirdum Gn",
    "sg:orig_category":"Onderhoudswerken",
    "sg:phone":"+31 596 573 177",
    "sg:postcode":"9917 PG",
    "sg:province":"Groningen",
    "wof:name":"Kroon, M B",
    "wof:placetype":"venue"
},
  "geometry": {"coordinates":[6.786128,53.322765],"type":"Point"}
}