{
  "type": "Feature",
  "properties": {
    "addr:full":"Hoepmakerstr 17 Gorinchem South Holland 4204 GM",
    "addr:housenumber":"17",
    "addr:postcode":"4204 gm",
    "addr:street":"Hoepmakerstr",
    "iso:country":"NL",
    "sg:address":"Hoepmakerstr 17",
    "sg:city":"Gorinchem",
    "sg:orig_category":"Product-Promotie",
    "sg:phone":"+31 183 630 399",
    "sg:postcode":"4204 GM",
    "sg:province":"South Holland",
    "wof:name":"Dierenopvang, Sticht",
    "wof:placetype":"venue"
},
  "geometry": {"coordinates":[4.954003,51.837448],"type":"Point"}
}