{
  "type": "Feature",
  "properties": {
    "addr:full":"Buurkerkhof 5 Utrecht Utrecht 3511 KC",
    "addr:housenumber":"5",
    "addr:postcode":"3511 kc",
    "addr:street":"Buurkerkhof",
    "iso:country":"NL",
    "sg:address":"Buurkerkhof 5",
    "sg:city":"Utrecht",
    "sg:orig_category":"Adviesbureaus",
    "sg:phone":"+31 30 231 4614",
    "sg:postcode":"3511 KC",
    "sg:province":"Utrecht",
    "wof:name":"Matsushita Van Der Wal",
    "wof:placetype":"venue"
},
  "geometry": {"coordinates":[5.118765,52.090343],"type":"Point"}
}