{
  "type": "Feature",
  "properties": {
    "addr:full":"Laan Copes V Cattenburch 46 'S Gravenhage Zuid-Holland 2585 GB",
    "addr:housenumber":"46",
    "addr:postcode":"2585 gb",
    "addr:street":"Laan Copes V Cattenburch;' S",
    "iso:country":"NL",
    "sg:address":"Laan Copes V Cattenburch 46",
    "sg:city":"'S Gravenhage",
    "sg:orig_category":"Diverse Grafische Activiteiten",
    "sg:phone":"+31 70 350 4000",
    "sg:postcode":"2585 GB",
    "sg:province":"Zuid-Holland",
    "wof:name":"Brienen & Baas",
    "wof:placetype":"venue"
},
  "geometry": {"coordinates":[4.305592,52.091225],"type":"Point"}
}