{
  "type": "Feature",
  "properties": {
    "addr:full":"Willemsstr 150 Amsterdam North Holland 1015 JE",
    "addr:housenumber":"150",
    "addr:postcode":"1015 je",
    "iso:country":"NL",
    "sg:address":"Willemsstr 150",
    "sg:city":"Amsterdam",
    "sg:orig_category":"Autorijscholen",
    "sg:phone":"+31 20 625 6469",
    "sg:postcode":"1015 JE",
    "sg:province":"North Holland",
    "wof:name":"Bertelkamp, J W",
    "wof:placetype":"venue"
},
  "geometry": {"coordinates":[4.884019,52.381268],"type":"Point"}
}