{
  "type": "Feature",
  "properties": {
    "addr:full":"Pottenbakkerstr 45 Ridderkerk Zuid-Holland 2984 AX",
    "addr:housenumber":"45",
    "addr:postcode":"2984 ax",
    "addr:street":"Pottenbakkerstr",
    "iso:country":"NL",
    "sg:address":"Pottenbakkerstr 45",
    "sg:city":"Ridderkerk",
    "sg:orig_category":"Horecabenodigdheden",
    "sg:phone":"+31 180 480 526",
    "sg:postcode":"2984 AX",
    "sg:province":"Zuid-Holland",
    "wof:name":"Ceso",
    "wof:placetype":"venue"
},
  "geometry": {"coordinates":[4.612444,51.878677],"type":"Point"}
}