{
  "type": "Feature",
  "properties": {
    "addr:full":"Zuiderweg 123 Zuidoostbeemster Noord-Holland 1461 GH",
    "addr:housenumber":"123",
    "addr:postcode":"1461 gh",
    "addr:street":"Zuiderweg",
    "iso:country":"NL",
    "sg:address":"Zuiderweg 123",
    "sg:city":"Zuidoostbeemster",
    "sg:orig_category":"Fotostudio'S And Fotografen",
    "sg:phone":"+31 299 438 650",
    "sg:postcode":"1461 GH",
    "sg:province":"Noord-Holland",
    "wof:name":"Fotostudio Fred Van Batum Vof",
    "wof:placetype":"venue"
},
  "geometry": {"coordinates":[4.939025,52.514118],"type":"Point"}
}