{
  "type": "Feature",
  "properties": {
    "addr:full":"Beethovenln 358 Zwolle Overijssel 8031 BX",
    "addr:housenumber":"358",
    "addr:postcode":"8031 bx",
    "iso:country":"NL",
    "sg:address":"Beethovenln 358",
    "sg:city":"Zwolle",
    "sg:orig_category":"Woningstoffeerders",
    "sg:phone":"+31 6 22744439",
    "sg:postcode":"8031 BX",
    "sg:province":"Overijssel",
    "wof:name":"Una",
    "wof:placetype":"venue"
},
  "geometry": {"coordinates":[6.0815358162,52.5247039795],"type":"Point"}
}