{
  "type": "Feature",
  "properties": {
    "addr:full":"Achtervang 3 Etten-Leur Noord-Brabant 4872 AM",
    "addr:housenumber":"3",
    "addr:postcode":"4872",
    "addr:street":"Achtervang",
    "iso:country":"NL",
    "sg:address":"Achtervang 3",
    "sg:city":"Etten-Leur",
    "sg:orig_category":"Kappers",
    "sg:phone":"+31 76 501 1160",
    "sg:postcode":"4872 AM",
    "sg:province":"Noord-Brabant",
    "wof:name":"Kapsalon Haarstudio Toosanna",
    "wof:placetype":"venue"
},
  "geometry": {"coordinates":[4.6380038261,51.5694541931],"type":"Point"}
}