{
  "type": "Feature",
  "properties": {
    "addr:full":"Gorredijksterw 7 Jubbega Friesland 8411 KA",
    "addr:housenumber":"7",
    "addr:postcode":"8411 ka",
    "addr:street":"Gorredijksterw",
    "iso:country":"NL",
    "sg:address":"Gorredijksterw 7",
    "sg:city":"Jubbega",
    "sg:orig_category":"Kappers",
    "sg:phone":"+31 516 461 688",
    "sg:postcode":"8411 KA",
    "sg:province":"Friesland",
    "wof:name":"Vos, O De",
    "wof:placetype":"venue"
},
  "geometry": {"coordinates":[6.098511,52.983292],"type":"Point"}
}