{
  "type": "Feature",
  "properties": {
    "iso:country":"NL",
    "sg:address":"Hammerstraat 8",
    "sg:city":"Epe",
    "sg:orig_category":"Autokeuringen",
    "sg:phone":"+31 578 615 547",
    "sg:postcode":"8161 PH",
    "sg:province":"Gelderland",
    "wof:name":"Van Vemde Epe Autoschades Bv",
    "wof:placetype":"venue"
},
  "geometry": {"coordinates":[5.994884,52.343609],"type":"Point"}
}