{
  "type": "Feature",
  "properties": {
    "addr:full":"Grietsestraat 66 Zevenaar Gelderland 6901 GW",
    "addr:housenumber":"66",
    "addr:postcode":"6901 gw",
    "addr:street":"Grietsestraat",
    "iso:country":"NL",
    "sg:address":"Grietsestraat 66",
    "sg:city":"Zevenaar",
    "sg:orig_category":"Banken And Kredietinstellingen",
    "sg:phone":"+31 316 582 111",
    "sg:postcode":"6901 GW",
    "sg:province":"Gelderland",
    "wof:name":"Ing Bank",
    "wof:placetype":"venue"
},
  "geometry": {"coordinates":[6.077683,51.930653],"type":"Point"}
}