{
  "type": "Feature",
  "properties": {
    "addr:full":"Hendrik Van Deventerstr 52 'S Gravenhage Zuid-Holland 2563 XV",
    "addr:housenumber":"52",
    "addr:postcode":"2563 xv",
    "addr:street":"Hendrik Van Deventerstr;' S",
    "iso:country":"NL",
    "sg:address":"Hendrik Van Deventerstr 52",
    "sg:city":"'S Gravenhage",
    "sg:orig_category":"Vertaal- And Tolkenbureaus",
    "sg:phone":"+31 70 364 3384",
    "sg:postcode":"2563 XV",
    "sg:province":"Zuid-Holland",
    "wof:name":"Frista Vertaalwerk En Services",
    "wof:placetype":"venue"
},
  "geometry": {"coordinates":[4.272666,52.072514],"type":"Point"}
}