{
  "type": "Feature",
  "properties": {
    "addr:full":"Dorpsstr 49 Uithoorn Utrecht 1421 AS",
    "addr:housenumber":"49",
    "addr:postcode":"1421 as",
    "addr:street":"Dorpsstr",
    "iso:country":"NL",
    "sg:address":"Dorpsstr 49",
    "sg:city":"Uithoorn",
    "sg:orig_category":"Woningtextiel",
    "sg:phone":"+31 297 561 229",
    "sg:postcode":"1421 AS",
    "sg:province":"Utrecht",
    "wof:name":"Smit Wooncomfort",
    "wof:placetype":"venue"
},
  "geometry": {"coordinates":[4.8320422173,52.2329711914],"type":"Point"}
}