{
  "type": "Feature",
  "properties": {
    "addr:full":"Leeuwendalersweg 67 Amsterdam North Holland 1061 BD",
    "addr:housenumber":"67",
    "addr:postcode":"1061 bd",
    "addr:street":"Leeuwendalersweg",
    "iso:country":"NL",
    "sg:address":"Leeuwendalersweg 67",
    "sg:city":"Amsterdam",
    "sg:orig_category":"Werving And Selectie Van Tijdelijk Personeel And Uitzendkantoren",
    "sg:phone":"+31 20 475 1018",
    "sg:postcode":"1061 BD",
    "sg:province":"North Holland",
    "wof:name":"Ecu Works",
    "wof:placetype":"venue"
},
  "geometry": {"coordinates":[4.8393921852,52.3790283203],"type":"Point"}
}