{
  "type": "Feature",
  "properties": {
    "addr:full":"Overgauwseweg 56 Pijnacker Zuid-Holland 2641 NG",
    "addr:housenumber":"56",
    "addr:postcode":"2641 ng",
    "addr:street":"Overgauwseweg",
    "iso:country":"NL",
    "sg:address":"Overgauwseweg 56",
    "sg:city":"Pijnacker",
    "sg:orig_category":"Bloemen- And Plantenteelt",
    "sg:phone":"+31 15 369 2989",
    "sg:postcode":"2641 NG",
    "sg:province":"Zuid-Holland",
    "wof:name":"Rozenkwekerij Joop Koot",
    "wof:placetype":"venue"
},
  "geometry": {"coordinates":[4.427033,52.007946],"type":"Point"}
}