{
  "type": "Feature",
  "properties": {
    "iso:country":"NL",
    "sg:address":"Middenwaard 94",
    "sg:city":"Heerhugowaard",
    "sg:orig_category":"Bloemen En Planten",
    "sg:phone":"+31 72 571 2872",
    "sg:postcode":"1703 SH",
    "sg:province":"North Holland",
    "wof:name":"Bas Bentzon",
    "wof:placetype":"venue"
},
  "geometry": {"coordinates":[4.826637,52.663643],"type":"Point"}
}