{
  "type": "Feature",
  "properties": {
    "addr:full":"Laurastr 51 Eygelshoven Limburg 6471 JH",
    "addr:housenumber":"51",
    "addr:postcode":"6471 jh",
    "addr:street":"Laurastr",
    "iso:country":"NL",
    "sg:address":"Laurastr 51",
    "sg:city":"Eygelshoven",
    "sg:orig_category":"Postkantoren",
    "sg:phone":"+31 45 535 4024",
    "sg:postcode":"6471 JH",
    "sg:province":"Limburg",
    "sg:website":"http://www.postkantoor.nl",
    "wof:name":"Postkantoor",
    "wof:placetype":"venue"
},
  "geometry": {"coordinates":[6.05685,50.893162],"type":"Point"}
}