{
  "type": "Feature",
  "properties": {
    "addr:full":"Hoogenwg 29 Hoogenweg NL.08 7793 HN",
    "addr:housenumber":"29;nl.08",
    "addr:postcode":"7793 hn",
    "addr:street":"Hoogenwg",
    "iso:country":"NL",
    "sg:address":"Hoogenwg 29",
    "sg:city":"Hoogenweg",
    "sg:orig_category":"Keukens",
    "sg:phone":"+31 523 262 347",
    "sg:postcode":"7793 HN",
    "sg:province":"NL.08",
    "sg:website":"http://www.bekmankeukens.nl",
    "wof:name":"Bekman",
    "wof:placetype":"venue"
},
  "geometry": {"coordinates":[6.664757,52.566269],"type":"Point"}
}