{
  "type": "Feature",
  "properties": {
    "addr:full":"Rijnzichtlaan 30 Bunnik Utrecht 3981 BV",
    "addr:housenumber":"30",
    "addr:postcode":"3981 bv",
    "addr:street":"Rijnzichtlaan",
    "iso:country":"NL",
    "sg:address":"Rijnzichtlaan 30",
    "sg:city":"Bunnik",
    "sg:orig_category":"Autokeuringen",
    "sg:phone":"+31 30 656 3695",
    "sg:postcode":"3981 BV",
    "sg:province":"Utrecht",
    "wof:name":"Vermeulen'S Automobiel Bedrijf",
    "wof:placetype":"venue"
},
  "geometry": {"coordinates":[5.208344,52.065502],"type":"Point"}
}