{
  "type": "Feature",
  "properties": {
    "addr:full":"Hoogstraat 91 Enschede NL.08 7512 GW",
    "addr:housenumber":"91",
    "addr:postcode":"7512 gw",
    "addr:street":"Hoogstraat",
    "iso:country":"NL",
    "sg:address":"Hoogstraat 91",
    "sg:city":"Enschede",
    "sg:orig_category":"Geluidsopnamen",
    "sg:phone":"+31 53 432 2002",
    "sg:postcode":"7512 GW",
    "sg:province":"NL.08",
    "wof:name":"Mels Music",
    "wof:placetype":"venue"
},
  "geometry": {"coordinates":[6.906432,52.213554],"type":"Point"}
}