{
  "type": "Feature",
  "properties": {
    "addr:full":"Zevenkampse Ring 922 Rotterdam Zuid-Holland 3069 MD",
    "addr:housenumber":"922",
    "addr:postcode":"3069",
    "addr:street":"Zevenkampse Ring",
    "iso:country":"NL",
    "sg:address":"Zevenkampse Ring 922",
    "sg:city":"Rotterdam",
    "sg:orig_category":"Dtp",
    "sg:phone":"+31 6 14434112",
    "sg:postcode":"3069 MD",
    "sg:province":"Zuid-Holland",
    "wof:name":"Samiro Design",
    "wof:placetype":"venue"
},
  "geometry": {"coordinates":[4.561807,51.967167],"type":"Point"}
}