{
  "type": "Feature",
  "properties": {
    "addr:full":"Purmerdk 5 Ilpendam Noord-Holland 1452 AE",
    "addr:housenumber":"5",
    "addr:postcode":"1452 ae",
    "addr:street":"Purmerdk",
    "iso:country":"NL",
    "sg:address":"Purmerdk 5",
    "sg:city":"Ilpendam",
    "sg:orig_category":"Artsen - Specialisten Oogheelkunde",
    "sg:phone":"+31 20 456 0867",
    "sg:postcode":"1452 AE",
    "sg:province":"Noord-Holland",
    "wof:name":"Visser En Zandbergen Oogartsen",
    "wof:placetype":"venue"
},
  "geometry": {"coordinates":[4.958069,52.468601],"type":"Point"}
}