{
  "type": "Feature",
  "properties": {
    "iso:country":"NL",
    "sg:address":"Ms V Riemsdykwg 7",
    "sg:city":"Amsterdam",
    "sg:orig_category":"Jachthavens - Jachtwerven",
    "sg:phone":"+31 20 631 2104",
    "sg:postcode":"1033 RC",
    "sg:province":"North Holland",
    "wof:name":"Rhebergen",
    "wof:placetype":"venue"
},
  "geometry": {"coordinates":[4.88555,52.407909],"type":"Point"}
}