{
  "type": "Feature",
  "properties": {
    "addr:full":"Handelsstr 37 Hardenberg Overijssel 7772 TS",
    "addr:housenumber":"37",
    "addr:postcode":"7772 ts",
    "addr:street":"Handelsstr",
    "iso:country":"NL",
    "sg:address":"Handelsstr 37",
    "sg:city":"Hardenberg",
    "sg:orig_category":"Bevestigingsmaterialen",
    "sg:phone":"+31 523 265 641",
    "sg:postcode":"7772 TS",
    "sg:province":"Overijssel",
    "wof:name":"Praag Bv, Van",
    "wof:placetype":"venue"
},
  "geometry": {"coordinates":[6.638258,52.559784],"type":"Point"}
}