{
  "type": "Feature",
  "properties": {
    "addr:full":"S Stevinwg 123 Hilversum Noord-Holland 1222 SR",
    "addr:housenumber":"123",
    "addr:postcode":"hilversum;1222 sr",
    "iso:country":"NL",
    "sg:address":"S Stevinwg 123",
    "sg:city":"Hilversum",
    "sg:orig_category":"Koeriersdiensten",
    "sg:phone":"+31 6 54302540",
    "sg:postcode":"1222 SR",
    "sg:province":"Noord-Holland",
    "wof:name":"Fietskoerier, De",
    "wof:placetype":"venue"
},
  "geometry": {"coordinates":[5.182793,52.236359],"type":"Point"}
}