{
  "type": "Feature",
  "properties": {
    "addr:full":"Venraysewg 26 Venlo Limburg 5928 NZ",
    "addr:housenumber":"26",
    "addr:postcode":"5928 nz",
    "addr:street":"Venraysewg",
    "iso:country":"NL",
    "sg:address":"Venraysewg 26",
    "sg:city":"Venlo",
    "sg:orig_category":"Automaterialen En Gereedschappen",
    "sg:phone":"+31 77 320 9090",
    "sg:postcode":"5928 NZ",
    "sg:province":"Limburg",
    "sg:website":"http://www.vankappel.nl",
    "wof:name":"Kappel Bv, Van",
    "wof:placetype":"venue"
},
  "geometry": {"coordinates":[6.121392,51.409958],"type":"Point"}
}