{
  "type": "Feature",
  "properties": {
    "addr:full":"Voorschoterweg 74 Valkenburg Zh South Holland 2235 SH",
    "addr:housenumber":"74",
    "addr:postcode":"zh;2235 sh",
    "addr:street":"Voorschoterweg",
    "iso:country":"NL",
    "sg:address":"Voorschoterweg 74",
    "sg:city":"Valkenburg Zh",
    "sg:orig_category":"Bloemen And Planten Gh",
    "sg:phone":"+31 71 576 3868",
    "sg:postcode":"2235 SH",
    "sg:province":"South Holland",
    "wof:name":"Bloemenexport Hendriksen Bv",
    "wof:placetype":"venue"
},
  "geometry": {"coordinates":[4.446338,52.162113],"type":"Point"}
}