{
  "type": "Feature",
  "properties": {
    "iso:country":"NL",
    "sg:address":"Stoomberg 12",
    "sg:city":"Dongen",
    "sg:orig_category":"Handelsbemiddeling Textiel And Lederwaren",
    "sg:phone":"+31 162 321 900",
    "sg:postcode":"5101 AA",
    "sg:province":"Noord-Brabant",
    "wof:name":"Jos Van Dongen Schoenagenturen",
    "wof:placetype":"venue"
},
  "geometry": {"coordinates":[4.934535,51.625774],"type":"Point"}
}