{
  "type": "Feature",
  "properties": {
    "addr:full":"Oude Kruisweg 164 Cruquius Noord-Holland 2142 EJ",
    "addr:housenumber":"164",
    "addr:postcode":"2142 ej",
    "addr:street":"Oude Kruisweg",
    "iso:country":"NL",
    "sg:address":"Oude Kruisweg 164",
    "sg:city":"Cruquius",
    "sg:orig_category":"Wegen And Sportterreinen",
    "sg:phone":"+31 23 528 5615",
    "sg:postcode":"2142 EJ",
    "sg:province":"Noord-Holland",
    "wof:name":"M Vervloed",
    "wof:placetype":"venue"
},
  "geometry": {"coordinates":[4.6394128799,52.3338394165],"type":"Point"}
}