{
  "type": "Feature",
  "properties": {
    "iso:country":"NL",
    "sg:address":"Oude Kruisweg 164",
    "sg:city":"Cruquius",
    "sg:orig_category":"Wegen And Sportterreinen",
    "sg:phone":"+31 23 528 5615",
    "sg:postcode":"2142 EJ",
    "sg:province":"Noord-Holland",
    "wof:name":"M Vervloed",
    "wof:placetype":"venue"
},
  "geometry": {"coordinates":[4.6394128799,52.3338394165],"type":"Point"}
}