{
  "type": "Feature",
  "properties": {
    "addr:full":"Korenbloemstraat 44 Tilburg North Brabant 5025 PS",
    "addr:housenumber":"44",
    "addr:postcode":"5025 ps",
    "addr:street":"Korenbloemstraat",
    "iso:country":"NL",
    "sg:address":"Korenbloemstraat 44",
    "sg:city":"Tilburg",
    "sg:orig_category":"Paramedische Behandelingen",
    "sg:phone":"+31 13 463 9950",
    "sg:postcode":"5025 PS",
    "sg:province":"North Brabant",
    "wof:name":"J.M.W. Janssen",
    "wof:placetype":"venue"
},
  "geometry": {"coordinates":[5.065597,51.551456],"type":"Point"}
}