{
  "type": "Feature",
  "properties": {
    "iso:country":"NL",
    "sg:address":"Daalseweg 368",
    "sg:city":"Nijmegen",
    "sg:orig_category":"Fietshandelaren",
    "sg:phone":"+31 24 322 9678",
    "sg:postcode":"6523 CG",
    "sg:province":"Gelderland",
    "wof:name":"Fa.Van Der Putten",
    "wof:placetype":"venue"
},
  "geometry": {"coordinates":[5.879487,51.834835],"type":"Point"}
}