{
  "type": "Feature",
  "properties": {
    "addr:full":"Oude Haven 63 Medemblik Noord-Holland 1671 AV",
    "addr:housenumber":"63",
    "addr:postcode":"1671 av",
    "addr:street":"Oude Haven",
    "iso:country":"NL",
    "sg:address":"Oude Haven 63",
    "sg:city":"Medemblik",
    "sg:orig_category":"Artsen And Specialisten",
    "sg:phone":"+31 227 541 234",
    "sg:postcode":"1671 AV",
    "sg:province":"Noord-Holland",
    "wof:name":"J.H. Kropf Bv",
    "wof:placetype":"venue"
},
  "geometry": {"coordinates":[5.111198,52.774002],"type":"Point"}
}