{
  "type": "Feature",
  "properties": {
    "iso:country":"NL",
    "sg:address":"Oranjestr 77",
    "sg:city":"Arnhem",
    "sg:orig_category":"Wijnkoperijen En -Groothandel",
    "sg:phone":"+31 26 443 3903",
    "sg:postcode":"6812 CM",
    "sg:province":"Gelderland",
    "wof:name":"Peters, Rob",
    "wof:placetype":"venue"
},
  "geometry": {"coordinates":[5.8818130493,51.9850158691],"type":"Point"}
}