{
  "type": "Feature",
  "properties": {
    "addr:full":"Burg Baumannln 148A Rotterdam South Holland 3042 AG",
    "addr:housenumber":"148a",
    "addr:postcode":"3042",
    "addr:street":"Burg",
    "iso:country":"NL",
    "sg:address":"Burg Baumannln 148A",
    "sg:city":"Rotterdam",
    "sg:orig_category":"Herenkleding",
    "sg:phone":"+31 10 437 8537",
    "sg:postcode":"3042 AG",
    "sg:province":"South Holland",
    "wof:name":"Hardi",
    "wof:placetype":"venue"
},
  "geometry": {"coordinates":[4.427653,51.935936],"type":"Point"}
}