{
  "type": "Feature",
  "properties": {
    "iso:country":"NL",
    "sg:address":"Raadhuispln 42",
    "sg:city":"Heerhugowaard",
    "sg:orig_category":"Bloemen En Planten",
    "sg:phone":"+31 72 572 4414",
    "sg:postcode":"1701 EJ",
    "sg:province":"North Holland",
    "sg:website":"http://www.groenbloemdecoraties.nl",
    "wof:name":"Groen Bloem Decoraties",
    "wof:placetype":"venue"
},
  "geometry": {"coordinates":[4.843161,52.670971],"type":"Point"}
}