{
  "type": "Feature",
  "properties": {
    "iso:country":"NL",
    "sg:address":"Van Vollenhovelaan 687",
    "sg:city":"Utrecht",
    "sg:orig_category":"Drukkerijen And Copyshops",
    "sg:phone":"+31 30 291 0016",
    "sg:postcode":"3527 JP",
    "sg:province":"Utrecht",
    "wof:name":"Multicopy",
    "wof:placetype":"venue"
},
  "geometry": {"coordinates":[5.097693,52.074875],"type":"Point"}
}