{
  "type": "Feature",
  "properties": {
    "addr:full":"Hippolytusbuurt 17 Delft Zuid-Holland 2611 HM",
    "addr:housenumber":"17",
    "addr:postcode":"2611 hm",
    "addr:street":"Hippolytusbuurt",
    "iso:country":"NL",
    "sg:address":"Hippolytusbuurt 17",
    "sg:city":"Delft",
    "sg:orig_category":"Zoetwaren - Winkels",
    "sg:phone":"+31 15 214 4138",
    "sg:postcode":"2611 HM",
    "sg:province":"Zuid-Holland",
    "wof:name":"Sweets 17",
    "wof:placetype":"venue"
},
  "geometry": {"coordinates":[4.35691,52.011871],"type":"Point"}
}