{
  "type": "Feature",
  "properties": {
    "iso:country":"NL",
    "sg:address":"3E Oosterparkstr 12Hs",
    "sg:city":"Amsterdam",
    "sg:orig_category":"Meubelmakerijen",
    "sg:phone":"+31 6 24219676",
    "sg:postcode":"1091 JX",
    "sg:province":"Noord-Holland",
    "wof:name":"Terecht",
    "wof:placetype":"venue"
},
  "geometry": {"coordinates":[4.913657,52.355389],"type":"Point"}
}