{
  "type": "Feature",
  "properties": {
    "addr:full":"Iepensteinlaan 10 Joure Provincie Friesland 8501 KM",
    "addr:housenumber":"10",
    "addr:postcode":"8501",
    "addr:street":"Iepensteinlaan;Provincie Friesland;Km",
    "iso:country":"NL",
    "sg:address":"Iepensteinlaan 10",
    "sg:city":"Joure",
    "sg:classifiers":[
        {
            "category":"Professional",
            "subcategory":"Accounting & Tax Preparation",
            "type":"Services"
        }
    ],
    "sg:phone":"+31 513 413 215",
    "sg:postcode":"8501 KM",
    "sg:province":"Provincie Friesland",
    "sg:tags":[
        "accountant"
    ],
    "wof:name":"Accountantskantoor Bruinsma Bv",
    "wof:placetype":"venue"
},
  "geometry": {"coordinates":[5.802972,52.961414],"type":"Point"}
}