{
  "type": "Feature",
  "properties": {
    "addr:full":"Verzetsheldenlaan 2 Eindhoven Noord-Brabant 5626 GH",
    "addr:housenumber":"2",
    "addr:postcode":"5626 gh",
    "addr:street":"Verzetsheldenlaan",
    "iso:country":"NL",
    "sg:address":"Verzetsheldenlaan 2",
    "sg:city":"Eindhoven",
    "sg:orig_category":"Wegen And Sportterreinen",
    "sg:phone":"+31 40 262 4141",
    "sg:postcode":"5626 GH",
    "sg:province":"Noord-Brabant",
    "wof:name":"Wegenbouwbedrijf Van Breugel-Smulders Bv",
    "wof:placetype":"venue"
},
  "geometry": {"coordinates":[5.4386291504,51.4736633301],"type":"Point"}
}