{
  "type": "Feature",
  "properties": {
    "iso:country":"NL",
    "sg:address":"Spoorstr 1",
    "sg:city":"Roelofarendsveen",
    "sg:orig_category":"Acupunctuur",
    "sg:phone":"+31 71 331 3450",
    "sg:postcode":"2371 XB",
    "sg:province":"Zuid-Holland",
    "wof:name":"Peet, N Van",
    "wof:placetype":"venue"
},
  "geometry": {"coordinates":[4.631135,52.203381],"type":"Point"}
}