{
  "type": "Feature",
  "properties": {
    "iso:country":"NL",
    "sg:address":"Mauvestr 45",
    "sg:city":"Amsterdam",
    "sg:orig_category":"Ziekenvervoer",
    "sg:phone":"+31 20 662 0708",
    "sg:postcode":"1073 RH",
    "sg:province":"Noord-Holland",
    "wof:name":"Verkerk",
    "wof:placetype":"venue"
},
  "geometry": {"coordinates":[4.903045,52.349964],"type":"Point"}
}