{
  "type": "Feature",
  "properties": {
    "addr:full":"De Loet 5 Heiloo North Holland 1851 CR",
    "addr:housenumber":"5;1851",
    "addr:postcode":"cr",
    "addr:street":"De Loet",
    "iso:country":"NL",
    "sg:address":"De Loet 5",
    "sg:city":"Heiloo",
    "sg:orig_category":"Verzekeringen - Verzekeringskantoren",
    "sg:phone":"+31 72 533 9917",
    "sg:postcode":"1851 CR",
    "sg:province":"North Holland",
    "wof:name":"Courton",
    "wof:placetype":"venue"
},
  "geometry": {"coordinates":[4.717163,52.603016],"type":"Point"}
}