{
  "type": "Feature",
  "properties": {
    "addr:full":"Maassenstr 7 Roggel Limburg 6088 CX",
    "addr:housenumber":"7",
    "addr:postcode":"6088 cx",
    "addr:street":"Maassenstr",
    "iso:country":"NL",
    "sg:address":"Maassenstr 7",
    "sg:city":"Roggel",
    "sg:orig_category":"Warenhuizen",
    "sg:phone":"+31 475 491 374",
    "sg:postcode":"6088 CX",
    "sg:province":"Limburg",
    "wof:name":"Lier, J G Van",
    "wof:placetype":"venue"
},
  "geometry": {"coordinates":[5.9218668938,51.2625312805],"type":"Point"}
}