{
  "type": "Feature",
  "properties": {
    "addr:full":"Kudelstaartsewg 239 Kudelstaart Noord-Holland 1433 GH",
    "addr:housenumber":"239",
    "addr:postcode":"1433 gh",
    "iso:country":"NL",
    "sg:address":"Kudelstaartsewg 239",
    "sg:city":"Kudelstaart",
    "sg:orig_category":"Verenigingsgebouwen",
    "sg:phone":"+31 297 326 289",
    "sg:postcode":"1433 GH",
    "sg:province":"Noord-Holland",
    "wof:name":"Dorpshuis Kudelstaart",
    "wof:placetype":"venue"
},
  "geometry": {"coordinates":[4.750707,52.23851],"type":"Point"}
}