{
  "type": "Feature",
  "properties": {
    "addr:full":"Da Costakd 114 Amsterdam North Holland 1053 XB",
    "addr:housenumber":"114",
    "addr:postcode":"1053 xb",
    "iso:country":"NL",
    "sg:address":"Da Costakd 114",
    "sg:city":"Amsterdam",
    "sg:orig_category":"Zetterijen",
    "sg:phone":"+31 20 616 6034",
    "sg:postcode":"1053 XB",
    "sg:province":"North Holland",
    "wof:name":"Cedilles",
    "wof:placetype":"venue"
},
  "geometry": {"coordinates":[4.86733,52.366638],"type":"Point"}
}