{
  "type": "Feature",
  "properties": {
    "iso:country":"NL",
    "sg:address":"Ansfridusstraat 21",
    "sg:city":"Rotterdam",
    "sg:orig_category":"Goederenvervoer Over De Weg",
    "sg:phone":"+31 10 419 5168",
    "sg:postcode":"3078 WD",
    "sg:province":"Zuid-Holland",
    "wof:name":"Goederenvervoer J.J. Vonk Vof",
    "wof:placetype":"venue"
},
  "geometry": {"coordinates":[4.535275,51.890366],"type":"Point"}
}