{
  "type": "Feature",
  "properties": {
    "addr:full":"Cranendoncklaan 20 Budel North Brabant 6021 JT",
    "addr:housenumber":"20",
    "addr:postcode":"6021 jt",
    "addr:street":"Cranendoncklaan",
    "iso:country":"NL",
    "sg:address":"Cranendoncklaan 20",
    "sg:city":"Budel",
    "sg:orig_category":"Beautyfarms And Sauna'S",
    "sg:phone":"+31 495 492 903",
    "sg:postcode":"6021 JT",
    "sg:province":"North Brabant",
    "wof:name":"F. Twardy",
    "wof:placetype":"venue"
},
  "geometry": {"coordinates":[5.571057,51.269428],"type":"Point"}
}