{
  "type": "Feature",
  "properties": {
    "addr:full":"Die 23 Bergen Nh Noord-Holland 1862 HW",
    "addr:housenumber":"23",
    "addr:postcode":"1862 hw",
    "addr:street":"Die",
    "iso:country":"NL",
    "sg:address":"Die 23",
    "sg:city":"Bergen Nh",
    "sg:orig_category":"Webdesign Bureaus",
    "sg:phone":"+31 72 589 9206",
    "sg:postcode":"1862 HW",
    "sg:province":"Noord-Holland",
    "wof:name":"Intervisie Bergen",
    "wof:placetype":"venue"
},
  "geometry": {"coordinates":[4.7212247849,52.6676139832],"type":"Point"}
}