{
  "type": "Feature",
  "properties": {
    "addr:full":"Koningin Wilhelminalaan 1 Amersfoort Utrecht 3818 HN",
    "addr:housenumber":"1",
    "addr:postcode":"3818 hn",
    "addr:street":"Koningin Wilhelminalaan",
    "iso:country":"NL",
    "sg:address":"Koningin Wilhelminalaan 1",
    "sg:city":"Amersfoort",
    "sg:orig_category":"Makelaars In Onroerend Goed",
    "sg:phone":"+31 33 465 9434",
    "sg:postcode":"3818 HN",
    "sg:province":"Utrecht",
    "wof:name":"Dynamis Vastgoedcons En Makelaars Nederland Bv",
    "wof:placetype":"venue"
},
  "geometry": {"coordinates":[5.369857,52.149345],"type":"Point"}
}