{
  "type": "Feature",
  "properties": {
    "addr:full":"Catamaranstr 11 Tilburg Noord-Brabant 5017 LJ",
    "addr:housenumber":"11",
    "addr:postcode":"5017 lj",
    "addr:street":"Catamaranstr",
    "iso:country":"NL",
    "sg:address":"Catamaranstr 11",
    "sg:city":"Tilburg",
    "sg:orig_category":"Bedrijfsopleidingen",
    "sg:phone":"+31 13 535 7497",
    "sg:postcode":"5017 LJ",
    "sg:province":"Noord-Brabant",
    "sg:website":"http://www.patil.nl",
    "wof:name":"Patil",
    "wof:placetype":"venue"
},
  "geometry": {"coordinates":[5.095375,51.554783],"type":"Point"}
}