{
  "type": "Feature",
  "properties": {
    "addr:full":"Noorderuitweg 33 Wijdenes Noord-Holland 1608 EA",
    "addr:housenumber":"33",
    "addr:postcode":"1608 ea",
    "addr:street":"Noorderuitweg",
    "iso:country":"NL",
    "sg:address":"Noorderuitweg 33",
    "sg:city":"Wijdenes",
    "sg:orig_category":"Hoefdierhouderijen",
    "sg:phone":"+31 229 501 703",
    "sg:postcode":"1608 EA",
    "sg:province":"Noord-Holland",
    "wof:name":"Stoeterij Tobias",
    "wof:placetype":"venue"
},
  "geometry": {"coordinates":[5.162088,52.647186],"type":"Point"}
}