{
  "type": "Feature",
  "properties": {
    "addr:full":"Reguliersdwarsstraat 51 Amsterdam Noord-Holland 1017 BK",
    "addr:housenumber":"51",
    "addr:postcode":"1017 bk",
    "addr:street":"Reguliersdwarsstraat",
    "iso:country":"NL",
    "sg:address":"Reguliersdwarsstraat 51",
    "sg:city":"Amsterdam",
    "sg:classifiers":[
        {
            "category":"Fast Food",
            "type":"Food & Drink"
        }
    ],
    "sg:phone":"+31 20 622 2723",
    "sg:postcode":"1017 BK",
    "sg:province":"Noord-Holland",
    "sg:tags":[
        "afhaal",
        "restaurant"
    ],
    "wof:name":"Midnight Snack",
    "wof:placetype":"venue"
},
  "geometry": {"coordinates":[4.891275,52.366364],"type":"Point"}
}