{
  "type": "Feature",
  "properties": {
    "iso:country":"NL",
    "sg:address":"Pascalstraat 1",
    "sg:city":"Reeuwijk",
    "sg:orig_category":"Huizensloop And Bouwrijp Maken",
    "sg:phone":"+31 182 525 459",
    "sg:postcode":"2811 EL",
    "sg:province":"Zuid-Holland",
    "wof:name":"Van Rijn Service",
    "wof:placetype":"venue"
},
  "geometry": {"coordinates":[4.717251,52.040668],"type":"Point"}
}