{
  "type": "Feature",
  "properties": {
    "addr:full":"Dapperstr 143 Amsterdam Noord-Holland 1093 BS",
    "addr:housenumber":"143",
    "addr:postcode":"1093 bs",
    "iso:country":"NL",
    "sg:address":"Dapperstr 143",
    "sg:city":"Amsterdam",
    "sg:orig_category":"Herenkleding",
    "sg:phone":"+31 20 692 6414",
    "sg:postcode":"1093 BS",
    "sg:province":"Noord-Holland",
    "wof:name":"Bodyline",
    "wof:placetype":"venue"
},
  "geometry": {"coordinates":[4.926513,52.364723],"type":"Point"}
}