{
  "type": "Feature",
  "properties": {
    "iso:country":"NL",
    "sg:address":"Adelaert 5",
    "sg:city":"Noordwyk Zh",
    "sg:orig_category":"Marketingbureaus",
    "sg:phone":"+31 71 361 6607",
    "sg:postcode":"2202 PM",
    "sg:province":"Zuid-Holland",
    "wof:name":"Adri Ulfman & Hans Heevel Bv",
    "wof:placetype":"venue"
},
  "geometry": {"coordinates":[4.435614,52.248837],"type":"Point"}
}