{
  "type": "Feature",
  "properties": {
    "addr:full":"Lg Brink 22 Apeldoorn Gelderland 7317 BE",
    "addr:housenumber":"22",
    "addr:postcode":"7317",
    "addr:street":"Lg Brink;Gelderland",
    "iso:country":"NL",
    "sg:address":"Lg Brink 22",
    "sg:city":"Apeldoorn",
    "sg:orig_category":"Onderhoudswerken",
    "sg:phone":"+31 55 578 9590",
    "sg:postcode":"7317 BE",
    "sg:province":"Gelderland",
    "wof:name":"Lamikon Bv",
    "wof:placetype":"venue"
},
  "geometry": {"coordinates":[5.97279,52.243389],"type":"Point"}
}