{
  "type": "Feature",
  "properties": {
    "addr:full":"Molenpad 9 Groet Noord-Holland 1873 HZ",
    "addr:housenumber":"9",
    "addr:postcode":"1873 hz",
    "addr:street":"Molenpad",
    "iso:country":"NL",
    "sg:address":"Molenpad 9",
    "sg:city":"Groet",
    "sg:orig_category":"Technische Studies And Onderzoek",
    "sg:phone":"+31 72 509 3241",
    "sg:postcode":"1873 HZ",
    "sg:province":"Noord-Holland",
    "wof:name":"Butter And Energy",
    "wof:placetype":"venue"
},
  "geometry": {"coordinates":[4.66927,52.722725],"type":"Point"}
}