{
  "type": "Feature",
  "properties": {
    "addr:full":"Bruggestraat 7 Harderwijk Gelderland 3841 CM",
    "addr:housenumber":"7",
    "addr:postcode":"3841 cm",
    "addr:street":"Bruggestraat;Gelderland",
    "iso:country":"NL",
    "sg:address":"Bruggestraat 7",
    "sg:city":"Harderwijk",
    "sg:classifiers":[
        {
            "category":"Fast Food",
            "type":"Food & Drink"
        }
    ],
    "sg:phone":"+31 341 431 770",
    "sg:postcode":"3841 CM",
    "sg:province":"Gelderland",
    "sg:tags":[
        "afhaal",
        "restaurant"
    ],
    "wof:name":"Pizzeria Roma",
    "wof:placetype":"venue"
},
  "geometry": {"coordinates":[5.61579,52.350571],"type":"Point"}
}