{
  "type": "Feature",
  "properties": {
    "addr:full":"De Engh 11 Driebergen Rysenb Utrecht 3972 JL",
    "addr:housenumber":"11",
    "addr:postcode":"3972 jl",
    "addr:street":"De Engh;Rysenb",
    "iso:country":"NL",
    "sg:address":"De Engh 11",
    "sg:city":"Driebergen Rysenb",
    "sg:orig_category":"Artsen - Huisartsen",
    "sg:phone":"+31 343 512 429",
    "sg:postcode":"3972 JL",
    "sg:province":"Utrecht",
    "wof:name":"Eeden, Dr L Van",
    "wof:placetype":"venue"
},
  "geometry": {"coordinates":[5.283112,52.050667],"type":"Point"}
}