{
  "type": "Feature",
  "properties": {
    "addr:full":"Marconistr 23 Assen Provincie Drenthe 9406 BW",
    "addr:housenumber":"23",
    "addr:postcode":"9406 bw",
    "addr:street":"Marconistr;Provincie Drenthe",
    "iso:country":"NL",
    "sg:address":"Marconistr 23",
    "sg:city":"Assen",
    "sg:orig_category":"Verenigingen En Stichtingen",
    "sg:phone":"+31 592 356 870",
    "sg:postcode":"9406 BW",
    "sg:province":"Provincie Drenthe",
    "wof:name":"Muziekkamer Assen, Sticht",
    "wof:placetype":"venue"
},
  "geometry": {"coordinates":[6.546915,52.997719],"type":"Point"}
}