{
  "type": "Feature",
  "properties": {
    "iso:country":"NL",
    "sg:address":"Edesewg 117",
    "sg:city":"Harskamp",
    "sg:orig_category":"Plafonds",
    "sg:phone":"+31 318 456 595",
    "sg:postcode":"6732 DA",
    "sg:province":"Gelderland",
    "wof:name":"Brink, W Van Den",
    "wof:placetype":"venue"
},
  "geometry": {"coordinates":[5.725928,52.124123],"type":"Point"}
}