{
  "type": "Feature",
  "properties": {
    "addr:full":"Keulschevaart 5 Breukelen Ut Utrecht 3621 MX",
    "addr:housenumber":"5",
    "addr:postcode":"3621 mx",
    "addr:street":"Keulschevaart",
    "iso:country":"NL",
    "sg:address":"Keulschevaart 5",
    "sg:city":"Breukelen Ut",
    "sg:orig_category":"Bruggenbouw",
    "sg:phone":"+31 346 263 565",
    "sg:postcode":"3621 MX",
    "sg:province":"Utrecht",
    "wof:name":"Stoel Bv, P H Van Der",
    "wof:placetype":"venue"
},
  "geometry": {"coordinates":[4.991919,52.165642],"type":"Point"}
}