{
  "type": "Feature",
  "properties": {
    "iso:country":"NL",
    "sg:address":"Latensteinsewg 11C",
    "sg:city":"Tiel",
    "sg:orig_category":"Kunststoffen- Verwerkende Industrie",
    "sg:phone":"+31 344 631 475",
    "sg:postcode":"4005 EG",
    "sg:province":"Gelderland",
    "sg:website":"http://www.langeveldkunststoffen.nl",
    "wof:name":"Langeveld Kunststoffen Bv",
    "wof:placetype":"venue"
},
  "geometry": {"coordinates":[5.450561,51.896072],"type":"Point"}
}