{
  "type": "Feature",
  "properties": {
    "addr:full":"Beethovenstr 5/B3 Amsterdam North Holland 1077 HK",
    "addr:housenumber":"5 / b3",
    "addr:postcode":"1077 hk",
    "addr:street":"Beethovenstr",
    "iso:country":"NL",
    "sg:address":"Beethovenstr 5/B3",
    "sg:city":"Amsterdam",
    "sg:orig_category":"Vertalers",
    "sg:phone":"+31 20 671 6668",
    "sg:postcode":"1077 HK",
    "sg:province":"North Holland",
    "wof:name":"Coronel, M",
    "wof:placetype":"venue"
},
  "geometry": {"coordinates":[4.87585,52.345482],"type":"Point"}
}