{
  "type": "Feature",
  "properties": {
    "addr:full":"Bakkenesln 25 Soesterberg Utrecht 3769 CC",
    "addr:housenumber":"25",
    "addr:postcode":"3769 cc",
    "addr:street":"Bakkenesln",
    "iso:country":"NL",
    "sg:address":"Bakkenesln 25",
    "sg:city":"Soesterberg",
    "sg:orig_category":"Medische Keuringen",
    "sg:phone":"+31 346 242 599",
    "sg:postcode":"3769 CC",
    "sg:province":"Utrecht",
    "wof:name":"Folmer, H A",
    "wof:placetype":"venue"
},
  "geometry": {"coordinates":[5.285409,52.12085],"type":"Point"}
}