{
  "type": "Feature",
  "properties": {
    "addr:full":"Dorpswg 75 Ysselmuiden Overijssel 8271 BK",
    "addr:housenumber":"75",
    "addr:postcode":"8271 bk",
    "addr:street":"Dorpswg;Overijssel",
    "iso:country":"NL",
    "sg:address":"Dorpswg 75",
    "sg:city":"Ysselmuiden",
    "sg:orig_category":"Boeken En Tijdschriften",
    "sg:phone":"+31 38 333 3888",
    "sg:postcode":"8271 BK",
    "sg:province":"Overijssel",
    "sg:website":"http://www.depelgrim.nl",
    "wof:name":"Pelgrim, De",
    "wof:placetype":"venue"
},
  "geometry": {"coordinates":[5.927467,52.565746],"type":"Point"}
}