{
  "type": "Feature",
  "properties": {
    "addr:full":"Akkerpad 19 S Hertogenbosch Noord-Brabant 5236 VD",
    "addr:housenumber":"19",
    "addr:postcode":"5236 vd",
    "addr:street":"Akkerpad;S",
    "iso:country":"NL",
    "sg:address":"Akkerpad 19",
    "sg:city":"S Hertogenbosch",
    "sg:orig_category":"Vertaalbureaus",
    "sg:phone":"+31 73 640 0126",
    "sg:postcode":"5236 VD",
    "sg:province":"Noord-Brabant",
    "wof:name":"Into Dutch",
    "wof:placetype":"venue"
},
  "geometry": {"coordinates":[5.325658,51.737423],"type":"Point"}
}