{
  "type": "Feature",
  "properties": {
    "addr:full":"Godelindestr 40 Bussum Noord-Holland 1402 WK",
    "addr:housenumber":"40",
    "addr:postcode":"1402 wk",
    "addr:street":"Godelindestr",
    "iso:country":"NL",
    "sg:address":"Godelindestr 40",
    "sg:city":"Bussum",
    "sg:orig_category":"Tekstschrijversters",
    "sg:phone":"+31 35 693 8419",
    "sg:postcode":"1402 WK",
    "sg:province":"Noord-Holland",
    "wof:name":"Majoor, Hanneke",
    "wof:placetype":"venue"
},
  "geometry": {"coordinates":[5.181732,52.274792],"type":"Point"}
}