{
  "type": "Feature",
  "properties": {
    "addr:full":"Koedijkerstraat 1 Alkmaar Noord-Holland 1823 CR",
    "addr:housenumber":"1",
    "addr:postcode":"1823 cr",
    "addr:street":"Koedijkerstraat",
    "iso:country":"NL",
    "sg:address":"Koedijkerstraat 1",
    "sg:city":"Alkmaar",
    "sg:orig_category":"Huishoudapparatuur, Televisies And Radio'S",
    "sg:phone":"+31 72 511 8700",
    "sg:postcode":"1823 CR",
    "sg:province":"Noord-Holland",
    "wof:name":"Karwei Bouwmarkt",
    "wof:placetype":"venue"
},
  "geometry": {"coordinates":[4.75406,52.637798],"type":"Point"}
}