{
  "type": "Feature",
  "properties": {
    "addr:full":"Vossiusstr 50 Amsterdam North Holland 1071 AK",
    "addr:housenumber":"50",
    "addr:postcode":"1071 ak",
    "addr:street":"Vossiusstr",
    "iso:country":"NL",
    "sg:address":"Vossiusstr 50",
    "sg:city":"Amsterdam",
    "sg:orig_category":"Journalisten Freelance",
    "sg:phone":"+31 6 53213324",
    "sg:postcode":"1071 AK",
    "sg:province":"North Holland",
    "wof:name":"Bletz, Jan",
    "wof:placetype":"venue"
},
  "geometry": {"coordinates":[4.878163,52.360195],"type":"Point"}
}