{
  "type": "Feature",
  "properties": {
    "addr:full":"Kerkweg 58 Ridderkerk South Holland 2985 AV",
    "addr:housenumber":"58",
    "addr:postcode":"2985 av",
    "addr:street":"Kerkweg",
    "iso:country":"NL",
    "sg:address":"Kerkweg 58",
    "sg:city":"Ridderkerk",
    "sg:orig_category":"Bloemen And Planten",
    "sg:phone":"+31 180 424 336",
    "sg:postcode":"2985 AV",
    "sg:province":"South Holland",
    "wof:name":"Bloemenhuis J. Van Der Waal En Zoon",
    "wof:placetype":"venue"
},
  "geometry": {"coordinates":[4.599816,51.866665],"type":"Point"}
}