{
  "type": "Feature",
  "properties": {
    "addr:full":"Groenmarkt 62 Dordrecht South Holland 3311 BE",
    "addr:housenumber":"62",
    "addr:postcode":"3311",
    "addr:street":"Groenmarkt",
    "iso:country":"NL",
    "sg:address":"Groenmarkt 62",
    "sg:city":"Dordrecht",
    "sg:orig_category":"Fietshandelaren",
    "sg:phone":"+31 78 614 0202",
    "sg:postcode":"3311 BE",
    "sg:province":"South Holland",
    "wof:name":"H. De Roo",
    "wof:placetype":"venue"
},
  "geometry": {"coordinates":[4.665401,51.814445],"type":"Point"}
}