{
  "type": "Feature",
  "properties": {
    "iso:country":"NL",
    "sg:address":"Groenmarkt 62",
    "sg:city":"Dordrecht",
    "sg:orig_category":"Fietshandelaren",
    "sg:phone":"+31 78 614 0202",
    "sg:postcode":"3311 BE",
    "sg:province":"South Holland",
    "wof:name":"H. De Roo",
    "wof:placetype":"venue"
},
  "geometry": {"coordinates":[4.665401,51.814445],"type":"Point"}
}