{
  "type": "Feature",
  "properties": {
    "iso:country":"NL",
    "sg:address":"Groenstraat 13",
    "sg:city":"Geleen",
    "sg:orig_category":"Werving And Selectie Van Tijdelijk Personeel And Uitzendkantoren",
    "sg:phone":"+31 46 475 6444",
    "sg:postcode":"6162 EM",
    "sg:province":"Limburg",
    "wof:name":"Randstad",
    "wof:placetype":"venue"
},
  "geometry": {"coordinates":[5.8304858208,50.9706192017],"type":"Point"}
}