{
  "type": "Feature",
  "properties": {
    "addr:full":"Leenkamp 15 Leidschendam South Holland 2264 KW",
    "addr:housenumber":"15",
    "addr:postcode":"2264 kw",
    "addr:street":"Leenkamp",
    "iso:country":"NL",
    "sg:address":"Leenkamp 15",
    "sg:city":"Leidschendam",
    "sg:orig_category":"Scholen Voor Basisonderwijs",
    "sg:phone":"+31 70 327 8018",
    "sg:postcode":"2264 KW",
    "sg:province":"South Holland",
    "wof:name":"Emma?s Rk-Pc",
    "wof:placetype":"venue"
},
  "geometry": {"coordinates":[4.40335,52.091698],"type":"Point"}
}