{
  "type": "Feature",
  "properties": {
    "addr:full":"Bremln 26 Bosch En Duin Utrecht 3735 KJ",
    "addr:housenumber":"26",
    "addr:postcode":"en duin;3735 kj",
    "addr:street":"Bremln",
    "iso:country":"NL",
    "sg:address":"Bremln 26",
    "sg:city":"Bosch En Duin",
    "sg:orig_category":"Adviesbureaus Bedrijfsorganisatie",
    "sg:phone":"+31 30 229 2784",
    "sg:postcode":"3735 KJ",
    "sg:province":"Utrecht",
    "wof:name":"Matser & Willemse Vof",
    "wof:placetype":"venue"
},
  "geometry": {"coordinates":[5.235476,52.135056],"type":"Point"}
}