{
  "type": "Feature",
  "properties": {
    "iso:country":"NL",
    "sg:address":"Ceintuurbaan 234",
    "sg:city":"Amsterdam",
    "sg:orig_category":"Kunst And Kunstenaarsbenodigdheden",
    "sg:phone":"+31 20 679 5346",
    "sg:postcode":"1072 GE",
    "sg:province":"Noord-Holland",
    "wof:name":"Kunsthandel En Encadreerinrichting G De",
    "wof:placetype":"venue"
},
  "geometry": {"coordinates":[4.888887,52.352268],"type":"Point"}
}