{
  "type": "Feature",
  "properties": {
    "addr:full":"Oude Telgterwg 140 Ermelo Gelderland 3851 EE",
    "addr:housenumber":"140",
    "addr:postcode":"3851 ee",
    "addr:street":"Oude Telgterwg;Gelderland",
    "iso:country":"NL",
    "sg:address":"Oude Telgterwg 140",
    "sg:city":"Ermelo",
    "sg:orig_category":"Verlichtingsartikelen - Fabrieken",
    "sg:phone":"+31 341 557 603",
    "sg:postcode":"3851 EE",
    "sg:province":"Gelderland",
    "wof:name":"Eclips",
    "wof:placetype":"venue"
},
  "geometry": {"coordinates":[5.612128,52.294163],"type":"Point"}
}