{
  "type": "Feature",
  "properties": {
    "addr:full":"Marijkelaan 1 Harderwijk Gelderland 3843 CD",
    "addr:housenumber":"1",
    "addr:postcode":"3843 cd",
    "addr:street":"Marijkelaan;Gelderland",
    "iso:country":"NL",
    "sg:address":"Marijkelaan 1",
    "sg:city":"Harderwijk",
    "sg:orig_category":"Kappers",
    "sg:phone":"+31 341 422 559",
    "sg:postcode":"3843 CD",
    "sg:province":"Gelderland",
    "wof:name":"C.P. Den Besten",
    "wof:placetype":"venue"
},
  "geometry": {"coordinates":[5.6324410439,52.3354225159],"type":"Point"}
}