{
  "type": "Feature",
  "properties": {
    "addr:full":"In De Bogaard D 1 Rijswijk Zh Zuid-Holland 2284 KD",
    "addr:housenumber":"1",
    "addr:postcode":"zh;2284 kd",
    "addr:street":"In De Bogaard D",
    "iso:country":"NL",
    "sg:address":"In De Bogaard D 1",
    "sg:city":"Rijswijk Zh",
    "sg:orig_category":"Verzekeringen",
    "sg:phone":"+31 70 394 1932",
    "sg:postcode":"2284 KD",
    "sg:province":"Zuid-Holland",
    "wof:name":"Vendopolis",
    "wof:placetype":"venue"
},
  "geometry": {"coordinates":[4.315979,52.037846],"type":"Point"}
}