{
  "type": "Feature",
  "properties": {
    "addr:full":"Dykje 6 Barneveld Gelderland 3771 BN",
    "addr:housenumber":"6",
    "addr:postcode":"3771 bn",
    "addr:street":"Dykje;Gelderland",
    "iso:country":"NL",
    "sg:address":"Dykje 6",
    "sg:city":"Barneveld",
    "sg:orig_category":"Verzekeringen - Verzekeringskantoren",
    "sg:phone":"+31 342 417 560",
    "sg:postcode":"3771 BN",
    "sg:province":"Gelderland",
    "sg:website":"http://www.acg-barneveld.nl",
    "wof:name":"Acg",
    "wof:placetype":"venue"
},
  "geometry": {"coordinates":[5.586231,52.140373],"type":"Point"}
}