{
  "type": "Feature",
  "properties": {
    "addr:full":"Wilfred Stillweg 10A Hollandscheveld Drenthe 7913 XB",
    "addr:housenumber":"10a",
    "addr:postcode":"7913 xb",
    "addr:street":"Wilfred Stillweg",
    "iso:country":"NL",
    "sg:address":"Wilfred Stillweg 10A",
    "sg:city":"Hollandscheveld",
    "sg:orig_category":"Begrafenisondernemers",
    "sg:phone":"+31 528 343 120",
    "sg:postcode":"7913 XB",
    "sg:province":"Drenthe",
    "wof:name":"De Marand",
    "wof:placetype":"venue"
},
  "geometry": {"coordinates":[6.54911,52.71133],"type":"Point"}
}