{
  "type": "Feature",
  "properties": {
    "addr:full":"Roerstraat 6 Maasbracht Limburg 6051 LH",
    "addr:housenumber":"6",
    "addr:postcode":"6051 lh",
    "addr:street":"Roerstraat",
    "iso:country":"NL",
    "sg:address":"Roerstraat 6",
    "sg:city":"Maasbracht",
    "sg:orig_category":"Pleziervaartuigen And Reparatie",
    "sg:phone":"+31 475 465 183",
    "sg:postcode":"6051 LH",
    "sg:province":"Limburg",
    "wof:name":"Mobiele Scheepsreparatie Marco Vof",
    "wof:placetype":"venue"
},
  "geometry": {"coordinates":[5.882706,51.138874],"type":"Point"}
}