{
  "type": "Feature",
  "properties": {
    "addr:full":"Dunantstr 40 Hoofddorp Noord-Holland 2131 RR",
    "addr:housenumber":"40",
    "addr:postcode":"2131 rr",
    "addr:street":"Dunantstr",
    "iso:country":"NL",
    "sg:address":"Dunantstr 40",
    "sg:city":"Hoofddorp",
    "sg:classifiers":[
        {
            "category":"Recreation",
            "subcategory":"Dog Park",
            "type":"Entertainment"
        }
    ],
    "sg:phone":"+31 23 563 7300",
    "sg:postcode":"2131 RR",
    "sg:province":"Noord-Holland",
    "sg:tags":[
        "chauffeur",
        "met",
        "autoverhuur"
    ],
    "sg:website":"http://www.businesslimo.com",
    "wof:name":"Business Limousines",
    "wof:placetype":"venue"
},
  "geometry": {"coordinates":[4.679539,52.304501],"type":"Point"}
}