{
  "type": "Feature",
  "properties": {
    "addr:full":"Postbus 728 Gouda Zuid-Holland 2800 AS",
    "addr:housenumber":"728",
    "addr:postcode":"2800 as",
    "addr:street":"Postbus",
    "iso:country":"NL",
    "sg:address":"Postbus 728",
    "sg:city":"Gouda",
    "sg:orig_category":"Voetbalverenigingen",
    "sg:phone":"+31 182 585 273",
    "sg:postcode":"2800 AS",
    "sg:province":"Zuid-Holland",
    "wof:name":"Watergras",
    "wof:placetype":"venue"
},
  "geometry": {"coordinates":[4.710715,52.010006],"type":"Point"}
}