{
  "type": "Feature",
  "properties": {
    "addr:full":"Julianastr 7B Andel North Brabant 4281 NR",
    "addr:housenumber":"7b",
    "addr:postcode":"4281 nr",
    "addr:street":"Julianastr",
    "iso:country":"NL",
    "sg:address":"Julianastr 7B",
    "sg:city":"Andel",
    "sg:orig_category":"Kappers",
    "sg:phone":"+31 183 443 541",
    "sg:postcode":"4281 NR",
    "sg:province":"North Brabant",
    "wof:name":"Knip-Inn",
    "wof:placetype":"venue"
},
  "geometry": {"coordinates":[5.054276,51.784706],"type":"Point"}
}