{
  "type": "Feature",
  "properties": {
    "addr:full":"Zwanenbelt 9 Almelo Overijssel 7607 JW",
    "addr:housenumber":"9",
    "addr:postcode":"7607 jw",
    "addr:street":"Zwanenbelt",
    "iso:country":"NL",
    "sg:address":"Zwanenbelt 9",
    "sg:city":"Almelo",
    "sg:orig_category":"Verlichting And Huishoudartikelen",
    "sg:phone":"+31 546 813 600",
    "sg:postcode":"7607 JW",
    "sg:province":"Overijssel",
    "wof:name":"Firma H.B. Atelier",
    "wof:placetype":"venue"
},
  "geometry": {"coordinates":[6.664543,52.354954],"type":"Point"}
}