{
  "type": "Feature",
  "properties": {
    "iso:country":"NL",
    "sg:address":"Jacobusstr 12",
    "sg:city":"Rotterdam",
    "sg:orig_category":"Webdesign Bureaus",
    "sg:phone":"+31 6 50697775",
    "sg:postcode":"3012 JN",
    "sg:province":"Zuid-Holland",
    "sg:website":"http://www.vof-hepp.nl",
    "wof:name":"Vof-Hepp",
    "wof:placetype":"venue"
},
  "geometry": {"coordinates":[4.4737877846,51.9187660217],"type":"Point"}
}