{
  "type": "Feature",
  "properties": {
    "addr:full":"Hoofdstr 17 Kerkrade Limburg 6461 CL",
    "addr:housenumber":"17",
    "addr:postcode":"6461",
    "addr:street":"Hoofdstr",
    "iso:country":"NL",
    "sg:address":"Hoofdstr 17",
    "sg:city":"Kerkrade",
    "sg:orig_category":"Herenkleding",
    "sg:phone":"+31 45 567 1051",
    "sg:postcode":"6461 CL",
    "sg:province":"Limburg",
    "wof:name":"Roger Bartels, Sportswear & Classics",
    "wof:placetype":"venue"
},
  "geometry": {"coordinates":[6.065333,50.864967],"type":"Point"}
}