{
  "type": "Feature",
  "properties": {
    "addr:full":"Westerveld 8 Annen Drenthe 9468 GP",
    "addr:housenumber":"8",
    "addr:postcode":"9468 gp",
    "addr:street":"Westerveld",
    "iso:country":"NL",
    "sg:address":"Westerveld 8",
    "sg:city":"Annen",
    "sg:orig_category":"Adviesbureaus Planologie",
    "sg:phone":"+31 592 271 721",
    "sg:postcode":"9468 GP",
    "sg:province":"Drenthe",
    "wof:name":"Kamp Vof, Van Der",
    "wof:placetype":"venue"
},
  "geometry": {"coordinates":[-79.253815,33.471233],"type":"Point"}
}