{
  "type": "Feature",
  "properties": {
    "addr:full":"A V Leeuwenhoekln 99 Soesterberg Utrecht 3769 XC",
    "addr:housenumber":"99",
    "addr:postcode":"3769 xc",
    "addr:street":"A;Leeuwenhoekln",
    "iso:country":"NL",
    "sg:address":"A V Leeuwenhoekln 99",
    "sg:city":"Soesterberg",
    "sg:orig_category":"Autorijscholen",
    "sg:phone":"+31 346 351 929",
    "sg:postcode":"3769 XC",
    "sg:province":"Utrecht",
    "wof:name":"Lieben",
    "wof:placetype":"venue"
},
  "geometry": {"coordinates":[5.285409,52.12085],"type":"Point"}
}