{
  "type": "Feature",
  "properties": {
    "addr:full":"Dorpsstr 27 Bergharen Gelderland 6617 AB",
    "addr:housenumber":"27",
    "addr:postcode":"6617 ab",
    "addr:street":"Dorpsstr;Gelderland",
    "iso:country":"NL",
    "sg:address":"Dorpsstr 27",
    "sg:city":"Bergharen",
    "sg:orig_category":"Grafisch Ontwerpers",
    "sg:phone":"+31 487 531 315",
    "sg:postcode":"6617 AB",
    "sg:province":"Gelderland",
    "wof:name":"Estee",
    "wof:placetype":"venue"
},
  "geometry": {"coordinates":[5.663702,51.850853],"type":"Point"}
}