{
  "type": "Feature",
  "properties": {
    "addr:full":"Klinkerstr 27/A Grave Louisiana 5361 GV",
    "addr:housenumber":"27 / a",
    "addr:postcode":"5361 gv",
    "addr:street":"Klinkerstr;Louisiana",
    "iso:country":"NL",
    "sg:address":"Klinkerstr 27/A",
    "sg:city":"Grave",
    "sg:orig_category":"Fietsen En Bromfietsen",
    "sg:phone":"+31 486 472 497",
    "sg:postcode":"5361 GV",
    "sg:province":"Louisiana",
    "wof:name":"Dekkers, J",
    "wof:placetype":"venue"
},
  "geometry": {"coordinates":[-92.151741,32.929253],"type":"Point"}
}