{
  "type": "Feature",
  "properties": {
    "addr:full":"Oudestraat 32 Assen Drenthe 9401 EK",
    "addr:housenumber":"32",
    "addr:postcode":"9401 ek",
    "addr:street":"Oudestraat",
    "iso:country":"NL",
    "sg:address":"Oudestraat 32",
    "sg:city":"Assen",
    "sg:classifiers":[
        {
            "category":"Shopping",
            "subcategory":"Clothing, Apparel, & Fashions",
            "type":"Retail Goods"
        }
    ],
    "sg:phone":"+31 592 312 039",
    "sg:postcode":"9401 EK",
    "sg:province":"Drenthe",
    "sg:tags":[
        "ondergoed",
        "lingerie"
    ],
    "wof:name":"Jambelle Beenmode",
    "wof:placetype":"venue"
},
  "geometry": {"coordinates":[6.562021,52.995979],"type":"Point"}
}