{
  "type": "Feature",
  "properties": {
    "iso:country":"NL",
    "sg:address":"Varikstr 1",
    "sg:city":"Amsterdam Zuidoost",
    "sg:orig_category":"Hulpverlening Sociaal",
    "sg:phone":"+31 20 691 7271",
    "sg:postcode":"1106 CT",
    "sg:province":"Noord-Holland",
    "wof:name":"Hvo",
    "wof:placetype":"venue"
},
  "geometry": {"coordinates":[4.982735,52.300674],"type":"Point"}
}