{
  "type": "Feature",
  "properties": {
    "addr:full":"Hoofdstraat 25 Deurningen Overijssel 7561 AB",
    "addr:housenumber":"25",
    "addr:postcode":"7561 ab",
    "addr:street":"Hoofdstraat",
    "iso:country":"NL",
    "sg:address":"Hoofdstraat 25",
    "sg:city":"Deurningen",
    "sg:orig_category":"Bibliotheken And Openbare Archieven",
    "sg:phone":"+31 74 277 2202",
    "sg:postcode":"7561 AB",
    "sg:province":"Overijssel",
    "wof:name":"Openb Bibliotheken",
    "wof:placetype":"venue"
},
  "geometry": {"coordinates":[6.833465,52.299915],"type":"Point"}
}