{
  "type": "Feature",
  "properties": {
    "addr:full":"Hildebrandhove 141 Zoetermeer Zuid-Holland 2726 AV",
    "addr:housenumber":"141",
    "addr:postcode":"2726 av",
    "addr:street":"Hildebrandhove",
    "iso:country":"NL",
    "sg:address":"Hildebrandhove 141",
    "sg:city":"Zoetermeer",
    "sg:orig_category":"Adviesbureaus Personeel",
    "sg:phone":"+31 79 323 8099",
    "sg:postcode":"2726 AV",
    "sg:province":"Zuid-Holland",
    "sg:website":"http://www.omc2.nl",
    "wof:name":"Omc Kwadraat Bv",
    "wof:placetype":"venue"
},
  "geometry": {"coordinates":[4.489395,52.064735],"type":"Point"}
}