{
  "type": "Feature",
  "properties": {
    "addr:full":"Keizersgr 62 Amsterdam North Holland 1015 CS",
    "addr:housenumber":"62",
    "addr:postcode":"1015 cs",
    "addr:street":"Keizersgr",
    "iso:country":"NL",
    "sg:address":"Keizersgr 62",
    "sg:city":"Amsterdam",
    "sg:orig_category":"Werving En Selectie",
    "sg:phone":"+31 20 520 7455",
    "sg:postcode":"1015 CS",
    "sg:province":"North Holland",
    "sg:website":"http://www.arcticgrounds.nl",
    "wof:name":"Arctic Grounds Bv",
    "wof:placetype":"venue"
},
  "geometry": {"coordinates":[4.8881788254,52.3783912659],"type":"Point"}
}