{
  "type": "Feature",
  "properties": {
    "addr:full":"Jan Voermanstraat 1 Ede Gld Gelderland 6717 VV",
    "addr:housenumber":"1",
    "addr:postcode":"6717 vv",
    "addr:street":"Jan Voermanstraat;Gld Gelderland",
    "iso:country":"NL",
    "sg:address":"Jan Voermanstraat 1",
    "sg:city":"Ede Gld",
    "sg:classifiers":[
        {
            "category":"Education",
            "subcategory":"Preschool",
            "type":"Public Place"
        }
    ],
    "sg:phone":"+31 318 632 160",
    "sg:postcode":"6717 VV",
    "sg:province":"Gelderland",
    "sg:tags":[
        "kleuteronderwijs",
        "basis-"
    ],
    "wof:name":"Cns Basisschool Prinses Juliana",
    "wof:placetype":"venue"
},
  "geometry": {"coordinates":[5.660034,52.015884],"type":"Point"}
}