{
  "type": "Feature",
  "properties": {
    "addr:full":"Pr Mauritsln 9 Wezep Gelderland 8091 AJ",
    "addr:housenumber":"9",
    "addr:postcode":"8091 aj",
    "iso:country":"NL",
    "sg:address":"Pr Mauritsln 9",
    "sg:city":"Wezep",
    "sg:orig_category":"Verenigingen En Stichtingen",
    "sg:phone":"+31 38 376 9692",
    "sg:postcode":"8091 AJ",
    "sg:province":"Gelderland",
    "wof:name":"Trajecten Naar Arbeid, Sticht",
    "wof:placetype":"venue"
},
  "geometry": {"coordinates":[5.99888,52.458267],"type":"Point"}
}