{
  "type": "Feature",
  "properties": {
    "addr:full":"Hoofdstr 14A Stadskanaal Groningen 9501 CL",
    "addr:housenumber":"14a",
    "addr:postcode":"9501",
    "addr:street":"Hoofdstr",
    "iso:country":"NL",
    "sg:address":"Hoofdstr 14A",
    "sg:city":"Stadskanaal",
    "sg:orig_category":"Hengelsportartikelen",
    "sg:phone":"+31 599 651 295",
    "sg:postcode":"9501 CL",
    "sg:province":"Groningen",
    "sg:website":"http://www1.tip.nl/~t150058",
    "wof:name":"Ara Hengelsportspeciaalzaak, De",
    "wof:placetype":"venue"
},
  "geometry": {"coordinates":[6.948748,52.98975],"type":"Point"}
}