{
  "type": "Feature",
  "properties": {
    "addr:full":"Vlaggeschip 27 Oosterhout Nb Noord-Brabant 4902 CN",
    "addr:housenumber":"27",
    "addr:postcode":"4902 cn",
    "addr:street":"Vlaggeschip",
    "iso:country":"NL",
    "sg:address":"Vlaggeschip 27",
    "sg:city":"Oosterhout Nb",
    "sg:orig_category":"Adviesbureaus Waterbouwkunde",
    "sg:phone":"+31 162 453 965",
    "sg:postcode":"4902 CN",
    "sg:province":"Noord-Brabant",
    "wof:name":"Db",
    "wof:placetype":"venue"
},
  "geometry": {"coordinates":[4.842533,51.641338],"type":"Point"}
}