{
  "type": "Feature",
  "properties": {
    "iso:country":"NL",
    "sg:address":"Weerterveld 43",
    "sg:city":"Meerssen",
    "sg:orig_category":"Meubelreparatie And -Restauratie",
    "sg:phone":"+31 43 364 1867",
    "sg:postcode":"6231 NC",
    "sg:province":"Limburg",
    "wof:name":"Doeleint Interieurbouw Vof",
    "wof:placetype":"venue"
},
  "geometry": {"coordinates":[5.737011,50.886246],"type":"Point"}
}