{
  "type": "Feature",
  "properties": {
    "addr:full":"Julianaweg 190 Volendam North Holland 1131 DL",
    "addr:housenumber":"190",
    "addr:postcode":"1131 dl",
    "addr:street":"Julianaweg",
    "iso:country":"NL",
    "sg:address":"Julianaweg 190",
    "sg:city":"Volendam",
    "sg:orig_category":"Woningbouwverenigingen",
    "sg:phone":"+31 299 399 960",
    "sg:postcode":"1131 DL",
    "sg:province":"North Holland",
    "wof:name":"Woningbouwvereniging De Vooruitgang",
    "wof:placetype":"venue"
},
  "geometry": {"coordinates":[5.0765790939,52.4994812012],"type":"Point"}
}