{
  "type": "Feature",
  "properties": {
    "addr:full":"Duvenee 44 Bergen Op Zoom North Brabant 4617 NB",
    "addr:housenumber":"44",
    "addr:postcode":"4617 nb",
    "addr:street":"Duvenee",
    "iso:country":"NL",
    "sg:address":"Duvenee 44",
    "sg:city":"Bergen Op Zoom",
    "sg:orig_category":"Chemische Producten Gh",
    "sg:phone":"+31 164 211 771",
    "sg:postcode":"4617 NB",
    "sg:province":"North Brabant",
    "wof:name":"Maxeco",
    "wof:placetype":"venue"
},
  "geometry": {"coordinates":[4.278946,51.476784],"type":"Point"}
}