{
  "type": "Feature",
  "properties": {
    "addr:full":"V Riebeeckwg 212 Hilversum Noord-Holland 1213 XZ",
    "addr:housenumber":"212",
    "addr:postcode":"hilversum;1213 xz",
    "iso:country":"NL",
    "sg:address":"V Riebeeckwg 212",
    "sg:city":"Hilversum",
    "sg:orig_category":"Kappers",
    "sg:phone":"+31 35 688 7485",
    "sg:postcode":"1213 XZ",
    "sg:province":"Noord-Holland",
    "wof:name":"Marina, Salon",
    "wof:placetype":"venue"
},
  "geometry": {"coordinates":[5.1695,52.228565],"type":"Point"}
}