{
  "type": "Feature",
  "properties": {
    "addr:full":"Marslandenwg 3 Borger Provincie Drenthe 9531 JS",
    "addr:housenumber":"3",
    "addr:postcode":"9531 js",
    "addr:street":"Marslandenwg;Provincie",
    "iso:country":"NL",
    "sg:address":"Marslandenwg 3",
    "sg:city":"Borger",
    "sg:orig_category":"Psychologen",
    "sg:phone":"+31 599 238 044",
    "sg:postcode":"9531 JS",
    "sg:province":"Provincie Drenthe",
    "wof:name":"Vlek",
    "wof:placetype":"venue"
},
  "geometry": {"coordinates":[6.795242,52.928001],"type":"Point"}
}