{
  "type": "Feature",
  "properties": {
    "addr:full":"Eikbosserweg 35 Hilversum Noord-Holland 1214 AE",
    "addr:housenumber":"35",
    "addr:postcode":"1214 ae",
    "addr:street":"Eikbosserweg",
    "iso:country":"NL",
    "sg:address":"Eikbosserweg 35",
    "sg:city":"Hilversum",
    "sg:orig_category":"Hypotheken And Hypotheekbanken",
    "sg:phone":"+31 35 628 4570",
    "sg:postcode":"1214 AE",
    "sg:province":"Noord-Holland",
    "wof:name":"Dijksterhuis",
    "wof:placetype":"venue"
},
  "geometry": {"coordinates":[5.174847,52.217121],"type":"Point"}
}