{
  "type": "Feature",
  "properties": {
    "iso:country":"NL",
    "sg:address":"Prof Zeemanwg 5",
    "sg:city":"Waalwyk",
    "sg:orig_category":"Woninginrichting",
    "sg:phone":"+31 416 651 905",
    "sg:postcode":"5144 NN",
    "sg:province":"North Brabant",
    "wof:name":"Kwantum",
    "wof:placetype":"venue"
},
  "geometry": {"coordinates":[5.0620298386,51.6775398254],"type":"Point"}
}