{
  "type": "Feature",
  "properties": {
    "iso:country":"NL",
    "sg:address":"H V Halterenstr 3",
    "sg:city":"Lichtenvoorde",
    "sg:orig_category":"Montagebedrijven",
    "sg:phone":"+31 544 376 751",
    "sg:postcode":"7131 ZM",
    "sg:province":"Gelderland",
    "wof:name":"Krabben Montage",
    "wof:placetype":"venue"
},
  "geometry": {"coordinates":[6.56445,51.9883],"type":"Point"}
}