{
  "type": "Feature",
  "properties": {
    "addr:full":"Postbus 1081 Den Bosch Noord-Holland 5200 BC",
    "addr:housenumber":"1081",
    "addr:postcode":"5200 bc",
    "addr:street":"Postbus",
    "iso:country":"NL",
    "sg:address":"Postbus 1081",
    "sg:city":"Den Bosch",
    "sg:orig_category":"Airconditioning And Ventilatie",
    "sg:phone":"+31 6 28784075",
    "sg:postcode":"5200 BC",
    "sg:province":"Noord-Holland",
    "wof:name":"Mulders Clima Service",
    "wof:placetype":"venue"
},
  "geometry": {"coordinates":[5.29824,51.69075],"type":"Point"}
}