{
  "type": "Feature",
  "properties": {
    "iso:country":"NL",
    "sg:address":"Het Rip 3",
    "sg:city":"Kamperland",
    "sg:orig_category":"Autokeuringen",
    "sg:phone":"+31 113 371 578",
    "sg:postcode":"4493 RL",
    "sg:province":"Zeeland",
    "wof:name":"Roland Poppe",
    "wof:placetype":"venue"
},
  "geometry": {"coordinates":[3.700144,51.573936],"type":"Point"}
}