{
  "type": "Feature",
  "properties": {
    "addr:full":"Graaf Florislaan 40 Hilversum Noord-Holland 1217 KM",
    "addr:housenumber":"40",
    "addr:postcode":"1217 km",
    "addr:street":"Graaf Florislaan",
    "iso:country":"NL",
    "sg:address":"Graaf Florislaan 40",
    "sg:city":"Hilversum",
    "sg:orig_category":"Film-, Tv- And Videoproductie",
    "sg:phone":"+31 35 623 3621",
    "sg:postcode":"1217 KM",
    "sg:province":"Noord-Holland",
    "wof:name":"Advanced Video Nederland Bv",
    "wof:placetype":"venue"
},
  "geometry": {"coordinates":[5.170445,52.230755],"type":"Point"}
}