{
  "type": "Feature",
  "properties": {
    "iso:country":"NL",
    "sg:address":"Pontdk 8",
    "sg:city":"Langweer",
    "sg:orig_category":"Jachthavens - Jachtwerven",
    "sg:phone":"+31 513 499 298",
    "sg:postcode":"8525 GG",
    "sg:province":"Provincie Friesland",
    "wof:name":"Kwvl",
    "wof:placetype":"venue"
},
  "geometry": {"coordinates":[5.718836,52.96109],"type":"Point"}
}