{
  "type": "Feature",
  "properties": {
    "addr:full":"Breitnerlaan 82 'S Gravenhage South Holland 2596 HD",
    "addr:housenumber":"82",
    "addr:postcode":"2596 hd",
    "addr:street":"Breitnerlaan;' S Gravenhage",
    "iso:country":"NL",
    "sg:address":"Breitnerlaan 82",
    "sg:city":"'S Gravenhage",
    "sg:orig_category":"Boekhouders",
    "sg:phone":"+31 70 328 3762",
    "sg:postcode":"2596 HD",
    "sg:province":"South Holland",
    "wof:name":"Jbg",
    "wof:placetype":"venue"
},
  "geometry": {"coordinates":[4.326751,52.093369],"type":"Point"}
}