{
  "type": "Feature",
  "properties": {
    "iso:country":"NL",
    "sg:address":"Brahmsstraat 3",
    "sg:city":"Raamsdonksveer",
    "sg:orig_category":"Bibliotheken And Openbare Archieven",
    "sg:phone":"+31 162 513 158",
    "sg:postcode":"4941 AG",
    "sg:province":"North Brabant",
    "wof:name":"Openbare Bibliotheek Raamsdonksveer",
    "wof:placetype":"venue"
},
  "geometry": {"coordinates":[4.880217,51.691124],"type":"Point"}
}