{
  "type": "Feature",
  "properties": {
    "addr:full":"Stranwei 30 Makkum Fr Provincie Friesland 8754 HA",
    "addr:housenumber":"30",
    "addr:postcode":"8754 ha",
    "addr:street":"Stranwei;Friesland",
    "iso:country":"NL",
    "sg:address":"Stranwei 30",
    "sg:city":"Makkum Fr",
    "sg:orig_category":"Jachthavens - Jachtwerven",
    "sg:phone":"+31 515 231 785",
    "sg:postcode":"8754 HA",
    "sg:province":"Provincie Friesland",
    "sg:website":"http://www.bloemsma-vanbreemen.nl",
    "wof:name":"Bloemsma & V Breemen Shipyard",
    "wof:placetype":"venue"
},
  "geometry": {"coordinates":[5.396994,53.053436],"type":"Point"}
}