{
  "type": "Feature",
  "properties": {
    "addr:full":"Haarlemmerstrwg 52 Oegstgeest South Holland 2343 LB",
    "addr:housenumber":"52",
    "addr:postcode":"2343 lb",
    "addr:street":"Haarlemmerstrwg",
    "iso:country":"NL",
    "sg:address":"Haarlemmerstrwg 52",
    "sg:city":"Oegstgeest",
    "sg:orig_category":"Opslag Inboedels",
    "sg:phone":"+31 71 519 2000",
    "sg:postcode":"2343 LB",
    "sg:province":"South Holland",
    "sg:website":"http://www.vanderluyt.nl",
    "wof:name":"Luyt Selfstorage Bv, V/D",
    "wof:placetype":"venue"
},
  "geometry": {"coordinates":[4.4682421684,52.1766166687],"type":"Point"}
}