{
  "type": "Feature",
  "properties": {
    "addr:full":"Arnhemstr 13 Deventer Overijssel 7418 CL",
    "addr:housenumber":"13",
    "addr:postcode":"7418",
    "addr:street":"Arnhemstr",
    "iso:country":"NL",
    "sg:address":"Arnhemstr 13",
    "sg:city":"Deventer",
    "sg:orig_category":"Drukkerijen",
    "sg:phone":"+31 570 624 218",
    "sg:postcode":"7418 CL",
    "sg:province":"Overijssel",
    "wof:name":"Pdfprint Bv",
    "wof:placetype":"venue"
},
  "geometry": {"coordinates":[6.180882,52.248619],"type":"Point"}
}