{
  "type": "Feature",
  "properties": {
    "iso:country":"NL",
    "sg:address":"Bedryfswg 37-41",
    "sg:city":"Best",
    "sg:orig_category":"Fitnesscentra",
    "sg:phone":"+31 499 390 112",
    "sg:postcode":"5683 CN",
    "sg:province":"Noord-Brabant",
    "wof:name":"Casemier",
    "wof:placetype":"venue"
},
  "geometry": {"coordinates":[-101.618134,31.224251],"type":"Point"}
}