{
  "type": "Feature",
  "properties": {
    "addr:full":"Snouckaertln 42 Amersfoort Utrecht 3811 MB",
    "addr:housenumber":"42",
    "addr:postcode":"3811 mb",
    "addr:street":"Snouckaertln",
    "iso:country":"NL",
    "sg:address":"Snouckaertln 42",
    "sg:city":"Amersfoort",
    "sg:orig_category":"Octrooigemachtigden- Bureaus",
    "sg:phone":"+31 33 422 7300",
    "sg:postcode":"3811 MB",
    "sg:province":"Utrecht",
    "sg:website":"http://www.vereenigde.nl",
    "wof:name":"Vereenigde",
    "wof:placetype":"venue"
},
  "geometry": {"coordinates":[5.381996,52.15353],"type":"Point"}
}