{
  "type": "Feature",
  "properties": {
    "addr:full":"Industrieweg 9 Harmelen Utrecht 3481 MD",
    "addr:housenumber":"9",
    "addr:postcode":"3481",
    "addr:street":"Industrieweg",
    "iso:country":"NL",
    "sg:address":"Industrieweg 9",
    "sg:city":"Harmelen",
    "sg:orig_category":"Fitnesscentra",
    "sg:phone":"+31 348 442 659",
    "sg:postcode":"3481 MD",
    "sg:province":"Utrecht",
    "wof:name":"Vitalis Lichaamsverzorging Centrum",
    "wof:placetype":"venue"
},
  "geometry": {"coordinates":[4.945509,52.099789],"type":"Point"}
}