{
  "type": "Feature",
  "properties": {
    "addr:full":"Tweehuizerwg 2 Velp Nb Noord-Brabant 5363 SH",
    "addr:housenumber":"2",
    "addr:postcode":"5363 sh",
    "addr:street":"Tweehuizerwg",
    "iso:country":"NL",
    "sg:address":"Tweehuizerwg 2",
    "sg:city":"Velp Nb",
    "sg:orig_category":"Open Haard Houtblokken",
    "sg:phone":"+31 486 471 628",
    "sg:postcode":"5363 SH",
    "sg:province":"Noord-Brabant",
    "wof:name":"Thijssen, Peter",
    "wof:placetype":"venue"
},
  "geometry": {"coordinates":[5.709299,51.736874],"type":"Point"}
}