{
  "type": "Feature",
  "properties": {
    "addr:full":"Polstr 68 Wyk En Aalburg Noord-Brabant 4261 BV",
    "addr:housenumber":"68",
    "addr:postcode":"4261 bv",
    "addr:street":"Polstr",
    "iso:country":"NL",
    "sg:address":"Polstr 68",
    "sg:city":"Wyk En Aalburg",
    "sg:orig_category":"Autorijscholen",
    "sg:phone":"+31 416 695 224",
    "sg:postcode":"4261 BV",
    "sg:province":"Noord-Brabant",
    "wof:name":"Forward",
    "wof:placetype":"venue"
},
  "geometry": {"coordinates":[5.119111,51.748817],"type":"Point"}
}