{
  "type": "Feature",
  "properties": {
    "addr:full":"Zeilbergsestraat 25 Deurne Noord-Brabant 5751 LG",
    "addr:housenumber":"25",
    "addr:postcode":"5751 lg",
    "addr:street":"Zeilbergsestraat",
    "iso:country":"NL",
    "sg:address":"Zeilbergsestraat 25",
    "sg:city":"Deurne",
    "sg:orig_category":"Bloemen And Planten",
    "sg:phone":"+31 493 322 688",
    "sg:postcode":"5751 LG",
    "sg:province":"Noord-Brabant",
    "wof:name":"T Bloemenhuis",
    "wof:placetype":"venue"
},
  "geometry": {"coordinates":[5.814941,51.454041],"type":"Point"}
}