{
  "type": "Feature",
  "properties": {
    "addr:full":"Verl Herewg 57 Groningen Groningen 9721 AG",
    "addr:housenumber":"57",
    "addr:postcode":"9721",
    "iso:country":"NL",
    "sg:address":"Verl Herewg 57",
    "sg:city":"Groningen",
    "sg:orig_category":"Banken",
    "sg:phone":"+31 50 525 6117",
    "sg:postcode":"9721 AG",
    "sg:province":"Groningen",
    "sg:website":"http://www.sns.nl",
    "wof:name":"Sns",
    "wof:placetype":"venue"
},
  "geometry": {"coordinates":[6.579441,53.198654],"type":"Point"}
}