{
  "type": "Feature",
  "properties": {
    "addr:full":"Van Heemstraweg 70 Beuningen Gld Gelderland 6641 AG",
    "addr:housenumber":"70",
    "addr:postcode":"6641",
    "addr:street":"Van Heemstraweg",
    "iso:country":"NL",
    "sg:address":"Van Heemstraweg 70",
    "sg:city":"Beuningen Gld",
    "sg:orig_category":"Autokeuringen",
    "sg:phone":"+31 24 677 1924",
    "sg:postcode":"6641 AG",
    "sg:province":"Gelderland",
    "wof:name":"J.C.A. Schneberger",
    "wof:placetype":"venue"
},
  "geometry": {"coordinates":[5.76956,51.85955],"type":"Point"}
}