{
  "type": "Feature",
  "properties": {
    "addr:full":"Overtoom 470 Amsterdam Noord-Holland 1054 JX",
    "addr:housenumber":"470",
    "addr:postcode":"1054 jx",
    "addr:street":"Overtoom",
    "iso:country":"NL",
    "sg:address":"Overtoom 470",
    "sg:city":"Amsterdam",
    "sg:classifiers":[
        {
            "category":"Food & Beverages",
            "subcategory":"Fruits & Vegetables",
            "type":"Retail Goods"
        }
    ],
    "sg:phone":"+31 20 612 3010",
    "sg:postcode":"1054 JX",
    "sg:province":"Noord-Holland",
    "sg:tags":[
        "groenten"
    ],
    "wof:name":"A.G.F. H. De Groot Vof",
    "wof:placetype":"venue"
},
  "geometry": {"coordinates":[4.861348,52.359493],"type":"Point"}
}