{
  "type": "Feature",
  "properties": {
    "iso:country":"NL",
    "sg:address":"Jacob Van Akenstraat 75",
    "sg:city":"Rotterdam",
    "sg:orig_category":"Loodgieterswerk, Verwarming And Sanitaire Installaties",
    "sg:phone":"+31 10 420 0809",
    "sg:postcode":"3067 JP",
    "sg:province":"South Holland",
    "wof:name":"J.M. De Haas Loodgieters- En Installatiebedrijf Bv",
    "wof:placetype":"venue"
},
  "geometry": {"coordinates":[4.539907,51.943386],"type":"Point"}
}