{
  "type": "Feature",
  "properties": {
    "addr:full":"Visweg 21 Limmen Noord-Holland 1906 CN",
    "addr:housenumber":"21",
    "addr:postcode":"1906 cn",
    "addr:street":"Visweg",
    "iso:country":"NL",
    "sg:address":"Visweg 21",
    "sg:city":"Limmen",
    "sg:orig_category":"Bloemen And Planten",
    "sg:phone":"+31 72 505 2361",
    "sg:postcode":"1906 CN",
    "sg:province":"Noord-Holland",
    "wof:name":"N.J. Beentjes",
    "wof:placetype":"venue"
},
  "geometry": {"coordinates":[4.699214,52.576134],"type":"Point"}
}