{
  "type": "Feature",
  "properties": {
    "addr:full":"Dr. A. Plesmanweg 28 Paterswolde Provincie Drenthe 9765 GT",
    "addr:housenumber":"28",
    "addr:postcode":"9765 gt",
    "addr:street":"Dr. A. Plesmanweg;Provincie Drenthe",
    "iso:country":"NL",
    "sg:address":"Dr. A. Plesmanweg 28",
    "sg:city":"Paterswolde",
    "sg:orig_category":"Metaalwerken",
    "sg:phone":"+31 6 53119828",
    "sg:postcode":"9765 GT",
    "sg:province":"Provincie Drenthe",
    "wof:name":"Remotech",
    "wof:placetype":"venue"
},
  "geometry": {"coordinates":[6.563925,53.148022],"type":"Point"}
}