{
  "type": "Feature",
  "properties": {
    "addr:full":"Kerkstr 66 Hapert Noord-Brabant 5527 EG",
    "addr:housenumber":"66",
    "addr:postcode":"5527 eg",
    "addr:street":"Kerkstr",
    "iso:country":"NL",
    "sg:address":"Kerkstr 66",
    "sg:city":"Hapert",
    "sg:orig_category":"Kappers",
    "sg:phone":"+31 497 382 281",
    "sg:postcode":"5527 EG",
    "sg:province":"Noord-Brabant",
    "wof:name":"Mollen, J",
    "wof:placetype":"venue"
},
  "geometry": {"coordinates":[5.25357,51.367123],"type":"Point"}
}