{
  "type": "Feature",
  "properties": {
    "iso:country":"NL",
    "sg:address":"Biltstr 337",
    "sg:city":"Utrecht",
    "sg:orig_category":"Verenigingen En Stichtingen",
    "sg:phone":"+31 30 236 8230",
    "sg:postcode":"3572 AS",
    "sg:province":"Utrecht",
    "wof:name":"Brillante, El",
    "wof:placetype":"venue"
},
  "geometry": {"coordinates":[5.13413,52.095341],"type":"Point"}
}