{
  "type": "Feature",
  "properties": {
    "addr:full":"Slobbeland 40 Volendam Noord-Holland 1131 AB",
    "addr:housenumber":"40",
    "addr:postcode":"1131 ab",
    "addr:street":"Slobbeland",
    "iso:country":"NL",
    "sg:address":"Slobbeland 40",
    "sg:city":"Volendam",
    "sg:classifiers":[
        {
            "category":"Wholesale",
            "subcategory":"Motor Vehicles",
            "type":"Manufacturing & Wholesale Goods"
        }
    ],
    "sg:phone":"+31 299 361 198",
    "sg:postcode":"1131 AB",
    "sg:province":"Noord-Holland",
    "sg:tags":[
        "scooter",
        "en"
    ],
    "sg:website":"http://www.v-twincustoms.nl",
    "wof:name":"V-Twin Customs",
    "wof:placetype":"venue"
},
  "geometry": {"coordinates":[5.065259,52.491238],"type":"Point"}
}