{
  "type": "Feature",
  "properties": {
    "addr:full":"Walmolenerf 137 Gouda South Holland 2807 DA",
    "addr:housenumber":"137",
    "addr:postcode":"2807 da",
    "addr:street":"Walmolenerf",
    "iso:country":"NL",
    "sg:address":"Walmolenerf 137",
    "sg:city":"Gouda",
    "sg:orig_category":"Juridische Adviseurs",
    "sg:phone":"+31 182 526 247",
    "sg:postcode":"2807 DA",
    "sg:province":"South Holland",
    "wof:name":"Bedrijfsjuridische Dienst",
    "wof:placetype":"venue"
},
  "geometry": {"coordinates":[4.740905,52.008858],"type":"Point"}
}