{
  "type": "Feature",
  "properties": {
    "addr:full":"Zaanstraat 56 Leiden Zuid-Holland 2314 XG",
    "addr:housenumber":"56",
    "addr:postcode":"2314 xg",
    "addr:street":"Zaanstraat",
    "iso:country":"NL",
    "sg:address":"Zaanstraat 56",
    "sg:city":"Leiden",
    "sg:orig_category":"Bedrijfs- And Managementsconsultants",
    "sg:phone":"+31 6 55100479",
    "sg:postcode":"2314 XG",
    "sg:province":"Zuid-Holland",
    "wof:name":"C Kranenburg",
    "wof:placetype":"venue"
},
  "geometry": {"coordinates":[4.516358,52.152206],"type":"Point"}
}