{
  "type": "Feature",
  "properties": {
    "addr:full":"Ommerkan W 22 Ommen NL.08 7731 XR",
    "addr:housenumber":"22;nl.08",
    "addr:postcode":"7731 xr",
    "addr:street":"W",
    "iso:country":"NL",
    "sg:address":"Ommerkan W 22",
    "sg:city":"Ommen",
    "sg:orig_category":"Verenigingsgebouwen",
    "sg:phone":"+31 523 676 372",
    "sg:postcode":"7731 XR",
    "sg:province":"NL.08",
    "wof:name":"Buurthuis Ommerkanaal",
    "wof:placetype":"venue"
},
  "geometry": {"coordinates":[6.429792,52.562527],"type":"Point"}
}