{
  "type": "Feature",
  "properties": {
    "addr:full":"Anthonie Verherentstraat 6 Heemskerk Noord-Holland 1961 GD",
    "addr:housenumber":"6",
    "addr:postcode":"1961 gd",
    "addr:street":"Anthonie Verherentstraat",
    "iso:country":"NL",
    "sg:address":"Anthonie Verherentstraat 6",
    "sg:city":"Heemskerk",
    "sg:orig_category":"Begrafenisondernemers",
    "sg:phone":"+31 251 234 518",
    "sg:postcode":"1961 GD",
    "sg:province":"Noord-Holland",
    "wof:name":"Heemskerk Koning",
    "wof:placetype":"venue"
},
  "geometry": {"coordinates":[4.674403,52.512161],"type":"Point"}
}