{
  "type": "Feature",
  "properties": {
    "addr:full":"Kooltuin 5A Alkmaar Noord-Holland 1811 MG",
    "addr:housenumber":"5a",
    "addr:postcode":"1811 mg",
    "addr:street":"Kooltuin",
    "iso:country":"NL",
    "sg:address":"Kooltuin 5A",
    "sg:city":"Alkmaar",
    "sg:orig_category":"Antiquiteiten",
    "sg:phone":"+31 72 515 0923",
    "sg:postcode":"1811 MG",
    "sg:province":"Noord-Holland",
    "wof:name":"Groesz, M",
    "wof:placetype":"venue"
},
  "geometry": {"coordinates":[4.752691,52.631779],"type":"Point"}
}