{
  "type": "Feature",
  "properties": {
    "iso:country":"NL",
    "sg:address":"Prinsengr 673",
    "sg:city":"Amsterdam",
    "sg:orig_category":"Luchtvaart- Maatschappijen",
    "sg:phone":"+31 20 620 8981",
    "sg:postcode":"1017 JT",
    "sg:province":"Noord-Holland",
    "wof:name":"W A & Co",
    "wof:placetype":"venue"
},
  "geometry": {"coordinates":[4.883528,52.366035],"type":"Point"}
}