{
  "type": "Feature",
  "properties": {
    "addr:full":"Markt 185 Helmond Noord-Brabant 5701 RJ",
    "addr:housenumber":"185",
    "addr:postcode":"5701 rj",
    "addr:street":"Markt",
    "iso:country":"NL",
    "sg:address":"Markt 185",
    "sg:city":"Helmond",
    "sg:orig_category":"Administratie- En Boekhoudkantoren",
    "sg:phone":"+31 492 541 688",
    "sg:postcode":"5701 RJ",
    "sg:province":"Noord-Brabant",
    "wof:name":"Deursen, Bart Van",
    "wof:placetype":"venue"
},
  "geometry": {"coordinates":[5.655669,51.480381],"type":"Point"}
}