{
  "type": "Feature",
  "properties": {
    "addr:full":"Koorstr 23-25 Alkmaar North Holland 1811 GM",
    "addr:housenumber":"23-25",
    "addr:postcode":"1811 gm",
    "iso:country":"NL",
    "sg:address":"Koorstr 23-25",
    "sg:city":"Alkmaar",
    "sg:orig_category":"Piano'S",
    "sg:phone":"+31 72 515 4344",
    "sg:postcode":"1811 GM",
    "sg:province":"North Holland",
    "wof:name":"Spanjaard Muziek Bv",
    "wof:placetype":"venue"
},
  "geometry": {"coordinates":[4.738863,52.632206],"type":"Point"}
}