{
  "type": "Feature",
  "properties": {
    "addr:full":"Vyfhuizerdk 165 Vyfhuizen Noord-Holland 2141 BH",
    "addr:housenumber":"165",
    "addr:postcode":"2141 bh",
    "addr:street":"Vyfhuizen Noord-Holland",
    "iso:country":"NL",
    "sg:address":"Vyfhuizerdk 165",
    "sg:city":"Vyfhuizen",
    "sg:classifiers":[
        {
            "category":"Manufacturing",
            "subcategory":"Rubber & Plastics",
            "type":"Manufacturing & Wholesale Goods"
        }
    ],
    "sg:phone":"+31 23 535 7823",
    "sg:postcode":"2141 BH",
    "sg:province":"Noord-Holland",
    "sg:tags":[
        "plexiglas"
    ],
    "sg:website":"http://www.elmaplast-bv.nl",
    "wof:name":"Elmaplast Bv",
    "wof:placetype":"venue"
},
  "geometry": {"coordinates":[4.679655,52.352299],"type":"Point"}
}