{
  "type": "Feature",
  "properties": {
    "iso:country":"NL",
    "sg:address":"Tussen Meer 57",
    "sg:city":"Amsterdam",
    "sg:orig_category":"Schoenen",
    "sg:phone":"+31 20 619 2596",
    "sg:postcode":"1068 EZ",
    "sg:province":"North Holland",
    "wof:name":"Leemans Bv",
    "wof:placetype":"venue"
},
  "geometry": {"coordinates":[4.801178,52.3582],"type":"Point"}
}