{
  "type": "Feature",
  "properties": {
    "addr:full":"Meeuwenln 122 Amsterdam Noord-Holland 1021 JN",
    "addr:housenumber":"122",
    "addr:postcode":"1021 jn",
    "iso:country":"NL",
    "sg:address":"Meeuwenln 122",
    "sg:city":"Amsterdam",
    "sg:orig_category":"Autoschade- Herstelbedrijven",
    "sg:phone":"+31 20 636 1853",
    "sg:postcode":"1021 JN",
    "sg:province":"Noord-Holland",
    "wof:name":"Korstanje, E J G",
    "wof:placetype":"venue"
},
  "geometry": {"coordinates":[4.923483,52.386517],"type":"Point"}
}