{
  "type": "Feature",
  "properties": {
    "addr:full":"Van Gijnstraat 13 Rijswijk Zh Zuid-Holland 2288 GB",
    "addr:housenumber":"13",
    "addr:postcode":"zh;2288 gb",
    "addr:street":"Van Gijnstraat",
    "iso:country":"NL",
    "sg:address":"Van Gijnstraat 13",
    "sg:city":"Rijswijk Zh",
    "sg:orig_category":"Public Relationbureaus",
    "sg:phone":"+31 70 307 0684",
    "sg:postcode":"2288 GB",
    "sg:province":"Zuid-Holland",
    "wof:name":"Logimark Advies Bedrijfskundig Marketing",
    "wof:placetype":"venue"
},
  "geometry": {"coordinates":[4.330929,52.038231],"type":"Point"}
}