{
  "type": "Feature",
  "properties": {
    "addr:full":"Muldershof 19 Zevenaar Gelderland 6901 GW",
    "addr:housenumber":"19",
    "addr:postcode":"6901 gw",
    "addr:street":"Muldershof",
    "iso:country":"NL",
    "sg:address":"Muldershof 19",
    "sg:city":"Zevenaar",
    "sg:orig_category":"Zonnebank- En Solariumcentra",
    "sg:phone":"+31 316 333 787",
    "sg:postcode":"6901 GW",
    "sg:province":"Gelderland",
    "wof:name":"Muldershof",
    "wof:placetype":"venue"
},
  "geometry": {"coordinates":[6.077079,51.930214],"type":"Point"}
}