{
  "type": "Feature",
  "properties": {
    "addr:full":"Avelingen W 41 Gorinchem Zuid-Holland 4202 MS",
    "addr:housenumber":"41",
    "addr:postcode":"4202 ms",
    "addr:street":"Avelingen W",
    "iso:country":"NL",
    "sg:address":"Avelingen W 41",
    "sg:city":"Gorinchem",
    "sg:orig_category":"Betonijzervlechten",
    "sg:phone":"+31 183 634 845",
    "sg:postcode":"4202 MS",
    "sg:province":"Zuid-Holland",
    "wof:name":"Muilwijk Bv, Gebr",
    "wof:placetype":"venue"
},
  "geometry": {"coordinates":[4.939638,51.834618],"type":"Point"}
}