{
  "type": "Feature",
  "properties": {
    "addr:full":"Kievitstraat 25 Boskoop South Holland 2771 TG",
    "addr:housenumber":"25",
    "addr:postcode":"2771 tg",
    "addr:street":"Kievitstraat",
    "iso:country":"NL",
    "sg:address":"Kievitstraat 25",
    "sg:city":"Boskoop",
    "sg:orig_category":"Personenvervoer Zonder Dienstregeling",
    "sg:phone":"+31 172 217 329",
    "sg:postcode":"2771 TG",
    "sg:province":"South Holland",
    "wof:name":"D Krouwel",
    "wof:placetype":"venue"
},
  "geometry": {"coordinates":[4.642377,52.066628],"type":"Point"}
}