{
  "type": "Feature",
  "properties": {
    "iso:country":"NL",
    "sg:address":"Grotestraat 77",
    "sg:city":"Goor",
    "sg:orig_category":"Fietshandelaren",
    "sg:phone":"+31 547 274 113",
    "sg:postcode":"7471 BL",
    "sg:province":"Overijssel",
    "wof:name":"Vof Tweewielspeciaalzaak Reef",
    "wof:placetype":"venue"
},
  "geometry": {"coordinates":[6.587023,52.233219],"type":"Point"}
}