{
  "type": "Feature",
  "properties": {
    "addr:full":"Dortmundstraat 10 Deventer Overijssel 7418 BH",
    "addr:housenumber":"10",
    "addr:postcode":"7418 bh",
    "addr:street":"Dortmundstraat",
    "iso:country":"NL",
    "sg:address":"Dortmundstraat 10",
    "sg:city":"Deventer",
    "sg:orig_category":"Autokeuringen",
    "sg:phone":"+31 570 622 299",
    "sg:postcode":"7418 BH",
    "sg:province":"Overijssel",
    "wof:name":"Kruitbosch En De Weerd Deventer Bv",
    "wof:placetype":"venue"
},
  "geometry": {"coordinates":[6.194179,52.244411],"type":"Point"}
}