{
  "type": "Feature",
  "properties": {
    "addr:full":"Adm De Ruyterstr 2 Schiedam Zuid-Holland 3115 HB",
    "addr:housenumber":"2",
    "addr:postcode":"3115 hb",
    "iso:country":"NL",
    "sg:address":"Adm De Ruyterstr 2",
    "sg:city":"Schiedam",
    "sg:orig_category":"Koeltechniek",
    "sg:phone":"+31 10 409 3900",
    "sg:postcode":"3115 HB",
    "sg:province":"Zuid-Holland",
    "sg:website":"http://www.coolmark.nl",
    "wof:name":"Coolmark Bv",
    "wof:placetype":"venue"
},
  "geometry": {"coordinates":[4.385972,51.907494],"type":"Point"}
}