{
  "type": "Feature",
  "properties": {
    "iso:country":"NL",
    "sg:address":"Kleine Houtstraat 90",
    "sg:city":"Haarlem",
    "sg:classifiers":[
        {
            "category":"Fast Food",
            "type":"Food & Drink"
        }
    ],
    "sg:phone":"+31 23 532 0086",
    "sg:postcode":"2011 DR",
    "sg:province":"Noord-Holland",
    "sg:tags":[
        "afhaal",
        "restaurant"
    ],
    "wof:name":"Snackbar 'T Snorretje",
    "wof:placetype":"venue"
},
  "geometry": {"coordinates":[4.635294,52.377293],"type":"Point"}
}