{
  "type": "Feature",
  "properties": {
    "addr:full":"Rijnbeekstraat 12 Venlo Limburg 5913 GB",
    "addr:housenumber":"12",
    "addr:postcode":"5913 gb",
    "addr:street":"Rijnbeekstraat",
    "iso:country":"NL",
    "sg:address":"Rijnbeekstraat 12",
    "sg:city":"Venlo",
    "sg:orig_category":"Organisaties And Verenigingen",
    "sg:phone":"+31 77 354 1049",
    "sg:postcode":"5913 GB",
    "sg:province":"Limburg",
    "wof:name":"Kunstuitleen Bonnefantenmuseum",
    "wof:placetype":"venue"
},
  "geometry": {"coordinates":[6.1875457764,51.3720092773],"type":"Point"}
}