{
  "type": "Feature",
  "properties": {
    "addr:full":"Aalsmeerderdijk 77 Oude Meer Noord-Holland 1438 AT",
    "addr:housenumber":"77",
    "addr:postcode":"meer;1438",
    "addr:street":"Aalsmeerderdijk",
    "iso:country":"NL",
    "sg:address":"Aalsmeerderdijk 77",
    "sg:city":"Oude Meer",
    "sg:orig_category":"Overheidsdiensten",
    "sg:phone":"+31 20 657 0036",
    "sg:postcode":"1438 AT",
    "sg:province":"Noord-Holland",
    "wof:name":"Het Dijkhuis",
    "wof:placetype":"venue"
},
  "geometry": {"coordinates":[-98.5797958374,34.7818336487],"type":"Point"}
}