{
  "type": "Feature",
  "properties": {
    "addr:full":"Haven Noordzijde 25 Almelo NL.08 7607 ER",
    "addr:housenumber":"25;nl.08",
    "addr:postcode":"7607 er",
    "addr:street":"Haven Noordzijde",
    "iso:country":"NL",
    "sg:address":"Haven Noordzijde 25",
    "sg:city":"Almelo",
    "sg:orig_category":"Werving And Selectie Van Tijdelijk Personeel And Uitzendkantoren",
    "sg:phone":"+31 546 821 505",
    "sg:postcode":"7607 ER",
    "sg:province":"NL.08",
    "wof:name":"Manpower Uitzendorganisatie Bv",
    "wof:placetype":"venue"
},
  "geometry": {"coordinates":[6.6600279808,52.3577384949],"type":"Point"}
}