{
  "type": "Feature",
  "properties": {
    "iso:country":"NL",
    "sg:address":"Huizerstraatweg 117",
    "sg:city":"Naarden",
    "sg:orig_category":"Farmaceutische Producten Gh",
    "sg:phone":"+31 35 699 3300",
    "sg:postcode":"1411 GM",
    "sg:province":"Noord-Holland",
    "wof:name":"Fort Dodge Animal Health Benelux Bv",
    "wof:placetype":"venue"
},
  "geometry": {"coordinates":[5.186438,52.292683],"type":"Point"}
}