{
  "type": "Feature",
  "properties": {
    "addr:full":"Boslaan 1 Vlieland Provincie Friesland 8899 BM",
    "addr:housenumber":"1",
    "addr:postcode":"8899 bm",
    "addr:street":"Boslaan;Friesland",
    "iso:country":"NL",
    "sg:address":"Boslaan 1",
    "sg:city":"Vlieland",
    "sg:orig_category":"Begrafenisondernemers",
    "sg:phone":"+31 562 451 735",
    "sg:postcode":"8899 BM",
    "sg:province":"Provincie Friesland",
    "wof:name":"Begrafenisvereniging Vlieland",
    "wof:placetype":"venue"
},
  "geometry": {"coordinates":[5.075044,53.297729],"type":"Point"}
}