{
  "type": "Feature",
  "properties": {
    "iso:country":"NL",
    "sg:address":"De Beverspyken 4B",
    "sg:city":"S Hertogenbosch",
    "sg:classifiers":[
        {
            "category":"Building & Trades",
            "subcategory":"Electrical",
            "type":"Services"
        }
    ],
    "sg:phone":"+31 73 633 0440",
    "sg:postcode":"5221 ED",
    "sg:province":"North Brabant",
    "sg:tags":[
        "distributor"
    ],
    "wof:name":"Spek, Nic Van Der",
    "wof:placetype":"venue"
},
  "geometry": {"coordinates":[5.262494,51.712105],"type":"Point"}
}