{
  "type": "Feature",
  "properties": {
    "addr:full":"Groesbeeksewg 9 Mook Limburg 6585 KE",
    "addr:housenumber":"9",
    "addr:postcode":"6585 ke",
    "addr:street":"Groesbeeksewg",
    "iso:country":"NL",
    "sg:address":"Groesbeeksewg 9",
    "sg:city":"Mook",
    "sg:orig_category":"Verzekeringen - Verzekeringskantoren",
    "sg:phone":"+31 24 397 3837",
    "sg:postcode":"6585 KE",
    "sg:province":"Limburg",
    "wof:name":"Eskes & Partners Bv",
    "wof:placetype":"venue"
},
  "geometry": {"coordinates":[5.88325,51.752285],"type":"Point"}
}