{
  "type": "Feature",
  "properties": {
    "addr:full":"Weverstraat 11 Uden North Brabant 5405 BM",
    "addr:housenumber":"11",
    "addr:postcode":"5405 bm",
    "addr:street":"Weverstraat",
    "iso:country":"NL",
    "sg:address":"Weverstraat 11",
    "sg:city":"Uden",
    "sg:orig_category":"Babyartikelen Detailhandel",
    "sg:phone":"+31 413 330 753",
    "sg:postcode":"5405 BM",
    "sg:province":"North Brabant",
    "wof:name":"Marimex",
    "wof:placetype":"venue"
},
  "geometry": {"coordinates":[5.650655,51.655285],"type":"Point"}
}