{
  "type": "Feature",
  "properties": {
    "iso:country":"NL",
    "sg:address":"Kerkstraat 95",
    "sg:city":"Wognum",
    "sg:orig_category":"Wegen And Sportterreinen",
    "sg:phone":"+31 229 571 227",
    "sg:postcode":"1687 AN",
    "sg:province":"North Holland",
    "wof:name":"Roemer Aanneming Bv",
    "wof:placetype":"venue"
},
  "geometry": {"coordinates":[5.0186948776,52.6869812012],"type":"Point"}
}