{
  "type": "Feature",
  "properties": {
    "addr:full":"Ruwekampwg 1 S Hertogenbosch North Brabant 5222 AT",
    "addr:housenumber":"1",
    "addr:postcode":"5222",
    "addr:street":"Ruwekampwg",
    "iso:country":"NL",
    "sg:address":"Ruwekampwg 1",
    "sg:city":"S Hertogenbosch",
    "sg:orig_category":"Levensmiddelen - Fabrieken En Groothandel",
    "sg:phone":"+31 73 621 2125",
    "sg:postcode":"5222 AT",
    "sg:province":"North Brabant",
    "wof:name":"Sligro Bv",
    "wof:placetype":"venue"
},
  "geometry": {"coordinates":[5.265084,51.706673],"type":"Point"}
}