{
  "type": "Feature",
  "properties": {
    "iso:country":"NL",
    "sg:address":"Noordsingel 128",
    "sg:city":"Rotterdam",
    "sg:orig_category":"Advocaten And Juridische Adviseurs",
    "sg:phone":"+31 10 465 4555",
    "sg:postcode":"3032 BJ",
    "sg:province":"Zuid-Holland",
    "wof:name":"Advocatenkantoor Frankhuijzen",
    "wof:placetype":"venue"
},
  "geometry": {"coordinates":[4.47655,51.930939],"type":"Point"}
}