{
  "type": "Feature",
  "properties": {
    "addr:full":"Stationstr 10 Alphen Nb North Brabant 5131 BN",
    "addr:housenumber":"10;nb",
    "addr:postcode":"5131 bn",
    "addr:street":"Stationstr",
    "iso:country":"NL",
    "sg:address":"Stationstr 10",
    "sg:city":"Alphen Nb",
    "sg:orig_category":"Accountants - Administratie- Consulenten En -Kantoren",
    "sg:phone":"+31 13 508 2535",
    "sg:postcode":"5131 BN",
    "sg:province":"North Brabant",
    "wof:name":"Abab",
    "wof:placetype":"venue"
},
  "geometry": {"coordinates":[4.956239,51.481499],"type":"Point"}
}