{
  "type": "Feature",
  "properties": {
    "addr:full":"Felland 9 Haren Gn Groningen 9753 TA",
    "addr:housenumber":"9",
    "addr:postcode":"9753 ta",
    "addr:street":"Felland",
    "iso:country":"NL",
    "sg:address":"Felland 9",
    "sg:city":"Haren Gn",
    "sg:orig_category":"Aannemers Woningbouw",
    "sg:phone":"+31 50 534 0243",
    "sg:postcode":"9753 TA",
    "sg:province":"Groningen",
    "wof:name":"Lammert Vrieling",
    "wof:placetype":"venue"
},
  "geometry": {"coordinates":[6.625037,53.164795],"type":"Point"}
}