{
  "type": "Feature",
  "properties": {
    "addr:full":"Zuidpln Hg 439 Rotterdam Zuid-Holland 3083 BE",
    "addr:housenumber":"439",
    "addr:postcode":"3083",
    "addr:street":"Hg",
    "iso:country":"NL",
    "sg:address":"Zuidpln Hg 439",
    "sg:city":"Rotterdam",
    "sg:orig_category":"Sportschoenen - Winkels",
    "sg:phone":"+31 10 293 7797",
    "sg:postcode":"3083 BE",
    "sg:province":"Zuid-Holland",
    "wof:name":"Aktiesport",
    "wof:placetype":"venue"
},
  "geometry": {"coordinates":[-73.97154999999999,42.786839],"type":"Point"}
}