{
  "type": "Feature",
  "properties": {
    "addr:full":"Mient 2A Capelle Ad Yssel Zuid-Holland 2903 LC",
    "addr:housenumber":"2a",
    "addr:postcode":"2903 lc",
    "addr:street":"Mient",
    "iso:country":"NL",
    "sg:address":"Mient 2A",
    "sg:city":"Capelle Ad Yssel",
    "sg:orig_category":"Veiligheidsuitrusting En -Kleding",
    "sg:phone":"+31 10 451 7493",
    "sg:postcode":"2903 LC",
    "sg:province":"Zuid-Holland",
    "wof:name":"Insapoint",
    "wof:placetype":"venue"
},
  "geometry": {"coordinates":[4.587853,51.922974],"type":"Point"}
}