{
  "type": "Feature",
  "properties": {
    "addr:full":"Burgemeester Mulderstr 1 Venlo Limburg 5913 AV",
    "addr:housenumber":"1",
    "addr:postcode":"5913 av",
    "addr:street":"Burgemeester Mulderstr",
    "iso:country":"NL",
    "sg:address":"Burgemeester Mulderstr 1",
    "sg:city":"Venlo",
    "sg:orig_category":"Verlichting And Huishoudartikelen",
    "sg:phone":"+31 77 351 8612",
    "sg:postcode":"5913 AV",
    "sg:province":"Limburg",
    "wof:name":"Bsf Wilkens Bv",
    "wof:placetype":"venue"
},
  "geometry": {"coordinates":[6.179476,51.370708],"type":"Point"}
}