{
  "type": "Feature",
  "properties": {
    "iso:country":"NL",
    "sg:address":"Burgemeester Mulderstr 1",
    "sg:city":"Venlo",
    "sg:orig_category":"Verlichting And Huishoudartikelen",
    "sg:phone":"+31 77 351 8612",
    "sg:postcode":"5913 AV",
    "sg:province":"Limburg",
    "wof:name":"Bsf Wilkens Bv",
    "wof:placetype":"venue"
},
  "geometry": {"coordinates":[6.179476,51.370708],"type":"Point"}
}