{
  "type": "Feature",
  "properties": {
    "addr:full":"Stationswg 53 Ede Gld Gelderland 6711 PK",
    "addr:housenumber":"53",
    "addr:postcode":"6711 pk",
    "addr:street":"Stationswg;Gld Gelderland",
    "iso:country":"NL",
    "sg:address":"Stationswg 53",
    "sg:city":"Ede Gld",
    "sg:orig_category":"Waterbehandeling En Waterzuiverings- Systemen",
    "sg:phone":"+31 318 613 227",
    "sg:postcode":"6711 PK",
    "sg:province":"Gelderland",
    "wof:name":"Edoch Bv",
    "wof:placetype":"venue"
},
  "geometry": {"coordinates":[5.6690502167,52.0376472473],"type":"Point"}
}