{
  "type": "Feature",
  "properties": {
    "addr:full":"Vd Giessenwg 53 Krimpen Ad Yssel Zuid-Holland 2921 LP",
    "addr:housenumber":"53",
    "addr:postcode":"2921 lp",
    "iso:country":"NL",
    "sg:address":"Vd Giessenwg 53",
    "sg:city":"Krimpen Ad Yssel",
    "sg:orig_category":"Metaalbewerking",
    "sg:phone":"+31 180 510 992",
    "sg:postcode":"2921 LP",
    "sg:province":"Zuid-Holland",
    "wof:name":"Albucom",
    "wof:placetype":"venue"
},
  "geometry": {"coordinates":[4.5731,51.909908],"type":"Point"}
}