{
  "type": "Feature",
  "properties": {
    "addr:full":"Klokkenplas 11 Enschede Overijssel 7511 NV",
    "addr:housenumber":"11",
    "addr:postcode":"7511 nv",
    "addr:street":"Klokkenplas",
    "iso:country":"NL",
    "sg:address":"Klokkenplas 11",
    "sg:city":"Enschede",
    "sg:orig_category":"Adviesbureaus Bedrijfsorganisatie",
    "sg:phone":"+31 53 436 4225",
    "sg:postcode":"7511 NV",
    "sg:province":"Overijssel",
    "sg:website":"http://www.extreme-consultancy.com",
    "wof:name":"Extreme",
    "wof:placetype":"venue"
},
  "geometry": {"coordinates":[6.89668,52.220013],"type":"Point"}
}