{
  "type": "Feature",
  "properties": {
    "addr:full":"Siersteenln 397 Groningen Groningen 9745 DX",
    "addr:housenumber":"397",
    "addr:postcode":"9745 dx",
    "iso:country":"NL",
    "sg:address":"Siersteenln 397",
    "sg:city":"Groningen",
    "sg:orig_category":"Keukens",
    "sg:phone":"+31 6 53432234",
    "sg:postcode":"9745 DX",
    "sg:province":"Groningen",
    "sg:website":"http://www.pasklaarkeukens.nl",
    "wof:name":"Pasklaar",
    "wof:placetype":"venue"
},
  "geometry": {"coordinates":[6.50229,53.21357],"type":"Point"}
}