{
  "type": "Feature",
  "properties": {
    "addr:full":"F V Eedenstr 1 Utrecht Utrecht 3532 CL",
    "addr:housenumber":"1",
    "addr:postcode":"3532",
    "addr:street":"Eedenstr",
    "iso:country":"NL",
    "sg:address":"F V Eedenstr 1",
    "sg:city":"Utrecht",
    "sg:orig_category":"Verenigingen En Stichtingen",
    "sg:phone":"+31 30 296 0407",
    "sg:postcode":"3532 CL",
    "sg:province":"Utrecht",
    "wof:name":"Lectorium Rosicrucianum",
    "wof:placetype":"venue"
},
  "geometry": {"coordinates":[5.09129,52.095211],"type":"Point"}
}