{
  "type": "Feature",
  "properties": {
    "addr:full":"Oostpln 5 Roosendaal North Brabant 4706 NL",
    "addr:housenumber":"5",
    "addr:postcode":"4706 nl",
    "addr:street":"Oostpln",
    "iso:country":"NL",
    "sg:address":"Oostpln 5",
    "sg:city":"Roosendaal",
    "sg:orig_category":"Woninginrichting",
    "sg:phone":"+31 165 533 034",
    "sg:postcode":"4706 NL",
    "sg:province":"North Brabant",
    "wof:name":"Leen Bakker",
    "wof:placetype":"venue"
},
  "geometry": {"coordinates":[4.4861412048,51.5369491577],"type":"Point"}
}