{
  "type": "Feature",
  "properties": {
    "addr:full":"Turbinestraat 7 Veenendaal Utrecht 3903 LV",
    "addr:housenumber":"7",
    "addr:postcode":"3903",
    "addr:street":"Turbinestraat",
    "iso:country":"NL",
    "sg:address":"Turbinestraat 7",
    "sg:city":"Veenendaal",
    "sg:orig_category":"Beveiligingsdiensten And Bewakingsbedrijven",
    "sg:phone":"+31 318 555 222",
    "sg:postcode":"3903 LV",
    "sg:province":"Utrecht",
    "wof:name":"Schipper",
    "wof:placetype":"venue"
},
  "geometry": {"coordinates":[5.569655,52.007126],"type":"Point"}
}