{
  "type": "Feature",
  "properties": {
    "addr:full":"Weverstr 9A Krommenie Noord-Holland 1561 EE",
    "addr:housenumber":"9a",
    "addr:postcode":"1561 ee",
    "addr:street":"Weverstr",
    "iso:country":"NL",
    "sg:address":"Weverstr 9A",
    "sg:city":"Krommenie",
    "sg:orig_category":"Accountants - Administratie- Consulenten En -Kantoren",
    "sg:phone":"+31 75 628 7474",
    "sg:postcode":"1561 EE",
    "sg:province":"Noord-Holland",
    "wof:name":"Huisman, A T",
    "wof:placetype":"venue"
},
  "geometry": {"coordinates":[4.765312,52.499866],"type":"Point"}
}