{
  "type": "Feature",
  "properties": {
    "addr:full":"Kleine Drift 65 Hilversum Noord-Holland 1221 JZ",
    "addr:housenumber":"65",
    "addr:postcode":"1221 jz",
    "addr:street":"Kleine Drift",
    "iso:country":"NL",
    "sg:address":"Kleine Drift 65",
    "sg:city":"Hilversum",
    "sg:orig_category":"Huishoudapparatuur, Televisies And Radio'S",
    "sg:phone":"+31 35 685 8635",
    "sg:postcode":"1221 JZ",
    "sg:province":"Noord-Holland",
    "wof:name":"Veldmeijer Audio Video",
    "wof:placetype":"venue"
},
  "geometry": {"coordinates":[5.189346,52.225876],"type":"Point"}
}