{
  "type": "Feature",
  "properties": {
    "addr:full":"Strausslaan 2 Bilthoven Utrecht 3723 JN",
    "addr:housenumber":"2",
    "addr:postcode":"3723 jn",
    "addr:street":"Strausslaan",
    "iso:country":"NL",
    "sg:address":"Strausslaan 2",
    "sg:city":"Bilthoven",
    "sg:orig_category":"Bedrijfs- And Managementsconsultants",
    "sg:phone":"+31 30 225 1300",
    "sg:postcode":"3723 JN",
    "sg:province":"Utrecht",
    "wof:name":"Ter Meulen Advies",
    "wof:placetype":"venue"
},
  "geometry": {"coordinates":[5.205415,52.13023],"type":"Point"}
}