{
  "type": "Feature",
  "properties": {
    "iso:country":"NL",
    "sg:address":"Theresiahof 1",
    "sg:city":"Hilversum",
    "sg:orig_category":"Adviesbureaus Bouwkunde",
    "sg:phone":"+31 35 622 1835",
    "sg:postcode":"1216 MH",
    "sg:province":"Noord-Holland",
    "wof:name":"Konvorm",
    "wof:placetype":"venue"
},
  "geometry": {"coordinates":[5.136698,52.219612],"type":"Point"}
}