{
  "type": "Feature",
  "properties": {
    "addr:full":"Theresiahof 1 Hilversum Noord-Holland 1216 MH",
    "addr:housenumber":"1",
    "addr:postcode":"1216 mh",
    "addr:street":"Theresiahof",
    "iso:country":"NL",
    "sg:address":"Theresiahof 1",
    "sg:city":"Hilversum",
    "sg:orig_category":"Adviesbureaus Bouwkunde",
    "sg:phone":"+31 35 622 1835",
    "sg:postcode":"1216 MH",
    "sg:province":"Noord-Holland",
    "wof:name":"Konvorm",
    "wof:placetype":"venue"
},
  "geometry": {"coordinates":[5.136698,52.219612],"type":"Point"}
}