{
  "type": "Feature",
  "properties": {
    "addr:full":"Nieuwe Langendijk 1A Delft Zuid-Holland 2611 VG",
    "addr:housenumber":"1a",
    "addr:postcode":"2611 vg",
    "addr:street":"Nieuwe Langendijk",
    "iso:country":"NL",
    "sg:address":"Nieuwe Langendijk 1A",
    "sg:city":"Delft",
    "sg:classifiers":[
        {
            "category":"Fast Food",
            "type":"Food & Drink"
        }
    ],
    "sg:phone":"+31 15 213 7726",
    "sg:postcode":"2611 VG",
    "sg:province":"Zuid-Holland",
    "sg:tags":[
        "afhaal",
        "restaurant"
    ],
    "wof:name":"Brasserie Robbedoez",
    "wof:placetype":"venue"
},
  "geometry": {"coordinates":[4.362601,52.012547],"type":"Point"}
}