{
  "type": "Feature",
  "properties": {
    "iso:country":"NL",
    "sg:address":"Clematisstraat 8",
    "sg:city":"Wezep",
    "sg:orig_category":"Banken And Kredietinstellingen",
    "sg:phone":"+31 38 376 1615",
    "sg:postcode":"8091 VK",
    "sg:province":"Gelderland",
    "wof:name":"Internationale Nederlanden Bank",
    "wof:placetype":"venue"
},
  "geometry": {"coordinates":[5.998157,52.462765],"type":"Point"}
}