{
  "type": "Feature",
  "properties": {
    "addr:full":"Nieuwstr 51 Zwolle NL.08 8011 TM",
    "addr:housenumber":"51",
    "addr:postcode":"8011 tm",
    "addr:street":"Nieuwstr",
    "iso:country":"NL",
    "sg:address":"Nieuwstr 51",
    "sg:city":"Zwolle",
    "sg:orig_category":"Verzekeringen - Verzekeringskantoren",
    "sg:phone":"+31 38 421 8784",
    "sg:postcode":"8011 TM",
    "sg:province":"NL.08",
    "sg:website":"http://www.vendopolis.nl",
    "wof:name":"Vendopolis Bv",
    "wof:placetype":"venue"
},
  "geometry": {"coordinates":[6.088738,52.512566],"type":"Point"}
}