{
  "type": "Feature",
  "properties": {
    "addr:full":"Willemsplein 11 Gouda Zuid-Holland 2807 PA",
    "addr:housenumber":"11",
    "addr:postcode":"2807 pa",
    "addr:street":"Willemsplein",
    "iso:country":"NL",
    "sg:address":"Willemsplein 11",
    "sg:city":"Gouda",
    "sg:orig_category":"Medische And Orthopedische Artikelen",
    "sg:phone":"+31 182 510 330",
    "sg:postcode":"2807 PA",
    "sg:province":"Zuid-Holland",
    "wof:name":"Woonvorm Gouda",
    "wof:placetype":"venue"
},
  "geometry": {"coordinates":[4.741991,52.014496],"type":"Point"}
}