{
  "type": "Feature",
  "properties": {
    "addr:full":"Hermelijnlaan 4 Waalre Noord-Brabant 5581 CJ",
    "addr:housenumber":"4",
    "addr:postcode":"5581 cj",
    "addr:street":"Hermelijnlaan",
    "iso:country":"NL",
    "sg:address":"Hermelijnlaan 4",
    "sg:city":"Waalre",
    "sg:orig_category":"Metaalwerken",
    "sg:phone":"+31 40 221 2911",
    "sg:postcode":"5581 CJ",
    "sg:province":"Noord-Brabant",
    "wof:name":"Hendriks Zonwering",
    "wof:placetype":"venue"
},
  "geometry": {"coordinates":[5.44678,51.391006],"type":"Point"}
}