{
  "type": "Feature",
  "properties": {
    "iso:country":"NL",
    "sg:address":"Voltastr 4",
    "sg:city":"Doetinchem",
    "sg:orig_category":"Autopoetsbedrijven",
    "sg:phone":"+31 314 378 400",
    "sg:postcode":"7006 RV",
    "sg:province":"Gelderland",
    "wof:name":"Betam Car Cleaning",
    "wof:placetype":"venue"
},
  "geometry": {"coordinates":[6.26021,51.970333],"type":"Point"}
}