{
  "type": "Feature",
  "properties": {
    "iso:country":"NL",
    "sg:address":"Nijverheidsweg 16",
    "sg:city":"Huizen",
    "sg:orig_category":"Meubels And Huishoudapparatuur Gh",
    "sg:phone":"+31 35 525 0024",
    "sg:postcode":"1271 EA",
    "sg:province":"North Holland",
    "wof:name":"Industrie & Handelmij Riviera Bv",
    "wof:placetype":"venue"
},
  "geometry": {"coordinates":[5.244279,52.302296],"type":"Point"}
}