{
  "type": "Feature",
  "properties": {
    "addr:full":"W.A. Scholtenstraat 30 A Assen Drenthe 9403  A",
    "addr:housenumber":"30 a;9403 a",
    "addr:street":"W.A. Scholtenstraat",
    "iso:country":"NL",
    "sg:address":"W.A. Scholtenstraat 30 A",
    "sg:city":"Assen",
    "sg:orig_category":"Verhuur Audiovisuele Apparatuur",
    "sg:phone":"+31 592 398 306",
    "sg:postcode":"9403  A",
    "sg:province":"Drenthe",
    "wof:name":"Rd & Rd Av Support",
    "wof:placetype":"venue"
},
  "geometry": {"coordinates":[6.574435,53.00758],"type":"Point"}
}