{
  "type": "Feature",
  "properties": {
    "addr:full":"Witte Paal 129 Schagen North Holland 1742 NX",
    "addr:housenumber":"129",
    "addr:postcode":"1742 nx",
    "addr:street":"Witte Paal",
    "iso:country":"NL",
    "sg:address":"Witte Paal 129",
    "sg:city":"Schagen",
    "sg:orig_category":"Gespecialiseerde Bouw",
    "sg:phone":"+31 224 213 941",
    "sg:postcode":"1742 NX",
    "sg:province":"North Holland",
    "wof:name":"Admiraal Kunst Smederij",
    "wof:placetype":"venue"
},
  "geometry": {"coordinates":[4.810396,52.777954],"type":"Point"}
}