{
  "type": "Feature",
  "properties": {
    "addr:full":"Torenstraat 11 Sambeek Noord-Brabant 5836 AJ",
    "addr:housenumber":"11",
    "addr:postcode":"5836 aj",
    "addr:street":"Torenstraat",
    "iso:country":"NL",
    "sg:address":"Torenstraat 11",
    "sg:city":"Sambeek",
    "sg:orig_category":"Autokeuringen",
    "sg:phone":"+31 485 571 428",
    "sg:postcode":"5836 AJ",
    "sg:province":"Noord-Brabant",
    "wof:name":"Vof Gebroeders Fransen",
    "wof:placetype":"venue"
},
  "geometry": {"coordinates":[5.961313,51.63966],"type":"Point"}
}