{
  "type": "Feature",
  "properties": {
    "addr:full":"Hietkamp 71 Rotterdam Zuid-Holland 3085 GA",
    "addr:housenumber":"71",
    "addr:postcode":"3085 ga",
    "addr:street":"Hietkamp",
    "iso:country":"NL",
    "sg:address":"Hietkamp 71",
    "sg:city":"Rotterdam",
    "sg:orig_category":"Drukkerijen",
    "sg:phone":"+31 10 481 7880",
    "sg:postcode":"3085 GA",
    "sg:province":"Zuid-Holland",
    "wof:name":"Matbaa Vof",
    "wof:placetype":"venue"
},
  "geometry": {"coordinates":[4.488765,51.873821],"type":"Point"}
}