{
  "type": "Feature",
  "properties": {
    "iso:country":"NL",
    "sg:address":"Ospelsewg 17",
    "sg:city":"Nederweert",
    "sg:orig_category":"Architecten En Architectenbureaus",
    "sg:phone":"+31 495 460 198",
    "sg:postcode":"6031 AK",
    "sg:province":"Limburg",
    "wof:name":"Truijen, A J F",
    "wof:placetype":"venue"
},
  "geometry": {"coordinates":[5.758074,51.284634],"type":"Point"}
}