{
  "type": "Feature",
  "properties": {
    "addr:full":"Voorwg 22 Noorden California 2431 AP",
    "addr:housenumber":"22",
    "addr:postcode":"2431 ap",
    "addr:street":"Voorwg",
    "iso:country":"NL",
    "sg:address":"Voorwg 22",
    "sg:city":"Noorden",
    "sg:orig_category":"Beeldende Kunstenaars",
    "sg:phone":"+31 172 408 376",
    "sg:postcode":"2431 AP",
    "sg:province":"California",
    "wof:name":"Johns-Thomas, M J",
    "wof:placetype":"venue"
},
  "geometry": {"coordinates":[-120.36385300000001,39.320374],"type":"Point"}
}