{
  "type": "Feature",
  "properties": {
    "iso:country":"NL",
    "sg:address":"Tussen De Bogen 41",
    "sg:city":"Amsterdam",
    "sg:orig_category":"Kunstenaars- Benodigdheden",
    "sg:phone":"+31 20 427 8530",
    "sg:postcode":"1013 JB",
    "sg:province":"Noord-Holland",
    "sg:website":"http://www.beeldhouwwinkel.nl",
    "wof:name":"Beeldhouwwinkel, De",
    "wof:placetype":"venue"
},
  "geometry": {"coordinates":[4.886909,52.383953],"type":"Point"}
}