{
  "type": "Feature",
  "properties": {
    "iso:country":"NL",
    "sg:address":"Perikweg 44",
    "sg:city":"Enschede",
    "sg:orig_category":"Glaszetten",
    "sg:phone":"+31 53 430 3368",
    "sg:postcode":"7512 DR",
    "sg:province":"NL.08",
    "wof:name":"Ter Horst Glas",
    "wof:placetype":"venue"
},
  "geometry": {"coordinates":[6.899319,52.213467],"type":"Point"}
}