{
  "type": "Feature",
  "properties": {
    "addr:full":"Invaltij 1 Noordwijk Zh Zuid-Holland 2201 WN",
    "addr:housenumber":"1",
    "addr:postcode":"2201 wn",
    "addr:street":"Invaltij",
    "iso:country":"NL",
    "sg:address":"Invaltij 1",
    "sg:city":"Noordwijk Zh",
    "sg:orig_category":"Bloemen And Planten Gh",
    "sg:phone":"+31 71 362 0620",
    "sg:postcode":"2201 WN",
    "sg:province":"Zuid-Holland",
    "wof:name":"Jan Van Der Linden Bloemenexport",
    "wof:placetype":"venue"
},
  "geometry": {"coordinates":[4.438922,52.228481],"type":"Point"}
}