{
  "type": "Feature",
  "properties": {
    "addr:full":"Voorstr 98 Katwyk Zh South Holland 2225 ET",
    "addr:housenumber":"98;zh",
    "addr:postcode":"2225 et",
    "addr:street":"Voorstr",
    "iso:country":"NL",
    "sg:address":"Voorstr 98",
    "sg:city":"Katwyk Zh",
    "sg:orig_category":"Kappers",
    "sg:phone":"+31 71 407 9797",
    "sg:postcode":"2225 ET",
    "sg:province":"South Holland",
    "wof:name":"Hem & Haar",
    "wof:placetype":"venue"
},
  "geometry": {"coordinates":[4.3965849876,52.2051086426],"type":"Point"}
}