{
  "type": "Feature",
  "properties": {
    "addr:full":"V Dongenln 8 Musselkanaal Groningen 9581 LL",
    "addr:housenumber":"8",
    "addr:postcode":"9581 ll",
    "addr:street":"V Dongenln",
    "iso:country":"NL",
    "sg:address":"V Dongenln 8",
    "sg:city":"Musselkanaal",
    "sg:orig_category":"Bedrijfskleding",
    "sg:phone":"+31 599 417 373",
    "sg:postcode":"9581 LL",
    "sg:province":"Groningen",
    "wof:name":"Stabo",
    "wof:placetype":"venue"
},
  "geometry": {"coordinates":[7.017255,52.927021],"type":"Point"}
}