{
  "type": "Feature",
  "properties": {
    "iso:country":"NL",
    "sg:address":"Valkenburgsngl 19",
    "sg:city":"Rotterdam",
    "sg:orig_category":"Verpakkingsmachines",
    "sg:phone":"+31 10 479 3241",
    "sg:postcode":"3077 TG",
    "sg:province":"Zuid-Holland",
    "wof:name":"Wifa",
    "wof:placetype":"venue"
},
  "geometry": {"coordinates":[4.561868,51.89846],"type":"Point"}
}