{
  "type": "Feature",
  "properties": {
    "addr:full":"Voorstr 440 Dordrecht South Holland 3311 CX",
    "addr:housenumber":"440",
    "addr:postcode":"3311 cx",
    "iso:country":"NL",
    "sg:address":"Voorstr 440",
    "sg:city":"Dordrecht",
    "sg:orig_category":"Muziekinstrumenten En Bladmuziek",
    "sg:phone":"+31 78 635 0380",
    "sg:postcode":"3311 CX",
    "sg:province":"South Holland",
    "sg:website":"http://www.4street.nl",
    "wof:name":"4 Street",
    "wof:placetype":"venue"
},
  "geometry": {"coordinates":[4.661634,51.813541],"type":"Point"}
}