{
  "type": "Feature",
  "properties": {
    "iso:country":"NL",
    "sg:address":"Julianalaan 266",
    "sg:city":"Bilthoven",
    "sg:orig_category":"Hoger Onderwijs",
    "sg:phone":"+31 30 229 3382",
    "sg:postcode":"3722 GX",
    "sg:province":"Utrecht",
    "wof:name":"Agogische Praktijk A. De Feyter",
    "wof:placetype":"venue"
},
  "geometry": {"coordinates":[5.225995,52.132504],"type":"Point"}
}