{
  "type": "Feature",
  "properties": {
    "addr:full":"Lagedk 3 Ysselstein Ut Utrecht 3401 RE",
    "addr:housenumber":"3",
    "addr:postcode":"3401",
    "addr:street":"Lagedk",
    "iso:country":"NL",
    "sg:address":"Lagedk 3",
    "sg:city":"Ysselstein Ut",
    "sg:orig_category":"Autoschade- Herstelbedrijven",
    "sg:phone":"+31 30 686 8140",
    "sg:postcode":"3401 RE",
    "sg:province":"Utrecht",
    "wof:name":"Griend, Van De",
    "wof:placetype":"venue"
},
  "geometry": {"coordinates":[5.062155,51.998135],"type":"Point"}
}