{
  "type": "Feature",
  "properties": {
    "addr:full":"Erasmuswg 7A Cadzand Zeeland 4506 AA",
    "addr:housenumber":"7a",
    "addr:postcode":"4506 aa",
    "addr:street":"Erasmuswg",
    "iso:country":"NL",
    "sg:address":"Erasmuswg 7A",
    "sg:city":"Cadzand",
    "sg:orig_category":"Etalageverzorging",
    "sg:phone":"+31 117 391 262",
    "sg:postcode":"4506 AA",
    "sg:province":"Zeeland",
    "wof:name":"Vergouwe, B",
    "wof:placetype":"venue"
},
  "geometry": {"coordinates":[3.408101,51.36964],"type":"Point"}
}