{
  "type": "Feature",
  "properties": {
    "addr:full":"Kerkhofln 3 Lunteren Gelderland 6741 BN",
    "addr:housenumber":"3",
    "addr:postcode":"6741 bn",
    "addr:street":"Kerkhofln;Gelderland",
    "iso:country":"NL",
    "sg:address":"Kerkhofln 3",
    "sg:city":"Lunteren",
    "sg:orig_category":"Zuivel - Groothandel",
    "sg:phone":"+31 318 481 511",
    "sg:postcode":"6741 BN",
    "sg:province":"Gelderland",
    "wof:name":"Geurink",
    "wof:placetype":"venue"
},
  "geometry": {"coordinates":[5.618998,52.08688],"type":"Point"}
}