{
  "type": "Feature",
  "properties": {
    "iso:country":"NL",
    "sg:address":"Wibautstr 133",
    "sg:city":"Amsterdam",
    "sg:orig_category":"Autorijscholen",
    "sg:phone":"+31 20 663 3773",
    "sg:postcode":"1097 DN",
    "sg:province":"Noord-Holland",
    "sg:website":"http://www.nelen.nl",
    "wof:name":"Aaa Rijopleiding",
    "wof:placetype":"venue"
},
  "geometry": {"coordinates":[4.917591,52.349701],"type":"Point"}
}