{
  "type": "Feature",
  "properties": {
    "addr:full":"Vespuccistr 102 Amsterdam Noord-Holland 1056 SR",
    "addr:housenumber":"102",
    "addr:postcode":"1056 sr",
    "iso:country":"NL",
    "sg:address":"Vespuccistr 102",
    "sg:city":"Amsterdam",
    "sg:orig_category":"Bedrijfsopleidingen",
    "sg:phone":"+31 20 489 0749",
    "sg:postcode":"1056 SR",
    "sg:province":"Noord-Holland",
    "wof:name":"Svc",
    "wof:placetype":"venue"
},
  "geometry": {"coordinates":[4.853084,52.372368],"type":"Point"}
}