{
  "type": "Feature",
  "properties": {
    "iso:country":"NL",
    "sg:address":"Westerlanderwg 89",
    "sg:city":"Westerland",
    "sg:orig_category":"Bloemen En Planten - Groothandel",
    "sg:phone":"+31 227 593 481",
    "sg:postcode":"1778 KN",
    "sg:province":"Noord-Holland",
    "wof:name":"Bloementuin, De",
    "wof:placetype":"venue"
},
  "geometry": {"coordinates":[4.927404,52.891647],"type":"Point"}
}