{
  "type": "Feature",
  "properties": {
    "iso:country":"NL",
    "sg:address":"Wilhelminastraat 35D",
    "sg:city":"Breda",
    "sg:orig_category":"Public Relationbureaus",
    "sg:phone":"+31 76 520 9066",
    "sg:postcode":"4818 SC",
    "sg:province":"Noord-Brabant",
    "wof:name":"Drs J J A Hendrickx Communicatie",
    "wof:placetype":"venue"
},
  "geometry": {"coordinates":[4.778162,51.579506],"type":"Point"}
}