{
  "type": "Feature",
  "properties": {
    "iso:country":"NL",
    "sg:address":"F Verpoortenstr 3",
    "sg:city":"Spaarndam",
    "sg:orig_category":"Administratie- En Boekhoudkantoren",
    "sg:phone":"+31 23 538 5996",
    "sg:postcode":"2064 LX",
    "sg:province":"Noord-Holland",
    "wof:name":"Bms",
    "wof:placetype":"venue"
},
  "geometry": {"coordinates":[4.689417,52.412868],"type":"Point"}
}