{
  "type": "Feature",
  "properties": {
    "addr:full":"Pr Hendrikpln 27 Veendam Groningen 9641 GJ",
    "addr:housenumber":"27",
    "addr:postcode":"9641 gj",
    "addr:street":"Veendam",
    "iso:country":"NL",
    "sg:address":"Pr Hendrikpln 27",
    "sg:city":"Veendam",
    "sg:classifiers":[
        {
            "category":"Shopping",
            "subcategory":"News",
            "type":"Retail Goods"
        }
    ],
    "sg:phone":"+31 598 696 644",
    "sg:postcode":"9641 GJ",
    "sg:province":"Groningen",
    "sg:tags":[
        "maandbladen",
        "en",
        "week-"
    ],
    "wof:name":"Veendammer, De",
    "wof:placetype":"venue"
},
  "geometry": {"coordinates":[6.8717918396,53.1062316895],"type":"Point"}
}