{
  "type": "Feature",
  "properties": {
    "addr:full":"Antwerpsestrwg 345 Bergen Op Zoom North Brabant 4625 AA",
    "addr:housenumber":"345",
    "addr:postcode":"4625 aa",
    "iso:country":"NL",
    "sg:address":"Antwerpsestrwg 345",
    "sg:city":"Bergen Op Zoom",
    "sg:orig_category":"Goudsmeden En Zilversmeden",
    "sg:phone":"+31 164 236 920",
    "sg:postcode":"4625 AA",
    "sg:province":"North Brabant",
    "wof:name":"Giels Bv, Gebr Van",
    "wof:placetype":"venue"
},
  "geometry": {"coordinates":[4.30118,51.479382],"type":"Point"}
}