{
  "type": "Feature",
  "properties": {
    "addr:full":"Ryksstrwg 151 Haren Gn Groningen 9752 BD",
    "addr:housenumber":"151",
    "addr:postcode":"9752 bd",
    "iso:country":"NL",
    "sg:address":"Ryksstrwg 151",
    "sg:city":"Haren Gn",
    "sg:classifiers":[
        {
            "category":"Shopping",
            "subcategory":"Adult",
            "type":"Retail Goods"
        }
    ],
    "sg:phone":"+31 50 534 9761",
    "sg:postcode":"9752 BD",
    "sg:province":"Groningen",
    "sg:tags":[
        "lingerie",
        "en",
        "tricotage"
    ],
    "wof:name":"Smid",
    "wof:placetype":"venue"
},
  "geometry": {"coordinates":[6.60632,53.170658],"type":"Point"}
}