{
  "type": "Feature",
  "properties": {
    "addr:full":"Kouvenderstraat 69 Hoensbroek Limburg 6431 HB",
    "addr:housenumber":"69",
    "addr:postcode":"6431 hb",
    "addr:street":"Kouvenderstraat",
    "iso:country":"NL",
    "sg:address":"Kouvenderstraat 69",
    "sg:city":"Hoensbroek",
    "sg:orig_category":"Bloemen And Planten",
    "sg:phone":"+31 45 522 9710",
    "sg:postcode":"6431 HB",
    "sg:province":"Limburg",
    "wof:name":"Bloemsierkunst Mille Fleurs",
    "wof:placetype":"venue"
},
  "geometry": {"coordinates":[5.928692,50.92543],"type":"Point"}
}