{
  "type": "Feature",
  "properties": {
    "iso:country":"NL",
    "sg:address":"Onderstestraat 44",
    "sg:city":"Valkenburg Lb",
    "sg:orig_category":"Slagerijen",
    "sg:phone":"+31 43 604 0352",
    "sg:postcode":"6301 KB",
    "sg:province":"Limburg",
    "wof:name":"Slagerij Jean Dreessen",
    "wof:placetype":"venue"
},
  "geometry": {"coordinates":[5.79451,50.871101],"type":"Point"}
}