{
  "type": "Feature",
  "properties": {
    "addr:full":"Groningerstr 8 Rotterdam Zuid-Holland 3074 RX",
    "addr:housenumber":"8",
    "addr:postcode":"3074 rx",
    "addr:street":"Groningerstr",
    "iso:country":"NL",
    "sg:address":"Groningerstr 8",
    "sg:city":"Rotterdam",
    "sg:orig_category":"Verenigingen En Stichtingen",
    "sg:phone":"+31 10 419 4217",
    "sg:postcode":"3074 RX",
    "sg:province":"Zuid-Holland",
    "wof:name":"Omij, Sticht",
    "wof:placetype":"venue"
},
  "geometry": {"coordinates":[4.511522,51.896996],"type":"Point"}
}