{
  "type": "Feature",
  "properties": {
    "addr:full":"Pijnackerplein 46 Rotterdam South Holland 3035 GG",
    "addr:housenumber":"46",
    "addr:postcode":"3035 gg",
    "addr:street":"Pijnackerplein",
    "iso:country":"NL",
    "sg:address":"Pijnackerplein 46",
    "sg:city":"Rotterdam",
    "sg:orig_category":"Boekhouders",
    "sg:phone":"+31 10 465 7847",
    "sg:postcode":"3035 GG",
    "sg:province":"South Holland",
    "wof:name":"Nieuwenhuis Administratiekantoor",
    "wof:placetype":"venue"
},
  "geometry": {"coordinates":[4.479421,51.934868],"type":"Point"}
}