{
  "type": "Feature",
  "properties": {
    "addr:full":"Kutersteenweg 12 Noorbeek Limburg 6255 PC",
    "addr:housenumber":"12",
    "addr:postcode":"6255 pc",
    "addr:street":"Kutersteenweg",
    "iso:country":"NL",
    "sg:address":"Kutersteenweg 12",
    "sg:city":"Noorbeek",
    "sg:orig_category":"Kampeerterreinen",
    "sg:phone":"+31 43 457 1376",
    "sg:postcode":"6255 PC",
    "sg:province":"Limburg",
    "wof:name":"Kampeerboerderij Terlinden",
    "wof:placetype":"venue"
},
  "geometry": {"coordinates":[5.8299808502,50.7813682556],"type":"Point"}
}