{
  "type": "Feature",
  "properties": {
    "addr:full":"Steenbankpad 4 Tollebeek Flevoland 8309 RB",
    "addr:housenumber":"4",
    "addr:postcode":"8309 rb",
    "addr:street":"Steenbankpad;Flevoland",
    "iso:country":"NL",
    "sg:address":"Steenbankpad 4",
    "sg:city":"Tollebeek",
    "sg:orig_category":"Bloemen En Planten - Decoratie",
    "sg:phone":"+31 527 271 624",
    "sg:postcode":"8309 RB",
    "sg:province":"Flevoland",
    "wof:name":"Korenbloem, De",
    "wof:placetype":"venue"
},
  "geometry": {"coordinates":[5.636457,52.695168],"type":"Point"}
}