{
  "type": "Feature",
  "properties": {
    "addr:full":"St Antoniesb Str 140 Amsterdam North Holland 1011 HB",
    "addr:housenumber":"140",
    "addr:postcode":"1011 hb",
    "addr:street":"Str",
    "iso:country":"NL",
    "sg:address":"St Antoniesb Str 140",
    "sg:city":"Amsterdam",
    "sg:orig_category":"Opticiens",
    "sg:phone":"+31 20 622 6718",
    "sg:postcode":"1011 HB",
    "sg:province":"North Holland",
    "wof:name":"Azijnman",
    "wof:placetype":"venue"
},
  "geometry": {"coordinates":[4.900703907,52.3697052002],"type":"Point"}
}