{
  "type": "Feature",
  "properties": {
    "iso:country":"NL",
    "sg:address":"Foareker 80",
    "sg:city":"Ureterp",
    "sg:orig_category":"Voegwerken",
    "sg:phone":"+31 512 302 855",
    "sg:postcode":"9247 AD",
    "sg:province":"Friesland",
    "wof:name":"Veen, H Van",
    "wof:placetype":"venue"
},
  "geometry": {"coordinates":[6.172151,53.097042],"type":"Point"}
}