{
  "type": "Feature",
  "properties": {
    "addr:full":"Watermanwg 341 Rotterdam Zuid-Holland 3067 GA",
    "addr:housenumber":"341",
    "addr:postcode":"3067 ga",
    "iso:country":"NL",
    "sg:address":"Watermanwg 341",
    "sg:city":"Rotterdam",
    "sg:orig_category":"Woninginrichting",
    "sg:phone":"+31 10 209 9788",
    "sg:postcode":"3067 GA",
    "sg:province":"Zuid-Holland",
    "wof:name":"Bibelot",
    "wof:placetype":"venue"
},
  "geometry": {"coordinates":[4.5568509102,51.9509391785],"type":"Point"}
}