{
  "type": "Feature",
  "properties": {
    "iso:country":"NL",
    "sg:address":"Hertogstraat 31",
    "sg:city":"Brunssum",
    "sg:orig_category":"Kappers",
    "sg:phone":"+31 45 525 2852",
    "sg:postcode":"6441 HA",
    "sg:province":"Limburg",
    "wof:name":"Kapsalon Ineke",
    "wof:placetype":"venue"
},
  "geometry": {"coordinates":[5.960006237,50.9463119507],"type":"Point"}
}