{
  "type": "Feature",
  "properties": {
    "addr:full":"J Evertsenstr 155 Amsterdam Noord-Holland 1057 BW",
    "addr:housenumber":"155",
    "addr:postcode":"1057 bw",
    "iso:country":"NL",
    "sg:address":"J Evertsenstr 155",
    "sg:city":"Amsterdam",
    "sg:orig_category":"Ontbijtservice",
    "sg:phone":"+31 20 447 0193",
    "sg:postcode":"1057 BW",
    "sg:province":"Noord-Holland",
    "wof:name":"Cupido",
    "wof:placetype":"venue"
},
  "geometry": {"coordinates":[4.84863,52.36961],"type":"Point"}
}