{
  "type": "Feature",
  "properties": {
    "addr:full":"T V Diessenstr 1 Goirle Noord-Brabant 5051 RJ",
    "addr:housenumber":"1",
    "addr:postcode":"5051 rj",
    "addr:street":"T;Diessenstr",
    "iso:country":"NL",
    "sg:address":"T V Diessenstr 1",
    "sg:city":"Goirle",
    "sg:orig_category":"Omroep",
    "sg:phone":"+31 13 534 1344",
    "sg:postcode":"5051 RJ",
    "sg:province":"Noord-Brabant",
    "sg:website":"http://www.lokaal.net/log",
    "wof:name":"Lok Omr Goirle",
    "wof:placetype":"venue"
},
  "geometry": {"coordinates":[5.067888,51.518623],"type":"Point"}
}