{
  "type": "Feature",
  "properties": {
    "addr:full":"Vughterstr 7 S Hertogenbosch Noord-Brabant 5211 EW",
    "addr:housenumber":"7",
    "addr:postcode":"5211 ew",
    "addr:street":"Vughterstr",
    "iso:country":"NL",
    "sg:address":"Vughterstr 7",
    "sg:city":"S Hertogenbosch",
    "sg:orig_category":"Verhuur",
    "sg:phone":"+31 73 613 1984",
    "sg:postcode":"5211 EW",
    "sg:province":"Noord-Brabant",
    "wof:name":"Skala",
    "wof:placetype":"venue"
},
  "geometry": {"coordinates":[5.301722,51.687771],"type":"Point"}
}