{
  "type": "Feature",
  "properties": {
    "addr:full":"Oranjeln 36 Waddinxveen Zuid-Holland 2741 ER",
    "addr:housenumber":"36",
    "addr:postcode":"2741 er",
    "addr:street":"Oranjeln",
    "iso:country":"NL",
    "sg:address":"Oranjeln 36",
    "sg:city":"Waddinxveen",
    "sg:orig_category":"Antiquiteiten",
    "sg:phone":"+31 182 612 849",
    "sg:postcode":"2741 ER",
    "sg:province":"Zuid-Holland",
    "wof:name":"Paradijsje, Het",
    "wof:placetype":"venue"
},
  "geometry": {"coordinates":[4.656921,52.044731],"type":"Point"}
}