{
  "type": "Feature",
  "properties": {
    "addr:full":"Van Veldekelaan 4 Haren Gn Groningen 9752 EL",
    "addr:housenumber":"4",
    "addr:postcode":"9752 el",
    "addr:street":"Van Veldekelaan",
    "iso:country":"NL",
    "sg:address":"Van Veldekelaan 4",
    "sg:city":"Haren Gn",
    "sg:orig_category":"Verzekeringen",
    "sg:phone":"+31 50 534 5269",
    "sg:postcode":"9752 EL",
    "sg:province":"Groningen",
    "wof:name":"Joh.Smits Assurantien",
    "wof:placetype":"venue"
},
  "geometry": {"coordinates":[6.59917,53.174694],"type":"Point"}
}