{
  "type": "Feature",
  "properties": {
    "addr:full":"De Beverspyken 20 S Hertogenbosch Noord-Brabant 5221 ED",
    "addr:housenumber":"20",
    "addr:postcode":"5221 ed",
    "addr:street":"S",
    "iso:country":"NL",
    "sg:address":"De Beverspyken 20",
    "sg:city":"S Hertogenbosch",
    "sg:orig_category":"Meubelen - Fabrieken En Groothandel",
    "sg:phone":"+31 73 633 9133",
    "sg:postcode":"5221 ED",
    "sg:province":"Noord-Brabant",
    "sg:website":"http://www.sdb-industries.nl",
    "wof:name":"Sdb Bv",
    "wof:placetype":"venue"
},
  "geometry": {"coordinates":[5.268157,51.713856],"type":"Point"}
}