{
  "type": "Feature",
  "properties": {
    "addr:full":"De Huesmolen 71 Hoorn Nh Noord-Holland 1625 HZ",
    "addr:housenumber":"71",
    "addr:postcode":"1625 hz",
    "addr:street":"De Huesmolen",
    "iso:country":"NL",
    "sg:address":"De Huesmolen 71",
    "sg:city":"Hoorn Nh",
    "sg:orig_category":"Opticiens",
    "sg:phone":"+31 229 235 165",
    "sg:postcode":"1625 HZ",
    "sg:province":"Noord-Holland",
    "wof:name":"Vof A. Ruttenberg & Zonen",
    "wof:placetype":"venue"
},
  "geometry": {"coordinates":[5.054060936,52.6580200195],"type":"Point"}
}