{
  "type": "Feature",
  "properties": {
    "addr:full":"Deilsedijk 60 Deil Obwalden 4158 CH",
    "addr:housenumber":"60",
    "addr:postcode":"4158",
    "addr:street":"Deilsedijk",
    "iso:country":"NL",
    "sg:address":"Deilsedijk 60",
    "sg:city":"Deil",
    "sg:orig_category":"Partycatering And -Organisatie",
    "sg:phone":"+31 345 652 152",
    "sg:postcode":"4158 CH",
    "sg:province":"Obwalden",
    "wof:name":"Melati Indonesische Party-Service",
    "wof:placetype":"venue"
},
  "geometry": {"coordinates":[8.22414,46.813091],"type":"Point"}
}