{
  "type": "Feature",
  "properties": {
    "addr:full":"Weststraat 72 Aardenburg Zeeland 4527 BV",
    "addr:housenumber":"72",
    "addr:postcode":"4527 bv",
    "addr:street":"Weststraat",
    "iso:country":"NL",
    "sg:address":"Weststraat 72",
    "sg:city":"Aardenburg",
    "sg:classifiers":[
        {
            "category":"Bakery",
            "type":"Food & Drink"
        }
    ],
    "sg:phone":"+31 117 491 523",
    "sg:postcode":"4527 BV",
    "sg:province":"Zeeland",
    "sg:tags":[
        "brood",
        "banket"
    ],
    "wof:name":"Vof Wijffels",
    "wof:placetype":"venue"
},
  "geometry": {"coordinates":[3.443509,51.274094],"type":"Point"}
}