{
  "type": "Feature",
  "properties": {
    "addr:full":"Prinses Beatrixstraat 36 Schoondijke Zeeland 4507 AL",
    "addr:housenumber":"36",
    "addr:postcode":"4507 al",
    "addr:street":"Prinses Beatrixstraat",
    "iso:country":"NL",
    "sg:address":"Prinses Beatrixstraat 36",
    "sg:city":"Schoondijke",
    "sg:orig_category":"Verhuur Voertuigen Behalve Auto'S",
    "sg:phone":"+31 117 401 770",
    "sg:postcode":"4507 AL",
    "sg:province":"Zeeland",
    "wof:name":"Ch.A. Van Den Bossche Aanhangwagenverhuu",
    "wof:placetype":"venue"
},
  "geometry": {"coordinates":[3.558235,51.354454],"type":"Point"}
}