{
  "type": "Feature",
  "properties": {
    "addr:full":"V Scherpenzeelwg 15 Mierlo Noord-Brabant 5731 EG",
    "addr:housenumber":"15",
    "addr:postcode":"5731 eg",
    "iso:country":"NL",
    "sg:address":"V Scherpenzeelwg 15",
    "sg:city":"Mierlo",
    "sg:orig_category":"Acupunctuur",
    "sg:phone":"+31 492 664 915",
    "sg:postcode":"5731 EG",
    "sg:province":"Noord-Brabant",
    "wof:name":"Plantema-De Bruin, M C M F",
    "wof:placetype":"venue"
},
  "geometry": {"coordinates":[5.619782,51.4436],"type":"Point"}
}