{
  "type": "Feature",
  "properties": {
    "addr:full":"Robertaland 13 'S Gravenhage Zuid-Holland 2591 HS",
    "addr:housenumber":"13",
    "addr:postcode":"2591 hs",
    "addr:street":"Robertaland;' S",
    "iso:country":"NL",
    "sg:address":"Robertaland 13",
    "sg:city":"'S Gravenhage",
    "sg:orig_category":"Artsen And Specialisten",
    "sg:phone":"+31 70 385 0850",
    "sg:postcode":"2591 HS",
    "sg:province":"Zuid-Holland",
    "wof:name":"C.T. Benningshof",
    "wof:placetype":"venue"
},
  "geometry": {"coordinates":[4.361598,52.097637],"type":"Point"}
}