{
  "type": "Feature",
  "properties": {
    "addr:full":"Aldringastr 15 Niekerk Grootegast Groningen 9822 AM",
    "addr:housenumber":"15",
    "addr:postcode":"9822",
    "addr:street":"Aldringastr",
    "iso:country":"NL",
    "sg:address":"Aldringastr 15",
    "sg:city":"Niekerk Grootegast",
    "sg:orig_category":"Bodemonderzoek",
    "sg:phone":"+31 594 548 410",
    "sg:postcode":"9822 AM",
    "sg:province":"Groningen",
    "wof:name":"Bouma",
    "wof:placetype":"venue"
},
  "geometry": {"coordinates":[6.353392,53.224419],"type":"Point"}
}