{
  "type": "Feature",
  "properties": {
    "addr:full":"Verl Fortln 50 Naarden North Holland 1412 CZ",
    "addr:housenumber":"50",
    "addr:postcode":"1412",
    "iso:country":"NL",
    "sg:address":"Verl Fortln 50",
    "sg:city":"Naarden",
    "sg:orig_category":"Fietsen En Bromfietsen",
    "sg:phone":"+31 35 694 4840",
    "sg:postcode":"1412 CZ",
    "sg:province":"North Holland",
    "sg:website":"http://www.fastfwd.nl",
    "wof:name":"Fastforward",
    "wof:placetype":"venue"
},
  "geometry": {"coordinates":[5.160918,52.28624],"type":"Point"}
}