{
  "type": "Feature",
  "properties": {
    "addr:full":"Ringallee 35 Velp Gld Gelderland 6881 MX",
    "addr:housenumber":"35",
    "addr:postcode":"6881 mx",
    "addr:street":"Ringallee;Gld Gelderland",
    "iso:country":"NL",
    "sg:address":"Ringallee 35",
    "sg:city":"Velp Gld",
    "sg:orig_category":"Adviesbureaus Marketing",
    "sg:phone":"+31 26 388 4748",
    "sg:postcode":"6881 MX",
    "sg:province":"Gelderland",
    "wof:name":"Make- It",
    "wof:placetype":"venue"
},
  "geometry": {"coordinates":[5.968404,52.001534],"type":"Point"}
}