{
  "type": "Feature",
  "properties": {
    "addr:full":"Mascherelstr 2 Wynandsrade Limburg 6363 AW",
    "addr:housenumber":"2",
    "addr:postcode":"6363 aw",
    "addr:street":"Mascherelstr",
    "iso:country":"NL",
    "sg:address":"Mascherelstr 2",
    "sg:city":"Wynandsrade",
    "sg:orig_category":"Verloskundigen",
    "sg:phone":"+31 45 524 4102",
    "sg:postcode":"6363 AW",
    "sg:province":"Limburg",
    "wof:name":"Greven-Van Zandvoort, D M H M",
    "wof:placetype":"venue"
},
  "geometry": {"coordinates":[5.884998,50.907532],"type":"Point"}
}