{
  "type": "Feature",
  "properties": {
    "addr:full":"Hogenoord 12 Utrecht Utrecht 3513 GX",
    "addr:housenumber":"12",
    "addr:postcode":"3513 gx",
    "addr:street":"Hogenoord",
    "iso:country":"NL",
    "sg:address":"Hogenoord 12",
    "sg:city":"Utrecht",
    "sg:orig_category":"Goudsmeden En Zilversmeden",
    "sg:phone":"+31 30 231 8505",
    "sg:postcode":"3513 GX",
    "sg:province":"Utrecht",
    "wof:name":"Kortenhorst, C M",
    "wof:placetype":"venue"
},
  "geometry": {"coordinates":[5.111055,52.10133],"type":"Point"}
}