{
  "type": "Feature",
  "properties": {
    "addr:full":"Hollewg 6 Herten Limburg 6049 GM",
    "addr:housenumber":"6",
    "addr:postcode":"6049 gm",
    "addr:street":"Hollewg",
    "iso:country":"NL",
    "sg:address":"Hollewg 6",
    "sg:city":"Herten",
    "sg:orig_category":"Zonnebank- En Solariumcentra",
    "sg:phone":"+31 475 339 220",
    "sg:postcode":"6049 GM",
    "sg:province":"Limburg",
    "wof:name":"Mari?lle",
    "wof:placetype":"venue"
},
  "geometry": {"coordinates":[5.967433,51.170864],"type":"Point"}
}