{
  "type": "Feature",
  "properties": {
    "iso:country":"NL",
    "sg:address":"Essenstr 8",
    "sg:city":"Deventer",
    "sg:orig_category":"Banden",
    "sg:phone":"+31 570 620 820",
    "sg:postcode":"7418 BM",
    "sg:province":"Overijssel",
    "sg:website":"http://www.steverinkbanden.nl",
    "wof:name":"Jan Steverink, Bandencentrum",
    "wof:placetype":"venue"
},
  "geometry": {"coordinates":[6.197408,52.24704],"type":"Point"}
}