{
  "type": "Feature",
  "properties": {
    "addr:full":"Ninnesweg 160 Panningen Limburg 5981 PD",
    "addr:housenumber":"160",
    "addr:postcode":"5981 pd",
    "addr:street":"Ninnesweg",
    "iso:country":"NL",
    "sg:address":"Ninnesweg 160",
    "sg:city":"Panningen",
    "sg:orig_category":"Hoefdierhouderijen",
    "sg:phone":"+31 77 307 6465",
    "sg:postcode":"5981 PD",
    "sg:province":"Limburg",
    "wof:name":"Riki'S Blue",
    "wof:placetype":"venue"
},
  "geometry": {"coordinates":[5.972685,51.345825],"type":"Point"}
}