{
  "type": "Feature",
  "properties": {
    "addr:full":"Graaf Janlaan 45 Amersfoort Utrecht 3818 DX",
    "addr:housenumber":"45",
    "addr:postcode":"3818 dx",
    "addr:street":"Graaf Janlaan",
    "iso:country":"NL",
    "sg:address":"Graaf Janlaan 45",
    "sg:city":"Amersfoort",
    "sg:orig_category":"Kinderopvang Behalve Thuis",
    "sg:phone":"+31 33 461 1020",
    "sg:postcode":"3818 DX",
    "sg:province":"Utrecht",
    "wof:name":"Kinderdagverblijf De Ukkenburg",
    "wof:placetype":"venue"
},
  "geometry": {"coordinates":[5.378816,52.148052],"type":"Point"}
}