{
  "type": "Feature",
  "properties": {
    "addr:full":"Achterzeedk 57Unit 46 Barendrecht Zuid-Holland 2992 SB",
    "addr:housenumber":"57unit 46",
    "addr:postcode":"2992 sb",
    "addr:street":"Achterzeedk",
    "iso:country":"NL",
    "sg:address":"Achterzeedk 57Unit 46",
    "sg:city":"Barendrecht",
    "sg:orig_category":"Hydraulische Apparaten En Installaties",
    "sg:phone":"+31 180 697 666",
    "sg:postcode":"2992 SB",
    "sg:province":"Zuid-Holland",
    "sg:website":"http://www.gshydro.nl",
    "wof:name":"Gs-Hydro Benelux Bv",
    "wof:placetype":"venue"
},
  "geometry": {"coordinates":[4.529279,51.835228],"type":"Point"}
}