{
  "type": "Feature",
  "properties": {
    "addr:full":"Van Hoornbeekstraat 71 'S-Gravenhage South Holland 2582 RC",
    "addr:housenumber":"71",
    "addr:postcode":"2582 rc",
    "addr:street":"Van Hoornbeekstraat",
    "iso:country":"NL",
    "sg:address":"Van Hoornbeekstraat 71",
    "sg:city":"'S-Gravenhage",
    "sg:orig_category":"Kopieerservice",
    "sg:phone":"+31 70 392 1237",
    "sg:postcode":"2582 RC",
    "sg:province":"South Holland",
    "sg:website":"http://www.ldcrepro.nl",
    "wof:name":"Ldc",
    "wof:placetype":"venue"
},
  "geometry": {"coordinates":[4.280007,52.094795],"type":"Point"}
}