{
  "type": "Feature",
  "properties": {
    "addr:full":"Zandkrab 18 Eindhoven Noord-Brabant 5658 AD",
    "addr:housenumber":"18",
    "addr:postcode":"5658 ad",
    "addr:street":"Zandkrab",
    "iso:country":"NL",
    "sg:address":"Zandkrab 18",
    "sg:city":"Eindhoven",
    "sg:orig_category":"Webdesign Bureaus",
    "sg:phone":"+31 40 291 2238",
    "sg:postcode":"5658 AD",
    "sg:province":"Noord-Brabant",
    "wof:name":"Huwae, Ronald",
    "wof:placetype":"venue"
},
  "geometry": {"coordinates":[5.4093060493,51.4496383667],"type":"Point"}
}