{
  "type": "Feature",
  "properties": {
    "addr:full":"Zwolsewg 471 Wenum Wiesel Gelderland 7345 AG",
    "addr:housenumber":"471",
    "addr:postcode":"7345",
    "iso:country":"NL",
    "sg:address":"Zwolsewg 471",
    "sg:city":"Wenum Wiesel",
    "sg:orig_category":"Drukkerijen",
    "sg:phone":"+31 55 360 2286",
    "sg:postcode":"7345 AG",
    "sg:province":"Gelderland",
    "wof:name":"Druk Plus",
    "wof:placetype":"venue"
},
  "geometry": {"coordinates":[5.95605,52.265903],"type":"Point"}
}