{
  "type": "Feature",
  "properties": {
    "addr:full":"Pastoor Hendrikspark 30 Laren Nh Noord-Holland 1251 MD",
    "addr:housenumber":"30",
    "addr:postcode":"1251",
    "addr:street":"Pastoor Hendrikspark",
    "iso:country":"NL",
    "sg:address":"Pastoor Hendrikspark 30",
    "sg:city":"Laren Nh",
    "sg:orig_category":"Artsen And Specialisten",
    "sg:phone":"+31 35 538 9005",
    "sg:postcode":"1251 MD",
    "sg:province":"Noord-Holland",
    "wof:name":"J.J.M. V.D. Werf",
    "wof:placetype":"venue"
},
  "geometry": {"coordinates":[5.230669,52.255157],"type":"Point"}
}