{
  "type": "Feature",
  "properties": {
    "addr:full":"A De Waalstr 25 Hoofddorp North Holland 2135 NN",
    "addr:housenumber":"25",
    "addr:postcode":"2135 nn",
    "addr:street":"A",
    "iso:country":"NL",
    "sg:address":"A De Waalstr 25",
    "sg:city":"Hoofddorp",
    "sg:orig_category":"Loonbedrijven",
    "sg:phone":"+31 6 10908585",
    "sg:postcode":"2135 NN",
    "sg:province":"North Holland",
    "wof:name":"Limpt, L J P Van",
    "wof:placetype":"venue"
},
  "geometry": {"coordinates":[4.664202,52.297909],"type":"Point"}
}