{
  "type": "Feature",
  "properties": {
    "addr:full":"De Berken 8 Delden Overijssel 7491 HJ",
    "addr:housenumber":"8",
    "addr:postcode":"7491 hj",
    "addr:street":"De Berken",
    "iso:country":"NL",
    "sg:address":"De Berken 8",
    "sg:city":"Delden",
    "sg:orig_category":"Messen En Bladen Industrieel",
    "sg:phone":"+31 74 376 6036",
    "sg:postcode":"7491 HJ",
    "sg:province":"Overijssel",
    "wof:name":"Marsman Bv",
    "wof:placetype":"venue"
},
  "geometry": {"coordinates":[6.698597,52.255932],"type":"Point"}
}