{
  "type": "Feature",
  "properties": {
    "addr:full":"Pr F Hendrikln 22 Naarden Noord-Holland 1411 GA",
    "addr:housenumber":"22",
    "addr:postcode":"1411 ga",
    "iso:country":"NL",
    "sg:address":"Pr F Hendrikln 22",
    "sg:city":"Naarden",
    "sg:orig_category":"Adviesbureaus Bedrijfsorganisatie",
    "sg:phone":"+31 35 694 3000",
    "sg:postcode":"1411 GA",
    "sg:province":"Noord-Holland",
    "wof:name":"Farmaflex",
    "wof:placetype":"venue"
},
  "geometry": {"coordinates":[5.161848,52.296371],"type":"Point"}
}