{
  "type": "Feature",
  "properties": {
    "addr:full":"Majellapk 50 Utrecht Utrecht 3532 CV",
    "addr:housenumber":"50",
    "addr:postcode":"3532 cv",
    "addr:street":"Majellapk",
    "iso:country":"NL",
    "sg:address":"Majellapk 50",
    "sg:city":"Utrecht",
    "sg:orig_category":"Adviesbureaus Personeel",
    "sg:phone":"+31 30 296 5887",
    "sg:postcode":"3532 CV",
    "sg:province":"Utrecht",
    "wof:name":"Fransen",
    "wof:placetype":"venue"
},
  "geometry": {"coordinates":[5.087602,52.095943],"type":"Point"}
}