{
  "type": "Feature",
  "properties": {
    "addr:full":"Willem Pijperlaan 58 Rotterdam South Holland 3055 WP",
    "addr:housenumber":"58",
    "addr:postcode":"3055 wp",
    "addr:street":"Willem Pijperlaan",
    "iso:country":"NL",
    "sg:address":"Willem Pijperlaan 58",
    "sg:city":"Rotterdam",
    "sg:orig_category":"Fruit And Groenten Gh",
    "sg:phone":"+31 10 461 4515",
    "sg:postcode":"3055 WP",
    "sg:province":"South Holland",
    "wof:name":"L.A. Meyboom Rotterdam Bv",
    "wof:placetype":"venue"
},
  "geometry": {"coordinates":[4.503048,51.965145],"type":"Point"}
}