{
  "type": "Feature",
  "properties": {
    "addr:full":"Hoofdstraat 118 Posterholt Limburg 6061 CG",
    "addr:housenumber":"118",
    "addr:postcode":"6061 cg",
    "addr:street":"Hoofdstraat",
    "iso:country":"NL",
    "sg:address":"Hoofdstraat 118",
    "sg:city":"Posterholt",
    "sg:orig_category":"Fitnesscentra",
    "sg:phone":"+31 475 403 137",
    "sg:postcode":"6061 CG",
    "sg:province":"Limburg",
    "wof:name":"Leon Visschers Schoenen En Sport",
    "wof:placetype":"venue"
},
  "geometry": {"coordinates":[6.036435,51.121719],"type":"Point"}
}