{
  "type": "Feature",
  "properties": {
    "addr:full":"Nieuwe Plantage 49 Delft South Holland 2611 XK",
    "addr:housenumber":"49",
    "addr:postcode":"2611 xk",
    "addr:street":"Nieuwe Plantage",
    "iso:country":"NL",
    "sg:address":"Nieuwe Plantage 49",
    "sg:city":"Delft",
    "sg:orig_category":"Architecten",
    "sg:phone":"+31 15 213 5620",
    "sg:postcode":"2611 XK",
    "sg:province":"South Holland",
    "wof:name":"Ir. A.I. Prevoo",
    "wof:placetype":"venue"
},
  "geometry": {"coordinates":[4.353441,52.017681],"type":"Point"}
}