{
  "type": "Feature",
  "properties": {
    "addr:full":"Jan Barendselaan 188 Poeldijk Zuid-Holland 2685 BX",
    "addr:housenumber":"188",
    "addr:postcode":"2685 bx",
    "addr:street":"Jan Barendselaan",
    "iso:country":"NL",
    "sg:address":"Jan Barendselaan 188",
    "sg:city":"Poeldijk",
    "sg:orig_category":"Benzinestations And Brandstoffen",
    "sg:phone":"+31 174 243 226",
    "sg:postcode":"2685 BX",
    "sg:province":"Zuid-Holland",
    "wof:name":"Ototol Bv",
    "wof:placetype":"venue"
},
  "geometry": {"coordinates":[4.220906,52.023178],"type":"Point"}
}