{
  "type": "Feature",
  "properties": {
    "addr:full":"Hoofdwg Wedderv 13 Wedde Groningen 9698 PA",
    "addr:housenumber":"13",
    "addr:postcode":"9698 pa",
    "addr:street":"Wedde",
    "iso:country":"NL",
    "sg:address":"Hoofdwg Wedderv 13",
    "sg:city":"Wedde",
    "sg:orig_category":"Oldtimers",
    "sg:phone":"+31 597 561 144",
    "sg:postcode":"9698 PA",
    "sg:province":"Groningen",
    "wof:name":"Boer, A D De",
    "wof:placetype":"venue"
},
  "geometry": {"coordinates":[7.067361,53.084507],"type":"Point"}
}