{
  "type": "Feature",
  "properties": {
    "addr:full":"Noorderblokken 3 Drouwenermond Drenthe 9523 TJ",
    "addr:housenumber":"3",
    "addr:postcode":"9523 tj",
    "addr:street":"Noorderblokken",
    "iso:country":"NL",
    "sg:address":"Noorderblokken 3",
    "sg:city":"Drouwenermond",
    "sg:orig_category":"Metaalbekleding And -Behandeling",
    "sg:phone":"+31 599 616 604",
    "sg:postcode":"9523 TJ",
    "sg:province":"Drenthe",
    "wof:name":"Thalens En Zonen Vof",
    "wof:placetype":"venue"
},
  "geometry": {"coordinates":[6.882969,52.973385],"type":"Point"}
}