{
  "type": "Feature",
  "properties": {
    "iso:country":"NL",
    "sg:address":"De Tarp 47",
    "sg:city":"Akersloot",
    "sg:orig_category":"Kantoor- En Secretariaatsservice",
    "sg:phone":"+31 251 311 168",
    "sg:postcode":"1921 VA",
    "sg:province":"North Holland",
    "wof:name":"Secretariaat, Het",
    "wof:placetype":"venue"
},
  "geometry": {"coordinates":[4.7286009789,52.555015564],"type":"Point"}
}