{
  "type": "Feature",
  "properties": {
    "addr:full":"Provincialew 13 Kornhorn Groningen 9864 PA",
    "addr:housenumber":"13",
    "addr:postcode":"9864 pa",
    "addr:street":"Provincialew",
    "iso:country":"NL",
    "sg:address":"Provincialew 13",
    "sg:city":"Kornhorn",
    "sg:orig_category":"Artsen - Huisartsen",
    "sg:phone":"+31 594 659 015",
    "sg:postcode":"9864 PA",
    "sg:province":"Groningen",
    "wof:name":"Smits, S J",
    "wof:placetype":"venue"
},
  "geometry": {"coordinates":[6.234997,53.180119],"type":"Point"}
}