{
  "type": "Feature",
  "properties": {
    "addr:full":"Kantstr 29 Landgraaf Limburg 6374 EE",
    "addr:housenumber":"29",
    "addr:postcode":"6374 ee",
    "addr:street":"Kantstr",
    "iso:country":"NL",
    "sg:address":"Kantstr 29",
    "sg:city":"Landgraaf",
    "sg:orig_category":"Keukens",
    "sg:phone":"+31 45 531 2267",
    "sg:postcode":"6374 EE",
    "sg:province":"Limburg",
    "wof:name":"Vermeulen Keukens",
    "wof:placetype":"venue"
},
  "geometry": {"coordinates":[6.042691,50.915859],"type":"Point"}
}