{
  "type": "Feature",
  "properties": {
    "addr:full":"Tulpstr 7 Arnhem Gelderland 6813 DS",
    "addr:housenumber":"7",
    "addr:postcode":"6813 ds",
    "addr:street":"Tulpstr",
    "iso:country":"NL",
    "sg:address":"Tulpstr 7",
    "sg:city":"Arnhem",
    "sg:orig_category":"Artiesten/Gezelschappen",
    "sg:phone":"+31 26 445 3091",
    "sg:postcode":"6813 DS",
    "sg:province":"Gelderland",
    "wof:name":"Kok De Koning",
    "wof:placetype":"venue"
},
  "geometry": {"coordinates":[5.887567,51.988144],"type":"Point"}
}