{
  "type": "Feature",
  "properties": {
    "iso:country":"NL",
    "sg:address":"Muntstr 17",
    "sg:city":"Maastricht",
    "sg:orig_category":"Boeken En Tijdschriften",
    "sg:phone":"+31 43 321 1410",
    "sg:postcode":"6211 EG",
    "sg:province":"Limburg",
    "wof:name":"Palero",
    "wof:placetype":"venue"
},
  "geometry": {"coordinates":[5.692434,50.850643],"type":"Point"}
}