{
  "type": "Feature",
  "properties": {
    "addr:full":"Romeln 10 S Hertogenbosch Noord-Brabant 5237 EB",
    "addr:housenumber":"10",
    "addr:postcode":"5237 eb",
    "addr:street":"Romeln;S",
    "iso:country":"NL",
    "sg:address":"Romeln 10",
    "sg:city":"S Hertogenbosch",
    "sg:orig_category":"Loopbaanbegeleiding",
    "sg:phone":"+31 73 612 3273",
    "sg:postcode":"5237 EB",
    "sg:province":"Noord-Brabant",
    "wof:name":"Kruis Bv, Gerrit",
    "wof:placetype":"venue"
},
  "geometry": {"coordinates":[5.2886,51.730911],"type":"Point"}
}