{
  "type": "Feature",
  "properties": {
    "iso:country":"NL",
    "sg:address":"Gageldonksepad 5",
    "sg:city":"Breda",
    "sg:orig_category":"Verenigingsgebouwen",
    "sg:phone":"+31 76 541 0425",
    "sg:postcode":"4824 PP",
    "sg:province":"Noord-Brabant",
    "wof:name":"Beemdentil, Cultureel Centrum De",
    "wof:placetype":"venue"
},
  "geometry": {"coordinates":[4.743678,51.602619],"type":"Point"}
}