{
  "type": "Feature",
  "properties": {
    "iso:country":"NL",
    "sg:address":"Waliensestraat 93",
    "sg:city":"Winterswijk",
    "sg:orig_category":"Discountwinkels",
    "sg:phone":"+31 543 513 560",
    "sg:postcode":"7103 WX",
    "sg:province":"Gelderland",
    "wof:name":"Fa H J Plettenburg & Zn",
    "wof:placetype":"venue"
},
  "geometry": {"coordinates":[6.722911,51.978439],"type":"Point"}
}