{
  "type": "Feature",
  "properties": {
    "addr:full":"Maasstr 16 Weert Limburg 6001 EC",
    "addr:housenumber":"16",
    "addr:postcode":"6001 ec",
    "addr:street":"Maasstr",
    "iso:country":"NL",
    "sg:address":"Maasstr 16",
    "sg:city":"Weert",
    "sg:orig_category":"Glas, Porselein En Aardewerk",
    "sg:phone":"+31 495 532 571",
    "sg:postcode":"6001 EC",
    "sg:province":"Limburg",
    "wof:name":"Coenen-Saes, J",
    "wof:placetype":"venue"
},
  "geometry": {"coordinates":[5.707588,51.252716],"type":"Point"}
}