{
  "type": "Feature",
  "properties": {
    "iso:country":"NL",
    "sg:address":"Kubus 121",
    "sg:city":"Sliedrecht",
    "sg:orig_category":"Bodemonderzoek",
    "sg:phone":"+31 184 618 010",
    "sg:postcode":"3364 DG",
    "sg:province":"Zuid-Holland",
    "sg:website":"http://www.inpijn-blokpoel.com",
    "wof:name":"Inpijn Blokpoel Bv",
    "wof:placetype":"venue"
},
  "geometry": {"coordinates":[4.796464,51.825577],"type":"Point"}
}