{
  "type": "Feature",
  "properties": {
    "addr:full":"Kornalynln 1 Groningen Groningen 9743 JK",
    "addr:housenumber":"1",
    "addr:postcode":"9743 jk",
    "addr:street":"Kornalynln",
    "iso:country":"NL",
    "sg:address":"Kornalynln 1",
    "sg:city":"Groningen",
    "sg:orig_category":"Gehandicapteninformatie",
    "sg:phone":"+31 50 577 3320",
    "sg:postcode":"9743 JK",
    "sg:province":"Groningen",
    "sg:website":"http://www.ilmarinen.nl",
    "wof:name":"Ilmarinen",
    "wof:placetype":"venue"
},
  "geometry": {"coordinates":[6.524753,53.22826],"type":"Point"}
}