{
  "type": "Feature",
  "properties": {
    "addr:full":"R Visscherstr 14 Gouda Zuid-Holland 2802 NB",
    "addr:housenumber":"14",
    "addr:postcode":"2802 nb",
    "iso:country":"NL",
    "sg:address":"R Visscherstr 14",
    "sg:city":"Gouda",
    "sg:orig_category":"Loodgieters",
    "sg:phone":"+31 182 583 518",
    "sg:postcode":"2802 NB",
    "sg:province":"Zuid-Holland",
    "wof:name":"Hartog, Den",
    "wof:placetype":"venue"
},
  "geometry": {"coordinates":[4.703196,52.004986],"type":"Point"}
}