{
  "type": "Feature",
  "properties": {
    "addr:full":"F A Molynln 28 Nunspeet Gelderland 8071 AG",
    "addr:housenumber":"28",
    "addr:postcode":"8071",
    "addr:street":"F;Molynln;Gelderland",
    "iso:country":"NL",
    "sg:address":"F A Molynln 28",
    "sg:city":"Nunspeet",
    "sg:orig_category":"Makelaars En Adviseurs Onroerende Goederen",
    "sg:phone":"+31 341 252 363",
    "sg:postcode":"8071 AG",
    "sg:province":"Gelderland",
    "sg:website":"http://www.vandeloosdrecht.nl",
    "wof:name":"Loosdrecht Bv, Van De",
    "wof:placetype":"venue"
},
  "geometry": {"coordinates":[5.772205,52.374981],"type":"Point"}
}