{
  "type": "Feature",
  "properties": {
    "addr:full":"Koestr 105 Tilburg Noord-Brabant 5014 EB",
    "addr:housenumber":"105",
    "addr:postcode":"5014 eb",
    "addr:street":"Tilburg",
    "iso:country":"NL",
    "sg:address":"Koestr 105",
    "sg:city":"Tilburg",
    "sg:orig_category":"Zonweringen",
    "sg:phone":"+31 13 536 7343",
    "sg:postcode":"5014 EB",
    "sg:province":"Noord-Brabant",
    "wof:name":"Vitra Wash",
    "wof:placetype":"venue"
},
  "geometry": {"coordinates":[5.106271,51.554928],"type":"Point"}
}