{
  "type": "Feature",
  "properties": {
    "addr:full":"Ericasestraat 71 Erica Drenthe 7887 GB",
    "addr:housenumber":"71",
    "addr:postcode":"7887 gb",
    "addr:street":"Ericasestraat",
    "iso:country":"NL",
    "sg:address":"Ericasestraat 71",
    "sg:city":"Erica",
    "sg:orig_category":"Verhuur Bouwmachines",
    "sg:phone":"+31 591 301 485",
    "sg:postcode":"7887 GB",
    "sg:province":"Drenthe",
    "wof:name":"Keromat Bv",
    "wof:placetype":"venue"
},
  "geometry": {"coordinates":[6.927604,52.721859],"type":"Point"}
}