{
  "type": "Feature",
  "properties": {
    "iso:country":"NL",
    "sg:address":"Brabantse Turfmarkt 23",
    "sg:city":"Delft",
    "sg:classifiers":[
        {
            "category":"Fast Food",
            "type":"Food & Drink"
        }
    ],
    "sg:phone":"+31 15 213 1629",
    "sg:postcode":"2611 CL",
    "sg:province":"Zuid-Holland",
    "sg:tags":[
        "afhaal",
        "restaurant"
    ],
    "wof:name":"Italiaans Restaurant Pizzeria San Marco",
    "wof:placetype":"venue"
},
  "geometry": {"coordinates":[4.360775,52.00946],"type":"Point"}
}