{
  "type": "Feature",
  "properties": {
    "addr:full":"Goudsbloemln 127 S Gravenhage Zuid-Holland 2565 CR",
    "addr:housenumber":"127;gravenhage;2565",
    "addr:postcode":"cr",
    "addr:street":"S",
    "iso:country":"NL",
    "sg:address":"Goudsbloemln 127",
    "sg:city":"S Gravenhage",
    "sg:orig_category":"Opticiens",
    "sg:phone":"+31 70 363 6736",
    "sg:postcode":"2565 CR",
    "sg:province":"Zuid-Holland",
    "wof:name":"Looze, De",
    "wof:placetype":"venue"
},
  "geometry": {"coordinates":[4.2612900734,52.0763816833],"type":"Point"}
}