{
  "type": "Feature",
  "properties": {
    "addr:full":"Herelsestraat 121 Heerle Noord-Brabant 4726 AD",
    "addr:housenumber":"121",
    "addr:postcode":"4726 ad",
    "addr:street":"Herelsestraat",
    "iso:country":"NL",
    "sg:address":"Herelsestraat 121",
    "sg:city":"Heerle",
    "sg:orig_category":"Banken And Kredietinstellingen",
    "sg:phone":"+31 165 304 530",
    "sg:postcode":"4726 AD",
    "sg:province":"Noord-Brabant",
    "wof:name":"Postkantoor",
    "wof:placetype":"venue"
},
  "geometry": {"coordinates":[4.362979,51.520096],"type":"Point"}
}