{
  "type": "Feature",
  "properties": {
    "addr:full":"Adm De Ruyterwg 288 Amsterdam North Holland 1055 MS",
    "addr:housenumber":"288",
    "addr:postcode":"1055 ms",
    "iso:country":"NL",
    "sg:address":"Adm De Ruyterwg 288",
    "sg:city":"Amsterdam",
    "sg:orig_category":"Geluidsinstallaties - Verhuur",
    "sg:phone":"+31 20 463 0404",
    "sg:postcode":"1055 MS",
    "sg:province":"North Holland",
    "sg:website":"http://www.evenblijaudio.nl",
    "wof:name":"Wilfrid Evenblij",
    "wof:placetype":"venue"
},
  "geometry": {"coordinates":[4.85337,52.380409],"type":"Point"}
}