{
  "type": "Feature",
  "properties": {
    "addr:full":"J W Hagemanstraat 15 Eibergen Gelderland 7151 AD",
    "addr:housenumber":"15",
    "addr:postcode":"7151 ad",
    "addr:street":"W Hagemanstraat;Gelderland",
    "iso:country":"NL",
    "sg:address":"J W Hagemanstraat 15",
    "sg:city":"Eibergen",
    "sg:orig_category":"Fotostudio'S And Fotografen",
    "sg:phone":"+31 545 473 200",
    "sg:postcode":"7151 AD",
    "sg:province":"Gelderland",
    "wof:name":"Adri Report Fotograaf",
    "wof:placetype":"venue"
},
  "geometry": {"coordinates":[6.651052,52.102413],"type":"Point"}
}