{
  "type": "Feature",
  "properties": {
    "iso:country":"NL",
    "sg:address":"Keulsebaan 6",
    "sg:city":"Neerkant",
    "sg:orig_category":"Machineonderhoud En -Reparatie",
    "sg:phone":"+31 77 466 3677",
    "sg:postcode":"5758 AB",
    "sg:province":"Noord-Brabant",
    "wof:name":"Nooijen",
    "wof:placetype":"venue"
},
  "geometry": {"coordinates":[5.865449,51.365589],"type":"Point"}
}