{
  "type": "Feature",
  "properties": {
    "addr:full":"Schalsumerwg 73 Franeker Friesland 8802 XE",
    "addr:housenumber":"73",
    "addr:postcode":"8802 xe",
    "addr:street":"Schalsumerwg",
    "iso:country":"NL",
    "sg:address":"Schalsumerwg 73",
    "sg:city":"Franeker",
    "sg:orig_category":"Administratie- En Boekhoudkantoren",
    "sg:phone":"+31 517 398 098",
    "sg:postcode":"8802 XE",
    "sg:province":"Friesland",
    "wof:name":"Administratie Serviceburo",
    "wof:placetype":"venue"
},
  "geometry": {"coordinates":[5.561051,53.191891],"type":"Point"}
}