{
  "type": "Feature",
  "properties": {
    "addr:full":"Het Haagje 3 Hoogeveen Drenthe 7902 LA",
    "addr:housenumber":"3",
    "addr:postcode":"7902 la",
    "addr:street":"Het Haagje",
    "iso:country":"NL",
    "sg:address":"Het Haagje 3",
    "sg:city":"Hoogeveen",
    "sg:orig_category":"Banken And Kredietinstellingen",
    "sg:phone":"+31 528 265 751",
    "sg:postcode":"7902 LA",
    "sg:province":"Drenthe",
    "wof:name":"Samenwerkende Nederlandse Spaarbanken Nv",
    "wof:placetype":"venue"
},
  "geometry": {"coordinates":[6.479405,52.720795],"type":"Point"}
}