{
  "type": "Feature",
  "properties": {
    "addr:full":"Westblaak 28-30 Rotterdam Zuid-Holland 3012 KM",
    "addr:housenumber":"28-30",
    "addr:postcode":"3012 km",
    "addr:street":"Westblaak",
    "iso:country":"NL",
    "sg:address":"Westblaak 28-30",
    "sg:city":"Rotterdam",
    "sg:orig_category":"Drukkerijen And Copyshops",
    "sg:phone":"+31 10 414 1446",
    "sg:postcode":"3012 KM",
    "sg:province":"Zuid-Holland",
    "wof:name":"Multicopy Drukwerkservice",
    "wof:placetype":"venue"
},
  "geometry": {"coordinates":[4.478542,51.917088],"type":"Point"}
}