{
  "type": "Feature",
  "properties": {
    "addr:full":"Jacques Urlusplantsoen 265 Leiden Zuid-Holland 2324 KV",
    "addr:housenumber":"265",
    "addr:postcode":"2324 kv",
    "addr:street":"Jacques Urlusplantsoen",
    "iso:country":"NL",
    "sg:address":"Jacques Urlusplantsoen 265",
    "sg:city":"Leiden",
    "sg:orig_category":"Werving And Selectie Van Tijdelijk Personeel And Uitzendkantoren",
    "sg:phone":"+31 71 576 1080",
    "sg:postcode":"2324 KV",
    "sg:province":"Zuid-Holland",
    "wof:name":"Asya",
    "wof:placetype":"venue"
},
  "geometry": {"coordinates":[4.4718780518,52.1518783569],"type":"Point"}
}