{
  "type": "Feature",
  "properties": {
    "addr:full":"Parklaan 83 Eindhoven North Brabant 5613 BB",
    "addr:housenumber":"83",
    "addr:postcode":"5613 bb",
    "addr:street":"Parklaan",
    "iso:country":"NL",
    "sg:address":"Parklaan 83",
    "sg:city":"Eindhoven",
    "sg:orig_category":"Fotostudio'S And Fotografen",
    "sg:phone":"+31 40 246 6496",
    "sg:postcode":"5613 BB",
    "sg:province":"North Brabant",
    "wof:name":"R.L. Stork",
    "wof:placetype":"venue"
},
  "geometry": {"coordinates":[5.492879,51.441631],"type":"Point"}
}