{
  "type": "Feature",
  "properties": {
    "addr:full":"De Kletten 8 Drachten Provincie Friesland 9206 BA",
    "addr:housenumber":"8",
    "addr:postcode":"9206 ba",
    "addr:street":"De Kletten;Provincie Friesland",
    "iso:country":"NL",
    "sg:address":"De Kletten 8",
    "sg:city":"Drachten",
    "sg:orig_category":"Accountants - Administratie- Consulenten En -Kantoren",
    "sg:phone":"+31 512 542 214",
    "sg:postcode":"9206 BA",
    "sg:province":"Provincie Friesland",
    "sg:website":"http://www.euro-file.nl",
    "wof:name":"Euro-File",
    "wof:placetype":"venue"
},
  "geometry": {"coordinates":[6.076914,53.11869],"type":"Point"}
}