{
  "type": "Feature",
  "properties": {
    "addr:full":"Rijksstraatweg 9 Geldermalsen Gelderland 4191 SC",
    "addr:housenumber":"9",
    "addr:postcode":"4191",
    "addr:street":"Rijksstraatweg;Gelderland",
    "iso:country":"NL",
    "sg:address":"Rijksstraatweg 9",
    "sg:city":"Geldermalsen",
    "sg:orig_category":"Kappers",
    "sg:phone":"+31 6 53143813",
    "sg:postcode":"4191 SC",
    "sg:province":"Gelderland",
    "wof:name":"Hairstyling Lieke",
    "wof:placetype":"venue"
},
  "geometry": {"coordinates":[5.2896800041,51.8828430176],"type":"Point"}
}