{
  "type": "Feature",
  "properties": {
    "iso:country":"NL",
    "sg:address":"Zeestr 127",
    "sg:city":"Noordwykerhout",
    "sg:orig_category":"Keukens",
    "sg:phone":"+31 6 27020112",
    "sg:postcode":"2211 XE",
    "sg:province":"South Holland",
    "wof:name":"Meubelstuk, Het",
    "wof:placetype":"venue"
},
  "geometry": {"coordinates":[4.485019,52.263744],"type":"Point"}
}