{
  "type": "Feature",
  "properties": {
    "iso:country":"NL",
    "sg:address":"Kerklaan 3",
    "sg:city":"Weesp",
    "sg:orig_category":"Juweliers",
    "sg:phone":"+31 294 418 272",
    "sg:postcode":"1382 AK",
    "sg:province":"North Holland",
    "wof:name":"M.T. De Geer",
    "wof:placetype":"venue"
},
  "geometry": {"coordinates":[5.040363,52.309193],"type":"Point"}
}