{
  "type": "Feature",
  "properties": {
    "addr:full":"V Alkemadeln 1256 S Gravenhage South Holland 2597 BP",
    "addr:housenumber":"1256",
    "addr:postcode":"2597 bp",
    "addr:street":"S Gravenhage",
    "iso:country":"NL",
    "sg:address":"V Alkemadeln 1256",
    "sg:city":"S Gravenhage",
    "sg:orig_category":"Houtbewerking",
    "sg:phone":"+31 70 416 4702",
    "sg:postcode":"2597 BP",
    "sg:province":"South Holland",
    "wof:name":"Pen Productiebedr Scheveningen",
    "wof:placetype":"venue"
},
  "geometry": {"coordinates":[4.31817,52.11031],"type":"Point"}
}