{
  "type": "Feature",
  "properties": {
    "addr:full":"Galvaniweg 2 Zwolle Overijssel 8013 RG",
    "addr:housenumber":"2",
    "addr:postcode":"8013 rg",
    "addr:street":"Galvaniweg",
    "iso:country":"NL",
    "sg:address":"Galvaniweg 2",
    "sg:city":"Zwolle",
    "sg:orig_category":"Woningbouwverenigingen",
    "sg:phone":"+31 38 468 0123",
    "sg:postcode":"8013 RG",
    "sg:province":"Overijssel",
    "wof:name":"Swz Woningcorporatie",
    "wof:placetype":"venue"
},
  "geometry": {"coordinates":[6.1342759132,52.4946289062],"type":"Point"}
}