{
  "type": "Feature",
  "properties": {
    "addr:full":"Kerkpln 5A St Oedenrode Noord-Brabant 5492 AN",
    "addr:housenumber":"5a",
    "addr:postcode":"5492 an",
    "addr:street":"Kerkpln;St",
    "iso:country":"NL",
    "sg:address":"Kerkpln 5A",
    "sg:city":"St Oedenrode",
    "sg:orig_category":"Opticiens",
    "sg:phone":"+31 413 474 860",
    "sg:postcode":"5492 AN",
    "sg:province":"Noord-Brabant",
    "wof:name":"Leenders, Leo",
    "wof:placetype":"venue"
},
  "geometry": {"coordinates":[5.4605631828,51.563205719],"type":"Point"}
}