{
  "type": "Feature",
  "properties": {
    "addr:full":"Nieuwpoortstr 84A Amsterdam Noord-Holland 1055 RZ",
    "addr:housenumber":"84a",
    "addr:postcode":"1055 rz",
    "addr:street":"Nieuwpoortstr",
    "iso:country":"NL",
    "sg:address":"Nieuwpoortstr 84A",
    "sg:city":"Amsterdam",
    "sg:orig_category":"Adviesbureaus Bedrijfsorganisatie",
    "sg:phone":"+31 20 403 7220",
    "sg:postcode":"1055 RZ",
    "sg:province":"Noord-Holland",
    "sg:website":"http://www.jostens.nl",
    "wof:name":"Jostens",
    "wof:placetype":"venue"
},
  "geometry": {"coordinates":[4.85812,52.38422],"type":"Point"}
}