{
  "type": "Feature",
  "properties": {
    "addr:full":"Poggenbeekstr 71Hg Amsterdam Noord-Holland 1073 JE",
    "addr:postcode":"1073 je",
    "iso:country":"NL",
    "sg:address":"Poggenbeekstr 71Hg",
    "sg:city":"Amsterdam",
    "sg:orig_category":"Beeldende Kunstenaars",
    "sg:phone":"+31 20 676 5687",
    "sg:postcode":"1073 JE",
    "sg:province":"Noord-Holland",
    "wof:name":"Max",
    "wof:placetype":"venue"
},
  "geometry": {"coordinates":[4.89773,52.348881],"type":"Point"}
}