{
  "type": "Feature",
  "properties": {
    "addr:full":"Stadhouderslaan 7 Veenendaal Utrecht 3905 HA",
    "addr:housenumber":"7",
    "addr:postcode":"3905 ha",
    "addr:street":"Stadhouderslaan",
    "iso:country":"NL",
    "sg:address":"Stadhouderslaan 7",
    "sg:city":"Veenendaal",
    "sg:orig_category":"Metalen And Ertsen Gh",
    "sg:phone":"+31 318 522 168",
    "sg:postcode":"3905 HA",
    "sg:province":"Utrecht",
    "wof:name":"G. Van Veldhuizen",
    "wof:placetype":"venue"
},
  "geometry": {"coordinates":[5.559407,52.033398],"type":"Point"}
}