{
  "type": "Feature",
  "properties": {
    "addr:full":"Frederik Hendriklaan 117 'S Gravenhage Zuid-Holland 2582 BX",
    "addr:housenumber":"117 '",
    "addr:postcode":"2582 bx",
    "addr:street":"Frederik Hendriklaan",
    "iso:country":"NL",
    "sg:address":"Frederik Hendriklaan 117",
    "sg:city":"'S Gravenhage",
    "sg:orig_category":"Drogisterijen",
    "sg:phone":"+31 70 351 4368",
    "sg:postcode":"2582 BX",
    "sg:province":"Zuid-Holland",
    "wof:name":"Kruidvat",
    "wof:placetype":"venue"
},
  "geometry": {"coordinates":[4.275973,52.093143],"type":"Point"}
}