{
  "type": "Feature",
  "properties": {
    "addr:full":"K.P. Van Der Mandelelaan 68 Rotterdam Zuid-Holland 3062 MB",
    "addr:housenumber":"68",
    "addr:postcode":"3062 mb",
    "addr:street":"K.P. Van Der Mandelelaan",
    "iso:country":"NL",
    "sg:address":"K.P. Van Der Mandelelaan 68",
    "sg:city":"Rotterdam",
    "sg:orig_category":"Verzekeringen",
    "sg:phone":"+31 10 242 5000",
    "sg:postcode":"3062 MB",
    "sg:province":"Zuid-Holland",
    "wof:name":"Pandimar Insurance Services Bv",
    "wof:placetype":"venue"
},
  "geometry": {"coordinates":[4.532681,51.917168],"type":"Point"}
}