{
  "type": "Feature",
  "properties": {
    "addr:full":"Veenenburg 44 Hillegom North Holland 2182 EH",
    "addr:housenumber":"44",
    "addr:postcode":"2182 eh",
    "addr:street":"Veenenburg",
    "iso:country":"NL",
    "sg:address":"Veenenburg 44",
    "sg:city":"Hillegom",
    "sg:classifiers":[
        {
            "category":"Personal",
            "subcategory":"Nail Salon",
            "type":"Services"
        }
    ],
    "sg:phone":"+31 252 516 519",
    "sg:postcode":"2182 EH",
    "sg:province":"North Holland",
    "sg:tags":[
        "pedicure"
    ],
    "wof:name":"Willemse-Blokker, A",
    "wof:placetype":"venue"
},
  "geometry": {"coordinates":[4.577557,52.288185],"type":"Point"}
}