{
  "type": "Feature",
  "properties": {
    "addr:full":"Van Campenvaart 75 'S-Gravenhage 2497 ZC",
    "addr:housenumber":"75",
    "addr:postcode":"2497 zc",
    "addr:street":"Van Campenvaart",
    "iso:country":"NL",
    "sg:address":"Van Campenvaart 75",
    "sg:city":"'S-Gravenhage",
    "sg:orig_category":"Administratie- En Boekhoudkantoren",
    "sg:phone":"+31 70 390 6551",
    "sg:postcode":"2497 ZC",
    "wof:name":"Dort, Van",
    "wof:placetype":"venue"
},
  "geometry": {"coordinates":[4.366201,52.036232],"type":"Point"}
}