{
  "type": "Feature",
  "properties": {
    "addr:full":"Parallelweg 1 Heusden Gem Heusden North Brabant 5256 PW",
    "addr:housenumber":"1",
    "addr:postcode":"5256 pw",
    "addr:street":"Parallelweg",
    "iso:country":"NL",
    "sg:address":"Parallelweg 1",
    "sg:city":"Heusden Gem Heusden",
    "sg:classifiers":[
        {
            "category":"Communications",
            "subcategory":"Television Station",
            "type":"Services"
        }
    ],
    "sg:phone":"+31 416 661 402",
    "sg:postcode":"5256 PW",
    "sg:province":"North Brabant",
    "sg:tags":[
        "video",
        "audio",
        "verhuur"
    ],
    "wof:name":"Videotheek De Schuur",
    "wof:placetype":"venue"
},
  "geometry": {"coordinates":[5.119295,51.731461],"type":"Point"}
}