{
  "type": "Feature",
  "properties": {
    "addr:full":"Leeuwerikplein 9 'S Gravenhage South Holland 2566 JX",
    "addr:housenumber":"9 '",
    "addr:postcode":"2566 jx",
    "addr:street":"Leeuwerikplein",
    "iso:country":"NL",
    "sg:address":"Leeuwerikplein 9",
    "sg:city":"'S Gravenhage",
    "sg:orig_category":"Vertaal- And Tolkenbureaus",
    "sg:phone":"+31 70 310 6233",
    "sg:postcode":"2566 JX",
    "sg:province":"South Holland",
    "wof:name":"Professional Transl Agency De Heer-Schol",
    "wof:placetype":"venue"
},
  "geometry": {"coordinates":[4.265317,52.084728],"type":"Point"}
}