{
  "type": "Feature",
  "properties": {
    "addr:full":"Nijverheidstraat 8 Moerkapelle Zuid-Holland 2751 GR",
    "addr:housenumber":"8",
    "addr:postcode":"2751",
    "addr:street":"Nijverheidstraat",
    "iso:country":"NL",
    "sg:address":"Nijverheidstraat 8",
    "sg:city":"Moerkapelle",
    "sg:orig_category":"Metaalbekleding And -Behandeling",
    "sg:phone":"+31 79 593 2994",
    "sg:postcode":"2751 GR",
    "sg:province":"Zuid-Holland",
    "wof:name":"Bolair Bv",
    "wof:placetype":"venue"
},
  "geometry": {"coordinates":[4.586883,52.043289],"type":"Point"}
}