{
  "type": "Feature",
  "properties": {
    "iso:country":"NL",
    "sg:address":"Galgenberg 9",
    "sg:city":"Bergeyk",
    "sg:orig_category":"Straalbedrijven",
    "sg:phone":"+31 497 542 232",
    "sg:postcode":"5571 SP",
    "sg:province":"Noord-Brabant",
    "wof:name":"Herk Bv, Van",
    "wof:placetype":"venue"
},
  "geometry": {"coordinates":[5.338614,51.316921],"type":"Point"}
}