{
  "type": "Feature",
  "properties": {
    "addr:full":"Bakenesserstr 13 Haarlem Noord-Holland 2011 JJ",
    "addr:housenumber":"13",
    "addr:postcode":"2011 jj",
    "addr:street":"Bakenesserstr",
    "iso:country":"NL",
    "sg:address":"Bakenesserstr 13",
    "sg:city":"Haarlem",
    "sg:orig_category":"Adviesbureaus Bedrijfsorganisatie",
    "sg:phone":"+31 23 551 1666",
    "sg:postcode":"2011 JJ",
    "sg:province":"Noord-Holland",
    "sg:website":"http://www.bourne-healy.nl",
    "wof:name":"Bourne En Healy Bv",
    "wof:placetype":"venue"
},
  "geometry": {"coordinates":[4.642652,52.381248],"type":"Point"}
}