{
  "type": "Feature",
  "properties": {
    "iso:country":"NL",
    "sg:address":"Ds. Van Den Boschlaan 36",
    "sg:city":"Rijswijk Zh",
    "sg:orig_category":"Bedrijfs- And Managementsconsultants",
    "sg:phone":"+31 70 394 4885",
    "sg:postcode":"2286 PM",
    "sg:province":"Zuid-Holland",
    "wof:name":"Schoneveld Consultancy Bv",
    "wof:placetype":"venue"
},
  "geometry": {"coordinates":[4.309388,52.031639],"type":"Point"}
}