{
  "type": "Feature",
  "properties": {
    "addr:full":"Nobelstraat 19 Brielle South Holland 3231 BA",
    "addr:housenumber":"19",
    "addr:postcode":"3231 ba",
    "addr:street":"Nobelstraat",
    "iso:country":"NL",
    "sg:address":"Nobelstraat 19",
    "sg:city":"Brielle",
    "sg:orig_category":"Vrachtvervoer",
    "sg:phone":"+31 10 436 2213",
    "sg:postcode":"3231 BA",
    "sg:province":"South Holland",
    "wof:name":"Mt Maritime Management Bv",
    "wof:placetype":"venue"
},
  "geometry": {"coordinates":[4.164544,51.901508],"type":"Point"}
}