{
  "type": "Feature",
  "properties": {
    "addr:full":"M Zeldenruststr 143 Hoofddorp Noord-Holland 2135 JN",
    "addr:housenumber":"143",
    "addr:postcode":"2135 jn",
    "iso:country":"NL",
    "sg:address":"M Zeldenruststr 143",
    "sg:city":"Hoofddorp",
    "sg:orig_category":"Ongediertebestrijding En Ontsmetting",
    "sg:phone":"+31 23 562 1441",
    "sg:postcode":"2135 JN",
    "sg:province":"Noord-Holland",
    "wof:name":"Mistral Hoofddorp",
    "wof:placetype":"venue"
},
  "geometry": {"coordinates":[4.670984,52.297474],"type":"Point"}
}