{
  "type": "Feature",
  "properties": {
    "addr:full":"Celebesstr 41C Amsterdam North Holland 1094 EN",
    "addr:housenumber":"41c",
    "addr:postcode":"1094 en",
    "addr:street":"Celebesstr",
    "iso:country":"NL",
    "sg:address":"Celebesstr 41C",
    "sg:city":"Amsterdam",
    "sg:orig_category":"Autorijscholen",
    "sg:phone":"+31 20 668 2879",
    "sg:postcode":"1094 EN",
    "sg:province":"North Holland",
    "wof:name":"Tuncay",
    "wof:placetype":"venue"
},
  "geometry": {"coordinates":[4.931668,52.36327],"type":"Point"}
}