{
  "type": "Feature",
  "properties": {
    "addr:full":"Geyzerstr 3 Deurne North Brabant 5753 RP",
    "addr:housenumber":"3",
    "addr:postcode":"5753 rp",
    "addr:street":"Geyzerstr",
    "iso:country":"NL",
    "sg:address":"Geyzerstr 3",
    "sg:city":"Deurne",
    "sg:orig_category":"Verf En Lak - Fabrieken En Groothandel",
    "sg:phone":"+31 493 352 452",
    "sg:postcode":"5753 RP",
    "sg:province":"North Brabant",
    "sg:website":"http://www.hoeka.nl",
    "wof:name":"Hoeka Bv",
    "wof:placetype":"venue"
},
  "geometry": {"coordinates":[5.807214,51.451046],"type":"Point"}
}