{
  "type": "Feature",
  "properties": {
    "addr:full":"Ryksstrwg 50 Wilp Gld Gelderland 7384 AD",
    "addr:housenumber":"50",
    "addr:postcode":"7384 ad",
    "addr:street":"Ryksstrwg;Gld Gelderland",
    "iso:country":"NL",
    "sg:address":"Ryksstrwg 50",
    "sg:city":"Wilp Gld",
    "sg:orig_category":"Parketvloeren",
    "sg:phone":"+31 571 261 414",
    "sg:postcode":"7384 AD",
    "sg:province":"Gelderland",
    "sg:website":"http://www.josnijhof.nl",
    "wof:name":"Jos Nijhof Bv",
    "wof:placetype":"venue"
},
  "geometry": {"coordinates":[6.147031,52.218868],"type":"Point"}
}