{
  "type": "Feature",
  "properties": {
    "addr:full":"Molenstraat 13 Harskamp Gelderland 6732 BP",
    "addr:housenumber":"13",
    "addr:postcode":"6732 bp",
    "addr:street":"Molenstraat;Gelderland",
    "iso:country":"NL",
    "sg:address":"Molenstraat 13",
    "sg:city":"Harskamp",
    "sg:orig_category":"Goederenvervoer Over De Weg",
    "sg:phone":"+31 318 457 252",
    "sg:postcode":"6732 BP",
    "sg:province":"Gelderland",
    "wof:name":"Int. Transportbedrijf Piet Wagtho",
    "wof:placetype":"venue"
},
  "geometry": {"coordinates":[5.754645,52.12413],"type":"Point"}
}