{
  "type": "Feature",
  "properties": {
    "addr:full":"Merelstr 33 Wolvega Provincie Friesland 8471 DC",
    "addr:housenumber":"33",
    "addr:postcode":"8471",
    "addr:street":"Merelstr;Provincie Friesland",
    "iso:country":"NL",
    "sg:address":"Merelstr 33",
    "sg:city":"Wolvega",
    "sg:orig_category":"Montagebedrijven",
    "sg:phone":"+31 561 446 575",
    "sg:postcode":"8471 DC",
    "sg:province":"Provincie Friesland",
    "wof:name":"Thor Montageteam Vof",
    "wof:placetype":"venue"
},
  "geometry": {"coordinates":[5.994145,52.87542],"type":"Point"}
}