{
  "type": "Feature",
  "properties": {
    "addr:full":"Vennootswg 1 Alphen Aan Den Ryn Zuid-Holland 2404 CG",
    "addr:housenumber":"1",
    "addr:postcode":"2404 cg",
    "addr:street":"Vennootswg;Aan Den Ryn",
    "iso:country":"NL",
    "sg:address":"Vennootswg 1",
    "sg:city":"Alphen Aan Den Ryn",
    "sg:orig_category":"Huishoudelijke Apparaten En Artikelen",
    "sg:phone":"+31 172 468 468",
    "sg:postcode":"2404 CG",
    "sg:province":"Zuid-Holland",
    "sg:website":"http://www.aeg.nl",
    "wof:name":"Aeg",
    "wof:placetype":"venue"
},
  "geometry": {"coordinates":[4.634211,52.134396],"type":"Point"}
}