{
  "type": "Feature",
  "properties": {
    "iso:country":"NL",
    "sg:address":"Rykswg Z 70",
    "sg:city":"Sittard",
    "sg:orig_category":"Scholen Voor Algemeen Voortgezet Onderwijs",
    "sg:phone":"+31 46 420 3700",
    "sg:postcode":"6134 AD",
    "sg:province":"Limburg",
    "sg:website":"http://www.dacapo-college.nl",
    "wof:name":"Dacapo College",
    "wof:placetype":"venue"
},
  "geometry": {"coordinates":[5.859444,50.995422],"type":"Point"}
}