{
  "type": "Feature",
  "properties": {
    "addr:full":"Hollewandswg 20 Zwolle Overijssel 8014 BH",
    "addr:housenumber":"20",
    "addr:postcode":"8014 bh",
    "addr:street":"Hollewandswg",
    "iso:country":"NL",
    "sg:address":"Hollewandswg 20",
    "sg:city":"Zwolle",
    "sg:orig_category":"Bewakingsdiensten",
    "sg:phone":"+31 800 8998668",
    "sg:postcode":"8014 BH",
    "sg:province":"Overijssel",
    "wof:name":"Vnv",
    "wof:placetype":"venue"
},
  "geometry": {"coordinates":[6.12529,52.475159],"type":"Point"}
}