{
  "type": "Feature",
  "properties": {
    "addr:full":"Lyclamastr 1 Appelscha Friesland 8426 EE",
    "addr:housenumber":"1",
    "addr:postcode":"8426 ee",
    "addr:street":"Lyclamastr",
    "iso:country":"NL",
    "sg:address":"Lyclamastr 1",
    "sg:city":"Appelscha",
    "sg:orig_category":"Autorijscholen",
    "sg:phone":"+31 516 431 604",
    "sg:postcode":"8426 EE",
    "sg:province":"Friesland",
    "wof:name":"Bijmholt, Rijschool",
    "wof:placetype":"venue"
},
  "geometry": {"coordinates":[6.360063,52.952518],"type":"Point"}
}