{
  "type": "Feature",
  "properties": {
    "addr:full":"Kanaalweg 85 Sluiskil Zeeland 4541 CA",
    "addr:housenumber":"85",
    "addr:postcode":"4541 ca",
    "addr:street":"Kanaalweg",
    "iso:country":"NL",
    "sg:address":"Kanaalweg 85",
    "sg:city":"Sluiskil",
    "sg:orig_category":"Architecten",
    "sg:phone":"+31 115 477 120",
    "sg:postcode":"4541 CA",
    "sg:province":"Zeeland",
    "wof:name":"Duwi Design Bv",
    "wof:placetype":"venue"
},
  "geometry": {"coordinates":[3.838706,51.278988],"type":"Point"}
}