{
  "type": "Feature",
  "properties": {
    "addr:full":"Uitwijksdijkje 4 Uitwijk Noord-Brabant 4288 JC",
    "addr:housenumber":"4",
    "addr:postcode":"4288 jc",
    "addr:street":"Uitwijksdijkje",
    "iso:country":"NL",
    "sg:address":"Uitwijksdijkje 4",
    "sg:city":"Uitwijk",
    "sg:orig_category":"Bloemen And Planten",
    "sg:phone":"+31 183 441 639",
    "sg:postcode":"4288 JC",
    "sg:province":"Noord-Brabant",
    "wof:name":"G. Nultenb., Handel In Bloemen En Tuinon",
    "wof:placetype":"venue"
},
  "geometry": {"coordinates":[5.008491,51.786705],"type":"Point"}
}