{
  "type": "Feature",
  "properties": {
    "iso:country":"NL",
    "sg:address":"Zeelt 24",
    "sg:city":"Oostzaan",
    "sg:orig_category":"Webdesign Bureaus",
    "sg:phone":"+31 75 684 8231",
    "sg:postcode":"1511 LL",
    "sg:province":"Noord-Holland",
    "sg:website":"http://www.mdb.nl",
    "wof:name":"Mdeb",
    "wof:placetype":"venue"
},
  "geometry": {"coordinates":[4.8686819077,52.4368743896],"type":"Point"}
}