{
  "type": "Feature",
  "properties": {
    "addr:full":"Herenweg 4 Hoogwoud North Holland 1718 AE",
    "addr:housenumber":"4",
    "addr:postcode":"1718 ae",
    "addr:street":"Herenweg",
    "iso:country":"NL",
    "sg:address":"Herenweg 4",
    "sg:city":"Hoogwoud",
    "sg:orig_category":"Overheidsdiensten",
    "sg:phone":"+31 226 353 686",
    "sg:postcode":"1718 AE",
    "sg:province":"North Holland",
    "wof:name":"J.C. Pardoes",
    "wof:placetype":"venue"
},
  "geometry": {"coordinates":[4.9429678917,52.7125587463],"type":"Point"}
}