{
  "type": "Feature",
  "properties": {
    "addr:full":"Postbus 664 Etten Leur North Brabant 4870 AR",
    "addr:housenumber":"664",
    "addr:postcode":"4870",
    "addr:street":"Postbus",
    "iso:country":"NL",
    "sg:address":"Postbus 664",
    "sg:city":"Etten Leur",
    "sg:orig_category":"Verpakkingsbedrijven",
    "sg:phone":"+31 76 503 6259",
    "sg:postcode":"4870 AR",
    "sg:province":"North Brabant",
    "wof:name":"Mf",
    "wof:placetype":"venue"
},
  "geometry": {"coordinates":[4.639522,51.570694],"type":"Point"}
}