{
  "type": "Feature",
  "properties": {
    "iso:country":"NL",
    "sg:address":"Havenstr 8",
    "sg:city":"Terneuzen",
    "sg:orig_category":"Advocaten En Advocatenkantoren",
    "sg:phone":"+31 115 617 733",
    "sg:postcode":"4531 EK",
    "sg:province":"Zeeland",
    "wof:name":"Burlet & Nobus Advocaten",
    "wof:placetype":"venue"
},
  "geometry": {"coordinates":[3.827487,51.337456],"type":"Point"}
}