{
  "type": "Feature",
  "properties": {
    "iso:country":"NL",
    "sg:address":"Merelhof 7",
    "sg:city":"Voorschoten",
    "sg:orig_category":"Overheidsdiensten",
    "sg:phone":"+31 71 561 7766",
    "sg:postcode":"2251 DA",
    "sg:province":"Zuid-Holland",
    "wof:name":"Ruimte Plus",
    "wof:placetype":"venue"
},
  "geometry": {"coordinates":[4.4486308098,52.1236534119],"type":"Point"}
}