{
  "type": "Feature",
  "properties": {
    "addr:full":"Weebosch 31 Bergeyk Noord-Brabant 5571 LV",
    "addr:housenumber":"31",
    "addr:postcode":"5571",
    "addr:street":"Weebosch",
    "iso:country":"NL",
    "sg:address":"Weebosch 31",
    "sg:city":"Bergeyk",
    "sg:orig_category":"Woningstoffeerders",
    "sg:phone":"+31 497 542 014",
    "sg:postcode":"5571 LV",
    "sg:province":"Noord-Brabant",
    "wof:name":"Hbs",
    "wof:placetype":"venue"
},
  "geometry": {"coordinates":[5.2981109619,51.3110847473],"type":"Point"}
}