{
  "type": "Feature",
  "properties": {
    "addr:full":"Spoorsngl 7 Rotterdam South Holland 3033 GE",
    "addr:housenumber":"7",
    "addr:postcode":"3033",
    "addr:street":"Spoorsngl",
    "iso:country":"NL",
    "sg:address":"Spoorsngl 7",
    "sg:city":"Rotterdam",
    "sg:orig_category":"Kappers",
    "sg:phone":"+31 10 466 5030",
    "sg:postcode":"3033 GE",
    "sg:province":"South Holland",
    "sg:website":"http://www.ibw.nl/laakes",
    "wof:name":"Laakes Karl",
    "wof:placetype":"venue"
},
  "geometry": {"coordinates":[4.46912,51.927521],"type":"Point"}
}