{
  "type": "Feature",
  "properties": {
    "addr:full":"Merel 10 Ridderkerk Zuid-Holland 2986 BB",
    "addr:housenumber":"10",
    "addr:postcode":"2986 bb",
    "addr:street":"Merel",
    "iso:country":"NL",
    "sg:address":"Merel 10",
    "sg:city":"Ridderkerk",
    "sg:orig_category":"Onderwijsmateriaal",
    "sg:phone":"+31 180 423 489",
    "sg:postcode":"2986 BB",
    "sg:province":"Zuid-Holland",
    "sg:website":"http://www.infrared.nl",
    "wof:name":"Infrared",
    "wof:placetype":"venue"
},
  "geometry": {"coordinates":[4.609207,51.863853],"type":"Point"}
}