{
  "type": "Feature",
  "properties": {
    "addr:full":"Giessenlaan 26 Giessenburg Zuid-Holland 3381 AM",
    "addr:housenumber":"26",
    "addr:postcode":"3381",
    "addr:street":"Giessenlaan",
    "iso:country":"NL",
    "sg:address":"Giessenlaan 26",
    "sg:city":"Giessenburg",
    "sg:classifiers":[
        {
            "category":"Education",
            "subcategory":"Preschool",
            "type":"Public Place"
        }
    ],
    "sg:phone":"+31 184 652 515",
    "sg:postcode":"3381 AM",
    "sg:province":"Zuid-Holland",
    "sg:tags":[
        "kleuteronderwijs",
        "basis-"
    ],
    "wof:name":"Obs Het Tweespan Locatie Giessen Nieuwkerk",
    "wof:placetype":"venue"
},
  "geometry": {"coordinates":[4.888009,51.850613],"type":"Point"}
}