{
  "type": "Feature",
  "properties": {
    "iso:country":"NL",
    "sg:address":"Postbus 4385",
    "sg:city":"Haarlem",
    "sg:orig_category":"Adviesbureaus Bouwkunde",
    "sg:phone":"+31 297 212 040",
    "sg:postcode":"2003 EJ",
    "sg:province":"Zeeland",
    "sg:website":"http://www.aksbouwmanagement.nl",
    "wof:name":"Aks",
    "wof:placetype":"venue"
},
  "geometry": {"coordinates":[4.64225,52.380562],"type":"Point"}
}