{
  "type": "Feature",
  "properties": {
    "addr:full":"Bleeksteen 17 Delfzyl Groningen 9934 LS",
    "addr:housenumber":"17",
    "addr:postcode":"9934 ls",
    "addr:street":"Bleeksteen",
    "iso:country":"NL",
    "sg:address":"Bleeksteen 17",
    "sg:city":"Delfzyl",
    "sg:orig_category":"Havenbedrijven",
    "sg:phone":"+31 596 613 139",
    "sg:postcode":"9934 LS",
    "sg:province":"Groningen",
    "wof:name":"Bvd/E",
    "wof:placetype":"venue"
},
  "geometry": {"coordinates":[6.90247,53.33028],"type":"Point"}
}