{
  "type": "Feature",
  "properties": {
    "addr:full":"Brouwhuisweg 45 Vlierden North Brabant 5756 PR",
    "addr:housenumber":"45",
    "addr:postcode":"5756 pr",
    "addr:street":"Brouwhuisweg",
    "iso:country":"NL",
    "sg:address":"Brouwhuisweg 45",
    "sg:city":"Vlierden",
    "sg:orig_category":"Verhuisdiensten",
    "sg:phone":"+31 493 315 429",
    "sg:postcode":"5756 PR",
    "sg:province":"North Brabant",
    "wof:name":"Firma Keijsers En De Klijn",
    "wof:placetype":"venue"
},
  "geometry": {"coordinates":[5.729752,51.44315],"type":"Point"}
}