{
  "type": "Feature",
  "properties": {
    "addr:full":"De Singel 26 Dalfsen NL.08 7722 RR",
    "addr:housenumber":"26;nl.08",
    "addr:postcode":"7722 rr",
    "addr:street":"De Singel",
    "iso:country":"NL",
    "sg:address":"De Singel 26",
    "sg:city":"Dalfsen",
    "sg:orig_category":"Kantoorartikelen",
    "sg:phone":"+31 529 432 532",
    "sg:postcode":"7722 RR",
    "sg:province":"NL.08",
    "wof:name":"Roessink Kantoormeubelen Bv",
    "wof:placetype":"venue"
},
  "geometry": {"coordinates":[6.2663149834,52.5107345581],"type":"Point"}
}