{
  "type": "Feature",
  "properties": {
    "addr:full":"Stroesln 4 Hilversum Noord-Holland 1222 EG",
    "addr:housenumber":"4",
    "addr:postcode":"1222 eg",
    "addr:street":"Stroesln",
    "iso:country":"NL",
    "sg:address":"Stroesln 4",
    "sg:city":"Hilversum",
    "sg:orig_category":"Peuterspeelzalen",
    "sg:phone":"+31 35 685 8896",
    "sg:postcode":"1222 EG",
    "sg:province":"Noord-Holland",
    "wof:name":"Troetelbeertje, Het",
    "wof:placetype":"venue"
},
  "geometry": {"coordinates":[5.18488,52.2495],"type":"Point"}
}