{
  "type": "Feature",
  "properties": {
    "addr:full":"Buitenlevenglop 3 Terschelling Midld Provincie Friesland 8891 GJ",
    "addr:housenumber":"3",
    "addr:postcode":"8891 gj",
    "addr:street":"Buitenlevenglop;Friesland",
    "iso:country":"NL",
    "sg:address":"Buitenlevenglop 3",
    "sg:city":"Terschelling Midld",
    "sg:orig_category":"Onderhoudswerken",
    "sg:phone":"+31 6 29592449",
    "sg:postcode":"8891 GJ",
    "sg:province":"Provincie Friesland",
    "wof:name":"Apeneutje, 'T",
    "wof:placetype":"venue"
},
  "geometry": {"coordinates":[5.28571,53.382603],"type":"Point"}
}