{
  "type": "Feature",
  "properties": {
    "addr:full":"Mandepad 7 Broek Op Langedyk Noord-Holland 1721 CE",
    "addr:housenumber":"7",
    "addr:postcode":"1721 ce",
    "addr:street":"Mandepad;Op Langedyk",
    "iso:country":"NL",
    "sg:address":"Mandepad 7",
    "sg:city":"Broek Op Langedyk",
    "sg:orig_category":"Autoschade- Herstelbedrijven",
    "sg:phone":"+31 226 314 283",
    "sg:postcode":"1721 CE",
    "sg:province":"Noord-Holland",
    "wof:name":"Pas, R Van De",
    "wof:placetype":"venue"
},
  "geometry": {"coordinates":[4.804341,52.67527],"type":"Point"}
}