{
  "type": "Feature",
  "properties": {
    "iso:country":"NL",
    "sg:address":"Mandepad 7",
    "sg:city":"Broek Op Langedyk",
    "sg:orig_category":"Autoschade- Herstelbedrijven",
    "sg:phone":"+31 226 314 283",
    "sg:postcode":"1721 CE",
    "sg:province":"Noord-Holland",
    "wof:name":"Pas, R Van De",
    "wof:placetype":"venue"
},
  "geometry": {"coordinates":[4.804341,52.67527],"type":"Point"}
}