{
  "type": "Feature",
  "properties": {
    "iso:country":"NL",
    "sg:address":"Kinkerstraat 72A",
    "sg:city":"Amsterdam",
    "sg:classifiers":[
        {
            "category":"Fast Food",
            "type":"Food & Drink"
        }
    ],
    "sg:phone":"+31 20 616 2055",
    "sg:postcode":"1053 EA",
    "sg:province":"Noord-Holland",
    "sg:tags":[
        "afhaal",
        "restaurant"
    ],
    "wof:name":"Kinker",
    "wof:placetype":"venue"
},
  "geometry": {"coordinates":[4.872504,52.3675],"type":"Point"}
}