{
  "type": "Feature",
  "properties": {
    "addr:full":"Grote Kerkstraat 8 Wijk En Aalburg Noord-Brabant 4261 BD",
    "addr:housenumber":"8",
    "addr:postcode":"4261 bd",
    "addr:street":"Grote Kerkstraat",
    "iso:country":"NL",
    "sg:address":"Grote Kerkstraat 8",
    "sg:city":"Wijk En Aalburg",
    "sg:orig_category":"Goederenvervoer Over De Weg",
    "sg:phone":"+31 416 691 719",
    "sg:postcode":"4261 BD",
    "sg:province":"Noord-Brabant",
    "wof:name":"Transportbedrijf L. Van Zandwijk Bv",
    "wof:placetype":"venue"
},
  "geometry": {"coordinates":[5.13236,51.757183],"type":"Point"}
}