{
  "type": "Feature",
  "properties": {
    "addr:full":"Klimop 2A Roden Provincie Drenthe 9301 PK",
    "addr:housenumber":"2a",
    "addr:postcode":"9301 pk",
    "addr:street":"Klimop;Provincie Drenthe",
    "iso:country":"NL",
    "sg:address":"Klimop 2A",
    "sg:city":"Roden",
    "sg:orig_category":"Verenigingen En Stichtingen",
    "sg:phone":"+31 50 501 3383",
    "sg:postcode":"9301 PK",
    "sg:province":"Provincie Drenthe",
    "wof:name":"Bomenbuurt Buurtver",
    "wof:placetype":"venue"
},
  "geometry": {"coordinates":[6.420993,53.144852],"type":"Point"}
}