{
  "type": "Feature",
  "properties": {
    "addr:full":"Peperstr 7-9 Amsterdam Noord-Holland 1011 TJ",
    "addr:housenumber":"7-9",
    "addr:postcode":"1011 tj",
    "addr:street":"Peperstr",
    "iso:country":"NL",
    "sg:address":"Peperstr 7-9",
    "sg:city":"Amsterdam",
    "sg:orig_category":"Fotografie Reclame En Mode",
    "sg:phone":"+31 20 427 3616",
    "sg:postcode":"1011 TJ",
    "sg:province":"Noord-Holland",
    "sg:website":"http://www.jonathanandrew.nl",
    "wof:name":"Andrew Jonathan Photography",
    "wof:placetype":"venue"
},
  "geometry": {"coordinates":[4.908435,52.371956],"type":"Point"}
}