{
  "type": "Feature",
  "properties": {
    "addr:full":"Weerdjesln 16 Doetinchem Gelderland 7006 BC",
    "addr:housenumber":"16",
    "addr:postcode":"7006 bc",
    "addr:street":"Weerdjesln;Gelderland",
    "iso:country":"NL",
    "sg:address":"Weerdjesln 16",
    "sg:city":"Doetinchem",
    "sg:orig_category":"Administratie- En Boekhoudkantoren",
    "sg:phone":"+31 314 340 485",
    "sg:postcode":"7006 BC",
    "sg:province":"Gelderland",
    "wof:name":"Kgp",
    "wof:placetype":"venue"
},
  "geometry": {"coordinates":[6.291055,51.963596],"type":"Point"}
}