{
  "type": "Feature",
  "properties": {
    "addr:full":"Krombraak 5 Oosterhout Nb Noord-Brabant 4906 CR",
    "addr:housenumber":"5",
    "addr:postcode":"4906 cr",
    "addr:street":"Krombraak",
    "iso:country":"NL",
    "sg:address":"Krombraak 5",
    "sg:city":"Oosterhout Nb",
    "sg:orig_category":"Kantoormachines Geen Computers Fab",
    "sg:phone":"+31 162 457 979",
    "sg:postcode":"4906 CR",
    "sg:province":"Noord-Brabant",
    "wof:name":"Multimark",
    "wof:placetype":"venue"
},
  "geometry": {"coordinates":[4.8394098282,51.6514892578],"type":"Point"}
}