{
  "type": "Feature",
  "properties": {
    "iso:country":"NL",
    "sg:address":"Bolstralaan 46",
    "sg:city":"Hoofddorp",
    "sg:orig_category":"Fotostudio'S And Fotografen",
    "sg:phone":"+31 23 561 4049",
    "sg:postcode":"2132 PM",
    "sg:province":"North Holland",
    "wof:name":"J.R.E. Beun",
    "wof:placetype":"venue"
},
  "geometry": {"coordinates":[4.710146,52.302895],"type":"Point"}
}