{
  "type": "Feature",
  "properties": {
    "addr:full":"Hinthamerstraat 144 'S Hertogenbosch Noord-Brabant 5211 MT",
    "addr:housenumber":"144 ' s",
    "addr:postcode":"5211",
    "addr:street":"Hinthamerstraat;Mt",
    "iso:country":"NL",
    "sg:address":"Hinthamerstraat 144",
    "sg:city":"'S Hertogenbosch",
    "sg:orig_category":"Voeding, Dranken And Tabak Gh",
    "sg:phone":"+31 73 614 3484",
    "sg:postcode":"5211 MT",
    "sg:province":"Noord-Brabant",
    "wof:name":"Surinaamse Winkel Shera",
    "wof:placetype":"venue"
},
  "geometry": {"coordinates":[5.311178,51.688663],"type":"Point"}
}