{
  "type": "Feature",
  "properties": {
    "addr:full":"Oude Vaart 125 Terneuzen Zeeland 4537 CE",
    "addr:housenumber":"125",
    "addr:postcode":"4537 ce",
    "addr:street":"Oude Vaart",
    "iso:country":"NL",
    "sg:address":"Oude Vaart 125",
    "sg:city":"Terneuzen",
    "sg:orig_category":"Sportverenigingen En Ontspannings- Verenigingen",
    "sg:phone":"+31 115 631 213",
    "sg:postcode":"4537 CE",
    "sg:province":"Zeeland",
    "wof:name":"Luctor Korfbalver",
    "wof:placetype":"venue"
},
  "geometry": {"coordinates":[3.827559,51.338146],"type":"Point"}
}