{
  "type": "Feature",
  "properties": {
    "addr:full":"Jennerstr 23 Amsterdam North Holland 1097 GB",
    "addr:housenumber":"23",
    "addr:postcode":"1097 gb",
    "addr:street":"Jennerstr",
    "iso:country":"NL",
    "sg:address":"Jennerstr 23",
    "sg:city":"Amsterdam",
    "sg:orig_category":"Psychotherapeuten",
    "sg:phone":"+31 20 623 9209",
    "sg:postcode":"1097 GB",
    "sg:province":"North Holland",
    "wof:name":"Schaik, Drs J G Van",
    "wof:placetype":"venue"
},
  "geometry": {"coordinates":[4.938691,52.347569],"type":"Point"}
}