{
  "type": "Feature",
  "properties": {
    "iso:country":"NL",
    "sg:address":"Klarinetsngl 74",
    "sg:city":"Zwyndrecht",
    "sg:orig_category":"Adviesbureaus Bedrijfsorganisatie",
    "sg:phone":"+31 78 610 6874",
    "sg:postcode":"3335 DE",
    "sg:province":"South Holland",
    "sg:website":"http://www.puijker.nl",
    "wof:name":"Puijker",
    "wof:placetype":"venue"
},
  "geometry": {"coordinates":[4.609739,51.821396],"type":"Point"}
}