{
  "type": "Feature",
  "properties": {
    "iso:country":"NL",
    "sg:address":"Aggemastate 97",
    "sg:city":"Leeuwarden",
    "sg:orig_category":"Grafmonumenten",
    "sg:phone":"+31 58 266 5732",
    "sg:postcode":"8926 PB",
    "sg:province":"Provincie Friesland",
    "sg:website":"http://www.sevenster-gedenkstenen.nl",
    "wof:name":"Sevenster",
    "wof:placetype":"venue"
},
  "geometry": {"coordinates":[5.831561,53.216385],"type":"Point"}
}