{
  "type": "Feature",
  "properties": {
    "addr:full":"Industrieweg 1 Emmeloord NL. 8304 AC",
    "addr:housenumber":"1",
    "addr:postcode":"8304 ac",
    "addr:street":"Industrieweg;Nl.",
    "iso:country":"NL",
    "sg:address":"Industrieweg 1",
    "sg:city":"Emmeloord",
    "sg:orig_category":"Loodgieterswerk, Verwarming And Sanitaire Installaties",
    "sg:phone":"+31 527 632 911",
    "sg:postcode":"8304 AC",
    "sg:province":"NL.",
    "wof:name":"Acm Emmeloord",
    "wof:placetype":"venue"
},
  "geometry": {"coordinates":[5.74604,52.703197],"type":"Point"}
}