{
  "type": "Feature",
  "properties": {
    "addr:full":"Kzr Karelwg 92 Amstelveen North Holland 1185 HX",
    "addr:housenumber":"92",
    "addr:postcode":"1185 hx",
    "iso:country":"NL",
    "sg:address":"Kzr Karelwg 92",
    "sg:city":"Amstelveen",
    "sg:orig_category":"Bedrijfsopleidingen",
    "sg:phone":"+31 20 641 5660",
    "sg:postcode":"1185 HX",
    "sg:province":"North Holland",
    "wof:name":"Wisse Communicatie",
    "wof:placetype":"venue"
},
  "geometry": {"coordinates":[4.850319,52.297348],"type":"Point"}
}