{
  "type": "Feature",
  "properties": {
    "addr:full":"Gen Winkelmanstr 175 Tilburg North Brabant 5025 XG",
    "addr:housenumber":"175",
    "addr:postcode":"5025 xg",
    "iso:country":"NL",
    "sg:address":"Gen Winkelmanstr 175",
    "sg:city":"Tilburg",
    "sg:orig_category":"Bejaarden - Verzorgingstehuizen",
    "sg:phone":"+31 13 465 7700",
    "sg:postcode":"5025 XG",
    "sg:province":"North Brabant",
    "sg:website":"http://www.hetlaar.nl",
    "wof:name":"Laar, Het",
    "wof:placetype":"venue"
},
  "geometry": {"coordinates":[5.059613,51.544106],"type":"Point"}
}