{
  "type": "Feature",
  "properties": {
    "addr:full":"Stationsstraat 12 Markelo NL.08 7475 AM",
    "addr:housenumber":"12;nl.08",
    "addr:postcode":"7475",
    "addr:street":"Stationsstraat",
    "iso:country":"NL",
    "sg:address":"Stationsstraat 12",
    "sg:city":"Markelo",
    "sg:orig_category":"Diverse Grafische Activiteiten",
    "sg:phone":"+31 547 363 348",
    "sg:postcode":"7475 AM",
    "sg:province":"NL.08",
    "wof:name":"Leen Brouwer Illustraties",
    "wof:placetype":"venue"
},
  "geometry": {"coordinates":[6.495555,52.23299],"type":"Point"}
}