{
  "type": "Feature",
  "properties": {
    "iso:country":"NL",
    "sg:address":"Wycker Brugstraat 5",
    "sg:city":"Maastricht",
    "sg:classifiers":[
        {
            "category":"Food & Beverages",
            "subcategory":"Fruits & Vegetables",
            "type":"Retail Goods"
        }
    ],
    "sg:phone":"+31 43 321 1963",
    "sg:postcode":"6221 EA",
    "sg:province":"Limburg",
    "sg:tags":[
        "groenten"
    ],
    "wof:name":"Greenshop Van Appeven Vof",
    "wof:placetype":"venue"
},
  "geometry": {"coordinates":[5.700607,50.84938],"type":"Point"}
}