{
  "type": "Feature",
  "properties": {
    "addr:full":"Eendrachtstr 3G Wormer North Holland 1531 DT",
    "addr:housenumber":"3g",
    "addr:postcode":"1531 dt",
    "addr:street":"Eendrachtstr",
    "iso:country":"NL",
    "sg:address":"Eendrachtstr 3G",
    "sg:city":"Wormer",
    "sg:orig_category":"Autoreclame",
    "sg:phone":"+31 75 642 7133",
    "sg:postcode":"1531 DT",
    "sg:province":"North Holland",
    "wof:name":"Future Design",
    "wof:placetype":"venue"
},
  "geometry": {"coordinates":[4.812706,52.490421],"type":"Point"}
}