{
  "type": "Feature",
  "properties": {
    "iso:country":"NL",
    "sg:address":"Leidsevaart 366",
    "sg:city":"Haarlem",
    "sg:orig_category":"Fitnesscentra",
    "sg:phone":"+31 23 524 7108",
    "sg:postcode":"2014 HL",
    "sg:province":"Noord-Holland",
    "wof:name":"Fitness Centrum Olympic",
    "wof:placetype":"venue"
},
  "geometry": {"coordinates":[4.617416,52.370525],"type":"Point"}
}