{
  "type": "Feature",
  "properties": {
    "iso:country":"NL",
    "sg:address":"Prins Hendrikplein 14",
    "sg:city":"'S Gravenhage",
    "sg:orig_category":"Werving And Selectie Van Tijdelijk Personeel And Uitzendkantoren",
    "sg:phone":"+31 70 346 7276",
    "sg:postcode":"2518 JC",
    "sg:province":"South Holland",
    "wof:name":"Cane",
    "wof:placetype":"venue"
},
  "geometry": {"coordinates":[4.2941417694,52.08203125],"type":"Point"}
}