{
  "type": "Feature",
  "properties": {
    "addr:full":"Boekweitstr 66 Nieuw Vennep Noord-Holland 2153 GL",
    "addr:housenumber":"66",
    "addr:postcode":"2153 gl",
    "addr:street":"Boekweitstr;Nieuw Vennep",
    "iso:country":"NL",
    "sg:address":"Boekweitstr 66",
    "sg:city":"Nieuw Vennep",
    "sg:orig_category":"Verenigingen En Stichtingen",
    "sg:phone":"+31 252 680 444",
    "sg:postcode":"2153 GL",
    "sg:province":"Noord-Holland",
    "wof:name":"Verwarming En Sanitair, Sticht",
    "wof:placetype":"venue"
},
  "geometry": {"coordinates":[4.650062,52.26659],"type":"Point"}
}