{
  "type": "Feature",
  "properties": {
    "iso:country":"NL",
    "sg:address":"Zeeweg 10",
    "sg:city":"Castricum",
    "sg:classifiers":[
        {
            "category":"Fast Food",
            "type":"Food & Drink"
        }
    ],
    "sg:phone":"+31 251 653 524",
    "sg:postcode":"1901 NZ",
    "sg:province":"Noord-Holland",
    "sg:tags":[
        "afhaal",
        "restaurant"
    ],
    "wof:name":"Strandpaviljoen De Jutter",
    "wof:placetype":"venue"
},
  "geometry": {"coordinates":[4.651557,52.56213],"type":"Point"}
}