{
  "type": "Feature",
  "properties": {
    "addr:full":"Holendrechtpln 37-38 Amsterdam Zuidoost North Holland 1106 LP",
    "addr:housenumber":"37-38",
    "addr:postcode":"1106 lp",
    "iso:country":"NL",
    "sg:address":"Holendrechtpln 37-38",
    "sg:city":"Amsterdam Zuidoost",
    "sg:orig_category":"Verenigingsgebouwen",
    "sg:phone":"+31 20 696 6389",
    "sg:postcode":"1106 LP",
    "sg:province":"North Holland",
    "wof:name":"Holendrecht Bzo",
    "wof:placetype":"venue"
},
  "geometry": {"coordinates":[4.964349,52.299805],"type":"Point"}
}