{
  "type": "Feature",
  "properties": {
    "addr:full":"Moliereln 132 Venlo Limburg 5924 AN",
    "addr:housenumber":"132",
    "addr:postcode":"5924 an",
    "iso:country":"NL",
    "sg:address":"Moliereln 132",
    "sg:city":"Venlo",
    "sg:orig_category":"Huidtherapeuten",
    "sg:phone":"+31 77 477 2597",
    "sg:postcode":"5924 AN",
    "sg:province":"Limburg",
    "wof:name":"Kleij-Van Lierop, E J G Van Der",
    "wof:placetype":"venue"
},
  "geometry": {"coordinates":[6.13,51.366501],"type":"Point"}
}