{
  "type": "Feature",
  "properties": {
    "addr:full":"Gen Foulkeswg 74 Wageningen Gelderland 6703 BW",
    "addr:housenumber":"74",
    "addr:postcode":"6703 bw",
    "addr:street":"Gelderland",
    "iso:country":"NL",
    "sg:address":"Gen Foulkeswg 74",
    "sg:city":"Wageningen",
    "sg:orig_category":"Verenigingen En Stichtingen",
    "sg:phone":"+31 317 412 909",
    "sg:postcode":"6703 BW",
    "sg:province":"Gelderland",
    "wof:name":"Jongerenver Unitas",
    "wof:placetype":"venue"
},
  "geometry": {"coordinates":[5.679784,51.966721],"type":"Point"}
}