{
  "type": "Feature",
  "properties": {
    "addr:full":"Kissel 46 Heerlen Limburg 6416 AC",
    "addr:housenumber":"46",
    "addr:postcode":"6416 ac",
    "addr:street":"Kissel",
    "iso:country":"NL",
    "sg:address":"Kissel 46",
    "sg:city":"Heerlen",
    "sg:orig_category":"Autokeuringen",
    "sg:phone":"+31 45 572 5447",
    "sg:postcode":"6416 AC",
    "sg:province":"Limburg",
    "wof:name":"Peter Maassen",
    "wof:placetype":"venue"
},
  "geometry": {"coordinates":[6.000796,50.889565],"type":"Point"}
}