{
  "type": "Feature",
  "properties": {
    "addr:full":"Beyerinckwg 38 Arnhem Gelderland 6827 BN",
    "addr:housenumber":"38",
    "addr:postcode":"6827 bn",
    "addr:street":"Beyerinckwg",
    "iso:country":"NL",
    "sg:address":"Beyerinckwg 38",
    "sg:city":"Arnhem",
    "sg:orig_category":"Autorijscholen",
    "sg:phone":"+31 26 364 2353",
    "sg:postcode":"6827 BN",
    "sg:province":"Gelderland",
    "wof:name":"Peters, Theo",
    "wof:placetype":"venue"
},
  "geometry": {"coordinates":[5.9358,51.96431],"type":"Point"}
}