{
  "type": "Feature",
  "properties": {
    "addr:full":"Boccherinistr 9 Castricum Noord-Holland 1901 VB",
    "addr:housenumber":"9",
    "addr:postcode":"1901 vb",
    "addr:street":"Boccherinistr",
    "iso:country":"NL",
    "sg:address":"Boccherinistr 9",
    "sg:city":"Castricum",
    "sg:orig_category":"Adviesbureaus Bedrijfsorganisatie",
    "sg:phone":"+31 251 671 449",
    "sg:postcode":"1901 VB",
    "sg:province":"Noord-Holland",
    "wof:name":"Fore C",
    "wof:placetype":"venue"
},
  "geometry": {"coordinates":[4.6717767715,52.5556983948],"type":"Point"}
}