{
  "type": "Feature",
  "properties": {
    "addr:full":"Dalmeyerplein 12 Dordrecht Zuid-Holland 3318 CB",
    "addr:housenumber":"12",
    "addr:postcode":"3318 cb",
    "addr:street":"Dalmeyerplein",
    "iso:country":"NL",
    "sg:address":"Dalmeyerplein 12",
    "sg:city":"Dordrecht",
    "sg:orig_category":"Bibliotheken And Openbare Archieven",
    "sg:phone":"+31 78 617 3229",
    "sg:postcode":"3318 CB",
    "sg:province":"Zuid-Holland",
    "wof:name":"Openbare Bibliotheek Sterrenburg",
    "wof:placetype":"venue"
},
  "geometry": {"coordinates":[4.678123,51.785213],"type":"Point"}
}