{
  "type": "Feature",
  "properties": {
    "addr:full":"Dovenetelhof 3 Baarn Utrecht 3742 EG",
    "addr:housenumber":"3",
    "addr:postcode":"3742 eg",
    "addr:street":"Dovenetelhof",
    "iso:country":"NL",
    "sg:address":"Dovenetelhof 3",
    "sg:city":"Baarn",
    "sg:orig_category":"Onderhoudswerken",
    "sg:phone":"+31 35 541 6642",
    "sg:postcode":"3742 EG",
    "sg:province":"Utrecht",
    "wof:name":"Voortgang, De",
    "wof:placetype":"venue"
},
  "geometry": {"coordinates":[5.301896,52.200436],"type":"Point"}
}