{
  "type": "Feature",
  "properties": {
    "addr:full":"Mr Hennequinln 9 Cadzand Zeeland 4506 JP",
    "addr:housenumber":"9",
    "addr:postcode":"4506 jp",
    "iso:country":"NL",
    "sg:address":"Mr Hennequinln 9",
    "sg:city":"Cadzand",
    "sg:orig_category":"Vakantieverblijven",
    "sg:phone":"+31 117 391 256",
    "sg:postcode":"4506 JP",
    "sg:province":"Zeeland",
    "wof:name":"Goede Ree",
    "wof:placetype":"venue"
},
  "geometry": {"coordinates":[3.390878,51.377529],"type":"Point"}
}