{
  "type": "Feature",
  "properties": {
    "iso:country":"NL",
    "sg:address":"Hippolytusbuurt 17",
    "sg:city":"Delft",
    "sg:orig_category":"Wasserettes And Stomerijen",
    "sg:phone":"+31 15 212 4780",
    "sg:postcode":"2611 HM",
    "sg:province":"Zuid-Holland",
    "wof:name":"Palthe Stomerijen Bv",
    "wof:placetype":"venue"
},
  "geometry": {"coordinates":[4.3569102287,52.0118713379],"type":"Point"}
}