{
  "type": "Feature",
  "properties": {
    "addr:full":"Hoofdwg 272 Bellingwolde Groningen 9695 AW",
    "addr:housenumber":"272",
    "addr:postcode":"9695 aw",
    "iso:country":"NL",
    "sg:address":"Hoofdwg 272",
    "sg:city":"Bellingwolde",
    "sg:orig_category":"Postkantoren",
    "sg:phone":"+31 597 531 440",
    "sg:postcode":"9695 AW",
    "sg:province":"Groningen",
    "sg:website":"http://www.postkantoor.nl",
    "wof:name":"Postkantoor",
    "wof:placetype":"venue"
},
  "geometry": {"coordinates":[7.168927,53.122955],"type":"Point"}
}