{
  "type": "Feature",
  "properties": {
    "iso:country":"NL",
    "sg:address":"Reguliersdwstr 70",
    "sg:city":"Amsterdam",
    "sg:orig_category":"Koffie- En Theehuizen",
    "sg:phone":"+31 20 622 7727",
    "sg:postcode":"1017 BN",
    "sg:province":"Noord-Holland",
    "wof:name":"Free I",
    "wof:placetype":"venue"
},
  "geometry": {"coordinates":[4.893275,52.365997],"type":"Point"}
}