{
  "type": "Feature",
  "properties": {
    "addr:full":"Oude Baan 7 Rosmalen Noord-Brabant 5242 HT",
    "addr:housenumber":"7",
    "addr:postcode":"5242 ht",
    "addr:street":"Oude Baan",
    "iso:country":"NL",
    "sg:address":"Oude Baan 7",
    "sg:city":"Rosmalen",
    "sg:orig_category":"Accountants - Administratie- Consulenten En -Kantoren",
    "sg:phone":"+31 73 521 1525",
    "sg:postcode":"5242 HT",
    "sg:province":"Noord-Brabant",
    "wof:name":"Bergeijk Bv, Adri Van",
    "wof:placetype":"venue"
},
  "geometry": {"coordinates":[5.363903,51.708282],"type":"Point"}
}