{
  "type": "Feature",
  "properties": {
    "addr:full":"Tiber 84 S Gravenhage 2491 DK",
    "addr:housenumber":"84",
    "addr:postcode":"2491 dk",
    "addr:street":"Tiber;S Gravenhage",
    "iso:country":"NL",
    "sg:address":"Tiber 84",
    "sg:city":"S Gravenhage",
    "sg:orig_category":"Beveiliging",
    "sg:phone":"+31 70 320 2681",
    "sg:postcode":"2491 DK",
    "wof:name":"Tss",
    "wof:placetype":"venue"
},
  "geometry": {"coordinates":[4.38382,52.065289],"type":"Point"}
}