{
  "type": "Feature",
  "properties": {
    "addr:full":"N Dillenburgstr 44 S Gravenhage Zuid-Holland 2596 AE",
    "addr:housenumber":"44;gravenhage",
    "addr:postcode":"2596 ae",
    "addr:street":"N;S",
    "iso:country":"NL",
    "sg:address":"N Dillenburgstr 44",
    "sg:city":"S Gravenhage",
    "sg:orig_category":"Verenigingen En Stichtingen",
    "sg:phone":"+31 70 324 4526",
    "sg:postcode":"2596 AE",
    "sg:province":"Zuid-Holland",
    "sg:website":"http://www.inta-net.org",
    "wof:name":"Inta Int Network For Urban Development",
    "wof:placetype":"venue"
},
  "geometry": {"coordinates":[4.31846,52.093311],"type":"Point"}
}