{
  "type": "Feature",
  "properties": {
    "iso:country":"NL",
    "sg:address":"Schoolstr 17 De Wilp",
    "sg:city":"De Wilp Gn",
    "sg:orig_category":"Verenigingsgebouwen",
    "sg:phone":"+31 594 641 795",
    "sg:postcode":"9367 PX",
    "sg:province":"Groningen",
    "wof:name":"Dorpshuis",
    "wof:placetype":"venue"
},
  "geometry": {"coordinates":[6.252655,53.11512],"type":"Point"}
}