{
  "type": "Feature",
  "properties": {
    "addr:full":"Okeghemstr 5 Amsterdam North Holland 1075 PJ",
    "addr:housenumber":"5",
    "addr:postcode":"1075 pj",
    "addr:street":"Okeghemstr",
    "iso:country":"NL",
    "sg:address":"Okeghemstr 5",
    "sg:city":"Amsterdam",
    "sg:orig_category":"Huidtherapeuten",
    "sg:phone":"+31 20 676 4240",
    "sg:postcode":"1075 PJ",
    "sg:province":"North Holland",
    "wof:name":"Sillevis Smitt, M W",
    "wof:placetype":"venue"
},
  "geometry": {"coordinates":[4.862918,52.352337],"type":"Point"}
}