{
  "type": "Feature",
  "properties": {
    "addr:full":"Nassaulaan 68 Schiedam Zuid-Holland 3116 EX",
    "addr:housenumber":"68",
    "addr:postcode":"3116 ex",
    "addr:street":"Nassaulaan",
    "iso:country":"NL",
    "sg:address":"Nassaulaan 68",
    "sg:city":"Schiedam",
    "sg:orig_category":"Begrafenisondernemers",
    "sg:phone":"+31 10 426 7678",
    "sg:postcode":"3116 EX",
    "sg:province":"Zuid-Holland",
    "wof:name":"Monuta",
    "wof:placetype":"venue"
},
  "geometry": {"coordinates":[4.399249,51.910149],"type":"Point"}
}