{
  "type": "Feature",
  "properties": {
    "addr:full":"Rynstr 2 Ymuiden Noord-Holland 1972 VG",
    "addr:housenumber":"2",
    "addr:postcode":"1972 vg",
    "addr:street":"Rynstr",
    "iso:country":"NL",
    "sg:address":"Rynstr 2",
    "sg:city":"Ymuiden",
    "sg:orig_category":"Verenigingsgebouwen",
    "sg:phone":"+31 255 520 960",
    "sg:postcode":"1972 VG",
    "sg:province":"Noord-Holland",
    "wof:name":"Delta-Dienstencentr Voor Ouderen, De",
    "wof:placetype":"venue"
},
  "geometry": {"coordinates":[4.61762,52.458302],"type":"Point"}
}