{
  "type": "Feature",
  "properties": {
    "addr:full":"Venneweide 23 Breda North Brabant 4824 EL",
    "addr:housenumber":"23",
    "addr:postcode":"4824 el",
    "addr:street":"Venneweide",
    "iso:country":"NL",
    "sg:address":"Venneweide 23",
    "sg:city":"Breda",
    "sg:orig_category":"Psychologen",
    "sg:phone":"+31 76 542 6951",
    "sg:postcode":"4824 EL",
    "sg:province":"North Brabant",
    "wof:name":"Gurchom, Drs M E H Van",
    "wof:placetype":"venue"
},
  "geometry": {"coordinates":[4.748164,51.609966],"type":"Point"}
}