{
  "type": "Feature",
  "properties": {
    "addr:full":"Hof Van Delftlaan 63 Delft Zuid-Holland 2613 BK",
    "addr:housenumber":"63",
    "addr:postcode":"2613 bk",
    "addr:street":"Hof Van Delftlaan",
    "iso:country":"NL",
    "sg:address":"Hof Van Delftlaan 63",
    "sg:city":"Delft",
    "sg:orig_category":"Kappers",
    "sg:phone":"+31 15 212 2286",
    "sg:postcode":"2613 BK",
    "sg:province":"Zuid-Holland",
    "wof:name":"Kapsalon De Hoofdzaak",
    "wof:placetype":"venue"
},
  "geometry": {"coordinates":[4.3478360176,52.0125389099],"type":"Point"}
}