{
  "type": "Feature",
  "properties": {
    "addr:full":"G V Amstelstr 365 Hilversum Noord-Holland 1215 CP",
    "addr:housenumber":"365",
    "addr:postcode":"1215 cp",
    "addr:street":"V Amstelstr",
    "iso:country":"NL",
    "sg:address":"G V Amstelstr 365",
    "sg:city":"Hilversum",
    "sg:orig_category":"Adviesbureaus Bouwkunde",
    "sg:phone":"+31 35 621 9191",
    "sg:postcode":"1215 CP",
    "sg:province":"Noord-Holland",
    "wof:name":"Potters'Bto",
    "wof:placetype":"venue"
},
  "geometry": {"coordinates":[5.1695,52.228565],"type":"Point"}
}