{
  "type": "Feature",
  "properties": {
    "addr:full":"Waterstraat 119-121 Nijmegen Gelderland 6541 TE",
    "addr:housenumber":"119-121",
    "addr:postcode":"6541 te",
    "addr:street":"Waterstraat;Gelderland",
    "iso:country":"NL",
    "sg:address":"Waterstraat 119-121",
    "sg:city":"Nijmegen",
    "sg:orig_category":"Wasserettes And Stomerijen",
    "sg:phone":"+31 24 377 2437",
    "sg:postcode":"6541 TE",
    "sg:province":"Gelderland",
    "wof:name":"Stomerij Perfecta Swagemakers",
    "wof:placetype":"venue"
},
  "geometry": {"coordinates":[5.8422970772,51.8485832214],"type":"Point"}
}