{
  "type": "Feature",
  "properties": {
    "addr:full":"Petrus Campersingel 265 Groningen Groningen 9713 AR",
    "addr:housenumber":"265",
    "addr:postcode":"9713",
    "addr:street":"Petrus Campersingel",
    "iso:country":"NL",
    "sg:address":"Petrus Campersingel 265",
    "sg:city":"Groningen",
    "sg:orig_category":"Artsen And Specialisten",
    "sg:phone":"+31 50 312 9440",
    "sg:postcode":"9713 AR",
    "sg:province":"Groningen",
    "wof:name":"J.G.A. Zijp Huisarts",
    "wof:placetype":"venue"
},
  "geometry": {"coordinates":[6.574856,53.22509],"type":"Point"}
}