{
  "type": "Feature",
  "properties": {
    "iso:country":"NL",
    "sg:address":"Luzernestr 10",
    "sg:city":"Nieuw Vennep",
    "sg:orig_category":"Gehandicapten - Hulpmiddelen",
    "sg:phone":"+31 252 621 848",
    "sg:postcode":"2153 GN",
    "sg:province":"Noord-Holland",
    "wof:name":"Leja Products Bv",
    "wof:placetype":"venue"
},
  "geometry": {"coordinates":[4.648217,52.263359],"type":"Point"}
}