{
  "type": "Feature",
  "properties": {
    "addr:full":"Beiroetstr 99 Rotterdam Zuid-Holland 3067 MA",
    "addr:housenumber":"99",
    "addr:postcode":"3067 ma",
    "addr:street":"Beiroetstr",
    "iso:country":"NL",
    "sg:address":"Beiroetstr 99",
    "sg:city":"Rotterdam",
    "sg:orig_category":"Podotherapeuten",
    "sg:phone":"+31 10 455 7755",
    "sg:postcode":"3067 MA",
    "sg:province":"Zuid-Holland",
    "wof:name":"Podotherapie, Praktijk",
    "wof:placetype":"venue"
},
  "geometry": {"coordinates":[4.557838,51.946663],"type":"Point"}
}