{
  "type": "Feature",
  "properties": {
    "addr:full":"Rozenstraat 37 Bergen Op Zoom Noord-Brabant 4613 AH",
    "addr:housenumber":"37",
    "addr:postcode":"4613 ah",
    "addr:street":"Rozenstraat",
    "iso:country":"NL",
    "sg:address":"Rozenstraat 37",
    "sg:city":"Bergen Op Zoom",
    "sg:orig_category":"Boekhouders",
    "sg:phone":"+31 164 261 204",
    "sg:postcode":"4613 AH",
    "sg:province":"Noord-Brabant",
    "wof:name":"Toledia",
    "wof:placetype":"venue"
},
  "geometry": {"coordinates":[4.283173,51.501732],"type":"Point"}
}