{
  "type": "Feature",
  "properties": {
    "addr:full":"Mauritswg 51A Rotterdam Zuid-Holland 3012 JW",
    "addr:housenumber":"51a",
    "addr:postcode":"3012 jw",
    "addr:street":"Mauritswg",
    "iso:country":"NL",
    "sg:address":"Mauritswg 51A",
    "sg:city":"Rotterdam",
    "sg:orig_category":"Architecten En Architectenbureaus",
    "sg:phone":"+31 10 240 0029",
    "sg:postcode":"3012 JW",
    "sg:province":"Zuid-Holland",
    "sg:website":"http://www.johandevriesarchitect.nl",
    "wof:name":"Vries Bv, Johan De",
    "wof:placetype":"venue"
},
  "geometry": {"coordinates":[4.47299,51.917892],"type":"Point"}
}