{
  "type": "Feature",
  "properties": {
    "addr:full":"Kokermolenpad 33 Almere Flevoland 1333 GA",
    "addr:housenumber":"33",
    "addr:postcode":"1333 ga",
    "addr:street":"Kokermolenpad;Flevoland",
    "iso:country":"NL",
    "sg:address":"Kokermolenpad 33",
    "sg:city":"Almere",
    "sg:orig_category":"Glazenwasserijen",
    "sg:phone":"+31 36 532 0918",
    "sg:postcode":"1333 GA",
    "sg:province":"Flevoland",
    "wof:name":"Noordanus Glazenwasserij, G M",
    "wof:placetype":"venue"
},
  "geometry": {"coordinates":[5.275175,52.399391],"type":"Point"}
}