{
  "type": "Feature",
  "properties": {
    "addr:full":"Deldenerstr 1 Hengelo Ov Overijssel 7551 AA",
    "addr:housenumber":"1",
    "addr:postcode":"7551 aa",
    "addr:street":"Deldenerstr;Ov",
    "iso:country":"NL",
    "sg:address":"Deldenerstr 1",
    "sg:city":"Hengelo Ov",
    "sg:orig_category":"Wasmachines En Wasdrogers - Onderhoud En Reparatie",
    "sg:phone":"+31 74 291 7132",
    "sg:postcode":"7551 AA",
    "sg:province":"Overijssel",
    "wof:name":"Nijhof Onderdelencentrum",
    "wof:placetype":"venue"
},
  "geometry": {"coordinates":[6.7915821075,52.266834259],"type":"Point"}
}