{
  "type": "Feature",
  "properties": {
    "addr:full":"Ardecheln 3 Eindhoven Noord-Brabant 5627 EM",
    "addr:housenumber":"3",
    "addr:postcode":"5627 em",
    "addr:street":"Ardecheln",
    "iso:country":"NL",
    "sg:address":"Ardecheln 3",
    "sg:city":"Eindhoven",
    "sg:orig_category":"Bloemen En Planten",
    "sg:phone":"+31 40 242 7220",
    "sg:postcode":"5627 EM",
    "sg:province":"Noord-Brabant",
    "wof:name":"Fleur, La",
    "wof:placetype":"venue"
},
  "geometry": {"coordinates":[5.44142,51.484638],"type":"Point"}
}