{
  "type": "Feature",
  "properties": {
    "addr:full":"Valeriaanstraat 36 Terneuzen Zeeland 4537 DC",
    "addr:housenumber":"36",
    "addr:postcode":"4537",
    "addr:street":"Valeriaanstraat",
    "iso:country":"NL",
    "sg:address":"Valeriaanstraat 36",
    "sg:city":"Terneuzen",
    "sg:orig_category":"Onderhoud And Reparatie Kantoorapparatuur",
    "sg:phone":"+31 115 612 008",
    "sg:postcode":"4537 DC",
    "sg:province":"Zeeland",
    "wof:name":"Stand-By Comp Support",
    "wof:placetype":"venue"
},
  "geometry": {"coordinates":[3.839786,51.317375],"type":"Point"}
}