{
  "type": "Feature",
  "properties": {
    "addr:full":"Kemphaanwg 1 Heusden Gem Asten Noord-Brabant 5725 RE",
    "addr:housenumber":"1",
    "addr:postcode":"5725 re",
    "addr:street":"Kemphaanwg",
    "iso:country":"NL",
    "sg:address":"Kemphaanwg 1",
    "sg:city":"Heusden Gem Asten",
    "sg:orig_category":"Pluimveebedrijven En -Handelaren",
    "sg:phone":"+31 493 560 252",
    "sg:postcode":"5725 RE",
    "sg:province":"Noord-Brabant",
    "wof:name":"Velden-Van Tilburg, J M Van Der",
    "wof:placetype":"venue"
},
  "geometry": {"coordinates":[5.787612,51.379177],"type":"Point"}
}