{
  "type": "Feature",
  "properties": {
    "addr:full":"Pretoriusstr 29/Hs Amsterdam North Holland 1092 EX",
    "addr:housenumber":"29 / hs",
    "addr:postcode":"1092 ex",
    "addr:street":"Pretoriusstr",
    "iso:country":"NL",
    "sg:address":"Pretoriusstr 29/Hs",
    "sg:city":"Amsterdam",
    "sg:orig_category":"Verenigingen En Stichtingen",
    "sg:phone":"+31 20 693 0580",
    "sg:postcode":"1092 EX",
    "sg:province":"North Holland",
    "wof:name":"Sanggar Tari Melati Ribuan Pulau, Sticht",
    "wof:placetype":"venue"
},
  "geometry": {"coordinates":[4.92168,52.357979],"type":"Point"}
}