{
  "type": "Feature",
  "properties": {
    "addr:full":"Salomonszegel 1 Deventer Overijssel 7422 LH",
    "addr:housenumber":"1",
    "addr:postcode":"7422 lh",
    "addr:street":"Salomonszegel",
    "iso:country":"NL",
    "sg:address":"Salomonszegel 1",
    "sg:city":"Deventer",
    "sg:orig_category":"Banken And Kredietinstellingen",
    "sg:phone":"+31 570 684 801",
    "sg:postcode":"7422 LH",
    "sg:province":"Overijssel",
    "wof:name":"Rabobank",
    "wof:placetype":"venue"
},
  "geometry": {"coordinates":[6.21846,52.247501],"type":"Point"}
}