{
  "type": "Feature",
  "properties": {
    "addr:full":"Treubstr 25 Ryswyk Zh Zuid-Holland 2288 EH",
    "addr:housenumber":"25",
    "addr:postcode":"2288 eh",
    "addr:street":"Treubstr",
    "iso:country":"NL",
    "sg:address":"Treubstr 25",
    "sg:city":"Ryswyk Zh",
    "sg:orig_category":"Administratie- En Boekhoudkantoren",
    "sg:phone":"+31 70 319 1100",
    "sg:postcode":"2288 EH",
    "sg:province":"Zuid-Holland",
    "wof:name":"Berg Administratie, V/D",
    "wof:placetype":"venue"
},
  "geometry": {"coordinates":[4.32436,52.037251],"type":"Point"}
}