{
  "type": "Feature",
  "properties": {
    "iso:country":"NL",
    "sg:address":"Oude Hoogstr 13",
    "sg:city":"Amsterdam",
    "sg:orig_category":"Koffie- En Theehuizen",
    "sg:phone":"+31 20 627 9910",
    "sg:postcode":"1012 CD",
    "sg:province":"North Holland",
    "wof:name":"Free Adam",
    "wof:placetype":"venue"
},
  "geometry": {"coordinates":[4.897554,52.371445],"type":"Point"}
}