{
  "type": "Feature",
  "properties": {
    "addr:full":"Blekerstr 21 Enschede NL.08 7513 DR",
    "addr:housenumber":"21;7513",
    "addr:street":"Blekerstr;Dr",
    "iso:country":"NL",
    "sg:address":"Blekerstr 21",
    "sg:city":"Enschede",
    "sg:orig_category":"Wijnkoperijen En -Groothandel",
    "sg:phone":"+31 53 436 7323",
    "sg:postcode":"7513 DR",
    "sg:province":"NL.08",
    "sg:website":"http://www.wijntotaal.nl",
    "wof:name":"Wijntotaal",
    "wof:placetype":"venue"
},
  "geometry": {"coordinates":[6.8879060745,52.2155990601],"type":"Point"}
}