{
  "type": "Feature",
  "properties": {
    "addr:full":"Nieuwe Rijn 11 Leiden Zuid-Holland 2312  J",
    "addr:housenumber":"11;2312 j",
    "addr:street":"Nieuwe Rijn",
    "iso:country":"NL",
    "sg:address":"Nieuwe Rijn 11",
    "sg:city":"Leiden",
    "sg:orig_category":"Feestartikelen",
    "sg:phone":"+31 71 512 1430",
    "sg:postcode":"2312  J",
    "sg:province":"Zuid-Holland",
    "wof:name":"Paddenburg",
    "wof:placetype":"venue"
},
  "geometry": {"coordinates":[4.491798,52.15871],"type":"Point"}
}