{
  "type": "Feature",
  "properties": {
    "addr:full":"Randweg 21 Hoensbroek Limburg 6431 AA",
    "addr:housenumber":"21",
    "addr:postcode":"6431 aa",
    "addr:street":"Randweg",
    "iso:country":"NL",
    "sg:address":"Randweg 21",
    "sg:city":"Hoensbroek",
    "sg:orig_category":"Vertaal- And Tolkenbureaus",
    "sg:phone":"+31 45 563 1005",
    "sg:postcode":"6431 AA",
    "sg:province":"Limburg",
    "wof:name":"A.A.J. Translators Teams",
    "wof:placetype":"venue"
},
  "geometry": {"coordinates":[5.922239,50.931553],"type":"Point"}
}