{
  "type": "Feature",
  "properties": {
    "iso:country":"NL",
    "sg:address":"Espeterwg 10",
    "sg:city":"Barneveld",
    "sg:orig_category":"Montagebedrijven",
    "sg:phone":"+31 6 54716001",
    "sg:postcode":"3771 RK",
    "sg:province":"Gelderland",
    "wof:name":"Bhw Vof",
    "wof:placetype":"venue"
},
  "geometry": {"coordinates":[5.61137,52.136375],"type":"Point"}
}