{
  "type": "Feature",
  "properties": {
    "addr:full":"Woldstraat 45 Meppel Drenthe 7941 LG",
    "addr:housenumber":"45",
    "addr:postcode":"7941 lg",
    "addr:street":"Woldstraat",
    "iso:country":"NL",
    "sg:address":"Woldstraat 45",
    "sg:city":"Meppel",
    "sg:orig_category":"Juweliers",
    "sg:phone":"+31 522 261 097",
    "sg:postcode":"7941 LG",
    "sg:province":"Drenthe",
    "wof:name":"Kunsjt",
    "wof:placetype":"venue"
},
  "geometry": {"coordinates":[6.192599,52.698296],"type":"Point"}
}