{
  "type": "Feature",
  "properties": {
    "addr:full":"Mynsherenln 183 Rotterdam Zuid-Holland 3081 GN",
    "addr:housenumber":"183",
    "addr:postcode":"3081 gn",
    "iso:country":"NL",
    "sg:address":"Mynsherenln 183",
    "sg:city":"Rotterdam",
    "sg:orig_category":"Administratie- En Boekhoudkantoren",
    "sg:phone":"+31 10 485 7044",
    "sg:postcode":"3081 GN",
    "sg:province":"Zuid-Holland",
    "wof:name":"Bevias Bv",
    "wof:placetype":"venue"
},
  "geometry": {"coordinates":[4.488913,51.891361],"type":"Point"}
}