{
  "type": "Feature",
  "properties": {
    "addr:full":"Kr Nering 12A Heerjansdam South Holland 2995 BH",
    "addr:housenumber":"12a",
    "addr:postcode":"2995 bh",
    "addr:street":"Kr Nering",
    "iso:country":"NL",
    "sg:address":"Kr Nering 12A",
    "sg:city":"Heerjansdam",
    "sg:orig_category":"Postkantoren",
    "sg:phone":"+31 78 677 1220",
    "sg:postcode":"2995 BH",
    "sg:province":"South Holland",
    "sg:website":"http://www.postkantoor.nl",
    "wof:name":"Postkantoor",
    "wof:placetype":"venue"
},
  "geometry": {"coordinates":[4.564294,51.83588],"type":"Point"}
}