{
  "type": "Feature",
  "properties": {
    "addr:full":"Jan Olieslagersstraat 25 Helmond Noord-Brabant 5703 HN",
    "addr:housenumber":"25",
    "addr:postcode":"5703 hn",
    "addr:street":"Jan Olieslagersstraat",
    "iso:country":"NL",
    "sg:address":"Jan Olieslagersstraat 25",
    "sg:city":"Helmond",
    "sg:orig_category":"Huizensloop And Bouwrijp Maken",
    "sg:phone":"+31 492 543 781",
    "sg:postcode":"5703 HN",
    "sg:province":"Noord-Brabant",
    "wof:name":"Handels- En Bouwonderneming A. Roubos",
    "wof:placetype":"venue"
},
  "geometry": {"coordinates":[5.681415,51.484512],"type":"Point"}
}