{
  "type": "Feature",
  "properties": {
    "addr:full":"Vlas En Graan 83 Veghel Noord-Brabant 5461 KL",
    "addr:housenumber":"83",
    "addr:postcode":"5461 kl",
    "addr:street":"Vlas En Graan",
    "iso:country":"NL",
    "sg:address":"Vlas En Graan 83",
    "sg:city":"Veghel",
    "sg:orig_category":"Metalen And Ertsen Gh",
    "sg:phone":"+31 413 344 165",
    "sg:postcode":"5461 KL",
    "sg:province":"Noord-Brabant",
    "wof:name":"Intof Nederland",
    "wof:placetype":"venue"
},
  "geometry": {"coordinates":[5.544711,51.615265],"type":"Point"}
}