{
  "type": "Feature",
  "properties": {
    "addr:full":"Kommiezenln 16 Schiedam Zuid-Holland 3125 AN",
    "addr:housenumber":"16",
    "addr:postcode":"3125 an",
    "addr:street":"Kommiezenln",
    "iso:country":"NL",
    "sg:address":"Kommiezenln 16",
    "sg:city":"Schiedam",
    "sg:orig_category":"Hijswerktuigen",
    "sg:phone":"+31 10 437 3033",
    "sg:postcode":"3125 AN",
    "sg:province":"Zuid-Holland",
    "sg:website":"http://www.mennens.nl",
    "wof:name":"Mennens Schiedam",
    "wof:placetype":"venue"
},
  "geometry": {"coordinates":[4.411808,51.924717],"type":"Point"}
}