{
  "type": "Feature",
  "properties": {
    "iso:country":"NL",
    "sg:address":"Hoofdstr 55",
    "sg:city":"Mechelen",
    "sg:orig_category":"Fietsen En Bromfietsen Verhuur",
    "sg:phone":"+31 43 455 1275",
    "sg:postcode":"6281 BB",
    "sg:province":"Limburg",
    "wof:name":"Hub Nix",
    "wof:placetype":"venue"
},
  "geometry": {"coordinates":[5.923167,50.795006],"type":"Point"}
}