{
  "type": "Feature",
  "properties": {
    "addr:full":"Molenweg 44 Bunnik Utrecht 3981 CC",
    "addr:housenumber":"44",
    "addr:postcode":"3981 cc",
    "addr:street":"Molenweg",
    "iso:country":"NL",
    "sg:address":"Molenweg 44",
    "sg:city":"Bunnik",
    "sg:orig_category":"Bloemen And Planten",
    "sg:phone":"+31 30 656 1334",
    "sg:postcode":"3981 CC",
    "sg:province":"Utrecht",
    "wof:name":"Bloemisterij Ter Hul",
    "wof:placetype":"venue"
},
  "geometry": {"coordinates":[5.202264,52.065239],"type":"Point"}
}