{
  "type": "Feature",
  "properties": {
    "iso:country":"NL",
    "sg:address":"Berkenlaan 5",
    "sg:city":"Ermelo",
    "sg:orig_category":"Watersport-, Sport- And Kampeerbenodigdheden Verhuur",
    "sg:phone":"+31 341 561 566",
    "sg:postcode":"3851 PP",
    "sg:province":"Gelderland",
    "wof:name":"Runa Mara",
    "wof:placetype":"venue"
},
  "geometry": {"coordinates":[5.6261901855,52.300945282],"type":"Point"}
}