{
  "type": "Feature",
  "properties": {
    "addr:full":"Ds M L Kingwg 130 Purmerend Noord-Holland 1444 EG",
    "addr:housenumber":"130",
    "addr:postcode":"1444 eg",
    "addr:street":"Ds M L Kingwg",
    "iso:country":"NL",
    "sg:address":"Ds M L Kingwg 130",
    "sg:city":"Purmerend",
    "sg:orig_category":"Koffie-Automaten",
    "sg:phone":"+31 800 0226800",
    "sg:postcode":"1444 EG",
    "sg:province":"Noord-Holland",
    "sg:website":"http://www.jede.com",
    "wof:name":"Jede Purmerend",
    "wof:placetype":"venue"
},
  "geometry": {"coordinates":[4.94793,52.507607],"type":"Point"}
}