{
  "type": "Feature",
  "properties": {
    "iso:country":"NL",
    "sg:address":"Kleine Bredeplaats 5",
    "sg:city":"Harlingen",
    "sg:orig_category":"Hypotheken And Hypotheekbanken",
    "sg:phone":"+31 517 430 549",
    "sg:postcode":"8861 BV",
    "sg:province":"Friesland",
    "wof:name":"Hypotheek Nummer 1",
    "wof:placetype":"venue"
},
  "geometry": {"coordinates":[5.416199,53.174728],"type":"Point"}
}