{
  "type": "Feature",
  "properties": {
    "addr:full":"Jan Ligthartstraat 209 Heemskerk Noord-Holland 1964 HG",
    "addr:housenumber":"209",
    "addr:postcode":"1964 hg",
    "addr:street":"Jan Ligthartstraat",
    "iso:country":"NL",
    "sg:address":"Jan Ligthartstraat 209",
    "sg:city":"Heemskerk",
    "sg:orig_category":"Elektronische Bedrijfsinstallaties",
    "sg:phone":"+31 251 230 264",
    "sg:postcode":"1964 HG",
    "sg:province":"Noord-Holland",
    "wof:name":"Connected",
    "wof:placetype":"venue"
},
  "geometry": {"coordinates":[4.664695,52.506485],"type":"Point"}
}