{
  "type": "Feature",
  "properties": {
    "addr:full":"M D De Grootstraat 44 Goes Zeeland 4461 WD",
    "addr:housenumber":"44",
    "addr:postcode":"4461 wd",
    "addr:street":"De Grootstraat",
    "iso:country":"NL",
    "sg:address":"M D De Grootstraat 44",
    "sg:city":"Goes",
    "sg:orig_category":"Boekhouders",
    "sg:phone":"+31 113 216 741",
    "sg:postcode":"4461 WD",
    "sg:province":"Zeeland",
    "wof:name":"Meijers Fiscale Administraties",
    "wof:placetype":"venue"
},
  "geometry": {"coordinates":[-83.914169,39.768833],"type":"Point"}
}