{
  "type": "Feature",
  "properties": {
    "addr:full":"V Blankenheimln 6 Zwolle NL.08 8034 PE",
    "addr:housenumber":"6",
    "addr:postcode":"8034 pe",
    "addr:street":"Blankenheimln",
    "iso:country":"NL",
    "sg:address":"V Blankenheimln 6",
    "sg:city":"Zwolle",
    "sg:orig_category":"Mensendieck - Oefentherapeuten",
    "sg:phone":"+31 38 454 1894",
    "sg:postcode":"8034 PE",
    "sg:province":"NL.08",
    "wof:name":"Berge, H W Van Den",
    "wof:placetype":"venue"
},
  "geometry": {"coordinates":[6.123745,52.537964],"type":"Point"}
}