{
  "type": "Feature",
  "properties": {
    "iso:country":"NL",
    "sg:address":"Herrebeugel 29",
    "sg:city":"Wijk En Aalburg",
    "sg:orig_category":"Boekhouders",
    "sg:phone":"+31 416 692 298",
    "sg:postcode":"4261 XN",
    "sg:province":"Noord-Brabant",
    "wof:name":"Administratiekantoor Aalburg",
    "wof:placetype":"venue"
},
  "geometry": {"coordinates":[5.128579,51.753448],"type":"Point"}
}