{
  "type": "Feature",
  "properties": {
    "addr:full":"Eem 47 Huizen Noord-Holland 1273 PD",
    "addr:housenumber":"47",
    "addr:postcode":"1273 pd",
    "addr:street":"Eem",
    "iso:country":"NL",
    "sg:address":"Eem 47",
    "sg:city":"Huizen",
    "sg:orig_category":"Schilderwerk",
    "sg:phone":"+31 35 526 7753",
    "sg:postcode":"1273 PD",
    "sg:province":"Noord-Holland",
    "wof:name":"C. De Kroon",
    "wof:placetype":"venue"
},
  "geometry": {"coordinates":[5.260695,52.304695],"type":"Point"}
}