{
  "type": "Feature",
  "properties": {
    "iso:country":"NL",
    "sg:address":"Delflandstr 47",
    "sg:city":"Nootdorp",
    "sg:orig_category":"Administratie- En Boekhoudkantoren",
    "sg:phone":"+31 15 310 8431",
    "sg:postcode":"2631 HA",
    "sg:province":"Zuid-Holland",
    "wof:name":"Leeuwen, H J Van",
    "wof:placetype":"venue"
},
  "geometry": {"coordinates":[4.39411,52.049969],"type":"Point"}
}