{
  "type": "Feature",
  "properties": {
    "iso:country":"NL",
    "sg:address":"Noordersngl 4",
    "sg:city":"Eemnes",
    "sg:orig_category":"Verenigingen En Stichtingen",
    "sg:phone":"+31 35 531 9284",
    "sg:postcode":"3755 EZ",
    "sg:province":"Utrecht",
    "wof:name":"Sticht De Singel",
    "wof:placetype":"venue"
},
  "geometry": {"coordinates":[5.25941,52.253288],"type":"Point"}
}