{
  "type": "Feature",
  "properties": {
    "addr:full":"Operapln 30 Apeldoorn Gelderland 7323 EL",
    "addr:housenumber":"30",
    "addr:postcode":"7323 el",
    "addr:street":"Operapln;Gelderland",
    "iso:country":"NL",
    "sg:address":"Operapln 30",
    "sg:city":"Apeldoorn",
    "sg:orig_category":"Kappers",
    "sg:phone":"+31 55 366 0596",
    "sg:postcode":"7323 EL",
    "sg:province":"Gelderland",
    "wof:name":"Carmen",
    "wof:placetype":"venue"
},
  "geometry": {"coordinates":[5.9853720665,52.2289085388],"type":"Point"}
}