{
  "type": "Feature",
  "properties": {
    "iso:country":"NL",
    "sg:address":"Markt 1",
    "sg:city":"Vlaardingen",
    "sg:orig_category":"Verlichting",
    "sg:phone":"+31 10 434 5196",
    "sg:postcode":"3131 CR",
    "sg:province":"Zuid-Holland",
    "wof:name":"L'Interieur Bon Go\u00fbt, De",
    "wof:placetype":"venue"
},
  "geometry": {"coordinates":[4.342619,51.908241],"type":"Point"}
}