{
  "type": "Feature",
  "properties": {
    "addr:full":"Havendk 22 Tilburg North Brabant 5017 AM",
    "addr:housenumber":"22",
    "addr:postcode":"5017",
    "addr:street":"Havendk",
    "iso:country":"NL",
    "sg:address":"Havendk 22",
    "sg:city":"Tilburg",
    "sg:orig_category":"Kunststoffen- Verwerkende Industrie",
    "sg:phone":"+31 13 580 1967",
    "sg:postcode":"5017 AM",
    "sg:province":"North Brabant",
    "wof:name":"Polynova",
    "wof:placetype":"venue"
},
  "geometry": {"coordinates":[5.103151,51.553432],"type":"Point"}
}