{
  "type": "Feature",
  "properties": {
    "addr:full":"Kranewg 76 Groningen Groningen 9718 JV",
    "addr:housenumber":"76",
    "addr:postcode":"9718 jv",
    "addr:street":"Kranewg",
    "iso:country":"NL",
    "sg:address":"Kranewg 76",
    "sg:city":"Groningen",
    "sg:orig_category":"Adviesbureaus Bedrijfsorganisatie",
    "sg:phone":"+31 50 526 0505",
    "sg:postcode":"9718 JV",
    "sg:province":"Groningen",
    "wof:name":"Doting, P",
    "wof:placetype":"venue"
},
  "geometry": {"coordinates":[6.548996,53.216671],"type":"Point"}
}