{
  "type": "Feature",
  "properties": {
    "iso:country":"NL",
    "sg:address":"Norgerwg 4",
    "sg:city":"Haulerwyk",
    "sg:orig_category":"Bloemen En Planten",
    "sg:phone":"+31 516 421 373",
    "sg:postcode":"8433 LL",
    "sg:province":"Friesland",
    "wof:name":"Acanthus",
    "wof:placetype":"venue"
},
  "geometry": {"coordinates":[6.332543,53.065655],"type":"Point"}
}