{
  "type": "Feature",
  "properties": {
    "addr:full":"Molenzichtwg 12 Bergen Op Zoom North Brabant 4624 RC",
    "addr:housenumber":"12",
    "addr:postcode":"4624 rc",
    "addr:street":"Molenzichtwg",
    "iso:country":"NL",
    "sg:address":"Molenzichtwg 12",
    "sg:city":"Bergen Op Zoom",
    "sg:orig_category":"Adviesbureaus Bedrijfsorganisatie",
    "sg:phone":"+31 164 242 571",
    "sg:postcode":"4624 RC",
    "sg:province":"North Brabant",
    "wof:name":"Houtman",
    "wof:placetype":"venue"
},
  "geometry": {"coordinates":[4.345959,51.482246],"type":"Point"}
}