{
  "type": "Feature",
  "properties": {
    "addr:full":"Cartesiuswg 100 Utrecht Utrecht 3534 BD",
    "addr:housenumber":"100",
    "addr:postcode":"3534 bd",
    "iso:country":"NL",
    "sg:address":"Cartesiuswg 100",
    "sg:city":"Utrecht",
    "sg:classifiers":[
        {
            "category":"Retail",
            "subcategory":"Auto Repair",
            "type":"Services"
        }
    ],
    "sg:phone":"+31 30 244 6313",
    "sg:postcode":"3534 BD",
    "sg:province":"Utrecht",
    "sg:tags":[
        "garage"
    ],
    "wof:name":"Olie Snelservice",
    "wof:placetype":"venue"
},
  "geometry": {"coordinates":[5.086649,52.099625],"type":"Point"}
}