{
  "type": "Feature",
  "properties": {
    "addr:full":"T Spiek 2 Beilen Drenthe 9411 KV",
    "addr:housenumber":"2",
    "addr:postcode":"9411 kv",
    "addr:street":"T Spiek",
    "iso:country":"NL",
    "sg:address":"T Spiek 2",
    "sg:city":"Beilen",
    "sg:classifiers":[
        {
            "category":"Education",
            "subcategory":"Preschool",
            "type":"Public Place"
        }
    ],
    "sg:phone":"+31 593 522 030",
    "sg:postcode":"9411 KV",
    "sg:province":"Drenthe",
    "sg:tags":[
        "kleuteronderwijs",
        "basis-"
    ],
    "wof:name":"Openbare Basisschool G.A. De Ridder",
    "wof:placetype":"venue"
},
  "geometry": {"coordinates":[6.512087,52.855564],"type":"Point"}
}