{
  "type": "Feature",
  "properties": {
    "addr:full":"Conradstr 12 Sliedrecht Zuid-Holland 3364 AC",
    "addr:housenumber":"12",
    "addr:postcode":"3364 ac",
    "addr:street":"Conradstr",
    "iso:country":"NL",
    "sg:address":"Conradstr 12",
    "sg:city":"Sliedrecht",
    "sg:orig_category":"Oldtimers",
    "sg:phone":"+31 184 421 570",
    "sg:postcode":"3364 AC",
    "sg:province":"Zuid-Holland",
    "wof:name":"Casey",
    "wof:placetype":"venue"
},
  "geometry": {"coordinates":[4.773918,51.829712],"type":"Point"}
}