{
  "type": "Feature",
  "properties": {
    "iso:country":"NL",
    "sg:address":"V Dalenln 171",
    "sg:city":"Santpoort Zuid",
    "sg:classifiers":[
        {
            "category":"Retail",
            "subcategory":"Auto Repair",
            "type":"Services"
        }
    ],
    "sg:phone":"+31 23 537 8550",
    "sg:postcode":"2082 VE",
    "sg:province":"Noord-Holland",
    "sg:tags":[
        "garage"
    ],
    "wof:name":"Immers Autobedrijf",
    "wof:placetype":"venue"
},
  "geometry": {"coordinates":[4.63207,52.424076],"type":"Point"}
}