{
  "type": "Feature",
  "properties": {
    "addr:full":"Jacob Van Lennepkade 334 Amsterdam Noord-Holland 1053 NJ",
    "addr:housenumber":"334",
    "addr:postcode":"1053 nj",
    "addr:street":"Jacob Van Lennepkade",
    "iso:country":"NL",
    "sg:address":"Jacob Van Lennepkade 334",
    "sg:city":"Amsterdam",
    "sg:orig_category":"Fotostudio'S And Fotografen",
    "sg:phone":"+31 20 685 0402",
    "sg:postcode":"1053 NJ",
    "sg:province":"Noord-Holland",
    "wof:name":"Giulio Dannetta Photography",
    "wof:placetype":"venue"
},
  "geometry": {"coordinates":[-94.58503,38.350479],"type":"Point"}
}