{
  "type": "Feature",
  "properties": {
    "addr:full":"Molenstr 14 Nieuwerkerk Zeeland 4306 CG",
    "addr:housenumber":"14",
    "addr:postcode":"4306 cg",
    "addr:street":"Molenstr",
    "iso:country":"NL",
    "sg:address":"Molenstr 14",
    "sg:city":"Nieuwerkerk",
    "sg:orig_category":"Glazenwasserijen",
    "sg:phone":"+31 111 643 750",
    "sg:postcode":"4306 CG",
    "sg:province":"Zeeland",
    "wof:name":"Veen, C B M In 'T",
    "wof:placetype":"venue"
},
  "geometry": {"coordinates":[4.003336,51.650162],"type":"Point"}
}