{
  "type": "Feature",
  "properties": {
    "addr:full":"Oorgat 23 Edam Noord-Holland 1135 CP",
    "addr:housenumber":"23",
    "addr:postcode":"1135 cp",
    "addr:street":"Oorgat",
    "iso:country":"NL",
    "sg:address":"Oorgat 23",
    "sg:city":"Edam",
    "sg:orig_category":"Administratie- En Boekhoudkantoren",
    "sg:phone":"+31 299 315 032",
    "sg:postcode":"1135 CP",
    "sg:province":"Noord-Holland",
    "wof:name":"Laarhoven, Bedrijfsadviseurs",
    "wof:placetype":"venue"
},
  "geometry": {"coordinates":[5.059504,52.513969],"type":"Point"}
}