{
  "type": "Feature",
  "properties": {
    "addr:full":"Koningsln 30 Amsterdam North Holland 1075 AD",
    "addr:housenumber":"30",
    "addr:postcode":"1075 ad",
    "addr:street":"Koningsln",
    "iso:country":"NL",
    "sg:address":"Koningsln 30",
    "sg:city":"Amsterdam",
    "sg:orig_category":"Belastingconsulenten/ Belastingadviseurs",
    "sg:phone":"+31 20 670 6159",
    "sg:postcode":"1075 AD",
    "sg:province":"North Holland",
    "wof:name":"Krol",
    "wof:placetype":"venue"
},
  "geometry": {"coordinates":[4.864337,52.355202],"type":"Point"}
}