{
  "type": "Feature",
  "properties": {
    "addr:full":"Burgemeester Cortenstr 41 Maastricht Limburg 6226 GR",
    "addr:housenumber":"41",
    "addr:postcode":"6226",
    "addr:street":"Burgemeester Cortenstr",
    "iso:country":"NL",
    "sg:address":"Burgemeester Cortenstr 41",
    "sg:city":"Maastricht",
    "sg:classifiers":[
        {
            "category":"Fast Food",
            "type":"Food & Drink"
        }
    ],
    "sg:phone":"+31 43 362 0656",
    "sg:postcode":"6226 GR",
    "sg:province":"Limburg",
    "sg:tags":[
        "afhaal",
        "restaurant"
    ],
    "wof:name":"Friture Cafetaria Sjefke",
    "wof:placetype":"venue"
},
  "geometry": {"coordinates":[5.727523,50.8452],"type":"Point"}
}