{
  "type": "Feature",
  "properties": {
    "addr:full":"Archipel 4427 Lelystad NL. 8224 HV",
    "addr:postcode":"4427;8224 hv",
    "addr:street":"Archipel;Nl.",
    "iso:country":"NL",
    "sg:address":"Archipel 4427",
    "sg:city":"Lelystad",
    "sg:orig_category":"Verenigingen En Stichtingen",
    "sg:phone":"+31 320 240 689",
    "sg:postcode":"8224 HV",
    "sg:province":"NL.",
    "wof:name":"Rover Reizigersver",
    "wof:placetype":"venue"
},
  "geometry": {"coordinates":[5.494513,52.508671],"type":"Point"}
}