{
  "type": "Feature",
  "properties": {
    "addr:full":"Ovenbouwershoek 33 Apeldoorn Gelderland 7328 JH",
    "addr:housenumber":"33",
    "addr:postcode":"7328 jh",
    "addr:street":"Ovenbouwershoek;Gelderland",
    "iso:country":"NL",
    "sg:address":"Ovenbouwershoek 33",
    "sg:city":"Apeldoorn",
    "sg:orig_category":"Honden- En Kattentrimsalons",
    "sg:phone":"+31 55 533 6892",
    "sg:postcode":"7328 JH",
    "sg:province":"Gelderland",
    "wof:name":"Doesjka",
    "wof:placetype":"venue"
},
  "geometry": {"coordinates":[5.981614,52.208508],"type":"Point"}
}