{
  "type": "Feature",
  "properties": {
    "iso:country":"NL",
    "sg:address":"Molenstraat 57",
    "sg:city":"Twello",
    "sg:orig_category":"Fietshandelaren",
    "sg:phone":"+31 571 271 889",
    "sg:postcode":"7391 AB",
    "sg:province":"Gelderland",
    "wof:name":"Jo Hafkamp En Zoon Tweewielers",
    "wof:placetype":"venue"
},
  "geometry": {"coordinates":[6.094561,52.232155],"type":"Point"}
}