{
  "type": "Feature",
  "properties": {
    "addr:full":"Postbus 369 Apeldoorn Gelderland 7300 AJ",
    "addr:housenumber":"369",
    "addr:postcode":"7300 aj",
    "addr:street":"Postbus;Gelderland",
    "iso:country":"NL",
    "sg:address":"Postbus 369",
    "sg:city":"Apeldoorn",
    "sg:orig_category":"Verenigingen En Stichtingen",
    "sg:phone":"+31 55 360 2882",
    "sg:postcode":"7300 AJ",
    "sg:province":"Gelderland",
    "wof:name":"Gehandicapten Beraad Apeldoorn, Sticht",
    "wof:placetype":"venue"
},
  "geometry": {"coordinates":[5.96246,52.214329],"type":"Point"}
}