{
  "type": "Feature",
  "properties": {
    "iso:country":"NL",
    "sg:address":"Sportparkln 13",
    "sg:city":"Hulsberg",
    "sg:orig_category":"Kappers",
    "sg:phone":"+31 45 405 2000",
    "sg:postcode":"6336 AA",
    "sg:province":"Limburg",
    "wof:name":"Marjo",
    "wof:placetype":"venue"
},
  "geometry": {"coordinates":[5.853495,50.891891],"type":"Point"}
}