{
  "type": "Feature",
  "properties": {
    "addr:full":"Hoofdwg 3 Buren Fr Provincie Friesland 9164 KL",
    "addr:housenumber":"3",
    "addr:postcode":"9164 kl",
    "addr:street":"Hoofdwg;Friesland",
    "iso:country":"NL",
    "sg:address":"Hoofdwg 3",
    "sg:city":"Buren Fr",
    "sg:orig_category":"Vakantieverblijven",
    "sg:phone":"+31 519 542 376",
    "sg:postcode":"9164 KL",
    "sg:province":"Provincie Friesland",
    "wof:name":"Duinzicht",
    "wof:placetype":"venue"
},
  "geometry": {"coordinates":[5.797331,53.447392],"type":"Point"}
}