{
  "type": "Feature",
  "properties": {
    "iso:country":"NL",
    "sg:address":"Polstr 28",
    "sg:city":"Wyk En Aalburg",
    "sg:orig_category":"Parketvloeren",
    "sg:phone":"+31 416 692 978",
    "sg:postcode":"4261 BT",
    "sg:province":"Noord-Brabant",
    "wof:name":"Beje",
    "wof:placetype":"venue"
},
  "geometry": {"coordinates":[5.128662,51.751713],"type":"Point"}
}