{
  "type": "Feature",
  "properties": {
    "addr:full":"Nieuwe Havenweg 81 Hilversum Noord-Holland 1216 BP",
    "addr:housenumber":"81",
    "addr:postcode":"1216 bp",
    "addr:street":"Nieuwe Havenweg",
    "iso:country":"NL",
    "sg:address":"Nieuwe Havenweg 81",
    "sg:city":"Hilversum",
    "sg:orig_category":"Autokeuringen",
    "sg:phone":"+31 35 624 8034",
    "sg:postcode":"1216 BP",
    "sg:province":"Noord-Holland",
    "wof:name":"Autodemontagebedrijf De Nieuwe Haven Bv",
    "wof:placetype":"venue"
},
  "geometry": {"coordinates":[5.142303,52.221882],"type":"Point"}
}