{
  "type": "Feature",
  "properties": {
    "addr:full":"Kamilleveld 11 Doetinchem Gelderland 7006 VB",
    "addr:housenumber":"11",
    "addr:postcode":"7006 vb",
    "addr:street":"Kamilleveld;Gelderland",
    "iso:country":"NL",
    "sg:address":"Kamilleveld 11",
    "sg:city":"Doetinchem",
    "sg:orig_category":"Publiciteitsbureaus",
    "sg:phone":"+31 314 364 029",
    "sg:postcode":"7006 VB",
    "sg:province":"Gelderland",
    "wof:name":"Verhagen, Jacques",
    "wof:placetype":"venue"
},
  "geometry": {"coordinates":[6.249745,51.961369],"type":"Point"}
}