{
  "type": "Feature",
  "properties": {
    "addr:full":"Grt Staat 34 Maastricht Limburg 6211 CW",
    "addr:housenumber":"34",
    "addr:postcode":"6211 cw",
    "addr:street":"Staat",
    "iso:country":"NL",
    "sg:address":"Grt Staat 34",
    "sg:city":"Maastricht",
    "sg:orig_category":"Herenkleding",
    "sg:phone":"+31 43 325 1210",
    "sg:postcode":"6211 CW",
    "sg:province":"Limburg",
    "wof:name":"Boebie'S",
    "wof:placetype":"venue"
},
  "geometry": {"coordinates":[5.690744,50.849915],"type":"Point"}
}