{
  "type": "Feature",
  "properties": {
    "addr:full":"V Metmanstr 43 Ryswyk Zh Zuid-Holland 2282 GM",
    "addr:housenumber":"43",
    "addr:postcode":"2282 gm",
    "addr:street":"Ryswyk",
    "iso:country":"NL",
    "sg:address":"V Metmanstr 43",
    "sg:city":"Ryswyk Zh",
    "sg:orig_category":"Adviesbureaus",
    "sg:phone":"+31 70 399 2348",
    "sg:postcode":"2282 GM",
    "sg:province":"Zuid-Holland",
    "sg:website":"http://www.bartoque.nl",
    "wof:name":"Bartoque",
    "wof:placetype":"venue"
},
  "geometry": {"coordinates":[4.33694,52.056503],"type":"Point"}
}