{
  "type": "Feature",
  "properties": {
    "addr:full":"Fellenoord 43 Eindhoven Noord-Brabant 5612 AA",
    "addr:housenumber":"43",
    "addr:postcode":"5612 aa",
    "addr:street":"Fellenoord",
    "iso:country":"NL",
    "sg:address":"Fellenoord 43",
    "sg:city":"Eindhoven",
    "sg:orig_category":"Facilitaire Dienstverlening",
    "sg:phone":"+31 40 237 0465",
    "sg:postcode":"5612 AA",
    "sg:province":"Noord-Brabant",
    "sg:website":"http://www.dbn.nu",
    "wof:name":"Duurzaam Bedrijventerrein Nederland Bv",
    "wof:placetype":"venue"
},
  "geometry": {"coordinates":[5.474349,51.443939],"type":"Point"}
}