{
  "type": "Feature",
  "properties": {
    "addr:full":"C Schellingerln 38 Zeist Utrecht 3703 SH",
    "addr:housenumber":"38",
    "addr:postcode":"3703 sh",
    "iso:country":"NL",
    "sg:address":"C Schellingerln 38",
    "sg:city":"Zeist",
    "sg:orig_category":"Adviesbureaus Bedrijfsorganisatie",
    "sg:phone":"+31 30 691 8199",
    "sg:postcode":"3703 SH",
    "sg:province":"Utrecht",
    "wof:name":"Leistra Bv",
    "wof:placetype":"venue"
},
  "geometry": {"coordinates":[5.229209,52.080818],"type":"Point"}
}