{
  "type": "Feature",
  "properties": {
    "addr:full":"Gastakker 84 Breda Noord-Brabant 4817 XD",
    "addr:housenumber":"84",
    "addr:postcode":"4817 xd",
    "addr:street":"Gastakker",
    "iso:country":"NL",
    "sg:address":"Gastakker 84",
    "sg:city":"Breda",
    "sg:orig_category":"Bedrijfsopleidingen",
    "sg:phone":"+31 76 571 2218",
    "sg:postcode":"4817 XD",
    "sg:province":"Noord-Brabant",
    "wof:name":"Jonkers",
    "wof:placetype":"venue"
},
  "geometry": {"coordinates":[4.813438,51.591427],"type":"Point"}
}