{
  "type": "Feature",
  "properties": {
    "addr:full":"Ackersdykstr 17A Rotterdam Zuid-Holland 3037 VA",
    "addr:housenumber":"17a",
    "addr:postcode":"3037",
    "addr:street":"Ackersdykstr",
    "iso:country":"NL",
    "sg:address":"Ackersdykstr 17A",
    "sg:city":"Rotterdam",
    "sg:orig_category":"Glazenwasserijen",
    "sg:phone":"+31 6 54274743",
    "sg:postcode":"3037 VA",
    "sg:province":"Zuid-Holland",
    "wof:name":"Strak",
    "wof:placetype":"venue"
},
  "geometry": {"coordinates":[4.471153,51.938381],"type":"Point"}
}