{
  "type": "Feature",
  "properties": {
    "addr:full":"Scheepstimmerm Ln 5A Rotterdam Zuid-Holland 3016 AC",
    "addr:housenumber":"5a",
    "addr:postcode":"3016 ac",
    "addr:street":"Scheepstimmerm Ln",
    "iso:country":"NL",
    "sg:address":"Scheepstimmerm Ln 5A",
    "sg:city":"Rotterdam",
    "sg:orig_category":"Kamerverhuur En -Bemiddeling",
    "sg:phone":"+31 10 225 1972",
    "sg:postcode":"3016 AC",
    "sg:province":"Zuid-Holland",
    "wof:name":"Damson Bv",
    "wof:placetype":"venue"
},
  "geometry": {"coordinates":[4.4772949219,51.910987854],"type":"Point"}
}