{
  "type": "Feature",
  "properties": {
    "addr:full":"J Vd Waalsstr 52-2 Amsterdam Noord-Holland 1098 PN",
    "addr:housenumber":"52-2",
    "addr:postcode":"1098 pn",
    "iso:country":"NL",
    "sg:address":"J Vd Waalsstr 52-2",
    "sg:city":"Amsterdam",
    "sg:orig_category":"Adviesbureaus Bedrijfsorganisatie",
    "sg:phone":"+31 20 772 9250",
    "sg:postcode":"1098 PN",
    "sg:province":"Noord-Holland",
    "sg:website":"http://www.zich-t.nl",
    "wof:name":"Zich-T",
    "wof:placetype":"venue"
},
  "geometry": {"coordinates":[4.94241,52.352222],"type":"Point"}
}