{
  "type": "Feature",
  "properties": {
    "iso:country":"NL",
    "sg:address":"Plein 4",
    "sg:city":"Wateringen",
    "sg:orig_category":"Notarissen En Notariskantoren",
    "sg:phone":"+31 174 298 981",
    "sg:postcode":"2291 CC",
    "sg:province":"Zuid-Holland",
    "wof:name":"Exel, Mr H L J M Van",
    "wof:placetype":"venue"
},
  "geometry": {"coordinates":[4.274317,52.023621],"type":"Point"}
}