{
  "type": "Feature",
  "properties": {
    "addr:full":"P Calandln 312 Amsterdam Noord-Holland 1060 TS",
    "addr:housenumber":"312",
    "addr:postcode":"1060 ts",
    "addr:street":"P",
    "iso:country":"NL",
    "sg:address":"P Calandln 312",
    "sg:city":"Amsterdam",
    "sg:orig_category":"Kunstgebitten",
    "sg:phone":"+31 20 619 5482",
    "sg:postcode":"1060 TS",
    "sg:province":"Noord-Holland",
    "wof:name":"Osdorp",
    "wof:placetype":"venue"
},
  "geometry": {"coordinates":[4.788872,52.350174],"type":"Point"}
}