{
  "type": "Feature",
  "properties": {
    "addr:full":"Princestraat 24 Katwijk Zh South Holland 2225 GC",
    "addr:housenumber":"24",
    "addr:postcode":"zh;2225 gc",
    "addr:street":"Princestraat",
    "iso:country":"NL",
    "sg:address":"Princestraat 24",
    "sg:city":"Katwijk Zh",
    "sg:classifiers":[
        {
            "category":"Shopping",
            "subcategory":"Clothing, Apparel, & Fashions",
            "type":"Retail Goods"
        }
    ],
    "sg:phone":"+31 71 401 3518",
    "sg:postcode":"2225 GC",
    "sg:province":"South Holland",
    "sg:tags":[
        "ondergoed",
        "lingerie"
    ],
    "wof:name":"Livera Peters Vof",
    "wof:placetype":"venue"
},
  "geometry": {"coordinates":[4.39395,52.203369],"type":"Point"}
}