{
  "type": "Feature",
  "properties": {
    "addr:full":"Kyckerwg 113 De Lier Zuid-Holland 2678 AC",
    "addr:housenumber":"113",
    "addr:postcode":"2678 ac",
    "iso:country":"NL",
    "sg:address":"Kyckerwg 113",
    "sg:city":"De Lier",
    "sg:orig_category":"Onroerende Goederen",
    "sg:phone":"+31 174 516 441",
    "sg:postcode":"2678 AC",
    "sg:province":"Zuid-Holland",
    "wof:name":"Donkersloot Groep Bv",
    "wof:placetype":"venue"
},
  "geometry": {"coordinates":[4.232361,51.974312],"type":"Point"}
}