{
  "type": "Feature",
  "properties": {
    "addr:full":"Bergerdensestraat 13 Bemmel Gelderland 6681 LK",
    "addr:housenumber":"13",
    "addr:postcode":"6681 lk",
    "addr:street":"Bergerdensestraat;Gelderland",
    "iso:country":"NL",
    "sg:address":"Bergerdensestraat 13",
    "sg:city":"Bemmel",
    "sg:orig_category":"Levende Dieren Gh",
    "sg:phone":"+31 26 325 0988",
    "sg:postcode":"6681 LK",
    "sg:province":"Gelderland",
    "wof:name":"Zaat Veehandel",
    "wof:placetype":"venue"
},
  "geometry": {"coordinates":[5.918241,51.923107],"type":"Point"}
}