{
  "type": "Feature",
  "properties": {
    "iso:country":"NL",
    "sg:address":"Zandstr 27",
    "sg:city":"Oostburg",
    "sg:classifiers":[
        {
            "category":"Building & Trades",
            "subcategory":"Electrical",
            "type":"Services"
        }
    ],
    "sg:phone":"+31 117 453 664",
    "sg:postcode":"4501 JW",
    "sg:province":"Zeeland",
    "sg:tags":[
        "distributor"
    ],
    "wof:name":"Poorter Vof, De",
    "wof:placetype":"venue"
},
  "geometry": {"coordinates":[3.493409,51.329578],"type":"Point"}
}