{
  "type": "Feature",
  "properties": {
    "addr:full":"Pluimerstr 31-33 Groningen Groningen 9711 SV",
    "addr:housenumber":"31-33",
    "addr:postcode":"9711 sv",
    "iso:country":"NL",
    "sg:address":"Pluimerstr 31-33",
    "sg:city":"Groningen",
    "sg:orig_category":"Zonnebank- En Solariumcentra",
    "sg:phone":"+31 50 318 6641",
    "sg:postcode":"9711 SV",
    "sg:province":"Groningen",
    "wof:name":"Body Colour Zonnestudio",
    "wof:placetype":"venue"
},
  "geometry": {"coordinates":[6.575288,53.217995],"type":"Point"}
}