{
  "type": "Feature",
  "properties": {
    "addr:full":"Pastoor Dominicus Hexstr 74 Meerssen Limburg 6231 HG",
    "addr:housenumber":"74",
    "addr:postcode":"6231 hg",
    "addr:street":"Pastoor Dominicus Hexstr",
    "iso:country":"NL",
    "sg:address":"Pastoor Dominicus Hexstr 74",
    "sg:city":"Meerssen",
    "sg:orig_category":"Verhuur Audiovisuele Apparatuur",
    "sg:phone":"+31 43 364 2235",
    "sg:postcode":"6231 HG",
    "sg:province":"Limburg",
    "wof:name":"M.H. Lemaire",
    "wof:placetype":"venue"
},
  "geometry": {"coordinates":[5.746796,50.888588],"type":"Point"}
}