{
  "type": "Feature",
  "properties": {
    "addr:full":"Marthahoeve 136 Amstelveen Noord-Holland 1187 LZ",
    "addr:housenumber":"136",
    "addr:postcode":"1187 lz",
    "addr:street":"Marthahoeve",
    "iso:country":"NL",
    "sg:address":"Marthahoeve 136",
    "sg:city":"Amstelveen",
    "sg:orig_category":"Vertalers",
    "sg:phone":"+31 20 345 1896",
    "sg:postcode":"1187 LZ",
    "sg:province":"Noord-Holland",
    "wof:name":"Jumale, Zeinab",
    "wof:placetype":"venue"
},
  "geometry": {"coordinates":[4.827579,52.282761],"type":"Point"}
}