{
  "type": "Feature",
  "properties": {
    "iso:country":"NL",
    "sg:address":"Bronovoln 5",
    "sg:city":"S Gravenhage",
    "sg:orig_category":"Logopedisten",
    "sg:phone":"+31 70 312 4519",
    "sg:postcode":"2597 AX",
    "sg:province":"South Holland",
    "wof:name":"Maria Kwak",
    "wof:placetype":"venue"
},
  "geometry": {"coordinates":[4.31817,52.11031],"type":"Point"}
}