{
  "type": "Feature",
  "properties": {
    "addr:full":"Wittelaan 27 Baarn Utrecht 3743 CP",
    "addr:housenumber":"27",
    "addr:postcode":"3743 cp",
    "addr:street":"Wittelaan",
    "iso:country":"NL",
    "sg:address":"Wittelaan 27",
    "sg:city":"Baarn",
    "sg:orig_category":"Vertaal- And Tolkenbureaus",
    "sg:phone":"+31 35 543 0774",
    "sg:postcode":"3743 CP",
    "sg:province":"Utrecht",
    "wof:name":"Language Connection",
    "wof:placetype":"venue"
},
  "geometry": {"coordinates":[5.292121,52.21101],"type":"Point"}
}