{
  "type": "Feature",
  "properties": {
    "addr:full":"Marathon 2 Hilversum Noord-Holland 1213 PH",
    "addr:housenumber":"2",
    "addr:postcode":"1213",
    "addr:street":"Marathon",
    "iso:country":"NL",
    "sg:address":"Marathon 2",
    "sg:city":"Hilversum",
    "sg:orig_category":"Adviesbureaus Bedrijfsorganisatie",
    "sg:phone":"+31 35 683 2525",
    "sg:postcode":"1213 PH",
    "sg:province":"Noord-Holland",
    "wof:name":"Core Counsellors",
    "wof:placetype":"venue"
},
  "geometry": {"coordinates":[5.193929,52.211693],"type":"Point"}
}