{
  "type": "Feature",
  "properties": {
    "iso:country":"NL",
    "sg:address":"Hunnenwg 25",
    "sg:city":"Voorthuizen",
    "sg:classifiers":[
        {
            "category":"Sports & Exercise",
            "subcategory":"Stables",
            "type":"Entertainment"
        }
    ],
    "sg:phone":"+31 342 476 941",
    "sg:postcode":"3781 NM",
    "sg:province":"Gelderland",
    "sg:tags":[
        "maneges"
    ],
    "wof:name":"Colorful Ranch",
    "wof:placetype":"venue"
},
  "geometry": {"coordinates":[5.638141,52.203644],"type":"Point"}
}