{
  "type": "Feature",
  "properties": {
    "iso:country":"NL",
    "sg:address":"Amelandhoeve 37",
    "sg:city":"Vlaardingen",
    "sg:orig_category":"Loodgieterswerk, Verwarming And Sanitaire Installaties",
    "sg:phone":"+31 10 474 9461",
    "sg:postcode":"3137 GA",
    "sg:province":"South Holland",
    "wof:name":"Bronmans",
    "wof:placetype":"venue"
},
  "geometry": {"coordinates":[4.351289,51.941952],"type":"Point"}
}