{
  "type": "Feature",
  "properties": {
    "addr:full":"Watermolen 2 Niezijl Groningen 9842 PX",
    "addr:housenumber":"2",
    "addr:postcode":"9842 px",
    "addr:street":"Watermolen",
    "iso:country":"NL",
    "sg:address":"Watermolen 2",
    "sg:city":"Niezijl",
    "sg:orig_category":"Boekhouders",
    "sg:phone":"+31 594 213 725",
    "sg:postcode":"9842 PX",
    "sg:province":"Groningen",
    "wof:name":"S. Snip",
    "wof:placetype":"venue"
},
  "geometry": {"coordinates":[6.341528,53.267811],"type":"Point"}
}