{
  "type": "Feature",
  "properties": {
    "iso:country":"NL",
    "sg:address":"Snippertweg 5A",
    "sg:city":"Losser",
    "sg:orig_category":"Pluimveehouderijen",
    "sg:phone":"+31 53 538 5627",
    "sg:postcode":"7582 PC",
    "sg:province":"NL.08",
    "wof:name":"J.F.A. Loos",
    "wof:placetype":"venue"
},
  "geometry": {"coordinates":[6.982494,52.268761],"type":"Point"}
}