{
  "type": "Feature",
  "properties": {
    "addr:full":"Nieuwstraat 60 Oldenzaal Overijssel 7571 BM",
    "addr:housenumber":"60",
    "addr:postcode":"7571 bm",
    "addr:street":"Nieuwstraat",
    "iso:country":"NL",
    "sg:address":"Nieuwstraat 60",
    "sg:city":"Oldenzaal",
    "sg:orig_category":"Hypotheken And Hypotheekbanken",
    "sg:phone":"+31 541 512 288",
    "sg:postcode":"7571 BM",
    "sg:province":"Overijssel",
    "wof:name":"Hypotheek Visie Oldenzaal",
    "wof:placetype":"venue"
},
  "geometry": {"coordinates":[6.92532,52.311161],"type":"Point"}
}