{
  "type": "Feature",
  "properties": {
    "addr:full":"Handelsln 10 Uden North Brabant 5405 AE",
    "addr:housenumber":"10",
    "addr:postcode":"5405 ae",
    "addr:street":"Handelsln",
    "iso:country":"NL",
    "sg:address":"Handelsln 10",
    "sg:city":"Uden",
    "sg:orig_category":"Grondwerken",
    "sg:phone":"+31 413 264 941",
    "sg:postcode":"5405 AE",
    "sg:province":"North Brabant",
    "wof:name":"Engelen Uden Bv",
    "wof:placetype":"venue"
},
  "geometry": {"coordinates":[5.618265,51.657413],"type":"Point"}
}