{
  "type": "Feature",
  "properties": {
    "addr:full":"Jachtln 44 Delfzyl Groningen 9934 JD",
    "addr:housenumber":"44",
    "addr:postcode":"9934 jd",
    "addr:street":"Jachtln",
    "iso:country":"NL",
    "sg:address":"Jachtln 44",
    "sg:city":"Delfzyl",
    "sg:orig_category":"Verenigingen En Stichtingen",
    "sg:phone":"+31 596 633 564",
    "sg:postcode":"9934 JD",
    "sg:province":"Groningen",
    "wof:name":"Samenwerkende Peuterspeelzalen, Sticht",
    "wof:placetype":"venue"
},
  "geometry": {"coordinates":[6.903212,53.331192],"type":"Point"}
}