{
  "type": "Feature",
  "properties": {
    "addr:full":"Linschotenstr 39B Rotterdam Zuid-Holland 3044 AV",
    "addr:housenumber":"39b",
    "addr:postcode":"3044 av",
    "addr:street":"Linschotenstr",
    "iso:country":"NL",
    "sg:address":"Linschotenstr 39B",
    "sg:city":"Rotterdam",
    "sg:orig_category":"Heftrucks",
    "sg:phone":"+31 10 462 4079",
    "sg:postcode":"3044 AV",
    "sg:province":"Zuid-Holland",
    "wof:name":"Staub Bv",
    "wof:placetype":"venue"
},
  "geometry": {"coordinates":[4.4214158058,51.9293479919],"type":"Point"}
}