{
  "type": "Feature",
  "properties": {
    "addr:full":"Hoofdstraat 54 Kortgene Zeeland 4484 CH",
    "addr:housenumber":"54",
    "addr:postcode":"4484",
    "addr:street":"Hoofdstraat",
    "iso:country":"NL",
    "sg:address":"Hoofdstraat 54",
    "sg:city":"Kortgene",
    "sg:orig_category":"Kappers",
    "sg:phone":"+31 113 301 215",
    "sg:postcode":"4484 CH",
    "sg:province":"Zeeland",
    "wof:name":"Kapsalon Scherp",
    "wof:placetype":"venue"
},
  "geometry": {"coordinates":[3.8020451069,51.5577964783],"type":"Point"}
}