{
  "type": "Feature",
  "properties": {
    "addr:full":"Chassestraat 59 Amsterdam Noord-Holland 1057 JA",
    "addr:housenumber":"59",
    "addr:postcode":"1057 ja",
    "addr:street":"Chassestraat",
    "iso:country":"NL",
    "sg:address":"Chassestraat 59",
    "sg:city":"Amsterdam",
    "sg:classifiers":[
        {
            "category":"Education",
            "subcategory":"Preschool",
            "type":"Public Place"
        }
    ],
    "sg:phone":"+31 20 616 0106",
    "sg:postcode":"1057 JA",
    "sg:province":"Noord-Holland",
    "sg:tags":[
        "kleuteronderwijs",
        "basis-"
    ],
    "wof:name":"10E Montessorischool De Meidoorn",
    "wof:placetype":"venue"
},
  "geometry": {"coordinates":[4.861306,52.368946],"type":"Point"}
}