{
  "type": "Feature",
  "properties": {
    "iso:country":"NL",
    "sg:address":"Eemwykpln 12",
    "sg:city":"Voorburg",
    "sg:orig_category":"Beeldende Kunstenaars",
    "sg:phone":"+31 70 386 7783",
    "sg:postcode":"2271 RA",
    "sg:province":"South Holland",
    "wof:name":"Magda Van Elck",
    "wof:placetype":"venue"
},
  "geometry": {"coordinates":[4.37715,52.075989],"type":"Point"}
}