{
  "type": "Feature",
  "properties": {
    "addr:full":"Oranjeln 63B Diepenveen Overijssel 7431 AB",
    "addr:housenumber":"63b",
    "addr:postcode":"7431 ab",
    "addr:street":"Oranjeln",
    "iso:country":"NL",
    "sg:address":"Oranjeln 63B",
    "sg:city":"Diepenveen",
    "sg:orig_category":"Boeken En Tijdschriften",
    "sg:phone":"+31 570 591 602",
    "sg:postcode":"7431 AB",
    "sg:province":"Overijssel",
    "wof:name":"Kasemir, G",
    "wof:placetype":"venue"
},
  "geometry": {"coordinates":[6.148194,52.286186],"type":"Point"}
}