{
  "type": "Feature",
  "properties": {
    "addr:full":"Patrijzenhof 84 Barneveld Gelderland 3772 RJ",
    "addr:housenumber":"84",
    "addr:postcode":"3772 rj",
    "addr:street":"Patrijzenhof;Gelderland",
    "iso:country":"NL",
    "sg:address":"Patrijzenhof 84",
    "sg:city":"Barneveld",
    "sg:classifiers":[
        {
            "category":"Bakery",
            "type":"Food & Drink"
        }
    ],
    "sg:phone":"+31 342 421 576",
    "sg:postcode":"3772 RJ",
    "sg:province":"Gelderland",
    "sg:tags":[
        "brood",
        "banket"
    ],
    "wof:name":"Koekebakker",
    "wof:placetype":"venue"
},
  "geometry": {"coordinates":[5.592218,52.130737],"type":"Point"}
}