{
  "type": "Feature",
  "properties": {
    "addr:full":"Hof 38 Amersfoort Utrecht 3811 CK",
    "addr:housenumber":"38",
    "addr:postcode":"3811 ck",
    "addr:street":"Hof",
    "iso:country":"NL",
    "sg:address":"Hof 38",
    "sg:city":"Amersfoort",
    "sg:classifiers":[
        {
            "category":"Fast Food",
            "type":"Food & Drink"
        }
    ],
    "sg:phone":"+31 33 463 8080",
    "sg:postcode":"3811 CK",
    "sg:province":"Utrecht",
    "sg:tags":[
        "afhaal",
        "restaurant"
    ],
    "wof:name":"Jerusalem Of Gold",
    "wof:placetype":"venue"
},
  "geometry": {"coordinates":[5.386085,52.152325],"type":"Point"}
}