{
  "type": "Feature",
  "properties": {
    "iso:country":"NL",
    "sg:address":"Langedyk 11",
    "sg:city":"Hurdegaryp",
    "sg:orig_category":"Loodgieterswerk, Verwarming And Sanitaire Installaties",
    "sg:phone":"+31 511 475 538",
    "sg:postcode":"9254 DP",
    "sg:province":"Friesland",
    "wof:name":"W. Hoekstra",
    "wof:placetype":"venue"
},
  "geometry": {"coordinates":[5.966514,53.220234],"type":"Point"}
}