{
  "type": "Feature",
  "properties": {
    "addr:full":"Noordvliet 235 Leeuwarden Friesland 8921 GG",
    "addr:housenumber":"235",
    "addr:postcode":"8921 gg",
    "addr:street":"Noordvliet",
    "iso:country":"NL",
    "sg:address":"Noordvliet 235",
    "sg:city":"Leeuwarden",
    "sg:orig_category":"Meubeltextiel Fab",
    "sg:phone":"+31 58 213 4925",
    "sg:postcode":"8921 GG",
    "sg:province":"Friesland",
    "wof:name":"J.M.A. Visser",
    "wof:placetype":"venue"
},
  "geometry": {"coordinates":[5.809009,53.202724],"type":"Point"}
}