{
  "type": "Feature",
  "properties": {
    "addr:full":"Mauritsstr 67 Vianen Zh South Holland 4132 GC",
    "addr:housenumber":"67",
    "addr:postcode":"zh;4132 gc",
    "addr:street":"Mauritsstr",
    "iso:country":"NL",
    "sg:address":"Mauritsstr 67",
    "sg:city":"Vianen Zh",
    "sg:orig_category":"Vertaalbureaus",
    "sg:phone":"+31 347 377 322",
    "sg:postcode":"4132 GC",
    "sg:province":"South Holland",
    "wof:name":"Maurik, Van",
    "wof:placetype":"venue"
},
  "geometry": {"coordinates":[5.093542,51.983238],"type":"Point"}
}