{
  "type": "Feature",
  "properties": {
    "addr:full":"Bruggensewg 29 Deurne Noord-Brabant 5752 SC",
    "addr:housenumber":"29",
    "addr:postcode":"5752 sc",
    "addr:street":"Bruggensewg",
    "iso:country":"NL",
    "sg:address":"Bruggensewg 29",
    "sg:city":"Deurne",
    "sg:orig_category":"Poeliers",
    "sg:phone":"+31 493 312 216",
    "sg:postcode":"5752 SC",
    "sg:province":"Noord-Brabant",
    "wof:name":"Verbaarschot",
    "wof:placetype":"venue"
},
  "geometry": {"coordinates":[5.753683,51.479729],"type":"Point"}
}