{
  "type": "Feature",
  "properties": {
    "addr:full":"Populierendreef 24 Vlaardingen Zuid-Holland 3137 CW",
    "addr:housenumber":"24",
    "addr:postcode":"3137 cw",
    "addr:street":"Populierendreef",
    "iso:country":"NL",
    "sg:address":"Populierendreef 24",
    "sg:city":"Vlaardingen",
    "sg:orig_category":"Boekhouders",
    "sg:phone":"+31 10 474 0418",
    "sg:postcode":"3137 CW",
    "sg:province":"Zuid-Holland",
    "wof:name":"P. Poldervaart Boekhouding & Administrat",
    "wof:placetype":"venue"
},
  "geometry": {"coordinates":[4.347144,51.94067],"type":"Point"}
}