{
  "type": "Feature",
  "properties": {
    "iso:country":"NL",
    "sg:address":"Sagitta 40",
    "sg:city":"Veldhoven",
    "sg:orig_category":"Bedrijfsinventaris Gh",
    "sg:phone":"+31 40 254 9563",
    "sg:postcode":"5505 RX",
    "sg:province":"Noord-Brabant",
    "wof:name":"Dams Development",
    "wof:placetype":"venue"
},
  "geometry": {"coordinates":[5.39507,51.413345],"type":"Point"}
}