{
  "type": "Feature",
  "properties": {
    "addr:full":"Jekerstr 21 Culemborg Gelderland 4105 ZD",
    "addr:housenumber":"21",
    "addr:postcode":"4105 zd",
    "addr:street":"Jekerstr;Gelderland",
    "iso:country":"NL",
    "sg:address":"Jekerstr 21",
    "sg:city":"Culemborg",
    "sg:orig_category":"Woningstoffeerders",
    "sg:phone":"+31 6 54917699",
    "sg:postcode":"4105 ZD",
    "sg:province":"Gelderland",
    "wof:name":"Decarolis, S",
    "wof:placetype":"venue"
},
  "geometry": {"coordinates":[5.211616993,51.9541893005],"type":"Point"}
}