{
  "type": "Feature",
  "properties": {
    "addr:full":"Schuttershofwg 1 Terneuzen Zeeland 4538 AA",
    "addr:housenumber":"1",
    "addr:postcode":"4538 aa",
    "addr:street":"Schuttershofwg",
    "iso:country":"NL",
    "sg:address":"Schuttershofwg 1",
    "sg:city":"Terneuzen",
    "sg:orig_category":"Kamers Van Koophandel",
    "sg:phone":"+31 115 612 952",
    "sg:postcode":"4538 AA",
    "sg:province":"Zeeland",
    "sg:website":"http://www.nl-menu.nl/nlmenu/bedrijven/kvk.html",
    "wof:name":"Kamer Van Koophandel Zeeland",
    "wof:placetype":"venue"
},
  "geometry": {"coordinates":[3.8286559582,51.3345756531],"type":"Point"}
}