{
  "type": "Feature",
  "properties": {
    "iso:country":"NL",
    "sg:address":"Spinfondswg 3",
    "sg:city":"Vaassen",
    "sg:orig_category":"Kunststoffen- Verwerkende Industrie",
    "sg:phone":"+31 578 571 361",
    "sg:postcode":"8171 NT",
    "sg:province":"Gelderland",
    "sg:website":"http://www.habeva.nl",
    "wof:name":"Habeva Bv",
    "wof:placetype":"venue"
},
  "geometry": {"coordinates":[5.985406,52.298824],"type":"Point"}
}