{
  "type": "Feature",
  "properties": {
    "addr:full":"Cantonlaan 7 Baarn Utrecht 3742 CH",
    "addr:housenumber":"7",
    "addr:postcode":"3742",
    "addr:street":"Cantonlaan",
    "iso:country":"NL",
    "sg:address":"Cantonlaan 7",
    "sg:city":"Baarn",
    "sg:orig_category":"Artsen And Specialisten",
    "sg:phone":"+31 35 542 0664",
    "sg:postcode":"3742 CH",
    "sg:province":"Utrecht",
    "wof:name":"J.H.P. Aarts",
    "wof:placetype":"venue"
},
  "geometry": {"coordinates":[5.294948,52.210312],"type":"Point"}
}