{
  "type": "Feature",
  "properties": {
    "addr:full":"K Tiendewg 8 Gouda Zuid-Holland 2801 JT",
    "addr:housenumber":"8",
    "addr:postcode":"2801 jt",
    "addr:street":"Tiendewg",
    "iso:country":"NL",
    "sg:address":"K Tiendewg 8",
    "sg:city":"Gouda",
    "sg:orig_category":"Behangselpapier En Wandbekleding",
    "sg:phone":"+31 182 513 758",
    "sg:postcode":"2801 JT",
    "sg:province":"Zuid-Holland",
    "wof:name":"Dam, C Van",
    "wof:placetype":"venue"
},
  "geometry": {"coordinates":[4.711722,52.011505],"type":"Point"}
}