{
  "type": "Feature",
  "properties": {
    "addr:full":"Gerrit Bolkade 62 A Zaandam Noord-Holland 1507 BR",
    "addr:housenumber":"62 a",
    "addr:postcode":"1507 br",
    "addr:street":"Gerrit Bolkade",
    "iso:country":"NL",
    "sg:address":"Gerrit Bolkade 62 A",
    "sg:city":"Zaandam",
    "sg:orig_category":"Verhuur Audiovisuele Apparatuur",
    "sg:phone":"+31 75 614 3198",
    "sg:postcode":"1507 BR",
    "sg:province":"Noord-Holland",
    "wof:name":"Top Music Service",
    "wof:placetype":"venue"
},
  "geometry": {"coordinates":[4.816071,52.42754],"type":"Point"}
}