{
  "type": "Feature",
  "properties": {
    "addr:full":"Postbus 632 Honselersdijk Zuid-Holland 2675 ZW",
    "addr:housenumber":"632",
    "addr:postcode":"2675 zw",
    "addr:street":"Postbus",
    "iso:country":"NL",
    "sg:address":"Postbus 632",
    "sg:city":"Honselersdijk",
    "sg:orig_category":"Bloemen En Planten - Veilingen",
    "sg:phone":"+31 174 615 310",
    "sg:postcode":"2675 ZW",
    "sg:province":"Zuid-Holland",
    "wof:name":"Hogewoning Bv",
    "wof:placetype":"venue"
},
  "geometry": {"coordinates":[4.22951,52.008755],"type":"Point"}
}