{
  "type": "Feature",
  "properties": {
    "iso:country":"NL",
    "sg:address":"Dwarsweg 4",
    "sg:city":"S Heer Arendskerke",
    "sg:orig_category":"Politieke Organisaties",
    "sg:phone":"+31 113 670 055",
    "sg:postcode":"4458 NE",
    "sg:province":"Zeeland",
    "wof:name":"Nederland-Mobiel Secretariaat",
    "wof:placetype":"venue"
},
  "geometry": {"coordinates":[3.762641,51.501801],"type":"Point"}
}