{
  "type": "Feature",
  "properties": {
    "addr:full":"Mathenessestr 41Bis Breda Noord-Brabant 4834 EA",
    "addr:housenumber":"41bis",
    "addr:postcode":"4834 ea",
    "iso:country":"NL",
    "sg:address":"Mathenessestr 41Bis",
    "sg:city":"Breda",
    "sg:orig_category":"Zonweringen",
    "sg:phone":"+31 76 564 0500",
    "sg:postcode":"4834 EA",
    "sg:province":"Noord-Brabant",
    "wof:name":"Weinor",
    "wof:placetype":"venue"
},
  "geometry": {"coordinates":[4.80072,51.573296],"type":"Point"}
}