{
  "type": "Feature",
  "properties": {
    "addr:full":"Iepenlaan 7 Harmelen Utrecht 3481 XA",
    "addr:housenumber":"7",
    "addr:postcode":"3481 xa",
    "addr:street":"Iepenlaan",
    "iso:country":"NL",
    "sg:address":"Iepenlaan 7",
    "sg:city":"Harmelen",
    "sg:orig_category":"Banken And Kredietinstellingen",
    "sg:phone":"+31 348 441 230",
    "sg:postcode":"3481 XA",
    "sg:province":"Utrecht",
    "wof:name":"Postkantoor",
    "wof:placetype":"venue"
},
  "geometry": {"coordinates":[4.965428,52.090786],"type":"Point"}
}