{
  "type": "Feature",
  "properties": {
    "addr:full":"Peppelweg 96 Rotterdam Zuid-Holland 3053 GR",
    "addr:housenumber":"96",
    "addr:postcode":"3053",
    "addr:street":"Peppelweg",
    "iso:country":"NL",
    "sg:address":"Peppelweg 96",
    "sg:city":"Rotterdam",
    "sg:orig_category":"Discountwinkels",
    "sg:phone":"+31 10 285 0030",
    "sg:postcode":"3053 GR",
    "sg:province":"Zuid-Holland",
    "wof:name":"Zeeman Textielsupers",
    "wof:placetype":"venue"
},
  "geometry": {"coordinates":[4.471948,51.959694],"type":"Point"}
}