{
  "type": "Feature",
  "properties": {
    "addr:full":"Mr Troelstraln 27 Amstelveen Noord-Holland 1181 VD",
    "addr:housenumber":"27",
    "addr:postcode":"1181 vd",
    "iso:country":"NL",
    "sg:address":"Mr Troelstraln 27",
    "sg:city":"Amstelveen",
    "sg:classifiers":[
        {
            "category":"Real Estate",
            "subcategory":"Real Estate Operator",
            "type":"Services"
        }
    ],
    "sg:phone":"+31 20 441 7673",
    "sg:postcode":"1181 VD",
    "sg:province":"Noord-Holland",
    "sg:tags":[
        "appartementen",
        "en",
        "flat"
    ],
    "wof:name":"Seaport Beach",
    "wof:placetype":"venue"
},
  "geometry": {"coordinates":[4.853461,52.30648],"type":"Point"}
}