{
  "type": "Feature",
  "properties": {
    "addr:full":"Breegraven 128 Warnsveld Gelderland 7231 JJ",
    "addr:housenumber":"128",
    "addr:postcode":"7231 jj",
    "addr:street":"Breegraven;Gelderland",
    "iso:country":"NL",
    "sg:address":"Breegraven 128",
    "sg:city":"Warnsveld",
    "sg:orig_category":"Goederenvervoer Over De Weg",
    "sg:phone":"+31 575 522 016",
    "sg:postcode":"7231 JJ",
    "sg:province":"Gelderland",
    "wof:name":"Transportbedrijf E. Disbergen",
    "wof:placetype":"venue"
},
  "geometry": {"coordinates":[6.227357,52.137352],"type":"Point"}
}