{
  "type": "Feature",
  "properties": {
    "addr:full":"Touwslagerswg 10 Woerden South Holland 3449 HX",
    "addr:housenumber":"10",
    "addr:postcode":"3449 hx",
    "addr:street":"Touwslagerswg",
    "iso:country":"NL",
    "sg:address":"Touwslagerswg 10",
    "sg:city":"Woerden",
    "sg:classifiers":[
        {
            "category":"Professional",
            "subcategory":"Accounting & Tax Preparation",
            "type":"Services"
        }
    ],
    "sg:phone":"+31 348 430 770",
    "sg:postcode":"3449 HX",
    "sg:province":"South Holland",
    "sg:tags":[
        "accountant",
        "en",
        "-kantoren",
        "register-"
    ],
    "wof:name":"Schalkwijk Registeraccountants En Belastingadviseurs Bv",
    "wof:placetype":"venue"
},
  "geometry": {"coordinates":[4.861193,52.083221],"type":"Point"}
}