{
  "type": "Feature",
  "properties": {
    "addr:full":"Wilhelminaln 1 Purmerend North Holland 1441 EK",
    "addr:housenumber":"1",
    "addr:postcode":"1441 ek",
    "addr:street":"Wilhelminaln",
    "iso:country":"NL",
    "sg:address":"Wilhelminaln 1",
    "sg:city":"Purmerend",
    "sg:orig_category":"Verenigingen En Stichtingen",
    "sg:phone":"+31 299 433 296",
    "sg:postcode":"1441 EK",
    "sg:province":"North Holland",
    "wof:name":"Ouderenhulp Svo",
    "wof:placetype":"venue"
},
  "geometry": {"coordinates":[4.952334,52.50462],"type":"Point"}
}