{
  "type": "Feature",
  "properties": {
    "addr:full":"P Heinstr 41 Delfzyl Groningen 9934 HK",
    "addr:housenumber":"41",
    "addr:postcode":"9934 hk",
    "addr:street":"P;Delfzyl",
    "iso:country":"NL",
    "sg:address":"P Heinstr 41",
    "sg:city":"Delfzyl",
    "sg:classifiers":[
        {
            "category":"Retail",
            "subcategory":"Auto Repair",
            "type":"Services"
        }
    ],
    "sg:phone":"+31 596 614 936",
    "sg:postcode":"9934 HK",
    "sg:province":"Groningen",
    "sg:tags":[
        "garage"
    ],
    "wof:name":"Oud-West",
    "wof:placetype":"venue"
},
  "geometry": {"coordinates":[6.903212,53.331192],"type":"Point"}
}