{
  "type": "Feature",
  "properties": {
    "addr:full":"Drossaard 57 Bergen Op Zoom Noord-Brabant 4624 KB",
    "addr:housenumber":"57",
    "addr:postcode":"4624 kb",
    "addr:street":"Drossaard",
    "iso:country":"NL",
    "sg:address":"Drossaard 57",
    "sg:city":"Bergen Op Zoom",
    "sg:orig_category":"Administratie- En Boekhoudkantoren",
    "sg:phone":"+31 164 266 116",
    "sg:postcode":"4624 KB",
    "sg:province":"Noord-Brabant",
    "wof:name":"Navigator-Surplus",
    "wof:placetype":"venue"
},
  "geometry": {"coordinates":[4.298131,51.479492],"type":"Point"}
}