{
  "type": "Feature",
  "properties": {
    "addr:full":"Huijghenslaan 22 Arnhem Gelderland 6824 JH",
    "addr:housenumber":"22",
    "addr:postcode":"6824 jh",
    "addr:street":"Huijghenslaan",
    "iso:country":"NL",
    "sg:address":"Huijghenslaan 22",
    "sg:city":"Arnhem",
    "sg:orig_category":"Bedrijfs- And Managementsconsultants",
    "sg:phone":"+31 26 445 3601",
    "sg:postcode":"6824 JH",
    "sg:province":"Gelderland",
    "wof:name":"Schoonbrood Management Services Bv",
    "wof:placetype":"venue"
},
  "geometry": {"coordinates":[5.934299,51.991726],"type":"Point"}
}