{
  "type": "Feature",
  "properties": {
    "addr:full":"W V Otterloostr 42 Hengelo NL.08 7558 BV",
    "addr:housenumber":"42;nl.08",
    "addr:postcode":"7558 bv",
    "addr:street":"W V Otterloostr",
    "iso:country":"NL",
    "sg:address":"W V Otterloostr 42",
    "sg:city":"Hengelo",
    "sg:orig_category":"Mensendieck - Oefentherapeuten",
    "sg:phone":"+31 74 277 1210",
    "sg:postcode":"7558 BV",
    "sg:province":"NL.08",
    "wof:name":"Kuster-Bellmann, A I",
    "wof:placetype":"venue"
},
  "geometry": {"coordinates":[6.789712,52.266361],"type":"Point"}
}