{
  "type": "Feature",
  "properties": {
    "addr:full":"Piet Blokkerstraat 64 Schagen Noord-Holland 1742 RZ",
    "addr:housenumber":"64",
    "addr:postcode":"1742 rz",
    "addr:street":"Piet Blokkerstraat",
    "iso:country":"NL",
    "sg:address":"Piet Blokkerstraat 64",
    "sg:city":"Schagen",
    "sg:orig_category":"Verhuur Bouwmachines",
    "sg:phone":"+31 224 216 795",
    "sg:postcode":"1742 RZ",
    "sg:province":"Noord-Holland",
    "wof:name":"Kraanverhuur Tieman",
    "wof:placetype":"venue"
},
  "geometry": {"coordinates":[4.80034,52.779995],"type":"Point"}
}