{
  "type": "Feature",
  "properties": {
    "addr:full":"Dordsedijk 101 Klazienaveen Provincie Drenthe 7891 NL",
    "addr:housenumber":"101",
    "addr:postcode":"7891",
    "addr:street":"Dordsedijk;Provincie Drenthe",
    "iso:country":"NL",
    "sg:address":"Dordsedijk 101",
    "sg:city":"Klazienaveen",
    "sg:orig_category":"Landbouwmachines Gh",
    "sg:phone":"+31 591 316 279",
    "sg:postcode":"7891 NL",
    "sg:province":"Provincie Drenthe",
    "wof:name":"W. Bryan Machines",
    "wof:placetype":"venue"
},
  "geometry": {"coordinates":[6.98345,52.707588],"type":"Point"}
}