{
  "type": "Feature",
  "properties": {
    "iso:country":"NL",
    "sg:address":"Dordsedijk 101",
    "sg:city":"Klazienaveen",
    "sg:orig_category":"Landbouwmachines Gh",
    "sg:phone":"+31 591 316 279",
    "sg:postcode":"7891 NL",
    "sg:province":"Provincie Drenthe",
    "wof:name":"W. Bryan Machines",
    "wof:placetype":"venue"
},
  "geometry": {"coordinates":[6.98345,52.707588],"type":"Point"}
}