{
  "type": "Feature",
  "properties": {
    "iso:country":"NL",
    "sg:address":"Lange Herenvest 82",
    "sg:city":"Haarlem",
    "sg:orig_category":"Schilderwerk",
    "sg:phone":"+31 23 545 1010",
    "sg:postcode":"2011 BV",
    "sg:province":"Noord-Holland",
    "wof:name":"Firma H. Bijster Jr & Zn",
    "wof:placetype":"venue"
},
  "geometry": {"coordinates":[4.643515,52.378403],"type":"Point"}
}