{
  "type": "Feature",
  "properties": {
    "addr:full":"Nieuwstraat 25 Woerden Utrecht 3441 EA",
    "addr:housenumber":"25",
    "addr:postcode":"3441 ea",
    "addr:street":"Nieuwstraat",
    "iso:country":"NL",
    "sg:address":"Nieuwstraat 25",
    "sg:city":"Woerden",
    "sg:orig_category":"Babyartikelen Detailhandel",
    "sg:phone":"+31 348 424 985",
    "sg:postcode":"3441 EA",
    "sg:province":"Utrecht",
    "wof:name":"Ravelijntje",
    "wof:placetype":"venue"
},
  "geometry": {"coordinates":[4.83671,52.114052],"type":"Point"}
}