{
  "type": "Feature",
  "properties": {
    "addr:full":"Spoorweide 2 Riel Noord-Brabant 5133 NM",
    "addr:housenumber":"2",
    "addr:postcode":"5133",
    "addr:street":"Spoorweide",
    "iso:country":"NL",
    "sg:address":"Spoorweide 2",
    "sg:city":"Riel",
    "sg:orig_category":"Verpakkingen En Verpakkingsmaterialen",
    "sg:phone":"+31 13 518 1456",
    "sg:postcode":"5133 NM",
    "sg:province":"Noord-Brabant",
    "wof:name":"Jaro Houten",
    "wof:placetype":"venue"
},
  "geometry": {"coordinates":[5.014516,51.520939],"type":"Point"}
}