{
  "type": "Feature",
  "properties": {
    "iso:country":"NL",
    "sg:address":"Oude Stadsgracht 1",
    "sg:city":"Eindhoven",
    "sg:orig_category":"Werving And Selectie Van Tijdelijk Personeel And Uitzendkantoren",
    "sg:phone":"+31 40 297 2300",
    "sg:postcode":"5611 DD",
    "sg:province":"Noord-Brabant",
    "wof:name":"Start",
    "wof:placetype":"venue"
},
  "geometry": {"coordinates":[5.4838151932,51.4363327026],"type":"Point"}
}