{
  "type": "Feature",
  "properties": {
    "addr:full":"Zevende Slagen 105 'S Hertogenbosch Noord-Brabant 5233 VB",
    "addr:housenumber":"105 ' s",
    "addr:postcode":"5233 vb",
    "addr:street":"Zevende Slagen",
    "iso:country":"NL",
    "sg:address":"Zevende Slagen 105",
    "sg:city":"'S Hertogenbosch",
    "sg:orig_category":"Fotostudio'S And Fotografen",
    "sg:phone":"+31 73 642 9346",
    "sg:postcode":"5233 VB",
    "sg:province":"Noord-Brabant",
    "wof:name":"Peer Reede",
    "wof:placetype":"venue"
},
  "geometry": {"coordinates":[5.322809,51.711159],"type":"Point"}
}