{
  "type": "Feature",
  "properties": {
    "addr:full":"Agter De Hoven 24 Wanssum Limburg 5861 CJ",
    "addr:housenumber":"24",
    "addr:postcode":"5861 cj",
    "addr:street":"Agter De Hoven",
    "iso:country":"NL",
    "sg:address":"Agter De Hoven 24",
    "sg:city":"Wanssum",
    "sg:orig_category":"Adviesbureaus Bedrijfsorganisatie",
    "sg:phone":"+31 478 539 143",
    "sg:postcode":"5861 CJ",
    "sg:province":"Limburg",
    "wof:name":"Joe",
    "wof:placetype":"venue"
},
  "geometry": {"coordinates":[6.070509,51.534035],"type":"Point"}
}