{
  "type": "Feature",
  "properties": {
    "iso:country":"NL",
    "sg:address":"Agter De Hoven 24",
    "sg:city":"Wanssum",
    "sg:orig_category":"Adviesbureaus Bedrijfsorganisatie",
    "sg:phone":"+31 478 539 143",
    "sg:postcode":"5861 CJ",
    "sg:province":"Limburg",
    "wof:name":"Joe",
    "wof:placetype":"venue"
},
  "geometry": {"coordinates":[6.070509,51.534035],"type":"Point"}
}