{
  "type": "Feature",
  "properties": {
    "iso:country":"NL",
    "sg:address":"Stoelery 14",
    "sg:city":"Zevenbergen",
    "sg:orig_category":"Pompen",
    "sg:phone":"+31 168 370 950",
    "sg:postcode":"4762 AN",
    "sg:province":"Noord-Brabant",
    "wof:name":"Nijhuis",
    "wof:placetype":"venue"
},
  "geometry": {"coordinates":[4.613566,51.643715],"type":"Point"}
}