{
  "type": "Feature",
  "properties": {
    "iso:country":"NL",
    "sg:address":"Peebos 25",
    "sg:city":"Opende",
    "sg:orig_category":"Adviesbureaus Bedrijfsorganisatie",
    "sg:phone":"+31 594 659 896",
    "sg:postcode":"9865 TG",
    "sg:province":"Groningen",
    "wof:name":"Harms",
    "wof:placetype":"venue"
},
  "geometry": {"coordinates":[6.216809,53.194653],"type":"Point"}
}