{
  "type": "Feature",
  "properties": {
    "addr:full":"Dracht 89 Heerenveen Provincie Friesland 8442 BM",
    "addr:housenumber":"89",
    "addr:postcode":"8442 bm",
    "addr:street":"Dracht;Provincie Friesland",
    "iso:country":"NL",
    "sg:address":"Dracht 89",
    "sg:city":"Heerenveen",
    "sg:classifiers":[
        {
            "category":"Retail",
            "subcategory":"Photofinishing",
            "type":"Services"
        }
    ],
    "sg:phone":"+31 513 622 401",
    "sg:postcode":"8442 BM",
    "sg:province":"Provincie Friesland",
    "sg:tags":[
        "foto",
        "film"
    ],
    "wof:name":"Objektief",
    "wof:placetype":"venue"
},
  "geometry": {"coordinates":[5.925366,52.958099],"type":"Point"}
}