{
  "type": "Feature",
  "properties": {
    "iso:country":"NL",
    "sg:address":"R. Van De Weijdenstraat 2",
    "sg:city":"Den Bosch",
    "sg:orig_category":"Overheidsdiensten",
    "sg:phone":"+31 73 614 4043",
    "sg:postcode":"5213 CA",
    "sg:province":"Noord-Brabant",
    "wof:name":"Buurthuis De Schuur",
    "wof:placetype":"venue"
},
  "geometry": {"coordinates":[5.3270897865,51.6980514526],"type":"Point"}
}