{
  "type": "Feature",
  "properties": {
    "addr:full":"Paardepad 2 Hindeloopen Friesland 8713 KR",
    "addr:housenumber":"2",
    "addr:postcode":"8713 kr",
    "addr:street":"Paardepad",
    "iso:country":"NL",
    "sg:address":"Paardepad 2",
    "sg:city":"Hindeloopen",
    "sg:classifiers":[
        {
            "category":"Travel",
            "subcategory":"Hotels & Motels",
            "type":"Entertainment"
        }
    ],
    "sg:phone":"+31 514 522 873",
    "sg:postcode":"8713 KR",
    "sg:province":"Friesland",
    "wof:name":"Twee Hondjes, Hotel-Pension De",
    "wof:placetype":"venue"
},
  "geometry": {"coordinates":[5.400509,52.942852],"type":"Point"}
}