{
  "type": "Feature",
  "properties": {
    "iso:country":"NL",
    "sg:address":"Dokwg 33A",
    "sg:city":"Ymuiden",
    "sg:orig_category":"Accountants - Administratie- Consulenten En -Kantoren",
    "sg:phone":"+31 255 518 813",
    "sg:postcode":"1976 CA",
    "sg:province":"Noord-Holland",
    "wof:name":"V & S Group Bv",
    "wof:placetype":"venue"
},
  "geometry": {"coordinates":[-119.270203,37.271832],"type":"Point"}
}