{
  "type": "Feature",
  "properties": {
    "iso:country":"NL",
    "sg:address":"Prinses Margrietlaan 6",
    "sg:city":"Rotterdam",
    "sg:classifiers":[
        {
            "category":"Education",
            "subcategory":"Preschool",
            "type":"Public Place"
        }
    ],
    "sg:phone":"+31 10 422 2435",
    "sg:postcode":"3051 AT",
    "sg:province":"South Holland",
    "sg:tags":[
        "kleuteronderwijs",
        "basis-"
    ],
    "wof:name":"Peuterspeelzaal De Malle Kikker",
    "wof:placetype":"venue"
},
  "geometry": {"coordinates":[4.485793,51.946819],"type":"Point"}
}