{
  "type": "Feature",
  "properties": {
    "addr:full":"Postbus 90170 Tilburg Noord-Brabant 5000 LM",
    "addr:housenumber":"90170",
    "addr:postcode":"5000 lm",
    "addr:street":"Postbus",
    "iso:country":"NL",
    "sg:address":"Postbus 90170",
    "sg:city":"Tilburg",
    "sg:orig_category":"Pensioenfondsen",
    "sg:phone":"+31 13 462 3517",
    "sg:postcode":"5000 LM",
    "sg:province":"Noord-Brabant",
    "wof:name":"Houtverwerkende Ind",
    "wof:placetype":"venue"
},
  "geometry": {"coordinates":[5.10623,51.554878],"type":"Point"}
}