{
  "type": "Feature",
  "properties": {
    "addr:full":"Noordmolenstr 22 Rotterdam Zuid-Holland 3035 RJ",
    "addr:housenumber":"22",
    "addr:postcode":"3035 rj",
    "addr:street":"Noordmolenstr",
    "iso:country":"NL",
    "sg:address":"Noordmolenstr 22",
    "sg:city":"Rotterdam",
    "sg:orig_category":"Poeliers",
    "sg:phone":"+31 10 467 0654",
    "sg:postcode":"3035 RJ",
    "sg:province":"Zuid-Holland",
    "wof:name":"Korfez",
    "wof:placetype":"venue"
},
  "geometry": {"coordinates":[4.483307,51.931271],"type":"Point"}
}