{
  "type": "Feature",
  "properties": {
    "addr:full":"Stoutenburgstr 45 Breda Noord-Brabant 4834 LN",
    "addr:housenumber":"45",
    "addr:postcode":"4834 ln",
    "addr:street":"Stoutenburgstr",
    "iso:country":"NL",
    "sg:address":"Stoutenburgstr 45",
    "sg:city":"Breda",
    "sg:orig_category":"Verenigingen En Stichtingen",
    "sg:phone":"+31 76 565 4108",
    "sg:postcode":"4834 LN",
    "sg:province":"Noord-Brabant",
    "wof:name":"Literaire Aktiviteiten Breda, Sticht",
    "wof:placetype":"venue"
},
  "geometry": {"coordinates":[4.808915,51.57156],"type":"Point"}
}