{
  "type": "Feature",
  "properties": {
    "iso:country":"NL",
    "sg:address":"Langeraarseweg 118",
    "sg:city":"Ter Aar",
    "sg:orig_category":"Boekhouders",
    "sg:phone":"+31 172 605 185",
    "sg:postcode":"2461 CM",
    "sg:province":"Zuid-Holland",
    "wof:name":"Adm- En Belastingadvieskantoor J.A.M. Turk",
    "wof:placetype":"venue"
},
  "geometry": {"coordinates":[4.70101,52.18919],"type":"Point"}
}