{
  "type": "Feature",
  "properties": {
    "addr:full":"Marconistr 10-12 Zwolle NL.08 8013 PK",
    "addr:housenumber":"10-12",
    "addr:postcode":"8013 pk",
    "iso:country":"NL",
    "sg:address":"Marconistr 10-12",
    "sg:city":"Zwolle",
    "sg:orig_category":"Automaterialen En Gereedschappen",
    "sg:phone":"+31 38 467 2872",
    "sg:postcode":"8013 PK",
    "sg:province":"NL.08",
    "wof:name":"Lasaulec Zwolle",
    "wof:placetype":"venue"
},
  "geometry": {"coordinates":[6.126228,52.497353],"type":"Point"}
}