{
  "type": "Feature",
  "properties": {
    "iso:country":"NL",
    "sg:address":"Vogelenzangseweg 1",
    "sg:city":"Lienden",
    "sg:orig_category":"Bloemen And Planten",
    "sg:phone":"+31 344 602 565",
    "sg:postcode":"4033 AG",
    "sg:province":"Gelderland",
    "wof:name":"Vof Bloemsierkunst J.D. Van Ingen",
    "wof:placetype":"venue"
},
  "geometry": {"coordinates":[5.515622,51.945732],"type":"Point"}
}