{
  "type": "Feature",
  "properties": {
    "addr:full":"Ln V Westmolen 51 Mynsheerenland Zuid-Holland 3271 BJ",
    "addr:housenumber":"51",
    "addr:postcode":"3271 bj",
    "addr:street":"Ln;Westmolen",
    "iso:country":"NL",
    "sg:address":"Ln V Westmolen 51",
    "sg:city":"Mynsheerenland",
    "sg:orig_category":"Sportverenigingen En Ontspannings- Verenigingen",
    "sg:phone":"+31 10 213 0299",
    "sg:postcode":"3271 BJ",
    "sg:province":"Zuid-Holland",
    "wof:name":"Herons Basketbalver",
    "wof:placetype":"venue"
},
  "geometry": {"coordinates":[4.492185,51.797523],"type":"Point"}
}