{
  "type": "Feature",
  "properties": {
    "addr:full":"Dorpsstraat 135 Zwaag Noord-Holland 1689 GA",
    "addr:housenumber":"135",
    "addr:postcode":"1689 ga",
    "addr:street":"Dorpsstraat",
    "iso:country":"NL",
    "sg:address":"Dorpsstraat 135",
    "sg:city":"Zwaag",
    "sg:orig_category":"Kappers",
    "sg:phone":"+31 229 236 832",
    "sg:postcode":"1689 GA",
    "sg:province":"Noord-Holland",
    "wof:name":"Maison Avenir",
    "wof:placetype":"venue"
},
  "geometry": {"coordinates":[5.069401,52.666893],"type":"Point"}
}