{
  "type": "Feature",
  "properties": {
    "addr:full":"Van Zeggelenplein 83 Haarlem North Holland 2032 KD",
    "addr:housenumber":"83",
    "addr:postcode":"2032 kd",
    "addr:street":"Van Zeggelenplein",
    "iso:country":"NL",
    "sg:address":"Van Zeggelenplein 83",
    "sg:city":"Haarlem",
    "sg:orig_category":"Kappers",
    "sg:phone":"+31 23 535 0682",
    "sg:postcode":"2032 KD",
    "sg:province":"North Holland",
    "wof:name":"Onze Knipsalon Nina En Monique",
    "wof:placetype":"venue"
},
  "geometry": {"coordinates":[4.658207,52.379272],"type":"Point"}
}