{
  "type": "Feature",
  "properties": {
    "iso:country":"NL",
    "sg:address":"St. Canisiussingel 26M",
    "sg:city":"Nijmegen",
    "sg:orig_category":"Werving And Selectie Van Tijdelijk Personeel And Uitzendkantoren",
    "sg:phone":"+31 24 388 8223",
    "sg:postcode":"6511 TJ",
    "sg:province":"Gelderland",
    "wof:name":"Start",
    "wof:placetype":"venue"
},
  "geometry": {"coordinates":[5.870516777,51.8441581726],"type":"Point"}
}