{
  "type": "Feature",
  "properties": {
    "iso:country":"NL",
    "sg:address":"Nicolaas Beetsplein 7",
    "sg:city":"Hoogeveen",
    "sg:orig_category":"Kappers",
    "sg:phone":"+31 528 268 604",
    "sg:postcode":"7901 KL",
    "sg:province":"Drenthe",
    "wof:name":"Kapsalon Bert De Vries",
    "wof:placetype":"venue"
},
  "geometry": {"coordinates":[6.4765791893,52.7233695984],"type":"Point"}
}