{
  "type": "Feature",
  "properties": {
    "addr:full":"Bruggelaan 26 Eindhoven North Brabant 5628 RH",
    "addr:housenumber":"26",
    "addr:postcode":"5628 rh",
    "addr:street":"Bruggelaan",
    "iso:country":"NL",
    "sg:address":"Bruggelaan 26",
    "sg:city":"Eindhoven",
    "sg:orig_category":"Paramedische Behandelingen",
    "sg:phone":"+31 40 241 3395",
    "sg:postcode":"5628 RH",
    "sg:province":"North Brabant",
    "wof:name":"W Verheyen-Timmer",
    "wof:placetype":"venue"
},
  "geometry": {"coordinates":[5.480033,51.478577],"type":"Point"}
}