{
  "type": "Feature",
  "properties": {
    "addr:full":"Sint Jozefstraat 1 Standdaarbuiten Noord-Brabant 4758 TD",
    "addr:housenumber":"1",
    "addr:postcode":"4758 td",
    "addr:street":"Sint Jozefstraat",
    "iso:country":"NL",
    "sg:address":"Sint Jozefstraat 1",
    "sg:city":"Standdaarbuiten",
    "sg:orig_category":"Goederenvervoer Over De Weg",
    "sg:phone":"+31 168 403 630",
    "sg:postcode":"4758 TD",
    "sg:province":"Noord-Brabant",
    "wof:name":"William Sitters",
    "wof:placetype":"venue"
},
  "geometry": {"coordinates":[4.530653,51.641964],"type":"Point"}
}