{
  "type": "Feature",
  "properties": {
    "addr:full":"Stationspln 8 Amersfoort Utrecht 3818 LE",
    "addr:housenumber":"8",
    "addr:postcode":"3818 le",
    "addr:street":"Stationspln",
    "iso:country":"NL",
    "sg:address":"Stationspln 8",
    "sg:city":"Amersfoort",
    "sg:orig_category":"Verenigingen En Stichtingen",
    "sg:phone":"+31 33 422 0982",
    "sg:postcode":"3818 LE",
    "sg:province":"Utrecht",
    "sg:website":"http://home.wxs.nl/~nlv/",
    "wof:name":"Ned Leverpati\u00ebnten Ver",
    "wof:placetype":"venue"
},
  "geometry": {"coordinates":[5.386085,52.152325],"type":"Point"}
}