{
  "type": "Feature",
  "properties": {
    "addr:full":"Vinkelsestraat 99 Heesch Noord-Brabant 5384 SE",
    "addr:housenumber":"99",
    "addr:postcode":"5384 se",
    "addr:street":"Vinkelsestraat",
    "iso:country":"NL",
    "sg:address":"Vinkelsestraat 99",
    "sg:city":"Heesch",
    "sg:orig_category":"Verhuur Catering-, Feest- En Evenementbenodigdheden",
    "sg:phone":"+31 412 451 492",
    "sg:postcode":"5384 SE",
    "sg:province":"Noord-Brabant",
    "wof:name":"Van De Wijgert Verhuur Bv",
    "wof:placetype":"venue"
},
  "geometry": {"coordinates":[5.503365,51.714558],"type":"Point"}
}