{
  "type": "Feature",
  "properties": {
    "addr:full":"Meerpaal 225 Groningen Groningen 9732 AN",
    "addr:housenumber":"225",
    "addr:postcode":"9732 an",
    "addr:street":"Meerpaal",
    "iso:country":"NL",
    "sg:address":"Meerpaal 225",
    "sg:city":"Groningen",
    "sg:orig_category":"Acupunctuur",
    "sg:phone":"+31 50 541 0964",
    "sg:postcode":"9732 AN",
    "sg:province":"Groningen",
    "wof:name":"Aukesz Van Der Meer, Drs W J J",
    "wof:placetype":"venue"
},
  "geometry": {"coordinates":[6.630546093,53.2350540161],"type":"Point"}
}