{
  "type": "Feature",
  "properties": {
    "addr:full":"Oostduinlaan 169 'S Gravenhage South Holland 2596 JL",
    "addr:housenumber":"169 '",
    "addr:postcode":"2596 jl",
    "addr:street":"Oostduinlaan",
    "iso:country":"NL",
    "sg:address":"Oostduinlaan 169",
    "sg:city":"'S Gravenhage",
    "sg:orig_category":"Bedrijfs- And Managementsconsultants",
    "sg:phone":"+31 70 354 9704",
    "sg:postcode":"2596 JL",
    "sg:province":"South Holland",
    "wof:name":"Ass Zorgmanagement Voorlopers Veranderin",
    "wof:placetype":"venue"
},
  "geometry": {"coordinates":[4.314889,52.092388],"type":"Point"}
}