{
  "type": "Feature",
  "properties": {
    "addr:full":"Overwinningsplein 6 Groningen Groningen 9728 GT",
    "addr:housenumber":"6",
    "addr:postcode":"9728 gt",
    "addr:street":"Overwinningsplein",
    "iso:country":"NL",
    "sg:address":"Overwinningsplein 6",
    "sg:city":"Groningen",
    "sg:orig_category":"Opticiens",
    "sg:phone":"+31 50 525 0288",
    "sg:postcode":"9728 GT",
    "sg:province":"Groningen",
    "wof:name":"Marrink Kompleet Optiek",
    "wof:placetype":"venue"
},
  "geometry": {"coordinates":[6.5597920418,53.19789505],"type":"Point"}
}