{
  "type": "Feature",
  "properties": {
    "addr:full":"Langeweg 20 Nieuwe Tonge South Holland 3244 BH",
    "addr:housenumber":"20",
    "addr:postcode":"3244 bh",
    "addr:street":"Langeweg;Nieuwe Tonge",
    "iso:country":"NL",
    "sg:address":"Langeweg 20",
    "sg:city":"Nieuwe Tonge",
    "sg:classifiers":[
        {
            "category":"Retail",
            "subcategory":"Storage",
            "type":"Services"
        }
    ],
    "sg:phone":"+31 187 651 283",
    "sg:postcode":"3244 BH",
    "sg:province":"South Holland",
    "sg:tags":[
        "opslag",
        "bewaring"
    ],
    "wof:name":"Visbeen Holding Bv",
    "wof:placetype":"venue"
},
  "geometry": {"coordinates":[4.1725611687,51.7232704163],"type":"Point"}
}