{
  "type": "Feature",
  "properties": {
    "iso:country":"NL",
    "sg:address":"Dorpsstr 213-215",
    "sg:city":"Scherpenzeel Gld",
    "sg:orig_category":"Fietsen En Bromfietsen",
    "sg:phone":"+31 33 277 1278",
    "sg:postcode":"3925 KB",
    "sg:province":"Gelderland",
    "wof:name":"Boer, J Den",
    "wof:placetype":"venue"
},
  "geometry": {"coordinates":[5.486276,52.079842],"type":"Point"}
}