{
  "type": "Feature",
  "properties": {
    "addr:full":"Grote Bredeplaats 31 Harlingen Friesland 8861 BA",
    "addr:housenumber":"31",
    "addr:postcode":"8861 ba",
    "addr:street":"Grote Bredeplaats",
    "iso:country":"NL",
    "sg:address":"Grote Bredeplaats 31",
    "sg:city":"Harlingen",
    "sg:orig_category":"Verzekeringen",
    "sg:phone":"+31 517 419 755",
    "sg:postcode":"8861 BA",
    "sg:province":"Friesland",
    "wof:name":"Assurantiekantoor Haringa",
    "wof:placetype":"venue"
},
  "geometry": {"coordinates":[5.415524,53.17503],"type":"Point"}
}