{
  "type": "Feature",
  "properties": {
    "iso:country":"NL",
    "sg:address":"Berkenhof 69",
    "sg:city":"Didam",
    "sg:orig_category":"Bodemonderzoek",
    "sg:phone":"+31 316 227 214",
    "sg:postcode":"6941 ZV",
    "sg:province":"Gelderland",
    "wof:name":"Milieu Techniek Didam",
    "wof:placetype":"venue"
},
  "geometry": {"coordinates":[6.131919,51.948143],"type":"Point"}
}