{
  "type": "Feature",
  "properties": {
    "addr:full":"Papsouwselaan 119 Delft Zuid-Holland 2624 AK",
    "addr:housenumber":"119",
    "addr:postcode":"2624 ak",
    "addr:street":"Papsouwselaan",
    "iso:country":"NL",
    "sg:address":"Papsouwselaan 119",
    "sg:city":"Delft",
    "sg:orig_category":"Banken And Kredietinstellingen",
    "sg:phone":"+31 15 261 8691",
    "sg:postcode":"2624 AK",
    "sg:province":"Zuid-Holland",
    "wof:name":"Fortis Bank",
    "wof:placetype":"venue"
},
  "geometry": {"coordinates":[4.354858,51.999916],"type":"Point"}
}