{
  "type": "Feature",
  "properties": {
    "addr:full":"Edisonweg 53 C Bathmen Overijssel 7437 PX",
    "addr:housenumber":"53 c",
    "addr:postcode":"7437 px",
    "addr:street":"Edisonweg",
    "iso:country":"NL",
    "sg:address":"Edisonweg 53 C",
    "sg:city":"Bathmen",
    "sg:orig_category":"Film-, Tv- And Videoproductie",
    "sg:phone":"+31 118 468 585",
    "sg:postcode":"7437 PX",
    "sg:province":"Overijssel",
    "wof:name":"Frisbee",
    "wof:placetype":"venue"
},
  "geometry": {"coordinates":[6.338425,52.252998],"type":"Point"}
}