{
  "type": "Feature",
  "properties": {
    "addr:full":"Nijreesweg 31 Almelo Overijssel 7609 PA",
    "addr:housenumber":"31",
    "addr:postcode":"7609 pa",
    "addr:street":"Nijreesweg",
    "iso:country":"NL",
    "sg:address":"Nijreesweg 31",
    "sg:city":"Almelo",
    "sg:orig_category":"Verlichting And Huishoudartikelen",
    "sg:phone":"+31 546 814 537",
    "sg:postcode":"7609 PA",
    "sg:province":"Overijssel",
    "wof:name":"Handelsonderneming Vlaskamp",
    "wof:placetype":"venue"
},
  "geometry": {"coordinates":[6.66384,52.339581],"type":"Point"}
}