{
  "type": "Feature",
  "properties": {
    "addr:full":"Janbinneslaan 2A Surhuisterveen Friesland 9231 CB",
    "addr:housenumber":"2a",
    "addr:postcode":"9231 cb",
    "addr:street":"Janbinneslaan",
    "iso:country":"NL",
    "sg:address":"Janbinneslaan 2A",
    "sg:city":"Surhuisterveen",
    "sg:orig_category":"Makelaars In Onroerend Goed",
    "sg:phone":"+31 512 361 474",
    "sg:postcode":"9231 CB",
    "sg:province":"Friesland",
    "wof:name":"Van Der Velde & Hoen Makelaardij",
    "wof:placetype":"venue"
},
  "geometry": {"coordinates":[6.162294,53.180904],"type":"Point"}
}