{
  "type": "Feature",
  "properties": {
    "iso:country":"NL",
    "sg:address":"Wolfhezerwg 94A",
    "sg:city":"Wolfheze",
    "sg:orig_category":"Verzekeringen - Verzekeringskantoren",
    "sg:phone":"+31 26 482 1751",
    "sg:postcode":"6874 AH",
    "sg:province":"Gelderland",
    "wof:name":"Ede Assuranti\u00ebn Bv, Van",
    "wof:placetype":"venue"
},
  "geometry": {"coordinates":[5.792199,52.006359],"type":"Point"}
}