{
  "type": "Feature",
  "properties": {
    "addr:full":"Dorpsstr 97 Elst Gld Gelderland 6661 EJ",
    "addr:housenumber":"97",
    "addr:postcode":"6661 ej",
    "addr:street":"Dorpsstr;Gld Gelderland",
    "iso:country":"NL",
    "sg:address":"Dorpsstr 97",
    "sg:city":"Elst Gld",
    "sg:orig_category":"Bloemen En Planten",
    "sg:phone":"+31 481 378 581",
    "sg:postcode":"6661 EJ",
    "sg:province":"Gelderland",
    "wof:name":"Verleiding, De",
    "wof:placetype":"venue"
},
  "geometry": {"coordinates":[5.841914,51.918842],"type":"Point"}
}