{
  "type": "Feature",
  "properties": {
    "iso:country":"NL",
    "sg:address":"Achillesstr 25",
    "sg:city":"Amsterdam",
    "sg:orig_category":"Metaaldraaierijen",
    "sg:phone":"+31 20 679 5915",
    "sg:postcode":"1076 PT",
    "sg:province":"North Holland",
    "wof:name":"Achilles",
    "wof:placetype":"venue"
},
  "geometry": {"coordinates":[4.865078,52.347248],"type":"Point"}
}