{
  "type": "Feature",
  "properties": {
    "iso:country":"NL",
    "sg:address":"Stormpolderdijk 34",
    "sg:city":"Krimpen A/D Ijssel",
    "sg:orig_category":"Verzekeringen",
    "sg:phone":"+31 180 550 378",
    "sg:postcode":"2921 LL",
    "sg:province":"South Holland",
    "wof:name":"Volta Assurantien Bv",
    "wof:placetype":"venue"
},
  "geometry": {"coordinates":[4.581723,51.909142],"type":"Point"}
}