{
  "type": "Feature",
  "properties": {
    "addr:full":"Hoofdstraat 36 Kaatsheuvel Noord-Brabant 5171 DD",
    "addr:housenumber":"36",
    "addr:postcode":"5171 dd",
    "addr:street":"Hoofdstraat",
    "iso:country":"NL",
    "sg:address":"Hoofdstraat 36",
    "sg:city":"Kaatsheuvel",
    "sg:orig_category":"Banken And Kredietinstellingen",
    "sg:phone":"+31 416 272 906",
    "sg:postcode":"5171 DD",
    "sg:province":"Noord-Brabant",
    "wof:name":"Ing Bank",
    "wof:placetype":"venue"
},
  "geometry": {"coordinates":[5.03487,51.661125],"type":"Point"}
}