{
  "type": "Feature",
  "properties": {
    "addr:full":"Beneden Molendk 10 Oud Beyerland Zuid-Holland 3262 AA",
    "addr:housenumber":"10",
    "addr:postcode":"3262 aa",
    "addr:street":"Beneden Molendk",
    "iso:country":"NL",
    "sg:address":"Beneden Molendk 10",
    "sg:city":"Oud Beyerland",
    "sg:classifiers":[
        {
            "category":"Food & Beverages",
            "subcategory":"Bakery",
            "type":"Retail Goods"
        }
    ],
    "sg:phone":"+31 186 626 671",
    "sg:postcode":"3262 AA",
    "sg:province":"Zuid-Holland",
    "sg:tags":[
        "pizza"
    ],
    "wof:name":"Porto Fino",
    "wof:placetype":"venue"
},
  "geometry": {"coordinates":[4.410315,51.826794],"type":"Point"}
}