{
  "type": "Feature",
  "properties": {
    "iso:country":"NL",
    "sg:address":"L Nering 140",
    "sg:city":"Emmeloord",
    "sg:orig_category":"Opticiens",
    "sg:phone":"+31 527 619 559",
    "sg:postcode":"8302 EG",
    "sg:province":"Flevoland",
    "sg:website":"http://www.hansanders.nl",
    "wof:name":"Hans Anders",
    "wof:placetype":"venue"
},
  "geometry": {"coordinates":[5.7616219521,52.7111740112],"type":"Point"}
}