{
  "type": "Feature",
  "properties": {
    "addr:full":"Beeldswg 17 Zuidland Zuid-Holland 3214 VA",
    "addr:housenumber":"17",
    "addr:postcode":"3214",
    "addr:street":"Beeldswg",
    "iso:country":"NL",
    "sg:address":"Beeldswg 17",
    "sg:city":"Zuidland",
    "sg:orig_category":"Verenigingen En Stichtingen",
    "sg:phone":"+31 181 453 127",
    "sg:postcode":"3214 VA",
    "sg:province":"Zuid-Holland",
    "wof:name":"Psoriasisvereniging Nederland",
    "wof:placetype":"venue"
},
  "geometry": {"coordinates":[4.253762,51.826397],"type":"Point"}
}