{
  "type": "Feature",
  "properties": {
    "iso:country":"NL",
    "sg:address":"Pastoor Hoefnagelstraat 2",
    "sg:city":"Milsbeek",
    "sg:orig_category":"Banken And Kredietinstellingen",
    "sg:phone":"+31 485 514 245",
    "sg:postcode":"6596 AJ",
    "sg:province":"Limburg",
    "wof:name":"Postagentschap De Joker",
    "wof:placetype":"venue"
},
  "geometry": {"coordinates":[5.952508,51.725189],"type":"Point"}
}