{
  "type": "Feature",
  "properties": {
    "addr:full":"V Speykstr 76 S Gravenhage South Holland 2518 GE",
    "addr:housenumber":"76",
    "addr:postcode":"2518",
    "addr:street":"S Gravenhage",
    "iso:country":"NL",
    "sg:address":"V Speykstr 76",
    "sg:city":"S Gravenhage",
    "sg:orig_category":"Vertaalbureaus",
    "sg:phone":"+31 70 362 8076",
    "sg:postcode":"2518 GE",
    "sg:province":"South Holland",
    "sg:website":"http://www.englishworks.nl",
    "wof:name":"Englishworks",
    "wof:placetype":"venue"
},
  "geometry": {"coordinates":[4.29348,52.080318],"type":"Point"}
}