{
  "type": "Feature",
  "properties": {
    "addr:full":"Balsemienstr 26 Gouda South Holland 2803 JD",
    "addr:housenumber":"26",
    "addr:postcode":"2803 jd",
    "addr:street":"Balsemienstr",
    "iso:country":"NL",
    "sg:address":"Balsemienstr 26",
    "sg:city":"Gouda",
    "sg:orig_category":"Kabelwerken",
    "sg:phone":"+31 182 531 783",
    "sg:postcode":"2803 JD",
    "sg:province":"South Holland",
    "wof:name":"Gramo",
    "wof:placetype":"venue"
},
  "geometry": {"coordinates":[4.6913948059,52.0317993164],"type":"Point"}
}