{
  "type": "Feature",
  "properties": {
    "iso:country":"NL",
    "sg:address":"Herewg 9",
    "sg:city":"Groningen",
    "sg:orig_category":"Adviesbureaus Bouwkunde",
    "sg:phone":"+31 50 529 0910",
    "sg:postcode":"9725 AA",
    "sg:province":"Groningen",
    "sg:website":"http://www.ipdubo.nl",
    "wof:name":"Duurzaam Bouwen",
    "wof:placetype":"venue"
},
  "geometry": {"coordinates":[6.571223,53.210476],"type":"Point"}
}