{
  "type": "Feature",
  "properties": {
    "addr:full":"De Hessellepln 31 Heerlen Limburg 6411 CH",
    "addr:housenumber":"31",
    "addr:postcode":"6411",
    "iso:country":"NL",
    "sg:address":"De Hessellepln 31",
    "sg:city":"Heerlen",
    "sg:orig_category":"Pensioenfondsen",
    "sg:phone":"+31 45 579 3058",
    "sg:postcode":"6411 CH",
    "sg:province":"Limburg",
    "wof:name":"Saip",
    "wof:placetype":"venue"
},
  "geometry": {"coordinates":[5.975101,50.883575],"type":"Point"}
}