{
  "type": "Feature",
  "properties": {
    "addr:full":"Stadspolderwg 9 Leiden Zuid-Holland 2316 AH",
    "addr:housenumber":"9",
    "addr:postcode":"2316 ah",
    "addr:street":"Stadspolderwg",
    "iso:country":"NL",
    "sg:address":"Stadspolderwg 9",
    "sg:city":"Leiden",
    "sg:orig_category":"Luchtbehandelings- Apparaten",
    "sg:phone":"+31 71 522 6327",
    "sg:postcode":"2316 AH",
    "sg:province":"Zuid-Holland",
    "sg:website":"http://www.alcoluchtbehandeling.nl",
    "wof:name":"Alco Luchtbehandeling",
    "wof:placetype":"venue"
},
  "geometry": {"coordinates":[4.490223,52.172062],"type":"Point"}
}