{
  "type": "Feature",
  "properties": {
    "iso:country":"NL",
    "sg:address":"De Doelen 114",
    "sg:city":"Oosterhout Nb",
    "sg:classifiers":[
        {
            "category":"Education",
            "subcategory":"Preschool",
            "type":"Public Place"
        }
    ],
    "sg:phone":"+31 162 425 466",
    "sg:postcode":"4901 JV",
    "sg:province":"Noord-Brabant",
    "sg:tags":[
        "kleuteronderwijs",
        "basis-"
    ],
    "wof:name":"Harlekijn",
    "wof:placetype":"venue"
},
  "geometry": {"coordinates":[4.859724,51.642609],"type":"Point"}
}