{
  "type": "Feature",
  "properties": {
    "addr:full":"Anemoonstraat 25 'S Gravenhage Zuid-Holland 2565 DD",
    "addr:housenumber":"25",
    "addr:postcode":"2565 dd",
    "addr:street":"Anemoonstraat;' S",
    "iso:country":"NL",
    "sg:address":"Anemoonstraat 25",
    "sg:city":"'S Gravenhage",
    "sg:orig_category":"Fotostudio'S And Fotografen",
    "sg:phone":"+31 70 360 3778",
    "sg:postcode":"2565 DD",
    "sg:province":"Zuid-Holland",
    "wof:name":"Janneke Bylmer En Theo Vogel Fotografie",
    "wof:placetype":"venue"
},
  "geometry": {"coordinates":[4.259365,52.075932],"type":"Point"}
}