{
  "type": "Feature",
  "properties": {
    "iso:country":"NL",
    "sg:address":"Pinksterbloem 25",
    "sg:city":"Apeldoorn",
    "sg:orig_category":"Kinderopvang",
    "sg:phone":"+31 55 366 3640",
    "sg:postcode":"7322 GS",
    "sg:province":"Gelderland",
    "wof:name":"Doggersbank",
    "wof:placetype":"venue"
},
  "geometry": {"coordinates":[5.983515,52.221516],"type":"Point"}
}