{
  "type": "Feature",
  "properties": {
    "addr:full":"Amersfoortseweg 18 Huis Ter Heide Ut Utrecht 3712 BC",
    "addr:housenumber":"18",
    "addr:postcode":"3712 bc",
    "addr:street":"Amersfoortseweg",
    "iso:country":"NL",
    "sg:address":"Amersfoortseweg 18",
    "sg:city":"Huis Ter Heide Ut",
    "sg:orig_category":"Verhuur Audiovisuele Apparatuur",
    "sg:phone":"+31 30 693 2675",
    "sg:postcode":"3712 BC",
    "sg:province":"Utrecht",
    "wof:name":"Protheo Sound",
    "wof:placetype":"venue"
},
  "geometry": {"coordinates":[5.253154,52.112099],"type":"Point"}
}