{
  "type": "Feature",
  "properties": {
    "addr:full":"Oude Singel 11 Oudewater Utrecht 3421 ED",
    "addr:housenumber":"11",
    "addr:postcode":"3421 ed",
    "addr:street":"Oude Singel",
    "iso:country":"NL",
    "sg:address":"Oude Singel 11",
    "sg:city":"Oudewater",
    "sg:classifiers":[
        {
            "category":"Education",
            "subcategory":"Preschool",
            "type":"Public Place"
        }
    ],
    "sg:phone":"+31 348 561 614",
    "sg:postcode":"3421 ED",
    "sg:province":"Utrecht",
    "sg:tags":[
        "kleuteronderwijs",
        "basis-"
    ],
    "wof:name":"Immanuel School",
    "wof:placetype":"venue"
},
  "geometry": {"coordinates":[4.868747,52.026131],"type":"Point"}
}