{
  "type": "Feature",
  "properties": {
    "addr:full":"Speelhuispln 2 Breda Noord-Brabant 4815 CK",
    "addr:housenumber":"2",
    "addr:postcode":"4815 ck",
    "addr:street":"Speelhuispln",
    "iso:country":"NL",
    "sg:address":"Speelhuispln 2",
    "sg:city":"Breda",
    "sg:classifiers":[
        {
            "category":"Retail",
            "subcategory":"Auto Repair",
            "type":"Services"
        }
    ],
    "sg:phone":"+31 76 587 1987",
    "sg:postcode":"4815 CK",
    "sg:province":"Noord-Brabant",
    "sg:tags":[
        "garage"
    ],
    "wof:name":"Graaf Auto Bv, De",
    "wof:placetype":"venue"
},
  "geometry": {"coordinates":[4.779995,51.596867],"type":"Point"}
}