{
  "type": "Feature",
  "properties": {
    "addr:full":"Dorpsstr 206 Assendelft North Holland 1566 AT",
    "addr:housenumber":"206",
    "addr:postcode":"1566",
    "iso:country":"NL",
    "sg:address":"Dorpsstr 206",
    "sg:city":"Assendelft",
    "sg:orig_category":"Pijpleidingen - Installatie En Onderhoud",
    "sg:phone":"+31 75 687 1261",
    "sg:postcode":"1566 AT",
    "sg:province":"North Holland",
    "sg:website":"http://www.c-ris.nl",
    "wof:name":"Ris Bv, C",
    "wof:placetype":"venue"
},
  "geometry": {"coordinates":[4.732596,52.455002],"type":"Point"}
}