{
  "type": "Feature",
  "properties": {
    "addr:full":"Westeinde 207 S Gravenhage Zuid-Holland 2512 GZ",
    "addr:housenumber":"207;gravenhage",
    "addr:postcode":"2512 gz",
    "addr:street":"Westeinde;S",
    "iso:country":"NL",
    "sg:address":"Westeinde 207",
    "sg:city":"S Gravenhage",
    "sg:orig_category":"Organisatiebureaus",
    "sg:phone":"+31 70 305 0487",
    "sg:postcode":"2512 GZ",
    "sg:province":"Zuid-Holland",
    "sg:website":"http://www.bfg.nl",
    "wof:name":"Bfg, Bureau",
    "wof:placetype":"venue"
},
  "geometry": {"coordinates":[4.3061800003,52.0732116699],"type":"Point"}
}