{
  "type": "Feature",
  "properties": {
    "addr:full":"Schout 32 Naaldwijk Zuid-Holland 2671 ZR",
    "addr:housenumber":"32",
    "addr:postcode":"2671 zr",
    "addr:street":"Schout",
    "iso:country":"NL",
    "sg:address":"Schout 32",
    "sg:city":"Naaldwijk",
    "sg:classifiers":[
        {
            "category":"Professional",
            "subcategory":"Accounting & Tax Preparation",
            "type":"Services"
        }
    ],
    "sg:phone":"+31 174 620 453",
    "sg:postcode":"2671 ZR",
    "sg:province":"Zuid-Holland",
    "sg:tags":[
        "accountant"
    ],
    "wof:name":"T.H.L. Zuidgeest A.A. Administratiekanto",
    "wof:placetype":"venue"
},
  "geometry": {"coordinates":[4.199323,51.988781],"type":"Point"}
}