{
  "type": "Feature",
  "properties": {
    "iso:country":"NL",
    "sg:address":"Kazernestraat 2",
    "sg:city":"Oss",
    "sg:classifiers":[
        {
            "category":"Fast Food",
            "type":"Food & Drink"
        }
    ],
    "sg:phone":"+31 412 641 220",
    "sg:postcode":"5341 CG",
    "sg:province":"Noord-Brabant",
    "sg:tags":[
        "afhaal",
        "restaurant"
    ],
    "wof:name":"Toet Anch Amon",
    "wof:placetype":"venue"
},
  "geometry": {"coordinates":[-77.235214,38.312599],"type":"Point"}
}