{
  "type": "Feature",
  "properties": {
    "iso:country":"NL",
    "sg:address":"Weerenwg 21-23",
    "sg:city":"Zwanenburg",
    "sg:orig_category":"Amusementshallen",
    "sg:phone":"+31 20 497 0207",
    "sg:postcode":"1161 AE",
    "sg:province":"Noord-Holland",
    "sg:website":"http://www.pinballmagic.nl",
    "wof:name":"Silverstone",
    "wof:placetype":"venue"
},
  "geometry": {"coordinates":[4.734651,52.384029],"type":"Point"}
}