{
  "type": "Feature",
  "properties": {
    "iso:country":"NL",
    "sg:address":"Friesestraat 31",
    "sg:city":"Coevorden",
    "sg:orig_category":"Opticiens",
    "sg:phone":"+31 524 512 917",
    "sg:postcode":"7741 GS",
    "sg:province":"Drenthe",
    "wof:name":"Krikke Optiek",
    "wof:placetype":"venue"
},
  "geometry": {"coordinates":[6.7387170792,52.6618537903],"type":"Point"}
}