{
  "type": "Feature",
  "properties": {
    "addr:full":"Nw Binnenwg 329 Rotterdam Zuid-Holland 3021 GJ",
    "addr:housenumber":"329",
    "addr:postcode":"3021 gj",
    "iso:country":"NL",
    "sg:address":"Nw Binnenwg 329",
    "sg:city":"Rotterdam",
    "sg:orig_category":"Verlichting",
    "sg:phone":"+31 10 476 9434",
    "sg:postcode":"3021 GJ",
    "sg:province":"Zuid-Holland",
    "wof:name":"Bakker & Rip, Fa",
    "wof:placetype":"venue"
},
  "geometry": {"coordinates":[4.45724,51.912807],"type":"Point"}
}