{
  "type": "Feature",
  "properties": {
    "addr:full":"De Luinink 2 Denekamp Overijssel 7591 DV",
    "addr:housenumber":"2",
    "addr:postcode":"7591 dv",
    "addr:street":"De Luinink",
    "iso:country":"NL",
    "sg:address":"De Luinink 2",
    "sg:city":"Denekamp",
    "sg:orig_category":"Logopedisten",
    "sg:phone":"+31 541 352 140",
    "sg:postcode":"7591 DV",
    "sg:province":"Overijssel",
    "wof:name":"Borgers-Beijen, J G M",
    "wof:placetype":"venue"
},
  "geometry": {"coordinates":[7.000177,52.37912],"type":"Point"}
}