{
  "type": "Feature",
  "properties": {
    "iso:country":"NL",
    "sg:address":"Maasambacht 3",
    "sg:city":"Maasdijk",
    "sg:orig_category":"Meubelzaken, Woning- And Keukeninrichting",
    "sg:phone":"+31 174 513 490",
    "sg:postcode":"2676 AW",
    "sg:province":"Zuid-Holland",
    "wof:name":"Nipius Wooncentrum Bv",
    "wof:placetype":"venue"
},
  "geometry": {"coordinates":[4.212196,51.960789],"type":"Point"}
}