{
  "type": "Feature",
  "properties": {
    "iso:country":"NL",
    "sg:address":"Noordmolenstr 81A",
    "sg:city":"Rotterdam",
    "sg:orig_category":"Herenkleding",
    "sg:phone":"+31 10 465 2103",
    "sg:postcode":"3035 RH",
    "sg:province":"Zuid-Holland",
    "wof:name":"Miles Bros",
    "wof:placetype":"venue"
},
  "geometry": {"coordinates":[4.481254,51.932331],"type":"Point"}
}