{
  "type": "Feature",
  "properties": {
    "addr:full":"Emmaln 23 Alphen Aan Den Ryn Zuid-Holland 2405 GA",
    "addr:housenumber":"23",
    "addr:postcode":"2405 ga",
    "addr:street":"Emmaln;Aan Den Ryn",
    "iso:country":"NL",
    "sg:address":"Emmaln 23",
    "sg:city":"Alphen Aan Den Ryn",
    "sg:orig_category":"Adviesbureaus Bedrijfsorganisatie",
    "sg:phone":"+31 172 491 821",
    "sg:postcode":"2405 GA",
    "sg:province":"Zuid-Holland",
    "wof:name":"Lijster, Alexander De",
    "wof:placetype":"venue"
},
  "geometry": {"coordinates":[-83.222931,32.678131],"type":"Point"}
}