{
  "type": "Feature",
  "properties": {
    "addr:full":"Putselaan 35 Rotterdam Zuid-Holland 3072 CB",
    "addr:housenumber":"35",
    "addr:postcode":"3072 cb",
    "addr:street":"Putselaan",
    "iso:country":"NL",
    "sg:address":"Putselaan 35",
    "sg:city":"Rotterdam",
    "sg:classifiers":[
        {
            "category":"Fast Food",
            "type":"Food & Drink"
        }
    ],
    "sg:phone":"+31 10 484 4536",
    "sg:postcode":"3072 CB",
    "sg:province":"Zuid-Holland",
    "sg:tags":[
        "afhaal",
        "restaurant"
    ],
    "wof:name":"De Babi Pangang",
    "wof:placetype":"venue"
},
  "geometry": {"coordinates":[4.507161,51.898766],"type":"Point"}
}