{
  "type": "Feature",
  "properties": {
    "iso:country":"NL",
    "sg:address":"De Scheper 6",
    "sg:city":"Grubbenvorst",
    "sg:orig_category":"Geluidsinstallaties - Verhuur",
    "sg:phone":"+31 77 366 3439",
    "sg:postcode":"5971 LE",
    "sg:province":"Limburg",
    "wof:name":"El & S",
    "wof:placetype":"venue"
},
  "geometry": {"coordinates":[6.145908,51.424435],"type":"Point"}
}