{
  "type": "Feature",
  "properties": {
    "addr:full":"Wal 2 Arcen Limburg 5944 AW",
    "addr:housenumber":"2",
    "addr:postcode":"5944 aw",
    "addr:street":"Wal",
    "iso:country":"NL",
    "sg:address":"Wal 2",
    "sg:city":"Arcen",
    "sg:orig_category":"Fietsen En Bromfietsen",
    "sg:phone":"+31 77 473 2190",
    "sg:postcode":"5944 AW",
    "sg:province":"Limburg",
    "wof:name":"Lemmen Tweewielers",
    "wof:placetype":"venue"
},
  "geometry": {"coordinates":[6.181747,51.474026],"type":"Point"}
}