{
  "type": "Feature",
  "properties": {
    "addr:full":"De Heerd 117 Raalte Overijssel 8102 LL",
    "addr:housenumber":"117",
    "addr:postcode":"8102 ll",
    "addr:street":"De Heerd",
    "iso:country":"NL",
    "sg:address":"De Heerd 117",
    "sg:city":"Raalte",
    "sg:orig_category":"Adviesbureaus Bedrijfsorganisatie",
    "sg:phone":"+31 572 361 677",
    "sg:postcode":"8102 LL",
    "sg:province":"Overijssel",
    "wof:name":"Mijl, C A Van Der",
    "wof:placetype":"venue"
},
  "geometry": {"coordinates":[6.275937,52.374363],"type":"Point"}
}