{
  "type": "Feature",
  "properties": {
    "addr:full":"Stationsstr 1 Assen Drenthe 9401 KV",
    "addr:housenumber":"1",
    "addr:postcode":"9401 kv",
    "addr:street":"Stationsstr",
    "iso:country":"NL",
    "sg:address":"Stationsstr 1",
    "sg:city":"Assen",
    "sg:orig_category":"Boeken En Tijdschriften",
    "sg:phone":"+31 592 313 292",
    "sg:postcode":"9401 KV",
    "sg:province":"Drenthe",
    "wof:name":"Plok",
    "wof:placetype":"venue"
},
  "geometry": {"coordinates":[6.565926,52.993496],"type":"Point"}
}