{
  "type": "Feature",
  "properties": {
    "addr:full":"Gaardenweg 28 Enter Overijssel 7468 EX",
    "addr:housenumber":"28",
    "addr:postcode":"7468 ex",
    "addr:street":"Gaardenweg",
    "iso:country":"NL",
    "sg:address":"Gaardenweg 28",
    "sg:city":"Enter",
    "sg:orig_category":"Chemische Producten Gh",
    "sg:phone":"+31 6 53222836",
    "sg:postcode":"7468 EX",
    "sg:province":"Overijssel",
    "wof:name":"Otten",
    "wof:placetype":"venue"
},
  "geometry": {"coordinates":[-76.841904,40.463078],"type":"Point"}
}