{
  "type": "Feature",
  "properties": {
    "addr:full":"Postbus 57 Zuidlaren Provincie Drenthe 9470 AB",
    "addr:housenumber":"57",
    "addr:postcode":"9470 ab",
    "addr:street":"Postbus;Provincie Drenthe",
    "iso:country":"NL",
    "sg:address":"Postbus 57",
    "sg:city":"Zuidlaren",
    "sg:orig_category":"Fotolaboratoria",
    "sg:phone":"+31 50 409 1625",
    "sg:postcode":"9470 AB",
    "sg:province":"Provincie Drenthe",
    "wof:name":"Mennen",
    "wof:placetype":"venue"
},
  "geometry": {"coordinates":[6.68134,53.0924],"type":"Point"}
}