{
  "type": "Feature",
  "properties": {
    "addr:full":"Garderbroekerwg 59 Kootwykerbroek Gelderland 3774 JC",
    "addr:housenumber":"59",
    "addr:postcode":"3774 jc",
    "addr:street":"Garderbroekerwg;Gelderland",
    "iso:country":"NL",
    "sg:address":"Garderbroekerwg 59",
    "sg:city":"Kootwykerbroek",
    "sg:orig_category":"Fietsen En Bromfietsen",
    "sg:phone":"+31 342 441 440",
    "sg:postcode":"3774 JC",
    "sg:province":"Gelderland",
    "sg:website":"http://www.bouwman-tweewielers.nl",
    "wof:name":"Bouwman, Firma",
    "wof:placetype":"venue"
},
  "geometry": {"coordinates":[5.643495,52.168968],"type":"Point"}
}