{
  "type": "Feature",
  "properties": {
    "addr:full":"Burgemeester Nielenplein 8 Heemskerk Noord-Holland 1961 NV",
    "addr:housenumber":"8",
    "addr:postcode":"1961 nv",
    "addr:street":"Burgemeester Nielenplein",
    "iso:country":"NL",
    "sg:address":"Burgemeester Nielenplein 8",
    "sg:city":"Heemskerk",
    "sg:orig_category":"Warenhuizen",
    "sg:phone":"+31 251 251 978",
    "sg:postcode":"1961 NV",
    "sg:province":"Noord-Holland",
    "wof:name":"Hema",
    "wof:placetype":"venue"
},
  "geometry": {"coordinates":[4.672372818,52.5106925964],"type":"Point"}
}