{
  "type": "Feature",
  "properties": {
    "addr:full":"St Janshof 29 Boskoop South Holland 2771 BM",
    "addr:housenumber":"29",
    "addr:postcode":"2771 bm",
    "addr:street":"St Janshof",
    "iso:country":"NL",
    "sg:address":"St Janshof 29",
    "sg:city":"Boskoop",
    "sg:orig_category":"Voetbalverenigingen",
    "sg:phone":"+31 172 215 268",
    "sg:postcode":"2771 BM",
    "sg:province":"South Holland",
    "wof:name":"Floreant",
    "wof:placetype":"venue"
},
  "geometry": {"coordinates":[4.662982,52.074978],"type":"Point"}
}