{
  "type": "Feature",
  "properties": {
    "iso:country":"NL",
    "sg:address":"Waalstraat 12",
    "sg:city":"Nijverdal",
    "sg:orig_category":"Kappers",
    "sg:phone":"+31 548 614 990",
    "sg:postcode":"7442 EK",
    "sg:province":"Overijssel",
    "wof:name":"Leidi Schwarte",
    "wof:placetype":"venue"
},
  "geometry": {"coordinates":[6.473802,52.361511],"type":"Point"}
}